{
  "cve_id": "CVE-2024-42426",
  "description": "Dell PowerScale OneFS Versions 9.5.0.x through 9.8.0.x contain an **uncontrolled resource consumption** vulnerability. A low privilege remote attacker could potentially exploit this vulnerability, leading to denial of service.",
  "key_phrases": {
    "rootcause": "",
    "weakness": "uncontrolled resource consumption",
    "impact": [
      "denial of service",
      "resource consumption"
    ],
    "vector": "",
    "attacker": "low privilege remote attacker",
    "product": "Dell PowerScale OneFS",
    "version": "9.5.0.x through 9.8.0.x",
    "component": ""
  },
  "reference_content": "Based on the provided content, here's the breakdown of CVE-2024-42426:\n\n**Root cause of vulnerability:**\n- Uncontrolled resource consumption.\n\n**Weaknesses/vulnerabilities present:**\n- The vulnerability stems from a lack of proper resource management.\n\n**Impact of exploitation:**\n- Successful exploitation can lead to a denial-of-service (DoS) condition.\n\n**Attack vectors:**\n- Remote attack vector.\n\n**Required attacker capabilities/position:**\n- The attacker needs to have low privileges on the target system.\n\n**Affected versions:**\n- Dell PowerScale OneFS versions 9.5.0.x through 9.8.0.x.\n\n**Remediated versions:**\n- Versions 9.7.1.3 or later for versions 9.5.0.0 through 9.7.1.2\n- Versions 9.9.0.1 or later for version 9.8.0.0",
  "similar_info": {
    "cwe_distribution": {},
    "cwe_consensus": "",
    "similarity_stats": {
      "thresholds": [],
      "total_samples_by_threshold": {},
      "top_cwes_by_threshold": {}
    }
  },
  "similarity_summary": {
    "consensus_cwe": "",
    "top_cwes": [],
    "confidence_levels": {},
    "total_samples": 0
  },
  "analysis": "# Summary\n| CWE ID | CWE Name | Confidence | CWE Abstraction Level | CWE Vulnerability Mapping Label | CWE-Vulnerability Mapping Notes |\n|---|---|---|---|---|---|\n| CWE-400 | Uncontrolled Resource Consumption | 0.9 | Class | Primary | Allowed-with-Review |\n| CWE-770 | Allocation of Resources Without Limits or Throttling | 0.7 | Base | Secondary | Allowed |\n\n## Evidence and Confidence\n\n*   **Confidence Score:** 0.8\n*   **Evidence Strength:** HIGH\n\n## Relationship Analysis\nThe primary relationship impacting the decision is that CWE-400 is a Class-level CWE, and it has more specific Base-level children. CWE-770, Allocation of Resources Without Limits or Throttling, is a child of CWE-400, and it is considered a possible candidate. Since the vulnerability is due to the lack of limits on resource allocation, CWE-770 could be considered a contributing factor, but the primary issue is the uncontrolled consumption which is a broader concept.\n\n```mermaid\ngraph TD\n    cwe400[\"CWE-400: Uncontrolled Resource Consumption\"]\n    cwe770[\"CWE-770: Allocation of Resources Without Limits or Throttling\"]\n\n    cwe770 -->|CHILDOF| cwe400\n\n    classDef primary fill:#f96,stroke:#333,stroke-width:2px\n    classDef secondary fill:#69f,stroke:#333\n    class cwe400 primary\n    class cwe770 secondary\n```\n\n## Vulnerability Chain\nThe vulnerability chain starts with an **uncontrolled resource consumption** (CWE-400) due to a lack of proper resource management, leading to a denial-of-service (DoS) condition. A possible factor is the **allocation of resources without limits or throttling** (CWE-770).\n\n## Summary of Analysis\nThe initial analysis strongly points to CWE-400, \"Uncontrolled Resource Consumption,\" as the primary weakness. The vulnerability description explicitly states \"**uncontrolled resource consumption**\". The CVE Reference Links Content Summary confirms this, stating the root cause is \"**Uncontrolled resource consumption**\" and that the vulnerability stems from a **lack of proper resource management**. This aligns perfectly with CWE-400.\n\nThe retriever results also list CWE-400 as the top candidate. While CWE-400 is a Class-level CWE, the available information doesn't provide enough detail to pinpoint a more specific Base-level CWE with high confidence. However, CWE-770, \"Allocation of Resources Without Limits or Throttling\" is a possible contributor because it is a child of CWE-400 and describes a resource allocation issue, but it is still a secondary candidate.\n\nThe decision to use CWE-400 is based on the direct evidence of the vulnerability description and CVE summary, which repeatedly emphasize the **uncontrolled resource consumption**. While a more specific CWE could potentially be identified with further investigation, the current evidence supports CWE-400 as the most appropriate classification.\n\nRelevant CWE Information:\n\n# Enhanced Context (25 CWEs)\nThe following CWEs were identified as potentially relevant to this vulnerability:\n\n## CWE-664: Improper Control of a Resource Through its Lifetime\n**Abstraction Level**: Pillar\n**Similarity Score**: 0.78\n**Source**: dense\n\n**Description**:\nThe product does not maintain or incorrectly maintains control over a resource throughout its lifetime of creation, use, and release.\n\n**Mapping Guidance**:\n- Usage: Discouraged\n- Rationale: This CWE entry is high-level when lower-level children are available.\n\n## CWE-400: Uncontrolled Resource Consumption\n**Abstraction Level**: class\n**Similarity Score**: 2.55\n**Source**: graph\n\n**Description**:\nCWE-400: Uncontrolled Resource Consumption\n\n**Mapping Guidance**:\n- Usage: Discouraged\n- Rationale: CWE-400 is intended for incorrect behaviors in which the product is expected to track and restrict how many resources it consumes, but CWE-400 is often misused because it is conflated with the \"technical impact\" of vulnerabilities in which resource consumption occurs. It is sometimes used for low-information vulnerability reports. It is a level-1 Class (i.e., a child of a Pillar).\n\n**Relationships**:\n- PARENTOF -> CWE-920\n- PARENTOF -> CWE-779\n- PARENTOF -> CWE-771\n- PARENTOF -> CWE-770\n- CANFOLLOW -> CWE-410\n\nCWE-400 is the primary CWE as the vulnerability description explicitly mentions **uncontrolled resource consumption**. The suggested alternative of child nodes is considered with CWE-770 being a candidate.\n\n## CWE-770: Allocation of Resources Without Limits or Throttling\n**Abstraction Level**: Base\n**Similarity Score**: 0.187\n**Source**: sparse\n\n**Description**:\nThe product allocates resources for a functionality, but it does not properly limit or throttle the amount of resources that are allocated, which can be exploited to cause a denial of service.\n\n**Mapping Guidance**:\n- Usage: Allowed\n- Rationale: This CWE entry is at the Base level of abstraction, which is a preferred level of abstraction for mapping to the root causes of vulnerabilities.\n\nCWE-770 is considered as a secondary issue, because **uncontrolled resource consumption** is the primary issue.\n\nCWE-410: Insufficient Resource Pool is not selected because the issue isn't an insufficient pool, but the uncontrolled consumption.\nCWE-834: Excessive Iteration is not selected because the description mentions a resource consumption and not iteration.\nCWE-772: Missing Release of Resource after Effective Lifetime is not selected because the vulnerability is about resource consumption, not necessarily a missing release.\nCWE-674: Uncontrolled Recursion is not selected because the resource consumption does not seem to be caused by recursion.\nCWE-789: Memory Allocation with Excessive Size Value is not selected because the resource consumption isn't necessarily memory allocation.\nCWE-693: Protection Mechanism Failure is not selected because the root cause is the uncontrolled resource consumption and not a protection mechanism failure.\nCWE-911: Improper Update of Reference Count is not selected because the root cause is the uncontrolled resource consumption and not reference counting.",
  "analysis_with_relationships": "# Summary\n| CWE ID | CWE Name | Confidence | CWE Abstraction Level | CWE Vulnerability Mapping Label | CWE-Vulnerability Mapping Notes |\n|---|---|---|---|---|---|\n| CWE-400 | Uncontrolled Resource Consumption | 0.9 | Class | Primary | Allowed-with-Review |\n| CWE-770 | Allocation of Resources Without Limits or Throttling | 0.7 | Base | Secondary | Allowed |\n\n## Evidence and Confidence\n\n*   **Confidence Score:** 0.8\n*   **Evidence Strength:** HIGH\n\n## Relationship Analysis\nThe primary relationship impacting the decision is that CWE-400 is a Class-level CWE, and it has more specific Base-level children. CWE-770, Allocation of Resources Without Limits or Throttling, is a child of CWE-400, and it is considered a possible candidate. Since the vulnerability is due to the lack of limits on resource allocation, CWE-770 could be considered a contributing factor, but the primary issue is the uncontrolled consumption which is a broader concept.\n\n```mermaid\ngraph TD\n    cwe400[\"CWE-400: Uncontrolled Resource Consumption\"]\n    cwe770[\"CWE-770: Allocation of Resources Without Limits or Throttling\"]\n\n    cwe770 -->|CHILDOF| cwe400\n\n    classDef primary fill:#f96,stroke:#333,stroke-width:2px\n    classDef secondary fill:#69f,stroke:#333\n    class cwe400 primary\n    class cwe770 secondary\n```\n\n## Vulnerability Chain\nThe vulnerability chain starts with an **uncontrolled resource consumption** (CWE-400) due to a lack of proper resource management, leading to a denial-of-service (DoS) condition. A possible factor is the **allocation of resources without limits or throttling** (CWE-770).\n\n## Summary of Analysis\nThe initial analysis strongly points to CWE-400, \"Uncontrolled Resource Consumption,\" as the primary weakness. The vulnerability description explicitly states \"**uncontrolled resource consumption**\". The CVE Reference Links Content Summary confirms this, stating the root cause is \"**Uncontrolled resource consumption**\" and that the vulnerability stems from a **lack of proper resource management**. This aligns perfectly with CWE-400.\n\nThe retriever results also list CWE-400 as the top candidate. While CWE-400 is a Class-level CWE, the available information doesn't provide enough detail to pinpoint a more specific Base-level CWE with high confidence. However, CWE-770, \"Allocation of Resources Without Limits or Throttling\" is a possible contributor because it is a child of CWE-400 and describes a resource allocation issue, but it is still a secondary candidate.\n\nThe decision to use CWE-400 is based on the direct evidence of the vulnerability description and CVE summary, which repeatedly emphasize the **uncontrolled resource consumption**. While a more specific CWE could potentially be identified with further investigation, the current evidence supports CWE-400 as the most appropriate classification.\n\nRelevant CWE Information:\n\n# Enhanced Context (25 CWEs)\nThe following CWEs were identified as potentially relevant to this vulnerability:\n\n## CWE-664: Improper Control of a Resource Through its Lifetime\n**Abstraction Level**: Pillar\n**Similarity Score**: 0.78\n**Source**: dense\n\n**Description**:\nThe product does not maintain or incorrectly maintains control over a resource throughout its lifetime of creation, use, and release.\n\n**Mapping Guidance**:\n- Usage: Discouraged\n- Rationale: This CWE entry is high-level when lower-level children are available.\n\n## CWE-400: Uncontrolled Resource Consumption\n**Abstraction Level**: class\n**Similarity Score**: 2.55\n**Source**: graph\n\n**Description**:\nCWE-400: Uncontrolled Resource Consumption\n\n**Mapping Guidance**:\n- Usage: Discouraged\n- Rationale: CWE-400 is intended for incorrect behaviors in which the product is expected to track and restrict how many resources it consumes, but CWE-400 is often misused because it is conflated with the \"technical impact\" of vulnerabilities in which resource consumption occurs. It is sometimes used for low-information vulnerability reports. It is a level-1 Class (i.e., a child of a Pillar).\n\n**Relationships**:\n- PARENTOF -> CWE-920\n- PARENTOF -> CWE-779\n- PARENTOF -> CWE-771\n- PARENTOF -> CWE-770\n- CANFOLLOW -> CWE-410\n\nCWE-400 is the primary CWE as the vulnerability description explicitly mentions **uncontrolled resource consumption**. The suggested alternative of child nodes is considered with CWE-770 being a candidate.\n\n## CWE-770: Allocation of Resources Without Limits or Throttling\n**Abstraction Level**: Base\n**Similarity Score**: 0.187\n**Source**: sparse\n\n**Description**:\nThe product allocates resources for a functionality, but it does not properly limit or throttle the amount of resources that are allocated, which can be exploited to cause a denial of service.\n\n**Mapping Guidance**:\n- Usage: Allowed\n- Rationale: This CWE entry is at the Base level of abstraction, which is a preferred level of abstraction for mapping to the root causes of vulnerabilities.\n\nCWE-770 is considered as a secondary issue, because **uncontrolled resource consumption** is the primary issue.\n\nCWE-410: Insufficient Resource Pool is not selected because the issue isn't an insufficient pool, but the uncontrolled consumption.\nCWE-834: Excessive Iteration is not selected because the description mentions a resource consumption and not iteration.\nCWE-772: Missing Release of Resource after Effective Lifetime is not selected because the vulnerability is about resource consumption, not necessarily a missing release.\nCWE-674: Uncontrolled Recursion is not selected because the resource consumption does not seem to be caused by recursion.\nCWE-789: Memory Allocation with Excessive Size Value is not selected because the resource consumption isn't necessarily memory allocation.\nCWE-693: Protection Mechanism Failure is not selected because the root cause is the uncontrolled resource consumption and not a protection mechanism failure.\nCWE-911: Improper Update of Reference Count is not selected because the root cause is the uncontrolled resource consumption and not reference counting.\n\n\n## CWE Relationship Analysis\n\nCurrent CWEs represent these abstraction levels: .\n\n\n### Vulnerability Chain Analysis\n\n**Chain starting from CWE-779:**\n- 779 (Logging of Excessive Data) - ROOT\n\n\n**Chain starting from CWE-400:**\n- 400 (Uncontrolled Resource Consumption) - ROOT\n\n\n\n### CWE Relationship Diagram\n\n```mermaid\ngraph TD\n    classDef primary fill:#f96,stroke:#333,stroke-width:2px\n    classDef secondary fill:#69f,stroke:#333\n    classDef tertiary fill:#9e9,stroke:#333\n```",
  "criticism": "",
  "resolution": "",
  "relevant_cwes": [
    {
      "metadata": {
        "doc_id": "400",
        "name": "Uncontrolled Resource Consumption",
        "source": "sparse"
      },
      "similarity": 230.83798482047962
    },
    {
      "metadata": {
        "doc_id": "834",
        "name": "Excessive Iteration",
        "source": "sparse"
      },
      "similarity": 206.93041064659772
    },
    {
      "metadata": {
        "doc_id": "1176",
        "name": "Inefficient CPU Computation",
        "source": "sparse"
      },
      "similarity": 189.88239997428593
    },
    {
      "metadata": {
        "doc_id": "770",
        "name": "Allocation of Resources Without Limits or Throttling",
        "source": "sparse"
      },
      "similarity": 186.56253645342338
    },
    {
      "metadata": {
        "doc_id": "772",
        "name": "Missing Release of Resource after Effective Lifetime",
        "source": "sparse"
      },
      "similarity": 186.38195776174732
    },
    {
      "metadata": {
        "doc_id": "674",
        "name": "Uncontrolled Recursion",
        "source": "sparse"
      },
      "similarity": 180.99383089295577
    },
    {
      "metadata": {
        "doc_id": "789",
        "name": "Memory Allocation with Excessive Size Value",
        "source": "sparse"
      },
      "similarity": 180.13899070601124
    },
    {
      "metadata": {
        "doc_id": "693",
        "name": "Protection Mechanism Failure",
        "source": "sparse"
      },
      "similarity": 179.53973621515877
    },
    {
      "metadata": {
        "doc_id": "410",
        "name": "Insufficient Resource Pool",
        "type": "Base",
        "original_content": "The product's resource pool is not large enough to handle peak demand, which allows an attacker to prevent others from accessing the resource by using a (relatively) large number of requests for resources.",
        "keyphrase_source": "weakness:uncontrolled resource consumption",
        "source": "dense",
        "mapping_notes": {
          "usage": "Allowed",
          "rationale": "This CWE entry is at the Base level of abstraction, which is a preferred level of abstraction for mapping to the root causes of vulnerabilities.",
          "comments": "Carefully read both the name and description to ensure that this mapping is an appropriate fit. Do not try to 'force' a mapping to a lower-level Base/Variant simply to comply with this preferred level of abstraction.",
          "reasons": [
            "Acceptable-Use"
          ]
        },
        "score_info": {
          "retrievers": [
            "dense",
            "sparse",
            "graph"
          ],
          "retriever_count": 3,
          "normalized_scores": {
            "dense": 0.5789972577448443,
            "sparse": 179.10871147317812,
            "graph": 2.856732889778391
          }
        }
      },
      "similarity": 0.5789972577448443
    },
    {
      "doc_id": "911",
      "text": "CWE-911: Improper Update of Reference Count",
      "score": 2.2100000000000004,
      "metadata": {
        "doc_id": "911",
        "name": "Improper Update of Reference Count",
        "type": "base",
        "original_content": "CWE-911: Improper Update of Reference Count",
        "relationships": [
          {
            "source_id": "911",
            "target_id": "772",
            "label": "CANPRECEDE",
            "properties": {
              "view_id": "1000"
            }
          },
          {
            "source_id": "911",
            "target_id": "672",
            "label": "CANPRECEDE",
            "properties": {
              "view_id": "1000"
            }
          },
          {
            "source_id": "911",
            "target_id": "664",
            "label": "CHILDOF",
            "properties": {
              "ordinal": "Primary",
              "view_id": "1000"
            }
          },
          {
            "source_id": "772",
            "target_id": "911",
            "label": "CANFOLLOW",
            "properties": {
              "view_id": "1000"
            }
          },
          {
            "source_id": "672",
            "target_id": "911",
            "label": "CANFOLLOW",
            "properties": {
              "view_id": "1000"
            }
          },
          {
            "source_id": "664",
            "target_id": "911",
            "label": "PARENTOF",
            "properties": {
              "ordinal": "Primary",
              "view_id": "1000"
            }
          }
        ],
        "score_components": {
          "relationship_chain": 1.0,
          "sequence_path": 1.0
        },
        "abstraction_factor": 1.3,
        "graph_path_info": {
          "path_types": [
            "relationship_chain",
            "vulnerability_sequence_forward",
            "vulnerability_sequence_backward"
          ],
          "best_paths": {
            "relationship_chain": {
              "path": [
                [
                  "772",
                  "911",
                  "CANFOLLOW"
                ]
              ],
              "score": 1.0,
              "type": "relationship_chain",
              "source": "772"
            },
            "vulnerability_sequence_forward": {
              "path": [
                [
                  "772",
                  "911",
                  "CANFOLLOW"
                ]
              ],
              "score": 0.9,
              "type": "vulnerability_sequence_forward",
              "source": "772"
            },
            "vulnerability_sequence_backward": {
              "path": [
                [
                  "911",
                  "772",
                  "CANPRECEDE"
                ]
              ],
              "score": 1.0,
              "type": "vulnerability_sequence_backward",
              "source": "772"
            }
          }
        },
        "position": "before",
        "sources": [
          "graph"
        ],
        "source": "graph",
        "mapping_notes": {
          "usage": "Allowed",
          "rationale": "This CWE entry is at the Base level of abstraction, which is a preferred level of abstraction for mapping to the root causes of vulnerabilities.",
          "comments": "Carefully read both the name and description to ensure that this mapping is an appropriate fit. Do not try to 'force' a mapping to a lower-level Base/Variant simply to comply with this preferred level of abstraction.",
          "reasons": [
            "Acceptable-Use"
          ]
        },
        "score_info": {
          "retrievers": [
            "graph"
          ],
          "retriever_count": 1,
          "normalized_scores": {
            "graph": 2.2100000000000004
          }
        }
      },
      "similarity": 2.2100000000000004
    }
  ],
  "identified_cwes": {
    "analyzer": [
      "CWE-779",
      "CWE-400",
      "CWE-911",
      "CWE-770",
      "CWE-834",
      "CWE-920",
      "CWE-410",
      "CWE-771",
      "CWE-674",
      "CWE-664",
      "CWE-693",
      "CWE-789",
      "CWE-772"
    ],
    "critic_additional": []
  },
  "keyphrase_cwe_mapping": {}
}