{
  "vulnerability_info": "VulnerabilityInfo(cve_id='CVE-2025-1744', description='Out-of-bounds Write vulnerability in radareorg radare2 allows **heap-based buffer over-read** or buffer overflow.This issue affects radare2 before <5.9.9.', key_phrases={'rootcause': '', 'weakness': ['heap-based buffer over-read', 'heap-based buffer overflow'], 'impact': '', 'vector': '', 'attacker': '', 'product': 'radareorg radare2', 'version': 'before <5.9.9', 'component': ''}, reference_content=\"CVE-2025-1744 - radare2 zlib Vulnerability\\n\\n**Root cause of vulnerability:**\\nThe vulnerability stems from a missing security patch in the zlib library used by radare2. Specifically, the issue arose because the cloned zlib version hadn't received a security fix (eff308af425b67093bab25f80f1ae950166bece1) present in the original zlib.\\n\\n**Weaknesses/vulnerabilities present:**\\n- Buffer overflow in `inflate()` function when handling gzip header extra fields. If the extra field is larger than the allocated space, and multiple calls to `inflate()` deliver the extra header data, a buffer overflow can occur.\\n- A potential segmentation fault was introduced by the initial patch (eff308af425b67093bab25f80f1ae950166bece1) and later fixed in a follow-up commit (1eb7682f845ac9e9bf9ae35bbfb3bad5dacbd91d) which was not included in the initial fix.\\n\\n**Impact of exploitation:**\\n- Buffer overflow could lead to crashes or potentially arbitrary code execution.\\n\\n**Attack vectors:**\\n- Processing a specially crafted gzip file with a large extra field in the header.\\n\\n**Required attacker capabilities/position:**\\n- Ability to provide a malicious gzip file as input to radare2.\\n\\n**Mitigation or fix:**\\n- The pull request #23969 applied the patch from madler/zlib@eff308af425b67093bab25f80f1ae950166bece1 to address the buffer overflow.\\n- A follow-up patch (1eb7682f845ac9e9bf9ae35bbfb3bad5dacbd91d) to address a segmentation fault introduced by the initial patch is suggested but not yet implemented.\\n- Backporting the patch to distribution packages is recommended until the next radare2 release (6.0.0).\\n\\n**Note:** The content provides more detail than the official CVE description, detailing the specific commits and the potential for a segmentation fault.\", similar_info={'cwe_distribution': {}, 'cwe_consensus': '', 'similarity_stats': {'thresholds': [], 'total_samples_by_threshold': {}, 'top_cwes_by_threshold': {}}}, similarity_summary=SimilarityInsight(consensus_cwe='', top_cwes=[], confidence_levels={}, total_samples=0), analysis='', analysis_with_relationships='', criticism='', resolution='', relevant_cwes=[{'metadata': {'doc_id': '126', 'name': 'Buffer Over-read', 'source': 'sparse', 'original_content': 'The product reads from a buffer using buffer access mechanisms such as indexes or pointers that reference memory locations after the targeted buffer.', 'keyphrase_sources': [{'id': 'weakness:heap-based buffer over-read', 'keyphrase': 'heap-based buffer over-read', 'type': 'weakness'}, {'id': 'weakness:heap-based buffer overflow', 'keyphrase': 'heap-based buffer overflow', 'type': 'weakness'}, {'id': 'product:radareorg radare2', 'keyphrase': 'radareorg radare2', 'type': 'product'}, {'id': 'version:before <5.9.9', 'keyphrase': 'before <5.9.9', 'type': 'version'}]}, 'similarity': np.float64(281.7757753605898)}, {'metadata': {'doc_id': '122', 'name': 'Heap-based Buffer Overflow', 'source': 'sparse', 'original_content': 'A heap overflow condition is a buffer overflow, where the buffer that can be overwritten is allocated in the heap portion of memory, generally meaning that the buffer was allocated using a routine such as malloc().', 'keyphrase_sources': [{'id': 'weakness:heap-based buffer over-read', 'keyphrase': 'heap-based buffer over-read', 'type': 'weakness'}, {'id': 'weakness:heap-based buffer overflow', 'keyphrase': 'heap-based buffer overflow', 'type': 'weakness'}, {'id': 'product:radareorg radare2', 'keyphrase': 'radareorg radare2', 'type': 'product'}, {'id': 'version:before <5.9.9', 'keyphrase': 'before <5.9.9', 'type': 'version'}]}, 'similarity': np.float64(275.3543217665666)}, {'metadata': {'doc_id': '193', 'name': 'Off-by-one Error', 'source': 'sparse', 'original_content': 'A product calculates or uses an incorrect maximum or minimum value that is 1 more, or 1 less, than the correct value.', 'keyphrase_sources': [{'id': 'weakness:heap-based buffer over-read', 'keyphrase': 'heap-based buffer over-read', 'type': 'weakness'}, {'id': 'weakness:heap-based buffer overflow', 'keyphrase': 'heap-based buffer overflow', 'type': 'weakness'}, {'id': 'version:before <5.9.9', 'keyphrase': 'before <5.9.9', 'type': 'version'}]}, 'similarity': np.float64(245.24211543765185)}, {'metadata': {'doc_id': '190', 'name': 'Integer Overflow or Wraparound', 'source': 'sparse', 'original_content': 'The product performs a calculation that can\\n         produce an integer overflow or wraparound when the logic\\n         assumes that the resulting value will always be larger than\\n         the original value. This occurs when an integer value is\\n         incremented to a value that is too large to store in the\\n         associated representation. When this occurs, the value may\\n         become a very small or negative number.', 'keyphrase_sources': [{'id': 'weakness:heap-based buffer over-read', 'keyphrase': 'heap-based buffer over-read', 'type': 'weakness'}, {'id': 'weakness:heap-based buffer overflow', 'keyphrase': 'heap-based buffer overflow', 'type': 'weakness'}, {'id': 'version:before <5.9.9', 'keyphrase': 'before <5.9.9', 'type': 'version'}]}, 'similarity': np.float64(239.70937433152304)}, {'metadata': {'doc_id': '131', 'name': 'Incorrect Calculation of Buffer Size', 'source': 'sparse', 'original_content': 'The product does not correctly calculate the size to be used when allocating a buffer, which could lead to a buffer overflow.', 'keyphrase_sources': [{'id': 'weakness:heap-based buffer overflow', 'keyphrase': 'heap-based buffer overflow', 'type': 'weakness'}]}, 'similarity': np.float64(226.19775641378112)}, {'metadata': {'doc_id': '125', 'name': 'Out-of-bounds Read', 'source': 'sparse', 'original_content': 'The product reads data past the end, or before the beginning, of the intended buffer.', 'keyphrase_sources': [{'id': 'weakness:heap-based buffer over-read', 'keyphrase': 'heap-based buffer over-read', 'type': 'weakness'}]}, 'similarity': np.float64(218.42457242736737)}, {'metadata': {'doc_id': '805', 'name': 'Buffer Access with Incorrect Length Value', 'source': 'sparse', 'original_content': 'The product uses a sequential operation to read or write a buffer, but it uses an incorrect length value that causes it to access memory that is outside of the bounds of the buffer.', 'keyphrase_sources': [{'id': 'product:radareorg radare2', 'keyphrase': 'radareorg radare2', 'type': 'product'}]}, 'similarity': np.float64(75.97053641344424)}, {'metadata': {'doc_id': '476', 'name': 'NULL Pointer Dereference', 'source': 'sparse', 'original_content': 'The product dereferences a pointer that it expects to be valid but is NULL.', 'keyphrase_sources': [{'id': 'product:radareorg radare2', 'keyphrase': 'radareorg radare2', 'type': 'product'}]}, 'similarity': np.float64(74.46745104232448)}, {'metadata': {'doc_id': '119', 'name': 'Improper Restriction of Operations within the Bounds of a Memory Buffer', 'source': 'sparse', 'original_content': \"The product performs operations on a memory buffer, but it reads from or writes to a memory location outside the buffer's intended boundary. This may result in read or write operations on unexpected memory locations that could be linked to other variables, data structures, or internal program data.\", 'keyphrase_sources': [{'id': 'product:radareorg radare2', 'keyphrase': 'radareorg radare2', 'type': 'product'}, {'id': 'version:before <5.9.9', 'keyphrase': 'before <5.9.9', 'type': 'version'}]}, 'similarity': np.float64(57.34555849002585)}], identified_cwes={'analyzer': [], 'critic_additional': []})",
  "retrieval_results": {
    "has_multiple_keyphrases": true,
    "keyphrase_cwe_sets": {
      "weakness:heap-based buffer over-read": {
        "keyphrase": "heap-based buffer over-read",
        "type": "weakness",
        "cwes": [
          {
            "metadata": {
              "doc_id": "126",
              "name": "Buffer Over-read",
              "source": "sparse",
              "original_content": "The product reads from a buffer using buffer access mechanisms such as indexes or pointers that reference memory locations after the targeted buffer.",
              "keyphrase_sources": [
                {
                  "id": "weakness:heap-based buffer over-read",
                  "keyphrase": "heap-based buffer over-read",
                  "type": "weakness"
                },
                {
                  "id": "weakness:heap-based buffer overflow",
                  "keyphrase": "heap-based buffer overflow",
                  "type": "weakness"
                },
                {
                  "id": "product:radareorg radare2",
                  "keyphrase": "radareorg radare2",
                  "type": "product"
                },
                {
                  "id": "version:before <5.9.9",
                  "keyphrase": "before <5.9.9",
                  "type": "version"
                }
              ]
            },
            "similarity": 281.7757753605898
          },
          {
            "metadata": {
              "doc_id": "122",
              "name": "Heap-based Buffer Overflow",
              "source": "sparse",
              "original_content": "A heap overflow condition is a buffer overflow, where the buffer that can be overwritten is allocated in the heap portion of memory, generally meaning that the buffer was allocated using a routine such as malloc().",
              "keyphrase_sources": [
                {
                  "id": "weakness:heap-based buffer over-read",
                  "keyphrase": "heap-based buffer over-read",
                  "type": "weakness"
                },
                {
                  "id": "weakness:heap-based buffer overflow",
                  "keyphrase": "heap-based buffer overflow",
                  "type": "weakness"
                },
                {
                  "id": "product:radareorg radare2",
                  "keyphrase": "radareorg radare2",
                  "type": "product"
                },
                {
                  "id": "version:before <5.9.9",
                  "keyphrase": "before <5.9.9",
                  "type": "version"
                }
              ]
            },
            "similarity": 275.3543217665666
          },
          {
            "metadata": {
              "doc_id": "193",
              "name": "Off-by-one Error",
              "source": "sparse",
              "original_content": "A product calculates or uses an incorrect maximum or minimum value that is 1 more, or 1 less, than the correct value.",
              "keyphrase_sources": [
                {
                  "id": "weakness:heap-based buffer over-read",
                  "keyphrase": "heap-based buffer over-read",
                  "type": "weakness"
                },
                {
                  "id": "weakness:heap-based buffer overflow",
                  "keyphrase": "heap-based buffer overflow",
                  "type": "weakness"
                },
                {
                  "id": "version:before <5.9.9",
                  "keyphrase": "before <5.9.9",
                  "type": "version"
                }
              ]
            },
            "similarity": 245.24211543765185
          },
          {
            "metadata": {
              "doc_id": "190",
              "name": "Integer Overflow or Wraparound",
              "source": "sparse",
              "original_content": "The product performs a calculation that can\n         produce an integer overflow or wraparound when the logic\n         assumes that the resulting value will always be larger than\n         the original value. This occurs when an integer value is\n         incremented to a value that is too large to store in the\n         associated representation. When this occurs, the value may\n         become a very small or negative number.",
              "keyphrase_sources": [
                {
                  "id": "weakness:heap-based buffer over-read",
                  "keyphrase": "heap-based buffer over-read",
                  "type": "weakness"
                },
                {
                  "id": "weakness:heap-based buffer overflow",
                  "keyphrase": "heap-based buffer overflow",
                  "type": "weakness"
                },
                {
                  "id": "version:before <5.9.9",
                  "keyphrase": "before <5.9.9",
                  "type": "version"
                }
              ]
            },
            "similarity": 239.70937433152304
          },
          {
            "metadata": {
              "doc_id": "125",
              "name": "Out-of-bounds Read",
              "source": "sparse",
              "original_content": "The product reads data past the end, or before the beginning, of the intended buffer.",
              "keyphrase_sources": [
                {
                  "id": "weakness:heap-based buffer over-read",
                  "keyphrase": "heap-based buffer over-read",
                  "type": "weakness"
                }
              ]
            },
            "similarity": 218.42457242736737
          }
        ]
      },
      "weakness:heap-based buffer overflow": {
        "keyphrase": "heap-based buffer overflow",
        "type": "weakness",
        "cwes": [
          {
            "metadata": {
              "doc_id": "122",
              "name": "Heap-based Buffer Overflow",
              "source": "sparse",
              "original_content": "A heap overflow condition is a buffer overflow, where the buffer that can be overwritten is allocated in the heap portion of memory, generally meaning that the buffer was allocated using a routine such as malloc()."
            },
            "similarity": 293.77504890731194
          },
          {
            "metadata": {
              "doc_id": "126",
              "name": "Buffer Over-read",
              "source": "sparse",
              "original_content": "The product reads from a buffer using buffer access mechanisms such as indexes or pointers that reference memory locations after the targeted buffer."
            },
            "similarity": 260.20389650812797
          },
          {
            "metadata": {
              "doc_id": "190",
              "name": "Integer Overflow or Wraparound",
              "source": "sparse",
              "original_content": "The product performs a calculation that can\n         produce an integer overflow or wraparound when the logic\n         assumes that the resulting value will always be larger than\n         the original value. This occurs when an integer value is\n         incremented to a value that is too large to store in the\n         associated representation. When this occurs, the value may\n         become a very small or negative number."
            },
            "similarity": 257.747226011052
          },
          {
            "metadata": {
              "doc_id": "193",
              "name": "Off-by-one Error",
              "source": "sparse",
              "original_content": "A product calculates or uses an incorrect maximum or minimum value that is 1 more, or 1 less, than the correct value."
            },
            "similarity": 251.0007641435891
          },
          {
            "metadata": {
              "doc_id": "131",
              "name": "Incorrect Calculation of Buffer Size",
              "source": "sparse",
              "original_content": "The product does not correctly calculate the size to be used when allocating a buffer, which could lead to a buffer overflow.",
              "keyphrase_sources": [
                {
                  "id": "weakness:heap-based buffer overflow",
                  "keyphrase": "heap-based buffer overflow",
                  "type": "weakness"
                }
              ]
            },
            "similarity": 226.19775641378112
          }
        ]
      },
      "product:radareorg radare2": {
        "keyphrase": "radareorg radare2",
        "type": "product",
        "cwes": [
          {
            "metadata": {
              "doc_id": "122",
              "name": "Heap-based Buffer Overflow",
              "source": "sparse",
              "original_content": "A heap overflow condition is a buffer overflow, where the buffer that can be overwritten is allocated in the heap portion of memory, generally meaning that the buffer was allocated using a routine such as malloc()."
            },
            "similarity": 80.03908914085409
          },
          {
            "metadata": {
              "doc_id": "805",
              "name": "Buffer Access with Incorrect Length Value",
              "source": "sparse",
              "original_content": "The product uses a sequential operation to read or write a buffer, but it uses an incorrect length value that causes it to access memory that is outside of the bounds of the buffer.",
              "keyphrase_sources": [
                {
                  "id": "product:radareorg radare2",
                  "keyphrase": "radareorg radare2",
                  "type": "product"
                }
              ]
            },
            "similarity": 75.97053641344424
          },
          {
            "metadata": {
              "doc_id": "476",
              "name": "NULL Pointer Dereference",
              "source": "sparse",
              "original_content": "The product dereferences a pointer that it expects to be valid but is NULL.",
              "keyphrase_sources": [
                {
                  "id": "product:radareorg radare2",
                  "keyphrase": "radareorg radare2",
                  "type": "product"
                }
              ]
            },
            "similarity": 74.46745104232448
          },
          {
            "metadata": {
              "doc_id": "126",
              "name": "Buffer Over-read",
              "source": "sparse",
              "original_content": "The product reads from a buffer using buffer access mechanisms such as indexes or pointers that reference memory locations after the targeted buffer."
            },
            "similarity": 68.11466028326517
          },
          {
            "metadata": {
              "doc_id": "119",
              "name": "Improper Restriction of Operations within the Bounds of a Memory Buffer",
              "source": "sparse",
              "original_content": "The product performs operations on a memory buffer, but it reads from or writes to a memory location outside the buffer's intended boundary. This may result in read or write operations on unexpected memory locations that could be linked to other variables, data structures, or internal program data.",
              "keyphrase_sources": [
                {
                  "id": "product:radareorg radare2",
                  "keyphrase": "radareorg radare2",
                  "type": "product"
                },
                {
                  "id": "version:before <5.9.9",
                  "keyphrase": "before <5.9.9",
                  "type": "version"
                }
              ]
            },
            "similarity": 57.34555849002585
          }
        ]
      },
      "version:before <5.9.9": {
        "keyphrase": "before <5.9.9",
        "type": "version",
        "cwes": [
          {
            "metadata": {
              "doc_id": "122",
              "name": "Heap-based Buffer Overflow",
              "source": "sparse",
              "original_content": "A heap overflow condition is a buffer overflow, where the buffer that can be overwritten is allocated in the heap portion of memory, generally meaning that the buffer was allocated using a routine such as malloc()."
            },
            "similarity": 78.61791801215506
          },
          {
            "metadata": {
              "doc_id": "126",
              "name": "Buffer Over-read",
              "source": "sparse",
              "original_content": "The product reads from a buffer using buffer access mechanisms such as indexes or pointers that reference memory locations after the targeted buffer."
            },
            "similarity": 75.10671175383331
          },
          {
            "metadata": {
              "doc_id": "119",
              "name": "Improper Restriction of Operations within the Bounds of a Memory Buffer",
              "source": "sparse",
              "original_content": "The product performs operations on a memory buffer, but it reads from or writes to a memory location outside the buffer's intended boundary. This may result in read or write operations on unexpected memory locations that could be linked to other variables, data structures, or internal program data."
            },
            "similarity": 65.97595809241277
          },
          {
            "metadata": {
              "doc_id": "190",
              "name": "Integer Overflow or Wraparound",
              "source": "sparse",
              "original_content": "The product performs a calculation that can\n         produce an integer overflow or wraparound when the logic\n         assumes that the resulting value will always be larger than\n         the original value. This occurs when an integer value is\n         incremented to a value that is too large to store in the\n         associated representation. When this occurs, the value may\n         become a very small or negative number."
            },
            "similarity": 65.65273805892008
          },
          {
            "metadata": {
              "doc_id": "193",
              "name": "Off-by-one Error",
              "source": "sparse",
              "original_content": "A product calculates or uses an incorrect maximum or minimum value that is 1 more, or 1 less, than the correct value."
            },
            "similarity": 63.34165392396109
          }
        ]
      }
    },
    "keyphrase_mapping": {
      "126": [
        {
          "id": "weakness:heap-based buffer over-read",
          "keyphrase": "heap-based buffer over-read",
          "type": "weakness"
        },
        {
          "id": "weakness:heap-based buffer overflow",
          "keyphrase": "heap-based buffer overflow",
          "type": "weakness"
        },
        {
          "id": "product:radareorg radare2",
          "keyphrase": "radareorg radare2",
          "type": "product"
        },
        {
          "id": "version:before <5.9.9",
          "keyphrase": "before <5.9.9",
          "type": "version"
        }
      ],
      "122": [
        {
          "id": "weakness:heap-based buffer over-read",
          "keyphrase": "heap-based buffer over-read",
          "type": "weakness"
        },
        {
          "id": "weakness:heap-based buffer overflow",
          "keyphrase": "heap-based buffer overflow",
          "type": "weakness"
        },
        {
          "id": "product:radareorg radare2",
          "keyphrase": "radareorg radare2",
          "type": "product"
        },
        {
          "id": "version:before <5.9.9",
          "keyphrase": "before <5.9.9",
          "type": "version"
        }
      ],
      "193": [
        {
          "id": "weakness:heap-based buffer over-read",
          "keyphrase": "heap-based buffer over-read",
          "type": "weakness"
        },
        {
          "id": "weakness:heap-based buffer overflow",
          "keyphrase": "heap-based buffer overflow",
          "type": "weakness"
        },
        {
          "id": "version:before <5.9.9",
          "keyphrase": "before <5.9.9",
          "type": "version"
        }
      ],
      "190": [
        {
          "id": "weakness:heap-based buffer over-read",
          "keyphrase": "heap-based buffer over-read",
          "type": "weakness"
        },
        {
          "id": "weakness:heap-based buffer overflow",
          "keyphrase": "heap-based buffer overflow",
          "type": "weakness"
        },
        {
          "id": "version:before <5.9.9",
          "keyphrase": "before <5.9.9",
          "type": "version"
        }
      ],
      "125": [
        {
          "id": "weakness:heap-based buffer over-read",
          "keyphrase": "heap-based buffer over-read",
          "type": "weakness"
        }
      ],
      "131": [
        {
          "id": "weakness:heap-based buffer overflow",
          "keyphrase": "heap-based buffer overflow",
          "type": "weakness"
        }
      ],
      "805": [
        {
          "id": "product:radareorg radare2",
          "keyphrase": "radareorg radare2",
          "type": "product"
        }
      ],
      "476": [
        {
          "id": "product:radareorg radare2",
          "keyphrase": "radareorg radare2",
          "type": "product"
        }
      ],
      "119": [
        {
          "id": "product:radareorg radare2",
          "keyphrase": "radareorg radare2",
          "type": "product"
        },
        {
          "id": "version:before <5.9.9",
          "keyphrase": "before <5.9.9",
          "type": "version"
        }
      ]
    },
    "relevant_cwes": [
      {
        "metadata": {
          "doc_id": "126",
          "name": "Buffer Over-read",
          "source": "sparse",
          "original_content": "The product reads from a buffer using buffer access mechanisms such as indexes or pointers that reference memory locations after the targeted buffer.",
          "keyphrase_sources": [
            {
              "id": "weakness:heap-based buffer over-read",
              "keyphrase": "heap-based buffer over-read",
              "type": "weakness"
            },
            {
              "id": "weakness:heap-based buffer overflow",
              "keyphrase": "heap-based buffer overflow",
              "type": "weakness"
            },
            {
              "id": "product:radareorg radare2",
              "keyphrase": "radareorg radare2",
              "type": "product"
            },
            {
              "id": "version:before <5.9.9",
              "keyphrase": "before <5.9.9",
              "type": "version"
            }
          ]
        },
        "similarity": 281.7757753605898
      },
      {
        "metadata": {
          "doc_id": "122",
          "name": "Heap-based Buffer Overflow",
          "source": "sparse",
          "original_content": "A heap overflow condition is a buffer overflow, where the buffer that can be overwritten is allocated in the heap portion of memory, generally meaning that the buffer was allocated using a routine such as malloc().",
          "keyphrase_sources": [
            {
              "id": "weakness:heap-based buffer over-read",
              "keyphrase": "heap-based buffer over-read",
              "type": "weakness"
            },
            {
              "id": "weakness:heap-based buffer overflow",
              "keyphrase": "heap-based buffer overflow",
              "type": "weakness"
            },
            {
              "id": "product:radareorg radare2",
              "keyphrase": "radareorg radare2",
              "type": "product"
            },
            {
              "id": "version:before <5.9.9",
              "keyphrase": "before <5.9.9",
              "type": "version"
            }
          ]
        },
        "similarity": 275.3543217665666
      },
      {
        "metadata": {
          "doc_id": "193",
          "name": "Off-by-one Error",
          "source": "sparse",
          "original_content": "A product calculates or uses an incorrect maximum or minimum value that is 1 more, or 1 less, than the correct value.",
          "keyphrase_sources": [
            {
              "id": "weakness:heap-based buffer over-read",
              "keyphrase": "heap-based buffer over-read",
              "type": "weakness"
            },
            {
              "id": "weakness:heap-based buffer overflow",
              "keyphrase": "heap-based buffer overflow",
              "type": "weakness"
            },
            {
              "id": "version:before <5.9.9",
              "keyphrase": "before <5.9.9",
              "type": "version"
            }
          ]
        },
        "similarity": 245.24211543765185
      },
      {
        "metadata": {
          "doc_id": "190",
          "name": "Integer Overflow or Wraparound",
          "source": "sparse",
          "original_content": "The product performs a calculation that can\n         produce an integer overflow or wraparound when the logic\n         assumes that the resulting value will always be larger than\n         the original value. This occurs when an integer value is\n         incremented to a value that is too large to store in the\n         associated representation. When this occurs, the value may\n         become a very small or negative number.",
          "keyphrase_sources": [
            {
              "id": "weakness:heap-based buffer over-read",
              "keyphrase": "heap-based buffer over-read",
              "type": "weakness"
            },
            {
              "id": "weakness:heap-based buffer overflow",
              "keyphrase": "heap-based buffer overflow",
              "type": "weakness"
            },
            {
              "id": "version:before <5.9.9",
              "keyphrase": "before <5.9.9",
              "type": "version"
            }
          ]
        },
        "similarity": 239.70937433152304
      },
      {
        "metadata": {
          "doc_id": "131",
          "name": "Incorrect Calculation of Buffer Size",
          "source": "sparse",
          "original_content": "The product does not correctly calculate the size to be used when allocating a buffer, which could lead to a buffer overflow.",
          "keyphrase_sources": [
            {
              "id": "weakness:heap-based buffer overflow",
              "keyphrase": "heap-based buffer overflow",
              "type": "weakness"
            }
          ]
        },
        "similarity": 226.19775641378112
      },
      {
        "metadata": {
          "doc_id": "125",
          "name": "Out-of-bounds Read",
          "source": "sparse",
          "original_content": "The product reads data past the end, or before the beginning, of the intended buffer.",
          "keyphrase_sources": [
            {
              "id": "weakness:heap-based buffer over-read",
              "keyphrase": "heap-based buffer over-read",
              "type": "weakness"
            }
          ]
        },
        "similarity": 218.42457242736737
      },
      {
        "metadata": {
          "doc_id": "805",
          "name": "Buffer Access with Incorrect Length Value",
          "source": "sparse",
          "original_content": "The product uses a sequential operation to read or write a buffer, but it uses an incorrect length value that causes it to access memory that is outside of the bounds of the buffer.",
          "keyphrase_sources": [
            {
              "id": "product:radareorg radare2",
              "keyphrase": "radareorg radare2",
              "type": "product"
            }
          ]
        },
        "similarity": 75.97053641344424
      },
      {
        "metadata": {
          "doc_id": "476",
          "name": "NULL Pointer Dereference",
          "source": "sparse",
          "original_content": "The product dereferences a pointer that it expects to be valid but is NULL.",
          "keyphrase_sources": [
            {
              "id": "product:radareorg radare2",
              "keyphrase": "radareorg radare2",
              "type": "product"
            }
          ]
        },
        "similarity": 74.46745104232448
      },
      {
        "metadata": {
          "doc_id": "119",
          "name": "Improper Restriction of Operations within the Bounds of a Memory Buffer",
          "source": "sparse",
          "original_content": "The product performs operations on a memory buffer, but it reads from or writes to a memory location outside the buffer's intended boundary. This may result in read or write operations on unexpected memory locations that could be linked to other variables, data structures, or internal program data.",
          "keyphrase_sources": [
            {
              "id": "product:radareorg radare2",
              "keyphrase": "radareorg radare2",
              "type": "product"
            },
            {
              "id": "version:before <5.9.9",
              "keyphrase": "before <5.9.9",
              "type": "version"
            }
          ]
        },
        "similarity": 57.34555849002585
      }
    ],
    "enhanced_query": "# Vulnerability Description\n\n    Out-of-bounds Write vulnerability in radareorg radare2 allows **heap-based buffer over-read** or buffer overflow.This issue affects radare2 before <5.9.9.\n\n    # Keyphrase-Specific CWE Analysis\n    This vulnerability contains multiple keyphrases that may map to different CWEs. \n    Please analyze each keyphrase separately and determine the most appropriate CWE(s) for each.\n\n    ## WEAKNESS: 'heap-based buffer over-read'\n\nRelevant CWEs for this WEAKNESS:\n\n### 1. CWE-126: Buffer Over-read (Score: 281.78)\n\nThe product reads from a buffer using buffer access mechanisms such as indexes or pointers that reference memory locations after the targeted buffer....\n\n### 2. CWE-122: Heap-based Buffer Overflow (Score: 275.35)\n\nA heap overflow condition is a buffer overflow, where the buffer that can be overwritten is allocated in the heap portion of memory, generally meaning that the buffer was allocated using a routine such as malloc()....\n\n### 3. CWE-193: Off-by-one Error (Score: 245.24)\n\nA product calculates or uses an incorrect maximum or minimum value that is 1 more, or 1 less, than the correct value....\n\n### 4. CWE-190: Integer Overflow or Wraparound (Score: 239.71)\n\nThe product performs a calculation that can\n         produce an integer overflow or wraparound when the logic\n         assumes that the resulting value will always be larger than\n         the original value. This occurs when an integer value is\n         incremented to a value that is too large to st...\n\n### 5. CWE-125: Out-of-bounds Read (Score: 218.42)\n\nThe product reads data past the end, or before the beginning, of the intended buffer....\n\n## WEAKNESS: 'heap-based buffer overflow'\n\nRelevant CWEs for this WEAKNESS:\n\n### 1. CWE-126: Buffer Over-read (Score: 281.78)\n\nThe product reads from a buffer using buffer access mechanisms such as indexes or pointers that reference memory locations after the targeted buffer....\n\n### 2. CWE-122: Heap-based Buffer Overflow (Score: 275.35)\n\nA heap overflow condition is a buffer overflow, where the buffer that can be overwritten is allocated in the heap portion of memory, generally meaning that the buffer was allocated using a routine such as malloc()....\n\n### 3. CWE-193: Off-by-one Error (Score: 245.24)\n\nA product calculates or uses an incorrect maximum or minimum value that is 1 more, or 1 less, than the correct value....\n\n### 4. CWE-190: Integer Overflow or Wraparound (Score: 239.71)\n\nThe product performs a calculation that can\n         produce an integer overflow or wraparound when the logic\n         assumes that the resulting value will always be larger than\n         the original value. This occurs when an integer value is\n         incremented to a value that is too large to st...\n\n### 5. CWE-131: Incorrect Calculation of Buffer Size (Score: 226.20)\n\nThe product does not correctly calculate the size to be used when allocating a buffer, which could lead to a buffer overflow....\n\n## PRODUCT: 'radareorg radare2'\n\nRelevant CWEs for this PRODUCT:\n\n### 1. CWE-126: Buffer Over-read (Score: 281.78)\n\nThe product reads from a buffer using buffer access mechanisms such as indexes or pointers that reference memory locations after the targeted buffer....\n\n### 2. CWE-122: Heap-based Buffer Overflow (Score: 275.35)\n\nA heap overflow condition is a buffer overflow, where the buffer that can be overwritten is allocated in the heap portion of memory, generally meaning that the buffer was allocated using a routine such as malloc()....\n\n### 3. CWE-805: Buffer Access with Incorrect Length Value (Score: 75.97)\n\nThe product uses a sequential operation to read or write a buffer, but it uses an incorrect length value that causes it to access memory that is outside of the bounds of the buffer....\n\n### 4. CWE-476: NULL Pointer Dereference (Score: 74.47)\n\nThe product dereferences a pointer that it expects to be valid but is NULL....\n\n### 5. CWE-119: Improper Restriction of Operations within the Bounds of a Memory Buffer (Score: 57.35)\n\nThe product performs operations on a memory buffer, but it reads from or writes to a memory location outside the buffer's intended boundary. This may result in read or write operations on unexpected memory locations that could be linked to other variables, data structures, or internal program data....\n\n## VERSION: 'before <5.9.9'\n\nRelevant CWEs for this VERSION:\n\n### 1. CWE-126: Buffer Over-read (Score: 281.78)\n\nThe product reads from a buffer using buffer access mechanisms such as indexes or pointers that reference memory locations after the targeted buffer....\n\n### 2. CWE-122: Heap-based Buffer Overflow (Score: 275.35)\n\nA heap overflow condition is a buffer overflow, where the buffer that can be overwritten is allocated in the heap portion of memory, generally meaning that the buffer was allocated using a routine such as malloc()....\n\n### 3. CWE-193: Off-by-one Error (Score: 245.24)\n\nA product calculates or uses an incorrect maximum or minimum value that is 1 more, or 1 less, than the correct value....\n\n### 4. CWE-190: Integer Overflow or Wraparound (Score: 239.71)\n\nThe product performs a calculation that can\n         produce an integer overflow or wraparound when the logic\n         assumes that the resulting value will always be larger than\n         the original value. This occurs when an integer value is\n         incremented to a value that is too large to st...\n\n### 5. CWE-119: Improper Restriction of Operations within the Bounds of a Memory Buffer (Score: 57.35)\n\nThe product performs operations on a memory buffer, but it reads from or writes to a memory location outside the buffer's intended boundary. This may result in read or write operations on unexpected memory locations that could be linked to other variables, data structures, or internal program data....\n\n\n    # Analysis Instructions\n    1. For each keyphrase, identify the most appropriate CWE(s) that represent the weakness.\n    2. Consider how the different keyphrases might relate to each other in the vulnerability chain.\n    3. Provide a final determination of primary CWE(s) and any secondary CWEs.\n    4. Format your response using the standard analysis template.\n\n    Please analyze how these different weaknesses interact and provide a comprehensive CWE classification.\n    "
  },
  "retrieval_time": 0.894136905670166
}