{
  "cve_id": "CVE-2025-2230",
  "description": "A flaw exists in the Windows login flow where an AuthContext token can be exploited for replay attacks and authentication bypass.",
  "key_phrases": {
    "rootcause": "",
    "weakness": "",
    "impact": [
      "authentication bypass",
      "replay attacks"
    ],
    "vector": "replay attacks",
    "attacker": "",
    "product": "Windows",
    "version": "",
    "component": "login flow"
  },
  "reference_content": "```\nNOINFO\n```",
  "similar_info": {
    "cwe_distribution": {},
    "cwe_consensus": "",
    "similarity_stats": {
      "thresholds": [],
      "total_samples_by_threshold": {},
      "top_cwes_by_threshold": {}
    }
  },
  "similarity_summary": {
    "consensus_cwe": "",
    "top_cwes": [],
    "confidence_levels": {},
    "total_samples": 0
  },
  "analysis": "# Summary\n| CWE ID | CWE Name | Confidence | CWE Abstraction Level | CWE Vulnerability Mapping Label | CWE-Vulnerability Mapping Notes |\n|---|---|---|---|---|---|\n| CWE-287 | Improper Authentication | 0.8 | Class |  Primary CWE | Discouraged |\n| CWE-294 | Authentication Bypass by Capture-replay | 0.5 | Base | Secondary Candidate | Allowed |\n\n## Evidence and Confidence\n\n*   **Confidence Score:** 0.7\n*   **Evidence Strength:** LOW\n\n## Relationship Analysis\nThe primary relationship identified is that CWE-287 is a class-level CWE, and several more specific CWEs, such as CWE-294, could be considered as potential child CWEs. The analysis focuses on authentication bypass, making authentication-related CWEs relevant.\n\n```mermaid\ngraph TD\n    cwe287[\"CWE-287: Improper Authentication\"]\n    cwe294[\"CWE-294: Authentication Bypass by Capture-replay\"]\n    cwe1390[\"CWE-1390: Weak Authentication\"]\n    \n    cwe294 -->|CHILDOF| cwe287\n    cwe1390 -->|CHILDOF| cwe287\n    \n    classDef primary fill:#f96,stroke:#333,stroke-width:2px\n    classDef secondary fill:#69f,stroke:#333\n    classDef tertiary fill:#9e9,stroke:#333\n    class cwe287 primary\n    class cwe294,cwe1390 secondary\n```\n\n## Vulnerability Chain\nThe vulnerability chain involves a **flaw in the Windows login flow** which leads to an **authentication bypass** through **replay attacks**. The root cause is the **improper authentication**, allowing the **AuthContext token** to be exploited.\n  - Root Cause: **Improper Authentication (CWE-287)**\n  - Mechanism: Replay Attack\n  - Impact: Authentication Bypass\n\n## Summary of Analysis\nThe initial assessment points to an authentication issue within the Windows login flow. The primary concern is the ability to bypass authentication using replay attacks on the AuthContext token.\n\nThe selection of CWE-287 is based on the vulnerability description indicating an **improper authentication** mechanism. However, due to the lack of detailed information in the \"CVE Reference Links Content Summary\", there's some uncertainty. Without more rootcause information, a more specific CWE is difficult to confirm.\n\nCWE-294 (Authentication Bypass by Capture-replay) is a strong candidate because the vulnerability description mentions replay attacks, but there is no supporting evidence to confirm this.\n\nRelevant CWE Information:\n\n# Enhanced Context (25 CWEs)\nThe following CWEs were identified as potentially relevant to this vulnerability:\n\n## CWE-287: Improper Authentication\n**Abstraction Level**: Class\n**Similarity Score**: 0.800\n**Source**: alternate_terms\n\n**Description**:\nThe product performs authentication, but there is a flaw in the authentication logic that allows attackers to bypass authentication.\n\n**Mapping Guidance**:\n- Usage: Discouraged\n- Rationale: CWE-287 is a very general class. More specific children are strongly preferred.\n\n## CWE-294: Authentication Bypass by Capture-replay\n**Abstraction Level**: Base\n**Similarity Score**: 0.051\n**Source**: sparse\n\n**Description**:\nA capture-replay flaw exists when the design of the product makes it possible for a malicious user to sniff network traffic and bypass authentication by replaying it to the server in question to the same effect as the original message (or with minor changes).\n\n**Mapping Guidance**:\n- Usage: Allowed\n- Rationale: This CWE entry is at the Base level of abstraction, which is a preferred level of abstraction for mapping to the root causes of vulnerabilities.\n\n## CWE-1390: Weak Authentication\n**Abstraction Level**: Class\n**Similarity Score**: 0.051\n**Source**: sparse\n\n**Description**:\nThe product uses an authentication mechanism to restrict access to specific users or identities, but the mechanism does not sufficiently prove that the claimed identity is correct.\n\n**Mapping Guidance**:\n- Usage: Allowed-with-Review\n- Rationale: This CWE entry is a Class and might have Base-level children that would be more appropriate\n\n## CWE-201: Insertion of Sensitive Information Into Sent Data\n**Abstraction Level**: Base\n**Similarity Score**: 0.046\n**Source**: sparse\n\n**Description**:\nCWE-201: Insertion of Sensitive Information Into Sent Data\n\n**Mapping Guidance**:\n- Usage: Allowed\n- Rationale: This CWE entry is at the Base level of abstraction, which is a preferred level of abstraction for mapping to the root causes of vulnerabilities.\n\n## CWE-1391: Use of Weak Credentials\n**Abstraction Level**: Class\n**Similarity Score**: 0.046\n**Source**: sparse\n\n**Description**:\nThe product uses weak credentials (such as a default key or hard-coded password) that can be calculated, derived, reused, or guessed by an attacker.\n\n**Mapping Guidance**:\n- Usage: Allowed-with-Review\n- Rationale: This CWE entry is a Class and might have Base-level children that would be more appropriate\n\n## CWE-522: Insufficiently Protected Credentials\n**Abstraction Level**: Class\n**Similarity Score**: 0.045\n**Source**: sparse\n\n**Description**:\nThe product stores credentials in a way that is not sufficiently protected, which can allow an attacker to obtain the credentials and use them to gain unauthorized access to the system.\n\n**Mapping Guidance**:\n- Usage: Allowed-with-Review\n- Rationale: This CWE entry is a Class and might have Base-level children that would be more appropriate\n\n## CWE-306: Missing Authentication for Critical Function\n**Abstraction Level**: Base\n**Similarity Score**: 0.045\n**Source**: sparse\n\n**Description**:\nThe product does not perform any authentication for functionality that requires a provable user identity or consumes a significant amount of resources.\n\n**Mapping Guidance**:\n- Usage: Allowed\n- Rationale: This CWE entry is at the Base level of abstraction, which is a preferred level of abstraction for mapping to the root causes of vulnerabilities.\n\n## CWE-208: Observable Timing Discrepancy\n**Abstraction Level**: Base\n**Similarity Score**: 0.045\n**Source**: sparse\n\n**Description**:\nCWE-208: Observable Timing Discrepancy\n\n**Mapping Guidance**:\n- Usage: Allowed\n- Rationale: This CWE entry is at the Base level of abstraction, which is a preferred level of abstraction for mapping to the root causes of vulnerabilities.\n\n## CWE-289: Authentication Bypass by Alternate Name\n**Abstraction Level**: base\n**Similarity Score**: 0.568\n**Source**: dense\n\n**Description**:\nCWE-289: Authentication Bypass by Alternate Name\n\n**Mapping Guidance**:\n- Usage: Allowed\n- Rationale: This CWE entry is at the Base level of abstraction, which is a preferred level of abstraction for mapping to the root causes of vulnerabilities.\n\n**Relationships**:\n- CANFOLLOW -> CWE-52\n- CANFOLLOW -> CWE-46\n- CANFOLLOW -> CWE-178\n- CANFOLLOW -> CWE-173\n- CHILDOF -> CWE-1390\n\n## CWE-178: Improper Handling of Case Sensitivity\n**Abstraction Level**: Base\n**Similarity Score**: 0.002\n**Source**: graph\n\n**Description**:\nThe product does not properly account for differences in case sensitivity when accessing or determining the properties of a resource, leading to inconsistent results.\n\n**Mapping Guidance**:\n- Usage: Allowed\n- Rationale: This CWE entry is at the Base level of abstraction, which is a preferred level of abstraction for mapping to the root causes of vulnerabilities.\n\n**Relationships**:\n- CANPRECEDE -> CWE-289\n- CANPRECEDE -> CWE-433\n- CHILDOF -> CWE-706\n- CHILDOF -> CWE-706\n- PARENTOF -> CWE-178\n\nCWE-287 is chosen as the primary CWE because the vulnerability involves a flaw in the authentication logic. CWE-294 is a secondary candidate because replay attacks are mentioned. The other CWEs were not chosen because there isn't enough evidence to support them.",
  "analysis_with_relationships": "# Summary\n| CWE ID | CWE Name | Confidence | CWE Abstraction Level | CWE Vulnerability Mapping Label | CWE-Vulnerability Mapping Notes |\n|---|---|---|---|---|---|\n| CWE-287 | Improper Authentication | 0.8 | Class |  Primary CWE | Discouraged |\n| CWE-294 | Authentication Bypass by Capture-replay | 0.5 | Base | Secondary Candidate | Allowed |\n\n## Evidence and Confidence\n\n*   **Confidence Score:** 0.7\n*   **Evidence Strength:** LOW\n\n## Relationship Analysis\nThe primary relationship identified is that CWE-287 is a class-level CWE, and several more specific CWEs, such as CWE-294, could be considered as potential child CWEs. The analysis focuses on authentication bypass, making authentication-related CWEs relevant.\n\n```mermaid\ngraph TD\n    cwe287[\"CWE-287: Improper Authentication\"]\n    cwe294[\"CWE-294: Authentication Bypass by Capture-replay\"]\n    cwe1390[\"CWE-1390: Weak Authentication\"]\n    \n    cwe294 -->|CHILDOF| cwe287\n    cwe1390 -->|CHILDOF| cwe287\n    \n    classDef primary fill:#f96,stroke:#333,stroke-width:2px\n    classDef secondary fill:#69f,stroke:#333\n    classDef tertiary fill:#9e9,stroke:#333\n    class cwe287 primary\n    class cwe294,cwe1390 secondary\n```\n\n## Vulnerability Chain\nThe vulnerability chain involves a **flaw in the Windows login flow** which leads to an **authentication bypass** through **replay attacks**. The root cause is the **improper authentication**, allowing the **AuthContext token** to be exploited.\n  - Root Cause: **Improper Authentication (CWE-287)**\n  - Mechanism: Replay Attack\n  - Impact: Authentication Bypass\n\n## Summary of Analysis\nThe initial assessment points to an authentication issue within the Windows login flow. The primary concern is the ability to bypass authentication using replay attacks on the AuthContext token.\n\nThe selection of CWE-287 is based on the vulnerability description indicating an **improper authentication** mechanism. However, due to the lack of detailed information in the \"CVE Reference Links Content Summary\", there's some uncertainty. Without more rootcause information, a more specific CWE is difficult to confirm.\n\nCWE-294 (Authentication Bypass by Capture-replay) is a strong candidate because the vulnerability description mentions replay attacks, but there is no supporting evidence to confirm this.\n\nRelevant CWE Information:\n\n# Enhanced Context (25 CWEs)\nThe following CWEs were identified as potentially relevant to this vulnerability:\n\n## CWE-287: Improper Authentication\n**Abstraction Level**: Class\n**Similarity Score**: 0.800\n**Source**: alternate_terms\n\n**Description**:\nThe product performs authentication, but there is a flaw in the authentication logic that allows attackers to bypass authentication.\n\n**Mapping Guidance**:\n- Usage: Discouraged\n- Rationale: CWE-287 is a very general class. More specific children are strongly preferred.\n\n## CWE-294: Authentication Bypass by Capture-replay\n**Abstraction Level**: Base\n**Similarity Score**: 0.051\n**Source**: sparse\n\n**Description**:\nA capture-replay flaw exists when the design of the product makes it possible for a malicious user to sniff network traffic and bypass authentication by replaying it to the server in question to the same effect as the original message (or with minor changes).\n\n**Mapping Guidance**:\n- Usage: Allowed\n- Rationale: This CWE entry is at the Base level of abstraction, which is a preferred level of abstraction for mapping to the root causes of vulnerabilities.\n\n## CWE-1390: Weak Authentication\n**Abstraction Level**: Class\n**Similarity Score**: 0.051\n**Source**: sparse\n\n**Description**:\nThe product uses an authentication mechanism to restrict access to specific users or identities, but the mechanism does not sufficiently prove that the claimed identity is correct.\n\n**Mapping Guidance**:\n- Usage: Allowed-with-Review\n- Rationale: This CWE entry is a Class and might have Base-level children that would be more appropriate\n\n## CWE-201: Insertion of Sensitive Information Into Sent Data\n**Abstraction Level**: Base\n**Similarity Score**: 0.046\n**Source**: sparse\n\n**Description**:\nCWE-201: Insertion of Sensitive Information Into Sent Data\n\n**Mapping Guidance**:\n- Usage: Allowed\n- Rationale: This CWE entry is at the Base level of abstraction, which is a preferred level of abstraction for mapping to the root causes of vulnerabilities.\n\n## CWE-1391: Use of Weak Credentials\n**Abstraction Level**: Class\n**Similarity Score**: 0.046\n**Source**: sparse\n\n**Description**:\nThe product uses weak credentials (such as a default key or hard-coded password) that can be calculated, derived, reused, or guessed by an attacker.\n\n**Mapping Guidance**:\n- Usage: Allowed-with-Review\n- Rationale: This CWE entry is a Class and might have Base-level children that would be more appropriate\n\n## CWE-522: Insufficiently Protected Credentials\n**Abstraction Level**: Class\n**Similarity Score**: 0.045\n**Source**: sparse\n\n**Description**:\nThe product stores credentials in a way that is not sufficiently protected, which can allow an attacker to obtain the credentials and use them to gain unauthorized access to the system.\n\n**Mapping Guidance**:\n- Usage: Allowed-with-Review\n- Rationale: This CWE entry is a Class and might have Base-level children that would be more appropriate\n\n## CWE-306: Missing Authentication for Critical Function\n**Abstraction Level**: Base\n**Similarity Score**: 0.045\n**Source**: sparse\n\n**Description**:\nThe product does not perform any authentication for functionality that requires a provable user identity or consumes a significant amount of resources.\n\n**Mapping Guidance**:\n- Usage: Allowed\n- Rationale: This CWE entry is at the Base level of abstraction, which is a preferred level of abstraction for mapping to the root causes of vulnerabilities.\n\n## CWE-208: Observable Timing Discrepancy\n**Abstraction Level**: Base\n**Similarity Score**: 0.045\n**Source**: sparse\n\n**Description**:\nCWE-208: Observable Timing Discrepancy\n\n**Mapping Guidance**:\n- Usage: Allowed\n- Rationale: This CWE entry is at the Base level of abstraction, which is a preferred level of abstraction for mapping to the root causes of vulnerabilities.\n\n## CWE-289: Authentication Bypass by Alternate Name\n**Abstraction Level**: base\n**Similarity Score**: 0.568\n**Source**: dense\n\n**Description**:\nCWE-289: Authentication Bypass by Alternate Name\n\n**Mapping Guidance**:\n- Usage: Allowed\n- Rationale: This CWE entry is at the Base level of abstraction, which is a preferred level of abstraction for mapping to the root causes of vulnerabilities.\n\n**Relationships**:\n- CANFOLLOW -> CWE-52\n- CANFOLLOW -> CWE-46\n- CANFOLLOW -> CWE-178\n- CANFOLLOW -> CWE-173\n- CHILDOF -> CWE-1390\n\n## CWE-178: Improper Handling of Case Sensitivity\n**Abstraction Level**: Base\n**Similarity Score**: 0.002\n**Source**: graph\n\n**Description**:\nThe product does not properly account for differences in case sensitivity when accessing or determining the properties of a resource, leading to inconsistent results.\n\n**Mapping Guidance**:\n- Usage: Allowed\n- Rationale: This CWE entry is at the Base level of abstraction, which is a preferred level of abstraction for mapping to the root causes of vulnerabilities.\n\n**Relationships**:\n- CANPRECEDE -> CWE-289\n- CANPRECEDE -> CWE-433\n- CHILDOF -> CWE-706\n- CHILDOF -> CWE-706\n- PARENTOF -> CWE-178\n\nCWE-287 is chosen as the primary CWE because the vulnerability involves a flaw in the authentication logic. CWE-294 is a secondary candidate because replay attacks are mentioned. The other CWEs were not chosen because there isn't enough evidence to support them.\n\n\n## CWE Relationship Analysis\n\nCurrent CWEs represent these abstraction levels: .\n\n\n### Vulnerability Chain Analysis\n\n**Chain starting from CWE-1390:**\n- 1390 (Weak Authentication) - ROOT\n\n\n**Chain starting from CWE-46:**\n- 46 (Path Equivalence: 'filename ' (Trailing Space)) - ROOT\n\n\n\n### CWE Relationship Diagram\n\n```mermaid\ngraph TD\n    classDef primary fill:#f96,stroke:#333,stroke-width:2px\n    classDef secondary fill:#69f,stroke:#333\n    classDef tertiary fill:#9e9,stroke:#333\n```",
  "criticism": "",
  "resolution": "",
  "relevant_cwes": [
    {
      "metadata": {
        "doc_id": "287",
        "name": "Improper Authentication",
        "source": "alternate_terms",
        "original_matched_text": "AlternateTerms: AuthC",
        "match_reason": "term_in_phrase_compound_part_0"
      },
      "similarity": 800.0,
      "alternate_term_match": true
    },
    {
      "metadata": {
        "doc_id": "294",
        "name": "Authentication Bypass by Capture-replay",
        "source": "sparse"
      },
      "similarity": 51.387520520091
    },
    {
      "metadata": {
        "doc_id": "1390",
        "name": "Weak Authentication",
        "source": "sparse"
      },
      "similarity": 50.5474455449291
    },
    {
      "metadata": {
        "doc_id": "201",
        "name": "Insertion of Sensitive Information Into Sent Data",
        "source": "sparse"
      },
      "similarity": 45.846908676727
    },
    {
      "metadata": {
        "doc_id": "1391",
        "name": "Use of Weak Credentials",
        "source": "sparse"
      },
      "similarity": 45.614182175000394
    },
    {
      "metadata": {
        "doc_id": "522",
        "name": "Insufficiently Protected Credentials",
        "source": "sparse"
      },
      "similarity": 45.11371079753105
    },
    {
      "metadata": {
        "doc_id": "306",
        "name": "Missing Authentication for Critical Function",
        "source": "sparse"
      },
      "similarity": 44.88220271685335
    },
    {
      "metadata": {
        "doc_id": "208",
        "name": "Observable Timing Discrepancy",
        "source": "sparse"
      },
      "similarity": 44.61062814849318
    },
    {
      "metadata": {
        "doc_id": "289",
        "name": "Authentication Bypass by Alternate Name",
        "type": "Base",
        "original_content": "The product performs authentication based on the name of a resource being accessed, or the name of the actor performing the access, but it does not properly check all possible names for that resource or actor.",
        "source": "dense",
        "mapping_notes": {
          "usage": "Allowed",
          "rationale": "This CWE entry is at the Base level of abstraction, which is a preferred level of abstraction for mapping to the root causes of vulnerabilities.",
          "comments": "Carefully read both the name and description to ensure that this mapping is an appropriate fit. Do not try to 'force' a mapping to a lower-level Base/Variant simply to comply with this preferred level of abstraction.",
          "reasons": [
            "Acceptable-Use"
          ]
        },
        "score_info": {
          "retrievers": [
            "dense",
            "graph"
          ],
          "retriever_count": 2,
          "normalized_scores": {
            "dense": 0.5681117569585524,
            "graph": 1.7460102397325046
          }
        }
      },
      "similarity": 0.5681117569585524
    },
    {
      "doc_id": "178",
      "text": "CWE-178: Improper Handling of Case Sensitivity",
      "score": 2.2100000000000004,
      "metadata": {
        "doc_id": "178",
        "name": "Improper Handling of Case Sensitivity",
        "type": "base",
        "original_content": "CWE-178: Improper Handling of Case Sensitivity",
        "relationships": [
          {
            "source_id": "178",
            "target_id": "289",
            "label": "CANPRECEDE",
            "properties": {
              "view_id": "1000"
            }
          },
          {
            "source_id": "178",
            "target_id": "433",
            "label": "CANPRECEDE",
            "properties": {
              "view_id": "1000"
            }
          },
          {
            "source_id": "178",
            "target_id": "706",
            "label": "CHILDOF",
            "properties": {
              "ordinal": "Primary",
              "view_id": "1003"
            }
          },
          {
            "source_id": "178",
            "target_id": "706",
            "label": "CHILDOF",
            "properties": {
              "ordinal": "Primary",
              "view_id": "1000"
            }
          },
          {
            "source_id": "706",
            "target_id": "178",
            "label": "PARENTOF",
            "properties": {
              "ordinal": "Primary",
              "view_id": "1000"
            }
          },
          {
            "source_id": "433",
            "target_id": "178",
            "label": "CANFOLLOW",
            "properties": {
              "view_id": "1000"
            }
          },
          {
            "source_id": "289",
            "target_id": "178",
            "label": "CANFOLLOW",
            "properties": {
              "view_id": "1000"
            }
          },
          {
            "source_id": "1289",
            "target_id": "178",
            "label": "PEEROF",
            "properties": {
              "ordinal": "Primary",
              "view_id": "1000"
            }
          }
        ],
        "score_components": {
          "relationship_chain": 1.0,
          "sequence_path": 1.0
        },
        "abstraction_factor": 1.3,
        "graph_path_info": {
          "path_types": [
            "relationship_chain",
            "vulnerability_sequence_forward",
            "vulnerability_sequence_backward"
          ],
          "best_paths": {
            "relationship_chain": {
              "path": [
                [
                  "289",
                  "178",
                  "CANFOLLOW"
                ]
              ],
              "score": 1.0,
              "type": "relationship_chain",
              "source": "289"
            },
            "vulnerability_sequence_forward": {
              "path": [
                [
                  "289",
                  "178",
                  "CANFOLLOW"
                ]
              ],
              "score": 0.9,
              "type": "vulnerability_sequence_forward",
              "source": "289"
            },
            "vulnerability_sequence_backward": {
              "path": [
                [
                  "178",
                  "289",
                  "CANPRECEDE"
                ]
              ],
              "score": 1.0,
              "type": "vulnerability_sequence_backward",
              "source": "289"
            }
          }
        },
        "position": "before",
        "sources": [
          "graph"
        ],
        "source": "graph",
        "mapping_notes": {
          "usage": "Allowed",
          "rationale": "This CWE entry is at the Base level of abstraction, which is a preferred level of abstraction for mapping to the root causes of vulnerabilities.",
          "comments": "Carefully read both the name and description to ensure that this mapping is an appropriate fit. Do not try to 'force' a mapping to a lower-level Base/Variant simply to comply with this preferred level of abstraction.",
          "reasons": [
            "Acceptable-Use"
          ]
        },
        "score_info": {
          "retrievers": [
            "graph"
          ],
          "retriever_count": 1,
          "normalized_scores": {
            "graph": 2.2100000000000004
          }
        }
      },
      "similarity": 2.2100000000000004
    }
  ],
  "identified_cwes": {
    "analyzer": [
      "CWE-1390",
      "CWE-46",
      "CWE-173",
      "CWE-306",
      "CWE-201",
      "CWE-52",
      "CWE-433",
      "CWE-178",
      "CWE-294",
      "CWE-208",
      "CWE-1391",
      "CWE-522",
      "CWE-706",
      "CWE-287",
      "CWE-289"
    ],
    "critic_additional": []
  },
  "keyphrase_cwe_mapping": {}
}