{
  "vulnerability_info": "VulnerabilityInfo(cve_id='CVE-2024-38303', description='Dell PowerEdge Platform, 14G Intel BIOS version(s) prior to 2.22.x, contains an **Improper Input Validation** vulnerability. A high privileged attacker with local access could potentially exploit this vulnerability, leading to Information disclosure.', key_phrases={'rootcause': ['Improper Input Validation', 'Input Validation vulnerability'], 'weakness': '', 'impact': 'Information disclosure', 'vector': '', 'attacker': 'high privileged attacker with local access', 'product': 'Dell PowerEdge Platform', 'version': '14G Intel BIOS version(s) prior to 2.22.x', 'component': ''}, reference_content=\"Based on the provided document, here's the information regarding CVE-2024-38303:\\n\\n**Root Cause of Vulnerability:**\\n- Improper Input Validation in the Dell PowerEdge Platform 14G Intel BIOS.\\n\\n**Weaknesses/Vulnerabilities Present:**\\n- The vulnerability lies in the BIOS's handling of input, specifically a lack of proper validation.\\n\\n**Impact of Exploitation:**\\n- Successful exploitation could lead to information disclosure.\\n\\n**Attack Vectors:**\\n- Local access is required for exploitation.\\n\\n**Required Attacker Capabilities/Position:**\\n- The attacker needs high privileges on the local system.\\n\\n**Affected Products and Remediation:**\\nThe vulnerability affects various Dell PowerEdge 14G servers and related systems, with BIOS versions prior to the following:\\n*   Versions prior to 2.22.2 for PowerEdge R740, R740XD, R640, R940, C6420, FC640, M640, C4140, DSS 8440, XE2420, XE7420, XE7440, Dell EMC Storage NX3240, NX3340, XC Core 6420, XC640, XC740xd, XC940.\\n*   Versions prior to 2.22.1 for PowerEdge R540, R440, T440, XR2, R740XD2, R840, R940XA, T640, MX740C, MX840C, Dell EMC XC Core XC740xd2, XCXR2.\\n\\nThe remediated versions are 2.22.2 or later for the first group of servers, and 2.22.1 or later for the second group.\\nThe document also contains links to the driver download pages for each affected product, where the updated BIOS can be found.\\n\\n**Additional Notes**\\n- The advisory credits codebreaker1337 for reporting the vulnerability.\\n- Dell recommends that all customers update to the latest BIOS versions, as previous BIOS versions were replaced due to updates addressing a functional issue.\\n- The CVSS score is 5.3 with a vector of CVSS:3.1/AV:L/AC:H/PR:H/UI:N/S:C/C:H/I:N/A:N, indicating local access, high privileges, and information disclosure as the main impact.\", similar_info={'cwe_distribution': {}, 'cwe_consensus': '', 'similarity_stats': {'thresholds': [], 'total_samples_by_threshold': {}, 'top_cwes_by_threshold': {}}}, similarity_summary=SimilarityInsight(consensus_cwe='', top_cwes=[], confidence_levels={}, total_samples=0), analysis='', analysis_with_relationships='', criticism='', resolution='', relevant_cwes=[{'metadata': {'doc_id': '119', 'name': 'Improper Restriction of Operations within the Bounds of a Memory Buffer', 'source': 'sparse', 'original_content': \"The product performs operations on a memory buffer, but it reads from or writes to a memory location outside the buffer's intended boundary. This may result in read or write operations on unexpected memory locations that could be linked to other variables, data structures, or internal program data.\", 'keyphrase_sources': [{'id': 'rootcause:Improper Input Validation', 'keyphrase': 'Improper Input Validation', 'type': 'rootcause'}, {'id': 'rootcause:Input Validation vulnerability', 'keyphrase': 'Input Validation vulnerability', 'type': 'rootcause'}, {'id': 'impact:Information disclosure', 'keyphrase': 'Information disclosure', 'type': 'impact'}, {'id': 'attacker:high privileged attacker with local access', 'keyphrase': 'high privileged attacker with local access', 'type': 'attacker'}, {'id': 'product:Dell PowerEdge Platform', 'keyphrase': 'Dell PowerEdge Platform', 'type': 'product'}, {'id': 'version:14G Intel BIOS version(s) prior to 2.22.x', 'keyphrase': '14G Intel BIOS version(s) prior to 2.22.x', 'type': 'version'}]}, 'similarity': np.float64(247.0832004578586)}, {'metadata': {'doc_id': '20', 'name': 'Improper Input Validation', 'source': 'sparse', 'original_content': 'The product receives input or data, but it does\\n        not validate or incorrectly validates that the input has the\\n        properties that are required to process the data safely and\\n        correctly.', 'keyphrase_sources': [{'id': 'rootcause:Improper Input Validation', 'keyphrase': 'Improper Input Validation', 'type': 'rootcause'}, {'id': 'rootcause:Input Validation vulnerability', 'keyphrase': 'Input Validation vulnerability', 'type': 'rootcause'}, {'id': 'impact:Information disclosure', 'keyphrase': 'Information disclosure', 'type': 'impact'}, {'id': 'attacker:high privileged attacker with local access', 'keyphrase': 'high privileged attacker with local access', 'type': 'attacker'}, {'id': 'product:Dell PowerEdge Platform', 'keyphrase': 'Dell PowerEdge Platform', 'type': 'product'}, {'id': 'version:14G Intel BIOS version(s) prior to 2.22.x', 'keyphrase': '14G Intel BIOS version(s) prior to 2.22.x', 'type': 'version'}]}, 'similarity': np.float64(241.1034084706245)}, {'metadata': {'doc_id': '287', 'name': 'Improper Authentication', 'source': 'sparse', 'original_content': 'When an actor claims to have a given identity, the product does not prove or insufficiently proves that the claim is correct.', 'keyphrase_sources': [{'id': 'rootcause:Improper Input Validation', 'keyphrase': 'Improper Input Validation', 'type': 'rootcause'}, {'id': 'rootcause:Input Validation vulnerability', 'keyphrase': 'Input Validation vulnerability', 'type': 'rootcause'}, {'id': 'impact:Information disclosure', 'keyphrase': 'Information disclosure', 'type': 'impact'}, {'id': 'attacker:high privileged attacker with local access', 'keyphrase': 'high privileged attacker with local access', 'type': 'attacker'}, {'id': 'version:14G Intel BIOS version(s) prior to 2.22.x', 'keyphrase': '14G Intel BIOS version(s) prior to 2.22.x', 'type': 'version'}]}, 'similarity': np.float64(209.15339108738038)}, {'metadata': {'doc_id': '1285', 'name': 'Improper Validation of Specified Index, Position, or Offset in Input', 'source': 'sparse', 'original_content': 'The product receives input that is expected to specify an index, position, or offset into an indexable resource such as a buffer or file, but it does not validate or incorrectly validates that the specified index/position/offset has the required properties.', 'keyphrase_sources': [{'id': 'rootcause:Improper Input Validation', 'keyphrase': 'Improper Input Validation', 'type': 'rootcause'}, {'id': 'rootcause:Input Validation vulnerability', 'keyphrase': 'Input Validation vulnerability', 'type': 'rootcause'}]}, 'similarity': np.float64(194.65548340327342)}, {'metadata': {'doc_id': '693', 'name': 'Protection Mechanism Failure', 'source': 'sparse', 'original_content': 'The product does not use or incorrectly uses a protection mechanism that provides sufficient defense against directed attacks against the product.', 'keyphrase_sources': [{'id': 'rootcause:Input Validation vulnerability', 'keyphrase': 'Input Validation vulnerability', 'type': 'rootcause'}, {'id': 'impact:Information disclosure', 'keyphrase': 'Information disclosure', 'type': 'impact'}, {'id': 'attacker:high privileged attacker with local access', 'keyphrase': 'high privileged attacker with local access', 'type': 'attacker'}, {'id': 'product:Dell PowerEdge Platform', 'keyphrase': 'Dell PowerEdge Platform', 'type': 'product'}, {'id': 'version:14G Intel BIOS version(s) prior to 2.22.x', 'keyphrase': '14G Intel BIOS version(s) prior to 2.22.x', 'type': 'version'}]}, 'similarity': np.float64(194.33244536259753)}, {'metadata': {'doc_id': '665', 'name': 'Improper Initialization', 'source': 'sparse', 'original_content': 'The product does not initialize or incorrectly initializes a resource, which might leave the resource in an unexpected state when it is accessed or used.', 'keyphrase_sources': [{'id': 'rootcause:Improper Input Validation', 'keyphrase': 'Improper Input Validation', 'type': 'rootcause'}]}, 'similarity': np.float64(194.02442169051764)}, {'metadata': {'doc_id': '284', 'name': 'Improper Access Control', 'source': 'sparse', 'original_content': 'The product does not restrict or incorrectly restricts access to a resource from an unauthorized actor.', 'keyphrase_sources': [{'id': 'version:14G Intel BIOS version(s) prior to 2.22.x', 'keyphrase': '14G Intel BIOS version(s) prior to 2.22.x', 'type': 'version'}]}, 'similarity': np.float64(96.76123413663237)}, {'metadata': {'doc_id': '269', 'name': 'Improper Privilege Management', 'source': 'sparse', 'original_content': 'The product does not properly assign, modify, track, or check privileges for an actor, creating an unintended sphere of control for that actor.', 'keyphrase_sources': [{'id': 'attacker:high privileged attacker with local access', 'keyphrase': 'high privileged attacker with local access', 'type': 'attacker'}]}, 'similarity': np.float64(89.20170460866056)}, {'metadata': {'doc_id': '261', 'name': 'Weak Encoding for Password', 'source': 'sparse', 'original_content': 'Obscuring a password with a trivial encoding does not protect the password.', 'keyphrase_sources': [{'id': 'product:Dell PowerEdge Platform', 'keyphrase': 'Dell PowerEdge Platform', 'type': 'product'}]}, 'similarity': np.float64(84.02723895013384)}, {'metadata': {'doc_id': '256', 'name': 'Plaintext Storage of a Password', 'source': 'sparse', 'original_content': 'Storing a password in plaintext may result in a system compromise.', 'keyphrase_sources': [{'id': 'product:Dell PowerEdge Platform', 'keyphrase': 'Dell PowerEdge Platform', 'type': 'product'}]}, 'similarity': np.float64(71.66351136597704)}, {'metadata': {'doc_id': '200', 'name': 'Exposure of Sensitive Information to an Unauthorized Actor', 'source': 'sparse', 'original_content': 'The product exposes sensitive information to an actor that is not explicitly authorized to have access to that information.', 'keyphrase_sources': [{'id': 'impact:Information disclosure', 'keyphrase': 'Information disclosure', 'type': 'impact'}]}, 'similarity': np.float64(67.40756493042504)}], identified_cwes={'analyzer': [], 'critic_additional': []})",
  "retrieval_results": {
    "has_multiple_keyphrases": true,
    "keyphrase_cwe_sets": {
      "rootcause:Improper Input Validation": {
        "keyphrase": "Improper Input Validation",
        "type": "rootcause",
        "cwes": [
          {
            "metadata": {
              "doc_id": "119",
              "name": "Improper Restriction of Operations within the Bounds of a Memory Buffer",
              "source": "sparse",
              "original_content": "The product performs operations on a memory buffer, but it reads from or writes to a memory location outside the buffer's intended boundary. This may result in read or write operations on unexpected memory locations that could be linked to other variables, data structures, or internal program data.",
              "keyphrase_sources": [
                {
                  "id": "rootcause:Improper Input Validation",
                  "keyphrase": "Improper Input Validation",
                  "type": "rootcause"
                },
                {
                  "id": "rootcause:Input Validation vulnerability",
                  "keyphrase": "Input Validation vulnerability",
                  "type": "rootcause"
                },
                {
                  "id": "impact:Information disclosure",
                  "keyphrase": "Information disclosure",
                  "type": "impact"
                },
                {
                  "id": "attacker:high privileged attacker with local access",
                  "keyphrase": "high privileged attacker with local access",
                  "type": "attacker"
                },
                {
                  "id": "product:Dell PowerEdge Platform",
                  "keyphrase": "Dell PowerEdge Platform",
                  "type": "product"
                },
                {
                  "id": "version:14G Intel BIOS version(s) prior to 2.22.x",
                  "keyphrase": "14G Intel BIOS version(s) prior to 2.22.x",
                  "type": "version"
                }
              ]
            },
            "similarity": 247.0832004578586
          },
          {
            "metadata": {
              "doc_id": "20",
              "name": "Improper Input Validation",
              "source": "sparse",
              "original_content": "The product receives input or data, but it does\n        not validate or incorrectly validates that the input has the\n        properties that are required to process the data safely and\n        correctly.",
              "keyphrase_sources": [
                {
                  "id": "rootcause:Improper Input Validation",
                  "keyphrase": "Improper Input Validation",
                  "type": "rootcause"
                },
                {
                  "id": "rootcause:Input Validation vulnerability",
                  "keyphrase": "Input Validation vulnerability",
                  "type": "rootcause"
                },
                {
                  "id": "impact:Information disclosure",
                  "keyphrase": "Information disclosure",
                  "type": "impact"
                },
                {
                  "id": "attacker:high privileged attacker with local access",
                  "keyphrase": "high privileged attacker with local access",
                  "type": "attacker"
                },
                {
                  "id": "product:Dell PowerEdge Platform",
                  "keyphrase": "Dell PowerEdge Platform",
                  "type": "product"
                },
                {
                  "id": "version:14G Intel BIOS version(s) prior to 2.22.x",
                  "keyphrase": "14G Intel BIOS version(s) prior to 2.22.x",
                  "type": "version"
                }
              ]
            },
            "similarity": 241.1034084706245
          },
          {
            "metadata": {
              "doc_id": "287",
              "name": "Improper Authentication",
              "source": "sparse",
              "original_content": "When an actor claims to have a given identity, the product does not prove or insufficiently proves that the claim is correct.",
              "keyphrase_sources": [
                {
                  "id": "rootcause:Improper Input Validation",
                  "keyphrase": "Improper Input Validation",
                  "type": "rootcause"
                },
                {
                  "id": "rootcause:Input Validation vulnerability",
                  "keyphrase": "Input Validation vulnerability",
                  "type": "rootcause"
                },
                {
                  "id": "impact:Information disclosure",
                  "keyphrase": "Information disclosure",
                  "type": "impact"
                },
                {
                  "id": "attacker:high privileged attacker with local access",
                  "keyphrase": "high privileged attacker with local access",
                  "type": "attacker"
                },
                {
                  "id": "version:14G Intel BIOS version(s) prior to 2.22.x",
                  "keyphrase": "14G Intel BIOS version(s) prior to 2.22.x",
                  "type": "version"
                }
              ]
            },
            "similarity": 209.15339108738038
          },
          {
            "metadata": {
              "doc_id": "1285",
              "name": "Improper Validation of Specified Index, Position, or Offset in Input",
              "source": "sparse",
              "original_content": "The product receives input that is expected to specify an index, position, or offset into an indexable resource such as a buffer or file, but it does not validate or incorrectly validates that the specified index/position/offset has the required properties.",
              "keyphrase_sources": [
                {
                  "id": "rootcause:Improper Input Validation",
                  "keyphrase": "Improper Input Validation",
                  "type": "rootcause"
                },
                {
                  "id": "rootcause:Input Validation vulnerability",
                  "keyphrase": "Input Validation vulnerability",
                  "type": "rootcause"
                }
              ]
            },
            "similarity": 194.65548340327342
          },
          {
            "metadata": {
              "doc_id": "665",
              "name": "Improper Initialization",
              "source": "sparse",
              "original_content": "The product does not initialize or incorrectly initializes a resource, which might leave the resource in an unexpected state when it is accessed or used.",
              "keyphrase_sources": [
                {
                  "id": "rootcause:Improper Input Validation",
                  "keyphrase": "Improper Input Validation",
                  "type": "rootcause"
                }
              ]
            },
            "similarity": 194.02442169051764
          }
        ]
      },
      "rootcause:Input Validation vulnerability": {
        "keyphrase": "Input Validation vulnerability",
        "type": "rootcause",
        "cwes": [
          {
            "metadata": {
              "doc_id": "119",
              "name": "Improper Restriction of Operations within the Bounds of a Memory Buffer",
              "source": "sparse",
              "original_content": "The product performs operations on a memory buffer, but it reads from or writes to a memory location outside the buffer's intended boundary. This may result in read or write operations on unexpected memory locations that could be linked to other variables, data structures, or internal program data."
            },
            "similarity": 242.61864912399244
          },
          {
            "metadata": {
              "doc_id": "20",
              "name": "Improper Input Validation",
              "source": "sparse",
              "original_content": "The product receives input or data, but it does\n        not validate or incorrectly validates that the input has the\n        properties that are required to process the data safely and\n        correctly."
            },
            "similarity": 236.35042995319006
          },
          {
            "metadata": {
              "doc_id": "287",
              "name": "Improper Authentication",
              "source": "sparse",
              "original_content": "When an actor claims to have a given identity, the product does not prove or insufficiently proves that the claim is correct."
            },
            "similarity": 204.4843174264583
          },
          {
            "metadata": {
              "doc_id": "693",
              "name": "Protection Mechanism Failure",
              "source": "sparse",
              "original_content": "The product does not use or incorrectly uses a protection mechanism that provides sufficient defense against directed attacks against the product.",
              "keyphrase_sources": [
                {
                  "id": "rootcause:Input Validation vulnerability",
                  "keyphrase": "Input Validation vulnerability",
                  "type": "rootcause"
                },
                {
                  "id": "impact:Information disclosure",
                  "keyphrase": "Information disclosure",
                  "type": "impact"
                },
                {
                  "id": "attacker:high privileged attacker with local access",
                  "keyphrase": "high privileged attacker with local access",
                  "type": "attacker"
                },
                {
                  "id": "product:Dell PowerEdge Platform",
                  "keyphrase": "Dell PowerEdge Platform",
                  "type": "product"
                },
                {
                  "id": "version:14G Intel BIOS version(s) prior to 2.22.x",
                  "keyphrase": "14G Intel BIOS version(s) prior to 2.22.x",
                  "type": "version"
                }
              ]
            },
            "similarity": 194.33244536259753
          },
          {
            "metadata": {
              "doc_id": "1285",
              "name": "Improper Validation of Specified Index, Position, or Offset in Input",
              "source": "sparse",
              "original_content": "The product receives input that is expected to specify an index, position, or offset into an indexable resource such as a buffer or file, but it does not validate or incorrectly validates that the specified index/position/offset has the required properties."
            },
            "similarity": 190.34635364386915
          }
        ]
      },
      "impact:Information disclosure": {
        "keyphrase": "Information disclosure",
        "type": "impact",
        "cwes": [
          {
            "metadata": {
              "doc_id": "119",
              "name": "Improper Restriction of Operations within the Bounds of a Memory Buffer",
              "source": "sparse",
              "original_content": "The product performs operations on a memory buffer, but it reads from or writes to a memory location outside the buffer's intended boundary. This may result in read or write operations on unexpected memory locations that could be linked to other variables, data structures, or internal program data."
            },
            "similarity": 81.56761824555731
          },
          {
            "metadata": {
              "doc_id": "20",
              "name": "Improper Input Validation",
              "source": "sparse",
              "original_content": "The product receives input or data, but it does\n        not validate or incorrectly validates that the input has the\n        properties that are required to process the data safely and\n        correctly."
            },
            "similarity": 71.79210642679718
          },
          {
            "metadata": {
              "doc_id": "693",
              "name": "Protection Mechanism Failure",
              "source": "sparse",
              "original_content": "The product does not use or incorrectly uses a protection mechanism that provides sufficient defense against directed attacks against the product."
            },
            "similarity": 70.29549290219954
          },
          {
            "metadata": {
              "doc_id": "200",
              "name": "Exposure of Sensitive Information to an Unauthorized Actor",
              "source": "sparse",
              "original_content": "The product exposes sensitive information to an actor that is not explicitly authorized to have access to that information.",
              "keyphrase_sources": [
                {
                  "id": "impact:Information disclosure",
                  "keyphrase": "Information disclosure",
                  "type": "impact"
                }
              ]
            },
            "similarity": 67.40756493042504
          },
          {
            "metadata": {
              "doc_id": "287",
              "name": "Improper Authentication",
              "source": "sparse",
              "original_content": "When an actor claims to have a given identity, the product does not prove or insufficiently proves that the claim is correct."
            },
            "similarity": 67.30857869697999
          }
        ]
      },
      "attacker:high privileged attacker with local access": {
        "keyphrase": "high privileged attacker with local access",
        "type": "attacker",
        "cwes": [
          {
            "metadata": {
              "doc_id": "119",
              "name": "Improper Restriction of Operations within the Bounds of a Memory Buffer",
              "source": "sparse",
              "original_content": "The product performs operations on a memory buffer, but it reads from or writes to a memory location outside the buffer's intended boundary. This may result in read or write operations on unexpected memory locations that could be linked to other variables, data structures, or internal program data."
            },
            "similarity": 111.76953979738731
          },
          {
            "metadata": {
              "doc_id": "693",
              "name": "Protection Mechanism Failure",
              "source": "sparse",
              "original_content": "The product does not use or incorrectly uses a protection mechanism that provides sufficient defense against directed attacks against the product."
            },
            "similarity": 95.00785023360811
          },
          {
            "metadata": {
              "doc_id": "20",
              "name": "Improper Input Validation",
              "source": "sparse",
              "original_content": "The product receives input or data, but it does\n        not validate or incorrectly validates that the input has the\n        properties that are required to process the data safely and\n        correctly."
            },
            "similarity": 94.02671270978993
          },
          {
            "metadata": {
              "doc_id": "287",
              "name": "Improper Authentication",
              "source": "sparse",
              "original_content": "When an actor claims to have a given identity, the product does not prove or insufficiently proves that the claim is correct."
            },
            "similarity": 90.47961506228951
          },
          {
            "metadata": {
              "doc_id": "269",
              "name": "Improper Privilege Management",
              "source": "sparse",
              "original_content": "The product does not properly assign, modify, track, or check privileges for an actor, creating an unintended sphere of control for that actor.",
              "keyphrase_sources": [
                {
                  "id": "attacker:high privileged attacker with local access",
                  "keyphrase": "high privileged attacker with local access",
                  "type": "attacker"
                }
              ]
            },
            "similarity": 89.20170460866056
          }
        ]
      },
      "product:Dell PowerEdge Platform": {
        "keyphrase": "Dell PowerEdge Platform",
        "type": "product",
        "cwes": [
          {
            "metadata": {
              "doc_id": "119",
              "name": "Improper Restriction of Operations within the Bounds of a Memory Buffer",
              "source": "sparse",
              "original_content": "The product performs operations on a memory buffer, but it reads from or writes to a memory location outside the buffer's intended boundary. This may result in read or write operations on unexpected memory locations that could be linked to other variables, data structures, or internal program data."
            },
            "similarity": 103.922456782261
          },
          {
            "metadata": {
              "doc_id": "261",
              "name": "Weak Encoding for Password",
              "source": "sparse",
              "original_content": "Obscuring a password with a trivial encoding does not protect the password.",
              "keyphrase_sources": [
                {
                  "id": "product:Dell PowerEdge Platform",
                  "keyphrase": "Dell PowerEdge Platform",
                  "type": "product"
                }
              ]
            },
            "similarity": 84.02723895013384
          },
          {
            "metadata": {
              "doc_id": "20",
              "name": "Improper Input Validation",
              "source": "sparse",
              "original_content": "The product receives input or data, but it does\n        not validate or incorrectly validates that the input has the\n        properties that are required to process the data safely and\n        correctly."
            },
            "similarity": 73.78685724967724
          },
          {
            "metadata": {
              "doc_id": "256",
              "name": "Plaintext Storage of a Password",
              "source": "sparse",
              "original_content": "Storing a password in plaintext may result in a system compromise.",
              "keyphrase_sources": [
                {
                  "id": "product:Dell PowerEdge Platform",
                  "keyphrase": "Dell PowerEdge Platform",
                  "type": "product"
                }
              ]
            },
            "similarity": 71.66351136597704
          },
          {
            "metadata": {
              "doc_id": "693",
              "name": "Protection Mechanism Failure",
              "source": "sparse",
              "original_content": "The product does not use or incorrectly uses a protection mechanism that provides sufficient defense against directed attacks against the product."
            },
            "similarity": 71.10544285633233
          }
        ]
      },
      "version:14G Intel BIOS version(s) prior to 2.22.x": {
        "keyphrase": "14G Intel BIOS version(s) prior to 2.22.x",
        "type": "version",
        "cwes": [
          {
            "metadata": {
              "doc_id": "119",
              "name": "Improper Restriction of Operations within the Bounds of a Memory Buffer",
              "source": "sparse",
              "original_content": "The product performs operations on a memory buffer, but it reads from or writes to a memory location outside the buffer's intended boundary. This may result in read or write operations on unexpected memory locations that could be linked to other variables, data structures, or internal program data."
            },
            "similarity": 122.40520829427676
          },
          {
            "metadata": {
              "doc_id": "20",
              "name": "Improper Input Validation",
              "source": "sparse",
              "original_content": "The product receives input or data, but it does\n        not validate or incorrectly validates that the input has the\n        properties that are required to process the data safely and\n        correctly."
            },
            "similarity": 104.45450851818322
          },
          {
            "metadata": {
              "doc_id": "693",
              "name": "Protection Mechanism Failure",
              "source": "sparse",
              "original_content": "The product does not use or incorrectly uses a protection mechanism that provides sufficient defense against directed attacks against the product."
            },
            "similarity": 102.60147547175002
          },
          {
            "metadata": {
              "doc_id": "287",
              "name": "Improper Authentication",
              "source": "sparse",
              "original_content": "When an actor claims to have a given identity, the product does not prove or insufficiently proves that the claim is correct."
            },
            "similarity": 99.6715429762147
          },
          {
            "metadata": {
              "doc_id": "284",
              "name": "Improper Access Control",
              "source": "sparse",
              "original_content": "The product does not restrict or incorrectly restricts access to a resource from an unauthorized actor.",
              "keyphrase_sources": [
                {
                  "id": "version:14G Intel BIOS version(s) prior to 2.22.x",
                  "keyphrase": "14G Intel BIOS version(s) prior to 2.22.x",
                  "type": "version"
                }
              ]
            },
            "similarity": 96.76123413663237
          }
        ]
      }
    },
    "keyphrase_mapping": {
      "119": [
        {
          "id": "rootcause:Improper Input Validation",
          "keyphrase": "Improper Input Validation",
          "type": "rootcause"
        },
        {
          "id": "rootcause:Input Validation vulnerability",
          "keyphrase": "Input Validation vulnerability",
          "type": "rootcause"
        },
        {
          "id": "impact:Information disclosure",
          "keyphrase": "Information disclosure",
          "type": "impact"
        },
        {
          "id": "attacker:high privileged attacker with local access",
          "keyphrase": "high privileged attacker with local access",
          "type": "attacker"
        },
        {
          "id": "product:Dell PowerEdge Platform",
          "keyphrase": "Dell PowerEdge Platform",
          "type": "product"
        },
        {
          "id": "version:14G Intel BIOS version(s) prior to 2.22.x",
          "keyphrase": "14G Intel BIOS version(s) prior to 2.22.x",
          "type": "version"
        }
      ],
      "20": [
        {
          "id": "rootcause:Improper Input Validation",
          "keyphrase": "Improper Input Validation",
          "type": "rootcause"
        },
        {
          "id": "rootcause:Input Validation vulnerability",
          "keyphrase": "Input Validation vulnerability",
          "type": "rootcause"
        },
        {
          "id": "impact:Information disclosure",
          "keyphrase": "Information disclosure",
          "type": "impact"
        },
        {
          "id": "attacker:high privileged attacker with local access",
          "keyphrase": "high privileged attacker with local access",
          "type": "attacker"
        },
        {
          "id": "product:Dell PowerEdge Platform",
          "keyphrase": "Dell PowerEdge Platform",
          "type": "product"
        },
        {
          "id": "version:14G Intel BIOS version(s) prior to 2.22.x",
          "keyphrase": "14G Intel BIOS version(s) prior to 2.22.x",
          "type": "version"
        }
      ],
      "287": [
        {
          "id": "rootcause:Improper Input Validation",
          "keyphrase": "Improper Input Validation",
          "type": "rootcause"
        },
        {
          "id": "rootcause:Input Validation vulnerability",
          "keyphrase": "Input Validation vulnerability",
          "type": "rootcause"
        },
        {
          "id": "impact:Information disclosure",
          "keyphrase": "Information disclosure",
          "type": "impact"
        },
        {
          "id": "attacker:high privileged attacker with local access",
          "keyphrase": "high privileged attacker with local access",
          "type": "attacker"
        },
        {
          "id": "version:14G Intel BIOS version(s) prior to 2.22.x",
          "keyphrase": "14G Intel BIOS version(s) prior to 2.22.x",
          "type": "version"
        }
      ],
      "1285": [
        {
          "id": "rootcause:Improper Input Validation",
          "keyphrase": "Improper Input Validation",
          "type": "rootcause"
        },
        {
          "id": "rootcause:Input Validation vulnerability",
          "keyphrase": "Input Validation vulnerability",
          "type": "rootcause"
        }
      ],
      "665": [
        {
          "id": "rootcause:Improper Input Validation",
          "keyphrase": "Improper Input Validation",
          "type": "rootcause"
        }
      ],
      "693": [
        {
          "id": "rootcause:Input Validation vulnerability",
          "keyphrase": "Input Validation vulnerability",
          "type": "rootcause"
        },
        {
          "id": "impact:Information disclosure",
          "keyphrase": "Information disclosure",
          "type": "impact"
        },
        {
          "id": "attacker:high privileged attacker with local access",
          "keyphrase": "high privileged attacker with local access",
          "type": "attacker"
        },
        {
          "id": "product:Dell PowerEdge Platform",
          "keyphrase": "Dell PowerEdge Platform",
          "type": "product"
        },
        {
          "id": "version:14G Intel BIOS version(s) prior to 2.22.x",
          "keyphrase": "14G Intel BIOS version(s) prior to 2.22.x",
          "type": "version"
        }
      ],
      "200": [
        {
          "id": "impact:Information disclosure",
          "keyphrase": "Information disclosure",
          "type": "impact"
        }
      ],
      "269": [
        {
          "id": "attacker:high privileged attacker with local access",
          "keyphrase": "high privileged attacker with local access",
          "type": "attacker"
        }
      ],
      "261": [
        {
          "id": "product:Dell PowerEdge Platform",
          "keyphrase": "Dell PowerEdge Platform",
          "type": "product"
        }
      ],
      "256": [
        {
          "id": "product:Dell PowerEdge Platform",
          "keyphrase": "Dell PowerEdge Platform",
          "type": "product"
        }
      ],
      "284": [
        {
          "id": "version:14G Intel BIOS version(s) prior to 2.22.x",
          "keyphrase": "14G Intel BIOS version(s) prior to 2.22.x",
          "type": "version"
        }
      ]
    },
    "relevant_cwes": [
      {
        "metadata": {
          "doc_id": "119",
          "name": "Improper Restriction of Operations within the Bounds of a Memory Buffer",
          "source": "sparse",
          "original_content": "The product performs operations on a memory buffer, but it reads from or writes to a memory location outside the buffer's intended boundary. This may result in read or write operations on unexpected memory locations that could be linked to other variables, data structures, or internal program data.",
          "keyphrase_sources": [
            {
              "id": "rootcause:Improper Input Validation",
              "keyphrase": "Improper Input Validation",
              "type": "rootcause"
            },
            {
              "id": "rootcause:Input Validation vulnerability",
              "keyphrase": "Input Validation vulnerability",
              "type": "rootcause"
            },
            {
              "id": "impact:Information disclosure",
              "keyphrase": "Information disclosure",
              "type": "impact"
            },
            {
              "id": "attacker:high privileged attacker with local access",
              "keyphrase": "high privileged attacker with local access",
              "type": "attacker"
            },
            {
              "id": "product:Dell PowerEdge Platform",
              "keyphrase": "Dell PowerEdge Platform",
              "type": "product"
            },
            {
              "id": "version:14G Intel BIOS version(s) prior to 2.22.x",
              "keyphrase": "14G Intel BIOS version(s) prior to 2.22.x",
              "type": "version"
            }
          ]
        },
        "similarity": 247.0832004578586
      },
      {
        "metadata": {
          "doc_id": "20",
          "name": "Improper Input Validation",
          "source": "sparse",
          "original_content": "The product receives input or data, but it does\n        not validate or incorrectly validates that the input has the\n        properties that are required to process the data safely and\n        correctly.",
          "keyphrase_sources": [
            {
              "id": "rootcause:Improper Input Validation",
              "keyphrase": "Improper Input Validation",
              "type": "rootcause"
            },
            {
              "id": "rootcause:Input Validation vulnerability",
              "keyphrase": "Input Validation vulnerability",
              "type": "rootcause"
            },
            {
              "id": "impact:Information disclosure",
              "keyphrase": "Information disclosure",
              "type": "impact"
            },
            {
              "id": "attacker:high privileged attacker with local access",
              "keyphrase": "high privileged attacker with local access",
              "type": "attacker"
            },
            {
              "id": "product:Dell PowerEdge Platform",
              "keyphrase": "Dell PowerEdge Platform",
              "type": "product"
            },
            {
              "id": "version:14G Intel BIOS version(s) prior to 2.22.x",
              "keyphrase": "14G Intel BIOS version(s) prior to 2.22.x",
              "type": "version"
            }
          ]
        },
        "similarity": 241.1034084706245
      },
      {
        "metadata": {
          "doc_id": "287",
          "name": "Improper Authentication",
          "source": "sparse",
          "original_content": "When an actor claims to have a given identity, the product does not prove or insufficiently proves that the claim is correct.",
          "keyphrase_sources": [
            {
              "id": "rootcause:Improper Input Validation",
              "keyphrase": "Improper Input Validation",
              "type": "rootcause"
            },
            {
              "id": "rootcause:Input Validation vulnerability",
              "keyphrase": "Input Validation vulnerability",
              "type": "rootcause"
            },
            {
              "id": "impact:Information disclosure",
              "keyphrase": "Information disclosure",
              "type": "impact"
            },
            {
              "id": "attacker:high privileged attacker with local access",
              "keyphrase": "high privileged attacker with local access",
              "type": "attacker"
            },
            {
              "id": "version:14G Intel BIOS version(s) prior to 2.22.x",
              "keyphrase": "14G Intel BIOS version(s) prior to 2.22.x",
              "type": "version"
            }
          ]
        },
        "similarity": 209.15339108738038
      },
      {
        "metadata": {
          "doc_id": "1285",
          "name": "Improper Validation of Specified Index, Position, or Offset in Input",
          "source": "sparse",
          "original_content": "The product receives input that is expected to specify an index, position, or offset into an indexable resource such as a buffer or file, but it does not validate or incorrectly validates that the specified index/position/offset has the required properties.",
          "keyphrase_sources": [
            {
              "id": "rootcause:Improper Input Validation",
              "keyphrase": "Improper Input Validation",
              "type": "rootcause"
            },
            {
              "id": "rootcause:Input Validation vulnerability",
              "keyphrase": "Input Validation vulnerability",
              "type": "rootcause"
            }
          ]
        },
        "similarity": 194.65548340327342
      },
      {
        "metadata": {
          "doc_id": "693",
          "name": "Protection Mechanism Failure",
          "source": "sparse",
          "original_content": "The product does not use or incorrectly uses a protection mechanism that provides sufficient defense against directed attacks against the product.",
          "keyphrase_sources": [
            {
              "id": "rootcause:Input Validation vulnerability",
              "keyphrase": "Input Validation vulnerability",
              "type": "rootcause"
            },
            {
              "id": "impact:Information disclosure",
              "keyphrase": "Information disclosure",
              "type": "impact"
            },
            {
              "id": "attacker:high privileged attacker with local access",
              "keyphrase": "high privileged attacker with local access",
              "type": "attacker"
            },
            {
              "id": "product:Dell PowerEdge Platform",
              "keyphrase": "Dell PowerEdge Platform",
              "type": "product"
            },
            {
              "id": "version:14G Intel BIOS version(s) prior to 2.22.x",
              "keyphrase": "14G Intel BIOS version(s) prior to 2.22.x",
              "type": "version"
            }
          ]
        },
        "similarity": 194.33244536259753
      },
      {
        "metadata": {
          "doc_id": "665",
          "name": "Improper Initialization",
          "source": "sparse",
          "original_content": "The product does not initialize or incorrectly initializes a resource, which might leave the resource in an unexpected state when it is accessed or used.",
          "keyphrase_sources": [
            {
              "id": "rootcause:Improper Input Validation",
              "keyphrase": "Improper Input Validation",
              "type": "rootcause"
            }
          ]
        },
        "similarity": 194.02442169051764
      },
      {
        "metadata": {
          "doc_id": "284",
          "name": "Improper Access Control",
          "source": "sparse",
          "original_content": "The product does not restrict or incorrectly restricts access to a resource from an unauthorized actor.",
          "keyphrase_sources": [
            {
              "id": "version:14G Intel BIOS version(s) prior to 2.22.x",
              "keyphrase": "14G Intel BIOS version(s) prior to 2.22.x",
              "type": "version"
            }
          ]
        },
        "similarity": 96.76123413663237
      },
      {
        "metadata": {
          "doc_id": "269",
          "name": "Improper Privilege Management",
          "source": "sparse",
          "original_content": "The product does not properly assign, modify, track, or check privileges for an actor, creating an unintended sphere of control for that actor.",
          "keyphrase_sources": [
            {
              "id": "attacker:high privileged attacker with local access",
              "keyphrase": "high privileged attacker with local access",
              "type": "attacker"
            }
          ]
        },
        "similarity": 89.20170460866056
      },
      {
        "metadata": {
          "doc_id": "261",
          "name": "Weak Encoding for Password",
          "source": "sparse",
          "original_content": "Obscuring a password with a trivial encoding does not protect the password.",
          "keyphrase_sources": [
            {
              "id": "product:Dell PowerEdge Platform",
              "keyphrase": "Dell PowerEdge Platform",
              "type": "product"
            }
          ]
        },
        "similarity": 84.02723895013384
      },
      {
        "metadata": {
          "doc_id": "256",
          "name": "Plaintext Storage of a Password",
          "source": "sparse",
          "original_content": "Storing a password in plaintext may result in a system compromise.",
          "keyphrase_sources": [
            {
              "id": "product:Dell PowerEdge Platform",
              "keyphrase": "Dell PowerEdge Platform",
              "type": "product"
            }
          ]
        },
        "similarity": 71.66351136597704
      },
      {
        "metadata": {
          "doc_id": "200",
          "name": "Exposure of Sensitive Information to an Unauthorized Actor",
          "source": "sparse",
          "original_content": "The product exposes sensitive information to an actor that is not explicitly authorized to have access to that information.",
          "keyphrase_sources": [
            {
              "id": "impact:Information disclosure",
              "keyphrase": "Information disclosure",
              "type": "impact"
            }
          ]
        },
        "similarity": 67.40756493042504
      }
    ],
    "enhanced_query": "# Vulnerability Description\n\n    Dell PowerEdge Platform, 14G Intel BIOS version(s) prior to 2.22.x, contains an **Improper Input Validation** vulnerability. A high privileged attacker with local access could potentially exploit this vulnerability, leading to Information disclosure.\n\n    # Keyphrase-Specific CWE Analysis\n    This vulnerability contains multiple keyphrases that may map to different CWEs. \n    Please analyze each keyphrase separately and determine the most appropriate CWE(s) for each.\n\n    ## ROOTCAUSE: 'Improper Input Validation'\n\nRelevant CWEs for this ROOTCAUSE:\n\n### 1. CWE-119: Improper Restriction of Operations within the Bounds of a Memory Buffer (Score: 247.08)\n\nThe product performs operations on a memory buffer, but it reads from or writes to a memory location outside the buffer's intended boundary. This may result in read or write operations on unexpected memory locations that could be linked to other variables, data structures, or internal program data....\n\n### 2. CWE-20: Improper Input Validation (Score: 241.10)\n\nThe product receives input or data, but it does\n        not validate or incorrectly validates that the input has the\n        properties that are required to process the data safely and\n        correctly....\n\n### 3. CWE-287: Improper Authentication (Score: 209.15)\n\nWhen an actor claims to have a given identity, the product does not prove or insufficiently proves that the claim is correct....\n\n### 4. CWE-1285: Improper Validation of Specified Index, Position, or Offset in Input (Score: 194.66)\n\nThe product receives input that is expected to specify an index, position, or offset into an indexable resource such as a buffer or file, but it does not validate or incorrectly validates that the specified index/position/offset has the required properties....\n\n### 5. CWE-665: Improper Initialization (Score: 194.02)\n\nThe product does not initialize or incorrectly initializes a resource, which might leave the resource in an unexpected state when it is accessed or used....\n\n## ROOTCAUSE: 'Input Validation vulnerability'\n\nRelevant CWEs for this ROOTCAUSE:\n\n### 1. CWE-119: Improper Restriction of Operations within the Bounds of a Memory Buffer (Score: 247.08)\n\nThe product performs operations on a memory buffer, but it reads from or writes to a memory location outside the buffer's intended boundary. This may result in read or write operations on unexpected memory locations that could be linked to other variables, data structures, or internal program data....\n\n### 2. CWE-20: Improper Input Validation (Score: 241.10)\n\nThe product receives input or data, but it does\n        not validate or incorrectly validates that the input has the\n        properties that are required to process the data safely and\n        correctly....\n\n### 3. CWE-287: Improper Authentication (Score: 209.15)\n\nWhen an actor claims to have a given identity, the product does not prove or insufficiently proves that the claim is correct....\n\n### 4. CWE-1285: Improper Validation of Specified Index, Position, or Offset in Input (Score: 194.66)\n\nThe product receives input that is expected to specify an index, position, or offset into an indexable resource such as a buffer or file, but it does not validate or incorrectly validates that the specified index/position/offset has the required properties....\n\n### 5. CWE-693: Protection Mechanism Failure (Score: 194.33)\n\nThe product does not use or incorrectly uses a protection mechanism that provides sufficient defense against directed attacks against the product....\n\n## IMPACT: 'Information disclosure'\n\nRelevant CWEs for this IMPACT:\n\n### 1. CWE-119: Improper Restriction of Operations within the Bounds of a Memory Buffer (Score: 247.08)\n\nThe product performs operations on a memory buffer, but it reads from or writes to a memory location outside the buffer's intended boundary. This may result in read or write operations on unexpected memory locations that could be linked to other variables, data structures, or internal program data....\n\n### 2. CWE-20: Improper Input Validation (Score: 241.10)\n\nThe product receives input or data, but it does\n        not validate or incorrectly validates that the input has the\n        properties that are required to process the data safely and\n        correctly....\n\n### 3. CWE-287: Improper Authentication (Score: 209.15)\n\nWhen an actor claims to have a given identity, the product does not prove or insufficiently proves that the claim is correct....\n\n### 4. CWE-693: Protection Mechanism Failure (Score: 194.33)\n\nThe product does not use or incorrectly uses a protection mechanism that provides sufficient defense against directed attacks against the product....\n\n### 5. CWE-200: Exposure of Sensitive Information to an Unauthorized Actor (Score: 67.41)\n\nThe product exposes sensitive information to an actor that is not explicitly authorized to have access to that information....\n\n## ATTACKER: 'high privileged attacker with local access'\n\nRelevant CWEs for this ATTACKER:\n\n### 1. CWE-119: Improper Restriction of Operations within the Bounds of a Memory Buffer (Score: 247.08)\n\nThe product performs operations on a memory buffer, but it reads from or writes to a memory location outside the buffer's intended boundary. This may result in read or write operations on unexpected memory locations that could be linked to other variables, data structures, or internal program data....\n\n### 2. CWE-20: Improper Input Validation (Score: 241.10)\n\nThe product receives input or data, but it does\n        not validate or incorrectly validates that the input has the\n        properties that are required to process the data safely and\n        correctly....\n\n### 3. CWE-287: Improper Authentication (Score: 209.15)\n\nWhen an actor claims to have a given identity, the product does not prove or insufficiently proves that the claim is correct....\n\n### 4. CWE-693: Protection Mechanism Failure (Score: 194.33)\n\nThe product does not use or incorrectly uses a protection mechanism that provides sufficient defense against directed attacks against the product....\n\n### 5. CWE-269: Improper Privilege Management (Score: 89.20)\n\nThe product does not properly assign, modify, track, or check privileges for an actor, creating an unintended sphere of control for that actor....\n\n## PRODUCT: 'Dell PowerEdge Platform'\n\nRelevant CWEs for this PRODUCT:\n\n### 1. CWE-119: Improper Restriction of Operations within the Bounds of a Memory Buffer (Score: 247.08)\n\nThe product performs operations on a memory buffer, but it reads from or writes to a memory location outside the buffer's intended boundary. This may result in read or write operations on unexpected memory locations that could be linked to other variables, data structures, or internal program data....\n\n### 2. CWE-20: Improper Input Validation (Score: 241.10)\n\nThe product receives input or data, but it does\n        not validate or incorrectly validates that the input has the\n        properties that are required to process the data safely and\n        correctly....\n\n### 3. CWE-693: Protection Mechanism Failure (Score: 194.33)\n\nThe product does not use or incorrectly uses a protection mechanism that provides sufficient defense against directed attacks against the product....\n\n### 4. CWE-261: Weak Encoding for Password (Score: 84.03)\n\nObscuring a password with a trivial encoding does not protect the password....\n\n### 5. CWE-256: Plaintext Storage of a Password (Score: 71.66)\n\nStoring a password in plaintext may result in a system compromise....\n\n## VERSION: '14G Intel BIOS version(s) prior to 2.22.x'\n\nRelevant CWEs for this VERSION:\n\n### 1. CWE-119: Improper Restriction of Operations within the Bounds of a Memory Buffer (Score: 247.08)\n\nThe product performs operations on a memory buffer, but it reads from or writes to a memory location outside the buffer's intended boundary. This may result in read or write operations on unexpected memory locations that could be linked to other variables, data structures, or internal program data....\n\n### 2. CWE-20: Improper Input Validation (Score: 241.10)\n\nThe product receives input or data, but it does\n        not validate or incorrectly validates that the input has the\n        properties that are required to process the data safely and\n        correctly....\n\n### 3. CWE-287: Improper Authentication (Score: 209.15)\n\nWhen an actor claims to have a given identity, the product does not prove or insufficiently proves that the claim is correct....\n\n### 4. CWE-693: Protection Mechanism Failure (Score: 194.33)\n\nThe product does not use or incorrectly uses a protection mechanism that provides sufficient defense against directed attacks against the product....\n\n### 5. CWE-284: Improper Access Control (Score: 96.76)\n\nThe product does not restrict or incorrectly restricts access to a resource from an unauthorized actor....\n\n\n    # Analysis Instructions\n    1. For each keyphrase, identify the most appropriate CWE(s) that represent the weakness.\n    2. Consider how the different keyphrases might relate to each other in the vulnerability chain.\n    3. Provide a final determination of primary CWE(s) and any secondary CWEs.\n    4. Format your response using the standard analysis template.\n\n    Please analyze how these different weaknesses interact and provide a comprehensive CWE classification.\n    "
  },
  "retrieval_time": 1.0522866249084473
}