{
  "cve_id": "CVE-2025-26494",
  "description": "**Server-Side Request Forgery** (SSRF) vulnerability in Salesforce Tableau Server allows Authentication Bypass.This issue affects Tableau Server from 2023.3 through 2023.3.5.",
  "key_phrases": {
    "rootcause": "Server-Side Request Forgery",
    "weakness": "",
    "impact": "Authentication Bypass",
    "vector": "",
    "attacker": "",
    "product": "Salesforce Tableau Server",
    "version": "from 2023.3 through 2023.3.5",
    "component": ""
  },
  "reference_content": "UNRELATED",
  "similar_info": {
    "cwe_distribution": {},
    "cwe_consensus": "",
    "similarity_stats": {
      "thresholds": [],
      "total_samples_by_threshold": {},
      "top_cwes_by_threshold": {}
    }
  },
  "similarity_summary": {
    "consensus_cwe": "",
    "top_cwes": [],
    "confidence_levels": {},
    "total_samples": 0
  },
  "analysis": "# Summary\n| CWE ID | CWE Name | Confidence | CWE Abstraction Level | CWE Vulnerability Mapping Label | CWE-Vulnerability Mapping Notes |\n|---|---|---|---|---|---|\n| CWE-918 | Server-Side Request Forgery (SSRF) | 0.9 | Base | Primary CWE | Allowed |\n| CWE-306 | Missing Authentication for Critical Function | 0.6 | Base | Secondary Candidate | Allowed |\n\n## Evidence and Confidence\n\n*   **Confidence Score:** 0.75\n*   **Evidence Strength:** MEDIUM\n\n## Relationship Analysis\nThe primary relationship is that of root cause to impact. The **Server-Side Request Forgery** (SSRF) vulnerability (CWE-918) allows for Authentication Bypass (CWE-306). In this case, the **Server-Side Request Forgery** can lead to bypassing authentication, so it can be considered the root cause. CWE-918 is a base level CWE and is preferred. CWE-306 is a base level CWE and is preferred.\n\n```mermaid\ngraph TD\n    cwe918[\"CWE-918: Server-Side Request Forgery (SSRF)\"]\n    cwe306[\"CWE-306: Missing Authentication for Critical Function\"]\n    \n    cwe918 -->|CANPRECEDE| cwe306\n    \n    classDef primary fill:#f96,stroke:#333,stroke-width:2px\n    classDef secondary fill:#69f,stroke:#333\n    \n    class cwe918 primary\n    class cwe306 secondary\n```\n\n## Vulnerability Chain\nThe vulnerability chain starts with the **Server-Side Request Forgery** (CWE-918), which then leads to the **Authentication Bypass** (CWE-306). The **Server-Side Request Forgery** is the root cause of the chain, and the **Authentication Bypass** is the impact.\n\n## Summary of Analysis\nThe initial analysis identified CWE-918 as the primary CWE due to the **Server-Side Request Forgery** being the root cause. The secondary CWE is CWE-306, which is the impact of the vulnerability. The graph relationships show that CWE-918 can precede CWE-306. The selection of CWE-918 is at the optimal level of specificity because it is a base level CWE and is the root cause of the vulnerability.\n\nThe vulnerability description clearly states a **Server-Side Request Forgery** (SSRF) vulnerability leading to Authentication Bypass.\n\n# Enhanced Context (25 CWEs)\nThe following CWEs were identified as potentially relevant to this vulnerability:\n\n## CWE-303: Incorrect Implementation of Authentication Algorithm\n**Abstraction Level**: Base\n**Similarity Score**: 0.76\n\n## CWE-918: Server-Side Request Forgery (SSRF)\n**Abstraction Level**: Base\n**Similarity Score**: 0.75\n**Source**: dense\n\n**Description**:\nThe web server receives a URL or similar request from an upstream component and retrieves the contents of this URL, but it does not sufficiently ensure that the request is being sent to the expected destination.\n\n**Mapping Guidance**:\n- Usage: Allowed\n- Rationale: This CWE entry is at the Base level of abstraction, which is a preferred level of abstraction for mapping to the root causes of vulnerabilities.\n\n## CWE-602: Client-Side Enforcement of Server-Side Security\n**Abstraction Level**: Class\n**Similarity Score**: 0.74\n\n## CWE-807: Reliance on Untrusted Inputs in a Security Decision\n**Abstraction Level**: Base\n**Similarity Score**: 0.74\n\n## CWE-294: Authentication Bypass by Capture-replay\n**Abstraction Level**: Base\n**Similarity Score**: 0.74\n\n## CWE-472: External Control of Assumed-Immutable Web Parameter\n**Abstraction Level**: Base\n**Similarity Score**: 0.74\n\n## CWE-212: Improper Removal of Sensitive Information Before Storage or Transfer\n**Abstraction Level**: Base\n**Similarity Score**: 0.74\n\n## CWE-668: Exposure of Resource to Wrong Sphere\n**Abstraction Level**: Class\n**Similarity Score**: 0.74\n\n## CWE-288: Authentication Bypass Using an Alternate Path or Channel\n**Abstraction Level**: Base\n**Similarity Score**: 0.74\n\n## CWE-74: Improper Neutralization of Special Elements in Output Used by a Downstream Component ('Injection')\n**Abstraction Level**: Class\n**Similarity Score**: 0.74\n\n## CWE-639: Authorization Bypass Through User-Controlled Key\n**Abstraction Level**: Base\n**Similarity Score**: 1160.13\n\n## CWE-863: Incorrect Authorization\n**Abstraction Level**: Class\n**Similarity Score**: 1149.63\n\n## CWE-285: Improper Authorization\n**Abstraction Level**: Class\n**Similarity Score**: 1127.43\n\n## CWE-113: Improper Neutralization of CRLF Sequences in HTTP Headers ('HTTP Request/Response Splitting')\n**Abstraction Level**: Variant\n**Similarity Score**: 1114.21\n\n## CWE-306: Missing Authentication for Critical Function\n**Abstraction Level**: Base\n**Similarity Score**: 1109.69\n\n**Description**:\nThe product does not perform any authentication for functionality that requires a provable user identity or consumes a significant amount of resources.\n\n**Mapping Guidance**:\n- Usage: Allowed\n- Rationale: This CWE entry is at the Base level of abstraction, which is a preferred level of abstraction for mapping to the root causes of vulnerabilities.\n\n## CWE-93: Improper Neutralization of CRLF Sequences ('CRLF Injection')\n**Abstraction Level**: base\n**Similarity Score**: 4.33\n\n## CWE-117: Improper Output Neutralization for Logs\n**Abstraction Level**: base\n**Similarity Score**: 4.33\n\n## CWE-79: Improper Neutralization of Input During Web Page Generation ('Cross-site Scripting')\n**Abstraction Level**: base\n**Similarity Score**: 2.91\n\n## CWE-611: Improper Restriction of XML External Entity Reference\n**Abstraction Level**: base\n**Similarity Score**: 2.77\n\n## CWE-1275: Sensitive Cookie with Improper SameSite Attribute\n**Abstraction Level**: variant\n**Similarity Score**: 2.55\n\n## CWE-601: URL Redirection to Untrusted Site ('Open Redirect')\n**Abstraction Level**: base\n**Similarity Score**: 2.40\n\n## CWE-306: Missing Authentication for Critical Function\n**Abstraction Level**: base\n**Similarity Score**: 2.33\n\n## CWE-941: Incorrectly Specified Destination in a Communication Channel\n**Abstraction Level**: base\n**Similarity Score**: 2.33\n\n## CWE-471: Modification of Assumed-Immutable Data (MAID)\n**Abstraction Level**: base\n**Similarity Score**: 2.21\n\n## CWE-113: Improper Neutralization of CRLF Sequences in HTTP Headers ('HTTP Request/Response Splitting')\n**Abstraction Level**: variant\n**Similarity Score**: 2.16\n\nRelevant CWE Information:\n\n### CWE-918: Server-Side Request Forgery (SSRF)\n* Technical Explanation: The vulnerability description explicitly mentions \"Server-Side Request Forgery (SSRF)\". This aligns directly with the definition of CWE-918, where the server retrieves the contents of a URL without sufficient validation, potentially leading to unintended consequences.\n* Security Implications: An attacker could exploit this vulnerability to make the server send requests to internal or external systems, potentially exposing sensitive data or performing unauthorized actions.\n* Relationship Analysis: CWE-918 is a root cause that can lead to other vulnerabilities like information disclosure or remote code execution.\n* Mapping Guidance: The Usage is \"Allowed\" and the Rationale states it is at the Base level of abstraction, which is preferred.\n\n### CWE-306: Missing Authentication for Critical Function\n* Technical Explanation: The vulnerability description mentions \"Authentication Bypass\". This aligns with CWE-306, where critical functionality lacks proper authentication mechanisms.\n* Security Implications: Without authentication, attackers can directly access and manipulate critical functions, leading to unauthorized actions and data breaches.\n* Relationship Analysis: CWE-306 is often a consequence of other vulnerabilities or misconfigurations, such as SSRF.\n* Mapping Guidance: The Usage is \"Allowed\" and the Rationale states it is at the Base level of abstraction, which is preferred.\n\n### Other CWEs Considered But Not Used:\n\n* CWE-611: While SSRF can sometimes involve XML External Entity (XXE) injection, the description doesn't specifically mention XML or entities, making CWE-611 less applicable.\n* CWE-89, CWE-93, CWE-113, CWE-601: These CWEs represent different types of injection vulnerabilities, but the description doesn't provide enough details to support their inclusion. The root cause appears to be an SSRF vulnerability, not a specific type of injection.\n* CWE-352: This CWE describes Cross-Site Request Forgery (CSRF). There is no mention of CSRF in the description, and therefore it is not applicable.\n\nI am overriding the retriever results and focusing on the root cause, which is the SSRF (",
  "analysis_with_relationships": "# Summary\n| CWE ID | CWE Name | Confidence | CWE Abstraction Level | CWE Vulnerability Mapping Label | CWE-Vulnerability Mapping Notes |\n|---|---|---|---|---|---|\n| CWE-918 | Server-Side Request Forgery (SSRF) | 0.9 | Base | Primary CWE | Allowed |\n| CWE-306 | Missing Authentication for Critical Function | 0.6 | Base | Secondary Candidate | Allowed |\n\n## Evidence and Confidence\n\n*   **Confidence Score:** 0.75\n*   **Evidence Strength:** MEDIUM\n\n## Relationship Analysis\nThe primary relationship is that of root cause to impact. The **Server-Side Request Forgery** (SSRF) vulnerability (CWE-918) allows for Authentication Bypass (CWE-306). In this case, the **Server-Side Request Forgery** can lead to bypassing authentication, so it can be considered the root cause. CWE-918 is a base level CWE and is preferred. CWE-306 is a base level CWE and is preferred.\n\n```mermaid\ngraph TD\n    cwe918[\"CWE-918: Server-Side Request Forgery (SSRF)\"]\n    cwe306[\"CWE-306: Missing Authentication for Critical Function\"]\n    \n    cwe918 -->|CANPRECEDE| cwe306\n    \n    classDef primary fill:#f96,stroke:#333,stroke-width:2px\n    classDef secondary fill:#69f,stroke:#333\n    \n    class cwe918 primary\n    class cwe306 secondary\n```\n\n## Vulnerability Chain\nThe vulnerability chain starts with the **Server-Side Request Forgery** (CWE-918), which then leads to the **Authentication Bypass** (CWE-306). The **Server-Side Request Forgery** is the root cause of the chain, and the **Authentication Bypass** is the impact.\n\n## Summary of Analysis\nThe initial analysis identified CWE-918 as the primary CWE due to the **Server-Side Request Forgery** being the root cause. The secondary CWE is CWE-306, which is the impact of the vulnerability. The graph relationships show that CWE-918 can precede CWE-306. The selection of CWE-918 is at the optimal level of specificity because it is a base level CWE and is the root cause of the vulnerability.\n\nThe vulnerability description clearly states a **Server-Side Request Forgery** (SSRF) vulnerability leading to Authentication Bypass.\n\n# Enhanced Context (25 CWEs)\nThe following CWEs were identified as potentially relevant to this vulnerability:\n\n## CWE-303: Incorrect Implementation of Authentication Algorithm\n**Abstraction Level**: Base\n**Similarity Score**: 0.76\n\n## CWE-918: Server-Side Request Forgery (SSRF)\n**Abstraction Level**: Base\n**Similarity Score**: 0.75\n**Source**: dense\n\n**Description**:\nThe web server receives a URL or similar request from an upstream component and retrieves the contents of this URL, but it does not sufficiently ensure that the request is being sent to the expected destination.\n\n**Mapping Guidance**:\n- Usage: Allowed\n- Rationale: This CWE entry is at the Base level of abstraction, which is a preferred level of abstraction for mapping to the root causes of vulnerabilities.\n\n## CWE-602: Client-Side Enforcement of Server-Side Security\n**Abstraction Level**: Class\n**Similarity Score**: 0.74\n\n## CWE-807: Reliance on Untrusted Inputs in a Security Decision\n**Abstraction Level**: Base\n**Similarity Score**: 0.74\n\n## CWE-294: Authentication Bypass by Capture-replay\n**Abstraction Level**: Base\n**Similarity Score**: 0.74\n\n## CWE-472: External Control of Assumed-Immutable Web Parameter\n**Abstraction Level**: Base\n**Similarity Score**: 0.74\n\n## CWE-212: Improper Removal of Sensitive Information Before Storage or Transfer\n**Abstraction Level**: Base\n**Similarity Score**: 0.74\n\n## CWE-668: Exposure of Resource to Wrong Sphere\n**Abstraction Level**: Class\n**Similarity Score**: 0.74\n\n## CWE-288: Authentication Bypass Using an Alternate Path or Channel\n**Abstraction Level**: Base\n**Similarity Score**: 0.74\n\n## CWE-74: Improper Neutralization of Special Elements in Output Used by a Downstream Component ('Injection')\n**Abstraction Level**: Class\n**Similarity Score**: 0.74\n\n## CWE-639: Authorization Bypass Through User-Controlled Key\n**Abstraction Level**: Base\n**Similarity Score**: 1160.13\n\n## CWE-863: Incorrect Authorization\n**Abstraction Level**: Class\n**Similarity Score**: 1149.63\n\n## CWE-285: Improper Authorization\n**Abstraction Level**: Class\n**Similarity Score**: 1127.43\n\n## CWE-113: Improper Neutralization of CRLF Sequences in HTTP Headers ('HTTP Request/Response Splitting')\n**Abstraction Level**: Variant\n**Similarity Score**: 1114.21\n\n## CWE-306: Missing Authentication for Critical Function\n**Abstraction Level**: Base\n**Similarity Score**: 1109.69\n\n**Description**:\nThe product does not perform any authentication for functionality that requires a provable user identity or consumes a significant amount of resources.\n\n**Mapping Guidance**:\n- Usage: Allowed\n- Rationale: This CWE entry is at the Base level of abstraction, which is a preferred level of abstraction for mapping to the root causes of vulnerabilities.\n\n## CWE-93: Improper Neutralization of CRLF Sequences ('CRLF Injection')\n**Abstraction Level**: base\n**Similarity Score**: 4.33\n\n## CWE-117: Improper Output Neutralization for Logs\n**Abstraction Level**: base\n**Similarity Score**: 4.33\n\n## CWE-79: Improper Neutralization of Input During Web Page Generation ('Cross-site Scripting')\n**Abstraction Level**: base\n**Similarity Score**: 2.91\n\n## CWE-611: Improper Restriction of XML External Entity Reference\n**Abstraction Level**: base\n**Similarity Score**: 2.77\n\n## CWE-1275: Sensitive Cookie with Improper SameSite Attribute\n**Abstraction Level**: variant\n**Similarity Score**: 2.55\n\n## CWE-601: URL Redirection to Untrusted Site ('Open Redirect')\n**Abstraction Level**: base\n**Similarity Score**: 2.40\n\n## CWE-306: Missing Authentication for Critical Function\n**Abstraction Level**: base\n**Similarity Score**: 2.33\n\n## CWE-941: Incorrectly Specified Destination in a Communication Channel\n**Abstraction Level**: base\n**Similarity Score**: 2.33\n\n## CWE-471: Modification of Assumed-Immutable Data (MAID)\n**Abstraction Level**: base\n**Similarity Score**: 2.21\n\n## CWE-113: Improper Neutralization of CRLF Sequences in HTTP Headers ('HTTP Request/Response Splitting')\n**Abstraction Level**: variant\n**Similarity Score**: 2.16\n\nRelevant CWE Information:\n\n### CWE-918: Server-Side Request Forgery (SSRF)\n* Technical Explanation: The vulnerability description explicitly mentions \"Server-Side Request Forgery (SSRF)\". This aligns directly with the definition of CWE-918, where the server retrieves the contents of a URL without sufficient validation, potentially leading to unintended consequences.\n* Security Implications: An attacker could exploit this vulnerability to make the server send requests to internal or external systems, potentially exposing sensitive data or performing unauthorized actions.\n* Relationship Analysis: CWE-918 is a root cause that can lead to other vulnerabilities like information disclosure or remote code execution.\n* Mapping Guidance: The Usage is \"Allowed\" and the Rationale states it is at the Base level of abstraction, which is preferred.\n\n### CWE-306: Missing Authentication for Critical Function\n* Technical Explanation: The vulnerability description mentions \"Authentication Bypass\". This aligns with CWE-306, where critical functionality lacks proper authentication mechanisms.\n* Security Implications: Without authentication, attackers can directly access and manipulate critical functions, leading to unauthorized actions and data breaches.\n* Relationship Analysis: CWE-306 is often a consequence of other vulnerabilities or misconfigurations, such as SSRF.\n* Mapping Guidance: The Usage is \"Allowed\" and the Rationale states it is at the Base level of abstraction, which is preferred.\n\n### Other CWEs Considered But Not Used:\n\n* CWE-611: While SSRF can sometimes involve XML External Entity (XXE) injection, the description doesn't specifically mention XML or entities, making CWE-611 less applicable.\n* CWE-89, CWE-93, CWE-113, CWE-601: These CWEs represent different types of injection vulnerabilities, but the description doesn't provide enough details to support their inclusion. The root cause appears to be an SSRF vulnerability, not a specific type of injection.\n* CWE-352: This CWE describes Cross-Site Request Forgery (CSRF). There is no mention of CSRF in the description, and therefore it is not applicable.\n\nI am overriding the retriever results and focusing on the root cause, which is the SSRF (\n\n\n## CWE Relationship Analysis\n\nCurrent CWEs represent these abstraction levels: .\n\n\n### Vulnerability Chain Analysis\n\n**Chain starting from CWE-471:**\n- 471 (Modification of Assumed-Immutable Data (MAID)) - ROOT\n\n\n**Chain starting from CWE-611:**\n- 611 (Improper Restriction of XML External Entity Reference) - ROOT\n\n\n\n### CWE Relationship Diagram\n\n```mermaid\ngraph TD\n    classDef primary fill:#f96,stroke:#333,stroke-width:2px\n    classDef secondary fill:#69f,stroke:#333\n    classDef tertiary fill:#9e9,stroke:#333\n```",
  "criticism": "",
  "resolution": "",
  "relevant_cwes": [
    {
      "metadata": {
        "doc_id": "918",
        "name": "Server-Side Request Forgery (SSRF)",
        "source": "sparse"
      },
      "similarity": 208.82407520817557
    },
    {
      "metadata": {
        "doc_id": "611",
        "name": "Improper Restriction of XML External Entity Reference",
        "source": "sparse"
      },
      "similarity": 173.6100690517546
    },
    {
      "metadata": {
        "doc_id": "89",
        "name": "Improper Neutralization of Special Elements used in an SQL Command ('SQL Injection')",
        "source": "sparse"
      },
      "similarity": 137.28801058227526
    },
    {
      "metadata": {
        "doc_id": "601",
        "name": "URL Redirection to Untrusted Site ('Open Redirect')",
        "source": "sparse"
      },
      "similarity": 126.1076722562121
    },
    {
      "metadata": {
        "doc_id": "93",
        "name": "Improper Neutralization of CRLF Sequences ('CRLF Injection')",
        "source": "sparse"
      },
      "similarity": 124.75946192248996
    },
    {
      "metadata": {
        "doc_id": "352",
        "name": "Cross-Site Request Forgery (CSRF)",
        "source": "sparse"
      },
      "similarity": 124.50801368147422
    },
    {
      "metadata": {
        "doc_id": "113",
        "name": "Improper Neutralization of CRLF Sequences in HTTP Headers ('HTTP Request/Response Splitting')",
        "source": "sparse"
      },
      "similarity": 116.91409598641366
    },
    {
      "metadata": {
        "doc_id": "941",
        "name": "Incorrectly Specified Destination in a Communication Channel",
        "source": "sparse"
      },
      "similarity": 114.78847690382983
    },
    {
      "metadata": {
        "doc_id": "294",
        "name": "Authentication Bypass by Capture-replay",
        "type": "Base",
        "original_content": "A capture-replay flaw exists when the design of the product makes it possible for a malicious user to sniff network traffic and bypass authentication by replaying it to the server in question to the same effect as the original message (or with minor changes).",
        "source": "dense",
        "mapping_notes": {
          "usage": "Allowed",
          "rationale": "This CWE entry is at the Base level of abstraction, which is a preferred level of abstraction for mapping to the root causes of vulnerabilities.",
          "comments": "Carefully read both the name and description to ensure that this mapping is an appropriate fit. Do not try to 'force' a mapping to a lower-level Base/Variant simply to comply with this preferred level of abstraction.",
          "reasons": [
            "Acceptable-Use"
          ]
        },
        "score_info": {
          "retrievers": [
            "dense",
            "graph"
          ],
          "retriever_count": 2,
          "normalized_scores": {
            "dense": 0.4884269605894558,
            "graph": 1.4892264445112322
          }
        }
      },
      "similarity": 0.4884269605894558
    },
    {
      "doc_id": "117",
      "text": "CWE-117: Improper Output Neutralization for Logs",
      "score": 2.2100000000000004,
      "metadata": {
        "doc_id": "117",
        "name": "Improper Output Neutralization for Logs",
        "type": "base",
        "original_content": "CWE-117: Improper Output Neutralization for Logs",
        "relationships": [
          {
            "source_id": "117",
            "target_id": "93",
            "label": "CANFOLLOW",
            "properties": {
              "view_id": "1000"
            }
          },
          {
            "source_id": "117",
            "target_id": "20",
            "label": "CHILDOF",
            "properties": {
              "ordinal": "Primary",
              "view_id": "700"
            }
          },
          {
            "source_id": "117",
            "target_id": "116",
            "label": "CHILDOF",
            "properties": {
              "ordinal": "Primary",
              "view_id": "1000"
            }
          },
          {
            "source_id": "93",
            "target_id": "117",
            "label": "CANPRECEDE",
            "properties": {
              "view_id": "1000"
            }
          },
          {
            "source_id": "20",
            "target_id": "117",
            "label": "PARENTOF",
            "properties": {
              "ordinal": "Primary",
              "view_id": "700"
            }
          },
          {
            "source_id": "116",
            "target_id": "117",
            "label": "PARENTOF",
            "properties": {
              "ordinal": "Primary",
              "view_id": "1000"
            }
          }
        ],
        "score_components": {
          "relationship_chain": 1.0,
          "sequence_path": 1.0
        },
        "abstraction_factor": 1.3,
        "graph_path_info": {
          "path_types": [
            "relationship_chain",
            "vulnerability_sequence_forward"
          ],
          "best_paths": {
            "relationship_chain": {
              "path": [
                [
                  "93",
                  "117",
                  "CANPRECEDE"
                ]
              ],
              "score": 1.0,
              "type": "relationship_chain",
              "source": "93"
            },
            "vulnerability_sequence_forward": {
              "path": [
                [
                  "93",
                  "117",
                  "CANPRECEDE"
                ]
              ],
              "score": 1.0,
              "type": "vulnerability_sequence_forward",
              "source": "93"
            }
          }
        },
        "position": "after",
        "sources": [
          "graph"
        ],
        "source": "graph",
        "mapping_notes": {
          "usage": "Allowed",
          "rationale": "This CWE entry is at the Base level of abstraction, which is a preferred level of abstraction for mapping to the root causes of vulnerabilities.",
          "comments": "Carefully read both the name and description to ensure that this mapping is an appropriate fit. Do not try to 'force' a mapping to a lower-level Base/Variant simply to comply with this preferred level of abstraction.",
          "reasons": [
            "Acceptable-Use"
          ]
        },
        "score_info": {
          "retrievers": [
            "graph"
          ],
          "retriever_count": 1,
          "normalized_scores": {
            "graph": 2.2100000000000004
          }
        }
      },
      "similarity": 2.2100000000000004
    }
  ],
  "identified_cwes": {
    "analyzer": [
      "CWE-471",
      "CWE-611",
      "CWE-93",
      "CWE-639",
      "CWE-79",
      "CWE-113",
      "CWE-74",
      "CWE-285",
      "CWE-117",
      "CWE-807",
      "CWE-89",
      "CWE-601",
      "CWE-306",
      "CWE-352",
      "CWE-918",
      "CWE-288",
      "CWE-863",
      "CWE-294",
      "CWE-668",
      "CWE-941",
      "CWE-212",
      "CWE-602",
      "CWE-472",
      "CWE-303",
      "CWE-1275"
    ],
    "critic_additional": []
  },
  "keyphrase_cwe_mapping": {}
}