{
  "vulnerability_info": "VulnerabilityInfo(cve_id='CVE-2024-7866', description='In Xpdf 4.05 (and earlier), a PDF object loop in a pattern resource leads to ****infinite recursion**** and a **stack overflow**.', key_phrases={'rootcause': 'infinite recursion', 'weakness': ['infinite recursion', 'stack overflow'], 'impact': '', 'vector': '', 'attacker': '', 'product': 'Xpdf', 'version': '4.05 (and earlier)', 'component': 'PDF object loop in a pattern resource'}, reference_content='Root cause of vulnerability: PDF files can contain \\'object loops\\', where one PDF object points back to itself, or a sequence of PDF objects point to each other in a longer loop. Xpdf doesn\\'t catch all of them.\\nWeaknesses/vulnerabilities present: Infinite loop, stack overflow.\\nImpact of exploitation: Infinite loop, ending with a stack overflow.\\nMitigation or fix: \"will be fixed in 4.06\" (for Gfx::drawForm)', similar_info={'cwe_distribution': {}, 'cwe_consensus': '', 'similarity_stats': {'thresholds': [], 'total_samples_by_threshold': {}, 'top_cwes_by_threshold': {}}}, similarity_summary=SimilarityInsight(consensus_cwe='', top_cwes=[], confidence_levels={}, total_samples=0), analysis='', analysis_with_relationships='', criticism='', resolution='', relevant_cwes=[{'metadata': {'doc_id': '674', 'name': 'Uncontrolled Recursion', 'source': 'sparse', 'original_content': 'The product does not properly control the amount of recursion that takes place,  consuming excessive resources, such as allocated memory or the program stack.', 'keyphrase_sources': [{'id': 'rootcause:infinite recursion', 'keyphrase': 'infinite recursion', 'type': 'rootcause'}, {'id': 'weakness:infinite recursion', 'keyphrase': 'infinite recursion', 'type': 'weakness'}, {'id': 'weakness:stack overflow', 'keyphrase': 'stack overflow', 'type': 'weakness'}, {'id': 'product:Xpdf', 'keyphrase': 'Xpdf', 'type': 'product'}, {'id': 'version:4.05 (and earlier)', 'keyphrase': '4.05 (and earlier)', 'type': 'version'}, {'id': 'component:PDF object loop in a pattern resource', 'keyphrase': 'PDF object loop in a pattern resource', 'type': 'component'}]}, 'similarity': np.float64(308.53315913272996)}, {'metadata': {'doc_id': '835', 'name': \"Loop with Unreachable Exit Condition ('Infinite Loop')\", 'source': 'sparse', 'original_content': 'The product contains an iteration or loop with an exit condition that cannot be reached, i.e., an infinite loop.', 'keyphrase_sources': [{'id': 'rootcause:infinite recursion', 'keyphrase': 'infinite recursion', 'type': 'rootcause'}, {'id': 'weakness:infinite recursion', 'keyphrase': 'infinite recursion', 'type': 'weakness'}, {'id': 'weakness:stack overflow', 'keyphrase': 'stack overflow', 'type': 'weakness'}, {'id': 'product:Xpdf', 'keyphrase': 'Xpdf', 'type': 'product'}, {'id': 'version:4.05 (and earlier)', 'keyphrase': '4.05 (and earlier)', 'type': 'version'}, {'id': 'component:PDF object loop in a pattern resource', 'keyphrase': 'PDF object loop in a pattern resource', 'type': 'component'}]}, 'similarity': np.float64(231.3868353336831)}, {'metadata': {'doc_id': '121', 'name': 'Stack-based Buffer Overflow', 'source': 'sparse', 'original_content': 'A stack-based buffer overflow condition is a condition where the buffer being overwritten is allocated on the stack (i.e., is a local variable or, rarely, a parameter to a function).', 'keyphrase_sources': [{'id': 'weakness:stack overflow', 'keyphrase': 'stack overflow', 'type': 'weakness'}, {'id': 'product:Xpdf', 'keyphrase': 'Xpdf', 'type': 'product'}, {'id': 'version:4.05 (and earlier)', 'keyphrase': '4.05 (and earlier)', 'type': 'version'}]}, 'similarity': np.float64(207.3173384838974)}, {'metadata': {'doc_id': '834', 'name': 'Excessive Iteration', 'source': 'sparse', 'original_content': 'The product performs an iteration or loop without sufficiently limiting the number of times that the loop is executed.', 'keyphrase_sources': [{'id': 'rootcause:infinite recursion', 'keyphrase': 'infinite recursion', 'type': 'rootcause'}, {'id': 'weakness:infinite recursion', 'keyphrase': 'infinite recursion', 'type': 'weakness'}, {'id': 'component:PDF object loop in a pattern resource', 'keyphrase': 'PDF object loop in a pattern resource', 'type': 'component'}]}, 'similarity': np.float64(182.61802661408933)}, {'metadata': {'doc_id': '120', 'name': \"Buffer Copy without Checking Size of Input ('Classic Buffer Overflow')\", 'source': 'sparse', 'original_content': 'The product copies an input buffer to an output buffer without verifying that the size of the input buffer is less than the size of the output buffer, leading to a buffer overflow.', 'keyphrase_sources': [{'id': 'weakness:stack overflow', 'keyphrase': 'stack overflow', 'type': 'weakness'}]}, 'similarity': np.float64(175.5716406383172)}, {'metadata': {'doc_id': '1325', 'name': 'Improperly Controlled Sequential Memory Allocation', 'source': 'sparse', 'original_content': 'The product manages a group of objects or resources and performs a separate memory allocation for each object, but it does not properly limit the total amount of memory that is consumed by all of the combined objects.', 'keyphrase_sources': [{'id': 'rootcause:infinite recursion', 'keyphrase': 'infinite recursion', 'type': 'rootcause'}, {'id': 'weakness:infinite recursion', 'keyphrase': 'infinite recursion', 'type': 'weakness'}, {'id': 'weakness:stack overflow', 'keyphrase': 'stack overflow', 'type': 'weakness'}, {'id': 'product:Xpdf', 'keyphrase': 'Xpdf', 'type': 'product'}]}, 'similarity': np.float64(173.37319444258293)}, {'metadata': {'doc_id': '1339', 'name': 'Insufficient Precision or Accuracy of a Real Number', 'source': 'sparse', 'original_content': \"The product processes a real number with an implementation in which the number's representation does not preserve required accuracy and precision in its fractional part, causing an incorrect result.\", 'keyphrase_sources': [{'id': 'rootcause:infinite recursion', 'keyphrase': 'infinite recursion', 'type': 'rootcause'}, {'id': 'weakness:infinite recursion', 'keyphrase': 'infinite recursion', 'type': 'weakness'}]}, 'similarity': np.float64(170.68403635329156)}, {'metadata': {'doc_id': '1265', 'name': 'Unintended Reentrant Invocation of Non-reentrant Code Via Nested Calls', 'source': 'sparse', 'original_content': 'During execution of non-reentrant code, the product performs a call that unintentionally produces a nested invocation of the non-reentrant code.', 'keyphrase_sources': [{'id': 'component:PDF object loop in a pattern resource', 'keyphrase': 'PDF object loop in a pattern resource', 'type': 'component'}]}, 'similarity': np.float64(85.27642783715815)}, {'metadata': {'doc_id': '1046', 'name': 'Creation of Immutable Text Using String Concatenation', 'source': 'sparse', 'original_content': 'The product creates an immutable text string using string concatenation operations.', 'keyphrase_sources': [{'id': 'component:PDF object loop in a pattern resource', 'keyphrase': 'PDF object loop in a pattern resource', 'type': 'component'}]}, 'similarity': np.float64(77.93891047916358)}, {'metadata': {'doc_id': '787', 'name': 'Out-of-bounds Write', 'source': 'sparse', 'original_content': 'The product writes data past the end, or before the beginning, of the intended buffer.', 'keyphrase_sources': [{'id': 'version:4.05 (and earlier)', 'keyphrase': '4.05 (and earlier)', 'type': 'version'}]}, 'similarity': np.float64(72.42863506129139)}, {'metadata': {'doc_id': '912', 'name': 'Hidden Functionality', 'source': 'sparse', 'original_content': \"The product contains functionality that is not documented, not part of the specification, and not accessible through an interface or command sequence that is obvious to the product's users or administrators.\", 'keyphrase_sources': [{'id': 'version:4.05 (and earlier)', 'keyphrase': '4.05 (and earlier)', 'type': 'version'}]}, 'similarity': np.float64(69.4778053620192)}, {'metadata': {'doc_id': '665', 'name': 'Improper Initialization', 'source': 'sparse', 'original_content': 'The product does not initialize or incorrectly initializes a resource, which might leave the resource in an unexpected state when it is accessed or used.', 'keyphrase_sources': [{'id': 'product:Xpdf', 'keyphrase': 'Xpdf', 'type': 'product'}]}, 'similarity': np.float64(49.58993756646753)}], identified_cwes={'analyzer': [], 'critic_additional': []})",
  "retrieval_results": {
    "has_multiple_keyphrases": true,
    "keyphrase_cwe_sets": {
      "rootcause:infinite recursion": {
        "keyphrase": "infinite recursion",
        "type": "rootcause",
        "cwes": [
          {
            "metadata": {
              "doc_id": "674",
              "name": "Uncontrolled Recursion",
              "source": "sparse",
              "original_content": "The product does not properly control the amount of recursion that takes place,  consuming excessive resources, such as allocated memory or the program stack.",
              "keyphrase_sources": [
                {
                  "id": "rootcause:infinite recursion",
                  "keyphrase": "infinite recursion",
                  "type": "rootcause"
                },
                {
                  "id": "weakness:infinite recursion",
                  "keyphrase": "infinite recursion",
                  "type": "weakness"
                },
                {
                  "id": "weakness:stack overflow",
                  "keyphrase": "stack overflow",
                  "type": "weakness"
                },
                {
                  "id": "product:Xpdf",
                  "keyphrase": "Xpdf",
                  "type": "product"
                },
                {
                  "id": "version:4.05 (and earlier)",
                  "keyphrase": "4.05 (and earlier)",
                  "type": "version"
                },
                {
                  "id": "component:PDF object loop in a pattern resource",
                  "keyphrase": "PDF object loop in a pattern resource",
                  "type": "component"
                }
              ]
            },
            "similarity": 308.53315913272996
          },
          {
            "metadata": {
              "doc_id": "835",
              "name": "Loop with Unreachable Exit Condition ('Infinite Loop')",
              "source": "sparse",
              "original_content": "The product contains an iteration or loop with an exit condition that cannot be reached, i.e., an infinite loop.",
              "keyphrase_sources": [
                {
                  "id": "rootcause:infinite recursion",
                  "keyphrase": "infinite recursion",
                  "type": "rootcause"
                },
                {
                  "id": "weakness:infinite recursion",
                  "keyphrase": "infinite recursion",
                  "type": "weakness"
                },
                {
                  "id": "weakness:stack overflow",
                  "keyphrase": "stack overflow",
                  "type": "weakness"
                },
                {
                  "id": "product:Xpdf",
                  "keyphrase": "Xpdf",
                  "type": "product"
                },
                {
                  "id": "version:4.05 (and earlier)",
                  "keyphrase": "4.05 (and earlier)",
                  "type": "version"
                },
                {
                  "id": "component:PDF object loop in a pattern resource",
                  "keyphrase": "PDF object loop in a pattern resource",
                  "type": "component"
                }
              ]
            },
            "similarity": 231.3868353336831
          },
          {
            "metadata": {
              "doc_id": "834",
              "name": "Excessive Iteration",
              "source": "sparse",
              "original_content": "The product performs an iteration or loop without sufficiently limiting the number of times that the loop is executed.",
              "keyphrase_sources": [
                {
                  "id": "rootcause:infinite recursion",
                  "keyphrase": "infinite recursion",
                  "type": "rootcause"
                },
                {
                  "id": "weakness:infinite recursion",
                  "keyphrase": "infinite recursion",
                  "type": "weakness"
                },
                {
                  "id": "component:PDF object loop in a pattern resource",
                  "keyphrase": "PDF object loop in a pattern resource",
                  "type": "component"
                }
              ]
            },
            "similarity": 182.61802661408933
          },
          {
            "metadata": {
              "doc_id": "1325",
              "name": "Improperly Controlled Sequential Memory Allocation",
              "source": "sparse",
              "original_content": "The product manages a group of objects or resources and performs a separate memory allocation for each object, but it does not properly limit the total amount of memory that is consumed by all of the combined objects.",
              "keyphrase_sources": [
                {
                  "id": "rootcause:infinite recursion",
                  "keyphrase": "infinite recursion",
                  "type": "rootcause"
                },
                {
                  "id": "weakness:infinite recursion",
                  "keyphrase": "infinite recursion",
                  "type": "weakness"
                },
                {
                  "id": "weakness:stack overflow",
                  "keyphrase": "stack overflow",
                  "type": "weakness"
                },
                {
                  "id": "product:Xpdf",
                  "keyphrase": "Xpdf",
                  "type": "product"
                }
              ]
            },
            "similarity": 173.37319444258293
          },
          {
            "metadata": {
              "doc_id": "1339",
              "name": "Insufficient Precision or Accuracy of a Real Number",
              "source": "sparse",
              "original_content": "The product processes a real number with an implementation in which the number's representation does not preserve required accuracy and precision in its fractional part, causing an incorrect result.",
              "keyphrase_sources": [
                {
                  "id": "rootcause:infinite recursion",
                  "keyphrase": "infinite recursion",
                  "type": "rootcause"
                },
                {
                  "id": "weakness:infinite recursion",
                  "keyphrase": "infinite recursion",
                  "type": "weakness"
                }
              ]
            },
            "similarity": 170.68403635329156
          }
        ]
      },
      "weakness:infinite recursion": {
        "keyphrase": "infinite recursion",
        "type": "weakness",
        "cwes": [
          {
            "metadata": {
              "doc_id": "674",
              "name": "Uncontrolled Recursion",
              "source": "sparse",
              "original_content": "The product does not properly control the amount of recursion that takes place,  consuming excessive resources, such as allocated memory or the program stack."
            },
            "similarity": 287.9642818572146
          },
          {
            "metadata": {
              "doc_id": "835",
              "name": "Loop with Unreachable Exit Condition ('Infinite Loop')",
              "source": "sparse",
              "original_content": "The product contains an iteration or loop with an exit condition that cannot be reached, i.e., an infinite loop."
            },
            "similarity": 215.96104631143757
          },
          {
            "metadata": {
              "doc_id": "834",
              "name": "Excessive Iteration",
              "source": "sparse",
              "original_content": "The product performs an iteration or loop without sufficiently limiting the number of times that the loop is executed."
            },
            "similarity": 170.44349150648338
          },
          {
            "metadata": {
              "doc_id": "1325",
              "name": "Improperly Controlled Sequential Memory Allocation",
              "source": "sparse",
              "original_content": "The product manages a group of objects or resources and performs a separate memory allocation for each object, but it does not properly limit the total amount of memory that is consumed by all of the combined objects."
            },
            "similarity": 161.81498147974406
          },
          {
            "metadata": {
              "doc_id": "1339",
              "name": "Insufficient Precision or Accuracy of a Real Number",
              "source": "sparse",
              "original_content": "The product processes a real number with an implementation in which the number's representation does not preserve required accuracy and precision in its fractional part, causing an incorrect result."
            },
            "similarity": 159.30510059640545
          }
        ]
      },
      "weakness:stack overflow": {
        "keyphrase": "stack overflow",
        "type": "weakness",
        "cwes": [
          {
            "metadata": {
              "doc_id": "674",
              "name": "Uncontrolled Recursion",
              "source": "sparse",
              "original_content": "The product does not properly control the amount of recursion that takes place,  consuming excessive resources, such as allocated memory or the program stack."
            },
            "similarity": 251.87598631012142
          },
          {
            "metadata": {
              "doc_id": "835",
              "name": "Loop with Unreachable Exit Condition ('Infinite Loop')",
              "source": "sparse",
              "original_content": "The product contains an iteration or loop with an exit condition that cannot be reached, i.e., an infinite loop."
            },
            "similarity": 211.43010917299725
          },
          {
            "metadata": {
              "doc_id": "121",
              "name": "Stack-based Buffer Overflow",
              "source": "sparse",
              "original_content": "A stack-based buffer overflow condition is a condition where the buffer being overwritten is allocated on the stack (i.e., is a local variable or, rarely, a parameter to a function).",
              "keyphrase_sources": [
                {
                  "id": "weakness:stack overflow",
                  "keyphrase": "stack overflow",
                  "type": "weakness"
                },
                {
                  "id": "product:Xpdf",
                  "keyphrase": "Xpdf",
                  "type": "product"
                },
                {
                  "id": "version:4.05 (and earlier)",
                  "keyphrase": "4.05 (and earlier)",
                  "type": "version"
                }
              ]
            },
            "similarity": 207.3173384838974
          },
          {
            "metadata": {
              "doc_id": "1325",
              "name": "Improperly Controlled Sequential Memory Allocation",
              "source": "sparse",
              "original_content": "The product manages a group of objects or resources and performs a separate memory allocation for each object, but it does not properly limit the total amount of memory that is consumed by all of the combined objects."
            },
            "similarity": 189.4497116670789
          },
          {
            "metadata": {
              "doc_id": "120",
              "name": "Buffer Copy without Checking Size of Input ('Classic Buffer Overflow')",
              "source": "sparse",
              "original_content": "The product copies an input buffer to an output buffer without verifying that the size of the input buffer is less than the size of the output buffer, leading to a buffer overflow.",
              "keyphrase_sources": [
                {
                  "id": "weakness:stack overflow",
                  "keyphrase": "stack overflow",
                  "type": "weakness"
                }
              ]
            },
            "similarity": 175.5716406383172
          }
        ]
      },
      "product:Xpdf": {
        "keyphrase": "Xpdf",
        "type": "product",
        "cwes": [
          {
            "metadata": {
              "doc_id": "674",
              "name": "Uncontrolled Recursion",
              "source": "sparse",
              "original_content": "The product does not properly control the amount of recursion that takes place,  consuming excessive resources, such as allocated memory or the program stack."
            },
            "similarity": 74.4441927587516
          },
          {
            "metadata": {
              "doc_id": "835",
              "name": "Loop with Unreachable Exit Condition ('Infinite Loop')",
              "source": "sparse",
              "original_content": "The product contains an iteration or loop with an exit condition that cannot be reached, i.e., an infinite loop."
            },
            "similarity": 61.063119877267766
          },
          {
            "metadata": {
              "doc_id": "121",
              "name": "Stack-based Buffer Overflow",
              "source": "sparse",
              "original_content": "A stack-based buffer overflow condition is a condition where the buffer being overwritten is allocated on the stack (i.e., is a local variable or, rarely, a parameter to a function)."
            },
            "similarity": 55.002809713643636
          },
          {
            "metadata": {
              "doc_id": "665",
              "name": "Improper Initialization",
              "source": "sparse",
              "original_content": "The product does not initialize or incorrectly initializes a resource, which might leave the resource in an unexpected state when it is accessed or used.",
              "keyphrase_sources": [
                {
                  "id": "product:Xpdf",
                  "keyphrase": "Xpdf",
                  "type": "product"
                }
              ]
            },
            "similarity": 49.58993756646753
          },
          {
            "metadata": {
              "doc_id": "1325",
              "name": "Improperly Controlled Sequential Memory Allocation",
              "source": "sparse",
              "original_content": "The product manages a group of objects or resources and performs a separate memory allocation for each object, but it does not properly limit the total amount of memory that is consumed by all of the combined objects."
            },
            "similarity": 48.75069789219482
          }
        ]
      },
      "version:4.05 (and earlier)": {
        "keyphrase": "4.05 (and earlier)",
        "type": "version",
        "cwes": [
          {
            "metadata": {
              "doc_id": "674",
              "name": "Uncontrolled Recursion",
              "source": "sparse",
              "original_content": "The product does not properly control the amount of recursion that takes place,  consuming excessive resources, such as allocated memory or the program stack."
            },
            "similarity": 80.15865972709727
          },
          {
            "metadata": {
              "doc_id": "787",
              "name": "Out-of-bounds Write",
              "source": "sparse",
              "original_content": "The product writes data past the end, or before the beginning, of the intended buffer.",
              "keyphrase_sources": [
                {
                  "id": "version:4.05 (and earlier)",
                  "keyphrase": "4.05 (and earlier)",
                  "type": "version"
                }
              ]
            },
            "similarity": 72.42863506129139
          },
          {
            "metadata": {
              "doc_id": "121",
              "name": "Stack-based Buffer Overflow",
              "source": "sparse",
              "original_content": "A stack-based buffer overflow condition is a condition where the buffer being overwritten is allocated on the stack (i.e., is a local variable or, rarely, a parameter to a function)."
            },
            "similarity": 72.35107319285008
          },
          {
            "metadata": {
              "doc_id": "835",
              "name": "Loop with Unreachable Exit Condition ('Infinite Loop')",
              "source": "sparse",
              "original_content": "The product contains an iteration or loop with an exit condition that cannot be reached, i.e., an infinite loop."
            },
            "similarity": 70.79785840156323
          },
          {
            "metadata": {
              "doc_id": "912",
              "name": "Hidden Functionality",
              "source": "sparse",
              "original_content": "The product contains functionality that is not documented, not part of the specification, and not accessible through an interface or command sequence that is obvious to the product's users or administrators.",
              "keyphrase_sources": [
                {
                  "id": "version:4.05 (and earlier)",
                  "keyphrase": "4.05 (and earlier)",
                  "type": "version"
                }
              ]
            },
            "similarity": 69.4778053620192
          }
        ]
      },
      "component:PDF object loop in a pattern resource": {
        "keyphrase": "PDF object loop in a pattern resource",
        "type": "component",
        "cwes": [
          {
            "metadata": {
              "doc_id": "835",
              "name": "Loop with Unreachable Exit Condition ('Infinite Loop')",
              "source": "sparse",
              "original_content": "The product contains an iteration or loop with an exit condition that cannot be reached, i.e., an infinite loop."
            },
            "similarity": 103.67277651769014
          },
          {
            "metadata": {
              "doc_id": "674",
              "name": "Uncontrolled Recursion",
              "source": "sparse",
              "original_content": "The product does not properly control the amount of recursion that takes place,  consuming excessive resources, such as allocated memory or the program stack."
            },
            "similarity": 92.6527300340731
          },
          {
            "metadata": {
              "doc_id": "1265",
              "name": "Unintended Reentrant Invocation of Non-reentrant Code Via Nested Calls",
              "source": "sparse",
              "original_content": "During execution of non-reentrant code, the product performs a call that unintentionally produces a nested invocation of the non-reentrant code.",
              "keyphrase_sources": [
                {
                  "id": "component:PDF object loop in a pattern resource",
                  "keyphrase": "PDF object loop in a pattern resource",
                  "type": "component"
                }
              ]
            },
            "similarity": 85.27642783715815
          },
          {
            "metadata": {
              "doc_id": "834",
              "name": "Excessive Iteration",
              "source": "sparse",
              "original_content": "The product performs an iteration or loop without sufficiently limiting the number of times that the loop is executed."
            },
            "similarity": 80.47423329937092
          },
          {
            "metadata": {
              "doc_id": "1046",
              "name": "Creation of Immutable Text Using String Concatenation",
              "source": "sparse",
              "original_content": "The product creates an immutable text string using string concatenation operations.",
              "keyphrase_sources": [
                {
                  "id": "component:PDF object loop in a pattern resource",
                  "keyphrase": "PDF object loop in a pattern resource",
                  "type": "component"
                }
              ]
            },
            "similarity": 77.93891047916358
          }
        ]
      }
    },
    "keyphrase_mapping": {
      "674": [
        {
          "id": "rootcause:infinite recursion",
          "keyphrase": "infinite recursion",
          "type": "rootcause"
        },
        {
          "id": "weakness:infinite recursion",
          "keyphrase": "infinite recursion",
          "type": "weakness"
        },
        {
          "id": "weakness:stack overflow",
          "keyphrase": "stack overflow",
          "type": "weakness"
        },
        {
          "id": "product:Xpdf",
          "keyphrase": "Xpdf",
          "type": "product"
        },
        {
          "id": "version:4.05 (and earlier)",
          "keyphrase": "4.05 (and earlier)",
          "type": "version"
        },
        {
          "id": "component:PDF object loop in a pattern resource",
          "keyphrase": "PDF object loop in a pattern resource",
          "type": "component"
        }
      ],
      "835": [
        {
          "id": "rootcause:infinite recursion",
          "keyphrase": "infinite recursion",
          "type": "rootcause"
        },
        {
          "id": "weakness:infinite recursion",
          "keyphrase": "infinite recursion",
          "type": "weakness"
        },
        {
          "id": "weakness:stack overflow",
          "keyphrase": "stack overflow",
          "type": "weakness"
        },
        {
          "id": "product:Xpdf",
          "keyphrase": "Xpdf",
          "type": "product"
        },
        {
          "id": "version:4.05 (and earlier)",
          "keyphrase": "4.05 (and earlier)",
          "type": "version"
        },
        {
          "id": "component:PDF object loop in a pattern resource",
          "keyphrase": "PDF object loop in a pattern resource",
          "type": "component"
        }
      ],
      "834": [
        {
          "id": "rootcause:infinite recursion",
          "keyphrase": "infinite recursion",
          "type": "rootcause"
        },
        {
          "id": "weakness:infinite recursion",
          "keyphrase": "infinite recursion",
          "type": "weakness"
        },
        {
          "id": "component:PDF object loop in a pattern resource",
          "keyphrase": "PDF object loop in a pattern resource",
          "type": "component"
        }
      ],
      "1325": [
        {
          "id": "rootcause:infinite recursion",
          "keyphrase": "infinite recursion",
          "type": "rootcause"
        },
        {
          "id": "weakness:infinite recursion",
          "keyphrase": "infinite recursion",
          "type": "weakness"
        },
        {
          "id": "weakness:stack overflow",
          "keyphrase": "stack overflow",
          "type": "weakness"
        },
        {
          "id": "product:Xpdf",
          "keyphrase": "Xpdf",
          "type": "product"
        }
      ],
      "1339": [
        {
          "id": "rootcause:infinite recursion",
          "keyphrase": "infinite recursion",
          "type": "rootcause"
        },
        {
          "id": "weakness:infinite recursion",
          "keyphrase": "infinite recursion",
          "type": "weakness"
        }
      ],
      "121": [
        {
          "id": "weakness:stack overflow",
          "keyphrase": "stack overflow",
          "type": "weakness"
        },
        {
          "id": "product:Xpdf",
          "keyphrase": "Xpdf",
          "type": "product"
        },
        {
          "id": "version:4.05 (and earlier)",
          "keyphrase": "4.05 (and earlier)",
          "type": "version"
        }
      ],
      "120": [
        {
          "id": "weakness:stack overflow",
          "keyphrase": "stack overflow",
          "type": "weakness"
        }
      ],
      "665": [
        {
          "id": "product:Xpdf",
          "keyphrase": "Xpdf",
          "type": "product"
        }
      ],
      "787": [
        {
          "id": "version:4.05 (and earlier)",
          "keyphrase": "4.05 (and earlier)",
          "type": "version"
        }
      ],
      "912": [
        {
          "id": "version:4.05 (and earlier)",
          "keyphrase": "4.05 (and earlier)",
          "type": "version"
        }
      ],
      "1265": [
        {
          "id": "component:PDF object loop in a pattern resource",
          "keyphrase": "PDF object loop in a pattern resource",
          "type": "component"
        }
      ],
      "1046": [
        {
          "id": "component:PDF object loop in a pattern resource",
          "keyphrase": "PDF object loop in a pattern resource",
          "type": "component"
        }
      ]
    },
    "relevant_cwes": [
      {
        "metadata": {
          "doc_id": "674",
          "name": "Uncontrolled Recursion",
          "source": "sparse",
          "original_content": "The product does not properly control the amount of recursion that takes place,  consuming excessive resources, such as allocated memory or the program stack.",
          "keyphrase_sources": [
            {
              "id": "rootcause:infinite recursion",
              "keyphrase": "infinite recursion",
              "type": "rootcause"
            },
            {
              "id": "weakness:infinite recursion",
              "keyphrase": "infinite recursion",
              "type": "weakness"
            },
            {
              "id": "weakness:stack overflow",
              "keyphrase": "stack overflow",
              "type": "weakness"
            },
            {
              "id": "product:Xpdf",
              "keyphrase": "Xpdf",
              "type": "product"
            },
            {
              "id": "version:4.05 (and earlier)",
              "keyphrase": "4.05 (and earlier)",
              "type": "version"
            },
            {
              "id": "component:PDF object loop in a pattern resource",
              "keyphrase": "PDF object loop in a pattern resource",
              "type": "component"
            }
          ]
        },
        "similarity": 308.53315913272996
      },
      {
        "metadata": {
          "doc_id": "835",
          "name": "Loop with Unreachable Exit Condition ('Infinite Loop')",
          "source": "sparse",
          "original_content": "The product contains an iteration or loop with an exit condition that cannot be reached, i.e., an infinite loop.",
          "keyphrase_sources": [
            {
              "id": "rootcause:infinite recursion",
              "keyphrase": "infinite recursion",
              "type": "rootcause"
            },
            {
              "id": "weakness:infinite recursion",
              "keyphrase": "infinite recursion",
              "type": "weakness"
            },
            {
              "id": "weakness:stack overflow",
              "keyphrase": "stack overflow",
              "type": "weakness"
            },
            {
              "id": "product:Xpdf",
              "keyphrase": "Xpdf",
              "type": "product"
            },
            {
              "id": "version:4.05 (and earlier)",
              "keyphrase": "4.05 (and earlier)",
              "type": "version"
            },
            {
              "id": "component:PDF object loop in a pattern resource",
              "keyphrase": "PDF object loop in a pattern resource",
              "type": "component"
            }
          ]
        },
        "similarity": 231.3868353336831
      },
      {
        "metadata": {
          "doc_id": "121",
          "name": "Stack-based Buffer Overflow",
          "source": "sparse",
          "original_content": "A stack-based buffer overflow condition is a condition where the buffer being overwritten is allocated on the stack (i.e., is a local variable or, rarely, a parameter to a function).",
          "keyphrase_sources": [
            {
              "id": "weakness:stack overflow",
              "keyphrase": "stack overflow",
              "type": "weakness"
            },
            {
              "id": "product:Xpdf",
              "keyphrase": "Xpdf",
              "type": "product"
            },
            {
              "id": "version:4.05 (and earlier)",
              "keyphrase": "4.05 (and earlier)",
              "type": "version"
            }
          ]
        },
        "similarity": 207.3173384838974
      },
      {
        "metadata": {
          "doc_id": "834",
          "name": "Excessive Iteration",
          "source": "sparse",
          "original_content": "The product performs an iteration or loop without sufficiently limiting the number of times that the loop is executed.",
          "keyphrase_sources": [
            {
              "id": "rootcause:infinite recursion",
              "keyphrase": "infinite recursion",
              "type": "rootcause"
            },
            {
              "id": "weakness:infinite recursion",
              "keyphrase": "infinite recursion",
              "type": "weakness"
            },
            {
              "id": "component:PDF object loop in a pattern resource",
              "keyphrase": "PDF object loop in a pattern resource",
              "type": "component"
            }
          ]
        },
        "similarity": 182.61802661408933
      },
      {
        "metadata": {
          "doc_id": "120",
          "name": "Buffer Copy without Checking Size of Input ('Classic Buffer Overflow')",
          "source": "sparse",
          "original_content": "The product copies an input buffer to an output buffer without verifying that the size of the input buffer is less than the size of the output buffer, leading to a buffer overflow.",
          "keyphrase_sources": [
            {
              "id": "weakness:stack overflow",
              "keyphrase": "stack overflow",
              "type": "weakness"
            }
          ]
        },
        "similarity": 175.5716406383172
      },
      {
        "metadata": {
          "doc_id": "1325",
          "name": "Improperly Controlled Sequential Memory Allocation",
          "source": "sparse",
          "original_content": "The product manages a group of objects or resources and performs a separate memory allocation for each object, but it does not properly limit the total amount of memory that is consumed by all of the combined objects.",
          "keyphrase_sources": [
            {
              "id": "rootcause:infinite recursion",
              "keyphrase": "infinite recursion",
              "type": "rootcause"
            },
            {
              "id": "weakness:infinite recursion",
              "keyphrase": "infinite recursion",
              "type": "weakness"
            },
            {
              "id": "weakness:stack overflow",
              "keyphrase": "stack overflow",
              "type": "weakness"
            },
            {
              "id": "product:Xpdf",
              "keyphrase": "Xpdf",
              "type": "product"
            }
          ]
        },
        "similarity": 173.37319444258293
      },
      {
        "metadata": {
          "doc_id": "1339",
          "name": "Insufficient Precision or Accuracy of a Real Number",
          "source": "sparse",
          "original_content": "The product processes a real number with an implementation in which the number's representation does not preserve required accuracy and precision in its fractional part, causing an incorrect result.",
          "keyphrase_sources": [
            {
              "id": "rootcause:infinite recursion",
              "keyphrase": "infinite recursion",
              "type": "rootcause"
            },
            {
              "id": "weakness:infinite recursion",
              "keyphrase": "infinite recursion",
              "type": "weakness"
            }
          ]
        },
        "similarity": 170.68403635329156
      },
      {
        "metadata": {
          "doc_id": "1265",
          "name": "Unintended Reentrant Invocation of Non-reentrant Code Via Nested Calls",
          "source": "sparse",
          "original_content": "During execution of non-reentrant code, the product performs a call that unintentionally produces a nested invocation of the non-reentrant code.",
          "keyphrase_sources": [
            {
              "id": "component:PDF object loop in a pattern resource",
              "keyphrase": "PDF object loop in a pattern resource",
              "type": "component"
            }
          ]
        },
        "similarity": 85.27642783715815
      },
      {
        "metadata": {
          "doc_id": "1046",
          "name": "Creation of Immutable Text Using String Concatenation",
          "source": "sparse",
          "original_content": "The product creates an immutable text string using string concatenation operations.",
          "keyphrase_sources": [
            {
              "id": "component:PDF object loop in a pattern resource",
              "keyphrase": "PDF object loop in a pattern resource",
              "type": "component"
            }
          ]
        },
        "similarity": 77.93891047916358
      },
      {
        "metadata": {
          "doc_id": "787",
          "name": "Out-of-bounds Write",
          "source": "sparse",
          "original_content": "The product writes data past the end, or before the beginning, of the intended buffer.",
          "keyphrase_sources": [
            {
              "id": "version:4.05 (and earlier)",
              "keyphrase": "4.05 (and earlier)",
              "type": "version"
            }
          ]
        },
        "similarity": 72.42863506129139
      },
      {
        "metadata": {
          "doc_id": "912",
          "name": "Hidden Functionality",
          "source": "sparse",
          "original_content": "The product contains functionality that is not documented, not part of the specification, and not accessible through an interface or command sequence that is obvious to the product's users or administrators.",
          "keyphrase_sources": [
            {
              "id": "version:4.05 (and earlier)",
              "keyphrase": "4.05 (and earlier)",
              "type": "version"
            }
          ]
        },
        "similarity": 69.4778053620192
      },
      {
        "metadata": {
          "doc_id": "665",
          "name": "Improper Initialization",
          "source": "sparse",
          "original_content": "The product does not initialize or incorrectly initializes a resource, which might leave the resource in an unexpected state when it is accessed or used.",
          "keyphrase_sources": [
            {
              "id": "product:Xpdf",
              "keyphrase": "Xpdf",
              "type": "product"
            }
          ]
        },
        "similarity": 49.58993756646753
      }
    ],
    "enhanced_query": "# Vulnerability Description\n\n    In Xpdf 4.05 (and earlier), a PDF object loop in a pattern resource leads to ****infinite recursion**** and a **stack overflow**.\n\n    # Keyphrase-Specific CWE Analysis\n    This vulnerability contains multiple keyphrases that may map to different CWEs. \n    Please analyze each keyphrase separately and determine the most appropriate CWE(s) for each.\n\n    ## ROOTCAUSE: 'infinite recursion'\n\nRelevant CWEs for this ROOTCAUSE:\n\n### 1. CWE-674: Uncontrolled Recursion (Score: 308.53)\n\nThe product does not properly control the amount of recursion that takes place,  consuming excessive resources, such as allocated memory or the program stack....\n\n### 2. CWE-835: Loop with Unreachable Exit Condition ('Infinite Loop') (Score: 231.39)\n\nThe product contains an iteration or loop with an exit condition that cannot be reached, i.e., an infinite loop....\n\n### 3. CWE-834: Excessive Iteration (Score: 182.62)\n\nThe product performs an iteration or loop without sufficiently limiting the number of times that the loop is executed....\n\n### 4. CWE-1325: Improperly Controlled Sequential Memory Allocation (Score: 173.37)\n\nThe product manages a group of objects or resources and performs a separate memory allocation for each object, but it does not properly limit the total amount of memory that is consumed by all of the combined objects....\n\n### 5. CWE-1339: Insufficient Precision or Accuracy of a Real Number (Score: 170.68)\n\nThe product processes a real number with an implementation in which the number's representation does not preserve required accuracy and precision in its fractional part, causing an incorrect result....\n\n## WEAKNESS: 'infinite recursion'\n\nRelevant CWEs for this WEAKNESS:\n\n### 1. CWE-674: Uncontrolled Recursion (Score: 308.53)\n\nThe product does not properly control the amount of recursion that takes place,  consuming excessive resources, such as allocated memory or the program stack....\n\n### 2. CWE-835: Loop with Unreachable Exit Condition ('Infinite Loop') (Score: 231.39)\n\nThe product contains an iteration or loop with an exit condition that cannot be reached, i.e., an infinite loop....\n\n### 3. CWE-834: Excessive Iteration (Score: 182.62)\n\nThe product performs an iteration or loop without sufficiently limiting the number of times that the loop is executed....\n\n### 4. CWE-1325: Improperly Controlled Sequential Memory Allocation (Score: 173.37)\n\nThe product manages a group of objects or resources and performs a separate memory allocation for each object, but it does not properly limit the total amount of memory that is consumed by all of the combined objects....\n\n### 5. CWE-1339: Insufficient Precision or Accuracy of a Real Number (Score: 170.68)\n\nThe product processes a real number with an implementation in which the number's representation does not preserve required accuracy and precision in its fractional part, causing an incorrect result....\n\n## WEAKNESS: 'stack overflow'\n\nRelevant CWEs for this WEAKNESS:\n\n### 1. CWE-674: Uncontrolled Recursion (Score: 308.53)\n\nThe product does not properly control the amount of recursion that takes place,  consuming excessive resources, such as allocated memory or the program stack....\n\n### 2. CWE-835: Loop with Unreachable Exit Condition ('Infinite Loop') (Score: 231.39)\n\nThe product contains an iteration or loop with an exit condition that cannot be reached, i.e., an infinite loop....\n\n### 3. CWE-121: Stack-based Buffer Overflow (Score: 207.32)\n\nA stack-based buffer overflow condition is a condition where the buffer being overwritten is allocated on the stack (i.e., is a local variable or, rarely, a parameter to a function)....\n\n### 4. CWE-120: Buffer Copy without Checking Size of Input ('Classic Buffer Overflow') (Score: 175.57)\n\nThe product copies an input buffer to an output buffer without verifying that the size of the input buffer is less than the size of the output buffer, leading to a buffer overflow....\n\n### 5. CWE-1325: Improperly Controlled Sequential Memory Allocation (Score: 173.37)\n\nThe product manages a group of objects or resources and performs a separate memory allocation for each object, but it does not properly limit the total amount of memory that is consumed by all of the combined objects....\n\n## PRODUCT: 'Xpdf'\n\nRelevant CWEs for this PRODUCT:\n\n### 1. CWE-674: Uncontrolled Recursion (Score: 308.53)\n\nThe product does not properly control the amount of recursion that takes place,  consuming excessive resources, such as allocated memory or the program stack....\n\n### 2. CWE-835: Loop with Unreachable Exit Condition ('Infinite Loop') (Score: 231.39)\n\nThe product contains an iteration or loop with an exit condition that cannot be reached, i.e., an infinite loop....\n\n### 3. CWE-121: Stack-based Buffer Overflow (Score: 207.32)\n\nA stack-based buffer overflow condition is a condition where the buffer being overwritten is allocated on the stack (i.e., is a local variable or, rarely, a parameter to a function)....\n\n### 4. CWE-1325: Improperly Controlled Sequential Memory Allocation (Score: 173.37)\n\nThe product manages a group of objects or resources and performs a separate memory allocation for each object, but it does not properly limit the total amount of memory that is consumed by all of the combined objects....\n\n### 5. CWE-665: Improper Initialization (Score: 49.59)\n\nThe product does not initialize or incorrectly initializes a resource, which might leave the resource in an unexpected state when it is accessed or used....\n\n## VERSION: '4.05 (and earlier)'\n\nRelevant CWEs for this VERSION:\n\n### 1. CWE-674: Uncontrolled Recursion (Score: 308.53)\n\nThe product does not properly control the amount of recursion that takes place,  consuming excessive resources, such as allocated memory or the program stack....\n\n### 2. CWE-835: Loop with Unreachable Exit Condition ('Infinite Loop') (Score: 231.39)\n\nThe product contains an iteration or loop with an exit condition that cannot be reached, i.e., an infinite loop....\n\n### 3. CWE-121: Stack-based Buffer Overflow (Score: 207.32)\n\nA stack-based buffer overflow condition is a condition where the buffer being overwritten is allocated on the stack (i.e., is a local variable or, rarely, a parameter to a function)....\n\n### 4. CWE-787: Out-of-bounds Write (Score: 72.43)\n\nThe product writes data past the end, or before the beginning, of the intended buffer....\n\n### 5. CWE-912: Hidden Functionality (Score: 69.48)\n\nThe product contains functionality that is not documented, not part of the specification, and not accessible through an interface or command sequence that is obvious to the product's users or administrators....\n\n## COMPONENT: 'PDF object loop in a pattern resource'\n\nRelevant CWEs for this COMPONENT:\n\n### 1. CWE-674: Uncontrolled Recursion (Score: 308.53)\n\nThe product does not properly control the amount of recursion that takes place,  consuming excessive resources, such as allocated memory or the program stack....\n\n### 2. CWE-835: Loop with Unreachable Exit Condition ('Infinite Loop') (Score: 231.39)\n\nThe product contains an iteration or loop with an exit condition that cannot be reached, i.e., an infinite loop....\n\n### 3. CWE-834: Excessive Iteration (Score: 182.62)\n\nThe product performs an iteration or loop without sufficiently limiting the number of times that the loop is executed....\n\n### 4. CWE-1265: Unintended Reentrant Invocation of Non-reentrant Code Via Nested Calls (Score: 85.28)\n\nDuring execution of non-reentrant code, the product performs a call that unintentionally produces a nested invocation of the non-reentrant code....\n\n### 5. CWE-1046: Creation of Immutable Text Using String Concatenation (Score: 77.94)\n\nThe product creates an immutable text string using string concatenation operations....\n\n\n    # Analysis Instructions\n    1. For each keyphrase, identify the most appropriate CWE(s) that represent the weakness.\n    2. Consider how the different keyphrases might relate to each other in the vulnerability chain.\n    3. Provide a final determination of primary CWE(s) and any secondary CWEs.\n    4. Format your response using the standard analysis template.\n\n    Please analyze how these different weaknesses interact and provide a comprehensive CWE classification.\n    "
  },
  "retrieval_time": 1.007781982421875
}