{
  "vulnerability_info": "VulnerabilityInfo(cve_id='CVE-2024-51551', description='**Default Credentail vulnerabilities** in ASPECT on Linux allows access to the product using publicly available **default credentials**. Affected products ABB ASPECT - Enterprise v3.07.02 NEXUS Series v3.07.02 MATRIX Series v3.07.02', key_phrases={'rootcause': ['Default Credentail vulnerabilities', 'default credentials'], 'weakness': '', 'impact': 'access to the product', 'vector': '', 'attacker': '', 'product': ['ABB ASPECT', 'Enterprise', 'NEXUS Series', 'MATRIX Series'], 'version': 'v3.07.02', 'component': ''}, reference_content='UNRELATED', similar_info={'cwe_distribution': {95: {'cwe_counts': defaultdict(<class 'int'>, {'CWE-193': 1}), 'total_samples': 1, 'distribution': [{'cwes': ['CWE-193'], 'frequency': 1, 'proportion': 1.0}]}, 90: {'cwe_counts': defaultdict(<class 'int'>, {'CWE-193': 1}), 'total_samples': 1, 'distribution': [{'cwes': ['CWE-193'], 'frequency': 1, 'proportion': 1.0}]}, 85: {'cwe_counts': defaultdict(<class 'int'>, {'CWE-193': 1}), 'total_samples': 1, 'distribution': [{'cwes': ['CWE-193'], 'frequency': 1, 'proportion': 1.0}]}, 80: {'cwe_counts': defaultdict(<class 'int'>, {'CWE-193': 1}), 'total_samples': 1, 'distribution': [{'cwes': ['CWE-193'], 'frequency': 1, 'proportion': 1.0}]}, 75: {'cwe_counts': defaultdict(<class 'int'>, {'CWE-193': 1, 'CWE-1393': 1, 'CWE-521': 1}), 'total_samples': 2, 'distribution': [{'cwes': ['CWE-193'], 'frequency': 1, 'proportion': 0.5}, {'cwes': ['CWE-1393', 'CWE-521'], 'frequency': 1, 'proportion': 0.5}]}, 70: {'cwe_counts': defaultdict(<class 'int'>, {'CWE-193': 1}), 'total_samples': 3, 'distribution': [{'cwes': [], 'frequency': 2, 'proportion': 0.667}, {'cwes': ['CWE-193'], 'frequency': 1, 'proportion': 0.333}]}}, 'cwe_consensus': 'CWE-193', 'similarity_stats': {'thresholds': [95, 90, 85, 80, 75, 70], 'total_samples_by_threshold': {95: 1, 90: 1, 85: 1, 80: 1, 75: 2, 70: 3}, 'top_cwes_by_threshold': {95: [('CWE-193', 1)], 90: [('CWE-193', 1)], 85: [('CWE-193', 1)], 80: [('CWE-193', 1)], 75: [('CWE-193', 1), ('CWE-1393', 1), ('CWE-521', 1)], 70: [('CWE-193', 1)]}}, 'raw_matches': [{'similarity': 95, 'cwes': ['193'], 'total': 1, 'frequency': 1, 'proportion': 1.0}, {'similarity': 90, 'cwes': ['193'], 'total': 1, 'frequency': 1, 'proportion': 1.0}, {'similarity': 85, 'cwes': ['193'], 'total': 1, 'frequency': 1, 'proportion': 1.0}, {'similarity': 80, 'cwes': ['193'], 'total': 1, 'frequency': 1, 'proportion': 1.0}, {'similarity': 75, 'cwes': ['193'], 'total': 2, 'frequency': 1, 'proportion': 0.5}, {'similarity': 75, 'cwes': ['1393', '521'], 'total': 2, 'frequency': 1, 'proportion': 0.5}, {'similarity': 70, 'cwes': [], 'total': 3, 'frequency': 2, 'proportion': 0.667}, {'similarity': 70, 'cwes': ['193'], 'total': 3, 'frequency': 1, 'proportion': 0.333}]}, similarity_summary=SimilarityInsight(consensus_cwe='CWE-193', top_cwes=[('CWE-193', 6), ('CWE-1393', 1), ('CWE-521', 1)], confidence_levels={'high': [], 'medium': [], 'low': []}, total_samples=9), analysis='', analysis_with_relationships='', criticism='', resolution='', relevant_cwes=[{'metadata': {'doc_id': '1392', 'name': 'Use of Default Credentials', 'source': 'sparse', 'original_content': 'The product uses default credentials (such as passwords or cryptographic keys) for potentially critical functionality.', 'keyphrase_sources': [{'id': 'rootcause:default credentials', 'keyphrase': 'default credentials', 'type': 'rootcause'}]}, 'similarity': np.float64(200.9675279180109)}, {'metadata': {'doc_id': '306', 'name': 'Missing Authentication for Critical Function', 'source': 'sparse', 'original_content': 'The product does not perform any authentication for functionality that requires a provable user identity or consumes a significant amount of resources.', 'keyphrase_sources': [{'id': 'rootcause:Default Credentail vulnerabilities', 'keyphrase': 'Default Credentail vulnerabilities', 'type': 'rootcause'}, {'id': 'rootcause:default credentials', 'keyphrase': 'default credentials', 'type': 'rootcause'}, {'id': 'impact:access to the product', 'keyphrase': 'access to the product', 'type': 'impact'}, {'id': 'product:Enterprise', 'keyphrase': 'Enterprise', 'type': 'product'}, {'id': 'product:NEXUS Series', 'keyphrase': 'NEXUS Series', 'type': 'product'}]}, 'similarity': np.float64(199.9667496138257)}, {'metadata': {'doc_id': '321', 'name': 'Use of Hard-coded Cryptographic Key', 'source': 'sparse', 'original_content': 'The use of a hard-coded cryptographic key significantly increases the possibility that encrypted data may be recovered.', 'keyphrase_sources': [{'id': 'rootcause:Default Credentail vulnerabilities', 'keyphrase': 'Default Credentail vulnerabilities', 'type': 'rootcause'}, {'id': 'rootcause:default credentials', 'keyphrase': 'default credentials', 'type': 'rootcause'}, {'id': 'impact:access to the product', 'keyphrase': 'access to the product', 'type': 'impact'}, {'id': 'product:Enterprise', 'keyphrase': 'Enterprise', 'type': 'product'}, {'id': 'product:NEXUS Series', 'keyphrase': 'NEXUS Series', 'type': 'product'}, {'id': 'product:MATRIX Series', 'keyphrase': 'MATRIX Series', 'type': 'product'}, {'id': 'version:v3.07.02', 'keyphrase': 'v3.07.02', 'type': 'version'}]}, 'similarity': np.float64(198.56982495265794)}, {'metadata': {'doc_id': '20', 'name': 'Improper Input Validation', 'source': 'sparse', 'original_content': 'The product receives input or data, but it does\\n        not validate or incorrectly validates that the input has the\\n        properties that are required to process the data safely and\\n        correctly.', 'keyphrase_sources': [{'id': 'rootcause:Default Credentail vulnerabilities', 'keyphrase': 'Default Credentail vulnerabilities', 'type': 'rootcause'}, {'id': 'product:ABB ASPECT', 'keyphrase': 'ABB ASPECT', 'type': 'product'}, {'id': 'product:Enterprise', 'keyphrase': 'Enterprise', 'type': 'product'}, {'id': 'product:NEXUS Series', 'keyphrase': 'NEXUS Series', 'type': 'product'}, {'id': 'product:MATRIX Series', 'keyphrase': 'MATRIX Series', 'type': 'product'}]}, 'similarity': np.float64(192.03650738883965)}, {'metadata': {'doc_id': '1391', 'name': 'Use of Weak Credentials', 'source': 'sparse', 'original_content': 'The product uses weak credentials (such as a default key or hard-coded password) that can be calculated, derived, reused, or guessed by an attacker.', 'keyphrase_sources': [{'id': 'rootcause:Default Credentail vulnerabilities', 'keyphrase': 'Default Credentail vulnerabilities', 'type': 'rootcause'}, {'id': 'rootcause:default credentials', 'keyphrase': 'default credentials', 'type': 'rootcause'}, {'id': 'version:v3.07.02', 'keyphrase': 'v3.07.02', 'type': 'version'}]}, 'similarity': np.float64(191.65123331603994)}, {'metadata': {'doc_id': '1393', 'name': 'Use of Default Password', 'source': 'sparse', 'original_content': 'The product uses default passwords for potentially critical functionality.', 'keyphrase_sources': [{'id': 'rootcause:Default Credentail vulnerabilities', 'keyphrase': 'Default Credentail vulnerabilities', 'type': 'rootcause'}, {'id': 'rootcause:default credentials', 'keyphrase': 'default credentials', 'type': 'rootcause'}, {'id': 'impact:access to the product', 'keyphrase': 'access to the product', 'type': 'impact'}, {'id': 'product:ABB ASPECT', 'keyphrase': 'ABB ASPECT', 'type': 'product'}, {'id': 'product:Enterprise', 'keyphrase': 'Enterprise', 'type': 'product'}]}, 'similarity': np.float64(191.17373715724887)}, {'metadata': {'doc_id': '294', 'name': 'Authentication Bypass by Capture-replay', 'source': 'sparse', 'original_content': 'A capture-replay flaw exists when the design of the product makes it possible for a malicious user to sniff network traffic and bypass authentication by replaying it to the server in question to the same effect as the original message (or with minor changes).', 'keyphrase_sources': [{'id': 'impact:access to the product', 'keyphrase': 'access to the product', 'type': 'impact'}, {'id': 'product:ABB ASPECT', 'keyphrase': 'ABB ASPECT', 'type': 'product'}, {'id': 'product:Enterprise', 'keyphrase': 'Enterprise', 'type': 'product'}, {'id': 'product:NEXUS Series', 'keyphrase': 'NEXUS Series', 'type': 'product'}, {'id': 'product:MATRIX Series', 'keyphrase': 'MATRIX Series', 'type': 'product'}, {'id': 'version:v3.07.02', 'keyphrase': 'v3.07.02', 'type': 'version'}]}, 'similarity': np.float64(87.57811522409186)}, {'metadata': {'doc_id': '345', 'name': 'Insufficient Verification of Data Authenticity', 'source': 'sparse', 'original_content': 'The product does not sufficiently verify the origin or authenticity of data, in a way that causes it to accept invalid data.', 'keyphrase_sources': [{'id': 'impact:access to the product', 'keyphrase': 'access to the product', 'type': 'impact'}, {'id': 'product:ABB ASPECT', 'keyphrase': 'ABB ASPECT', 'type': 'product'}, {'id': 'product:NEXUS Series', 'keyphrase': 'NEXUS Series', 'type': 'product'}, {'id': 'product:MATRIX Series', 'keyphrase': 'MATRIX Series', 'type': 'product'}, {'id': 'version:v3.07.02', 'keyphrase': 'v3.07.02', 'type': 'version'}]}, 'similarity': np.float64(80.9196184305201)}, {'metadata': {'doc_id': '36', 'name': 'Absolute Path Traversal', 'source': 'sparse', 'original_content': 'The product uses external input to construct a pathname that should be within a restricted directory, but it does not properly neutralize absolute path sequences such as \"/abs/path\" that can resolve to a location that is outside of that directory.', 'keyphrase_sources': [{'id': 'version:v3.07.02', 'keyphrase': 'v3.07.02', 'type': 'version'}]}, 'similarity': np.float64(73.66908544078234)}, {'metadata': {'doc_id': '257', 'name': 'Storing Passwords in a Recoverable Format', 'source': 'sparse', 'original_content': 'The storage of passwords in a recoverable format makes them subject to password reuse attacks by malicious users. In fact, it should be noted that recoverable encrypted passwords provide no significant benefit over plaintext passwords since they are subject not only to reuse by malicious attackers but also by malicious insiders. If a system administrator can recover a password directly, or use a brute force search on the available information, the administrator can use the password on other accounts.', 'keyphrase_sources': [{'id': 'product:ABB ASPECT', 'keyphrase': 'ABB ASPECT', 'type': 'product'}]}, 'similarity': np.float64(64.9447973191311)}, {'metadata': {'doc_id': '290', 'name': 'Authentication Bypass by Spoofing', 'source': 'sparse', 'original_content': 'This attack-focused weakness is caused by incorrectly implemented authentication schemes that are subject to spoofing attacks.', 'keyphrase_sources': [{'id': 'product:MATRIX Series', 'keyphrase': 'MATRIX Series', 'type': 'product'}]}, 'similarity': np.float64(63.97897205354502)}], identified_cwes={'analyzer': [], 'critic_additional': []})",
  "retrieval_results": {
    "has_multiple_keyphrases": true,
    "keyphrase_cwe_sets": {
      "rootcause:Default Credentail vulnerabilities": {
        "keyphrase": "Default Credentail vulnerabilities",
        "type": "rootcause",
        "cwes": [
          {
            "metadata": {
              "doc_id": "306",
              "name": "Missing Authentication for Critical Function",
              "source": "sparse",
              "original_content": "The product does not perform any authentication for functionality that requires a provable user identity or consumes a significant amount of resources.",
              "keyphrase_sources": [
                {
                  "id": "rootcause:Default Credentail vulnerabilities",
                  "keyphrase": "Default Credentail vulnerabilities",
                  "type": "rootcause"
                },
                {
                  "id": "rootcause:default credentials",
                  "keyphrase": "default credentials",
                  "type": "rootcause"
                },
                {
                  "id": "impact:access to the product",
                  "keyphrase": "access to the product",
                  "type": "impact"
                },
                {
                  "id": "product:Enterprise",
                  "keyphrase": "Enterprise",
                  "type": "product"
                },
                {
                  "id": "product:NEXUS Series",
                  "keyphrase": "NEXUS Series",
                  "type": "product"
                }
              ]
            },
            "similarity": 199.9667496138257
          },
          {
            "metadata": {
              "doc_id": "321",
              "name": "Use of Hard-coded Cryptographic Key",
              "source": "sparse",
              "original_content": "The use of a hard-coded cryptographic key significantly increases the possibility that encrypted data may be recovered.",
              "keyphrase_sources": [
                {
                  "id": "rootcause:Default Credentail vulnerabilities",
                  "keyphrase": "Default Credentail vulnerabilities",
                  "type": "rootcause"
                },
                {
                  "id": "rootcause:default credentials",
                  "keyphrase": "default credentials",
                  "type": "rootcause"
                },
                {
                  "id": "impact:access to the product",
                  "keyphrase": "access to the product",
                  "type": "impact"
                },
                {
                  "id": "product:Enterprise",
                  "keyphrase": "Enterprise",
                  "type": "product"
                },
                {
                  "id": "product:NEXUS Series",
                  "keyphrase": "NEXUS Series",
                  "type": "product"
                },
                {
                  "id": "product:MATRIX Series",
                  "keyphrase": "MATRIX Series",
                  "type": "product"
                },
                {
                  "id": "version:v3.07.02",
                  "keyphrase": "v3.07.02",
                  "type": "version"
                }
              ]
            },
            "similarity": 198.56982495265794
          },
          {
            "metadata": {
              "doc_id": "20",
              "name": "Improper Input Validation",
              "source": "sparse",
              "original_content": "The product receives input or data, but it does\n        not validate or incorrectly validates that the input has the\n        properties that are required to process the data safely and\n        correctly.",
              "keyphrase_sources": [
                {
                  "id": "rootcause:Default Credentail vulnerabilities",
                  "keyphrase": "Default Credentail vulnerabilities",
                  "type": "rootcause"
                },
                {
                  "id": "product:ABB ASPECT",
                  "keyphrase": "ABB ASPECT",
                  "type": "product"
                },
                {
                  "id": "product:Enterprise",
                  "keyphrase": "Enterprise",
                  "type": "product"
                },
                {
                  "id": "product:NEXUS Series",
                  "keyphrase": "NEXUS Series",
                  "type": "product"
                },
                {
                  "id": "product:MATRIX Series",
                  "keyphrase": "MATRIX Series",
                  "type": "product"
                }
              ]
            },
            "similarity": 192.03650738883965
          },
          {
            "metadata": {
              "doc_id": "1391",
              "name": "Use of Weak Credentials",
              "source": "sparse",
              "original_content": "The product uses weak credentials (such as a default key or hard-coded password) that can be calculated, derived, reused, or guessed by an attacker.",
              "keyphrase_sources": [
                {
                  "id": "rootcause:Default Credentail vulnerabilities",
                  "keyphrase": "Default Credentail vulnerabilities",
                  "type": "rootcause"
                },
                {
                  "id": "rootcause:default credentials",
                  "keyphrase": "default credentials",
                  "type": "rootcause"
                },
                {
                  "id": "version:v3.07.02",
                  "keyphrase": "v3.07.02",
                  "type": "version"
                }
              ]
            },
            "similarity": 191.65123331603994
          },
          {
            "metadata": {
              "doc_id": "1393",
              "name": "Use of Default Password",
              "source": "sparse",
              "original_content": "The product uses default passwords for potentially critical functionality.",
              "keyphrase_sources": [
                {
                  "id": "rootcause:Default Credentail vulnerabilities",
                  "keyphrase": "Default Credentail vulnerabilities",
                  "type": "rootcause"
                },
                {
                  "id": "rootcause:default credentials",
                  "keyphrase": "default credentials",
                  "type": "rootcause"
                },
                {
                  "id": "impact:access to the product",
                  "keyphrase": "access to the product",
                  "type": "impact"
                },
                {
                  "id": "product:ABB ASPECT",
                  "keyphrase": "ABB ASPECT",
                  "type": "product"
                },
                {
                  "id": "product:Enterprise",
                  "keyphrase": "Enterprise",
                  "type": "product"
                }
              ]
            },
            "similarity": 191.17373715724887
          }
        ]
      },
      "rootcause:default credentials": {
        "keyphrase": "default credentials",
        "type": "rootcause",
        "cwes": [
          {
            "metadata": {
              "doc_id": "1391",
              "name": "Use of Weak Credentials",
              "source": "sparse",
              "original_content": "The product uses weak credentials (such as a default key or hard-coded password) that can be calculated, derived, reused, or guessed by an attacker."
            },
            "similarity": 215.9965701993151
          },
          {
            "metadata": {
              "doc_id": "1393",
              "name": "Use of Default Password",
              "source": "sparse",
              "original_content": "The product uses default passwords for potentially critical functionality."
            },
            "similarity": 212.70931527085563
          },
          {
            "metadata": {
              "doc_id": "321",
              "name": "Use of Hard-coded Cryptographic Key",
              "source": "sparse",
              "original_content": "The use of a hard-coded cryptographic key significantly increases the possibility that encrypted data may be recovered."
            },
            "similarity": 210.69588174109563
          },
          {
            "metadata": {
              "doc_id": "306",
              "name": "Missing Authentication for Critical Function",
              "source": "sparse",
              "original_content": "The product does not perform any authentication for functionality that requires a provable user identity or consumes a significant amount of resources."
            },
            "similarity": 205.18532426143958
          },
          {
            "metadata": {
              "doc_id": "1392",
              "name": "Use of Default Credentials",
              "source": "sparse",
              "original_content": "The product uses default credentials (such as passwords or cryptographic keys) for potentially critical functionality.",
              "keyphrase_sources": [
                {
                  "id": "rootcause:default credentials",
                  "keyphrase": "default credentials",
                  "type": "rootcause"
                }
              ]
            },
            "similarity": 200.9675279180109
          }
        ]
      },
      "impact:access to the product": {
        "keyphrase": "access to the product",
        "type": "impact",
        "cwes": [
          {
            "metadata": {
              "doc_id": "294",
              "name": "Authentication Bypass by Capture-replay",
              "source": "sparse",
              "original_content": "A capture-replay flaw exists when the design of the product makes it possible for a malicious user to sniff network traffic and bypass authentication by replaying it to the server in question to the same effect as the original message (or with minor changes).",
              "keyphrase_sources": [
                {
                  "id": "impact:access to the product",
                  "keyphrase": "access to the product",
                  "type": "impact"
                },
                {
                  "id": "product:ABB ASPECT",
                  "keyphrase": "ABB ASPECT",
                  "type": "product"
                },
                {
                  "id": "product:Enterprise",
                  "keyphrase": "Enterprise",
                  "type": "product"
                },
                {
                  "id": "product:NEXUS Series",
                  "keyphrase": "NEXUS Series",
                  "type": "product"
                },
                {
                  "id": "product:MATRIX Series",
                  "keyphrase": "MATRIX Series",
                  "type": "product"
                },
                {
                  "id": "version:v3.07.02",
                  "keyphrase": "v3.07.02",
                  "type": "version"
                }
              ]
            },
            "similarity": 87.57811522409186
          },
          {
            "metadata": {
              "doc_id": "306",
              "name": "Missing Authentication for Critical Function",
              "source": "sparse",
              "original_content": "The product does not perform any authentication for functionality that requires a provable user identity or consumes a significant amount of resources."
            },
            "similarity": 83.29760168872117
          },
          {
            "metadata": {
              "doc_id": "1393",
              "name": "Use of Default Password",
              "source": "sparse",
              "original_content": "The product uses default passwords for potentially critical functionality."
            },
            "similarity": 82.2050948258042
          },
          {
            "metadata": {
              "doc_id": "321",
              "name": "Use of Hard-coded Cryptographic Key",
              "source": "sparse",
              "original_content": "The use of a hard-coded cryptographic key significantly increases the possibility that encrypted data may be recovered."
            },
            "similarity": 81.11450887007096
          },
          {
            "metadata": {
              "doc_id": "345",
              "name": "Insufficient Verification of Data Authenticity",
              "source": "sparse",
              "original_content": "The product does not sufficiently verify the origin or authenticity of data, in a way that causes it to accept invalid data.",
              "keyphrase_sources": [
                {
                  "id": "impact:access to the product",
                  "keyphrase": "access to the product",
                  "type": "impact"
                },
                {
                  "id": "product:ABB ASPECT",
                  "keyphrase": "ABB ASPECT",
                  "type": "product"
                },
                {
                  "id": "product:NEXUS Series",
                  "keyphrase": "NEXUS Series",
                  "type": "product"
                },
                {
                  "id": "product:MATRIX Series",
                  "keyphrase": "MATRIX Series",
                  "type": "product"
                },
                {
                  "id": "version:v3.07.02",
                  "keyphrase": "v3.07.02",
                  "type": "version"
                }
              ]
            },
            "similarity": 80.9196184305201
          }
        ]
      },
      "product:ABB ASPECT": {
        "keyphrase": "ABB ASPECT",
        "type": "product",
        "cwes": [
          {
            "metadata": {
              "doc_id": "1393",
              "name": "Use of Default Password",
              "source": "sparse",
              "original_content": "The product uses default passwords for potentially critical functionality."
            },
            "similarity": 66.24745275840024
          },
          {
            "metadata": {
              "doc_id": "257",
              "name": "Storing Passwords in a Recoverable Format",
              "source": "sparse",
              "original_content": "The storage of passwords in a recoverable format makes them subject to password reuse attacks by malicious users. In fact, it should be noted that recoverable encrypted passwords provide no significant benefit over plaintext passwords since they are subject not only to reuse by malicious attackers but also by malicious insiders. If a system administrator can recover a password directly, or use a brute force search on the available information, the administrator can use the password on other accounts.",
              "keyphrase_sources": [
                {
                  "id": "product:ABB ASPECT",
                  "keyphrase": "ABB ASPECT",
                  "type": "product"
                }
              ]
            },
            "similarity": 64.9447973191311
          },
          {
            "metadata": {
              "doc_id": "294",
              "name": "Authentication Bypass by Capture-replay",
              "source": "sparse",
              "original_content": "A capture-replay flaw exists when the design of the product makes it possible for a malicious user to sniff network traffic and bypass authentication by replaying it to the server in question to the same effect as the original message (or with minor changes)."
            },
            "similarity": 63.55920814845858
          },
          {
            "metadata": {
              "doc_id": "20",
              "name": "Improper Input Validation",
              "source": "sparse",
              "original_content": "The product receives input or data, but it does\n        not validate or incorrectly validates that the input has the\n        properties that are required to process the data safely and\n        correctly."
            },
            "similarity": 59.28662316284374
          },
          {
            "metadata": {
              "doc_id": "345",
              "name": "Insufficient Verification of Data Authenticity",
              "source": "sparse",
              "original_content": "The product does not sufficiently verify the origin or authenticity of data, in a way that causes it to accept invalid data."
            },
            "similarity": 59.26488880202853
          }
        ]
      },
      "product:Enterprise": {
        "keyphrase": "Enterprise",
        "type": "product",
        "cwes": [
          {
            "metadata": {
              "doc_id": "294",
              "name": "Authentication Bypass by Capture-replay",
              "source": "sparse",
              "original_content": "A capture-replay flaw exists when the design of the product makes it possible for a malicious user to sniff network traffic and bypass authentication by replaying it to the server in question to the same effect as the original message (or with minor changes)."
            },
            "similarity": 63.55920814845858
          },
          {
            "metadata": {
              "doc_id": "306",
              "name": "Missing Authentication for Critical Function",
              "source": "sparse",
              "original_content": "The product does not perform any authentication for functionality that requires a provable user identity or consumes a significant amount of resources."
            },
            "similarity": 63.02091578788732
          },
          {
            "metadata": {
              "doc_id": "1393",
              "name": "Use of Default Password",
              "source": "sparse",
              "original_content": "The product uses default passwords for potentially critical functionality."
            },
            "similarity": 61.307748352287156
          },
          {
            "metadata": {
              "doc_id": "20",
              "name": "Improper Input Validation",
              "source": "sparse",
              "original_content": "The product receives input or data, but it does\n        not validate or incorrectly validates that the input has the\n        properties that are required to process the data safely and\n        correctly."
            },
            "similarity": 60.71681976273739
          },
          {
            "metadata": {
              "doc_id": "321",
              "name": "Use of Hard-coded Cryptographic Key",
              "source": "sparse",
              "original_content": "The use of a hard-coded cryptographic key significantly increases the possibility that encrypted data may be recovered."
            },
            "similarity": 60.44597375727822
          }
        ]
      },
      "product:NEXUS Series": {
        "keyphrase": "NEXUS Series",
        "type": "product",
        "cwes": [
          {
            "metadata": {
              "doc_id": "294",
              "name": "Authentication Bypass by Capture-replay",
              "source": "sparse",
              "original_content": "A capture-replay flaw exists when the design of the product makes it possible for a malicious user to sniff network traffic and bypass authentication by replaying it to the server in question to the same effect as the original message (or with minor changes)."
            },
            "similarity": 72.78805504571916
          },
          {
            "metadata": {
              "doc_id": "345",
              "name": "Insufficient Verification of Data Authenticity",
              "source": "sparse",
              "original_content": "The product does not sufficiently verify the origin or authenticity of data, in a way that causes it to accept invalid data."
            },
            "similarity": 68.29954327442032
          },
          {
            "metadata": {
              "doc_id": "306",
              "name": "Missing Authentication for Critical Function",
              "source": "sparse",
              "original_content": "The product does not perform any authentication for functionality that requires a provable user identity or consumes a significant amount of resources."
            },
            "similarity": 64.94649389342588
          },
          {
            "metadata": {
              "doc_id": "321",
              "name": "Use of Hard-coded Cryptographic Key",
              "source": "sparse",
              "original_content": "The use of a hard-coded cryptographic key significantly increases the possibility that encrypted data may be recovered."
            },
            "similarity": 62.901979243814246
          },
          {
            "metadata": {
              "doc_id": "20",
              "name": "Improper Input Validation",
              "source": "sparse",
              "original_content": "The product receives input or data, but it does\n        not validate or incorrectly validates that the input has the\n        properties that are required to process the data safely and\n        correctly."
            },
            "similarity": 62.59446590493286
          }
        ]
      },
      "product:MATRIX Series": {
        "keyphrase": "MATRIX Series",
        "type": "product",
        "cwes": [
          {
            "metadata": {
              "doc_id": "294",
              "name": "Authentication Bypass by Capture-replay",
              "source": "sparse",
              "original_content": "A capture-replay flaw exists when the design of the product makes it possible for a malicious user to sniff network traffic and bypass authentication by replaying it to the server in question to the same effect as the original message (or with minor changes)."
            },
            "similarity": 72.78805504571916
          },
          {
            "metadata": {
              "doc_id": "345",
              "name": "Insufficient Verification of Data Authenticity",
              "source": "sparse",
              "original_content": "The product does not sufficiently verify the origin or authenticity of data, in a way that causes it to accept invalid data."
            },
            "similarity": 68.29954327442032
          },
          {
            "metadata": {
              "doc_id": "20",
              "name": "Improper Input Validation",
              "source": "sparse",
              "original_content": "The product receives input or data, but it does\n        not validate or incorrectly validates that the input has the\n        properties that are required to process the data safely and\n        correctly."
            },
            "similarity": 64.04926232551232
          },
          {
            "metadata": {
              "doc_id": "290",
              "name": "Authentication Bypass by Spoofing",
              "source": "sparse",
              "original_content": "This attack-focused weakness is caused by incorrectly implemented authentication schemes that are subject to spoofing attacks.",
              "keyphrase_sources": [
                {
                  "id": "product:MATRIX Series",
                  "keyphrase": "MATRIX Series",
                  "type": "product"
                }
              ]
            },
            "similarity": 63.97897205354502
          },
          {
            "metadata": {
              "doc_id": "321",
              "name": "Use of Hard-coded Cryptographic Key",
              "source": "sparse",
              "original_content": "The use of a hard-coded cryptographic key significantly increases the possibility that encrypted data may be recovered."
            },
            "similarity": 62.901979243814246
          }
        ]
      },
      "version:v3.07.02": {
        "keyphrase": "v3.07.02",
        "type": "version",
        "cwes": [
          {
            "metadata": {
              "doc_id": "294",
              "name": "Authentication Bypass by Capture-replay",
              "source": "sparse",
              "original_content": "A capture-replay flaw exists when the design of the product makes it possible for a malicious user to sniff network traffic and bypass authentication by replaying it to the server in question to the same effect as the original message (or with minor changes)."
            },
            "similarity": 85.16728694994809
          },
          {
            "metadata": {
              "doc_id": "345",
              "name": "Insufficient Verification of Data Authenticity",
              "source": "sparse",
              "original_content": "The product does not sufficiently verify the origin or authenticity of data, in a way that causes it to accept invalid data."
            },
            "similarity": 78.23820918728198
          },
          {
            "metadata": {
              "doc_id": "1391",
              "name": "Use of Weak Credentials",
              "source": "sparse",
              "original_content": "The product uses weak credentials (such as a default key or hard-coded password) that can be calculated, derived, reused, or guessed by an attacker."
            },
            "similarity": 73.80245150184203
          },
          {
            "metadata": {
              "doc_id": "36",
              "name": "Absolute Path Traversal",
              "source": "sparse",
              "original_content": "The product uses external input to construct a pathname that should be within a restricted directory, but it does not properly neutralize absolute path sequences such as \"/abs/path\" that can resolve to a location that is outside of that directory.",
              "keyphrase_sources": [
                {
                  "id": "version:v3.07.02",
                  "keyphrase": "v3.07.02",
                  "type": "version"
                }
              ]
            },
            "similarity": 73.66908544078234
          },
          {
            "metadata": {
              "doc_id": "321",
              "name": "Use of Hard-coded Cryptographic Key",
              "source": "sparse",
              "original_content": "The use of a hard-coded cryptographic key significantly increases the possibility that encrypted data may be recovered."
            },
            "similarity": 72.6033687935298
          }
        ]
      }
    },
    "keyphrase_mapping": {
      "306": [
        {
          "id": "rootcause:Default Credentail vulnerabilities",
          "keyphrase": "Default Credentail vulnerabilities",
          "type": "rootcause"
        },
        {
          "id": "rootcause:default credentials",
          "keyphrase": "default credentials",
          "type": "rootcause"
        },
        {
          "id": "impact:access to the product",
          "keyphrase": "access to the product",
          "type": "impact"
        },
        {
          "id": "product:Enterprise",
          "keyphrase": "Enterprise",
          "type": "product"
        },
        {
          "id": "product:NEXUS Series",
          "keyphrase": "NEXUS Series",
          "type": "product"
        }
      ],
      "321": [
        {
          "id": "rootcause:Default Credentail vulnerabilities",
          "keyphrase": "Default Credentail vulnerabilities",
          "type": "rootcause"
        },
        {
          "id": "rootcause:default credentials",
          "keyphrase": "default credentials",
          "type": "rootcause"
        },
        {
          "id": "impact:access to the product",
          "keyphrase": "access to the product",
          "type": "impact"
        },
        {
          "id": "product:Enterprise",
          "keyphrase": "Enterprise",
          "type": "product"
        },
        {
          "id": "product:NEXUS Series",
          "keyphrase": "NEXUS Series",
          "type": "product"
        },
        {
          "id": "product:MATRIX Series",
          "keyphrase": "MATRIX Series",
          "type": "product"
        },
        {
          "id": "version:v3.07.02",
          "keyphrase": "v3.07.02",
          "type": "version"
        }
      ],
      "20": [
        {
          "id": "rootcause:Default Credentail vulnerabilities",
          "keyphrase": "Default Credentail vulnerabilities",
          "type": "rootcause"
        },
        {
          "id": "product:ABB ASPECT",
          "keyphrase": "ABB ASPECT",
          "type": "product"
        },
        {
          "id": "product:Enterprise",
          "keyphrase": "Enterprise",
          "type": "product"
        },
        {
          "id": "product:NEXUS Series",
          "keyphrase": "NEXUS Series",
          "type": "product"
        },
        {
          "id": "product:MATRIX Series",
          "keyphrase": "MATRIX Series",
          "type": "product"
        }
      ],
      "1391": [
        {
          "id": "rootcause:Default Credentail vulnerabilities",
          "keyphrase": "Default Credentail vulnerabilities",
          "type": "rootcause"
        },
        {
          "id": "rootcause:default credentials",
          "keyphrase": "default credentials",
          "type": "rootcause"
        },
        {
          "id": "version:v3.07.02",
          "keyphrase": "v3.07.02",
          "type": "version"
        }
      ],
      "1393": [
        {
          "id": "rootcause:Default Credentail vulnerabilities",
          "keyphrase": "Default Credentail vulnerabilities",
          "type": "rootcause"
        },
        {
          "id": "rootcause:default credentials",
          "keyphrase": "default credentials",
          "type": "rootcause"
        },
        {
          "id": "impact:access to the product",
          "keyphrase": "access to the product",
          "type": "impact"
        },
        {
          "id": "product:ABB ASPECT",
          "keyphrase": "ABB ASPECT",
          "type": "product"
        },
        {
          "id": "product:Enterprise",
          "keyphrase": "Enterprise",
          "type": "product"
        }
      ],
      "1392": [
        {
          "id": "rootcause:default credentials",
          "keyphrase": "default credentials",
          "type": "rootcause"
        }
      ],
      "294": [
        {
          "id": "impact:access to the product",
          "keyphrase": "access to the product",
          "type": "impact"
        },
        {
          "id": "product:ABB ASPECT",
          "keyphrase": "ABB ASPECT",
          "type": "product"
        },
        {
          "id": "product:Enterprise",
          "keyphrase": "Enterprise",
          "type": "product"
        },
        {
          "id": "product:NEXUS Series",
          "keyphrase": "NEXUS Series",
          "type": "product"
        },
        {
          "id": "product:MATRIX Series",
          "keyphrase": "MATRIX Series",
          "type": "product"
        },
        {
          "id": "version:v3.07.02",
          "keyphrase": "v3.07.02",
          "type": "version"
        }
      ],
      "345": [
        {
          "id": "impact:access to the product",
          "keyphrase": "access to the product",
          "type": "impact"
        },
        {
          "id": "product:ABB ASPECT",
          "keyphrase": "ABB ASPECT",
          "type": "product"
        },
        {
          "id": "product:NEXUS Series",
          "keyphrase": "NEXUS Series",
          "type": "product"
        },
        {
          "id": "product:MATRIX Series",
          "keyphrase": "MATRIX Series",
          "type": "product"
        },
        {
          "id": "version:v3.07.02",
          "keyphrase": "v3.07.02",
          "type": "version"
        }
      ],
      "257": [
        {
          "id": "product:ABB ASPECT",
          "keyphrase": "ABB ASPECT",
          "type": "product"
        }
      ],
      "290": [
        {
          "id": "product:MATRIX Series",
          "keyphrase": "MATRIX Series",
          "type": "product"
        }
      ],
      "36": [
        {
          "id": "version:v3.07.02",
          "keyphrase": "v3.07.02",
          "type": "version"
        }
      ]
    },
    "relevant_cwes": [
      {
        "metadata": {
          "doc_id": "1392",
          "name": "Use of Default Credentials",
          "source": "sparse",
          "original_content": "The product uses default credentials (such as passwords or cryptographic keys) for potentially critical functionality.",
          "keyphrase_sources": [
            {
              "id": "rootcause:default credentials",
              "keyphrase": "default credentials",
              "type": "rootcause"
            }
          ]
        },
        "similarity": 200.9675279180109
      },
      {
        "metadata": {
          "doc_id": "306",
          "name": "Missing Authentication for Critical Function",
          "source": "sparse",
          "original_content": "The product does not perform any authentication for functionality that requires a provable user identity or consumes a significant amount of resources.",
          "keyphrase_sources": [
            {
              "id": "rootcause:Default Credentail vulnerabilities",
              "keyphrase": "Default Credentail vulnerabilities",
              "type": "rootcause"
            },
            {
              "id": "rootcause:default credentials",
              "keyphrase": "default credentials",
              "type": "rootcause"
            },
            {
              "id": "impact:access to the product",
              "keyphrase": "access to the product",
              "type": "impact"
            },
            {
              "id": "product:Enterprise",
              "keyphrase": "Enterprise",
              "type": "product"
            },
            {
              "id": "product:NEXUS Series",
              "keyphrase": "NEXUS Series",
              "type": "product"
            }
          ]
        },
        "similarity": 199.9667496138257
      },
      {
        "metadata": {
          "doc_id": "321",
          "name": "Use of Hard-coded Cryptographic Key",
          "source": "sparse",
          "original_content": "The use of a hard-coded cryptographic key significantly increases the possibility that encrypted data may be recovered.",
          "keyphrase_sources": [
            {
              "id": "rootcause:Default Credentail vulnerabilities",
              "keyphrase": "Default Credentail vulnerabilities",
              "type": "rootcause"
            },
            {
              "id": "rootcause:default credentials",
              "keyphrase": "default credentials",
              "type": "rootcause"
            },
            {
              "id": "impact:access to the product",
              "keyphrase": "access to the product",
              "type": "impact"
            },
            {
              "id": "product:Enterprise",
              "keyphrase": "Enterprise",
              "type": "product"
            },
            {
              "id": "product:NEXUS Series",
              "keyphrase": "NEXUS Series",
              "type": "product"
            },
            {
              "id": "product:MATRIX Series",
              "keyphrase": "MATRIX Series",
              "type": "product"
            },
            {
              "id": "version:v3.07.02",
              "keyphrase": "v3.07.02",
              "type": "version"
            }
          ]
        },
        "similarity": 198.56982495265794
      },
      {
        "metadata": {
          "doc_id": "20",
          "name": "Improper Input Validation",
          "source": "sparse",
          "original_content": "The product receives input or data, but it does\n        not validate or incorrectly validates that the input has the\n        properties that are required to process the data safely and\n        correctly.",
          "keyphrase_sources": [
            {
              "id": "rootcause:Default Credentail vulnerabilities",
              "keyphrase": "Default Credentail vulnerabilities",
              "type": "rootcause"
            },
            {
              "id": "product:ABB ASPECT",
              "keyphrase": "ABB ASPECT",
              "type": "product"
            },
            {
              "id": "product:Enterprise",
              "keyphrase": "Enterprise",
              "type": "product"
            },
            {
              "id": "product:NEXUS Series",
              "keyphrase": "NEXUS Series",
              "type": "product"
            },
            {
              "id": "product:MATRIX Series",
              "keyphrase": "MATRIX Series",
              "type": "product"
            }
          ]
        },
        "similarity": 192.03650738883965
      },
      {
        "metadata": {
          "doc_id": "1391",
          "name": "Use of Weak Credentials",
          "source": "sparse",
          "original_content": "The product uses weak credentials (such as a default key or hard-coded password) that can be calculated, derived, reused, or guessed by an attacker.",
          "keyphrase_sources": [
            {
              "id": "rootcause:Default Credentail vulnerabilities",
              "keyphrase": "Default Credentail vulnerabilities",
              "type": "rootcause"
            },
            {
              "id": "rootcause:default credentials",
              "keyphrase": "default credentials",
              "type": "rootcause"
            },
            {
              "id": "version:v3.07.02",
              "keyphrase": "v3.07.02",
              "type": "version"
            }
          ]
        },
        "similarity": 191.65123331603994
      },
      {
        "metadata": {
          "doc_id": "1393",
          "name": "Use of Default Password",
          "source": "sparse",
          "original_content": "The product uses default passwords for potentially critical functionality.",
          "keyphrase_sources": [
            {
              "id": "rootcause:Default Credentail vulnerabilities",
              "keyphrase": "Default Credentail vulnerabilities",
              "type": "rootcause"
            },
            {
              "id": "rootcause:default credentials",
              "keyphrase": "default credentials",
              "type": "rootcause"
            },
            {
              "id": "impact:access to the product",
              "keyphrase": "access to the product",
              "type": "impact"
            },
            {
              "id": "product:ABB ASPECT",
              "keyphrase": "ABB ASPECT",
              "type": "product"
            },
            {
              "id": "product:Enterprise",
              "keyphrase": "Enterprise",
              "type": "product"
            }
          ]
        },
        "similarity": 191.17373715724887
      },
      {
        "metadata": {
          "doc_id": "294",
          "name": "Authentication Bypass by Capture-replay",
          "source": "sparse",
          "original_content": "A capture-replay flaw exists when the design of the product makes it possible for a malicious user to sniff network traffic and bypass authentication by replaying it to the server in question to the same effect as the original message (or with minor changes).",
          "keyphrase_sources": [
            {
              "id": "impact:access to the product",
              "keyphrase": "access to the product",
              "type": "impact"
            },
            {
              "id": "product:ABB ASPECT",
              "keyphrase": "ABB ASPECT",
              "type": "product"
            },
            {
              "id": "product:Enterprise",
              "keyphrase": "Enterprise",
              "type": "product"
            },
            {
              "id": "product:NEXUS Series",
              "keyphrase": "NEXUS Series",
              "type": "product"
            },
            {
              "id": "product:MATRIX Series",
              "keyphrase": "MATRIX Series",
              "type": "product"
            },
            {
              "id": "version:v3.07.02",
              "keyphrase": "v3.07.02",
              "type": "version"
            }
          ]
        },
        "similarity": 87.57811522409186
      },
      {
        "metadata": {
          "doc_id": "345",
          "name": "Insufficient Verification of Data Authenticity",
          "source": "sparse",
          "original_content": "The product does not sufficiently verify the origin or authenticity of data, in a way that causes it to accept invalid data.",
          "keyphrase_sources": [
            {
              "id": "impact:access to the product",
              "keyphrase": "access to the product",
              "type": "impact"
            },
            {
              "id": "product:ABB ASPECT",
              "keyphrase": "ABB ASPECT",
              "type": "product"
            },
            {
              "id": "product:NEXUS Series",
              "keyphrase": "NEXUS Series",
              "type": "product"
            },
            {
              "id": "product:MATRIX Series",
              "keyphrase": "MATRIX Series",
              "type": "product"
            },
            {
              "id": "version:v3.07.02",
              "keyphrase": "v3.07.02",
              "type": "version"
            }
          ]
        },
        "similarity": 80.9196184305201
      },
      {
        "metadata": {
          "doc_id": "36",
          "name": "Absolute Path Traversal",
          "source": "sparse",
          "original_content": "The product uses external input to construct a pathname that should be within a restricted directory, but it does not properly neutralize absolute path sequences such as \"/abs/path\" that can resolve to a location that is outside of that directory.",
          "keyphrase_sources": [
            {
              "id": "version:v3.07.02",
              "keyphrase": "v3.07.02",
              "type": "version"
            }
          ]
        },
        "similarity": 73.66908544078234
      },
      {
        "metadata": {
          "doc_id": "257",
          "name": "Storing Passwords in a Recoverable Format",
          "source": "sparse",
          "original_content": "The storage of passwords in a recoverable format makes them subject to password reuse attacks by malicious users. In fact, it should be noted that recoverable encrypted passwords provide no significant benefit over plaintext passwords since they are subject not only to reuse by malicious attackers but also by malicious insiders. If a system administrator can recover a password directly, or use a brute force search on the available information, the administrator can use the password on other accounts.",
          "keyphrase_sources": [
            {
              "id": "product:ABB ASPECT",
              "keyphrase": "ABB ASPECT",
              "type": "product"
            }
          ]
        },
        "similarity": 64.9447973191311
      },
      {
        "metadata": {
          "doc_id": "290",
          "name": "Authentication Bypass by Spoofing",
          "source": "sparse",
          "original_content": "This attack-focused weakness is caused by incorrectly implemented authentication schemes that are subject to spoofing attacks.",
          "keyphrase_sources": [
            {
              "id": "product:MATRIX Series",
              "keyphrase": "MATRIX Series",
              "type": "product"
            }
          ]
        },
        "similarity": 63.97897205354502
      }
    ],
    "enhanced_query": "# Vulnerability Description\n\n    **Default Credentail vulnerabilities** in ASPECT on Linux allows access to the product using publicly available **default credentials**. Affected products ABB ASPECT - Enterprise v3.07.02 NEXUS Series v3.07.02 MATRIX Series v3.07.02\n\n    # Keyphrase-Specific CWE Analysis\n    This vulnerability contains multiple keyphrases that may map to different CWEs. \n    Please analyze each keyphrase separately and determine the most appropriate CWE(s) for each.\n\n    ## ROOTCAUSE: 'default credentials'\n\nRelevant CWEs for this ROOTCAUSE:\n\n### 1. CWE-1392: Use of Default Credentials (Score: 200.97)\n\nThe product uses default credentials (such as passwords or cryptographic keys) for potentially critical functionality....\n\n### 2. CWE-306: Missing Authentication for Critical Function (Score: 199.97)\n\nThe product does not perform any authentication for functionality that requires a provable user identity or consumes a significant amount of resources....\n\n### 3. CWE-321: Use of Hard-coded Cryptographic Key (Score: 198.57)\n\nThe use of a hard-coded cryptographic key significantly increases the possibility that encrypted data may be recovered....\n\n### 4. CWE-1391: Use of Weak Credentials (Score: 191.65)\n\nThe product uses weak credentials (such as a default key or hard-coded password) that can be calculated, derived, reused, or guessed by an attacker....\n\n### 5. CWE-1393: Use of Default Password (Score: 191.17)\n\nThe product uses default passwords for potentially critical functionality....\n\n## ROOTCAUSE: 'Default Credentail vulnerabilities'\n\nRelevant CWEs for this ROOTCAUSE:\n\n### 1. CWE-306: Missing Authentication for Critical Function (Score: 199.97)\n\nThe product does not perform any authentication for functionality that requires a provable user identity or consumes a significant amount of resources....\n\n### 2. CWE-321: Use of Hard-coded Cryptographic Key (Score: 198.57)\n\nThe use of a hard-coded cryptographic key significantly increases the possibility that encrypted data may be recovered....\n\n### 3. CWE-20: Improper Input Validation (Score: 192.04)\n\nThe product receives input or data, but it does\n        not validate or incorrectly validates that the input has the\n        properties that are required to process the data safely and\n        correctly....\n\n### 4. CWE-1391: Use of Weak Credentials (Score: 191.65)\n\nThe product uses weak credentials (such as a default key or hard-coded password) that can be calculated, derived, reused, or guessed by an attacker....\n\n### 5. CWE-1393: Use of Default Password (Score: 191.17)\n\nThe product uses default passwords for potentially critical functionality....\n\n## IMPACT: 'access to the product'\n\nRelevant CWEs for this IMPACT:\n\n### 1. CWE-306: Missing Authentication for Critical Function (Score: 199.97)\n\nThe product does not perform any authentication for functionality that requires a provable user identity or consumes a significant amount of resources....\n\n### 2. CWE-321: Use of Hard-coded Cryptographic Key (Score: 198.57)\n\nThe use of a hard-coded cryptographic key significantly increases the possibility that encrypted data may be recovered....\n\n### 3. CWE-1393: Use of Default Password (Score: 191.17)\n\nThe product uses default passwords for potentially critical functionality....\n\n### 4. CWE-294: Authentication Bypass by Capture-replay (Score: 87.58)\n\nA capture-replay flaw exists when the design of the product makes it possible for a malicious user to sniff network traffic and bypass authentication by replaying it to the server in question to the same effect as the original message (or with minor changes)....\n\n### 5. CWE-345: Insufficient Verification of Data Authenticity (Score: 80.92)\n\nThe product does not sufficiently verify the origin or authenticity of data, in a way that causes it to accept invalid data....\n\n## PRODUCT: 'Enterprise'\n\nRelevant CWEs for this PRODUCT:\n\n### 1. CWE-306: Missing Authentication for Critical Function (Score: 199.97)\n\nThe product does not perform any authentication for functionality that requires a provable user identity or consumes a significant amount of resources....\n\n### 2. CWE-321: Use of Hard-coded Cryptographic Key (Score: 198.57)\n\nThe use of a hard-coded cryptographic key significantly increases the possibility that encrypted data may be recovered....\n\n### 3. CWE-20: Improper Input Validation (Score: 192.04)\n\nThe product receives input or data, but it does\n        not validate or incorrectly validates that the input has the\n        properties that are required to process the data safely and\n        correctly....\n\n### 4. CWE-1393: Use of Default Password (Score: 191.17)\n\nThe product uses default passwords for potentially critical functionality....\n\n### 5. CWE-294: Authentication Bypass by Capture-replay (Score: 87.58)\n\nA capture-replay flaw exists when the design of the product makes it possible for a malicious user to sniff network traffic and bypass authentication by replaying it to the server in question to the same effect as the original message (or with minor changes)....\n\n## PRODUCT: 'NEXUS Series'\n\nRelevant CWEs for this PRODUCT:\n\n### 1. CWE-306: Missing Authentication for Critical Function (Score: 199.97)\n\nThe product does not perform any authentication for functionality that requires a provable user identity or consumes a significant amount of resources....\n\n### 2. CWE-321: Use of Hard-coded Cryptographic Key (Score: 198.57)\n\nThe use of a hard-coded cryptographic key significantly increases the possibility that encrypted data may be recovered....\n\n### 3. CWE-20: Improper Input Validation (Score: 192.04)\n\nThe product receives input or data, but it does\n        not validate or incorrectly validates that the input has the\n        properties that are required to process the data safely and\n        correctly....\n\n### 4. CWE-294: Authentication Bypass by Capture-replay (Score: 87.58)\n\nA capture-replay flaw exists when the design of the product makes it possible for a malicious user to sniff network traffic and bypass authentication by replaying it to the server in question to the same effect as the original message (or with minor changes)....\n\n### 5. CWE-345: Insufficient Verification of Data Authenticity (Score: 80.92)\n\nThe product does not sufficiently verify the origin or authenticity of data, in a way that causes it to accept invalid data....\n\n## PRODUCT: 'MATRIX Series'\n\nRelevant CWEs for this PRODUCT:\n\n### 1. CWE-321: Use of Hard-coded Cryptographic Key (Score: 198.57)\n\nThe use of a hard-coded cryptographic key significantly increases the possibility that encrypted data may be recovered....\n\n### 2. CWE-20: Improper Input Validation (Score: 192.04)\n\nThe product receives input or data, but it does\n        not validate or incorrectly validates that the input has the\n        properties that are required to process the data safely and\n        correctly....\n\n### 3. CWE-294: Authentication Bypass by Capture-replay (Score: 87.58)\n\nA capture-replay flaw exists when the design of the product makes it possible for a malicious user to sniff network traffic and bypass authentication by replaying it to the server in question to the same effect as the original message (or with minor changes)....\n\n### 4. CWE-345: Insufficient Verification of Data Authenticity (Score: 80.92)\n\nThe product does not sufficiently verify the origin or authenticity of data, in a way that causes it to accept invalid data....\n\n### 5. CWE-290: Authentication Bypass by Spoofing (Score: 63.98)\n\nThis attack-focused weakness is caused by incorrectly implemented authentication schemes that are subject to spoofing attacks....\n\n## VERSION: 'v3.07.02'\n\nRelevant CWEs for this VERSION:\n\n### 1. CWE-321: Use of Hard-coded Cryptographic Key (Score: 198.57)\n\nThe use of a hard-coded cryptographic key significantly increases the possibility that encrypted data may be recovered....\n\n### 2. CWE-1391: Use of Weak Credentials (Score: 191.65)\n\nThe product uses weak credentials (such as a default key or hard-coded password) that can be calculated, derived, reused, or guessed by an attacker....\n\n### 3. CWE-294: Authentication Bypass by Capture-replay (Score: 87.58)\n\nA capture-replay flaw exists when the design of the product makes it possible for a malicious user to sniff network traffic and bypass authentication by replaying it to the server in question to the same effect as the original message (or with minor changes)....\n\n### 4. CWE-345: Insufficient Verification of Data Authenticity (Score: 80.92)\n\nThe product does not sufficiently verify the origin or authenticity of data, in a way that causes it to accept invalid data....\n\n### 5. CWE-36: Absolute Path Traversal (Score: 73.67)\n\nThe product uses external input to construct a pathname that should be within a restricted directory, but it does not properly neutralize absolute path sequences such as \"/abs/path\" that can resolve to a location that is outside of that directory....\n\n## PRODUCT: 'ABB ASPECT'\n\nRelevant CWEs for this PRODUCT:\n\n### 1. CWE-20: Improper Input Validation (Score: 192.04)\n\nThe product receives input or data, but it does\n        not validate or incorrectly validates that the input has the\n        properties that are required to process the data safely and\n        correctly....\n\n### 2. CWE-1393: Use of Default Password (Score: 191.17)\n\nThe product uses default passwords for potentially critical functionality....\n\n### 3. CWE-294: Authentication Bypass by Capture-replay (Score: 87.58)\n\nA capture-replay flaw exists when the design of the product makes it possible for a malicious user to sniff network traffic and bypass authentication by replaying it to the server in question to the same effect as the original message (or with minor changes)....\n\n### 4. CWE-345: Insufficient Verification of Data Authenticity (Score: 80.92)\n\nThe product does not sufficiently verify the origin or authenticity of data, in a way that causes it to accept invalid data....\n\n### 5. CWE-257: Storing Passwords in a Recoverable Format (Score: 64.94)\n\nThe storage of passwords in a recoverable format makes them subject to password reuse attacks by malicious users. In fact, it should be noted that recoverable encrypted passwords provide no significant benefit over plaintext passwords since they are subject not only to reuse by malicious attackers b...\n\n\n    # Analysis Instructions\n    1. For each keyphrase, identify the most appropriate CWE(s) that represent the weakness.\n    2. Consider how the different keyphrases might relate to each other in the vulnerability chain.\n    3. Provide a final determination of primary CWE(s) and any secondary CWEs.\n    4. Format your response using the standard analysis template.\n\n    Please analyze how these different weaknesses interact and provide a comprehensive CWE classification.\n    "
  },
  "retrieval_time": 1.1793708801269531
}