{
  "cve_id": "CVE-2024-20078",
  "description": "In venc, there is a possible **out of bounds write** due to **type confusion**. This could lead to local escalation of privilege with System execution privileges needed. User interaction is not needed for exploitation. Patch ID ALPS08737250 Issue ID MSV-1452.",
  "key_phrases": {
    "rootcause": "type confusion",
    "weakness": "out of bounds write",
    "impact": "local escalation of privilege",
    "vector": "",
    "attacker": "",
    "product": "",
    "version": "",
    "component": "venc"
  },
  "reference_content": "- **Root cause of vulnerability**: Type confusion in the `venc` component leading to an out-of-bounds write.\n- **Weaknesses/vulnerabilities present**: Type confusion (CWE-843) leading to an out-of-bounds write.\n- **Impact of exploitation**: Local escalation of privilege.\n- **Attack vectors**: Local, a malicious actor must already have System privileges to exploit the vulnerability.\n- **Required attacker capabilities/position**: The attacker needs to have already obtained System privilege on the affected device. User interaction is not required for exploitation.",
  "similar_info": {
    "cwe_distribution": {},
    "cwe_consensus": "",
    "similarity_stats": {
      "thresholds": [],
      "total_samples_by_threshold": {},
      "top_cwes_by_threshold": {}
    }
  },
  "similarity_summary": {
    "consensus_cwe": "",
    "top_cwes": [],
    "confidence_levels": {},
    "total_samples": 0
  },
  "analysis": "# Summary\n| CWE ID | CWE Name | Confidence | CWE Abstraction Level | CWE Vulnerability Mapping Label | CWE-Vulnerability Mapping Notes |\n|---|---|---|---|---|---|\n| CWE-843 | Access of Resource Using Incompatible Type ('Type Confusion') | 0.9 | Base | Primary | Allowed |\n| CWE-787 | Out-of-bounds Write | 0.8 | Base | Secondary | Allowed |\n\n## Evidence and Confidence\n\n*   **Confidence Score:** 0.9\n*   **Evidence Strength:** HIGH\n\n## Relationship Analysis\nThe primary weakness is **type confusion** (CWE-843), which leads to an **out-of-bounds write** (CWE-787). CWE-787 is a child of CWE-119 (Improper Restriction of Operations within the Bounds of a Memory Buffer), indicating a more general class of buffer-related errors. The relationship CANPRECEDE from CWE-120 (Buffer Copy without Checking Size of Input) to CWE-787 highlights a common path where insufficient size checking leads to out-of-bounds writes. Choosing CWE-843 as primary and CWE-787 as secondary captures both the root cause and the direct consequence.\n\n```mermaid\ngraph TD\n    cwe843[\"CWE-843: Access of Resource Using Incompatible Type ('Type Confusion')\"]\n    cwe787[\"CWE-787: Out-of-bounds Write\"]\n    cwe119[\"CWE-119: Improper Restriction of Operations within the Bounds of a Memory Buffer\"]\n\n    cwe787 -->|CHILDOF| cwe119\n    cwe843 -->|CANPRECEDE| cwe787\n\n    classDef primary fill:#f96,stroke:#333,stroke-width:2px\n    classDef secondary fill:#69f,stroke:#333\n    classDef tertiary fill:#9e9,stroke:#333\n    class cwe843 primary\n    class cwe787 secondary\n    class cwe119 tertiary\n```\n\n## Vulnerability Chain\nThe vulnerability chain starts with **type confusion** (CWE-843) in the `venc` component. This **type confusion** leads to an **out-of-bounds write** (CWE-787). The impact of the **out-of-bounds write** is local escalation of privilege.\n\n## Summary of Analysis\nThe primary root cause of the vulnerability is **type confusion**, which results in an **out-of-bounds write**. The vulnerability description clearly states \"**out of bounds write** due to **type confusion**.\" The evidence is strong, with supporting information in the \"Vulnerability Description Key Phrases\" and \"CVE Reference Links Content Summary.\" The retriever results also list CWE-843 and CWE-787 as highly relevant. The selection of CWE-843 as the primary cause and CWE-787 as a secondary weakness reflects the direct sequence of events. The abstraction levels are appropriate, with both CWEs at the Base level.\n\nCWEs considered but not used:\n\n*   CWE-266, CWE-274, CWE-280, CWE-267, CWE-269, CWE-285, CWE-863: These CWEs relate to incorrect privilege management or authorization, but the vulnerability description does not indicate any privilege or permission issues other than the final impact (escalation of privilege). The root cause is **type confusion** and the resulting **out-of-bounds write**, not a direct privilege management flaw.\n*   CWE-667: Improper Locking: The vulnerability description does not suggest any issues with concurrent execution or locking.\n*   CWE-404: Improper Resource Shutdown or Release: The vulnerability description does not suggest any issues with resource management.\n*   CWE-754, CWE-703: Improper Check for Unusual or Exceptional Conditions: While an **out-of-bounds write** could be considered an exceptional condition, these CWEs are too high-level and do not capture the specific nature of the vulnerability.\n*   CWE-131: Incorrect Calculation of Buffer Size: While it could lead to an out-of-bounds write, it isn't the root cause as it is **type confusion**.\n*   CWE-362: Concurrent Execution using Shared Resource with Improper Synchronization ('Race Condition'): There is no evidence of concurrency issues.\n*   CWE-1260, CWE-1257: Improper Handling of Overlap Between Protected Memory Ranges: There is no evidence of memory region overlap.\n*   CWE-250: Execution with Unnecessary Privileges: The issue is not about the program running with elevated privileges.\n*   CWE-123: Write-what-where Condition: While technically an out-of-bounds write allows writing to an arbitrary location, CWE-787 is a more direct and appropriate classification.\n*   CWE-306: Missing Authentication for Critical Function: No authentication issues are mentioned.\n*   CWE-191: Integer Underflow (Wrap or Wraparound): The vulnerability description does not indicate integer underflow issues.\n*   CWE-908: Use of Uninitialized Resource: The description doesn't mention this condition.\n*   CWE-223: Omission of Security-relevant Information: The description doesn't mention this condition.\n*   CWE-1021: Improper Restriction of Rendered UI Layers or Frames: The description doesn't mention this condition.",
  "analysis_with_relationships": "# Summary\n| CWE ID | CWE Name | Confidence | CWE Abstraction Level | CWE Vulnerability Mapping Label | CWE-Vulnerability Mapping Notes |\n|---|---|---|---|---|---|\n| CWE-843 | Access of Resource Using Incompatible Type ('Type Confusion') | 0.9 | Base | Primary | Allowed |\n| CWE-787 | Out-of-bounds Write | 0.8 | Base | Secondary | Allowed |\n\n## Evidence and Confidence\n\n*   **Confidence Score:** 0.9\n*   **Evidence Strength:** HIGH\n\n## Relationship Analysis\nThe primary weakness is **type confusion** (CWE-843), which leads to an **out-of-bounds write** (CWE-787). CWE-787 is a child of CWE-119 (Improper Restriction of Operations within the Bounds of a Memory Buffer), indicating a more general class of buffer-related errors. The relationship CANPRECEDE from CWE-120 (Buffer Copy without Checking Size of Input) to CWE-787 highlights a common path where insufficient size checking leads to out-of-bounds writes. Choosing CWE-843 as primary and CWE-787 as secondary captures both the root cause and the direct consequence.\n\n```mermaid\ngraph TD\n    cwe843[\"CWE-843: Access of Resource Using Incompatible Type ('Type Confusion')\"]\n    cwe787[\"CWE-787: Out-of-bounds Write\"]\n    cwe119[\"CWE-119: Improper Restriction of Operations within the Bounds of a Memory Buffer\"]\n\n    cwe787 -->|CHILDOF| cwe119\n    cwe843 -->|CANPRECEDE| cwe787\n\n    classDef primary fill:#f96,stroke:#333,stroke-width:2px\n    classDef secondary fill:#69f,stroke:#333\n    classDef tertiary fill:#9e9,stroke:#333\n    class cwe843 primary\n    class cwe787 secondary\n    class cwe119 tertiary\n```\n\n## Vulnerability Chain\nThe vulnerability chain starts with **type confusion** (CWE-843) in the `venc` component. This **type confusion** leads to an **out-of-bounds write** (CWE-787). The impact of the **out-of-bounds write** is local escalation of privilege.\n\n## Summary of Analysis\nThe primary root cause of the vulnerability is **type confusion**, which results in an **out-of-bounds write**. The vulnerability description clearly states \"**out of bounds write** due to **type confusion**.\" The evidence is strong, with supporting information in the \"Vulnerability Description Key Phrases\" and \"CVE Reference Links Content Summary.\" The retriever results also list CWE-843 and CWE-787 as highly relevant. The selection of CWE-843 as the primary cause and CWE-787 as a secondary weakness reflects the direct sequence of events. The abstraction levels are appropriate, with both CWEs at the Base level.\n\nCWEs considered but not used:\n\n*   CWE-266, CWE-274, CWE-280, CWE-267, CWE-269, CWE-285, CWE-863: These CWEs relate to incorrect privilege management or authorization, but the vulnerability description does not indicate any privilege or permission issues other than the final impact (escalation of privilege). The root cause is **type confusion** and the resulting **out-of-bounds write**, not a direct privilege management flaw.\n*   CWE-667: Improper Locking: The vulnerability description does not suggest any issues with concurrent execution or locking.\n*   CWE-404: Improper Resource Shutdown or Release: The vulnerability description does not suggest any issues with resource management.\n*   CWE-754, CWE-703: Improper Check for Unusual or Exceptional Conditions: While an **out-of-bounds write** could be considered an exceptional condition, these CWEs are too high-level and do not capture the specific nature of the vulnerability.\n*   CWE-131: Incorrect Calculation of Buffer Size: While it could lead to an out-of-bounds write, it isn't the root cause as it is **type confusion**.\n*   CWE-362: Concurrent Execution using Shared Resource with Improper Synchronization ('Race Condition'): There is no evidence of concurrency issues.\n*   CWE-1260, CWE-1257: Improper Handling of Overlap Between Protected Memory Ranges: There is no evidence of memory region overlap.\n*   CWE-250: Execution with Unnecessary Privileges: The issue is not about the program running with elevated privileges.\n*   CWE-123: Write-what-where Condition: While technically an out-of-bounds write allows writing to an arbitrary location, CWE-787 is a more direct and appropriate classification.\n*   CWE-306: Missing Authentication for Critical Function: No authentication issues are mentioned.\n*   CWE-191: Integer Underflow (Wrap or Wraparound): The vulnerability description does not indicate integer underflow issues.\n*   CWE-908: Use of Uninitialized Resource: The description doesn't mention this condition.\n*   CWE-223: Omission of Security-relevant Information: The description doesn't mention this condition.\n*   CWE-1021: Improper Restriction of Rendered UI Layers or Frames: The description doesn't mention this condition.\n\n\n## CWE Relationship Analysis\n\nCurrent CWEs represent these abstraction levels: .\n\n\n### Vulnerability Chain Analysis\n\n**Chain starting from CWE-274:**\n- 274 (Improper Handling of Insufficient Privileges) - ROOT\n\n\n**Chain starting from CWE-131:**\n- 131 (Incorrect Calculation of Buffer Size) - ROOT\n\n\n\n### CWE Relationship Diagram\n\n```mermaid\ngraph TD\n    classDef primary fill:#f96,stroke:#333,stroke-width:2px\n    classDef secondary fill:#69f,stroke:#333\n    classDef tertiary fill:#9e9,stroke:#333\n```",
  "criticism": "",
  "resolution": "",
  "relevant_cwes": [
    {
      "metadata": {
        "doc_id": "843",
        "name": "Access of Resource Using Incompatible Type ('Type Confusion')",
        "source": "alternate_terms",
        "original_matched_text": "AlternateTerms: Object Type Confusion",
        "match_reason": "phrase_in_term_whole_phrase"
      },
      "similarity": 700.0,
      "alternate_term_match": true
    },
    {
      "metadata": {
        "doc_id": "131",
        "name": "Incorrect Calculation of Buffer Size",
        "source": "sparse"
      },
      "similarity": 331.29513346814934
    },
    {
      "metadata": {
        "doc_id": "908",
        "name": "Use of Uninitialized Resource",
        "source": "sparse"
      },
      "similarity": 326.2106210698265
    },
    {
      "metadata": {
        "doc_id": "667",
        "name": "Improper Locking",
        "source": "sparse"
      },
      "similarity": 310.17338257880107
    },
    {
      "metadata": {
        "doc_id": "191",
        "name": "Integer Underflow (Wrap or Wraparound)",
        "source": "sparse"
      },
      "similarity": 300.97025661005745
    },
    {
      "metadata": {
        "doc_id": "223",
        "name": "Omission of Security-relevant Information",
        "source": "sparse"
      },
      "similarity": 296.9547440513781
    },
    {
      "metadata": {
        "doc_id": "362",
        "name": "Concurrent Execution using Shared Resource with Improper Synchronization ('Race Condition')",
        "source": "sparse"
      },
      "similarity": 295.52609324210755
    },
    {
      "metadata": {
        "doc_id": "1021",
        "name": "Improper Restriction of Rendered UI Layers or Frames",
        "source": "sparse"
      },
      "similarity": 286.8893182470156
    },
    {
      "metadata": {
        "doc_id": "1260",
        "name": "Improper Handling of Overlap Between Protected Memory Ranges",
        "type": "Base",
        "original_content": "The product allows address regions to overlap, which can result in the bypassing of intended memory protection.",
        "keyphrase_source": "weakness:out of bounds write",
        "source": "dense",
        "mapping_notes": {
          "usage": "Allowed",
          "rationale": "This CWE entry is at the Base level of abstraction, which is a preferred level of abstraction for mapping to the root causes of vulnerabilities.",
          "comments": "Carefully read both the name and description to ensure that this mapping is an appropriate fit. Do not try to 'force' a mapping to a lower-level Base/Variant simply to comply with this preferred level of abstraction.",
          "reasons": [
            "Acceptable-Use"
          ]
        },
        "score_info": {
          "retrievers": [
            "dense",
            "graph"
          ],
          "retriever_count": 2,
          "normalized_scores": {
            "dense": 0.6032118706933759,
            "graph": 2.532213220641517
          }
        }
      },
      "similarity": 0.6032118706933759
    },
    {
      "doc_id": "787",
      "text": "CWE-787: Out-of-bounds Write",
      "score": 2.2100000000000004,
      "metadata": {
        "doc_id": "787",
        "name": "Out-of-bounds Write",
        "type": "base",
        "original_content": "CWE-787: Out-of-bounds Write",
        "relationships": [
          {
            "source_id": "787",
            "target_id": "825",
            "label": "CANFOLLOW",
            "properties": {
              "view_id": "1000"
            }
          },
          {
            "source_id": "787",
            "target_id": "824",
            "label": "CANFOLLOW",
            "properties": {
              "view_id": "1000"
            }
          },
          {
            "source_id": "787",
            "target_id": "823",
            "label": "CANFOLLOW",
            "properties": {
              "view_id": "1000"
            }
          },
          {
            "source_id": "787",
            "target_id": "822",
            "label": "CANFOLLOW",
            "properties": {
              "view_id": "1000"
            }
          },
          {
            "source_id": "787",
            "target_id": "124",
            "label": "PARENTOF",
            "properties": {
              "view_id": "1000"
            }
          },
          {
            "source_id": "787",
            "target_id": "123",
            "label": "PARENTOF",
            "properties": {
              "ordinal": "Primary",
              "view_id": "1000"
            }
          },
          {
            "source_id": "787",
            "target_id": "122",
            "label": "PARENTOF",
            "properties": {
              "view_id": "1000"
            }
          },
          {
            "source_id": "787",
            "target_id": "121",
            "label": "PARENTOF",
            "properties": {
              "view_id": "1000"
            }
          },
          {
            "source_id": "787",
            "target_id": "119",
            "label": "CHILDOF",
            "properties": {
              "ordinal": "Primary",
              "view_id": "1340"
            }
          },
          {
            "source_id": "787",
            "target_id": "119",
            "label": "CHILDOF",
            "properties": {
              "ordinal": "Primary",
              "view_id": "1305"
            }
          },
          {
            "source_id": "787",
            "target_id": "119",
            "label": "CHILDOF",
            "properties": {
              "ordinal": "Primary",
              "view_id": "1003"
            }
          },
          {
            "source_id": "787",
            "target_id": "119",
            "label": "CHILDOF",
            "properties": {
              "ordinal": "Primary",
              "view_id": "1000"
            }
          },
          {
            "source_id": "825",
            "target_id": "787",
            "label": "CANPRECEDE",
            "properties": {
              "view_id": "1000"
            }
          },
          {
            "source_id": "824",
            "target_id": "787",
            "label": "CANPRECEDE",
            "properties": {
              "view_id": "1000"
            }
          },
          {
            "source_id": "823",
            "target_id": "787",
            "label": "CANPRECEDE",
            "properties": {
              "view_id": "1000"
            }
          },
          {
            "source_id": "822",
            "target_id": "787",
            "label": "CANPRECEDE",
            "properties": {
              "view_id": "1000"
            }
          },
          {
            "source_id": "124",
            "target_id": "787",
            "label": "CHILDOF",
            "properties": {
              "view_id": "1000"
            }
          },
          {
            "source_id": "123",
            "target_id": "787",
            "label": "CHILDOF",
            "properties": {
              "ordinal": "Primary",
              "view_id": "1000"
            }
          },
          {
            "source_id": "122",
            "target_id": "787",
            "label": "CHILDOF",
            "properties": {
              "view_id": "1000"
            }
          },
          {
            "source_id": "121",
            "target_id": "787",
            "label": "CHILDOF",
            "properties": {
              "view_id": "1000"
            }
          },
          {
            "source_id": "119",
            "target_id": "787",
            "label": "PARENTOF",
            "properties": {
              "ordinal": "Primary",
              "view_id": "1000"
            }
          }
        ],
        "score_components": {
          "relationship_chain": 1.0,
          "sequence_path": 1.0
        },
        "abstraction_factor": 1.3,
        "graph_path_info": {
          "path_types": [
            "relationship_chain",
            "vulnerability_sequence_forward"
          ],
          "best_paths": {
            "relationship_chain": {
              "path": [
                [
                  "823",
                  "787",
                  "CANPRECEDE"
                ]
              ],
              "score": 1.0,
              "type": "relationship_chain",
              "source": "823"
            },
            "vulnerability_sequence_forward": {
              "path": [
                [
                  "823",
                  "787",
                  "CANPRECEDE"
                ]
              ],
              "score": 1.0,
              "type": "vulnerability_sequence_forward",
              "source": "823"
            }
          }
        },
        "position": "after",
        "sources": [
          "graph"
        ],
        "source": "graph",
        "mapping_notes": {
          "usage": "Allowed",
          "rationale": "This CWE entry is at the Base level of abstraction, which is a preferred level of abstraction for mapping to the root causes of vulnerabilities.",
          "comments": "Carefully read both the name and description to ensure that this mapping is an appropriate fit. Do not try to 'force' a mapping to a lower-level Base/Variant simply to comply with this preferred level of abstraction.",
          "reasons": [
            "Acceptable-Use"
          ]
        },
        "score_info": {
          "retrievers": [
            "sparse",
            "graph"
          ],
          "retriever_count": 2,
          "normalized_scores": {
            "sparse": 277.4260802941657,
            "graph": 2.2100000000000004
          }
        }
      },
      "similarity": 2.2100000000000004
    }
  ],
  "identified_cwes": {
    "analyzer": [
      "CWE-274",
      "CWE-131",
      "CWE-787",
      "CWE-1257",
      "CWE-843",
      "CWE-269",
      "CWE-285",
      "CWE-123",
      "CWE-306",
      "CWE-191",
      "CWE-1021",
      "CWE-267",
      "CWE-266",
      "CWE-120",
      "CWE-1260",
      "CWE-863",
      "CWE-280",
      "CWE-667",
      "CWE-223",
      "CWE-703",
      "CWE-404",
      "CWE-362",
      "CWE-250",
      "CWE-119",
      "CWE-908",
      "CWE-754"
    ],
    "critic_additional": []
  },
  "keyphrase_cwe_mapping": {}
}