{
  "vulnerability_info": "VulnerabilityInfo(cve_id='CVE-2024-43683', description='URL Redirection to Untrusted Site (Open Redirect) vulnerability in Microchip TimeProvider 4100 allows **XSS** Through HTTP Headers.This issue affects TimeProvider 4100 from 1.0.', key_phrases={'rootcause': '', 'weakness': ['URL redirection to untrusted site', 'XSS'], 'impact': 'cross-site scripting', 'vector': 'HTTP headers', 'attacker': '', 'product': 'Microchip TimeProvider 4100', 'version': '1.0', 'component': ''}, reference_content='Based on the provided content, here\\'s an analysis of CVE-2024-43683:\\n\\n**1. Verification of Relevance to CVE-2024-43683**\\n\\n   - The provided content includes a section specifically titled \"**CVE-2024-43683: TimeProvider\u00ae 4100 Grandmaster Improper Verification of the Host Header**\" and it describes a vulnerability that matches the description for a host header injection/open redirect. This confirms that the content is **RELEVANT** to the specified CVE.\\n\\n**2. Extracted Vulnerability Information:**\\n\\n   - **Root Cause:** The web front-end of the TimeProvider\u00ae 4100 Grandmaster does not properly verify the `Host` header field in HTTP requests. This allows an attacker to inject a malicious host, leading to redirection.\\n\\n   - **Weaknesses/Vulnerabilities:**\\n      - **Improper Input Validation:** Lack of proper validation of the `Host` header.\\n      - **Open Redirection:** The vulnerability allows redirection to an arbitrary, untrusted site.\\n\\n   - **Impact of Exploitation:**\\n      - An attacker could redirect a logged-in user to an untrusted, potentially malicious, site. This can be used for phishing attacks.\\n\\n   - **Attack Vectors:**\\n      - Network-based attack via a crafted HTTP request targeting the web interface of the TimeProvider\u00ae 4100 Grandmaster.\\n        - The `Host` header is modified to a malicious domain.\\n   - **Required Attacker Capabilities/Position:**\\n      - The attacker needs to be able to send HTTP requests to the TimeProvider device\\'s web interface.\\n      - No specific privilege is needed by the attacker other than network access to the device.\\n\\n**3. Additional Details:**\\n  *   The content includes the following additional details:\\n      *   **Affected Product:** TimeProvider\u00ae 4100 Grandmaster\\n      *   **Affected Versions:** Firmware 1.0 through 2.4.7\\n      *   **CVSS Score:** 8.7 (CVSS:4.0/AV:N/AC:H/AT:P/PR:N/UI:P/VC:H/VI:H/VA:H/SC:N/SI:N/SA:H/R:U/V:C/RE:M/U:Amber)\\n       *   **Mitigation:** The document suggests:\\n             - Not exposing the web interface on the management port to untrusted networks.\\n             - Disabling the web interface completely for added security.\\n       *   **Acknowledgement:** The vulnerability was reported by a security research team: Armando Huesca Prida, Marco Negro, Antonio Carriero, Vito Pistillo, Davide Renna, Manuel Leone, Massimiliano Brolli and TIM Security Red Team Research\\n   * This information adds more context and details to the vulnerability compared to a standard CVE description.', similar_info={'cwe_distribution': {}, 'cwe_consensus': '', 'similarity_stats': {'thresholds': [], 'total_samples_by_threshold': {}, 'top_cwes_by_threshold': {}}}, similarity_summary=SimilarityInsight(consensus_cwe='', top_cwes=[], confidence_levels={}, total_samples=0), analysis='', analysis_with_relationships='', criticism='', resolution='', relevant_cwes=[{'metadata': {'doc_id': '601', 'name': \"URL Redirection to Untrusted Site ('Open Redirect')\", 'source': 'sparse', 'original_content': 'The web application accepts a user-controlled input that specifies a link to an external site, and uses that link in a redirect.', 'keyphrase_sources': [{'id': 'weakness:URL redirection to untrusted site', 'keyphrase': 'URL redirection to untrusted site', 'type': 'weakness'}, {'id': 'impact:cross-site scripting', 'keyphrase': 'cross-site scripting', 'type': 'impact'}, {'id': 'product:Microchip TimeProvider 4100', 'keyphrase': 'Microchip TimeProvider 4100', 'type': 'product'}, {'id': 'version:1.0', 'keyphrase': '1.0', 'type': 'version'}]}, 'similarity': np.float64(243.29977293515347)}, {'metadata': {'doc_id': '1022', 'name': 'Use of Web Link to Untrusted Target with window.opener Access', 'source': 'sparse', 'original_content': 'The web application produces links to untrusted external sites outside of its sphere of control, but it does not properly prevent the external site from modifying  security-critical properties of the window.opener object, such as the location property.', 'keyphrase_sources': [{'id': 'weakness:URL redirection to untrusted site', 'keyphrase': 'URL redirection to untrusted site', 'type': 'weakness'}, {'id': 'product:Microchip TimeProvider 4100', 'keyphrase': 'Microchip TimeProvider 4100', 'type': 'product'}, {'id': 'version:1.0', 'keyphrase': '1.0', 'type': 'version'}]}, 'similarity': np.float64(227.19506109674649)}, {'metadata': {'doc_id': '79', 'name': \"Improper Neutralization of Input During Web Page Generation ('Cross-site Scripting')\", 'source': 'sparse', 'original_content': 'The product does not neutralize or incorrectly neutralizes user-controllable input before it is placed in output that is used as a web page that is served to other users.', 'keyphrase_sources': [{'id': 'weakness:URL redirection to untrusted site', 'keyphrase': 'URL redirection to untrusted site', 'type': 'weakness'}, {'id': 'weakness:XSS', 'keyphrase': 'XSS', 'type': 'weakness'}, {'id': 'impact:cross-site scripting', 'keyphrase': 'cross-site scripting', 'type': 'impact'}, {'id': 'vector:HTTP headers', 'keyphrase': 'HTTP headers', 'type': 'vector'}, {'id': 'product:Microchip TimeProvider 4100', 'keyphrase': 'Microchip TimeProvider 4100', 'type': 'product'}, {'id': 'version:1.0', 'keyphrase': '1.0', 'type': 'version'}]}, 'similarity': np.float64(187.71895003241843)}, {'metadata': {'doc_id': '113', 'name': \"Improper Neutralization of CRLF Sequences in HTTP Headers ('HTTP Request/Response Splitting')\", 'source': 'sparse', 'original_content': 'The product receives data from an HTTP agent/component (e.g., web server, proxy, browser, etc.), but it does not neutralize or incorrectly neutralizes CR and LF characters before the data is included in outgoing HTTP headers.', 'keyphrase_sources': [{'id': 'weakness:URL redirection to untrusted site', 'keyphrase': 'URL redirection to untrusted site', 'type': 'weakness'}, {'id': 'weakness:XSS', 'keyphrase': 'XSS', 'type': 'weakness'}, {'id': 'vector:HTTP headers', 'keyphrase': 'HTTP headers', 'type': 'vector'}, {'id': 'product:Microchip TimeProvider 4100', 'keyphrase': 'Microchip TimeProvider 4100', 'type': 'product'}, {'id': 'version:1.0', 'keyphrase': '1.0', 'type': 'version'}]}, 'similarity': np.float64(185.0436462364794)}, {'metadata': {'doc_id': '352', 'name': 'Cross-Site Request Forgery (CSRF)', 'source': 'sparse', 'original_content': 'The web application does not, or can not, sufficiently verify whether a well-formed, valid, consistent request was intentionally provided by the user who submitted the request.', 'keyphrase_sources': [{'id': 'weakness:URL redirection to untrusted site', 'keyphrase': 'URL redirection to untrusted site', 'type': 'weakness'}, {'id': 'weakness:XSS', 'keyphrase': 'XSS', 'type': 'weakness'}, {'id': 'impact:cross-site scripting', 'keyphrase': 'cross-site scripting', 'type': 'impact'}]}, 'similarity': np.float64(175.47506341043038)}, {'metadata': {'doc_id': '1289', 'name': 'Improper Validation of Unsafe Equivalence in Input', 'source': 'sparse', 'original_content': 'The product receives an input value that is used as a resource identifier or other type of reference, but it does not validate or incorrectly validates that the input is equivalent to a potentially-unsafe value.', 'keyphrase_sources': [{'id': 'weakness:XSS', 'keyphrase': 'XSS', 'type': 'weakness'}]}, 'similarity': np.float64(119.36188841293169)}, {'metadata': {'doc_id': '80', 'name': 'Improper Neutralization of Script-Related HTML Tags in a Web Page (Basic XSS)', 'source': 'sparse', 'original_content': 'The product receives input from an upstream component, but it does not neutralize or incorrectly neutralizes special characters such as \"<\", \">\", and \"&\" that could be interpreted as web-scripting elements when they are sent to a downstream component that processes web pages.', 'keyphrase_sources': [{'id': 'weakness:XSS', 'keyphrase': 'XSS', 'type': 'weakness'}, {'id': 'impact:cross-site scripting', 'keyphrase': 'cross-site scripting', 'type': 'impact'}]}, 'similarity': np.float64(119.0316010071095)}, {'metadata': {'doc_id': '942', 'name': 'Permissive Cross-domain Policy with Untrusted Domains', 'source': 'sparse', 'original_content': 'The product uses a cross-domain policy file that includes domains that should not be trusted.', 'keyphrase_sources': [{'id': 'impact:cross-site scripting', 'keyphrase': 'cross-site scripting', 'type': 'impact'}]}, 'similarity': np.float64(60.19663797394678)}, {'metadata': {'doc_id': '212', 'name': 'Improper Removal of Sensitive Information Before Storage or Transfer', 'source': 'sparse', 'original_content': 'The product stores, transfers, or shares a resource that contains sensitive information, but it does not properly remove that information before the product makes the resource available to unauthorized actors.', 'keyphrase_sources': [{'id': 'vector:HTTP headers', 'keyphrase': 'HTTP headers', 'type': 'vector'}, {'id': 'version:1.0', 'keyphrase': '1.0', 'type': 'version'}]}, 'similarity': np.float64(55.7910725282934)}, {'metadata': {'doc_id': '444', 'name': \"Inconsistent Interpretation of HTTP Requests ('HTTP Request/Response Smuggling')\", 'source': 'sparse', 'original_content': 'The product acts as an intermediary HTTP agent\\n         (such as a proxy or firewall) in the data flow between two\\n         entities such as a client and server, but it does not\\n         interpret malformed HTTP requests or responses in ways that\\n         are consistent with how the messages will be processed by\\n         those entities that are at the ultimate destination.', 'keyphrase_sources': [{'id': 'vector:HTTP headers', 'keyphrase': 'HTTP headers', 'type': 'vector'}]}, 'similarity': np.float64(50.8150416242088)}, {'metadata': {'doc_id': '93', 'name': \"Improper Neutralization of CRLF Sequences ('CRLF Injection')\", 'source': 'sparse', 'original_content': 'The product uses CRLF (carriage return line feeds) as a special element, e.g. to separate lines or records, but it does not neutralize or incorrectly neutralizes CRLF sequences from inputs.', 'keyphrase_sources': [{'id': 'vector:HTTP headers', 'keyphrase': 'HTTP headers', 'type': 'vector'}]}, 'similarity': np.float64(48.68295861793428)}, {'metadata': {'doc_id': '696', 'name': 'Incorrect Behavior Order', 'source': 'sparse', 'original_content': 'The product performs multiple related behaviors, but the behaviors are performed in the wrong order in ways which may produce resultant weaknesses.', 'keyphrase_sources': [{'id': 'product:Microchip TimeProvider 4100', 'keyphrase': 'Microchip TimeProvider 4100', 'type': 'product'}]}, 'similarity': np.float64(45.843314058657484)}], identified_cwes={'analyzer': [], 'critic_additional': []})",
  "retrieval_results": {
    "has_multiple_keyphrases": true,
    "keyphrase_cwe_sets": {
      "weakness:URL redirection to untrusted site": {
        "keyphrase": "URL redirection to untrusted site",
        "type": "weakness",
        "cwes": [
          {
            "metadata": {
              "doc_id": "601",
              "name": "URL Redirection to Untrusted Site ('Open Redirect')",
              "source": "sparse",
              "original_content": "The web application accepts a user-controlled input that specifies a link to an external site, and uses that link in a redirect.",
              "keyphrase_sources": [
                {
                  "id": "weakness:URL redirection to untrusted site",
                  "keyphrase": "URL redirection to untrusted site",
                  "type": "weakness"
                },
                {
                  "id": "impact:cross-site scripting",
                  "keyphrase": "cross-site scripting",
                  "type": "impact"
                },
                {
                  "id": "product:Microchip TimeProvider 4100",
                  "keyphrase": "Microchip TimeProvider 4100",
                  "type": "product"
                },
                {
                  "id": "version:1.0",
                  "keyphrase": "1.0",
                  "type": "version"
                }
              ]
            },
            "similarity": 243.29977293515347
          },
          {
            "metadata": {
              "doc_id": "1022",
              "name": "Use of Web Link to Untrusted Target with window.opener Access",
              "source": "sparse",
              "original_content": "The web application produces links to untrusted external sites outside of its sphere of control, but it does not properly prevent the external site from modifying  security-critical properties of the window.opener object, such as the location property.",
              "keyphrase_sources": [
                {
                  "id": "weakness:URL redirection to untrusted site",
                  "keyphrase": "URL redirection to untrusted site",
                  "type": "weakness"
                },
                {
                  "id": "product:Microchip TimeProvider 4100",
                  "keyphrase": "Microchip TimeProvider 4100",
                  "type": "product"
                },
                {
                  "id": "version:1.0",
                  "keyphrase": "1.0",
                  "type": "version"
                }
              ]
            },
            "similarity": 227.19506109674649
          },
          {
            "metadata": {
              "doc_id": "79",
              "name": "Improper Neutralization of Input During Web Page Generation ('Cross-site Scripting')",
              "source": "sparse",
              "original_content": "The product does not neutralize or incorrectly neutralizes user-controllable input before it is placed in output that is used as a web page that is served to other users.",
              "keyphrase_sources": [
                {
                  "id": "weakness:URL redirection to untrusted site",
                  "keyphrase": "URL redirection to untrusted site",
                  "type": "weakness"
                },
                {
                  "id": "weakness:XSS",
                  "keyphrase": "XSS",
                  "type": "weakness"
                },
                {
                  "id": "impact:cross-site scripting",
                  "keyphrase": "cross-site scripting",
                  "type": "impact"
                },
                {
                  "id": "vector:HTTP headers",
                  "keyphrase": "HTTP headers",
                  "type": "vector"
                },
                {
                  "id": "product:Microchip TimeProvider 4100",
                  "keyphrase": "Microchip TimeProvider 4100",
                  "type": "product"
                },
                {
                  "id": "version:1.0",
                  "keyphrase": "1.0",
                  "type": "version"
                }
              ]
            },
            "similarity": 187.71895003241843
          },
          {
            "metadata": {
              "doc_id": "113",
              "name": "Improper Neutralization of CRLF Sequences in HTTP Headers ('HTTP Request/Response Splitting')",
              "source": "sparse",
              "original_content": "The product receives data from an HTTP agent/component (e.g., web server, proxy, browser, etc.), but it does not neutralize or incorrectly neutralizes CR and LF characters before the data is included in outgoing HTTP headers.",
              "keyphrase_sources": [
                {
                  "id": "weakness:URL redirection to untrusted site",
                  "keyphrase": "URL redirection to untrusted site",
                  "type": "weakness"
                },
                {
                  "id": "weakness:XSS",
                  "keyphrase": "XSS",
                  "type": "weakness"
                },
                {
                  "id": "vector:HTTP headers",
                  "keyphrase": "HTTP headers",
                  "type": "vector"
                },
                {
                  "id": "product:Microchip TimeProvider 4100",
                  "keyphrase": "Microchip TimeProvider 4100",
                  "type": "product"
                },
                {
                  "id": "version:1.0",
                  "keyphrase": "1.0",
                  "type": "version"
                }
              ]
            },
            "similarity": 185.0436462364794
          },
          {
            "metadata": {
              "doc_id": "352",
              "name": "Cross-Site Request Forgery (CSRF)",
              "source": "sparse",
              "original_content": "The web application does not, or can not, sufficiently verify whether a well-formed, valid, consistent request was intentionally provided by the user who submitted the request.",
              "keyphrase_sources": [
                {
                  "id": "weakness:URL redirection to untrusted site",
                  "keyphrase": "URL redirection to untrusted site",
                  "type": "weakness"
                },
                {
                  "id": "weakness:XSS",
                  "keyphrase": "XSS",
                  "type": "weakness"
                },
                {
                  "id": "impact:cross-site scripting",
                  "keyphrase": "cross-site scripting",
                  "type": "impact"
                }
              ]
            },
            "similarity": 175.47506341043038
          }
        ]
      },
      "weakness:XSS": {
        "keyphrase": "XSS",
        "type": "weakness",
        "cwes": [
          {
            "metadata": {
              "doc_id": "79",
              "name": "Improper Neutralization of Input During Web Page Generation ('Cross-site Scripting')",
              "source": "sparse",
              "original_content": "The product does not neutralize or incorrectly neutralizes user-controllable input before it is placed in output that is used as a web page that is served to other users."
            },
            "similarity": 146.42303015303835
          },
          {
            "metadata": {
              "doc_id": "113",
              "name": "Improper Neutralization of CRLF Sequences in HTTP Headers ('HTTP Request/Response Splitting')",
              "source": "sparse",
              "original_content": "The product receives data from an HTTP agent/component (e.g., web server, proxy, browser, etc.), but it does not neutralize or incorrectly neutralizes CR and LF characters before the data is included in outgoing HTTP headers."
            },
            "similarity": 130.412174356539
          },
          {
            "metadata": {
              "doc_id": "352",
              "name": "Cross-Site Request Forgery (CSRF)",
              "source": "sparse",
              "original_content": "The web application does not, or can not, sufficiently verify whether a well-formed, valid, consistent request was intentionally provided by the user who submitted the request."
            },
            "similarity": 126.8580156561288
          },
          {
            "metadata": {
              "doc_id": "1289",
              "name": "Improper Validation of Unsafe Equivalence in Input",
              "source": "sparse",
              "original_content": "The product receives an input value that is used as a resource identifier or other type of reference, but it does not validate or incorrectly validates that the input is equivalent to a potentially-unsafe value.",
              "keyphrase_sources": [
                {
                  "id": "weakness:XSS",
                  "keyphrase": "XSS",
                  "type": "weakness"
                }
              ]
            },
            "similarity": 119.36188841293169
          },
          {
            "metadata": {
              "doc_id": "80",
              "name": "Improper Neutralization of Script-Related HTML Tags in a Web Page (Basic XSS)",
              "source": "sparse",
              "original_content": "The product receives input from an upstream component, but it does not neutralize or incorrectly neutralizes special characters such as \"<\", \">\", and \"&\" that could be interpreted as web-scripting elements when they are sent to a downstream component that processes web pages.",
              "keyphrase_sources": [
                {
                  "id": "weakness:XSS",
                  "keyphrase": "XSS",
                  "type": "weakness"
                },
                {
                  "id": "impact:cross-site scripting",
                  "keyphrase": "cross-site scripting",
                  "type": "impact"
                }
              ]
            },
            "similarity": 119.0316010071095
          }
        ]
      },
      "impact:cross-site scripting": {
        "keyphrase": "cross-site scripting",
        "type": "impact",
        "cwes": [
          {
            "metadata": {
              "doc_id": "79",
              "name": "Improper Neutralization of Input During Web Page Generation ('Cross-site Scripting')",
              "source": "sparse",
              "original_content": "The product does not neutralize or incorrectly neutralizes user-controllable input before it is placed in output that is used as a web page that is served to other users."
            },
            "similarity": 74.42422196783019
          },
          {
            "metadata": {
              "doc_id": "352",
              "name": "Cross-Site Request Forgery (CSRF)",
              "source": "sparse",
              "original_content": "The web application does not, or can not, sufficiently verify whether a well-formed, valid, consistent request was intentionally provided by the user who submitted the request."
            },
            "similarity": 69.60041461866598
          },
          {
            "metadata": {
              "doc_id": "601",
              "name": "URL Redirection to Untrusted Site ('Open Redirect')",
              "source": "sparse",
              "original_content": "The web application accepts a user-controlled input that specifies a link to an external site, and uses that link in a redirect."
            },
            "similarity": 62.897816085979116
          },
          {
            "metadata": {
              "doc_id": "80",
              "name": "Improper Neutralization of Script-Related HTML Tags in a Web Page (Basic XSS)",
              "source": "sparse",
              "original_content": "The product receives input from an upstream component, but it does not neutralize or incorrectly neutralizes special characters such as \"<\", \">\", and \"&\" that could be interpreted as web-scripting elements when they are sent to a downstream component that processes web pages."
            },
            "similarity": 62.75360865199565
          },
          {
            "metadata": {
              "doc_id": "942",
              "name": "Permissive Cross-domain Policy with Untrusted Domains",
              "source": "sparse",
              "original_content": "The product uses a cross-domain policy file that includes domains that should not be trusted.",
              "keyphrase_sources": [
                {
                  "id": "impact:cross-site scripting",
                  "keyphrase": "cross-site scripting",
                  "type": "impact"
                }
              ]
            },
            "similarity": 60.19663797394678
          }
        ]
      },
      "vector:HTTP headers": {
        "keyphrase": "HTTP headers",
        "type": "vector",
        "cwes": [
          {
            "metadata": {
              "doc_id": "113",
              "name": "Improper Neutralization of CRLF Sequences in HTTP Headers ('HTTP Request/Response Splitting')",
              "source": "sparse",
              "original_content": "The product receives data from an HTTP agent/component (e.g., web server, proxy, browser, etc.), but it does not neutralize or incorrectly neutralizes CR and LF characters before the data is included in outgoing HTTP headers."
            },
            "similarity": 60.717767312359726
          },
          {
            "metadata": {
              "doc_id": "212",
              "name": "Improper Removal of Sensitive Information Before Storage or Transfer",
              "source": "sparse",
              "original_content": "The product stores, transfers, or shares a resource that contains sensitive information, but it does not properly remove that information before the product makes the resource available to unauthorized actors.",
              "keyphrase_sources": [
                {
                  "id": "vector:HTTP headers",
                  "keyphrase": "HTTP headers",
                  "type": "vector"
                },
                {
                  "id": "version:1.0",
                  "keyphrase": "1.0",
                  "type": "version"
                }
              ]
            },
            "similarity": 55.7910725282934
          },
          {
            "metadata": {
              "doc_id": "444",
              "name": "Inconsistent Interpretation of HTTP Requests ('HTTP Request/Response Smuggling')",
              "source": "sparse",
              "original_content": "The product acts as an intermediary HTTP agent\n         (such as a proxy or firewall) in the data flow between two\n         entities such as a client and server, but it does not\n         interpret malformed HTTP requests or responses in ways that\n         are consistent with how the messages will be processed by\n         those entities that are at the ultimate destination.",
              "keyphrase_sources": [
                {
                  "id": "vector:HTTP headers",
                  "keyphrase": "HTTP headers",
                  "type": "vector"
                }
              ]
            },
            "similarity": 50.8150416242088
          },
          {
            "metadata": {
              "doc_id": "93",
              "name": "Improper Neutralization of CRLF Sequences ('CRLF Injection')",
              "source": "sparse",
              "original_content": "The product uses CRLF (carriage return line feeds) as a special element, e.g. to separate lines or records, but it does not neutralize or incorrectly neutralizes CRLF sequences from inputs.",
              "keyphrase_sources": [
                {
                  "id": "vector:HTTP headers",
                  "keyphrase": "HTTP headers",
                  "type": "vector"
                }
              ]
            },
            "similarity": 48.68295861793428
          },
          {
            "metadata": {
              "doc_id": "79",
              "name": "Improper Neutralization of Input During Web Page Generation ('Cross-site Scripting')",
              "source": "sparse",
              "original_content": "The product does not neutralize or incorrectly neutralizes user-controllable input before it is placed in output that is used as a web page that is served to other users."
            },
            "similarity": 48.32789724858302
          }
        ]
      },
      "product:Microchip TimeProvider 4100": {
        "keyphrase": "Microchip TimeProvider 4100",
        "type": "product",
        "cwes": [
          {
            "metadata": {
              "doc_id": "696",
              "name": "Incorrect Behavior Order",
              "source": "sparse",
              "original_content": "The product performs multiple related behaviors, but the behaviors are performed in the wrong order in ways which may produce resultant weaknesses.",
              "keyphrase_sources": [
                {
                  "id": "product:Microchip TimeProvider 4100",
                  "keyphrase": "Microchip TimeProvider 4100",
                  "type": "product"
                }
              ]
            },
            "similarity": 45.843314058657484
          },
          {
            "metadata": {
              "doc_id": "601",
              "name": "URL Redirection to Untrusted Site ('Open Redirect')",
              "source": "sparse",
              "original_content": "The web application accepts a user-controlled input that specifies a link to an external site, and uses that link in a redirect."
            },
            "similarity": 42.45458108163395
          },
          {
            "metadata": {
              "doc_id": "79",
              "name": "Improper Neutralization of Input During Web Page Generation ('Cross-site Scripting')",
              "source": "sparse",
              "original_content": "The product does not neutralize or incorrectly neutralizes user-controllable input before it is placed in output that is used as a web page that is served to other users."
            },
            "similarity": 41.72757095155264
          },
          {
            "metadata": {
              "doc_id": "113",
              "name": "Improper Neutralization of CRLF Sequences in HTTP Headers ('HTTP Request/Response Splitting')",
              "source": "sparse",
              "original_content": "The product receives data from an HTTP agent/component (e.g., web server, proxy, browser, etc.), but it does not neutralize or incorrectly neutralizes CR and LF characters before the data is included in outgoing HTTP headers."
            },
            "similarity": 41.20310983683788
          },
          {
            "metadata": {
              "doc_id": "1022",
              "name": "Use of Web Link to Untrusted Target with window.opener Access",
              "source": "sparse",
              "original_content": "The web application produces links to untrusted external sites outside of its sphere of control, but it does not properly prevent the external site from modifying  security-critical properties of the window.opener object, such as the location property."
            },
            "similarity": 40.62974206554274
          }
        ]
      },
      "version:1.0": {
        "keyphrase": "1.0",
        "type": "version",
        "cwes": [
          {
            "metadata": {
              "doc_id": "79",
              "name": "Improper Neutralization of Input During Web Page Generation ('Cross-site Scripting')",
              "source": "sparse",
              "original_content": "The product does not neutralize or incorrectly neutralizes user-controllable input before it is placed in output that is used as a web page that is served to other users."
            },
            "similarity": 44.9475268539932
          },
          {
            "metadata": {
              "doc_id": "601",
              "name": "URL Redirection to Untrusted Site ('Open Redirect')",
              "source": "sparse",
              "original_content": "The web application accepts a user-controlled input that specifies a link to an external site, and uses that link in a redirect."
            },
            "similarity": 44.5600206435965
          },
          {
            "metadata": {
              "doc_id": "113",
              "name": "Improper Neutralization of CRLF Sequences in HTTP Headers ('HTTP Request/Response Splitting')",
              "source": "sparse",
              "original_content": "The product receives data from an HTTP agent/component (e.g., web server, proxy, browser, etc.), but it does not neutralize or incorrectly neutralizes CR and LF characters before the data is included in outgoing HTTP headers."
            },
            "similarity": 44.54029749580468
          },
          {
            "metadata": {
              "doc_id": "1022",
              "name": "Use of Web Link to Untrusted Target with window.opener Access",
              "source": "sparse",
              "original_content": "The web application produces links to untrusted external sites outside of its sphere of control, but it does not properly prevent the external site from modifying  security-critical properties of the window.opener object, such as the location property."
            },
            "similarity": 43.42716361714447
          },
          {
            "metadata": {
              "doc_id": "212",
              "name": "Improper Removal of Sensitive Information Before Storage or Transfer",
              "source": "sparse",
              "original_content": "The product stores, transfers, or shares a resource that contains sensitive information, but it does not properly remove that information before the product makes the resource available to unauthorized actors."
            },
            "similarity": 42.00193271538551
          }
        ]
      }
    },
    "keyphrase_mapping": {
      "601": [
        {
          "id": "weakness:URL redirection to untrusted site",
          "keyphrase": "URL redirection to untrusted site",
          "type": "weakness"
        },
        {
          "id": "impact:cross-site scripting",
          "keyphrase": "cross-site scripting",
          "type": "impact"
        },
        {
          "id": "product:Microchip TimeProvider 4100",
          "keyphrase": "Microchip TimeProvider 4100",
          "type": "product"
        },
        {
          "id": "version:1.0",
          "keyphrase": "1.0",
          "type": "version"
        }
      ],
      "1022": [
        {
          "id": "weakness:URL redirection to untrusted site",
          "keyphrase": "URL redirection to untrusted site",
          "type": "weakness"
        },
        {
          "id": "product:Microchip TimeProvider 4100",
          "keyphrase": "Microchip TimeProvider 4100",
          "type": "product"
        },
        {
          "id": "version:1.0",
          "keyphrase": "1.0",
          "type": "version"
        }
      ],
      "79": [
        {
          "id": "weakness:URL redirection to untrusted site",
          "keyphrase": "URL redirection to untrusted site",
          "type": "weakness"
        },
        {
          "id": "weakness:XSS",
          "keyphrase": "XSS",
          "type": "weakness"
        },
        {
          "id": "impact:cross-site scripting",
          "keyphrase": "cross-site scripting",
          "type": "impact"
        },
        {
          "id": "vector:HTTP headers",
          "keyphrase": "HTTP headers",
          "type": "vector"
        },
        {
          "id": "product:Microchip TimeProvider 4100",
          "keyphrase": "Microchip TimeProvider 4100",
          "type": "product"
        },
        {
          "id": "version:1.0",
          "keyphrase": "1.0",
          "type": "version"
        }
      ],
      "113": [
        {
          "id": "weakness:URL redirection to untrusted site",
          "keyphrase": "URL redirection to untrusted site",
          "type": "weakness"
        },
        {
          "id": "weakness:XSS",
          "keyphrase": "XSS",
          "type": "weakness"
        },
        {
          "id": "vector:HTTP headers",
          "keyphrase": "HTTP headers",
          "type": "vector"
        },
        {
          "id": "product:Microchip TimeProvider 4100",
          "keyphrase": "Microchip TimeProvider 4100",
          "type": "product"
        },
        {
          "id": "version:1.0",
          "keyphrase": "1.0",
          "type": "version"
        }
      ],
      "352": [
        {
          "id": "weakness:URL redirection to untrusted site",
          "keyphrase": "URL redirection to untrusted site",
          "type": "weakness"
        },
        {
          "id": "weakness:XSS",
          "keyphrase": "XSS",
          "type": "weakness"
        },
        {
          "id": "impact:cross-site scripting",
          "keyphrase": "cross-site scripting",
          "type": "impact"
        }
      ],
      "1289": [
        {
          "id": "weakness:XSS",
          "keyphrase": "XSS",
          "type": "weakness"
        }
      ],
      "80": [
        {
          "id": "weakness:XSS",
          "keyphrase": "XSS",
          "type": "weakness"
        },
        {
          "id": "impact:cross-site scripting",
          "keyphrase": "cross-site scripting",
          "type": "impact"
        }
      ],
      "942": [
        {
          "id": "impact:cross-site scripting",
          "keyphrase": "cross-site scripting",
          "type": "impact"
        }
      ],
      "212": [
        {
          "id": "vector:HTTP headers",
          "keyphrase": "HTTP headers",
          "type": "vector"
        },
        {
          "id": "version:1.0",
          "keyphrase": "1.0",
          "type": "version"
        }
      ],
      "444": [
        {
          "id": "vector:HTTP headers",
          "keyphrase": "HTTP headers",
          "type": "vector"
        }
      ],
      "93": [
        {
          "id": "vector:HTTP headers",
          "keyphrase": "HTTP headers",
          "type": "vector"
        }
      ],
      "696": [
        {
          "id": "product:Microchip TimeProvider 4100",
          "keyphrase": "Microchip TimeProvider 4100",
          "type": "product"
        }
      ]
    },
    "relevant_cwes": [
      {
        "metadata": {
          "doc_id": "601",
          "name": "URL Redirection to Untrusted Site ('Open Redirect')",
          "source": "sparse",
          "original_content": "The web application accepts a user-controlled input that specifies a link to an external site, and uses that link in a redirect.",
          "keyphrase_sources": [
            {
              "id": "weakness:URL redirection to untrusted site",
              "keyphrase": "URL redirection to untrusted site",
              "type": "weakness"
            },
            {
              "id": "impact:cross-site scripting",
              "keyphrase": "cross-site scripting",
              "type": "impact"
            },
            {
              "id": "product:Microchip TimeProvider 4100",
              "keyphrase": "Microchip TimeProvider 4100",
              "type": "product"
            },
            {
              "id": "version:1.0",
              "keyphrase": "1.0",
              "type": "version"
            }
          ]
        },
        "similarity": 243.29977293515347
      },
      {
        "metadata": {
          "doc_id": "1022",
          "name": "Use of Web Link to Untrusted Target with window.opener Access",
          "source": "sparse",
          "original_content": "The web application produces links to untrusted external sites outside of its sphere of control, but it does not properly prevent the external site from modifying  security-critical properties of the window.opener object, such as the location property.",
          "keyphrase_sources": [
            {
              "id": "weakness:URL redirection to untrusted site",
              "keyphrase": "URL redirection to untrusted site",
              "type": "weakness"
            },
            {
              "id": "product:Microchip TimeProvider 4100",
              "keyphrase": "Microchip TimeProvider 4100",
              "type": "product"
            },
            {
              "id": "version:1.0",
              "keyphrase": "1.0",
              "type": "version"
            }
          ]
        },
        "similarity": 227.19506109674649
      },
      {
        "metadata": {
          "doc_id": "79",
          "name": "Improper Neutralization of Input During Web Page Generation ('Cross-site Scripting')",
          "source": "sparse",
          "original_content": "The product does not neutralize or incorrectly neutralizes user-controllable input before it is placed in output that is used as a web page that is served to other users.",
          "keyphrase_sources": [
            {
              "id": "weakness:URL redirection to untrusted site",
              "keyphrase": "URL redirection to untrusted site",
              "type": "weakness"
            },
            {
              "id": "weakness:XSS",
              "keyphrase": "XSS",
              "type": "weakness"
            },
            {
              "id": "impact:cross-site scripting",
              "keyphrase": "cross-site scripting",
              "type": "impact"
            },
            {
              "id": "vector:HTTP headers",
              "keyphrase": "HTTP headers",
              "type": "vector"
            },
            {
              "id": "product:Microchip TimeProvider 4100",
              "keyphrase": "Microchip TimeProvider 4100",
              "type": "product"
            },
            {
              "id": "version:1.0",
              "keyphrase": "1.0",
              "type": "version"
            }
          ]
        },
        "similarity": 187.71895003241843
      },
      {
        "metadata": {
          "doc_id": "113",
          "name": "Improper Neutralization of CRLF Sequences in HTTP Headers ('HTTP Request/Response Splitting')",
          "source": "sparse",
          "original_content": "The product receives data from an HTTP agent/component (e.g., web server, proxy, browser, etc.), but it does not neutralize or incorrectly neutralizes CR and LF characters before the data is included in outgoing HTTP headers.",
          "keyphrase_sources": [
            {
              "id": "weakness:URL redirection to untrusted site",
              "keyphrase": "URL redirection to untrusted site",
              "type": "weakness"
            },
            {
              "id": "weakness:XSS",
              "keyphrase": "XSS",
              "type": "weakness"
            },
            {
              "id": "vector:HTTP headers",
              "keyphrase": "HTTP headers",
              "type": "vector"
            },
            {
              "id": "product:Microchip TimeProvider 4100",
              "keyphrase": "Microchip TimeProvider 4100",
              "type": "product"
            },
            {
              "id": "version:1.0",
              "keyphrase": "1.0",
              "type": "version"
            }
          ]
        },
        "similarity": 185.0436462364794
      },
      {
        "metadata": {
          "doc_id": "352",
          "name": "Cross-Site Request Forgery (CSRF)",
          "source": "sparse",
          "original_content": "The web application does not, or can not, sufficiently verify whether a well-formed, valid, consistent request was intentionally provided by the user who submitted the request.",
          "keyphrase_sources": [
            {
              "id": "weakness:URL redirection to untrusted site",
              "keyphrase": "URL redirection to untrusted site",
              "type": "weakness"
            },
            {
              "id": "weakness:XSS",
              "keyphrase": "XSS",
              "type": "weakness"
            },
            {
              "id": "impact:cross-site scripting",
              "keyphrase": "cross-site scripting",
              "type": "impact"
            }
          ]
        },
        "similarity": 175.47506341043038
      },
      {
        "metadata": {
          "doc_id": "1289",
          "name": "Improper Validation of Unsafe Equivalence in Input",
          "source": "sparse",
          "original_content": "The product receives an input value that is used as a resource identifier or other type of reference, but it does not validate or incorrectly validates that the input is equivalent to a potentially-unsafe value.",
          "keyphrase_sources": [
            {
              "id": "weakness:XSS",
              "keyphrase": "XSS",
              "type": "weakness"
            }
          ]
        },
        "similarity": 119.36188841293169
      },
      {
        "metadata": {
          "doc_id": "80",
          "name": "Improper Neutralization of Script-Related HTML Tags in a Web Page (Basic XSS)",
          "source": "sparse",
          "original_content": "The product receives input from an upstream component, but it does not neutralize or incorrectly neutralizes special characters such as \"<\", \">\", and \"&\" that could be interpreted as web-scripting elements when they are sent to a downstream component that processes web pages.",
          "keyphrase_sources": [
            {
              "id": "weakness:XSS",
              "keyphrase": "XSS",
              "type": "weakness"
            },
            {
              "id": "impact:cross-site scripting",
              "keyphrase": "cross-site scripting",
              "type": "impact"
            }
          ]
        },
        "similarity": 119.0316010071095
      },
      {
        "metadata": {
          "doc_id": "942",
          "name": "Permissive Cross-domain Policy with Untrusted Domains",
          "source": "sparse",
          "original_content": "The product uses a cross-domain policy file that includes domains that should not be trusted.",
          "keyphrase_sources": [
            {
              "id": "impact:cross-site scripting",
              "keyphrase": "cross-site scripting",
              "type": "impact"
            }
          ]
        },
        "similarity": 60.19663797394678
      },
      {
        "metadata": {
          "doc_id": "212",
          "name": "Improper Removal of Sensitive Information Before Storage or Transfer",
          "source": "sparse",
          "original_content": "The product stores, transfers, or shares a resource that contains sensitive information, but it does not properly remove that information before the product makes the resource available to unauthorized actors.",
          "keyphrase_sources": [
            {
              "id": "vector:HTTP headers",
              "keyphrase": "HTTP headers",
              "type": "vector"
            },
            {
              "id": "version:1.0",
              "keyphrase": "1.0",
              "type": "version"
            }
          ]
        },
        "similarity": 55.7910725282934
      },
      {
        "metadata": {
          "doc_id": "444",
          "name": "Inconsistent Interpretation of HTTP Requests ('HTTP Request/Response Smuggling')",
          "source": "sparse",
          "original_content": "The product acts as an intermediary HTTP agent\n         (such as a proxy or firewall) in the data flow between two\n         entities such as a client and server, but it does not\n         interpret malformed HTTP requests or responses in ways that\n         are consistent with how the messages will be processed by\n         those entities that are at the ultimate destination.",
          "keyphrase_sources": [
            {
              "id": "vector:HTTP headers",
              "keyphrase": "HTTP headers",
              "type": "vector"
            }
          ]
        },
        "similarity": 50.8150416242088
      },
      {
        "metadata": {
          "doc_id": "93",
          "name": "Improper Neutralization of CRLF Sequences ('CRLF Injection')",
          "source": "sparse",
          "original_content": "The product uses CRLF (carriage return line feeds) as a special element, e.g. to separate lines or records, but it does not neutralize or incorrectly neutralizes CRLF sequences from inputs.",
          "keyphrase_sources": [
            {
              "id": "vector:HTTP headers",
              "keyphrase": "HTTP headers",
              "type": "vector"
            }
          ]
        },
        "similarity": 48.68295861793428
      },
      {
        "metadata": {
          "doc_id": "696",
          "name": "Incorrect Behavior Order",
          "source": "sparse",
          "original_content": "The product performs multiple related behaviors, but the behaviors are performed in the wrong order in ways which may produce resultant weaknesses.",
          "keyphrase_sources": [
            {
              "id": "product:Microchip TimeProvider 4100",
              "keyphrase": "Microchip TimeProvider 4100",
              "type": "product"
            }
          ]
        },
        "similarity": 45.843314058657484
      }
    ],
    "enhanced_query": "# Vulnerability Description\n\n    URL Redirection to Untrusted Site (Open Redirect) vulnerability in Microchip TimeProvider 4100 allows **XSS** Through HTTP Headers.This issue affects TimeProvider 4100 from 1.0.\n\n    # Keyphrase-Specific CWE Analysis\n    This vulnerability contains multiple keyphrases that may map to different CWEs. \n    Please analyze each keyphrase separately and determine the most appropriate CWE(s) for each.\n\n    ## WEAKNESS: 'URL redirection to untrusted site'\n\nRelevant CWEs for this WEAKNESS:\n\n### 1. CWE-601: URL Redirection to Untrusted Site ('Open Redirect') (Score: 243.30)\n\nThe web application accepts a user-controlled input that specifies a link to an external site, and uses that link in a redirect....\n\n### 2. CWE-1022: Use of Web Link to Untrusted Target with window.opener Access (Score: 227.20)\n\nThe web application produces links to untrusted external sites outside of its sphere of control, but it does not properly prevent the external site from modifying  security-critical properties of the window.opener object, such as the location property....\n\n### 3. CWE-79: Improper Neutralization of Input During Web Page Generation ('Cross-site Scripting') (Score: 187.72)\n\nThe product does not neutralize or incorrectly neutralizes user-controllable input before it is placed in output that is used as a web page that is served to other users....\n\n### 4. CWE-113: Improper Neutralization of CRLF Sequences in HTTP Headers ('HTTP Request/Response Splitting') (Score: 185.04)\n\nThe product receives data from an HTTP agent/component (e.g., web server, proxy, browser, etc.), but it does not neutralize or incorrectly neutralizes CR and LF characters before the data is included in outgoing HTTP headers....\n\n### 5. CWE-352: Cross-Site Request Forgery (CSRF) (Score: 175.48)\n\nThe web application does not, or can not, sufficiently verify whether a well-formed, valid, consistent request was intentionally provided by the user who submitted the request....\n\n## IMPACT: 'cross-site scripting'\n\nRelevant CWEs for this IMPACT:\n\n### 1. CWE-601: URL Redirection to Untrusted Site ('Open Redirect') (Score: 243.30)\n\nThe web application accepts a user-controlled input that specifies a link to an external site, and uses that link in a redirect....\n\n### 2. CWE-79: Improper Neutralization of Input During Web Page Generation ('Cross-site Scripting') (Score: 187.72)\n\nThe product does not neutralize or incorrectly neutralizes user-controllable input before it is placed in output that is used as a web page that is served to other users....\n\n### 3. CWE-352: Cross-Site Request Forgery (CSRF) (Score: 175.48)\n\nThe web application does not, or can not, sufficiently verify whether a well-formed, valid, consistent request was intentionally provided by the user who submitted the request....\n\n### 4. CWE-80: Improper Neutralization of Script-Related HTML Tags in a Web Page (Basic XSS) (Score: 119.03)\n\nThe product receives input from an upstream component, but it does not neutralize or incorrectly neutralizes special characters such as \"<\", \">\", and \"&\" that could be interpreted as web-scripting elements when they are sent to a downstream component that processes web pages....\n\n### 5. CWE-942: Permissive Cross-domain Policy with Untrusted Domains (Score: 60.20)\n\nThe product uses a cross-domain policy file that includes domains that should not be trusted....\n\n## PRODUCT: 'Microchip TimeProvider 4100'\n\nRelevant CWEs for this PRODUCT:\n\n### 1. CWE-601: URL Redirection to Untrusted Site ('Open Redirect') (Score: 243.30)\n\nThe web application accepts a user-controlled input that specifies a link to an external site, and uses that link in a redirect....\n\n### 2. CWE-1022: Use of Web Link to Untrusted Target with window.opener Access (Score: 227.20)\n\nThe web application produces links to untrusted external sites outside of its sphere of control, but it does not properly prevent the external site from modifying  security-critical properties of the window.opener object, such as the location property....\n\n### 3. CWE-79: Improper Neutralization of Input During Web Page Generation ('Cross-site Scripting') (Score: 187.72)\n\nThe product does not neutralize or incorrectly neutralizes user-controllable input before it is placed in output that is used as a web page that is served to other users....\n\n### 4. CWE-113: Improper Neutralization of CRLF Sequences in HTTP Headers ('HTTP Request/Response Splitting') (Score: 185.04)\n\nThe product receives data from an HTTP agent/component (e.g., web server, proxy, browser, etc.), but it does not neutralize or incorrectly neutralizes CR and LF characters before the data is included in outgoing HTTP headers....\n\n### 5. CWE-696: Incorrect Behavior Order (Score: 45.84)\n\nThe product performs multiple related behaviors, but the behaviors are performed in the wrong order in ways which may produce resultant weaknesses....\n\n## VERSION: '1.0'\n\nRelevant CWEs for this VERSION:\n\n### 1. CWE-601: URL Redirection to Untrusted Site ('Open Redirect') (Score: 243.30)\n\nThe web application accepts a user-controlled input that specifies a link to an external site, and uses that link in a redirect....\n\n### 2. CWE-1022: Use of Web Link to Untrusted Target with window.opener Access (Score: 227.20)\n\nThe web application produces links to untrusted external sites outside of its sphere of control, but it does not properly prevent the external site from modifying  security-critical properties of the window.opener object, such as the location property....\n\n### 3. CWE-79: Improper Neutralization of Input During Web Page Generation ('Cross-site Scripting') (Score: 187.72)\n\nThe product does not neutralize or incorrectly neutralizes user-controllable input before it is placed in output that is used as a web page that is served to other users....\n\n### 4. CWE-113: Improper Neutralization of CRLF Sequences in HTTP Headers ('HTTP Request/Response Splitting') (Score: 185.04)\n\nThe product receives data from an HTTP agent/component (e.g., web server, proxy, browser, etc.), but it does not neutralize or incorrectly neutralizes CR and LF characters before the data is included in outgoing HTTP headers....\n\n### 5. CWE-212: Improper Removal of Sensitive Information Before Storage or Transfer (Score: 55.79)\n\nThe product stores, transfers, or shares a resource that contains sensitive information, but it does not properly remove that information before the product makes the resource available to unauthorized actors....\n\n## WEAKNESS: 'XSS'\n\nRelevant CWEs for this WEAKNESS:\n\n### 1. CWE-79: Improper Neutralization of Input During Web Page Generation ('Cross-site Scripting') (Score: 187.72)\n\nThe product does not neutralize or incorrectly neutralizes user-controllable input before it is placed in output that is used as a web page that is served to other users....\n\n### 2. CWE-113: Improper Neutralization of CRLF Sequences in HTTP Headers ('HTTP Request/Response Splitting') (Score: 185.04)\n\nThe product receives data from an HTTP agent/component (e.g., web server, proxy, browser, etc.), but it does not neutralize or incorrectly neutralizes CR and LF characters before the data is included in outgoing HTTP headers....\n\n### 3. CWE-352: Cross-Site Request Forgery (CSRF) (Score: 175.48)\n\nThe web application does not, or can not, sufficiently verify whether a well-formed, valid, consistent request was intentionally provided by the user who submitted the request....\n\n### 4. CWE-1289: Improper Validation of Unsafe Equivalence in Input (Score: 119.36)\n\nThe product receives an input value that is used as a resource identifier or other type of reference, but it does not validate or incorrectly validates that the input is equivalent to a potentially-unsafe value....\n\n### 5. CWE-80: Improper Neutralization of Script-Related HTML Tags in a Web Page (Basic XSS) (Score: 119.03)\n\nThe product receives input from an upstream component, but it does not neutralize or incorrectly neutralizes special characters such as \"<\", \">\", and \"&\" that could be interpreted as web-scripting elements when they are sent to a downstream component that processes web pages....\n\n## VECTOR: 'HTTP headers'\n\nRelevant CWEs for this VECTOR:\n\n### 1. CWE-79: Improper Neutralization of Input During Web Page Generation ('Cross-site Scripting') (Score: 187.72)\n\nThe product does not neutralize or incorrectly neutralizes user-controllable input before it is placed in output that is used as a web page that is served to other users....\n\n### 2. CWE-113: Improper Neutralization of CRLF Sequences in HTTP Headers ('HTTP Request/Response Splitting') (Score: 185.04)\n\nThe product receives data from an HTTP agent/component (e.g., web server, proxy, browser, etc.), but it does not neutralize or incorrectly neutralizes CR and LF characters before the data is included in outgoing HTTP headers....\n\n### 3. CWE-212: Improper Removal of Sensitive Information Before Storage or Transfer (Score: 55.79)\n\nThe product stores, transfers, or shares a resource that contains sensitive information, but it does not properly remove that information before the product makes the resource available to unauthorized actors....\n\n### 4. CWE-444: Inconsistent Interpretation of HTTP Requests ('HTTP Request/Response Smuggling') (Score: 50.82)\n\nThe product acts as an intermediary HTTP agent\n         (such as a proxy or firewall) in the data flow between two\n         entities such as a client and server, but it does not\n         interpret malformed HTTP requests or responses in ways that\n         are consistent with how the messages will be...\n\n### 5. CWE-93: Improper Neutralization of CRLF Sequences ('CRLF Injection') (Score: 48.68)\n\nThe product uses CRLF (carriage return line feeds) as a special element, e.g. to separate lines or records, but it does not neutralize or incorrectly neutralizes CRLF sequences from inputs....\n\n\n    # Analysis Instructions\n    1. For each keyphrase, identify the most appropriate CWE(s) that represent the weakness.\n    2. Consider how the different keyphrases might relate to each other in the vulnerability chain.\n    3. Provide a final determination of primary CWE(s) and any secondary CWEs.\n    4. Format your response using the standard analysis template.\n\n    Please analyze how these different weaknesses interact and provide a comprehensive CWE classification.\n    "
  },
  "retrieval_time": 0.9935939311981201
}