{
  "vulnerability_info": "VulnerabilityInfo(cve_id='CVE-2024-6473', description='Yandex Browser for Desktop before 24.7.1.380 has a ****DLL Hijacking** Vulnerability** because an **untrusted search path** is used.', key_phrases={'rootcause': ['DLL Hijacking Vulnerability', 'untrusted search path'], 'weakness': 'DLL Hijacking', 'impact': 'DLL hijacking', 'vector': '', 'attacker': '', 'product': 'Yandex Browser for Desktop', 'version': 'before 24.7.1.380', 'component': ''}, reference_content=\"- **Root cause of vulnerability**: The vulnerability is caused by the usage of an untrusted search path when loading DLLs.\\n- **Weaknesses/vulnerabilities present**: DLL Hijacking.\\n- **Impact of exploitation**: An attacker could potentially execute arbitrary code by placing a malicious DLL in a location where Yandex Browser searches for DLLs, and have it loaded instead of the legitimate one. This could lead to a complete compromise of the user's system if the attacker gains sufficient privileges.\\n- **Attack vectors**: An attacker needs to place a malicious DLL with the name of a DLL that Yandex Browser attempts to load.\\n- **Required attacker capabilities/position**: The attacker needs to have write access to a directory where the browser searches for DLLs before a legitimate DLL with the same name is loaded. This is typically achieved by placing the malicious DLL in a folder higher up in the search path.\", similar_info={'cwe_distribution': {}, 'cwe_consensus': '', 'similarity_stats': {'thresholds': [], 'total_samples_by_threshold': {}, 'top_cwes_by_threshold': {}}}, similarity_summary=SimilarityInsight(consensus_cwe='', top_cwes=[], confidence_levels={}, total_samples=0), analysis='', analysis_with_relationships='', criticism='', resolution='', relevant_cwes=[{'metadata': {'doc_id': '427', 'name': 'Uncontrolled Search Path Element', 'source': 'sparse', 'original_content': 'The product uses a fixed or controlled search path to find resources, but one or more locations in that path can be under the control of unintended actors.', 'keyphrase_sources': [{'id': 'rootcause:DLL Hijacking Vulnerability', 'keyphrase': 'DLL Hijacking Vulnerability', 'type': 'rootcause'}, {'id': 'rootcause:untrusted search path', 'keyphrase': 'untrusted search path', 'type': 'rootcause'}, {'id': 'weakness:DLL Hijacking', 'keyphrase': 'DLL Hijacking', 'type': 'weakness'}, {'id': 'impact:DLL hijacking', 'keyphrase': 'DLL hijacking', 'type': 'impact'}, {'id': 'product:Yandex Browser for Desktop', 'keyphrase': 'Yandex Browser for Desktop', 'type': 'product'}, {'id': 'version:before 24.7.1.380', 'keyphrase': 'before 24.7.1.380', 'type': 'version'}]}, 'similarity': np.float64(245.7762804594101)}, {'metadata': {'doc_id': '278', 'name': 'Insecure Preserved Inherited Permissions', 'source': 'sparse', 'original_content': 'A product inherits a set of insecure permissions for an object, e.g. when copying from an archive file, without user awareness or involvement.', 'keyphrase_sources': [{'id': 'rootcause:DLL Hijacking Vulnerability', 'keyphrase': 'DLL Hijacking Vulnerability', 'type': 'rootcause'}, {'id': 'rootcause:untrusted search path', 'keyphrase': 'untrusted search path', 'type': 'rootcause'}, {'id': 'weakness:DLL Hijacking', 'keyphrase': 'DLL Hijacking', 'type': 'weakness'}, {'id': 'impact:DLL hijacking', 'keyphrase': 'DLL hijacking', 'type': 'impact'}]}, 'similarity': np.float64(185.2140719563991)}, {'metadata': {'doc_id': '426', 'name': 'Untrusted Search Path', 'source': 'sparse', 'original_content': \"The product searches for critical resources using an externally-supplied search path that can point to resources that are not under the product's direct control.\", 'keyphrase_sources': [{'id': 'rootcause:DLL Hijacking Vulnerability', 'keyphrase': 'DLL Hijacking Vulnerability', 'type': 'rootcause'}, {'id': 'rootcause:untrusted search path', 'keyphrase': 'untrusted search path', 'type': 'rootcause'}, {'id': 'weakness:DLL Hijacking', 'keyphrase': 'DLL Hijacking', 'type': 'weakness'}, {'id': 'impact:DLL hijacking', 'keyphrase': 'DLL hijacking', 'type': 'impact'}]}, 'similarity': np.float64(150.02686922383097)}, {'metadata': {'doc_id': '642', 'name': 'External Control of Critical State Data', 'source': 'sparse', 'original_content': 'The product stores security-critical state information about its users, or the product itself, in a location that is accessible to unauthorized actors.', 'keyphrase_sources': [{'id': 'rootcause:untrusted search path', 'keyphrase': 'untrusted search path', 'type': 'rootcause'}]}, 'similarity': np.float64(146.55834786688095)}, {'metadata': {'doc_id': '732', 'name': 'Incorrect Permission Assignment for Critical Resource', 'source': 'sparse', 'original_content': 'The product specifies permissions for a security-critical resource in a way that allows that resource to be read or modified by unintended actors.', 'keyphrase_sources': [{'id': 'rootcause:DLL Hijacking Vulnerability', 'keyphrase': 'DLL Hijacking Vulnerability', 'type': 'rootcause'}, {'id': 'weakness:DLL Hijacking', 'keyphrase': 'DLL Hijacking', 'type': 'weakness'}, {'id': 'impact:DLL hijacking', 'keyphrase': 'DLL hijacking', 'type': 'impact'}, {'id': 'product:Yandex Browser for Desktop', 'keyphrase': 'Yandex Browser for Desktop', 'type': 'product'}]}, 'similarity': np.float64(134.48543739933595)}, {'metadata': {'doc_id': '113', 'name': \"Improper Neutralization of CRLF Sequences in HTTP Headers ('HTTP Request/Response Splitting')\", 'source': 'sparse', 'original_content': 'The product receives data from an HTTP agent/component (e.g., web server, proxy, browser, etc.), but it does not neutralize or incorrectly neutralizes CR and LF characters before the data is included in outgoing HTTP headers.', 'keyphrase_sources': [{'id': 'rootcause:untrusted search path', 'keyphrase': 'untrusted search path', 'type': 'rootcause'}]}, 'similarity': np.float64(128.7826950304346)}, {'metadata': {'doc_id': '1385', 'name': 'Missing Origin Validation in WebSockets', 'source': 'sparse', 'original_content': 'The product uses a WebSocket, but it does not properly verify that the source of data or communication is valid.', 'keyphrase_sources': [{'id': 'rootcause:DLL Hijacking Vulnerability', 'keyphrase': 'DLL Hijacking Vulnerability', 'type': 'rootcause'}, {'id': 'weakness:DLL Hijacking', 'keyphrase': 'DLL Hijacking', 'type': 'weakness'}, {'id': 'impact:DLL hijacking', 'keyphrase': 'DLL hijacking', 'type': 'impact'}]}, 'similarity': np.float64(122.49125107612589)}, {'metadata': {'doc_id': '379', 'name': 'Creation of Temporary File in Directory with Insecure Permissions', 'source': 'sparse', 'original_content': \"The product creates a temporary file in a directory whose permissions allow unintended actors to determine the file's existence or otherwise access that file.\", 'keyphrase_sources': [{'id': 'product:Yandex Browser for Desktop', 'keyphrase': 'Yandex Browser for Desktop', 'type': 'product'}, {'id': 'version:before 24.7.1.380', 'keyphrase': 'before 24.7.1.380', 'type': 'version'}]}, 'similarity': np.float64(63.86541131253485)}, {'metadata': {'doc_id': '79', 'name': \"Improper Neutralization of Input During Web Page Generation ('Cross-site Scripting')\", 'source': 'sparse', 'original_content': 'The product does not neutralize or incorrectly neutralizes user-controllable input before it is placed in output that is used as a web page that is served to other users.', 'keyphrase_sources': [{'id': 'product:Yandex Browser for Desktop', 'keyphrase': 'Yandex Browser for Desktop', 'type': 'product'}, {'id': 'version:before 24.7.1.380', 'keyphrase': 'before 24.7.1.380', 'type': 'version'}]}, 'similarity': np.float64(47.54965765327232)}, {'metadata': {'doc_id': '295', 'name': 'Improper Certificate Validation', 'source': 'sparse', 'original_content': 'The product does not validate, or incorrectly validates, a certificate.', 'keyphrase_sources': [{'id': 'product:Yandex Browser for Desktop', 'keyphrase': 'Yandex Browser for Desktop', 'type': 'product'}]}, 'similarity': np.float64(46.078415301727)}, {'metadata': {'doc_id': '73', 'name': 'External Control of File Name or Path', 'source': 'sparse', 'original_content': 'The product allows user input to control or influence paths or file names that are used in filesystem operations.', 'keyphrase_sources': [{'id': 'version:before 24.7.1.380', 'keyphrase': 'before 24.7.1.380', 'type': 'version'}]}, 'similarity': np.float64(41.67393976432571)}, {'metadata': {'doc_id': '22', 'name': \"Improper Limitation of a Pathname to a Restricted Directory ('Path Traversal')\", 'source': 'sparse', 'original_content': 'The product uses external input to construct a pathname that is intended to identify a file or directory that is located underneath a restricted parent directory, but the product does not properly neutralize special elements within the pathname that can cause the pathname to resolve to a location that is outside of the restricted directory.', 'keyphrase_sources': [{'id': 'version:before 24.7.1.380', 'keyphrase': 'before 24.7.1.380', 'type': 'version'}]}, 'similarity': np.float64(40.29075702562571)}], identified_cwes={'analyzer': [], 'critic_additional': []})",
  "retrieval_results": {
    "has_multiple_keyphrases": true,
    "keyphrase_cwe_sets": {
      "rootcause:DLL Hijacking Vulnerability": {
        "keyphrase": "DLL Hijacking Vulnerability",
        "type": "rootcause",
        "cwes": [
          {
            "metadata": {
              "doc_id": "427",
              "name": "Uncontrolled Search Path Element",
              "source": "sparse",
              "original_content": "The product uses a fixed or controlled search path to find resources, but one or more locations in that path can be under the control of unintended actors.",
              "keyphrase_sources": [
                {
                  "id": "rootcause:DLL Hijacking Vulnerability",
                  "keyphrase": "DLL Hijacking Vulnerability",
                  "type": "rootcause"
                },
                {
                  "id": "rootcause:untrusted search path",
                  "keyphrase": "untrusted search path",
                  "type": "rootcause"
                },
                {
                  "id": "weakness:DLL Hijacking",
                  "keyphrase": "DLL Hijacking",
                  "type": "weakness"
                },
                {
                  "id": "impact:DLL hijacking",
                  "keyphrase": "DLL hijacking",
                  "type": "impact"
                },
                {
                  "id": "product:Yandex Browser for Desktop",
                  "keyphrase": "Yandex Browser for Desktop",
                  "type": "product"
                },
                {
                  "id": "version:before 24.7.1.380",
                  "keyphrase": "before 24.7.1.380",
                  "type": "version"
                }
              ]
            },
            "similarity": 245.7762804594101
          },
          {
            "metadata": {
              "doc_id": "278",
              "name": "Insecure Preserved Inherited Permissions",
              "source": "sparse",
              "original_content": "A product inherits a set of insecure permissions for an object, e.g. when copying from an archive file, without user awareness or involvement.",
              "keyphrase_sources": [
                {
                  "id": "rootcause:DLL Hijacking Vulnerability",
                  "keyphrase": "DLL Hijacking Vulnerability",
                  "type": "rootcause"
                },
                {
                  "id": "rootcause:untrusted search path",
                  "keyphrase": "untrusted search path",
                  "type": "rootcause"
                },
                {
                  "id": "weakness:DLL Hijacking",
                  "keyphrase": "DLL Hijacking",
                  "type": "weakness"
                },
                {
                  "id": "impact:DLL hijacking",
                  "keyphrase": "DLL hijacking",
                  "type": "impact"
                }
              ]
            },
            "similarity": 185.2140719563991
          },
          {
            "metadata": {
              "doc_id": "426",
              "name": "Untrusted Search Path",
              "source": "sparse",
              "original_content": "The product searches for critical resources using an externally-supplied search path that can point to resources that are not under the product's direct control.",
              "keyphrase_sources": [
                {
                  "id": "rootcause:DLL Hijacking Vulnerability",
                  "keyphrase": "DLL Hijacking Vulnerability",
                  "type": "rootcause"
                },
                {
                  "id": "rootcause:untrusted search path",
                  "keyphrase": "untrusted search path",
                  "type": "rootcause"
                },
                {
                  "id": "weakness:DLL Hijacking",
                  "keyphrase": "DLL Hijacking",
                  "type": "weakness"
                },
                {
                  "id": "impact:DLL hijacking",
                  "keyphrase": "DLL hijacking",
                  "type": "impact"
                }
              ]
            },
            "similarity": 150.02686922383097
          },
          {
            "metadata": {
              "doc_id": "732",
              "name": "Incorrect Permission Assignment for Critical Resource",
              "source": "sparse",
              "original_content": "The product specifies permissions for a security-critical resource in a way that allows that resource to be read or modified by unintended actors.",
              "keyphrase_sources": [
                {
                  "id": "rootcause:DLL Hijacking Vulnerability",
                  "keyphrase": "DLL Hijacking Vulnerability",
                  "type": "rootcause"
                },
                {
                  "id": "weakness:DLL Hijacking",
                  "keyphrase": "DLL Hijacking",
                  "type": "weakness"
                },
                {
                  "id": "impact:DLL hijacking",
                  "keyphrase": "DLL hijacking",
                  "type": "impact"
                },
                {
                  "id": "product:Yandex Browser for Desktop",
                  "keyphrase": "Yandex Browser for Desktop",
                  "type": "product"
                }
              ]
            },
            "similarity": 134.48543739933595
          },
          {
            "metadata": {
              "doc_id": "1385",
              "name": "Missing Origin Validation in WebSockets",
              "source": "sparse",
              "original_content": "The product uses a WebSocket, but it does not properly verify that the source of data or communication is valid.",
              "keyphrase_sources": [
                {
                  "id": "rootcause:DLL Hijacking Vulnerability",
                  "keyphrase": "DLL Hijacking Vulnerability",
                  "type": "rootcause"
                },
                {
                  "id": "weakness:DLL Hijacking",
                  "keyphrase": "DLL Hijacking",
                  "type": "weakness"
                },
                {
                  "id": "impact:DLL hijacking",
                  "keyphrase": "DLL hijacking",
                  "type": "impact"
                }
              ]
            },
            "similarity": 122.49125107612589
          }
        ]
      },
      "rootcause:untrusted search path": {
        "keyphrase": "untrusted search path",
        "type": "rootcause",
        "cwes": [
          {
            "metadata": {
              "doc_id": "427",
              "name": "Uncontrolled Search Path Element",
              "source": "sparse",
              "original_content": "The product uses a fixed or controlled search path to find resources, but one or more locations in that path can be under the control of unintended actors."
            },
            "similarity": 239.07379545250686
          },
          {
            "metadata": {
              "doc_id": "426",
              "name": "Untrusted Search Path",
              "source": "sparse",
              "original_content": "The product searches for critical resources using an externally-supplied search path that can point to resources that are not under the product's direct control."
            },
            "similarity": 194.1901708703524
          },
          {
            "metadata": {
              "doc_id": "278",
              "name": "Insecure Preserved Inherited Permissions",
              "source": "sparse",
              "original_content": "A product inherits a set of insecure permissions for an object, e.g. when copying from an archive file, without user awareness or involvement."
            },
            "similarity": 161.79442085102298
          },
          {
            "metadata": {
              "doc_id": "642",
              "name": "External Control of Critical State Data",
              "source": "sparse",
              "original_content": "The product stores security-critical state information about its users, or the product itself, in a location that is accessible to unauthorized actors.",
              "keyphrase_sources": [
                {
                  "id": "rootcause:untrusted search path",
                  "keyphrase": "untrusted search path",
                  "type": "rootcause"
                }
              ]
            },
            "similarity": 146.55834786688095
          },
          {
            "metadata": {
              "doc_id": "113",
              "name": "Improper Neutralization of CRLF Sequences in HTTP Headers ('HTTP Request/Response Splitting')",
              "source": "sparse",
              "original_content": "The product receives data from an HTTP agent/component (e.g., web server, proxy, browser, etc.), but it does not neutralize or incorrectly neutralizes CR and LF characters before the data is included in outgoing HTTP headers.",
              "keyphrase_sources": [
                {
                  "id": "rootcause:untrusted search path",
                  "keyphrase": "untrusted search path",
                  "type": "rootcause"
                }
              ]
            },
            "similarity": 128.7826950304346
          }
        ]
      },
      "weakness:DLL Hijacking": {
        "keyphrase": "DLL Hijacking",
        "type": "weakness",
        "cwes": [
          {
            "metadata": {
              "doc_id": "427",
              "name": "Uncontrolled Search Path Element",
              "source": "sparse",
              "original_content": "The product uses a fixed or controlled search path to find resources, but one or more locations in that path can be under the control of unintended actors."
            },
            "similarity": 226.31021974575515
          },
          {
            "metadata": {
              "doc_id": "278",
              "name": "Insecure Preserved Inherited Permissions",
              "source": "sparse",
              "original_content": "A product inherits a set of insecure permissions for an object, e.g. when copying from an archive file, without user awareness or involvement."
            },
            "similarity": 172.8664671593058
          },
          {
            "metadata": {
              "doc_id": "426",
              "name": "Untrusted Search Path",
              "source": "sparse",
              "original_content": "The product searches for critical resources using an externally-supplied search path that can point to resources that are not under the product's direct control."
            },
            "similarity": 136.9820019195405
          },
          {
            "metadata": {
              "doc_id": "732",
              "name": "Incorrect Permission Assignment for Critical Resource",
              "source": "sparse",
              "original_content": "The product specifies permissions for a security-critical resource in a way that allows that resource to be read or modified by unintended actors."
            },
            "similarity": 122.42227608724014
          },
          {
            "metadata": {
              "doc_id": "1385",
              "name": "Missing Origin Validation in WebSockets",
              "source": "sparse",
              "original_content": "The product uses a WebSocket, but it does not properly verify that the source of data or communication is valid."
            },
            "similarity": 112.57787509489323
          }
        ]
      },
      "impact:DLL hijacking": {
        "keyphrase": "DLL hijacking",
        "type": "impact",
        "cwes": [
          {
            "metadata": {
              "doc_id": "427",
              "name": "Uncontrolled Search Path Element",
              "source": "sparse",
              "original_content": "The product uses a fixed or controlled search path to find resources, but one or more locations in that path can be under the control of unintended actors."
            },
            "similarity": 80.82507848062684
          },
          {
            "metadata": {
              "doc_id": "278",
              "name": "Insecure Preserved Inherited Permissions",
              "source": "sparse",
              "original_content": "A product inherits a set of insecure permissions for an object, e.g. when copying from an archive file, without user awareness or involvement."
            },
            "similarity": 61.73802398546636
          },
          {
            "metadata": {
              "doc_id": "426",
              "name": "Untrusted Search Path",
              "source": "sparse",
              "original_content": "The product searches for critical resources using an externally-supplied search path that can point to resources that are not under the product's direct control."
            },
            "similarity": 48.922143542693036
          },
          {
            "metadata": {
              "doc_id": "732",
              "name": "Incorrect Permission Assignment for Critical Resource",
              "source": "sparse",
              "original_content": "The product specifies permissions for a security-critical resource in a way that allows that resource to be read or modified by unintended actors."
            },
            "similarity": 43.72224145972862
          },
          {
            "metadata": {
              "doc_id": "1385",
              "name": "Missing Origin Validation in WebSockets",
              "source": "sparse",
              "original_content": "The product uses a WebSocket, but it does not properly verify that the source of data or communication is valid."
            },
            "similarity": 40.20638396246187
          }
        ]
      },
      "product:Yandex Browser for Desktop": {
        "keyphrase": "Yandex Browser for Desktop",
        "type": "product",
        "cwes": [
          {
            "metadata": {
              "doc_id": "427",
              "name": "Uncontrolled Search Path Element",
              "source": "sparse",
              "original_content": "The product uses a fixed or controlled search path to find resources, but one or more locations in that path can be under the control of unintended actors."
            },
            "similarity": 68.11478446485181
          },
          {
            "metadata": {
              "doc_id": "379",
              "name": "Creation of Temporary File in Directory with Insecure Permissions",
              "source": "sparse",
              "original_content": "The product creates a temporary file in a directory whose permissions allow unintended actors to determine the file's existence or otherwise access that file.",
              "keyphrase_sources": [
                {
                  "id": "product:Yandex Browser for Desktop",
                  "keyphrase": "Yandex Browser for Desktop",
                  "type": "product"
                },
                {
                  "id": "version:before 24.7.1.380",
                  "keyphrase": "before 24.7.1.380",
                  "type": "version"
                }
              ]
            },
            "similarity": 63.86541131253485
          },
          {
            "metadata": {
              "doc_id": "732",
              "name": "Incorrect Permission Assignment for Critical Resource",
              "source": "sparse",
              "original_content": "The product specifies permissions for a security-critical resource in a way that allows that resource to be read or modified by unintended actors."
            },
            "similarity": 48.77873767808762
          },
          {
            "metadata": {
              "doc_id": "79",
              "name": "Improper Neutralization of Input During Web Page Generation ('Cross-site Scripting')",
              "source": "sparse",
              "original_content": "The product does not neutralize or incorrectly neutralizes user-controllable input before it is placed in output that is used as a web page that is served to other users.",
              "keyphrase_sources": [
                {
                  "id": "product:Yandex Browser for Desktop",
                  "keyphrase": "Yandex Browser for Desktop",
                  "type": "product"
                },
                {
                  "id": "version:before 24.7.1.380",
                  "keyphrase": "before 24.7.1.380",
                  "type": "version"
                }
              ]
            },
            "similarity": 47.54965765327232
          },
          {
            "metadata": {
              "doc_id": "295",
              "name": "Improper Certificate Validation",
              "source": "sparse",
              "original_content": "The product does not validate, or incorrectly validates, a certificate.",
              "keyphrase_sources": [
                {
                  "id": "product:Yandex Browser for Desktop",
                  "keyphrase": "Yandex Browser for Desktop",
                  "type": "product"
                }
              ]
            },
            "similarity": 46.078415301727
          }
        ]
      },
      "version:before 24.7.1.380": {
        "keyphrase": "before 24.7.1.380",
        "type": "version",
        "cwes": [
          {
            "metadata": {
              "doc_id": "427",
              "name": "Uncontrolled Search Path Element",
              "source": "sparse",
              "original_content": "The product uses a fixed or controlled search path to find resources, but one or more locations in that path can be under the control of unintended actors."
            },
            "similarity": 59.88958520483341
          },
          {
            "metadata": {
              "doc_id": "79",
              "name": "Improper Neutralization of Input During Web Page Generation ('Cross-site Scripting')",
              "source": "sparse",
              "original_content": "The product does not neutralize or incorrectly neutralizes user-controllable input before it is placed in output that is used as a web page that is served to other users."
            },
            "similarity": 57.73559939549584
          },
          {
            "metadata": {
              "doc_id": "73",
              "name": "External Control of File Name or Path",
              "source": "sparse",
              "original_content": "The product allows user input to control or influence paths or file names that are used in filesystem operations.",
              "keyphrase_sources": [
                {
                  "id": "version:before 24.7.1.380",
                  "keyphrase": "before 24.7.1.380",
                  "type": "version"
                }
              ]
            },
            "similarity": 41.67393976432571
          },
          {
            "metadata": {
              "doc_id": "379",
              "name": "Creation of Temporary File in Directory with Insecure Permissions",
              "source": "sparse",
              "original_content": "The product creates a temporary file in a directory whose permissions allow unintended actors to determine the file's existence or otherwise access that file."
            },
            "similarity": 40.72178225907383
          },
          {
            "metadata": {
              "doc_id": "22",
              "name": "Improper Limitation of a Pathname to a Restricted Directory ('Path Traversal')",
              "source": "sparse",
              "original_content": "The product uses external input to construct a pathname that is intended to identify a file or directory that is located underneath a restricted parent directory, but the product does not properly neutralize special elements within the pathname that can cause the pathname to resolve to a location that is outside of the restricted directory.",
              "keyphrase_sources": [
                {
                  "id": "version:before 24.7.1.380",
                  "keyphrase": "before 24.7.1.380",
                  "type": "version"
                }
              ]
            },
            "similarity": 40.29075702562571
          }
        ]
      }
    },
    "keyphrase_mapping": {
      "427": [
        {
          "id": "rootcause:DLL Hijacking Vulnerability",
          "keyphrase": "DLL Hijacking Vulnerability",
          "type": "rootcause"
        },
        {
          "id": "rootcause:untrusted search path",
          "keyphrase": "untrusted search path",
          "type": "rootcause"
        },
        {
          "id": "weakness:DLL Hijacking",
          "keyphrase": "DLL Hijacking",
          "type": "weakness"
        },
        {
          "id": "impact:DLL hijacking",
          "keyphrase": "DLL hijacking",
          "type": "impact"
        },
        {
          "id": "product:Yandex Browser for Desktop",
          "keyphrase": "Yandex Browser for Desktop",
          "type": "product"
        },
        {
          "id": "version:before 24.7.1.380",
          "keyphrase": "before 24.7.1.380",
          "type": "version"
        }
      ],
      "278": [
        {
          "id": "rootcause:DLL Hijacking Vulnerability",
          "keyphrase": "DLL Hijacking Vulnerability",
          "type": "rootcause"
        },
        {
          "id": "rootcause:untrusted search path",
          "keyphrase": "untrusted search path",
          "type": "rootcause"
        },
        {
          "id": "weakness:DLL Hijacking",
          "keyphrase": "DLL Hijacking",
          "type": "weakness"
        },
        {
          "id": "impact:DLL hijacking",
          "keyphrase": "DLL hijacking",
          "type": "impact"
        }
      ],
      "426": [
        {
          "id": "rootcause:DLL Hijacking Vulnerability",
          "keyphrase": "DLL Hijacking Vulnerability",
          "type": "rootcause"
        },
        {
          "id": "rootcause:untrusted search path",
          "keyphrase": "untrusted search path",
          "type": "rootcause"
        },
        {
          "id": "weakness:DLL Hijacking",
          "keyphrase": "DLL Hijacking",
          "type": "weakness"
        },
        {
          "id": "impact:DLL hijacking",
          "keyphrase": "DLL hijacking",
          "type": "impact"
        }
      ],
      "732": [
        {
          "id": "rootcause:DLL Hijacking Vulnerability",
          "keyphrase": "DLL Hijacking Vulnerability",
          "type": "rootcause"
        },
        {
          "id": "weakness:DLL Hijacking",
          "keyphrase": "DLL Hijacking",
          "type": "weakness"
        },
        {
          "id": "impact:DLL hijacking",
          "keyphrase": "DLL hijacking",
          "type": "impact"
        },
        {
          "id": "product:Yandex Browser for Desktop",
          "keyphrase": "Yandex Browser for Desktop",
          "type": "product"
        }
      ],
      "1385": [
        {
          "id": "rootcause:DLL Hijacking Vulnerability",
          "keyphrase": "DLL Hijacking Vulnerability",
          "type": "rootcause"
        },
        {
          "id": "weakness:DLL Hijacking",
          "keyphrase": "DLL Hijacking",
          "type": "weakness"
        },
        {
          "id": "impact:DLL hijacking",
          "keyphrase": "DLL hijacking",
          "type": "impact"
        }
      ],
      "642": [
        {
          "id": "rootcause:untrusted search path",
          "keyphrase": "untrusted search path",
          "type": "rootcause"
        }
      ],
      "113": [
        {
          "id": "rootcause:untrusted search path",
          "keyphrase": "untrusted search path",
          "type": "rootcause"
        }
      ],
      "379": [
        {
          "id": "product:Yandex Browser for Desktop",
          "keyphrase": "Yandex Browser for Desktop",
          "type": "product"
        },
        {
          "id": "version:before 24.7.1.380",
          "keyphrase": "before 24.7.1.380",
          "type": "version"
        }
      ],
      "79": [
        {
          "id": "product:Yandex Browser for Desktop",
          "keyphrase": "Yandex Browser for Desktop",
          "type": "product"
        },
        {
          "id": "version:before 24.7.1.380",
          "keyphrase": "before 24.7.1.380",
          "type": "version"
        }
      ],
      "295": [
        {
          "id": "product:Yandex Browser for Desktop",
          "keyphrase": "Yandex Browser for Desktop",
          "type": "product"
        }
      ],
      "73": [
        {
          "id": "version:before 24.7.1.380",
          "keyphrase": "before 24.7.1.380",
          "type": "version"
        }
      ],
      "22": [
        {
          "id": "version:before 24.7.1.380",
          "keyphrase": "before 24.7.1.380",
          "type": "version"
        }
      ]
    },
    "relevant_cwes": [
      {
        "metadata": {
          "doc_id": "427",
          "name": "Uncontrolled Search Path Element",
          "source": "sparse",
          "original_content": "The product uses a fixed or controlled search path to find resources, but one or more locations in that path can be under the control of unintended actors.",
          "keyphrase_sources": [
            {
              "id": "rootcause:DLL Hijacking Vulnerability",
              "keyphrase": "DLL Hijacking Vulnerability",
              "type": "rootcause"
            },
            {
              "id": "rootcause:untrusted search path",
              "keyphrase": "untrusted search path",
              "type": "rootcause"
            },
            {
              "id": "weakness:DLL Hijacking",
              "keyphrase": "DLL Hijacking",
              "type": "weakness"
            },
            {
              "id": "impact:DLL hijacking",
              "keyphrase": "DLL hijacking",
              "type": "impact"
            },
            {
              "id": "product:Yandex Browser for Desktop",
              "keyphrase": "Yandex Browser for Desktop",
              "type": "product"
            },
            {
              "id": "version:before 24.7.1.380",
              "keyphrase": "before 24.7.1.380",
              "type": "version"
            }
          ]
        },
        "similarity": 245.7762804594101
      },
      {
        "metadata": {
          "doc_id": "278",
          "name": "Insecure Preserved Inherited Permissions",
          "source": "sparse",
          "original_content": "A product inherits a set of insecure permissions for an object, e.g. when copying from an archive file, without user awareness or involvement.",
          "keyphrase_sources": [
            {
              "id": "rootcause:DLL Hijacking Vulnerability",
              "keyphrase": "DLL Hijacking Vulnerability",
              "type": "rootcause"
            },
            {
              "id": "rootcause:untrusted search path",
              "keyphrase": "untrusted search path",
              "type": "rootcause"
            },
            {
              "id": "weakness:DLL Hijacking",
              "keyphrase": "DLL Hijacking",
              "type": "weakness"
            },
            {
              "id": "impact:DLL hijacking",
              "keyphrase": "DLL hijacking",
              "type": "impact"
            }
          ]
        },
        "similarity": 185.2140719563991
      },
      {
        "metadata": {
          "doc_id": "426",
          "name": "Untrusted Search Path",
          "source": "sparse",
          "original_content": "The product searches for critical resources using an externally-supplied search path that can point to resources that are not under the product's direct control.",
          "keyphrase_sources": [
            {
              "id": "rootcause:DLL Hijacking Vulnerability",
              "keyphrase": "DLL Hijacking Vulnerability",
              "type": "rootcause"
            },
            {
              "id": "rootcause:untrusted search path",
              "keyphrase": "untrusted search path",
              "type": "rootcause"
            },
            {
              "id": "weakness:DLL Hijacking",
              "keyphrase": "DLL Hijacking",
              "type": "weakness"
            },
            {
              "id": "impact:DLL hijacking",
              "keyphrase": "DLL hijacking",
              "type": "impact"
            }
          ]
        },
        "similarity": 150.02686922383097
      },
      {
        "metadata": {
          "doc_id": "642",
          "name": "External Control of Critical State Data",
          "source": "sparse",
          "original_content": "The product stores security-critical state information about its users, or the product itself, in a location that is accessible to unauthorized actors.",
          "keyphrase_sources": [
            {
              "id": "rootcause:untrusted search path",
              "keyphrase": "untrusted search path",
              "type": "rootcause"
            }
          ]
        },
        "similarity": 146.55834786688095
      },
      {
        "metadata": {
          "doc_id": "732",
          "name": "Incorrect Permission Assignment for Critical Resource",
          "source": "sparse",
          "original_content": "The product specifies permissions for a security-critical resource in a way that allows that resource to be read or modified by unintended actors.",
          "keyphrase_sources": [
            {
              "id": "rootcause:DLL Hijacking Vulnerability",
              "keyphrase": "DLL Hijacking Vulnerability",
              "type": "rootcause"
            },
            {
              "id": "weakness:DLL Hijacking",
              "keyphrase": "DLL Hijacking",
              "type": "weakness"
            },
            {
              "id": "impact:DLL hijacking",
              "keyphrase": "DLL hijacking",
              "type": "impact"
            },
            {
              "id": "product:Yandex Browser for Desktop",
              "keyphrase": "Yandex Browser for Desktop",
              "type": "product"
            }
          ]
        },
        "similarity": 134.48543739933595
      },
      {
        "metadata": {
          "doc_id": "113",
          "name": "Improper Neutralization of CRLF Sequences in HTTP Headers ('HTTP Request/Response Splitting')",
          "source": "sparse",
          "original_content": "The product receives data from an HTTP agent/component (e.g., web server, proxy, browser, etc.), but it does not neutralize or incorrectly neutralizes CR and LF characters before the data is included in outgoing HTTP headers.",
          "keyphrase_sources": [
            {
              "id": "rootcause:untrusted search path",
              "keyphrase": "untrusted search path",
              "type": "rootcause"
            }
          ]
        },
        "similarity": 128.7826950304346
      },
      {
        "metadata": {
          "doc_id": "1385",
          "name": "Missing Origin Validation in WebSockets",
          "source": "sparse",
          "original_content": "The product uses a WebSocket, but it does not properly verify that the source of data or communication is valid.",
          "keyphrase_sources": [
            {
              "id": "rootcause:DLL Hijacking Vulnerability",
              "keyphrase": "DLL Hijacking Vulnerability",
              "type": "rootcause"
            },
            {
              "id": "weakness:DLL Hijacking",
              "keyphrase": "DLL Hijacking",
              "type": "weakness"
            },
            {
              "id": "impact:DLL hijacking",
              "keyphrase": "DLL hijacking",
              "type": "impact"
            }
          ]
        },
        "similarity": 122.49125107612589
      },
      {
        "metadata": {
          "doc_id": "379",
          "name": "Creation of Temporary File in Directory with Insecure Permissions",
          "source": "sparse",
          "original_content": "The product creates a temporary file in a directory whose permissions allow unintended actors to determine the file's existence or otherwise access that file.",
          "keyphrase_sources": [
            {
              "id": "product:Yandex Browser for Desktop",
              "keyphrase": "Yandex Browser for Desktop",
              "type": "product"
            },
            {
              "id": "version:before 24.7.1.380",
              "keyphrase": "before 24.7.1.380",
              "type": "version"
            }
          ]
        },
        "similarity": 63.86541131253485
      },
      {
        "metadata": {
          "doc_id": "79",
          "name": "Improper Neutralization of Input During Web Page Generation ('Cross-site Scripting')",
          "source": "sparse",
          "original_content": "The product does not neutralize or incorrectly neutralizes user-controllable input before it is placed in output that is used as a web page that is served to other users.",
          "keyphrase_sources": [
            {
              "id": "product:Yandex Browser for Desktop",
              "keyphrase": "Yandex Browser for Desktop",
              "type": "product"
            },
            {
              "id": "version:before 24.7.1.380",
              "keyphrase": "before 24.7.1.380",
              "type": "version"
            }
          ]
        },
        "similarity": 47.54965765327232
      },
      {
        "metadata": {
          "doc_id": "295",
          "name": "Improper Certificate Validation",
          "source": "sparse",
          "original_content": "The product does not validate, or incorrectly validates, a certificate.",
          "keyphrase_sources": [
            {
              "id": "product:Yandex Browser for Desktop",
              "keyphrase": "Yandex Browser for Desktop",
              "type": "product"
            }
          ]
        },
        "similarity": 46.078415301727
      },
      {
        "metadata": {
          "doc_id": "73",
          "name": "External Control of File Name or Path",
          "source": "sparse",
          "original_content": "The product allows user input to control or influence paths or file names that are used in filesystem operations.",
          "keyphrase_sources": [
            {
              "id": "version:before 24.7.1.380",
              "keyphrase": "before 24.7.1.380",
              "type": "version"
            }
          ]
        },
        "similarity": 41.67393976432571
      },
      {
        "metadata": {
          "doc_id": "22",
          "name": "Improper Limitation of a Pathname to a Restricted Directory ('Path Traversal')",
          "source": "sparse",
          "original_content": "The product uses external input to construct a pathname that is intended to identify a file or directory that is located underneath a restricted parent directory, but the product does not properly neutralize special elements within the pathname that can cause the pathname to resolve to a location that is outside of the restricted directory.",
          "keyphrase_sources": [
            {
              "id": "version:before 24.7.1.380",
              "keyphrase": "before 24.7.1.380",
              "type": "version"
            }
          ]
        },
        "similarity": 40.29075702562571
      }
    ],
    "enhanced_query": "# Vulnerability Description\n\n    Yandex Browser for Desktop before 24.7.1.380 has a ****DLL Hijacking** Vulnerability** because an **untrusted search path** is used.\n\n    # Keyphrase-Specific CWE Analysis\n    This vulnerability contains multiple keyphrases that may map to different CWEs. \n    Please analyze each keyphrase separately and determine the most appropriate CWE(s) for each.\n\n    ## ROOTCAUSE: 'DLL Hijacking Vulnerability'\n\nRelevant CWEs for this ROOTCAUSE:\n\n### 1. CWE-427: Uncontrolled Search Path Element (Score: 245.78)\n\nThe product uses a fixed or controlled search path to find resources, but one or more locations in that path can be under the control of unintended actors....\n\n### 2. CWE-278: Insecure Preserved Inherited Permissions (Score: 185.21)\n\nA product inherits a set of insecure permissions for an object, e.g. when copying from an archive file, without user awareness or involvement....\n\n### 3. CWE-426: Untrusted Search Path (Score: 150.03)\n\nThe product searches for critical resources using an externally-supplied search path that can point to resources that are not under the product's direct control....\n\n### 4. CWE-732: Incorrect Permission Assignment for Critical Resource (Score: 134.49)\n\nThe product specifies permissions for a security-critical resource in a way that allows that resource to be read or modified by unintended actors....\n\n### 5. CWE-1385: Missing Origin Validation in WebSockets (Score: 122.49)\n\nThe product uses a WebSocket, but it does not properly verify that the source of data or communication is valid....\n\n## ROOTCAUSE: 'untrusted search path'\n\nRelevant CWEs for this ROOTCAUSE:\n\n### 1. CWE-427: Uncontrolled Search Path Element (Score: 245.78)\n\nThe product uses a fixed or controlled search path to find resources, but one or more locations in that path can be under the control of unintended actors....\n\n### 2. CWE-278: Insecure Preserved Inherited Permissions (Score: 185.21)\n\nA product inherits a set of insecure permissions for an object, e.g. when copying from an archive file, without user awareness or involvement....\n\n### 3. CWE-426: Untrusted Search Path (Score: 150.03)\n\nThe product searches for critical resources using an externally-supplied search path that can point to resources that are not under the product's direct control....\n\n### 4. CWE-642: External Control of Critical State Data (Score: 146.56)\n\nThe product stores security-critical state information about its users, or the product itself, in a location that is accessible to unauthorized actors....\n\n### 5. CWE-113: Improper Neutralization of CRLF Sequences in HTTP Headers ('HTTP Request/Response Splitting') (Score: 128.78)\n\nThe product receives data from an HTTP agent/component (e.g., web server, proxy, browser, etc.), but it does not neutralize or incorrectly neutralizes CR and LF characters before the data is included in outgoing HTTP headers....\n\n## WEAKNESS: 'DLL Hijacking'\n\nRelevant CWEs for this WEAKNESS:\n\n### 1. CWE-427: Uncontrolled Search Path Element (Score: 245.78)\n\nThe product uses a fixed or controlled search path to find resources, but one or more locations in that path can be under the control of unintended actors....\n\n### 2. CWE-278: Insecure Preserved Inherited Permissions (Score: 185.21)\n\nA product inherits a set of insecure permissions for an object, e.g. when copying from an archive file, without user awareness or involvement....\n\n### 3. CWE-426: Untrusted Search Path (Score: 150.03)\n\nThe product searches for critical resources using an externally-supplied search path that can point to resources that are not under the product's direct control....\n\n### 4. CWE-732: Incorrect Permission Assignment for Critical Resource (Score: 134.49)\n\nThe product specifies permissions for a security-critical resource in a way that allows that resource to be read or modified by unintended actors....\n\n### 5. CWE-1385: Missing Origin Validation in WebSockets (Score: 122.49)\n\nThe product uses a WebSocket, but it does not properly verify that the source of data or communication is valid....\n\n## IMPACT: 'DLL hijacking'\n\nRelevant CWEs for this IMPACT:\n\n### 1. CWE-427: Uncontrolled Search Path Element (Score: 245.78)\n\nThe product uses a fixed or controlled search path to find resources, but one or more locations in that path can be under the control of unintended actors....\n\n### 2. CWE-278: Insecure Preserved Inherited Permissions (Score: 185.21)\n\nA product inherits a set of insecure permissions for an object, e.g. when copying from an archive file, without user awareness or involvement....\n\n### 3. CWE-426: Untrusted Search Path (Score: 150.03)\n\nThe product searches for critical resources using an externally-supplied search path that can point to resources that are not under the product's direct control....\n\n### 4. CWE-732: Incorrect Permission Assignment for Critical Resource (Score: 134.49)\n\nThe product specifies permissions for a security-critical resource in a way that allows that resource to be read or modified by unintended actors....\n\n### 5. CWE-1385: Missing Origin Validation in WebSockets (Score: 122.49)\n\nThe product uses a WebSocket, but it does not properly verify that the source of data or communication is valid....\n\n## PRODUCT: 'Yandex Browser for Desktop'\n\nRelevant CWEs for this PRODUCT:\n\n### 1. CWE-427: Uncontrolled Search Path Element (Score: 245.78)\n\nThe product uses a fixed or controlled search path to find resources, but one or more locations in that path can be under the control of unintended actors....\n\n### 2. CWE-732: Incorrect Permission Assignment for Critical Resource (Score: 134.49)\n\nThe product specifies permissions for a security-critical resource in a way that allows that resource to be read or modified by unintended actors....\n\n### 3. CWE-379: Creation of Temporary File in Directory with Insecure Permissions (Score: 63.87)\n\nThe product creates a temporary file in a directory whose permissions allow unintended actors to determine the file's existence or otherwise access that file....\n\n### 4. CWE-79: Improper Neutralization of Input During Web Page Generation ('Cross-site Scripting') (Score: 47.55)\n\nThe product does not neutralize or incorrectly neutralizes user-controllable input before it is placed in output that is used as a web page that is served to other users....\n\n### 5. CWE-295: Improper Certificate Validation (Score: 46.08)\n\nThe product does not validate, or incorrectly validates, a certificate....\n\n## VERSION: 'before 24.7.1.380'\n\nRelevant CWEs for this VERSION:\n\n### 1. CWE-427: Uncontrolled Search Path Element (Score: 245.78)\n\nThe product uses a fixed or controlled search path to find resources, but one or more locations in that path can be under the control of unintended actors....\n\n### 2. CWE-379: Creation of Temporary File in Directory with Insecure Permissions (Score: 63.87)\n\nThe product creates a temporary file in a directory whose permissions allow unintended actors to determine the file's existence or otherwise access that file....\n\n### 3. CWE-79: Improper Neutralization of Input During Web Page Generation ('Cross-site Scripting') (Score: 47.55)\n\nThe product does not neutralize or incorrectly neutralizes user-controllable input before it is placed in output that is used as a web page that is served to other users....\n\n### 4. CWE-73: External Control of File Name or Path (Score: 41.67)\n\nThe product allows user input to control or influence paths or file names that are used in filesystem operations....\n\n### 5. CWE-22: Improper Limitation of a Pathname to a Restricted Directory ('Path Traversal') (Score: 40.29)\n\nThe product uses external input to construct a pathname that is intended to identify a file or directory that is located underneath a restricted parent directory, but the product does not properly neutralize special elements within the pathname that can cause the pathname to resolve to a location th...\n\n\n    # Analysis Instructions\n    1. For each keyphrase, identify the most appropriate CWE(s) that represent the weakness.\n    2. Consider how the different keyphrases might relate to each other in the vulnerability chain.\n    3. Provide a final determination of primary CWE(s) and any secondary CWEs.\n    4. Format your response using the standard analysis template.\n\n    Please analyze how these different weaknesses interact and provide a comprehensive CWE classification.\n    "
  },
  "retrieval_time": 0.9909532070159912
}