{
  "vulnerability_info": "VulnerabilityInfo(cve_id='CVE-2025-46512', description='**Cross-Site Request Forgery** (CSRF) vulnerability in Shamim Hasan Custom Functions Plugin allows Stored **XSS**. This issue affects Custom Functions Plugin from n/a through 1.1.', key_phrases={'rootcause': '', 'weakness': ['Cross-Site Request Forgery', 'XSS'], 'impact': '', 'vector': '', 'attacker': '', 'product': 'Shamim Hasan Custom Functions Plugin', 'version': 'through 1.1', 'component': ''}, reference_content='Root cause of vulnerability:\\nThe WordPress Custom Functions Plugin is vulnerable to Cross Site Request Forgery (CSRF).\\n\\nWeaknesses/vulnerabilities present:\\nCross Site Request Forgery (CSRF) vulnerability.\\n\\nImpact of exploitation:\\nA malicious actor could force higher privileged users to execute unwanted actions under their current authentication. The impact varies case by case.\\n\\nAttack vectors:\\nNot specified in the content.\\n\\nRequired attacker capabilities/position:\\nUnauthenticated.\\n\\nMitigation or fix:\\nNo official fix is available. Patchstack vPatching can auto-mitigate the vulnerability.\\n\\nAdditional details:\\n- CVSS score: 7.1 (Low severity)\\n- Vulnerable versions: <= 1.1\\n- Fixed in: N/A\\n- OWASP Top 10: A3: Injection\\n- Reported by: johska\\n- Published by Patchstack: 24 April 2025', similar_info={'cwe_distribution': {}, 'cwe_consensus': '', 'similarity_stats': {'thresholds': [], 'total_samples_by_threshold': {}, 'top_cwes_by_threshold': {}}}, similarity_summary=SimilarityInsight(consensus_cwe='', top_cwes=[], confidence_levels={}, total_samples=0), analysis='', analysis_with_relationships='', criticism='', resolution='', relevant_cwes=[{'metadata': {'doc_id': '352', 'name': 'Cross-Site Request Forgery (CSRF)', 'source': 'sparse', 'original_content': 'The web application does not, or can not, sufficiently verify whether a well-formed, valid, consistent request was intentionally provided by the user who submitted the request.', 'keyphrase_sources': [{'id': 'weakness:Cross-Site Request Forgery', 'keyphrase': 'Cross-Site Request Forgery', 'type': 'weakness'}, {'id': 'weakness:XSS', 'keyphrase': 'XSS', 'type': 'weakness'}, {'id': 'product:Shamim Hasan Custom Functions Plugin', 'keyphrase': 'Shamim Hasan Custom Functions Plugin', 'type': 'product'}, {'id': 'version:through 1.1', 'keyphrase': 'through 1.1', 'type': 'version'}]}, 'similarity': np.float64(305.77636618336726)}, {'metadata': {'doc_id': '89', 'name': \"Improper Neutralization of Special Elements used in an SQL Command ('SQL Injection')\", 'source': 'sparse', 'original_content': 'The product constructs all or part of an SQL command using externally-influenced input from an upstream component, but it does not neutralize or incorrectly neutralizes special elements that could modify the intended SQL command when it is sent to a downstream component. Without sufficient removal or quoting of SQL syntax in user-controllable inputs, the generated SQL query can cause those inputs to be interpreted as SQL instead of ordinary user data.', 'keyphrase_sources': [{'id': 'weakness:Cross-Site Request Forgery', 'keyphrase': 'Cross-Site Request Forgery', 'type': 'weakness'}, {'id': 'version:through 1.1', 'keyphrase': 'through 1.1', 'type': 'version'}]}, 'similarity': np.float64(245.3066962989419)}, {'metadata': {'doc_id': '918', 'name': 'Server-Side Request Forgery (SSRF)', 'source': 'sparse', 'original_content': 'The web server receives a URL or similar request from an upstream component and retrieves the contents of this URL, but it does not sufficiently ensure that the request is being sent to the expected destination.', 'keyphrase_sources': [{'id': 'weakness:Cross-Site Request Forgery', 'keyphrase': 'Cross-Site Request Forgery', 'type': 'weakness'}, {'id': 'weakness:XSS', 'keyphrase': 'XSS', 'type': 'weakness'}]}, 'similarity': np.float64(230.4212340942032)}, {'metadata': {'doc_id': '79', 'name': \"Improper Neutralization of Input During Web Page Generation ('Cross-site Scripting')\", 'source': 'sparse', 'original_content': 'The product does not neutralize or incorrectly neutralizes user-controllable input before it is placed in output that is used as a web page that is served to other users.', 'keyphrase_sources': [{'id': 'weakness:Cross-Site Request Forgery', 'keyphrase': 'Cross-Site Request Forgery', 'type': 'weakness'}, {'id': 'weakness:XSS', 'keyphrase': 'XSS', 'type': 'weakness'}, {'id': 'version:through 1.1', 'keyphrase': 'through 1.1', 'type': 'version'}]}, 'similarity': np.float64(218.53009278002787)}, {'metadata': {'doc_id': '601', 'name': \"URL Redirection to Untrusted Site ('Open Redirect')\", 'source': 'sparse', 'original_content': 'The web application accepts a user-controlled input that specifies a link to an external site, and uses that link in a redirect.', 'keyphrase_sources': [{'id': 'weakness:Cross-Site Request Forgery', 'keyphrase': 'Cross-Site Request Forgery', 'type': 'weakness'}]}, 'similarity': np.float64(206.4350997057642)}, {'metadata': {'doc_id': '116', 'name': 'Improper Encoding or Escaping of Output', 'source': 'sparse', 'original_content': 'The product prepares a structured message for communication with another component, but encoding or escaping of the data is either missing or done incorrectly. As a result, the intended structure of the message is not preserved.', 'keyphrase_sources': [{'id': 'weakness:XSS', 'keyphrase': 'XSS', 'type': 'weakness'}, {'id': 'product:Shamim Hasan Custom Functions Plugin', 'keyphrase': 'Shamim Hasan Custom Functions Plugin', 'type': 'product'}, {'id': 'version:through 1.1', 'keyphrase': 'through 1.1', 'type': 'version'}]}, 'similarity': np.float64(170.56899092193825)}, {'metadata': {'doc_id': '434', 'name': 'Unrestricted Upload of File with Dangerous Type', 'source': 'sparse', 'original_content': 'The product allows the upload or transfer of dangerous file types that are automatically processed within its environment.', 'keyphrase_sources': [{'id': 'weakness:XSS', 'keyphrase': 'XSS', 'type': 'weakness'}, {'id': 'product:Shamim Hasan Custom Functions Plugin', 'keyphrase': 'Shamim Hasan Custom Functions Plugin', 'type': 'product'}, {'id': 'version:through 1.1', 'keyphrase': 'through 1.1', 'type': 'version'}]}, 'similarity': np.float64(166.0498430921616)}, {'metadata': {'doc_id': '862', 'name': 'Missing Authorization', 'source': 'sparse', 'original_content': 'The product does not perform an authorization check when an actor attempts to access a resource or perform an action.', 'keyphrase_sources': [{'id': 'product:Shamim Hasan Custom Functions Plugin', 'keyphrase': 'Shamim Hasan Custom Functions Plugin', 'type': 'product'}]}, 'similarity': np.float64(63.44729266619143)}, {'metadata': {'doc_id': '611', 'name': 'Improper Restriction of XML External Entity Reference', 'source': 'sparse', 'original_content': 'The product processes an XML document that can contain XML entities with URIs that resolve to documents outside of the intended sphere of control, causing the product to embed incorrect documents into its output.', 'keyphrase_sources': [{'id': 'product:Shamim Hasan Custom Functions Plugin', 'keyphrase': 'Shamim Hasan Custom Functions Plugin', 'type': 'product'}]}, 'similarity': np.float64(62.15029481447312)}], identified_cwes={'analyzer': [], 'critic_additional': []})",
  "retrieval_results": {
    "has_multiple_keyphrases": true,
    "keyphrase_cwe_sets": {
      "weakness:Cross-Site Request Forgery": {
        "keyphrase": "Cross-Site Request Forgery",
        "type": "weakness",
        "cwes": [
          {
            "metadata": {
              "doc_id": "352",
              "name": "Cross-Site Request Forgery (CSRF)",
              "source": "sparse",
              "original_content": "The web application does not, or can not, sufficiently verify whether a well-formed, valid, consistent request was intentionally provided by the user who submitted the request.",
              "keyphrase_sources": [
                {
                  "id": "weakness:Cross-Site Request Forgery",
                  "keyphrase": "Cross-Site Request Forgery",
                  "type": "weakness"
                },
                {
                  "id": "weakness:XSS",
                  "keyphrase": "XSS",
                  "type": "weakness"
                },
                {
                  "id": "product:Shamim Hasan Custom Functions Plugin",
                  "keyphrase": "Shamim Hasan Custom Functions Plugin",
                  "type": "product"
                },
                {
                  "id": "version:through 1.1",
                  "keyphrase": "through 1.1",
                  "type": "version"
                }
              ]
            },
            "similarity": 305.77636618336726
          },
          {
            "metadata": {
              "doc_id": "89",
              "name": "Improper Neutralization of Special Elements used in an SQL Command ('SQL Injection')",
              "source": "sparse",
              "original_content": "The product constructs all or part of an SQL command using externally-influenced input from an upstream component, but it does not neutralize or incorrectly neutralizes special elements that could modify the intended SQL command when it is sent to a downstream component. Without sufficient removal or quoting of SQL syntax in user-controllable inputs, the generated SQL query can cause those inputs to be interpreted as SQL instead of ordinary user data.",
              "keyphrase_sources": [
                {
                  "id": "weakness:Cross-Site Request Forgery",
                  "keyphrase": "Cross-Site Request Forgery",
                  "type": "weakness"
                },
                {
                  "id": "version:through 1.1",
                  "keyphrase": "through 1.1",
                  "type": "version"
                }
              ]
            },
            "similarity": 245.3066962989419
          },
          {
            "metadata": {
              "doc_id": "918",
              "name": "Server-Side Request Forgery (SSRF)",
              "source": "sparse",
              "original_content": "The web server receives a URL or similar request from an upstream component and retrieves the contents of this URL, but it does not sufficiently ensure that the request is being sent to the expected destination.",
              "keyphrase_sources": [
                {
                  "id": "weakness:Cross-Site Request Forgery",
                  "keyphrase": "Cross-Site Request Forgery",
                  "type": "weakness"
                },
                {
                  "id": "weakness:XSS",
                  "keyphrase": "XSS",
                  "type": "weakness"
                }
              ]
            },
            "similarity": 230.4212340942032
          },
          {
            "metadata": {
              "doc_id": "79",
              "name": "Improper Neutralization of Input During Web Page Generation ('Cross-site Scripting')",
              "source": "sparse",
              "original_content": "The product does not neutralize or incorrectly neutralizes user-controllable input before it is placed in output that is used as a web page that is served to other users.",
              "keyphrase_sources": [
                {
                  "id": "weakness:Cross-Site Request Forgery",
                  "keyphrase": "Cross-Site Request Forgery",
                  "type": "weakness"
                },
                {
                  "id": "weakness:XSS",
                  "keyphrase": "XSS",
                  "type": "weakness"
                },
                {
                  "id": "version:through 1.1",
                  "keyphrase": "through 1.1",
                  "type": "version"
                }
              ]
            },
            "similarity": 218.53009278002787
          },
          {
            "metadata": {
              "doc_id": "601",
              "name": "URL Redirection to Untrusted Site ('Open Redirect')",
              "source": "sparse",
              "original_content": "The web application accepts a user-controlled input that specifies a link to an external site, and uses that link in a redirect.",
              "keyphrase_sources": [
                {
                  "id": "weakness:Cross-Site Request Forgery",
                  "keyphrase": "Cross-Site Request Forgery",
                  "type": "weakness"
                }
              ]
            },
            "similarity": 206.4350997057642
          }
        ]
      },
      "weakness:XSS": {
        "keyphrase": "XSS",
        "type": "weakness",
        "cwes": [
          {
            "metadata": {
              "doc_id": "352",
              "name": "Cross-Site Request Forgery (CSRF)",
              "source": "sparse",
              "original_content": "The web application does not, or can not, sufficiently verify whether a well-formed, valid, consistent request was intentionally provided by the user who submitted the request."
            },
            "similarity": 219.59661657004943
          },
          {
            "metadata": {
              "doc_id": "79",
              "name": "Improper Neutralization of Input During Web Page Generation ('Cross-site Scripting')",
              "source": "sparse",
              "original_content": "The product does not neutralize or incorrectly neutralizes user-controllable input before it is placed in output that is used as a web page that is served to other users."
            },
            "similarity": 175.72971080002017
          },
          {
            "metadata": {
              "doc_id": "116",
              "name": "Improper Encoding or Escaping of Output",
              "source": "sparse",
              "original_content": "The product prepares a structured message for communication with another component, but encoding or escaping of the data is either missing or done incorrectly. As a result, the intended structure of the message is not preserved.",
              "keyphrase_sources": [
                {
                  "id": "weakness:XSS",
                  "keyphrase": "XSS",
                  "type": "weakness"
                },
                {
                  "id": "product:Shamim Hasan Custom Functions Plugin",
                  "keyphrase": "Shamim Hasan Custom Functions Plugin",
                  "type": "product"
                },
                {
                  "id": "version:through 1.1",
                  "keyphrase": "through 1.1",
                  "type": "version"
                }
              ]
            },
            "similarity": 170.56899092193825
          },
          {
            "metadata": {
              "doc_id": "434",
              "name": "Unrestricted Upload of File with Dangerous Type",
              "source": "sparse",
              "original_content": "The product allows the upload or transfer of dangerous file types that are automatically processed within its environment.",
              "keyphrase_sources": [
                {
                  "id": "weakness:XSS",
                  "keyphrase": "XSS",
                  "type": "weakness"
                },
                {
                  "id": "product:Shamim Hasan Custom Functions Plugin",
                  "keyphrase": "Shamim Hasan Custom Functions Plugin",
                  "type": "product"
                },
                {
                  "id": "version:through 1.1",
                  "keyphrase": "through 1.1",
                  "type": "version"
                }
              ]
            },
            "similarity": 166.0498430921616
          },
          {
            "metadata": {
              "doc_id": "918",
              "name": "Server-Side Request Forgery (SSRF)",
              "source": "sparse",
              "original_content": "The web server receives a URL or similar request from an upstream component and retrieves the contents of this URL, but it does not sufficiently ensure that the request is being sent to the expected destination."
            },
            "similarity": 147.21872808838881
          }
        ]
      },
      "product:Shamim Hasan Custom Functions Plugin": {
        "keyphrase": "Shamim Hasan Custom Functions Plugin",
        "type": "product",
        "cwes": [
          {
            "metadata": {
              "doc_id": "352",
              "name": "Cross-Site Request Forgery (CSRF)",
              "source": "sparse",
              "original_content": "The web application does not, or can not, sufficiently verify whether a well-formed, valid, consistent request was intentionally provided by the user who submitted the request."
            },
            "similarity": 83.9352032158647
          },
          {
            "metadata": {
              "doc_id": "116",
              "name": "Improper Encoding or Escaping of Output",
              "source": "sparse",
              "original_content": "The product prepares a structured message for communication with another component, but encoding or escaping of the data is either missing or done incorrectly. As a result, the intended structure of the message is not preserved."
            },
            "similarity": 64.55879546479638
          },
          {
            "metadata": {
              "doc_id": "862",
              "name": "Missing Authorization",
              "source": "sparse",
              "original_content": "The product does not perform an authorization check when an actor attempts to access a resource or perform an action.",
              "keyphrase_sources": [
                {
                  "id": "product:Shamim Hasan Custom Functions Plugin",
                  "keyphrase": "Shamim Hasan Custom Functions Plugin",
                  "type": "product"
                }
              ]
            },
            "similarity": 63.44729266619143
          },
          {
            "metadata": {
              "doc_id": "434",
              "name": "Unrestricted Upload of File with Dangerous Type",
              "source": "sparse",
              "original_content": "The product allows the upload or transfer of dangerous file types that are automatically processed within its environment."
            },
            "similarity": 63.08326297329208
          },
          {
            "metadata": {
              "doc_id": "611",
              "name": "Improper Restriction of XML External Entity Reference",
              "source": "sparse",
              "original_content": "The product processes an XML document that can contain XML entities with URIs that resolve to documents outside of the intended sphere of control, causing the product to embed incorrect documents into its output.",
              "keyphrase_sources": [
                {
                  "id": "product:Shamim Hasan Custom Functions Plugin",
                  "keyphrase": "Shamim Hasan Custom Functions Plugin",
                  "type": "product"
                }
              ]
            },
            "similarity": 62.15029481447312
          }
        ]
      },
      "version:through 1.1": {
        "keyphrase": "through 1.1",
        "type": "version",
        "cwes": [
          {
            "metadata": {
              "doc_id": "352",
              "name": "Cross-Site Request Forgery (CSRF)",
              "source": "sparse",
              "original_content": "The web application does not, or can not, sufficiently verify whether a well-formed, valid, consistent request was intentionally provided by the user who submitted the request."
            },
            "similarity": 75.66915802707484
          },
          {
            "metadata": {
              "doc_id": "79",
              "name": "Improper Neutralization of Input During Web Page Generation ('Cross-site Scripting')",
              "source": "sparse",
              "original_content": "The product does not neutralize or incorrectly neutralizes user-controllable input before it is placed in output that is used as a web page that is served to other users."
            },
            "similarity": 57.7217528536766
          },
          {
            "metadata": {
              "doc_id": "434",
              "name": "Unrestricted Upload of File with Dangerous Type",
              "source": "sparse",
              "original_content": "The product allows the upload or transfer of dangerous file types that are automatically processed within its environment."
            },
            "similarity": 57.632460360513946
          },
          {
            "metadata": {
              "doc_id": "116",
              "name": "Improper Encoding or Escaping of Output",
              "source": "sparse",
              "original_content": "The product prepares a structured message for communication with another component, but encoding or escaping of the data is either missing or done incorrectly. As a result, the intended structure of the message is not preserved."
            },
            "similarity": 56.88263315132164
          },
          {
            "metadata": {
              "doc_id": "89",
              "name": "Improper Neutralization of Special Elements used in an SQL Command ('SQL Injection')",
              "source": "sparse",
              "original_content": "The product constructs all or part of an SQL command using externally-influenced input from an upstream component, but it does not neutralize or incorrectly neutralizes special elements that could modify the intended SQL command when it is sent to a downstream component. Without sufficient removal or quoting of SQL syntax in user-controllable inputs, the generated SQL query can cause those inputs to be interpreted as SQL instead of ordinary user data."
            },
            "similarity": 55.2847301517576
          }
        ]
      }
    },
    "keyphrase_mapping": {
      "352": [
        {
          "id": "weakness:Cross-Site Request Forgery",
          "keyphrase": "Cross-Site Request Forgery",
          "type": "weakness"
        },
        {
          "id": "weakness:XSS",
          "keyphrase": "XSS",
          "type": "weakness"
        },
        {
          "id": "product:Shamim Hasan Custom Functions Plugin",
          "keyphrase": "Shamim Hasan Custom Functions Plugin",
          "type": "product"
        },
        {
          "id": "version:through 1.1",
          "keyphrase": "through 1.1",
          "type": "version"
        }
      ],
      "89": [
        {
          "id": "weakness:Cross-Site Request Forgery",
          "keyphrase": "Cross-Site Request Forgery",
          "type": "weakness"
        },
        {
          "id": "version:through 1.1",
          "keyphrase": "through 1.1",
          "type": "version"
        }
      ],
      "918": [
        {
          "id": "weakness:Cross-Site Request Forgery",
          "keyphrase": "Cross-Site Request Forgery",
          "type": "weakness"
        },
        {
          "id": "weakness:XSS",
          "keyphrase": "XSS",
          "type": "weakness"
        }
      ],
      "79": [
        {
          "id": "weakness:Cross-Site Request Forgery",
          "keyphrase": "Cross-Site Request Forgery",
          "type": "weakness"
        },
        {
          "id": "weakness:XSS",
          "keyphrase": "XSS",
          "type": "weakness"
        },
        {
          "id": "version:through 1.1",
          "keyphrase": "through 1.1",
          "type": "version"
        }
      ],
      "601": [
        {
          "id": "weakness:Cross-Site Request Forgery",
          "keyphrase": "Cross-Site Request Forgery",
          "type": "weakness"
        }
      ],
      "116": [
        {
          "id": "weakness:XSS",
          "keyphrase": "XSS",
          "type": "weakness"
        },
        {
          "id": "product:Shamim Hasan Custom Functions Plugin",
          "keyphrase": "Shamim Hasan Custom Functions Plugin",
          "type": "product"
        },
        {
          "id": "version:through 1.1",
          "keyphrase": "through 1.1",
          "type": "version"
        }
      ],
      "434": [
        {
          "id": "weakness:XSS",
          "keyphrase": "XSS",
          "type": "weakness"
        },
        {
          "id": "product:Shamim Hasan Custom Functions Plugin",
          "keyphrase": "Shamim Hasan Custom Functions Plugin",
          "type": "product"
        },
        {
          "id": "version:through 1.1",
          "keyphrase": "through 1.1",
          "type": "version"
        }
      ],
      "862": [
        {
          "id": "product:Shamim Hasan Custom Functions Plugin",
          "keyphrase": "Shamim Hasan Custom Functions Plugin",
          "type": "product"
        }
      ],
      "611": [
        {
          "id": "product:Shamim Hasan Custom Functions Plugin",
          "keyphrase": "Shamim Hasan Custom Functions Plugin",
          "type": "product"
        }
      ]
    },
    "relevant_cwes": [
      {
        "metadata": {
          "doc_id": "352",
          "name": "Cross-Site Request Forgery (CSRF)",
          "source": "sparse",
          "original_content": "The web application does not, or can not, sufficiently verify whether a well-formed, valid, consistent request was intentionally provided by the user who submitted the request.",
          "keyphrase_sources": [
            {
              "id": "weakness:Cross-Site Request Forgery",
              "keyphrase": "Cross-Site Request Forgery",
              "type": "weakness"
            },
            {
              "id": "weakness:XSS",
              "keyphrase": "XSS",
              "type": "weakness"
            },
            {
              "id": "product:Shamim Hasan Custom Functions Plugin",
              "keyphrase": "Shamim Hasan Custom Functions Plugin",
              "type": "product"
            },
            {
              "id": "version:through 1.1",
              "keyphrase": "through 1.1",
              "type": "version"
            }
          ]
        },
        "similarity": 305.77636618336726
      },
      {
        "metadata": {
          "doc_id": "89",
          "name": "Improper Neutralization of Special Elements used in an SQL Command ('SQL Injection')",
          "source": "sparse",
          "original_content": "The product constructs all or part of an SQL command using externally-influenced input from an upstream component, but it does not neutralize or incorrectly neutralizes special elements that could modify the intended SQL command when it is sent to a downstream component. Without sufficient removal or quoting of SQL syntax in user-controllable inputs, the generated SQL query can cause those inputs to be interpreted as SQL instead of ordinary user data.",
          "keyphrase_sources": [
            {
              "id": "weakness:Cross-Site Request Forgery",
              "keyphrase": "Cross-Site Request Forgery",
              "type": "weakness"
            },
            {
              "id": "version:through 1.1",
              "keyphrase": "through 1.1",
              "type": "version"
            }
          ]
        },
        "similarity": 245.3066962989419
      },
      {
        "metadata": {
          "doc_id": "918",
          "name": "Server-Side Request Forgery (SSRF)",
          "source": "sparse",
          "original_content": "The web server receives a URL or similar request from an upstream component and retrieves the contents of this URL, but it does not sufficiently ensure that the request is being sent to the expected destination.",
          "keyphrase_sources": [
            {
              "id": "weakness:Cross-Site Request Forgery",
              "keyphrase": "Cross-Site Request Forgery",
              "type": "weakness"
            },
            {
              "id": "weakness:XSS",
              "keyphrase": "XSS",
              "type": "weakness"
            }
          ]
        },
        "similarity": 230.4212340942032
      },
      {
        "metadata": {
          "doc_id": "79",
          "name": "Improper Neutralization of Input During Web Page Generation ('Cross-site Scripting')",
          "source": "sparse",
          "original_content": "The product does not neutralize or incorrectly neutralizes user-controllable input before it is placed in output that is used as a web page that is served to other users.",
          "keyphrase_sources": [
            {
              "id": "weakness:Cross-Site Request Forgery",
              "keyphrase": "Cross-Site Request Forgery",
              "type": "weakness"
            },
            {
              "id": "weakness:XSS",
              "keyphrase": "XSS",
              "type": "weakness"
            },
            {
              "id": "version:through 1.1",
              "keyphrase": "through 1.1",
              "type": "version"
            }
          ]
        },
        "similarity": 218.53009278002787
      },
      {
        "metadata": {
          "doc_id": "601",
          "name": "URL Redirection to Untrusted Site ('Open Redirect')",
          "source": "sparse",
          "original_content": "The web application accepts a user-controlled input that specifies a link to an external site, and uses that link in a redirect.",
          "keyphrase_sources": [
            {
              "id": "weakness:Cross-Site Request Forgery",
              "keyphrase": "Cross-Site Request Forgery",
              "type": "weakness"
            }
          ]
        },
        "similarity": 206.4350997057642
      },
      {
        "metadata": {
          "doc_id": "116",
          "name": "Improper Encoding or Escaping of Output",
          "source": "sparse",
          "original_content": "The product prepares a structured message for communication with another component, but encoding or escaping of the data is either missing or done incorrectly. As a result, the intended structure of the message is not preserved.",
          "keyphrase_sources": [
            {
              "id": "weakness:XSS",
              "keyphrase": "XSS",
              "type": "weakness"
            },
            {
              "id": "product:Shamim Hasan Custom Functions Plugin",
              "keyphrase": "Shamim Hasan Custom Functions Plugin",
              "type": "product"
            },
            {
              "id": "version:through 1.1",
              "keyphrase": "through 1.1",
              "type": "version"
            }
          ]
        },
        "similarity": 170.56899092193825
      },
      {
        "metadata": {
          "doc_id": "434",
          "name": "Unrestricted Upload of File with Dangerous Type",
          "source": "sparse",
          "original_content": "The product allows the upload or transfer of dangerous file types that are automatically processed within its environment.",
          "keyphrase_sources": [
            {
              "id": "weakness:XSS",
              "keyphrase": "XSS",
              "type": "weakness"
            },
            {
              "id": "product:Shamim Hasan Custom Functions Plugin",
              "keyphrase": "Shamim Hasan Custom Functions Plugin",
              "type": "product"
            },
            {
              "id": "version:through 1.1",
              "keyphrase": "through 1.1",
              "type": "version"
            }
          ]
        },
        "similarity": 166.0498430921616
      },
      {
        "metadata": {
          "doc_id": "862",
          "name": "Missing Authorization",
          "source": "sparse",
          "original_content": "The product does not perform an authorization check when an actor attempts to access a resource or perform an action.",
          "keyphrase_sources": [
            {
              "id": "product:Shamim Hasan Custom Functions Plugin",
              "keyphrase": "Shamim Hasan Custom Functions Plugin",
              "type": "product"
            }
          ]
        },
        "similarity": 63.44729266619143
      },
      {
        "metadata": {
          "doc_id": "611",
          "name": "Improper Restriction of XML External Entity Reference",
          "source": "sparse",
          "original_content": "The product processes an XML document that can contain XML entities with URIs that resolve to documents outside of the intended sphere of control, causing the product to embed incorrect documents into its output.",
          "keyphrase_sources": [
            {
              "id": "product:Shamim Hasan Custom Functions Plugin",
              "keyphrase": "Shamim Hasan Custom Functions Plugin",
              "type": "product"
            }
          ]
        },
        "similarity": 62.15029481447312
      }
    ],
    "enhanced_query": "# Vulnerability Description\n\n    **Cross-Site Request Forgery** (CSRF) vulnerability in Shamim Hasan Custom Functions Plugin allows Stored **XSS**. This issue affects Custom Functions Plugin from n/a through 1.1.\n\n    # Keyphrase-Specific CWE Analysis\n    This vulnerability contains multiple keyphrases that may map to different CWEs. \n    Please analyze each keyphrase separately and determine the most appropriate CWE(s) for each.\n\n    ## WEAKNESS: 'Cross-Site Request Forgery'\n\nRelevant CWEs for this WEAKNESS:\n\n### 1. CWE-352: Cross-Site Request Forgery (CSRF) (Score: 305.78)\n\nThe web application does not, or can not, sufficiently verify whether a well-formed, valid, consistent request was intentionally provided by the user who submitted the request....\n\n### 2. CWE-89: Improper Neutralization of Special Elements used in an SQL Command ('SQL Injection') (Score: 245.31)\n\nThe product constructs all or part of an SQL command using externally-influenced input from an upstream component, but it does not neutralize or incorrectly neutralizes special elements that could modify the intended SQL command when it is sent to a downstream component. Without sufficient removal o...\n\n### 3. CWE-918: Server-Side Request Forgery (SSRF) (Score: 230.42)\n\nThe web server receives a URL or similar request from an upstream component and retrieves the contents of this URL, but it does not sufficiently ensure that the request is being sent to the expected destination....\n\n### 4. CWE-79: Improper Neutralization of Input During Web Page Generation ('Cross-site Scripting') (Score: 218.53)\n\nThe product does not neutralize or incorrectly neutralizes user-controllable input before it is placed in output that is used as a web page that is served to other users....\n\n### 5. CWE-601: URL Redirection to Untrusted Site ('Open Redirect') (Score: 206.44)\n\nThe web application accepts a user-controlled input that specifies a link to an external site, and uses that link in a redirect....\n\n## WEAKNESS: 'XSS'\n\nRelevant CWEs for this WEAKNESS:\n\n### 1. CWE-352: Cross-Site Request Forgery (CSRF) (Score: 305.78)\n\nThe web application does not, or can not, sufficiently verify whether a well-formed, valid, consistent request was intentionally provided by the user who submitted the request....\n\n### 2. CWE-918: Server-Side Request Forgery (SSRF) (Score: 230.42)\n\nThe web server receives a URL or similar request from an upstream component and retrieves the contents of this URL, but it does not sufficiently ensure that the request is being sent to the expected destination....\n\n### 3. CWE-79: Improper Neutralization of Input During Web Page Generation ('Cross-site Scripting') (Score: 218.53)\n\nThe product does not neutralize or incorrectly neutralizes user-controllable input before it is placed in output that is used as a web page that is served to other users....\n\n### 4. CWE-116: Improper Encoding or Escaping of Output (Score: 170.57)\n\nThe product prepares a structured message for communication with another component, but encoding or escaping of the data is either missing or done incorrectly. As a result, the intended structure of the message is not preserved....\n\n### 5. CWE-434: Unrestricted Upload of File with Dangerous Type (Score: 166.05)\n\nThe product allows the upload or transfer of dangerous file types that are automatically processed within its environment....\n\n## PRODUCT: 'Shamim Hasan Custom Functions Plugin'\n\nRelevant CWEs for this PRODUCT:\n\n### 1. CWE-352: Cross-Site Request Forgery (CSRF) (Score: 305.78)\n\nThe web application does not, or can not, sufficiently verify whether a well-formed, valid, consistent request was intentionally provided by the user who submitted the request....\n\n### 2. CWE-116: Improper Encoding or Escaping of Output (Score: 170.57)\n\nThe product prepares a structured message for communication with another component, but encoding or escaping of the data is either missing or done incorrectly. As a result, the intended structure of the message is not preserved....\n\n### 3. CWE-434: Unrestricted Upload of File with Dangerous Type (Score: 166.05)\n\nThe product allows the upload or transfer of dangerous file types that are automatically processed within its environment....\n\n### 4. CWE-862: Missing Authorization (Score: 63.45)\n\nThe product does not perform an authorization check when an actor attempts to access a resource or perform an action....\n\n### 5. CWE-611: Improper Restriction of XML External Entity Reference (Score: 62.15)\n\nThe product processes an XML document that can contain XML entities with URIs that resolve to documents outside of the intended sphere of control, causing the product to embed incorrect documents into its output....\n\n## VERSION: 'through 1.1'\n\nRelevant CWEs for this VERSION:\n\n### 1. CWE-352: Cross-Site Request Forgery (CSRF) (Score: 305.78)\n\nThe web application does not, or can not, sufficiently verify whether a well-formed, valid, consistent request was intentionally provided by the user who submitted the request....\n\n### 2. CWE-89: Improper Neutralization of Special Elements used in an SQL Command ('SQL Injection') (Score: 245.31)\n\nThe product constructs all or part of an SQL command using externally-influenced input from an upstream component, but it does not neutralize or incorrectly neutralizes special elements that could modify the intended SQL command when it is sent to a downstream component. Without sufficient removal o...\n\n### 3. CWE-79: Improper Neutralization of Input During Web Page Generation ('Cross-site Scripting') (Score: 218.53)\n\nThe product does not neutralize or incorrectly neutralizes user-controllable input before it is placed in output that is used as a web page that is served to other users....\n\n### 4. CWE-116: Improper Encoding or Escaping of Output (Score: 170.57)\n\nThe product prepares a structured message for communication with another component, but encoding or escaping of the data is either missing or done incorrectly. As a result, the intended structure of the message is not preserved....\n\n### 5. CWE-434: Unrestricted Upload of File with Dangerous Type (Score: 166.05)\n\nThe product allows the upload or transfer of dangerous file types that are automatically processed within its environment....\n\n\n    # Analysis Instructions\n    1. For each keyphrase, identify the most appropriate CWE(s) that represent the weakness.\n    2. Consider how the different keyphrases might relate to each other in the vulnerability chain.\n    3. Provide a final determination of primary CWE(s) and any secondary CWEs.\n    4. Format your response using the standard analysis template.\n\n    Please analyze how these different weaknesses interact and provide a comprehensive CWE classification.\n    "
  },
  "retrieval_time": 1.0410499572753906
}