{
  "cve_id": "CVE-2024-21455",
  "description": "**Memory corruption** when a compat IOCTL call is followed by another IOCTL call from userspace to a driver.",
  "key_phrases": {
    "rootcause": "",
    "weakness": [
      "Memory corruption",
      "race condition"
    ],
    "impact": "memory corruption",
    "vector": "",
    "attacker": "",
    "product": "",
    "version": "",
    "component": ""
  },
  "reference_content": null,
  "similar_info": {
    "cwe_distribution": {},
    "cwe_consensus": "",
    "similarity_stats": {
      "thresholds": [],
      "total_samples_by_threshold": {},
      "top_cwes_by_threshold": {}
    }
  },
  "similarity_summary": {
    "consensus_cwe": "",
    "top_cwes": [],
    "confidence_levels": {},
    "total_samples": 0
  },
  "analysis": "# Summary\n| CWE ID | CWE Name | Confidence | CWE Abstraction Level | CWE Vulnerability Mapping Label | CWE-Vulnerability Mapping Notes |\n|---|---|---|---|---|---|\n| CWE-787 | Out-of-bounds Write | 0.8 | Base | Primary | Allowed |\n| CWE-362 | Concurrent Execution using Shared Resource with Improper Synchronization ('Race Condition') | 0.7 | Class | Secondary | Allowed-with-Review |\n\n## Evidence and Confidence\n\n*   **Confidence Score:** 0.75\n*   **Evidence Strength:** MEDIUM\n\n## Relationship Analysis\nThe primary weakness is identified as CWE-787, representing an out-of-bounds write, which aligns with the \"memory corruption\" aspect of the vulnerability. CWE-362 is considered a secondary weakness because the vulnerability involves a **race condition** due to concurrent execution and improper synchronization, potentially leading to the memory corruption. CWE-362 is a Class-level CWE, and there might be more specific Base-level children, but the description provided doesn't give enough information to narrow it down further.\n\n```mermaid\ngraph TD\n    cwe787[\"CWE-787: Out-of-bounds Write\"]\n    cwe362[\"CWE-362: Concurrent Execution using Shared Resource with Improper Synchronization ('Race Condition')\"]\n    cwe119[\"CWE-119: Improper Restriction of Operations\"]\n    \n    cwe787 -->|CHILDOF| cwe119\n    cwe362 -->|PARENT_OF| cwe689[\"CWE-689: Race Condition Involving Read-Modify-Write\"]\n    cwe362 -->|PARENT_OF| cwe421[\"CWE-421: Race Condition During Initialization\"]\n    \n    classDef primary fill:#f96,stroke:#333,stroke-width:2px\n    classDef secondary fill:#69f,stroke:#333\n    class cwe787 primary\n    class cwe362 secondary\n```\n\n## Vulnerability Chain\nThe vulnerability chain starts with a **race condition** (CWE-362), possibly due to improper locking or synchronization. This leads to memory corruption, specifically an out-of-bounds write (CWE-787), when a compat IOCTL call is followed by another IOCTL call from userspace to a driver.\n\n## Summary of Analysis\nThe analysis focuses on the provided evidence, which highlights **memory corruption** and a **race condition**. The primary CWE, CWE-787, directly addresses the **memory corruption** resulting from an out-of-bounds write. The secondary CWE, CWE-362, accounts for the concurrent execution and synchronization issues that trigger the vulnerability. The relatively lower confidence is primarily due to the limited information on the specific root cause for the **race condition** or the **memory corruption** in the vulnerability description. Additional information is needed to determine a lower level child CWE for the **race condition** (CWE-362).\n\nRelevant CWE Information:\n\n# Enhanced Context (25 CWEs)\nThe following CWEs were identified as potentially relevant to this vulnerability:\n\n## CWE-782: Exposed IOCTL with Insufficient Access Control\n**Abstraction Level**: Variant\n**Similarity Score**: 0.74\n**Source**: dense\n\n**Description**:\nThe product implements an IOCTL with functionality that should be restricted, but it does not properly enforce access control for the IOCTL.\n\n**Mapping Guidance**:\n- Usage: Allowed\n- Rationale: This CWE entry is at the Variant level of abstraction, which is a preferred level of abstraction for mapping to the root causes of vulnerabilities.\n\n\n\n## CWE-131: Incorrect Calculation of Buffer Size\n**Abstraction Level**: Base\n**Similarity Score**: 0.72\n**Source**: dense\n\n**Description**:\nThe product does not correctly calculate the size to be used when allocating a buffer, which could lead to a buffer overflow.\n\n**Mapping Guidance**:\n- Usage: Allowed\n- Rationale: This CWE entry is at the Base level of abstraction, which is a preferred level of abstraction for mapping to the root causes of vulnerabilities.\n\n\n\n## CWE-667: Improper Locking\n**Abstraction Level**: Class\n**Similarity Score**: 0.72\n**Source**: dense\n\n**Description**:\nThe product does not properly acquire or release a lock on a resource, leading to unexpected resource state changes and behaviors.\n\n**Mapping Guidance**:\n- Usage: Allowed-with-Review\n- Rationale: This CWE entry is a Class and might have Base-level children that would be more appropriate\n\n\n\n## CWE-824: Access of Uninitialized Pointer\n**Abstraction Level**: Base\n**Similarity Score**: 0.72\n**Source**: dense\n\n**Description**:\nThe product accesses or uses a pointer that has not been initialized.\n\n**Mapping Guidance**:\n- Usage: Allowed\n- Rationale: This CWE entry is at the Base level of abstraction, which is a preferred level of abstraction for mapping to the root causes of vulnerabilities.\n\n\n\n## CWE-703: Improper Check or Handling of Exceptional Conditions\n**Abstraction Level**: Pillar\n**Similarity Score**: 0.71\n**Source**: dense\n\n**Description**:\nThe product does not properly anticipate or handle exceptional conditions that rarely occur during normal operation of the product.\n\n**Mapping Guidance**:\n- Usage: Discouraged\n- Rationale: This CWE entry is extremely high-level, a Pillar.\n\n\n\n## CWE-274: Improper Handling of Insufficient Privileges\n**Abstraction Level**: Base\n**Similarity Score**: 0.71\n**Source**: dense\n\n**Description**:\nThe product does not handle or incorrectly handles when it has insufficient privileges to perform an operation, leading to resultant weaknesses.\n\n**Mapping Guidance**:\n- Usage: Discouraged\n- Rationale: This CWE entry could be deprecated in a future version of CWE.\n\n\n\n## CWE-696: Incorrect Behavior Order\n**Abstraction Level**: Class\n**Similarity Score**: 0.71\n**Source**: dense\n\n**Description**:\nThe product performs multiple related behaviors, but the behaviors are performed in the wrong order in ways which may produce resultant weaknesses.\n\n**Mapping Guidance**:\n- Usage: Allowed-with-Review\n- Rationale: This CWE entry is a Class and might have Base-level children that would be more appropriate\n\n\n\n## CWE-134: Use of Externally-Controlled Format String\n**Abstraction Level**: Base\n**Similarity Score**: 0.71\n**Source**: dense\n\n**Description**:\nThe product uses a function that accepts a format string as an argument, but the format string originates from an external source.\n\n**Mapping Guidance**:\n- Usage: Allowed\n- Rationale: This CWE entry is at the Base level of abstraction, which is a preferred level of abstraction for mapping to the root causes of vulnerabilities.\n\n\n\n## CWE-657: Violation of Secure Design Principles\n**Abstraction Level**: Class\n**Similarity Score**: 0.70\n**Source**: dense\n\n**Description**:\nThe product violates well-established principles for secure design.\n\n**Mapping Guidance**:\n- Usage: Discouraged\n- Rationale: This CWE entry is a level-1 Class (i.e., a child of a Pillar). It might have lower-level children that would be more appropriate\n\n\n\n## CWE-367: Time-of-check Time-of-use (TOCTOU) Race Condition\n**Abstraction Level**: Base\n**Similarity Score**: 0.70\n**Source**: dense\n\n**Description**:\nThe product checks the state of a resource before using that resource, but the resource's state can change between the check and the use in a way that invalidates the results of the check. This can cause the product to perform invalid actions when the resource is in an unexpected state.\n\n**Mapping Guidance**:\n- Usage: Allowed\n- Rationale: This CWE entry is at the Base level of abstraction, which is a preferred level of abstraction for mapping to the root causes of vulnerabilities.\n\n\n\n## CWE-667: Improper Locking\n**Abstraction Level**: Class\n**Similarity Score**: 1299.44\n**Source**: sparse\n\n**Description**:\nThe product does not properly acquire or release a lock on a resource, leading to unexpected resource state changes and behaviors.\n\n**Mapping Guidance**:\n- Usage: Allowed-with-Review\n- Rationale: This CWE entry is a Class and might have Base-level children that would be more appropriate\n\n\n\n## CWE-367: Time-of-check Time-of-use (TOCTOU) Race Condition\n**Abstraction Level**: Base\n**Similarity Score**: 1249.26\n**Source**: sparse\n\n**Description**:\nThe product checks the state of a resource before using that resource, but the resource's state can change between the check and the use in a way that invalidates the results of the check. This can cause the product to perform invalid actions when the resource is in an unexpected state.\n\n**Mapping Guidance**:\n- Usage: Allowed\n- Rationale: This CWE entry is at the Base level of abstraction, which is a preferred level of abstraction for mapping to the root causes of vulnerabilities.\n\n\n\n## CWE-362: Concurrent Execution using Shared Resource with Improper Synchronization ('Race Condition')\n**Abstraction Level**: Class\n**Similarity Score**: 1245.71\n**Source**: sparse\n\n**Description**:\nThe product contains a concurrent",
  "analysis_with_relationships": "# Summary\n| CWE ID | CWE Name | Confidence | CWE Abstraction Level | CWE Vulnerability Mapping Label | CWE-Vulnerability Mapping Notes |\n|---|---|---|---|---|---|\n| CWE-787 | Out-of-bounds Write | 0.8 | Base | Primary | Allowed |\n| CWE-362 | Concurrent Execution using Shared Resource with Improper Synchronization ('Race Condition') | 0.7 | Class | Secondary | Allowed-with-Review |\n\n## Evidence and Confidence\n\n*   **Confidence Score:** 0.75\n*   **Evidence Strength:** MEDIUM\n\n## Relationship Analysis\nThe primary weakness is identified as CWE-787, representing an out-of-bounds write, which aligns with the \"memory corruption\" aspect of the vulnerability. CWE-362 is considered a secondary weakness because the vulnerability involves a **race condition** due to concurrent execution and improper synchronization, potentially leading to the memory corruption. CWE-362 is a Class-level CWE, and there might be more specific Base-level children, but the description provided doesn't give enough information to narrow it down further.\n\n```mermaid\ngraph TD\n    cwe787[\"CWE-787: Out-of-bounds Write\"]\n    cwe362[\"CWE-362: Concurrent Execution using Shared Resource with Improper Synchronization ('Race Condition')\"]\n    cwe119[\"CWE-119: Improper Restriction of Operations\"]\n    \n    cwe787 -->|CHILDOF| cwe119\n    cwe362 -->|PARENT_OF| cwe689[\"CWE-689: Race Condition Involving Read-Modify-Write\"]\n    cwe362 -->|PARENT_OF| cwe421[\"CWE-421: Race Condition During Initialization\"]\n    \n    classDef primary fill:#f96,stroke:#333,stroke-width:2px\n    classDef secondary fill:#69f,stroke:#333\n    class cwe787 primary\n    class cwe362 secondary\n```\n\n## Vulnerability Chain\nThe vulnerability chain starts with a **race condition** (CWE-362), possibly due to improper locking or synchronization. This leads to memory corruption, specifically an out-of-bounds write (CWE-787), when a compat IOCTL call is followed by another IOCTL call from userspace to a driver.\n\n## Summary of Analysis\nThe analysis focuses on the provided evidence, which highlights **memory corruption** and a **race condition**. The primary CWE, CWE-787, directly addresses the **memory corruption** resulting from an out-of-bounds write. The secondary CWE, CWE-362, accounts for the concurrent execution and synchronization issues that trigger the vulnerability. The relatively lower confidence is primarily due to the limited information on the specific root cause for the **race condition** or the **memory corruption** in the vulnerability description. Additional information is needed to determine a lower level child CWE for the **race condition** (CWE-362).\n\nRelevant CWE Information:\n\n# Enhanced Context (25 CWEs)\nThe following CWEs were identified as potentially relevant to this vulnerability:\n\n## CWE-782: Exposed IOCTL with Insufficient Access Control\n**Abstraction Level**: Variant\n**Similarity Score**: 0.74\n**Source**: dense\n\n**Description**:\nThe product implements an IOCTL with functionality that should be restricted, but it does not properly enforce access control for the IOCTL.\n\n**Mapping Guidance**:\n- Usage: Allowed\n- Rationale: This CWE entry is at the Variant level of abstraction, which is a preferred level of abstraction for mapping to the root causes of vulnerabilities.\n\n\n\n## CWE-131: Incorrect Calculation of Buffer Size\n**Abstraction Level**: Base\n**Similarity Score**: 0.72\n**Source**: dense\n\n**Description**:\nThe product does not correctly calculate the size to be used when allocating a buffer, which could lead to a buffer overflow.\n\n**Mapping Guidance**:\n- Usage: Allowed\n- Rationale: This CWE entry is at the Base level of abstraction, which is a preferred level of abstraction for mapping to the root causes of vulnerabilities.\n\n\n\n## CWE-667: Improper Locking\n**Abstraction Level**: Class\n**Similarity Score**: 0.72\n**Source**: dense\n\n**Description**:\nThe product does not properly acquire or release a lock on a resource, leading to unexpected resource state changes and behaviors.\n\n**Mapping Guidance**:\n- Usage: Allowed-with-Review\n- Rationale: This CWE entry is a Class and might have Base-level children that would be more appropriate\n\n\n\n## CWE-824: Access of Uninitialized Pointer\n**Abstraction Level**: Base\n**Similarity Score**: 0.72\n**Source**: dense\n\n**Description**:\nThe product accesses or uses a pointer that has not been initialized.\n\n**Mapping Guidance**:\n- Usage: Allowed\n- Rationale: This CWE entry is at the Base level of abstraction, which is a preferred level of abstraction for mapping to the root causes of vulnerabilities.\n\n\n\n## CWE-703: Improper Check or Handling of Exceptional Conditions\n**Abstraction Level**: Pillar\n**Similarity Score**: 0.71\n**Source**: dense\n\n**Description**:\nThe product does not properly anticipate or handle exceptional conditions that rarely occur during normal operation of the product.\n\n**Mapping Guidance**:\n- Usage: Discouraged\n- Rationale: This CWE entry is extremely high-level, a Pillar.\n\n\n\n## CWE-274: Improper Handling of Insufficient Privileges\n**Abstraction Level**: Base\n**Similarity Score**: 0.71\n**Source**: dense\n\n**Description**:\nThe product does not handle or incorrectly handles when it has insufficient privileges to perform an operation, leading to resultant weaknesses.\n\n**Mapping Guidance**:\n- Usage: Discouraged\n- Rationale: This CWE entry could be deprecated in a future version of CWE.\n\n\n\n## CWE-696: Incorrect Behavior Order\n**Abstraction Level**: Class\n**Similarity Score**: 0.71\n**Source**: dense\n\n**Description**:\nThe product performs multiple related behaviors, but the behaviors are performed in the wrong order in ways which may produce resultant weaknesses.\n\n**Mapping Guidance**:\n- Usage: Allowed-with-Review\n- Rationale: This CWE entry is a Class and might have Base-level children that would be more appropriate\n\n\n\n## CWE-134: Use of Externally-Controlled Format String\n**Abstraction Level**: Base\n**Similarity Score**: 0.71\n**Source**: dense\n\n**Description**:\nThe product uses a function that accepts a format string as an argument, but the format string originates from an external source.\n\n**Mapping Guidance**:\n- Usage: Allowed\n- Rationale: This CWE entry is at the Base level of abstraction, which is a preferred level of abstraction for mapping to the root causes of vulnerabilities.\n\n\n\n## CWE-657: Violation of Secure Design Principles\n**Abstraction Level**: Class\n**Similarity Score**: 0.70\n**Source**: dense\n\n**Description**:\nThe product violates well-established principles for secure design.\n\n**Mapping Guidance**:\n- Usage: Discouraged\n- Rationale: This CWE entry is a level-1 Class (i.e., a child of a Pillar). It might have lower-level children that would be more appropriate\n\n\n\n## CWE-367: Time-of-check Time-of-use (TOCTOU) Race Condition\n**Abstraction Level**: Base\n**Similarity Score**: 0.70\n**Source**: dense\n\n**Description**:\nThe product checks the state of a resource before using that resource, but the resource's state can change between the check and the use in a way that invalidates the results of the check. This can cause the product to perform invalid actions when the resource is in an unexpected state.\n\n**Mapping Guidance**:\n- Usage: Allowed\n- Rationale: This CWE entry is at the Base level of abstraction, which is a preferred level of abstraction for mapping to the root causes of vulnerabilities.\n\n\n\n## CWE-667: Improper Locking\n**Abstraction Level**: Class\n**Similarity Score**: 1299.44\n**Source**: sparse\n\n**Description**:\nThe product does not properly acquire or release a lock on a resource, leading to unexpected resource state changes and behaviors.\n\n**Mapping Guidance**:\n- Usage: Allowed-with-Review\n- Rationale: This CWE entry is a Class and might have Base-level children that would be more appropriate\n\n\n\n## CWE-367: Time-of-check Time-of-use (TOCTOU) Race Condition\n**Abstraction Level**: Base\n**Similarity Score**: 1249.26\n**Source**: sparse\n\n**Description**:\nThe product checks the state of a resource before using that resource, but the resource's state can change between the check and the use in a way that invalidates the results of the check. This can cause the product to perform invalid actions when the resource is in an unexpected state.\n\n**Mapping Guidance**:\n- Usage: Allowed\n- Rationale: This CWE entry is at the Base level of abstraction, which is a preferred level of abstraction for mapping to the root causes of vulnerabilities.\n\n\n\n## CWE-362: Concurrent Execution using Shared Resource with Improper Synchronization ('Race Condition')\n**Abstraction Level**: Class\n**Similarity Score**: 1245.71\n**Source**: sparse\n\n**Description**:\nThe product contains a concurrent\n\n\n## CWE Relationship Analysis\n\nCurrent CWEs represent these abstraction levels: .\n\n\n### Vulnerability Chain Analysis\n\n**Chain starting from CWE-274:**\n- 274 (Improper Handling of Insufficient Privileges) - ROOT\n\n\n**Chain starting from CWE-131:**\n- 131 (Incorrect Calculation of Buffer Size) - ROOT\n\n\n\n### CWE Relationship Diagram\n\n```mermaid\ngraph TD\n    classDef primary fill:#f96,stroke:#333,stroke-width:2px\n    classDef secondary fill:#69f,stroke:#333\n    classDef tertiary fill:#9e9,stroke:#333\n```",
  "criticism": "",
  "resolution": "",
  "relevant_cwes": [
    {
      "metadata": {
        "doc_id": "782",
        "name": "Exposed IOCTL with Insufficient Access Control",
        "source": "sparse",
        "original_content": "The product implements an IOCTL with functionality that should be restricted, but it does not properly enforce access control for the IOCTL.",
        "keyphrase_sources": [
          {
            "id": "weakness:Memory corruption",
            "keyphrase": "Memory corruption",
            "type": "weakness"
          },
          {
            "id": "weakness:race condition",
            "keyphrase": "race condition",
            "type": "weakness"
          },
          {
            "id": "impact:memory corruption",
            "keyphrase": "memory corruption",
            "type": "impact"
          }
        ]
      },
      "similarity": 165.40358660714335
    },
    {
      "metadata": {
        "doc_id": "362",
        "name": "Concurrent Execution using Shared Resource with Improper Synchronization ('Race Condition')",
        "source": "sparse",
        "original_content": "The product contains a concurrent code sequence that requires temporary, exclusive access to a shared resource, but a timing window exists in which the shared resource can be modified by another code sequence operating concurrently.",
        "keyphrase_sources": [
          {
            "id": "weakness:race condition",
            "keyphrase": "race condition",
            "type": "weakness"
          }
        ]
      },
      "similarity": 156.52771146948848
    },
    {
      "metadata": {
        "doc_id": "667",
        "name": "Improper Locking",
        "source": "sparse",
        "original_content": "The product does not properly acquire or release a lock on a resource, leading to unexpected resource state changes and behaviors.",
        "keyphrase_sources": [
          {
            "id": "weakness:Memory corruption",
            "keyphrase": "Memory corruption",
            "type": "weakness"
          },
          {
            "id": "weakness:race condition",
            "keyphrase": "race condition",
            "type": "weakness"
          },
          {
            "id": "impact:memory corruption",
            "keyphrase": "memory corruption",
            "type": "impact"
          }
        ]
      },
      "similarity": 155.64406200808196
    },
    {
      "metadata": {
        "doc_id": "787",
        "name": "Out-of-bounds Write",
        "source": "sparse",
        "original_content": "The product writes data past the end, or before the beginning, of the intended buffer.",
        "keyphrase_sources": [
          {
            "id": "weakness:Memory corruption",
            "keyphrase": "Memory corruption",
            "type": "weakness"
          },
          {
            "id": "impact:memory corruption",
            "keyphrase": "memory corruption",
            "type": "impact"
          }
        ]
      },
      "similarity": 154.66086653982364
    },
    {
      "metadata": {
        "doc_id": "394",
        "name": "Unexpected Status Code or Return Value",
        "source": "sparse",
        "original_content": "The product does not properly check when a function or operation returns a value that is legitimate for the function, but is not expected by the product.",
        "keyphrase_sources": [
          {
            "id": "weakness:Memory corruption",
            "keyphrase": "Memory corruption",
            "type": "weakness"
          },
          {
            "id": "impact:memory corruption",
            "keyphrase": "memory corruption",
            "type": "impact"
          }
        ]
      },
      "similarity": 151.88594953011827
    },
    {
      "metadata": {
        "doc_id": "131",
        "name": "Incorrect Calculation of Buffer Size",
        "source": "sparse",
        "original_content": "The product does not correctly calculate the size to be used when allocating a buffer, which could lead to a buffer overflow.",
        "keyphrase_sources": [
          {
            "id": "weakness:Memory corruption",
            "keyphrase": "Memory corruption",
            "type": "weakness"
          },
          {
            "id": "impact:memory corruption",
            "keyphrase": "memory corruption",
            "type": "impact"
          }
        ]
      },
      "similarity": 146.8863724827199
    },
    {
      "metadata": {
        "doc_id": "367",
        "name": "Time-of-check Time-of-use (TOCTOU) Race Condition",
        "source": "sparse",
        "original_content": "The product checks the state of a resource before using that resource, but the resource's state can change between the check and the use in a way that invalidates the results of the check. This can cause the product to perform invalid actions when the resource is in an unexpected state.",
        "keyphrase_sources": [
          {
            "id": "weakness:race condition",
            "keyphrase": "race condition",
            "type": "weakness"
          }
        ]
      },
      "similarity": 143.29447218758898
    },
    {
      "metadata": {
        "doc_id": "364",
        "name": "Signal Handler Race Condition",
        "source": "sparse",
        "original_content": "The product uses a signal handler that introduces a race condition.",
        "keyphrase_sources": [
          {
            "id": "weakness:race condition",
            "keyphrase": "race condition",
            "type": "weakness"
          }
        ]
      },
      "similarity": 137.4390077065814
    }
  ],
  "identified_cwes": {
    "analyzer": [
      "CWE-274",
      "CWE-131",
      "CWE-787",
      "CWE-667",
      "CWE-657",
      "CWE-782",
      "CWE-824",
      "CWE-362",
      "CWE-696",
      "CWE-689",
      "CWE-421",
      "CWE-119",
      "CWE-134",
      "CWE-703",
      "CWE-367"
    ],
    "critic_additional": []
  },
  "keyphrase_cwe_mapping": {
    "782": [
      {
        "id": "weakness:Memory corruption",
        "keyphrase": "Memory corruption",
        "type": "weakness"
      },
      {
        "id": "weakness:race condition",
        "keyphrase": "race condition",
        "type": "weakness"
      },
      {
        "id": "impact:memory corruption",
        "keyphrase": "memory corruption",
        "type": "impact"
      }
    ],
    "667": [
      {
        "id": "weakness:Memory corruption",
        "keyphrase": "Memory corruption",
        "type": "weakness"
      },
      {
        "id": "weakness:race condition",
        "keyphrase": "race condition",
        "type": "weakness"
      },
      {
        "id": "impact:memory corruption",
        "keyphrase": "memory corruption",
        "type": "impact"
      }
    ],
    "787": [
      {
        "id": "weakness:Memory corruption",
        "keyphrase": "Memory corruption",
        "type": "weakness"
      },
      {
        "id": "impact:memory corruption",
        "keyphrase": "memory corruption",
        "type": "impact"
      }
    ],
    "394": [
      {
        "id": "weakness:Memory corruption",
        "keyphrase": "Memory corruption",
        "type": "weakness"
      },
      {
        "id": "impact:memory corruption",
        "keyphrase": "memory corruption",
        "type": "impact"
      }
    ],
    "131": [
      {
        "id": "weakness:Memory corruption",
        "keyphrase": "Memory corruption",
        "type": "weakness"
      },
      {
        "id": "impact:memory corruption",
        "keyphrase": "memory corruption",
        "type": "impact"
      }
    ],
    "362": [
      {
        "id": "weakness:race condition",
        "keyphrase": "race condition",
        "type": "weakness"
      }
    ],
    "367": [
      {
        "id": "weakness:race condition",
        "keyphrase": "race condition",
        "type": "weakness"
      }
    ],
    "364": [
      {
        "id": "weakness:race condition",
        "keyphrase": "race condition",
        "type": "weakness"
      }
    ]
  }
}