{
  "vulnerability_info": "VulnerabilityInfo(cve_id='CVE-2025-23817', description='Cross-Site Request Forgery (CSRF) vulnerability in Mahadir Ahmad MHR-Custom-Anti-Copy allows Stored **XSS**.This issue affects MHR-Custom-Anti-Copy from n/a through 2.0.', key_phrases={'rootcause': 'cross-site request forgery', 'weakness': ['stored cross-site scripting', 'XSS'], 'impact': '', 'vector': '', 'attacker': '', 'product': 'Mahadir Ahmad MHR-Custom-Anti-Copy', 'version': 'n/a through 2', 'component': ''}, reference_content='Root cause of vulnerability:\\nThe MHR-Custom-Anti-Copy plugin is vulnerable to Cross Site Request Forgery (CSRF).\\n\\nWeaknesses/vulnerabilities present:\\nCross Site Request Forgery (CSRF) - allows a malicious actor to force higher privileged users to execute unwanted actions under their current authentication.\\n\\nImpact of exploitation:\\nA malicious actor can force higher privileged users to execute unwanted actions. The specific impact varies case by case.\\n\\nAttack vectors:\\nCross-Site Request Forgery (CSRF) attack.\\n\\nRequired attacker capabilities/position:\\nUnauthenticated attacker.\\n\\nMitigation or fix:\\nNo official fix available. Patchstack vPatching can auto-mitigate the vulnerability.\\n\\nAdditional details:\\n- CVSS score: 7.1 (Low severity)\\n- Affected versions: <= 2.0\\n- OWASP Top 10: A1: Broken Access Control\\n- Reported by: SOPROBRO\\n- Published by Patchstack: January 16, 2025\\n- Plugin: MHR-Custom-Anti-Copy\\n\\nThe content provides more detail than the placeholder CVE description, specifically detailing the vulnerability type (CSRF), its impact, and affected versions.', similar_info={'cwe_distribution': {}, 'cwe_consensus': '', 'similarity_stats': {'thresholds': [], 'total_samples_by_threshold': {}, 'top_cwes_by_threshold': {}}}, similarity_summary=SimilarityInsight(consensus_cwe='', top_cwes=[], confidence_levels={}, total_samples=0), analysis='', analysis_with_relationships='', criticism='', resolution='', relevant_cwes=[{'metadata': {'doc_id': '352', 'name': 'Cross-Site Request Forgery (CSRF)', 'source': 'sparse', 'original_content': 'The web application does not, or can not, sufficiently verify whether a well-formed, valid, consistent request was intentionally provided by the user who submitted the request.', 'keyphrase_sources': [{'id': 'rootcause:cross-site request forgery', 'keyphrase': 'cross-site request forgery', 'type': 'rootcause'}, {'id': 'weakness:stored cross-site scripting', 'keyphrase': 'stored cross-site scripting', 'type': 'weakness'}, {'id': 'weakness:XSS', 'keyphrase': 'XSS', 'type': 'weakness'}, {'id': 'product:Mahadir Ahmad MHR-Custom-Anti-Copy', 'keyphrase': 'Mahadir Ahmad MHR-Custom-Anti-Copy', 'type': 'product'}, {'id': 'version:n/a through 2', 'keyphrase': 'n/a through 2', 'type': 'version'}]}, 'similarity': np.float64(300.2531152320282)}, {'metadata': {'doc_id': '89', 'name': \"Improper Neutralization of Special Elements used in an SQL Command ('SQL Injection')\", 'source': 'sparse', 'original_content': 'The product constructs all or part of an SQL command using externally-influenced input from an upstream component, but it does not neutralize or incorrectly neutralizes special elements that could modify the intended SQL command when it is sent to a downstream component. Without sufficient removal or quoting of SQL syntax in user-controllable inputs, the generated SQL query can cause those inputs to be interpreted as SQL instead of ordinary user data.', 'keyphrase_sources': [{'id': 'rootcause:cross-site request forgery', 'keyphrase': 'cross-site request forgery', 'type': 'rootcause'}]}, 'similarity': np.float64(243.19304393547807)}, {'metadata': {'doc_id': '79', 'name': \"Improper Neutralization of Input During Web Page Generation ('Cross-site Scripting')\", 'source': 'sparse', 'original_content': 'The product does not neutralize or incorrectly neutralizes user-controllable input before it is placed in output that is used as a web page that is served to other users.', 'keyphrase_sources': [{'id': 'weakness:stored cross-site scripting', 'keyphrase': 'stored cross-site scripting', 'type': 'weakness'}, {'id': 'weakness:XSS', 'keyphrase': 'XSS', 'type': 'weakness'}, {'id': 'product:Mahadir Ahmad MHR-Custom-Anti-Copy', 'keyphrase': 'Mahadir Ahmad MHR-Custom-Anti-Copy', 'type': 'product'}, {'id': 'version:n/a through 2', 'keyphrase': 'n/a through 2', 'type': 'version'}]}, 'similarity': np.float64(239.0781176880759)}, {'metadata': {'doc_id': '1275', 'name': 'Sensitive Cookie with Improper SameSite Attribute', 'source': 'sparse', 'original_content': 'The SameSite attribute for sensitive cookies is not set, or an insecure value is used.', 'keyphrase_sources': [{'id': 'rootcause:cross-site request forgery', 'keyphrase': 'cross-site request forgery', 'type': 'rootcause'}, {'id': 'product:Mahadir Ahmad MHR-Custom-Anti-Copy', 'keyphrase': 'Mahadir Ahmad MHR-Custom-Anti-Copy', 'type': 'product'}]}, 'similarity': np.float64(236.845081864363)}, {'metadata': {'doc_id': '918', 'name': 'Server-Side Request Forgery (SSRF)', 'source': 'sparse', 'original_content': 'The web server receives a URL or similar request from an upstream component and retrieves the contents of this URL, but it does not sufficiently ensure that the request is being sent to the expected destination.', 'keyphrase_sources': [{'id': 'rootcause:cross-site request forgery', 'keyphrase': 'cross-site request forgery', 'type': 'rootcause'}]}, 'similarity': np.float64(234.07103063282216)}, {'metadata': {'doc_id': '601', 'name': \"URL Redirection to Untrusted Site ('Open Redirect')\", 'source': 'sparse', 'original_content': 'The web application accepts a user-controlled input that specifies a link to an external site, and uses that link in a redirect.', 'keyphrase_sources': [{'id': 'rootcause:cross-site request forgery', 'keyphrase': 'cross-site request forgery', 'type': 'rootcause'}]}, 'similarity': np.float64(222.7792135343558)}, {'metadata': {'doc_id': '116', 'name': 'Improper Encoding or Escaping of Output', 'source': 'sparse', 'original_content': 'The product prepares a structured message for communication with another component, but encoding or escaping of the data is either missing or done incorrectly. As a result, the intended structure of the message is not preserved.', 'keyphrase_sources': [{'id': 'weakness:stored cross-site scripting', 'keyphrase': 'stored cross-site scripting', 'type': 'weakness'}, {'id': 'weakness:XSS', 'keyphrase': 'XSS', 'type': 'weakness'}, {'id': 'product:Mahadir Ahmad MHR-Custom-Anti-Copy', 'keyphrase': 'Mahadir Ahmad MHR-Custom-Anti-Copy', 'type': 'product'}]}, 'similarity': np.float64(219.35592258357738)}, {'metadata': {'doc_id': '80', 'name': 'Improper Neutralization of Script-Related HTML Tags in a Web Page (Basic XSS)', 'source': 'sparse', 'original_content': 'The product receives input from an upstream component, but it does not neutralize or incorrectly neutralizes special characters such as \"<\", \">\", and \"&\" that could be interpreted as web-scripting elements when they are sent to a downstream component that processes web pages.', 'keyphrase_sources': [{'id': 'weakness:stored cross-site scripting', 'keyphrase': 'stored cross-site scripting', 'type': 'weakness'}]}, 'similarity': np.float64(209.91108310080557)}, {'metadata': {'doc_id': '434', 'name': 'Unrestricted Upload of File with Dangerous Type', 'source': 'sparse', 'original_content': 'The product allows the upload or transfer of dangerous file types that are automatically processed within its environment.', 'keyphrase_sources': [{'id': 'weakness:stored cross-site scripting', 'keyphrase': 'stored cross-site scripting', 'type': 'weakness'}, {'id': 'weakness:XSS', 'keyphrase': 'XSS', 'type': 'weakness'}, {'id': 'version:n/a through 2', 'keyphrase': 'n/a through 2', 'type': 'version'}]}, 'similarity': np.float64(199.5353617535373)}, {'metadata': {'doc_id': '1004', 'name': \"Sensitive Cookie Without 'HttpOnly' Flag\", 'source': 'sparse', 'original_content': 'The product uses a cookie to store sensitive information, but the cookie is not marked with the HttpOnly flag.', 'keyphrase_sources': [{'id': 'weakness:XSS', 'keyphrase': 'XSS', 'type': 'weakness'}]}, 'similarity': np.float64(143.55840017232558)}, {'metadata': {'doc_id': '611', 'name': 'Improper Restriction of XML External Entity Reference', 'source': 'sparse', 'original_content': 'The product processes an XML document that can contain XML entities with URIs that resolve to documents outside of the intended sphere of control, causing the product to embed incorrect documents into its output.', 'keyphrase_sources': [{'id': 'version:n/a through 2', 'keyphrase': 'n/a through 2', 'type': 'version'}]}, 'similarity': np.float64(61.74368686430733)}, {'metadata': {'doc_id': '22', 'name': \"Improper Limitation of a Pathname to a Restricted Directory ('Path Traversal')\", 'source': 'sparse', 'original_content': 'The product uses external input to construct a pathname that is intended to identify a file or directory that is located underneath a restricted parent directory, but the product does not properly neutralize special elements within the pathname that can cause the pathname to resolve to a location that is outside of the restricted directory.', 'keyphrase_sources': [{'id': 'product:Mahadir Ahmad MHR-Custom-Anti-Copy', 'keyphrase': 'Mahadir Ahmad MHR-Custom-Anti-Copy', 'type': 'product'}, {'id': 'version:n/a through 2', 'keyphrase': 'n/a through 2', 'type': 'version'}]}, 'similarity': np.float64(48.088355500008895)}], identified_cwes={'analyzer': [], 'critic_additional': []})",
  "retrieval_results": {
    "has_multiple_keyphrases": true,
    "keyphrase_cwe_sets": {
      "rootcause:cross-site request forgery": {
        "keyphrase": "cross-site request forgery",
        "type": "rootcause",
        "cwes": [
          {
            "metadata": {
              "doc_id": "352",
              "name": "Cross-Site Request Forgery (CSRF)",
              "source": "sparse",
              "original_content": "The web application does not, or can not, sufficiently verify whether a well-formed, valid, consistent request was intentionally provided by the user who submitted the request.",
              "keyphrase_sources": [
                {
                  "id": "rootcause:cross-site request forgery",
                  "keyphrase": "cross-site request forgery",
                  "type": "rootcause"
                },
                {
                  "id": "weakness:stored cross-site scripting",
                  "keyphrase": "stored cross-site scripting",
                  "type": "weakness"
                },
                {
                  "id": "weakness:XSS",
                  "keyphrase": "XSS",
                  "type": "weakness"
                },
                {
                  "id": "product:Mahadir Ahmad MHR-Custom-Anti-Copy",
                  "keyphrase": "Mahadir Ahmad MHR-Custom-Anti-Copy",
                  "type": "product"
                },
                {
                  "id": "version:n/a through 2",
                  "keyphrase": "n/a through 2",
                  "type": "version"
                }
              ]
            },
            "similarity": 300.2531152320282
          },
          {
            "metadata": {
              "doc_id": "89",
              "name": "Improper Neutralization of Special Elements used in an SQL Command ('SQL Injection')",
              "source": "sparse",
              "original_content": "The product constructs all or part of an SQL command using externally-influenced input from an upstream component, but it does not neutralize or incorrectly neutralizes special elements that could modify the intended SQL command when it is sent to a downstream component. Without sufficient removal or quoting of SQL syntax in user-controllable inputs, the generated SQL query can cause those inputs to be interpreted as SQL instead of ordinary user data.",
              "keyphrase_sources": [
                {
                  "id": "rootcause:cross-site request forgery",
                  "keyphrase": "cross-site request forgery",
                  "type": "rootcause"
                }
              ]
            },
            "similarity": 243.19304393547807
          },
          {
            "metadata": {
              "doc_id": "1275",
              "name": "Sensitive Cookie with Improper SameSite Attribute",
              "source": "sparse",
              "original_content": "The SameSite attribute for sensitive cookies is not set, or an insecure value is used.",
              "keyphrase_sources": [
                {
                  "id": "rootcause:cross-site request forgery",
                  "keyphrase": "cross-site request forgery",
                  "type": "rootcause"
                },
                {
                  "id": "product:Mahadir Ahmad MHR-Custom-Anti-Copy",
                  "keyphrase": "Mahadir Ahmad MHR-Custom-Anti-Copy",
                  "type": "product"
                }
              ]
            },
            "similarity": 236.845081864363
          },
          {
            "metadata": {
              "doc_id": "918",
              "name": "Server-Side Request Forgery (SSRF)",
              "source": "sparse",
              "original_content": "The web server receives a URL or similar request from an upstream component and retrieves the contents of this URL, but it does not sufficiently ensure that the request is being sent to the expected destination.",
              "keyphrase_sources": [
                {
                  "id": "rootcause:cross-site request forgery",
                  "keyphrase": "cross-site request forgery",
                  "type": "rootcause"
                }
              ]
            },
            "similarity": 234.07103063282216
          },
          {
            "metadata": {
              "doc_id": "601",
              "name": "URL Redirection to Untrusted Site ('Open Redirect')",
              "source": "sparse",
              "original_content": "The web application accepts a user-controlled input that specifies a link to an external site, and uses that link in a redirect.",
              "keyphrase_sources": [
                {
                  "id": "rootcause:cross-site request forgery",
                  "keyphrase": "cross-site request forgery",
                  "type": "rootcause"
                }
              ]
            },
            "similarity": 222.7792135343558
          }
        ]
      },
      "weakness:stored cross-site scripting": {
        "keyphrase": "stored cross-site scripting",
        "type": "weakness",
        "cwes": [
          {
            "metadata": {
              "doc_id": "352",
              "name": "Cross-Site Request Forgery (CSRF)",
              "source": "sparse",
              "original_content": "The web application does not, or can not, sufficiently verify whether a well-formed, valid, consistent request was intentionally provided by the user who submitted the request."
            },
            "similarity": 284.82476137295464
          },
          {
            "metadata": {
              "doc_id": "79",
              "name": "Improper Neutralization of Input During Web Page Generation ('Cross-site Scripting')",
              "source": "sparse",
              "original_content": "The product does not neutralize or incorrectly neutralizes user-controllable input before it is placed in output that is used as a web page that is served to other users.",
              "keyphrase_sources": [
                {
                  "id": "weakness:stored cross-site scripting",
                  "keyphrase": "stored cross-site scripting",
                  "type": "weakness"
                },
                {
                  "id": "weakness:XSS",
                  "keyphrase": "XSS",
                  "type": "weakness"
                },
                {
                  "id": "product:Mahadir Ahmad MHR-Custom-Anti-Copy",
                  "keyphrase": "Mahadir Ahmad MHR-Custom-Anti-Copy",
                  "type": "product"
                },
                {
                  "id": "version:n/a through 2",
                  "keyphrase": "n/a through 2",
                  "type": "version"
                }
              ]
            },
            "similarity": 239.0781176880759
          },
          {
            "metadata": {
              "doc_id": "116",
              "name": "Improper Encoding or Escaping of Output",
              "source": "sparse",
              "original_content": "The product prepares a structured message for communication with another component, but encoding or escaping of the data is either missing or done incorrectly. As a result, the intended structure of the message is not preserved.",
              "keyphrase_sources": [
                {
                  "id": "weakness:stored cross-site scripting",
                  "keyphrase": "stored cross-site scripting",
                  "type": "weakness"
                },
                {
                  "id": "weakness:XSS",
                  "keyphrase": "XSS",
                  "type": "weakness"
                },
                {
                  "id": "product:Mahadir Ahmad MHR-Custom-Anti-Copy",
                  "keyphrase": "Mahadir Ahmad MHR-Custom-Anti-Copy",
                  "type": "product"
                }
              ]
            },
            "similarity": 219.35592258357738
          },
          {
            "metadata": {
              "doc_id": "80",
              "name": "Improper Neutralization of Script-Related HTML Tags in a Web Page (Basic XSS)",
              "source": "sparse",
              "original_content": "The product receives input from an upstream component, but it does not neutralize or incorrectly neutralizes special characters such as \"<\", \">\", and \"&\" that could be interpreted as web-scripting elements when they are sent to a downstream component that processes web pages.",
              "keyphrase_sources": [
                {
                  "id": "weakness:stored cross-site scripting",
                  "keyphrase": "stored cross-site scripting",
                  "type": "weakness"
                }
              ]
            },
            "similarity": 209.91108310080557
          },
          {
            "metadata": {
              "doc_id": "434",
              "name": "Unrestricted Upload of File with Dangerous Type",
              "source": "sparse",
              "original_content": "The product allows the upload or transfer of dangerous file types that are automatically processed within its environment.",
              "keyphrase_sources": [
                {
                  "id": "weakness:stored cross-site scripting",
                  "keyphrase": "stored cross-site scripting",
                  "type": "weakness"
                },
                {
                  "id": "weakness:XSS",
                  "keyphrase": "XSS",
                  "type": "weakness"
                },
                {
                  "id": "version:n/a through 2",
                  "keyphrase": "n/a through 2",
                  "type": "version"
                }
              ]
            },
            "similarity": 199.5353617535373
          }
        ]
      },
      "weakness:XSS": {
        "keyphrase": "XSS",
        "type": "weakness",
        "cwes": [
          {
            "metadata": {
              "doc_id": "352",
              "name": "Cross-Site Request Forgery (CSRF)",
              "source": "sparse",
              "original_content": "The web application does not, or can not, sufficiently verify whether a well-formed, valid, consistent request was intentionally provided by the user who submitted the request."
            },
            "similarity": 194.0564912699085
          },
          {
            "metadata": {
              "doc_id": "79",
              "name": "Improper Neutralization of Input During Web Page Generation ('Cross-site Scripting')",
              "source": "sparse",
              "original_content": "The product does not neutralize or incorrectly neutralizes user-controllable input before it is placed in output that is used as a web page that is served to other users."
            },
            "similarity": 160.28960330793305
          },
          {
            "metadata": {
              "doc_id": "116",
              "name": "Improper Encoding or Escaping of Output",
              "source": "sparse",
              "original_content": "The product prepares a structured message for communication with another component, but encoding or escaping of the data is either missing or done incorrectly. As a result, the intended structure of the message is not preserved."
            },
            "similarity": 153.51045780219988
          },
          {
            "metadata": {
              "doc_id": "434",
              "name": "Unrestricted Upload of File with Dangerous Type",
              "source": "sparse",
              "original_content": "The product allows the upload or transfer of dangerous file types that are automatically processed within its environment."
            },
            "similarity": 144.12349416514166
          },
          {
            "metadata": {
              "doc_id": "1004",
              "name": "Sensitive Cookie Without 'HttpOnly' Flag",
              "source": "sparse",
              "original_content": "The product uses a cookie to store sensitive information, but the cookie is not marked with the HttpOnly flag.",
              "keyphrase_sources": [
                {
                  "id": "weakness:XSS",
                  "keyphrase": "XSS",
                  "type": "weakness"
                }
              ]
            },
            "similarity": 143.55840017232558
          }
        ]
      },
      "product:Mahadir Ahmad MHR-Custom-Anti-Copy": {
        "keyphrase": "Mahadir Ahmad MHR-Custom-Anti-Copy",
        "type": "product",
        "cwes": [
          {
            "metadata": {
              "doc_id": "352",
              "name": "Cross-Site Request Forgery (CSRF)",
              "source": "sparse",
              "original_content": "The web application does not, or can not, sufficiently verify whether a well-formed, valid, consistent request was intentionally provided by the user who submitted the request."
            },
            "similarity": 65.52646235139491
          },
          {
            "metadata": {
              "doc_id": "1275",
              "name": "Sensitive Cookie with Improper SameSite Attribute",
              "source": "sparse",
              "original_content": "The SameSite attribute for sensitive cookies is not set, or an insecure value is used."
            },
            "similarity": 55.4989366281306
          },
          {
            "metadata": {
              "doc_id": "116",
              "name": "Improper Encoding or Escaping of Output",
              "source": "sparse",
              "original_content": "The product prepares a structured message for communication with another component, but encoding or escaping of the data is either missing or done incorrectly. As a result, the intended structure of the message is not preserved."
            },
            "similarity": 52.19273716498162
          },
          {
            "metadata": {
              "doc_id": "79",
              "name": "Improper Neutralization of Input During Web Page Generation ('Cross-site Scripting')",
              "source": "sparse",
              "original_content": "The product does not neutralize or incorrectly neutralizes user-controllable input before it is placed in output that is used as a web page that is served to other users."
            },
            "similarity": 48.344578675228746
          },
          {
            "metadata": {
              "doc_id": "22",
              "name": "Improper Limitation of a Pathname to a Restricted Directory ('Path Traversal')",
              "source": "sparse",
              "original_content": "The product uses external input to construct a pathname that is intended to identify a file or directory that is located underneath a restricted parent directory, but the product does not properly neutralize special elements within the pathname that can cause the pathname to resolve to a location that is outside of the restricted directory.",
              "keyphrase_sources": [
                {
                  "id": "product:Mahadir Ahmad MHR-Custom-Anti-Copy",
                  "keyphrase": "Mahadir Ahmad MHR-Custom-Anti-Copy",
                  "type": "product"
                },
                {
                  "id": "version:n/a through 2",
                  "keyphrase": "n/a through 2",
                  "type": "version"
                }
              ]
            },
            "similarity": 48.088355500008895
          }
        ]
      },
      "version:n/a through 2": {
        "keyphrase": "n/a through 2",
        "type": "version",
        "cwes": [
          {
            "metadata": {
              "doc_id": "352",
              "name": "Cross-Site Request Forgery (CSRF)",
              "source": "sparse",
              "original_content": "The web application does not, or can not, sufficiently verify whether a well-formed, valid, consistent request was intentionally provided by the user who submitted the request."
            },
            "similarity": 72.39365002625372
          },
          {
            "metadata": {
              "doc_id": "22",
              "name": "Improper Limitation of a Pathname to a Restricted Directory ('Path Traversal')",
              "source": "sparse",
              "original_content": "The product uses external input to construct a pathname that is intended to identify a file or directory that is located underneath a restricted parent directory, but the product does not properly neutralize special elements within the pathname that can cause the pathname to resolve to a location that is outside of the restricted directory."
            },
            "similarity": 63.12058719194007
          },
          {
            "metadata": {
              "doc_id": "611",
              "name": "Improper Restriction of XML External Entity Reference",
              "source": "sparse",
              "original_content": "The product processes an XML document that can contain XML entities with URIs that resolve to documents outside of the intended sphere of control, causing the product to embed incorrect documents into its output.",
              "keyphrase_sources": [
                {
                  "id": "version:n/a through 2",
                  "keyphrase": "n/a through 2",
                  "type": "version"
                }
              ]
            },
            "similarity": 61.74368686430733
          },
          {
            "metadata": {
              "doc_id": "434",
              "name": "Unrestricted Upload of File with Dangerous Type",
              "source": "sparse",
              "original_content": "The product allows the upload or transfer of dangerous file types that are automatically processed within its environment."
            },
            "similarity": 61.559034245203
          },
          {
            "metadata": {
              "doc_id": "79",
              "name": "Improper Neutralization of Input During Web Page Generation ('Cross-site Scripting')",
              "source": "sparse",
              "original_content": "The product does not neutralize or incorrectly neutralizes user-controllable input before it is placed in output that is used as a web page that is served to other users."
            },
            "similarity": 58.2438367901338
          }
        ]
      }
    },
    "keyphrase_mapping": {
      "352": [
        {
          "id": "rootcause:cross-site request forgery",
          "keyphrase": "cross-site request forgery",
          "type": "rootcause"
        },
        {
          "id": "weakness:stored cross-site scripting",
          "keyphrase": "stored cross-site scripting",
          "type": "weakness"
        },
        {
          "id": "weakness:XSS",
          "keyphrase": "XSS",
          "type": "weakness"
        },
        {
          "id": "product:Mahadir Ahmad MHR-Custom-Anti-Copy",
          "keyphrase": "Mahadir Ahmad MHR-Custom-Anti-Copy",
          "type": "product"
        },
        {
          "id": "version:n/a through 2",
          "keyphrase": "n/a through 2",
          "type": "version"
        }
      ],
      "89": [
        {
          "id": "rootcause:cross-site request forgery",
          "keyphrase": "cross-site request forgery",
          "type": "rootcause"
        }
      ],
      "1275": [
        {
          "id": "rootcause:cross-site request forgery",
          "keyphrase": "cross-site request forgery",
          "type": "rootcause"
        },
        {
          "id": "product:Mahadir Ahmad MHR-Custom-Anti-Copy",
          "keyphrase": "Mahadir Ahmad MHR-Custom-Anti-Copy",
          "type": "product"
        }
      ],
      "918": [
        {
          "id": "rootcause:cross-site request forgery",
          "keyphrase": "cross-site request forgery",
          "type": "rootcause"
        }
      ],
      "601": [
        {
          "id": "rootcause:cross-site request forgery",
          "keyphrase": "cross-site request forgery",
          "type": "rootcause"
        }
      ],
      "79": [
        {
          "id": "weakness:stored cross-site scripting",
          "keyphrase": "stored cross-site scripting",
          "type": "weakness"
        },
        {
          "id": "weakness:XSS",
          "keyphrase": "XSS",
          "type": "weakness"
        },
        {
          "id": "product:Mahadir Ahmad MHR-Custom-Anti-Copy",
          "keyphrase": "Mahadir Ahmad MHR-Custom-Anti-Copy",
          "type": "product"
        },
        {
          "id": "version:n/a through 2",
          "keyphrase": "n/a through 2",
          "type": "version"
        }
      ],
      "116": [
        {
          "id": "weakness:stored cross-site scripting",
          "keyphrase": "stored cross-site scripting",
          "type": "weakness"
        },
        {
          "id": "weakness:XSS",
          "keyphrase": "XSS",
          "type": "weakness"
        },
        {
          "id": "product:Mahadir Ahmad MHR-Custom-Anti-Copy",
          "keyphrase": "Mahadir Ahmad MHR-Custom-Anti-Copy",
          "type": "product"
        }
      ],
      "80": [
        {
          "id": "weakness:stored cross-site scripting",
          "keyphrase": "stored cross-site scripting",
          "type": "weakness"
        }
      ],
      "434": [
        {
          "id": "weakness:stored cross-site scripting",
          "keyphrase": "stored cross-site scripting",
          "type": "weakness"
        },
        {
          "id": "weakness:XSS",
          "keyphrase": "XSS",
          "type": "weakness"
        },
        {
          "id": "version:n/a through 2",
          "keyphrase": "n/a through 2",
          "type": "version"
        }
      ],
      "1004": [
        {
          "id": "weakness:XSS",
          "keyphrase": "XSS",
          "type": "weakness"
        }
      ],
      "22": [
        {
          "id": "product:Mahadir Ahmad MHR-Custom-Anti-Copy",
          "keyphrase": "Mahadir Ahmad MHR-Custom-Anti-Copy",
          "type": "product"
        },
        {
          "id": "version:n/a through 2",
          "keyphrase": "n/a through 2",
          "type": "version"
        }
      ],
      "611": [
        {
          "id": "version:n/a through 2",
          "keyphrase": "n/a through 2",
          "type": "version"
        }
      ]
    },
    "relevant_cwes": [
      {
        "metadata": {
          "doc_id": "352",
          "name": "Cross-Site Request Forgery (CSRF)",
          "source": "sparse",
          "original_content": "The web application does not, or can not, sufficiently verify whether a well-formed, valid, consistent request was intentionally provided by the user who submitted the request.",
          "keyphrase_sources": [
            {
              "id": "rootcause:cross-site request forgery",
              "keyphrase": "cross-site request forgery",
              "type": "rootcause"
            },
            {
              "id": "weakness:stored cross-site scripting",
              "keyphrase": "stored cross-site scripting",
              "type": "weakness"
            },
            {
              "id": "weakness:XSS",
              "keyphrase": "XSS",
              "type": "weakness"
            },
            {
              "id": "product:Mahadir Ahmad MHR-Custom-Anti-Copy",
              "keyphrase": "Mahadir Ahmad MHR-Custom-Anti-Copy",
              "type": "product"
            },
            {
              "id": "version:n/a through 2",
              "keyphrase": "n/a through 2",
              "type": "version"
            }
          ]
        },
        "similarity": 300.2531152320282
      },
      {
        "metadata": {
          "doc_id": "89",
          "name": "Improper Neutralization of Special Elements used in an SQL Command ('SQL Injection')",
          "source": "sparse",
          "original_content": "The product constructs all or part of an SQL command using externally-influenced input from an upstream component, but it does not neutralize or incorrectly neutralizes special elements that could modify the intended SQL command when it is sent to a downstream component. Without sufficient removal or quoting of SQL syntax in user-controllable inputs, the generated SQL query can cause those inputs to be interpreted as SQL instead of ordinary user data.",
          "keyphrase_sources": [
            {
              "id": "rootcause:cross-site request forgery",
              "keyphrase": "cross-site request forgery",
              "type": "rootcause"
            }
          ]
        },
        "similarity": 243.19304393547807
      },
      {
        "metadata": {
          "doc_id": "79",
          "name": "Improper Neutralization of Input During Web Page Generation ('Cross-site Scripting')",
          "source": "sparse",
          "original_content": "The product does not neutralize or incorrectly neutralizes user-controllable input before it is placed in output that is used as a web page that is served to other users.",
          "keyphrase_sources": [
            {
              "id": "weakness:stored cross-site scripting",
              "keyphrase": "stored cross-site scripting",
              "type": "weakness"
            },
            {
              "id": "weakness:XSS",
              "keyphrase": "XSS",
              "type": "weakness"
            },
            {
              "id": "product:Mahadir Ahmad MHR-Custom-Anti-Copy",
              "keyphrase": "Mahadir Ahmad MHR-Custom-Anti-Copy",
              "type": "product"
            },
            {
              "id": "version:n/a through 2",
              "keyphrase": "n/a through 2",
              "type": "version"
            }
          ]
        },
        "similarity": 239.0781176880759
      },
      {
        "metadata": {
          "doc_id": "1275",
          "name": "Sensitive Cookie with Improper SameSite Attribute",
          "source": "sparse",
          "original_content": "The SameSite attribute for sensitive cookies is not set, or an insecure value is used.",
          "keyphrase_sources": [
            {
              "id": "rootcause:cross-site request forgery",
              "keyphrase": "cross-site request forgery",
              "type": "rootcause"
            },
            {
              "id": "product:Mahadir Ahmad MHR-Custom-Anti-Copy",
              "keyphrase": "Mahadir Ahmad MHR-Custom-Anti-Copy",
              "type": "product"
            }
          ]
        },
        "similarity": 236.845081864363
      },
      {
        "metadata": {
          "doc_id": "918",
          "name": "Server-Side Request Forgery (SSRF)",
          "source": "sparse",
          "original_content": "The web server receives a URL or similar request from an upstream component and retrieves the contents of this URL, but it does not sufficiently ensure that the request is being sent to the expected destination.",
          "keyphrase_sources": [
            {
              "id": "rootcause:cross-site request forgery",
              "keyphrase": "cross-site request forgery",
              "type": "rootcause"
            }
          ]
        },
        "similarity": 234.07103063282216
      },
      {
        "metadata": {
          "doc_id": "601",
          "name": "URL Redirection to Untrusted Site ('Open Redirect')",
          "source": "sparse",
          "original_content": "The web application accepts a user-controlled input that specifies a link to an external site, and uses that link in a redirect.",
          "keyphrase_sources": [
            {
              "id": "rootcause:cross-site request forgery",
              "keyphrase": "cross-site request forgery",
              "type": "rootcause"
            }
          ]
        },
        "similarity": 222.7792135343558
      },
      {
        "metadata": {
          "doc_id": "116",
          "name": "Improper Encoding or Escaping of Output",
          "source": "sparse",
          "original_content": "The product prepares a structured message for communication with another component, but encoding or escaping of the data is either missing or done incorrectly. As a result, the intended structure of the message is not preserved.",
          "keyphrase_sources": [
            {
              "id": "weakness:stored cross-site scripting",
              "keyphrase": "stored cross-site scripting",
              "type": "weakness"
            },
            {
              "id": "weakness:XSS",
              "keyphrase": "XSS",
              "type": "weakness"
            },
            {
              "id": "product:Mahadir Ahmad MHR-Custom-Anti-Copy",
              "keyphrase": "Mahadir Ahmad MHR-Custom-Anti-Copy",
              "type": "product"
            }
          ]
        },
        "similarity": 219.35592258357738
      },
      {
        "metadata": {
          "doc_id": "80",
          "name": "Improper Neutralization of Script-Related HTML Tags in a Web Page (Basic XSS)",
          "source": "sparse",
          "original_content": "The product receives input from an upstream component, but it does not neutralize or incorrectly neutralizes special characters such as \"<\", \">\", and \"&\" that could be interpreted as web-scripting elements when they are sent to a downstream component that processes web pages.",
          "keyphrase_sources": [
            {
              "id": "weakness:stored cross-site scripting",
              "keyphrase": "stored cross-site scripting",
              "type": "weakness"
            }
          ]
        },
        "similarity": 209.91108310080557
      },
      {
        "metadata": {
          "doc_id": "434",
          "name": "Unrestricted Upload of File with Dangerous Type",
          "source": "sparse",
          "original_content": "The product allows the upload or transfer of dangerous file types that are automatically processed within its environment.",
          "keyphrase_sources": [
            {
              "id": "weakness:stored cross-site scripting",
              "keyphrase": "stored cross-site scripting",
              "type": "weakness"
            },
            {
              "id": "weakness:XSS",
              "keyphrase": "XSS",
              "type": "weakness"
            },
            {
              "id": "version:n/a through 2",
              "keyphrase": "n/a through 2",
              "type": "version"
            }
          ]
        },
        "similarity": 199.5353617535373
      },
      {
        "metadata": {
          "doc_id": "1004",
          "name": "Sensitive Cookie Without 'HttpOnly' Flag",
          "source": "sparse",
          "original_content": "The product uses a cookie to store sensitive information, but the cookie is not marked with the HttpOnly flag.",
          "keyphrase_sources": [
            {
              "id": "weakness:XSS",
              "keyphrase": "XSS",
              "type": "weakness"
            }
          ]
        },
        "similarity": 143.55840017232558
      },
      {
        "metadata": {
          "doc_id": "611",
          "name": "Improper Restriction of XML External Entity Reference",
          "source": "sparse",
          "original_content": "The product processes an XML document that can contain XML entities with URIs that resolve to documents outside of the intended sphere of control, causing the product to embed incorrect documents into its output.",
          "keyphrase_sources": [
            {
              "id": "version:n/a through 2",
              "keyphrase": "n/a through 2",
              "type": "version"
            }
          ]
        },
        "similarity": 61.74368686430733
      },
      {
        "metadata": {
          "doc_id": "22",
          "name": "Improper Limitation of a Pathname to a Restricted Directory ('Path Traversal')",
          "source": "sparse",
          "original_content": "The product uses external input to construct a pathname that is intended to identify a file or directory that is located underneath a restricted parent directory, but the product does not properly neutralize special elements within the pathname that can cause the pathname to resolve to a location that is outside of the restricted directory.",
          "keyphrase_sources": [
            {
              "id": "product:Mahadir Ahmad MHR-Custom-Anti-Copy",
              "keyphrase": "Mahadir Ahmad MHR-Custom-Anti-Copy",
              "type": "product"
            },
            {
              "id": "version:n/a through 2",
              "keyphrase": "n/a through 2",
              "type": "version"
            }
          ]
        },
        "similarity": 48.088355500008895
      }
    ],
    "enhanced_query": "# Vulnerability Description\n\n    Cross-Site Request Forgery (CSRF) vulnerability in Mahadir Ahmad MHR-Custom-Anti-Copy allows Stored **XSS**.This issue affects MHR-Custom-Anti-Copy from n/a through 2.0.\n\n    # Keyphrase-Specific CWE Analysis\n    This vulnerability contains multiple keyphrases that may map to different CWEs. \n    Please analyze each keyphrase separately and determine the most appropriate CWE(s) for each.\n\n    ## ROOTCAUSE: 'cross-site request forgery'\n\nRelevant CWEs for this ROOTCAUSE:\n\n### 1. CWE-352: Cross-Site Request Forgery (CSRF) (Score: 300.25)\n\nThe web application does not, or can not, sufficiently verify whether a well-formed, valid, consistent request was intentionally provided by the user who submitted the request....\n\n### 2. CWE-89: Improper Neutralization of Special Elements used in an SQL Command ('SQL Injection') (Score: 243.19)\n\nThe product constructs all or part of an SQL command using externally-influenced input from an upstream component, but it does not neutralize or incorrectly neutralizes special elements that could modify the intended SQL command when it is sent to a downstream component. Without sufficient removal o...\n\n### 3. CWE-1275: Sensitive Cookie with Improper SameSite Attribute (Score: 236.85)\n\nThe SameSite attribute for sensitive cookies is not set, or an insecure value is used....\n\n### 4. CWE-918: Server-Side Request Forgery (SSRF) (Score: 234.07)\n\nThe web server receives a URL or similar request from an upstream component and retrieves the contents of this URL, but it does not sufficiently ensure that the request is being sent to the expected destination....\n\n### 5. CWE-601: URL Redirection to Untrusted Site ('Open Redirect') (Score: 222.78)\n\nThe web application accepts a user-controlled input that specifies a link to an external site, and uses that link in a redirect....\n\n## WEAKNESS: 'stored cross-site scripting'\n\nRelevant CWEs for this WEAKNESS:\n\n### 1. CWE-352: Cross-Site Request Forgery (CSRF) (Score: 300.25)\n\nThe web application does not, or can not, sufficiently verify whether a well-formed, valid, consistent request was intentionally provided by the user who submitted the request....\n\n### 2. CWE-79: Improper Neutralization of Input During Web Page Generation ('Cross-site Scripting') (Score: 239.08)\n\nThe product does not neutralize or incorrectly neutralizes user-controllable input before it is placed in output that is used as a web page that is served to other users....\n\n### 3. CWE-116: Improper Encoding or Escaping of Output (Score: 219.36)\n\nThe product prepares a structured message for communication with another component, but encoding or escaping of the data is either missing or done incorrectly. As a result, the intended structure of the message is not preserved....\n\n### 4. CWE-80: Improper Neutralization of Script-Related HTML Tags in a Web Page (Basic XSS) (Score: 209.91)\n\nThe product receives input from an upstream component, but it does not neutralize or incorrectly neutralizes special characters such as \"<\", \">\", and \"&\" that could be interpreted as web-scripting elements when they are sent to a downstream component that processes web pages....\n\n### 5. CWE-434: Unrestricted Upload of File with Dangerous Type (Score: 199.54)\n\nThe product allows the upload or transfer of dangerous file types that are automatically processed within its environment....\n\n## WEAKNESS: 'XSS'\n\nRelevant CWEs for this WEAKNESS:\n\n### 1. CWE-352: Cross-Site Request Forgery (CSRF) (Score: 300.25)\n\nThe web application does not, or can not, sufficiently verify whether a well-formed, valid, consistent request was intentionally provided by the user who submitted the request....\n\n### 2. CWE-79: Improper Neutralization of Input During Web Page Generation ('Cross-site Scripting') (Score: 239.08)\n\nThe product does not neutralize or incorrectly neutralizes user-controllable input before it is placed in output that is used as a web page that is served to other users....\n\n### 3. CWE-116: Improper Encoding or Escaping of Output (Score: 219.36)\n\nThe product prepares a structured message for communication with another component, but encoding or escaping of the data is either missing or done incorrectly. As a result, the intended structure of the message is not preserved....\n\n### 4. CWE-434: Unrestricted Upload of File with Dangerous Type (Score: 199.54)\n\nThe product allows the upload or transfer of dangerous file types that are automatically processed within its environment....\n\n### 5. CWE-1004: Sensitive Cookie Without 'HttpOnly' Flag (Score: 143.56)\n\nThe product uses a cookie to store sensitive information, but the cookie is not marked with the HttpOnly flag....\n\n## PRODUCT: 'Mahadir Ahmad MHR-Custom-Anti-Copy'\n\nRelevant CWEs for this PRODUCT:\n\n### 1. CWE-352: Cross-Site Request Forgery (CSRF) (Score: 300.25)\n\nThe web application does not, or can not, sufficiently verify whether a well-formed, valid, consistent request was intentionally provided by the user who submitted the request....\n\n### 2. CWE-79: Improper Neutralization of Input During Web Page Generation ('Cross-site Scripting') (Score: 239.08)\n\nThe product does not neutralize or incorrectly neutralizes user-controllable input before it is placed in output that is used as a web page that is served to other users....\n\n### 3. CWE-1275: Sensitive Cookie with Improper SameSite Attribute (Score: 236.85)\n\nThe SameSite attribute for sensitive cookies is not set, or an insecure value is used....\n\n### 4. CWE-116: Improper Encoding or Escaping of Output (Score: 219.36)\n\nThe product prepares a structured message for communication with another component, but encoding or escaping of the data is either missing or done incorrectly. As a result, the intended structure of the message is not preserved....\n\n### 5. CWE-22: Improper Limitation of a Pathname to a Restricted Directory ('Path Traversal') (Score: 48.09)\n\nThe product uses external input to construct a pathname that is intended to identify a file or directory that is located underneath a restricted parent directory, but the product does not properly neutralize special elements within the pathname that can cause the pathname to resolve to a location th...\n\n## VERSION: 'n/a through 2'\n\nRelevant CWEs for this VERSION:\n\n### 1. CWE-352: Cross-Site Request Forgery (CSRF) (Score: 300.25)\n\nThe web application does not, or can not, sufficiently verify whether a well-formed, valid, consistent request was intentionally provided by the user who submitted the request....\n\n### 2. CWE-79: Improper Neutralization of Input During Web Page Generation ('Cross-site Scripting') (Score: 239.08)\n\nThe product does not neutralize or incorrectly neutralizes user-controllable input before it is placed in output that is used as a web page that is served to other users....\n\n### 3. CWE-434: Unrestricted Upload of File with Dangerous Type (Score: 199.54)\n\nThe product allows the upload or transfer of dangerous file types that are automatically processed within its environment....\n\n### 4. CWE-611: Improper Restriction of XML External Entity Reference (Score: 61.74)\n\nThe product processes an XML document that can contain XML entities with URIs that resolve to documents outside of the intended sphere of control, causing the product to embed incorrect documents into its output....\n\n### 5. CWE-22: Improper Limitation of a Pathname to a Restricted Directory ('Path Traversal') (Score: 48.09)\n\nThe product uses external input to construct a pathname that is intended to identify a file or directory that is located underneath a restricted parent directory, but the product does not properly neutralize special elements within the pathname that can cause the pathname to resolve to a location th...\n\n\n    # Analysis Instructions\n    1. For each keyphrase, identify the most appropriate CWE(s) that represent the weakness.\n    2. Consider how the different keyphrases might relate to each other in the vulnerability chain.\n    3. Provide a final determination of primary CWE(s) and any secondary CWEs.\n    4. Format your response using the standard analysis template.\n\n    Please analyze how these different weaknesses interact and provide a comprehensive CWE classification.\n    "
  },
  "retrieval_time": 1.589839220046997
}