{
  "vulnerability_info": "VulnerabilityInfo(cve_id='CVE-2025-3600', description='In Progress Telerik UI for AJAX, versions 2011.2.712 to 2025.1.218, an **unsafe reflection** vulnerability exists that may lead to an **unhandled exception** resulting in a crash of the hosting process and denial of service.', key_phrases={'rootcause': ['unhandled exception', 'unsafe reflection'], 'weakness': '', 'impact': 'crash of the hosting process and denial of service', 'vector': '', 'attacker': '', 'product': 'Telerik UI for AJAX', 'version': '2011.2.712 to 2025.1.218', 'component': ''}, reference_content=\"## Analysis of CVE-2025-3600 Content\\n\\nThe provided content is directly related to CVE-2025-3600. It's a Telerik security advisory detailing an unsafe reflection vulnerability in Telerik UI for ASP.NET AJAX. Here's a breakdown of the information:\\n\\n**Root cause of vulnerability:**\\n\\n*   Unsafe Reflection (CWE-470): Use of externally-controlled input to select classes or code.\\n\\n**Weaknesses/vulnerabilities present:**\\n\\n*   An attacker can send a specially crafted request that triggers an unsafe reflection vulnerability.\\n\\n**Impact of exploitation:**\\n\\n*   Unhandled exception leading to a crash of the hosting process.\\n*   Denial of Service (DoS) \u2013 the application restarts after crashing.\\n\\n**Attack vectors:**\\n\\n*   Specifically crafted HTTP requests targeting `Telerik.Web.UI.WebResource.axd`.\\n*   Exploitation involves manipulating query string parameters (`type` and `prtype`).\\n\\n**Required attacker capabilities/position:**\\n\\n*   An unauthenticated attacker can send malicious requests.\\n\\n**Mitigation or fix:**\\n\\n*   **Upgrade:** Upgrade to version 2025.1.416 (2025 Q1 SP2) or later.\\n*   **Assembly Binding Redirect (Option 1):** For versions 2024.2 or later, replace DLLs with patched versions and use a binding redirect in `web.config`.\\n*   **HTTP Request Filtering Module (Option 2):** Implement a custom HTTP module to block malicious requests based on query string parameters.\\n*   **URL Rewrite (Option 3):** Use URL rewrite rules in `web.config` to block requests to the affected endpoint.\\n\\n**Verification:**\\n\\n*   Check project references for `Telerik.Web.UI.dll`.\\n*   Verify the assembly version (should be between 2011.2.712 and 2025.1.218 inclusive to be vulnerable).\\n*   Inspect `web.config` for the presence of the `Telerik.Web.UI.WebResource.axd` handler.\\n\\n**Additional Details (more than official CVE description):**\\n\\n*   The advisory provides detailed instructions for mitigation, including code examples for the HTTP Request Filtering Module and URL Rewrite options.\\n*   It specifies the exact query string parameters to look for in mitigation efforts.\\n*   It acknowledges the security researcher who reported the vulnerability (Piotr Bazydlo of watchTowr).\\n*   It provides links to relevant documentation and resources.\\n*   CVSS score of 7.5 (HIGH).\", similar_info={'cwe_distribution': {}, 'cwe_consensus': '', 'similarity_stats': {'thresholds': [], 'total_samples_by_threshold': {}, 'top_cwes_by_threshold': {}}}, similarity_summary=SimilarityInsight(consensus_cwe='', top_cwes=[], confidence_levels={}, total_samples=0), analysis='', analysis_with_relationships='', criticism='', resolution='', relevant_cwes=[{'metadata': {'doc_id': '248', 'name': 'Uncaught Exception', 'source': 'sparse', 'original_content': 'An exception is thrown from a function, but it is not caught.', 'keyphrase_sources': [{'id': 'rootcause:unhandled exception', 'keyphrase': 'unhandled exception', 'type': 'rootcause'}, {'id': 'rootcause:unsafe reflection', 'keyphrase': 'unsafe reflection', 'type': 'rootcause'}, {'id': 'impact:crash of the hosting process and denial of service', 'keyphrase': 'crash of the hosting process and denial of service', 'type': 'impact'}, {'id': 'product:Telerik UI for AJAX', 'keyphrase': 'Telerik UI for AJAX', 'type': 'product'}, {'id': 'version:2011.2.712 to 2025.1.218', 'keyphrase': '2011.2.712 to 2025.1.218', 'type': 'version'}]}, 'similarity': np.float64(332.70939877281415)}, {'metadata': {'doc_id': '470', 'name': \"Use of Externally-Controlled Input to Select Classes or Code ('Unsafe Reflection')\", 'source': 'sparse', 'original_content': 'The product uses external input with reflection to select which classes or code to use, but it does not sufficiently prevent the input from selecting improper classes or code.', 'keyphrase_sources': [{'id': 'rootcause:unsafe reflection', 'keyphrase': 'unsafe reflection', 'type': 'rootcause'}]}, 'similarity': np.float64(284.46530968485195)}, {'metadata': {'doc_id': '502', 'name': 'Deserialization of Untrusted Data', 'source': 'sparse', 'original_content': 'The product deserializes untrusted data without sufficiently ensuring that the resulting data will be valid.', 'keyphrase_sources': [{'id': 'rootcause:unsafe reflection', 'keyphrase': 'unsafe reflection', 'type': 'rootcause'}, {'id': 'product:Telerik UI for AJAX', 'keyphrase': 'Telerik UI for AJAX', 'type': 'product'}, {'id': 'version:2011.2.712 to 2025.1.218', 'keyphrase': '2011.2.712 to 2025.1.218', 'type': 'version'}]}, 'similarity': np.float64(256.1038526425859)}, {'metadata': {'doc_id': '617', 'name': 'Reachable Assertion', 'source': 'sparse', 'original_content': 'The product contains an assert() or similar statement that can be triggered by an attacker, which leads to an application exit or other behavior that is more severe than necessary.', 'keyphrase_sources': [{'id': 'rootcause:unhandled exception', 'keyphrase': 'unhandled exception', 'type': 'rootcause'}, {'id': 'impact:crash of the hosting process and denial of service', 'keyphrase': 'crash of the hosting process and denial of service', 'type': 'impact'}]}, 'similarity': np.float64(249.3757457254636)}, {'metadata': {'doc_id': '610', 'name': 'Externally Controlled Reference to a Resource in Another Sphere', 'source': 'sparse', 'original_content': 'The product uses an externally controlled name or reference that resolves to a resource that is outside of the intended control sphere.', 'keyphrase_sources': [{'id': 'rootcause:unsafe reflection', 'keyphrase': 'unsafe reflection', 'type': 'rootcause'}]}, 'similarity': np.float64(245.87760247634142)}, {'metadata': {'doc_id': '789', 'name': 'Memory Allocation with Excessive Size Value', 'source': 'sparse', 'original_content': 'The product allocates memory based on an untrusted, large size value, but it does not ensure that the size is within expected limits, allowing arbitrary amounts of memory to be allocated.', 'keyphrase_sources': [{'id': 'rootcause:unhandled exception', 'keyphrase': 'unhandled exception', 'type': 'rootcause'}, {'id': 'impact:crash of the hosting process and denial of service', 'keyphrase': 'crash of the hosting process and denial of service', 'type': 'impact'}]}, 'similarity': np.float64(241.32924476864008)}, {'metadata': {'doc_id': '755', 'name': 'Improper Handling of Exceptional Conditions', 'source': 'sparse', 'original_content': 'The product does not handle or incorrectly handles an exceptional condition.', 'keyphrase_sources': [{'id': 'rootcause:unhandled exception', 'keyphrase': 'unhandled exception', 'type': 'rootcause'}, {'id': 'impact:crash of the hosting process and denial of service', 'keyphrase': 'crash of the hosting process and denial of service', 'type': 'impact'}]}, 'similarity': np.float64(240.49623092486092)}, {'metadata': {'doc_id': '664', 'name': 'Improper Control of a Resource Through its Lifetime', 'source': 'sparse', 'original_content': 'The product does not maintain or incorrectly maintains control over a resource throughout its lifetime of creation, use, and release.', 'keyphrase_sources': [{'id': 'rootcause:unsafe reflection', 'keyphrase': 'unsafe reflection', 'type': 'rootcause'}]}, 'similarity': np.float64(239.23413331343215)}, {'metadata': {'doc_id': '476', 'name': 'NULL Pointer Dereference', 'source': 'sparse', 'original_content': 'The product dereferences a pointer that it expects to be valid but is NULL.', 'keyphrase_sources': [{'id': 'rootcause:unhandled exception', 'keyphrase': 'unhandled exception', 'type': 'rootcause'}, {'id': 'impact:crash of the hosting process and denial of service', 'keyphrase': 'crash of the hosting process and denial of service', 'type': 'impact'}, {'id': 'product:Telerik UI for AJAX', 'keyphrase': 'Telerik UI for AJAX', 'type': 'product'}]}, 'similarity': np.float64(237.8900176120173)}, {'metadata': {'doc_id': '835', 'name': \"Loop with Unreachable Exit Condition ('Infinite Loop')\", 'source': 'sparse', 'original_content': 'The product contains an iteration or loop with an exit condition that cannot be reached, i.e., an infinite loop.', 'keyphrase_sources': [{'id': 'version:2011.2.712 to 2025.1.218', 'keyphrase': '2011.2.712 to 2025.1.218', 'type': 'version'}]}, 'similarity': np.float64(88.49282788177014)}, {'metadata': {'doc_id': '206', 'name': 'Observable Internal Behavioral Discrepancy', 'source': 'sparse', 'original_content': 'The product performs multiple behaviors that are combined to produce a single result, but the individual behaviors are observable separately in a way that allows attackers to reveal internal state or internal decision points.', 'keyphrase_sources': [{'id': 'version:2011.2.712 to 2025.1.218', 'keyphrase': '2011.2.712 to 2025.1.218', 'type': 'version'}]}, 'similarity': np.float64(86.956048607106)}, {'metadata': {'doc_id': '776', 'name': \"Improper Restriction of Recursive Entity References in DTDs ('XML Entity Expansion')\", 'source': 'sparse', 'original_content': 'The product uses XML documents and allows their structure to be defined with a Document Type Definition (DTD), but it does not properly control the number of recursive definitions of entities.', 'keyphrase_sources': [{'id': 'version:2011.2.712 to 2025.1.218', 'keyphrase': '2011.2.712 to 2025.1.218', 'type': 'version'}]}, 'similarity': np.float64(85.85367393551593)}, {'metadata': {'doc_id': '862', 'name': 'Missing Authorization', 'source': 'sparse', 'original_content': 'The product does not perform an authorization check when an actor attempts to access a resource or perform an action.', 'keyphrase_sources': [{'id': 'product:Telerik UI for AJAX', 'keyphrase': 'Telerik UI for AJAX', 'type': 'product'}]}, 'similarity': np.float64(84.04827627545762)}, {'metadata': {'doc_id': '352', 'name': 'Cross-Site Request Forgery (CSRF)', 'source': 'sparse', 'original_content': 'The web application does not, or can not, sufficiently verify whether a well-formed, valid, consistent request was intentionally provided by the user who submitted the request.', 'keyphrase_sources': [{'id': 'product:Telerik UI for AJAX', 'keyphrase': 'Telerik UI for AJAX', 'type': 'product'}]}, 'similarity': np.float64(79.92210928682721)}], identified_cwes={'analyzer': [], 'critic_additional': []})",
  "retrieval_results": {
    "has_multiple_keyphrases": true,
    "keyphrase_cwe_sets": {
      "rootcause:unhandled exception": {
        "keyphrase": "unhandled exception",
        "type": "rootcause",
        "cwes": [
          {
            "metadata": {
              "doc_id": "248",
              "name": "Uncaught Exception",
              "source": "sparse",
              "original_content": "An exception is thrown from a function, but it is not caught.",
              "keyphrase_sources": [
                {
                  "id": "rootcause:unhandled exception",
                  "keyphrase": "unhandled exception",
                  "type": "rootcause"
                },
                {
                  "id": "rootcause:unsafe reflection",
                  "keyphrase": "unsafe reflection",
                  "type": "rootcause"
                },
                {
                  "id": "impact:crash of the hosting process and denial of service",
                  "keyphrase": "crash of the hosting process and denial of service",
                  "type": "impact"
                },
                {
                  "id": "product:Telerik UI for AJAX",
                  "keyphrase": "Telerik UI for AJAX",
                  "type": "product"
                },
                {
                  "id": "version:2011.2.712 to 2025.1.218",
                  "keyphrase": "2011.2.712 to 2025.1.218",
                  "type": "version"
                }
              ]
            },
            "similarity": 332.70939877281415
          },
          {
            "metadata": {
              "doc_id": "617",
              "name": "Reachable Assertion",
              "source": "sparse",
              "original_content": "The product contains an assert() or similar statement that can be triggered by an attacker, which leads to an application exit or other behavior that is more severe than necessary.",
              "keyphrase_sources": [
                {
                  "id": "rootcause:unhandled exception",
                  "keyphrase": "unhandled exception",
                  "type": "rootcause"
                },
                {
                  "id": "impact:crash of the hosting process and denial of service",
                  "keyphrase": "crash of the hosting process and denial of service",
                  "type": "impact"
                }
              ]
            },
            "similarity": 249.3757457254636
          },
          {
            "metadata": {
              "doc_id": "789",
              "name": "Memory Allocation with Excessive Size Value",
              "source": "sparse",
              "original_content": "The product allocates memory based on an untrusted, large size value, but it does not ensure that the size is within expected limits, allowing arbitrary amounts of memory to be allocated.",
              "keyphrase_sources": [
                {
                  "id": "rootcause:unhandled exception",
                  "keyphrase": "unhandled exception",
                  "type": "rootcause"
                },
                {
                  "id": "impact:crash of the hosting process and denial of service",
                  "keyphrase": "crash of the hosting process and denial of service",
                  "type": "impact"
                }
              ]
            },
            "similarity": 241.32924476864008
          },
          {
            "metadata": {
              "doc_id": "755",
              "name": "Improper Handling of Exceptional Conditions",
              "source": "sparse",
              "original_content": "The product does not handle or incorrectly handles an exceptional condition.",
              "keyphrase_sources": [
                {
                  "id": "rootcause:unhandled exception",
                  "keyphrase": "unhandled exception",
                  "type": "rootcause"
                },
                {
                  "id": "impact:crash of the hosting process and denial of service",
                  "keyphrase": "crash of the hosting process and denial of service",
                  "type": "impact"
                }
              ]
            },
            "similarity": 240.49623092486092
          },
          {
            "metadata": {
              "doc_id": "476",
              "name": "NULL Pointer Dereference",
              "source": "sparse",
              "original_content": "The product dereferences a pointer that it expects to be valid but is NULL.",
              "keyphrase_sources": [
                {
                  "id": "rootcause:unhandled exception",
                  "keyphrase": "unhandled exception",
                  "type": "rootcause"
                },
                {
                  "id": "impact:crash of the hosting process and denial of service",
                  "keyphrase": "crash of the hosting process and denial of service",
                  "type": "impact"
                },
                {
                  "id": "product:Telerik UI for AJAX",
                  "keyphrase": "Telerik UI for AJAX",
                  "type": "product"
                }
              ]
            },
            "similarity": 237.8900176120173
          }
        ]
      },
      "rootcause:unsafe reflection": {
        "keyphrase": "unsafe reflection",
        "type": "rootcause",
        "cwes": [
          {
            "metadata": {
              "doc_id": "470",
              "name": "Use of Externally-Controlled Input to Select Classes or Code ('Unsafe Reflection')",
              "source": "sparse",
              "original_content": "The product uses external input with reflection to select which classes or code to use, but it does not sufficiently prevent the input from selecting improper classes or code.",
              "keyphrase_sources": [
                {
                  "id": "rootcause:unsafe reflection",
                  "keyphrase": "unsafe reflection",
                  "type": "rootcause"
                }
              ]
            },
            "similarity": 284.46530968485195
          },
          {
            "metadata": {
              "doc_id": "502",
              "name": "Deserialization of Untrusted Data",
              "source": "sparse",
              "original_content": "The product deserializes untrusted data without sufficiently ensuring that the resulting data will be valid.",
              "keyphrase_sources": [
                {
                  "id": "rootcause:unsafe reflection",
                  "keyphrase": "unsafe reflection",
                  "type": "rootcause"
                },
                {
                  "id": "product:Telerik UI for AJAX",
                  "keyphrase": "Telerik UI for AJAX",
                  "type": "product"
                },
                {
                  "id": "version:2011.2.712 to 2025.1.218",
                  "keyphrase": "2011.2.712 to 2025.1.218",
                  "type": "version"
                }
              ]
            },
            "similarity": 256.1038526425859
          },
          {
            "metadata": {
              "doc_id": "610",
              "name": "Externally Controlled Reference to a Resource in Another Sphere",
              "source": "sparse",
              "original_content": "The product uses an externally controlled name or reference that resolves to a resource that is outside of the intended control sphere.",
              "keyphrase_sources": [
                {
                  "id": "rootcause:unsafe reflection",
                  "keyphrase": "unsafe reflection",
                  "type": "rootcause"
                }
              ]
            },
            "similarity": 245.87760247634142
          },
          {
            "metadata": {
              "doc_id": "248",
              "name": "Uncaught Exception",
              "source": "sparse",
              "original_content": "An exception is thrown from a function, but it is not caught."
            },
            "similarity": 242.20768448800868
          },
          {
            "metadata": {
              "doc_id": "664",
              "name": "Improper Control of a Resource Through its Lifetime",
              "source": "sparse",
              "original_content": "The product does not maintain or incorrectly maintains control over a resource throughout its lifetime of creation, use, and release.",
              "keyphrase_sources": [
                {
                  "id": "rootcause:unsafe reflection",
                  "keyphrase": "unsafe reflection",
                  "type": "rootcause"
                }
              ]
            },
            "similarity": 239.23413331343215
          }
        ]
      },
      "impact:crash of the hosting process and denial of service": {
        "keyphrase": "crash of the hosting process and denial of service",
        "type": "impact",
        "cwes": [
          {
            "metadata": {
              "doc_id": "248",
              "name": "Uncaught Exception",
              "source": "sparse",
              "original_content": "An exception is thrown from a function, but it is not caught."
            },
            "similarity": 128.40969321123097
          },
          {
            "metadata": {
              "doc_id": "755",
              "name": "Improper Handling of Exceptional Conditions",
              "source": "sparse",
              "original_content": "The product does not handle or incorrectly handles an exceptional condition."
            },
            "similarity": 123.47730119283152
          },
          {
            "metadata": {
              "doc_id": "476",
              "name": "NULL Pointer Dereference",
              "source": "sparse",
              "original_content": "The product dereferences a pointer that it expects to be valid but is NULL."
            },
            "similarity": 121.22077362705475
          },
          {
            "metadata": {
              "doc_id": "617",
              "name": "Reachable Assertion",
              "source": "sparse",
              "original_content": "The product contains an assert() or similar statement that can be triggered by an attacker, which leads to an application exit or other behavior that is more severe than necessary."
            },
            "similarity": 118.42796875323407
          },
          {
            "metadata": {
              "doc_id": "789",
              "name": "Memory Allocation with Excessive Size Value",
              "source": "sparse",
              "original_content": "The product allocates memory based on an untrusted, large size value, but it does not ensure that the size is within expected limits, allowing arbitrary amounts of memory to be allocated."
            },
            "similarity": 117.86233264387319
          }
        ]
      },
      "product:Telerik UI for AJAX": {
        "keyphrase": "Telerik UI for AJAX",
        "type": "product",
        "cwes": [
          {
            "metadata": {
              "doc_id": "502",
              "name": "Deserialization of Untrusted Data",
              "source": "sparse",
              "original_content": "The product deserializes untrusted data without sufficiently ensuring that the resulting data will be valid."
            },
            "similarity": 91.03958305311393
          },
          {
            "metadata": {
              "doc_id": "248",
              "name": "Uncaught Exception",
              "source": "sparse",
              "original_content": "An exception is thrown from a function, but it is not caught."
            },
            "similarity": 87.45550350848602
          },
          {
            "metadata": {
              "doc_id": "862",
              "name": "Missing Authorization",
              "source": "sparse",
              "original_content": "The product does not perform an authorization check when an actor attempts to access a resource or perform an action.",
              "keyphrase_sources": [
                {
                  "id": "product:Telerik UI for AJAX",
                  "keyphrase": "Telerik UI for AJAX",
                  "type": "product"
                }
              ]
            },
            "similarity": 84.04827627545762
          },
          {
            "metadata": {
              "doc_id": "352",
              "name": "Cross-Site Request Forgery (CSRF)",
              "source": "sparse",
              "original_content": "The web application does not, or can not, sufficiently verify whether a well-formed, valid, consistent request was intentionally provided by the user who submitted the request.",
              "keyphrase_sources": [
                {
                  "id": "product:Telerik UI for AJAX",
                  "keyphrase": "Telerik UI for AJAX",
                  "type": "product"
                }
              ]
            },
            "similarity": 79.92210928682721
          },
          {
            "metadata": {
              "doc_id": "476",
              "name": "NULL Pointer Dereference",
              "source": "sparse",
              "original_content": "The product dereferences a pointer that it expects to be valid but is NULL."
            },
            "similarity": 78.71200434839464
          }
        ]
      },
      "version:2011.2.712 to 2025.1.218": {
        "keyphrase": "2011.2.712 to 2025.1.218",
        "type": "version",
        "cwes": [
          {
            "metadata": {
              "doc_id": "248",
              "name": "Uncaught Exception",
              "source": "sparse",
              "original_content": "An exception is thrown from a function, but it is not caught."
            },
            "similarity": 91.44152551234778
          },
          {
            "metadata": {
              "doc_id": "835",
              "name": "Loop with Unreachable Exit Condition ('Infinite Loop')",
              "source": "sparse",
              "original_content": "The product contains an iteration or loop with an exit condition that cannot be reached, i.e., an infinite loop.",
              "keyphrase_sources": [
                {
                  "id": "version:2011.2.712 to 2025.1.218",
                  "keyphrase": "2011.2.712 to 2025.1.218",
                  "type": "version"
                }
              ]
            },
            "similarity": 88.49282788177014
          },
          {
            "metadata": {
              "doc_id": "206",
              "name": "Observable Internal Behavioral Discrepancy",
              "source": "sparse",
              "original_content": "The product performs multiple behaviors that are combined to produce a single result, but the individual behaviors are observable separately in a way that allows attackers to reveal internal state or internal decision points.",
              "keyphrase_sources": [
                {
                  "id": "version:2011.2.712 to 2025.1.218",
                  "keyphrase": "2011.2.712 to 2025.1.218",
                  "type": "version"
                }
              ]
            },
            "similarity": 86.956048607106
          },
          {
            "metadata": {
              "doc_id": "502",
              "name": "Deserialization of Untrusted Data",
              "source": "sparse",
              "original_content": "The product deserializes untrusted data without sufficiently ensuring that the resulting data will be valid."
            },
            "similarity": 86.71635755237263
          },
          {
            "metadata": {
              "doc_id": "776",
              "name": "Improper Restriction of Recursive Entity References in DTDs ('XML Entity Expansion')",
              "source": "sparse",
              "original_content": "The product uses XML documents and allows their structure to be defined with a Document Type Definition (DTD), but it does not properly control the number of recursive definitions of entities.",
              "keyphrase_sources": [
                {
                  "id": "version:2011.2.712 to 2025.1.218",
                  "keyphrase": "2011.2.712 to 2025.1.218",
                  "type": "version"
                }
              ]
            },
            "similarity": 85.85367393551593
          }
        ]
      }
    },
    "keyphrase_mapping": {
      "248": [
        {
          "id": "rootcause:unhandled exception",
          "keyphrase": "unhandled exception",
          "type": "rootcause"
        },
        {
          "id": "rootcause:unsafe reflection",
          "keyphrase": "unsafe reflection",
          "type": "rootcause"
        },
        {
          "id": "impact:crash of the hosting process and denial of service",
          "keyphrase": "crash of the hosting process and denial of service",
          "type": "impact"
        },
        {
          "id": "product:Telerik UI for AJAX",
          "keyphrase": "Telerik UI for AJAX",
          "type": "product"
        },
        {
          "id": "version:2011.2.712 to 2025.1.218",
          "keyphrase": "2011.2.712 to 2025.1.218",
          "type": "version"
        }
      ],
      "617": [
        {
          "id": "rootcause:unhandled exception",
          "keyphrase": "unhandled exception",
          "type": "rootcause"
        },
        {
          "id": "impact:crash of the hosting process and denial of service",
          "keyphrase": "crash of the hosting process and denial of service",
          "type": "impact"
        }
      ],
      "789": [
        {
          "id": "rootcause:unhandled exception",
          "keyphrase": "unhandled exception",
          "type": "rootcause"
        },
        {
          "id": "impact:crash of the hosting process and denial of service",
          "keyphrase": "crash of the hosting process and denial of service",
          "type": "impact"
        }
      ],
      "755": [
        {
          "id": "rootcause:unhandled exception",
          "keyphrase": "unhandled exception",
          "type": "rootcause"
        },
        {
          "id": "impact:crash of the hosting process and denial of service",
          "keyphrase": "crash of the hosting process and denial of service",
          "type": "impact"
        }
      ],
      "476": [
        {
          "id": "rootcause:unhandled exception",
          "keyphrase": "unhandled exception",
          "type": "rootcause"
        },
        {
          "id": "impact:crash of the hosting process and denial of service",
          "keyphrase": "crash of the hosting process and denial of service",
          "type": "impact"
        },
        {
          "id": "product:Telerik UI for AJAX",
          "keyphrase": "Telerik UI for AJAX",
          "type": "product"
        }
      ],
      "470": [
        {
          "id": "rootcause:unsafe reflection",
          "keyphrase": "unsafe reflection",
          "type": "rootcause"
        }
      ],
      "502": [
        {
          "id": "rootcause:unsafe reflection",
          "keyphrase": "unsafe reflection",
          "type": "rootcause"
        },
        {
          "id": "product:Telerik UI for AJAX",
          "keyphrase": "Telerik UI for AJAX",
          "type": "product"
        },
        {
          "id": "version:2011.2.712 to 2025.1.218",
          "keyphrase": "2011.2.712 to 2025.1.218",
          "type": "version"
        }
      ],
      "610": [
        {
          "id": "rootcause:unsafe reflection",
          "keyphrase": "unsafe reflection",
          "type": "rootcause"
        }
      ],
      "664": [
        {
          "id": "rootcause:unsafe reflection",
          "keyphrase": "unsafe reflection",
          "type": "rootcause"
        }
      ],
      "862": [
        {
          "id": "product:Telerik UI for AJAX",
          "keyphrase": "Telerik UI for AJAX",
          "type": "product"
        }
      ],
      "352": [
        {
          "id": "product:Telerik UI for AJAX",
          "keyphrase": "Telerik UI for AJAX",
          "type": "product"
        }
      ],
      "835": [
        {
          "id": "version:2011.2.712 to 2025.1.218",
          "keyphrase": "2011.2.712 to 2025.1.218",
          "type": "version"
        }
      ],
      "206": [
        {
          "id": "version:2011.2.712 to 2025.1.218",
          "keyphrase": "2011.2.712 to 2025.1.218",
          "type": "version"
        }
      ],
      "776": [
        {
          "id": "version:2011.2.712 to 2025.1.218",
          "keyphrase": "2011.2.712 to 2025.1.218",
          "type": "version"
        }
      ]
    },
    "relevant_cwes": [
      {
        "metadata": {
          "doc_id": "248",
          "name": "Uncaught Exception",
          "source": "sparse",
          "original_content": "An exception is thrown from a function, but it is not caught.",
          "keyphrase_sources": [
            {
              "id": "rootcause:unhandled exception",
              "keyphrase": "unhandled exception",
              "type": "rootcause"
            },
            {
              "id": "rootcause:unsafe reflection",
              "keyphrase": "unsafe reflection",
              "type": "rootcause"
            },
            {
              "id": "impact:crash of the hosting process and denial of service",
              "keyphrase": "crash of the hosting process and denial of service",
              "type": "impact"
            },
            {
              "id": "product:Telerik UI for AJAX",
              "keyphrase": "Telerik UI for AJAX",
              "type": "product"
            },
            {
              "id": "version:2011.2.712 to 2025.1.218",
              "keyphrase": "2011.2.712 to 2025.1.218",
              "type": "version"
            }
          ]
        },
        "similarity": 332.70939877281415
      },
      {
        "metadata": {
          "doc_id": "470",
          "name": "Use of Externally-Controlled Input to Select Classes or Code ('Unsafe Reflection')",
          "source": "sparse",
          "original_content": "The product uses external input with reflection to select which classes or code to use, but it does not sufficiently prevent the input from selecting improper classes or code.",
          "keyphrase_sources": [
            {
              "id": "rootcause:unsafe reflection",
              "keyphrase": "unsafe reflection",
              "type": "rootcause"
            }
          ]
        },
        "similarity": 284.46530968485195
      },
      {
        "metadata": {
          "doc_id": "502",
          "name": "Deserialization of Untrusted Data",
          "source": "sparse",
          "original_content": "The product deserializes untrusted data without sufficiently ensuring that the resulting data will be valid.",
          "keyphrase_sources": [
            {
              "id": "rootcause:unsafe reflection",
              "keyphrase": "unsafe reflection",
              "type": "rootcause"
            },
            {
              "id": "product:Telerik UI for AJAX",
              "keyphrase": "Telerik UI for AJAX",
              "type": "product"
            },
            {
              "id": "version:2011.2.712 to 2025.1.218",
              "keyphrase": "2011.2.712 to 2025.1.218",
              "type": "version"
            }
          ]
        },
        "similarity": 256.1038526425859
      },
      {
        "metadata": {
          "doc_id": "617",
          "name": "Reachable Assertion",
          "source": "sparse",
          "original_content": "The product contains an assert() or similar statement that can be triggered by an attacker, which leads to an application exit or other behavior that is more severe than necessary.",
          "keyphrase_sources": [
            {
              "id": "rootcause:unhandled exception",
              "keyphrase": "unhandled exception",
              "type": "rootcause"
            },
            {
              "id": "impact:crash of the hosting process and denial of service",
              "keyphrase": "crash of the hosting process and denial of service",
              "type": "impact"
            }
          ]
        },
        "similarity": 249.3757457254636
      },
      {
        "metadata": {
          "doc_id": "610",
          "name": "Externally Controlled Reference to a Resource in Another Sphere",
          "source": "sparse",
          "original_content": "The product uses an externally controlled name or reference that resolves to a resource that is outside of the intended control sphere.",
          "keyphrase_sources": [
            {
              "id": "rootcause:unsafe reflection",
              "keyphrase": "unsafe reflection",
              "type": "rootcause"
            }
          ]
        },
        "similarity": 245.87760247634142
      },
      {
        "metadata": {
          "doc_id": "789",
          "name": "Memory Allocation with Excessive Size Value",
          "source": "sparse",
          "original_content": "The product allocates memory based on an untrusted, large size value, but it does not ensure that the size is within expected limits, allowing arbitrary amounts of memory to be allocated.",
          "keyphrase_sources": [
            {
              "id": "rootcause:unhandled exception",
              "keyphrase": "unhandled exception",
              "type": "rootcause"
            },
            {
              "id": "impact:crash of the hosting process and denial of service",
              "keyphrase": "crash of the hosting process and denial of service",
              "type": "impact"
            }
          ]
        },
        "similarity": 241.32924476864008
      },
      {
        "metadata": {
          "doc_id": "755",
          "name": "Improper Handling of Exceptional Conditions",
          "source": "sparse",
          "original_content": "The product does not handle or incorrectly handles an exceptional condition.",
          "keyphrase_sources": [
            {
              "id": "rootcause:unhandled exception",
              "keyphrase": "unhandled exception",
              "type": "rootcause"
            },
            {
              "id": "impact:crash of the hosting process and denial of service",
              "keyphrase": "crash of the hosting process and denial of service",
              "type": "impact"
            }
          ]
        },
        "similarity": 240.49623092486092
      },
      {
        "metadata": {
          "doc_id": "664",
          "name": "Improper Control of a Resource Through its Lifetime",
          "source": "sparse",
          "original_content": "The product does not maintain or incorrectly maintains control over a resource throughout its lifetime of creation, use, and release.",
          "keyphrase_sources": [
            {
              "id": "rootcause:unsafe reflection",
              "keyphrase": "unsafe reflection",
              "type": "rootcause"
            }
          ]
        },
        "similarity": 239.23413331343215
      },
      {
        "metadata": {
          "doc_id": "476",
          "name": "NULL Pointer Dereference",
          "source": "sparse",
          "original_content": "The product dereferences a pointer that it expects to be valid but is NULL.",
          "keyphrase_sources": [
            {
              "id": "rootcause:unhandled exception",
              "keyphrase": "unhandled exception",
              "type": "rootcause"
            },
            {
              "id": "impact:crash of the hosting process and denial of service",
              "keyphrase": "crash of the hosting process and denial of service",
              "type": "impact"
            },
            {
              "id": "product:Telerik UI for AJAX",
              "keyphrase": "Telerik UI for AJAX",
              "type": "product"
            }
          ]
        },
        "similarity": 237.8900176120173
      },
      {
        "metadata": {
          "doc_id": "835",
          "name": "Loop with Unreachable Exit Condition ('Infinite Loop')",
          "source": "sparse",
          "original_content": "The product contains an iteration or loop with an exit condition that cannot be reached, i.e., an infinite loop.",
          "keyphrase_sources": [
            {
              "id": "version:2011.2.712 to 2025.1.218",
              "keyphrase": "2011.2.712 to 2025.1.218",
              "type": "version"
            }
          ]
        },
        "similarity": 88.49282788177014
      },
      {
        "metadata": {
          "doc_id": "206",
          "name": "Observable Internal Behavioral Discrepancy",
          "source": "sparse",
          "original_content": "The product performs multiple behaviors that are combined to produce a single result, but the individual behaviors are observable separately in a way that allows attackers to reveal internal state or internal decision points.",
          "keyphrase_sources": [
            {
              "id": "version:2011.2.712 to 2025.1.218",
              "keyphrase": "2011.2.712 to 2025.1.218",
              "type": "version"
            }
          ]
        },
        "similarity": 86.956048607106
      },
      {
        "metadata": {
          "doc_id": "776",
          "name": "Improper Restriction of Recursive Entity References in DTDs ('XML Entity Expansion')",
          "source": "sparse",
          "original_content": "The product uses XML documents and allows their structure to be defined with a Document Type Definition (DTD), but it does not properly control the number of recursive definitions of entities.",
          "keyphrase_sources": [
            {
              "id": "version:2011.2.712 to 2025.1.218",
              "keyphrase": "2011.2.712 to 2025.1.218",
              "type": "version"
            }
          ]
        },
        "similarity": 85.85367393551593
      },
      {
        "metadata": {
          "doc_id": "862",
          "name": "Missing Authorization",
          "source": "sparse",
          "original_content": "The product does not perform an authorization check when an actor attempts to access a resource or perform an action.",
          "keyphrase_sources": [
            {
              "id": "product:Telerik UI for AJAX",
              "keyphrase": "Telerik UI for AJAX",
              "type": "product"
            }
          ]
        },
        "similarity": 84.04827627545762
      },
      {
        "metadata": {
          "doc_id": "352",
          "name": "Cross-Site Request Forgery (CSRF)",
          "source": "sparse",
          "original_content": "The web application does not, or can not, sufficiently verify whether a well-formed, valid, consistent request was intentionally provided by the user who submitted the request.",
          "keyphrase_sources": [
            {
              "id": "product:Telerik UI for AJAX",
              "keyphrase": "Telerik UI for AJAX",
              "type": "product"
            }
          ]
        },
        "similarity": 79.92210928682721
      }
    ],
    "enhanced_query": "# Vulnerability Description\n\n    In Progress Telerik UI for AJAX, versions 2011.2.712 to 2025.1.218, an **unsafe reflection** vulnerability exists that may lead to an **unhandled exception** resulting in a crash of the hosting process and denial of service.\n\n    # Keyphrase-Specific CWE Analysis\n    This vulnerability contains multiple keyphrases that may map to different CWEs. \n    Please analyze each keyphrase separately and determine the most appropriate CWE(s) for each.\n\n    ## ROOTCAUSE: 'unhandled exception'\n\nRelevant CWEs for this ROOTCAUSE:\n\n### 1. CWE-248: Uncaught Exception (Score: 332.71)\n\nAn exception is thrown from a function, but it is not caught....\n\n### 2. CWE-617: Reachable Assertion (Score: 249.38)\n\nThe product contains an assert() or similar statement that can be triggered by an attacker, which leads to an application exit or other behavior that is more severe than necessary....\n\n### 3. CWE-789: Memory Allocation with Excessive Size Value (Score: 241.33)\n\nThe product allocates memory based on an untrusted, large size value, but it does not ensure that the size is within expected limits, allowing arbitrary amounts of memory to be allocated....\n\n### 4. CWE-755: Improper Handling of Exceptional Conditions (Score: 240.50)\n\nThe product does not handle or incorrectly handles an exceptional condition....\n\n### 5. CWE-476: NULL Pointer Dereference (Score: 237.89)\n\nThe product dereferences a pointer that it expects to be valid but is NULL....\n\n## ROOTCAUSE: 'unsafe reflection'\n\nRelevant CWEs for this ROOTCAUSE:\n\n### 1. CWE-248: Uncaught Exception (Score: 332.71)\n\nAn exception is thrown from a function, but it is not caught....\n\n### 2. CWE-470: Use of Externally-Controlled Input to Select Classes or Code ('Unsafe Reflection') (Score: 284.47)\n\nThe product uses external input with reflection to select which classes or code to use, but it does not sufficiently prevent the input from selecting improper classes or code....\n\n### 3. CWE-502: Deserialization of Untrusted Data (Score: 256.10)\n\nThe product deserializes untrusted data without sufficiently ensuring that the resulting data will be valid....\n\n### 4. CWE-610: Externally Controlled Reference to a Resource in Another Sphere (Score: 245.88)\n\nThe product uses an externally controlled name or reference that resolves to a resource that is outside of the intended control sphere....\n\n### 5. CWE-664: Improper Control of a Resource Through its Lifetime (Score: 239.23)\n\nThe product does not maintain or incorrectly maintains control over a resource throughout its lifetime of creation, use, and release....\n\n## IMPACT: 'crash of the hosting process and denial of service'\n\nRelevant CWEs for this IMPACT:\n\n### 1. CWE-248: Uncaught Exception (Score: 332.71)\n\nAn exception is thrown from a function, but it is not caught....\n\n### 2. CWE-617: Reachable Assertion (Score: 249.38)\n\nThe product contains an assert() or similar statement that can be triggered by an attacker, which leads to an application exit or other behavior that is more severe than necessary....\n\n### 3. CWE-789: Memory Allocation with Excessive Size Value (Score: 241.33)\n\nThe product allocates memory based on an untrusted, large size value, but it does not ensure that the size is within expected limits, allowing arbitrary amounts of memory to be allocated....\n\n### 4. CWE-755: Improper Handling of Exceptional Conditions (Score: 240.50)\n\nThe product does not handle or incorrectly handles an exceptional condition....\n\n### 5. CWE-476: NULL Pointer Dereference (Score: 237.89)\n\nThe product dereferences a pointer that it expects to be valid but is NULL....\n\n## PRODUCT: 'Telerik UI for AJAX'\n\nRelevant CWEs for this PRODUCT:\n\n### 1. CWE-248: Uncaught Exception (Score: 332.71)\n\nAn exception is thrown from a function, but it is not caught....\n\n### 2. CWE-502: Deserialization of Untrusted Data (Score: 256.10)\n\nThe product deserializes untrusted data without sufficiently ensuring that the resulting data will be valid....\n\n### 3. CWE-476: NULL Pointer Dereference (Score: 237.89)\n\nThe product dereferences a pointer that it expects to be valid but is NULL....\n\n### 4. CWE-862: Missing Authorization (Score: 84.05)\n\nThe product does not perform an authorization check when an actor attempts to access a resource or perform an action....\n\n### 5. CWE-352: Cross-Site Request Forgery (CSRF) (Score: 79.92)\n\nThe web application does not, or can not, sufficiently verify whether a well-formed, valid, consistent request was intentionally provided by the user who submitted the request....\n\n## VERSION: '2011.2.712 to 2025.1.218'\n\nRelevant CWEs for this VERSION:\n\n### 1. CWE-248: Uncaught Exception (Score: 332.71)\n\nAn exception is thrown from a function, but it is not caught....\n\n### 2. CWE-502: Deserialization of Untrusted Data (Score: 256.10)\n\nThe product deserializes untrusted data without sufficiently ensuring that the resulting data will be valid....\n\n### 3. CWE-835: Loop with Unreachable Exit Condition ('Infinite Loop') (Score: 88.49)\n\nThe product contains an iteration or loop with an exit condition that cannot be reached, i.e., an infinite loop....\n\n### 4. CWE-206: Observable Internal Behavioral Discrepancy (Score: 86.96)\n\nThe product performs multiple behaviors that are combined to produce a single result, but the individual behaviors are observable separately in a way that allows attackers to reveal internal state or internal decision points....\n\n### 5. CWE-776: Improper Restriction of Recursive Entity References in DTDs ('XML Entity Expansion') (Score: 85.85)\n\nThe product uses XML documents and allows their structure to be defined with a Document Type Definition (DTD), but it does not properly control the number of recursive definitions of entities....\n\n\n    # Analysis Instructions\n    1. For each keyphrase, identify the most appropriate CWE(s) that represent the weakness.\n    2. Consider how the different keyphrases might relate to each other in the vulnerability chain.\n    3. Provide a final determination of primary CWE(s) and any secondary CWEs.\n    4. Format your response using the standard analysis template.\n\n    Please analyze how these different weaknesses interact and provide a comprehensive CWE classification.\n    "
  },
  "retrieval_time": 1.1094059944152832
}