{
  "vulnerability_info": "VulnerabilityInfo(cve_id='CVE-2025-32075', description='Improper **Input Validation vulnerability** in The Wikimedia Foundation Mediawiki - Tabs Extension allows Code Injection.This issue affects Mediawiki - Tabs Extension from 1.39 through 1.43.', key_phrases={'rootcause': ['Input Validation vulnerability', 'Improper Input Validation'], 'weakness': 'code injection', 'impact': 'code injection', 'vector': '', 'attacker': '', 'product': 'The Wikimedia Foundation Mediawiki', 'version': 'Tabs Extension from 1.39 through 1.43', 'component': ''}, reference_content='## CVE-2025-32075 Analysis\\n\\nThis content is directly related to CVE-2025-32075. It provides significantly more detail than a standard CVE description.\\n\\n**Root cause of vulnerability:**\\n\\n*   CSS injection in system message tabs-dropdown-bgcolor due to insufficient sanitization of user-supplied input.\\n*   IP address and user agent leaks when rendering standalone tabs and regular tabs, stemming from issues within the `Tabs.php` file.\\n*   IP + User agent leak in the CSS sanitisation function.\\n\\n**Weaknesses/vulnerabilities present:**\\n\\n*   CSS Injection\\n*   Information Leakage (IP address and User-Agent)\\n*   Insufficient input sanitization\\n\\n**Impact of exploitation:**\\n\\n*   **CSS Injection:** An attacker can inject malicious CSS code, potentially altering the appearance and functionality of the page, and potentially leading to phishing or other attacks.\\n*   **Information Leakage:** Exposure of user IP addresses and User-Agent strings, compromising user privacy.\\n\\n**Attack vectors:**\\n\\n*   Setting a malicious message containing CSS code in the `tabs-dropdown-bgcolor` parameter.\\n*   Rendering a tab with a specific container configuration that triggers the IP/User-Agent leak.\\n*   Crafting a tab style attribute that bypasses CSS sanitization.\\n\\n**Required attacker capabilities/position:**\\n\\n*   Ability to control the content of messages or tab configurations.\\n*   No authentication is required to trigger the information leak.\\n\\n**Mitigation or fix:**\\n\\n*   The vulnerability was addressed by a patch set (changes 1121573, 1121581, 1121582, 1121583, 1121584) that includes sanitization improvements to prevent CSS injection and address the IP/User-Agent leakage issues.\\n*   The patch was merged into the `master`, `REL1_39`, `REL1_41`, `REL1_42`, and `REL1_43` branches of the `mediawiki/extensions/Tabs` repository.\\n*   The task was marked as resolved and the fix has been deployed.\\n\\n**Additional Details:**\\n\\n*   The vulnerable code is located in `includes/Tabs.php` within the `mediawiki/extensions/Tabs` extension. Specific lines mentioned are 420, 212, 279, and 372.\\n*   Screenshots are provided demonstrating the CSS injection and information leakage.\\n*   Gerrit links are provided for the relevant code changes and patch sets.\\n*   The risk rating is assessed as Medium.', similar_info={'cwe_distribution': {}, 'cwe_consensus': '', 'similarity_stats': {'thresholds': [], 'total_samples_by_threshold': {}, 'top_cwes_by_threshold': {}}}, similarity_summary=SimilarityInsight(consensus_cwe='', top_cwes=[], confidence_levels={}, total_samples=0), analysis='', analysis_with_relationships='', criticism='', resolution='', relevant_cwes=[{'metadata': {'doc_id': '79', 'name': \"Improper Neutralization of Input During Web Page Generation ('Cross-site Scripting')\", 'source': 'sparse', 'original_content': 'The product does not neutralize or incorrectly neutralizes user-controllable input before it is placed in output that is used as a web page that is served to other users.', 'keyphrase_sources': [{'id': 'rootcause:Input Validation vulnerability', 'keyphrase': 'Input Validation vulnerability', 'type': 'rootcause'}, {'id': 'rootcause:Improper Input Validation', 'keyphrase': 'Improper Input Validation', 'type': 'rootcause'}, {'id': 'weakness:code injection', 'keyphrase': 'code injection', 'type': 'weakness'}, {'id': 'impact:code injection', 'keyphrase': 'code injection', 'type': 'impact'}, {'id': 'product:The Wikimedia Foundation Mediawiki', 'keyphrase': 'The Wikimedia Foundation Mediawiki', 'type': 'product'}, {'id': 'version:Tabs Extension from 1.39 through 1.43', 'keyphrase': 'Tabs Extension from 1.39 through 1.43', 'type': 'version'}]}, 'similarity': np.float64(129.21494648446864)}, {'metadata': {'doc_id': '20', 'name': 'Improper Input Validation', 'source': 'sparse', 'original_content': 'The product receives input or data, but it does\\n        not validate or incorrectly validates that the input has the\\n        properties that are required to process the data safely and\\n        correctly.', 'keyphrase_sources': [{'id': 'rootcause:Input Validation vulnerability', 'keyphrase': 'Input Validation vulnerability', 'type': 'rootcause'}, {'id': 'rootcause:Improper Input Validation', 'keyphrase': 'Improper Input Validation', 'type': 'rootcause'}]}, 'similarity': np.float64(127.00886488358293)}, {'metadata': {'doc_id': '1284', 'name': 'Improper Validation of Specified Quantity in Input', 'source': 'sparse', 'original_content': 'The product receives input that is expected to specify a quantity (such as size or length), but it does not validate or incorrectly validates that the quantity has the required properties.', 'keyphrase_sources': [{'id': 'rootcause:Input Validation vulnerability', 'keyphrase': 'Input Validation vulnerability', 'type': 'rootcause'}, {'id': 'rootcause:Improper Input Validation', 'keyphrase': 'Improper Input Validation', 'type': 'rootcause'}]}, 'similarity': np.float64(124.06491370174282)}, {'metadata': {'doc_id': '179', 'name': 'Incorrect Behavior Order: Early Validation', 'source': 'sparse', 'original_content': 'The product validates input before applying protection mechanisms that modify the input, which could allow an attacker to bypass the validation via dangerous inputs that only arise after the modification.', 'keyphrase_sources': [{'id': 'rootcause:Input Validation vulnerability', 'keyphrase': 'Input Validation vulnerability', 'type': 'rootcause'}]}, 'similarity': np.float64(119.33005378274424)}, {'metadata': {'doc_id': '267', 'name': 'Privilege Defined With Unsafe Actions', 'source': 'sparse', 'original_content': 'A particular privilege, role, capability, or right can be used to perform unsafe actions that were not intended, even when it is assigned to the correct entity.', 'keyphrase_sources': [{'id': 'rootcause:Improper Input Validation', 'keyphrase': 'Improper Input Validation', 'type': 'rootcause'}, {'id': 'product:The Wikimedia Foundation Mediawiki', 'keyphrase': 'The Wikimedia Foundation Mediawiki', 'type': 'product'}, {'id': 'version:Tabs Extension from 1.39 through 1.43', 'keyphrase': 'Tabs Extension from 1.39 through 1.43', 'type': 'version'}]}, 'similarity': np.float64(118.85262711704107)}, {'metadata': {'doc_id': '116', 'name': 'Improper Encoding or Escaping of Output', 'source': 'sparse', 'original_content': 'The product prepares a structured message for communication with another component, but encoding or escaping of the data is either missing or done incorrectly. As a result, the intended structure of the message is not preserved.', 'keyphrase_sources': [{'id': 'rootcause:Input Validation vulnerability', 'keyphrase': 'Input Validation vulnerability', 'type': 'rootcause'}, {'id': 'rootcause:Improper Input Validation', 'keyphrase': 'Improper Input Validation', 'type': 'rootcause'}]}, 'similarity': np.float64(118.51737512180328)}, {'metadata': {'doc_id': '1336', 'name': 'Improper Neutralization of Special Elements Used in a Template Engine', 'source': 'sparse', 'original_content': 'The product uses a template engine to insert or process externally-influenced input, but it does not neutralize or incorrectly neutralizes special elements or syntax that can be interpreted as template expressions or other code directives when processed by the engine.', 'keyphrase_sources': [{'id': 'weakness:code injection', 'keyphrase': 'code injection', 'type': 'weakness'}, {'id': 'impact:code injection', 'keyphrase': 'code injection', 'type': 'impact'}]}, 'similarity': np.float64(115.4925671348627)}, {'metadata': {'doc_id': '138', 'name': 'Improper Neutralization of Special Elements', 'source': 'sparse', 'original_content': 'The product receives input from an upstream component, but it does not neutralize or incorrectly neutralizes special elements that could be interpreted as control elements or syntactic markers when they are sent to a downstream component.', 'keyphrase_sources': [{'id': 'weakness:code injection', 'keyphrase': 'code injection', 'type': 'weakness'}, {'id': 'impact:code injection', 'keyphrase': 'code injection', 'type': 'impact'}]}, 'similarity': np.float64(108.42847695290092)}, {'metadata': {'doc_id': '88', 'name': \"Improper Neutralization of Argument Delimiters in a Command ('Argument Injection')\", 'source': 'sparse', 'original_content': 'The product constructs a string for a command to be executed by a separate component\\nin another control sphere, but it does not properly delimit the\\nintended arguments, options, or switches within that command string.', 'keyphrase_sources': [{'id': 'weakness:code injection', 'keyphrase': 'code injection', 'type': 'weakness'}, {'id': 'impact:code injection', 'keyphrase': 'code injection', 'type': 'impact'}]}, 'similarity': np.float64(107.45300699018924)}, {'metadata': {'doc_id': '94', 'name': \"Improper Control of Generation of Code ('Code Injection')\", 'source': 'sparse', 'original_content': 'The product constructs all or part of a code segment using externally-influenced input from an upstream component, but it does not neutralize or incorrectly neutralizes special elements that could modify the syntax or behavior of the intended code segment.', 'keyphrase_sources': [{'id': 'weakness:code injection', 'keyphrase': 'code injection', 'type': 'weakness'}, {'id': 'impact:code injection', 'keyphrase': 'code injection', 'type': 'impact'}]}, 'similarity': np.float64(105.8713951238396)}, {'metadata': {'doc_id': '288', 'name': 'Authentication Bypass Using an Alternate Path or Channel', 'source': 'sparse', 'original_content': 'The product requires authentication, but the product has an alternate path or channel that does not require authentication.', 'keyphrase_sources': [{'id': 'version:Tabs Extension from 1.39 through 1.43', 'keyphrase': 'Tabs Extension from 1.39 through 1.43', 'type': 'version'}]}, 'similarity': np.float64(58.14341514927917)}, {'metadata': {'doc_id': '201', 'name': 'Insertion of Sensitive Information Into Sent Data', 'source': 'sparse', 'original_content': 'The code transmits data to another actor, but a portion of the data includes sensitive information that should not be accessible to that actor.', 'keyphrase_sources': [{'id': 'product:The Wikimedia Foundation Mediawiki', 'keyphrase': 'The Wikimedia Foundation Mediawiki', 'type': 'product'}, {'id': 'version:Tabs Extension from 1.39 through 1.43', 'keyphrase': 'Tabs Extension from 1.39 through 1.43', 'type': 'version'}]}, 'similarity': np.float64(54.18654188376406)}, {'metadata': {'doc_id': '820', 'name': 'Missing Synchronization', 'source': 'sparse', 'original_content': 'The product utilizes a shared resource in a concurrent manner but does not attempt to synchronize access to the resource.', 'keyphrase_sources': [{'id': 'version:Tabs Extension from 1.39 through 1.43', 'keyphrase': 'Tabs Extension from 1.39 through 1.43', 'type': 'version'}]}, 'similarity': np.float64(49.8864539079178)}, {'metadata': {'doc_id': '113', 'name': \"Improper Neutralization of CRLF Sequences in HTTP Headers ('HTTP Request/Response Splitting')\", 'source': 'sparse', 'original_content': 'The product receives data from an HTTP agent/component (e.g., web server, proxy, browser, etc.), but it does not neutralize or incorrectly neutralizes CR and LF characters before the data is included in outgoing HTTP headers.', 'keyphrase_sources': [{'id': 'product:The Wikimedia Foundation Mediawiki', 'keyphrase': 'The Wikimedia Foundation Mediawiki', 'type': 'product'}]}, 'similarity': np.float64(46.12311504530642)}, {'metadata': {'doc_id': '540', 'name': 'Inclusion of Sensitive Information in Source Code', 'source': 'sparse', 'original_content': 'Source code on a web server or repository often contains sensitive information and should generally not be accessible to users.', 'keyphrase_sources': [{'id': 'product:The Wikimedia Foundation Mediawiki', 'keyphrase': 'The Wikimedia Foundation Mediawiki', 'type': 'product'}]}, 'similarity': np.float64(44.825762373286956)}], identified_cwes={'analyzer': [], 'critic_additional': []})",
  "retrieval_results": {
    "has_multiple_keyphrases": true,
    "keyphrase_cwe_sets": {
      "rootcause:Input Validation vulnerability": {
        "keyphrase": "Input Validation vulnerability",
        "type": "rootcause",
        "cwes": [
          {
            "metadata": {
              "doc_id": "79",
              "name": "Improper Neutralization of Input During Web Page Generation ('Cross-site Scripting')",
              "source": "sparse",
              "original_content": "The product does not neutralize or incorrectly neutralizes user-controllable input before it is placed in output that is used as a web page that is served to other users.",
              "keyphrase_sources": [
                {
                  "id": "rootcause:Input Validation vulnerability",
                  "keyphrase": "Input Validation vulnerability",
                  "type": "rootcause"
                },
                {
                  "id": "rootcause:Improper Input Validation",
                  "keyphrase": "Improper Input Validation",
                  "type": "rootcause"
                },
                {
                  "id": "weakness:code injection",
                  "keyphrase": "code injection",
                  "type": "weakness"
                },
                {
                  "id": "impact:code injection",
                  "keyphrase": "code injection",
                  "type": "impact"
                },
                {
                  "id": "product:The Wikimedia Foundation Mediawiki",
                  "keyphrase": "The Wikimedia Foundation Mediawiki",
                  "type": "product"
                },
                {
                  "id": "version:Tabs Extension from 1.39 through 1.43",
                  "keyphrase": "Tabs Extension from 1.39 through 1.43",
                  "type": "version"
                }
              ]
            },
            "similarity": 129.21494648446864
          },
          {
            "metadata": {
              "doc_id": "20",
              "name": "Improper Input Validation",
              "source": "sparse",
              "original_content": "The product receives input or data, but it does\n        not validate or incorrectly validates that the input has the\n        properties that are required to process the data safely and\n        correctly.",
              "keyphrase_sources": [
                {
                  "id": "rootcause:Input Validation vulnerability",
                  "keyphrase": "Input Validation vulnerability",
                  "type": "rootcause"
                },
                {
                  "id": "rootcause:Improper Input Validation",
                  "keyphrase": "Improper Input Validation",
                  "type": "rootcause"
                }
              ]
            },
            "similarity": 127.00886488358293
          },
          {
            "metadata": {
              "doc_id": "1284",
              "name": "Improper Validation of Specified Quantity in Input",
              "source": "sparse",
              "original_content": "The product receives input that is expected to specify a quantity (such as size or length), but it does not validate or incorrectly validates that the quantity has the required properties.",
              "keyphrase_sources": [
                {
                  "id": "rootcause:Input Validation vulnerability",
                  "keyphrase": "Input Validation vulnerability",
                  "type": "rootcause"
                },
                {
                  "id": "rootcause:Improper Input Validation",
                  "keyphrase": "Improper Input Validation",
                  "type": "rootcause"
                }
              ]
            },
            "similarity": 124.06491370174282
          },
          {
            "metadata": {
              "doc_id": "179",
              "name": "Incorrect Behavior Order: Early Validation",
              "source": "sparse",
              "original_content": "The product validates input before applying protection mechanisms that modify the input, which could allow an attacker to bypass the validation via dangerous inputs that only arise after the modification.",
              "keyphrase_sources": [
                {
                  "id": "rootcause:Input Validation vulnerability",
                  "keyphrase": "Input Validation vulnerability",
                  "type": "rootcause"
                }
              ]
            },
            "similarity": 119.33005378274424
          },
          {
            "metadata": {
              "doc_id": "116",
              "name": "Improper Encoding or Escaping of Output",
              "source": "sparse",
              "original_content": "The product prepares a structured message for communication with another component, but encoding or escaping of the data is either missing or done incorrectly. As a result, the intended structure of the message is not preserved.",
              "keyphrase_sources": [
                {
                  "id": "rootcause:Input Validation vulnerability",
                  "keyphrase": "Input Validation vulnerability",
                  "type": "rootcause"
                },
                {
                  "id": "rootcause:Improper Input Validation",
                  "keyphrase": "Improper Input Validation",
                  "type": "rootcause"
                }
              ]
            },
            "similarity": 118.51737512180328
          }
        ]
      },
      "rootcause:Improper Input Validation": {
        "keyphrase": "Improper Input Validation",
        "type": "rootcause",
        "cwes": [
          {
            "metadata": {
              "doc_id": "20",
              "name": "Improper Input Validation",
              "source": "sparse",
              "original_content": "The product receives input or data, but it does\n        not validate or incorrectly validates that the input has the\n        properties that are required to process the data safely and\n        correctly."
            },
            "similarity": 131.76184340101733
          },
          {
            "metadata": {
              "doc_id": "79",
              "name": "Improper Neutralization of Input During Web Page Generation ('Cross-site Scripting')",
              "source": "sparse",
              "original_content": "The product does not neutralize or incorrectly neutralizes user-controllable input before it is placed in output that is used as a web page that is served to other users."
            },
            "similarity": 129.65227708227337
          },
          {
            "metadata": {
              "doc_id": "1284",
              "name": "Improper Validation of Specified Quantity in Input",
              "source": "sparse",
              "original_content": "The product receives input that is expected to specify a quantity (such as size or length), but it does not validate or incorrectly validates that the quantity has the required properties."
            },
            "similarity": 127.11982356601258
          },
          {
            "metadata": {
              "doc_id": "116",
              "name": "Improper Encoding or Escaping of Output",
              "source": "sparse",
              "original_content": "The product prepares a structured message for communication with another component, but encoding or escaping of the data is either missing or done incorrectly. As a result, the intended structure of the message is not preserved."
            },
            "similarity": 120.96371205353063
          },
          {
            "metadata": {
              "doc_id": "267",
              "name": "Privilege Defined With Unsafe Actions",
              "source": "sparse",
              "original_content": "A particular privilege, role, capability, or right can be used to perform unsafe actions that were not intended, even when it is assigned to the correct entity.",
              "keyphrase_sources": [
                {
                  "id": "rootcause:Improper Input Validation",
                  "keyphrase": "Improper Input Validation",
                  "type": "rootcause"
                },
                {
                  "id": "product:The Wikimedia Foundation Mediawiki",
                  "keyphrase": "The Wikimedia Foundation Mediawiki",
                  "type": "product"
                },
                {
                  "id": "version:Tabs Extension from 1.39 through 1.43",
                  "keyphrase": "Tabs Extension from 1.39 through 1.43",
                  "type": "version"
                }
              ]
            },
            "similarity": 118.85262711704107
          }
        ]
      },
      "weakness:code injection": {
        "keyphrase": "code injection",
        "type": "weakness",
        "cwes": [
          {
            "metadata": {
              "doc_id": "79",
              "name": "Improper Neutralization of Input During Web Page Generation ('Cross-site Scripting')",
              "source": "sparse",
              "original_content": "The product does not neutralize or incorrectly neutralizes user-controllable input before it is placed in output that is used as a web page that is served to other users."
            },
            "similarity": 128.19642772613847
          },
          {
            "metadata": {
              "doc_id": "1336",
              "name": "Improper Neutralization of Special Elements Used in a Template Engine",
              "source": "sparse",
              "original_content": "The product uses a template engine to insert or process externally-influenced input, but it does not neutralize or incorrectly neutralizes special elements or syntax that can be interpreted as template expressions or other code directives when processed by the engine.",
              "keyphrase_sources": [
                {
                  "id": "weakness:code injection",
                  "keyphrase": "code injection",
                  "type": "weakness"
                },
                {
                  "id": "impact:code injection",
                  "keyphrase": "code injection",
                  "type": "impact"
                }
              ]
            },
            "similarity": 115.4925671348627
          },
          {
            "metadata": {
              "doc_id": "138",
              "name": "Improper Neutralization of Special Elements",
              "source": "sparse",
              "original_content": "The product receives input from an upstream component, but it does not neutralize or incorrectly neutralizes special elements that could be interpreted as control elements or syntactic markers when they are sent to a downstream component.",
              "keyphrase_sources": [
                {
                  "id": "weakness:code injection",
                  "keyphrase": "code injection",
                  "type": "weakness"
                },
                {
                  "id": "impact:code injection",
                  "keyphrase": "code injection",
                  "type": "impact"
                }
              ]
            },
            "similarity": 108.42847695290092
          },
          {
            "metadata": {
              "doc_id": "88",
              "name": "Improper Neutralization of Argument Delimiters in a Command ('Argument Injection')",
              "source": "sparse",
              "original_content": "The product constructs a string for a command to be executed by a separate component\nin another control sphere, but it does not properly delimit the\nintended arguments, options, or switches within that command string.",
              "keyphrase_sources": [
                {
                  "id": "weakness:code injection",
                  "keyphrase": "code injection",
                  "type": "weakness"
                },
                {
                  "id": "impact:code injection",
                  "keyphrase": "code injection",
                  "type": "impact"
                }
              ]
            },
            "similarity": 107.45300699018924
          },
          {
            "metadata": {
              "doc_id": "94",
              "name": "Improper Control of Generation of Code ('Code Injection')",
              "source": "sparse",
              "original_content": "The product constructs all or part of a code segment using externally-influenced input from an upstream component, but it does not neutralize or incorrectly neutralizes special elements that could modify the syntax or behavior of the intended code segment.",
              "keyphrase_sources": [
                {
                  "id": "weakness:code injection",
                  "keyphrase": "code injection",
                  "type": "weakness"
                },
                {
                  "id": "impact:code injection",
                  "keyphrase": "code injection",
                  "type": "impact"
                }
              ]
            },
            "similarity": 105.8713951238396
          }
        ]
      },
      "impact:code injection": {
        "keyphrase": "code injection",
        "type": "impact",
        "cwes": [
          {
            "metadata": {
              "doc_id": "79",
              "name": "Improper Neutralization of Input During Web Page Generation ('Cross-site Scripting')",
              "source": "sparse",
              "original_content": "The product does not neutralize or incorrectly neutralizes user-controllable input before it is placed in output that is used as a web page that is served to other users."
            },
            "similarity": 45.78443847362088
          },
          {
            "metadata": {
              "doc_id": "1336",
              "name": "Improper Neutralization of Special Elements Used in a Template Engine",
              "source": "sparse",
              "original_content": "The product uses a template engine to insert or process externally-influenced input, but it does not neutralize or incorrectly neutralizes special elements or syntax that can be interpreted as template expressions or other code directives when processed by the engine."
            },
            "similarity": 41.24734540530811
          },
          {
            "metadata": {
              "doc_id": "138",
              "name": "Improper Neutralization of Special Elements",
              "source": "sparse",
              "original_content": "The product receives input from an upstream component, but it does not neutralize or incorrectly neutralizes special elements that could be interpreted as control elements or syntactic markers when they are sent to a downstream component."
            },
            "similarity": 38.72445605460747
          },
          {
            "metadata": {
              "doc_id": "88",
              "name": "Improper Neutralization of Argument Delimiters in a Command ('Argument Injection')",
              "source": "sparse",
              "original_content": "The product constructs a string for a command to be executed by a separate component\nin another control sphere, but it does not properly delimit the\nintended arguments, options, or switches within that command string."
            },
            "similarity": 38.37607392506759
          },
          {
            "metadata": {
              "doc_id": "94",
              "name": "Improper Control of Generation of Code ('Code Injection')",
              "source": "sparse",
              "original_content": "The product constructs all or part of a code segment using externally-influenced input from an upstream component, but it does not neutralize or incorrectly neutralizes special elements that could modify the syntax or behavior of the intended code segment."
            },
            "similarity": 37.81121254422843
          }
        ]
      },
      "product:The Wikimedia Foundation Mediawiki": {
        "keyphrase": "The Wikimedia Foundation Mediawiki",
        "type": "product",
        "cwes": [
          {
            "metadata": {
              "doc_id": "201",
              "name": "Insertion of Sensitive Information Into Sent Data",
              "source": "sparse",
              "original_content": "The code transmits data to another actor, but a portion of the data includes sensitive information that should not be accessible to that actor.",
              "keyphrase_sources": [
                {
                  "id": "product:The Wikimedia Foundation Mediawiki",
                  "keyphrase": "The Wikimedia Foundation Mediawiki",
                  "type": "product"
                },
                {
                  "id": "version:Tabs Extension from 1.39 through 1.43",
                  "keyphrase": "Tabs Extension from 1.39 through 1.43",
                  "type": "version"
                }
              ]
            },
            "similarity": 54.18654188376406
          },
          {
            "metadata": {
              "doc_id": "267",
              "name": "Privilege Defined With Unsafe Actions",
              "source": "sparse",
              "original_content": "A particular privilege, role, capability, or right can be used to perform unsafe actions that were not intended, even when it is assigned to the correct entity."
            },
            "similarity": 52.40840576899273
          },
          {
            "metadata": {
              "doc_id": "79",
              "name": "Improper Neutralization of Input During Web Page Generation ('Cross-site Scripting')",
              "source": "sparse",
              "original_content": "The product does not neutralize or incorrectly neutralizes user-controllable input before it is placed in output that is used as a web page that is served to other users."
            },
            "similarity": 47.62923656907421
          },
          {
            "metadata": {
              "doc_id": "113",
              "name": "Improper Neutralization of CRLF Sequences in HTTP Headers ('HTTP Request/Response Splitting')",
              "source": "sparse",
              "original_content": "The product receives data from an HTTP agent/component (e.g., web server, proxy, browser, etc.), but it does not neutralize or incorrectly neutralizes CR and LF characters before the data is included in outgoing HTTP headers.",
              "keyphrase_sources": [
                {
                  "id": "product:The Wikimedia Foundation Mediawiki",
                  "keyphrase": "The Wikimedia Foundation Mediawiki",
                  "type": "product"
                }
              ]
            },
            "similarity": 46.12311504530642
          },
          {
            "metadata": {
              "doc_id": "540",
              "name": "Inclusion of Sensitive Information in Source Code",
              "source": "sparse",
              "original_content": "Source code on a web server or repository often contains sensitive information and should generally not be accessible to users.",
              "keyphrase_sources": [
                {
                  "id": "product:The Wikimedia Foundation Mediawiki",
                  "keyphrase": "The Wikimedia Foundation Mediawiki",
                  "type": "product"
                }
              ]
            },
            "similarity": 44.825762373286956
          }
        ]
      },
      "version:Tabs Extension from 1.39 through 1.43": {
        "keyphrase": "Tabs Extension from 1.39 through 1.43",
        "type": "version",
        "cwes": [
          {
            "metadata": {
              "doc_id": "79",
              "name": "Improper Neutralization of Input During Web Page Generation ('Cross-site Scripting')",
              "source": "sparse",
              "original_content": "The product does not neutralize or incorrectly neutralizes user-controllable input before it is placed in output that is used as a web page that is served to other users."
            },
            "similarity": 59.67240953169991
          },
          {
            "metadata": {
              "doc_id": "288",
              "name": "Authentication Bypass Using an Alternate Path or Channel",
              "source": "sparse",
              "original_content": "The product requires authentication, but the product has an alternate path or channel that does not require authentication.",
              "keyphrase_sources": [
                {
                  "id": "version:Tabs Extension from 1.39 through 1.43",
                  "keyphrase": "Tabs Extension from 1.39 through 1.43",
                  "type": "version"
                }
              ]
            },
            "similarity": 58.14341514927917
          },
          {
            "metadata": {
              "doc_id": "201",
              "name": "Insertion of Sensitive Information Into Sent Data",
              "source": "sparse",
              "original_content": "The code transmits data to another actor, but a portion of the data includes sensitive information that should not be accessible to that actor."
            },
            "similarity": 56.54169474327151
          },
          {
            "metadata": {
              "doc_id": "267",
              "name": "Privilege Defined With Unsafe Actions",
              "source": "sparse",
              "original_content": "A particular privilege, role, capability, or right can be used to perform unsafe actions that were not intended, even when it is assigned to the correct entity."
            },
            "similarity": 50.953979774775355
          },
          {
            "metadata": {
              "doc_id": "820",
              "name": "Missing Synchronization",
              "source": "sparse",
              "original_content": "The product utilizes a shared resource in a concurrent manner but does not attempt to synchronize access to the resource.",
              "keyphrase_sources": [
                {
                  "id": "version:Tabs Extension from 1.39 through 1.43",
                  "keyphrase": "Tabs Extension from 1.39 through 1.43",
                  "type": "version"
                }
              ]
            },
            "similarity": 49.8864539079178
          }
        ]
      }
    },
    "keyphrase_mapping": {
      "79": [
        {
          "id": "rootcause:Input Validation vulnerability",
          "keyphrase": "Input Validation vulnerability",
          "type": "rootcause"
        },
        {
          "id": "rootcause:Improper Input Validation",
          "keyphrase": "Improper Input Validation",
          "type": "rootcause"
        },
        {
          "id": "weakness:code injection",
          "keyphrase": "code injection",
          "type": "weakness"
        },
        {
          "id": "impact:code injection",
          "keyphrase": "code injection",
          "type": "impact"
        },
        {
          "id": "product:The Wikimedia Foundation Mediawiki",
          "keyphrase": "The Wikimedia Foundation Mediawiki",
          "type": "product"
        },
        {
          "id": "version:Tabs Extension from 1.39 through 1.43",
          "keyphrase": "Tabs Extension from 1.39 through 1.43",
          "type": "version"
        }
      ],
      "20": [
        {
          "id": "rootcause:Input Validation vulnerability",
          "keyphrase": "Input Validation vulnerability",
          "type": "rootcause"
        },
        {
          "id": "rootcause:Improper Input Validation",
          "keyphrase": "Improper Input Validation",
          "type": "rootcause"
        }
      ],
      "1284": [
        {
          "id": "rootcause:Input Validation vulnerability",
          "keyphrase": "Input Validation vulnerability",
          "type": "rootcause"
        },
        {
          "id": "rootcause:Improper Input Validation",
          "keyphrase": "Improper Input Validation",
          "type": "rootcause"
        }
      ],
      "179": [
        {
          "id": "rootcause:Input Validation vulnerability",
          "keyphrase": "Input Validation vulnerability",
          "type": "rootcause"
        }
      ],
      "116": [
        {
          "id": "rootcause:Input Validation vulnerability",
          "keyphrase": "Input Validation vulnerability",
          "type": "rootcause"
        },
        {
          "id": "rootcause:Improper Input Validation",
          "keyphrase": "Improper Input Validation",
          "type": "rootcause"
        }
      ],
      "267": [
        {
          "id": "rootcause:Improper Input Validation",
          "keyphrase": "Improper Input Validation",
          "type": "rootcause"
        },
        {
          "id": "product:The Wikimedia Foundation Mediawiki",
          "keyphrase": "The Wikimedia Foundation Mediawiki",
          "type": "product"
        },
        {
          "id": "version:Tabs Extension from 1.39 through 1.43",
          "keyphrase": "Tabs Extension from 1.39 through 1.43",
          "type": "version"
        }
      ],
      "1336": [
        {
          "id": "weakness:code injection",
          "keyphrase": "code injection",
          "type": "weakness"
        },
        {
          "id": "impact:code injection",
          "keyphrase": "code injection",
          "type": "impact"
        }
      ],
      "138": [
        {
          "id": "weakness:code injection",
          "keyphrase": "code injection",
          "type": "weakness"
        },
        {
          "id": "impact:code injection",
          "keyphrase": "code injection",
          "type": "impact"
        }
      ],
      "88": [
        {
          "id": "weakness:code injection",
          "keyphrase": "code injection",
          "type": "weakness"
        },
        {
          "id": "impact:code injection",
          "keyphrase": "code injection",
          "type": "impact"
        }
      ],
      "94": [
        {
          "id": "weakness:code injection",
          "keyphrase": "code injection",
          "type": "weakness"
        },
        {
          "id": "impact:code injection",
          "keyphrase": "code injection",
          "type": "impact"
        }
      ],
      "201": [
        {
          "id": "product:The Wikimedia Foundation Mediawiki",
          "keyphrase": "The Wikimedia Foundation Mediawiki",
          "type": "product"
        },
        {
          "id": "version:Tabs Extension from 1.39 through 1.43",
          "keyphrase": "Tabs Extension from 1.39 through 1.43",
          "type": "version"
        }
      ],
      "113": [
        {
          "id": "product:The Wikimedia Foundation Mediawiki",
          "keyphrase": "The Wikimedia Foundation Mediawiki",
          "type": "product"
        }
      ],
      "540": [
        {
          "id": "product:The Wikimedia Foundation Mediawiki",
          "keyphrase": "The Wikimedia Foundation Mediawiki",
          "type": "product"
        }
      ],
      "288": [
        {
          "id": "version:Tabs Extension from 1.39 through 1.43",
          "keyphrase": "Tabs Extension from 1.39 through 1.43",
          "type": "version"
        }
      ],
      "820": [
        {
          "id": "version:Tabs Extension from 1.39 through 1.43",
          "keyphrase": "Tabs Extension from 1.39 through 1.43",
          "type": "version"
        }
      ]
    },
    "relevant_cwes": [
      {
        "metadata": {
          "doc_id": "79",
          "name": "Improper Neutralization of Input During Web Page Generation ('Cross-site Scripting')",
          "source": "sparse",
          "original_content": "The product does not neutralize or incorrectly neutralizes user-controllable input before it is placed in output that is used as a web page that is served to other users.",
          "keyphrase_sources": [
            {
              "id": "rootcause:Input Validation vulnerability",
              "keyphrase": "Input Validation vulnerability",
              "type": "rootcause"
            },
            {
              "id": "rootcause:Improper Input Validation",
              "keyphrase": "Improper Input Validation",
              "type": "rootcause"
            },
            {
              "id": "weakness:code injection",
              "keyphrase": "code injection",
              "type": "weakness"
            },
            {
              "id": "impact:code injection",
              "keyphrase": "code injection",
              "type": "impact"
            },
            {
              "id": "product:The Wikimedia Foundation Mediawiki",
              "keyphrase": "The Wikimedia Foundation Mediawiki",
              "type": "product"
            },
            {
              "id": "version:Tabs Extension from 1.39 through 1.43",
              "keyphrase": "Tabs Extension from 1.39 through 1.43",
              "type": "version"
            }
          ]
        },
        "similarity": 129.21494648446864
      },
      {
        "metadata": {
          "doc_id": "20",
          "name": "Improper Input Validation",
          "source": "sparse",
          "original_content": "The product receives input or data, but it does\n        not validate or incorrectly validates that the input has the\n        properties that are required to process the data safely and\n        correctly.",
          "keyphrase_sources": [
            {
              "id": "rootcause:Input Validation vulnerability",
              "keyphrase": "Input Validation vulnerability",
              "type": "rootcause"
            },
            {
              "id": "rootcause:Improper Input Validation",
              "keyphrase": "Improper Input Validation",
              "type": "rootcause"
            }
          ]
        },
        "similarity": 127.00886488358293
      },
      {
        "metadata": {
          "doc_id": "1284",
          "name": "Improper Validation of Specified Quantity in Input",
          "source": "sparse",
          "original_content": "The product receives input that is expected to specify a quantity (such as size or length), but it does not validate or incorrectly validates that the quantity has the required properties.",
          "keyphrase_sources": [
            {
              "id": "rootcause:Input Validation vulnerability",
              "keyphrase": "Input Validation vulnerability",
              "type": "rootcause"
            },
            {
              "id": "rootcause:Improper Input Validation",
              "keyphrase": "Improper Input Validation",
              "type": "rootcause"
            }
          ]
        },
        "similarity": 124.06491370174282
      },
      {
        "metadata": {
          "doc_id": "179",
          "name": "Incorrect Behavior Order: Early Validation",
          "source": "sparse",
          "original_content": "The product validates input before applying protection mechanisms that modify the input, which could allow an attacker to bypass the validation via dangerous inputs that only arise after the modification.",
          "keyphrase_sources": [
            {
              "id": "rootcause:Input Validation vulnerability",
              "keyphrase": "Input Validation vulnerability",
              "type": "rootcause"
            }
          ]
        },
        "similarity": 119.33005378274424
      },
      {
        "metadata": {
          "doc_id": "267",
          "name": "Privilege Defined With Unsafe Actions",
          "source": "sparse",
          "original_content": "A particular privilege, role, capability, or right can be used to perform unsafe actions that were not intended, even when it is assigned to the correct entity.",
          "keyphrase_sources": [
            {
              "id": "rootcause:Improper Input Validation",
              "keyphrase": "Improper Input Validation",
              "type": "rootcause"
            },
            {
              "id": "product:The Wikimedia Foundation Mediawiki",
              "keyphrase": "The Wikimedia Foundation Mediawiki",
              "type": "product"
            },
            {
              "id": "version:Tabs Extension from 1.39 through 1.43",
              "keyphrase": "Tabs Extension from 1.39 through 1.43",
              "type": "version"
            }
          ]
        },
        "similarity": 118.85262711704107
      },
      {
        "metadata": {
          "doc_id": "116",
          "name": "Improper Encoding or Escaping of Output",
          "source": "sparse",
          "original_content": "The product prepares a structured message for communication with another component, but encoding or escaping of the data is either missing or done incorrectly. As a result, the intended structure of the message is not preserved.",
          "keyphrase_sources": [
            {
              "id": "rootcause:Input Validation vulnerability",
              "keyphrase": "Input Validation vulnerability",
              "type": "rootcause"
            },
            {
              "id": "rootcause:Improper Input Validation",
              "keyphrase": "Improper Input Validation",
              "type": "rootcause"
            }
          ]
        },
        "similarity": 118.51737512180328
      },
      {
        "metadata": {
          "doc_id": "1336",
          "name": "Improper Neutralization of Special Elements Used in a Template Engine",
          "source": "sparse",
          "original_content": "The product uses a template engine to insert or process externally-influenced input, but it does not neutralize or incorrectly neutralizes special elements or syntax that can be interpreted as template expressions or other code directives when processed by the engine.",
          "keyphrase_sources": [
            {
              "id": "weakness:code injection",
              "keyphrase": "code injection",
              "type": "weakness"
            },
            {
              "id": "impact:code injection",
              "keyphrase": "code injection",
              "type": "impact"
            }
          ]
        },
        "similarity": 115.4925671348627
      },
      {
        "metadata": {
          "doc_id": "138",
          "name": "Improper Neutralization of Special Elements",
          "source": "sparse",
          "original_content": "The product receives input from an upstream component, but it does not neutralize or incorrectly neutralizes special elements that could be interpreted as control elements or syntactic markers when they are sent to a downstream component.",
          "keyphrase_sources": [
            {
              "id": "weakness:code injection",
              "keyphrase": "code injection",
              "type": "weakness"
            },
            {
              "id": "impact:code injection",
              "keyphrase": "code injection",
              "type": "impact"
            }
          ]
        },
        "similarity": 108.42847695290092
      },
      {
        "metadata": {
          "doc_id": "88",
          "name": "Improper Neutralization of Argument Delimiters in a Command ('Argument Injection')",
          "source": "sparse",
          "original_content": "The product constructs a string for a command to be executed by a separate component\nin another control sphere, but it does not properly delimit the\nintended arguments, options, or switches within that command string.",
          "keyphrase_sources": [
            {
              "id": "weakness:code injection",
              "keyphrase": "code injection",
              "type": "weakness"
            },
            {
              "id": "impact:code injection",
              "keyphrase": "code injection",
              "type": "impact"
            }
          ]
        },
        "similarity": 107.45300699018924
      },
      {
        "metadata": {
          "doc_id": "94",
          "name": "Improper Control of Generation of Code ('Code Injection')",
          "source": "sparse",
          "original_content": "The product constructs all or part of a code segment using externally-influenced input from an upstream component, but it does not neutralize or incorrectly neutralizes special elements that could modify the syntax or behavior of the intended code segment.",
          "keyphrase_sources": [
            {
              "id": "weakness:code injection",
              "keyphrase": "code injection",
              "type": "weakness"
            },
            {
              "id": "impact:code injection",
              "keyphrase": "code injection",
              "type": "impact"
            }
          ]
        },
        "similarity": 105.8713951238396
      },
      {
        "metadata": {
          "doc_id": "288",
          "name": "Authentication Bypass Using an Alternate Path or Channel",
          "source": "sparse",
          "original_content": "The product requires authentication, but the product has an alternate path or channel that does not require authentication.",
          "keyphrase_sources": [
            {
              "id": "version:Tabs Extension from 1.39 through 1.43",
              "keyphrase": "Tabs Extension from 1.39 through 1.43",
              "type": "version"
            }
          ]
        },
        "similarity": 58.14341514927917
      },
      {
        "metadata": {
          "doc_id": "201",
          "name": "Insertion of Sensitive Information Into Sent Data",
          "source": "sparse",
          "original_content": "The code transmits data to another actor, but a portion of the data includes sensitive information that should not be accessible to that actor.",
          "keyphrase_sources": [
            {
              "id": "product:The Wikimedia Foundation Mediawiki",
              "keyphrase": "The Wikimedia Foundation Mediawiki",
              "type": "product"
            },
            {
              "id": "version:Tabs Extension from 1.39 through 1.43",
              "keyphrase": "Tabs Extension from 1.39 through 1.43",
              "type": "version"
            }
          ]
        },
        "similarity": 54.18654188376406
      },
      {
        "metadata": {
          "doc_id": "820",
          "name": "Missing Synchronization",
          "source": "sparse",
          "original_content": "The product utilizes a shared resource in a concurrent manner but does not attempt to synchronize access to the resource.",
          "keyphrase_sources": [
            {
              "id": "version:Tabs Extension from 1.39 through 1.43",
              "keyphrase": "Tabs Extension from 1.39 through 1.43",
              "type": "version"
            }
          ]
        },
        "similarity": 49.8864539079178
      },
      {
        "metadata": {
          "doc_id": "113",
          "name": "Improper Neutralization of CRLF Sequences in HTTP Headers ('HTTP Request/Response Splitting')",
          "source": "sparse",
          "original_content": "The product receives data from an HTTP agent/component (e.g., web server, proxy, browser, etc.), but it does not neutralize or incorrectly neutralizes CR and LF characters before the data is included in outgoing HTTP headers.",
          "keyphrase_sources": [
            {
              "id": "product:The Wikimedia Foundation Mediawiki",
              "keyphrase": "The Wikimedia Foundation Mediawiki",
              "type": "product"
            }
          ]
        },
        "similarity": 46.12311504530642
      },
      {
        "metadata": {
          "doc_id": "540",
          "name": "Inclusion of Sensitive Information in Source Code",
          "source": "sparse",
          "original_content": "Source code on a web server or repository often contains sensitive information and should generally not be accessible to users.",
          "keyphrase_sources": [
            {
              "id": "product:The Wikimedia Foundation Mediawiki",
              "keyphrase": "The Wikimedia Foundation Mediawiki",
              "type": "product"
            }
          ]
        },
        "similarity": 44.825762373286956
      }
    ],
    "enhanced_query": "# Vulnerability Description\n\n    Improper **Input Validation vulnerability** in The Wikimedia Foundation Mediawiki - Tabs Extension allows Code Injection.This issue affects Mediawiki - Tabs Extension from 1.39 through 1.43.\n\n    # Keyphrase-Specific CWE Analysis\n    This vulnerability contains multiple keyphrases that may map to different CWEs. \n    Please analyze each keyphrase separately and determine the most appropriate CWE(s) for each.\n\n    ## ROOTCAUSE: 'Input Validation vulnerability'\n\nRelevant CWEs for this ROOTCAUSE:\n\n### 1. CWE-79: Improper Neutralization of Input During Web Page Generation ('Cross-site Scripting') (Score: 129.21)\n\nThe product does not neutralize or incorrectly neutralizes user-controllable input before it is placed in output that is used as a web page that is served to other users....\n\n### 2. CWE-20: Improper Input Validation (Score: 127.01)\n\nThe product receives input or data, but it does\n        not validate or incorrectly validates that the input has the\n        properties that are required to process the data safely and\n        correctly....\n\n### 3. CWE-1284: Improper Validation of Specified Quantity in Input (Score: 124.06)\n\nThe product receives input that is expected to specify a quantity (such as size or length), but it does not validate or incorrectly validates that the quantity has the required properties....\n\n### 4. CWE-179: Incorrect Behavior Order: Early Validation (Score: 119.33)\n\nThe product validates input before applying protection mechanisms that modify the input, which could allow an attacker to bypass the validation via dangerous inputs that only arise after the modification....\n\n### 5. CWE-116: Improper Encoding or Escaping of Output (Score: 118.52)\n\nThe product prepares a structured message for communication with another component, but encoding or escaping of the data is either missing or done incorrectly. As a result, the intended structure of the message is not preserved....\n\n## ROOTCAUSE: 'Improper Input Validation'\n\nRelevant CWEs for this ROOTCAUSE:\n\n### 1. CWE-79: Improper Neutralization of Input During Web Page Generation ('Cross-site Scripting') (Score: 129.21)\n\nThe product does not neutralize or incorrectly neutralizes user-controllable input before it is placed in output that is used as a web page that is served to other users....\n\n### 2. CWE-20: Improper Input Validation (Score: 127.01)\n\nThe product receives input or data, but it does\n        not validate or incorrectly validates that the input has the\n        properties that are required to process the data safely and\n        correctly....\n\n### 3. CWE-1284: Improper Validation of Specified Quantity in Input (Score: 124.06)\n\nThe product receives input that is expected to specify a quantity (such as size or length), but it does not validate or incorrectly validates that the quantity has the required properties....\n\n### 4. CWE-267: Privilege Defined With Unsafe Actions (Score: 118.85)\n\nA particular privilege, role, capability, or right can be used to perform unsafe actions that were not intended, even when it is assigned to the correct entity....\n\n### 5. CWE-116: Improper Encoding or Escaping of Output (Score: 118.52)\n\nThe product prepares a structured message for communication with another component, but encoding or escaping of the data is either missing or done incorrectly. As a result, the intended structure of the message is not preserved....\n\n## WEAKNESS: 'code injection'\n\nRelevant CWEs for this WEAKNESS:\n\n### 1. CWE-79: Improper Neutralization of Input During Web Page Generation ('Cross-site Scripting') (Score: 129.21)\n\nThe product does not neutralize or incorrectly neutralizes user-controllable input before it is placed in output that is used as a web page that is served to other users....\n\n### 2. CWE-1336: Improper Neutralization of Special Elements Used in a Template Engine (Score: 115.49)\n\nThe product uses a template engine to insert or process externally-influenced input, but it does not neutralize or incorrectly neutralizes special elements or syntax that can be interpreted as template expressions or other code directives when processed by the engine....\n\n### 3. CWE-138: Improper Neutralization of Special Elements (Score: 108.43)\n\nThe product receives input from an upstream component, but it does not neutralize or incorrectly neutralizes special elements that could be interpreted as control elements or syntactic markers when they are sent to a downstream component....\n\n### 4. CWE-88: Improper Neutralization of Argument Delimiters in a Command ('Argument Injection') (Score: 107.45)\n\nThe product constructs a string for a command to be executed by a separate component\nin another control sphere, but it does not properly delimit the\nintended arguments, options, or switches within that command string....\n\n### 5. CWE-94: Improper Control of Generation of Code ('Code Injection') (Score: 105.87)\n\nThe product constructs all or part of a code segment using externally-influenced input from an upstream component, but it does not neutralize or incorrectly neutralizes special elements that could modify the syntax or behavior of the intended code segment....\n\n## IMPACT: 'code injection'\n\nRelevant CWEs for this IMPACT:\n\n### 1. CWE-79: Improper Neutralization of Input During Web Page Generation ('Cross-site Scripting') (Score: 129.21)\n\nThe product does not neutralize or incorrectly neutralizes user-controllable input before it is placed in output that is used as a web page that is served to other users....\n\n### 2. CWE-1336: Improper Neutralization of Special Elements Used in a Template Engine (Score: 115.49)\n\nThe product uses a template engine to insert or process externally-influenced input, but it does not neutralize or incorrectly neutralizes special elements or syntax that can be interpreted as template expressions or other code directives when processed by the engine....\n\n### 3. CWE-138: Improper Neutralization of Special Elements (Score: 108.43)\n\nThe product receives input from an upstream component, but it does not neutralize or incorrectly neutralizes special elements that could be interpreted as control elements or syntactic markers when they are sent to a downstream component....\n\n### 4. CWE-88: Improper Neutralization of Argument Delimiters in a Command ('Argument Injection') (Score: 107.45)\n\nThe product constructs a string for a command to be executed by a separate component\nin another control sphere, but it does not properly delimit the\nintended arguments, options, or switches within that command string....\n\n### 5. CWE-94: Improper Control of Generation of Code ('Code Injection') (Score: 105.87)\n\nThe product constructs all or part of a code segment using externally-influenced input from an upstream component, but it does not neutralize or incorrectly neutralizes special elements that could modify the syntax or behavior of the intended code segment....\n\n## PRODUCT: 'The Wikimedia Foundation Mediawiki'\n\nRelevant CWEs for this PRODUCT:\n\n### 1. CWE-79: Improper Neutralization of Input During Web Page Generation ('Cross-site Scripting') (Score: 129.21)\n\nThe product does not neutralize or incorrectly neutralizes user-controllable input before it is placed in output that is used as a web page that is served to other users....\n\n### 2. CWE-267: Privilege Defined With Unsafe Actions (Score: 118.85)\n\nA particular privilege, role, capability, or right can be used to perform unsafe actions that were not intended, even when it is assigned to the correct entity....\n\n### 3. CWE-201: Insertion of Sensitive Information Into Sent Data (Score: 54.19)\n\nThe code transmits data to another actor, but a portion of the data includes sensitive information that should not be accessible to that actor....\n\n### 4. CWE-113: Improper Neutralization of CRLF Sequences in HTTP Headers ('HTTP Request/Response Splitting') (Score: 46.12)\n\nThe product receives data from an HTTP agent/component (e.g., web server, proxy, browser, etc.), but it does not neutralize or incorrectly neutralizes CR and LF characters before the data is included in outgoing HTTP headers....\n\n### 5. CWE-540: Inclusion of Sensitive Information in Source Code (Score: 44.83)\n\nSource code on a web server or repository often contains sensitive information and should generally not be accessible to users....\n\n## VERSION: 'Tabs Extension from 1.39 through 1.43'\n\nRelevant CWEs for this VERSION:\n\n### 1. CWE-79: Improper Neutralization of Input During Web Page Generation ('Cross-site Scripting') (Score: 129.21)\n\nThe product does not neutralize or incorrectly neutralizes user-controllable input before it is placed in output that is used as a web page that is served to other users....\n\n### 2. CWE-267: Privilege Defined With Unsafe Actions (Score: 118.85)\n\nA particular privilege, role, capability, or right can be used to perform unsafe actions that were not intended, even when it is assigned to the correct entity....\n\n### 3. CWE-288: Authentication Bypass Using an Alternate Path or Channel (Score: 58.14)\n\nThe product requires authentication, but the product has an alternate path or channel that does not require authentication....\n\n### 4. CWE-201: Insertion of Sensitive Information Into Sent Data (Score: 54.19)\n\nThe code transmits data to another actor, but a portion of the data includes sensitive information that should not be accessible to that actor....\n\n### 5. CWE-820: Missing Synchronization (Score: 49.89)\n\nThe product utilizes a shared resource in a concurrent manner but does not attempt to synchronize access to the resource....\n\n\n    # Analysis Instructions\n    1. For each keyphrase, identify the most appropriate CWE(s) that represent the weakness.\n    2. Consider how the different keyphrases might relate to each other in the vulnerability chain.\n    3. Provide a final determination of primary CWE(s) and any secondary CWEs.\n    4. Format your response using the standard analysis template.\n\n    Please analyze how these different weaknesses interact and provide a comprehensive CWE classification.\n    "
  },
  "retrieval_time": 1.0597989559173584
}