{
  "vulnerability_info": "VulnerabilityInfo(cve_id='CVE-2025-23446', description='Cross-Site Request Forgery (CSRF) vulnerability in NotFound WP SpaceContent allows Stored **XSS**. This issue affects WP SpaceContent from n/a through 0.4.5.', key_phrases={'rootcause': 'cross-site request forgery', 'weakness': ['stored cross-site scripting', 'XSS'], 'impact': '', 'vector': '', 'attacker': '', 'product': 'NotFound WP SpaceContent', 'version': 'n/a through 0.4.5', 'component': ''}, reference_content='Root cause of vulnerability: Cross Site Request Forgery (CSRF)\\nWeaknesses/vulnerabilities present: Cross Site Request Forgery (CSRF)\\nImpact of exploitation: Could allow a malicious actor to force higher privileged users to execute unwanted actions under their current authentication.\\nAttack vectors: Not specified\\nRequired attacker capabilities/position: Unauthenticated\\nMitigation or fix: Patchstack has issued a virtual patch to mitigate this issue by blocking any attacks until an official fix becomes available.\\nVulnerable software: WP SpaceContent plugin <= 0.4.5\\nSeverity: Medium (CVSS 7.1)\\nMore detail than the official CVE description: Yes, the content provides details on the vulnerable software, type of vulnerability, impact, and mitigation. It also provides the CVSS score.', similar_info={'cwe_distribution': {}, 'cwe_consensus': '', 'similarity_stats': {'thresholds': [], 'total_samples_by_threshold': {}, 'top_cwes_by_threshold': {}}}, similarity_summary=SimilarityInsight(consensus_cwe='', top_cwes=[], confidence_levels={}, total_samples=0), analysis='', analysis_with_relationships='', criticism='', resolution='', relevant_cwes=[{'metadata': {'doc_id': '352', 'name': 'Cross-Site Request Forgery (CSRF)', 'source': 'sparse', 'original_content': 'The web application does not, or can not, sufficiently verify whether a well-formed, valid, consistent request was intentionally provided by the user who submitted the request.', 'keyphrase_sources': [{'id': 'rootcause:cross-site request forgery', 'keyphrase': 'cross-site request forgery', 'type': 'rootcause'}, {'id': 'weakness:stored cross-site scripting', 'keyphrase': 'stored cross-site scripting', 'type': 'weakness'}, {'id': 'weakness:XSS', 'keyphrase': 'XSS', 'type': 'weakness'}, {'id': 'product:NotFound WP SpaceContent', 'keyphrase': 'NotFound WP SpaceContent', 'type': 'product'}, {'id': 'version:n/a through 0.4.5', 'keyphrase': 'n/a through 0.4.5', 'type': 'version'}]}, 'similarity': np.float64(321.13207282482745)}, {'metadata': {'doc_id': '89', 'name': \"Improper Neutralization of Special Elements used in an SQL Command ('SQL Injection')\", 'source': 'sparse', 'original_content': 'The product constructs all or part of an SQL command using externally-influenced input from an upstream component, but it does not neutralize or incorrectly neutralizes special elements that could modify the intended SQL command when it is sent to a downstream component. Without sufficient removal or quoting of SQL syntax in user-controllable inputs, the generated SQL query can cause those inputs to be interpreted as SQL instead of ordinary user data.', 'keyphrase_sources': [{'id': 'rootcause:cross-site request forgery', 'keyphrase': 'cross-site request forgery', 'type': 'rootcause'}, {'id': 'product:NotFound WP SpaceContent', 'keyphrase': 'NotFound WP SpaceContent', 'type': 'product'}, {'id': 'version:n/a through 0.4.5', 'keyphrase': 'n/a through 0.4.5', 'type': 'version'}]}, 'similarity': np.float64(254.41887095612884)}, {'metadata': {'doc_id': '918', 'name': 'Server-Side Request Forgery (SSRF)', 'source': 'sparse', 'original_content': 'The web server receives a URL or similar request from an upstream component and retrieves the contents of this URL, but it does not sufficiently ensure that the request is being sent to the expected destination.', 'keyphrase_sources': [{'id': 'rootcause:cross-site request forgery', 'keyphrase': 'cross-site request forgery', 'type': 'rootcause'}]}, 'similarity': np.float64(239.75008491636135)}, {'metadata': {'doc_id': '79', 'name': \"Improper Neutralization of Input During Web Page Generation ('Cross-site Scripting')\", 'source': 'sparse', 'original_content': 'The product does not neutralize or incorrectly neutralizes user-controllable input before it is placed in output that is used as a web page that is served to other users.', 'keyphrase_sources': [{'id': 'rootcause:cross-site request forgery', 'keyphrase': 'cross-site request forgery', 'type': 'rootcause'}, {'id': 'weakness:stored cross-site scripting', 'keyphrase': 'stored cross-site scripting', 'type': 'weakness'}, {'id': 'weakness:XSS', 'keyphrase': 'XSS', 'type': 'weakness'}, {'id': 'product:NotFound WP SpaceContent', 'keyphrase': 'NotFound WP SpaceContent', 'type': 'product'}, {'id': 'version:n/a through 0.4.5', 'keyphrase': 'n/a through 0.4.5', 'type': 'version'}]}, 'similarity': np.float64(225.54631968227434)}, {'metadata': {'doc_id': '434', 'name': 'Unrestricted Upload of File with Dangerous Type', 'source': 'sparse', 'original_content': 'The product allows the upload or transfer of dangerous file types that are automatically processed within its environment.', 'keyphrase_sources': [{'id': 'weakness:stored cross-site scripting', 'keyphrase': 'stored cross-site scripting', 'type': 'weakness'}, {'id': 'weakness:XSS', 'keyphrase': 'XSS', 'type': 'weakness'}, {'id': 'product:NotFound WP SpaceContent', 'keyphrase': 'NotFound WP SpaceContent', 'type': 'product'}, {'id': 'version:n/a through 0.4.5', 'keyphrase': 'n/a through 0.4.5', 'type': 'version'}]}, 'similarity': np.float64(224.13370936881464)}, {'metadata': {'doc_id': '601', 'name': \"URL Redirection to Untrusted Site ('Open Redirect')\", 'source': 'sparse', 'original_content': 'The web application accepts a user-controlled input that specifies a link to an external site, and uses that link in a redirect.', 'keyphrase_sources': [{'id': 'rootcause:cross-site request forgery', 'keyphrase': 'cross-site request forgery', 'type': 'rootcause'}]}, 'similarity': np.float64(220.33731053434383)}, {'metadata': {'doc_id': '80', 'name': 'Improper Neutralization of Script-Related HTML Tags in a Web Page (Basic XSS)', 'source': 'sparse', 'original_content': 'The product receives input from an upstream component, but it does not neutralize or incorrectly neutralizes special characters such as \"<\", \">\", and \"&\" that could be interpreted as web-scripting elements when they are sent to a downstream component that processes web pages.', 'keyphrase_sources': [{'id': 'weakness:stored cross-site scripting', 'keyphrase': 'stored cross-site scripting', 'type': 'weakness'}]}, 'similarity': np.float64(210.56718221169456)}, {'metadata': {'doc_id': '116', 'name': 'Improper Encoding or Escaping of Output', 'source': 'sparse', 'original_content': 'The product prepares a structured message for communication with another component, but encoding or escaping of the data is either missing or done incorrectly. As a result, the intended structure of the message is not preserved.', 'keyphrase_sources': [{'id': 'weakness:stored cross-site scripting', 'keyphrase': 'stored cross-site scripting', 'type': 'weakness'}, {'id': 'weakness:XSS', 'keyphrase': 'XSS', 'type': 'weakness'}]}, 'similarity': np.float64(208.4565767268942)}, {'metadata': {'doc_id': '1004', 'name': \"Sensitive Cookie Without 'HttpOnly' Flag\", 'source': 'sparse', 'original_content': 'The product uses a cookie to store sensitive information, but the cookie is not marked with the HttpOnly flag.', 'keyphrase_sources': [{'id': 'weakness:XSS', 'keyphrase': 'XSS', 'type': 'weakness'}]}, 'similarity': np.float64(146.28978125821106)}, {'metadata': {'doc_id': '22', 'name': \"Improper Limitation of a Pathname to a Restricted Directory ('Path Traversal')\", 'source': 'sparse', 'original_content': 'The product uses external input to construct a pathname that is intended to identify a file or directory that is located underneath a restricted parent directory, but the product does not properly neutralize special elements within the pathname that can cause the pathname to resolve to a location that is outside of the restricted directory.', 'keyphrase_sources': [{'id': 'version:n/a through 0.4.5', 'keyphrase': 'n/a through 0.4.5', 'type': 'version'}]}, 'similarity': np.float64(63.50888177463658)}, {'metadata': {'doc_id': '862', 'name': 'Missing Authorization', 'source': 'sparse', 'original_content': 'The product does not perform an authorization check when an actor attempts to access a resource or perform an action.', 'keyphrase_sources': [{'id': 'product:NotFound WP SpaceContent', 'keyphrase': 'NotFound WP SpaceContent', 'type': 'product'}]}, 'similarity': np.float64(45.67273869082757)}], identified_cwes={'analyzer': [], 'critic_additional': []})",
  "retrieval_results": {
    "has_multiple_keyphrases": true,
    "keyphrase_cwe_sets": {
      "rootcause:cross-site request forgery": {
        "keyphrase": "cross-site request forgery",
        "type": "rootcause",
        "cwes": [
          {
            "metadata": {
              "doc_id": "352",
              "name": "Cross-Site Request Forgery (CSRF)",
              "source": "sparse",
              "original_content": "The web application does not, or can not, sufficiently verify whether a well-formed, valid, consistent request was intentionally provided by the user who submitted the request.",
              "keyphrase_sources": [
                {
                  "id": "rootcause:cross-site request forgery",
                  "keyphrase": "cross-site request forgery",
                  "type": "rootcause"
                },
                {
                  "id": "weakness:stored cross-site scripting",
                  "keyphrase": "stored cross-site scripting",
                  "type": "weakness"
                },
                {
                  "id": "weakness:XSS",
                  "keyphrase": "XSS",
                  "type": "weakness"
                },
                {
                  "id": "product:NotFound WP SpaceContent",
                  "keyphrase": "NotFound WP SpaceContent",
                  "type": "product"
                },
                {
                  "id": "version:n/a through 0.4.5",
                  "keyphrase": "n/a through 0.4.5",
                  "type": "version"
                }
              ]
            },
            "similarity": 321.13207282482745
          },
          {
            "metadata": {
              "doc_id": "89",
              "name": "Improper Neutralization of Special Elements used in an SQL Command ('SQL Injection')",
              "source": "sparse",
              "original_content": "The product constructs all or part of an SQL command using externally-influenced input from an upstream component, but it does not neutralize or incorrectly neutralizes special elements that could modify the intended SQL command when it is sent to a downstream component. Without sufficient removal or quoting of SQL syntax in user-controllable inputs, the generated SQL query can cause those inputs to be interpreted as SQL instead of ordinary user data.",
              "keyphrase_sources": [
                {
                  "id": "rootcause:cross-site request forgery",
                  "keyphrase": "cross-site request forgery",
                  "type": "rootcause"
                },
                {
                  "id": "product:NotFound WP SpaceContent",
                  "keyphrase": "NotFound WP SpaceContent",
                  "type": "product"
                },
                {
                  "id": "version:n/a through 0.4.5",
                  "keyphrase": "n/a through 0.4.5",
                  "type": "version"
                }
              ]
            },
            "similarity": 254.41887095612884
          },
          {
            "metadata": {
              "doc_id": "918",
              "name": "Server-Side Request Forgery (SSRF)",
              "source": "sparse",
              "original_content": "The web server receives a URL or similar request from an upstream component and retrieves the contents of this URL, but it does not sufficiently ensure that the request is being sent to the expected destination.",
              "keyphrase_sources": [
                {
                  "id": "rootcause:cross-site request forgery",
                  "keyphrase": "cross-site request forgery",
                  "type": "rootcause"
                }
              ]
            },
            "similarity": 239.75008491636135
          },
          {
            "metadata": {
              "doc_id": "79",
              "name": "Improper Neutralization of Input During Web Page Generation ('Cross-site Scripting')",
              "source": "sparse",
              "original_content": "The product does not neutralize or incorrectly neutralizes user-controllable input before it is placed in output that is used as a web page that is served to other users.",
              "keyphrase_sources": [
                {
                  "id": "rootcause:cross-site request forgery",
                  "keyphrase": "cross-site request forgery",
                  "type": "rootcause"
                },
                {
                  "id": "weakness:stored cross-site scripting",
                  "keyphrase": "stored cross-site scripting",
                  "type": "weakness"
                },
                {
                  "id": "weakness:XSS",
                  "keyphrase": "XSS",
                  "type": "weakness"
                },
                {
                  "id": "product:NotFound WP SpaceContent",
                  "keyphrase": "NotFound WP SpaceContent",
                  "type": "product"
                },
                {
                  "id": "version:n/a through 0.4.5",
                  "keyphrase": "n/a through 0.4.5",
                  "type": "version"
                }
              ]
            },
            "similarity": 225.54631968227434
          },
          {
            "metadata": {
              "doc_id": "601",
              "name": "URL Redirection to Untrusted Site ('Open Redirect')",
              "source": "sparse",
              "original_content": "The web application accepts a user-controlled input that specifies a link to an external site, and uses that link in a redirect.",
              "keyphrase_sources": [
                {
                  "id": "rootcause:cross-site request forgery",
                  "keyphrase": "cross-site request forgery",
                  "type": "rootcause"
                }
              ]
            },
            "similarity": 220.33731053434383
          }
        ]
      },
      "weakness:stored cross-site scripting": {
        "keyphrase": "stored cross-site scripting",
        "type": "weakness",
        "cwes": [
          {
            "metadata": {
              "doc_id": "352",
              "name": "Cross-Site Request Forgery (CSRF)",
              "source": "sparse",
              "original_content": "The web application does not, or can not, sufficiently verify whether a well-formed, valid, consistent request was intentionally provided by the user who submitted the request."
            },
            "similarity": 304.3117884595672
          },
          {
            "metadata": {
              "doc_id": "79",
              "name": "Improper Neutralization of Input During Web Page Generation ('Cross-site Scripting')",
              "source": "sparse",
              "original_content": "The product does not neutralize or incorrectly neutralizes user-controllable input before it is placed in output that is used as a web page that is served to other users."
            },
            "similarity": 246.49803077025794
          },
          {
            "metadata": {
              "doc_id": "434",
              "name": "Unrestricted Upload of File with Dangerous Type",
              "source": "sparse",
              "original_content": "The product allows the upload or transfer of dangerous file types that are automatically processed within its environment.",
              "keyphrase_sources": [
                {
                  "id": "weakness:stored cross-site scripting",
                  "keyphrase": "stored cross-site scripting",
                  "type": "weakness"
                },
                {
                  "id": "weakness:XSS",
                  "keyphrase": "XSS",
                  "type": "weakness"
                },
                {
                  "id": "product:NotFound WP SpaceContent",
                  "keyphrase": "NotFound WP SpaceContent",
                  "type": "product"
                },
                {
                  "id": "version:n/a through 0.4.5",
                  "keyphrase": "n/a through 0.4.5",
                  "type": "version"
                }
              ]
            },
            "similarity": 224.13370936881464
          },
          {
            "metadata": {
              "doc_id": "80",
              "name": "Improper Neutralization of Script-Related HTML Tags in a Web Page (Basic XSS)",
              "source": "sparse",
              "original_content": "The product receives input from an upstream component, but it does not neutralize or incorrectly neutralizes special characters such as \"<\", \">\", and \"&\" that could be interpreted as web-scripting elements when they are sent to a downstream component that processes web pages.",
              "keyphrase_sources": [
                {
                  "id": "weakness:stored cross-site scripting",
                  "keyphrase": "stored cross-site scripting",
                  "type": "weakness"
                }
              ]
            },
            "similarity": 210.56718221169456
          },
          {
            "metadata": {
              "doc_id": "116",
              "name": "Improper Encoding or Escaping of Output",
              "source": "sparse",
              "original_content": "The product prepares a structured message for communication with another component, but encoding or escaping of the data is either missing or done incorrectly. As a result, the intended structure of the message is not preserved.",
              "keyphrase_sources": [
                {
                  "id": "weakness:stored cross-site scripting",
                  "keyphrase": "stored cross-site scripting",
                  "type": "weakness"
                },
                {
                  "id": "weakness:XSS",
                  "keyphrase": "XSS",
                  "type": "weakness"
                }
              ]
            },
            "similarity": 208.4565767268942
          }
        ]
      },
      "weakness:XSS": {
        "keyphrase": "XSS",
        "type": "weakness",
        "cwes": [
          {
            "metadata": {
              "doc_id": "352",
              "name": "Cross-Site Request Forgery (CSRF)",
              "source": "sparse",
              "original_content": "The web application does not, or can not, sufficiently verify whether a well-formed, valid, consistent request was intentionally provided by the user who submitted the request."
            },
            "similarity": 213.54351835652108
          },
          {
            "metadata": {
              "doc_id": "434",
              "name": "Unrestricted Upload of File with Dangerous Type",
              "source": "sparse",
              "original_content": "The product allows the upload or transfer of dangerous file types that are automatically processed within its environment."
            },
            "similarity": 168.721841780419
          },
          {
            "metadata": {
              "doc_id": "79",
              "name": "Improper Neutralization of Input During Web Page Generation ('Cross-site Scripting')",
              "source": "sparse",
              "original_content": "The product does not neutralize or incorrectly neutralizes user-controllable input before it is placed in output that is used as a web page that is served to other users."
            },
            "similarity": 167.70951639011506
          },
          {
            "metadata": {
              "doc_id": "1004",
              "name": "Sensitive Cookie Without 'HttpOnly' Flag",
              "source": "sparse",
              "original_content": "The product uses a cookie to store sensitive information, but the cookie is not marked with the HttpOnly flag.",
              "keyphrase_sources": [
                {
                  "id": "weakness:XSS",
                  "keyphrase": "XSS",
                  "type": "weakness"
                }
              ]
            },
            "similarity": 146.28978125821106
          },
          {
            "metadata": {
              "doc_id": "116",
              "name": "Improper Encoding or Escaping of Output",
              "source": "sparse",
              "original_content": "The product prepares a structured message for communication with another component, but encoding or escaping of the data is either missing or done incorrectly. As a result, the intended structure of the message is not preserved."
            },
            "similarity": 142.6111119455167
          }
        ]
      },
      "product:NotFound WP SpaceContent": {
        "keyphrase": "NotFound WP SpaceContent",
        "type": "product",
        "cwes": [
          {
            "metadata": {
              "doc_id": "352",
              "name": "Cross-Site Request Forgery (CSRF)",
              "source": "sparse",
              "original_content": "The web application does not, or can not, sufficiently verify whether a well-formed, valid, consistent request was intentionally provided by the user who submitted the request."
            },
            "similarity": 77.48949755529989
          },
          {
            "metadata": {
              "doc_id": "434",
              "name": "Unrestricted Upload of File with Dangerous Type",
              "source": "sparse",
              "original_content": "The product allows the upload or transfer of dangerous file types that are automatically processed within its environment."
            },
            "similarity": 63.182676812728275
          },
          {
            "metadata": {
              "doc_id": "79",
              "name": "Improper Neutralization of Input During Web Page Generation ('Cross-site Scripting')",
              "source": "sparse",
              "original_content": "The product does not neutralize or incorrectly neutralizes user-controllable input before it is placed in output that is used as a web page that is served to other users."
            },
            "similarity": 51.636202237688174
          },
          {
            "metadata": {
              "doc_id": "89",
              "name": "Improper Neutralization of Special Elements used in an SQL Command ('SQL Injection')",
              "source": "sparse",
              "original_content": "The product constructs all or part of an SQL command using externally-influenced input from an upstream component, but it does not neutralize or incorrectly neutralizes special elements that could modify the intended SQL command when it is sent to a downstream component. Without sufficient removal or quoting of SQL syntax in user-controllable inputs, the generated SQL query can cause those inputs to be interpreted as SQL instead of ordinary user data."
            },
            "similarity": 48.25083098587094
          },
          {
            "metadata": {
              "doc_id": "862",
              "name": "Missing Authorization",
              "source": "sparse",
              "original_content": "The product does not perform an authorization check when an actor attempts to access a resource or perform an action.",
              "keyphrase_sources": [
                {
                  "id": "product:NotFound WP SpaceContent",
                  "keyphrase": "NotFound WP SpaceContent",
                  "type": "product"
                }
              ]
            },
            "similarity": 45.67273869082757
          }
        ]
      },
      "version:n/a through 0.4.5": {
        "keyphrase": "n/a through 0.4.5",
        "type": "version",
        "cwes": [
          {
            "metadata": {
              "doc_id": "352",
              "name": "Cross-Site Request Forgery (CSRF)",
              "source": "sparse",
              "original_content": "The web application does not, or can not, sufficiently verify whether a well-formed, valid, consistent request was intentionally provided by the user who submitted the request."
            },
            "similarity": 84.80776564457142
          },
          {
            "metadata": {
              "doc_id": "434",
              "name": "Unrestricted Upload of File with Dangerous Type",
              "source": "sparse",
              "original_content": "The product allows the upload or transfer of dangerous file types that are automatically processed within its environment."
            },
            "similarity": 75.11850251641387
          },
          {
            "metadata": {
              "doc_id": "79",
              "name": "Improper Neutralization of Input During Web Page Generation ('Cross-site Scripting')",
              "source": "sparse",
              "original_content": "The product does not neutralize or incorrectly neutralizes user-controllable input before it is placed in output that is used as a web page that is served to other users."
            },
            "similarity": 66.5583315279802
          },
          {
            "metadata": {
              "doc_id": "22",
              "name": "Improper Limitation of a Pathname to a Restricted Directory ('Path Traversal')",
              "source": "sparse",
              "original_content": "The product uses external input to construct a pathname that is intended to identify a file or directory that is located underneath a restricted parent directory, but the product does not properly neutralize special elements within the pathname that can cause the pathname to resolve to a location that is outside of the restricted directory.",
              "keyphrase_sources": [
                {
                  "id": "version:n/a through 0.4.5",
                  "keyphrase": "n/a through 0.4.5",
                  "type": "version"
                }
              ]
            },
            "similarity": 63.50888177463658
          },
          {
            "metadata": {
              "doc_id": "89",
              "name": "Improper Neutralization of Special Elements used in an SQL Command ('SQL Injection')",
              "source": "sparse",
              "original_content": "The product constructs all or part of an SQL command using externally-influenced input from an upstream component, but it does not neutralize or incorrectly neutralizes special elements that could modify the intended SQL command when it is sent to a downstream component. Without sufficient removal or quoting of SQL syntax in user-controllable inputs, the generated SQL query can cause those inputs to be interpreted as SQL instead of ordinary user data."
            },
            "similarity": 63.421045125604174
          }
        ]
      }
    },
    "keyphrase_mapping": {
      "352": [
        {
          "id": "rootcause:cross-site request forgery",
          "keyphrase": "cross-site request forgery",
          "type": "rootcause"
        },
        {
          "id": "weakness:stored cross-site scripting",
          "keyphrase": "stored cross-site scripting",
          "type": "weakness"
        },
        {
          "id": "weakness:XSS",
          "keyphrase": "XSS",
          "type": "weakness"
        },
        {
          "id": "product:NotFound WP SpaceContent",
          "keyphrase": "NotFound WP SpaceContent",
          "type": "product"
        },
        {
          "id": "version:n/a through 0.4.5",
          "keyphrase": "n/a through 0.4.5",
          "type": "version"
        }
      ],
      "89": [
        {
          "id": "rootcause:cross-site request forgery",
          "keyphrase": "cross-site request forgery",
          "type": "rootcause"
        },
        {
          "id": "product:NotFound WP SpaceContent",
          "keyphrase": "NotFound WP SpaceContent",
          "type": "product"
        },
        {
          "id": "version:n/a through 0.4.5",
          "keyphrase": "n/a through 0.4.5",
          "type": "version"
        }
      ],
      "918": [
        {
          "id": "rootcause:cross-site request forgery",
          "keyphrase": "cross-site request forgery",
          "type": "rootcause"
        }
      ],
      "79": [
        {
          "id": "rootcause:cross-site request forgery",
          "keyphrase": "cross-site request forgery",
          "type": "rootcause"
        },
        {
          "id": "weakness:stored cross-site scripting",
          "keyphrase": "stored cross-site scripting",
          "type": "weakness"
        },
        {
          "id": "weakness:XSS",
          "keyphrase": "XSS",
          "type": "weakness"
        },
        {
          "id": "product:NotFound WP SpaceContent",
          "keyphrase": "NotFound WP SpaceContent",
          "type": "product"
        },
        {
          "id": "version:n/a through 0.4.5",
          "keyphrase": "n/a through 0.4.5",
          "type": "version"
        }
      ],
      "601": [
        {
          "id": "rootcause:cross-site request forgery",
          "keyphrase": "cross-site request forgery",
          "type": "rootcause"
        }
      ],
      "434": [
        {
          "id": "weakness:stored cross-site scripting",
          "keyphrase": "stored cross-site scripting",
          "type": "weakness"
        },
        {
          "id": "weakness:XSS",
          "keyphrase": "XSS",
          "type": "weakness"
        },
        {
          "id": "product:NotFound WP SpaceContent",
          "keyphrase": "NotFound WP SpaceContent",
          "type": "product"
        },
        {
          "id": "version:n/a through 0.4.5",
          "keyphrase": "n/a through 0.4.5",
          "type": "version"
        }
      ],
      "80": [
        {
          "id": "weakness:stored cross-site scripting",
          "keyphrase": "stored cross-site scripting",
          "type": "weakness"
        }
      ],
      "116": [
        {
          "id": "weakness:stored cross-site scripting",
          "keyphrase": "stored cross-site scripting",
          "type": "weakness"
        },
        {
          "id": "weakness:XSS",
          "keyphrase": "XSS",
          "type": "weakness"
        }
      ],
      "1004": [
        {
          "id": "weakness:XSS",
          "keyphrase": "XSS",
          "type": "weakness"
        }
      ],
      "862": [
        {
          "id": "product:NotFound WP SpaceContent",
          "keyphrase": "NotFound WP SpaceContent",
          "type": "product"
        }
      ],
      "22": [
        {
          "id": "version:n/a through 0.4.5",
          "keyphrase": "n/a through 0.4.5",
          "type": "version"
        }
      ]
    },
    "relevant_cwes": [
      {
        "metadata": {
          "doc_id": "352",
          "name": "Cross-Site Request Forgery (CSRF)",
          "source": "sparse",
          "original_content": "The web application does not, or can not, sufficiently verify whether a well-formed, valid, consistent request was intentionally provided by the user who submitted the request.",
          "keyphrase_sources": [
            {
              "id": "rootcause:cross-site request forgery",
              "keyphrase": "cross-site request forgery",
              "type": "rootcause"
            },
            {
              "id": "weakness:stored cross-site scripting",
              "keyphrase": "stored cross-site scripting",
              "type": "weakness"
            },
            {
              "id": "weakness:XSS",
              "keyphrase": "XSS",
              "type": "weakness"
            },
            {
              "id": "product:NotFound WP SpaceContent",
              "keyphrase": "NotFound WP SpaceContent",
              "type": "product"
            },
            {
              "id": "version:n/a through 0.4.5",
              "keyphrase": "n/a through 0.4.5",
              "type": "version"
            }
          ]
        },
        "similarity": 321.13207282482745
      },
      {
        "metadata": {
          "doc_id": "89",
          "name": "Improper Neutralization of Special Elements used in an SQL Command ('SQL Injection')",
          "source": "sparse",
          "original_content": "The product constructs all or part of an SQL command using externally-influenced input from an upstream component, but it does not neutralize or incorrectly neutralizes special elements that could modify the intended SQL command when it is sent to a downstream component. Without sufficient removal or quoting of SQL syntax in user-controllable inputs, the generated SQL query can cause those inputs to be interpreted as SQL instead of ordinary user data.",
          "keyphrase_sources": [
            {
              "id": "rootcause:cross-site request forgery",
              "keyphrase": "cross-site request forgery",
              "type": "rootcause"
            },
            {
              "id": "product:NotFound WP SpaceContent",
              "keyphrase": "NotFound WP SpaceContent",
              "type": "product"
            },
            {
              "id": "version:n/a through 0.4.5",
              "keyphrase": "n/a through 0.4.5",
              "type": "version"
            }
          ]
        },
        "similarity": 254.41887095612884
      },
      {
        "metadata": {
          "doc_id": "918",
          "name": "Server-Side Request Forgery (SSRF)",
          "source": "sparse",
          "original_content": "The web server receives a URL or similar request from an upstream component and retrieves the contents of this URL, but it does not sufficiently ensure that the request is being sent to the expected destination.",
          "keyphrase_sources": [
            {
              "id": "rootcause:cross-site request forgery",
              "keyphrase": "cross-site request forgery",
              "type": "rootcause"
            }
          ]
        },
        "similarity": 239.75008491636135
      },
      {
        "metadata": {
          "doc_id": "79",
          "name": "Improper Neutralization of Input During Web Page Generation ('Cross-site Scripting')",
          "source": "sparse",
          "original_content": "The product does not neutralize or incorrectly neutralizes user-controllable input before it is placed in output that is used as a web page that is served to other users.",
          "keyphrase_sources": [
            {
              "id": "rootcause:cross-site request forgery",
              "keyphrase": "cross-site request forgery",
              "type": "rootcause"
            },
            {
              "id": "weakness:stored cross-site scripting",
              "keyphrase": "stored cross-site scripting",
              "type": "weakness"
            },
            {
              "id": "weakness:XSS",
              "keyphrase": "XSS",
              "type": "weakness"
            },
            {
              "id": "product:NotFound WP SpaceContent",
              "keyphrase": "NotFound WP SpaceContent",
              "type": "product"
            },
            {
              "id": "version:n/a through 0.4.5",
              "keyphrase": "n/a through 0.4.5",
              "type": "version"
            }
          ]
        },
        "similarity": 225.54631968227434
      },
      {
        "metadata": {
          "doc_id": "434",
          "name": "Unrestricted Upload of File with Dangerous Type",
          "source": "sparse",
          "original_content": "The product allows the upload or transfer of dangerous file types that are automatically processed within its environment.",
          "keyphrase_sources": [
            {
              "id": "weakness:stored cross-site scripting",
              "keyphrase": "stored cross-site scripting",
              "type": "weakness"
            },
            {
              "id": "weakness:XSS",
              "keyphrase": "XSS",
              "type": "weakness"
            },
            {
              "id": "product:NotFound WP SpaceContent",
              "keyphrase": "NotFound WP SpaceContent",
              "type": "product"
            },
            {
              "id": "version:n/a through 0.4.5",
              "keyphrase": "n/a through 0.4.5",
              "type": "version"
            }
          ]
        },
        "similarity": 224.13370936881464
      },
      {
        "metadata": {
          "doc_id": "601",
          "name": "URL Redirection to Untrusted Site ('Open Redirect')",
          "source": "sparse",
          "original_content": "The web application accepts a user-controlled input that specifies a link to an external site, and uses that link in a redirect.",
          "keyphrase_sources": [
            {
              "id": "rootcause:cross-site request forgery",
              "keyphrase": "cross-site request forgery",
              "type": "rootcause"
            }
          ]
        },
        "similarity": 220.33731053434383
      },
      {
        "metadata": {
          "doc_id": "80",
          "name": "Improper Neutralization of Script-Related HTML Tags in a Web Page (Basic XSS)",
          "source": "sparse",
          "original_content": "The product receives input from an upstream component, but it does not neutralize or incorrectly neutralizes special characters such as \"<\", \">\", and \"&\" that could be interpreted as web-scripting elements when they are sent to a downstream component that processes web pages.",
          "keyphrase_sources": [
            {
              "id": "weakness:stored cross-site scripting",
              "keyphrase": "stored cross-site scripting",
              "type": "weakness"
            }
          ]
        },
        "similarity": 210.56718221169456
      },
      {
        "metadata": {
          "doc_id": "116",
          "name": "Improper Encoding or Escaping of Output",
          "source": "sparse",
          "original_content": "The product prepares a structured message for communication with another component, but encoding or escaping of the data is either missing or done incorrectly. As a result, the intended structure of the message is not preserved.",
          "keyphrase_sources": [
            {
              "id": "weakness:stored cross-site scripting",
              "keyphrase": "stored cross-site scripting",
              "type": "weakness"
            },
            {
              "id": "weakness:XSS",
              "keyphrase": "XSS",
              "type": "weakness"
            }
          ]
        },
        "similarity": 208.4565767268942
      },
      {
        "metadata": {
          "doc_id": "1004",
          "name": "Sensitive Cookie Without 'HttpOnly' Flag",
          "source": "sparse",
          "original_content": "The product uses a cookie to store sensitive information, but the cookie is not marked with the HttpOnly flag.",
          "keyphrase_sources": [
            {
              "id": "weakness:XSS",
              "keyphrase": "XSS",
              "type": "weakness"
            }
          ]
        },
        "similarity": 146.28978125821106
      },
      {
        "metadata": {
          "doc_id": "22",
          "name": "Improper Limitation of a Pathname to a Restricted Directory ('Path Traversal')",
          "source": "sparse",
          "original_content": "The product uses external input to construct a pathname that is intended to identify a file or directory that is located underneath a restricted parent directory, but the product does not properly neutralize special elements within the pathname that can cause the pathname to resolve to a location that is outside of the restricted directory.",
          "keyphrase_sources": [
            {
              "id": "version:n/a through 0.4.5",
              "keyphrase": "n/a through 0.4.5",
              "type": "version"
            }
          ]
        },
        "similarity": 63.50888177463658
      },
      {
        "metadata": {
          "doc_id": "862",
          "name": "Missing Authorization",
          "source": "sparse",
          "original_content": "The product does not perform an authorization check when an actor attempts to access a resource or perform an action.",
          "keyphrase_sources": [
            {
              "id": "product:NotFound WP SpaceContent",
              "keyphrase": "NotFound WP SpaceContent",
              "type": "product"
            }
          ]
        },
        "similarity": 45.67273869082757
      }
    ],
    "enhanced_query": "# Vulnerability Description\n\n    Cross-Site Request Forgery (CSRF) vulnerability in NotFound WP SpaceContent allows Stored **XSS**. This issue affects WP SpaceContent from n/a through 0.4.5.\n\n    # Keyphrase-Specific CWE Analysis\n    This vulnerability contains multiple keyphrases that may map to different CWEs. \n    Please analyze each keyphrase separately and determine the most appropriate CWE(s) for each.\n\n    ## ROOTCAUSE: 'cross-site request forgery'\n\nRelevant CWEs for this ROOTCAUSE:\n\n### 1. CWE-352: Cross-Site Request Forgery (CSRF) (Score: 321.13)\n\nThe web application does not, or can not, sufficiently verify whether a well-formed, valid, consistent request was intentionally provided by the user who submitted the request....\n\n### 2. CWE-89: Improper Neutralization of Special Elements used in an SQL Command ('SQL Injection') (Score: 254.42)\n\nThe product constructs all or part of an SQL command using externally-influenced input from an upstream component, but it does not neutralize or incorrectly neutralizes special elements that could modify the intended SQL command when it is sent to a downstream component. Without sufficient removal o...\n\n### 3. CWE-918: Server-Side Request Forgery (SSRF) (Score: 239.75)\n\nThe web server receives a URL or similar request from an upstream component and retrieves the contents of this URL, but it does not sufficiently ensure that the request is being sent to the expected destination....\n\n### 4. CWE-79: Improper Neutralization of Input During Web Page Generation ('Cross-site Scripting') (Score: 225.55)\n\nThe product does not neutralize or incorrectly neutralizes user-controllable input before it is placed in output that is used as a web page that is served to other users....\n\n### 5. CWE-601: URL Redirection to Untrusted Site ('Open Redirect') (Score: 220.34)\n\nThe web application accepts a user-controlled input that specifies a link to an external site, and uses that link in a redirect....\n\n## WEAKNESS: 'stored cross-site scripting'\n\nRelevant CWEs for this WEAKNESS:\n\n### 1. CWE-352: Cross-Site Request Forgery (CSRF) (Score: 321.13)\n\nThe web application does not, or can not, sufficiently verify whether a well-formed, valid, consistent request was intentionally provided by the user who submitted the request....\n\n### 2. CWE-79: Improper Neutralization of Input During Web Page Generation ('Cross-site Scripting') (Score: 225.55)\n\nThe product does not neutralize or incorrectly neutralizes user-controllable input before it is placed in output that is used as a web page that is served to other users....\n\n### 3. CWE-434: Unrestricted Upload of File with Dangerous Type (Score: 224.13)\n\nThe product allows the upload or transfer of dangerous file types that are automatically processed within its environment....\n\n### 4. CWE-80: Improper Neutralization of Script-Related HTML Tags in a Web Page (Basic XSS) (Score: 210.57)\n\nThe product receives input from an upstream component, but it does not neutralize or incorrectly neutralizes special characters such as \"<\", \">\", and \"&\" that could be interpreted as web-scripting elements when they are sent to a downstream component that processes web pages....\n\n### 5. CWE-116: Improper Encoding or Escaping of Output (Score: 208.46)\n\nThe product prepares a structured message for communication with another component, but encoding or escaping of the data is either missing or done incorrectly. As a result, the intended structure of the message is not preserved....\n\n## WEAKNESS: 'XSS'\n\nRelevant CWEs for this WEAKNESS:\n\n### 1. CWE-352: Cross-Site Request Forgery (CSRF) (Score: 321.13)\n\nThe web application does not, or can not, sufficiently verify whether a well-formed, valid, consistent request was intentionally provided by the user who submitted the request....\n\n### 2. CWE-79: Improper Neutralization of Input During Web Page Generation ('Cross-site Scripting') (Score: 225.55)\n\nThe product does not neutralize or incorrectly neutralizes user-controllable input before it is placed in output that is used as a web page that is served to other users....\n\n### 3. CWE-434: Unrestricted Upload of File with Dangerous Type (Score: 224.13)\n\nThe product allows the upload or transfer of dangerous file types that are automatically processed within its environment....\n\n### 4. CWE-116: Improper Encoding or Escaping of Output (Score: 208.46)\n\nThe product prepares a structured message for communication with another component, but encoding or escaping of the data is either missing or done incorrectly. As a result, the intended structure of the message is not preserved....\n\n### 5. CWE-1004: Sensitive Cookie Without 'HttpOnly' Flag (Score: 146.29)\n\nThe product uses a cookie to store sensitive information, but the cookie is not marked with the HttpOnly flag....\n\n## PRODUCT: 'NotFound WP SpaceContent'\n\nRelevant CWEs for this PRODUCT:\n\n### 1. CWE-352: Cross-Site Request Forgery (CSRF) (Score: 321.13)\n\nThe web application does not, or can not, sufficiently verify whether a well-formed, valid, consistent request was intentionally provided by the user who submitted the request....\n\n### 2. CWE-89: Improper Neutralization of Special Elements used in an SQL Command ('SQL Injection') (Score: 254.42)\n\nThe product constructs all or part of an SQL command using externally-influenced input from an upstream component, but it does not neutralize or incorrectly neutralizes special elements that could modify the intended SQL command when it is sent to a downstream component. Without sufficient removal o...\n\n### 3. CWE-79: Improper Neutralization of Input During Web Page Generation ('Cross-site Scripting') (Score: 225.55)\n\nThe product does not neutralize or incorrectly neutralizes user-controllable input before it is placed in output that is used as a web page that is served to other users....\n\n### 4. CWE-434: Unrestricted Upload of File with Dangerous Type (Score: 224.13)\n\nThe product allows the upload or transfer of dangerous file types that are automatically processed within its environment....\n\n### 5. CWE-862: Missing Authorization (Score: 45.67)\n\nThe product does not perform an authorization check when an actor attempts to access a resource or perform an action....\n\n## VERSION: 'n/a through 0.4.5'\n\nRelevant CWEs for this VERSION:\n\n### 1. CWE-352: Cross-Site Request Forgery (CSRF) (Score: 321.13)\n\nThe web application does not, or can not, sufficiently verify whether a well-formed, valid, consistent request was intentionally provided by the user who submitted the request....\n\n### 2. CWE-89: Improper Neutralization of Special Elements used in an SQL Command ('SQL Injection') (Score: 254.42)\n\nThe product constructs all or part of an SQL command using externally-influenced input from an upstream component, but it does not neutralize or incorrectly neutralizes special elements that could modify the intended SQL command when it is sent to a downstream component. Without sufficient removal o...\n\n### 3. CWE-79: Improper Neutralization of Input During Web Page Generation ('Cross-site Scripting') (Score: 225.55)\n\nThe product does not neutralize or incorrectly neutralizes user-controllable input before it is placed in output that is used as a web page that is served to other users....\n\n### 4. CWE-434: Unrestricted Upload of File with Dangerous Type (Score: 224.13)\n\nThe product allows the upload or transfer of dangerous file types that are automatically processed within its environment....\n\n### 5. CWE-22: Improper Limitation of a Pathname to a Restricted Directory ('Path Traversal') (Score: 63.51)\n\nThe product uses external input to construct a pathname that is intended to identify a file or directory that is located underneath a restricted parent directory, but the product does not properly neutralize special elements within the pathname that can cause the pathname to resolve to a location th...\n\n\n    # Analysis Instructions\n    1. For each keyphrase, identify the most appropriate CWE(s) that represent the weakness.\n    2. Consider how the different keyphrases might relate to each other in the vulnerability chain.\n    3. Provide a final determination of primary CWE(s) and any secondary CWEs.\n    4. Format your response using the standard analysis template.\n\n    Please analyze how these different weaknesses interact and provide a comprehensive CWE classification.\n    "
  },
  "retrieval_time": 0.9972903728485107
}