{
  "vulnerability_info": "VulnerabilityInfo(cve_id='CVE-2024-50105', description='In the Linux kernel, the following vulnerability has been resolved ASoC qcom sc7280 Fix missing Soundwire runtime stream alloc Commit 15c7fab0e047 (ASoC qcom Move Soundwire runtime stream alloc to soundcards) moved the allocation of Soundwire stream runtime from the Qualcomm Soundwire driver to each individual machine sound card driver, except that it **forgot to update SC7280 card**. Just like for other Qualcomm sound cards using Soundwire, the card driver should allocate and release the runtime. Otherwise sound playback will result in a NULL pointer dereference or other effect of **uninitialized memory** accesses (which was confirmed on SDM845 having similar issue).', key_phrases={'rootcause': ['forgot to update SC7280 card', 'uninitialized memory'], 'weakness': 'uninitialized memory accesses', 'impact': 'NULL pointer dereference', 'vector': '', 'attacker': '', 'product': 'Linux kernel', 'version': '', 'component': 'ASoC qcom sc7280'}, reference_content=\"The provided content relates to a fix for a vulnerability in the Linux kernel's ASoC (Audio System on Chip) subsystem, specifically concerning the SC7280 sound card driver. This vulnerability is a result of a missing Soundwire runtime stream allocation.\\n\\n**Root cause of vulnerability:**\\n\\n- A previous commit (15c7fab0e047) moved the allocation of the Soundwire stream runtime from the Qualcomm Soundwire driver to individual machine sound card drivers.\\n- The SC7280 sound card driver was not updated to perform this allocation.\\n\\n**Weaknesses/vulnerabilities present:**\\n\\n- Missing allocation of the Soundwire runtime stream in the SC7280 driver.\\n- This results in a NULL pointer dereference or other effects due to uninitialized memory access during sound playback.\\n\\n**Impact of exploitation:**\\n\\n-  A NULL pointer dereference or uninitialized memory access during sound playback, potentially leading to system instability or crashes.\\n\\n**Attack vectors:**\\n\\n- Triggering sound playback using the SC7280 sound card.\\n\\n**Required attacker capabilities/position:**\\n\\n- The attacker needs to be able to initiate sound playback on a system using the affected SC7280 sound card.\", similar_info={'cwe_distribution': {}, 'cwe_consensus': '', 'similarity_stats': {'thresholds': [], 'total_samples_by_threshold': {}, 'top_cwes_by_threshold': {}}}, similarity_summary=SimilarityInsight(consensus_cwe='', top_cwes=[], confidence_levels={}, total_samples=0), analysis='', analysis_with_relationships='', criticism='', resolution='', relevant_cwes=[{'metadata': {'doc_id': '476', 'name': 'NULL Pointer Dereference', 'source': 'sparse', 'original_content': 'The product dereferences a pointer that it expects to be valid but is NULL.', 'keyphrase_sources': [{'id': 'rootcause:forgot to update SC7280 card', 'keyphrase': 'forgot to update SC7280 card', 'type': 'rootcause'}, {'id': 'rootcause:uninitialized memory', 'keyphrase': 'uninitialized memory', 'type': 'rootcause'}, {'id': 'weakness:uninitialized memory accesses', 'keyphrase': 'uninitialized memory accesses', 'type': 'weakness'}, {'id': 'impact:NULL pointer dereference', 'keyphrase': 'NULL pointer dereference', 'type': 'impact'}, {'id': 'product:Linux kernel', 'keyphrase': 'Linux kernel', 'type': 'product'}, {'id': 'component:ASoC qcom sc7280', 'keyphrase': 'ASoC qcom sc7280', 'type': 'component'}]}, 'similarity': np.float64(501.55633820624064)}, {'metadata': {'doc_id': '909', 'name': 'Missing Initialization of Resource', 'source': 'sparse', 'original_content': 'The product does not initialize a critical resource.', 'keyphrase_sources': [{'id': 'rootcause:uninitialized memory', 'keyphrase': 'uninitialized memory', 'type': 'rootcause'}, {'id': 'weakness:uninitialized memory accesses', 'keyphrase': 'uninitialized memory accesses', 'type': 'weakness'}, {'id': 'product:Linux kernel', 'keyphrase': 'Linux kernel', 'type': 'product'}, {'id': 'component:ASoC qcom sc7280', 'keyphrase': 'ASoC qcom sc7280', 'type': 'component'}]}, 'similarity': np.float64(454.48394386131946)}, {'metadata': {'doc_id': '824', 'name': 'Access of Uninitialized Pointer', 'source': 'sparse', 'original_content': 'The product accesses or uses a pointer that has not been initialized.', 'keyphrase_sources': [{'id': 'rootcause:uninitialized memory', 'keyphrase': 'uninitialized memory', 'type': 'rootcause'}, {'id': 'weakness:uninitialized memory accesses', 'keyphrase': 'uninitialized memory accesses', 'type': 'weakness'}, {'id': 'impact:NULL pointer dereference', 'keyphrase': 'NULL pointer dereference', 'type': 'impact'}]}, 'similarity': np.float64(453.1520832355077)}, {'metadata': {'doc_id': '823', 'name': 'Use of Out-of-range Pointer Offset', 'source': 'sparse', 'original_content': 'The product performs pointer arithmetic on a valid pointer, but it uses an offset that can point outside of the intended range of valid memory locations for the resulting pointer.', 'keyphrase_sources': [{'id': 'rootcause:forgot to update SC7280 card', 'keyphrase': 'forgot to update SC7280 card', 'type': 'rootcause'}, {'id': 'impact:NULL pointer dereference', 'keyphrase': 'NULL pointer dereference', 'type': 'impact'}, {'id': 'product:Linux kernel', 'keyphrase': 'Linux kernel', 'type': 'product'}, {'id': 'component:ASoC qcom sc7280', 'keyphrase': 'ASoC qcom sc7280', 'type': 'component'}]}, 'similarity': np.float64(450.2425898668704)}, {'metadata': {'doc_id': '770', 'name': 'Allocation of Resources Without Limits or Throttling', 'source': 'sparse', 'original_content': 'The product allocates a reusable resource or group of resources on behalf of an actor without imposing any restrictions on the size or number of resources that can be allocated, in violation of the intended security policy for that actor.', 'keyphrase_sources': [{'id': 'rootcause:forgot to update SC7280 card', 'keyphrase': 'forgot to update SC7280 card', 'type': 'rootcause'}, {'id': 'rootcause:uninitialized memory', 'keyphrase': 'uninitialized memory', 'type': 'rootcause'}, {'id': 'weakness:uninitialized memory accesses', 'keyphrase': 'uninitialized memory accesses', 'type': 'weakness'}, {'id': 'product:Linux kernel', 'keyphrase': 'Linux kernel', 'type': 'product'}, {'id': 'component:ASoC qcom sc7280', 'keyphrase': 'ASoC qcom sc7280', 'type': 'component'}]}, 'similarity': np.float64(436.54169881017185)}, {'metadata': {'doc_id': '908', 'name': 'Use of Uninitialized Resource', 'source': 'sparse', 'original_content': 'The product uses or accesses a resource that has not been initialized.', 'keyphrase_sources': [{'id': 'rootcause:uninitialized memory', 'keyphrase': 'uninitialized memory', 'type': 'rootcause'}, {'id': 'weakness:uninitialized memory accesses', 'keyphrase': 'uninitialized memory accesses', 'type': 'weakness'}]}, 'similarity': np.float64(434.9384076978598)}, {'metadata': {'doc_id': '833', 'name': 'Deadlock', 'source': 'sparse', 'original_content': 'The product contains multiple threads or executable segments that are waiting for each other to release a necessary lock, resulting in deadlock.', 'keyphrase_sources': [{'id': 'rootcause:forgot to update SC7280 card', 'keyphrase': 'forgot to update SC7280 card', 'type': 'rootcause'}, {'id': 'impact:NULL pointer dereference', 'keyphrase': 'NULL pointer dereference', 'type': 'impact'}, {'id': 'product:Linux kernel', 'keyphrase': 'Linux kernel', 'type': 'product'}, {'id': 'component:ASoC qcom sc7280', 'keyphrase': 'ASoC qcom sc7280', 'type': 'component'}]}, 'similarity': np.float64(420.5997027572601)}, {'metadata': {'doc_id': '345', 'name': 'Insufficient Verification of Data Authenticity', 'source': 'sparse', 'original_content': 'The product does not sufficiently verify the origin or authenticity of data, in a way that causes it to accept invalid data.', 'keyphrase_sources': [{'id': 'rootcause:forgot to update SC7280 card', 'keyphrase': 'forgot to update SC7280 card', 'type': 'rootcause'}]}, 'similarity': np.float64(415.88998099021137)}, {'metadata': {'doc_id': '252', 'name': 'Unchecked Return Value', 'source': 'sparse', 'original_content': 'The product does not check the return value from a method or function, which can prevent it from detecting unexpected states and conditions.', 'keyphrase_sources': [{'id': 'impact:NULL pointer dereference', 'keyphrase': 'NULL pointer dereference', 'type': 'impact'}]}, 'similarity': np.float64(148.410941744164)}], identified_cwes={'analyzer': [], 'critic_additional': []})",
  "retrieval_results": {
    "has_multiple_keyphrases": true,
    "keyphrase_cwe_sets": {
      "rootcause:forgot to update SC7280 card": {
        "keyphrase": "forgot to update SC7280 card",
        "type": "rootcause",
        "cwes": [
          {
            "metadata": {
              "doc_id": "476",
              "name": "NULL Pointer Dereference",
              "source": "sparse",
              "original_content": "The product dereferences a pointer that it expects to be valid but is NULL.",
              "keyphrase_sources": [
                {
                  "id": "rootcause:forgot to update SC7280 card",
                  "keyphrase": "forgot to update SC7280 card",
                  "type": "rootcause"
                },
                {
                  "id": "rootcause:uninitialized memory",
                  "keyphrase": "uninitialized memory",
                  "type": "rootcause"
                },
                {
                  "id": "weakness:uninitialized memory accesses",
                  "keyphrase": "uninitialized memory accesses",
                  "type": "weakness"
                },
                {
                  "id": "impact:NULL pointer dereference",
                  "keyphrase": "NULL pointer dereference",
                  "type": "impact"
                },
                {
                  "id": "product:Linux kernel",
                  "keyphrase": "Linux kernel",
                  "type": "product"
                },
                {
                  "id": "component:ASoC qcom sc7280",
                  "keyphrase": "ASoC qcom sc7280",
                  "type": "component"
                }
              ]
            },
            "similarity": 501.55633820624064
          },
          {
            "metadata": {
              "doc_id": "823",
              "name": "Use of Out-of-range Pointer Offset",
              "source": "sparse",
              "original_content": "The product performs pointer arithmetic on a valid pointer, but it uses an offset that can point outside of the intended range of valid memory locations for the resulting pointer.",
              "keyphrase_sources": [
                {
                  "id": "rootcause:forgot to update SC7280 card",
                  "keyphrase": "forgot to update SC7280 card",
                  "type": "rootcause"
                },
                {
                  "id": "impact:NULL pointer dereference",
                  "keyphrase": "NULL pointer dereference",
                  "type": "impact"
                },
                {
                  "id": "product:Linux kernel",
                  "keyphrase": "Linux kernel",
                  "type": "product"
                },
                {
                  "id": "component:ASoC qcom sc7280",
                  "keyphrase": "ASoC qcom sc7280",
                  "type": "component"
                }
              ]
            },
            "similarity": 450.2425898668704
          },
          {
            "metadata": {
              "doc_id": "770",
              "name": "Allocation of Resources Without Limits or Throttling",
              "source": "sparse",
              "original_content": "The product allocates a reusable resource or group of resources on behalf of an actor without imposing any restrictions on the size or number of resources that can be allocated, in violation of the intended security policy for that actor.",
              "keyphrase_sources": [
                {
                  "id": "rootcause:forgot to update SC7280 card",
                  "keyphrase": "forgot to update SC7280 card",
                  "type": "rootcause"
                },
                {
                  "id": "rootcause:uninitialized memory",
                  "keyphrase": "uninitialized memory",
                  "type": "rootcause"
                },
                {
                  "id": "weakness:uninitialized memory accesses",
                  "keyphrase": "uninitialized memory accesses",
                  "type": "weakness"
                },
                {
                  "id": "product:Linux kernel",
                  "keyphrase": "Linux kernel",
                  "type": "product"
                },
                {
                  "id": "component:ASoC qcom sc7280",
                  "keyphrase": "ASoC qcom sc7280",
                  "type": "component"
                }
              ]
            },
            "similarity": 436.54169881017185
          },
          {
            "metadata": {
              "doc_id": "833",
              "name": "Deadlock",
              "source": "sparse",
              "original_content": "The product contains multiple threads or executable segments that are waiting for each other to release a necessary lock, resulting in deadlock.",
              "keyphrase_sources": [
                {
                  "id": "rootcause:forgot to update SC7280 card",
                  "keyphrase": "forgot to update SC7280 card",
                  "type": "rootcause"
                },
                {
                  "id": "impact:NULL pointer dereference",
                  "keyphrase": "NULL pointer dereference",
                  "type": "impact"
                },
                {
                  "id": "product:Linux kernel",
                  "keyphrase": "Linux kernel",
                  "type": "product"
                },
                {
                  "id": "component:ASoC qcom sc7280",
                  "keyphrase": "ASoC qcom sc7280",
                  "type": "component"
                }
              ]
            },
            "similarity": 420.5997027572601
          },
          {
            "metadata": {
              "doc_id": "345",
              "name": "Insufficient Verification of Data Authenticity",
              "source": "sparse",
              "original_content": "The product does not sufficiently verify the origin or authenticity of data, in a way that causes it to accept invalid data.",
              "keyphrase_sources": [
                {
                  "id": "rootcause:forgot to update SC7280 card",
                  "keyphrase": "forgot to update SC7280 card",
                  "type": "rootcause"
                }
              ]
            },
            "similarity": 415.88998099021137
          }
        ]
      },
      "rootcause:uninitialized memory": {
        "keyphrase": "uninitialized memory",
        "type": "rootcause",
        "cwes": [
          {
            "metadata": {
              "doc_id": "476",
              "name": "NULL Pointer Dereference",
              "source": "sparse",
              "original_content": "The product dereferences a pointer that it expects to be valid but is NULL."
            },
            "similarity": 503.68274764471516
          },
          {
            "metadata": {
              "doc_id": "909",
              "name": "Missing Initialization of Resource",
              "source": "sparse",
              "original_content": "The product does not initialize a critical resource.",
              "keyphrase_sources": [
                {
                  "id": "rootcause:uninitialized memory",
                  "keyphrase": "uninitialized memory",
                  "type": "rootcause"
                },
                {
                  "id": "weakness:uninitialized memory accesses",
                  "keyphrase": "uninitialized memory accesses",
                  "type": "weakness"
                },
                {
                  "id": "product:Linux kernel",
                  "keyphrase": "Linux kernel",
                  "type": "product"
                },
                {
                  "id": "component:ASoC qcom sc7280",
                  "keyphrase": "ASoC qcom sc7280",
                  "type": "component"
                }
              ]
            },
            "similarity": 454.48394386131946
          },
          {
            "metadata": {
              "doc_id": "824",
              "name": "Access of Uninitialized Pointer",
              "source": "sparse",
              "original_content": "The product accesses or uses a pointer that has not been initialized.",
              "keyphrase_sources": [
                {
                  "id": "rootcause:uninitialized memory",
                  "keyphrase": "uninitialized memory",
                  "type": "rootcause"
                },
                {
                  "id": "weakness:uninitialized memory accesses",
                  "keyphrase": "uninitialized memory accesses",
                  "type": "weakness"
                },
                {
                  "id": "impact:NULL pointer dereference",
                  "keyphrase": "NULL pointer dereference",
                  "type": "impact"
                }
              ]
            },
            "similarity": 453.1520832355077
          },
          {
            "metadata": {
              "doc_id": "908",
              "name": "Use of Uninitialized Resource",
              "source": "sparse",
              "original_content": "The product uses or accesses a resource that has not been initialized.",
              "keyphrase_sources": [
                {
                  "id": "rootcause:uninitialized memory",
                  "keyphrase": "uninitialized memory",
                  "type": "rootcause"
                },
                {
                  "id": "weakness:uninitialized memory accesses",
                  "keyphrase": "uninitialized memory accesses",
                  "type": "weakness"
                }
              ]
            },
            "similarity": 434.9384076978598
          },
          {
            "metadata": {
              "doc_id": "770",
              "name": "Allocation of Resources Without Limits or Throttling",
              "source": "sparse",
              "original_content": "The product allocates a reusable resource or group of resources on behalf of an actor without imposing any restrictions on the size or number of resources that can be allocated, in violation of the intended security policy for that actor."
            },
            "similarity": 428.1051284375942
          }
        ]
      },
      "weakness:uninitialized memory accesses": {
        "keyphrase": "uninitialized memory accesses",
        "type": "weakness",
        "cwes": [
          {
            "metadata": {
              "doc_id": "476",
              "name": "NULL Pointer Dereference",
              "source": "sparse",
              "original_content": "The product dereferences a pointer that it expects to be valid but is NULL."
            },
            "similarity": 470.1038978017341
          },
          {
            "metadata": {
              "doc_id": "824",
              "name": "Access of Uninitialized Pointer",
              "source": "sparse",
              "original_content": "The product accesses or uses a pointer that has not been initialized."
            },
            "similarity": 449.8233666291894
          },
          {
            "metadata": {
              "doc_id": "909",
              "name": "Missing Initialization of Resource",
              "source": "sparse",
              "original_content": "The product does not initialize a critical resource."
            },
            "similarity": 424.1850142705648
          },
          {
            "metadata": {
              "doc_id": "908",
              "name": "Use of Uninitialized Resource",
              "source": "sparse",
              "original_content": "The product uses or accesses a resource that has not been initialized."
            },
            "similarity": 420.36258371400015
          },
          {
            "metadata": {
              "doc_id": "770",
              "name": "Allocation of Resources Without Limits or Throttling",
              "source": "sparse",
              "original_content": "The product allocates a reusable resource or group of resources on behalf of an actor without imposing any restrictions on the size or number of resources that can be allocated, in violation of the intended security policy for that actor."
            },
            "similarity": 399.56478654175453
          }
        ]
      },
      "impact:NULL pointer dereference": {
        "keyphrase": "NULL pointer dereference",
        "type": "impact",
        "cwes": [
          {
            "metadata": {
              "doc_id": "476",
              "name": "NULL Pointer Dereference",
              "source": "sparse",
              "original_content": "The product dereferences a pointer that it expects to be valid but is NULL."
            },
            "similarity": 193.61224331644272
          },
          {
            "metadata": {
              "doc_id": "824",
              "name": "Access of Uninitialized Pointer",
              "source": "sparse",
              "original_content": "The product accesses or uses a pointer that has not been initialized."
            },
            "similarity": 157.294286889698
          },
          {
            "metadata": {
              "doc_id": "823",
              "name": "Use of Out-of-range Pointer Offset",
              "source": "sparse",
              "original_content": "The product performs pointer arithmetic on a valid pointer, but it uses an offset that can point outside of the intended range of valid memory locations for the resulting pointer."
            },
            "similarity": 150.60457329977626
          },
          {
            "metadata": {
              "doc_id": "833",
              "name": "Deadlock",
              "source": "sparse",
              "original_content": "The product contains multiple threads or executable segments that are waiting for each other to release a necessary lock, resulting in deadlock."
            },
            "similarity": 149.60520207164444
          },
          {
            "metadata": {
              "doc_id": "252",
              "name": "Unchecked Return Value",
              "source": "sparse",
              "original_content": "The product does not check the return value from a method or function, which can prevent it from detecting unexpected states and conditions.",
              "keyphrase_sources": [
                {
                  "id": "impact:NULL pointer dereference",
                  "keyphrase": "NULL pointer dereference",
                  "type": "impact"
                }
              ]
            },
            "similarity": 148.410941744164
          }
        ]
      },
      "product:Linux kernel": {
        "keyphrase": "Linux kernel",
        "type": "product",
        "cwes": [
          {
            "metadata": {
              "doc_id": "476",
              "name": "NULL Pointer Dereference",
              "source": "sparse",
              "original_content": "The product dereferences a pointer that it expects to be valid but is NULL."
            },
            "similarity": 163.99268170056385
          },
          {
            "metadata": {
              "doc_id": "909",
              "name": "Missing Initialization of Resource",
              "source": "sparse",
              "original_content": "The product does not initialize a critical resource."
            },
            "similarity": 147.5801229878184
          },
          {
            "metadata": {
              "doc_id": "833",
              "name": "Deadlock",
              "source": "sparse",
              "original_content": "The product contains multiple threads or executable segments that are waiting for each other to release a necessary lock, resulting in deadlock."
            },
            "similarity": 146.81831776941823
          },
          {
            "metadata": {
              "doc_id": "770",
              "name": "Allocation of Resources Without Limits or Throttling",
              "source": "sparse",
              "original_content": "The product allocates a reusable resource or group of resources on behalf of an actor without imposing any restrictions on the size or number of resources that can be allocated, in violation of the intended security policy for that actor."
            },
            "similarity": 143.69301777859053
          },
          {
            "metadata": {
              "doc_id": "823",
              "name": "Use of Out-of-range Pointer Offset",
              "source": "sparse",
              "original_content": "The product performs pointer arithmetic on a valid pointer, but it uses an offset that can point outside of the intended range of valid memory locations for the resulting pointer."
            },
            "similarity": 141.71743473653962
          }
        ]
      },
      "component:ASoC qcom sc7280": {
        "keyphrase": "ASoC qcom sc7280",
        "type": "component",
        "cwes": [
          {
            "metadata": {
              "doc_id": "476",
              "name": "NULL Pointer Dereference",
              "source": "sparse",
              "original_content": "The product dereferences a pointer that it expects to be valid but is NULL."
            },
            "similarity": 154.07402656174074
          },
          {
            "metadata": {
              "doc_id": "770",
              "name": "Allocation of Resources Without Limits or Throttling",
              "source": "sparse",
              "original_content": "The product allocates a reusable resource or group of resources on behalf of an actor without imposing any restrictions on the size or number of resources that can be allocated, in violation of the intended security policy for that actor."
            },
            "similarity": 137.21194467227676
          },
          {
            "metadata": {
              "doc_id": "833",
              "name": "Deadlock",
              "source": "sparse",
              "original_content": "The product contains multiple threads or executable segments that are waiting for each other to release a necessary lock, resulting in deadlock."
            },
            "similarity": 133.08007511099868
          },
          {
            "metadata": {
              "doc_id": "823",
              "name": "Use of Out-of-range Pointer Offset",
              "source": "sparse",
              "original_content": "The product performs pointer arithmetic on a valid pointer, but it uses an offset that can point outside of the intended range of valid memory locations for the resulting pointer."
            },
            "similarity": 131.72743622006394
          },
          {
            "metadata": {
              "doc_id": "909",
              "name": "Missing Initialization of Resource",
              "source": "sparse",
              "original_content": "The product does not initialize a critical resource."
            },
            "similarity": 131.1193694613387
          }
        ]
      }
    },
    "keyphrase_mapping": {
      "476": [
        {
          "id": "rootcause:forgot to update SC7280 card",
          "keyphrase": "forgot to update SC7280 card",
          "type": "rootcause"
        },
        {
          "id": "rootcause:uninitialized memory",
          "keyphrase": "uninitialized memory",
          "type": "rootcause"
        },
        {
          "id": "weakness:uninitialized memory accesses",
          "keyphrase": "uninitialized memory accesses",
          "type": "weakness"
        },
        {
          "id": "impact:NULL pointer dereference",
          "keyphrase": "NULL pointer dereference",
          "type": "impact"
        },
        {
          "id": "product:Linux kernel",
          "keyphrase": "Linux kernel",
          "type": "product"
        },
        {
          "id": "component:ASoC qcom sc7280",
          "keyphrase": "ASoC qcom sc7280",
          "type": "component"
        }
      ],
      "823": [
        {
          "id": "rootcause:forgot to update SC7280 card",
          "keyphrase": "forgot to update SC7280 card",
          "type": "rootcause"
        },
        {
          "id": "impact:NULL pointer dereference",
          "keyphrase": "NULL pointer dereference",
          "type": "impact"
        },
        {
          "id": "product:Linux kernel",
          "keyphrase": "Linux kernel",
          "type": "product"
        },
        {
          "id": "component:ASoC qcom sc7280",
          "keyphrase": "ASoC qcom sc7280",
          "type": "component"
        }
      ],
      "770": [
        {
          "id": "rootcause:forgot to update SC7280 card",
          "keyphrase": "forgot to update SC7280 card",
          "type": "rootcause"
        },
        {
          "id": "rootcause:uninitialized memory",
          "keyphrase": "uninitialized memory",
          "type": "rootcause"
        },
        {
          "id": "weakness:uninitialized memory accesses",
          "keyphrase": "uninitialized memory accesses",
          "type": "weakness"
        },
        {
          "id": "product:Linux kernel",
          "keyphrase": "Linux kernel",
          "type": "product"
        },
        {
          "id": "component:ASoC qcom sc7280",
          "keyphrase": "ASoC qcom sc7280",
          "type": "component"
        }
      ],
      "833": [
        {
          "id": "rootcause:forgot to update SC7280 card",
          "keyphrase": "forgot to update SC7280 card",
          "type": "rootcause"
        },
        {
          "id": "impact:NULL pointer dereference",
          "keyphrase": "NULL pointer dereference",
          "type": "impact"
        },
        {
          "id": "product:Linux kernel",
          "keyphrase": "Linux kernel",
          "type": "product"
        },
        {
          "id": "component:ASoC qcom sc7280",
          "keyphrase": "ASoC qcom sc7280",
          "type": "component"
        }
      ],
      "345": [
        {
          "id": "rootcause:forgot to update SC7280 card",
          "keyphrase": "forgot to update SC7280 card",
          "type": "rootcause"
        }
      ],
      "909": [
        {
          "id": "rootcause:uninitialized memory",
          "keyphrase": "uninitialized memory",
          "type": "rootcause"
        },
        {
          "id": "weakness:uninitialized memory accesses",
          "keyphrase": "uninitialized memory accesses",
          "type": "weakness"
        },
        {
          "id": "product:Linux kernel",
          "keyphrase": "Linux kernel",
          "type": "product"
        },
        {
          "id": "component:ASoC qcom sc7280",
          "keyphrase": "ASoC qcom sc7280",
          "type": "component"
        }
      ],
      "824": [
        {
          "id": "rootcause:uninitialized memory",
          "keyphrase": "uninitialized memory",
          "type": "rootcause"
        },
        {
          "id": "weakness:uninitialized memory accesses",
          "keyphrase": "uninitialized memory accesses",
          "type": "weakness"
        },
        {
          "id": "impact:NULL pointer dereference",
          "keyphrase": "NULL pointer dereference",
          "type": "impact"
        }
      ],
      "908": [
        {
          "id": "rootcause:uninitialized memory",
          "keyphrase": "uninitialized memory",
          "type": "rootcause"
        },
        {
          "id": "weakness:uninitialized memory accesses",
          "keyphrase": "uninitialized memory accesses",
          "type": "weakness"
        }
      ],
      "252": [
        {
          "id": "impact:NULL pointer dereference",
          "keyphrase": "NULL pointer dereference",
          "type": "impact"
        }
      ]
    },
    "relevant_cwes": [
      {
        "metadata": {
          "doc_id": "476",
          "name": "NULL Pointer Dereference",
          "source": "sparse",
          "original_content": "The product dereferences a pointer that it expects to be valid but is NULL.",
          "keyphrase_sources": [
            {
              "id": "rootcause:forgot to update SC7280 card",
              "keyphrase": "forgot to update SC7280 card",
              "type": "rootcause"
            },
            {
              "id": "rootcause:uninitialized memory",
              "keyphrase": "uninitialized memory",
              "type": "rootcause"
            },
            {
              "id": "weakness:uninitialized memory accesses",
              "keyphrase": "uninitialized memory accesses",
              "type": "weakness"
            },
            {
              "id": "impact:NULL pointer dereference",
              "keyphrase": "NULL pointer dereference",
              "type": "impact"
            },
            {
              "id": "product:Linux kernel",
              "keyphrase": "Linux kernel",
              "type": "product"
            },
            {
              "id": "component:ASoC qcom sc7280",
              "keyphrase": "ASoC qcom sc7280",
              "type": "component"
            }
          ]
        },
        "similarity": 501.55633820624064
      },
      {
        "metadata": {
          "doc_id": "909",
          "name": "Missing Initialization of Resource",
          "source": "sparse",
          "original_content": "The product does not initialize a critical resource.",
          "keyphrase_sources": [
            {
              "id": "rootcause:uninitialized memory",
              "keyphrase": "uninitialized memory",
              "type": "rootcause"
            },
            {
              "id": "weakness:uninitialized memory accesses",
              "keyphrase": "uninitialized memory accesses",
              "type": "weakness"
            },
            {
              "id": "product:Linux kernel",
              "keyphrase": "Linux kernel",
              "type": "product"
            },
            {
              "id": "component:ASoC qcom sc7280",
              "keyphrase": "ASoC qcom sc7280",
              "type": "component"
            }
          ]
        },
        "similarity": 454.48394386131946
      },
      {
        "metadata": {
          "doc_id": "824",
          "name": "Access of Uninitialized Pointer",
          "source": "sparse",
          "original_content": "The product accesses or uses a pointer that has not been initialized.",
          "keyphrase_sources": [
            {
              "id": "rootcause:uninitialized memory",
              "keyphrase": "uninitialized memory",
              "type": "rootcause"
            },
            {
              "id": "weakness:uninitialized memory accesses",
              "keyphrase": "uninitialized memory accesses",
              "type": "weakness"
            },
            {
              "id": "impact:NULL pointer dereference",
              "keyphrase": "NULL pointer dereference",
              "type": "impact"
            }
          ]
        },
        "similarity": 453.1520832355077
      },
      {
        "metadata": {
          "doc_id": "823",
          "name": "Use of Out-of-range Pointer Offset",
          "source": "sparse",
          "original_content": "The product performs pointer arithmetic on a valid pointer, but it uses an offset that can point outside of the intended range of valid memory locations for the resulting pointer.",
          "keyphrase_sources": [
            {
              "id": "rootcause:forgot to update SC7280 card",
              "keyphrase": "forgot to update SC7280 card",
              "type": "rootcause"
            },
            {
              "id": "impact:NULL pointer dereference",
              "keyphrase": "NULL pointer dereference",
              "type": "impact"
            },
            {
              "id": "product:Linux kernel",
              "keyphrase": "Linux kernel",
              "type": "product"
            },
            {
              "id": "component:ASoC qcom sc7280",
              "keyphrase": "ASoC qcom sc7280",
              "type": "component"
            }
          ]
        },
        "similarity": 450.2425898668704
      },
      {
        "metadata": {
          "doc_id": "770",
          "name": "Allocation of Resources Without Limits or Throttling",
          "source": "sparse",
          "original_content": "The product allocates a reusable resource or group of resources on behalf of an actor without imposing any restrictions on the size or number of resources that can be allocated, in violation of the intended security policy for that actor.",
          "keyphrase_sources": [
            {
              "id": "rootcause:forgot to update SC7280 card",
              "keyphrase": "forgot to update SC7280 card",
              "type": "rootcause"
            },
            {
              "id": "rootcause:uninitialized memory",
              "keyphrase": "uninitialized memory",
              "type": "rootcause"
            },
            {
              "id": "weakness:uninitialized memory accesses",
              "keyphrase": "uninitialized memory accesses",
              "type": "weakness"
            },
            {
              "id": "product:Linux kernel",
              "keyphrase": "Linux kernel",
              "type": "product"
            },
            {
              "id": "component:ASoC qcom sc7280",
              "keyphrase": "ASoC qcom sc7280",
              "type": "component"
            }
          ]
        },
        "similarity": 436.54169881017185
      },
      {
        "metadata": {
          "doc_id": "908",
          "name": "Use of Uninitialized Resource",
          "source": "sparse",
          "original_content": "The product uses or accesses a resource that has not been initialized.",
          "keyphrase_sources": [
            {
              "id": "rootcause:uninitialized memory",
              "keyphrase": "uninitialized memory",
              "type": "rootcause"
            },
            {
              "id": "weakness:uninitialized memory accesses",
              "keyphrase": "uninitialized memory accesses",
              "type": "weakness"
            }
          ]
        },
        "similarity": 434.9384076978598
      },
      {
        "metadata": {
          "doc_id": "833",
          "name": "Deadlock",
          "source": "sparse",
          "original_content": "The product contains multiple threads or executable segments that are waiting for each other to release a necessary lock, resulting in deadlock.",
          "keyphrase_sources": [
            {
              "id": "rootcause:forgot to update SC7280 card",
              "keyphrase": "forgot to update SC7280 card",
              "type": "rootcause"
            },
            {
              "id": "impact:NULL pointer dereference",
              "keyphrase": "NULL pointer dereference",
              "type": "impact"
            },
            {
              "id": "product:Linux kernel",
              "keyphrase": "Linux kernel",
              "type": "product"
            },
            {
              "id": "component:ASoC qcom sc7280",
              "keyphrase": "ASoC qcom sc7280",
              "type": "component"
            }
          ]
        },
        "similarity": 420.5997027572601
      },
      {
        "metadata": {
          "doc_id": "345",
          "name": "Insufficient Verification of Data Authenticity",
          "source": "sparse",
          "original_content": "The product does not sufficiently verify the origin or authenticity of data, in a way that causes it to accept invalid data.",
          "keyphrase_sources": [
            {
              "id": "rootcause:forgot to update SC7280 card",
              "keyphrase": "forgot to update SC7280 card",
              "type": "rootcause"
            }
          ]
        },
        "similarity": 415.88998099021137
      },
      {
        "metadata": {
          "doc_id": "252",
          "name": "Unchecked Return Value",
          "source": "sparse",
          "original_content": "The product does not check the return value from a method or function, which can prevent it from detecting unexpected states and conditions.",
          "keyphrase_sources": [
            {
              "id": "impact:NULL pointer dereference",
              "keyphrase": "NULL pointer dereference",
              "type": "impact"
            }
          ]
        },
        "similarity": 148.410941744164
      }
    ],
    "enhanced_query": "# Vulnerability Description\n\n    In the Linux kernel, the following vulnerability has been resolved ASoC qcom sc7280 Fix missing Soundwire runtime stream alloc Commit 15c7fab0e047 (ASoC qcom Move Soundwire runtime stream alloc to soundcards) moved the allocation of Soundwire stream runtime from the Qualcomm Soundwire driver to each individual machine sound card driver, except that it **forgot to update SC7280 card**. Just like for other Qualcomm sound cards using Soundwire, the card driver should allocate and release the runtime. Otherwise sound playback will result in a NULL pointer dereference or other effect of **uninitialized memory** accesses (which was confirmed on SDM845 having similar issue).\n\n    # Keyphrase-Specific CWE Analysis\n    This vulnerability contains multiple keyphrases that may map to different CWEs. \n    Please analyze each keyphrase separately and determine the most appropriate CWE(s) for each.\n\n    ## ROOTCAUSE: 'forgot to update SC7280 card'\n\nRelevant CWEs for this ROOTCAUSE:\n\n### 1. CWE-476: NULL Pointer Dereference (Score: 501.56)\n\nThe product dereferences a pointer that it expects to be valid but is NULL....\n\n### 2. CWE-823: Use of Out-of-range Pointer Offset (Score: 450.24)\n\nThe product performs pointer arithmetic on a valid pointer, but it uses an offset that can point outside of the intended range of valid memory locations for the resulting pointer....\n\n### 3. CWE-770: Allocation of Resources Without Limits or Throttling (Score: 436.54)\n\nThe product allocates a reusable resource or group of resources on behalf of an actor without imposing any restrictions on the size or number of resources that can be allocated, in violation of the intended security policy for that actor....\n\n### 4. CWE-833: Deadlock (Score: 420.60)\n\nThe product contains multiple threads or executable segments that are waiting for each other to release a necessary lock, resulting in deadlock....\n\n### 5. CWE-345: Insufficient Verification of Data Authenticity (Score: 415.89)\n\nThe product does not sufficiently verify the origin or authenticity of data, in a way that causes it to accept invalid data....\n\n## ROOTCAUSE: 'uninitialized memory'\n\nRelevant CWEs for this ROOTCAUSE:\n\n### 1. CWE-476: NULL Pointer Dereference (Score: 501.56)\n\nThe product dereferences a pointer that it expects to be valid but is NULL....\n\n### 2. CWE-909: Missing Initialization of Resource (Score: 454.48)\n\nThe product does not initialize a critical resource....\n\n### 3. CWE-824: Access of Uninitialized Pointer (Score: 453.15)\n\nThe product accesses or uses a pointer that has not been initialized....\n\n### 4. CWE-770: Allocation of Resources Without Limits or Throttling (Score: 436.54)\n\nThe product allocates a reusable resource or group of resources on behalf of an actor without imposing any restrictions on the size or number of resources that can be allocated, in violation of the intended security policy for that actor....\n\n### 5. CWE-908: Use of Uninitialized Resource (Score: 434.94)\n\nThe product uses or accesses a resource that has not been initialized....\n\n## WEAKNESS: 'uninitialized memory accesses'\n\nRelevant CWEs for this WEAKNESS:\n\n### 1. CWE-476: NULL Pointer Dereference (Score: 501.56)\n\nThe product dereferences a pointer that it expects to be valid but is NULL....\n\n### 2. CWE-909: Missing Initialization of Resource (Score: 454.48)\n\nThe product does not initialize a critical resource....\n\n### 3. CWE-824: Access of Uninitialized Pointer (Score: 453.15)\n\nThe product accesses or uses a pointer that has not been initialized....\n\n### 4. CWE-770: Allocation of Resources Without Limits or Throttling (Score: 436.54)\n\nThe product allocates a reusable resource or group of resources on behalf of an actor without imposing any restrictions on the size or number of resources that can be allocated, in violation of the intended security policy for that actor....\n\n### 5. CWE-908: Use of Uninitialized Resource (Score: 434.94)\n\nThe product uses or accesses a resource that has not been initialized....\n\n## IMPACT: 'NULL pointer dereference'\n\nRelevant CWEs for this IMPACT:\n\n### 1. CWE-476: NULL Pointer Dereference (Score: 501.56)\n\nThe product dereferences a pointer that it expects to be valid but is NULL....\n\n### 2. CWE-824: Access of Uninitialized Pointer (Score: 453.15)\n\nThe product accesses or uses a pointer that has not been initialized....\n\n### 3. CWE-823: Use of Out-of-range Pointer Offset (Score: 450.24)\n\nThe product performs pointer arithmetic on a valid pointer, but it uses an offset that can point outside of the intended range of valid memory locations for the resulting pointer....\n\n### 4. CWE-833: Deadlock (Score: 420.60)\n\nThe product contains multiple threads or executable segments that are waiting for each other to release a necessary lock, resulting in deadlock....\n\n### 5. CWE-252: Unchecked Return Value (Score: 148.41)\n\nThe product does not check the return value from a method or function, which can prevent it from detecting unexpected states and conditions....\n\n## PRODUCT: 'Linux kernel'\n\nRelevant CWEs for this PRODUCT:\n\n### 1. CWE-476: NULL Pointer Dereference (Score: 501.56)\n\nThe product dereferences a pointer that it expects to be valid but is NULL....\n\n### 2. CWE-909: Missing Initialization of Resource (Score: 454.48)\n\nThe product does not initialize a critical resource....\n\n### 3. CWE-823: Use of Out-of-range Pointer Offset (Score: 450.24)\n\nThe product performs pointer arithmetic on a valid pointer, but it uses an offset that can point outside of the intended range of valid memory locations for the resulting pointer....\n\n### 4. CWE-770: Allocation of Resources Without Limits or Throttling (Score: 436.54)\n\nThe product allocates a reusable resource or group of resources on behalf of an actor without imposing any restrictions on the size or number of resources that can be allocated, in violation of the intended security policy for that actor....\n\n### 5. CWE-833: Deadlock (Score: 420.60)\n\nThe product contains multiple threads or executable segments that are waiting for each other to release a necessary lock, resulting in deadlock....\n\n## COMPONENT: 'ASoC qcom sc7280'\n\nRelevant CWEs for this COMPONENT:\n\n### 1. CWE-476: NULL Pointer Dereference (Score: 501.56)\n\nThe product dereferences a pointer that it expects to be valid but is NULL....\n\n### 2. CWE-909: Missing Initialization of Resource (Score: 454.48)\n\nThe product does not initialize a critical resource....\n\n### 3. CWE-823: Use of Out-of-range Pointer Offset (Score: 450.24)\n\nThe product performs pointer arithmetic on a valid pointer, but it uses an offset that can point outside of the intended range of valid memory locations for the resulting pointer....\n\n### 4. CWE-770: Allocation of Resources Without Limits or Throttling (Score: 436.54)\n\nThe product allocates a reusable resource or group of resources on behalf of an actor without imposing any restrictions on the size or number of resources that can be allocated, in violation of the intended security policy for that actor....\n\n### 5. CWE-833: Deadlock (Score: 420.60)\n\nThe product contains multiple threads or executable segments that are waiting for each other to release a necessary lock, resulting in deadlock....\n\n\n    # Analysis Instructions\n    1. For each keyphrase, identify the most appropriate CWE(s) that represent the weakness.\n    2. Consider how the different keyphrases might relate to each other in the vulnerability chain.\n    3. Provide a final determination of primary CWE(s) and any secondary CWEs.\n    4. Format your response using the standard analysis template.\n\n    Please analyze how these different weaknesses interact and provide a comprehensive CWE classification.\n    "
  },
  "retrieval_time": 1.3443799018859863
}