{
  "vulnerability_info": "VulnerabilityInfo(cve_id='CVE-2024-47238', description='Dell Client Platform BIOS contains an **Improper Input Validation** vulnerability in an externally developed component. A high privileged attacker with local access could potentially exploit this vulnerability, leading to arbitrary code execution.', key_phrases={'rootcause': ['Improper Input Validation', 'Input Validation vulnerability'], 'weakness': '', 'impact': 'arbitrary code execution', 'vector': '', 'attacker': 'high privileged attacker with local access', 'product': 'Dell Client Platform BIOS', 'version': '', 'component': 'externally developed component'}, reference_content=\"Based on the provided document, here's a breakdown of the vulnerability:\\n\\n**CVE ID:** CVE-2024-47238\\n\\n**Root Cause:** The vulnerability is due to an Improper Input Validation in an externally developed component of the Dell Client Platform BIOS.\\n\\n**Weaknesses/Vulnerabilities:** The primary weakness is the insufficient input validation within the BIOS component. This lack of proper validation allows for the injection or manipulation of data in a way that the system was not designed to handle.\\n\\n**Impact of Exploitation:** A successful exploit could lead to arbitrary code execution, meaning an attacker could run any code they desire on the compromised system. This level of access can allow for complete system takeover, data theft, malware installation, and more.\\n\\n**Attack Vectors:** The attack vector is local access. This means the attacker must have some level of access to the physical system or a remote access method that allows them to interact with the system as if they were local.\\n\\n**Required Attacker Capabilities/Position:**\\n*   **High Privileged Access:** The attacker needs high-level privileges on the system to be able to exploit this vulnerability. This implies administrative or similar access to the system.\\n*   **Local Access:**  The attacker must have local access to the system or a remote access method that allows them to interact with the system as if they were local.\\n\\n**CVSS Score:** 7.5 (High)\\n\\n**CVSS Vector String:** CVSS:3.1/AV:L/AC:H/PR:H/UI:N/S:C/C:H/I:H/A:H\\n\\n**Affected Products:**\\n*   Dell Edge Gateway 5000\\n*   Edge Gateway 3000 series\\n*   Embedded Box PC 3000\\n\\n**Remediation:** Update the BIOS to the following versions or later:\\n* Dell Edge Gateway 5000: Version 1.29.0 or later\\n* Edge Gateway 3000 series: Version 1.19.0 or later\\n* Embedded Box PC 3000: Version 1.25.0 or later\\n\\n**Additional Details:**\\n* The vulnerability was reported by Eclypsium.\\n* Dell recommends customers consider both CVSS base score and any temporal and environmental scores.\", similar_info={'cwe_distribution': {}, 'cwe_consensus': '', 'similarity_stats': {'thresholds': [], 'total_samples_by_threshold': {}, 'top_cwes_by_threshold': {}}}, similarity_summary=SimilarityInsight(consensus_cwe='', top_cwes=[], confidence_levels={}, total_samples=0), analysis='', analysis_with_relationships='', criticism='', resolution='', relevant_cwes=[{'metadata': {'doc_id': '20', 'name': 'Improper Input Validation', 'source': 'sparse', 'original_content': 'The product receives input or data, but it does\\n        not validate or incorrectly validates that the input has the\\n        properties that are required to process the data safely and\\n        correctly.', 'keyphrase_sources': [{'id': 'rootcause:Improper Input Validation', 'keyphrase': 'Improper Input Validation', 'type': 'rootcause'}, {'id': 'rootcause:Input Validation vulnerability', 'keyphrase': 'Input Validation vulnerability', 'type': 'rootcause'}, {'id': 'impact:arbitrary code execution', 'keyphrase': 'arbitrary code execution', 'type': 'impact'}, {'id': 'attacker:high privileged attacker with local access', 'keyphrase': 'high privileged attacker with local access', 'type': 'attacker'}, {'id': 'product:Dell Client Platform BIOS', 'keyphrase': 'Dell Client Platform BIOS', 'type': 'product'}, {'id': 'component:externally developed component', 'keyphrase': 'externally developed component', 'type': 'component'}]}, 'similarity': np.float64(223.37216696088583)}, {'metadata': {'doc_id': '119', 'name': 'Improper Restriction of Operations within the Bounds of a Memory Buffer', 'source': 'sparse', 'original_content': \"The product performs operations on a memory buffer, but it reads from or writes to a memory location outside the buffer's intended boundary. This may result in read or write operations on unexpected memory locations that could be linked to other variables, data structures, or internal program data.\", 'keyphrase_sources': [{'id': 'rootcause:Improper Input Validation', 'keyphrase': 'Improper Input Validation', 'type': 'rootcause'}, {'id': 'rootcause:Input Validation vulnerability', 'keyphrase': 'Input Validation vulnerability', 'type': 'rootcause'}, {'id': 'impact:arbitrary code execution', 'keyphrase': 'arbitrary code execution', 'type': 'impact'}, {'id': 'attacker:high privileged attacker with local access', 'keyphrase': 'high privileged attacker with local access', 'type': 'attacker'}, {'id': 'product:Dell Client Platform BIOS', 'keyphrase': 'Dell Client Platform BIOS', 'type': 'product'}, {'id': 'component:externally developed component', 'keyphrase': 'externally developed component', 'type': 'component'}]}, 'similarity': np.float64(206.87393001905417)}, {'metadata': {'doc_id': '287', 'name': 'Improper Authentication', 'source': 'sparse', 'original_content': 'When an actor claims to have a given identity, the product does not prove or insufficiently proves that the claim is correct.', 'keyphrase_sources': [{'id': 'rootcause:Improper Input Validation', 'keyphrase': 'Improper Input Validation', 'type': 'rootcause'}, {'id': 'rootcause:Input Validation vulnerability', 'keyphrase': 'Input Validation vulnerability', 'type': 'rootcause'}, {'id': 'product:Dell Client Platform BIOS', 'keyphrase': 'Dell Client Platform BIOS', 'type': 'product'}]}, 'similarity': np.float64(189.34261351323062)}, {'metadata': {'doc_id': '1285', 'name': 'Improper Validation of Specified Index, Position, or Offset in Input', 'source': 'sparse', 'original_content': 'The product receives input that is expected to specify an index, position, or offset into an indexable resource such as a buffer or file, but it does not validate or incorrectly validates that the specified index/position/offset has the required properties.', 'keyphrase_sources': [{'id': 'rootcause:Improper Input Validation', 'keyphrase': 'Improper Input Validation', 'type': 'rootcause'}]}, 'similarity': np.float64(186.5087490529439)}, {'metadata': {'doc_id': '1284', 'name': 'Improper Validation of Specified Quantity in Input', 'source': 'sparse', 'original_content': 'The product receives input that is expected to specify a quantity (such as size or length), but it does not validate or incorrectly validates that the quantity has the required properties.', 'keyphrase_sources': [{'id': 'rootcause:Improper Input Validation', 'keyphrase': 'Improper Input Validation', 'type': 'rootcause'}, {'id': 'rootcause:Input Validation vulnerability', 'keyphrase': 'Input Validation vulnerability', 'type': 'rootcause'}]}, 'similarity': np.float64(186.28747932745122)}, {'metadata': {'doc_id': '125', 'name': 'Out-of-bounds Read', 'source': 'sparse', 'original_content': 'The product reads data past the end, or before the beginning, of the intended buffer.', 'keyphrase_sources': [{'id': 'rootcause:Input Validation vulnerability', 'keyphrase': 'Input Validation vulnerability', 'type': 'rootcause'}, {'id': 'impact:arbitrary code execution', 'keyphrase': 'arbitrary code execution', 'type': 'impact'}, {'id': 'product:Dell Client Platform BIOS', 'keyphrase': 'Dell Client Platform BIOS', 'type': 'product'}, {'id': 'component:externally developed component', 'keyphrase': 'externally developed component', 'type': 'component'}]}, 'similarity': np.float64(183.89403753172837)}, {'metadata': {'doc_id': '250', 'name': 'Execution with Unnecessary Privileges', 'source': 'sparse', 'original_content': 'The product performs an operation at a privilege level that is higher than the minimum level required, which creates new weaknesses or amplifies the consequences of other weaknesses.', 'keyphrase_sources': [{'id': 'attacker:high privileged attacker with local access', 'keyphrase': 'high privileged attacker with local access', 'type': 'attacker'}]}, 'similarity': np.float64(86.06715036389008)}, {'metadata': {'doc_id': '269', 'name': 'Improper Privilege Management', 'source': 'sparse', 'original_content': 'The product does not properly assign, modify, track, or check privileges for an actor, creating an unintended sphere of control for that actor.', 'keyphrase_sources': [{'id': 'attacker:high privileged attacker with local access', 'keyphrase': 'high privileged attacker with local access', 'type': 'attacker'}]}, 'similarity': np.float64(85.44257267681722)}, {'metadata': {'doc_id': '200', 'name': 'Exposure of Sensitive Information to an Unauthorized Actor', 'source': 'sparse', 'original_content': 'The product exposes sensitive information to an actor that is not explicitly authorized to have access to that information.', 'keyphrase_sources': [{'id': 'product:Dell Client Platform BIOS', 'keyphrase': 'Dell Client Platform BIOS', 'type': 'product'}]}, 'similarity': np.float64(67.97535975390468)}, {'metadata': {'doc_id': '823', 'name': 'Use of Out-of-range Pointer Offset', 'source': 'sparse', 'original_content': 'The product performs pointer arithmetic on a valid pointer, but it uses an offset that can point outside of the intended range of valid memory locations for the resulting pointer.', 'keyphrase_sources': [{'id': 'component:externally developed component', 'keyphrase': 'externally developed component', 'type': 'component'}]}, 'similarity': np.float64(62.13582525305223)}, {'metadata': {'doc_id': '94', 'name': \"Improper Control of Generation of Code ('Code Injection')\", 'source': 'sparse', 'original_content': 'The product constructs all or part of a code segment using externally-influenced input from an upstream component, but it does not neutralize or incorrectly neutralizes special elements that could modify the syntax or behavior of the intended code segment.', 'keyphrase_sources': [{'id': 'impact:arbitrary code execution', 'keyphrase': 'arbitrary code execution', 'type': 'impact'}]}, 'similarity': np.float64(61.352250720379374)}, {'metadata': {'doc_id': '732', 'name': 'Incorrect Permission Assignment for Critical Resource', 'source': 'sparse', 'original_content': 'The product specifies permissions for a security-critical resource in a way that allows that resource to be read or modified by unintended actors.', 'keyphrase_sources': [{'id': 'impact:arbitrary code execution', 'keyphrase': 'arbitrary code execution', 'type': 'impact'}, {'id': 'attacker:high privileged attacker with local access', 'keyphrase': 'high privileged attacker with local access', 'type': 'attacker'}, {'id': 'component:externally developed component', 'keyphrase': 'externally developed component', 'type': 'component'}]}, 'similarity': np.float64(61.21653059452898)}], identified_cwes={'analyzer': [], 'critic_additional': []})",
  "retrieval_results": {
    "has_multiple_keyphrases": true,
    "keyphrase_cwe_sets": {
      "rootcause:Improper Input Validation": {
        "keyphrase": "Improper Input Validation",
        "type": "rootcause",
        "cwes": [
          {
            "metadata": {
              "doc_id": "20",
              "name": "Improper Input Validation",
              "source": "sparse",
              "original_content": "The product receives input or data, but it does\n        not validate or incorrectly validates that the input has the\n        properties that are required to process the data safely and\n        correctly.",
              "keyphrase_sources": [
                {
                  "id": "rootcause:Improper Input Validation",
                  "keyphrase": "Improper Input Validation",
                  "type": "rootcause"
                },
                {
                  "id": "rootcause:Input Validation vulnerability",
                  "keyphrase": "Input Validation vulnerability",
                  "type": "rootcause"
                },
                {
                  "id": "impact:arbitrary code execution",
                  "keyphrase": "arbitrary code execution",
                  "type": "impact"
                },
                {
                  "id": "attacker:high privileged attacker with local access",
                  "keyphrase": "high privileged attacker with local access",
                  "type": "attacker"
                },
                {
                  "id": "product:Dell Client Platform BIOS",
                  "keyphrase": "Dell Client Platform BIOS",
                  "type": "product"
                },
                {
                  "id": "component:externally developed component",
                  "keyphrase": "externally developed component",
                  "type": "component"
                }
              ]
            },
            "similarity": 223.37216696088583
          },
          {
            "metadata": {
              "doc_id": "119",
              "name": "Improper Restriction of Operations within the Bounds of a Memory Buffer",
              "source": "sparse",
              "original_content": "The product performs operations on a memory buffer, but it reads from or writes to a memory location outside the buffer's intended boundary. This may result in read or write operations on unexpected memory locations that could be linked to other variables, data structures, or internal program data.",
              "keyphrase_sources": [
                {
                  "id": "rootcause:Improper Input Validation",
                  "keyphrase": "Improper Input Validation",
                  "type": "rootcause"
                },
                {
                  "id": "rootcause:Input Validation vulnerability",
                  "keyphrase": "Input Validation vulnerability",
                  "type": "rootcause"
                },
                {
                  "id": "impact:arbitrary code execution",
                  "keyphrase": "arbitrary code execution",
                  "type": "impact"
                },
                {
                  "id": "attacker:high privileged attacker with local access",
                  "keyphrase": "high privileged attacker with local access",
                  "type": "attacker"
                },
                {
                  "id": "product:Dell Client Platform BIOS",
                  "keyphrase": "Dell Client Platform BIOS",
                  "type": "product"
                },
                {
                  "id": "component:externally developed component",
                  "keyphrase": "externally developed component",
                  "type": "component"
                }
              ]
            },
            "similarity": 206.87393001905417
          },
          {
            "metadata": {
              "doc_id": "287",
              "name": "Improper Authentication",
              "source": "sparse",
              "original_content": "When an actor claims to have a given identity, the product does not prove or insufficiently proves that the claim is correct.",
              "keyphrase_sources": [
                {
                  "id": "rootcause:Improper Input Validation",
                  "keyphrase": "Improper Input Validation",
                  "type": "rootcause"
                },
                {
                  "id": "rootcause:Input Validation vulnerability",
                  "keyphrase": "Input Validation vulnerability",
                  "type": "rootcause"
                },
                {
                  "id": "product:Dell Client Platform BIOS",
                  "keyphrase": "Dell Client Platform BIOS",
                  "type": "product"
                }
              ]
            },
            "similarity": 189.34261351323062
          },
          {
            "metadata": {
              "doc_id": "1285",
              "name": "Improper Validation of Specified Index, Position, or Offset in Input",
              "source": "sparse",
              "original_content": "The product receives input that is expected to specify an index, position, or offset into an indexable resource such as a buffer or file, but it does not validate or incorrectly validates that the specified index/position/offset has the required properties.",
              "keyphrase_sources": [
                {
                  "id": "rootcause:Improper Input Validation",
                  "keyphrase": "Improper Input Validation",
                  "type": "rootcause"
                }
              ]
            },
            "similarity": 186.5087490529439
          },
          {
            "metadata": {
              "doc_id": "1284",
              "name": "Improper Validation of Specified Quantity in Input",
              "source": "sparse",
              "original_content": "The product receives input that is expected to specify a quantity (such as size or length), but it does not validate or incorrectly validates that the quantity has the required properties.",
              "keyphrase_sources": [
                {
                  "id": "rootcause:Improper Input Validation",
                  "keyphrase": "Improper Input Validation",
                  "type": "rootcause"
                },
                {
                  "id": "rootcause:Input Validation vulnerability",
                  "keyphrase": "Input Validation vulnerability",
                  "type": "rootcause"
                }
              ]
            },
            "similarity": 186.28747932745122
          }
        ]
      },
      "rootcause:Input Validation vulnerability": {
        "keyphrase": "Input Validation vulnerability",
        "type": "rootcause",
        "cwes": [
          {
            "metadata": {
              "doc_id": "20",
              "name": "Improper Input Validation",
              "source": "sparse",
              "original_content": "The product receives input or data, but it does\n        not validate or incorrectly validates that the input has the\n        properties that are required to process the data safely and\n        correctly."
            },
            "similarity": 218.6191884434514
          },
          {
            "metadata": {
              "doc_id": "119",
              "name": "Improper Restriction of Operations within the Bounds of a Memory Buffer",
              "source": "sparse",
              "original_content": "The product performs operations on a memory buffer, but it reads from or writes to a memory location outside the buffer's intended boundary. This may result in read or write operations on unexpected memory locations that could be linked to other variables, data structures, or internal program data."
            },
            "similarity": 202.40937868518802
          },
          {
            "metadata": {
              "doc_id": "287",
              "name": "Improper Authentication",
              "source": "sparse",
              "original_content": "When an actor claims to have a given identity, the product does not prove or insufficiently proves that the claim is correct."
            },
            "similarity": 184.6735398523085
          },
          {
            "metadata": {
              "doc_id": "125",
              "name": "Out-of-bounds Read",
              "source": "sparse",
              "original_content": "The product reads data past the end, or before the beginning, of the intended buffer.",
              "keyphrase_sources": [
                {
                  "id": "rootcause:Input Validation vulnerability",
                  "keyphrase": "Input Validation vulnerability",
                  "type": "rootcause"
                },
                {
                  "id": "impact:arbitrary code execution",
                  "keyphrase": "arbitrary code execution",
                  "type": "impact"
                },
                {
                  "id": "product:Dell Client Platform BIOS",
                  "keyphrase": "Dell Client Platform BIOS",
                  "type": "product"
                },
                {
                  "id": "component:externally developed component",
                  "keyphrase": "externally developed component",
                  "type": "component"
                }
              ]
            },
            "similarity": 183.89403753172837
          },
          {
            "metadata": {
              "doc_id": "1284",
              "name": "Improper Validation of Specified Quantity in Input",
              "source": "sparse",
              "original_content": "The product receives input that is expected to specify a quantity (such as size or length), but it does not validate or incorrectly validates that the quantity has the required properties."
            },
            "similarity": 183.23256946318145
          }
        ]
      },
      "impact:arbitrary code execution": {
        "keyphrase": "arbitrary code execution",
        "type": "impact",
        "cwes": [
          {
            "metadata": {
              "doc_id": "119",
              "name": "Improper Restriction of Operations within the Bounds of a Memory Buffer",
              "source": "sparse",
              "original_content": "The product performs operations on a memory buffer, but it reads from or writes to a memory location outside the buffer's intended boundary. This may result in read or write operations on unexpected memory locations that could be linked to other variables, data structures, or internal program data."
            },
            "similarity": 72.77912729742256
          },
          {
            "metadata": {
              "doc_id": "20",
              "name": "Improper Input Validation",
              "source": "sparse",
              "original_content": "The product receives input or data, but it does\n        not validate or incorrectly validates that the input has the\n        properties that are required to process the data safely and\n        correctly."
            },
            "similarity": 69.01933516002956
          },
          {
            "metadata": {
              "doc_id": "125",
              "name": "Out-of-bounds Read",
              "source": "sparse",
              "original_content": "The product reads data past the end, or before the beginning, of the intended buffer."
            },
            "similarity": 62.83046563168139
          },
          {
            "metadata": {
              "doc_id": "94",
              "name": "Improper Control of Generation of Code ('Code Injection')",
              "source": "sparse",
              "original_content": "The product constructs all or part of a code segment using externally-influenced input from an upstream component, but it does not neutralize or incorrectly neutralizes special elements that could modify the syntax or behavior of the intended code segment.",
              "keyphrase_sources": [
                {
                  "id": "impact:arbitrary code execution",
                  "keyphrase": "arbitrary code execution",
                  "type": "impact"
                }
              ]
            },
            "similarity": 61.352250720379374
          },
          {
            "metadata": {
              "doc_id": "732",
              "name": "Incorrect Permission Assignment for Critical Resource",
              "source": "sparse",
              "original_content": "The product specifies permissions for a security-critical resource in a way that allows that resource to be read or modified by unintended actors.",
              "keyphrase_sources": [
                {
                  "id": "impact:arbitrary code execution",
                  "keyphrase": "arbitrary code execution",
                  "type": "impact"
                },
                {
                  "id": "attacker:high privileged attacker with local access",
                  "keyphrase": "high privileged attacker with local access",
                  "type": "attacker"
                },
                {
                  "id": "component:externally developed component",
                  "keyphrase": "externally developed component",
                  "type": "component"
                }
              ]
            },
            "similarity": 61.21653059452898
          }
        ]
      },
      "attacker:high privileged attacker with local access": {
        "keyphrase": "high privileged attacker with local access",
        "type": "attacker",
        "cwes": [
          {
            "metadata": {
              "doc_id": "119",
              "name": "Improper Restriction of Operations within the Bounds of a Memory Buffer",
              "source": "sparse",
              "original_content": "The product performs operations on a memory buffer, but it reads from or writes to a memory location outside the buffer's intended boundary. This may result in read or write operations on unexpected memory locations that could be linked to other variables, data structures, or internal program data."
            },
            "similarity": 98.36644965111917
          },
          {
            "metadata": {
              "doc_id": "20",
              "name": "Improper Input Validation",
              "source": "sparse",
              "original_content": "The product receives input or data, but it does\n        not validate or incorrectly validates that the input has the\n        properties that are required to process the data safely and\n        correctly."
            },
            "similarity": 88.11629887321038
          },
          {
            "metadata": {
              "doc_id": "732",
              "name": "Incorrect Permission Assignment for Critical Resource",
              "source": "sparse",
              "original_content": "The product specifies permissions for a security-critical resource in a way that allows that resource to be read or modified by unintended actors."
            },
            "similarity": 87.99845066052207
          },
          {
            "metadata": {
              "doc_id": "250",
              "name": "Execution with Unnecessary Privileges",
              "source": "sparse",
              "original_content": "The product performs an operation at a privilege level that is higher than the minimum level required, which creates new weaknesses or amplifies the consequences of other weaknesses.",
              "keyphrase_sources": [
                {
                  "id": "attacker:high privileged attacker with local access",
                  "keyphrase": "high privileged attacker with local access",
                  "type": "attacker"
                }
              ]
            },
            "similarity": 86.06715036389008
          },
          {
            "metadata": {
              "doc_id": "269",
              "name": "Improper Privilege Management",
              "source": "sparse",
              "original_content": "The product does not properly assign, modify, track, or check privileges for an actor, creating an unintended sphere of control for that actor.",
              "keyphrase_sources": [
                {
                  "id": "attacker:high privileged attacker with local access",
                  "keyphrase": "high privileged attacker with local access",
                  "type": "attacker"
                }
              ]
            },
            "similarity": 85.44257267681722
          }
        ]
      },
      "product:Dell Client Platform BIOS": {
        "keyphrase": "Dell Client Platform BIOS",
        "type": "product",
        "cwes": [
          {
            "metadata": {
              "doc_id": "119",
              "name": "Improper Restriction of Operations within the Bounds of a Memory Buffer",
              "source": "sparse",
              "original_content": "The product performs operations on a memory buffer, but it reads from or writes to a memory location outside the buffer's intended boundary. This may result in read or write operations on unexpected memory locations that could be linked to other variables, data structures, or internal program data."
            },
            "similarity": 89.18250487692033
          },
          {
            "metadata": {
              "doc_id": "20",
              "name": "Improper Input Validation",
              "source": "sparse",
              "original_content": "The product receives input or data, but it does\n        not validate or incorrectly validates that the input has the\n        properties that are required to process the data safely and\n        correctly."
            },
            "similarity": 74.72640092154741
          },
          {
            "metadata": {
              "doc_id": "125",
              "name": "Out-of-bounds Read",
              "source": "sparse",
              "original_content": "The product reads data past the end, or before the beginning, of the intended buffer."
            },
            "similarity": 70.11149740978887
          },
          {
            "metadata": {
              "doc_id": "287",
              "name": "Improper Authentication",
              "source": "sparse",
              "original_content": "When an actor claims to have a given identity, the product does not prove or insufficiently proves that the claim is correct."
            },
            "similarity": 69.48008953786866
          },
          {
            "metadata": {
              "doc_id": "200",
              "name": "Exposure of Sensitive Information to an Unauthorized Actor",
              "source": "sparse",
              "original_content": "The product exposes sensitive information to an actor that is not explicitly authorized to have access to that information.",
              "keyphrase_sources": [
                {
                  "id": "product:Dell Client Platform BIOS",
                  "keyphrase": "Dell Client Platform BIOS",
                  "type": "product"
                }
              ]
            },
            "similarity": 67.97535975390468
          }
        ]
      },
      "component:externally developed component": {
        "keyphrase": "externally developed component",
        "type": "component",
        "cwes": [
          {
            "metadata": {
              "doc_id": "119",
              "name": "Improper Restriction of Operations within the Bounds of a Memory Buffer",
              "source": "sparse",
              "original_content": "The product performs operations on a memory buffer, but it reads from or writes to a memory location outside the buffer's intended boundary. This may result in read or write operations on unexpected memory locations that could be linked to other variables, data structures, or internal program data."
            },
            "similarity": 65.20790092274787
          },
          {
            "metadata": {
              "doc_id": "20",
              "name": "Improper Input Validation",
              "source": "sparse",
              "original_content": "The product receives input or data, but it does\n        not validate or incorrectly validates that the input has the\n        properties that are required to process the data safely and\n        correctly."
            },
            "similarity": 62.78999163039781
          },
          {
            "metadata": {
              "doc_id": "823",
              "name": "Use of Out-of-range Pointer Offset",
              "source": "sparse",
              "original_content": "The product performs pointer arithmetic on a valid pointer, but it uses an offset that can point outside of the intended range of valid memory locations for the resulting pointer.",
              "keyphrase_sources": [
                {
                  "id": "component:externally developed component",
                  "keyphrase": "externally developed component",
                  "type": "component"
                }
              ]
            },
            "similarity": 62.13582525305223
          },
          {
            "metadata": {
              "doc_id": "125",
              "name": "Out-of-bounds Read",
              "source": "sparse",
              "original_content": "The product reads data past the end, or before the beginning, of the intended buffer."
            },
            "similarity": 60.42877028596227
          },
          {
            "metadata": {
              "doc_id": "732",
              "name": "Incorrect Permission Assignment for Critical Resource",
              "source": "sparse",
              "original_content": "The product specifies permissions for a security-critical resource in a way that allows that resource to be read or modified by unintended actors."
            },
            "similarity": 59.440585012921275
          }
        ]
      }
    },
    "keyphrase_mapping": {
      "20": [
        {
          "id": "rootcause:Improper Input Validation",
          "keyphrase": "Improper Input Validation",
          "type": "rootcause"
        },
        {
          "id": "rootcause:Input Validation vulnerability",
          "keyphrase": "Input Validation vulnerability",
          "type": "rootcause"
        },
        {
          "id": "impact:arbitrary code execution",
          "keyphrase": "arbitrary code execution",
          "type": "impact"
        },
        {
          "id": "attacker:high privileged attacker with local access",
          "keyphrase": "high privileged attacker with local access",
          "type": "attacker"
        },
        {
          "id": "product:Dell Client Platform BIOS",
          "keyphrase": "Dell Client Platform BIOS",
          "type": "product"
        },
        {
          "id": "component:externally developed component",
          "keyphrase": "externally developed component",
          "type": "component"
        }
      ],
      "119": [
        {
          "id": "rootcause:Improper Input Validation",
          "keyphrase": "Improper Input Validation",
          "type": "rootcause"
        },
        {
          "id": "rootcause:Input Validation vulnerability",
          "keyphrase": "Input Validation vulnerability",
          "type": "rootcause"
        },
        {
          "id": "impact:arbitrary code execution",
          "keyphrase": "arbitrary code execution",
          "type": "impact"
        },
        {
          "id": "attacker:high privileged attacker with local access",
          "keyphrase": "high privileged attacker with local access",
          "type": "attacker"
        },
        {
          "id": "product:Dell Client Platform BIOS",
          "keyphrase": "Dell Client Platform BIOS",
          "type": "product"
        },
        {
          "id": "component:externally developed component",
          "keyphrase": "externally developed component",
          "type": "component"
        }
      ],
      "287": [
        {
          "id": "rootcause:Improper Input Validation",
          "keyphrase": "Improper Input Validation",
          "type": "rootcause"
        },
        {
          "id": "rootcause:Input Validation vulnerability",
          "keyphrase": "Input Validation vulnerability",
          "type": "rootcause"
        },
        {
          "id": "product:Dell Client Platform BIOS",
          "keyphrase": "Dell Client Platform BIOS",
          "type": "product"
        }
      ],
      "1285": [
        {
          "id": "rootcause:Improper Input Validation",
          "keyphrase": "Improper Input Validation",
          "type": "rootcause"
        }
      ],
      "1284": [
        {
          "id": "rootcause:Improper Input Validation",
          "keyphrase": "Improper Input Validation",
          "type": "rootcause"
        },
        {
          "id": "rootcause:Input Validation vulnerability",
          "keyphrase": "Input Validation vulnerability",
          "type": "rootcause"
        }
      ],
      "125": [
        {
          "id": "rootcause:Input Validation vulnerability",
          "keyphrase": "Input Validation vulnerability",
          "type": "rootcause"
        },
        {
          "id": "impact:arbitrary code execution",
          "keyphrase": "arbitrary code execution",
          "type": "impact"
        },
        {
          "id": "product:Dell Client Platform BIOS",
          "keyphrase": "Dell Client Platform BIOS",
          "type": "product"
        },
        {
          "id": "component:externally developed component",
          "keyphrase": "externally developed component",
          "type": "component"
        }
      ],
      "94": [
        {
          "id": "impact:arbitrary code execution",
          "keyphrase": "arbitrary code execution",
          "type": "impact"
        }
      ],
      "732": [
        {
          "id": "impact:arbitrary code execution",
          "keyphrase": "arbitrary code execution",
          "type": "impact"
        },
        {
          "id": "attacker:high privileged attacker with local access",
          "keyphrase": "high privileged attacker with local access",
          "type": "attacker"
        },
        {
          "id": "component:externally developed component",
          "keyphrase": "externally developed component",
          "type": "component"
        }
      ],
      "250": [
        {
          "id": "attacker:high privileged attacker with local access",
          "keyphrase": "high privileged attacker with local access",
          "type": "attacker"
        }
      ],
      "269": [
        {
          "id": "attacker:high privileged attacker with local access",
          "keyphrase": "high privileged attacker with local access",
          "type": "attacker"
        }
      ],
      "200": [
        {
          "id": "product:Dell Client Platform BIOS",
          "keyphrase": "Dell Client Platform BIOS",
          "type": "product"
        }
      ],
      "823": [
        {
          "id": "component:externally developed component",
          "keyphrase": "externally developed component",
          "type": "component"
        }
      ]
    },
    "relevant_cwes": [
      {
        "metadata": {
          "doc_id": "20",
          "name": "Improper Input Validation",
          "source": "sparse",
          "original_content": "The product receives input or data, but it does\n        not validate or incorrectly validates that the input has the\n        properties that are required to process the data safely and\n        correctly.",
          "keyphrase_sources": [
            {
              "id": "rootcause:Improper Input Validation",
              "keyphrase": "Improper Input Validation",
              "type": "rootcause"
            },
            {
              "id": "rootcause:Input Validation vulnerability",
              "keyphrase": "Input Validation vulnerability",
              "type": "rootcause"
            },
            {
              "id": "impact:arbitrary code execution",
              "keyphrase": "arbitrary code execution",
              "type": "impact"
            },
            {
              "id": "attacker:high privileged attacker with local access",
              "keyphrase": "high privileged attacker with local access",
              "type": "attacker"
            },
            {
              "id": "product:Dell Client Platform BIOS",
              "keyphrase": "Dell Client Platform BIOS",
              "type": "product"
            },
            {
              "id": "component:externally developed component",
              "keyphrase": "externally developed component",
              "type": "component"
            }
          ]
        },
        "similarity": 223.37216696088583
      },
      {
        "metadata": {
          "doc_id": "119",
          "name": "Improper Restriction of Operations within the Bounds of a Memory Buffer",
          "source": "sparse",
          "original_content": "The product performs operations on a memory buffer, but it reads from or writes to a memory location outside the buffer's intended boundary. This may result in read or write operations on unexpected memory locations that could be linked to other variables, data structures, or internal program data.",
          "keyphrase_sources": [
            {
              "id": "rootcause:Improper Input Validation",
              "keyphrase": "Improper Input Validation",
              "type": "rootcause"
            },
            {
              "id": "rootcause:Input Validation vulnerability",
              "keyphrase": "Input Validation vulnerability",
              "type": "rootcause"
            },
            {
              "id": "impact:arbitrary code execution",
              "keyphrase": "arbitrary code execution",
              "type": "impact"
            },
            {
              "id": "attacker:high privileged attacker with local access",
              "keyphrase": "high privileged attacker with local access",
              "type": "attacker"
            },
            {
              "id": "product:Dell Client Platform BIOS",
              "keyphrase": "Dell Client Platform BIOS",
              "type": "product"
            },
            {
              "id": "component:externally developed component",
              "keyphrase": "externally developed component",
              "type": "component"
            }
          ]
        },
        "similarity": 206.87393001905417
      },
      {
        "metadata": {
          "doc_id": "287",
          "name": "Improper Authentication",
          "source": "sparse",
          "original_content": "When an actor claims to have a given identity, the product does not prove or insufficiently proves that the claim is correct.",
          "keyphrase_sources": [
            {
              "id": "rootcause:Improper Input Validation",
              "keyphrase": "Improper Input Validation",
              "type": "rootcause"
            },
            {
              "id": "rootcause:Input Validation vulnerability",
              "keyphrase": "Input Validation vulnerability",
              "type": "rootcause"
            },
            {
              "id": "product:Dell Client Platform BIOS",
              "keyphrase": "Dell Client Platform BIOS",
              "type": "product"
            }
          ]
        },
        "similarity": 189.34261351323062
      },
      {
        "metadata": {
          "doc_id": "1285",
          "name": "Improper Validation of Specified Index, Position, or Offset in Input",
          "source": "sparse",
          "original_content": "The product receives input that is expected to specify an index, position, or offset into an indexable resource such as a buffer or file, but it does not validate or incorrectly validates that the specified index/position/offset has the required properties.",
          "keyphrase_sources": [
            {
              "id": "rootcause:Improper Input Validation",
              "keyphrase": "Improper Input Validation",
              "type": "rootcause"
            }
          ]
        },
        "similarity": 186.5087490529439
      },
      {
        "metadata": {
          "doc_id": "1284",
          "name": "Improper Validation of Specified Quantity in Input",
          "source": "sparse",
          "original_content": "The product receives input that is expected to specify a quantity (such as size or length), but it does not validate or incorrectly validates that the quantity has the required properties.",
          "keyphrase_sources": [
            {
              "id": "rootcause:Improper Input Validation",
              "keyphrase": "Improper Input Validation",
              "type": "rootcause"
            },
            {
              "id": "rootcause:Input Validation vulnerability",
              "keyphrase": "Input Validation vulnerability",
              "type": "rootcause"
            }
          ]
        },
        "similarity": 186.28747932745122
      },
      {
        "metadata": {
          "doc_id": "125",
          "name": "Out-of-bounds Read",
          "source": "sparse",
          "original_content": "The product reads data past the end, or before the beginning, of the intended buffer.",
          "keyphrase_sources": [
            {
              "id": "rootcause:Input Validation vulnerability",
              "keyphrase": "Input Validation vulnerability",
              "type": "rootcause"
            },
            {
              "id": "impact:arbitrary code execution",
              "keyphrase": "arbitrary code execution",
              "type": "impact"
            },
            {
              "id": "product:Dell Client Platform BIOS",
              "keyphrase": "Dell Client Platform BIOS",
              "type": "product"
            },
            {
              "id": "component:externally developed component",
              "keyphrase": "externally developed component",
              "type": "component"
            }
          ]
        },
        "similarity": 183.89403753172837
      },
      {
        "metadata": {
          "doc_id": "250",
          "name": "Execution with Unnecessary Privileges",
          "source": "sparse",
          "original_content": "The product performs an operation at a privilege level that is higher than the minimum level required, which creates new weaknesses or amplifies the consequences of other weaknesses.",
          "keyphrase_sources": [
            {
              "id": "attacker:high privileged attacker with local access",
              "keyphrase": "high privileged attacker with local access",
              "type": "attacker"
            }
          ]
        },
        "similarity": 86.06715036389008
      },
      {
        "metadata": {
          "doc_id": "269",
          "name": "Improper Privilege Management",
          "source": "sparse",
          "original_content": "The product does not properly assign, modify, track, or check privileges for an actor, creating an unintended sphere of control for that actor.",
          "keyphrase_sources": [
            {
              "id": "attacker:high privileged attacker with local access",
              "keyphrase": "high privileged attacker with local access",
              "type": "attacker"
            }
          ]
        },
        "similarity": 85.44257267681722
      },
      {
        "metadata": {
          "doc_id": "200",
          "name": "Exposure of Sensitive Information to an Unauthorized Actor",
          "source": "sparse",
          "original_content": "The product exposes sensitive information to an actor that is not explicitly authorized to have access to that information.",
          "keyphrase_sources": [
            {
              "id": "product:Dell Client Platform BIOS",
              "keyphrase": "Dell Client Platform BIOS",
              "type": "product"
            }
          ]
        },
        "similarity": 67.97535975390468
      },
      {
        "metadata": {
          "doc_id": "823",
          "name": "Use of Out-of-range Pointer Offset",
          "source": "sparse",
          "original_content": "The product performs pointer arithmetic on a valid pointer, but it uses an offset that can point outside of the intended range of valid memory locations for the resulting pointer.",
          "keyphrase_sources": [
            {
              "id": "component:externally developed component",
              "keyphrase": "externally developed component",
              "type": "component"
            }
          ]
        },
        "similarity": 62.13582525305223
      },
      {
        "metadata": {
          "doc_id": "94",
          "name": "Improper Control of Generation of Code ('Code Injection')",
          "source": "sparse",
          "original_content": "The product constructs all or part of a code segment using externally-influenced input from an upstream component, but it does not neutralize or incorrectly neutralizes special elements that could modify the syntax or behavior of the intended code segment.",
          "keyphrase_sources": [
            {
              "id": "impact:arbitrary code execution",
              "keyphrase": "arbitrary code execution",
              "type": "impact"
            }
          ]
        },
        "similarity": 61.352250720379374
      },
      {
        "metadata": {
          "doc_id": "732",
          "name": "Incorrect Permission Assignment for Critical Resource",
          "source": "sparse",
          "original_content": "The product specifies permissions for a security-critical resource in a way that allows that resource to be read or modified by unintended actors.",
          "keyphrase_sources": [
            {
              "id": "impact:arbitrary code execution",
              "keyphrase": "arbitrary code execution",
              "type": "impact"
            },
            {
              "id": "attacker:high privileged attacker with local access",
              "keyphrase": "high privileged attacker with local access",
              "type": "attacker"
            },
            {
              "id": "component:externally developed component",
              "keyphrase": "externally developed component",
              "type": "component"
            }
          ]
        },
        "similarity": 61.21653059452898
      }
    ],
    "enhanced_query": "# Vulnerability Description\n\n    Dell Client Platform BIOS contains an **Improper Input Validation** vulnerability in an externally developed component. A high privileged attacker with local access could potentially exploit this vulnerability, leading to arbitrary code execution.\n\n    # Keyphrase-Specific CWE Analysis\n    This vulnerability contains multiple keyphrases that may map to different CWEs. \n    Please analyze each keyphrase separately and determine the most appropriate CWE(s) for each.\n\n    ## ROOTCAUSE: 'Improper Input Validation'\n\nRelevant CWEs for this ROOTCAUSE:\n\n### 1. CWE-20: Improper Input Validation (Score: 223.37)\n\nThe product receives input or data, but it does\n        not validate or incorrectly validates that the input has the\n        properties that are required to process the data safely and\n        correctly....\n\n### 2. CWE-119: Improper Restriction of Operations within the Bounds of a Memory Buffer (Score: 206.87)\n\nThe product performs operations on a memory buffer, but it reads from or writes to a memory location outside the buffer's intended boundary. This may result in read or write operations on unexpected memory locations that could be linked to other variables, data structures, or internal program data....\n\n### 3. CWE-287: Improper Authentication (Score: 189.34)\n\nWhen an actor claims to have a given identity, the product does not prove or insufficiently proves that the claim is correct....\n\n### 4. CWE-1285: Improper Validation of Specified Index, Position, or Offset in Input (Score: 186.51)\n\nThe product receives input that is expected to specify an index, position, or offset into an indexable resource such as a buffer or file, but it does not validate or incorrectly validates that the specified index/position/offset has the required properties....\n\n### 5. CWE-1284: Improper Validation of Specified Quantity in Input (Score: 186.29)\n\nThe product receives input that is expected to specify a quantity (such as size or length), but it does not validate or incorrectly validates that the quantity has the required properties....\n\n## ROOTCAUSE: 'Input Validation vulnerability'\n\nRelevant CWEs for this ROOTCAUSE:\n\n### 1. CWE-20: Improper Input Validation (Score: 223.37)\n\nThe product receives input or data, but it does\n        not validate or incorrectly validates that the input has the\n        properties that are required to process the data safely and\n        correctly....\n\n### 2. CWE-119: Improper Restriction of Operations within the Bounds of a Memory Buffer (Score: 206.87)\n\nThe product performs operations on a memory buffer, but it reads from or writes to a memory location outside the buffer's intended boundary. This may result in read or write operations on unexpected memory locations that could be linked to other variables, data structures, or internal program data....\n\n### 3. CWE-287: Improper Authentication (Score: 189.34)\n\nWhen an actor claims to have a given identity, the product does not prove or insufficiently proves that the claim is correct....\n\n### 4. CWE-1284: Improper Validation of Specified Quantity in Input (Score: 186.29)\n\nThe product receives input that is expected to specify a quantity (such as size or length), but it does not validate or incorrectly validates that the quantity has the required properties....\n\n### 5. CWE-125: Out-of-bounds Read (Score: 183.89)\n\nThe product reads data past the end, or before the beginning, of the intended buffer....\n\n## IMPACT: 'arbitrary code execution'\n\nRelevant CWEs for this IMPACT:\n\n### 1. CWE-20: Improper Input Validation (Score: 223.37)\n\nThe product receives input or data, but it does\n        not validate or incorrectly validates that the input has the\n        properties that are required to process the data safely and\n        correctly....\n\n### 2. CWE-119: Improper Restriction of Operations within the Bounds of a Memory Buffer (Score: 206.87)\n\nThe product performs operations on a memory buffer, but it reads from or writes to a memory location outside the buffer's intended boundary. This may result in read or write operations on unexpected memory locations that could be linked to other variables, data structures, or internal program data....\n\n### 3. CWE-125: Out-of-bounds Read (Score: 183.89)\n\nThe product reads data past the end, or before the beginning, of the intended buffer....\n\n### 4. CWE-94: Improper Control of Generation of Code ('Code Injection') (Score: 61.35)\n\nThe product constructs all or part of a code segment using externally-influenced input from an upstream component, but it does not neutralize or incorrectly neutralizes special elements that could modify the syntax or behavior of the intended code segment....\n\n### 5. CWE-732: Incorrect Permission Assignment for Critical Resource (Score: 61.22)\n\nThe product specifies permissions for a security-critical resource in a way that allows that resource to be read or modified by unintended actors....\n\n## ATTACKER: 'high privileged attacker with local access'\n\nRelevant CWEs for this ATTACKER:\n\n### 1. CWE-20: Improper Input Validation (Score: 223.37)\n\nThe product receives input or data, but it does\n        not validate or incorrectly validates that the input has the\n        properties that are required to process the data safely and\n        correctly....\n\n### 2. CWE-119: Improper Restriction of Operations within the Bounds of a Memory Buffer (Score: 206.87)\n\nThe product performs operations on a memory buffer, but it reads from or writes to a memory location outside the buffer's intended boundary. This may result in read or write operations on unexpected memory locations that could be linked to other variables, data structures, or internal program data....\n\n### 3. CWE-250: Execution with Unnecessary Privileges (Score: 86.07)\n\nThe product performs an operation at a privilege level that is higher than the minimum level required, which creates new weaknesses or amplifies the consequences of other weaknesses....\n\n### 4. CWE-269: Improper Privilege Management (Score: 85.44)\n\nThe product does not properly assign, modify, track, or check privileges for an actor, creating an unintended sphere of control for that actor....\n\n### 5. CWE-732: Incorrect Permission Assignment for Critical Resource (Score: 61.22)\n\nThe product specifies permissions for a security-critical resource in a way that allows that resource to be read or modified by unintended actors....\n\n## PRODUCT: 'Dell Client Platform BIOS'\n\nRelevant CWEs for this PRODUCT:\n\n### 1. CWE-20: Improper Input Validation (Score: 223.37)\n\nThe product receives input or data, but it does\n        not validate or incorrectly validates that the input has the\n        properties that are required to process the data safely and\n        correctly....\n\n### 2. CWE-119: Improper Restriction of Operations within the Bounds of a Memory Buffer (Score: 206.87)\n\nThe product performs operations on a memory buffer, but it reads from or writes to a memory location outside the buffer's intended boundary. This may result in read or write operations on unexpected memory locations that could be linked to other variables, data structures, or internal program data....\n\n### 3. CWE-287: Improper Authentication (Score: 189.34)\n\nWhen an actor claims to have a given identity, the product does not prove or insufficiently proves that the claim is correct....\n\n### 4. CWE-125: Out-of-bounds Read (Score: 183.89)\n\nThe product reads data past the end, or before the beginning, of the intended buffer....\n\n### 5. CWE-200: Exposure of Sensitive Information to an Unauthorized Actor (Score: 67.98)\n\nThe product exposes sensitive information to an actor that is not explicitly authorized to have access to that information....\n\n## COMPONENT: 'externally developed component'\n\nRelevant CWEs for this COMPONENT:\n\n### 1. CWE-20: Improper Input Validation (Score: 223.37)\n\nThe product receives input or data, but it does\n        not validate or incorrectly validates that the input has the\n        properties that are required to process the data safely and\n        correctly....\n\n### 2. CWE-119: Improper Restriction of Operations within the Bounds of a Memory Buffer (Score: 206.87)\n\nThe product performs operations on a memory buffer, but it reads from or writes to a memory location outside the buffer's intended boundary. This may result in read or write operations on unexpected memory locations that could be linked to other variables, data structures, or internal program data....\n\n### 3. CWE-125: Out-of-bounds Read (Score: 183.89)\n\nThe product reads data past the end, or before the beginning, of the intended buffer....\n\n### 4. CWE-823: Use of Out-of-range Pointer Offset (Score: 62.14)\n\nThe product performs pointer arithmetic on a valid pointer, but it uses an offset that can point outside of the intended range of valid memory locations for the resulting pointer....\n\n### 5. CWE-732: Incorrect Permission Assignment for Critical Resource (Score: 61.22)\n\nThe product specifies permissions for a security-critical resource in a way that allows that resource to be read or modified by unintended actors....\n\n\n    # Analysis Instructions\n    1. For each keyphrase, identify the most appropriate CWE(s) that represent the weakness.\n    2. Consider how the different keyphrases might relate to each other in the vulnerability chain.\n    3. Provide a final determination of primary CWE(s) and any secondary CWEs.\n    4. Format your response using the standard analysis template.\n\n    Please analyze how these different weaknesses interact and provide a comprehensive CWE classification.\n    "
  },
  "retrieval_time": 1.1408984661102295
}