{
  "vulnerability_info": "VulnerabilityInfo(cve_id='CVE-2024-40658', description='In getConfig of SoftVideoDecoderOMXComponent.cpp, there is a possible **out of bounds write** due to a **heap buffer overflow**. This could lead to local escalation of privilege with no additional execution privileges needed. User interaction is not needed for exploitation.', key_phrases={'rootcause': '', 'weakness': ['heap buffer overflow', 'out of bounds write'], 'impact': 'local escalation of privilege', 'vector': 'out of bounds write', 'attacker': '', 'product': '', 'version': '', 'component': 'getConfig of SoftVideoDecoderOMXComponent.cpp'}, reference_content='```\\n{\\n  \"vulnerability_details\": [\\n    {\\n      \"cve_id\": \"CVE-2024-40658\",\\n      \"root_cause\": \"The vulnerability lies in the OpenMAX (omx) component where the HDR10+ info parameter size is not properly checked.\",\\n      \"weaknesses\": [\\n        \"Improper input validation\"\\n      ],\\n      \"impact\": \"Elevation of privilege\",\\n      \"attack_vectors\": [\\n        \"Local exploitation\"\\n      ],\\n       \"required_capabilities\": [\\n        \"No additional execution privileges needed.\"\\n      ],\\n      \"additional_details\": \"The commit message indicates a check for HDR10+ info parameter size was added to address the bug. This suggests that an improperly sized HDR10+ parameter could lead to the vulnerability being triggered.\"\\n    }\\n  ]\\n}\\n```', similar_info={'cwe_distribution': {}, 'cwe_consensus': '', 'similarity_stats': {'thresholds': [], 'total_samples_by_threshold': {}, 'top_cwes_by_threshold': {}}}, similarity_summary=SimilarityInsight(consensus_cwe='', top_cwes=[], confidence_levels={}, total_samples=0), analysis='', analysis_with_relationships='', criticism='', resolution='', relevant_cwes=[{'metadata': {'doc_id': '131', 'name': 'Incorrect Calculation of Buffer Size', 'source': 'sparse', 'original_content': 'The product does not correctly calculate the size to be used when allocating a buffer, which could lead to a buffer overflow.', 'keyphrase_sources': [{'id': 'weakness:heap buffer overflow', 'keyphrase': 'heap buffer overflow', 'type': 'weakness'}, {'id': 'weakness:out of bounds write', 'keyphrase': 'out of bounds write', 'type': 'weakness'}, {'id': 'impact:local escalation of privilege', 'keyphrase': 'local escalation of privilege', 'type': 'impact'}, {'id': 'vector:out of bounds write', 'keyphrase': 'out of bounds write', 'type': 'vector'}, {'id': 'component:getConfig of SoftVideoDecoderOMXComponent.cpp', 'keyphrase': 'getConfig of SoftVideoDecoderOMXComponent.cpp', 'type': 'component'}]}, 'similarity': np.float64(401.504425014375)}, {'metadata': {'doc_id': '122', 'name': 'Heap-based Buffer Overflow', 'source': 'sparse', 'original_content': 'A heap overflow condition is a buffer overflow, where the buffer that can be overwritten is allocated in the heap portion of memory, generally meaning that the buffer was allocated using a routine such as malloc().', 'keyphrase_sources': [{'id': 'weakness:heap buffer overflow', 'keyphrase': 'heap buffer overflow', 'type': 'weakness'}, {'id': 'weakness:out of bounds write', 'keyphrase': 'out of bounds write', 'type': 'weakness'}, {'id': 'vector:out of bounds write', 'keyphrase': 'out of bounds write', 'type': 'vector'}, {'id': 'component:getConfig of SoftVideoDecoderOMXComponent.cpp', 'keyphrase': 'getConfig of SoftVideoDecoderOMXComponent.cpp', 'type': 'component'}]}, 'similarity': np.float64(396.37836126879046)}, {'metadata': {'doc_id': '908', 'name': 'Use of Uninitialized Resource', 'source': 'sparse', 'original_content': 'The product uses or accesses a resource that has not been initialized.', 'keyphrase_sources': [{'id': 'weakness:out of bounds write', 'keyphrase': 'out of bounds write', 'type': 'weakness'}, {'id': 'impact:local escalation of privilege', 'keyphrase': 'local escalation of privilege', 'type': 'impact'}, {'id': 'vector:out of bounds write', 'keyphrase': 'out of bounds write', 'type': 'vector'}, {'id': 'component:getConfig of SoftVideoDecoderOMXComponent.cpp', 'keyphrase': 'getConfig of SoftVideoDecoderOMXComponent.cpp', 'type': 'component'}]}, 'similarity': np.float64(385.3167396521011)}, {'metadata': {'doc_id': '190', 'name': 'Integer Overflow or Wraparound', 'source': 'sparse', 'original_content': 'The product performs a calculation that can\\n         produce an integer overflow or wraparound when the logic\\n         assumes that the resulting value will always be larger than\\n         the original value. This occurs when an integer value is\\n         incremented to a value that is too large to store in the\\n         associated representation. When this occurs, the value may\\n         become a very small or negative number.', 'keyphrase_sources': [{'id': 'weakness:heap buffer overflow', 'keyphrase': 'heap buffer overflow', 'type': 'weakness'}, {'id': 'weakness:out of bounds write', 'keyphrase': 'out of bounds write', 'type': 'weakness'}, {'id': 'vector:out of bounds write', 'keyphrase': 'out of bounds write', 'type': 'vector'}]}, 'similarity': np.float64(385.1582863009457)}, {'metadata': {'doc_id': '191', 'name': 'Integer Underflow (Wrap or Wraparound)', 'source': 'sparse', 'original_content': 'The product subtracts one value from another, such that the result is less than the minimum allowable integer value, which produces a value that is not equal to the correct result.', 'keyphrase_sources': [{'id': 'weakness:heap buffer overflow', 'keyphrase': 'heap buffer overflow', 'type': 'weakness'}, {'id': 'weakness:out of bounds write', 'keyphrase': 'out of bounds write', 'type': 'weakness'}, {'id': 'impact:local escalation of privilege', 'keyphrase': 'local escalation of privilege', 'type': 'impact'}, {'id': 'vector:out of bounds write', 'keyphrase': 'out of bounds write', 'type': 'vector'}, {'id': 'component:getConfig of SoftVideoDecoderOMXComponent.cpp', 'keyphrase': 'getConfig of SoftVideoDecoderOMXComponent.cpp', 'type': 'component'}]}, 'similarity': np.float64(378.0819687831939)}, {'metadata': {'doc_id': '1284', 'name': 'Improper Validation of Specified Quantity in Input', 'source': 'sparse', 'original_content': 'The product receives input that is expected to specify a quantity (such as size or length), but it does not validate or incorrectly validates that the quantity has the required properties.', 'keyphrase_sources': [{'id': 'weakness:heap buffer overflow', 'keyphrase': 'heap buffer overflow', 'type': 'weakness'}]}, 'similarity': np.float64(346.5056743010385)}, {'metadata': {'doc_id': '362', 'name': \"Concurrent Execution using Shared Resource with Improper Synchronization ('Race Condition')\", 'source': 'sparse', 'original_content': 'The product contains a concurrent code sequence that requires temporary, exclusive access to a shared resource, but a timing window exists in which the shared resource can be modified by another code sequence operating concurrently.', 'keyphrase_sources': [{'id': 'impact:local escalation of privilege', 'keyphrase': 'local escalation of privilege', 'type': 'impact'}, {'id': 'component:getConfig of SoftVideoDecoderOMXComponent.cpp', 'keyphrase': 'getConfig of SoftVideoDecoderOMXComponent.cpp', 'type': 'component'}]}, 'similarity': np.float64(126.72460321127264)}, {'metadata': {'doc_id': '667', 'name': 'Improper Locking', 'source': 'sparse', 'original_content': 'The product does not properly acquire or release a lock on a resource, leading to unexpected resource state changes and behaviors.', 'keyphrase_sources': [{'id': 'impact:local escalation of privilege', 'keyphrase': 'local escalation of privilege', 'type': 'impact'}]}, 'similarity': np.float64(126.28157151893535)}], identified_cwes={'analyzer': [], 'critic_additional': []})",
  "retrieval_results": {
    "has_multiple_keyphrases": true,
    "keyphrase_cwe_sets": {
      "weakness:heap buffer overflow": {
        "keyphrase": "heap buffer overflow",
        "type": "weakness",
        "cwes": [
          {
            "metadata": {
              "doc_id": "131",
              "name": "Incorrect Calculation of Buffer Size",
              "source": "sparse",
              "original_content": "The product does not correctly calculate the size to be used when allocating a buffer, which could lead to a buffer overflow.",
              "keyphrase_sources": [
                {
                  "id": "weakness:heap buffer overflow",
                  "keyphrase": "heap buffer overflow",
                  "type": "weakness"
                },
                {
                  "id": "weakness:out of bounds write",
                  "keyphrase": "out of bounds write",
                  "type": "weakness"
                },
                {
                  "id": "impact:local escalation of privilege",
                  "keyphrase": "local escalation of privilege",
                  "type": "impact"
                },
                {
                  "id": "vector:out of bounds write",
                  "keyphrase": "out of bounds write",
                  "type": "vector"
                },
                {
                  "id": "component:getConfig of SoftVideoDecoderOMXComponent.cpp",
                  "keyphrase": "getConfig of SoftVideoDecoderOMXComponent.cpp",
                  "type": "component"
                }
              ]
            },
            "similarity": 401.504425014375
          },
          {
            "metadata": {
              "doc_id": "122",
              "name": "Heap-based Buffer Overflow",
              "source": "sparse",
              "original_content": "A heap overflow condition is a buffer overflow, where the buffer that can be overwritten is allocated in the heap portion of memory, generally meaning that the buffer was allocated using a routine such as malloc().",
              "keyphrase_sources": [
                {
                  "id": "weakness:heap buffer overflow",
                  "keyphrase": "heap buffer overflow",
                  "type": "weakness"
                },
                {
                  "id": "weakness:out of bounds write",
                  "keyphrase": "out of bounds write",
                  "type": "weakness"
                },
                {
                  "id": "vector:out of bounds write",
                  "keyphrase": "out of bounds write",
                  "type": "vector"
                },
                {
                  "id": "component:getConfig of SoftVideoDecoderOMXComponent.cpp",
                  "keyphrase": "getConfig of SoftVideoDecoderOMXComponent.cpp",
                  "type": "component"
                }
              ]
            },
            "similarity": 396.37836126879046
          },
          {
            "metadata": {
              "doc_id": "190",
              "name": "Integer Overflow or Wraparound",
              "source": "sparse",
              "original_content": "The product performs a calculation that can\n         produce an integer overflow or wraparound when the logic\n         assumes that the resulting value will always be larger than\n         the original value. This occurs when an integer value is\n         incremented to a value that is too large to store in the\n         associated representation. When this occurs, the value may\n         become a very small or negative number.",
              "keyphrase_sources": [
                {
                  "id": "weakness:heap buffer overflow",
                  "keyphrase": "heap buffer overflow",
                  "type": "weakness"
                },
                {
                  "id": "weakness:out of bounds write",
                  "keyphrase": "out of bounds write",
                  "type": "weakness"
                },
                {
                  "id": "vector:out of bounds write",
                  "keyphrase": "out of bounds write",
                  "type": "vector"
                }
              ]
            },
            "similarity": 385.1582863009457
          },
          {
            "metadata": {
              "doc_id": "191",
              "name": "Integer Underflow (Wrap or Wraparound)",
              "source": "sparse",
              "original_content": "The product subtracts one value from another, such that the result is less than the minimum allowable integer value, which produces a value that is not equal to the correct result.",
              "keyphrase_sources": [
                {
                  "id": "weakness:heap buffer overflow",
                  "keyphrase": "heap buffer overflow",
                  "type": "weakness"
                },
                {
                  "id": "weakness:out of bounds write",
                  "keyphrase": "out of bounds write",
                  "type": "weakness"
                },
                {
                  "id": "impact:local escalation of privilege",
                  "keyphrase": "local escalation of privilege",
                  "type": "impact"
                },
                {
                  "id": "vector:out of bounds write",
                  "keyphrase": "out of bounds write",
                  "type": "vector"
                },
                {
                  "id": "component:getConfig of SoftVideoDecoderOMXComponent.cpp",
                  "keyphrase": "getConfig of SoftVideoDecoderOMXComponent.cpp",
                  "type": "component"
                }
              ]
            },
            "similarity": 378.0819687831939
          },
          {
            "metadata": {
              "doc_id": "1284",
              "name": "Improper Validation of Specified Quantity in Input",
              "source": "sparse",
              "original_content": "The product receives input that is expected to specify a quantity (such as size or length), but it does not validate or incorrectly validates that the quantity has the required properties.",
              "keyphrase_sources": [
                {
                  "id": "weakness:heap buffer overflow",
                  "keyphrase": "heap buffer overflow",
                  "type": "weakness"
                }
              ]
            },
            "similarity": 346.5056743010385
          }
        ]
      },
      "weakness:out of bounds write": {
        "keyphrase": "out of bounds write",
        "type": "weakness",
        "cwes": [
          {
            "metadata": {
              "doc_id": "131",
              "name": "Incorrect Calculation of Buffer Size",
              "source": "sparse",
              "original_content": "The product does not correctly calculate the size to be used when allocating a buffer, which could lead to a buffer overflow."
            },
            "similarity": 406.99714929455257
          },
          {
            "metadata": {
              "doc_id": "191",
              "name": "Integer Underflow (Wrap or Wraparound)",
              "source": "sparse",
              "original_content": "The product subtracts one value from another, such that the result is less than the minimum allowable integer value, which produces a value that is not equal to the correct result."
            },
            "similarity": 392.0817166925282
          },
          {
            "metadata": {
              "doc_id": "908",
              "name": "Use of Uninitialized Resource",
              "source": "sparse",
              "original_content": "The product uses or accesses a resource that has not been initialized.",
              "keyphrase_sources": [
                {
                  "id": "weakness:out of bounds write",
                  "keyphrase": "out of bounds write",
                  "type": "weakness"
                },
                {
                  "id": "impact:local escalation of privilege",
                  "keyphrase": "local escalation of privilege",
                  "type": "impact"
                },
                {
                  "id": "vector:out of bounds write",
                  "keyphrase": "out of bounds write",
                  "type": "vector"
                },
                {
                  "id": "component:getConfig of SoftVideoDecoderOMXComponent.cpp",
                  "keyphrase": "getConfig of SoftVideoDecoderOMXComponent.cpp",
                  "type": "component"
                }
              ]
            },
            "similarity": 385.3167396521011
          },
          {
            "metadata": {
              "doc_id": "122",
              "name": "Heap-based Buffer Overflow",
              "source": "sparse",
              "original_content": "A heap overflow condition is a buffer overflow, where the buffer that can be overwritten is allocated in the heap portion of memory, generally meaning that the buffer was allocated using a routine such as malloc()."
            },
            "similarity": 377.23756158992944
          },
          {
            "metadata": {
              "doc_id": "190",
              "name": "Integer Overflow or Wraparound",
              "source": "sparse",
              "original_content": "The product performs a calculation that can\n         produce an integer overflow or wraparound when the logic\n         assumes that the resulting value will always be larger than\n         the original value. This occurs when an integer value is\n         incremented to a value that is too large to store in the\n         associated representation. When this occurs, the value may\n         become a very small or negative number."
            },
            "similarity": 371.70323498277156
          }
        ]
      },
      "impact:local escalation of privilege": {
        "keyphrase": "local escalation of privilege",
        "type": "impact",
        "cwes": [
          {
            "metadata": {
              "doc_id": "131",
              "name": "Incorrect Calculation of Buffer Size",
              "source": "sparse",
              "original_content": "The product does not correctly calculate the size to be used when allocating a buffer, which could lead to a buffer overflow."
            },
            "similarity": 138.23373735653072
          },
          {
            "metadata": {
              "doc_id": "908",
              "name": "Use of Uninitialized Resource",
              "source": "sparse",
              "original_content": "The product uses or accesses a resource that has not been initialized."
            },
            "similarity": 131.30195623333566
          },
          {
            "metadata": {
              "doc_id": "191",
              "name": "Integer Underflow (Wrap or Wraparound)",
              "source": "sparse",
              "original_content": "The product subtracts one value from another, such that the result is less than the minimum allowable integer value, which produces a value that is not equal to the correct result."
            },
            "similarity": 128.33294138257364
          },
          {
            "metadata": {
              "doc_id": "362",
              "name": "Concurrent Execution using Shared Resource with Improper Synchronization ('Race Condition')",
              "source": "sparse",
              "original_content": "The product contains a concurrent code sequence that requires temporary, exclusive access to a shared resource, but a timing window exists in which the shared resource can be modified by another code sequence operating concurrently.",
              "keyphrase_sources": [
                {
                  "id": "impact:local escalation of privilege",
                  "keyphrase": "local escalation of privilege",
                  "type": "impact"
                },
                {
                  "id": "component:getConfig of SoftVideoDecoderOMXComponent.cpp",
                  "keyphrase": "getConfig of SoftVideoDecoderOMXComponent.cpp",
                  "type": "component"
                }
              ]
            },
            "similarity": 126.72460321127264
          },
          {
            "metadata": {
              "doc_id": "667",
              "name": "Improper Locking",
              "source": "sparse",
              "original_content": "The product does not properly acquire or release a lock on a resource, leading to unexpected resource state changes and behaviors.",
              "keyphrase_sources": [
                {
                  "id": "impact:local escalation of privilege",
                  "keyphrase": "local escalation of privilege",
                  "type": "impact"
                }
              ]
            },
            "similarity": 126.28157151893535
          }
        ]
      },
      "vector:out of bounds write": {
        "keyphrase": "out of bounds write",
        "type": "vector",
        "cwes": [
          {
            "metadata": {
              "doc_id": "131",
              "name": "Incorrect Calculation of Buffer Size",
              "source": "sparse",
              "original_content": "The product does not correctly calculate the size to be used when allocating a buffer, which could lead to a buffer overflow."
            },
            "similarity": 145.3561247480545
          },
          {
            "metadata": {
              "doc_id": "191",
              "name": "Integer Underflow (Wrap or Wraparound)",
              "source": "sparse",
              "original_content": "The product subtracts one value from another, such that the result is less than the minimum allowable integer value, which produces a value that is not equal to the correct result."
            },
            "similarity": 140.0291845330458
          },
          {
            "metadata": {
              "doc_id": "908",
              "name": "Use of Uninitialized Resource",
              "source": "sparse",
              "original_content": "The product uses or accesses a resource that has not been initialized."
            },
            "similarity": 137.61312130432182
          },
          {
            "metadata": {
              "doc_id": "122",
              "name": "Heap-based Buffer Overflow",
              "source": "sparse",
              "original_content": "A heap overflow condition is a buffer overflow, where the buffer that can be overwritten is allocated in the heap portion of memory, generally meaning that the buffer was allocated using a routine such as malloc()."
            },
            "similarity": 134.72770056783196
          },
          {
            "metadata": {
              "doc_id": "190",
              "name": "Integer Overflow or Wraparound",
              "source": "sparse",
              "original_content": "The product performs a calculation that can\n         produce an integer overflow or wraparound when the logic\n         assumes that the resulting value will always be larger than\n         the original value. This occurs when an integer value is\n         incremented to a value that is too large to store in the\n         associated representation. When this occurs, the value may\n         become a very small or negative number."
            },
            "similarity": 132.75115535098985
          }
        ]
      },
      "component:getConfig of SoftVideoDecoderOMXComponent.cpp": {
        "keyphrase": "getConfig of SoftVideoDecoderOMXComponent.cpp",
        "type": "component",
        "cwes": [
          {
            "metadata": {
              "doc_id": "908",
              "name": "Use of Uninitialized Resource",
              "source": "sparse",
              "original_content": "The product uses or accesses a resource that has not been initialized."
            },
            "similarity": 123.72984956235064
          },
          {
            "metadata": {
              "doc_id": "191",
              "name": "Integer Underflow (Wrap or Wraparound)",
              "source": "sparse",
              "original_content": "The product subtracts one value from another, such that the result is less than the minimum allowable integer value, which produces a value that is not equal to the correct result."
            },
            "similarity": 123.65339892087387
          },
          {
            "metadata": {
              "doc_id": "122",
              "name": "Heap-based Buffer Overflow",
              "source": "sparse",
              "original_content": "A heap overflow condition is a buffer overflow, where the buffer that can be overwritten is allocated in the heap portion of memory, generally meaning that the buffer was allocated using a routine such as malloc()."
            },
            "similarity": 123.40429646406074
          },
          {
            "metadata": {
              "doc_id": "131",
              "name": "Incorrect Calculation of Buffer Size",
              "source": "sparse",
              "original_content": "The product does not correctly calculate the size to be used when allocating a buffer, which could lead to a buffer overflow."
            },
            "similarity": 122.21177119905087
          },
          {
            "metadata": {
              "doc_id": "362",
              "name": "Concurrent Execution using Shared Resource with Improper Synchronization ('Race Condition')",
              "source": "sparse",
              "original_content": "The product contains a concurrent code sequence that requires temporary, exclusive access to a shared resource, but a timing window exists in which the shared resource can be modified by another code sequence operating concurrently."
            },
            "similarity": 115.12439188719554
          }
        ]
      }
    },
    "keyphrase_mapping": {
      "131": [
        {
          "id": "weakness:heap buffer overflow",
          "keyphrase": "heap buffer overflow",
          "type": "weakness"
        },
        {
          "id": "weakness:out of bounds write",
          "keyphrase": "out of bounds write",
          "type": "weakness"
        },
        {
          "id": "impact:local escalation of privilege",
          "keyphrase": "local escalation of privilege",
          "type": "impact"
        },
        {
          "id": "vector:out of bounds write",
          "keyphrase": "out of bounds write",
          "type": "vector"
        },
        {
          "id": "component:getConfig of SoftVideoDecoderOMXComponent.cpp",
          "keyphrase": "getConfig of SoftVideoDecoderOMXComponent.cpp",
          "type": "component"
        }
      ],
      "122": [
        {
          "id": "weakness:heap buffer overflow",
          "keyphrase": "heap buffer overflow",
          "type": "weakness"
        },
        {
          "id": "weakness:out of bounds write",
          "keyphrase": "out of bounds write",
          "type": "weakness"
        },
        {
          "id": "vector:out of bounds write",
          "keyphrase": "out of bounds write",
          "type": "vector"
        },
        {
          "id": "component:getConfig of SoftVideoDecoderOMXComponent.cpp",
          "keyphrase": "getConfig of SoftVideoDecoderOMXComponent.cpp",
          "type": "component"
        }
      ],
      "190": [
        {
          "id": "weakness:heap buffer overflow",
          "keyphrase": "heap buffer overflow",
          "type": "weakness"
        },
        {
          "id": "weakness:out of bounds write",
          "keyphrase": "out of bounds write",
          "type": "weakness"
        },
        {
          "id": "vector:out of bounds write",
          "keyphrase": "out of bounds write",
          "type": "vector"
        }
      ],
      "191": [
        {
          "id": "weakness:heap buffer overflow",
          "keyphrase": "heap buffer overflow",
          "type": "weakness"
        },
        {
          "id": "weakness:out of bounds write",
          "keyphrase": "out of bounds write",
          "type": "weakness"
        },
        {
          "id": "impact:local escalation of privilege",
          "keyphrase": "local escalation of privilege",
          "type": "impact"
        },
        {
          "id": "vector:out of bounds write",
          "keyphrase": "out of bounds write",
          "type": "vector"
        },
        {
          "id": "component:getConfig of SoftVideoDecoderOMXComponent.cpp",
          "keyphrase": "getConfig of SoftVideoDecoderOMXComponent.cpp",
          "type": "component"
        }
      ],
      "1284": [
        {
          "id": "weakness:heap buffer overflow",
          "keyphrase": "heap buffer overflow",
          "type": "weakness"
        }
      ],
      "908": [
        {
          "id": "weakness:out of bounds write",
          "keyphrase": "out of bounds write",
          "type": "weakness"
        },
        {
          "id": "impact:local escalation of privilege",
          "keyphrase": "local escalation of privilege",
          "type": "impact"
        },
        {
          "id": "vector:out of bounds write",
          "keyphrase": "out of bounds write",
          "type": "vector"
        },
        {
          "id": "component:getConfig of SoftVideoDecoderOMXComponent.cpp",
          "keyphrase": "getConfig of SoftVideoDecoderOMXComponent.cpp",
          "type": "component"
        }
      ],
      "362": [
        {
          "id": "impact:local escalation of privilege",
          "keyphrase": "local escalation of privilege",
          "type": "impact"
        },
        {
          "id": "component:getConfig of SoftVideoDecoderOMXComponent.cpp",
          "keyphrase": "getConfig of SoftVideoDecoderOMXComponent.cpp",
          "type": "component"
        }
      ],
      "667": [
        {
          "id": "impact:local escalation of privilege",
          "keyphrase": "local escalation of privilege",
          "type": "impact"
        }
      ]
    },
    "relevant_cwes": [
      {
        "metadata": {
          "doc_id": "131",
          "name": "Incorrect Calculation of Buffer Size",
          "source": "sparse",
          "original_content": "The product does not correctly calculate the size to be used when allocating a buffer, which could lead to a buffer overflow.",
          "keyphrase_sources": [
            {
              "id": "weakness:heap buffer overflow",
              "keyphrase": "heap buffer overflow",
              "type": "weakness"
            },
            {
              "id": "weakness:out of bounds write",
              "keyphrase": "out of bounds write",
              "type": "weakness"
            },
            {
              "id": "impact:local escalation of privilege",
              "keyphrase": "local escalation of privilege",
              "type": "impact"
            },
            {
              "id": "vector:out of bounds write",
              "keyphrase": "out of bounds write",
              "type": "vector"
            },
            {
              "id": "component:getConfig of SoftVideoDecoderOMXComponent.cpp",
              "keyphrase": "getConfig of SoftVideoDecoderOMXComponent.cpp",
              "type": "component"
            }
          ]
        },
        "similarity": 401.504425014375
      },
      {
        "metadata": {
          "doc_id": "122",
          "name": "Heap-based Buffer Overflow",
          "source": "sparse",
          "original_content": "A heap overflow condition is a buffer overflow, where the buffer that can be overwritten is allocated in the heap portion of memory, generally meaning that the buffer was allocated using a routine such as malloc().",
          "keyphrase_sources": [
            {
              "id": "weakness:heap buffer overflow",
              "keyphrase": "heap buffer overflow",
              "type": "weakness"
            },
            {
              "id": "weakness:out of bounds write",
              "keyphrase": "out of bounds write",
              "type": "weakness"
            },
            {
              "id": "vector:out of bounds write",
              "keyphrase": "out of bounds write",
              "type": "vector"
            },
            {
              "id": "component:getConfig of SoftVideoDecoderOMXComponent.cpp",
              "keyphrase": "getConfig of SoftVideoDecoderOMXComponent.cpp",
              "type": "component"
            }
          ]
        },
        "similarity": 396.37836126879046
      },
      {
        "metadata": {
          "doc_id": "908",
          "name": "Use of Uninitialized Resource",
          "source": "sparse",
          "original_content": "The product uses or accesses a resource that has not been initialized.",
          "keyphrase_sources": [
            {
              "id": "weakness:out of bounds write",
              "keyphrase": "out of bounds write",
              "type": "weakness"
            },
            {
              "id": "impact:local escalation of privilege",
              "keyphrase": "local escalation of privilege",
              "type": "impact"
            },
            {
              "id": "vector:out of bounds write",
              "keyphrase": "out of bounds write",
              "type": "vector"
            },
            {
              "id": "component:getConfig of SoftVideoDecoderOMXComponent.cpp",
              "keyphrase": "getConfig of SoftVideoDecoderOMXComponent.cpp",
              "type": "component"
            }
          ]
        },
        "similarity": 385.3167396521011
      },
      {
        "metadata": {
          "doc_id": "190",
          "name": "Integer Overflow or Wraparound",
          "source": "sparse",
          "original_content": "The product performs a calculation that can\n         produce an integer overflow or wraparound when the logic\n         assumes that the resulting value will always be larger than\n         the original value. This occurs when an integer value is\n         incremented to a value that is too large to store in the\n         associated representation. When this occurs, the value may\n         become a very small or negative number.",
          "keyphrase_sources": [
            {
              "id": "weakness:heap buffer overflow",
              "keyphrase": "heap buffer overflow",
              "type": "weakness"
            },
            {
              "id": "weakness:out of bounds write",
              "keyphrase": "out of bounds write",
              "type": "weakness"
            },
            {
              "id": "vector:out of bounds write",
              "keyphrase": "out of bounds write",
              "type": "vector"
            }
          ]
        },
        "similarity": 385.1582863009457
      },
      {
        "metadata": {
          "doc_id": "191",
          "name": "Integer Underflow (Wrap or Wraparound)",
          "source": "sparse",
          "original_content": "The product subtracts one value from another, such that the result is less than the minimum allowable integer value, which produces a value that is not equal to the correct result.",
          "keyphrase_sources": [
            {
              "id": "weakness:heap buffer overflow",
              "keyphrase": "heap buffer overflow",
              "type": "weakness"
            },
            {
              "id": "weakness:out of bounds write",
              "keyphrase": "out of bounds write",
              "type": "weakness"
            },
            {
              "id": "impact:local escalation of privilege",
              "keyphrase": "local escalation of privilege",
              "type": "impact"
            },
            {
              "id": "vector:out of bounds write",
              "keyphrase": "out of bounds write",
              "type": "vector"
            },
            {
              "id": "component:getConfig of SoftVideoDecoderOMXComponent.cpp",
              "keyphrase": "getConfig of SoftVideoDecoderOMXComponent.cpp",
              "type": "component"
            }
          ]
        },
        "similarity": 378.0819687831939
      },
      {
        "metadata": {
          "doc_id": "1284",
          "name": "Improper Validation of Specified Quantity in Input",
          "source": "sparse",
          "original_content": "The product receives input that is expected to specify a quantity (such as size or length), but it does not validate or incorrectly validates that the quantity has the required properties.",
          "keyphrase_sources": [
            {
              "id": "weakness:heap buffer overflow",
              "keyphrase": "heap buffer overflow",
              "type": "weakness"
            }
          ]
        },
        "similarity": 346.5056743010385
      },
      {
        "metadata": {
          "doc_id": "362",
          "name": "Concurrent Execution using Shared Resource with Improper Synchronization ('Race Condition')",
          "source": "sparse",
          "original_content": "The product contains a concurrent code sequence that requires temporary, exclusive access to a shared resource, but a timing window exists in which the shared resource can be modified by another code sequence operating concurrently.",
          "keyphrase_sources": [
            {
              "id": "impact:local escalation of privilege",
              "keyphrase": "local escalation of privilege",
              "type": "impact"
            },
            {
              "id": "component:getConfig of SoftVideoDecoderOMXComponent.cpp",
              "keyphrase": "getConfig of SoftVideoDecoderOMXComponent.cpp",
              "type": "component"
            }
          ]
        },
        "similarity": 126.72460321127264
      },
      {
        "metadata": {
          "doc_id": "667",
          "name": "Improper Locking",
          "source": "sparse",
          "original_content": "The product does not properly acquire or release a lock on a resource, leading to unexpected resource state changes and behaviors.",
          "keyphrase_sources": [
            {
              "id": "impact:local escalation of privilege",
              "keyphrase": "local escalation of privilege",
              "type": "impact"
            }
          ]
        },
        "similarity": 126.28157151893535
      }
    ],
    "enhanced_query": "# Vulnerability Description\n\n    In getConfig of SoftVideoDecoderOMXComponent.cpp, there is a possible **out of bounds write** due to a **heap buffer overflow**. This could lead to local escalation of privilege with no additional execution privileges needed. User interaction is not needed for exploitation.\n\n    # Keyphrase-Specific CWE Analysis\n    This vulnerability contains multiple keyphrases that may map to different CWEs. \n    Please analyze each keyphrase separately and determine the most appropriate CWE(s) for each.\n\n    ## WEAKNESS: 'heap buffer overflow'\n\nRelevant CWEs for this WEAKNESS:\n\n### 1. CWE-131: Incorrect Calculation of Buffer Size (Score: 401.50)\n\nThe product does not correctly calculate the size to be used when allocating a buffer, which could lead to a buffer overflow....\n\n### 2. CWE-122: Heap-based Buffer Overflow (Score: 396.38)\n\nA heap overflow condition is a buffer overflow, where the buffer that can be overwritten is allocated in the heap portion of memory, generally meaning that the buffer was allocated using a routine such as malloc()....\n\n### 3. CWE-190: Integer Overflow or Wraparound (Score: 385.16)\n\nThe product performs a calculation that can\n         produce an integer overflow or wraparound when the logic\n         assumes that the resulting value will always be larger than\n         the original value. This occurs when an integer value is\n         incremented to a value that is too large to st...\n\n### 4. CWE-191: Integer Underflow (Wrap or Wraparound) (Score: 378.08)\n\nThe product subtracts one value from another, such that the result is less than the minimum allowable integer value, which produces a value that is not equal to the correct result....\n\n### 5. CWE-1284: Improper Validation of Specified Quantity in Input (Score: 346.51)\n\nThe product receives input that is expected to specify a quantity (such as size or length), but it does not validate or incorrectly validates that the quantity has the required properties....\n\n## WEAKNESS: 'out of bounds write'\n\nRelevant CWEs for this WEAKNESS:\n\n### 1. CWE-131: Incorrect Calculation of Buffer Size (Score: 401.50)\n\nThe product does not correctly calculate the size to be used when allocating a buffer, which could lead to a buffer overflow....\n\n### 2. CWE-122: Heap-based Buffer Overflow (Score: 396.38)\n\nA heap overflow condition is a buffer overflow, where the buffer that can be overwritten is allocated in the heap portion of memory, generally meaning that the buffer was allocated using a routine such as malloc()....\n\n### 3. CWE-908: Use of Uninitialized Resource (Score: 385.32)\n\nThe product uses or accesses a resource that has not been initialized....\n\n### 4. CWE-190: Integer Overflow or Wraparound (Score: 385.16)\n\nThe product performs a calculation that can\n         produce an integer overflow or wraparound when the logic\n         assumes that the resulting value will always be larger than\n         the original value. This occurs when an integer value is\n         incremented to a value that is too large to st...\n\n### 5. CWE-191: Integer Underflow (Wrap or Wraparound) (Score: 378.08)\n\nThe product subtracts one value from another, such that the result is less than the minimum allowable integer value, which produces a value that is not equal to the correct result....\n\n## IMPACT: 'local escalation of privilege'\n\nRelevant CWEs for this IMPACT:\n\n### 1. CWE-131: Incorrect Calculation of Buffer Size (Score: 401.50)\n\nThe product does not correctly calculate the size to be used when allocating a buffer, which could lead to a buffer overflow....\n\n### 2. CWE-908: Use of Uninitialized Resource (Score: 385.32)\n\nThe product uses or accesses a resource that has not been initialized....\n\n### 3. CWE-191: Integer Underflow (Wrap or Wraparound) (Score: 378.08)\n\nThe product subtracts one value from another, such that the result is less than the minimum allowable integer value, which produces a value that is not equal to the correct result....\n\n### 4. CWE-362: Concurrent Execution using Shared Resource with Improper Synchronization ('Race Condition') (Score: 126.72)\n\nThe product contains a concurrent code sequence that requires temporary, exclusive access to a shared resource, but a timing window exists in which the shared resource can be modified by another code sequence operating concurrently....\n\n### 5. CWE-667: Improper Locking (Score: 126.28)\n\nThe product does not properly acquire or release a lock on a resource, leading to unexpected resource state changes and behaviors....\n\n## VECTOR: 'out of bounds write'\n\nRelevant CWEs for this VECTOR:\n\n### 1. CWE-131: Incorrect Calculation of Buffer Size (Score: 401.50)\n\nThe product does not correctly calculate the size to be used when allocating a buffer, which could lead to a buffer overflow....\n\n### 2. CWE-122: Heap-based Buffer Overflow (Score: 396.38)\n\nA heap overflow condition is a buffer overflow, where the buffer that can be overwritten is allocated in the heap portion of memory, generally meaning that the buffer was allocated using a routine such as malloc()....\n\n### 3. CWE-908: Use of Uninitialized Resource (Score: 385.32)\n\nThe product uses or accesses a resource that has not been initialized....\n\n### 4. CWE-190: Integer Overflow or Wraparound (Score: 385.16)\n\nThe product performs a calculation that can\n         produce an integer overflow or wraparound when the logic\n         assumes that the resulting value will always be larger than\n         the original value. This occurs when an integer value is\n         incremented to a value that is too large to st...\n\n### 5. CWE-191: Integer Underflow (Wrap or Wraparound) (Score: 378.08)\n\nThe product subtracts one value from another, such that the result is less than the minimum allowable integer value, which produces a value that is not equal to the correct result....\n\n## COMPONENT: 'getConfig of SoftVideoDecoderOMXComponent.cpp'\n\nRelevant CWEs for this COMPONENT:\n\n### 1. CWE-131: Incorrect Calculation of Buffer Size (Score: 401.50)\n\nThe product does not correctly calculate the size to be used when allocating a buffer, which could lead to a buffer overflow....\n\n### 2. CWE-122: Heap-based Buffer Overflow (Score: 396.38)\n\nA heap overflow condition is a buffer overflow, where the buffer that can be overwritten is allocated in the heap portion of memory, generally meaning that the buffer was allocated using a routine such as malloc()....\n\n### 3. CWE-908: Use of Uninitialized Resource (Score: 385.32)\n\nThe product uses or accesses a resource that has not been initialized....\n\n### 4. CWE-191: Integer Underflow (Wrap or Wraparound) (Score: 378.08)\n\nThe product subtracts one value from another, such that the result is less than the minimum allowable integer value, which produces a value that is not equal to the correct result....\n\n### 5. CWE-362: Concurrent Execution using Shared Resource with Improper Synchronization ('Race Condition') (Score: 126.72)\n\nThe product contains a concurrent code sequence that requires temporary, exclusive access to a shared resource, but a timing window exists in which the shared resource can be modified by another code sequence operating concurrently....\n\n\n    # Analysis Instructions\n    1. For each keyphrase, identify the most appropriate CWE(s) that represent the weakness.\n    2. Consider how the different keyphrases might relate to each other in the vulnerability chain.\n    3. Provide a final determination of primary CWE(s) and any secondary CWEs.\n    4. Format your response using the standard analysis template.\n\n    Please analyze how these different weaknesses interact and provide a comprehensive CWE classification.\n    "
  },
  "retrieval_time": 1.204592227935791
}