{
  "vulnerability_info": "VulnerabilityInfo(cve_id='CVE-2024-26126', description='Adobe Experience Manager versions 6.5.20 and earlier are affected by an **Improper Input Validation** vulnerability that could result in a security feature bypass. A low-privileged attacker could leverage this vulnerability to bypass security measures and affect the integrity of the page. Exploitation of this issue requires user interaction.', key_phrases={'rootcause': ['Improper Input Validation', 'Input Validation vulnerability'], 'weakness': '', 'impact': ['integrity', 'security feature bypass'], 'vector': '', 'attacker': 'low-privileged attacker', 'product': 'Adobe Experience Manager', 'version': '6.5.20 and earlier', 'component': ''}, reference_content='The provided content is related to CVE-2024-26126.\\n\\n- **Root cause of vulnerability**: Improper Input Validation\\n- **Weaknesses/vulnerabilities present**:  The vulnerability is categorized as Improper Input Validation (CWE-20). This means that the software does not properly validate user-supplied input, leading to potential security issues.\\n-  **Impact of exploitation**: Successful exploitation could result in a security feature bypass, potentially allowing an attacker to circumvent security measures within the application.\\n- **Attack vectors**: The attack vector is network-based (AV:N), with a low attack complexity (AC:L).\\n- **Required attacker capabilities/position**: The attacker needs to be a low-privileged user (PR:L) and requires user interaction (UI:R) to trigger the vulnerability. The scope is unchanged (S:U), and the impact is limited to low integrity (I:L) without affecting confidentiality or availability.\\n\\nThe provided information gives a more detailed breakdown of the vulnerability, including the specific CWE and CVSS vector, compared to the standard CVE description.', similar_info={'cwe_distribution': {95: {'cwe_counts': defaultdict(<class 'int'>, {'CWE-NVD-noinfo': 1}), 'total_samples': 3, 'distribution': [{'cwes': [], 'frequency': 2, 'proportion': 0.667}, {'cwes': ['CWE-NVD-noinfo'], 'frequency': 1, 'proportion': 0.333}]}, 90: {'cwe_counts': defaultdict(<class 'int'>, {'CWE-NVD-noinfo': 2}), 'total_samples': 4, 'distribution': [{'cwes': ['CWE-NVD-noinfo'], 'frequency': 2, 'proportion': 0.5}, {'cwes': [], 'frequency': 2, 'proportion': 0.5}]}, 85: {'cwe_counts': defaultdict(<class 'int'>, {'CWE-NVD-noinfo': 2}), 'total_samples': 4, 'distribution': [{'cwes': ['CWE-NVD-noinfo'], 'frequency': 2, 'proportion': 0.5}, {'cwes': [], 'frequency': 2, 'proportion': 0.5}]}, 80: {'cwe_counts': defaultdict(<class 'int'>, {'CWE-NVD-noinfo': 3}), 'total_samples': 5, 'distribution': [{'cwes': ['CWE-NVD-noinfo'], 'frequency': 3, 'proportion': 0.6}, {'cwes': [], 'frequency': 2, 'proportion': 0.4}]}, 75: {'cwe_counts': defaultdict(<class 'int'>, {'CWE-NVD-noinfo': 5}), 'total_samples': 10, 'distribution': [{'cwes': ['CWE-NVD-noinfo'], 'frequency': 5, 'proportion': 0.5}, {'cwes': [], 'frequency': 5, 'proportion': 0.5}]}, 70: {'cwe_counts': defaultdict(<class 'int'>, {'CWE-NVD-noinfo': 29, 'CWE-NVD-Other': 8, 'CWE-863': 3, 'CWE-284': 1}), 'total_samples': 59, 'distribution': [{'cwes': ['CWE-NVD-noinfo'], 'frequency': 29, 'proportion': 0.492}, {'cwes': [], 'frequency': 18, 'proportion': 0.305}, {'cwes': ['CWE-NVD-Other'], 'frequency': 8, 'proportion': 0.136}, {'cwes': ['CWE-863'], 'frequency': 3, 'proportion': 0.051}, {'cwes': ['CWE-284'], 'frequency': 1, 'proportion': 0.017}]}}, 'cwe_consensus': 'CWE-NVD-noinfo', 'similarity_stats': {'thresholds': [95, 90, 85, 80, 75, 70], 'total_samples_by_threshold': {95: 3, 90: 4, 85: 4, 80: 5, 75: 10, 70: 59}, 'top_cwes_by_threshold': {95: [('CWE-NVD-noinfo', 1)], 90: [('CWE-NVD-noinfo', 2)], 85: [('CWE-NVD-noinfo', 2)], 80: [('CWE-NVD-noinfo', 3)], 75: [('CWE-NVD-noinfo', 5)], 70: [('CWE-NVD-noinfo', 29), ('CWE-NVD-Other', 8), ('CWE-863', 3)]}}, 'raw_matches': [{'similarity': 95, 'cwes': [], 'total': 3, 'frequency': 2, 'proportion': 0.667}, {'similarity': 95, 'cwes': ['NVD-noinfo'], 'total': 3, 'frequency': 1, 'proportion': 0.333}, {'similarity': 90, 'cwes': ['NVD-noinfo'], 'total': 4, 'frequency': 2, 'proportion': 0.5}, {'similarity': 90, 'cwes': [], 'total': 4, 'frequency': 2, 'proportion': 0.5}, {'similarity': 85, 'cwes': ['NVD-noinfo'], 'total': 4, 'frequency': 2, 'proportion': 0.5}, {'similarity': 85, 'cwes': [], 'total': 4, 'frequency': 2, 'proportion': 0.5}, {'similarity': 80, 'cwes': ['NVD-noinfo'], 'total': 5, 'frequency': 3, 'proportion': 0.6}, {'similarity': 80, 'cwes': [], 'total': 5, 'frequency': 2, 'proportion': 0.4}, {'similarity': 75, 'cwes': ['NVD-noinfo'], 'total': 10, 'frequency': 5, 'proportion': 0.5}, {'similarity': 75, 'cwes': [], 'total': 10, 'frequency': 5, 'proportion': 0.5}, {'similarity': 70, 'cwes': ['NVD-noinfo'], 'total': 59, 'frequency': 29, 'proportion': 0.492}, {'similarity': 70, 'cwes': [], 'total': 59, 'frequency': 18, 'proportion': 0.305}, {'similarity': 70, 'cwes': ['NVD-Other'], 'total': 59, 'frequency': 8, 'proportion': 0.136}, {'similarity': 70, 'cwes': ['863'], 'total': 59, 'frequency': 3, 'proportion': 0.051}, {'similarity': 70, 'cwes': ['284'], 'total': 59, 'frequency': 1, 'proportion': 0.017}]}, similarity_summary=SimilarityInsight(consensus_cwe='CWE-NVD-noinfo', top_cwes=[('CWE-NVD-noinfo', 42), ('CWE-NVD-Other', 8), ('CWE-863', 3)], confidence_levels={'high': [], 'medium': [], 'low': []}, total_samples=85), analysis='', analysis_with_relationships='', criticism='', resolution='', relevant_cwes=[{'metadata': {'doc_id': '20', 'name': 'Improper Input Validation', 'source': 'sparse', 'original_content': 'The product receives input or data, but it does\\n        not validate or incorrectly validates that the input has the\\n        properties that are required to process the data safely and\\n        correctly.', 'keyphrase_sources': [{'id': 'rootcause:Improper Input Validation', 'keyphrase': 'Improper Input Validation', 'type': 'rootcause'}, {'id': 'rootcause:Input Validation vulnerability', 'keyphrase': 'Input Validation vulnerability', 'type': 'rootcause'}, {'id': 'impact:integrity', 'keyphrase': 'integrity', 'type': 'impact'}, {'id': 'impact:security feature bypass', 'keyphrase': 'security feature bypass', 'type': 'impact'}, {'id': 'attacker:low-privileged attacker', 'keyphrase': 'low-privileged attacker', 'type': 'attacker'}, {'id': 'version:6.5.20 and earlier', 'keyphrase': '6.5.20 and earlier', 'type': 'version'}]}, 'similarity': np.float64(346.19443008865545)}, {'metadata': {'doc_id': '787', 'name': 'Out-of-bounds Write', 'source': 'sparse', 'original_content': 'The product writes data past the end, or before the beginning, of the intended buffer.', 'keyphrase_sources': [{'id': 'rootcause:Improper Input Validation', 'keyphrase': 'Improper Input Validation', 'type': 'rootcause'}, {'id': 'rootcause:Input Validation vulnerability', 'keyphrase': 'Input Validation vulnerability', 'type': 'rootcause'}, {'id': 'impact:integrity', 'keyphrase': 'integrity', 'type': 'impact'}, {'id': 'product:Adobe Experience Manager', 'keyphrase': 'Adobe Experience Manager', 'type': 'product'}, {'id': 'version:6.5.20 and earlier', 'keyphrase': '6.5.20 and earlier', 'type': 'version'}]}, 'similarity': np.float64(325.1815190196035)}, {'metadata': {'doc_id': '285', 'name': 'Improper Authorization', 'source': 'sparse', 'original_content': 'The product does not perform or incorrectly performs an authorization check when an actor attempts to access a resource or perform an action.', 'keyphrase_sources': [{'id': 'rootcause:Improper Input Validation', 'keyphrase': 'Improper Input Validation', 'type': 'rootcause'}, {'id': 'rootcause:Input Validation vulnerability', 'keyphrase': 'Input Validation vulnerability', 'type': 'rootcause'}, {'id': 'impact:integrity', 'keyphrase': 'integrity', 'type': 'impact'}, {'id': 'impact:security feature bypass', 'keyphrase': 'security feature bypass', 'type': 'impact'}, {'id': 'attacker:low-privileged attacker', 'keyphrase': 'low-privileged attacker', 'type': 'attacker'}, {'id': 'product:Adobe Experience Manager', 'keyphrase': 'Adobe Experience Manager', 'type': 'product'}, {'id': 'version:6.5.20 and earlier', 'keyphrase': '6.5.20 and earlier', 'type': 'version'}]}, 'similarity': np.float64(318.7396246456584)}, {'metadata': {'doc_id': '367', 'name': 'Time-of-check Time-of-use (TOCTOU) Race Condition', 'source': 'sparse', 'original_content': \"The product checks the state of a resource before using that resource, but the resource's state can change between the check and the use in a way that invalidates the results of the check. This can cause the product to perform invalid actions when the resource is in an unexpected state.\", 'keyphrase_sources': [{'id': 'rootcause:Improper Input Validation', 'keyphrase': 'Improper Input Validation', 'type': 'rootcause'}, {'id': 'rootcause:Input Validation vulnerability', 'keyphrase': 'Input Validation vulnerability', 'type': 'rootcause'}, {'id': 'impact:integrity', 'keyphrase': 'integrity', 'type': 'impact'}, {'id': 'impact:security feature bypass', 'keyphrase': 'security feature bypass', 'type': 'impact'}, {'id': 'attacker:low-privileged attacker', 'keyphrase': 'low-privileged attacker', 'type': 'attacker'}, {'id': 'version:6.5.20 and earlier', 'keyphrase': '6.5.20 and earlier', 'type': 'version'}]}, 'similarity': np.float64(317.40010204576237)}, {'metadata': {'doc_id': '665', 'name': 'Improper Initialization', 'source': 'sparse', 'original_content': 'The product does not initialize or incorrectly initializes a resource, which might leave the resource in an unexpected state when it is accessed or used.', 'keyphrase_sources': [{'id': 'rootcause:Improper Input Validation', 'keyphrase': 'Improper Input Validation', 'type': 'rootcause'}]}, 'similarity': np.float64(316.1494106730263)}, {'metadata': {'doc_id': '657', 'name': 'Violation of Secure Design Principles', 'source': 'sparse', 'original_content': 'The product violates well-established principles for secure design.', 'keyphrase_sources': [{'id': 'rootcause:Input Validation vulnerability', 'keyphrase': 'Input Validation vulnerability', 'type': 'rootcause'}, {'id': 'impact:integrity', 'keyphrase': 'integrity', 'type': 'impact'}, {'id': 'impact:security feature bypass', 'keyphrase': 'security feature bypass', 'type': 'impact'}, {'id': 'attacker:low-privileged attacker', 'keyphrase': 'low-privileged attacker', 'type': 'attacker'}, {'id': 'product:Adobe Experience Manager', 'keyphrase': 'Adobe Experience Manager', 'type': 'product'}, {'id': 'version:6.5.20 and earlier', 'keyphrase': '6.5.20 and earlier', 'type': 'version'}]}, 'similarity': np.float64(315.45919931532586)}, {'metadata': {'doc_id': '732', 'name': 'Incorrect Permission Assignment for Critical Resource', 'source': 'sparse', 'original_content': 'The product specifies permissions for a security-critical resource in a way that allows that resource to be read or modified by unintended actors.', 'keyphrase_sources': [{'id': 'attacker:low-privileged attacker', 'keyphrase': 'low-privileged attacker', 'type': 'attacker'}]}, 'similarity': np.float64(117.33053987153421)}, {'metadata': {'doc_id': '379', 'name': 'Creation of Temporary File in Directory with Insecure Permissions', 'source': 'sparse', 'original_content': \"The product creates a temporary file in a directory whose permissions allow unintended actors to determine the file's existence or otherwise access that file.\", 'keyphrase_sources': [{'id': 'product:Adobe Experience Manager', 'keyphrase': 'Adobe Experience Manager', 'type': 'product'}]}, 'similarity': np.float64(115.69533455422338)}, {'metadata': {'doc_id': '788', 'name': 'Access of Memory Location After End of Buffer', 'source': 'sparse', 'original_content': 'The product reads or writes to a buffer using an index or pointer that references a memory location after the end of the buffer.', 'keyphrase_sources': [{'id': 'product:Adobe Experience Manager', 'keyphrase': 'Adobe Experience Manager', 'type': 'product'}]}, 'similarity': np.float64(112.70056888923406)}, {'metadata': {'doc_id': '863', 'name': 'Incorrect Authorization', 'source': 'sparse', 'original_content': 'The product performs an authorization check when an actor attempts to access a resource or perform an action, but it does not correctly perform the check.', 'keyphrase_sources': [{'id': 'impact:security feature bypass', 'keyphrase': 'security feature bypass', 'type': 'impact'}]}, 'similarity': np.float64(104.65680116625914)}], identified_cwes={'analyzer': [], 'critic_additional': []})",
  "retrieval_results": {
    "has_multiple_keyphrases": true,
    "keyphrase_cwe_sets": {
      "rootcause:Improper Input Validation": {
        "keyphrase": "Improper Input Validation",
        "type": "rootcause",
        "cwes": [
          {
            "metadata": {
              "doc_id": "20",
              "name": "Improper Input Validation",
              "source": "sparse",
              "original_content": "The product receives input or data, but it does\n        not validate or incorrectly validates that the input has the\n        properties that are required to process the data safely and\n        correctly.",
              "keyphrase_sources": [
                {
                  "id": "rootcause:Improper Input Validation",
                  "keyphrase": "Improper Input Validation",
                  "type": "rootcause"
                },
                {
                  "id": "rootcause:Input Validation vulnerability",
                  "keyphrase": "Input Validation vulnerability",
                  "type": "rootcause"
                },
                {
                  "id": "impact:integrity",
                  "keyphrase": "integrity",
                  "type": "impact"
                },
                {
                  "id": "impact:security feature bypass",
                  "keyphrase": "security feature bypass",
                  "type": "impact"
                },
                {
                  "id": "attacker:low-privileged attacker",
                  "keyphrase": "low-privileged attacker",
                  "type": "attacker"
                },
                {
                  "id": "version:6.5.20 and earlier",
                  "keyphrase": "6.5.20 and earlier",
                  "type": "version"
                }
              ]
            },
            "similarity": 346.19443008865545
          },
          {
            "metadata": {
              "doc_id": "787",
              "name": "Out-of-bounds Write",
              "source": "sparse",
              "original_content": "The product writes data past the end, or before the beginning, of the intended buffer.",
              "keyphrase_sources": [
                {
                  "id": "rootcause:Improper Input Validation",
                  "keyphrase": "Improper Input Validation",
                  "type": "rootcause"
                },
                {
                  "id": "rootcause:Input Validation vulnerability",
                  "keyphrase": "Input Validation vulnerability",
                  "type": "rootcause"
                },
                {
                  "id": "impact:integrity",
                  "keyphrase": "integrity",
                  "type": "impact"
                },
                {
                  "id": "product:Adobe Experience Manager",
                  "keyphrase": "Adobe Experience Manager",
                  "type": "product"
                },
                {
                  "id": "version:6.5.20 and earlier",
                  "keyphrase": "6.5.20 and earlier",
                  "type": "version"
                }
              ]
            },
            "similarity": 325.1815190196035
          },
          {
            "metadata": {
              "doc_id": "285",
              "name": "Improper Authorization",
              "source": "sparse",
              "original_content": "The product does not perform or incorrectly performs an authorization check when an actor attempts to access a resource or perform an action.",
              "keyphrase_sources": [
                {
                  "id": "rootcause:Improper Input Validation",
                  "keyphrase": "Improper Input Validation",
                  "type": "rootcause"
                },
                {
                  "id": "rootcause:Input Validation vulnerability",
                  "keyphrase": "Input Validation vulnerability",
                  "type": "rootcause"
                },
                {
                  "id": "impact:integrity",
                  "keyphrase": "integrity",
                  "type": "impact"
                },
                {
                  "id": "impact:security feature bypass",
                  "keyphrase": "security feature bypass",
                  "type": "impact"
                },
                {
                  "id": "attacker:low-privileged attacker",
                  "keyphrase": "low-privileged attacker",
                  "type": "attacker"
                },
                {
                  "id": "product:Adobe Experience Manager",
                  "keyphrase": "Adobe Experience Manager",
                  "type": "product"
                },
                {
                  "id": "version:6.5.20 and earlier",
                  "keyphrase": "6.5.20 and earlier",
                  "type": "version"
                }
              ]
            },
            "similarity": 318.7396246456584
          },
          {
            "metadata": {
              "doc_id": "367",
              "name": "Time-of-check Time-of-use (TOCTOU) Race Condition",
              "source": "sparse",
              "original_content": "The product checks the state of a resource before using that resource, but the resource's state can change between the check and the use in a way that invalidates the results of the check. This can cause the product to perform invalid actions when the resource is in an unexpected state.",
              "keyphrase_sources": [
                {
                  "id": "rootcause:Improper Input Validation",
                  "keyphrase": "Improper Input Validation",
                  "type": "rootcause"
                },
                {
                  "id": "rootcause:Input Validation vulnerability",
                  "keyphrase": "Input Validation vulnerability",
                  "type": "rootcause"
                },
                {
                  "id": "impact:integrity",
                  "keyphrase": "integrity",
                  "type": "impact"
                },
                {
                  "id": "impact:security feature bypass",
                  "keyphrase": "security feature bypass",
                  "type": "impact"
                },
                {
                  "id": "attacker:low-privileged attacker",
                  "keyphrase": "low-privileged attacker",
                  "type": "attacker"
                },
                {
                  "id": "version:6.5.20 and earlier",
                  "keyphrase": "6.5.20 and earlier",
                  "type": "version"
                }
              ]
            },
            "similarity": 317.40010204576237
          },
          {
            "metadata": {
              "doc_id": "665",
              "name": "Improper Initialization",
              "source": "sparse",
              "original_content": "The product does not initialize or incorrectly initializes a resource, which might leave the resource in an unexpected state when it is accessed or used.",
              "keyphrase_sources": [
                {
                  "id": "rootcause:Improper Input Validation",
                  "keyphrase": "Improper Input Validation",
                  "type": "rootcause"
                }
              ]
            },
            "similarity": 316.1494106730263
          }
        ]
      },
      "rootcause:Input Validation vulnerability": {
        "keyphrase": "Input Validation vulnerability",
        "type": "rootcause",
        "cwes": [
          {
            "metadata": {
              "doc_id": "20",
              "name": "Improper Input Validation",
              "source": "sparse",
              "original_content": "The product receives input or data, but it does\n        not validate or incorrectly validates that the input has the\n        properties that are required to process the data safely and\n        correctly."
            },
            "similarity": 341.441451571221
          },
          {
            "metadata": {
              "doc_id": "787",
              "name": "Out-of-bounds Write",
              "source": "sparse",
              "original_content": "The product writes data past the end, or before the beginning, of the intended buffer."
            },
            "similarity": 324.63278754172666
          },
          {
            "metadata": {
              "doc_id": "657",
              "name": "Violation of Secure Design Principles",
              "source": "sparse",
              "original_content": "The product violates well-established principles for secure design.",
              "keyphrase_sources": [
                {
                  "id": "rootcause:Input Validation vulnerability",
                  "keyphrase": "Input Validation vulnerability",
                  "type": "rootcause"
                },
                {
                  "id": "impact:integrity",
                  "keyphrase": "integrity",
                  "type": "impact"
                },
                {
                  "id": "impact:security feature bypass",
                  "keyphrase": "security feature bypass",
                  "type": "impact"
                },
                {
                  "id": "attacker:low-privileged attacker",
                  "keyphrase": "low-privileged attacker",
                  "type": "attacker"
                },
                {
                  "id": "product:Adobe Experience Manager",
                  "keyphrase": "Adobe Experience Manager",
                  "type": "product"
                },
                {
                  "id": "version:6.5.20 and earlier",
                  "keyphrase": "6.5.20 and earlier",
                  "type": "version"
                }
              ]
            },
            "similarity": 315.45919931532586
          },
          {
            "metadata": {
              "doc_id": "367",
              "name": "Time-of-check Time-of-use (TOCTOU) Race Condition",
              "source": "sparse",
              "original_content": "The product checks the state of a resource before using that resource, but the resource's state can change between the check and the use in a way that invalidates the results of the check. This can cause the product to perform invalid actions when the resource is in an unexpected state."
            },
            "similarity": 315.10980984266973
          },
          {
            "metadata": {
              "doc_id": "285",
              "name": "Improper Authorization",
              "source": "sparse",
              "original_content": "The product does not perform or incorrectly performs an authorization check when an actor attempts to access a resource or perform an action."
            },
            "similarity": 313.86844115222175
          }
        ]
      },
      "impact:integrity": {
        "keyphrase": "integrity",
        "type": "impact",
        "cwes": [
          {
            "metadata": {
              "doc_id": "787",
              "name": "Out-of-bounds Write",
              "source": "sparse",
              "original_content": "The product writes data past the end, or before the beginning, of the intended buffer."
            },
            "similarity": 105.12404396419825
          },
          {
            "metadata": {
              "doc_id": "285",
              "name": "Improper Authorization",
              "source": "sparse",
              "original_content": "The product does not perform or incorrectly performs an authorization check when an actor attempts to access a resource or perform an action."
            },
            "similarity": 104.4574338449465
          },
          {
            "metadata": {
              "doc_id": "657",
              "name": "Violation of Secure Design Principles",
              "source": "sparse",
              "original_content": "The product violates well-established principles for secure design."
            },
            "similarity": 104.30812502488348
          },
          {
            "metadata": {
              "doc_id": "20",
              "name": "Improper Input Validation",
              "source": "sparse",
              "original_content": "The product receives input or data, but it does\n        not validate or incorrectly validates that the input has the\n        properties that are required to process the data safely and\n        correctly."
            },
            "similarity": 103.81928610929583
          },
          {
            "metadata": {
              "doc_id": "367",
              "name": "Time-of-check Time-of-use (TOCTOU) Race Condition",
              "source": "sparse",
              "original_content": "The product checks the state of a resource before using that resource, but the resource's state can change between the check and the use in a way that invalidates the results of the check. This can cause the product to perform invalid actions when the resource is in an unexpected state."
            },
            "similarity": 103.38104906273021
          }
        ]
      },
      "impact:security feature bypass": {
        "keyphrase": "security feature bypass",
        "type": "impact",
        "cwes": [
          {
            "metadata": {
              "doc_id": "657",
              "name": "Violation of Secure Design Principles",
              "source": "sparse",
              "original_content": "The product violates well-established principles for secure design."
            },
            "similarity": 113.81134828995226
          },
          {
            "metadata": {
              "doc_id": "285",
              "name": "Improper Authorization",
              "source": "sparse",
              "original_content": "The product does not perform or incorrectly performs an authorization check when an actor attempts to access a resource or perform an action."
            },
            "similarity": 108.86981467573476
          },
          {
            "metadata": {
              "doc_id": "20",
              "name": "Improper Input Validation",
              "source": "sparse",
              "original_content": "The product receives input or data, but it does\n        not validate or incorrectly validates that the input has the\n        properties that are required to process the data safely and\n        correctly."
            },
            "similarity": 106.88842935852821
          },
          {
            "metadata": {
              "doc_id": "367",
              "name": "Time-of-check Time-of-use (TOCTOU) Race Condition",
              "source": "sparse",
              "original_content": "The product checks the state of a resource before using that resource, but the resource's state can change between the check and the use in a way that invalidates the results of the check. This can cause the product to perform invalid actions when the resource is in an unexpected state."
            },
            "similarity": 104.71820407724069
          },
          {
            "metadata": {
              "doc_id": "863",
              "name": "Incorrect Authorization",
              "source": "sparse",
              "original_content": "The product performs an authorization check when an actor attempts to access a resource or perform an action, but it does not correctly perform the check.",
              "keyphrase_sources": [
                {
                  "id": "impact:security feature bypass",
                  "keyphrase": "security feature bypass",
                  "type": "impact"
                }
              ]
            },
            "similarity": 104.65680116625914
          }
        ]
      },
      "attacker:low-privileged attacker": {
        "keyphrase": "low-privileged attacker",
        "type": "attacker",
        "cwes": [
          {
            "metadata": {
              "doc_id": "285",
              "name": "Improper Authorization",
              "source": "sparse",
              "original_content": "The product does not perform or incorrectly performs an authorization check when an actor attempts to access a resource or perform an action."
            },
            "similarity": 119.29843906171642
          },
          {
            "metadata": {
              "doc_id": "732",
              "name": "Incorrect Permission Assignment for Critical Resource",
              "source": "sparse",
              "original_content": "The product specifies permissions for a security-critical resource in a way that allows that resource to be read or modified by unintended actors.",
              "keyphrase_sources": [
                {
                  "id": "attacker:low-privileged attacker",
                  "keyphrase": "low-privileged attacker",
                  "type": "attacker"
                }
              ]
            },
            "similarity": 117.33053987153421
          },
          {
            "metadata": {
              "doc_id": "657",
              "name": "Violation of Secure Design Principles",
              "source": "sparse",
              "original_content": "The product violates well-established principles for secure design."
            },
            "similarity": 116.23292937773726
          },
          {
            "metadata": {
              "doc_id": "367",
              "name": "Time-of-check Time-of-use (TOCTOU) Race Condition",
              "source": "sparse",
              "original_content": "The product checks the state of a resource before using that resource, but the resource's state can change between the check and the use in a way that invalidates the results of the check. This can cause the product to perform invalid actions when the resource is in an unexpected state."
            },
            "similarity": 114.60253196692334
          },
          {
            "metadata": {
              "doc_id": "20",
              "name": "Improper Input Validation",
              "source": "sparse",
              "original_content": "The product receives input or data, but it does\n        not validate or incorrectly validates that the input has the\n        properties that are required to process the data safely and\n        correctly."
            },
            "similarity": 114.58785709993313
          }
        ]
      },
      "product:Adobe Experience Manager": {
        "keyphrase": "Adobe Experience Manager",
        "type": "product",
        "cwes": [
          {
            "metadata": {
              "doc_id": "657",
              "name": "Violation of Secure Design Principles",
              "source": "sparse",
              "original_content": "The product violates well-established principles for secure design."
            },
            "similarity": 130.65016944004043
          },
          {
            "metadata": {
              "doc_id": "379",
              "name": "Creation of Temporary File in Directory with Insecure Permissions",
              "source": "sparse",
              "original_content": "The product creates a temporary file in a directory whose permissions allow unintended actors to determine the file's existence or otherwise access that file.",
              "keyphrase_sources": [
                {
                  "id": "product:Adobe Experience Manager",
                  "keyphrase": "Adobe Experience Manager",
                  "type": "product"
                }
              ]
            },
            "similarity": 115.69533455422338
          },
          {
            "metadata": {
              "doc_id": "788",
              "name": "Access of Memory Location After End of Buffer",
              "source": "sparse",
              "original_content": "The product reads or writes to a buffer using an index or pointer that references a memory location after the end of the buffer.",
              "keyphrase_sources": [
                {
                  "id": "product:Adobe Experience Manager",
                  "keyphrase": "Adobe Experience Manager",
                  "type": "product"
                }
              ]
            },
            "similarity": 112.70056888923406
          },
          {
            "metadata": {
              "doc_id": "787",
              "name": "Out-of-bounds Write",
              "source": "sparse",
              "original_content": "The product writes data past the end, or before the beginning, of the intended buffer."
            },
            "similarity": 112.49512635697545
          },
          {
            "metadata": {
              "doc_id": "285",
              "name": "Improper Authorization",
              "source": "sparse",
              "original_content": "The product does not perform or incorrectly performs an authorization check when an actor attempts to access a resource or perform an action."
            },
            "similarity": 110.72914914556132
          }
        ]
      },
      "version:6.5.20 and earlier": {
        "keyphrase": "6.5.20 and earlier",
        "type": "version",
        "cwes": [
          {
            "metadata": {
              "doc_id": "657",
              "name": "Violation of Secure Design Principles",
              "source": "sparse",
              "original_content": "The product violates well-established principles for secure design."
            },
            "similarity": 128.4390177210591
          },
          {
            "metadata": {
              "doc_id": "285",
              "name": "Improper Authorization",
              "source": "sparse",
              "original_content": "The product does not perform or incorrectly performs an authorization check when an actor attempts to access a resource or perform an action."
            },
            "similarity": 125.12764025102153
          },
          {
            "metadata": {
              "doc_id": "787",
              "name": "Out-of-bounds Write",
              "source": "sparse",
              "original_content": "The product writes data past the end, or before the beginning, of the intended buffer."
            },
            "similarity": 124.97482088464997
          },
          {
            "metadata": {
              "doc_id": "20",
              "name": "Improper Input Validation",
              "source": "sparse",
              "original_content": "The product receives input or data, but it does\n        not validate or incorrectly validates that the input has the\n        properties that are required to process the data safely and\n        correctly."
            },
            "similarity": 124.40868593698724
          },
          {
            "metadata": {
              "doc_id": "367",
              "name": "Time-of-check Time-of-use (TOCTOU) Race Condition",
              "source": "sparse",
              "original_content": "The product checks the state of a resource before using that resource, but the resource's state can change between the check and the use in a way that invalidates the results of the check. This can cause the product to perform invalid actions when the resource is in an unexpected state."
            },
            "similarity": 122.71316416226402
          }
        ]
      }
    },
    "keyphrase_mapping": {
      "20": [
        {
          "id": "rootcause:Improper Input Validation",
          "keyphrase": "Improper Input Validation",
          "type": "rootcause"
        },
        {
          "id": "rootcause:Input Validation vulnerability",
          "keyphrase": "Input Validation vulnerability",
          "type": "rootcause"
        },
        {
          "id": "impact:integrity",
          "keyphrase": "integrity",
          "type": "impact"
        },
        {
          "id": "impact:security feature bypass",
          "keyphrase": "security feature bypass",
          "type": "impact"
        },
        {
          "id": "attacker:low-privileged attacker",
          "keyphrase": "low-privileged attacker",
          "type": "attacker"
        },
        {
          "id": "version:6.5.20 and earlier",
          "keyphrase": "6.5.20 and earlier",
          "type": "version"
        }
      ],
      "787": [
        {
          "id": "rootcause:Improper Input Validation",
          "keyphrase": "Improper Input Validation",
          "type": "rootcause"
        },
        {
          "id": "rootcause:Input Validation vulnerability",
          "keyphrase": "Input Validation vulnerability",
          "type": "rootcause"
        },
        {
          "id": "impact:integrity",
          "keyphrase": "integrity",
          "type": "impact"
        },
        {
          "id": "product:Adobe Experience Manager",
          "keyphrase": "Adobe Experience Manager",
          "type": "product"
        },
        {
          "id": "version:6.5.20 and earlier",
          "keyphrase": "6.5.20 and earlier",
          "type": "version"
        }
      ],
      "285": [
        {
          "id": "rootcause:Improper Input Validation",
          "keyphrase": "Improper Input Validation",
          "type": "rootcause"
        },
        {
          "id": "rootcause:Input Validation vulnerability",
          "keyphrase": "Input Validation vulnerability",
          "type": "rootcause"
        },
        {
          "id": "impact:integrity",
          "keyphrase": "integrity",
          "type": "impact"
        },
        {
          "id": "impact:security feature bypass",
          "keyphrase": "security feature bypass",
          "type": "impact"
        },
        {
          "id": "attacker:low-privileged attacker",
          "keyphrase": "low-privileged attacker",
          "type": "attacker"
        },
        {
          "id": "product:Adobe Experience Manager",
          "keyphrase": "Adobe Experience Manager",
          "type": "product"
        },
        {
          "id": "version:6.5.20 and earlier",
          "keyphrase": "6.5.20 and earlier",
          "type": "version"
        }
      ],
      "367": [
        {
          "id": "rootcause:Improper Input Validation",
          "keyphrase": "Improper Input Validation",
          "type": "rootcause"
        },
        {
          "id": "rootcause:Input Validation vulnerability",
          "keyphrase": "Input Validation vulnerability",
          "type": "rootcause"
        },
        {
          "id": "impact:integrity",
          "keyphrase": "integrity",
          "type": "impact"
        },
        {
          "id": "impact:security feature bypass",
          "keyphrase": "security feature bypass",
          "type": "impact"
        },
        {
          "id": "attacker:low-privileged attacker",
          "keyphrase": "low-privileged attacker",
          "type": "attacker"
        },
        {
          "id": "version:6.5.20 and earlier",
          "keyphrase": "6.5.20 and earlier",
          "type": "version"
        }
      ],
      "665": [
        {
          "id": "rootcause:Improper Input Validation",
          "keyphrase": "Improper Input Validation",
          "type": "rootcause"
        }
      ],
      "657": [
        {
          "id": "rootcause:Input Validation vulnerability",
          "keyphrase": "Input Validation vulnerability",
          "type": "rootcause"
        },
        {
          "id": "impact:integrity",
          "keyphrase": "integrity",
          "type": "impact"
        },
        {
          "id": "impact:security feature bypass",
          "keyphrase": "security feature bypass",
          "type": "impact"
        },
        {
          "id": "attacker:low-privileged attacker",
          "keyphrase": "low-privileged attacker",
          "type": "attacker"
        },
        {
          "id": "product:Adobe Experience Manager",
          "keyphrase": "Adobe Experience Manager",
          "type": "product"
        },
        {
          "id": "version:6.5.20 and earlier",
          "keyphrase": "6.5.20 and earlier",
          "type": "version"
        }
      ],
      "863": [
        {
          "id": "impact:security feature bypass",
          "keyphrase": "security feature bypass",
          "type": "impact"
        }
      ],
      "732": [
        {
          "id": "attacker:low-privileged attacker",
          "keyphrase": "low-privileged attacker",
          "type": "attacker"
        }
      ],
      "379": [
        {
          "id": "product:Adobe Experience Manager",
          "keyphrase": "Adobe Experience Manager",
          "type": "product"
        }
      ],
      "788": [
        {
          "id": "product:Adobe Experience Manager",
          "keyphrase": "Adobe Experience Manager",
          "type": "product"
        }
      ]
    },
    "relevant_cwes": [
      {
        "metadata": {
          "doc_id": "20",
          "name": "Improper Input Validation",
          "source": "sparse",
          "original_content": "The product receives input or data, but it does\n        not validate or incorrectly validates that the input has the\n        properties that are required to process the data safely and\n        correctly.",
          "keyphrase_sources": [
            {
              "id": "rootcause:Improper Input Validation",
              "keyphrase": "Improper Input Validation",
              "type": "rootcause"
            },
            {
              "id": "rootcause:Input Validation vulnerability",
              "keyphrase": "Input Validation vulnerability",
              "type": "rootcause"
            },
            {
              "id": "impact:integrity",
              "keyphrase": "integrity",
              "type": "impact"
            },
            {
              "id": "impact:security feature bypass",
              "keyphrase": "security feature bypass",
              "type": "impact"
            },
            {
              "id": "attacker:low-privileged attacker",
              "keyphrase": "low-privileged attacker",
              "type": "attacker"
            },
            {
              "id": "version:6.5.20 and earlier",
              "keyphrase": "6.5.20 and earlier",
              "type": "version"
            }
          ]
        },
        "similarity": 346.19443008865545
      },
      {
        "metadata": {
          "doc_id": "787",
          "name": "Out-of-bounds Write",
          "source": "sparse",
          "original_content": "The product writes data past the end, or before the beginning, of the intended buffer.",
          "keyphrase_sources": [
            {
              "id": "rootcause:Improper Input Validation",
              "keyphrase": "Improper Input Validation",
              "type": "rootcause"
            },
            {
              "id": "rootcause:Input Validation vulnerability",
              "keyphrase": "Input Validation vulnerability",
              "type": "rootcause"
            },
            {
              "id": "impact:integrity",
              "keyphrase": "integrity",
              "type": "impact"
            },
            {
              "id": "product:Adobe Experience Manager",
              "keyphrase": "Adobe Experience Manager",
              "type": "product"
            },
            {
              "id": "version:6.5.20 and earlier",
              "keyphrase": "6.5.20 and earlier",
              "type": "version"
            }
          ]
        },
        "similarity": 325.1815190196035
      },
      {
        "metadata": {
          "doc_id": "285",
          "name": "Improper Authorization",
          "source": "sparse",
          "original_content": "The product does not perform or incorrectly performs an authorization check when an actor attempts to access a resource or perform an action.",
          "keyphrase_sources": [
            {
              "id": "rootcause:Improper Input Validation",
              "keyphrase": "Improper Input Validation",
              "type": "rootcause"
            },
            {
              "id": "rootcause:Input Validation vulnerability",
              "keyphrase": "Input Validation vulnerability",
              "type": "rootcause"
            },
            {
              "id": "impact:integrity",
              "keyphrase": "integrity",
              "type": "impact"
            },
            {
              "id": "impact:security feature bypass",
              "keyphrase": "security feature bypass",
              "type": "impact"
            },
            {
              "id": "attacker:low-privileged attacker",
              "keyphrase": "low-privileged attacker",
              "type": "attacker"
            },
            {
              "id": "product:Adobe Experience Manager",
              "keyphrase": "Adobe Experience Manager",
              "type": "product"
            },
            {
              "id": "version:6.5.20 and earlier",
              "keyphrase": "6.5.20 and earlier",
              "type": "version"
            }
          ]
        },
        "similarity": 318.7396246456584
      },
      {
        "metadata": {
          "doc_id": "367",
          "name": "Time-of-check Time-of-use (TOCTOU) Race Condition",
          "source": "sparse",
          "original_content": "The product checks the state of a resource before using that resource, but the resource's state can change between the check and the use in a way that invalidates the results of the check. This can cause the product to perform invalid actions when the resource is in an unexpected state.",
          "keyphrase_sources": [
            {
              "id": "rootcause:Improper Input Validation",
              "keyphrase": "Improper Input Validation",
              "type": "rootcause"
            },
            {
              "id": "rootcause:Input Validation vulnerability",
              "keyphrase": "Input Validation vulnerability",
              "type": "rootcause"
            },
            {
              "id": "impact:integrity",
              "keyphrase": "integrity",
              "type": "impact"
            },
            {
              "id": "impact:security feature bypass",
              "keyphrase": "security feature bypass",
              "type": "impact"
            },
            {
              "id": "attacker:low-privileged attacker",
              "keyphrase": "low-privileged attacker",
              "type": "attacker"
            },
            {
              "id": "version:6.5.20 and earlier",
              "keyphrase": "6.5.20 and earlier",
              "type": "version"
            }
          ]
        },
        "similarity": 317.40010204576237
      },
      {
        "metadata": {
          "doc_id": "665",
          "name": "Improper Initialization",
          "source": "sparse",
          "original_content": "The product does not initialize or incorrectly initializes a resource, which might leave the resource in an unexpected state when it is accessed or used.",
          "keyphrase_sources": [
            {
              "id": "rootcause:Improper Input Validation",
              "keyphrase": "Improper Input Validation",
              "type": "rootcause"
            }
          ]
        },
        "similarity": 316.1494106730263
      },
      {
        "metadata": {
          "doc_id": "657",
          "name": "Violation of Secure Design Principles",
          "source": "sparse",
          "original_content": "The product violates well-established principles for secure design.",
          "keyphrase_sources": [
            {
              "id": "rootcause:Input Validation vulnerability",
              "keyphrase": "Input Validation vulnerability",
              "type": "rootcause"
            },
            {
              "id": "impact:integrity",
              "keyphrase": "integrity",
              "type": "impact"
            },
            {
              "id": "impact:security feature bypass",
              "keyphrase": "security feature bypass",
              "type": "impact"
            },
            {
              "id": "attacker:low-privileged attacker",
              "keyphrase": "low-privileged attacker",
              "type": "attacker"
            },
            {
              "id": "product:Adobe Experience Manager",
              "keyphrase": "Adobe Experience Manager",
              "type": "product"
            },
            {
              "id": "version:6.5.20 and earlier",
              "keyphrase": "6.5.20 and earlier",
              "type": "version"
            }
          ]
        },
        "similarity": 315.45919931532586
      },
      {
        "metadata": {
          "doc_id": "732",
          "name": "Incorrect Permission Assignment for Critical Resource",
          "source": "sparse",
          "original_content": "The product specifies permissions for a security-critical resource in a way that allows that resource to be read or modified by unintended actors.",
          "keyphrase_sources": [
            {
              "id": "attacker:low-privileged attacker",
              "keyphrase": "low-privileged attacker",
              "type": "attacker"
            }
          ]
        },
        "similarity": 117.33053987153421
      },
      {
        "metadata": {
          "doc_id": "379",
          "name": "Creation of Temporary File in Directory with Insecure Permissions",
          "source": "sparse",
          "original_content": "The product creates a temporary file in a directory whose permissions allow unintended actors to determine the file's existence or otherwise access that file.",
          "keyphrase_sources": [
            {
              "id": "product:Adobe Experience Manager",
              "keyphrase": "Adobe Experience Manager",
              "type": "product"
            }
          ]
        },
        "similarity": 115.69533455422338
      },
      {
        "metadata": {
          "doc_id": "788",
          "name": "Access of Memory Location After End of Buffer",
          "source": "sparse",
          "original_content": "The product reads or writes to a buffer using an index or pointer that references a memory location after the end of the buffer.",
          "keyphrase_sources": [
            {
              "id": "product:Adobe Experience Manager",
              "keyphrase": "Adobe Experience Manager",
              "type": "product"
            }
          ]
        },
        "similarity": 112.70056888923406
      },
      {
        "metadata": {
          "doc_id": "863",
          "name": "Incorrect Authorization",
          "source": "sparse",
          "original_content": "The product performs an authorization check when an actor attempts to access a resource or perform an action, but it does not correctly perform the check.",
          "keyphrase_sources": [
            {
              "id": "impact:security feature bypass",
              "keyphrase": "security feature bypass",
              "type": "impact"
            }
          ]
        },
        "similarity": 104.65680116625914
      }
    ],
    "enhanced_query": "# Vulnerability Description\n\n    Adobe Experience Manager versions 6.5.20 and earlier are affected by an **Improper Input Validation** vulnerability that could result in a security feature bypass. A low-privileged attacker could leverage this vulnerability to bypass security measures and affect the integrity of the page. Exploitation of this issue requires user interaction.\n\n    # Keyphrase-Specific CWE Analysis\n    This vulnerability contains multiple keyphrases that may map to different CWEs. \n    Please analyze each keyphrase separately and determine the most appropriate CWE(s) for each.\n\n    ## ROOTCAUSE: 'Improper Input Validation'\n\nRelevant CWEs for this ROOTCAUSE:\n\n### 1. CWE-20: Improper Input Validation (Score: 346.19)\n\nThe product receives input or data, but it does\n        not validate or incorrectly validates that the input has the\n        properties that are required to process the data safely and\n        correctly....\n\n### 2. CWE-787: Out-of-bounds Write (Score: 325.18)\n\nThe product writes data past the end, or before the beginning, of the intended buffer....\n\n### 3. CWE-285: Improper Authorization (Score: 318.74)\n\nThe product does not perform or incorrectly performs an authorization check when an actor attempts to access a resource or perform an action....\n\n### 4. CWE-367: Time-of-check Time-of-use (TOCTOU) Race Condition (Score: 317.40)\n\nThe product checks the state of a resource before using that resource, but the resource's state can change between the check and the use in a way that invalidates the results of the check. This can cause the product to perform invalid actions when the resource is in an unexpected state....\n\n### 5. CWE-665: Improper Initialization (Score: 316.15)\n\nThe product does not initialize or incorrectly initializes a resource, which might leave the resource in an unexpected state when it is accessed or used....\n\n## ROOTCAUSE: 'Input Validation vulnerability'\n\nRelevant CWEs for this ROOTCAUSE:\n\n### 1. CWE-20: Improper Input Validation (Score: 346.19)\n\nThe product receives input or data, but it does\n        not validate or incorrectly validates that the input has the\n        properties that are required to process the data safely and\n        correctly....\n\n### 2. CWE-787: Out-of-bounds Write (Score: 325.18)\n\nThe product writes data past the end, or before the beginning, of the intended buffer....\n\n### 3. CWE-285: Improper Authorization (Score: 318.74)\n\nThe product does not perform or incorrectly performs an authorization check when an actor attempts to access a resource or perform an action....\n\n### 4. CWE-367: Time-of-check Time-of-use (TOCTOU) Race Condition (Score: 317.40)\n\nThe product checks the state of a resource before using that resource, but the resource's state can change between the check and the use in a way that invalidates the results of the check. This can cause the product to perform invalid actions when the resource is in an unexpected state....\n\n### 5. CWE-657: Violation of Secure Design Principles (Score: 315.46)\n\nThe product violates well-established principles for secure design....\n\n## IMPACT: 'integrity'\n\nRelevant CWEs for this IMPACT:\n\n### 1. CWE-20: Improper Input Validation (Score: 346.19)\n\nThe product receives input or data, but it does\n        not validate or incorrectly validates that the input has the\n        properties that are required to process the data safely and\n        correctly....\n\n### 2. CWE-787: Out-of-bounds Write (Score: 325.18)\n\nThe product writes data past the end, or before the beginning, of the intended buffer....\n\n### 3. CWE-285: Improper Authorization (Score: 318.74)\n\nThe product does not perform or incorrectly performs an authorization check when an actor attempts to access a resource or perform an action....\n\n### 4. CWE-367: Time-of-check Time-of-use (TOCTOU) Race Condition (Score: 317.40)\n\nThe product checks the state of a resource before using that resource, but the resource's state can change between the check and the use in a way that invalidates the results of the check. This can cause the product to perform invalid actions when the resource is in an unexpected state....\n\n### 5. CWE-657: Violation of Secure Design Principles (Score: 315.46)\n\nThe product violates well-established principles for secure design....\n\n## IMPACT: 'security feature bypass'\n\nRelevant CWEs for this IMPACT:\n\n### 1. CWE-20: Improper Input Validation (Score: 346.19)\n\nThe product receives input or data, but it does\n        not validate or incorrectly validates that the input has the\n        properties that are required to process the data safely and\n        correctly....\n\n### 2. CWE-285: Improper Authorization (Score: 318.74)\n\nThe product does not perform or incorrectly performs an authorization check when an actor attempts to access a resource or perform an action....\n\n### 3. CWE-367: Time-of-check Time-of-use (TOCTOU) Race Condition (Score: 317.40)\n\nThe product checks the state of a resource before using that resource, but the resource's state can change between the check and the use in a way that invalidates the results of the check. This can cause the product to perform invalid actions when the resource is in an unexpected state....\n\n### 4. CWE-657: Violation of Secure Design Principles (Score: 315.46)\n\nThe product violates well-established principles for secure design....\n\n### 5. CWE-863: Incorrect Authorization (Score: 104.66)\n\nThe product performs an authorization check when an actor attempts to access a resource or perform an action, but it does not correctly perform the check....\n\n## ATTACKER: 'low-privileged attacker'\n\nRelevant CWEs for this ATTACKER:\n\n### 1. CWE-20: Improper Input Validation (Score: 346.19)\n\nThe product receives input or data, but it does\n        not validate or incorrectly validates that the input has the\n        properties that are required to process the data safely and\n        correctly....\n\n### 2. CWE-285: Improper Authorization (Score: 318.74)\n\nThe product does not perform or incorrectly performs an authorization check when an actor attempts to access a resource or perform an action....\n\n### 3. CWE-367: Time-of-check Time-of-use (TOCTOU) Race Condition (Score: 317.40)\n\nThe product checks the state of a resource before using that resource, but the resource's state can change between the check and the use in a way that invalidates the results of the check. This can cause the product to perform invalid actions when the resource is in an unexpected state....\n\n### 4. CWE-657: Violation of Secure Design Principles (Score: 315.46)\n\nThe product violates well-established principles for secure design....\n\n### 5. CWE-732: Incorrect Permission Assignment for Critical Resource (Score: 117.33)\n\nThe product specifies permissions for a security-critical resource in a way that allows that resource to be read or modified by unintended actors....\n\n## VERSION: '6.5.20 and earlier'\n\nRelevant CWEs for this VERSION:\n\n### 1. CWE-20: Improper Input Validation (Score: 346.19)\n\nThe product receives input or data, but it does\n        not validate or incorrectly validates that the input has the\n        properties that are required to process the data safely and\n        correctly....\n\n### 2. CWE-787: Out-of-bounds Write (Score: 325.18)\n\nThe product writes data past the end, or before the beginning, of the intended buffer....\n\n### 3. CWE-285: Improper Authorization (Score: 318.74)\n\nThe product does not perform or incorrectly performs an authorization check when an actor attempts to access a resource or perform an action....\n\n### 4. CWE-367: Time-of-check Time-of-use (TOCTOU) Race Condition (Score: 317.40)\n\nThe product checks the state of a resource before using that resource, but the resource's state can change between the check and the use in a way that invalidates the results of the check. This can cause the product to perform invalid actions when the resource is in an unexpected state....\n\n### 5. CWE-657: Violation of Secure Design Principles (Score: 315.46)\n\nThe product violates well-established principles for secure design....\n\n## PRODUCT: 'Adobe Experience Manager'\n\nRelevant CWEs for this PRODUCT:\n\n### 1. CWE-787: Out-of-bounds Write (Score: 325.18)\n\nThe product writes data past the end, or before the beginning, of the intended buffer....\n\n### 2. CWE-285: Improper Authorization (Score: 318.74)\n\nThe product does not perform or incorrectly performs an authorization check when an actor attempts to access a resource or perform an action....\n\n### 3. CWE-657: Violation of Secure Design Principles (Score: 315.46)\n\nThe product violates well-established principles for secure design....\n\n### 4. CWE-379: Creation of Temporary File in Directory with Insecure Permissions (Score: 115.70)\n\nThe product creates a temporary file in a directory whose permissions allow unintended actors to determine the file's existence or otherwise access that file....\n\n### 5. CWE-788: Access of Memory Location After End of Buffer (Score: 112.70)\n\nThe product reads or writes to a buffer using an index or pointer that references a memory location after the end of the buffer....\n\n\n    # Analysis Instructions\n    1. For each keyphrase, identify the most appropriate CWE(s) that represent the weakness.\n    2. Consider how the different keyphrases might relate to each other in the vulnerability chain.\n    3. Provide a final determination of primary CWE(s) and any secondary CWEs.\n    4. Format your response using the standard analysis template.\n\n    Please analyze how these different weaknesses interact and provide a comprehensive CWE classification.\n    "
  },
  "retrieval_time": 2.6079180240631104
}