{
  "vulnerability_info": "VulnerabilityInfo(cve_id='CVE-2024-45761', description='Dell OpenManage Server Administrator, versions 11.0.1.0 and prior, contains an **improper input validation** vulnerability. A remote low-privileged malicious user could potentially exploit this vulnerability to load any web plugins or Java class leading to the possibility of altering the behavior of certain apps/OS or Denial of Service.', key_phrases={'rootcause': ['improper input validation', 'input validation vulnerability'], 'weakness': '', 'impact': [\"['load any web plugins or Java class'\", \"'alter the behavior of certain apps/OS'\", \"'Denial of Service']\"], 'vector': '', 'attacker': 'remote low-privileged malicious user', 'product': 'Dell OpenManage Server Administrator', 'version': '11.0.1.0 and prior', 'component': ''}, reference_content=\"Based on the provided content, here's the information regarding CVE-2024-45761:\\n\\n**Root Cause of Vulnerability:**\\n- Improper input validation within Dell OpenManage Server Administrator (OMSA).\\n\\n**Weaknesses/Vulnerabilities Present:**\\n- The vulnerability lies in how OMSA handles input, specifically related to loading web plugins or Java classes.\\n\\n**Impact of Exploitation:**\\n- Successful exploitation can lead to:\\n    - Loading of arbitrary web plugins or Java classes.\\n    - Potential alteration of the behavior of certain apps or the OS.\\n    - Denial of Service (DoS).\\n\\n**Attack Vectors:**\\n- The attack vector is remote, meaning the attacker does not need physical access to the affected system.\\n\\n**Required Attacker Capabilities/Position:**\\n- The attacker needs to be a low-privileged user.\\n\\n**Affected Versions:**\\n- Dell OpenManage Server Administrator versions 11.0.1.0 and prior are affected.\\n\\n**Remediated Versions:**\\n- Dell OpenManage Server Administrator version 11.1.0.0 addresses this vulnerability.\\n\\n**Additional Details:**\\n- The vulnerability is exploitable via the network.\\n- CVSS Base Score is 5.4 with a vector of CVSS:3.1/AV:N/AC:L/PR:L/UI:N/S:U/C:N/I:L/A:L.\", similar_info={'cwe_distribution': {}, 'cwe_consensus': '', 'similarity_stats': {'thresholds': [], 'total_samples_by_threshold': {}, 'top_cwes_by_threshold': {}}}, similarity_summary=SimilarityInsight(consensus_cwe='', top_cwes=[], confidence_levels={}, total_samples=0), analysis='', analysis_with_relationships='', criticism='', resolution='', relevant_cwes=[{'metadata': {'doc_id': '20', 'name': 'Improper Input Validation', 'source': 'sparse', 'original_content': 'The product receives input or data, but it does\\n        not validate or incorrectly validates that the input has the\\n        properties that are required to process the data safely and\\n        correctly.', 'keyphrase_sources': [{'id': 'rootcause:improper input validation', 'keyphrase': 'improper input validation', 'type': 'rootcause'}, {'id': 'rootcause:input validation vulnerability', 'keyphrase': 'input validation vulnerability', 'type': 'rootcause'}, {'id': \"impact:['load any web plugins or Java class'\", 'keyphrase': \"['load any web plugins or Java class'\", 'type': 'impact'}, {'id': \"impact:'alter the behavior of certain apps/OS'\", 'keyphrase': \"'alter the behavior of certain apps/OS'\", 'type': 'impact'}, {'id': \"impact:'Denial of Service']\", 'keyphrase': \"'Denial of Service']\", 'type': 'impact'}, {'id': 'attacker:remote low-privileged malicious user', 'keyphrase': 'remote low-privileged malicious user', 'type': 'attacker'}, {'id': 'version:11.0.1.0 and prior', 'keyphrase': '11.0.1.0 and prior', 'type': 'version'}]}, 'similarity': np.float64(306.767755913869)}, {'metadata': {'doc_id': '1284', 'name': 'Improper Validation of Specified Quantity in Input', 'source': 'sparse', 'original_content': 'The product receives input that is expected to specify a quantity (such as size or length), but it does not validate or incorrectly validates that the quantity has the required properties.', 'keyphrase_sources': [{'id': 'rootcause:improper input validation', 'keyphrase': 'improper input validation', 'type': 'rootcause'}, {'id': 'rootcause:input validation vulnerability', 'keyphrase': 'input validation vulnerability', 'type': 'rootcause'}]}, 'similarity': np.float64(282.9938148838528)}, {'metadata': {'doc_id': '269', 'name': 'Improper Privilege Management', 'source': 'sparse', 'original_content': 'The product does not properly assign, modify, track, or check privileges for an actor, creating an unintended sphere of control for that actor.', 'keyphrase_sources': [{'id': 'rootcause:improper input validation', 'keyphrase': 'improper input validation', 'type': 'rootcause'}, {'id': 'rootcause:input validation vulnerability', 'keyphrase': 'input validation vulnerability', 'type': 'rootcause'}, {'id': \"impact:'alter the behavior of certain apps/OS'\", 'keyphrase': \"'alter the behavior of certain apps/OS'\", 'type': 'impact'}, {'id': \"impact:'Denial of Service']\", 'keyphrase': \"'Denial of Service']\", 'type': 'impact'}, {'id': 'attacker:remote low-privileged malicious user', 'keyphrase': 'remote low-privileged malicious user', 'type': 'attacker'}, {'id': 'product:Dell OpenManage Server Administrator', 'keyphrase': 'Dell OpenManage Server Administrator', 'type': 'product'}, {'id': 'version:11.0.1.0 and prior', 'keyphrase': '11.0.1.0 and prior', 'type': 'version'}]}, 'similarity': np.float64(279.5046789446745)}, {'metadata': {'doc_id': '287', 'name': 'Improper Authentication', 'source': 'sparse', 'original_content': 'When an actor claims to have a given identity, the product does not prove or insufficiently proves that the claim is correct.', 'keyphrase_sources': [{'id': 'rootcause:improper input validation', 'keyphrase': 'improper input validation', 'type': 'rootcause'}, {'id': 'rootcause:input validation vulnerability', 'keyphrase': 'input validation vulnerability', 'type': 'rootcause'}, {'id': \"impact:'alter the behavior of certain apps/OS'\", 'keyphrase': \"'alter the behavior of certain apps/OS'\", 'type': 'impact'}, {'id': 'product:Dell OpenManage Server Administrator', 'keyphrase': 'Dell OpenManage Server Administrator', 'type': 'product'}, {'id': 'version:11.0.1.0 and prior', 'keyphrase': '11.0.1.0 and prior', 'type': 'version'}]}, 'similarity': np.float64(277.8044167154874)}, {'metadata': {'doc_id': '285', 'name': 'Improper Authorization', 'source': 'sparse', 'original_content': 'The product does not perform or incorrectly performs an authorization check when an actor attempts to access a resource or perform an action.', 'keyphrase_sources': [{'id': 'rootcause:improper input validation', 'keyphrase': 'improper input validation', 'type': 'rootcause'}, {'id': \"impact:['load any web plugins or Java class'\", 'keyphrase': \"['load any web plugins or Java class'\", 'type': 'impact'}, {'id': \"impact:'alter the behavior of certain apps/OS'\", 'keyphrase': \"'alter the behavior of certain apps/OS'\", 'type': 'impact'}, {'id': \"impact:'Denial of Service']\", 'keyphrase': \"'Denial of Service']\", 'type': 'impact'}, {'id': 'attacker:remote low-privileged malicious user', 'keyphrase': 'remote low-privileged malicious user', 'type': 'attacker'}, {'id': 'product:Dell OpenManage Server Administrator', 'keyphrase': 'Dell OpenManage Server Administrator', 'type': 'product'}, {'id': 'version:11.0.1.0 and prior', 'keyphrase': '11.0.1.0 and prior', 'type': 'version'}]}, 'similarity': np.float64(275.3665438479781)}, {'metadata': {'doc_id': '74', 'name': \"Improper Neutralization of Special Elements in Output Used by a Downstream Component ('Injection')\", 'source': 'sparse', 'original_content': 'The product constructs all or part of a command, data structure, or record using externally-influenced input from an upstream component, but it does not neutralize or incorrectly neutralizes special elements that could modify how it is parsed or interpreted when it is sent to a downstream component.', 'keyphrase_sources': [{'id': 'rootcause:input validation vulnerability', 'keyphrase': 'input validation vulnerability', 'type': 'rootcause'}, {'id': 'product:Dell OpenManage Server Administrator', 'keyphrase': 'Dell OpenManage Server Administrator', 'type': 'product'}]}, 'similarity': np.float64(271.16287563283845)}, {'metadata': {'doc_id': '470', 'name': \"Use of Externally-Controlled Input to Select Classes or Code ('Unsafe Reflection')\", 'source': 'sparse', 'original_content': 'The product uses external input with reflection to select which classes or code to use, but it does not sufficiently prevent the input from selecting improper classes or code.', 'keyphrase_sources': [{'id': \"impact:['load any web plugins or Java class'\", 'keyphrase': \"['load any web plugins or Java class'\", 'type': 'impact'}]}, 'similarity': np.float64(118.00281086948155)}, {'metadata': {'doc_id': '347', 'name': 'Improper Verification of Cryptographic Signature', 'source': 'sparse', 'original_content': 'The product does not verify, or incorrectly verifies, the cryptographic signature for data.', 'keyphrase_sources': [{'id': \"impact:'alter the behavior of certain apps/OS'\", 'keyphrase': \"'alter the behavior of certain apps/OS'\", 'type': 'impact'}]}, 'similarity': np.float64(112.86431002679578)}, {'metadata': {'doc_id': '732', 'name': 'Incorrect Permission Assignment for Critical Resource', 'source': 'sparse', 'original_content': 'The product specifies permissions for a security-critical resource in a way that allows that resource to be read or modified by unintended actors.', 'keyphrase_sources': [{'id': \"impact:['load any web plugins or Java class'\", 'keyphrase': \"['load any web plugins or Java class'\", 'type': 'impact'}, {'id': \"impact:'Denial of Service']\", 'keyphrase': \"'Denial of Service']\", 'type': 'impact'}, {'id': 'attacker:remote low-privileged malicious user', 'keyphrase': 'remote low-privileged malicious user', 'type': 'attacker'}, {'id': 'product:Dell OpenManage Server Administrator', 'keyphrase': 'Dell OpenManage Server Administrator', 'type': 'product'}, {'id': 'version:11.0.1.0 and prior', 'keyphrase': '11.0.1.0 and prior', 'type': 'version'}]}, 'similarity': np.float64(104.31873165137284)}, {'metadata': {'doc_id': '23', 'name': 'Relative Path Traversal', 'source': 'sparse', 'original_content': 'The product uses external input to construct a pathname that should be within a restricted directory, but it does not properly neutralize sequences such as \"..\" that can resolve to a location that is outside of that directory.', 'keyphrase_sources': [{'id': \"impact:['load any web plugins or Java class'\", 'keyphrase': \"['load any web plugins or Java class'\", 'type': 'impact'}]}, 'similarity': np.float64(102.17053806938446)}, {'metadata': {'doc_id': '250', 'name': 'Execution with Unnecessary Privileges', 'source': 'sparse', 'original_content': 'The product performs an operation at a privilege level that is higher than the minimum level required, which creates new weaknesses or amplifies the consequences of other weaknesses.', 'keyphrase_sources': [{'id': 'attacker:remote low-privileged malicious user', 'keyphrase': 'remote low-privileged malicious user', 'type': 'attacker'}]}, 'similarity': np.float64(99.31774834909922)}, {'metadata': {'doc_id': '119', 'name': 'Improper Restriction of Operations within the Bounds of a Memory Buffer', 'source': 'sparse', 'original_content': \"The product performs operations on a memory buffer, but it reads from or writes to a memory location outside the buffer's intended boundary. This may result in read or write operations on unexpected memory locations that could be linked to other variables, data structures, or internal program data.\", 'keyphrase_sources': [{'id': \"impact:'Denial of Service']\", 'keyphrase': \"'Denial of Service']\", 'type': 'impact'}]}, 'similarity': np.float64(98.94429328691186)}], identified_cwes={'analyzer': [], 'critic_additional': []})",
  "retrieval_results": {
    "has_multiple_keyphrases": true,
    "keyphrase_cwe_sets": {
      "rootcause:improper input validation": {
        "keyphrase": "improper input validation",
        "type": "rootcause",
        "cwes": [
          {
            "metadata": {
              "doc_id": "20",
              "name": "Improper Input Validation",
              "source": "sparse",
              "original_content": "The product receives input or data, but it does\n        not validate or incorrectly validates that the input has the\n        properties that are required to process the data safely and\n        correctly.",
              "keyphrase_sources": [
                {
                  "id": "rootcause:improper input validation",
                  "keyphrase": "improper input validation",
                  "type": "rootcause"
                },
                {
                  "id": "rootcause:input validation vulnerability",
                  "keyphrase": "input validation vulnerability",
                  "type": "rootcause"
                },
                {
                  "id": "impact:['load any web plugins or Java class'",
                  "keyphrase": "['load any web plugins or Java class'",
                  "type": "impact"
                },
                {
                  "id": "impact:'alter the behavior of certain apps/OS'",
                  "keyphrase": "'alter the behavior of certain apps/OS'",
                  "type": "impact"
                },
                {
                  "id": "impact:'Denial of Service']",
                  "keyphrase": "'Denial of Service']",
                  "type": "impact"
                },
                {
                  "id": "attacker:remote low-privileged malicious user",
                  "keyphrase": "remote low-privileged malicious user",
                  "type": "attacker"
                },
                {
                  "id": "version:11.0.1.0 and prior",
                  "keyphrase": "11.0.1.0 and prior",
                  "type": "version"
                }
              ]
            },
            "similarity": 306.767755913869
          },
          {
            "metadata": {
              "doc_id": "1284",
              "name": "Improper Validation of Specified Quantity in Input",
              "source": "sparse",
              "original_content": "The product receives input that is expected to specify a quantity (such as size or length), but it does not validate or incorrectly validates that the quantity has the required properties.",
              "keyphrase_sources": [
                {
                  "id": "rootcause:improper input validation",
                  "keyphrase": "improper input validation",
                  "type": "rootcause"
                },
                {
                  "id": "rootcause:input validation vulnerability",
                  "keyphrase": "input validation vulnerability",
                  "type": "rootcause"
                }
              ]
            },
            "similarity": 282.9938148838528
          },
          {
            "metadata": {
              "doc_id": "269",
              "name": "Improper Privilege Management",
              "source": "sparse",
              "original_content": "The product does not properly assign, modify, track, or check privileges for an actor, creating an unintended sphere of control for that actor.",
              "keyphrase_sources": [
                {
                  "id": "rootcause:improper input validation",
                  "keyphrase": "improper input validation",
                  "type": "rootcause"
                },
                {
                  "id": "rootcause:input validation vulnerability",
                  "keyphrase": "input validation vulnerability",
                  "type": "rootcause"
                },
                {
                  "id": "impact:'alter the behavior of certain apps/OS'",
                  "keyphrase": "'alter the behavior of certain apps/OS'",
                  "type": "impact"
                },
                {
                  "id": "impact:'Denial of Service']",
                  "keyphrase": "'Denial of Service']",
                  "type": "impact"
                },
                {
                  "id": "attacker:remote low-privileged malicious user",
                  "keyphrase": "remote low-privileged malicious user",
                  "type": "attacker"
                },
                {
                  "id": "product:Dell OpenManage Server Administrator",
                  "keyphrase": "Dell OpenManage Server Administrator",
                  "type": "product"
                },
                {
                  "id": "version:11.0.1.0 and prior",
                  "keyphrase": "11.0.1.0 and prior",
                  "type": "version"
                }
              ]
            },
            "similarity": 279.5046789446745
          },
          {
            "metadata": {
              "doc_id": "287",
              "name": "Improper Authentication",
              "source": "sparse",
              "original_content": "When an actor claims to have a given identity, the product does not prove or insufficiently proves that the claim is correct.",
              "keyphrase_sources": [
                {
                  "id": "rootcause:improper input validation",
                  "keyphrase": "improper input validation",
                  "type": "rootcause"
                },
                {
                  "id": "rootcause:input validation vulnerability",
                  "keyphrase": "input validation vulnerability",
                  "type": "rootcause"
                },
                {
                  "id": "impact:'alter the behavior of certain apps/OS'",
                  "keyphrase": "'alter the behavior of certain apps/OS'",
                  "type": "impact"
                },
                {
                  "id": "product:Dell OpenManage Server Administrator",
                  "keyphrase": "Dell OpenManage Server Administrator",
                  "type": "product"
                },
                {
                  "id": "version:11.0.1.0 and prior",
                  "keyphrase": "11.0.1.0 and prior",
                  "type": "version"
                }
              ]
            },
            "similarity": 277.8044167154874
          },
          {
            "metadata": {
              "doc_id": "285",
              "name": "Improper Authorization",
              "source": "sparse",
              "original_content": "The product does not perform or incorrectly performs an authorization check when an actor attempts to access a resource or perform an action.",
              "keyphrase_sources": [
                {
                  "id": "rootcause:improper input validation",
                  "keyphrase": "improper input validation",
                  "type": "rootcause"
                },
                {
                  "id": "impact:['load any web plugins or Java class'",
                  "keyphrase": "['load any web plugins or Java class'",
                  "type": "impact"
                },
                {
                  "id": "impact:'alter the behavior of certain apps/OS'",
                  "keyphrase": "'alter the behavior of certain apps/OS'",
                  "type": "impact"
                },
                {
                  "id": "impact:'Denial of Service']",
                  "keyphrase": "'Denial of Service']",
                  "type": "impact"
                },
                {
                  "id": "attacker:remote low-privileged malicious user",
                  "keyphrase": "remote low-privileged malicious user",
                  "type": "attacker"
                },
                {
                  "id": "product:Dell OpenManage Server Administrator",
                  "keyphrase": "Dell OpenManage Server Administrator",
                  "type": "product"
                },
                {
                  "id": "version:11.0.1.0 and prior",
                  "keyphrase": "11.0.1.0 and prior",
                  "type": "version"
                }
              ]
            },
            "similarity": 275.3665438479781
          }
        ]
      },
      "rootcause:input validation vulnerability": {
        "keyphrase": "input validation vulnerability",
        "type": "rootcause",
        "cwes": [
          {
            "metadata": {
              "doc_id": "20",
              "name": "Improper Input Validation",
              "source": "sparse",
              "original_content": "The product receives input or data, but it does\n        not validate or incorrectly validates that the input has the\n        properties that are required to process the data safely and\n        correctly."
            },
            "similarity": 302.01477739643457
          },
          {
            "metadata": {
              "doc_id": "1284",
              "name": "Improper Validation of Specified Quantity in Input",
              "source": "sparse",
              "original_content": "The product receives input that is expected to specify a quantity (such as size or length), but it does not validate or incorrectly validates that the quantity has the required properties."
            },
            "similarity": 279.9389050195831
          },
          {
            "metadata": {
              "doc_id": "269",
              "name": "Improper Privilege Management",
              "source": "sparse",
              "original_content": "The product does not properly assign, modify, track, or check privileges for an actor, creating an unintended sphere of control for that actor."
            },
            "similarity": 274.80427257185084
          },
          {
            "metadata": {
              "doc_id": "287",
              "name": "Improper Authentication",
              "source": "sparse",
              "original_content": "When an actor claims to have a given identity, the product does not prove or insufficiently proves that the claim is correct."
            },
            "similarity": 273.1353430545652
          },
          {
            "metadata": {
              "doc_id": "74",
              "name": "Improper Neutralization of Special Elements in Output Used by a Downstream Component ('Injection')",
              "source": "sparse",
              "original_content": "The product constructs all or part of a command, data structure, or record using externally-influenced input from an upstream component, but it does not neutralize or incorrectly neutralizes special elements that could modify how it is parsed or interpreted when it is sent to a downstream component.",
              "keyphrase_sources": [
                {
                  "id": "rootcause:input validation vulnerability",
                  "keyphrase": "input validation vulnerability",
                  "type": "rootcause"
                },
                {
                  "id": "product:Dell OpenManage Server Administrator",
                  "keyphrase": "Dell OpenManage Server Administrator",
                  "type": "product"
                }
              ]
            },
            "similarity": 271.16287563283845
          }
        ]
      },
      "impact:['load any web plugins or Java class'": {
        "keyphrase": "['load any web plugins or Java class'",
        "type": "impact",
        "cwes": [
          {
            "metadata": {
              "doc_id": "470",
              "name": "Use of Externally-Controlled Input to Select Classes or Code ('Unsafe Reflection')",
              "source": "sparse",
              "original_content": "The product uses external input with reflection to select which classes or code to use, but it does not sufficiently prevent the input from selecting improper classes or code.",
              "keyphrase_sources": [
                {
                  "id": "impact:['load any web plugins or Java class'",
                  "keyphrase": "['load any web plugins or Java class'",
                  "type": "impact"
                }
              ]
            },
            "similarity": 118.00281086948155
          },
          {
            "metadata": {
              "doc_id": "285",
              "name": "Improper Authorization",
              "source": "sparse",
              "original_content": "The product does not perform or incorrectly performs an authorization check when an actor attempts to access a resource or perform an action."
            },
            "similarity": 106.92676030743071
          },
          {
            "metadata": {
              "doc_id": "732",
              "name": "Incorrect Permission Assignment for Critical Resource",
              "source": "sparse",
              "original_content": "The product specifies permissions for a security-critical resource in a way that allows that resource to be read or modified by unintended actors.",
              "keyphrase_sources": [
                {
                  "id": "impact:['load any web plugins or Java class'",
                  "keyphrase": "['load any web plugins or Java class'",
                  "type": "impact"
                },
                {
                  "id": "impact:'Denial of Service']",
                  "keyphrase": "'Denial of Service']",
                  "type": "impact"
                },
                {
                  "id": "attacker:remote low-privileged malicious user",
                  "keyphrase": "remote low-privileged malicious user",
                  "type": "attacker"
                },
                {
                  "id": "product:Dell OpenManage Server Administrator",
                  "keyphrase": "Dell OpenManage Server Administrator",
                  "type": "product"
                },
                {
                  "id": "version:11.0.1.0 and prior",
                  "keyphrase": "11.0.1.0 and prior",
                  "type": "version"
                }
              ]
            },
            "similarity": 104.31873165137284
          },
          {
            "metadata": {
              "doc_id": "20",
              "name": "Improper Input Validation",
              "source": "sparse",
              "original_content": "The product receives input or data, but it does\n        not validate or incorrectly validates that the input has the\n        properties that are required to process the data safely and\n        correctly."
            },
            "similarity": 103.98637546747811
          },
          {
            "metadata": {
              "doc_id": "23",
              "name": "Relative Path Traversal",
              "source": "sparse",
              "original_content": "The product uses external input to construct a pathname that should be within a restricted directory, but it does not properly neutralize sequences such as \"..\" that can resolve to a location that is outside of that directory.",
              "keyphrase_sources": [
                {
                  "id": "impact:['load any web plugins or Java class'",
                  "keyphrase": "['load any web plugins or Java class'",
                  "type": "impact"
                }
              ]
            },
            "similarity": 102.17053806938446
          }
        ]
      },
      "impact:'alter the behavior of certain apps/OS'": {
        "keyphrase": "'alter the behavior of certain apps/OS'",
        "type": "impact",
        "cwes": [
          {
            "metadata": {
              "doc_id": "347",
              "name": "Improper Verification of Cryptographic Signature",
              "source": "sparse",
              "original_content": "The product does not verify, or incorrectly verifies, the cryptographic signature for data.",
              "keyphrase_sources": [
                {
                  "id": "impact:'alter the behavior of certain apps/OS'",
                  "keyphrase": "'alter the behavior of certain apps/OS'",
                  "type": "impact"
                }
              ]
            },
            "similarity": 112.86431002679578
          },
          {
            "metadata": {
              "doc_id": "269",
              "name": "Improper Privilege Management",
              "source": "sparse",
              "original_content": "The product does not properly assign, modify, track, or check privileges for an actor, creating an unintended sphere of control for that actor."
            },
            "similarity": 112.73026138345826
          },
          {
            "metadata": {
              "doc_id": "285",
              "name": "Improper Authorization",
              "source": "sparse",
              "original_content": "The product does not perform or incorrectly performs an authorization check when an actor attempts to access a resource or perform an action."
            },
            "similarity": 112.44607488286823
          },
          {
            "metadata": {
              "doc_id": "20",
              "name": "Improper Input Validation",
              "source": "sparse",
              "original_content": "The product receives input or data, but it does\n        not validate or incorrectly validates that the input has the\n        properties that are required to process the data safely and\n        correctly."
            },
            "similarity": 112.32841349472996
          },
          {
            "metadata": {
              "doc_id": "287",
              "name": "Improper Authentication",
              "source": "sparse",
              "original_content": "When an actor claims to have a given identity, the product does not prove or insufficiently proves that the claim is correct."
            },
            "similarity": 112.10820209454499
          }
        ]
      },
      "impact:'Denial of Service']": {
        "keyphrase": "'Denial of Service']",
        "type": "impact",
        "cwes": [
          {
            "metadata": {
              "doc_id": "20",
              "name": "Improper Input Validation",
              "source": "sparse",
              "original_content": "The product receives input or data, but it does\n        not validate or incorrectly validates that the input has the\n        properties that are required to process the data safely and\n        correctly."
            },
            "similarity": 103.81671512837299
          },
          {
            "metadata": {
              "doc_id": "269",
              "name": "Improper Privilege Management",
              "source": "sparse",
              "original_content": "The product does not properly assign, modify, track, or check privileges for an actor, creating an unintended sphere of control for that actor."
            },
            "similarity": 100.58246429488689
          },
          {
            "metadata": {
              "doc_id": "285",
              "name": "Improper Authorization",
              "source": "sparse",
              "original_content": "The product does not perform or incorrectly performs an authorization check when an actor attempts to access a resource or perform an action."
            },
            "similarity": 100.24810643458476
          },
          {
            "metadata": {
              "doc_id": "732",
              "name": "Incorrect Permission Assignment for Critical Resource",
              "source": "sparse",
              "original_content": "The product specifies permissions for a security-critical resource in a way that allows that resource to be read or modified by unintended actors."
            },
            "similarity": 99.72525818809635
          },
          {
            "metadata": {
              "doc_id": "119",
              "name": "Improper Restriction of Operations within the Bounds of a Memory Buffer",
              "source": "sparse",
              "original_content": "The product performs operations on a memory buffer, but it reads from or writes to a memory location outside the buffer's intended boundary. This may result in read or write operations on unexpected memory locations that could be linked to other variables, data structures, or internal program data.",
              "keyphrase_sources": [
                {
                  "id": "impact:'Denial of Service']",
                  "keyphrase": "'Denial of Service']",
                  "type": "impact"
                }
              ]
            },
            "similarity": 98.94429328691186
          }
        ]
      },
      "attacker:remote low-privileged malicious user": {
        "keyphrase": "remote low-privileged malicious user",
        "type": "attacker",
        "cwes": [
          {
            "metadata": {
              "doc_id": "269",
              "name": "Improper Privilege Management",
              "source": "sparse",
              "original_content": "The product does not properly assign, modify, track, or check privileges for an actor, creating an unintended sphere of control for that actor."
            },
            "similarity": 106.90532461664445
          },
          {
            "metadata": {
              "doc_id": "732",
              "name": "Incorrect Permission Assignment for Critical Resource",
              "source": "sparse",
              "original_content": "The product specifies permissions for a security-critical resource in a way that allows that resource to be read or modified by unintended actors."
            },
            "similarity": 106.6405828314729
          },
          {
            "metadata": {
              "doc_id": "285",
              "name": "Improper Authorization",
              "source": "sparse",
              "original_content": "The product does not perform or incorrectly performs an authorization check when an actor attempts to access a resource or perform an action."
            },
            "similarity": 104.04049734378121
          },
          {
            "metadata": {
              "doc_id": "20",
              "name": "Improper Input Validation",
              "source": "sparse",
              "original_content": "The product receives input or data, but it does\n        not validate or incorrectly validates that the input has the\n        properties that are required to process the data safely and\n        correctly."
            },
            "similarity": 100.884069708224
          },
          {
            "metadata": {
              "doc_id": "250",
              "name": "Execution with Unnecessary Privileges",
              "source": "sparse",
              "original_content": "The product performs an operation at a privilege level that is higher than the minimum level required, which creates new weaknesses or amplifies the consequences of other weaknesses.",
              "keyphrase_sources": [
                {
                  "id": "attacker:remote low-privileged malicious user",
                  "keyphrase": "remote low-privileged malicious user",
                  "type": "attacker"
                }
              ]
            },
            "similarity": 99.31774834909922
          }
        ]
      },
      "product:Dell OpenManage Server Administrator": {
        "keyphrase": "Dell OpenManage Server Administrator",
        "type": "product",
        "cwes": [
          {
            "metadata": {
              "doc_id": "74",
              "name": "Improper Neutralization of Special Elements in Output Used by a Downstream Component ('Injection')",
              "source": "sparse",
              "original_content": "The product constructs all or part of a command, data structure, or record using externally-influenced input from an upstream component, but it does not neutralize or incorrectly neutralizes special elements that could modify how it is parsed or interpreted when it is sent to a downstream component."
            },
            "similarity": 103.74140150849377
          },
          {
            "metadata": {
              "doc_id": "285",
              "name": "Improper Authorization",
              "source": "sparse",
              "original_content": "The product does not perform or incorrectly performs an authorization check when an actor attempts to access a resource or perform an action."
            },
            "similarity": 99.55160417233584
          },
          {
            "metadata": {
              "doc_id": "269",
              "name": "Improper Privilege Management",
              "source": "sparse",
              "original_content": "The product does not properly assign, modify, track, or check privileges for an actor, creating an unintended sphere of control for that actor."
            },
            "similarity": 98.73661623538776
          },
          {
            "metadata": {
              "doc_id": "732",
              "name": "Incorrect Permission Assignment for Critical Resource",
              "source": "sparse",
              "original_content": "The product specifies permissions for a security-critical resource in a way that allows that resource to be read or modified by unintended actors."
            },
            "similarity": 97.67213343771277
          },
          {
            "metadata": {
              "doc_id": "287",
              "name": "Improper Authentication",
              "source": "sparse",
              "original_content": "When an actor claims to have a given identity, the product does not prove or insufficiently proves that the claim is correct."
            },
            "similarity": 97.32875730921917
          }
        ]
      },
      "version:11.0.1.0 and prior": {
        "keyphrase": "11.0.1.0 and prior",
        "type": "version",
        "cwes": [
          {
            "metadata": {
              "doc_id": "269",
              "name": "Improper Privilege Management",
              "source": "sparse",
              "original_content": "The product does not properly assign, modify, track, or check privileges for an actor, creating an unintended sphere of control for that actor."
            },
            "similarity": 107.55745998329495
          },
          {
            "metadata": {
              "doc_id": "20",
              "name": "Improper Input Validation",
              "source": "sparse",
              "original_content": "The product receives input or data, but it does\n        not validate or incorrectly validates that the input has the\n        properties that are required to process the data safely and\n        correctly."
            },
            "similarity": 107.20007126836227
          },
          {
            "metadata": {
              "doc_id": "732",
              "name": "Incorrect Permission Assignment for Critical Resource",
              "source": "sparse",
              "original_content": "The product specifies permissions for a security-critical resource in a way that allows that resource to be read or modified by unintended actors."
            },
            "similarity": 106.9380816239169
          },
          {
            "metadata": {
              "doc_id": "285",
              "name": "Improper Authorization",
              "source": "sparse",
              "original_content": "The product does not perform or incorrectly performs an authorization check when an actor attempts to access a resource or perform an action."
            },
            "similarity": 105.67739247002983
          },
          {
            "metadata": {
              "doc_id": "287",
              "name": "Improper Authentication",
              "source": "sparse",
              "original_content": "When an actor claims to have a given identity, the product does not prove or insufficiently proves that the claim is correct."
            },
            "similarity": 104.26774062059921
          }
        ]
      }
    },
    "keyphrase_mapping": {
      "20": [
        {
          "id": "rootcause:improper input validation",
          "keyphrase": "improper input validation",
          "type": "rootcause"
        },
        {
          "id": "rootcause:input validation vulnerability",
          "keyphrase": "input validation vulnerability",
          "type": "rootcause"
        },
        {
          "id": "impact:['load any web plugins or Java class'",
          "keyphrase": "['load any web plugins or Java class'",
          "type": "impact"
        },
        {
          "id": "impact:'alter the behavior of certain apps/OS'",
          "keyphrase": "'alter the behavior of certain apps/OS'",
          "type": "impact"
        },
        {
          "id": "impact:'Denial of Service']",
          "keyphrase": "'Denial of Service']",
          "type": "impact"
        },
        {
          "id": "attacker:remote low-privileged malicious user",
          "keyphrase": "remote low-privileged malicious user",
          "type": "attacker"
        },
        {
          "id": "version:11.0.1.0 and prior",
          "keyphrase": "11.0.1.0 and prior",
          "type": "version"
        }
      ],
      "1284": [
        {
          "id": "rootcause:improper input validation",
          "keyphrase": "improper input validation",
          "type": "rootcause"
        },
        {
          "id": "rootcause:input validation vulnerability",
          "keyphrase": "input validation vulnerability",
          "type": "rootcause"
        }
      ],
      "269": [
        {
          "id": "rootcause:improper input validation",
          "keyphrase": "improper input validation",
          "type": "rootcause"
        },
        {
          "id": "rootcause:input validation vulnerability",
          "keyphrase": "input validation vulnerability",
          "type": "rootcause"
        },
        {
          "id": "impact:'alter the behavior of certain apps/OS'",
          "keyphrase": "'alter the behavior of certain apps/OS'",
          "type": "impact"
        },
        {
          "id": "impact:'Denial of Service']",
          "keyphrase": "'Denial of Service']",
          "type": "impact"
        },
        {
          "id": "attacker:remote low-privileged malicious user",
          "keyphrase": "remote low-privileged malicious user",
          "type": "attacker"
        },
        {
          "id": "product:Dell OpenManage Server Administrator",
          "keyphrase": "Dell OpenManage Server Administrator",
          "type": "product"
        },
        {
          "id": "version:11.0.1.0 and prior",
          "keyphrase": "11.0.1.0 and prior",
          "type": "version"
        }
      ],
      "287": [
        {
          "id": "rootcause:improper input validation",
          "keyphrase": "improper input validation",
          "type": "rootcause"
        },
        {
          "id": "rootcause:input validation vulnerability",
          "keyphrase": "input validation vulnerability",
          "type": "rootcause"
        },
        {
          "id": "impact:'alter the behavior of certain apps/OS'",
          "keyphrase": "'alter the behavior of certain apps/OS'",
          "type": "impact"
        },
        {
          "id": "product:Dell OpenManage Server Administrator",
          "keyphrase": "Dell OpenManage Server Administrator",
          "type": "product"
        },
        {
          "id": "version:11.0.1.0 and prior",
          "keyphrase": "11.0.1.0 and prior",
          "type": "version"
        }
      ],
      "285": [
        {
          "id": "rootcause:improper input validation",
          "keyphrase": "improper input validation",
          "type": "rootcause"
        },
        {
          "id": "impact:['load any web plugins or Java class'",
          "keyphrase": "['load any web plugins or Java class'",
          "type": "impact"
        },
        {
          "id": "impact:'alter the behavior of certain apps/OS'",
          "keyphrase": "'alter the behavior of certain apps/OS'",
          "type": "impact"
        },
        {
          "id": "impact:'Denial of Service']",
          "keyphrase": "'Denial of Service']",
          "type": "impact"
        },
        {
          "id": "attacker:remote low-privileged malicious user",
          "keyphrase": "remote low-privileged malicious user",
          "type": "attacker"
        },
        {
          "id": "product:Dell OpenManage Server Administrator",
          "keyphrase": "Dell OpenManage Server Administrator",
          "type": "product"
        },
        {
          "id": "version:11.0.1.0 and prior",
          "keyphrase": "11.0.1.0 and prior",
          "type": "version"
        }
      ],
      "74": [
        {
          "id": "rootcause:input validation vulnerability",
          "keyphrase": "input validation vulnerability",
          "type": "rootcause"
        },
        {
          "id": "product:Dell OpenManage Server Administrator",
          "keyphrase": "Dell OpenManage Server Administrator",
          "type": "product"
        }
      ],
      "470": [
        {
          "id": "impact:['load any web plugins or Java class'",
          "keyphrase": "['load any web plugins or Java class'",
          "type": "impact"
        }
      ],
      "732": [
        {
          "id": "impact:['load any web plugins or Java class'",
          "keyphrase": "['load any web plugins or Java class'",
          "type": "impact"
        },
        {
          "id": "impact:'Denial of Service']",
          "keyphrase": "'Denial of Service']",
          "type": "impact"
        },
        {
          "id": "attacker:remote low-privileged malicious user",
          "keyphrase": "remote low-privileged malicious user",
          "type": "attacker"
        },
        {
          "id": "product:Dell OpenManage Server Administrator",
          "keyphrase": "Dell OpenManage Server Administrator",
          "type": "product"
        },
        {
          "id": "version:11.0.1.0 and prior",
          "keyphrase": "11.0.1.0 and prior",
          "type": "version"
        }
      ],
      "23": [
        {
          "id": "impact:['load any web plugins or Java class'",
          "keyphrase": "['load any web plugins or Java class'",
          "type": "impact"
        }
      ],
      "347": [
        {
          "id": "impact:'alter the behavior of certain apps/OS'",
          "keyphrase": "'alter the behavior of certain apps/OS'",
          "type": "impact"
        }
      ],
      "119": [
        {
          "id": "impact:'Denial of Service']",
          "keyphrase": "'Denial of Service']",
          "type": "impact"
        }
      ],
      "250": [
        {
          "id": "attacker:remote low-privileged malicious user",
          "keyphrase": "remote low-privileged malicious user",
          "type": "attacker"
        }
      ]
    },
    "relevant_cwes": [
      {
        "metadata": {
          "doc_id": "20",
          "name": "Improper Input Validation",
          "source": "sparse",
          "original_content": "The product receives input or data, but it does\n        not validate or incorrectly validates that the input has the\n        properties that are required to process the data safely and\n        correctly.",
          "keyphrase_sources": [
            {
              "id": "rootcause:improper input validation",
              "keyphrase": "improper input validation",
              "type": "rootcause"
            },
            {
              "id": "rootcause:input validation vulnerability",
              "keyphrase": "input validation vulnerability",
              "type": "rootcause"
            },
            {
              "id": "impact:['load any web plugins or Java class'",
              "keyphrase": "['load any web plugins or Java class'",
              "type": "impact"
            },
            {
              "id": "impact:'alter the behavior of certain apps/OS'",
              "keyphrase": "'alter the behavior of certain apps/OS'",
              "type": "impact"
            },
            {
              "id": "impact:'Denial of Service']",
              "keyphrase": "'Denial of Service']",
              "type": "impact"
            },
            {
              "id": "attacker:remote low-privileged malicious user",
              "keyphrase": "remote low-privileged malicious user",
              "type": "attacker"
            },
            {
              "id": "version:11.0.1.0 and prior",
              "keyphrase": "11.0.1.0 and prior",
              "type": "version"
            }
          ]
        },
        "similarity": 306.767755913869
      },
      {
        "metadata": {
          "doc_id": "1284",
          "name": "Improper Validation of Specified Quantity in Input",
          "source": "sparse",
          "original_content": "The product receives input that is expected to specify a quantity (such as size or length), but it does not validate or incorrectly validates that the quantity has the required properties.",
          "keyphrase_sources": [
            {
              "id": "rootcause:improper input validation",
              "keyphrase": "improper input validation",
              "type": "rootcause"
            },
            {
              "id": "rootcause:input validation vulnerability",
              "keyphrase": "input validation vulnerability",
              "type": "rootcause"
            }
          ]
        },
        "similarity": 282.9938148838528
      },
      {
        "metadata": {
          "doc_id": "269",
          "name": "Improper Privilege Management",
          "source": "sparse",
          "original_content": "The product does not properly assign, modify, track, or check privileges for an actor, creating an unintended sphere of control for that actor.",
          "keyphrase_sources": [
            {
              "id": "rootcause:improper input validation",
              "keyphrase": "improper input validation",
              "type": "rootcause"
            },
            {
              "id": "rootcause:input validation vulnerability",
              "keyphrase": "input validation vulnerability",
              "type": "rootcause"
            },
            {
              "id": "impact:'alter the behavior of certain apps/OS'",
              "keyphrase": "'alter the behavior of certain apps/OS'",
              "type": "impact"
            },
            {
              "id": "impact:'Denial of Service']",
              "keyphrase": "'Denial of Service']",
              "type": "impact"
            },
            {
              "id": "attacker:remote low-privileged malicious user",
              "keyphrase": "remote low-privileged malicious user",
              "type": "attacker"
            },
            {
              "id": "product:Dell OpenManage Server Administrator",
              "keyphrase": "Dell OpenManage Server Administrator",
              "type": "product"
            },
            {
              "id": "version:11.0.1.0 and prior",
              "keyphrase": "11.0.1.0 and prior",
              "type": "version"
            }
          ]
        },
        "similarity": 279.5046789446745
      },
      {
        "metadata": {
          "doc_id": "287",
          "name": "Improper Authentication",
          "source": "sparse",
          "original_content": "When an actor claims to have a given identity, the product does not prove or insufficiently proves that the claim is correct.",
          "keyphrase_sources": [
            {
              "id": "rootcause:improper input validation",
              "keyphrase": "improper input validation",
              "type": "rootcause"
            },
            {
              "id": "rootcause:input validation vulnerability",
              "keyphrase": "input validation vulnerability",
              "type": "rootcause"
            },
            {
              "id": "impact:'alter the behavior of certain apps/OS'",
              "keyphrase": "'alter the behavior of certain apps/OS'",
              "type": "impact"
            },
            {
              "id": "product:Dell OpenManage Server Administrator",
              "keyphrase": "Dell OpenManage Server Administrator",
              "type": "product"
            },
            {
              "id": "version:11.0.1.0 and prior",
              "keyphrase": "11.0.1.0 and prior",
              "type": "version"
            }
          ]
        },
        "similarity": 277.8044167154874
      },
      {
        "metadata": {
          "doc_id": "285",
          "name": "Improper Authorization",
          "source": "sparse",
          "original_content": "The product does not perform or incorrectly performs an authorization check when an actor attempts to access a resource or perform an action.",
          "keyphrase_sources": [
            {
              "id": "rootcause:improper input validation",
              "keyphrase": "improper input validation",
              "type": "rootcause"
            },
            {
              "id": "impact:['load any web plugins or Java class'",
              "keyphrase": "['load any web plugins or Java class'",
              "type": "impact"
            },
            {
              "id": "impact:'alter the behavior of certain apps/OS'",
              "keyphrase": "'alter the behavior of certain apps/OS'",
              "type": "impact"
            },
            {
              "id": "impact:'Denial of Service']",
              "keyphrase": "'Denial of Service']",
              "type": "impact"
            },
            {
              "id": "attacker:remote low-privileged malicious user",
              "keyphrase": "remote low-privileged malicious user",
              "type": "attacker"
            },
            {
              "id": "product:Dell OpenManage Server Administrator",
              "keyphrase": "Dell OpenManage Server Administrator",
              "type": "product"
            },
            {
              "id": "version:11.0.1.0 and prior",
              "keyphrase": "11.0.1.0 and prior",
              "type": "version"
            }
          ]
        },
        "similarity": 275.3665438479781
      },
      {
        "metadata": {
          "doc_id": "74",
          "name": "Improper Neutralization of Special Elements in Output Used by a Downstream Component ('Injection')",
          "source": "sparse",
          "original_content": "The product constructs all or part of a command, data structure, or record using externally-influenced input from an upstream component, but it does not neutralize or incorrectly neutralizes special elements that could modify how it is parsed or interpreted when it is sent to a downstream component.",
          "keyphrase_sources": [
            {
              "id": "rootcause:input validation vulnerability",
              "keyphrase": "input validation vulnerability",
              "type": "rootcause"
            },
            {
              "id": "product:Dell OpenManage Server Administrator",
              "keyphrase": "Dell OpenManage Server Administrator",
              "type": "product"
            }
          ]
        },
        "similarity": 271.16287563283845
      },
      {
        "metadata": {
          "doc_id": "470",
          "name": "Use of Externally-Controlled Input to Select Classes or Code ('Unsafe Reflection')",
          "source": "sparse",
          "original_content": "The product uses external input with reflection to select which classes or code to use, but it does not sufficiently prevent the input from selecting improper classes or code.",
          "keyphrase_sources": [
            {
              "id": "impact:['load any web plugins or Java class'",
              "keyphrase": "['load any web plugins or Java class'",
              "type": "impact"
            }
          ]
        },
        "similarity": 118.00281086948155
      },
      {
        "metadata": {
          "doc_id": "347",
          "name": "Improper Verification of Cryptographic Signature",
          "source": "sparse",
          "original_content": "The product does not verify, or incorrectly verifies, the cryptographic signature for data.",
          "keyphrase_sources": [
            {
              "id": "impact:'alter the behavior of certain apps/OS'",
              "keyphrase": "'alter the behavior of certain apps/OS'",
              "type": "impact"
            }
          ]
        },
        "similarity": 112.86431002679578
      },
      {
        "metadata": {
          "doc_id": "732",
          "name": "Incorrect Permission Assignment for Critical Resource",
          "source": "sparse",
          "original_content": "The product specifies permissions for a security-critical resource in a way that allows that resource to be read or modified by unintended actors.",
          "keyphrase_sources": [
            {
              "id": "impact:['load any web plugins or Java class'",
              "keyphrase": "['load any web plugins or Java class'",
              "type": "impact"
            },
            {
              "id": "impact:'Denial of Service']",
              "keyphrase": "'Denial of Service']",
              "type": "impact"
            },
            {
              "id": "attacker:remote low-privileged malicious user",
              "keyphrase": "remote low-privileged malicious user",
              "type": "attacker"
            },
            {
              "id": "product:Dell OpenManage Server Administrator",
              "keyphrase": "Dell OpenManage Server Administrator",
              "type": "product"
            },
            {
              "id": "version:11.0.1.0 and prior",
              "keyphrase": "11.0.1.0 and prior",
              "type": "version"
            }
          ]
        },
        "similarity": 104.31873165137284
      },
      {
        "metadata": {
          "doc_id": "23",
          "name": "Relative Path Traversal",
          "source": "sparse",
          "original_content": "The product uses external input to construct a pathname that should be within a restricted directory, but it does not properly neutralize sequences such as \"..\" that can resolve to a location that is outside of that directory.",
          "keyphrase_sources": [
            {
              "id": "impact:['load any web plugins or Java class'",
              "keyphrase": "['load any web plugins or Java class'",
              "type": "impact"
            }
          ]
        },
        "similarity": 102.17053806938446
      },
      {
        "metadata": {
          "doc_id": "250",
          "name": "Execution with Unnecessary Privileges",
          "source": "sparse",
          "original_content": "The product performs an operation at a privilege level that is higher than the minimum level required, which creates new weaknesses or amplifies the consequences of other weaknesses.",
          "keyphrase_sources": [
            {
              "id": "attacker:remote low-privileged malicious user",
              "keyphrase": "remote low-privileged malicious user",
              "type": "attacker"
            }
          ]
        },
        "similarity": 99.31774834909922
      },
      {
        "metadata": {
          "doc_id": "119",
          "name": "Improper Restriction of Operations within the Bounds of a Memory Buffer",
          "source": "sparse",
          "original_content": "The product performs operations on a memory buffer, but it reads from or writes to a memory location outside the buffer's intended boundary. This may result in read or write operations on unexpected memory locations that could be linked to other variables, data structures, or internal program data.",
          "keyphrase_sources": [
            {
              "id": "impact:'Denial of Service']",
              "keyphrase": "'Denial of Service']",
              "type": "impact"
            }
          ]
        },
        "similarity": 98.94429328691186
      }
    ],
    "enhanced_query": "# Vulnerability Description\n\n    Dell OpenManage Server Administrator, versions 11.0.1.0 and prior, contains an **improper input validation** vulnerability. A remote low-privileged malicious user could potentially exploit this vulnerability to load any web plugins or Java class leading to the possibility of altering the behavior of certain apps/OS or Denial of Service.\n\n    # Keyphrase-Specific CWE Analysis\n    This vulnerability contains multiple keyphrases that may map to different CWEs. \n    Please analyze each keyphrase separately and determine the most appropriate CWE(s) for each.\n\n    ## ROOTCAUSE: 'improper input validation'\n\nRelevant CWEs for this ROOTCAUSE:\n\n### 1. CWE-20: Improper Input Validation (Score: 306.77)\n\nThe product receives input or data, but it does\n        not validate or incorrectly validates that the input has the\n        properties that are required to process the data safely and\n        correctly....\n\n### 2. CWE-1284: Improper Validation of Specified Quantity in Input (Score: 282.99)\n\nThe product receives input that is expected to specify a quantity (such as size or length), but it does not validate or incorrectly validates that the quantity has the required properties....\n\n### 3. CWE-269: Improper Privilege Management (Score: 279.50)\n\nThe product does not properly assign, modify, track, or check privileges for an actor, creating an unintended sphere of control for that actor....\n\n### 4. CWE-287: Improper Authentication (Score: 277.80)\n\nWhen an actor claims to have a given identity, the product does not prove or insufficiently proves that the claim is correct....\n\n### 5. CWE-285: Improper Authorization (Score: 275.37)\n\nThe product does not perform or incorrectly performs an authorization check when an actor attempts to access a resource or perform an action....\n\n## ROOTCAUSE: 'input validation vulnerability'\n\nRelevant CWEs for this ROOTCAUSE:\n\n### 1. CWE-20: Improper Input Validation (Score: 306.77)\n\nThe product receives input or data, but it does\n        not validate or incorrectly validates that the input has the\n        properties that are required to process the data safely and\n        correctly....\n\n### 2. CWE-1284: Improper Validation of Specified Quantity in Input (Score: 282.99)\n\nThe product receives input that is expected to specify a quantity (such as size or length), but it does not validate or incorrectly validates that the quantity has the required properties....\n\n### 3. CWE-269: Improper Privilege Management (Score: 279.50)\n\nThe product does not properly assign, modify, track, or check privileges for an actor, creating an unintended sphere of control for that actor....\n\n### 4. CWE-287: Improper Authentication (Score: 277.80)\n\nWhen an actor claims to have a given identity, the product does not prove or insufficiently proves that the claim is correct....\n\n### 5. CWE-74: Improper Neutralization of Special Elements in Output Used by a Downstream Component ('Injection') (Score: 271.16)\n\nThe product constructs all or part of a command, data structure, or record using externally-influenced input from an upstream component, but it does not neutralize or incorrectly neutralizes special elements that could modify how it is parsed or interpreted when it is sent to a downstream component....\n\n## IMPACT: '['load any web plugins or Java class''\n\nRelevant CWEs for this IMPACT:\n\n### 1. CWE-20: Improper Input Validation (Score: 306.77)\n\nThe product receives input or data, but it does\n        not validate or incorrectly validates that the input has the\n        properties that are required to process the data safely and\n        correctly....\n\n### 2. CWE-285: Improper Authorization (Score: 275.37)\n\nThe product does not perform or incorrectly performs an authorization check when an actor attempts to access a resource or perform an action....\n\n### 3. CWE-470: Use of Externally-Controlled Input to Select Classes or Code ('Unsafe Reflection') (Score: 118.00)\n\nThe product uses external input with reflection to select which classes or code to use, but it does not sufficiently prevent the input from selecting improper classes or code....\n\n### 4. CWE-732: Incorrect Permission Assignment for Critical Resource (Score: 104.32)\n\nThe product specifies permissions for a security-critical resource in a way that allows that resource to be read or modified by unintended actors....\n\n### 5. CWE-23: Relative Path Traversal (Score: 102.17)\n\nThe product uses external input to construct a pathname that should be within a restricted directory, but it does not properly neutralize sequences such as \"..\" that can resolve to a location that is outside of that directory....\n\n## IMPACT: ''alter the behavior of certain apps/OS''\n\nRelevant CWEs for this IMPACT:\n\n### 1. CWE-20: Improper Input Validation (Score: 306.77)\n\nThe product receives input or data, but it does\n        not validate or incorrectly validates that the input has the\n        properties that are required to process the data safely and\n        correctly....\n\n### 2. CWE-269: Improper Privilege Management (Score: 279.50)\n\nThe product does not properly assign, modify, track, or check privileges for an actor, creating an unintended sphere of control for that actor....\n\n### 3. CWE-287: Improper Authentication (Score: 277.80)\n\nWhen an actor claims to have a given identity, the product does not prove or insufficiently proves that the claim is correct....\n\n### 4. CWE-285: Improper Authorization (Score: 275.37)\n\nThe product does not perform or incorrectly performs an authorization check when an actor attempts to access a resource or perform an action....\n\n### 5. CWE-347: Improper Verification of Cryptographic Signature (Score: 112.86)\n\nThe product does not verify, or incorrectly verifies, the cryptographic signature for data....\n\n## IMPACT: ''Denial of Service']'\n\nRelevant CWEs for this IMPACT:\n\n### 1. CWE-20: Improper Input Validation (Score: 306.77)\n\nThe product receives input or data, but it does\n        not validate or incorrectly validates that the input has the\n        properties that are required to process the data safely and\n        correctly....\n\n### 2. CWE-269: Improper Privilege Management (Score: 279.50)\n\nThe product does not properly assign, modify, track, or check privileges for an actor, creating an unintended sphere of control for that actor....\n\n### 3. CWE-285: Improper Authorization (Score: 275.37)\n\nThe product does not perform or incorrectly performs an authorization check when an actor attempts to access a resource or perform an action....\n\n### 4. CWE-732: Incorrect Permission Assignment for Critical Resource (Score: 104.32)\n\nThe product specifies permissions for a security-critical resource in a way that allows that resource to be read or modified by unintended actors....\n\n### 5. CWE-119: Improper Restriction of Operations within the Bounds of a Memory Buffer (Score: 98.94)\n\nThe product performs operations on a memory buffer, but it reads from or writes to a memory location outside the buffer's intended boundary. This may result in read or write operations on unexpected memory locations that could be linked to other variables, data structures, or internal program data....\n\n## ATTACKER: 'remote low-privileged malicious user'\n\nRelevant CWEs for this ATTACKER:\n\n### 1. CWE-20: Improper Input Validation (Score: 306.77)\n\nThe product receives input or data, but it does\n        not validate or incorrectly validates that the input has the\n        properties that are required to process the data safely and\n        correctly....\n\n### 2. CWE-269: Improper Privilege Management (Score: 279.50)\n\nThe product does not properly assign, modify, track, or check privileges for an actor, creating an unintended sphere of control for that actor....\n\n### 3. CWE-285: Improper Authorization (Score: 275.37)\n\nThe product does not perform or incorrectly performs an authorization check when an actor attempts to access a resource or perform an action....\n\n### 4. CWE-732: Incorrect Permission Assignment for Critical Resource (Score: 104.32)\n\nThe product specifies permissions for a security-critical resource in a way that allows that resource to be read or modified by unintended actors....\n\n### 5. CWE-250: Execution with Unnecessary Privileges (Score: 99.32)\n\nThe product performs an operation at a privilege level that is higher than the minimum level required, which creates new weaknesses or amplifies the consequences of other weaknesses....\n\n## VERSION: '11.0.1.0 and prior'\n\nRelevant CWEs for this VERSION:\n\n### 1. CWE-20: Improper Input Validation (Score: 306.77)\n\nThe product receives input or data, but it does\n        not validate or incorrectly validates that the input has the\n        properties that are required to process the data safely and\n        correctly....\n\n### 2. CWE-269: Improper Privilege Management (Score: 279.50)\n\nThe product does not properly assign, modify, track, or check privileges for an actor, creating an unintended sphere of control for that actor....\n\n### 3. CWE-287: Improper Authentication (Score: 277.80)\n\nWhen an actor claims to have a given identity, the product does not prove or insufficiently proves that the claim is correct....\n\n### 4. CWE-285: Improper Authorization (Score: 275.37)\n\nThe product does not perform or incorrectly performs an authorization check when an actor attempts to access a resource or perform an action....\n\n### 5. CWE-732: Incorrect Permission Assignment for Critical Resource (Score: 104.32)\n\nThe product specifies permissions for a security-critical resource in a way that allows that resource to be read or modified by unintended actors....\n\n## PRODUCT: 'Dell OpenManage Server Administrator'\n\nRelevant CWEs for this PRODUCT:\n\n### 1. CWE-269: Improper Privilege Management (Score: 279.50)\n\nThe product does not properly assign, modify, track, or check privileges for an actor, creating an unintended sphere of control for that actor....\n\n### 2. CWE-287: Improper Authentication (Score: 277.80)\n\nWhen an actor claims to have a given identity, the product does not prove or insufficiently proves that the claim is correct....\n\n### 3. CWE-285: Improper Authorization (Score: 275.37)\n\nThe product does not perform or incorrectly performs an authorization check when an actor attempts to access a resource or perform an action....\n\n### 4. CWE-74: Improper Neutralization of Special Elements in Output Used by a Downstream Component ('Injection') (Score: 271.16)\n\nThe product constructs all or part of a command, data structure, or record using externally-influenced input from an upstream component, but it does not neutralize or incorrectly neutralizes special elements that could modify how it is parsed or interpreted when it is sent to a downstream component....\n\n### 5. CWE-732: Incorrect Permission Assignment for Critical Resource (Score: 104.32)\n\nThe product specifies permissions for a security-critical resource in a way that allows that resource to be read or modified by unintended actors....\n\n\n    # Analysis Instructions\n    1. For each keyphrase, identify the most appropriate CWE(s) that represent the weakness.\n    2. Consider how the different keyphrases might relate to each other in the vulnerability chain.\n    3. Provide a final determination of primary CWE(s) and any secondary CWEs.\n    4. Format your response using the standard analysis template.\n\n    Please analyze how these different weaknesses interact and provide a comprehensive CWE classification.\n    "
  },
  "retrieval_time": 1.332472324371338
}