{
  "vulnerability_info": "VulnerabilityInfo(cve_id='CVE-2024-38479', description='**Improper Input Validation** vulnerability in Apache Traffic Server. This issue affects Apache Traffic Server from 8.0.0 through 8.1.11, from 9.0.0 through 9.2.5. Users are recommended to upgrade to version 9.2.6, which fixes the issue, or 10.0.2, which does not have the issue.', key_phrases={'rootcause': ['Improper Input Validation', 'Input Validation vulnerability'], 'weakness': '', 'impact': '', 'vector': '', 'attacker': '', 'product': 'Apache Traffic Server', 'version': ['8.0.0 through 8.1.11', '9.0.0 through 9.2.5'], 'component': ''}, reference_content='UNRELATED', similar_info={'cwe_distribution': {}, 'cwe_consensus': '', 'similarity_stats': {'thresholds': [], 'total_samples_by_threshold': {}, 'top_cwes_by_threshold': {}}}, similarity_summary=SimilarityInsight(consensus_cwe='', top_cwes=[], confidence_levels={}, total_samples=0), analysis='', analysis_with_relationships='', criticism='', resolution='', relevant_cwes=[{'metadata': {'doc_id': '20', 'name': 'Improper Input Validation', 'source': 'sparse', 'original_content': 'The product receives input or data, but it does\\n        not validate or incorrectly validates that the input has the\\n        properties that are required to process the data safely and\\n        correctly.', 'keyphrase_sources': [{'id': 'rootcause:Improper Input Validation', 'keyphrase': 'Improper Input Validation', 'type': 'rootcause'}, {'id': 'rootcause:Input Validation vulnerability', 'keyphrase': 'Input Validation vulnerability', 'type': 'rootcause'}, {'id': 'product:Apache Traffic Server', 'keyphrase': 'Apache Traffic Server', 'type': 'product'}, {'id': 'version:8.0.0 through 8.1.11', 'keyphrase': '8.0.0 through 8.1.11', 'type': 'version'}, {'id': 'version:9.0.0 through 9.2.5', 'keyphrase': '9.0.0 through 9.2.5', 'type': 'version'}]}, 'similarity': np.float64(322.4125875755275)}, {'metadata': {'doc_id': '116', 'name': 'Improper Encoding or Escaping of Output', 'source': 'sparse', 'original_content': 'The product prepares a structured message for communication with another component, but encoding or escaping of the data is either missing or done incorrectly. As a result, the intended structure of the message is not preserved.', 'keyphrase_sources': [{'id': 'rootcause:Improper Input Validation', 'keyphrase': 'Improper Input Validation', 'type': 'rootcause'}, {'id': 'rootcause:Input Validation vulnerability', 'keyphrase': 'Input Validation vulnerability', 'type': 'rootcause'}]}, 'similarity': np.float64(309.02094240005226)}, {'metadata': {'doc_id': '1284', 'name': 'Improper Validation of Specified Quantity in Input', 'source': 'sparse', 'original_content': 'The product receives input that is expected to specify a quantity (such as size or length), but it does not validate or incorrectly validates that the quantity has the required properties.', 'keyphrase_sources': [{'id': 'rootcause:Improper Input Validation', 'keyphrase': 'Improper Input Validation', 'type': 'rootcause'}, {'id': 'rootcause:Input Validation vulnerability', 'keyphrase': 'Input Validation vulnerability', 'type': 'rootcause'}]}, 'similarity': np.float64(304.95963331000803)}, {'metadata': {'doc_id': '90', 'name': \"Improper Neutralization of Special Elements used in an LDAP Query ('LDAP Injection')\", 'source': 'sparse', 'original_content': 'The product constructs all or part of an LDAP query using externally-influenced input from an upstream component, but it does not neutralize or incorrectly neutralizes special elements that could modify the intended LDAP query when it is sent to a downstream component.', 'keyphrase_sources': [{'id': 'rootcause:Improper Input Validation', 'keyphrase': 'Improper Input Validation', 'type': 'rootcause'}, {'id': 'rootcause:Input Validation vulnerability', 'keyphrase': 'Input Validation vulnerability', 'type': 'rootcause'}, {'id': 'product:Apache Traffic Server', 'keyphrase': 'Apache Traffic Server', 'type': 'product'}]}, 'similarity': np.float64(304.10854919489185)}, {'metadata': {'doc_id': '1333', 'name': 'Inefficient Regular Expression Complexity', 'source': 'sparse', 'original_content': 'The product uses a regular expression with an inefficient, possibly exponential worst-case computational complexity that consumes excessive CPU cycles.', 'keyphrase_sources': [{'id': 'rootcause:Input Validation vulnerability', 'keyphrase': 'Input Validation vulnerability', 'type': 'rootcause'}]}, 'similarity': np.float64(303.5930486785998)}, {'metadata': {'doc_id': '923', 'name': 'Improper Restriction of Communication Channel to Intended Endpoints', 'source': 'sparse', 'original_content': 'The product establishes a communication channel to (or from) an endpoint for privileged or protected operations, but it does not properly ensure that it is communicating with the correct endpoint.', 'keyphrase_sources': [{'id': 'rootcause:Improper Input Validation', 'keyphrase': 'Improper Input Validation', 'type': 'rootcause'}, {'id': 'product:Apache Traffic Server', 'keyphrase': 'Apache Traffic Server', 'type': 'product'}, {'id': 'version:9.0.0 through 9.2.5', 'keyphrase': '9.0.0 through 9.2.5', 'type': 'version'}]}, 'similarity': np.float64(301.9385756366287)}, {'metadata': {'doc_id': '863', 'name': 'Incorrect Authorization', 'source': 'sparse', 'original_content': 'The product performs an authorization check when an actor attempts to access a resource or perform an action, but it does not correctly perform the check.', 'keyphrase_sources': [{'id': 'version:8.0.0 through 8.1.11', 'keyphrase': '8.0.0 through 8.1.11', 'type': 'version'}, {'id': 'version:9.0.0 through 9.2.5', 'keyphrase': '9.0.0 through 9.2.5', 'type': 'version'}]}, 'similarity': np.float64(113.96660559687153)}, {'metadata': {'doc_id': '22', 'name': \"Improper Limitation of a Pathname to a Restricted Directory ('Path Traversal')\", 'source': 'sparse', 'original_content': 'The product uses external input to construct a pathname that is intended to identify a file or directory that is located underneath a restricted parent directory, but the product does not properly neutralize special elements within the pathname that can cause the pathname to resolve to a location that is outside of the restricted directory.', 'keyphrase_sources': [{'id': 'version:8.0.0 through 8.1.11', 'keyphrase': '8.0.0 through 8.1.11', 'type': 'version'}]}, 'similarity': np.float64(111.32787484606185)}, {'metadata': {'doc_id': '93', 'name': \"Improper Neutralization of CRLF Sequences ('CRLF Injection')\", 'source': 'sparse', 'original_content': 'The product uses CRLF (carriage return line feeds) as a special element, e.g. to separate lines or records, but it does not neutralize or incorrectly neutralizes CRLF sequences from inputs.', 'keyphrase_sources': [{'id': 'version:8.0.0 through 8.1.11', 'keyphrase': '8.0.0 through 8.1.11', 'type': 'version'}]}, 'similarity': np.float64(110.97118752537557)}, {'metadata': {'doc_id': '532', 'name': 'Insertion of Sensitive Information into Log File', 'source': 'sparse', 'original_content': 'The product writes sensitive information to a log file.', 'keyphrase_sources': [{'id': 'version:9.0.0 through 9.2.5', 'keyphrase': '9.0.0 through 9.2.5', 'type': 'version'}]}, 'similarity': np.float64(110.65547906935656)}, {'metadata': {'doc_id': '614', 'name': \"Sensitive Cookie in HTTPS Session Without 'Secure' Attribute\", 'source': 'sparse', 'original_content': 'The Secure attribute for sensitive cookies in HTTPS sessions is not set, which could cause the user agent to send those cookies in plaintext over an HTTP session.', 'keyphrase_sources': [{'id': 'product:Apache Traffic Server', 'keyphrase': 'Apache Traffic Server', 'type': 'product'}]}, 'similarity': np.float64(110.4241072105773)}, {'metadata': {'doc_id': '201', 'name': 'Insertion of Sensitive Information Into Sent Data', 'source': 'sparse', 'original_content': 'The code transmits data to another actor, but a portion of the data includes sensitive information that should not be accessible to that actor.', 'keyphrase_sources': [{'id': 'product:Apache Traffic Server', 'keyphrase': 'Apache Traffic Server', 'type': 'product'}, {'id': 'version:8.0.0 through 8.1.11', 'keyphrase': '8.0.0 through 8.1.11', 'type': 'version'}, {'id': 'version:9.0.0 through 9.2.5', 'keyphrase': '9.0.0 through 9.2.5', 'type': 'version'}]}, 'similarity': np.float64(107.21284953399241)}], identified_cwes={'analyzer': [], 'critic_additional': []})",
  "retrieval_results": {
    "has_multiple_keyphrases": true,
    "keyphrase_cwe_sets": {
      "rootcause:Improper Input Validation": {
        "keyphrase": "Improper Input Validation",
        "type": "rootcause",
        "cwes": [
          {
            "metadata": {
              "doc_id": "20",
              "name": "Improper Input Validation",
              "source": "sparse",
              "original_content": "The product receives input or data, but it does\n        not validate or incorrectly validates that the input has the\n        properties that are required to process the data safely and\n        correctly.",
              "keyphrase_sources": [
                {
                  "id": "rootcause:Improper Input Validation",
                  "keyphrase": "Improper Input Validation",
                  "type": "rootcause"
                },
                {
                  "id": "rootcause:Input Validation vulnerability",
                  "keyphrase": "Input Validation vulnerability",
                  "type": "rootcause"
                },
                {
                  "id": "product:Apache Traffic Server",
                  "keyphrase": "Apache Traffic Server",
                  "type": "product"
                },
                {
                  "id": "version:8.0.0 through 8.1.11",
                  "keyphrase": "8.0.0 through 8.1.11",
                  "type": "version"
                },
                {
                  "id": "version:9.0.0 through 9.2.5",
                  "keyphrase": "9.0.0 through 9.2.5",
                  "type": "version"
                }
              ]
            },
            "similarity": 322.4125875755275
          },
          {
            "metadata": {
              "doc_id": "116",
              "name": "Improper Encoding or Escaping of Output",
              "source": "sparse",
              "original_content": "The product prepares a structured message for communication with another component, but encoding or escaping of the data is either missing or done incorrectly. As a result, the intended structure of the message is not preserved.",
              "keyphrase_sources": [
                {
                  "id": "rootcause:Improper Input Validation",
                  "keyphrase": "Improper Input Validation",
                  "type": "rootcause"
                },
                {
                  "id": "rootcause:Input Validation vulnerability",
                  "keyphrase": "Input Validation vulnerability",
                  "type": "rootcause"
                }
              ]
            },
            "similarity": 309.02094240005226
          },
          {
            "metadata": {
              "doc_id": "1284",
              "name": "Improper Validation of Specified Quantity in Input",
              "source": "sparse",
              "original_content": "The product receives input that is expected to specify a quantity (such as size or length), but it does not validate or incorrectly validates that the quantity has the required properties.",
              "keyphrase_sources": [
                {
                  "id": "rootcause:Improper Input Validation",
                  "keyphrase": "Improper Input Validation",
                  "type": "rootcause"
                },
                {
                  "id": "rootcause:Input Validation vulnerability",
                  "keyphrase": "Input Validation vulnerability",
                  "type": "rootcause"
                }
              ]
            },
            "similarity": 304.95963331000803
          },
          {
            "metadata": {
              "doc_id": "90",
              "name": "Improper Neutralization of Special Elements used in an LDAP Query ('LDAP Injection')",
              "source": "sparse",
              "original_content": "The product constructs all or part of an LDAP query using externally-influenced input from an upstream component, but it does not neutralize or incorrectly neutralizes special elements that could modify the intended LDAP query when it is sent to a downstream component.",
              "keyphrase_sources": [
                {
                  "id": "rootcause:Improper Input Validation",
                  "keyphrase": "Improper Input Validation",
                  "type": "rootcause"
                },
                {
                  "id": "rootcause:Input Validation vulnerability",
                  "keyphrase": "Input Validation vulnerability",
                  "type": "rootcause"
                },
                {
                  "id": "product:Apache Traffic Server",
                  "keyphrase": "Apache Traffic Server",
                  "type": "product"
                }
              ]
            },
            "similarity": 304.10854919489185
          },
          {
            "metadata": {
              "doc_id": "923",
              "name": "Improper Restriction of Communication Channel to Intended Endpoints",
              "source": "sparse",
              "original_content": "The product establishes a communication channel to (or from) an endpoint for privileged or protected operations, but it does not properly ensure that it is communicating with the correct endpoint.",
              "keyphrase_sources": [
                {
                  "id": "rootcause:Improper Input Validation",
                  "keyphrase": "Improper Input Validation",
                  "type": "rootcause"
                },
                {
                  "id": "product:Apache Traffic Server",
                  "keyphrase": "Apache Traffic Server",
                  "type": "product"
                },
                {
                  "id": "version:9.0.0 through 9.2.5",
                  "keyphrase": "9.0.0 through 9.2.5",
                  "type": "version"
                }
              ]
            },
            "similarity": 301.9385756366287
          }
        ]
      },
      "rootcause:Input Validation vulnerability": {
        "keyphrase": "Input Validation vulnerability",
        "type": "rootcause",
        "cwes": [
          {
            "metadata": {
              "doc_id": "20",
              "name": "Improper Input Validation",
              "source": "sparse",
              "original_content": "The product receives input or data, but it does\n        not validate or incorrectly validates that the input has the\n        properties that are required to process the data safely and\n        correctly."
            },
            "similarity": 317.65960905809305
          },
          {
            "metadata": {
              "doc_id": "116",
              "name": "Improper Encoding or Escaping of Output",
              "source": "sparse",
              "original_content": "The product prepares a structured message for communication with another component, but encoding or escaping of the data is either missing or done incorrectly. As a result, the intended structure of the message is not preserved."
            },
            "similarity": 306.5746054683249
          },
          {
            "metadata": {
              "doc_id": "1333",
              "name": "Inefficient Regular Expression Complexity",
              "source": "sparse",
              "original_content": "The product uses a regular expression with an inefficient, possibly exponential worst-case computational complexity that consumes excessive CPU cycles.",
              "keyphrase_sources": [
                {
                  "id": "rootcause:Input Validation vulnerability",
                  "keyphrase": "Input Validation vulnerability",
                  "type": "rootcause"
                }
              ]
            },
            "similarity": 303.5930486785998
          },
          {
            "metadata": {
              "doc_id": "90",
              "name": "Improper Neutralization of Special Elements used in an LDAP Query ('LDAP Injection')",
              "source": "sparse",
              "original_content": "The product constructs all or part of an LDAP query using externally-influenced input from an upstream component, but it does not neutralize or incorrectly neutralizes special elements that could modify the intended LDAP query when it is sent to a downstream component."
            },
            "similarity": 302.21298739140695
          },
          {
            "metadata": {
              "doc_id": "1284",
              "name": "Improper Validation of Specified Quantity in Input",
              "source": "sparse",
              "original_content": "The product receives input that is expected to specify a quantity (such as size or length), but it does not validate or incorrectly validates that the quantity has the required properties."
            },
            "similarity": 301.90472344573834
          }
        ]
      },
      "product:Apache Traffic Server": {
        "keyphrase": "Apache Traffic Server",
        "type": "product",
        "cwes": [
          {
            "metadata": {
              "doc_id": "923",
              "name": "Improper Restriction of Communication Channel to Intended Endpoints",
              "source": "sparse",
              "original_content": "The product establishes a communication channel to (or from) an endpoint for privileged or protected operations, but it does not properly ensure that it is communicating with the correct endpoint."
            },
            "similarity": 110.79692682361296
          },
          {
            "metadata": {
              "doc_id": "614",
              "name": "Sensitive Cookie in HTTPS Session Without 'Secure' Attribute",
              "source": "sparse",
              "original_content": "The Secure attribute for sensitive cookies in HTTPS sessions is not set, which could cause the user agent to send those cookies in plaintext over an HTTP session.",
              "keyphrase_sources": [
                {
                  "id": "product:Apache Traffic Server",
                  "keyphrase": "Apache Traffic Server",
                  "type": "product"
                }
              ]
            },
            "similarity": 110.4241072105773
          },
          {
            "metadata": {
              "doc_id": "90",
              "name": "Improper Neutralization of Special Elements used in an LDAP Query ('LDAP Injection')",
              "source": "sparse",
              "original_content": "The product constructs all or part of an LDAP query using externally-influenced input from an upstream component, but it does not neutralize or incorrectly neutralizes special elements that could modify the intended LDAP query when it is sent to a downstream component."
            },
            "similarity": 109.74583222437748
          },
          {
            "metadata": {
              "doc_id": "201",
              "name": "Insertion of Sensitive Information Into Sent Data",
              "source": "sparse",
              "original_content": "The code transmits data to another actor, but a portion of the data includes sensitive information that should not be accessible to that actor.",
              "keyphrase_sources": [
                {
                  "id": "product:Apache Traffic Server",
                  "keyphrase": "Apache Traffic Server",
                  "type": "product"
                },
                {
                  "id": "version:8.0.0 through 8.1.11",
                  "keyphrase": "8.0.0 through 8.1.11",
                  "type": "version"
                },
                {
                  "id": "version:9.0.0 through 9.2.5",
                  "keyphrase": "9.0.0 through 9.2.5",
                  "type": "version"
                }
              ]
            },
            "similarity": 107.21284953399241
          },
          {
            "metadata": {
              "doc_id": "20",
              "name": "Improper Input Validation",
              "source": "sparse",
              "original_content": "The product receives input or data, but it does\n        not validate or incorrectly validates that the input has the\n        properties that are required to process the data safely and\n        correctly."
            },
            "similarity": 105.41535075280488
          }
        ]
      },
      "version:8.0.0 through 8.1.11": {
        "keyphrase": "8.0.0 through 8.1.11",
        "type": "version",
        "cwes": [
          {
            "metadata": {
              "doc_id": "863",
              "name": "Incorrect Authorization",
              "source": "sparse",
              "original_content": "The product performs an authorization check when an actor attempts to access a resource or perform an action, but it does not correctly perform the check.",
              "keyphrase_sources": [
                {
                  "id": "version:8.0.0 through 8.1.11",
                  "keyphrase": "8.0.0 through 8.1.11",
                  "type": "version"
                },
                {
                  "id": "version:9.0.0 through 9.2.5",
                  "keyphrase": "9.0.0 through 9.2.5",
                  "type": "version"
                }
              ]
            },
            "similarity": 113.96660559687153
          },
          {
            "metadata": {
              "doc_id": "201",
              "name": "Insertion of Sensitive Information Into Sent Data",
              "source": "sparse",
              "original_content": "The code transmits data to another actor, but a portion of the data includes sensitive information that should not be accessible to that actor."
            },
            "similarity": 113.23208453024428
          },
          {
            "metadata": {
              "doc_id": "22",
              "name": "Improper Limitation of a Pathname to a Restricted Directory ('Path Traversal')",
              "source": "sparse",
              "original_content": "The product uses external input to construct a pathname that is intended to identify a file or directory that is located underneath a restricted parent directory, but the product does not properly neutralize special elements within the pathname that can cause the pathname to resolve to a location that is outside of the restricted directory.",
              "keyphrase_sources": [
                {
                  "id": "version:8.0.0 through 8.1.11",
                  "keyphrase": "8.0.0 through 8.1.11",
                  "type": "version"
                }
              ]
            },
            "similarity": 111.32787484606185
          },
          {
            "metadata": {
              "doc_id": "20",
              "name": "Improper Input Validation",
              "source": "sparse",
              "original_content": "The product receives input or data, but it does\n        not validate or incorrectly validates that the input has the\n        properties that are required to process the data safely and\n        correctly."
            },
            "similarity": 111.1152549596382
          },
          {
            "metadata": {
              "doc_id": "93",
              "name": "Improper Neutralization of CRLF Sequences ('CRLF Injection')",
              "source": "sparse",
              "original_content": "The product uses CRLF (carriage return line feeds) as a special element, e.g. to separate lines or records, but it does not neutralize or incorrectly neutralizes CRLF sequences from inputs.",
              "keyphrase_sources": [
                {
                  "id": "version:8.0.0 through 8.1.11",
                  "keyphrase": "8.0.0 through 8.1.11",
                  "type": "version"
                }
              ]
            },
            "similarity": 110.97118752537557
          }
        ]
      },
      "version:9.0.0 through 9.2.5": {
        "keyphrase": "9.0.0 through 9.2.5",
        "type": "version",
        "cwes": [
          {
            "metadata": {
              "doc_id": "923",
              "name": "Improper Restriction of Communication Channel to Intended Endpoints",
              "source": "sparse",
              "original_content": "The product establishes a communication channel to (or from) an endpoint for privileged or protected operations, but it does not properly ensure that it is communicating with the correct endpoint."
            },
            "similarity": 115.01537250166443
          },
          {
            "metadata": {
              "doc_id": "863",
              "name": "Incorrect Authorization",
              "source": "sparse",
              "original_content": "The product performs an authorization check when an actor attempts to access a resource or perform an action, but it does not correctly perform the check."
            },
            "similarity": 114.06260777852351
          },
          {
            "metadata": {
              "doc_id": "201",
              "name": "Insertion of Sensitive Information Into Sent Data",
              "source": "sparse",
              "original_content": "The code transmits data to another actor, but a portion of the data includes sensitive information that should not be accessible to that actor."
            },
            "similarity": 113.05096299541138
          },
          {
            "metadata": {
              "doc_id": "20",
              "name": "Improper Input Validation",
              "source": "sparse",
              "original_content": "The product receives input or data, but it does\n        not validate or incorrectly validates that the input has the\n        properties that are required to process the data safely and\n        correctly."
            },
            "similarity": 111.0337974340231
          },
          {
            "metadata": {
              "doc_id": "532",
              "name": "Insertion of Sensitive Information into Log File",
              "source": "sparse",
              "original_content": "The product writes sensitive information to a log file.",
              "keyphrase_sources": [
                {
                  "id": "version:9.0.0 through 9.2.5",
                  "keyphrase": "9.0.0 through 9.2.5",
                  "type": "version"
                }
              ]
            },
            "similarity": 110.65547906935656
          }
        ]
      }
    },
    "keyphrase_mapping": {
      "20": [
        {
          "id": "rootcause:Improper Input Validation",
          "keyphrase": "Improper Input Validation",
          "type": "rootcause"
        },
        {
          "id": "rootcause:Input Validation vulnerability",
          "keyphrase": "Input Validation vulnerability",
          "type": "rootcause"
        },
        {
          "id": "product:Apache Traffic Server",
          "keyphrase": "Apache Traffic Server",
          "type": "product"
        },
        {
          "id": "version:8.0.0 through 8.1.11",
          "keyphrase": "8.0.0 through 8.1.11",
          "type": "version"
        },
        {
          "id": "version:9.0.0 through 9.2.5",
          "keyphrase": "9.0.0 through 9.2.5",
          "type": "version"
        }
      ],
      "116": [
        {
          "id": "rootcause:Improper Input Validation",
          "keyphrase": "Improper Input Validation",
          "type": "rootcause"
        },
        {
          "id": "rootcause:Input Validation vulnerability",
          "keyphrase": "Input Validation vulnerability",
          "type": "rootcause"
        }
      ],
      "1284": [
        {
          "id": "rootcause:Improper Input Validation",
          "keyphrase": "Improper Input Validation",
          "type": "rootcause"
        },
        {
          "id": "rootcause:Input Validation vulnerability",
          "keyphrase": "Input Validation vulnerability",
          "type": "rootcause"
        }
      ],
      "90": [
        {
          "id": "rootcause:Improper Input Validation",
          "keyphrase": "Improper Input Validation",
          "type": "rootcause"
        },
        {
          "id": "rootcause:Input Validation vulnerability",
          "keyphrase": "Input Validation vulnerability",
          "type": "rootcause"
        },
        {
          "id": "product:Apache Traffic Server",
          "keyphrase": "Apache Traffic Server",
          "type": "product"
        }
      ],
      "923": [
        {
          "id": "rootcause:Improper Input Validation",
          "keyphrase": "Improper Input Validation",
          "type": "rootcause"
        },
        {
          "id": "product:Apache Traffic Server",
          "keyphrase": "Apache Traffic Server",
          "type": "product"
        },
        {
          "id": "version:9.0.0 through 9.2.5",
          "keyphrase": "9.0.0 through 9.2.5",
          "type": "version"
        }
      ],
      "1333": [
        {
          "id": "rootcause:Input Validation vulnerability",
          "keyphrase": "Input Validation vulnerability",
          "type": "rootcause"
        }
      ],
      "614": [
        {
          "id": "product:Apache Traffic Server",
          "keyphrase": "Apache Traffic Server",
          "type": "product"
        }
      ],
      "201": [
        {
          "id": "product:Apache Traffic Server",
          "keyphrase": "Apache Traffic Server",
          "type": "product"
        },
        {
          "id": "version:8.0.0 through 8.1.11",
          "keyphrase": "8.0.0 through 8.1.11",
          "type": "version"
        },
        {
          "id": "version:9.0.0 through 9.2.5",
          "keyphrase": "9.0.0 through 9.2.5",
          "type": "version"
        }
      ],
      "863": [
        {
          "id": "version:8.0.0 through 8.1.11",
          "keyphrase": "8.0.0 through 8.1.11",
          "type": "version"
        },
        {
          "id": "version:9.0.0 through 9.2.5",
          "keyphrase": "9.0.0 through 9.2.5",
          "type": "version"
        }
      ],
      "22": [
        {
          "id": "version:8.0.0 through 8.1.11",
          "keyphrase": "8.0.0 through 8.1.11",
          "type": "version"
        }
      ],
      "93": [
        {
          "id": "version:8.0.0 through 8.1.11",
          "keyphrase": "8.0.0 through 8.1.11",
          "type": "version"
        }
      ],
      "532": [
        {
          "id": "version:9.0.0 through 9.2.5",
          "keyphrase": "9.0.0 through 9.2.5",
          "type": "version"
        }
      ]
    },
    "relevant_cwes": [
      {
        "metadata": {
          "doc_id": "20",
          "name": "Improper Input Validation",
          "source": "sparse",
          "original_content": "The product receives input or data, but it does\n        not validate or incorrectly validates that the input has the\n        properties that are required to process the data safely and\n        correctly.",
          "keyphrase_sources": [
            {
              "id": "rootcause:Improper Input Validation",
              "keyphrase": "Improper Input Validation",
              "type": "rootcause"
            },
            {
              "id": "rootcause:Input Validation vulnerability",
              "keyphrase": "Input Validation vulnerability",
              "type": "rootcause"
            },
            {
              "id": "product:Apache Traffic Server",
              "keyphrase": "Apache Traffic Server",
              "type": "product"
            },
            {
              "id": "version:8.0.0 through 8.1.11",
              "keyphrase": "8.0.0 through 8.1.11",
              "type": "version"
            },
            {
              "id": "version:9.0.0 through 9.2.5",
              "keyphrase": "9.0.0 through 9.2.5",
              "type": "version"
            }
          ]
        },
        "similarity": 322.4125875755275
      },
      {
        "metadata": {
          "doc_id": "116",
          "name": "Improper Encoding or Escaping of Output",
          "source": "sparse",
          "original_content": "The product prepares a structured message for communication with another component, but encoding or escaping of the data is either missing or done incorrectly. As a result, the intended structure of the message is not preserved.",
          "keyphrase_sources": [
            {
              "id": "rootcause:Improper Input Validation",
              "keyphrase": "Improper Input Validation",
              "type": "rootcause"
            },
            {
              "id": "rootcause:Input Validation vulnerability",
              "keyphrase": "Input Validation vulnerability",
              "type": "rootcause"
            }
          ]
        },
        "similarity": 309.02094240005226
      },
      {
        "metadata": {
          "doc_id": "1284",
          "name": "Improper Validation of Specified Quantity in Input",
          "source": "sparse",
          "original_content": "The product receives input that is expected to specify a quantity (such as size or length), but it does not validate or incorrectly validates that the quantity has the required properties.",
          "keyphrase_sources": [
            {
              "id": "rootcause:Improper Input Validation",
              "keyphrase": "Improper Input Validation",
              "type": "rootcause"
            },
            {
              "id": "rootcause:Input Validation vulnerability",
              "keyphrase": "Input Validation vulnerability",
              "type": "rootcause"
            }
          ]
        },
        "similarity": 304.95963331000803
      },
      {
        "metadata": {
          "doc_id": "90",
          "name": "Improper Neutralization of Special Elements used in an LDAP Query ('LDAP Injection')",
          "source": "sparse",
          "original_content": "The product constructs all or part of an LDAP query using externally-influenced input from an upstream component, but it does not neutralize or incorrectly neutralizes special elements that could modify the intended LDAP query when it is sent to a downstream component.",
          "keyphrase_sources": [
            {
              "id": "rootcause:Improper Input Validation",
              "keyphrase": "Improper Input Validation",
              "type": "rootcause"
            },
            {
              "id": "rootcause:Input Validation vulnerability",
              "keyphrase": "Input Validation vulnerability",
              "type": "rootcause"
            },
            {
              "id": "product:Apache Traffic Server",
              "keyphrase": "Apache Traffic Server",
              "type": "product"
            }
          ]
        },
        "similarity": 304.10854919489185
      },
      {
        "metadata": {
          "doc_id": "1333",
          "name": "Inefficient Regular Expression Complexity",
          "source": "sparse",
          "original_content": "The product uses a regular expression with an inefficient, possibly exponential worst-case computational complexity that consumes excessive CPU cycles.",
          "keyphrase_sources": [
            {
              "id": "rootcause:Input Validation vulnerability",
              "keyphrase": "Input Validation vulnerability",
              "type": "rootcause"
            }
          ]
        },
        "similarity": 303.5930486785998
      },
      {
        "metadata": {
          "doc_id": "923",
          "name": "Improper Restriction of Communication Channel to Intended Endpoints",
          "source": "sparse",
          "original_content": "The product establishes a communication channel to (or from) an endpoint for privileged or protected operations, but it does not properly ensure that it is communicating with the correct endpoint.",
          "keyphrase_sources": [
            {
              "id": "rootcause:Improper Input Validation",
              "keyphrase": "Improper Input Validation",
              "type": "rootcause"
            },
            {
              "id": "product:Apache Traffic Server",
              "keyphrase": "Apache Traffic Server",
              "type": "product"
            },
            {
              "id": "version:9.0.0 through 9.2.5",
              "keyphrase": "9.0.0 through 9.2.5",
              "type": "version"
            }
          ]
        },
        "similarity": 301.9385756366287
      },
      {
        "metadata": {
          "doc_id": "863",
          "name": "Incorrect Authorization",
          "source": "sparse",
          "original_content": "The product performs an authorization check when an actor attempts to access a resource or perform an action, but it does not correctly perform the check.",
          "keyphrase_sources": [
            {
              "id": "version:8.0.0 through 8.1.11",
              "keyphrase": "8.0.0 through 8.1.11",
              "type": "version"
            },
            {
              "id": "version:9.0.0 through 9.2.5",
              "keyphrase": "9.0.0 through 9.2.5",
              "type": "version"
            }
          ]
        },
        "similarity": 113.96660559687153
      },
      {
        "metadata": {
          "doc_id": "22",
          "name": "Improper Limitation of a Pathname to a Restricted Directory ('Path Traversal')",
          "source": "sparse",
          "original_content": "The product uses external input to construct a pathname that is intended to identify a file or directory that is located underneath a restricted parent directory, but the product does not properly neutralize special elements within the pathname that can cause the pathname to resolve to a location that is outside of the restricted directory.",
          "keyphrase_sources": [
            {
              "id": "version:8.0.0 through 8.1.11",
              "keyphrase": "8.0.0 through 8.1.11",
              "type": "version"
            }
          ]
        },
        "similarity": 111.32787484606185
      },
      {
        "metadata": {
          "doc_id": "93",
          "name": "Improper Neutralization of CRLF Sequences ('CRLF Injection')",
          "source": "sparse",
          "original_content": "The product uses CRLF (carriage return line feeds) as a special element, e.g. to separate lines or records, but it does not neutralize or incorrectly neutralizes CRLF sequences from inputs.",
          "keyphrase_sources": [
            {
              "id": "version:8.0.0 through 8.1.11",
              "keyphrase": "8.0.0 through 8.1.11",
              "type": "version"
            }
          ]
        },
        "similarity": 110.97118752537557
      },
      {
        "metadata": {
          "doc_id": "532",
          "name": "Insertion of Sensitive Information into Log File",
          "source": "sparse",
          "original_content": "The product writes sensitive information to a log file.",
          "keyphrase_sources": [
            {
              "id": "version:9.0.0 through 9.2.5",
              "keyphrase": "9.0.0 through 9.2.5",
              "type": "version"
            }
          ]
        },
        "similarity": 110.65547906935656
      },
      {
        "metadata": {
          "doc_id": "614",
          "name": "Sensitive Cookie in HTTPS Session Without 'Secure' Attribute",
          "source": "sparse",
          "original_content": "The Secure attribute for sensitive cookies in HTTPS sessions is not set, which could cause the user agent to send those cookies in plaintext over an HTTP session.",
          "keyphrase_sources": [
            {
              "id": "product:Apache Traffic Server",
              "keyphrase": "Apache Traffic Server",
              "type": "product"
            }
          ]
        },
        "similarity": 110.4241072105773
      },
      {
        "metadata": {
          "doc_id": "201",
          "name": "Insertion of Sensitive Information Into Sent Data",
          "source": "sparse",
          "original_content": "The code transmits data to another actor, but a portion of the data includes sensitive information that should not be accessible to that actor.",
          "keyphrase_sources": [
            {
              "id": "product:Apache Traffic Server",
              "keyphrase": "Apache Traffic Server",
              "type": "product"
            },
            {
              "id": "version:8.0.0 through 8.1.11",
              "keyphrase": "8.0.0 through 8.1.11",
              "type": "version"
            },
            {
              "id": "version:9.0.0 through 9.2.5",
              "keyphrase": "9.0.0 through 9.2.5",
              "type": "version"
            }
          ]
        },
        "similarity": 107.21284953399241
      }
    ],
    "enhanced_query": "# Vulnerability Description\n\n    **Improper Input Validation** vulnerability in Apache Traffic Server. This issue affects Apache Traffic Server from 8.0.0 through 8.1.11, from 9.0.0 through 9.2.5. Users are recommended to upgrade to version 9.2.6, which fixes the issue, or 10.0.2, which does not have the issue.\n\n    # Keyphrase-Specific CWE Analysis\n    This vulnerability contains multiple keyphrases that may map to different CWEs. \n    Please analyze each keyphrase separately and determine the most appropriate CWE(s) for each.\n\n    ## ROOTCAUSE: 'Improper Input Validation'\n\nRelevant CWEs for this ROOTCAUSE:\n\n### 1. CWE-20: Improper Input Validation (Score: 322.41)\n\nThe product receives input or data, but it does\n        not validate or incorrectly validates that the input has the\n        properties that are required to process the data safely and\n        correctly....\n\n### 2. CWE-116: Improper Encoding or Escaping of Output (Score: 309.02)\n\nThe product prepares a structured message for communication with another component, but encoding or escaping of the data is either missing or done incorrectly. As a result, the intended structure of the message is not preserved....\n\n### 3. CWE-1284: Improper Validation of Specified Quantity in Input (Score: 304.96)\n\nThe product receives input that is expected to specify a quantity (such as size or length), but it does not validate or incorrectly validates that the quantity has the required properties....\n\n### 4. CWE-90: Improper Neutralization of Special Elements used in an LDAP Query ('LDAP Injection') (Score: 304.11)\n\nThe product constructs all or part of an LDAP query using externally-influenced input from an upstream component, but it does not neutralize or incorrectly neutralizes special elements that could modify the intended LDAP query when it is sent to a downstream component....\n\n### 5. CWE-923: Improper Restriction of Communication Channel to Intended Endpoints (Score: 301.94)\n\nThe product establishes a communication channel to (or from) an endpoint for privileged or protected operations, but it does not properly ensure that it is communicating with the correct endpoint....\n\n## ROOTCAUSE: 'Input Validation vulnerability'\n\nRelevant CWEs for this ROOTCAUSE:\n\n### 1. CWE-20: Improper Input Validation (Score: 322.41)\n\nThe product receives input or data, but it does\n        not validate or incorrectly validates that the input has the\n        properties that are required to process the data safely and\n        correctly....\n\n### 2. CWE-116: Improper Encoding or Escaping of Output (Score: 309.02)\n\nThe product prepares a structured message for communication with another component, but encoding or escaping of the data is either missing or done incorrectly. As a result, the intended structure of the message is not preserved....\n\n### 3. CWE-1284: Improper Validation of Specified Quantity in Input (Score: 304.96)\n\nThe product receives input that is expected to specify a quantity (such as size or length), but it does not validate or incorrectly validates that the quantity has the required properties....\n\n### 4. CWE-90: Improper Neutralization of Special Elements used in an LDAP Query ('LDAP Injection') (Score: 304.11)\n\nThe product constructs all or part of an LDAP query using externally-influenced input from an upstream component, but it does not neutralize or incorrectly neutralizes special elements that could modify the intended LDAP query when it is sent to a downstream component....\n\n### 5. CWE-1333: Inefficient Regular Expression Complexity (Score: 303.59)\n\nThe product uses a regular expression with an inefficient, possibly exponential worst-case computational complexity that consumes excessive CPU cycles....\n\n## PRODUCT: 'Apache Traffic Server'\n\nRelevant CWEs for this PRODUCT:\n\n### 1. CWE-20: Improper Input Validation (Score: 322.41)\n\nThe product receives input or data, but it does\n        not validate or incorrectly validates that the input has the\n        properties that are required to process the data safely and\n        correctly....\n\n### 2. CWE-90: Improper Neutralization of Special Elements used in an LDAP Query ('LDAP Injection') (Score: 304.11)\n\nThe product constructs all or part of an LDAP query using externally-influenced input from an upstream component, but it does not neutralize or incorrectly neutralizes special elements that could modify the intended LDAP query when it is sent to a downstream component....\n\n### 3. CWE-923: Improper Restriction of Communication Channel to Intended Endpoints (Score: 301.94)\n\nThe product establishes a communication channel to (or from) an endpoint for privileged or protected operations, but it does not properly ensure that it is communicating with the correct endpoint....\n\n### 4. CWE-614: Sensitive Cookie in HTTPS Session Without 'Secure' Attribute (Score: 110.42)\n\nThe Secure attribute for sensitive cookies in HTTPS sessions is not set, which could cause the user agent to send those cookies in plaintext over an HTTP session....\n\n### 5. CWE-201: Insertion of Sensitive Information Into Sent Data (Score: 107.21)\n\nThe code transmits data to another actor, but a portion of the data includes sensitive information that should not be accessible to that actor....\n\n## VERSION: '8.0.0 through 8.1.11'\n\nRelevant CWEs for this VERSION:\n\n### 1. CWE-20: Improper Input Validation (Score: 322.41)\n\nThe product receives input or data, but it does\n        not validate or incorrectly validates that the input has the\n        properties that are required to process the data safely and\n        correctly....\n\n### 2. CWE-863: Incorrect Authorization (Score: 113.97)\n\nThe product performs an authorization check when an actor attempts to access a resource or perform an action, but it does not correctly perform the check....\n\n### 3. CWE-22: Improper Limitation of a Pathname to a Restricted Directory ('Path Traversal') (Score: 111.33)\n\nThe product uses external input to construct a pathname that is intended to identify a file or directory that is located underneath a restricted parent directory, but the product does not properly neutralize special elements within the pathname that can cause the pathname to resolve to a location th...\n\n### 4. CWE-93: Improper Neutralization of CRLF Sequences ('CRLF Injection') (Score: 110.97)\n\nThe product uses CRLF (carriage return line feeds) as a special element, e.g. to separate lines or records, but it does not neutralize or incorrectly neutralizes CRLF sequences from inputs....\n\n### 5. CWE-201: Insertion of Sensitive Information Into Sent Data (Score: 107.21)\n\nThe code transmits data to another actor, but a portion of the data includes sensitive information that should not be accessible to that actor....\n\n## VERSION: '9.0.0 through 9.2.5'\n\nRelevant CWEs for this VERSION:\n\n### 1. CWE-20: Improper Input Validation (Score: 322.41)\n\nThe product receives input or data, but it does\n        not validate or incorrectly validates that the input has the\n        properties that are required to process the data safely and\n        correctly....\n\n### 2. CWE-923: Improper Restriction of Communication Channel to Intended Endpoints (Score: 301.94)\n\nThe product establishes a communication channel to (or from) an endpoint for privileged or protected operations, but it does not properly ensure that it is communicating with the correct endpoint....\n\n### 3. CWE-863: Incorrect Authorization (Score: 113.97)\n\nThe product performs an authorization check when an actor attempts to access a resource or perform an action, but it does not correctly perform the check....\n\n### 4. CWE-532: Insertion of Sensitive Information into Log File (Score: 110.66)\n\nThe product writes sensitive information to a log file....\n\n### 5. CWE-201: Insertion of Sensitive Information Into Sent Data (Score: 107.21)\n\nThe code transmits data to another actor, but a portion of the data includes sensitive information that should not be accessible to that actor....\n\n\n    # Analysis Instructions\n    1. For each keyphrase, identify the most appropriate CWE(s) that represent the weakness.\n    2. Consider how the different keyphrases might relate to each other in the vulnerability chain.\n    3. Provide a final determination of primary CWE(s) and any secondary CWEs.\n    4. Format your response using the standard analysis template.\n\n    Please analyze how these different weaknesses interact and provide a comprehensive CWE classification.\n    "
  },
  "retrieval_time": 1.1396453380584717
}