{
  "vulnerability_info": "VulnerabilityInfo(cve_id='CVE-2025-32069', description='Improper **Input Validation vulnerability** in The Wikimedia Foundation Mediawiki - Wikibase Media Info Extension allows **Cross-Site Scripting** (XSS).This issue affects Mediawiki - Wikibase Media Info Extension from 1.39 through 1.43.', key_phrases={'rootcause': ['Input Validation vulnerability', 'Improper Input Validation'], 'weakness': 'Cross-Site Scripting', 'impact': '', 'vector': '', 'attacker': '', 'product': 'Wikimedia Foundation Mediawiki - Wikibase Media Info Extension', 'version': '1.39 through 1.43', 'component': ''}, reference_content='```\\n* Root cause of vulnerability: Wikitext stored XSS on filepages due to dangerous WBMI serialization.\\n* Weaknesses/vulnerabilities present: XSS vulnerability.\\n* Impact of exploitation:  An alert box appears.\\n* Attack vectors: Paste a specific code into a file page wikitext to trigger the vulnerability.\\n* Mitigation or fix:\\n  * The attributes should be named with data-mw.\\n  * The patch was deployed to fix the XSS vulnerability.\\n```', similar_info={'cwe_distribution': {}, 'cwe_consensus': '', 'similarity_stats': {'thresholds': [], 'total_samples_by_threshold': {}, 'top_cwes_by_threshold': {}}}, similarity_summary=SimilarityInsight(consensus_cwe='', top_cwes=[], confidence_levels={}, total_samples=0), analysis='', analysis_with_relationships='', criticism='', resolution='', relevant_cwes=[{'metadata': {'doc_id': '942', 'name': 'Permissive Cross-domain Policy with Untrusted Domains', 'source': 'sparse', 'original_content': 'The product uses a cross-domain policy file that includes domains that should not be trusted.', 'keyphrase_sources': [{'id': 'weakness:Cross-Site Scripting', 'keyphrase': 'Cross-Site Scripting', 'type': 'weakness'}]}, 'similarity': np.float64(180.10425558878086)}, {'metadata': {'doc_id': '79', 'name': \"Improper Neutralization of Input During Web Page Generation ('Cross-site Scripting')\", 'source': 'sparse', 'original_content': 'The product does not neutralize or incorrectly neutralizes user-controllable input before it is placed in output that is used as a web page that is served to other users.', 'keyphrase_sources': [{'id': 'rootcause:Input Validation vulnerability', 'keyphrase': 'Input Validation vulnerability', 'type': 'rootcause'}, {'id': 'rootcause:Improper Input Validation', 'keyphrase': 'Improper Input Validation', 'type': 'rootcause'}, {'id': 'weakness:Cross-Site Scripting', 'keyphrase': 'Cross-Site Scripting', 'type': 'weakness'}, {'id': 'product:Wikimedia Foundation Mediawiki - Wikibase Media Info Extension', 'keyphrase': 'Wikimedia Foundation Mediawiki - Wikibase Media Info Extension', 'type': 'product'}, {'id': 'version:1.39 through 1.43', 'keyphrase': '1.39 through 1.43', 'type': 'version'}]}, 'similarity': np.float64(175.52717156523659)}, {'metadata': {'doc_id': '116', 'name': 'Improper Encoding or Escaping of Output', 'source': 'sparse', 'original_content': 'The product prepares a structured message for communication with another component, but encoding or escaping of the data is either missing or done incorrectly. As a result, the intended structure of the message is not preserved.', 'keyphrase_sources': [{'id': 'rootcause:Input Validation vulnerability', 'keyphrase': 'Input Validation vulnerability', 'type': 'rootcause'}, {'id': 'rootcause:Improper Input Validation', 'keyphrase': 'Improper Input Validation', 'type': 'rootcause'}, {'id': 'weakness:Cross-Site Scripting', 'keyphrase': 'Cross-Site Scripting', 'type': 'weakness'}, {'id': 'version:1.39 through 1.43', 'keyphrase': '1.39 through 1.43', 'type': 'version'}]}, 'similarity': np.float64(158.0337882785209)}, {'metadata': {'doc_id': '80', 'name': 'Improper Neutralization of Script-Related HTML Tags in a Web Page (Basic XSS)', 'source': 'sparse', 'original_content': 'The product receives input from an upstream component, but it does not neutralize or incorrectly neutralizes special characters such as \"<\", \">\", and \"&\" that could be interpreted as web-scripting elements when they are sent to a downstream component that processes web pages.', 'keyphrase_sources': [{'id': 'rootcause:Input Validation vulnerability', 'keyphrase': 'Input Validation vulnerability', 'type': 'rootcause'}, {'id': 'rootcause:Improper Input Validation', 'keyphrase': 'Improper Input Validation', 'type': 'rootcause'}, {'id': 'weakness:Cross-Site Scripting', 'keyphrase': 'Cross-Site Scripting', 'type': 'weakness'}]}, 'similarity': np.float64(150.8336665666067)}, {'metadata': {'doc_id': '352', 'name': 'Cross-Site Request Forgery (CSRF)', 'source': 'sparse', 'original_content': 'The web application does not, or can not, sufficiently verify whether a well-formed, valid, consistent request was intentionally provided by the user who submitted the request.', 'keyphrase_sources': [{'id': 'rootcause:Input Validation vulnerability', 'keyphrase': 'Input Validation vulnerability', 'type': 'rootcause'}, {'id': 'weakness:Cross-Site Scripting', 'keyphrase': 'Cross-Site Scripting', 'type': 'weakness'}, {'id': 'version:1.39 through 1.43', 'keyphrase': '1.39 through 1.43', 'type': 'version'}]}, 'similarity': np.float64(144.35505847936065)}, {'metadata': {'doc_id': '138', 'name': 'Improper Neutralization of Special Elements', 'source': 'sparse', 'original_content': 'The product receives input from an upstream component, but it does not neutralize or incorrectly neutralizes special elements that could be interpreted as control elements or syntactic markers when they are sent to a downstream component.', 'keyphrase_sources': [{'id': 'rootcause:Input Validation vulnerability', 'keyphrase': 'Input Validation vulnerability', 'type': 'rootcause'}, {'id': 'rootcause:Improper Input Validation', 'keyphrase': 'Improper Input Validation', 'type': 'rootcause'}]}, 'similarity': np.float64(144.27158251317644)}, {'metadata': {'doc_id': '20', 'name': 'Improper Input Validation', 'source': 'sparse', 'original_content': 'The product receives input or data, but it does\\n        not validate or incorrectly validates that the input has the\\n        properties that are required to process the data safely and\\n        correctly.', 'keyphrase_sources': [{'id': 'rootcause:Improper Input Validation', 'keyphrase': 'Improper Input Validation', 'type': 'rootcause'}]}, 'similarity': np.float64(143.2357054728878)}, {'metadata': {'doc_id': '201', 'name': 'Insertion of Sensitive Information Into Sent Data', 'source': 'sparse', 'original_content': 'The code transmits data to another actor, but a portion of the data includes sensitive information that should not be accessible to that actor.', 'keyphrase_sources': [{'id': 'product:Wikimedia Foundation Mediawiki - Wikibase Media Info Extension', 'keyphrase': 'Wikimedia Foundation Mediawiki - Wikibase Media Info Extension', 'type': 'product'}, {'id': 'version:1.39 through 1.43', 'keyphrase': '1.39 through 1.43', 'type': 'version'}]}, 'similarity': np.float64(60.76715593160238)}, {'metadata': {'doc_id': '288', 'name': 'Authentication Bypass Using an Alternate Path or Channel', 'source': 'sparse', 'original_content': 'The product requires authentication, but the product has an alternate path or channel that does not require authentication.', 'keyphrase_sources': [{'id': 'version:1.39 through 1.43', 'keyphrase': '1.39 through 1.43', 'type': 'version'}]}, 'similarity': np.float64(51.505020416040054)}, {'metadata': {'doc_id': '434', 'name': 'Unrestricted Upload of File with Dangerous Type', 'source': 'sparse', 'original_content': 'The product allows the upload or transfer of dangerous file types that are automatically processed within its environment.', 'keyphrase_sources': [{'id': 'product:Wikimedia Foundation Mediawiki - Wikibase Media Info Extension', 'keyphrase': 'Wikimedia Foundation Mediawiki - Wikibase Media Info Extension', 'type': 'product'}]}, 'similarity': np.float64(50.400929753906524)}, {'metadata': {'doc_id': '267', 'name': 'Privilege Defined With Unsafe Actions', 'source': 'sparse', 'original_content': 'A particular privilege, role, capability, or right can be used to perform unsafe actions that were not intended, even when it is assigned to the correct entity.', 'keyphrase_sources': [{'id': 'product:Wikimedia Foundation Mediawiki - Wikibase Media Info Extension', 'keyphrase': 'Wikimedia Foundation Mediawiki - Wikibase Media Info Extension', 'type': 'product'}]}, 'similarity': np.float64(49.19198769358779)}, {'metadata': {'doc_id': '416', 'name': 'Use After Free', 'source': 'sparse', 'original_content': 'The product reuses or references memory after it has been freed. At some point afterward, the memory may be allocated again and saved in another pointer, while the original pointer references a location somewhere within the new allocation. Any operations using the original pointer are no longer valid because the memory \"belongs\" to the code that operates on the new pointer.', 'keyphrase_sources': [{'id': 'product:Wikimedia Foundation Mediawiki - Wikibase Media Info Extension', 'keyphrase': 'Wikimedia Foundation Mediawiki - Wikibase Media Info Extension', 'type': 'product'}]}, 'similarity': np.float64(47.88823498477221)}], identified_cwes={'analyzer': [], 'critic_additional': []})",
  "retrieval_results": {
    "has_multiple_keyphrases": true,
    "keyphrase_cwe_sets": {
      "rootcause:Input Validation vulnerability": {
        "keyphrase": "Input Validation vulnerability",
        "type": "rootcause",
        "cwes": [
          {
            "metadata": {
              "doc_id": "79",
              "name": "Improper Neutralization of Input During Web Page Generation ('Cross-site Scripting')",
              "source": "sparse",
              "original_content": "The product does not neutralize or incorrectly neutralizes user-controllable input before it is placed in output that is used as a web page that is served to other users.",
              "keyphrase_sources": [
                {
                  "id": "rootcause:Input Validation vulnerability",
                  "keyphrase": "Input Validation vulnerability",
                  "type": "rootcause"
                },
                {
                  "id": "rootcause:Improper Input Validation",
                  "keyphrase": "Improper Input Validation",
                  "type": "rootcause"
                },
                {
                  "id": "weakness:Cross-Site Scripting",
                  "keyphrase": "Cross-Site Scripting",
                  "type": "weakness"
                },
                {
                  "id": "product:Wikimedia Foundation Mediawiki - Wikibase Media Info Extension",
                  "keyphrase": "Wikimedia Foundation Mediawiki - Wikibase Media Info Extension",
                  "type": "product"
                },
                {
                  "id": "version:1.39 through 1.43",
                  "keyphrase": "1.39 through 1.43",
                  "type": "version"
                }
              ]
            },
            "similarity": 175.52717156523659
          },
          {
            "metadata": {
              "doc_id": "116",
              "name": "Improper Encoding or Escaping of Output",
              "source": "sparse",
              "original_content": "The product prepares a structured message for communication with another component, but encoding or escaping of the data is either missing or done incorrectly. As a result, the intended structure of the message is not preserved.",
              "keyphrase_sources": [
                {
                  "id": "rootcause:Input Validation vulnerability",
                  "keyphrase": "Input Validation vulnerability",
                  "type": "rootcause"
                },
                {
                  "id": "rootcause:Improper Input Validation",
                  "keyphrase": "Improper Input Validation",
                  "type": "rootcause"
                },
                {
                  "id": "weakness:Cross-Site Scripting",
                  "keyphrase": "Cross-Site Scripting",
                  "type": "weakness"
                },
                {
                  "id": "version:1.39 through 1.43",
                  "keyphrase": "1.39 through 1.43",
                  "type": "version"
                }
              ]
            },
            "similarity": 158.0337882785209
          },
          {
            "metadata": {
              "doc_id": "80",
              "name": "Improper Neutralization of Script-Related HTML Tags in a Web Page (Basic XSS)",
              "source": "sparse",
              "original_content": "The product receives input from an upstream component, but it does not neutralize or incorrectly neutralizes special characters such as \"<\", \">\", and \"&\" that could be interpreted as web-scripting elements when they are sent to a downstream component that processes web pages.",
              "keyphrase_sources": [
                {
                  "id": "rootcause:Input Validation vulnerability",
                  "keyphrase": "Input Validation vulnerability",
                  "type": "rootcause"
                },
                {
                  "id": "rootcause:Improper Input Validation",
                  "keyphrase": "Improper Input Validation",
                  "type": "rootcause"
                },
                {
                  "id": "weakness:Cross-Site Scripting",
                  "keyphrase": "Cross-Site Scripting",
                  "type": "weakness"
                }
              ]
            },
            "similarity": 150.8336665666067
          },
          {
            "metadata": {
              "doc_id": "352",
              "name": "Cross-Site Request Forgery (CSRF)",
              "source": "sparse",
              "original_content": "The web application does not, or can not, sufficiently verify whether a well-formed, valid, consistent request was intentionally provided by the user who submitted the request.",
              "keyphrase_sources": [
                {
                  "id": "rootcause:Input Validation vulnerability",
                  "keyphrase": "Input Validation vulnerability",
                  "type": "rootcause"
                },
                {
                  "id": "weakness:Cross-Site Scripting",
                  "keyphrase": "Cross-Site Scripting",
                  "type": "weakness"
                },
                {
                  "id": "version:1.39 through 1.43",
                  "keyphrase": "1.39 through 1.43",
                  "type": "version"
                }
              ]
            },
            "similarity": 144.35505847936065
          },
          {
            "metadata": {
              "doc_id": "138",
              "name": "Improper Neutralization of Special Elements",
              "source": "sparse",
              "original_content": "The product receives input from an upstream component, but it does not neutralize or incorrectly neutralizes special elements that could be interpreted as control elements or syntactic markers when they are sent to a downstream component.",
              "keyphrase_sources": [
                {
                  "id": "rootcause:Input Validation vulnerability",
                  "keyphrase": "Input Validation vulnerability",
                  "type": "rootcause"
                },
                {
                  "id": "rootcause:Improper Input Validation",
                  "keyphrase": "Improper Input Validation",
                  "type": "rootcause"
                }
              ]
            },
            "similarity": 144.27158251317644
          }
        ]
      },
      "rootcause:Improper Input Validation": {
        "keyphrase": "Improper Input Validation",
        "type": "rootcause",
        "cwes": [
          {
            "metadata": {
              "doc_id": "79",
              "name": "Improper Neutralization of Input During Web Page Generation ('Cross-site Scripting')",
              "source": "sparse",
              "original_content": "The product does not neutralize or incorrectly neutralizes user-controllable input before it is placed in output that is used as a web page that is served to other users."
            },
            "similarity": 175.96450216304132
          },
          {
            "metadata": {
              "doc_id": "116",
              "name": "Improper Encoding or Escaping of Output",
              "source": "sparse",
              "original_content": "The product prepares a structured message for communication with another component, but encoding or escaping of the data is either missing or done incorrectly. As a result, the intended structure of the message is not preserved."
            },
            "similarity": 160.48012521024822
          },
          {
            "metadata": {
              "doc_id": "80",
              "name": "Improper Neutralization of Script-Related HTML Tags in a Web Page (Basic XSS)",
              "source": "sparse",
              "original_content": "The product receives input from an upstream component, but it does not neutralize or incorrectly neutralizes special characters such as \"<\", \">\", and \"&\" that could be interpreted as web-scripting elements when they are sent to a downstream component that processes web pages."
            },
            "similarity": 154.79002454871517
          },
          {
            "metadata": {
              "doc_id": "138",
              "name": "Improper Neutralization of Special Elements",
              "source": "sparse",
              "original_content": "The product receives input from an upstream component, but it does not neutralize or incorrectly neutralizes special elements that could be interpreted as control elements or syntactic markers when they are sent to a downstream component."
            },
            "similarity": 148.7287054731839
          },
          {
            "metadata": {
              "doc_id": "20",
              "name": "Improper Input Validation",
              "source": "sparse",
              "original_content": "The product receives input or data, but it does\n        not validate or incorrectly validates that the input has the\n        properties that are required to process the data safely and\n        correctly.",
              "keyphrase_sources": [
                {
                  "id": "rootcause:Improper Input Validation",
                  "keyphrase": "Improper Input Validation",
                  "type": "rootcause"
                }
              ]
            },
            "similarity": 143.2357054728878
          }
        ]
      },
      "weakness:Cross-Site Scripting": {
        "keyphrase": "Cross-Site Scripting",
        "type": "weakness",
        "cwes": [
          {
            "metadata": {
              "doc_id": "79",
              "name": "Improper Neutralization of Input During Web Page Generation ('Cross-site Scripting')",
              "source": "sparse",
              "original_content": "The product does not neutralize or incorrectly neutralizes user-controllable input before it is placed in output that is used as a web page that is served to other users."
            },
            "similarity": 240.7507275725402
          },
          {
            "metadata": {
              "doc_id": "352",
              "name": "Cross-Site Request Forgery (CSRF)",
              "source": "sparse",
              "original_content": "The web application does not, or can not, sufficiently verify whether a well-formed, valid, consistent request was intentionally provided by the user who submitted the request."
            },
            "similarity": 213.45825069999117
          },
          {
            "metadata": {
              "doc_id": "80",
              "name": "Improper Neutralization of Script-Related HTML Tags in a Web Page (Basic XSS)",
              "source": "sparse",
              "original_content": "The product receives input from an upstream component, but it does not neutralize or incorrectly neutralizes special characters such as \"<\", \">\", and \"&\" that could be interpreted as web-scripting elements when they are sent to a downstream component that processes web pages."
            },
            "similarity": 206.59866929921512
          },
          {
            "metadata": {
              "doc_id": "116",
              "name": "Improper Encoding or Escaping of Output",
              "source": "sparse",
              "original_content": "The product prepares a structured message for communication with another component, but encoding or escaping of the data is either missing or done incorrectly. As a result, the intended structure of the message is not preserved."
            },
            "similarity": 192.1874448879201
          },
          {
            "metadata": {
              "doc_id": "942",
              "name": "Permissive Cross-domain Policy with Untrusted Domains",
              "source": "sparse",
              "original_content": "The product uses a cross-domain policy file that includes domains that should not be trusted.",
              "keyphrase_sources": [
                {
                  "id": "weakness:Cross-Site Scripting",
                  "keyphrase": "Cross-Site Scripting",
                  "type": "weakness"
                }
              ]
            },
            "similarity": 180.10425558878086
          }
        ]
      },
      "product:Wikimedia Foundation Mediawiki - Wikibase Media Info Extension": {
        "keyphrase": "Wikimedia Foundation Mediawiki - Wikibase Media Info Extension",
        "type": "product",
        "cwes": [
          {
            "metadata": {
              "doc_id": "79",
              "name": "Improper Neutralization of Input During Web Page Generation ('Cross-site Scripting')",
              "source": "sparse",
              "original_content": "The product does not neutralize or incorrectly neutralizes user-controllable input before it is placed in output that is used as a web page that is served to other users."
            },
            "similarity": 62.16339521930361
          },
          {
            "metadata": {
              "doc_id": "201",
              "name": "Insertion of Sensitive Information Into Sent Data",
              "source": "sparse",
              "original_content": "The code transmits data to another actor, but a portion of the data includes sensitive information that should not be accessible to that actor.",
              "keyphrase_sources": [
                {
                  "id": "product:Wikimedia Foundation Mediawiki - Wikibase Media Info Extension",
                  "keyphrase": "Wikimedia Foundation Mediawiki - Wikibase Media Info Extension",
                  "type": "product"
                },
                {
                  "id": "version:1.39 through 1.43",
                  "keyphrase": "1.39 through 1.43",
                  "type": "version"
                }
              ]
            },
            "similarity": 60.76715593160238
          },
          {
            "metadata": {
              "doc_id": "434",
              "name": "Unrestricted Upload of File with Dangerous Type",
              "source": "sparse",
              "original_content": "The product allows the upload or transfer of dangerous file types that are automatically processed within its environment.",
              "keyphrase_sources": [
                {
                  "id": "product:Wikimedia Foundation Mediawiki - Wikibase Media Info Extension",
                  "keyphrase": "Wikimedia Foundation Mediawiki - Wikibase Media Info Extension",
                  "type": "product"
                }
              ]
            },
            "similarity": 50.400929753906524
          },
          {
            "metadata": {
              "doc_id": "267",
              "name": "Privilege Defined With Unsafe Actions",
              "source": "sparse",
              "original_content": "A particular privilege, role, capability, or right can be used to perform unsafe actions that were not intended, even when it is assigned to the correct entity.",
              "keyphrase_sources": [
                {
                  "id": "product:Wikimedia Foundation Mediawiki - Wikibase Media Info Extension",
                  "keyphrase": "Wikimedia Foundation Mediawiki - Wikibase Media Info Extension",
                  "type": "product"
                }
              ]
            },
            "similarity": 49.19198769358779
          },
          {
            "metadata": {
              "doc_id": "416",
              "name": "Use After Free",
              "source": "sparse",
              "original_content": "The product reuses or references memory after it has been freed. At some point afterward, the memory may be allocated again and saved in another pointer, while the original pointer references a location somewhere within the new allocation. Any operations using the original pointer are no longer valid because the memory \"belongs\" to the code that operates on the new pointer.",
              "keyphrase_sources": [
                {
                  "id": "product:Wikimedia Foundation Mediawiki - Wikibase Media Info Extension",
                  "keyphrase": "Wikimedia Foundation Mediawiki - Wikibase Media Info Extension",
                  "type": "product"
                }
              ]
            },
            "similarity": 47.88823498477221
          }
        ]
      },
      "version:1.39 through 1.43": {
        "keyphrase": "1.39 through 1.43",
        "type": "version",
        "cwes": [
          {
            "metadata": {
              "doc_id": "79",
              "name": "Improper Neutralization of Input During Web Page Generation ('Cross-site Scripting')",
              "source": "sparse",
              "original_content": "The product does not neutralize or incorrectly neutralizes user-controllable input before it is placed in output that is used as a web page that is served to other users."
            },
            "similarity": 61.24292914018669
          },
          {
            "metadata": {
              "doc_id": "201",
              "name": "Insertion of Sensitive Information Into Sent Data",
              "source": "sparse",
              "original_content": "The code transmits data to another actor, but a portion of the data includes sensitive information that should not be accessible to that actor."
            },
            "similarity": 51.71827295222368
          },
          {
            "metadata": {
              "doc_id": "288",
              "name": "Authentication Bypass Using an Alternate Path or Channel",
              "source": "sparse",
              "original_content": "The product requires authentication, but the product has an alternate path or channel that does not require authentication.",
              "keyphrase_sources": [
                {
                  "id": "version:1.39 through 1.43",
                  "keyphrase": "1.39 through 1.43",
                  "type": "version"
                }
              ]
            },
            "similarity": 51.505020416040054
          },
          {
            "metadata": {
              "doc_id": "352",
              "name": "Cross-Site Request Forgery (CSRF)",
              "source": "sparse",
              "original_content": "The web application does not, or can not, sufficiently verify whether a well-formed, valid, consistent request was intentionally provided by the user who submitted the request."
            },
            "similarity": 49.18290404629119
          },
          {
            "metadata": {
              "doc_id": "116",
              "name": "Improper Encoding or Escaping of Output",
              "source": "sparse",
              "original_content": "The product prepares a structured message for communication with another component, but encoding or escaping of the data is either missing or done incorrectly. As a result, the intended structure of the message is not preserved."
            },
            "similarity": 47.75699960911499
          }
        ]
      }
    },
    "keyphrase_mapping": {
      "79": [
        {
          "id": "rootcause:Input Validation vulnerability",
          "keyphrase": "Input Validation vulnerability",
          "type": "rootcause"
        },
        {
          "id": "rootcause:Improper Input Validation",
          "keyphrase": "Improper Input Validation",
          "type": "rootcause"
        },
        {
          "id": "weakness:Cross-Site Scripting",
          "keyphrase": "Cross-Site Scripting",
          "type": "weakness"
        },
        {
          "id": "product:Wikimedia Foundation Mediawiki - Wikibase Media Info Extension",
          "keyphrase": "Wikimedia Foundation Mediawiki - Wikibase Media Info Extension",
          "type": "product"
        },
        {
          "id": "version:1.39 through 1.43",
          "keyphrase": "1.39 through 1.43",
          "type": "version"
        }
      ],
      "116": [
        {
          "id": "rootcause:Input Validation vulnerability",
          "keyphrase": "Input Validation vulnerability",
          "type": "rootcause"
        },
        {
          "id": "rootcause:Improper Input Validation",
          "keyphrase": "Improper Input Validation",
          "type": "rootcause"
        },
        {
          "id": "weakness:Cross-Site Scripting",
          "keyphrase": "Cross-Site Scripting",
          "type": "weakness"
        },
        {
          "id": "version:1.39 through 1.43",
          "keyphrase": "1.39 through 1.43",
          "type": "version"
        }
      ],
      "80": [
        {
          "id": "rootcause:Input Validation vulnerability",
          "keyphrase": "Input Validation vulnerability",
          "type": "rootcause"
        },
        {
          "id": "rootcause:Improper Input Validation",
          "keyphrase": "Improper Input Validation",
          "type": "rootcause"
        },
        {
          "id": "weakness:Cross-Site Scripting",
          "keyphrase": "Cross-Site Scripting",
          "type": "weakness"
        }
      ],
      "352": [
        {
          "id": "rootcause:Input Validation vulnerability",
          "keyphrase": "Input Validation vulnerability",
          "type": "rootcause"
        },
        {
          "id": "weakness:Cross-Site Scripting",
          "keyphrase": "Cross-Site Scripting",
          "type": "weakness"
        },
        {
          "id": "version:1.39 through 1.43",
          "keyphrase": "1.39 through 1.43",
          "type": "version"
        }
      ],
      "138": [
        {
          "id": "rootcause:Input Validation vulnerability",
          "keyphrase": "Input Validation vulnerability",
          "type": "rootcause"
        },
        {
          "id": "rootcause:Improper Input Validation",
          "keyphrase": "Improper Input Validation",
          "type": "rootcause"
        }
      ],
      "20": [
        {
          "id": "rootcause:Improper Input Validation",
          "keyphrase": "Improper Input Validation",
          "type": "rootcause"
        }
      ],
      "942": [
        {
          "id": "weakness:Cross-Site Scripting",
          "keyphrase": "Cross-Site Scripting",
          "type": "weakness"
        }
      ],
      "201": [
        {
          "id": "product:Wikimedia Foundation Mediawiki - Wikibase Media Info Extension",
          "keyphrase": "Wikimedia Foundation Mediawiki - Wikibase Media Info Extension",
          "type": "product"
        },
        {
          "id": "version:1.39 through 1.43",
          "keyphrase": "1.39 through 1.43",
          "type": "version"
        }
      ],
      "434": [
        {
          "id": "product:Wikimedia Foundation Mediawiki - Wikibase Media Info Extension",
          "keyphrase": "Wikimedia Foundation Mediawiki - Wikibase Media Info Extension",
          "type": "product"
        }
      ],
      "267": [
        {
          "id": "product:Wikimedia Foundation Mediawiki - Wikibase Media Info Extension",
          "keyphrase": "Wikimedia Foundation Mediawiki - Wikibase Media Info Extension",
          "type": "product"
        }
      ],
      "416": [
        {
          "id": "product:Wikimedia Foundation Mediawiki - Wikibase Media Info Extension",
          "keyphrase": "Wikimedia Foundation Mediawiki - Wikibase Media Info Extension",
          "type": "product"
        }
      ],
      "288": [
        {
          "id": "version:1.39 through 1.43",
          "keyphrase": "1.39 through 1.43",
          "type": "version"
        }
      ]
    },
    "relevant_cwes": [
      {
        "metadata": {
          "doc_id": "942",
          "name": "Permissive Cross-domain Policy with Untrusted Domains",
          "source": "sparse",
          "original_content": "The product uses a cross-domain policy file that includes domains that should not be trusted.",
          "keyphrase_sources": [
            {
              "id": "weakness:Cross-Site Scripting",
              "keyphrase": "Cross-Site Scripting",
              "type": "weakness"
            }
          ]
        },
        "similarity": 180.10425558878086
      },
      {
        "metadata": {
          "doc_id": "79",
          "name": "Improper Neutralization of Input During Web Page Generation ('Cross-site Scripting')",
          "source": "sparse",
          "original_content": "The product does not neutralize or incorrectly neutralizes user-controllable input before it is placed in output that is used as a web page that is served to other users.",
          "keyphrase_sources": [
            {
              "id": "rootcause:Input Validation vulnerability",
              "keyphrase": "Input Validation vulnerability",
              "type": "rootcause"
            },
            {
              "id": "rootcause:Improper Input Validation",
              "keyphrase": "Improper Input Validation",
              "type": "rootcause"
            },
            {
              "id": "weakness:Cross-Site Scripting",
              "keyphrase": "Cross-Site Scripting",
              "type": "weakness"
            },
            {
              "id": "product:Wikimedia Foundation Mediawiki - Wikibase Media Info Extension",
              "keyphrase": "Wikimedia Foundation Mediawiki - Wikibase Media Info Extension",
              "type": "product"
            },
            {
              "id": "version:1.39 through 1.43",
              "keyphrase": "1.39 through 1.43",
              "type": "version"
            }
          ]
        },
        "similarity": 175.52717156523659
      },
      {
        "metadata": {
          "doc_id": "116",
          "name": "Improper Encoding or Escaping of Output",
          "source": "sparse",
          "original_content": "The product prepares a structured message for communication with another component, but encoding or escaping of the data is either missing or done incorrectly. As a result, the intended structure of the message is not preserved.",
          "keyphrase_sources": [
            {
              "id": "rootcause:Input Validation vulnerability",
              "keyphrase": "Input Validation vulnerability",
              "type": "rootcause"
            },
            {
              "id": "rootcause:Improper Input Validation",
              "keyphrase": "Improper Input Validation",
              "type": "rootcause"
            },
            {
              "id": "weakness:Cross-Site Scripting",
              "keyphrase": "Cross-Site Scripting",
              "type": "weakness"
            },
            {
              "id": "version:1.39 through 1.43",
              "keyphrase": "1.39 through 1.43",
              "type": "version"
            }
          ]
        },
        "similarity": 158.0337882785209
      },
      {
        "metadata": {
          "doc_id": "80",
          "name": "Improper Neutralization of Script-Related HTML Tags in a Web Page (Basic XSS)",
          "source": "sparse",
          "original_content": "The product receives input from an upstream component, but it does not neutralize or incorrectly neutralizes special characters such as \"<\", \">\", and \"&\" that could be interpreted as web-scripting elements when they are sent to a downstream component that processes web pages.",
          "keyphrase_sources": [
            {
              "id": "rootcause:Input Validation vulnerability",
              "keyphrase": "Input Validation vulnerability",
              "type": "rootcause"
            },
            {
              "id": "rootcause:Improper Input Validation",
              "keyphrase": "Improper Input Validation",
              "type": "rootcause"
            },
            {
              "id": "weakness:Cross-Site Scripting",
              "keyphrase": "Cross-Site Scripting",
              "type": "weakness"
            }
          ]
        },
        "similarity": 150.8336665666067
      },
      {
        "metadata": {
          "doc_id": "352",
          "name": "Cross-Site Request Forgery (CSRF)",
          "source": "sparse",
          "original_content": "The web application does not, or can not, sufficiently verify whether a well-formed, valid, consistent request was intentionally provided by the user who submitted the request.",
          "keyphrase_sources": [
            {
              "id": "rootcause:Input Validation vulnerability",
              "keyphrase": "Input Validation vulnerability",
              "type": "rootcause"
            },
            {
              "id": "weakness:Cross-Site Scripting",
              "keyphrase": "Cross-Site Scripting",
              "type": "weakness"
            },
            {
              "id": "version:1.39 through 1.43",
              "keyphrase": "1.39 through 1.43",
              "type": "version"
            }
          ]
        },
        "similarity": 144.35505847936065
      },
      {
        "metadata": {
          "doc_id": "138",
          "name": "Improper Neutralization of Special Elements",
          "source": "sparse",
          "original_content": "The product receives input from an upstream component, but it does not neutralize or incorrectly neutralizes special elements that could be interpreted as control elements or syntactic markers when they are sent to a downstream component.",
          "keyphrase_sources": [
            {
              "id": "rootcause:Input Validation vulnerability",
              "keyphrase": "Input Validation vulnerability",
              "type": "rootcause"
            },
            {
              "id": "rootcause:Improper Input Validation",
              "keyphrase": "Improper Input Validation",
              "type": "rootcause"
            }
          ]
        },
        "similarity": 144.27158251317644
      },
      {
        "metadata": {
          "doc_id": "20",
          "name": "Improper Input Validation",
          "source": "sparse",
          "original_content": "The product receives input or data, but it does\n        not validate or incorrectly validates that the input has the\n        properties that are required to process the data safely and\n        correctly.",
          "keyphrase_sources": [
            {
              "id": "rootcause:Improper Input Validation",
              "keyphrase": "Improper Input Validation",
              "type": "rootcause"
            }
          ]
        },
        "similarity": 143.2357054728878
      },
      {
        "metadata": {
          "doc_id": "201",
          "name": "Insertion of Sensitive Information Into Sent Data",
          "source": "sparse",
          "original_content": "The code transmits data to another actor, but a portion of the data includes sensitive information that should not be accessible to that actor.",
          "keyphrase_sources": [
            {
              "id": "product:Wikimedia Foundation Mediawiki - Wikibase Media Info Extension",
              "keyphrase": "Wikimedia Foundation Mediawiki - Wikibase Media Info Extension",
              "type": "product"
            },
            {
              "id": "version:1.39 through 1.43",
              "keyphrase": "1.39 through 1.43",
              "type": "version"
            }
          ]
        },
        "similarity": 60.76715593160238
      },
      {
        "metadata": {
          "doc_id": "288",
          "name": "Authentication Bypass Using an Alternate Path or Channel",
          "source": "sparse",
          "original_content": "The product requires authentication, but the product has an alternate path or channel that does not require authentication.",
          "keyphrase_sources": [
            {
              "id": "version:1.39 through 1.43",
              "keyphrase": "1.39 through 1.43",
              "type": "version"
            }
          ]
        },
        "similarity": 51.505020416040054
      },
      {
        "metadata": {
          "doc_id": "434",
          "name": "Unrestricted Upload of File with Dangerous Type",
          "source": "sparse",
          "original_content": "The product allows the upload or transfer of dangerous file types that are automatically processed within its environment.",
          "keyphrase_sources": [
            {
              "id": "product:Wikimedia Foundation Mediawiki - Wikibase Media Info Extension",
              "keyphrase": "Wikimedia Foundation Mediawiki - Wikibase Media Info Extension",
              "type": "product"
            }
          ]
        },
        "similarity": 50.400929753906524
      },
      {
        "metadata": {
          "doc_id": "267",
          "name": "Privilege Defined With Unsafe Actions",
          "source": "sparse",
          "original_content": "A particular privilege, role, capability, or right can be used to perform unsafe actions that were not intended, even when it is assigned to the correct entity.",
          "keyphrase_sources": [
            {
              "id": "product:Wikimedia Foundation Mediawiki - Wikibase Media Info Extension",
              "keyphrase": "Wikimedia Foundation Mediawiki - Wikibase Media Info Extension",
              "type": "product"
            }
          ]
        },
        "similarity": 49.19198769358779
      },
      {
        "metadata": {
          "doc_id": "416",
          "name": "Use After Free",
          "source": "sparse",
          "original_content": "The product reuses or references memory after it has been freed. At some point afterward, the memory may be allocated again and saved in another pointer, while the original pointer references a location somewhere within the new allocation. Any operations using the original pointer are no longer valid because the memory \"belongs\" to the code that operates on the new pointer.",
          "keyphrase_sources": [
            {
              "id": "product:Wikimedia Foundation Mediawiki - Wikibase Media Info Extension",
              "keyphrase": "Wikimedia Foundation Mediawiki - Wikibase Media Info Extension",
              "type": "product"
            }
          ]
        },
        "similarity": 47.88823498477221
      }
    ],
    "enhanced_query": "# Vulnerability Description\n\n    Improper **Input Validation vulnerability** in The Wikimedia Foundation Mediawiki - Wikibase Media Info Extension allows **Cross-Site Scripting** (XSS).This issue affects Mediawiki - Wikibase Media Info Extension from 1.39 through 1.43.\n\n    # Keyphrase-Specific CWE Analysis\n    This vulnerability contains multiple keyphrases that may map to different CWEs. \n    Please analyze each keyphrase separately and determine the most appropriate CWE(s) for each.\n\n    ## WEAKNESS: 'Cross-Site Scripting'\n\nRelevant CWEs for this WEAKNESS:\n\n### 1. CWE-942: Permissive Cross-domain Policy with Untrusted Domains (Score: 180.10)\n\nThe product uses a cross-domain policy file that includes domains that should not be trusted....\n\n### 2. CWE-79: Improper Neutralization of Input During Web Page Generation ('Cross-site Scripting') (Score: 175.53)\n\nThe product does not neutralize or incorrectly neutralizes user-controllable input before it is placed in output that is used as a web page that is served to other users....\n\n### 3. CWE-116: Improper Encoding or Escaping of Output (Score: 158.03)\n\nThe product prepares a structured message for communication with another component, but encoding or escaping of the data is either missing or done incorrectly. As a result, the intended structure of the message is not preserved....\n\n### 4. CWE-80: Improper Neutralization of Script-Related HTML Tags in a Web Page (Basic XSS) (Score: 150.83)\n\nThe product receives input from an upstream component, but it does not neutralize or incorrectly neutralizes special characters such as \"<\", \">\", and \"&\" that could be interpreted as web-scripting elements when they are sent to a downstream component that processes web pages....\n\n### 5. CWE-352: Cross-Site Request Forgery (CSRF) (Score: 144.36)\n\nThe web application does not, or can not, sufficiently verify whether a well-formed, valid, consistent request was intentionally provided by the user who submitted the request....\n\n## ROOTCAUSE: 'Input Validation vulnerability'\n\nRelevant CWEs for this ROOTCAUSE:\n\n### 1. CWE-79: Improper Neutralization of Input During Web Page Generation ('Cross-site Scripting') (Score: 175.53)\n\nThe product does not neutralize or incorrectly neutralizes user-controllable input before it is placed in output that is used as a web page that is served to other users....\n\n### 2. CWE-116: Improper Encoding or Escaping of Output (Score: 158.03)\n\nThe product prepares a structured message for communication with another component, but encoding or escaping of the data is either missing or done incorrectly. As a result, the intended structure of the message is not preserved....\n\n### 3. CWE-80: Improper Neutralization of Script-Related HTML Tags in a Web Page (Basic XSS) (Score: 150.83)\n\nThe product receives input from an upstream component, but it does not neutralize or incorrectly neutralizes special characters such as \"<\", \">\", and \"&\" that could be interpreted as web-scripting elements when they are sent to a downstream component that processes web pages....\n\n### 4. CWE-352: Cross-Site Request Forgery (CSRF) (Score: 144.36)\n\nThe web application does not, or can not, sufficiently verify whether a well-formed, valid, consistent request was intentionally provided by the user who submitted the request....\n\n### 5. CWE-138: Improper Neutralization of Special Elements (Score: 144.27)\n\nThe product receives input from an upstream component, but it does not neutralize or incorrectly neutralizes special elements that could be interpreted as control elements or syntactic markers when they are sent to a downstream component....\n\n## ROOTCAUSE: 'Improper Input Validation'\n\nRelevant CWEs for this ROOTCAUSE:\n\n### 1. CWE-79: Improper Neutralization of Input During Web Page Generation ('Cross-site Scripting') (Score: 175.53)\n\nThe product does not neutralize or incorrectly neutralizes user-controllable input before it is placed in output that is used as a web page that is served to other users....\n\n### 2. CWE-116: Improper Encoding or Escaping of Output (Score: 158.03)\n\nThe product prepares a structured message for communication with another component, but encoding or escaping of the data is either missing or done incorrectly. As a result, the intended structure of the message is not preserved....\n\n### 3. CWE-80: Improper Neutralization of Script-Related HTML Tags in a Web Page (Basic XSS) (Score: 150.83)\n\nThe product receives input from an upstream component, but it does not neutralize or incorrectly neutralizes special characters such as \"<\", \">\", and \"&\" that could be interpreted as web-scripting elements when they are sent to a downstream component that processes web pages....\n\n### 4. CWE-138: Improper Neutralization of Special Elements (Score: 144.27)\n\nThe product receives input from an upstream component, but it does not neutralize or incorrectly neutralizes special elements that could be interpreted as control elements or syntactic markers when they are sent to a downstream component....\n\n### 5. CWE-20: Improper Input Validation (Score: 143.24)\n\nThe product receives input or data, but it does\n        not validate or incorrectly validates that the input has the\n        properties that are required to process the data safely and\n        correctly....\n\n## PRODUCT: 'Wikimedia Foundation Mediawiki - Wikibase Media Info Extension'\n\nRelevant CWEs for this PRODUCT:\n\n### 1. CWE-79: Improper Neutralization of Input During Web Page Generation ('Cross-site Scripting') (Score: 175.53)\n\nThe product does not neutralize or incorrectly neutralizes user-controllable input before it is placed in output that is used as a web page that is served to other users....\n\n### 2. CWE-201: Insertion of Sensitive Information Into Sent Data (Score: 60.77)\n\nThe code transmits data to another actor, but a portion of the data includes sensitive information that should not be accessible to that actor....\n\n### 3. CWE-434: Unrestricted Upload of File with Dangerous Type (Score: 50.40)\n\nThe product allows the upload or transfer of dangerous file types that are automatically processed within its environment....\n\n### 4. CWE-267: Privilege Defined With Unsafe Actions (Score: 49.19)\n\nA particular privilege, role, capability, or right can be used to perform unsafe actions that were not intended, even when it is assigned to the correct entity....\n\n### 5. CWE-416: Use After Free (Score: 47.89)\n\nThe product reuses or references memory after it has been freed. At some point afterward, the memory may be allocated again and saved in another pointer, while the original pointer references a location somewhere within the new allocation. Any operations using the original pointer are no longer vali...\n\n## VERSION: '1.39 through 1.43'\n\nRelevant CWEs for this VERSION:\n\n### 1. CWE-79: Improper Neutralization of Input During Web Page Generation ('Cross-site Scripting') (Score: 175.53)\n\nThe product does not neutralize or incorrectly neutralizes user-controllable input before it is placed in output that is used as a web page that is served to other users....\n\n### 2. CWE-116: Improper Encoding or Escaping of Output (Score: 158.03)\n\nThe product prepares a structured message for communication with another component, but encoding or escaping of the data is either missing or done incorrectly. As a result, the intended structure of the message is not preserved....\n\n### 3. CWE-352: Cross-Site Request Forgery (CSRF) (Score: 144.36)\n\nThe web application does not, or can not, sufficiently verify whether a well-formed, valid, consistent request was intentionally provided by the user who submitted the request....\n\n### 4. CWE-201: Insertion of Sensitive Information Into Sent Data (Score: 60.77)\n\nThe code transmits data to another actor, but a portion of the data includes sensitive information that should not be accessible to that actor....\n\n### 5. CWE-288: Authentication Bypass Using an Alternate Path or Channel (Score: 51.51)\n\nThe product requires authentication, but the product has an alternate path or channel that does not require authentication....\n\n\n    # Analysis Instructions\n    1. For each keyphrase, identify the most appropriate CWE(s) that represent the weakness.\n    2. Consider how the different keyphrases might relate to each other in the vulnerability chain.\n    3. Provide a final determination of primary CWE(s) and any secondary CWEs.\n    4. Format your response using the standard analysis template.\n\n    Please analyze how these different weaknesses interact and provide a comprehensive CWE classification.\n    "
  },
  "retrieval_time": 1.0633273124694824
}