{
  "cve_id": "CVE-2024-22170",
  "description": "****Improper Restriction of Operations within the Bounds of a Memory Buffer**** vulnerability in Western Digital My Cloud ddns-start on Linux allows **Overflow** Buffers.This issue affects My Cloud before 5.29.102.",
  "key_phrases": {
    "rootcause": "Improper Restriction of Operations within the Bounds of a Memory Buffer",
    "weakness": [
      "Improper Restriction of Operations within the Bounds of a Memory Buffer",
      "Overflow"
    ],
    "impact": "overflow buffers",
    "vector": "",
    "attacker": "",
    "product": "Western Digital My Cloud",
    "version": "before 5.29.102",
    "component": "ddns-start"
  },
  "reference_content": "- **Root cause of vulnerability:** An unchecked buffer in the Dynamic DNS client within My Cloud firmware.\n- **Weaknesses/vulnerabilities present:** Buffer overflow vulnerability.\n- **Impact of exploitation:** An attacker could execute arbitrary code on the affected device.\n- **Attack vectors:** A Man-in-the-Middle (MitM) attack could be used to intercept a Dynamic DNS update request and respond with a crafted payload designed to overflow the buffer.\n- **Required attacker capabilities/position:** An attacker needs to be positioned to perform a MitM attack, allowing them to intercept and modify network traffic between the My Cloud device and the Dynamic DNS server.\n\nThis content provides more detail than the official CVE description, by specifying the attack vector (MitM), and the vulnerable component (Dynamic DNS client).",
  "similar_info": {
    "cwe_distribution": {},
    "cwe_consensus": "",
    "similarity_stats": {
      "thresholds": [],
      "total_samples_by_threshold": {},
      "top_cwes_by_threshold": {}
    }
  },
  "similarity_summary": {
    "consensus_cwe": "",
    "top_cwes": [],
    "confidence_levels": {},
    "total_samples": 0
  },
  "analysis": "# Summary\n\n| CWE ID  | CWE Name  | Confidence | CWE Abstraction Level | CWE Vulnerability Mapping Label | CWE-Vulnerability Mapping Notes |\n|---|---|---|---|---|---|\n| CWE-119 | Improper Restriction of Operations within the Bounds of a Memory Buffer | 1.0 | Class | Allowed | Primary CWE |\n| CWE-787 | Out-of-bounds Write | 0.7 | Base | Allowed | Secondary Candidate |\n\n## Evidence and Confidence\n\n*   **Confidence Score:** 0.9\n*   **Evidence Strength:** HIGH\n\n## Relationship Analysis\n\nThe primary relationship that influenced the decision was the hierarchical relationship, specifically the ChildOf relationship. While the description points to a buffer overflow, the root cause is the **improper restriction of operations** within the bounds of the memory buffer. CWE-119 is a Class-level CWE, and CWE-787 is a Base-level CWE that is often a consequence of CWE-119.\n\n```mermaid\ngraph TD\n    cwe119[\"CWE-119: Improper Restriction of Operations within the Bounds of a Memory Buffer\"]\n    cwe787[\"CWE-787: Out-of-bounds Write\"]\n    \n    cwe787 -->|CHILDOF| cwe119\n    \n    classDef primary fill:#f96,stroke:#333,stroke-width:2px\n    classDef secondary fill:#69f,stroke:#333\n    class cwe119 primary\n    class cwe787 secondary\n```\n\n## Vulnerability Chain\n\nThe vulnerability chain starts with the **improper restriction of operations** within a memory buffer (CWE-119). This can lead to an out-of-bounds write (CWE-787), which results in a buffer overflow.\n\n## Summary of Analysis\n\nThe initial analysis strongly suggests CWE-119 as the primary weakness, supported by the vulnerability description and the keyphrase analysis. The description explicitly mentions \"**Improper Restriction of Operations within the Bounds of a Memory Buffer**\" as a root cause. The term \"**Overflow** Buffers\" indicates the impact of the vulnerability, which is often associated with buffer overflows caused by **improper** bounds checking or **improper** memory management. The vulnerability description provided sufficient evidence, and the retriever results confirmed the relevance of CWE-119. Although CWE-787 is strongly considered as a secondary weakness, it is not the primary cause.\n\nThe selection of CWE-119 is at the optimal level of specificity because it directly reflects the **improper restriction** that leads to the overflow. More specific CWEs like CWE-120 (Buffer Copy without Checking Size of Input) were considered but deemed less appropriate because the provided information does not specifically mention a buffer copy operation.\n\nRelevant CWE Information:\n\n*   **CWE-119 (Improper Restriction of Operations within the Bounds of a Memory Buffer)**: The product performs operations on a memory buffer, but it reads from or writes to a memory location outside the buffer's intended boundary.\n*   **CWE-787 (Out-of-bounds Write)**: The product writes data past the end, or before the beginning, of the intended buffer.\n\nThe following CWEs were considered but not used as the primary CWE:\n\n*   **CWE-190 (Integer Overflow or Wraparound)**: Although listed in the retriever results, this CWE is not directly related to the **improper restriction of operations** causing the buffer overflow in this specific case. It is related to arithmetic errors, which are not explicitly mentioned in the description.\n*   **CWE-125 (Out-of-bounds Read)**: This CWE describes reading data outside the intended buffer, while the description emphasizes writing (**Overflow**), making CWE-787 a more suitable secondary candidate.\n*   **CWE-197 (Numeric Truncation Error)**: Similar to CWE-190, this CWE is not directly relevant to the buffer overflow scenario described.\n*   **CWE-122 (Heap-based Buffer Overflow)**: While this could be a possible impact, the root cause is still the **improper restriction of operations**, and the location of the buffer (heap) is not specified.\n*   **CWE-770 (Allocation of Resources Without Limits or Throttling)**: This CWE is related to resource management, which is not the primary issue described in the vulnerability.\n*   **CWE-124 (Buffer Underwrite ('Buffer Underflow'))**: The description specifies an **overflow**, not an underflow.\n*   **CWE-22 (Improper Limitation of a Pathname to a Restricted Directory ('Path Traversal'))**: This CWE is related to path traversal vulnerabilities, which are not relevant to the described buffer overflow.\n*   **CWE-522 (Insufficiently Protected Credentials)**: This CWE is related to credential management, which is not relevant to the described buffer overflow.\n*   **CWE-116 (Improper Encoding or Escaping of Output)**: This CWE is related to output encoding, which is not relevant to the described buffer overflow.\n*   **CWE-194 (Unexpected Sign Extension)**: This CWE is related to sign extension issues, which are not directly relevant to the described buffer overflow.\n*   **CWE-131 (Incorrect Calculation of Buffer Size)**: While related to buffer overflows, the description focuses on the **improper restriction of operations**, making CWE-119 a more direct match to the root cause.\n*   **CWE-703 (Improper Check or Handling of Exceptional Conditions)**: Too high-level and doesn't specify the nature of the exceptional condition.\n*   **CWE-1391 (Use of Weak Credentials)**: Not relevant as it deals with weak credentials.\n*   **CWE-668 (Exposure of Resource to Wrong Sphere)**: Too general and doesn't specify the root cause.\n*   **CWE-41 (Improper Resolution of Path Equivalence)**: Not relevant as it deals with path equivalence issues.\n*   **CWE-697 (Incorrect Comparison)**: Too high-level.\n*   **CWE-754 (Improper Check for Unusual or Exceptional Conditions)**: Too high-level and doesn't specify the nature of the exceptional condition.\n*   **CWE-345 (Insufficient Verification of Data Authenticity)**: Not relevant as it deals with data authenticity.\n*   **CWE-212 (Improper Removal of Sensitive Information Before Storage or Transfer)**: Not relevant as it deals with sensitive information exposure.\n*   **CWE-274 (Improper Handling of Insufficient Privileges)**: Not relevant as it deals with privilege handling.\n*   **CWE-128 (Wrap-around Error)**: Arithmetic error, not directly related.\n*   **CWE-1339 (Insufficient Precision or Accuracy of a Real Number)**: Deals with real number precision, not relevant here.",
  "analysis_with_relationships": "# Summary\n\n| CWE ID  | CWE Name  | Confidence | CWE Abstraction Level | CWE Vulnerability Mapping Label | CWE-Vulnerability Mapping Notes |\n|---|---|---|---|---|---|\n| CWE-119 | Improper Restriction of Operations within the Bounds of a Memory Buffer | 1.0 | Class | Allowed | Primary CWE |\n| CWE-787 | Out-of-bounds Write | 0.7 | Base | Allowed | Secondary Candidate |\n\n## Evidence and Confidence\n\n*   **Confidence Score:** 0.9\n*   **Evidence Strength:** HIGH\n\n## Relationship Analysis\n\nThe primary relationship that influenced the decision was the hierarchical relationship, specifically the ChildOf relationship. While the description points to a buffer overflow, the root cause is the **improper restriction of operations** within the bounds of the memory buffer. CWE-119 is a Class-level CWE, and CWE-787 is a Base-level CWE that is often a consequence of CWE-119.\n\n```mermaid\ngraph TD\n    cwe119[\"CWE-119: Improper Restriction of Operations within the Bounds of a Memory Buffer\"]\n    cwe787[\"CWE-787: Out-of-bounds Write\"]\n    \n    cwe787 -->|CHILDOF| cwe119\n    \n    classDef primary fill:#f96,stroke:#333,stroke-width:2px\n    classDef secondary fill:#69f,stroke:#333\n    class cwe119 primary\n    class cwe787 secondary\n```\n\n## Vulnerability Chain\n\nThe vulnerability chain starts with the **improper restriction of operations** within a memory buffer (CWE-119). This can lead to an out-of-bounds write (CWE-787), which results in a buffer overflow.\n\n## Summary of Analysis\n\nThe initial analysis strongly suggests CWE-119 as the primary weakness, supported by the vulnerability description and the keyphrase analysis. The description explicitly mentions \"**Improper Restriction of Operations within the Bounds of a Memory Buffer**\" as a root cause. The term \"**Overflow** Buffers\" indicates the impact of the vulnerability, which is often associated with buffer overflows caused by **improper** bounds checking or **improper** memory management. The vulnerability description provided sufficient evidence, and the retriever results confirmed the relevance of CWE-119. Although CWE-787 is strongly considered as a secondary weakness, it is not the primary cause.\n\nThe selection of CWE-119 is at the optimal level of specificity because it directly reflects the **improper restriction** that leads to the overflow. More specific CWEs like CWE-120 (Buffer Copy without Checking Size of Input) were considered but deemed less appropriate because the provided information does not specifically mention a buffer copy operation.\n\nRelevant CWE Information:\n\n*   **CWE-119 (Improper Restriction of Operations within the Bounds of a Memory Buffer)**: The product performs operations on a memory buffer, but it reads from or writes to a memory location outside the buffer's intended boundary.\n*   **CWE-787 (Out-of-bounds Write)**: The product writes data past the end, or before the beginning, of the intended buffer.\n\nThe following CWEs were considered but not used as the primary CWE:\n\n*   **CWE-190 (Integer Overflow or Wraparound)**: Although listed in the retriever results, this CWE is not directly related to the **improper restriction of operations** causing the buffer overflow in this specific case. It is related to arithmetic errors, which are not explicitly mentioned in the description.\n*   **CWE-125 (Out-of-bounds Read)**: This CWE describes reading data outside the intended buffer, while the description emphasizes writing (**Overflow**), making CWE-787 a more suitable secondary candidate.\n*   **CWE-197 (Numeric Truncation Error)**: Similar to CWE-190, this CWE is not directly relevant to the buffer overflow scenario described.\n*   **CWE-122 (Heap-based Buffer Overflow)**: While this could be a possible impact, the root cause is still the **improper restriction of operations**, and the location of the buffer (heap) is not specified.\n*   **CWE-770 (Allocation of Resources Without Limits or Throttling)**: This CWE is related to resource management, which is not the primary issue described in the vulnerability.\n*   **CWE-124 (Buffer Underwrite ('Buffer Underflow'))**: The description specifies an **overflow**, not an underflow.\n*   **CWE-22 (Improper Limitation of a Pathname to a Restricted Directory ('Path Traversal'))**: This CWE is related to path traversal vulnerabilities, which are not relevant to the described buffer overflow.\n*   **CWE-522 (Insufficiently Protected Credentials)**: This CWE is related to credential management, which is not relevant to the described buffer overflow.\n*   **CWE-116 (Improper Encoding or Escaping of Output)**: This CWE is related to output encoding, which is not relevant to the described buffer overflow.\n*   **CWE-194 (Unexpected Sign Extension)**: This CWE is related to sign extension issues, which are not directly relevant to the described buffer overflow.\n*   **CWE-131 (Incorrect Calculation of Buffer Size)**: While related to buffer overflows, the description focuses on the **improper restriction of operations**, making CWE-119 a more direct match to the root cause.\n*   **CWE-703 (Improper Check or Handling of Exceptional Conditions)**: Too high-level and doesn't specify the nature of the exceptional condition.\n*   **CWE-1391 (Use of Weak Credentials)**: Not relevant as it deals with weak credentials.\n*   **CWE-668 (Exposure of Resource to Wrong Sphere)**: Too general and doesn't specify the root cause.\n*   **CWE-41 (Improper Resolution of Path Equivalence)**: Not relevant as it deals with path equivalence issues.\n*   **CWE-697 (Incorrect Comparison)**: Too high-level.\n*   **CWE-754 (Improper Check for Unusual or Exceptional Conditions)**: Too high-level and doesn't specify the nature of the exceptional condition.\n*   **CWE-345 (Insufficient Verification of Data Authenticity)**: Not relevant as it deals with data authenticity.\n*   **CWE-212 (Improper Removal of Sensitive Information Before Storage or Transfer)**: Not relevant as it deals with sensitive information exposure.\n*   **CWE-274 (Improper Handling of Insufficient Privileges)**: Not relevant as it deals with privilege handling.\n*   **CWE-128 (Wrap-around Error)**: Arithmetic error, not directly related.\n*   **CWE-1339 (Insufficient Precision or Accuracy of a Real Number)**: Deals with real number precision, not relevant here.\n\n\n## CWE Relationship Analysis\n\nCurrent CWEs represent these abstraction levels: .\n\n\n### Vulnerability Chain Analysis\n\n**Chain starting from CWE-274:**\n- 274 (Improper Handling of Insufficient Privileges) - ROOT\n\n\n**Chain starting from CWE-345:**\n- 345 (Insufficient Verification of Data Authenticity) - ROOT\n\n\n\n### CWE Relationship Diagram\n\n```mermaid\ngraph TD\n    classDef primary fill:#f96,stroke:#333,stroke-width:2px\n    classDef secondary fill:#69f,stroke:#333\n    classDef tertiary fill:#9e9,stroke:#333\n```",
  "criticism": "",
  "resolution": "",
  "relevant_cwes": [
    {
      "metadata": {
        "doc_id": "119",
        "name": "Improper Restriction of Operations within the Bounds of a Memory Buffer",
        "source": "sparse",
        "original_content": "The product performs operations on a memory buffer, but it reads from or writes to a memory location outside the buffer's intended boundary. This may result in read or write operations on unexpected memory locations that could be linked to other variables, data structures, or internal program data.",
        "keyphrase_sources": [
          {
            "id": "rootcause:Improper Restriction of Operations within the Bounds of a Memory Buffer",
            "keyphrase": "Improper Restriction of Operations within the Bounds of a Memory Buffer",
            "type": "rootcause"
          },
          {
            "id": "weakness:Improper Restriction of Operations within the Bounds of a Memory Buffer",
            "keyphrase": "Improper Restriction of Operations within the Bounds of a Memory Buffer",
            "type": "weakness"
          },
          {
            "id": "weakness:Overflow",
            "keyphrase": "Overflow",
            "type": "weakness"
          },
          {
            "id": "impact:overflow buffers",
            "keyphrase": "overflow buffers",
            "type": "impact"
          },
          {
            "id": "product:Western Digital My Cloud",
            "keyphrase": "Western Digital My Cloud",
            "type": "product"
          },
          {
            "id": "version:before 5.29.102",
            "keyphrase": "before 5.29.102",
            "type": "version"
          },
          {
            "id": "component:ddns-start",
            "keyphrase": "ddns-start",
            "type": "component"
          }
        ]
      },
      "similarity": 431.31628647190416
    },
    {
      "metadata": {
        "doc_id": "190",
        "name": "Integer Overflow or Wraparound",
        "source": "sparse",
        "original_content": "The product performs a calculation that can\n         produce an integer overflow or wraparound when the logic\n         assumes that the resulting value will always be larger than\n         the original value. This occurs when an integer value is\n         incremented to a value that is too large to store in the\n         associated representation. When this occurs, the value may\n         become a very small or negative number.",
        "keyphrase_sources": [
          {
            "id": "rootcause:Improper Restriction of Operations within the Bounds of a Memory Buffer",
            "keyphrase": "Improper Restriction of Operations within the Bounds of a Memory Buffer",
            "type": "rootcause"
          },
          {
            "id": "weakness:Improper Restriction of Operations within the Bounds of a Memory Buffer",
            "keyphrase": "Improper Restriction of Operations within the Bounds of a Memory Buffer",
            "type": "weakness"
          },
          {
            "id": "weakness:Overflow",
            "keyphrase": "Overflow",
            "type": "weakness"
          },
          {
            "id": "impact:overflow buffers",
            "keyphrase": "overflow buffers",
            "type": "impact"
          },
          {
            "id": "product:Western Digital My Cloud",
            "keyphrase": "Western Digital My Cloud",
            "type": "product"
          },
          {
            "id": "version:before 5.29.102",
            "keyphrase": "before 5.29.102",
            "type": "version"
          },
          {
            "id": "component:ddns-start",
            "keyphrase": "ddns-start",
            "type": "component"
          }
        ]
      },
      "similarity": 361.2630430656409
    },
    {
      "metadata": {
        "doc_id": "125",
        "name": "Out-of-bounds Read",
        "source": "sparse",
        "original_content": "The product reads data past the end, or before the beginning, of the intended buffer.",
        "keyphrase_sources": [
          {
            "id": "rootcause:Improper Restriction of Operations within the Bounds of a Memory Buffer",
            "keyphrase": "Improper Restriction of Operations within the Bounds of a Memory Buffer",
            "type": "rootcause"
          },
          {
            "id": "weakness:Improper Restriction of Operations within the Bounds of a Memory Buffer",
            "keyphrase": "Improper Restriction of Operations within the Bounds of a Memory Buffer",
            "type": "weakness"
          },
          {
            "id": "weakness:Overflow",
            "keyphrase": "Overflow",
            "type": "weakness"
          },
          {
            "id": "impact:overflow buffers",
            "keyphrase": "overflow buffers",
            "type": "impact"
          },
          {
            "id": "component:ddns-start",
            "keyphrase": "ddns-start",
            "type": "component"
          }
        ]
      },
      "similarity": 347.5631280923407
    },
    {
      "metadata": {
        "doc_id": "197",
        "name": "Numeric Truncation Error",
        "source": "sparse",
        "original_content": "Truncation errors occur when a primitive is cast to a primitive of a smaller size and data is lost in the conversion.",
        "keyphrase_sources": [
          {
            "id": "rootcause:Improper Restriction of Operations within the Bounds of a Memory Buffer",
            "keyphrase": "Improper Restriction of Operations within the Bounds of a Memory Buffer",
            "type": "rootcause"
          },
          {
            "id": "weakness:Improper Restriction of Operations within the Bounds of a Memory Buffer",
            "keyphrase": "Improper Restriction of Operations within the Bounds of a Memory Buffer",
            "type": "weakness"
          }
        ]
      },
      "similarity": 327.1345755544401
    },
    {
      "metadata": {
        "doc_id": "787",
        "name": "Out-of-bounds Write",
        "source": "sparse",
        "original_content": "The product writes data past the end, or before the beginning, of the intended buffer.",
        "keyphrase_sources": [
          {
            "id": "rootcause:Improper Restriction of Operations within the Bounds of a Memory Buffer",
            "keyphrase": "Improper Restriction of Operations within the Bounds of a Memory Buffer",
            "type": "rootcause"
          },
          {
            "id": "weakness:Improper Restriction of Operations within the Bounds of a Memory Buffer",
            "keyphrase": "Improper Restriction of Operations within the Bounds of a Memory Buffer",
            "type": "weakness"
          },
          {
            "id": "version:before 5.29.102",
            "keyphrase": "before 5.29.102",
            "type": "version"
          }
        ]
      },
      "similarity": 324.0712157862537
    },
    {
      "metadata": {
        "doc_id": "122",
        "name": "Heap-based Buffer Overflow",
        "source": "sparse",
        "original_content": "A heap overflow condition is a buffer overflow, where the buffer that can be overwritten is allocated in the heap portion of memory, generally meaning that the buffer was allocated using a routine such as malloc().",
        "keyphrase_sources": [
          {
            "id": "weakness:Overflow",
            "keyphrase": "Overflow",
            "type": "weakness"
          },
          {
            "id": "impact:overflow buffers",
            "keyphrase": "overflow buffers",
            "type": "impact"
          }
        ]
      },
      "similarity": 174.42200090433494
    },
    {
      "metadata": {
        "doc_id": "682",
        "name": "Incorrect Calculation",
        "source": "sparse",
        "original_content": "The product performs a calculation that generates incorrect or unintended results that are later used in security-critical decisions or resource management.",
        "keyphrase_sources": [
          {
            "id": "weakness:Overflow",
            "keyphrase": "Overflow",
            "type": "weakness"
          },
          {
            "id": "version:before 5.29.102",
            "keyphrase": "before 5.29.102",
            "type": "version"
          }
        ]
      },
      "similarity": 169.4089546220892
    },
    {
      "metadata": {
        "doc_id": "22",
        "name": "Improper Limitation of a Pathname to a Restricted Directory ('Path Traversal')",
        "source": "sparse",
        "original_content": "The product uses external input to construct a pathname that is intended to identify a file or directory that is located underneath a restricted parent directory, but the product does not properly neutralize special elements within the pathname that can cause the pathname to resolve to a location that is outside of the restricted directory.",
        "keyphrase_sources": [
          {
            "id": "product:Western Digital My Cloud",
            "keyphrase": "Western Digital My Cloud",
            "type": "product"
          },
          {
            "id": "component:ddns-start",
            "keyphrase": "ddns-start",
            "type": "component"
          }
        ]
      },
      "similarity": 73.95213091489596
    },
    {
      "metadata": {
        "doc_id": "522",
        "name": "Insufficiently Protected Credentials",
        "source": "sparse",
        "original_content": "The product transmits or stores authentication credentials, but it uses an insecure method that is susceptible to unauthorized interception and/or retrieval.",
        "keyphrase_sources": [
          {
            "id": "product:Western Digital My Cloud",
            "keyphrase": "Western Digital My Cloud",
            "type": "product"
          }
        ]
      },
      "similarity": 68.88415563842186
    },
    {
      "metadata": {
        "doc_id": "770",
        "name": "Allocation of Resources Without Limits or Throttling",
        "source": "sparse",
        "original_content": "The product allocates a reusable resource or group of resources on behalf of an actor without imposing any restrictions on the size or number of resources that can be allocated, in violation of the intended security policy for that actor.",
        "keyphrase_sources": [
          {
            "id": "impact:overflow buffers",
            "keyphrase": "overflow buffers",
            "type": "impact"
          }
        ]
      },
      "similarity": 64.85943026712664
    },
    {
      "metadata": {
        "doc_id": "124",
        "name": "Buffer Underwrite ('Buffer Underflow')",
        "source": "sparse",
        "original_content": "The product writes to a buffer using an index or pointer that references a memory location prior to the beginning of the buffer.",
        "keyphrase_sources": [
          {
            "id": "version:before 5.29.102",
            "keyphrase": "before 5.29.102",
            "type": "version"
          }
        ]
      },
      "similarity": 62.58982926778942
    },
    {
      "metadata": {
        "doc_id": "116",
        "name": "Improper Encoding or Escaping of Output",
        "source": "sparse",
        "original_content": "The product prepares a structured message for communication with another component, but encoding or escaping of the data is either missing or done incorrectly. As a result, the intended structure of the message is not preserved.",
        "keyphrase_sources": [
          {
            "id": "product:Western Digital My Cloud",
            "keyphrase": "Western Digital My Cloud",
            "type": "product"
          }
        ]
      },
      "similarity": 59.50572772223904
    },
    {
      "metadata": {
        "doc_id": "194",
        "name": "Unexpected Sign Extension",
        "source": "sparse",
        "original_content": "The product performs an operation on a number that causes it to be sign extended when it is transformed into a larger data type. When the original number is negative, this can produce unexpected values that lead to resultant weaknesses.",
        "keyphrase_sources": [
          {
            "id": "component:ddns-start",
            "keyphrase": "ddns-start",
            "type": "component"
          }
        ]
      },
      "similarity": 55.06289255844437
    }
  ],
  "identified_cwes": {
    "analyzer": [
      "CWE-274",
      "CWE-345",
      "CWE-770",
      "CWE-125",
      "CWE-131",
      "CWE-787",
      "CWE-194",
      "CWE-1339",
      "CWE-197",
      "CWE-120",
      "CWE-697",
      "CWE-41",
      "CWE-128",
      "CWE-122",
      "CWE-668",
      "CWE-1391",
      "CWE-522",
      "CWE-703",
      "CWE-212",
      "CWE-116",
      "CWE-22",
      "CWE-190",
      "CWE-124",
      "CWE-119",
      "CWE-754"
    ],
    "critic_additional": []
  },
  "keyphrase_cwe_mapping": {
    "119": [
      {
        "id": "rootcause:Improper Restriction of Operations within the Bounds of a Memory Buffer",
        "keyphrase": "Improper Restriction of Operations within the Bounds of a Memory Buffer",
        "type": "rootcause"
      },
      {
        "id": "weakness:Improper Restriction of Operations within the Bounds of a Memory Buffer",
        "keyphrase": "Improper Restriction of Operations within the Bounds of a Memory Buffer",
        "type": "weakness"
      },
      {
        "id": "weakness:Overflow",
        "keyphrase": "Overflow",
        "type": "weakness"
      },
      {
        "id": "impact:overflow buffers",
        "keyphrase": "overflow buffers",
        "type": "impact"
      },
      {
        "id": "product:Western Digital My Cloud",
        "keyphrase": "Western Digital My Cloud",
        "type": "product"
      },
      {
        "id": "version:before 5.29.102",
        "keyphrase": "before 5.29.102",
        "type": "version"
      },
      {
        "id": "component:ddns-start",
        "keyphrase": "ddns-start",
        "type": "component"
      }
    ],
    "190": [
      {
        "id": "rootcause:Improper Restriction of Operations within the Bounds of a Memory Buffer",
        "keyphrase": "Improper Restriction of Operations within the Bounds of a Memory Buffer",
        "type": "rootcause"
      },
      {
        "id": "weakness:Improper Restriction of Operations within the Bounds of a Memory Buffer",
        "keyphrase": "Improper Restriction of Operations within the Bounds of a Memory Buffer",
        "type": "weakness"
      },
      {
        "id": "weakness:Overflow",
        "keyphrase": "Overflow",
        "type": "weakness"
      },
      {
        "id": "impact:overflow buffers",
        "keyphrase": "overflow buffers",
        "type": "impact"
      },
      {
        "id": "product:Western Digital My Cloud",
        "keyphrase": "Western Digital My Cloud",
        "type": "product"
      },
      {
        "id": "version:before 5.29.102",
        "keyphrase": "before 5.29.102",
        "type": "version"
      },
      {
        "id": "component:ddns-start",
        "keyphrase": "ddns-start",
        "type": "component"
      }
    ],
    "125": [
      {
        "id": "rootcause:Improper Restriction of Operations within the Bounds of a Memory Buffer",
        "keyphrase": "Improper Restriction of Operations within the Bounds of a Memory Buffer",
        "type": "rootcause"
      },
      {
        "id": "weakness:Improper Restriction of Operations within the Bounds of a Memory Buffer",
        "keyphrase": "Improper Restriction of Operations within the Bounds of a Memory Buffer",
        "type": "weakness"
      },
      {
        "id": "weakness:Overflow",
        "keyphrase": "Overflow",
        "type": "weakness"
      },
      {
        "id": "impact:overflow buffers",
        "keyphrase": "overflow buffers",
        "type": "impact"
      },
      {
        "id": "component:ddns-start",
        "keyphrase": "ddns-start",
        "type": "component"
      }
    ],
    "197": [
      {
        "id": "rootcause:Improper Restriction of Operations within the Bounds of a Memory Buffer",
        "keyphrase": "Improper Restriction of Operations within the Bounds of a Memory Buffer",
        "type": "rootcause"
      },
      {
        "id": "weakness:Improper Restriction of Operations within the Bounds of a Memory Buffer",
        "keyphrase": "Improper Restriction of Operations within the Bounds of a Memory Buffer",
        "type": "weakness"
      }
    ],
    "787": [
      {
        "id": "rootcause:Improper Restriction of Operations within the Bounds of a Memory Buffer",
        "keyphrase": "Improper Restriction of Operations within the Bounds of a Memory Buffer",
        "type": "rootcause"
      },
      {
        "id": "weakness:Improper Restriction of Operations within the Bounds of a Memory Buffer",
        "keyphrase": "Improper Restriction of Operations within the Bounds of a Memory Buffer",
        "type": "weakness"
      },
      {
        "id": "version:before 5.29.102",
        "keyphrase": "before 5.29.102",
        "type": "version"
      }
    ],
    "122": [
      {
        "id": "weakness:Overflow",
        "keyphrase": "Overflow",
        "type": "weakness"
      },
      {
        "id": "impact:overflow buffers",
        "keyphrase": "overflow buffers",
        "type": "impact"
      }
    ],
    "682": [
      {
        "id": "weakness:Overflow",
        "keyphrase": "Overflow",
        "type": "weakness"
      },
      {
        "id": "version:before 5.29.102",
        "keyphrase": "before 5.29.102",
        "type": "version"
      }
    ],
    "770": [
      {
        "id": "impact:overflow buffers",
        "keyphrase": "overflow buffers",
        "type": "impact"
      }
    ],
    "22": [
      {
        "id": "product:Western Digital My Cloud",
        "keyphrase": "Western Digital My Cloud",
        "type": "product"
      },
      {
        "id": "component:ddns-start",
        "keyphrase": "ddns-start",
        "type": "component"
      }
    ],
    "522": [
      {
        "id": "product:Western Digital My Cloud",
        "keyphrase": "Western Digital My Cloud",
        "type": "product"
      }
    ],
    "116": [
      {
        "id": "product:Western Digital My Cloud",
        "keyphrase": "Western Digital My Cloud",
        "type": "product"
      }
    ],
    "124": [
      {
        "id": "version:before 5.29.102",
        "keyphrase": "before 5.29.102",
        "type": "version"
      }
    ],
    "194": [
      {
        "id": "component:ddns-start",
        "keyphrase": "ddns-start",
        "type": "component"
      }
    ]
  }
}