{
  "vulnerability_info": "VulnerabilityInfo(cve_id='CVE-2024-5126', description='An **improper access control** vulnerability exists in the lunary-ai/lunary repository, specifically within the versions.patch functionality for updating prompts. Affected versions include 1.2.2 up to but not including 1.2.25. The vulnerability allows unauthorized users to update prompt details due to **insufficient access control** checks. This issue was addressed and fixed in version 1.2.25.', key_phrases={'rootcause': ['improper access control', 'insufficient access control'], 'weakness': '', 'impact': 'update prompt details', 'vector': '', 'attacker': 'unauthorized users', 'product': 'lunary-ai/lunary', 'version': '1.2.2 up to but not including 1.2.25', 'component': 'versions.patch functionality for updating prompts'}, reference_content='Based on the provided content, here\\'s an analysis:\\n\\n**Content Analysis:**\\n\\nThe provided content consists of two HTML documents: one from GitHub showing a commit diff and another from huntr.com. The GitHub commit diff shows changes to `template-versions.ts` and `users.ts` files, but neither of these relate to a known CVE. The huntr.com content is a general website footer.\\n\\n**CVE Relevance:**\\n\\nThe provided content **does not** appear to contain information related to a CVE. The GitHub commit diff is a code change to fix a backend plan check in a project called \"lunary\" which seems unrelated to any known vulnerability. There is no vulnerability information to extract from this context.\\n\\n**Response:**\\n\\nNOINFO', similar_info={'cwe_distribution': {}, 'cwe_consensus': '', 'similarity_stats': {'thresholds': [], 'total_samples_by_threshold': {}, 'top_cwes_by_threshold': {}}}, similarity_summary=SimilarityInsight(consensus_cwe='', top_cwes=[], confidence_levels={}, total_samples=0), analysis='', analysis_with_relationships='', criticism='', resolution='', relevant_cwes=[{'metadata': {'doc_id': '285', 'name': 'Improper Authorization', 'source': 'sparse', 'original_content': 'The product does not perform or incorrectly performs an authorization check when an actor attempts to access a resource or perform an action.', 'keyphrase_sources': [{'id': 'rootcause:improper access control', 'keyphrase': 'improper access control', 'type': 'rootcause'}, {'id': 'rootcause:insufficient access control', 'keyphrase': 'insufficient access control', 'type': 'rootcause'}, {'id': 'impact:update prompt details', 'keyphrase': 'update prompt details', 'type': 'impact'}, {'id': 'attacker:unauthorized users', 'keyphrase': 'unauthorized users', 'type': 'attacker'}, {'id': 'product:lunary-ai/lunary', 'keyphrase': 'lunary-ai/lunary', 'type': 'product'}, {'id': 'version:1.2.2 up to but not including 1.2.25', 'keyphrase': '1.2.2 up to but not including 1.2.25', 'type': 'version'}, {'id': 'component:versions.patch functionality for updating prompts', 'keyphrase': 'versions.patch functionality for updating prompts', 'type': 'component'}]}, 'similarity': np.float64(344.4019312049114)}, {'metadata': {'doc_id': '284', 'name': 'Improper Access Control', 'source': 'sparse', 'original_content': 'The product does not restrict or incorrectly restricts access to a resource from an unauthorized actor.', 'keyphrase_sources': [{'id': 'rootcause:improper access control', 'keyphrase': 'improper access control', 'type': 'rootcause'}, {'id': 'rootcause:insufficient access control', 'keyphrase': 'insufficient access control', 'type': 'rootcause'}, {'id': 'impact:update prompt details', 'keyphrase': 'update prompt details', 'type': 'impact'}, {'id': 'attacker:unauthorized users', 'keyphrase': 'unauthorized users', 'type': 'attacker'}, {'id': 'product:lunary-ai/lunary', 'keyphrase': 'lunary-ai/lunary', 'type': 'product'}, {'id': 'version:1.2.2 up to but not including 1.2.25', 'keyphrase': '1.2.2 up to but not including 1.2.25', 'type': 'version'}]}, 'similarity': np.float64(339.05885144009505)}, {'metadata': {'doc_id': '287', 'name': 'Improper Authentication', 'source': 'sparse', 'original_content': 'When an actor claims to have a given identity, the product does not prove or insufficiently proves that the claim is correct.', 'keyphrase_sources': [{'id': 'rootcause:improper access control', 'keyphrase': 'improper access control', 'type': 'rootcause'}, {'id': 'rootcause:insufficient access control', 'keyphrase': 'insufficient access control', 'type': 'rootcause'}, {'id': 'attacker:unauthorized users', 'keyphrase': 'unauthorized users', 'type': 'attacker'}, {'id': 'product:lunary-ai/lunary', 'keyphrase': 'lunary-ai/lunary', 'type': 'product'}, {'id': 'component:versions.patch functionality for updating prompts', 'keyphrase': 'versions.patch functionality for updating prompts', 'type': 'component'}]}, 'similarity': np.float64(327.78169815553906)}, {'metadata': {'doc_id': '863', 'name': 'Incorrect Authorization', 'source': 'sparse', 'original_content': 'The product performs an authorization check when an actor attempts to access a resource or perform an action, but it does not correctly perform the check.', 'keyphrase_sources': [{'id': 'rootcause:improper access control', 'keyphrase': 'improper access control', 'type': 'rootcause'}, {'id': 'rootcause:insufficient access control', 'keyphrase': 'insufficient access control', 'type': 'rootcause'}, {'id': 'impact:update prompt details', 'keyphrase': 'update prompt details', 'type': 'impact'}, {'id': 'attacker:unauthorized users', 'keyphrase': 'unauthorized users', 'type': 'attacker'}, {'id': 'product:lunary-ai/lunary', 'keyphrase': 'lunary-ai/lunary', 'type': 'product'}, {'id': 'version:1.2.2 up to but not including 1.2.25', 'keyphrase': '1.2.2 up to but not including 1.2.25', 'type': 'version'}, {'id': 'component:versions.patch functionality for updating prompts', 'keyphrase': 'versions.patch functionality for updating prompts', 'type': 'component'}]}, 'similarity': np.float64(327.1410122945211)}, {'metadata': {'doc_id': '20', 'name': 'Improper Input Validation', 'source': 'sparse', 'original_content': 'The product receives input or data, but it does\\n        not validate or incorrectly validates that the input has the\\n        properties that are required to process the data safely and\\n        correctly.', 'keyphrase_sources': [{'id': 'rootcause:insufficient access control', 'keyphrase': 'insufficient access control', 'type': 'rootcause'}, {'id': 'product:lunary-ai/lunary', 'keyphrase': 'lunary-ai/lunary', 'type': 'product'}]}, 'similarity': np.float64(319.31599552187146)}, {'metadata': {'doc_id': '639', 'name': 'Authorization Bypass Through User-Controlled Key', 'source': 'sparse', 'original_content': \"The system's authorization functionality does not prevent one user from gaining access to another user's data or record by modifying the key value identifying the data.\", 'keyphrase_sources': [{'id': 'rootcause:improper access control', 'keyphrase': 'improper access control', 'type': 'rootcause'}, {'id': 'component:versions.patch functionality for updating prompts', 'keyphrase': 'versions.patch functionality for updating prompts', 'type': 'component'}]}, 'similarity': np.float64(318.805127524509)}, {'metadata': {'doc_id': '61', 'name': 'UNIX Symbolic Link (Symlink) Following', 'source': 'sparse', 'original_content': 'The product, when opening a file or directory, does not sufficiently account for when the file is a symbolic link that resolves to a target outside of the intended control sphere. This could allow an attacker to cause the product to operate on unauthorized files.', 'keyphrase_sources': [{'id': 'version:1.2.2 up to but not including 1.2.25', 'keyphrase': '1.2.2 up to but not including 1.2.25', 'type': 'version'}]}, 'similarity': np.float64(126.99190498085393)}, {'metadata': {'doc_id': '347', 'name': 'Improper Verification of Cryptographic Signature', 'source': 'sparse', 'original_content': 'The product does not verify, or incorrectly verifies, the cryptographic signature for data.', 'keyphrase_sources': [{'id': 'version:1.2.2 up to but not including 1.2.25', 'keyphrase': '1.2.2 up to but not including 1.2.25', 'type': 'version'}]}, 'similarity': np.float64(126.3724041495015)}, {'metadata': {'doc_id': '620', 'name': 'Unverified Password Change', 'source': 'sparse', 'original_content': 'When setting a new password for a user, the product does not require knowledge of the original password, or using another form of authentication.', 'keyphrase_sources': [{'id': 'impact:update prompt details', 'keyphrase': 'update prompt details', 'type': 'impact'}]}, 'similarity': np.float64(107.87025939166631)}, {'metadata': {'doc_id': '1336', 'name': 'Improper Neutralization of Special Elements Used in a Template Engine', 'source': 'sparse', 'original_content': 'The product uses a template engine to insert or process externally-influenced input, but it does not neutralize or incorrectly neutralizes special elements or syntax that can be interpreted as template expressions or other code directives when processed by the engine.', 'keyphrase_sources': [{'id': 'impact:update prompt details', 'keyphrase': 'update prompt details', 'type': 'impact'}]}, 'similarity': np.float64(104.35543489167387)}, {'metadata': {'doc_id': '306', 'name': 'Missing Authentication for Critical Function', 'source': 'sparse', 'original_content': 'The product does not perform any authentication for functionality that requires a provable user identity or consumes a significant amount of resources.', 'keyphrase_sources': [{'id': 'attacker:unauthorized users', 'keyphrase': 'unauthorized users', 'type': 'attacker'}, {'id': 'component:versions.patch functionality for updating prompts', 'keyphrase': 'versions.patch functionality for updating prompts', 'type': 'component'}]}, 'similarity': np.float64(103.26816379904162)}], identified_cwes={'analyzer': [], 'critic_additional': []})",
  "retrieval_results": {
    "has_multiple_keyphrases": true,
    "keyphrase_cwe_sets": {
      "rootcause:improper access control": {
        "keyphrase": "improper access control",
        "type": "rootcause",
        "cwes": [
          {
            "metadata": {
              "doc_id": "285",
              "name": "Improper Authorization",
              "source": "sparse",
              "original_content": "The product does not perform or incorrectly performs an authorization check when an actor attempts to access a resource or perform an action.",
              "keyphrase_sources": [
                {
                  "id": "rootcause:improper access control",
                  "keyphrase": "improper access control",
                  "type": "rootcause"
                },
                {
                  "id": "rootcause:insufficient access control",
                  "keyphrase": "insufficient access control",
                  "type": "rootcause"
                },
                {
                  "id": "impact:update prompt details",
                  "keyphrase": "update prompt details",
                  "type": "impact"
                },
                {
                  "id": "attacker:unauthorized users",
                  "keyphrase": "unauthorized users",
                  "type": "attacker"
                },
                {
                  "id": "product:lunary-ai/lunary",
                  "keyphrase": "lunary-ai/lunary",
                  "type": "product"
                },
                {
                  "id": "version:1.2.2 up to but not including 1.2.25",
                  "keyphrase": "1.2.2 up to but not including 1.2.25",
                  "type": "version"
                },
                {
                  "id": "component:versions.patch functionality for updating prompts",
                  "keyphrase": "versions.patch functionality for updating prompts",
                  "type": "component"
                }
              ]
            },
            "similarity": 344.4019312049114
          },
          {
            "metadata": {
              "doc_id": "284",
              "name": "Improper Access Control",
              "source": "sparse",
              "original_content": "The product does not restrict or incorrectly restricts access to a resource from an unauthorized actor.",
              "keyphrase_sources": [
                {
                  "id": "rootcause:improper access control",
                  "keyphrase": "improper access control",
                  "type": "rootcause"
                },
                {
                  "id": "rootcause:insufficient access control",
                  "keyphrase": "insufficient access control",
                  "type": "rootcause"
                },
                {
                  "id": "impact:update prompt details",
                  "keyphrase": "update prompt details",
                  "type": "impact"
                },
                {
                  "id": "attacker:unauthorized users",
                  "keyphrase": "unauthorized users",
                  "type": "attacker"
                },
                {
                  "id": "product:lunary-ai/lunary",
                  "keyphrase": "lunary-ai/lunary",
                  "type": "product"
                },
                {
                  "id": "version:1.2.2 up to but not including 1.2.25",
                  "keyphrase": "1.2.2 up to but not including 1.2.25",
                  "type": "version"
                }
              ]
            },
            "similarity": 339.05885144009505
          },
          {
            "metadata": {
              "doc_id": "287",
              "name": "Improper Authentication",
              "source": "sparse",
              "original_content": "When an actor claims to have a given identity, the product does not prove or insufficiently proves that the claim is correct.",
              "keyphrase_sources": [
                {
                  "id": "rootcause:improper access control",
                  "keyphrase": "improper access control",
                  "type": "rootcause"
                },
                {
                  "id": "rootcause:insufficient access control",
                  "keyphrase": "insufficient access control",
                  "type": "rootcause"
                },
                {
                  "id": "attacker:unauthorized users",
                  "keyphrase": "unauthorized users",
                  "type": "attacker"
                },
                {
                  "id": "product:lunary-ai/lunary",
                  "keyphrase": "lunary-ai/lunary",
                  "type": "product"
                },
                {
                  "id": "component:versions.patch functionality for updating prompts",
                  "keyphrase": "versions.patch functionality for updating prompts",
                  "type": "component"
                }
              ]
            },
            "similarity": 327.78169815553906
          },
          {
            "metadata": {
              "doc_id": "863",
              "name": "Incorrect Authorization",
              "source": "sparse",
              "original_content": "The product performs an authorization check when an actor attempts to access a resource or perform an action, but it does not correctly perform the check.",
              "keyphrase_sources": [
                {
                  "id": "rootcause:improper access control",
                  "keyphrase": "improper access control",
                  "type": "rootcause"
                },
                {
                  "id": "rootcause:insufficient access control",
                  "keyphrase": "insufficient access control",
                  "type": "rootcause"
                },
                {
                  "id": "impact:update prompt details",
                  "keyphrase": "update prompt details",
                  "type": "impact"
                },
                {
                  "id": "attacker:unauthorized users",
                  "keyphrase": "unauthorized users",
                  "type": "attacker"
                },
                {
                  "id": "product:lunary-ai/lunary",
                  "keyphrase": "lunary-ai/lunary",
                  "type": "product"
                },
                {
                  "id": "version:1.2.2 up to but not including 1.2.25",
                  "keyphrase": "1.2.2 up to but not including 1.2.25",
                  "type": "version"
                },
                {
                  "id": "component:versions.patch functionality for updating prompts",
                  "keyphrase": "versions.patch functionality for updating prompts",
                  "type": "component"
                }
              ]
            },
            "similarity": 327.1410122945211
          },
          {
            "metadata": {
              "doc_id": "639",
              "name": "Authorization Bypass Through User-Controlled Key",
              "source": "sparse",
              "original_content": "The system's authorization functionality does not prevent one user from gaining access to another user's data or record by modifying the key value identifying the data.",
              "keyphrase_sources": [
                {
                  "id": "rootcause:improper access control",
                  "keyphrase": "improper access control",
                  "type": "rootcause"
                },
                {
                  "id": "component:versions.patch functionality for updating prompts",
                  "keyphrase": "versions.patch functionality for updating prompts",
                  "type": "component"
                }
              ]
            },
            "similarity": 318.805127524509
          }
        ]
      },
      "rootcause:insufficient access control": {
        "keyphrase": "insufficient access control",
        "type": "rootcause",
        "cwes": [
          {
            "metadata": {
              "doc_id": "284",
              "name": "Improper Access Control",
              "source": "sparse",
              "original_content": "The product does not restrict or incorrectly restricts access to a resource from an unauthorized actor."
            },
            "similarity": 344.41978286066063
          },
          {
            "metadata": {
              "doc_id": "285",
              "name": "Improper Authorization",
              "source": "sparse",
              "original_content": "The product does not perform or incorrectly performs an authorization check when an actor attempts to access a resource or perform an action."
            },
            "similarity": 343.566397271487
          },
          {
            "metadata": {
              "doc_id": "863",
              "name": "Incorrect Authorization",
              "source": "sparse",
              "original_content": "The product performs an authorization check when an actor attempts to access a resource or perform an action, but it does not correctly perform the check."
            },
            "similarity": 334.95561293869457
          },
          {
            "metadata": {
              "doc_id": "287",
              "name": "Improper Authentication",
              "source": "sparse",
              "original_content": "When an actor claims to have a given identity, the product does not prove or insufficiently proves that the claim is correct."
            },
            "similarity": 327.7576405473244
          },
          {
            "metadata": {
              "doc_id": "20",
              "name": "Improper Input Validation",
              "source": "sparse",
              "original_content": "The product receives input or data, but it does\n        not validate or incorrectly validates that the input has the\n        properties that are required to process the data safely and\n        correctly.",
              "keyphrase_sources": [
                {
                  "id": "rootcause:insufficient access control",
                  "keyphrase": "insufficient access control",
                  "type": "rootcause"
                },
                {
                  "id": "product:lunary-ai/lunary",
                  "keyphrase": "lunary-ai/lunary",
                  "type": "product"
                }
              ]
            },
            "similarity": 319.31599552187146
          }
        ]
      },
      "impact:update prompt details": {
        "keyphrase": "update prompt details",
        "type": "impact",
        "cwes": [
          {
            "metadata": {
              "doc_id": "285",
              "name": "Improper Authorization",
              "source": "sparse",
              "original_content": "The product does not perform or incorrectly performs an authorization check when an actor attempts to access a resource or perform an action."
            },
            "similarity": 109.19732646054557
          },
          {
            "metadata": {
              "doc_id": "620",
              "name": "Unverified Password Change",
              "source": "sparse",
              "original_content": "When setting a new password for a user, the product does not require knowledge of the original password, or using another form of authentication.",
              "keyphrase_sources": [
                {
                  "id": "impact:update prompt details",
                  "keyphrase": "update prompt details",
                  "type": "impact"
                }
              ]
            },
            "similarity": 107.87025939166631
          },
          {
            "metadata": {
              "doc_id": "284",
              "name": "Improper Access Control",
              "source": "sparse",
              "original_content": "The product does not restrict or incorrectly restricts access to a resource from an unauthorized actor."
            },
            "similarity": 105.45556698953092
          },
          {
            "metadata": {
              "doc_id": "1336",
              "name": "Improper Neutralization of Special Elements Used in a Template Engine",
              "source": "sparse",
              "original_content": "The product uses a template engine to insert or process externally-influenced input, but it does not neutralize or incorrectly neutralizes special elements or syntax that can be interpreted as template expressions or other code directives when processed by the engine.",
              "keyphrase_sources": [
                {
                  "id": "impact:update prompt details",
                  "keyphrase": "update prompt details",
                  "type": "impact"
                }
              ]
            },
            "similarity": 104.35543489167387
          },
          {
            "metadata": {
              "doc_id": "863",
              "name": "Incorrect Authorization",
              "source": "sparse",
              "original_content": "The product performs an authorization check when an actor attempts to access a resource or perform an action, but it does not correctly perform the check."
            },
            "similarity": 104.21099771374075
          }
        ]
      },
      "attacker:unauthorized users": {
        "keyphrase": "unauthorized users",
        "type": "attacker",
        "cwes": [
          {
            "metadata": {
              "doc_id": "285",
              "name": "Improper Authorization",
              "source": "sparse",
              "original_content": "The product does not perform or incorrectly performs an authorization check when an actor attempts to access a resource or perform an action."
            },
            "similarity": 112.42279051872272
          },
          {
            "metadata": {
              "doc_id": "284",
              "name": "Improper Access Control",
              "source": "sparse",
              "original_content": "The product does not restrict or incorrectly restricts access to a resource from an unauthorized actor."
            },
            "similarity": 107.63164712892177
          },
          {
            "metadata": {
              "doc_id": "863",
              "name": "Incorrect Authorization",
              "source": "sparse",
              "original_content": "The product performs an authorization check when an actor attempts to access a resource or perform an action, but it does not correctly perform the check."
            },
            "similarity": 106.02688961404435
          },
          {
            "metadata": {
              "doc_id": "287",
              "name": "Improper Authentication",
              "source": "sparse",
              "original_content": "When an actor claims to have a given identity, the product does not prove or insufficiently proves that the claim is correct."
            },
            "similarity": 105.66484558194358
          },
          {
            "metadata": {
              "doc_id": "306",
              "name": "Missing Authentication for Critical Function",
              "source": "sparse",
              "original_content": "The product does not perform any authentication for functionality that requires a provable user identity or consumes a significant amount of resources.",
              "keyphrase_sources": [
                {
                  "id": "attacker:unauthorized users",
                  "keyphrase": "unauthorized users",
                  "type": "attacker"
                },
                {
                  "id": "component:versions.patch functionality for updating prompts",
                  "keyphrase": "versions.patch functionality for updating prompts",
                  "type": "component"
                }
              ]
            },
            "similarity": 103.26816379904162
          }
        ]
      },
      "product:lunary-ai/lunary": {
        "keyphrase": "lunary-ai/lunary",
        "type": "product",
        "cwes": [
          {
            "metadata": {
              "doc_id": "285",
              "name": "Improper Authorization",
              "source": "sparse",
              "original_content": "The product does not perform or incorrectly performs an authorization check when an actor attempts to access a resource or perform an action."
            },
            "similarity": 102.48391533057928
          },
          {
            "metadata": {
              "doc_id": "284",
              "name": "Improper Access Control",
              "source": "sparse",
              "original_content": "The product does not restrict or incorrectly restricts access to a resource from an unauthorized actor."
            },
            "similarity": 99.57890733633101
          },
          {
            "metadata": {
              "doc_id": "863",
              "name": "Incorrect Authorization",
              "source": "sparse",
              "original_content": "The product performs an authorization check when an actor attempts to access a resource or perform an action, but it does not correctly perform the check."
            },
            "similarity": 98.00705239995749
          },
          {
            "metadata": {
              "doc_id": "287",
              "name": "Improper Authentication",
              "source": "sparse",
              "original_content": "When an actor claims to have a given identity, the product does not prove or insufficiently proves that the claim is correct."
            },
            "similarity": 97.34910476671581
          },
          {
            "metadata": {
              "doc_id": "20",
              "name": "Improper Input Validation",
              "source": "sparse",
              "original_content": "The product receives input or data, but it does\n        not validate or incorrectly validates that the input has the\n        properties that are required to process the data safely and\n        correctly."
            },
            "similarity": 95.75419520435388
          }
        ]
      },
      "version:1.2.2 up to but not including 1.2.25": {
        "keyphrase": "1.2.2 up to but not including 1.2.25",
        "type": "version",
        "cwes": [
          {
            "metadata": {
              "doc_id": "285",
              "name": "Improper Authorization",
              "source": "sparse",
              "original_content": "The product does not perform or incorrectly performs an authorization check when an actor attempts to access a resource or perform an action."
            },
            "similarity": 132.24531939975404
          },
          {
            "metadata": {
              "doc_id": "284",
              "name": "Improper Access Control",
              "source": "sparse",
              "original_content": "The product does not restrict or incorrectly restricts access to a resource from an unauthorized actor."
            },
            "similarity": 131.73992439353694
          },
          {
            "metadata": {
              "doc_id": "61",
              "name": "UNIX Symbolic Link (Symlink) Following",
              "source": "sparse",
              "original_content": "The product, when opening a file or directory, does not sufficiently account for when the file is a symbolic link that resolves to a target outside of the intended control sphere. This could allow an attacker to cause the product to operate on unauthorized files.",
              "keyphrase_sources": [
                {
                  "id": "version:1.2.2 up to but not including 1.2.25",
                  "keyphrase": "1.2.2 up to but not including 1.2.25",
                  "type": "version"
                }
              ]
            },
            "similarity": 126.99190498085393
          },
          {
            "metadata": {
              "doc_id": "863",
              "name": "Incorrect Authorization",
              "source": "sparse",
              "original_content": "The product performs an authorization check when an actor attempts to access a resource or perform an action, but it does not correctly perform the check."
            },
            "similarity": 126.93228907403328
          },
          {
            "metadata": {
              "doc_id": "347",
              "name": "Improper Verification of Cryptographic Signature",
              "source": "sparse",
              "original_content": "The product does not verify, or incorrectly verifies, the cryptographic signature for data.",
              "keyphrase_sources": [
                {
                  "id": "version:1.2.2 up to but not including 1.2.25",
                  "keyphrase": "1.2.2 up to but not including 1.2.25",
                  "type": "version"
                }
              ]
            },
            "similarity": 126.3724041495015
          }
        ]
      },
      "component:versions.patch functionality for updating prompts": {
        "keyphrase": "versions.patch functionality for updating prompts",
        "type": "component",
        "cwes": [
          {
            "metadata": {
              "doc_id": "285",
              "name": "Improper Authorization",
              "source": "sparse",
              "original_content": "The product does not perform or incorrectly performs an authorization check when an actor attempts to access a resource or perform an action."
            },
            "similarity": 115.8090010773734
          },
          {
            "metadata": {
              "doc_id": "863",
              "name": "Incorrect Authorization",
              "source": "sparse",
              "original_content": "The product performs an authorization check when an actor attempts to access a resource or perform an action, but it does not correctly perform the check."
            },
            "similarity": 113.0378482533449
          },
          {
            "metadata": {
              "doc_id": "287",
              "name": "Improper Authentication",
              "source": "sparse",
              "original_content": "When an actor claims to have a given identity, the product does not prove or insufficiently proves that the claim is correct."
            },
            "similarity": 112.84089058605647
          },
          {
            "metadata": {
              "doc_id": "306",
              "name": "Missing Authentication for Critical Function",
              "source": "sparse",
              "original_content": "The product does not perform any authentication for functionality that requires a provable user identity or consumes a significant amount of resources."
            },
            "similarity": 112.34850108244187
          },
          {
            "metadata": {
              "doc_id": "639",
              "name": "Authorization Bypass Through User-Controlled Key",
              "source": "sparse",
              "original_content": "The system's authorization functionality does not prevent one user from gaining access to another user's data or record by modifying the key value identifying the data."
            },
            "similarity": 111.75409641586072
          }
        ]
      }
    },
    "keyphrase_mapping": {
      "285": [
        {
          "id": "rootcause:improper access control",
          "keyphrase": "improper access control",
          "type": "rootcause"
        },
        {
          "id": "rootcause:insufficient access control",
          "keyphrase": "insufficient access control",
          "type": "rootcause"
        },
        {
          "id": "impact:update prompt details",
          "keyphrase": "update prompt details",
          "type": "impact"
        },
        {
          "id": "attacker:unauthorized users",
          "keyphrase": "unauthorized users",
          "type": "attacker"
        },
        {
          "id": "product:lunary-ai/lunary",
          "keyphrase": "lunary-ai/lunary",
          "type": "product"
        },
        {
          "id": "version:1.2.2 up to but not including 1.2.25",
          "keyphrase": "1.2.2 up to but not including 1.2.25",
          "type": "version"
        },
        {
          "id": "component:versions.patch functionality for updating prompts",
          "keyphrase": "versions.patch functionality for updating prompts",
          "type": "component"
        }
      ],
      "284": [
        {
          "id": "rootcause:improper access control",
          "keyphrase": "improper access control",
          "type": "rootcause"
        },
        {
          "id": "rootcause:insufficient access control",
          "keyphrase": "insufficient access control",
          "type": "rootcause"
        },
        {
          "id": "impact:update prompt details",
          "keyphrase": "update prompt details",
          "type": "impact"
        },
        {
          "id": "attacker:unauthorized users",
          "keyphrase": "unauthorized users",
          "type": "attacker"
        },
        {
          "id": "product:lunary-ai/lunary",
          "keyphrase": "lunary-ai/lunary",
          "type": "product"
        },
        {
          "id": "version:1.2.2 up to but not including 1.2.25",
          "keyphrase": "1.2.2 up to but not including 1.2.25",
          "type": "version"
        }
      ],
      "287": [
        {
          "id": "rootcause:improper access control",
          "keyphrase": "improper access control",
          "type": "rootcause"
        },
        {
          "id": "rootcause:insufficient access control",
          "keyphrase": "insufficient access control",
          "type": "rootcause"
        },
        {
          "id": "attacker:unauthorized users",
          "keyphrase": "unauthorized users",
          "type": "attacker"
        },
        {
          "id": "product:lunary-ai/lunary",
          "keyphrase": "lunary-ai/lunary",
          "type": "product"
        },
        {
          "id": "component:versions.patch functionality for updating prompts",
          "keyphrase": "versions.patch functionality for updating prompts",
          "type": "component"
        }
      ],
      "863": [
        {
          "id": "rootcause:improper access control",
          "keyphrase": "improper access control",
          "type": "rootcause"
        },
        {
          "id": "rootcause:insufficient access control",
          "keyphrase": "insufficient access control",
          "type": "rootcause"
        },
        {
          "id": "impact:update prompt details",
          "keyphrase": "update prompt details",
          "type": "impact"
        },
        {
          "id": "attacker:unauthorized users",
          "keyphrase": "unauthorized users",
          "type": "attacker"
        },
        {
          "id": "product:lunary-ai/lunary",
          "keyphrase": "lunary-ai/lunary",
          "type": "product"
        },
        {
          "id": "version:1.2.2 up to but not including 1.2.25",
          "keyphrase": "1.2.2 up to but not including 1.2.25",
          "type": "version"
        },
        {
          "id": "component:versions.patch functionality for updating prompts",
          "keyphrase": "versions.patch functionality for updating prompts",
          "type": "component"
        }
      ],
      "639": [
        {
          "id": "rootcause:improper access control",
          "keyphrase": "improper access control",
          "type": "rootcause"
        },
        {
          "id": "component:versions.patch functionality for updating prompts",
          "keyphrase": "versions.patch functionality for updating prompts",
          "type": "component"
        }
      ],
      "20": [
        {
          "id": "rootcause:insufficient access control",
          "keyphrase": "insufficient access control",
          "type": "rootcause"
        },
        {
          "id": "product:lunary-ai/lunary",
          "keyphrase": "lunary-ai/lunary",
          "type": "product"
        }
      ],
      "620": [
        {
          "id": "impact:update prompt details",
          "keyphrase": "update prompt details",
          "type": "impact"
        }
      ],
      "1336": [
        {
          "id": "impact:update prompt details",
          "keyphrase": "update prompt details",
          "type": "impact"
        }
      ],
      "306": [
        {
          "id": "attacker:unauthorized users",
          "keyphrase": "unauthorized users",
          "type": "attacker"
        },
        {
          "id": "component:versions.patch functionality for updating prompts",
          "keyphrase": "versions.patch functionality for updating prompts",
          "type": "component"
        }
      ],
      "61": [
        {
          "id": "version:1.2.2 up to but not including 1.2.25",
          "keyphrase": "1.2.2 up to but not including 1.2.25",
          "type": "version"
        }
      ],
      "347": [
        {
          "id": "version:1.2.2 up to but not including 1.2.25",
          "keyphrase": "1.2.2 up to but not including 1.2.25",
          "type": "version"
        }
      ]
    },
    "relevant_cwes": [
      {
        "metadata": {
          "doc_id": "285",
          "name": "Improper Authorization",
          "source": "sparse",
          "original_content": "The product does not perform or incorrectly performs an authorization check when an actor attempts to access a resource or perform an action.",
          "keyphrase_sources": [
            {
              "id": "rootcause:improper access control",
              "keyphrase": "improper access control",
              "type": "rootcause"
            },
            {
              "id": "rootcause:insufficient access control",
              "keyphrase": "insufficient access control",
              "type": "rootcause"
            },
            {
              "id": "impact:update prompt details",
              "keyphrase": "update prompt details",
              "type": "impact"
            },
            {
              "id": "attacker:unauthorized users",
              "keyphrase": "unauthorized users",
              "type": "attacker"
            },
            {
              "id": "product:lunary-ai/lunary",
              "keyphrase": "lunary-ai/lunary",
              "type": "product"
            },
            {
              "id": "version:1.2.2 up to but not including 1.2.25",
              "keyphrase": "1.2.2 up to but not including 1.2.25",
              "type": "version"
            },
            {
              "id": "component:versions.patch functionality for updating prompts",
              "keyphrase": "versions.patch functionality for updating prompts",
              "type": "component"
            }
          ]
        },
        "similarity": 344.4019312049114
      },
      {
        "metadata": {
          "doc_id": "284",
          "name": "Improper Access Control",
          "source": "sparse",
          "original_content": "The product does not restrict or incorrectly restricts access to a resource from an unauthorized actor.",
          "keyphrase_sources": [
            {
              "id": "rootcause:improper access control",
              "keyphrase": "improper access control",
              "type": "rootcause"
            },
            {
              "id": "rootcause:insufficient access control",
              "keyphrase": "insufficient access control",
              "type": "rootcause"
            },
            {
              "id": "impact:update prompt details",
              "keyphrase": "update prompt details",
              "type": "impact"
            },
            {
              "id": "attacker:unauthorized users",
              "keyphrase": "unauthorized users",
              "type": "attacker"
            },
            {
              "id": "product:lunary-ai/lunary",
              "keyphrase": "lunary-ai/lunary",
              "type": "product"
            },
            {
              "id": "version:1.2.2 up to but not including 1.2.25",
              "keyphrase": "1.2.2 up to but not including 1.2.25",
              "type": "version"
            }
          ]
        },
        "similarity": 339.05885144009505
      },
      {
        "metadata": {
          "doc_id": "287",
          "name": "Improper Authentication",
          "source": "sparse",
          "original_content": "When an actor claims to have a given identity, the product does not prove or insufficiently proves that the claim is correct.",
          "keyphrase_sources": [
            {
              "id": "rootcause:improper access control",
              "keyphrase": "improper access control",
              "type": "rootcause"
            },
            {
              "id": "rootcause:insufficient access control",
              "keyphrase": "insufficient access control",
              "type": "rootcause"
            },
            {
              "id": "attacker:unauthorized users",
              "keyphrase": "unauthorized users",
              "type": "attacker"
            },
            {
              "id": "product:lunary-ai/lunary",
              "keyphrase": "lunary-ai/lunary",
              "type": "product"
            },
            {
              "id": "component:versions.patch functionality for updating prompts",
              "keyphrase": "versions.patch functionality for updating prompts",
              "type": "component"
            }
          ]
        },
        "similarity": 327.78169815553906
      },
      {
        "metadata": {
          "doc_id": "863",
          "name": "Incorrect Authorization",
          "source": "sparse",
          "original_content": "The product performs an authorization check when an actor attempts to access a resource or perform an action, but it does not correctly perform the check.",
          "keyphrase_sources": [
            {
              "id": "rootcause:improper access control",
              "keyphrase": "improper access control",
              "type": "rootcause"
            },
            {
              "id": "rootcause:insufficient access control",
              "keyphrase": "insufficient access control",
              "type": "rootcause"
            },
            {
              "id": "impact:update prompt details",
              "keyphrase": "update prompt details",
              "type": "impact"
            },
            {
              "id": "attacker:unauthorized users",
              "keyphrase": "unauthorized users",
              "type": "attacker"
            },
            {
              "id": "product:lunary-ai/lunary",
              "keyphrase": "lunary-ai/lunary",
              "type": "product"
            },
            {
              "id": "version:1.2.2 up to but not including 1.2.25",
              "keyphrase": "1.2.2 up to but not including 1.2.25",
              "type": "version"
            },
            {
              "id": "component:versions.patch functionality for updating prompts",
              "keyphrase": "versions.patch functionality for updating prompts",
              "type": "component"
            }
          ]
        },
        "similarity": 327.1410122945211
      },
      {
        "metadata": {
          "doc_id": "20",
          "name": "Improper Input Validation",
          "source": "sparse",
          "original_content": "The product receives input or data, but it does\n        not validate or incorrectly validates that the input has the\n        properties that are required to process the data safely and\n        correctly.",
          "keyphrase_sources": [
            {
              "id": "rootcause:insufficient access control",
              "keyphrase": "insufficient access control",
              "type": "rootcause"
            },
            {
              "id": "product:lunary-ai/lunary",
              "keyphrase": "lunary-ai/lunary",
              "type": "product"
            }
          ]
        },
        "similarity": 319.31599552187146
      },
      {
        "metadata": {
          "doc_id": "639",
          "name": "Authorization Bypass Through User-Controlled Key",
          "source": "sparse",
          "original_content": "The system's authorization functionality does not prevent one user from gaining access to another user's data or record by modifying the key value identifying the data.",
          "keyphrase_sources": [
            {
              "id": "rootcause:improper access control",
              "keyphrase": "improper access control",
              "type": "rootcause"
            },
            {
              "id": "component:versions.patch functionality for updating prompts",
              "keyphrase": "versions.patch functionality for updating prompts",
              "type": "component"
            }
          ]
        },
        "similarity": 318.805127524509
      },
      {
        "metadata": {
          "doc_id": "61",
          "name": "UNIX Symbolic Link (Symlink) Following",
          "source": "sparse",
          "original_content": "The product, when opening a file or directory, does not sufficiently account for when the file is a symbolic link that resolves to a target outside of the intended control sphere. This could allow an attacker to cause the product to operate on unauthorized files.",
          "keyphrase_sources": [
            {
              "id": "version:1.2.2 up to but not including 1.2.25",
              "keyphrase": "1.2.2 up to but not including 1.2.25",
              "type": "version"
            }
          ]
        },
        "similarity": 126.99190498085393
      },
      {
        "metadata": {
          "doc_id": "347",
          "name": "Improper Verification of Cryptographic Signature",
          "source": "sparse",
          "original_content": "The product does not verify, or incorrectly verifies, the cryptographic signature for data.",
          "keyphrase_sources": [
            {
              "id": "version:1.2.2 up to but not including 1.2.25",
              "keyphrase": "1.2.2 up to but not including 1.2.25",
              "type": "version"
            }
          ]
        },
        "similarity": 126.3724041495015
      },
      {
        "metadata": {
          "doc_id": "620",
          "name": "Unverified Password Change",
          "source": "sparse",
          "original_content": "When setting a new password for a user, the product does not require knowledge of the original password, or using another form of authentication.",
          "keyphrase_sources": [
            {
              "id": "impact:update prompt details",
              "keyphrase": "update prompt details",
              "type": "impact"
            }
          ]
        },
        "similarity": 107.87025939166631
      },
      {
        "metadata": {
          "doc_id": "1336",
          "name": "Improper Neutralization of Special Elements Used in a Template Engine",
          "source": "sparse",
          "original_content": "The product uses a template engine to insert or process externally-influenced input, but it does not neutralize or incorrectly neutralizes special elements or syntax that can be interpreted as template expressions or other code directives when processed by the engine.",
          "keyphrase_sources": [
            {
              "id": "impact:update prompt details",
              "keyphrase": "update prompt details",
              "type": "impact"
            }
          ]
        },
        "similarity": 104.35543489167387
      },
      {
        "metadata": {
          "doc_id": "306",
          "name": "Missing Authentication for Critical Function",
          "source": "sparse",
          "original_content": "The product does not perform any authentication for functionality that requires a provable user identity or consumes a significant amount of resources.",
          "keyphrase_sources": [
            {
              "id": "attacker:unauthorized users",
              "keyphrase": "unauthorized users",
              "type": "attacker"
            },
            {
              "id": "component:versions.patch functionality for updating prompts",
              "keyphrase": "versions.patch functionality for updating prompts",
              "type": "component"
            }
          ]
        },
        "similarity": 103.26816379904162
      }
    ],
    "enhanced_query": "# Vulnerability Description\n\n    An **improper access control** vulnerability exists in the lunary-ai/lunary repository, specifically within the versions.patch functionality for updating prompts. Affected versions include 1.2.2 up to but not including 1.2.25. The vulnerability allows unauthorized users to update prompt details due to **insufficient access control** checks. This issue was addressed and fixed in version 1.2.25.\n\n    # Keyphrase-Specific CWE Analysis\n    This vulnerability contains multiple keyphrases that may map to different CWEs. \n    Please analyze each keyphrase separately and determine the most appropriate CWE(s) for each.\n\n    ## ROOTCAUSE: 'improper access control'\n\nRelevant CWEs for this ROOTCAUSE:\n\n### 1. CWE-285: Improper Authorization (Score: 344.40)\n\nThe product does not perform or incorrectly performs an authorization check when an actor attempts to access a resource or perform an action....\n\n### 2. CWE-284: Improper Access Control (Score: 339.06)\n\nThe product does not restrict or incorrectly restricts access to a resource from an unauthorized actor....\n\n### 3. CWE-287: Improper Authentication (Score: 327.78)\n\nWhen an actor claims to have a given identity, the product does not prove or insufficiently proves that the claim is correct....\n\n### 4. CWE-863: Incorrect Authorization (Score: 327.14)\n\nThe product performs an authorization check when an actor attempts to access a resource or perform an action, but it does not correctly perform the check....\n\n### 5. CWE-639: Authorization Bypass Through User-Controlled Key (Score: 318.81)\n\nThe system's authorization functionality does not prevent one user from gaining access to another user's data or record by modifying the key value identifying the data....\n\n## ROOTCAUSE: 'insufficient access control'\n\nRelevant CWEs for this ROOTCAUSE:\n\n### 1. CWE-285: Improper Authorization (Score: 344.40)\n\nThe product does not perform or incorrectly performs an authorization check when an actor attempts to access a resource or perform an action....\n\n### 2. CWE-284: Improper Access Control (Score: 339.06)\n\nThe product does not restrict or incorrectly restricts access to a resource from an unauthorized actor....\n\n### 3. CWE-287: Improper Authentication (Score: 327.78)\n\nWhen an actor claims to have a given identity, the product does not prove or insufficiently proves that the claim is correct....\n\n### 4. CWE-863: Incorrect Authorization (Score: 327.14)\n\nThe product performs an authorization check when an actor attempts to access a resource or perform an action, but it does not correctly perform the check....\n\n### 5. CWE-20: Improper Input Validation (Score: 319.32)\n\nThe product receives input or data, but it does\n        not validate or incorrectly validates that the input has the\n        properties that are required to process the data safely and\n        correctly....\n\n## IMPACT: 'update prompt details'\n\nRelevant CWEs for this IMPACT:\n\n### 1. CWE-285: Improper Authorization (Score: 344.40)\n\nThe product does not perform or incorrectly performs an authorization check when an actor attempts to access a resource or perform an action....\n\n### 2. CWE-284: Improper Access Control (Score: 339.06)\n\nThe product does not restrict or incorrectly restricts access to a resource from an unauthorized actor....\n\n### 3. CWE-863: Incorrect Authorization (Score: 327.14)\n\nThe product performs an authorization check when an actor attempts to access a resource or perform an action, but it does not correctly perform the check....\n\n### 4. CWE-620: Unverified Password Change (Score: 107.87)\n\nWhen setting a new password for a user, the product does not require knowledge of the original password, or using another form of authentication....\n\n### 5. CWE-1336: Improper Neutralization of Special Elements Used in a Template Engine (Score: 104.36)\n\nThe product uses a template engine to insert or process externally-influenced input, but it does not neutralize or incorrectly neutralizes special elements or syntax that can be interpreted as template expressions or other code directives when processed by the engine....\n\n## ATTACKER: 'unauthorized users'\n\nRelevant CWEs for this ATTACKER:\n\n### 1. CWE-285: Improper Authorization (Score: 344.40)\n\nThe product does not perform or incorrectly performs an authorization check when an actor attempts to access a resource or perform an action....\n\n### 2. CWE-284: Improper Access Control (Score: 339.06)\n\nThe product does not restrict or incorrectly restricts access to a resource from an unauthorized actor....\n\n### 3. CWE-287: Improper Authentication (Score: 327.78)\n\nWhen an actor claims to have a given identity, the product does not prove or insufficiently proves that the claim is correct....\n\n### 4. CWE-863: Incorrect Authorization (Score: 327.14)\n\nThe product performs an authorization check when an actor attempts to access a resource or perform an action, but it does not correctly perform the check....\n\n### 5. CWE-306: Missing Authentication for Critical Function (Score: 103.27)\n\nThe product does not perform any authentication for functionality that requires a provable user identity or consumes a significant amount of resources....\n\n## PRODUCT: 'lunary-ai/lunary'\n\nRelevant CWEs for this PRODUCT:\n\n### 1. CWE-285: Improper Authorization (Score: 344.40)\n\nThe product does not perform or incorrectly performs an authorization check when an actor attempts to access a resource or perform an action....\n\n### 2. CWE-284: Improper Access Control (Score: 339.06)\n\nThe product does not restrict or incorrectly restricts access to a resource from an unauthorized actor....\n\n### 3. CWE-287: Improper Authentication (Score: 327.78)\n\nWhen an actor claims to have a given identity, the product does not prove or insufficiently proves that the claim is correct....\n\n### 4. CWE-863: Incorrect Authorization (Score: 327.14)\n\nThe product performs an authorization check when an actor attempts to access a resource or perform an action, but it does not correctly perform the check....\n\n### 5. CWE-20: Improper Input Validation (Score: 319.32)\n\nThe product receives input or data, but it does\n        not validate or incorrectly validates that the input has the\n        properties that are required to process the data safely and\n        correctly....\n\n## VERSION: '1.2.2 up to but not including 1.2.25'\n\nRelevant CWEs for this VERSION:\n\n### 1. CWE-285: Improper Authorization (Score: 344.40)\n\nThe product does not perform or incorrectly performs an authorization check when an actor attempts to access a resource or perform an action....\n\n### 2. CWE-284: Improper Access Control (Score: 339.06)\n\nThe product does not restrict or incorrectly restricts access to a resource from an unauthorized actor....\n\n### 3. CWE-863: Incorrect Authorization (Score: 327.14)\n\nThe product performs an authorization check when an actor attempts to access a resource or perform an action, but it does not correctly perform the check....\n\n### 4. CWE-61: UNIX Symbolic Link (Symlink) Following (Score: 126.99)\n\nThe product, when opening a file or directory, does not sufficiently account for when the file is a symbolic link that resolves to a target outside of the intended control sphere. This could allow an attacker to cause the product to operate on unauthorized files....\n\n### 5. CWE-347: Improper Verification of Cryptographic Signature (Score: 126.37)\n\nThe product does not verify, or incorrectly verifies, the cryptographic signature for data....\n\n## COMPONENT: 'versions.patch functionality for updating prompts'\n\nRelevant CWEs for this COMPONENT:\n\n### 1. CWE-285: Improper Authorization (Score: 344.40)\n\nThe product does not perform or incorrectly performs an authorization check when an actor attempts to access a resource or perform an action....\n\n### 2. CWE-287: Improper Authentication (Score: 327.78)\n\nWhen an actor claims to have a given identity, the product does not prove or insufficiently proves that the claim is correct....\n\n### 3. CWE-863: Incorrect Authorization (Score: 327.14)\n\nThe product performs an authorization check when an actor attempts to access a resource or perform an action, but it does not correctly perform the check....\n\n### 4. CWE-639: Authorization Bypass Through User-Controlled Key (Score: 318.81)\n\nThe system's authorization functionality does not prevent one user from gaining access to another user's data or record by modifying the key value identifying the data....\n\n### 5. CWE-306: Missing Authentication for Critical Function (Score: 103.27)\n\nThe product does not perform any authentication for functionality that requires a provable user identity or consumes a significant amount of resources....\n\n\n    # Analysis Instructions\n    1. For each keyphrase, identify the most appropriate CWE(s) that represent the weakness.\n    2. Consider how the different keyphrases might relate to each other in the vulnerability chain.\n    3. Provide a final determination of primary CWE(s) and any secondary CWEs.\n    4. Format your response using the standard analysis template.\n\n    Please analyze how these different weaknesses interact and provide a comprehensive CWE classification.\n    "
  },
  "retrieval_time": 1.6996190547943115
}