{
  "vulnerability_info": "VulnerabilityInfo(cve_id='CVE-2025-24756', description='Cross-Site Request Forgery (CSRF) vulnerability in mgplugin Roi Calculator allows Stored **XSS**. This issue affects Roi Calculator from n/a through 1.0.', key_phrases={'rootcause': '', 'weakness': ['Cross-Site Scripting', 'XSS'], 'impact': '', 'vector': '', 'attacker': '', 'product': 'mgplugin Roi Calculator', 'version': 'n/a through 1.0', 'component': ''}, reference_content='Root cause of vulnerability:\\nThe WordPress Roi Calculator Plugin versions less than or equal to 1.0 are vulnerable to Cross Site Request Forgery (CSRF).\\n\\nWeaknesses/vulnerabilities present:\\nCross Site Request Forgery (CSRF) - specifically, the plugin lacks CSRF protection.\\n\\nImpact of exploitation:\\nA malicious actor can force higher privileged users to execute unwanted actions under their current authentication. The impact varies case by case.\\n\\nAttack vectors:\\nExploitation occurs through Cross-Site Request Forgery attacks.\\n\\nRequired attacker capabilities/position:\\nUnauthenticated attacker.\\n\\nMitigation or fix:\\nUpdate to version 1.1 or later. Patchstack users can enable auto-updates for vulnerable plugins.\\n\\nAdditional details:\\n- CVSS score: 7.1 (Low severity)\\n- OWASP Top 10: A1: Broken Access Control\\n- Plugin: Roi Calculator\\n- Vulnerable versions: <= 1.0\\n- Fixed in: 1.1\\n- Reported by: SOPROBRO on October 9, 2024\\n- Published by Patchstack on January 24, 2025.\\n\\nThe content provides more detail than the placeholder CVE description.', similar_info={'cwe_distribution': {}, 'cwe_consensus': '', 'similarity_stats': {'thresholds': [], 'total_samples_by_threshold': {}, 'top_cwes_by_threshold': {}}}, similarity_summary=SimilarityInsight(consensus_cwe='', top_cwes=[], confidence_levels={}, total_samples=0), analysis='', analysis_with_relationships='', criticism='', resolution='', relevant_cwes=[{'metadata': {'doc_id': '352', 'name': 'Cross-Site Request Forgery (CSRF)', 'source': 'sparse', 'original_content': 'The web application does not, or can not, sufficiently verify whether a well-formed, valid, consistent request was intentionally provided by the user who submitted the request.', 'keyphrase_sources': [{'id': 'weakness:Cross-Site Scripting', 'keyphrase': 'Cross-Site Scripting', 'type': 'weakness'}, {'id': 'weakness:XSS', 'keyphrase': 'XSS', 'type': 'weakness'}, {'id': 'product:mgplugin Roi Calculator', 'keyphrase': 'mgplugin Roi Calculator', 'type': 'product'}, {'id': 'version:n/a through 1.0', 'keyphrase': 'n/a through 1.0', 'type': 'version'}]}, 'similarity': np.float64(268.3345076142385)}, {'metadata': {'doc_id': '79', 'name': \"Improper Neutralization of Input During Web Page Generation ('Cross-site Scripting')\", 'source': 'sparse', 'original_content': 'The product does not neutralize or incorrectly neutralizes user-controllable input before it is placed in output that is used as a web page that is served to other users.', 'keyphrase_sources': [{'id': 'weakness:Cross-Site Scripting', 'keyphrase': 'Cross-Site Scripting', 'type': 'weakness'}, {'id': 'weakness:XSS', 'keyphrase': 'XSS', 'type': 'weakness'}, {'id': 'product:mgplugin Roi Calculator', 'keyphrase': 'mgplugin Roi Calculator', 'type': 'product'}, {'id': 'version:n/a through 1.0', 'keyphrase': 'n/a through 1.0', 'type': 'version'}]}, 'similarity': np.float64(216.80953659753771)}, {'metadata': {'doc_id': '80', 'name': 'Improper Neutralization of Script-Related HTML Tags in a Web Page (Basic XSS)', 'source': 'sparse', 'original_content': 'The product receives input from an upstream component, but it does not neutralize or incorrectly neutralizes special characters such as \"<\", \">\", and \"&\" that could be interpreted as web-scripting elements when they are sent to a downstream component that processes web pages.', 'keyphrase_sources': [{'id': 'weakness:Cross-Site Scripting', 'keyphrase': 'Cross-Site Scripting', 'type': 'weakness'}, {'id': 'weakness:XSS', 'keyphrase': 'XSS', 'type': 'weakness'}]}, 'similarity': np.float64(192.6484504057272)}, {'metadata': {'doc_id': '1004', 'name': \"Sensitive Cookie Without 'HttpOnly' Flag\", 'source': 'sparse', 'original_content': 'The product uses a cookie to store sensitive information, but the cookie is not marked with the HttpOnly flag.', 'keyphrase_sources': [{'id': 'weakness:Cross-Site Scripting', 'keyphrase': 'Cross-Site Scripting', 'type': 'weakness'}, {'id': 'weakness:XSS', 'keyphrase': 'XSS', 'type': 'weakness'}, {'id': 'product:mgplugin Roi Calculator', 'keyphrase': 'mgplugin Roi Calculator', 'type': 'product'}]}, 'similarity': np.float64(187.32576949546464)}, {'metadata': {'doc_id': '116', 'name': 'Improper Encoding or Escaping of Output', 'source': 'sparse', 'original_content': 'The product prepares a structured message for communication with another component, but encoding or escaping of the data is either missing or done incorrectly. As a result, the intended structure of the message is not preserved.', 'keyphrase_sources': [{'id': 'weakness:Cross-Site Scripting', 'keyphrase': 'Cross-Site Scripting', 'type': 'weakness'}, {'id': 'weakness:XSS', 'keyphrase': 'XSS', 'type': 'weakness'}]}, 'similarity': np.float64(183.33681159811476)}, {'metadata': {'doc_id': '434', 'name': 'Unrestricted Upload of File with Dangerous Type', 'source': 'sparse', 'original_content': 'The product allows the upload or transfer of dangerous file types that are automatically processed within its environment.', 'keyphrase_sources': [{'id': 'version:n/a through 1.0', 'keyphrase': 'n/a through 1.0', 'type': 'version'}]}, 'similarity': np.float64(59.24029739324023)}, {'metadata': {'doc_id': '22', 'name': \"Improper Limitation of a Pathname to a Restricted Directory ('Path Traversal')\", 'source': 'sparse', 'original_content': 'The product uses external input to construct a pathname that is intended to identify a file or directory that is located underneath a restricted parent directory, but the product does not properly neutralize special elements within the pathname that can cause the pathname to resolve to a location that is outside of the restricted directory.', 'keyphrase_sources': [{'id': 'version:n/a through 1.0', 'keyphrase': 'n/a through 1.0', 'type': 'version'}]}, 'similarity': np.float64(56.05162128191628)}, {'metadata': {'doc_id': '89', 'name': \"Improper Neutralization of Special Elements used in an SQL Command ('SQL Injection')\", 'source': 'sparse', 'original_content': 'The product constructs all or part of an SQL command using externally-influenced input from an upstream component, but it does not neutralize or incorrectly neutralizes special elements that could modify the intended SQL command when it is sent to a downstream component. Without sufficient removal or quoting of SQL syntax in user-controllable inputs, the generated SQL query can cause those inputs to be interpreted as SQL instead of ordinary user data.', 'keyphrase_sources': [{'id': 'product:mgplugin Roi Calculator', 'keyphrase': 'mgplugin Roi Calculator', 'type': 'product'}, {'id': 'version:n/a through 1.0', 'keyphrase': 'n/a through 1.0', 'type': 'version'}]}, 'similarity': np.float64(42.12558207127824)}, {'metadata': {'doc_id': '918', 'name': 'Server-Side Request Forgery (SSRF)', 'source': 'sparse', 'original_content': 'The web server receives a URL or similar request from an upstream component and retrieves the contents of this URL, but it does not sufficiently ensure that the request is being sent to the expected destination.', 'keyphrase_sources': [{'id': 'product:mgplugin Roi Calculator', 'keyphrase': 'mgplugin Roi Calculator', 'type': 'product'}]}, 'similarity': np.float64(40.87545758027548)}], identified_cwes={'analyzer': [], 'critic_additional': []})",
  "retrieval_results": {
    "has_multiple_keyphrases": true,
    "keyphrase_cwe_sets": {
      "weakness:Cross-Site Scripting": {
        "keyphrase": "Cross-Site Scripting",
        "type": "weakness",
        "cwes": [
          {
            "metadata": {
              "doc_id": "352",
              "name": "Cross-Site Request Forgery (CSRF)",
              "source": "sparse",
              "original_content": "The web application does not, or can not, sufficiently verify whether a well-formed, valid, consistent request was intentionally provided by the user who submitted the request.",
              "keyphrase_sources": [
                {
                  "id": "weakness:Cross-Site Scripting",
                  "keyphrase": "Cross-Site Scripting",
                  "type": "weakness"
                },
                {
                  "id": "weakness:XSS",
                  "keyphrase": "XSS",
                  "type": "weakness"
                },
                {
                  "id": "product:mgplugin Roi Calculator",
                  "keyphrase": "mgplugin Roi Calculator",
                  "type": "product"
                },
                {
                  "id": "version:n/a through 1.0",
                  "keyphrase": "n/a through 1.0",
                  "type": "version"
                }
              ]
            },
            "similarity": 268.3345076142385
          },
          {
            "metadata": {
              "doc_id": "79",
              "name": "Improper Neutralization of Input During Web Page Generation ('Cross-site Scripting')",
              "source": "sparse",
              "original_content": "The product does not neutralize or incorrectly neutralizes user-controllable input before it is placed in output that is used as a web page that is served to other users.",
              "keyphrase_sources": [
                {
                  "id": "weakness:Cross-Site Scripting",
                  "keyphrase": "Cross-Site Scripting",
                  "type": "weakness"
                },
                {
                  "id": "weakness:XSS",
                  "keyphrase": "XSS",
                  "type": "weakness"
                },
                {
                  "id": "product:mgplugin Roi Calculator",
                  "keyphrase": "mgplugin Roi Calculator",
                  "type": "product"
                },
                {
                  "id": "version:n/a through 1.0",
                  "keyphrase": "n/a through 1.0",
                  "type": "version"
                }
              ]
            },
            "similarity": 216.80953659753771
          },
          {
            "metadata": {
              "doc_id": "80",
              "name": "Improper Neutralization of Script-Related HTML Tags in a Web Page (Basic XSS)",
              "source": "sparse",
              "original_content": "The product receives input from an upstream component, but it does not neutralize or incorrectly neutralizes special characters such as \"<\", \">\", and \"&\" that could be interpreted as web-scripting elements when they are sent to a downstream component that processes web pages.",
              "keyphrase_sources": [
                {
                  "id": "weakness:Cross-Site Scripting",
                  "keyphrase": "Cross-Site Scripting",
                  "type": "weakness"
                },
                {
                  "id": "weakness:XSS",
                  "keyphrase": "XSS",
                  "type": "weakness"
                }
              ]
            },
            "similarity": 192.6484504057272
          },
          {
            "metadata": {
              "doc_id": "1004",
              "name": "Sensitive Cookie Without 'HttpOnly' Flag",
              "source": "sparse",
              "original_content": "The product uses a cookie to store sensitive information, but the cookie is not marked with the HttpOnly flag.",
              "keyphrase_sources": [
                {
                  "id": "weakness:Cross-Site Scripting",
                  "keyphrase": "Cross-Site Scripting",
                  "type": "weakness"
                },
                {
                  "id": "weakness:XSS",
                  "keyphrase": "XSS",
                  "type": "weakness"
                },
                {
                  "id": "product:mgplugin Roi Calculator",
                  "keyphrase": "mgplugin Roi Calculator",
                  "type": "product"
                }
              ]
            },
            "similarity": 187.32576949546464
          },
          {
            "metadata": {
              "doc_id": "116",
              "name": "Improper Encoding or Escaping of Output",
              "source": "sparse",
              "original_content": "The product prepares a structured message for communication with another component, but encoding or escaping of the data is either missing or done incorrectly. As a result, the intended structure of the message is not preserved.",
              "keyphrase_sources": [
                {
                  "id": "weakness:Cross-Site Scripting",
                  "keyphrase": "Cross-Site Scripting",
                  "type": "weakness"
                },
                {
                  "id": "weakness:XSS",
                  "keyphrase": "XSS",
                  "type": "weakness"
                }
              ]
            },
            "similarity": 183.33681159811476
          }
        ]
      },
      "weakness:XSS": {
        "keyphrase": "XSS",
        "type": "weakness",
        "cwes": [
          {
            "metadata": {
              "doc_id": "352",
              "name": "Cross-Site Request Forgery (CSRF)",
              "source": "sparse",
              "original_content": "The web application does not, or can not, sufficiently verify whether a well-formed, valid, consistent request was intentionally provided by the user who submitted the request."
            },
            "similarity": 200.3113623381025
          },
          {
            "metadata": {
              "doc_id": "79",
              "name": "Improper Neutralization of Input During Web Page Generation ('Cross-site Scripting')",
              "source": "sparse",
              "original_content": "The product does not neutralize or incorrectly neutralizes user-controllable input before it is placed in output that is used as a web page that is served to other users."
            },
            "similarity": 154.84474524065155
          },
          {
            "metadata": {
              "doc_id": "1004",
              "name": "Sensitive Cookie Without 'HttpOnly' Flag",
              "source": "sparse",
              "original_content": "The product uses a cookie to store sensitive information, but the cookie is not marked with the HttpOnly flag."
            },
            "similarity": 142.77399274931983
          },
          {
            "metadata": {
              "doc_id": "116",
              "name": "Improper Encoding or Escaping of Output",
              "source": "sparse",
              "original_content": "The product prepares a structured message for communication with another component, but encoding or escaping of the data is either missing or done incorrectly. As a result, the intended structure of the message is not preserved."
            },
            "similarity": 136.1665837139543
          },
          {
            "metadata": {
              "doc_id": "80",
              "name": "Improper Neutralization of Script-Related HTML Tags in a Web Page (Basic XSS)",
              "source": "sparse",
              "original_content": "The product receives input from an upstream component, but it does not neutralize or incorrectly neutralizes special characters such as \"<\", \">\", and \"&\" that could be interpreted as web-scripting elements when they are sent to a downstream component that processes web pages."
            },
            "similarity": 135.9699471872489
          }
        ]
      },
      "product:mgplugin Roi Calculator": {
        "keyphrase": "mgplugin Roi Calculator",
        "type": "product",
        "cwes": [
          {
            "metadata": {
              "doc_id": "352",
              "name": "Cross-Site Request Forgery (CSRF)",
              "source": "sparse",
              "original_content": "The web application does not, or can not, sufficiently verify whether a well-formed, valid, consistent request was intentionally provided by the user who submitted the request."
            },
            "similarity": 70.20424163052864
          },
          {
            "metadata": {
              "doc_id": "79",
              "name": "Improper Neutralization of Input During Web Page Generation ('Cross-site Scripting')",
              "source": "sparse",
              "original_content": "The product does not neutralize or incorrectly neutralizes user-controllable input before it is placed in output that is used as a web page that is served to other users."
            },
            "similarity": 44.735326339985924
          },
          {
            "metadata": {
              "doc_id": "89",
              "name": "Improper Neutralization of Special Elements used in an SQL Command ('SQL Injection')",
              "source": "sparse",
              "original_content": "The product constructs all or part of an SQL command using externally-influenced input from an upstream component, but it does not neutralize or incorrectly neutralizes special elements that could modify the intended SQL command when it is sent to a downstream component. Without sufficient removal or quoting of SQL syntax in user-controllable inputs, the generated SQL query can cause those inputs to be interpreted as SQL instead of ordinary user data.",
              "keyphrase_sources": [
                {
                  "id": "product:mgplugin Roi Calculator",
                  "keyphrase": "mgplugin Roi Calculator",
                  "type": "product"
                },
                {
                  "id": "version:n/a through 1.0",
                  "keyphrase": "n/a through 1.0",
                  "type": "version"
                }
              ]
            },
            "similarity": 42.12558207127824
          },
          {
            "metadata": {
              "doc_id": "1004",
              "name": "Sensitive Cookie Without 'HttpOnly' Flag",
              "source": "sparse",
              "original_content": "The product uses a cookie to store sensitive information, but the cookie is not marked with the HttpOnly flag."
            },
            "similarity": 42.12525228595669
          },
          {
            "metadata": {
              "doc_id": "918",
              "name": "Server-Side Request Forgery (SSRF)",
              "source": "sparse",
              "original_content": "The web server receives a URL or similar request from an upstream component and retrieves the contents of this URL, but it does not sufficiently ensure that the request is being sent to the expected destination.",
              "keyphrase_sources": [
                {
                  "id": "product:mgplugin Roi Calculator",
                  "keyphrase": "mgplugin Roi Calculator",
                  "type": "product"
                }
              ]
            },
            "similarity": 40.87545758027548
          }
        ]
      },
      "version:n/a through 1.0": {
        "keyphrase": "n/a through 1.0",
        "type": "version",
        "cwes": [
          {
            "metadata": {
              "doc_id": "352",
              "name": "Cross-Site Request Forgery (CSRF)",
              "source": "sparse",
              "original_content": "The web application does not, or can not, sufficiently verify whether a well-formed, valid, consistent request was intentionally provided by the user who submitted the request."
            },
            "similarity": 75.74942746122366
          },
          {
            "metadata": {
              "doc_id": "434",
              "name": "Unrestricted Upload of File with Dangerous Type",
              "source": "sparse",
              "original_content": "The product allows the upload or transfer of dangerous file types that are automatically processed within its environment.",
              "keyphrase_sources": [
                {
                  "id": "version:n/a through 1.0",
                  "keyphrase": "n/a through 1.0",
                  "type": "version"
                }
              ]
            },
            "similarity": 59.24029739324023
          },
          {
            "metadata": {
              "doc_id": "79",
              "name": "Improper Neutralization of Input During Web Page Generation ('Cross-site Scripting')",
              "source": "sparse",
              "original_content": "The product does not neutralize or incorrectly neutralizes user-controllable input before it is placed in output that is used as a web page that is served to other users."
            },
            "similarity": 57.387277699342725
          },
          {
            "metadata": {
              "doc_id": "22",
              "name": "Improper Limitation of a Pathname to a Restricted Directory ('Path Traversal')",
              "source": "sparse",
              "original_content": "The product uses external input to construct a pathname that is intended to identify a file or directory that is located underneath a restricted parent directory, but the product does not properly neutralize special elements within the pathname that can cause the pathname to resolve to a location that is outside of the restricted directory.",
              "keyphrase_sources": [
                {
                  "id": "version:n/a through 1.0",
                  "keyphrase": "n/a through 1.0",
                  "type": "version"
                }
              ]
            },
            "similarity": 56.05162128191628
          },
          {
            "metadata": {
              "doc_id": "89",
              "name": "Improper Neutralization of Special Elements used in an SQL Command ('SQL Injection')",
              "source": "sparse",
              "original_content": "The product constructs all or part of an SQL command using externally-influenced input from an upstream component, but it does not neutralize or incorrectly neutralizes special elements that could modify the intended SQL command when it is sent to a downstream component. Without sufficient removal or quoting of SQL syntax in user-controllable inputs, the generated SQL query can cause those inputs to be interpreted as SQL instead of ordinary user data."
            },
            "similarity": 55.46197438436359
          }
        ]
      }
    },
    "keyphrase_mapping": {
      "352": [
        {
          "id": "weakness:Cross-Site Scripting",
          "keyphrase": "Cross-Site Scripting",
          "type": "weakness"
        },
        {
          "id": "weakness:XSS",
          "keyphrase": "XSS",
          "type": "weakness"
        },
        {
          "id": "product:mgplugin Roi Calculator",
          "keyphrase": "mgplugin Roi Calculator",
          "type": "product"
        },
        {
          "id": "version:n/a through 1.0",
          "keyphrase": "n/a through 1.0",
          "type": "version"
        }
      ],
      "79": [
        {
          "id": "weakness:Cross-Site Scripting",
          "keyphrase": "Cross-Site Scripting",
          "type": "weakness"
        },
        {
          "id": "weakness:XSS",
          "keyphrase": "XSS",
          "type": "weakness"
        },
        {
          "id": "product:mgplugin Roi Calculator",
          "keyphrase": "mgplugin Roi Calculator",
          "type": "product"
        },
        {
          "id": "version:n/a through 1.0",
          "keyphrase": "n/a through 1.0",
          "type": "version"
        }
      ],
      "80": [
        {
          "id": "weakness:Cross-Site Scripting",
          "keyphrase": "Cross-Site Scripting",
          "type": "weakness"
        },
        {
          "id": "weakness:XSS",
          "keyphrase": "XSS",
          "type": "weakness"
        }
      ],
      "1004": [
        {
          "id": "weakness:Cross-Site Scripting",
          "keyphrase": "Cross-Site Scripting",
          "type": "weakness"
        },
        {
          "id": "weakness:XSS",
          "keyphrase": "XSS",
          "type": "weakness"
        },
        {
          "id": "product:mgplugin Roi Calculator",
          "keyphrase": "mgplugin Roi Calculator",
          "type": "product"
        }
      ],
      "116": [
        {
          "id": "weakness:Cross-Site Scripting",
          "keyphrase": "Cross-Site Scripting",
          "type": "weakness"
        },
        {
          "id": "weakness:XSS",
          "keyphrase": "XSS",
          "type": "weakness"
        }
      ],
      "89": [
        {
          "id": "product:mgplugin Roi Calculator",
          "keyphrase": "mgplugin Roi Calculator",
          "type": "product"
        },
        {
          "id": "version:n/a through 1.0",
          "keyphrase": "n/a through 1.0",
          "type": "version"
        }
      ],
      "918": [
        {
          "id": "product:mgplugin Roi Calculator",
          "keyphrase": "mgplugin Roi Calculator",
          "type": "product"
        }
      ],
      "434": [
        {
          "id": "version:n/a through 1.0",
          "keyphrase": "n/a through 1.0",
          "type": "version"
        }
      ],
      "22": [
        {
          "id": "version:n/a through 1.0",
          "keyphrase": "n/a through 1.0",
          "type": "version"
        }
      ]
    },
    "relevant_cwes": [
      {
        "metadata": {
          "doc_id": "352",
          "name": "Cross-Site Request Forgery (CSRF)",
          "source": "sparse",
          "original_content": "The web application does not, or can not, sufficiently verify whether a well-formed, valid, consistent request was intentionally provided by the user who submitted the request.",
          "keyphrase_sources": [
            {
              "id": "weakness:Cross-Site Scripting",
              "keyphrase": "Cross-Site Scripting",
              "type": "weakness"
            },
            {
              "id": "weakness:XSS",
              "keyphrase": "XSS",
              "type": "weakness"
            },
            {
              "id": "product:mgplugin Roi Calculator",
              "keyphrase": "mgplugin Roi Calculator",
              "type": "product"
            },
            {
              "id": "version:n/a through 1.0",
              "keyphrase": "n/a through 1.0",
              "type": "version"
            }
          ]
        },
        "similarity": 268.3345076142385
      },
      {
        "metadata": {
          "doc_id": "79",
          "name": "Improper Neutralization of Input During Web Page Generation ('Cross-site Scripting')",
          "source": "sparse",
          "original_content": "The product does not neutralize or incorrectly neutralizes user-controllable input before it is placed in output that is used as a web page that is served to other users.",
          "keyphrase_sources": [
            {
              "id": "weakness:Cross-Site Scripting",
              "keyphrase": "Cross-Site Scripting",
              "type": "weakness"
            },
            {
              "id": "weakness:XSS",
              "keyphrase": "XSS",
              "type": "weakness"
            },
            {
              "id": "product:mgplugin Roi Calculator",
              "keyphrase": "mgplugin Roi Calculator",
              "type": "product"
            },
            {
              "id": "version:n/a through 1.0",
              "keyphrase": "n/a through 1.0",
              "type": "version"
            }
          ]
        },
        "similarity": 216.80953659753771
      },
      {
        "metadata": {
          "doc_id": "80",
          "name": "Improper Neutralization of Script-Related HTML Tags in a Web Page (Basic XSS)",
          "source": "sparse",
          "original_content": "The product receives input from an upstream component, but it does not neutralize or incorrectly neutralizes special characters such as \"<\", \">\", and \"&\" that could be interpreted as web-scripting elements when they are sent to a downstream component that processes web pages.",
          "keyphrase_sources": [
            {
              "id": "weakness:Cross-Site Scripting",
              "keyphrase": "Cross-Site Scripting",
              "type": "weakness"
            },
            {
              "id": "weakness:XSS",
              "keyphrase": "XSS",
              "type": "weakness"
            }
          ]
        },
        "similarity": 192.6484504057272
      },
      {
        "metadata": {
          "doc_id": "1004",
          "name": "Sensitive Cookie Without 'HttpOnly' Flag",
          "source": "sparse",
          "original_content": "The product uses a cookie to store sensitive information, but the cookie is not marked with the HttpOnly flag.",
          "keyphrase_sources": [
            {
              "id": "weakness:Cross-Site Scripting",
              "keyphrase": "Cross-Site Scripting",
              "type": "weakness"
            },
            {
              "id": "weakness:XSS",
              "keyphrase": "XSS",
              "type": "weakness"
            },
            {
              "id": "product:mgplugin Roi Calculator",
              "keyphrase": "mgplugin Roi Calculator",
              "type": "product"
            }
          ]
        },
        "similarity": 187.32576949546464
      },
      {
        "metadata": {
          "doc_id": "116",
          "name": "Improper Encoding or Escaping of Output",
          "source": "sparse",
          "original_content": "The product prepares a structured message for communication with another component, but encoding or escaping of the data is either missing or done incorrectly. As a result, the intended structure of the message is not preserved.",
          "keyphrase_sources": [
            {
              "id": "weakness:Cross-Site Scripting",
              "keyphrase": "Cross-Site Scripting",
              "type": "weakness"
            },
            {
              "id": "weakness:XSS",
              "keyphrase": "XSS",
              "type": "weakness"
            }
          ]
        },
        "similarity": 183.33681159811476
      },
      {
        "metadata": {
          "doc_id": "434",
          "name": "Unrestricted Upload of File with Dangerous Type",
          "source": "sparse",
          "original_content": "The product allows the upload or transfer of dangerous file types that are automatically processed within its environment.",
          "keyphrase_sources": [
            {
              "id": "version:n/a through 1.0",
              "keyphrase": "n/a through 1.0",
              "type": "version"
            }
          ]
        },
        "similarity": 59.24029739324023
      },
      {
        "metadata": {
          "doc_id": "22",
          "name": "Improper Limitation of a Pathname to a Restricted Directory ('Path Traversal')",
          "source": "sparse",
          "original_content": "The product uses external input to construct a pathname that is intended to identify a file or directory that is located underneath a restricted parent directory, but the product does not properly neutralize special elements within the pathname that can cause the pathname to resolve to a location that is outside of the restricted directory.",
          "keyphrase_sources": [
            {
              "id": "version:n/a through 1.0",
              "keyphrase": "n/a through 1.0",
              "type": "version"
            }
          ]
        },
        "similarity": 56.05162128191628
      },
      {
        "metadata": {
          "doc_id": "89",
          "name": "Improper Neutralization of Special Elements used in an SQL Command ('SQL Injection')",
          "source": "sparse",
          "original_content": "The product constructs all or part of an SQL command using externally-influenced input from an upstream component, but it does not neutralize or incorrectly neutralizes special elements that could modify the intended SQL command when it is sent to a downstream component. Without sufficient removal or quoting of SQL syntax in user-controllable inputs, the generated SQL query can cause those inputs to be interpreted as SQL instead of ordinary user data.",
          "keyphrase_sources": [
            {
              "id": "product:mgplugin Roi Calculator",
              "keyphrase": "mgplugin Roi Calculator",
              "type": "product"
            },
            {
              "id": "version:n/a through 1.0",
              "keyphrase": "n/a through 1.0",
              "type": "version"
            }
          ]
        },
        "similarity": 42.12558207127824
      },
      {
        "metadata": {
          "doc_id": "918",
          "name": "Server-Side Request Forgery (SSRF)",
          "source": "sparse",
          "original_content": "The web server receives a URL or similar request from an upstream component and retrieves the contents of this URL, but it does not sufficiently ensure that the request is being sent to the expected destination.",
          "keyphrase_sources": [
            {
              "id": "product:mgplugin Roi Calculator",
              "keyphrase": "mgplugin Roi Calculator",
              "type": "product"
            }
          ]
        },
        "similarity": 40.87545758027548
      }
    ],
    "enhanced_query": "# Vulnerability Description\n\n    Cross-Site Request Forgery (CSRF) vulnerability in mgplugin Roi Calculator allows Stored **XSS**. This issue affects Roi Calculator from n/a through 1.0.\n\n    # Keyphrase-Specific CWE Analysis\n    This vulnerability contains multiple keyphrases that may map to different CWEs. \n    Please analyze each keyphrase separately and determine the most appropriate CWE(s) for each.\n\n    ## WEAKNESS: 'Cross-Site Scripting'\n\nRelevant CWEs for this WEAKNESS:\n\n### 1. CWE-352: Cross-Site Request Forgery (CSRF) (Score: 268.33)\n\nThe web application does not, or can not, sufficiently verify whether a well-formed, valid, consistent request was intentionally provided by the user who submitted the request....\n\n### 2. CWE-79: Improper Neutralization of Input During Web Page Generation ('Cross-site Scripting') (Score: 216.81)\n\nThe product does not neutralize or incorrectly neutralizes user-controllable input before it is placed in output that is used as a web page that is served to other users....\n\n### 3. CWE-80: Improper Neutralization of Script-Related HTML Tags in a Web Page (Basic XSS) (Score: 192.65)\n\nThe product receives input from an upstream component, but it does not neutralize or incorrectly neutralizes special characters such as \"<\", \">\", and \"&\" that could be interpreted as web-scripting elements when they are sent to a downstream component that processes web pages....\n\n### 4. CWE-1004: Sensitive Cookie Without 'HttpOnly' Flag (Score: 187.33)\n\nThe product uses a cookie to store sensitive information, but the cookie is not marked with the HttpOnly flag....\n\n### 5. CWE-116: Improper Encoding or Escaping of Output (Score: 183.34)\n\nThe product prepares a structured message for communication with another component, but encoding or escaping of the data is either missing or done incorrectly. As a result, the intended structure of the message is not preserved....\n\n## WEAKNESS: 'XSS'\n\nRelevant CWEs for this WEAKNESS:\n\n### 1. CWE-352: Cross-Site Request Forgery (CSRF) (Score: 268.33)\n\nThe web application does not, or can not, sufficiently verify whether a well-formed, valid, consistent request was intentionally provided by the user who submitted the request....\n\n### 2. CWE-79: Improper Neutralization of Input During Web Page Generation ('Cross-site Scripting') (Score: 216.81)\n\nThe product does not neutralize or incorrectly neutralizes user-controllable input before it is placed in output that is used as a web page that is served to other users....\n\n### 3. CWE-80: Improper Neutralization of Script-Related HTML Tags in a Web Page (Basic XSS) (Score: 192.65)\n\nThe product receives input from an upstream component, but it does not neutralize or incorrectly neutralizes special characters such as \"<\", \">\", and \"&\" that could be interpreted as web-scripting elements when they are sent to a downstream component that processes web pages....\n\n### 4. CWE-1004: Sensitive Cookie Without 'HttpOnly' Flag (Score: 187.33)\n\nThe product uses a cookie to store sensitive information, but the cookie is not marked with the HttpOnly flag....\n\n### 5. CWE-116: Improper Encoding or Escaping of Output (Score: 183.34)\n\nThe product prepares a structured message for communication with another component, but encoding or escaping of the data is either missing or done incorrectly. As a result, the intended structure of the message is not preserved....\n\n## PRODUCT: 'mgplugin Roi Calculator'\n\nRelevant CWEs for this PRODUCT:\n\n### 1. CWE-352: Cross-Site Request Forgery (CSRF) (Score: 268.33)\n\nThe web application does not, or can not, sufficiently verify whether a well-formed, valid, consistent request was intentionally provided by the user who submitted the request....\n\n### 2. CWE-79: Improper Neutralization of Input During Web Page Generation ('Cross-site Scripting') (Score: 216.81)\n\nThe product does not neutralize or incorrectly neutralizes user-controllable input before it is placed in output that is used as a web page that is served to other users....\n\n### 3. CWE-1004: Sensitive Cookie Without 'HttpOnly' Flag (Score: 187.33)\n\nThe product uses a cookie to store sensitive information, but the cookie is not marked with the HttpOnly flag....\n\n### 4. CWE-89: Improper Neutralization of Special Elements used in an SQL Command ('SQL Injection') (Score: 42.13)\n\nThe product constructs all or part of an SQL command using externally-influenced input from an upstream component, but it does not neutralize or incorrectly neutralizes special elements that could modify the intended SQL command when it is sent to a downstream component. Without sufficient removal o...\n\n### 5. CWE-918: Server-Side Request Forgery (SSRF) (Score: 40.88)\n\nThe web server receives a URL or similar request from an upstream component and retrieves the contents of this URL, but it does not sufficiently ensure that the request is being sent to the expected destination....\n\n## VERSION: 'n/a through 1.0'\n\nRelevant CWEs for this VERSION:\n\n### 1. CWE-352: Cross-Site Request Forgery (CSRF) (Score: 268.33)\n\nThe web application does not, or can not, sufficiently verify whether a well-formed, valid, consistent request was intentionally provided by the user who submitted the request....\n\n### 2. CWE-79: Improper Neutralization of Input During Web Page Generation ('Cross-site Scripting') (Score: 216.81)\n\nThe product does not neutralize or incorrectly neutralizes user-controllable input before it is placed in output that is used as a web page that is served to other users....\n\n### 3. CWE-434: Unrestricted Upload of File with Dangerous Type (Score: 59.24)\n\nThe product allows the upload or transfer of dangerous file types that are automatically processed within its environment....\n\n### 4. CWE-22: Improper Limitation of a Pathname to a Restricted Directory ('Path Traversal') (Score: 56.05)\n\nThe product uses external input to construct a pathname that is intended to identify a file or directory that is located underneath a restricted parent directory, but the product does not properly neutralize special elements within the pathname that can cause the pathname to resolve to a location th...\n\n### 5. CWE-89: Improper Neutralization of Special Elements used in an SQL Command ('SQL Injection') (Score: 42.13)\n\nThe product constructs all or part of an SQL command using externally-influenced input from an upstream component, but it does not neutralize or incorrectly neutralizes special elements that could modify the intended SQL command when it is sent to a downstream component. Without sufficient removal o...\n\n\n    # Analysis Instructions\n    1. For each keyphrase, identify the most appropriate CWE(s) that represent the weakness.\n    2. Consider how the different keyphrases might relate to each other in the vulnerability chain.\n    3. Provide a final determination of primary CWE(s) and any secondary CWEs.\n    4. Format your response using the standard analysis template.\n\n    Please analyze how these different weaknesses interact and provide a comprehensive CWE classification.\n    "
  },
  "retrieval_time": 1.0561766624450684
}