{
  "cve_id": "CVE-2024-52510",
  "description": "The Nextcloud Desktop Client is a tool to synchronize files from Nextcloud Server with your computer. The Desktop client did not stop with an error but allowed **by-passing the signature validation**, if a manipulated server sends an empty initial signature. It is recommended that the Nextcloud Desktop client is upgraded to 3.14.2 or later.",
  "key_phrases": {
    "rootcause": "by-passing the signature validation",
    "weakness": "",
    "impact": "",
    "vector": "manipulated server sends an empty initial signature",
    "attacker": "",
    "product": "Nextcloud Desktop Client",
    "version": "before 3.14.2",
    "component": ""
  },
  "reference_content": "Based on the provided information, here's an analysis of CVE-2024-52510:\n\n**Root Cause of Vulnerability:**\nThe Nextcloud desktop client did not properly handle an empty initial end-to-end encryption signature from the server, allowing it to bypass signature validation.\n\n**Weaknesses/Vulnerabilities Present:**\n- Improper Input Validation: The client failed to check if the received signature was empty before attempting to process it.\n- Logic Error: The client proceeded with metadata setup even with an empty signature, potentially leading to data corruption or unauthorized access to encrypted data.\n- Vulnerability to man-in-the-middle (MITM): The client did not enforce signature validation for the encrypted data sent by the server.\n\n**Impact of Exploitation:**\n- Bypassing signature validation for end-to-end encrypted data.\n- Potential for the attacker to compromise the confidentiality and integrity of encrypted data by sending modified encrypted data with an empty signature.\n\n**Attack Vectors:**\n- Network-based attack, where a malicious server can send an empty initial end-to-end encryption signature to the Nextcloud desktop client.\n\n**Required Attacker Capabilities/Position:**\n- The attacker needs to be able to manipulate the server response to the Nextcloud desktop client, which could involve a compromised server or a man-in-the-middle attack.\n- The attacker needs to have high privileges on the server to control the data and signatures sent to the client.\n- The user is required to interact with the client for the exploitation to take place.\n\n**Additional Details:**\n\n- The vulnerability was fixed in Nextcloud Desktop client version 3.14.2.\n- The fix includes checks for empty signatures in `discoveryphase.cpp` and `foldermetadata.cpp`. If the signature is empty, the client reports an error and does not proceed with the setup.\n- A new test case (`testFolderMetadataWithEmptySignatureDecryptFails`) was added to ensure the fix is effective.\n- The vulnerability is classified as having a \"Moderate\" severity.\n\n**CVSS Vector:**\nCVSS:3.1/AV:N/AC:H/PR:H/UI:R/S:U/C:H/I:N/A:N\n- AV:N (Network)\n- AC:H (High)\n- PR:H (High)\n- UI:R (Required)\n- S:U (Unchanged)\n- C:H (High)\n- I:N (None)\n- A:N (None)",
  "similar_info": {
    "cwe_distribution": {},
    "cwe_consensus": "",
    "similarity_stats": {
      "thresholds": [],
      "total_samples_by_threshold": {},
      "top_cwes_by_threshold": {}
    }
  },
  "similarity_summary": {
    "consensus_cwe": "",
    "top_cwes": [],
    "confidence_levels": {},
    "total_samples": 0
  },
  "analysis": "# Summary\n\n| CWE ID   | CWE Name                                                                                      | Confidence | CWE Abstraction Level | CWE Vulnerability Mapping Label | CWE-Vulnerability Mapping Notes |\n| :-------- | :-------------------------------------------------------------------------------------------- | :--------- | :---------------------- | :------------------------------ | :------------------------------ |\n| CWE-347   | Improper Verification of Cryptographic Signature                                            | 0.95      | Base                    | Primary                         | Allowed                         |\n| CWE-295   | Improper Certificate Validation                                                               | 0.75      | Base                    | Secondary                       | Allowed                         |\n\n## Evidence and Confidence\n\n*   **Confidence Score:** 0.85\n*   **Evidence Strength:** HIGH\n\n## Relationship Analysis\n\nThe primary CWE identified is CWE-347 [Improper Verification of Cryptographic Signature], which is a **Base** level CWE. The secondary CWE identified is CWE-295 [Improper Certificate Validation], which is also a **Base** level CWE. Both CWEs are related to cryptographic issues. There are no direct parent-child relationships between them, but they share a peer relationship in the context of security vulnerabilities related to trust and verification. The abstraction levels influenced the selection by focusing on the root cause of the vulnerability rather than a broader class.\n\n```mermaid\ngraph TD\n    cwe347[\"CWE-347: Improper Verification of Cryptographic Signature\"]\n    cwe295[\"CWE-295: Improper Certificate Validation\"]\n    \n    cwe347 -- PEER OF --> cwe295\n    \n    classDef primary fill:#f96,stroke:#333,stroke-width:2px\n    classDef secondary fill:#69f,stroke:#333\n    class cwe347 primary\n    class cwe295 secondary\n```\n\n## Vulnerability Chain\n\nThe vulnerability chain starts with the Nextcloud Desktop Client's failure to properly validate the signature, specifically the handling of an empty initial signature from a manipulated server. This **improper verification** (CWE-347) leads to a bypass of signature validation, potentially resulting in unauthorized access to encrypted data. The chain can be summarized as:\n\n1.  **Root Cause:** CWE-347 [Improper Verification of Cryptographic Signature] - The client **does not properly** verify the cryptographic signature.\n2.  **Impact:** Bypassing signature validation, leading to the potential compromise of data confidentiality and integrity.\n\n## Summary of Analysis\n\nThe initial analysis focused on the **by-passing of the signature validation** due to the client not stopping with an error when receiving an empty initial signature. This aligns strongly with CWE-347 [Improper Verification of Cryptographic Signature], as the root cause is the **improper handling** of cryptographic signatures. The \"CVE Reference Links Content Summary\" further supports this, stating that the client \"failed to check if the received signature was empty before attempting to process it.\" The relationship analysis highlights the connection between signature verification and certificate validation, making CWE-295 [Improper Certificate Validation] a relevant secondary consideration. The selected CWEs are at the optimal level of specificity, as they directly address the weakness in the cryptographic signature verification process. The decision is primarily based on the provided evidence, with high confidence.\nCWE-99 [Improper Control of Resource Identifiers ('Resource Injection')], CWE-427 [Uncontrolled Search Path Element], CWE-923 [Improper Restriction of Communication Channel to Intended Endpoints], CWE-209 [Generation of Error Message Containing Sensitive Information], CWE-789 [Memory Allocation with Excessive Size Value], CWE-1390 [Weak Authentication], CWE-603 [Use of Client-Side Authentication], and CWE-322 [Key Exchange without Entity Authentication] were considered but deemed less relevant as they do not directly address the core issue of **improper signature validation**.\n# Enhanced Context (25 CWEs)\nThe following CWEs were identified as potentially relevant to this vulnerability:\n\n## CWE-295: Improper Certificate Validation\n**Abstraction Level**: Base\n**Similarity Score**: 0.72\n**Source**: dense\n\n**Description**:\nThe product does not validate, or incorrectly validates, a certificate.\n\n**Mapping Guidance**:\n- Usage: Allowed\n- Rationale: This CWE entry is at the Base level of abstraction, which is a preferred level of abstraction for mapping to the root causes of vulnerabilities.\n\n\n\n## CWE-347: Improper Verification of Cryptographic Signature\n**Abstraction Level**: Base\n**Similarity Score**: 0.70\n**Source**: dense\n\n**Description**:\nThe product does not verify, or incorrectly verifies, the cryptographic signature for data.\n\n**Mapping Guidance**:\n- Usage: Allowed\n- Rationale: This CWE entry is at the Base level of abstraction, which is a preferred level of abstraction for mapping to the root causes of vulnerabilities.\n\n\n\n## CWE-209: Generation of Error Message Containing Sensitive Information\n**Abstraction Level**: Base\n**Similarity Score**: 0.70\n**Source**: dense\n\n**Description**:\nThe product generates an error message that includes sensitive information about its environment, users, or associated data.\n\n**Mapping Guidance**:\n- Usage: Allowed\n- Rationale: This CWE entry is at the Base level of abstraction, which is a preferred level of abstraction for mapping to the root causes of vulnerabilities.\n\n\n\n## CWE-1391: Use of Weak Credentials\n**Abstraction Level**: Class\n**Similarity Score**: 0.70\n**Source**: dense\n\n**Description**:\nThe product uses weak credentials (such as a default key or hard-coded password) that can be calculated, derived, reused, or guessed by an attacker.\n\n**Mapping Guidance**:\n- Usage: Allowed-with-Review\n- Rationale: This CWE entry is a Class and might have Base-level children that would be more appropriate\n\n\n\n## CWE-345: Insufficient Verification of Data Authenticity\n**Abstraction Level**: Class\n**Similarity Score**: 0.70\n**Source**: dense\n\n**Description**:\nThe product does not sufficiently verify the origin or authenticity of data, in a way that causes it to accept invalid data.\n\n**Mapping Guidance**:\n- Usage: Discouraged\n- Rationale: This CWE entry is a level-1 Class (i.e., a child of a Pillar). It might have lower-level children that would be more appropriate\n\n\n\n## CWE-93: Improper Neutralization of CRLF Sequences ('CRLF Injection')\n**Abstraction Level**: Base\n**Similarity Score**: 0.70\n**Source**: dense\n\n**Description**:\nThe product uses CRLF (carriage return line feeds) as a special element, e.g. to separate lines or records, but it does not neutralize or incorrectly neutralizes CRLF sequences from inputs.\n\n**Mapping Guidance**:\n- Usage: Allowed\n- Rationale: This CWE entry is at the Base level of abstraction, which is a preferred level of abstraction for mapping to the root causes of vulnerabilities.\n\n\n\n## CWE-459: Incomplete Cleanup\n**Abstraction Level**: Base\n**Similarity Score**: 0.69\n**Source**: dense\n\n**Description**:\nThe product does not properly \"clean up\" and remove temporary or supporting resources after they have been used.\n\n**Mapping Guidance**:\n- Usage: Allowed\n- Rationale: This CWE entry is at the Base level of abstraction, which is a preferred level of abstraction for mapping to the root causes of vulnerabilities.\n\n\n\n## CWE-303: Incorrect Implementation of Authentication Algorithm\n**Abstraction Level**: Base\n**Similarity Score**: 0.69\n**Source**: dense\n\n**Description**:\nThe requirements for the product dictate the use of an established authentication algorithm, but the implementation of the algorithm is incorrect.\n\n**Mapping Guidance**:\n- Usage: Allowed\n- Rationale: This CWE entry is at the Base level of abstraction, which is a preferred level of abstraction for mapping to the root causes of vulnerabilities.\n\n\n\n## CWE-203: Observable Discrepancy\n**Abstraction Level**: Base\n**Similarity Score**: 0.69\n**Source**: dense\n\n**Description**:\nThe product behaves differently or sends different responses under different circumstances in a way that is observable to an unauthorized actor, which exposes security-relevant information about the state of the product, such as whether a particular operation was successful or not.\n\n**Mapping Guidance**:\n- Usage: Allowed\n- Rationale: This CWE entry is at the Base level of abstraction, which is a preferred level of abstraction for mapping to the root causes of vulnerabilities.\n\n\n\n## CWE-288: Authentication Bypass Using an Alternate Path or Channel\n**Abstraction Level**: Base\n**Similarity Score**: 0.68\n**Source**: dense\n\n**Description**:\nThe product requires authentication, but the product has an alternate path or channel that does not require authentication.\n\n**Mapping Guidance**:\n- Usage: Allowed\n- Rationale: This CWE entry is at the Base level of abstraction, which is a preferred level of abstraction for mapping to the root causes of vulnerabilities.\n\n\n\n## CWE-347: Improper Verification of Cryptographic Signature\n**Abstraction Level**: Base\n**Similarity Score**: 1161.26\n**Source**: sparse\n\n**Description**:\nThe product does not verify, or incorrectly verifies, the cryptographic signature for data.\n\n**Mapping Guidance**:\n- Usage: Allowed\n- Rationale: This CWE entry is at the Base level of abstraction, which is a preferred level of abstraction for mapping to the root causes of vulnerabilities.\n\n\n\n## CWE-295: Improper",
  "analysis_with_relationships": "# Summary\n\n| CWE ID   | CWE Name                                                                                      | Confidence | CWE Abstraction Level | CWE Vulnerability Mapping Label | CWE-Vulnerability Mapping Notes |\n| :-------- | :-------------------------------------------------------------------------------------------- | :--------- | :---------------------- | :------------------------------ | :------------------------------ |\n| CWE-347   | Improper Verification of Cryptographic Signature                                            | 0.95      | Base                    | Primary                         | Allowed                         |\n| CWE-295   | Improper Certificate Validation                                                               | 0.75      | Base                    | Secondary                       | Allowed                         |\n\n## Evidence and Confidence\n\n*   **Confidence Score:** 0.85\n*   **Evidence Strength:** HIGH\n\n## Relationship Analysis\n\nThe primary CWE identified is CWE-347 [Improper Verification of Cryptographic Signature], which is a **Base** level CWE. The secondary CWE identified is CWE-295 [Improper Certificate Validation], which is also a **Base** level CWE. Both CWEs are related to cryptographic issues. There are no direct parent-child relationships between them, but they share a peer relationship in the context of security vulnerabilities related to trust and verification. The abstraction levels influenced the selection by focusing on the root cause of the vulnerability rather than a broader class.\n\n```mermaid\ngraph TD\n    cwe347[\"CWE-347: Improper Verification of Cryptographic Signature\"]\n    cwe295[\"CWE-295: Improper Certificate Validation\"]\n    \n    cwe347 -- PEER OF --> cwe295\n    \n    classDef primary fill:#f96,stroke:#333,stroke-width:2px\n    classDef secondary fill:#69f,stroke:#333\n    class cwe347 primary\n    class cwe295 secondary\n```\n\n## Vulnerability Chain\n\nThe vulnerability chain starts with the Nextcloud Desktop Client's failure to properly validate the signature, specifically the handling of an empty initial signature from a manipulated server. This **improper verification** (CWE-347) leads to a bypass of signature validation, potentially resulting in unauthorized access to encrypted data. The chain can be summarized as:\n\n1.  **Root Cause:** CWE-347 [Improper Verification of Cryptographic Signature] - The client **does not properly** verify the cryptographic signature.\n2.  **Impact:** Bypassing signature validation, leading to the potential compromise of data confidentiality and integrity.\n\n## Summary of Analysis\n\nThe initial analysis focused on the **by-passing of the signature validation** due to the client not stopping with an error when receiving an empty initial signature. This aligns strongly with CWE-347 [Improper Verification of Cryptographic Signature], as the root cause is the **improper handling** of cryptographic signatures. The \"CVE Reference Links Content Summary\" further supports this, stating that the client \"failed to check if the received signature was empty before attempting to process it.\" The relationship analysis highlights the connection between signature verification and certificate validation, making CWE-295 [Improper Certificate Validation] a relevant secondary consideration. The selected CWEs are at the optimal level of specificity, as they directly address the weakness in the cryptographic signature verification process. The decision is primarily based on the provided evidence, with high confidence.\nCWE-99 [Improper Control of Resource Identifiers ('Resource Injection')], CWE-427 [Uncontrolled Search Path Element], CWE-923 [Improper Restriction of Communication Channel to Intended Endpoints], CWE-209 [Generation of Error Message Containing Sensitive Information], CWE-789 [Memory Allocation with Excessive Size Value], CWE-1390 [Weak Authentication], CWE-603 [Use of Client-Side Authentication], and CWE-322 [Key Exchange without Entity Authentication] were considered but deemed less relevant as they do not directly address the core issue of **improper signature validation**.\n# Enhanced Context (25 CWEs)\nThe following CWEs were identified as potentially relevant to this vulnerability:\n\n## CWE-295: Improper Certificate Validation\n**Abstraction Level**: Base\n**Similarity Score**: 0.72\n**Source**: dense\n\n**Description**:\nThe product does not validate, or incorrectly validates, a certificate.\n\n**Mapping Guidance**:\n- Usage: Allowed\n- Rationale: This CWE entry is at the Base level of abstraction, which is a preferred level of abstraction for mapping to the root causes of vulnerabilities.\n\n\n\n## CWE-347: Improper Verification of Cryptographic Signature\n**Abstraction Level**: Base\n**Similarity Score**: 0.70\n**Source**: dense\n\n**Description**:\nThe product does not verify, or incorrectly verifies, the cryptographic signature for data.\n\n**Mapping Guidance**:\n- Usage: Allowed\n- Rationale: This CWE entry is at the Base level of abstraction, which is a preferred level of abstraction for mapping to the root causes of vulnerabilities.\n\n\n\n## CWE-209: Generation of Error Message Containing Sensitive Information\n**Abstraction Level**: Base\n**Similarity Score**: 0.70\n**Source**: dense\n\n**Description**:\nThe product generates an error message that includes sensitive information about its environment, users, or associated data.\n\n**Mapping Guidance**:\n- Usage: Allowed\n- Rationale: This CWE entry is at the Base level of abstraction, which is a preferred level of abstraction for mapping to the root causes of vulnerabilities.\n\n\n\n## CWE-1391: Use of Weak Credentials\n**Abstraction Level**: Class\n**Similarity Score**: 0.70\n**Source**: dense\n\n**Description**:\nThe product uses weak credentials (such as a default key or hard-coded password) that can be calculated, derived, reused, or guessed by an attacker.\n\n**Mapping Guidance**:\n- Usage: Allowed-with-Review\n- Rationale: This CWE entry is a Class and might have Base-level children that would be more appropriate\n\n\n\n## CWE-345: Insufficient Verification of Data Authenticity\n**Abstraction Level**: Class\n**Similarity Score**: 0.70\n**Source**: dense\n\n**Description**:\nThe product does not sufficiently verify the origin or authenticity of data, in a way that causes it to accept invalid data.\n\n**Mapping Guidance**:\n- Usage: Discouraged\n- Rationale: This CWE entry is a level-1 Class (i.e., a child of a Pillar). It might have lower-level children that would be more appropriate\n\n\n\n## CWE-93: Improper Neutralization of CRLF Sequences ('CRLF Injection')\n**Abstraction Level**: Base\n**Similarity Score**: 0.70\n**Source**: dense\n\n**Description**:\nThe product uses CRLF (carriage return line feeds) as a special element, e.g. to separate lines or records, but it does not neutralize or incorrectly neutralizes CRLF sequences from inputs.\n\n**Mapping Guidance**:\n- Usage: Allowed\n- Rationale: This CWE entry is at the Base level of abstraction, which is a preferred level of abstraction for mapping to the root causes of vulnerabilities.\n\n\n\n## CWE-459: Incomplete Cleanup\n**Abstraction Level**: Base\n**Similarity Score**: 0.69\n**Source**: dense\n\n**Description**:\nThe product does not properly \"clean up\" and remove temporary or supporting resources after they have been used.\n\n**Mapping Guidance**:\n- Usage: Allowed\n- Rationale: This CWE entry is at the Base level of abstraction, which is a preferred level of abstraction for mapping to the root causes of vulnerabilities.\n\n\n\n## CWE-303: Incorrect Implementation of Authentication Algorithm\n**Abstraction Level**: Base\n**Similarity Score**: 0.69\n**Source**: dense\n\n**Description**:\nThe requirements for the product dictate the use of an established authentication algorithm, but the implementation of the algorithm is incorrect.\n\n**Mapping Guidance**:\n- Usage: Allowed\n- Rationale: This CWE entry is at the Base level of abstraction, which is a preferred level of abstraction for mapping to the root causes of vulnerabilities.\n\n\n\n## CWE-203: Observable Discrepancy\n**Abstraction Level**: Base\n**Similarity Score**: 0.69\n**Source**: dense\n\n**Description**:\nThe product behaves differently or sends different responses under different circumstances in a way that is observable to an unauthorized actor, which exposes security-relevant information about the state of the product, such as whether a particular operation was successful or not.\n\n**Mapping Guidance**:\n- Usage: Allowed\n- Rationale: This CWE entry is at the Base level of abstraction, which is a preferred level of abstraction for mapping to the root causes of vulnerabilities.\n\n\n\n## CWE-288: Authentication Bypass Using an Alternate Path or Channel\n**Abstraction Level**: Base\n**Similarity Score**: 0.68\n**Source**: dense\n\n**Description**:\nThe product requires authentication, but the product has an alternate path or channel that does not require authentication.\n\n**Mapping Guidance**:\n- Usage: Allowed\n- Rationale: This CWE entry is at the Base level of abstraction, which is a preferred level of abstraction for mapping to the root causes of vulnerabilities.\n\n\n\n## CWE-347: Improper Verification of Cryptographic Signature\n**Abstraction Level**: Base\n**Similarity Score**: 1161.26\n**Source**: sparse\n\n**Description**:\nThe product does not verify, or incorrectly verifies, the cryptographic signature for data.\n\n**Mapping Guidance**:\n- Usage: Allowed\n- Rationale: This CWE entry is at the Base level of abstraction, which is a preferred level of abstraction for mapping to the root causes of vulnerabilities.\n\n\n\n## CWE-295: Improper\n\n\n## CWE Relationship Analysis\n\nCurrent CWEs represent these abstraction levels: .\n\n\n### Vulnerability Chain Analysis\n\n**Chain starting from CWE-1390:**\n- 1390 (Weak Authentication) - ROOT\n\n\n**Chain starting from CWE-99:**\n- 99 (Improper Control of Resource Identifiers ('Resource Injection')) - ROOT\n\n\n\n### CWE Relationship Diagram\n\n```mermaid\ngraph TD\n    classDef primary fill:#f96,stroke:#333,stroke-width:2px\n    classDef secondary fill:#69f,stroke:#333\n    classDef tertiary fill:#9e9,stroke:#333\n```",
  "criticism": "",
  "resolution": "",
  "relevant_cwes": [
    {
      "metadata": {
        "doc_id": "99",
        "name": "Improper Control of Resource Identifiers ('Resource Injection')",
        "source": "sparse"
      },
      "similarity": 420.439302670462
    },
    {
      "metadata": {
        "doc_id": "295",
        "name": "Improper Certificate Validation",
        "source": "sparse"
      },
      "similarity": 410.4148196077434
    },
    {
      "metadata": {
        "doc_id": "427",
        "name": "Uncontrolled Search Path Element",
        "source": "sparse"
      },
      "similarity": 395.1532233844779
    },
    {
      "metadata": {
        "doc_id": "923",
        "name": "Improper Restriction of Communication Channel to Intended Endpoints",
        "source": "sparse"
      },
      "similarity": 387.32210168378356
    },
    {
      "metadata": {
        "doc_id": "347",
        "name": "Improper Verification of Cryptographic Signature",
        "source": "sparse"
      },
      "similarity": 369.30082914781536
    },
    {
      "metadata": {
        "doc_id": "209",
        "name": "Generation of Error Message Containing Sensitive Information",
        "source": "sparse"
      },
      "similarity": 366.44375167411704
    },
    {
      "metadata": {
        "doc_id": "789",
        "name": "Memory Allocation with Excessive Size Value",
        "source": "sparse"
      },
      "similarity": 357.01316718449556
    },
    {
      "metadata": {
        "doc_id": "1390",
        "name": "Weak Authentication",
        "source": "sparse"
      },
      "similarity": 355.953879822406
    },
    {
      "metadata": {
        "doc_id": "603",
        "name": "Use of Client-Side Authentication",
        "type": "Base",
        "original_content": "A client/server product performs authentication within client code but not in server code, allowing server-side authentication to be bypassed via a modified client that omits the authentication check.",
        "keyphrase_source": "rootcause:by-passing the signature validation",
        "source": "dense",
        "mapping_notes": {
          "usage": "Allowed",
          "rationale": "This CWE entry is at the Base level of abstraction, which is a preferred level of abstraction for mapping to the root causes of vulnerabilities.",
          "comments": "Carefully read both the name and description to ensure that this mapping is an appropriate fit. Do not try to 'force' a mapping to a lower-level Base/Variant simply to comply with this preferred level of abstraction.",
          "reasons": [
            "Acceptable-Use"
          ]
        },
        "score_info": {
          "retrievers": [
            "dense",
            "graph"
          ],
          "retriever_count": 2,
          "normalized_scores": {
            "dense": 0.4084949186816148,
            "graph": 2.1423250120845387
          }
        }
      },
      "similarity": 0.4084949186816148
    },
    {
      "doc_id": "322",
      "text": "CWE-322: Key Exchange without Entity Authentication",
      "score": 2.9120000000000004,
      "metadata": {
        "doc_id": "322",
        "name": "Key Exchange without Entity Authentication",
        "type": "base",
        "original_content": "CWE-322: Key Exchange without Entity Authentication",
        "relationships": [
          {
            "source_id": "322",
            "target_id": "295",
            "label": "PEEROF",
            "properties": {
              "view_id": "1000"
            }
          },
          {
            "source_id": "322",
            "target_id": "923",
            "label": "CANPRECEDE",
            "properties": {
              "view_id": "1000"
            }
          },
          {
            "source_id": "322",
            "target_id": "306",
            "label": "CHILDOF",
            "properties": {
              "ordinal": "Primary",
              "view_id": "1000"
            }
          },
          {
            "source_id": "923",
            "target_id": "322",
            "label": "CANFOLLOW",
            "properties": {
              "view_id": "1000"
            }
          },
          {
            "source_id": "306",
            "target_id": "322",
            "label": "PARENTOF",
            "properties": {
              "ordinal": "Primary",
              "view_id": "1000"
            }
          },
          {
            "source_id": "295",
            "target_id": "322",
            "label": "PEEROF",
            "properties": {
              "view_id": "1000"
            }
          }
        ],
        "score_components": {
          "relationship_chain": 1.0,
          "sequence_path": 1.0,
          "peer_group": 0.9
        },
        "abstraction_factor": 1.3,
        "graph_path_info": {
          "path_types": [
            "relationship_chain",
            "vulnerability_sequence_forward",
            "vulnerability_sequence_backward",
            "peer_relationship"
          ],
          "best_paths": {
            "relationship_chain": {
              "path": [
                [
                  "923",
                  "322",
                  "CANFOLLOW"
                ]
              ],
              "score": 1.0,
              "type": "relationship_chain",
              "source": "923"
            },
            "vulnerability_sequence_forward": {
              "path": [
                [
                  "923",
                  "322",
                  "CANFOLLOW"
                ]
              ],
              "score": 0.9,
              "type": "vulnerability_sequence_forward",
              "source": "923"
            },
            "vulnerability_sequence_backward": {
              "path": [
                [
                  "322",
                  "923",
                  "CANPRECEDE"
                ]
              ],
              "score": 1.0,
              "type": "vulnerability_sequence_backward",
              "source": "923"
            },
            "peer_relationship": {
              "path": [
                [
                  "295",
                  "322",
                  "PEEROF"
                ]
              ],
              "score": 0.9,
              "type": "peer_relationship",
              "source": "295"
            }
          }
        },
        "position": "before",
        "sources": [
          "graph"
        ],
        "source": "graph",
        "mapping_notes": {
          "usage": "Allowed",
          "rationale": "This CWE entry is at the Base level of abstraction, which is a preferred level of abstraction for mapping to the root causes of vulnerabilities.",
          "comments": "Carefully read both the name and description to ensure that this mapping is an appropriate fit. Do not try to 'force' a mapping to a lower-level Base/Variant simply to comply with this preferred level of abstraction.",
          "reasons": [
            "Acceptable-Use"
          ]
        },
        "score_info": {
          "retrievers": [
            "graph"
          ],
          "retriever_count": 1,
          "normalized_scores": {
            "graph": 2.9120000000000004
          }
        }
      },
      "similarity": 2.9120000000000004
    }
  ],
  "identified_cwes": {
    "analyzer": [
      "CWE-1390",
      "CWE-99",
      "CWE-288",
      "CWE-427",
      "CWE-203",
      "CWE-345",
      "CWE-93",
      "CWE-923",
      "CWE-459",
      "CWE-209",
      "CWE-347",
      "CWE-322",
      "CWE-303",
      "CWE-1391",
      "CWE-603",
      "CWE-789",
      "CWE-295"
    ],
    "critic_additional": []
  },
  "keyphrase_cwe_mapping": {}
}