{
  "vulnerability_info": "VulnerabilityInfo(cve_id='CVE-2024-38561', description='In the Linux kernel, the following vulnerability has been resolved kunit Fix kthread reference There is a **race condition** when a kthread finishes after the deadline and before the call to kthread_stop(), which may lead to **use after free**.', key_phrases={'rootcause': ['race condition', 'use after free'], 'weakness': '', 'impact': '', 'vector': '', 'attacker': '', 'product': 'Linux kernel', 'version': '', 'component': ''}, reference_content=\"Based on the provided information, here's an analysis of the vulnerability:\\n\\n**Root Cause:**\\n\\nThe vulnerability stems from a race condition in the kunit try-catch mechanism when a kthread finishes execution after the defined deadline but before the `kthread_stop()` function is called. This timing issue can lead to a use-after-free (UAF) vulnerability.\\n\\n**Vulnerabilities/Weaknesses:**\\n\\n- **Race Condition:** The core issue is the race between the kthread finishing and the `kthread_stop()` call, which doesn't properly handle the scenario where the thread exits prematurely.\\n- **Use-After-Free:** If the thread finishes before `kthread_stop()` is called, the task_struct might be freed, and the subsequent call to `kthread_stop()` on the freed memory would result in a UAF.\\n\\n**Impact of Exploitation:**\\n\\n- A use-after-free vulnerability can lead to various issues including:\\n    - **System Instability:**  The UAF may cause the kernel to crash.\\n    - **Arbitrary Code Execution:** In some cases, exploitation could potentially allow for arbitrary code execution in the kernel context.\\n\\n**Attack Vectors:**\\n\\n- The attack vector is through the execution of a KUnit test case that utilizes `kunit_try_catch_run`, particularly in scenarios where the test case execution time exceeds its deadline, creating the race condition.\\n\\n**Required Attacker Capabilities/Position:**\\n\\n- The attacker needs to be able to trigger the execution of a KUnit test that can reliably trigger the race condition. This usually requires having the ability to run code or configure the system to run KUnit tests. This could be achieved through a compromised test environment, or potentially by exploiting another vulnerability that allows control over test execution.\\n\\n**Additional Details:**\\n\\n- The fix involves switching from `kthread_run` to `kthread_create` followed by a `get_task_struct()` and `wake_up_process` to ensure the task struct remains valid until after `kthread_stop`. A corresponding `put_task_struct` is also added after the call to `kthread_stop`.\\n- The patch addresses a UAF that was reported and fixed in the context of kfence tests and is related to the `test_gfpzero` test case.\\n- The fix was backported across multiple kernel versions.\", similar_info={'cwe_distribution': {}, 'cwe_consensus': '', 'similarity_stats': {'thresholds': [], 'total_samples_by_threshold': {}, 'top_cwes_by_threshold': {}}}, similarity_summary=SimilarityInsight(consensus_cwe='', top_cwes=[], confidence_levels={}, total_samples=0), analysis='', analysis_with_relationships='', criticism='', resolution='', relevant_cwes=[{'metadata': {'doc_id': '362', 'name': \"Concurrent Execution using Shared Resource with Improper Synchronization ('Race Condition')\", 'source': 'sparse', 'original_content': 'The product contains a concurrent code sequence that requires temporary, exclusive access to a shared resource, but a timing window exists in which the shared resource can be modified by another code sequence operating concurrently.', 'keyphrase_sources': [{'id': 'rootcause:race condition', 'keyphrase': 'race condition', 'type': 'rootcause'}, {'id': 'rootcause:use after free', 'keyphrase': 'use after free', 'type': 'rootcause'}, {'id': 'product:Linux kernel', 'keyphrase': 'Linux kernel', 'type': 'product'}]}, 'similarity': np.float64(336.54308056238676)}, {'metadata': {'doc_id': '667', 'name': 'Improper Locking', 'source': 'sparse', 'original_content': 'The product does not properly acquire or release a lock on a resource, leading to unexpected resource state changes and behaviors.', 'keyphrase_sources': [{'id': 'rootcause:race condition', 'keyphrase': 'race condition', 'type': 'rootcause'}, {'id': 'rootcause:use after free', 'keyphrase': 'use after free', 'type': 'rootcause'}, {'id': 'product:Linux kernel', 'keyphrase': 'Linux kernel', 'type': 'product'}]}, 'similarity': np.float64(301.9851498752477)}, {'metadata': {'doc_id': '367', 'name': 'Time-of-check Time-of-use (TOCTOU) Race Condition', 'source': 'sparse', 'original_content': \"The product checks the state of a resource before using that resource, but the resource's state can change between the check and the use in a way that invalidates the results of the check. This can cause the product to perform invalid actions when the resource is in an unexpected state.\", 'keyphrase_sources': [{'id': 'rootcause:race condition', 'keyphrase': 'race condition', 'type': 'rootcause'}, {'id': 'product:Linux kernel', 'keyphrase': 'Linux kernel', 'type': 'product'}]}, 'similarity': np.float64(301.01824859863683)}, {'metadata': {'doc_id': '911', 'name': 'Improper Update of Reference Count', 'source': 'sparse', 'original_content': 'The product uses a reference count to manage a resource, but it does not update or incorrectly updates the reference count.', 'keyphrase_sources': [{'id': 'rootcause:use after free', 'keyphrase': 'use after free', 'type': 'rootcause'}, {'id': 'product:Linux kernel', 'keyphrase': 'Linux kernel', 'type': 'product'}]}, 'similarity': np.float64(296.99111984132946)}, {'metadata': {'doc_id': '415', 'name': 'Double Free', 'source': 'sparse', 'original_content': 'The product calls free() twice on the same memory address, potentially leading to modification of unexpected memory locations.', 'keyphrase_sources': [{'id': 'rootcause:use after free', 'keyphrase': 'use after free', 'type': 'rootcause'}, {'id': 'product:Linux kernel', 'keyphrase': 'Linux kernel', 'type': 'product'}]}, 'similarity': np.float64(290.26336178623063)}, {'metadata': {'doc_id': '364', 'name': 'Signal Handler Race Condition', 'source': 'sparse', 'original_content': 'The product uses a signal handler that introduces a race condition.', 'keyphrase_sources': [{'id': 'rootcause:race condition', 'keyphrase': 'race condition', 'type': 'rootcause'}]}, 'similarity': np.float64(286.35689189881964)}, {'metadata': {'doc_id': '662', 'name': 'Improper Synchronization', 'source': 'sparse', 'original_content': 'The product utilizes multiple threads or processes to allow temporary access to a shared resource that can only be exclusive to one process at a time, but it does not properly synchronize these actions, which might cause simultaneous accesses of this resource by multiple threads or processes.', 'keyphrase_sources': [{'id': 'rootcause:race condition', 'keyphrase': 'race condition', 'type': 'rootcause'}]}, 'similarity': np.float64(279.07715677264713)}, {'metadata': {'doc_id': '416', 'name': 'Use After Free', 'source': 'sparse', 'original_content': 'The product reuses or references memory after it has been freed. At some point afterward, the memory may be allocated again and saved in another pointer, while the original pointer references a location somewhere within the new allocation. Any operations using the original pointer are no longer valid because the memory \"belongs\" to the code that operates on the new pointer.', 'keyphrase_sources': [{'id': 'rootcause:use after free', 'keyphrase': 'use after free', 'type': 'rootcause'}]}, 'similarity': np.float64(278.72644755103147)}], identified_cwes={'analyzer': [], 'critic_additional': []})",
  "retrieval_results": {
    "has_multiple_keyphrases": true,
    "keyphrase_cwe_sets": {
      "rootcause:race condition": {
        "keyphrase": "race condition",
        "type": "rootcause",
        "cwes": [
          {
            "metadata": {
              "doc_id": "362",
              "name": "Concurrent Execution using Shared Resource with Improper Synchronization ('Race Condition')",
              "source": "sparse",
              "original_content": "The product contains a concurrent code sequence that requires temporary, exclusive access to a shared resource, but a timing window exists in which the shared resource can be modified by another code sequence operating concurrently.",
              "keyphrase_sources": [
                {
                  "id": "rootcause:race condition",
                  "keyphrase": "race condition",
                  "type": "rootcause"
                },
                {
                  "id": "rootcause:use after free",
                  "keyphrase": "use after free",
                  "type": "rootcause"
                },
                {
                  "id": "product:Linux kernel",
                  "keyphrase": "Linux kernel",
                  "type": "product"
                }
              ]
            },
            "similarity": 336.54308056238676
          },
          {
            "metadata": {
              "doc_id": "667",
              "name": "Improper Locking",
              "source": "sparse",
              "original_content": "The product does not properly acquire or release a lock on a resource, leading to unexpected resource state changes and behaviors.",
              "keyphrase_sources": [
                {
                  "id": "rootcause:race condition",
                  "keyphrase": "race condition",
                  "type": "rootcause"
                },
                {
                  "id": "rootcause:use after free",
                  "keyphrase": "use after free",
                  "type": "rootcause"
                },
                {
                  "id": "product:Linux kernel",
                  "keyphrase": "Linux kernel",
                  "type": "product"
                }
              ]
            },
            "similarity": 301.9851498752477
          },
          {
            "metadata": {
              "doc_id": "367",
              "name": "Time-of-check Time-of-use (TOCTOU) Race Condition",
              "source": "sparse",
              "original_content": "The product checks the state of a resource before using that resource, but the resource's state can change between the check and the use in a way that invalidates the results of the check. This can cause the product to perform invalid actions when the resource is in an unexpected state.",
              "keyphrase_sources": [
                {
                  "id": "rootcause:race condition",
                  "keyphrase": "race condition",
                  "type": "rootcause"
                },
                {
                  "id": "product:Linux kernel",
                  "keyphrase": "Linux kernel",
                  "type": "product"
                }
              ]
            },
            "similarity": 301.01824859863683
          },
          {
            "metadata": {
              "doc_id": "364",
              "name": "Signal Handler Race Condition",
              "source": "sparse",
              "original_content": "The product uses a signal handler that introduces a race condition.",
              "keyphrase_sources": [
                {
                  "id": "rootcause:race condition",
                  "keyphrase": "race condition",
                  "type": "rootcause"
                }
              ]
            },
            "similarity": 286.35689189881964
          },
          {
            "metadata": {
              "doc_id": "662",
              "name": "Improper Synchronization",
              "source": "sparse",
              "original_content": "The product utilizes multiple threads or processes to allow temporary access to a shared resource that can only be exclusive to one process at a time, but it does not properly synchronize these actions, which might cause simultaneous accesses of this resource by multiple threads or processes.",
              "keyphrase_sources": [
                {
                  "id": "rootcause:race condition",
                  "keyphrase": "race condition",
                  "type": "rootcause"
                }
              ]
            },
            "similarity": 279.07715677264713
          }
        ]
      },
      "rootcause:use after free": {
        "keyphrase": "use after free",
        "type": "rootcause",
        "cwes": [
          {
            "metadata": {
              "doc_id": "362",
              "name": "Concurrent Execution using Shared Resource with Improper Synchronization ('Race Condition')",
              "source": "sparse",
              "original_content": "The product contains a concurrent code sequence that requires temporary, exclusive access to a shared resource, but a timing window exists in which the shared resource can be modified by another code sequence operating concurrently."
            },
            "similarity": 326.0089871057129
          },
          {
            "metadata": {
              "doc_id": "667",
              "name": "Improper Locking",
              "source": "sparse",
              "original_content": "The product does not properly acquire or release a lock on a resource, leading to unexpected resource state changes and behaviors."
            },
            "similarity": 299.7888186213584
          },
          {
            "metadata": {
              "doc_id": "911",
              "name": "Improper Update of Reference Count",
              "source": "sparse",
              "original_content": "The product uses a reference count to manage a resource, but it does not update or incorrectly updates the reference count.",
              "keyphrase_sources": [
                {
                  "id": "rootcause:use after free",
                  "keyphrase": "use after free",
                  "type": "rootcause"
                },
                {
                  "id": "product:Linux kernel",
                  "keyphrase": "Linux kernel",
                  "type": "product"
                }
              ]
            },
            "similarity": 296.99111984132946
          },
          {
            "metadata": {
              "doc_id": "415",
              "name": "Double Free",
              "source": "sparse",
              "original_content": "The product calls free() twice on the same memory address, potentially leading to modification of unexpected memory locations.",
              "keyphrase_sources": [
                {
                  "id": "rootcause:use after free",
                  "keyphrase": "use after free",
                  "type": "rootcause"
                },
                {
                  "id": "product:Linux kernel",
                  "keyphrase": "Linux kernel",
                  "type": "product"
                }
              ]
            },
            "similarity": 290.26336178623063
          },
          {
            "metadata": {
              "doc_id": "416",
              "name": "Use After Free",
              "source": "sparse",
              "original_content": "The product reuses or references memory after it has been freed. At some point afterward, the memory may be allocated again and saved in another pointer, while the original pointer references a location somewhere within the new allocation. Any operations using the original pointer are no longer valid because the memory \"belongs\" to the code that operates on the new pointer.",
              "keyphrase_sources": [
                {
                  "id": "rootcause:use after free",
                  "keyphrase": "use after free",
                  "type": "rootcause"
                }
              ]
            },
            "similarity": 278.72644755103147
          }
        ]
      },
      "product:Linux kernel": {
        "keyphrase": "Linux kernel",
        "type": "product",
        "cwes": [
          {
            "metadata": {
              "doc_id": "362",
              "name": "Concurrent Execution using Shared Resource with Improper Synchronization ('Race Condition')",
              "source": "sparse",
              "original_content": "The product contains a concurrent code sequence that requires temporary, exclusive access to a shared resource, but a timing window exists in which the shared resource can be modified by another code sequence operating concurrently."
            },
            "similarity": 106.51294137913811
          },
          {
            "metadata": {
              "doc_id": "667",
              "name": "Improper Locking",
              "source": "sparse",
              "original_content": "The product does not properly acquire or release a lock on a resource, leading to unexpected resource state changes and behaviors."
            },
            "similarity": 98.26992232217036
          },
          {
            "metadata": {
              "doc_id": "911",
              "name": "Improper Update of Reference Count",
              "source": "sparse",
              "original_content": "The product uses a reference count to manage a resource, but it does not update or incorrectly updates the reference count."
            },
            "similarity": 98.04450537299671
          },
          {
            "metadata": {
              "doc_id": "415",
              "name": "Double Free",
              "source": "sparse",
              "original_content": "The product calls free() twice on the same memory address, potentially leading to modification of unexpected memory locations."
            },
            "similarity": 92.78329048191193
          },
          {
            "metadata": {
              "doc_id": "367",
              "name": "Time-of-check Time-of-use (TOCTOU) Race Condition",
              "source": "sparse",
              "original_content": "The product checks the state of a resource before using that resource, but the resource's state can change between the check and the use in a way that invalidates the results of the check. This can cause the product to perform invalid actions when the resource is in an unexpected state."
            },
            "similarity": 92.13769642737518
          }
        ]
      }
    },
    "keyphrase_mapping": {
      "362": [
        {
          "id": "rootcause:race condition",
          "keyphrase": "race condition",
          "type": "rootcause"
        },
        {
          "id": "rootcause:use after free",
          "keyphrase": "use after free",
          "type": "rootcause"
        },
        {
          "id": "product:Linux kernel",
          "keyphrase": "Linux kernel",
          "type": "product"
        }
      ],
      "667": [
        {
          "id": "rootcause:race condition",
          "keyphrase": "race condition",
          "type": "rootcause"
        },
        {
          "id": "rootcause:use after free",
          "keyphrase": "use after free",
          "type": "rootcause"
        },
        {
          "id": "product:Linux kernel",
          "keyphrase": "Linux kernel",
          "type": "product"
        }
      ],
      "367": [
        {
          "id": "rootcause:race condition",
          "keyphrase": "race condition",
          "type": "rootcause"
        },
        {
          "id": "product:Linux kernel",
          "keyphrase": "Linux kernel",
          "type": "product"
        }
      ],
      "364": [
        {
          "id": "rootcause:race condition",
          "keyphrase": "race condition",
          "type": "rootcause"
        }
      ],
      "662": [
        {
          "id": "rootcause:race condition",
          "keyphrase": "race condition",
          "type": "rootcause"
        }
      ],
      "911": [
        {
          "id": "rootcause:use after free",
          "keyphrase": "use after free",
          "type": "rootcause"
        },
        {
          "id": "product:Linux kernel",
          "keyphrase": "Linux kernel",
          "type": "product"
        }
      ],
      "415": [
        {
          "id": "rootcause:use after free",
          "keyphrase": "use after free",
          "type": "rootcause"
        },
        {
          "id": "product:Linux kernel",
          "keyphrase": "Linux kernel",
          "type": "product"
        }
      ],
      "416": [
        {
          "id": "rootcause:use after free",
          "keyphrase": "use after free",
          "type": "rootcause"
        }
      ]
    },
    "relevant_cwes": [
      {
        "metadata": {
          "doc_id": "362",
          "name": "Concurrent Execution using Shared Resource with Improper Synchronization ('Race Condition')",
          "source": "sparse",
          "original_content": "The product contains a concurrent code sequence that requires temporary, exclusive access to a shared resource, but a timing window exists in which the shared resource can be modified by another code sequence operating concurrently.",
          "keyphrase_sources": [
            {
              "id": "rootcause:race condition",
              "keyphrase": "race condition",
              "type": "rootcause"
            },
            {
              "id": "rootcause:use after free",
              "keyphrase": "use after free",
              "type": "rootcause"
            },
            {
              "id": "product:Linux kernel",
              "keyphrase": "Linux kernel",
              "type": "product"
            }
          ]
        },
        "similarity": 336.54308056238676
      },
      {
        "metadata": {
          "doc_id": "667",
          "name": "Improper Locking",
          "source": "sparse",
          "original_content": "The product does not properly acquire or release a lock on a resource, leading to unexpected resource state changes and behaviors.",
          "keyphrase_sources": [
            {
              "id": "rootcause:race condition",
              "keyphrase": "race condition",
              "type": "rootcause"
            },
            {
              "id": "rootcause:use after free",
              "keyphrase": "use after free",
              "type": "rootcause"
            },
            {
              "id": "product:Linux kernel",
              "keyphrase": "Linux kernel",
              "type": "product"
            }
          ]
        },
        "similarity": 301.9851498752477
      },
      {
        "metadata": {
          "doc_id": "367",
          "name": "Time-of-check Time-of-use (TOCTOU) Race Condition",
          "source": "sparse",
          "original_content": "The product checks the state of a resource before using that resource, but the resource's state can change between the check and the use in a way that invalidates the results of the check. This can cause the product to perform invalid actions when the resource is in an unexpected state.",
          "keyphrase_sources": [
            {
              "id": "rootcause:race condition",
              "keyphrase": "race condition",
              "type": "rootcause"
            },
            {
              "id": "product:Linux kernel",
              "keyphrase": "Linux kernel",
              "type": "product"
            }
          ]
        },
        "similarity": 301.01824859863683
      },
      {
        "metadata": {
          "doc_id": "911",
          "name": "Improper Update of Reference Count",
          "source": "sparse",
          "original_content": "The product uses a reference count to manage a resource, but it does not update or incorrectly updates the reference count.",
          "keyphrase_sources": [
            {
              "id": "rootcause:use after free",
              "keyphrase": "use after free",
              "type": "rootcause"
            },
            {
              "id": "product:Linux kernel",
              "keyphrase": "Linux kernel",
              "type": "product"
            }
          ]
        },
        "similarity": 296.99111984132946
      },
      {
        "metadata": {
          "doc_id": "415",
          "name": "Double Free",
          "source": "sparse",
          "original_content": "The product calls free() twice on the same memory address, potentially leading to modification of unexpected memory locations.",
          "keyphrase_sources": [
            {
              "id": "rootcause:use after free",
              "keyphrase": "use after free",
              "type": "rootcause"
            },
            {
              "id": "product:Linux kernel",
              "keyphrase": "Linux kernel",
              "type": "product"
            }
          ]
        },
        "similarity": 290.26336178623063
      },
      {
        "metadata": {
          "doc_id": "364",
          "name": "Signal Handler Race Condition",
          "source": "sparse",
          "original_content": "The product uses a signal handler that introduces a race condition.",
          "keyphrase_sources": [
            {
              "id": "rootcause:race condition",
              "keyphrase": "race condition",
              "type": "rootcause"
            }
          ]
        },
        "similarity": 286.35689189881964
      },
      {
        "metadata": {
          "doc_id": "662",
          "name": "Improper Synchronization",
          "source": "sparse",
          "original_content": "The product utilizes multiple threads or processes to allow temporary access to a shared resource that can only be exclusive to one process at a time, but it does not properly synchronize these actions, which might cause simultaneous accesses of this resource by multiple threads or processes.",
          "keyphrase_sources": [
            {
              "id": "rootcause:race condition",
              "keyphrase": "race condition",
              "type": "rootcause"
            }
          ]
        },
        "similarity": 279.07715677264713
      },
      {
        "metadata": {
          "doc_id": "416",
          "name": "Use After Free",
          "source": "sparse",
          "original_content": "The product reuses or references memory after it has been freed. At some point afterward, the memory may be allocated again and saved in another pointer, while the original pointer references a location somewhere within the new allocation. Any operations using the original pointer are no longer valid because the memory \"belongs\" to the code that operates on the new pointer.",
          "keyphrase_sources": [
            {
              "id": "rootcause:use after free",
              "keyphrase": "use after free",
              "type": "rootcause"
            }
          ]
        },
        "similarity": 278.72644755103147
      }
    ],
    "enhanced_query": "# Vulnerability Description\n\n    In the Linux kernel, the following vulnerability has been resolved kunit Fix kthread reference There is a **race condition** when a kthread finishes after the deadline and before the call to kthread_stop(), which may lead to **use after free**.\n\n    # Keyphrase-Specific CWE Analysis\n    This vulnerability contains multiple keyphrases that may map to different CWEs. \n    Please analyze each keyphrase separately and determine the most appropriate CWE(s) for each.\n\n    ## ROOTCAUSE: 'race condition'\n\nRelevant CWEs for this ROOTCAUSE:\n\n### 1. CWE-362: Concurrent Execution using Shared Resource with Improper Synchronization ('Race Condition') (Score: 336.54)\n\nThe product contains a concurrent code sequence that requires temporary, exclusive access to a shared resource, but a timing window exists in which the shared resource can be modified by another code sequence operating concurrently....\n\n### 2. CWE-667: Improper Locking (Score: 301.99)\n\nThe product does not properly acquire or release a lock on a resource, leading to unexpected resource state changes and behaviors....\n\n### 3. CWE-367: Time-of-check Time-of-use (TOCTOU) Race Condition (Score: 301.02)\n\nThe product checks the state of a resource before using that resource, but the resource's state can change between the check and the use in a way that invalidates the results of the check. This can cause the product to perform invalid actions when the resource is in an unexpected state....\n\n### 4. CWE-364: Signal Handler Race Condition (Score: 286.36)\n\nThe product uses a signal handler that introduces a race condition....\n\n### 5. CWE-662: Improper Synchronization (Score: 279.08)\n\nThe product utilizes multiple threads or processes to allow temporary access to a shared resource that can only be exclusive to one process at a time, but it does not properly synchronize these actions, which might cause simultaneous accesses of this resource by multiple threads or processes....\n\n## ROOTCAUSE: 'use after free'\n\nRelevant CWEs for this ROOTCAUSE:\n\n### 1. CWE-362: Concurrent Execution using Shared Resource with Improper Synchronization ('Race Condition') (Score: 336.54)\n\nThe product contains a concurrent code sequence that requires temporary, exclusive access to a shared resource, but a timing window exists in which the shared resource can be modified by another code sequence operating concurrently....\n\n### 2. CWE-667: Improper Locking (Score: 301.99)\n\nThe product does not properly acquire or release a lock on a resource, leading to unexpected resource state changes and behaviors....\n\n### 3. CWE-911: Improper Update of Reference Count (Score: 296.99)\n\nThe product uses a reference count to manage a resource, but it does not update or incorrectly updates the reference count....\n\n### 4. CWE-415: Double Free (Score: 290.26)\n\nThe product calls free() twice on the same memory address, potentially leading to modification of unexpected memory locations....\n\n### 5. CWE-416: Use After Free (Score: 278.73)\n\nThe product reuses or references memory after it has been freed. At some point afterward, the memory may be allocated again and saved in another pointer, while the original pointer references a location somewhere within the new allocation. Any operations using the original pointer are no longer vali...\n\n## PRODUCT: 'Linux kernel'\n\nRelevant CWEs for this PRODUCT:\n\n### 1. CWE-362: Concurrent Execution using Shared Resource with Improper Synchronization ('Race Condition') (Score: 336.54)\n\nThe product contains a concurrent code sequence that requires temporary, exclusive access to a shared resource, but a timing window exists in which the shared resource can be modified by another code sequence operating concurrently....\n\n### 2. CWE-667: Improper Locking (Score: 301.99)\n\nThe product does not properly acquire or release a lock on a resource, leading to unexpected resource state changes and behaviors....\n\n### 3. CWE-367: Time-of-check Time-of-use (TOCTOU) Race Condition (Score: 301.02)\n\nThe product checks the state of a resource before using that resource, but the resource's state can change between the check and the use in a way that invalidates the results of the check. This can cause the product to perform invalid actions when the resource is in an unexpected state....\n\n### 4. CWE-911: Improper Update of Reference Count (Score: 296.99)\n\nThe product uses a reference count to manage a resource, but it does not update or incorrectly updates the reference count....\n\n### 5. CWE-415: Double Free (Score: 290.26)\n\nThe product calls free() twice on the same memory address, potentially leading to modification of unexpected memory locations....\n\n\n    # Analysis Instructions\n    1. For each keyphrase, identify the most appropriate CWE(s) that represent the weakness.\n    2. Consider how the different keyphrases might relate to each other in the vulnerability chain.\n    3. Provide a final determination of primary CWE(s) and any secondary CWEs.\n    4. Format your response using the standard analysis template.\n\n    Please analyze how these different weaknesses interact and provide a comprehensive CWE classification.\n    "
  },
  "retrieval_time": 1.0449943542480469
}