{
  "vulnerability_info": "VulnerabilityInfo(cve_id='CVE-2024-13909', description='The Accredible Certificates & Open Badges plugin for WordPress is vulnerable to time-based SQL Injection via the orderby parameter in all versions up to, and including, 1.4.9 due to **insufficient escaping on the user supplied parameter and lack of sufficient preparation on the existing SQL query**. This makes it possible for authenticated attackers, with Administrator-level access and above, to append additional SQL queries into already existing queries that can be used to extract sensitive information from the database.', key_phrases={'rootcause': ['insufficient escaping on the user supplied parameter and lack of sufficient preparation on the existing SQL query', 'insufficient escaping on user supplied parameter'], 'weakness': 'time-based SQL injection', 'impact': 'extract sensitive information from the database', 'vector': 'orderby parameter', 'attacker': 'authenticated attackers with Administrator-level access', 'product': 'Accredible Certificates & Open Badges plugin for WordPress', 'version': 'all versions up to and including 1.4.9', 'component': ''}, reference_content=\"## Analysis of CVE-2024-13909 Content\\n\\nBased on the provided content, here's an analysis related to CVE-2024-13909.  Since the CVE description is a placeholder, I'm assessing if the content relates to potential vulnerabilities within the Accredible Certificates plugin.\\n\\n**Root cause of vulnerability:**\\n\\nThe code snippet from `users_list.php` shows a potential SQL injection vulnerability in lines 54-69. The query is constructed using user-supplied input (`$_REQUEST['s']`) directly within the SQL query string, even though `esc_sql()` is used.  However, the way the `LIKE` operator is used with the wildcard `%` before and after the user input can still be exploited if not handled carefully.\\n\\n**Weaknesses/vulnerabilities present:**\\n\\n*   **Potential SQL Injection:** The use of user-supplied input in the SQL query without proper sanitization could allow an attacker to inject malicious SQL code.\\n*   **Insufficient Input Validation:** The code relies on `esc_sql()` which might not be sufficient to prevent all SQL injection attacks, especially when used with `LIKE` clauses and wildcards.\\n\\n**Impact of exploitation:**\\n\\nSuccessful exploitation of this vulnerability could allow an attacker to:\\n\\n*   **Read sensitive data:** Access user information (usernames, emails, etc.) from the WordPress database.\\n*   **Modify data:** Potentially alter data within the database.\\n*   **Execute arbitrary code:** In some cases, SQL injection can lead to the execution of arbitrary code on the server.\\n\\n**Attack vectors:**\\n\\n*   **Search Field:** An attacker could craft a malicious search query through the plugin's search functionality (likely accessible in the admin interface) to inject SQL code.\\n\\n**Required attacker capabilities/position:**\\n\\n*   **Authenticated User (potentially):** Depending on where the search field is located, an attacker might need to be an authenticated user with access to the admin interface.  However, if the search functionality is exposed publicly, it could be exploited without authentication.\\n*   **SQL Injection Knowledge:** The attacker needs to have knowledge of SQL injection techniques to craft a malicious query.\\n\\n**Mitigation or fix:**\\n\\n*   **Prepared Statements:** The most effective mitigation is to use prepared statements with parameterized queries. This prevents user input from being interpreted as SQL code.\\n*   **Input Sanitization:**  While `esc_sql()` is used, it's crucial to ensure it's applied correctly and is sufficient for the specific context. Consider using more robust sanitization functions if necessary.\\n*   **Least Privilege:** Ensure the database user used by the WordPress application has only the necessary privileges to perform its tasks.\\n\\n**Note:** This analysis is based on the code snippet provided and assumes a potential vulnerability. A thorough security audit would be required to confirm the vulnerability and determine the best course of action.\\n\\nThe content provides more detail than the official CVE description (which is currently a placeholder).\", similar_info={'cwe_distribution': {}, 'cwe_consensus': '', 'similarity_stats': {'thresholds': [], 'total_samples_by_threshold': {}, 'top_cwes_by_threshold': {}}}, similarity_summary=SimilarityInsight(consensus_cwe='', top_cwes=[], confidence_levels={}, total_samples=0), analysis='', analysis_with_relationships='', criticism='', resolution='', relevant_cwes=[{'metadata': {'doc_id': '116', 'name': 'Improper Encoding or Escaping of Output', 'source': 'sparse', 'original_content': 'The product prepares a structured message for communication with another component, but encoding or escaping of the data is either missing or done incorrectly. As a result, the intended structure of the message is not preserved.', 'keyphrase_sources': [{'id': 'rootcause:insufficient escaping on the user supplied parameter and lack of sufficient preparation on the existing SQL query', 'keyphrase': 'insufficient escaping on the user supplied parameter and lack of sufficient preparation on the existing SQL query', 'type': 'rootcause'}, {'id': 'rootcause:insufficient escaping on user supplied parameter', 'keyphrase': 'insufficient escaping on user supplied parameter', 'type': 'rootcause'}, {'id': 'weakness:time-based SQL injection', 'keyphrase': 'time-based SQL injection', 'type': 'weakness'}, {'id': 'impact:extract sensitive information from the database', 'keyphrase': 'extract sensitive information from the database', 'type': 'impact'}, {'id': 'vector:orderby parameter', 'keyphrase': 'orderby parameter', 'type': 'vector'}, {'id': 'attacker:authenticated attackers with Administrator-level access', 'keyphrase': 'authenticated attackers with Administrator-level access', 'type': 'attacker'}, {'id': 'product:Accredible Certificates & Open Badges plugin for WordPress', 'keyphrase': 'Accredible Certificates & Open Badges plugin for WordPress', 'type': 'product'}, {'id': 'version:all versions up to and including 1.4.9', 'keyphrase': 'all versions up to and including 1.4.9', 'type': 'version'}]}, 'similarity': np.float64(757.173075143163)}, {'metadata': {'doc_id': '89', 'name': \"Improper Neutralization of Special Elements used in an SQL Command ('SQL Injection')\", 'source': 'sparse', 'original_content': 'The product constructs all or part of an SQL command using externally-influenced input from an upstream component, but it does not neutralize or incorrectly neutralizes special elements that could modify the intended SQL command when it is sent to a downstream component. Without sufficient removal or quoting of SQL syntax in user-controllable inputs, the generated SQL query can cause those inputs to be interpreted as SQL instead of ordinary user data.', 'keyphrase_sources': [{'id': 'rootcause:insufficient escaping on the user supplied parameter and lack of sufficient preparation on the existing SQL query', 'keyphrase': 'insufficient escaping on the user supplied parameter and lack of sufficient preparation on the existing SQL query', 'type': 'rootcause'}, {'id': 'rootcause:insufficient escaping on user supplied parameter', 'keyphrase': 'insufficient escaping on user supplied parameter', 'type': 'rootcause'}, {'id': 'weakness:time-based SQL injection', 'keyphrase': 'time-based SQL injection', 'type': 'weakness'}, {'id': 'impact:extract sensitive information from the database', 'keyphrase': 'extract sensitive information from the database', 'type': 'impact'}, {'id': 'vector:orderby parameter', 'keyphrase': 'orderby parameter', 'type': 'vector'}, {'id': 'attacker:authenticated attackers with Administrator-level access', 'keyphrase': 'authenticated attackers with Administrator-level access', 'type': 'attacker'}, {'id': 'product:Accredible Certificates & Open Badges plugin for WordPress', 'keyphrase': 'Accredible Certificates & Open Badges plugin for WordPress', 'type': 'product'}, {'id': 'version:all versions up to and including 1.4.9', 'keyphrase': 'all versions up to and including 1.4.9', 'type': 'version'}]}, 'similarity': np.float64(744.7034647559881)}, {'metadata': {'doc_id': '352', 'name': 'Cross-Site Request Forgery (CSRF)', 'source': 'sparse', 'original_content': 'The web application does not, or can not, sufficiently verify whether a well-formed, valid, consistent request was intentionally provided by the user who submitted the request.', 'keyphrase_sources': [{'id': 'rootcause:insufficient escaping on the user supplied parameter and lack of sufficient preparation on the existing SQL query', 'keyphrase': 'insufficient escaping on the user supplied parameter and lack of sufficient preparation on the existing SQL query', 'type': 'rootcause'}, {'id': 'rootcause:insufficient escaping on user supplied parameter', 'keyphrase': 'insufficient escaping on user supplied parameter', 'type': 'rootcause'}, {'id': 'impact:extract sensitive information from the database', 'keyphrase': 'extract sensitive information from the database', 'type': 'impact'}, {'id': 'vector:orderby parameter', 'keyphrase': 'orderby parameter', 'type': 'vector'}, {'id': 'attacker:authenticated attackers with Administrator-level access', 'keyphrase': 'authenticated attackers with Administrator-level access', 'type': 'attacker'}, {'id': 'product:Accredible Certificates & Open Badges plugin for WordPress', 'keyphrase': 'Accredible Certificates & Open Badges plugin for WordPress', 'type': 'product'}, {'id': 'version:all versions up to and including 1.4.9', 'keyphrase': 'all versions up to and including 1.4.9', 'type': 'version'}]}, 'similarity': np.float64(682.8840806779352)}, {'metadata': {'doc_id': '90', 'name': \"Improper Neutralization of Special Elements used in an LDAP Query ('LDAP Injection')\", 'source': 'sparse', 'original_content': 'The product constructs all or part of an LDAP query using externally-influenced input from an upstream component, but it does not neutralize or incorrectly neutralizes special elements that could modify the intended LDAP query when it is sent to a downstream component.', 'keyphrase_sources': [{'id': 'rootcause:insufficient escaping on the user supplied parameter and lack of sufficient preparation on the existing SQL query', 'keyphrase': 'insufficient escaping on the user supplied parameter and lack of sufficient preparation on the existing SQL query', 'type': 'rootcause'}, {'id': 'rootcause:insufficient escaping on user supplied parameter', 'keyphrase': 'insufficient escaping on user supplied parameter', 'type': 'rootcause'}, {'id': 'weakness:time-based SQL injection', 'keyphrase': 'time-based SQL injection', 'type': 'weakness'}, {'id': 'impact:extract sensitive information from the database', 'keyphrase': 'extract sensitive information from the database', 'type': 'impact'}, {'id': 'vector:orderby parameter', 'keyphrase': 'orderby parameter', 'type': 'vector'}]}, 'similarity': np.float64(682.7973381262995)}, {'metadata': {'doc_id': '20', 'name': 'Improper Input Validation', 'source': 'sparse', 'original_content': 'The product receives input or data, but it does\\n        not validate or incorrectly validates that the input has the\\n        properties that are required to process the data safely and\\n        correctly.', 'keyphrase_sources': [{'id': 'rootcause:insufficient escaping on the user supplied parameter and lack of sufficient preparation on the existing SQL query', 'keyphrase': 'insufficient escaping on the user supplied parameter and lack of sufficient preparation on the existing SQL query', 'type': 'rootcause'}]}, 'similarity': np.float64(649.1342952366622)}, {'metadata': {'doc_id': '790', 'name': 'Improper Filtering of Special Elements', 'source': 'sparse', 'original_content': 'The product receives data from an upstream component, but does not filter or incorrectly filters special elements before sending it to a downstream component.', 'keyphrase_sources': [{'id': 'rootcause:insufficient escaping on user supplied parameter', 'keyphrase': 'insufficient escaping on user supplied parameter', 'type': 'rootcause'}, {'id': 'vector:orderby parameter', 'keyphrase': 'orderby parameter', 'type': 'vector'}]}, 'similarity': np.float64(526.6065398513887)}, {'metadata': {'doc_id': '502', 'name': 'Deserialization of Untrusted Data', 'source': 'sparse', 'original_content': 'The product deserializes untrusted data without sufficiently ensuring that the resulting data will be valid.', 'keyphrase_sources': [{'id': 'weakness:time-based SQL injection', 'keyphrase': 'time-based SQL injection', 'type': 'weakness'}, {'id': 'version:all versions up to and including 1.4.9', 'keyphrase': 'all versions up to and including 1.4.9', 'type': 'version'}]}, 'similarity': np.float64(468.012978897068)}, {'metadata': {'doc_id': '138', 'name': 'Improper Neutralization of Special Elements', 'source': 'sparse', 'original_content': 'The product receives input from an upstream component, but it does not neutralize or incorrectly neutralizes special elements that could be interpreted as control elements or syntactic markers when they are sent to a downstream component.', 'keyphrase_sources': [{'id': 'weakness:time-based SQL injection', 'keyphrase': 'time-based SQL injection', 'type': 'weakness'}]}, 'similarity': np.float64(452.410584822661)}, {'metadata': {'doc_id': '862', 'name': 'Missing Authorization', 'source': 'sparse', 'original_content': 'The product does not perform an authorization check when an actor attempts to access a resource or perform an action.', 'keyphrase_sources': [{'id': 'attacker:authenticated attackers with Administrator-level access', 'keyphrase': 'authenticated attackers with Administrator-level access', 'type': 'attacker'}, {'id': 'product:Accredible Certificates & Open Badges plugin for WordPress', 'keyphrase': 'Accredible Certificates & Open Badges plugin for WordPress', 'type': 'product'}]}, 'similarity': np.float64(171.50013131785246)}, {'metadata': {'doc_id': '863', 'name': 'Incorrect Authorization', 'source': 'sparse', 'original_content': 'The product performs an authorization check when an actor attempts to access a resource or perform an action, but it does not correctly perform the check.', 'keyphrase_sources': [{'id': 'impact:extract sensitive information from the database', 'keyphrase': 'extract sensitive information from the database', 'type': 'impact'}, {'id': 'attacker:authenticated attackers with Administrator-level access', 'keyphrase': 'authenticated attackers with Administrator-level access', 'type': 'attacker'}, {'id': 'product:Accredible Certificates & Open Badges plugin for WordPress', 'keyphrase': 'Accredible Certificates & Open Badges plugin for WordPress', 'type': 'product'}, {'id': 'version:all versions up to and including 1.4.9', 'keyphrase': 'all versions up to and including 1.4.9', 'type': 'version'}]}, 'similarity': np.float64(170.6507706102156)}], identified_cwes={'analyzer': [], 'critic_additional': []})",
  "retrieval_results": {
    "has_multiple_keyphrases": true,
    "keyphrase_cwe_sets": {
      "rootcause:insufficient escaping on the user supplied parameter and lack of sufficient preparation on the existing SQL query": {
        "keyphrase": "insufficient escaping on the user supplied parameter and lack of sufficient preparation on the existing SQL query",
        "type": "rootcause",
        "cwes": [
          {
            "metadata": {
              "doc_id": "116",
              "name": "Improper Encoding or Escaping of Output",
              "source": "sparse",
              "original_content": "The product prepares a structured message for communication with another component, but encoding or escaping of the data is either missing or done incorrectly. As a result, the intended structure of the message is not preserved.",
              "keyphrase_sources": [
                {
                  "id": "rootcause:insufficient escaping on the user supplied parameter and lack of sufficient preparation on the existing SQL query",
                  "keyphrase": "insufficient escaping on the user supplied parameter and lack of sufficient preparation on the existing SQL query",
                  "type": "rootcause"
                },
                {
                  "id": "rootcause:insufficient escaping on user supplied parameter",
                  "keyphrase": "insufficient escaping on user supplied parameter",
                  "type": "rootcause"
                },
                {
                  "id": "weakness:time-based SQL injection",
                  "keyphrase": "time-based SQL injection",
                  "type": "weakness"
                },
                {
                  "id": "impact:extract sensitive information from the database",
                  "keyphrase": "extract sensitive information from the database",
                  "type": "impact"
                },
                {
                  "id": "vector:orderby parameter",
                  "keyphrase": "orderby parameter",
                  "type": "vector"
                },
                {
                  "id": "attacker:authenticated attackers with Administrator-level access",
                  "keyphrase": "authenticated attackers with Administrator-level access",
                  "type": "attacker"
                },
                {
                  "id": "product:Accredible Certificates & Open Badges plugin for WordPress",
                  "keyphrase": "Accredible Certificates & Open Badges plugin for WordPress",
                  "type": "product"
                },
                {
                  "id": "version:all versions up to and including 1.4.9",
                  "keyphrase": "all versions up to and including 1.4.9",
                  "type": "version"
                }
              ]
            },
            "similarity": 757.173075143163
          },
          {
            "metadata": {
              "doc_id": "89",
              "name": "Improper Neutralization of Special Elements used in an SQL Command ('SQL Injection')",
              "source": "sparse",
              "original_content": "The product constructs all or part of an SQL command using externally-influenced input from an upstream component, but it does not neutralize or incorrectly neutralizes special elements that could modify the intended SQL command when it is sent to a downstream component. Without sufficient removal or quoting of SQL syntax in user-controllable inputs, the generated SQL query can cause those inputs to be interpreted as SQL instead of ordinary user data.",
              "keyphrase_sources": [
                {
                  "id": "rootcause:insufficient escaping on the user supplied parameter and lack of sufficient preparation on the existing SQL query",
                  "keyphrase": "insufficient escaping on the user supplied parameter and lack of sufficient preparation on the existing SQL query",
                  "type": "rootcause"
                },
                {
                  "id": "rootcause:insufficient escaping on user supplied parameter",
                  "keyphrase": "insufficient escaping on user supplied parameter",
                  "type": "rootcause"
                },
                {
                  "id": "weakness:time-based SQL injection",
                  "keyphrase": "time-based SQL injection",
                  "type": "weakness"
                },
                {
                  "id": "impact:extract sensitive information from the database",
                  "keyphrase": "extract sensitive information from the database",
                  "type": "impact"
                },
                {
                  "id": "vector:orderby parameter",
                  "keyphrase": "orderby parameter",
                  "type": "vector"
                },
                {
                  "id": "attacker:authenticated attackers with Administrator-level access",
                  "keyphrase": "authenticated attackers with Administrator-level access",
                  "type": "attacker"
                },
                {
                  "id": "product:Accredible Certificates & Open Badges plugin for WordPress",
                  "keyphrase": "Accredible Certificates & Open Badges plugin for WordPress",
                  "type": "product"
                },
                {
                  "id": "version:all versions up to and including 1.4.9",
                  "keyphrase": "all versions up to and including 1.4.9",
                  "type": "version"
                }
              ]
            },
            "similarity": 744.7034647559881
          },
          {
            "metadata": {
              "doc_id": "352",
              "name": "Cross-Site Request Forgery (CSRF)",
              "source": "sparse",
              "original_content": "The web application does not, or can not, sufficiently verify whether a well-formed, valid, consistent request was intentionally provided by the user who submitted the request.",
              "keyphrase_sources": [
                {
                  "id": "rootcause:insufficient escaping on the user supplied parameter and lack of sufficient preparation on the existing SQL query",
                  "keyphrase": "insufficient escaping on the user supplied parameter and lack of sufficient preparation on the existing SQL query",
                  "type": "rootcause"
                },
                {
                  "id": "rootcause:insufficient escaping on user supplied parameter",
                  "keyphrase": "insufficient escaping on user supplied parameter",
                  "type": "rootcause"
                },
                {
                  "id": "impact:extract sensitive information from the database",
                  "keyphrase": "extract sensitive information from the database",
                  "type": "impact"
                },
                {
                  "id": "vector:orderby parameter",
                  "keyphrase": "orderby parameter",
                  "type": "vector"
                },
                {
                  "id": "attacker:authenticated attackers with Administrator-level access",
                  "keyphrase": "authenticated attackers with Administrator-level access",
                  "type": "attacker"
                },
                {
                  "id": "product:Accredible Certificates & Open Badges plugin for WordPress",
                  "keyphrase": "Accredible Certificates & Open Badges plugin for WordPress",
                  "type": "product"
                },
                {
                  "id": "version:all versions up to and including 1.4.9",
                  "keyphrase": "all versions up to and including 1.4.9",
                  "type": "version"
                }
              ]
            },
            "similarity": 682.8840806779352
          },
          {
            "metadata": {
              "doc_id": "90",
              "name": "Improper Neutralization of Special Elements used in an LDAP Query ('LDAP Injection')",
              "source": "sparse",
              "original_content": "The product constructs all or part of an LDAP query using externally-influenced input from an upstream component, but it does not neutralize or incorrectly neutralizes special elements that could modify the intended LDAP query when it is sent to a downstream component.",
              "keyphrase_sources": [
                {
                  "id": "rootcause:insufficient escaping on the user supplied parameter and lack of sufficient preparation on the existing SQL query",
                  "keyphrase": "insufficient escaping on the user supplied parameter and lack of sufficient preparation on the existing SQL query",
                  "type": "rootcause"
                },
                {
                  "id": "rootcause:insufficient escaping on user supplied parameter",
                  "keyphrase": "insufficient escaping on user supplied parameter",
                  "type": "rootcause"
                },
                {
                  "id": "weakness:time-based SQL injection",
                  "keyphrase": "time-based SQL injection",
                  "type": "weakness"
                },
                {
                  "id": "impact:extract sensitive information from the database",
                  "keyphrase": "extract sensitive information from the database",
                  "type": "impact"
                },
                {
                  "id": "vector:orderby parameter",
                  "keyphrase": "orderby parameter",
                  "type": "vector"
                }
              ]
            },
            "similarity": 682.7973381262995
          },
          {
            "metadata": {
              "doc_id": "20",
              "name": "Improper Input Validation",
              "source": "sparse",
              "original_content": "The product receives input or data, but it does\n        not validate or incorrectly validates that the input has the\n        properties that are required to process the data safely and\n        correctly.",
              "keyphrase_sources": [
                {
                  "id": "rootcause:insufficient escaping on the user supplied parameter and lack of sufficient preparation on the existing SQL query",
                  "keyphrase": "insufficient escaping on the user supplied parameter and lack of sufficient preparation on the existing SQL query",
                  "type": "rootcause"
                }
              ]
            },
            "similarity": 649.1342952366622
          }
        ]
      },
      "rootcause:insufficient escaping on user supplied parameter": {
        "keyphrase": "insufficient escaping on user supplied parameter",
        "type": "rootcause",
        "cwes": [
          {
            "metadata": {
              "doc_id": "116",
              "name": "Improper Encoding or Escaping of Output",
              "source": "sparse",
              "original_content": "The product prepares a structured message for communication with another component, but encoding or escaping of the data is either missing or done incorrectly. As a result, the intended structure of the message is not preserved."
            },
            "similarity": 614.6848388775281
          },
          {
            "metadata": {
              "doc_id": "89",
              "name": "Improper Neutralization of Special Elements used in an SQL Command ('SQL Injection')",
              "source": "sparse",
              "original_content": "The product constructs all or part of an SQL command using externally-influenced input from an upstream component, but it does not neutralize or incorrectly neutralizes special elements that could modify the intended SQL command when it is sent to a downstream component. Without sufficient removal or quoting of SQL syntax in user-controllable inputs, the generated SQL query can cause those inputs to be interpreted as SQL instead of ordinary user data."
            },
            "similarity": 575.8898054891346
          },
          {
            "metadata": {
              "doc_id": "352",
              "name": "Cross-Site Request Forgery (CSRF)",
              "source": "sparse",
              "original_content": "The web application does not, or can not, sufficiently verify whether a well-formed, valid, consistent request was intentionally provided by the user who submitted the request."
            },
            "similarity": 541.215015962883
          },
          {
            "metadata": {
              "doc_id": "90",
              "name": "Improper Neutralization of Special Elements used in an LDAP Query ('LDAP Injection')",
              "source": "sparse",
              "original_content": "The product constructs all or part of an LDAP query using externally-influenced input from an upstream component, but it does not neutralize or incorrectly neutralizes special elements that could modify the intended LDAP query when it is sent to a downstream component."
            },
            "similarity": 540.3389660149097
          },
          {
            "metadata": {
              "doc_id": "790",
              "name": "Improper Filtering of Special Elements",
              "source": "sparse",
              "original_content": "The product receives data from an upstream component, but does not filter or incorrectly filters special elements before sending it to a downstream component.",
              "keyphrase_sources": [
                {
                  "id": "rootcause:insufficient escaping on user supplied parameter",
                  "keyphrase": "insufficient escaping on user supplied parameter",
                  "type": "rootcause"
                },
                {
                  "id": "vector:orderby parameter",
                  "keyphrase": "orderby parameter",
                  "type": "vector"
                }
              ]
            },
            "similarity": 526.6065398513887
          }
        ]
      },
      "weakness:time-based SQL injection": {
        "keyphrase": "time-based SQL injection",
        "type": "weakness",
        "cwes": [
          {
            "metadata": {
              "doc_id": "89",
              "name": "Improper Neutralization of Special Elements used in an SQL Command ('SQL Injection')",
              "source": "sparse",
              "original_content": "The product constructs all or part of an SQL command using externally-influenced input from an upstream component, but it does not neutralize or incorrectly neutralizes special elements that could modify the intended SQL command when it is sent to a downstream component. Without sufficient removal or quoting of SQL syntax in user-controllable inputs, the generated SQL query can cause those inputs to be interpreted as SQL instead of ordinary user data."
            },
            "similarity": 556.0965940052422
          },
          {
            "metadata": {
              "doc_id": "116",
              "name": "Improper Encoding or Escaping of Output",
              "source": "sparse",
              "original_content": "The product prepares a structured message for communication with another component, but encoding or escaping of the data is either missing or done incorrectly. As a result, the intended structure of the message is not preserved."
            },
            "similarity": 506.5616516055005
          },
          {
            "metadata": {
              "doc_id": "502",
              "name": "Deserialization of Untrusted Data",
              "source": "sparse",
              "original_content": "The product deserializes untrusted data without sufficiently ensuring that the resulting data will be valid.",
              "keyphrase_sources": [
                {
                  "id": "weakness:time-based SQL injection",
                  "keyphrase": "time-based SQL injection",
                  "type": "weakness"
                },
                {
                  "id": "version:all versions up to and including 1.4.9",
                  "keyphrase": "all versions up to and including 1.4.9",
                  "type": "version"
                }
              ]
            },
            "similarity": 468.012978897068
          },
          {
            "metadata": {
              "doc_id": "90",
              "name": "Improper Neutralization of Special Elements used in an LDAP Query ('LDAP Injection')",
              "source": "sparse",
              "original_content": "The product constructs all or part of an LDAP query using externally-influenced input from an upstream component, but it does not neutralize or incorrectly neutralizes special elements that could modify the intended LDAP query when it is sent to a downstream component."
            },
            "similarity": 459.80263100615616
          },
          {
            "metadata": {
              "doc_id": "138",
              "name": "Improper Neutralization of Special Elements",
              "source": "sparse",
              "original_content": "The product receives input from an upstream component, but it does not neutralize or incorrectly neutralizes special elements that could be interpreted as control elements or syntactic markers when they are sent to a downstream component.",
              "keyphrase_sources": [
                {
                  "id": "weakness:time-based SQL injection",
                  "keyphrase": "time-based SQL injection",
                  "type": "weakness"
                }
              ]
            },
            "similarity": 452.410584822661
          }
        ]
      },
      "impact:extract sensitive information from the database": {
        "keyphrase": "extract sensitive information from the database",
        "type": "impact",
        "cwes": [
          {
            "metadata": {
              "doc_id": "89",
              "name": "Improper Neutralization of Special Elements used in an SQL Command ('SQL Injection')",
              "source": "sparse",
              "original_content": "The product constructs all or part of an SQL command using externally-influenced input from an upstream component, but it does not neutralize or incorrectly neutralizes special elements that could modify the intended SQL command when it is sent to a downstream component. Without sufficient removal or quoting of SQL syntax in user-controllable inputs, the generated SQL query can cause those inputs to be interpreted as SQL instead of ordinary user data."
            },
            "similarity": 199.40794163272585
          },
          {
            "metadata": {
              "doc_id": "116",
              "name": "Improper Encoding or Escaping of Output",
              "source": "sparse",
              "original_content": "The product prepares a structured message for communication with another component, but encoding or escaping of the data is either missing or done incorrectly. As a result, the intended structure of the message is not preserved."
            },
            "similarity": 179.40749178574558
          },
          {
            "metadata": {
              "doc_id": "90",
              "name": "Improper Neutralization of Special Elements used in an LDAP Query ('LDAP Injection')",
              "source": "sparse",
              "original_content": "The product constructs all or part of an LDAP query using externally-influenced input from an upstream component, but it does not neutralize or incorrectly neutralizes special elements that could modify the intended LDAP query when it is sent to a downstream component."
            },
            "similarity": 173.069702217575
          },
          {
            "metadata": {
              "doc_id": "863",
              "name": "Incorrect Authorization",
              "source": "sparse",
              "original_content": "The product performs an authorization check when an actor attempts to access a resource or perform an action, but it does not correctly perform the check.",
              "keyphrase_sources": [
                {
                  "id": "impact:extract sensitive information from the database",
                  "keyphrase": "extract sensitive information from the database",
                  "type": "impact"
                },
                {
                  "id": "attacker:authenticated attackers with Administrator-level access",
                  "keyphrase": "authenticated attackers with Administrator-level access",
                  "type": "attacker"
                },
                {
                  "id": "product:Accredible Certificates & Open Badges plugin for WordPress",
                  "keyphrase": "Accredible Certificates & Open Badges plugin for WordPress",
                  "type": "product"
                },
                {
                  "id": "version:all versions up to and including 1.4.9",
                  "keyphrase": "all versions up to and including 1.4.9",
                  "type": "version"
                }
              ]
            },
            "similarity": 170.6507706102156
          },
          {
            "metadata": {
              "doc_id": "352",
              "name": "Cross-Site Request Forgery (CSRF)",
              "source": "sparse",
              "original_content": "The web application does not, or can not, sufficiently verify whether a well-formed, valid, consistent request was intentionally provided by the user who submitted the request."
            },
            "similarity": 167.4745307330154
          }
        ]
      },
      "vector:orderby parameter": {
        "keyphrase": "orderby parameter",
        "type": "vector",
        "cwes": [
          {
            "metadata": {
              "doc_id": "89",
              "name": "Improper Neutralization of Special Elements used in an SQL Command ('SQL Injection')",
              "source": "sparse",
              "original_content": "The product constructs all or part of an SQL command using externally-influenced input from an upstream component, but it does not neutralize or incorrectly neutralizes special elements that could modify the intended SQL command when it is sent to a downstream component. Without sufficient removal or quoting of SQL syntax in user-controllable inputs, the generated SQL query can cause those inputs to be interpreted as SQL instead of ordinary user data."
            },
            "similarity": 187.1273745317568
          },
          {
            "metadata": {
              "doc_id": "116",
              "name": "Improper Encoding or Escaping of Output",
              "source": "sparse",
              "original_content": "The product prepares a structured message for communication with another component, but encoding or escaping of the data is either missing or done incorrectly. As a result, the intended structure of the message is not preserved."
            },
            "similarity": 172.16239037573425
          },
          {
            "metadata": {
              "doc_id": "90",
              "name": "Improper Neutralization of Special Elements used in an LDAP Query ('LDAP Injection')",
              "source": "sparse",
              "original_content": "The product constructs all or part of an LDAP query using externally-influenced input from an upstream component, but it does not neutralize or incorrectly neutralizes special elements that could modify the intended LDAP query when it is sent to a downstream component."
            },
            "similarity": 160.2451756263742
          },
          {
            "metadata": {
              "doc_id": "352",
              "name": "Cross-Site Request Forgery (CSRF)",
              "source": "sparse",
              "original_content": "The web application does not, or can not, sufficiently verify whether a well-formed, valid, consistent request was intentionally provided by the user who submitted the request."
            },
            "similarity": 157.71730886299792
          },
          {
            "metadata": {
              "doc_id": "790",
              "name": "Improper Filtering of Special Elements",
              "source": "sparse",
              "original_content": "The product receives data from an upstream component, but does not filter or incorrectly filters special elements before sending it to a downstream component."
            },
            "similarity": 157.30393900952143
          }
        ]
      },
      "attacker:authenticated attackers with Administrator-level access": {
        "keyphrase": "authenticated attackers with Administrator-level access",
        "type": "attacker",
        "cwes": [
          {
            "metadata": {
              "doc_id": "89",
              "name": "Improper Neutralization of Special Elements used in an SQL Command ('SQL Injection')",
              "source": "sparse",
              "original_content": "The product constructs all or part of an SQL command using externally-influenced input from an upstream component, but it does not neutralize or incorrectly neutralizes special elements that could modify the intended SQL command when it is sent to a downstream component. Without sufficient removal or quoting of SQL syntax in user-controllable inputs, the generated SQL query can cause those inputs to be interpreted as SQL instead of ordinary user data."
            },
            "similarity": 195.32899681631744
          },
          {
            "metadata": {
              "doc_id": "116",
              "name": "Improper Encoding or Escaping of Output",
              "source": "sparse",
              "original_content": "The product prepares a structured message for communication with another component, but encoding or escaping of the data is either missing or done incorrectly. As a result, the intended structure of the message is not preserved."
            },
            "similarity": 182.61504903660054
          },
          {
            "metadata": {
              "doc_id": "863",
              "name": "Incorrect Authorization",
              "source": "sparse",
              "original_content": "The product performs an authorization check when an actor attempts to access a resource or perform an action, but it does not correctly perform the check."
            },
            "similarity": 178.9648141518166
          },
          {
            "metadata": {
              "doc_id": "352",
              "name": "Cross-Site Request Forgery (CSRF)",
              "source": "sparse",
              "original_content": "The web application does not, or can not, sufficiently verify whether a well-formed, valid, consistent request was intentionally provided by the user who submitted the request."
            },
            "similarity": 176.7268488338555
          },
          {
            "metadata": {
              "doc_id": "862",
              "name": "Missing Authorization",
              "source": "sparse",
              "original_content": "The product does not perform an authorization check when an actor attempts to access a resource or perform an action.",
              "keyphrase_sources": [
                {
                  "id": "attacker:authenticated attackers with Administrator-level access",
                  "keyphrase": "authenticated attackers with Administrator-level access",
                  "type": "attacker"
                },
                {
                  "id": "product:Accredible Certificates & Open Badges plugin for WordPress",
                  "keyphrase": "Accredible Certificates & Open Badges plugin for WordPress",
                  "type": "product"
                }
              ]
            },
            "similarity": 171.50013131785246
          }
        ]
      },
      "product:Accredible Certificates & Open Badges plugin for WordPress": {
        "keyphrase": "Accredible Certificates & Open Badges plugin for WordPress",
        "type": "product",
        "cwes": [
          {
            "metadata": {
              "doc_id": "89",
              "name": "Improper Neutralization of Special Elements used in an SQL Command ('SQL Injection')",
              "source": "sparse",
              "original_content": "The product constructs all or part of an SQL command using externally-influenced input from an upstream component, but it does not neutralize or incorrectly neutralizes special elements that could modify the intended SQL command when it is sent to a downstream component. Without sufficient removal or quoting of SQL syntax in user-controllable inputs, the generated SQL query can cause those inputs to be interpreted as SQL instead of ordinary user data."
            },
            "similarity": 192.36190913215648
          },
          {
            "metadata": {
              "doc_id": "116",
              "name": "Improper Encoding or Escaping of Output",
              "source": "sparse",
              "original_content": "The product prepares a structured message for communication with another component, but encoding or escaping of the data is either missing or done incorrectly. As a result, the intended structure of the message is not preserved."
            },
            "similarity": 191.15946371798697
          },
          {
            "metadata": {
              "doc_id": "352",
              "name": "Cross-Site Request Forgery (CSRF)",
              "source": "sparse",
              "original_content": "The web application does not, or can not, sufficiently verify whether a well-formed, valid, consistent request was intentionally provided by the user who submitted the request."
            },
            "similarity": 186.76491442702968
          },
          {
            "metadata": {
              "doc_id": "863",
              "name": "Incorrect Authorization",
              "source": "sparse",
              "original_content": "The product performs an authorization check when an actor attempts to access a resource or perform an action, but it does not correctly perform the check."
            },
            "similarity": 181.15718649708433
          },
          {
            "metadata": {
              "doc_id": "862",
              "name": "Missing Authorization",
              "source": "sparse",
              "original_content": "The product does not perform an authorization check when an actor attempts to access a resource or perform an action."
            },
            "similarity": 175.5095080918434
          }
        ]
      },
      "version:all versions up to and including 1.4.9": {
        "keyphrase": "all versions up to and including 1.4.9",
        "type": "version",
        "cwes": [
          {
            "metadata": {
              "doc_id": "116",
              "name": "Improper Encoding or Escaping of Output",
              "source": "sparse",
              "original_content": "The product prepares a structured message for communication with another component, but encoding or escaping of the data is either missing or done incorrectly. As a result, the intended structure of the message is not preserved."
            },
            "similarity": 199.17867839918804
          },
          {
            "metadata": {
              "doc_id": "89",
              "name": "Improper Neutralization of Special Elements used in an SQL Command ('SQL Injection')",
              "source": "sparse",
              "original_content": "The product constructs all or part of an SQL command using externally-influenced input from an upstream component, but it does not neutralize or incorrectly neutralizes special elements that could modify the intended SQL command when it is sent to a downstream component. Without sufficient removal or quoting of SQL syntax in user-controllable inputs, the generated SQL query can cause those inputs to be interpreted as SQL instead of ordinary user data."
            },
            "similarity": 198.84209590654336
          },
          {
            "metadata": {
              "doc_id": "352",
              "name": "Cross-Site Request Forgery (CSRF)",
              "source": "sparse",
              "original_content": "The web application does not, or can not, sufficiently verify whether a well-formed, valid, consistent request was intentionally provided by the user who submitted the request."
            },
            "similarity": 186.59607636906549
          },
          {
            "metadata": {
              "doc_id": "863",
              "name": "Incorrect Authorization",
              "source": "sparse",
              "original_content": "The product performs an authorization check when an actor attempts to access a resource or perform an action, but it does not correctly perform the check."
            },
            "similarity": 184.57360821879456
          },
          {
            "metadata": {
              "doc_id": "502",
              "name": "Deserialization of Untrusted Data",
              "source": "sparse",
              "original_content": "The product deserializes untrusted data without sufficiently ensuring that the resulting data will be valid."
            },
            "similarity": 184.1951020797293
          }
        ]
      }
    },
    "keyphrase_mapping": {
      "116": [
        {
          "id": "rootcause:insufficient escaping on the user supplied parameter and lack of sufficient preparation on the existing SQL query",
          "keyphrase": "insufficient escaping on the user supplied parameter and lack of sufficient preparation on the existing SQL query",
          "type": "rootcause"
        },
        {
          "id": "rootcause:insufficient escaping on user supplied parameter",
          "keyphrase": "insufficient escaping on user supplied parameter",
          "type": "rootcause"
        },
        {
          "id": "weakness:time-based SQL injection",
          "keyphrase": "time-based SQL injection",
          "type": "weakness"
        },
        {
          "id": "impact:extract sensitive information from the database",
          "keyphrase": "extract sensitive information from the database",
          "type": "impact"
        },
        {
          "id": "vector:orderby parameter",
          "keyphrase": "orderby parameter",
          "type": "vector"
        },
        {
          "id": "attacker:authenticated attackers with Administrator-level access",
          "keyphrase": "authenticated attackers with Administrator-level access",
          "type": "attacker"
        },
        {
          "id": "product:Accredible Certificates & Open Badges plugin for WordPress",
          "keyphrase": "Accredible Certificates & Open Badges plugin for WordPress",
          "type": "product"
        },
        {
          "id": "version:all versions up to and including 1.4.9",
          "keyphrase": "all versions up to and including 1.4.9",
          "type": "version"
        }
      ],
      "89": [
        {
          "id": "rootcause:insufficient escaping on the user supplied parameter and lack of sufficient preparation on the existing SQL query",
          "keyphrase": "insufficient escaping on the user supplied parameter and lack of sufficient preparation on the existing SQL query",
          "type": "rootcause"
        },
        {
          "id": "rootcause:insufficient escaping on user supplied parameter",
          "keyphrase": "insufficient escaping on user supplied parameter",
          "type": "rootcause"
        },
        {
          "id": "weakness:time-based SQL injection",
          "keyphrase": "time-based SQL injection",
          "type": "weakness"
        },
        {
          "id": "impact:extract sensitive information from the database",
          "keyphrase": "extract sensitive information from the database",
          "type": "impact"
        },
        {
          "id": "vector:orderby parameter",
          "keyphrase": "orderby parameter",
          "type": "vector"
        },
        {
          "id": "attacker:authenticated attackers with Administrator-level access",
          "keyphrase": "authenticated attackers with Administrator-level access",
          "type": "attacker"
        },
        {
          "id": "product:Accredible Certificates & Open Badges plugin for WordPress",
          "keyphrase": "Accredible Certificates & Open Badges plugin for WordPress",
          "type": "product"
        },
        {
          "id": "version:all versions up to and including 1.4.9",
          "keyphrase": "all versions up to and including 1.4.9",
          "type": "version"
        }
      ],
      "352": [
        {
          "id": "rootcause:insufficient escaping on the user supplied parameter and lack of sufficient preparation on the existing SQL query",
          "keyphrase": "insufficient escaping on the user supplied parameter and lack of sufficient preparation on the existing SQL query",
          "type": "rootcause"
        },
        {
          "id": "rootcause:insufficient escaping on user supplied parameter",
          "keyphrase": "insufficient escaping on user supplied parameter",
          "type": "rootcause"
        },
        {
          "id": "impact:extract sensitive information from the database",
          "keyphrase": "extract sensitive information from the database",
          "type": "impact"
        },
        {
          "id": "vector:orderby parameter",
          "keyphrase": "orderby parameter",
          "type": "vector"
        },
        {
          "id": "attacker:authenticated attackers with Administrator-level access",
          "keyphrase": "authenticated attackers with Administrator-level access",
          "type": "attacker"
        },
        {
          "id": "product:Accredible Certificates & Open Badges plugin for WordPress",
          "keyphrase": "Accredible Certificates & Open Badges plugin for WordPress",
          "type": "product"
        },
        {
          "id": "version:all versions up to and including 1.4.9",
          "keyphrase": "all versions up to and including 1.4.9",
          "type": "version"
        }
      ],
      "90": [
        {
          "id": "rootcause:insufficient escaping on the user supplied parameter and lack of sufficient preparation on the existing SQL query",
          "keyphrase": "insufficient escaping on the user supplied parameter and lack of sufficient preparation on the existing SQL query",
          "type": "rootcause"
        },
        {
          "id": "rootcause:insufficient escaping on user supplied parameter",
          "keyphrase": "insufficient escaping on user supplied parameter",
          "type": "rootcause"
        },
        {
          "id": "weakness:time-based SQL injection",
          "keyphrase": "time-based SQL injection",
          "type": "weakness"
        },
        {
          "id": "impact:extract sensitive information from the database",
          "keyphrase": "extract sensitive information from the database",
          "type": "impact"
        },
        {
          "id": "vector:orderby parameter",
          "keyphrase": "orderby parameter",
          "type": "vector"
        }
      ],
      "20": [
        {
          "id": "rootcause:insufficient escaping on the user supplied parameter and lack of sufficient preparation on the existing SQL query",
          "keyphrase": "insufficient escaping on the user supplied parameter and lack of sufficient preparation on the existing SQL query",
          "type": "rootcause"
        }
      ],
      "790": [
        {
          "id": "rootcause:insufficient escaping on user supplied parameter",
          "keyphrase": "insufficient escaping on user supplied parameter",
          "type": "rootcause"
        },
        {
          "id": "vector:orderby parameter",
          "keyphrase": "orderby parameter",
          "type": "vector"
        }
      ],
      "502": [
        {
          "id": "weakness:time-based SQL injection",
          "keyphrase": "time-based SQL injection",
          "type": "weakness"
        },
        {
          "id": "version:all versions up to and including 1.4.9",
          "keyphrase": "all versions up to and including 1.4.9",
          "type": "version"
        }
      ],
      "138": [
        {
          "id": "weakness:time-based SQL injection",
          "keyphrase": "time-based SQL injection",
          "type": "weakness"
        }
      ],
      "863": [
        {
          "id": "impact:extract sensitive information from the database",
          "keyphrase": "extract sensitive information from the database",
          "type": "impact"
        },
        {
          "id": "attacker:authenticated attackers with Administrator-level access",
          "keyphrase": "authenticated attackers with Administrator-level access",
          "type": "attacker"
        },
        {
          "id": "product:Accredible Certificates & Open Badges plugin for WordPress",
          "keyphrase": "Accredible Certificates & Open Badges plugin for WordPress",
          "type": "product"
        },
        {
          "id": "version:all versions up to and including 1.4.9",
          "keyphrase": "all versions up to and including 1.4.9",
          "type": "version"
        }
      ],
      "862": [
        {
          "id": "attacker:authenticated attackers with Administrator-level access",
          "keyphrase": "authenticated attackers with Administrator-level access",
          "type": "attacker"
        },
        {
          "id": "product:Accredible Certificates & Open Badges plugin for WordPress",
          "keyphrase": "Accredible Certificates & Open Badges plugin for WordPress",
          "type": "product"
        }
      ]
    },
    "relevant_cwes": [
      {
        "metadata": {
          "doc_id": "116",
          "name": "Improper Encoding or Escaping of Output",
          "source": "sparse",
          "original_content": "The product prepares a structured message for communication with another component, but encoding or escaping of the data is either missing or done incorrectly. As a result, the intended structure of the message is not preserved.",
          "keyphrase_sources": [
            {
              "id": "rootcause:insufficient escaping on the user supplied parameter and lack of sufficient preparation on the existing SQL query",
              "keyphrase": "insufficient escaping on the user supplied parameter and lack of sufficient preparation on the existing SQL query",
              "type": "rootcause"
            },
            {
              "id": "rootcause:insufficient escaping on user supplied parameter",
              "keyphrase": "insufficient escaping on user supplied parameter",
              "type": "rootcause"
            },
            {
              "id": "weakness:time-based SQL injection",
              "keyphrase": "time-based SQL injection",
              "type": "weakness"
            },
            {
              "id": "impact:extract sensitive information from the database",
              "keyphrase": "extract sensitive information from the database",
              "type": "impact"
            },
            {
              "id": "vector:orderby parameter",
              "keyphrase": "orderby parameter",
              "type": "vector"
            },
            {
              "id": "attacker:authenticated attackers with Administrator-level access",
              "keyphrase": "authenticated attackers with Administrator-level access",
              "type": "attacker"
            },
            {
              "id": "product:Accredible Certificates & Open Badges plugin for WordPress",
              "keyphrase": "Accredible Certificates & Open Badges plugin for WordPress",
              "type": "product"
            },
            {
              "id": "version:all versions up to and including 1.4.9",
              "keyphrase": "all versions up to and including 1.4.9",
              "type": "version"
            }
          ]
        },
        "similarity": 757.173075143163
      },
      {
        "metadata": {
          "doc_id": "89",
          "name": "Improper Neutralization of Special Elements used in an SQL Command ('SQL Injection')",
          "source": "sparse",
          "original_content": "The product constructs all or part of an SQL command using externally-influenced input from an upstream component, but it does not neutralize or incorrectly neutralizes special elements that could modify the intended SQL command when it is sent to a downstream component. Without sufficient removal or quoting of SQL syntax in user-controllable inputs, the generated SQL query can cause those inputs to be interpreted as SQL instead of ordinary user data.",
          "keyphrase_sources": [
            {
              "id": "rootcause:insufficient escaping on the user supplied parameter and lack of sufficient preparation on the existing SQL query",
              "keyphrase": "insufficient escaping on the user supplied parameter and lack of sufficient preparation on the existing SQL query",
              "type": "rootcause"
            },
            {
              "id": "rootcause:insufficient escaping on user supplied parameter",
              "keyphrase": "insufficient escaping on user supplied parameter",
              "type": "rootcause"
            },
            {
              "id": "weakness:time-based SQL injection",
              "keyphrase": "time-based SQL injection",
              "type": "weakness"
            },
            {
              "id": "impact:extract sensitive information from the database",
              "keyphrase": "extract sensitive information from the database",
              "type": "impact"
            },
            {
              "id": "vector:orderby parameter",
              "keyphrase": "orderby parameter",
              "type": "vector"
            },
            {
              "id": "attacker:authenticated attackers with Administrator-level access",
              "keyphrase": "authenticated attackers with Administrator-level access",
              "type": "attacker"
            },
            {
              "id": "product:Accredible Certificates & Open Badges plugin for WordPress",
              "keyphrase": "Accredible Certificates & Open Badges plugin for WordPress",
              "type": "product"
            },
            {
              "id": "version:all versions up to and including 1.4.9",
              "keyphrase": "all versions up to and including 1.4.9",
              "type": "version"
            }
          ]
        },
        "similarity": 744.7034647559881
      },
      {
        "metadata": {
          "doc_id": "352",
          "name": "Cross-Site Request Forgery (CSRF)",
          "source": "sparse",
          "original_content": "The web application does not, or can not, sufficiently verify whether a well-formed, valid, consistent request was intentionally provided by the user who submitted the request.",
          "keyphrase_sources": [
            {
              "id": "rootcause:insufficient escaping on the user supplied parameter and lack of sufficient preparation on the existing SQL query",
              "keyphrase": "insufficient escaping on the user supplied parameter and lack of sufficient preparation on the existing SQL query",
              "type": "rootcause"
            },
            {
              "id": "rootcause:insufficient escaping on user supplied parameter",
              "keyphrase": "insufficient escaping on user supplied parameter",
              "type": "rootcause"
            },
            {
              "id": "impact:extract sensitive information from the database",
              "keyphrase": "extract sensitive information from the database",
              "type": "impact"
            },
            {
              "id": "vector:orderby parameter",
              "keyphrase": "orderby parameter",
              "type": "vector"
            },
            {
              "id": "attacker:authenticated attackers with Administrator-level access",
              "keyphrase": "authenticated attackers with Administrator-level access",
              "type": "attacker"
            },
            {
              "id": "product:Accredible Certificates & Open Badges plugin for WordPress",
              "keyphrase": "Accredible Certificates & Open Badges plugin for WordPress",
              "type": "product"
            },
            {
              "id": "version:all versions up to and including 1.4.9",
              "keyphrase": "all versions up to and including 1.4.9",
              "type": "version"
            }
          ]
        },
        "similarity": 682.8840806779352
      },
      {
        "metadata": {
          "doc_id": "90",
          "name": "Improper Neutralization of Special Elements used in an LDAP Query ('LDAP Injection')",
          "source": "sparse",
          "original_content": "The product constructs all or part of an LDAP query using externally-influenced input from an upstream component, but it does not neutralize or incorrectly neutralizes special elements that could modify the intended LDAP query when it is sent to a downstream component.",
          "keyphrase_sources": [
            {
              "id": "rootcause:insufficient escaping on the user supplied parameter and lack of sufficient preparation on the existing SQL query",
              "keyphrase": "insufficient escaping on the user supplied parameter and lack of sufficient preparation on the existing SQL query",
              "type": "rootcause"
            },
            {
              "id": "rootcause:insufficient escaping on user supplied parameter",
              "keyphrase": "insufficient escaping on user supplied parameter",
              "type": "rootcause"
            },
            {
              "id": "weakness:time-based SQL injection",
              "keyphrase": "time-based SQL injection",
              "type": "weakness"
            },
            {
              "id": "impact:extract sensitive information from the database",
              "keyphrase": "extract sensitive information from the database",
              "type": "impact"
            },
            {
              "id": "vector:orderby parameter",
              "keyphrase": "orderby parameter",
              "type": "vector"
            }
          ]
        },
        "similarity": 682.7973381262995
      },
      {
        "metadata": {
          "doc_id": "20",
          "name": "Improper Input Validation",
          "source": "sparse",
          "original_content": "The product receives input or data, but it does\n        not validate or incorrectly validates that the input has the\n        properties that are required to process the data safely and\n        correctly.",
          "keyphrase_sources": [
            {
              "id": "rootcause:insufficient escaping on the user supplied parameter and lack of sufficient preparation on the existing SQL query",
              "keyphrase": "insufficient escaping on the user supplied parameter and lack of sufficient preparation on the existing SQL query",
              "type": "rootcause"
            }
          ]
        },
        "similarity": 649.1342952366622
      },
      {
        "metadata": {
          "doc_id": "790",
          "name": "Improper Filtering of Special Elements",
          "source": "sparse",
          "original_content": "The product receives data from an upstream component, but does not filter or incorrectly filters special elements before sending it to a downstream component.",
          "keyphrase_sources": [
            {
              "id": "rootcause:insufficient escaping on user supplied parameter",
              "keyphrase": "insufficient escaping on user supplied parameter",
              "type": "rootcause"
            },
            {
              "id": "vector:orderby parameter",
              "keyphrase": "orderby parameter",
              "type": "vector"
            }
          ]
        },
        "similarity": 526.6065398513887
      },
      {
        "metadata": {
          "doc_id": "502",
          "name": "Deserialization of Untrusted Data",
          "source": "sparse",
          "original_content": "The product deserializes untrusted data without sufficiently ensuring that the resulting data will be valid.",
          "keyphrase_sources": [
            {
              "id": "weakness:time-based SQL injection",
              "keyphrase": "time-based SQL injection",
              "type": "weakness"
            },
            {
              "id": "version:all versions up to and including 1.4.9",
              "keyphrase": "all versions up to and including 1.4.9",
              "type": "version"
            }
          ]
        },
        "similarity": 468.012978897068
      },
      {
        "metadata": {
          "doc_id": "138",
          "name": "Improper Neutralization of Special Elements",
          "source": "sparse",
          "original_content": "The product receives input from an upstream component, but it does not neutralize or incorrectly neutralizes special elements that could be interpreted as control elements or syntactic markers when they are sent to a downstream component.",
          "keyphrase_sources": [
            {
              "id": "weakness:time-based SQL injection",
              "keyphrase": "time-based SQL injection",
              "type": "weakness"
            }
          ]
        },
        "similarity": 452.410584822661
      },
      {
        "metadata": {
          "doc_id": "862",
          "name": "Missing Authorization",
          "source": "sparse",
          "original_content": "The product does not perform an authorization check when an actor attempts to access a resource or perform an action.",
          "keyphrase_sources": [
            {
              "id": "attacker:authenticated attackers with Administrator-level access",
              "keyphrase": "authenticated attackers with Administrator-level access",
              "type": "attacker"
            },
            {
              "id": "product:Accredible Certificates & Open Badges plugin for WordPress",
              "keyphrase": "Accredible Certificates & Open Badges plugin for WordPress",
              "type": "product"
            }
          ]
        },
        "similarity": 171.50013131785246
      },
      {
        "metadata": {
          "doc_id": "863",
          "name": "Incorrect Authorization",
          "source": "sparse",
          "original_content": "The product performs an authorization check when an actor attempts to access a resource or perform an action, but it does not correctly perform the check.",
          "keyphrase_sources": [
            {
              "id": "impact:extract sensitive information from the database",
              "keyphrase": "extract sensitive information from the database",
              "type": "impact"
            },
            {
              "id": "attacker:authenticated attackers with Administrator-level access",
              "keyphrase": "authenticated attackers with Administrator-level access",
              "type": "attacker"
            },
            {
              "id": "product:Accredible Certificates & Open Badges plugin for WordPress",
              "keyphrase": "Accredible Certificates & Open Badges plugin for WordPress",
              "type": "product"
            },
            {
              "id": "version:all versions up to and including 1.4.9",
              "keyphrase": "all versions up to and including 1.4.9",
              "type": "version"
            }
          ]
        },
        "similarity": 170.6507706102156
      }
    ],
    "enhanced_query": "# Vulnerability Description\n\n    The Accredible Certificates & Open Badges plugin for WordPress is vulnerable to time-based SQL Injection via the orderby parameter in all versions up to, and including, 1.4.9 due to **insufficient escaping on the user supplied parameter and lack of sufficient preparation on the existing SQL query**. This makes it possible for authenticated attackers, with Administrator-level access and above, to append additional SQL queries into already existing queries that can be used to extract sensitive information from the database.\n\n    # Keyphrase-Specific CWE Analysis\n    This vulnerability contains multiple keyphrases that may map to different CWEs. \n    Please analyze each keyphrase separately and determine the most appropriate CWE(s) for each.\n\n    ## ROOTCAUSE: 'insufficient escaping on the user supplied parameter and lack of sufficient preparation on the existing SQL query'\n\nRelevant CWEs for this ROOTCAUSE:\n\n### 1. CWE-116: Improper Encoding or Escaping of Output (Score: 757.17)\n\nThe product prepares a structured message for communication with another component, but encoding or escaping of the data is either missing or done incorrectly. As a result, the intended structure of the message is not preserved....\n\n### 2. CWE-89: Improper Neutralization of Special Elements used in an SQL Command ('SQL Injection') (Score: 744.70)\n\nThe product constructs all or part of an SQL command using externally-influenced input from an upstream component, but it does not neutralize or incorrectly neutralizes special elements that could modify the intended SQL command when it is sent to a downstream component. Without sufficient removal o...\n\n### 3. CWE-352: Cross-Site Request Forgery (CSRF) (Score: 682.88)\n\nThe web application does not, or can not, sufficiently verify whether a well-formed, valid, consistent request was intentionally provided by the user who submitted the request....\n\n### 4. CWE-90: Improper Neutralization of Special Elements used in an LDAP Query ('LDAP Injection') (Score: 682.80)\n\nThe product constructs all or part of an LDAP query using externally-influenced input from an upstream component, but it does not neutralize or incorrectly neutralizes special elements that could modify the intended LDAP query when it is sent to a downstream component....\n\n### 5. CWE-20: Improper Input Validation (Score: 649.13)\n\nThe product receives input or data, but it does\n        not validate or incorrectly validates that the input has the\n        properties that are required to process the data safely and\n        correctly....\n\n## ROOTCAUSE: 'insufficient escaping on user supplied parameter'\n\nRelevant CWEs for this ROOTCAUSE:\n\n### 1. CWE-116: Improper Encoding or Escaping of Output (Score: 757.17)\n\nThe product prepares a structured message for communication with another component, but encoding or escaping of the data is either missing or done incorrectly. As a result, the intended structure of the message is not preserved....\n\n### 2. CWE-89: Improper Neutralization of Special Elements used in an SQL Command ('SQL Injection') (Score: 744.70)\n\nThe product constructs all or part of an SQL command using externally-influenced input from an upstream component, but it does not neutralize or incorrectly neutralizes special elements that could modify the intended SQL command when it is sent to a downstream component. Without sufficient removal o...\n\n### 3. CWE-352: Cross-Site Request Forgery (CSRF) (Score: 682.88)\n\nThe web application does not, or can not, sufficiently verify whether a well-formed, valid, consistent request was intentionally provided by the user who submitted the request....\n\n### 4. CWE-90: Improper Neutralization of Special Elements used in an LDAP Query ('LDAP Injection') (Score: 682.80)\n\nThe product constructs all or part of an LDAP query using externally-influenced input from an upstream component, but it does not neutralize or incorrectly neutralizes special elements that could modify the intended LDAP query when it is sent to a downstream component....\n\n### 5. CWE-790: Improper Filtering of Special Elements (Score: 526.61)\n\nThe product receives data from an upstream component, but does not filter or incorrectly filters special elements before sending it to a downstream component....\n\n## WEAKNESS: 'time-based SQL injection'\n\nRelevant CWEs for this WEAKNESS:\n\n### 1. CWE-116: Improper Encoding or Escaping of Output (Score: 757.17)\n\nThe product prepares a structured message for communication with another component, but encoding or escaping of the data is either missing or done incorrectly. As a result, the intended structure of the message is not preserved....\n\n### 2. CWE-89: Improper Neutralization of Special Elements used in an SQL Command ('SQL Injection') (Score: 744.70)\n\nThe product constructs all or part of an SQL command using externally-influenced input from an upstream component, but it does not neutralize or incorrectly neutralizes special elements that could modify the intended SQL command when it is sent to a downstream component. Without sufficient removal o...\n\n### 3. CWE-90: Improper Neutralization of Special Elements used in an LDAP Query ('LDAP Injection') (Score: 682.80)\n\nThe product constructs all or part of an LDAP query using externally-influenced input from an upstream component, but it does not neutralize or incorrectly neutralizes special elements that could modify the intended LDAP query when it is sent to a downstream component....\n\n### 4. CWE-502: Deserialization of Untrusted Data (Score: 468.01)\n\nThe product deserializes untrusted data without sufficiently ensuring that the resulting data will be valid....\n\n### 5. CWE-138: Improper Neutralization of Special Elements (Score: 452.41)\n\nThe product receives input from an upstream component, but it does not neutralize or incorrectly neutralizes special elements that could be interpreted as control elements or syntactic markers when they are sent to a downstream component....\n\n## IMPACT: 'extract sensitive information from the database'\n\nRelevant CWEs for this IMPACT:\n\n### 1. CWE-116: Improper Encoding or Escaping of Output (Score: 757.17)\n\nThe product prepares a structured message for communication with another component, but encoding or escaping of the data is either missing or done incorrectly. As a result, the intended structure of the message is not preserved....\n\n### 2. CWE-89: Improper Neutralization of Special Elements used in an SQL Command ('SQL Injection') (Score: 744.70)\n\nThe product constructs all or part of an SQL command using externally-influenced input from an upstream component, but it does not neutralize or incorrectly neutralizes special elements that could modify the intended SQL command when it is sent to a downstream component. Without sufficient removal o...\n\n### 3. CWE-352: Cross-Site Request Forgery (CSRF) (Score: 682.88)\n\nThe web application does not, or can not, sufficiently verify whether a well-formed, valid, consistent request was intentionally provided by the user who submitted the request....\n\n### 4. CWE-90: Improper Neutralization of Special Elements used in an LDAP Query ('LDAP Injection') (Score: 682.80)\n\nThe product constructs all or part of an LDAP query using externally-influenced input from an upstream component, but it does not neutralize or incorrectly neutralizes special elements that could modify the intended LDAP query when it is sent to a downstream component....\n\n### 5. CWE-863: Incorrect Authorization (Score: 170.65)\n\nThe product performs an authorization check when an actor attempts to access a resource or perform an action, but it does not correctly perform the check....\n\n## VECTOR: 'orderby parameter'\n\nRelevant CWEs for this VECTOR:\n\n### 1. CWE-116: Improper Encoding or Escaping of Output (Score: 757.17)\n\nThe product prepares a structured message for communication with another component, but encoding or escaping of the data is either missing or done incorrectly. As a result, the intended structure of the message is not preserved....\n\n### 2. CWE-89: Improper Neutralization of Special Elements used in an SQL Command ('SQL Injection') (Score: 744.70)\n\nThe product constructs all or part of an SQL command using externally-influenced input from an upstream component, but it does not neutralize or incorrectly neutralizes special elements that could modify the intended SQL command when it is sent to a downstream component. Without sufficient removal o...\n\n### 3. CWE-352: Cross-Site Request Forgery (CSRF) (Score: 682.88)\n\nThe web application does not, or can not, sufficiently verify whether a well-formed, valid, consistent request was intentionally provided by the user who submitted the request....\n\n### 4. CWE-90: Improper Neutralization of Special Elements used in an LDAP Query ('LDAP Injection') (Score: 682.80)\n\nThe product constructs all or part of an LDAP query using externally-influenced input from an upstream component, but it does not neutralize or incorrectly neutralizes special elements that could modify the intended LDAP query when it is sent to a downstream component....\n\n### 5. CWE-790: Improper Filtering of Special Elements (Score: 526.61)\n\nThe product receives data from an upstream component, but does not filter or incorrectly filters special elements before sending it to a downstream component....\n\n## ATTACKER: 'authenticated attackers with Administrator-level access'\n\nRelevant CWEs for this ATTACKER:\n\n### 1. CWE-116: Improper Encoding or Escaping of Output (Score: 757.17)\n\nThe product prepares a structured message for communication with another component, but encoding or escaping of the data is either missing or done incorrectly. As a result, the intended structure of the message is not preserved....\n\n### 2. CWE-89: Improper Neutralization of Special Elements used in an SQL Command ('SQL Injection') (Score: 744.70)\n\nThe product constructs all or part of an SQL command using externally-influenced input from an upstream component, but it does not neutralize or incorrectly neutralizes special elements that could modify the intended SQL command when it is sent to a downstream component. Without sufficient removal o...\n\n### 3. CWE-352: Cross-Site Request Forgery (CSRF) (Score: 682.88)\n\nThe web application does not, or can not, sufficiently verify whether a well-formed, valid, consistent request was intentionally provided by the user who submitted the request....\n\n### 4. CWE-862: Missing Authorization (Score: 171.50)\n\nThe product does not perform an authorization check when an actor attempts to access a resource or perform an action....\n\n### 5. CWE-863: Incorrect Authorization (Score: 170.65)\n\nThe product performs an authorization check when an actor attempts to access a resource or perform an action, but it does not correctly perform the check....\n\n## PRODUCT: 'Accredible Certificates & Open Badges plugin for WordPress'\n\nRelevant CWEs for this PRODUCT:\n\n### 1. CWE-116: Improper Encoding or Escaping of Output (Score: 757.17)\n\nThe product prepares a structured message for communication with another component, but encoding or escaping of the data is either missing or done incorrectly. As a result, the intended structure of the message is not preserved....\n\n### 2. CWE-89: Improper Neutralization of Special Elements used in an SQL Command ('SQL Injection') (Score: 744.70)\n\nThe product constructs all or part of an SQL command using externally-influenced input from an upstream component, but it does not neutralize or incorrectly neutralizes special elements that could modify the intended SQL command when it is sent to a downstream component. Without sufficient removal o...\n\n### 3. CWE-352: Cross-Site Request Forgery (CSRF) (Score: 682.88)\n\nThe web application does not, or can not, sufficiently verify whether a well-formed, valid, consistent request was intentionally provided by the user who submitted the request....\n\n### 4. CWE-862: Missing Authorization (Score: 171.50)\n\nThe product does not perform an authorization check when an actor attempts to access a resource or perform an action....\n\n### 5. CWE-863: Incorrect Authorization (Score: 170.65)\n\nThe product performs an authorization check when an actor attempts to access a resource or perform an action, but it does not correctly perform the check....\n\n## VERSION: 'all versions up to and including 1.4.9'\n\nRelevant CWEs for this VERSION:\n\n### 1. CWE-116: Improper Encoding or Escaping of Output (Score: 757.17)\n\nThe product prepares a structured message for communication with another component, but encoding or escaping of the data is either missing or done incorrectly. As a result, the intended structure of the message is not preserved....\n\n### 2. CWE-89: Improper Neutralization of Special Elements used in an SQL Command ('SQL Injection') (Score: 744.70)\n\nThe product constructs all or part of an SQL command using externally-influenced input from an upstream component, but it does not neutralize or incorrectly neutralizes special elements that could modify the intended SQL command when it is sent to a downstream component. Without sufficient removal o...\n\n### 3. CWE-352: Cross-Site Request Forgery (CSRF) (Score: 682.88)\n\nThe web application does not, or can not, sufficiently verify whether a well-formed, valid, consistent request was intentionally provided by the user who submitted the request....\n\n### 4. CWE-502: Deserialization of Untrusted Data (Score: 468.01)\n\nThe product deserializes untrusted data without sufficiently ensuring that the resulting data will be valid....\n\n### 5. CWE-863: Incorrect Authorization (Score: 170.65)\n\nThe product performs an authorization check when an actor attempts to access a resource or perform an action, but it does not correctly perform the check....\n\n\n    # Analysis Instructions\n    1. For each keyphrase, identify the most appropriate CWE(s) that represent the weakness.\n    2. Consider how the different keyphrases might relate to each other in the vulnerability chain.\n    3. Provide a final determination of primary CWE(s) and any secondary CWEs.\n    4. Format your response using the standard analysis template.\n\n    Please analyze how these different weaknesses interact and provide a comprehensive CWE classification.\n    "
  },
  "retrieval_time": 3.3322651386260986
}