{
  "vulnerability_info": "VulnerabilityInfo(cve_id='CVE-2024-51633', description='Cross-Site Request Forgery (CSRF) vulnerability in IvyCat Web Services Simple Page Specific Sidebars allows Stored **XSS**.This issue affects Simple Page Specific Sidebars from n/a through 2.14.1.', key_phrases={'rootcause': 'lack of CSRF protection', 'weakness': ['XSS', 'cross-site scripting'], 'impact': '', 'vector': '', 'attacker': '', 'product': 'IvyCat Web Services', 'version': 'n/a through 2.14.1', 'component': 'Simple Page Specific Sidebars'}, reference_content='The provided content relates to CVE-2024-51633.\\n\\n**Root cause of vulnerability:** The vulnerability is due to a lack of CSRF protection in the Simple Page Specific Sidebars plugin for WordPress.\\n\\n**Weaknesses/vulnerabilities present:**\\n- Cross-Site Request Forgery (CSRF) vulnerability.\\n\\n**Impact of exploitation:**\\n- A malicious actor could force higher-privileged users to perform unwanted actions under their current authentication.\\n- This could lead to unauthorized modifications or actions within the WordPress site, depending on the privileges of the targeted user.\\n\\n**Attack vectors:**\\n- The attack vector is through a crafted request that exploits the lack of CSRF protection.\\n- An attacker could trick a logged-in administrator to click a malicious link or visit a malicious website, which would then perform unintended actions on the vulnerable WordPress site.\\n\\n**Required attacker capabilities/position:**\\n- The attacker needs to be able to craft a malicious request.\\n- They need to be able to trick a logged-in user, with sufficient privileges, to trigger the request.\\n- The attacker does not need to have any pre-existing authentication to the vulnerable website.', similar_info={'cwe_distribution': {}, 'cwe_consensus': '', 'similarity_stats': {'thresholds': [], 'total_samples_by_threshold': {}, 'top_cwes_by_threshold': {}}}, similarity_summary=SimilarityInsight(consensus_cwe='', top_cwes=[], confidence_levels={}, total_samples=0), analysis='', analysis_with_relationships='', criticism='', resolution='', relevant_cwes=[{'metadata': {'doc_id': '352', 'name': 'Cross-Site Request Forgery (CSRF)', 'source': 'sparse', 'original_content': 'The web application does not, or can not, sufficiently verify whether a well-formed, valid, consistent request was intentionally provided by the user who submitted the request.', 'keyphrase_sources': [{'id': 'rootcause:lack of CSRF protection', 'keyphrase': 'lack of CSRF protection', 'type': 'rootcause'}, {'id': 'weakness:XSS', 'keyphrase': 'XSS', 'type': 'weakness'}, {'id': 'weakness:cross-site scripting', 'keyphrase': 'cross-site scripting', 'type': 'weakness'}, {'id': 'product:IvyCat Web Services', 'keyphrase': 'IvyCat Web Services', 'type': 'product'}, {'id': 'version:n/a through 2.14.1', 'keyphrase': 'n/a through 2.14.1', 'type': 'version'}, {'id': 'component:Simple Page Specific Sidebars', 'keyphrase': 'Simple Page Specific Sidebars', 'type': 'component'}]}, 'similarity': np.float64(307.63449020867574)}, {'metadata': {'doc_id': '116', 'name': 'Improper Encoding or Escaping of Output', 'source': 'sparse', 'original_content': 'The product prepares a structured message for communication with another component, but encoding or escaping of the data is either missing or done incorrectly. As a result, the intended structure of the message is not preserved.', 'keyphrase_sources': [{'id': 'rootcause:lack of CSRF protection', 'keyphrase': 'lack of CSRF protection', 'type': 'rootcause'}, {'id': 'weakness:XSS', 'keyphrase': 'XSS', 'type': 'weakness'}, {'id': 'weakness:cross-site scripting', 'keyphrase': 'cross-site scripting', 'type': 'weakness'}, {'id': 'product:IvyCat Web Services', 'keyphrase': 'IvyCat Web Services', 'type': 'product'}, {'id': 'version:n/a through 2.14.1', 'keyphrase': 'n/a through 2.14.1', 'type': 'version'}, {'id': 'component:Simple Page Specific Sidebars', 'keyphrase': 'Simple Page Specific Sidebars', 'type': 'component'}]}, 'similarity': np.float64(236.2106826157256)}, {'metadata': {'doc_id': '79', 'name': \"Improper Neutralization of Input During Web Page Generation ('Cross-site Scripting')\", 'source': 'sparse', 'original_content': 'The product does not neutralize or incorrectly neutralizes user-controllable input before it is placed in output that is used as a web page that is served to other users.', 'keyphrase_sources': [{'id': 'rootcause:lack of CSRF protection', 'keyphrase': 'lack of CSRF protection', 'type': 'rootcause'}, {'id': 'weakness:XSS', 'keyphrase': 'XSS', 'type': 'weakness'}, {'id': 'weakness:cross-site scripting', 'keyphrase': 'cross-site scripting', 'type': 'weakness'}, {'id': 'product:IvyCat Web Services', 'keyphrase': 'IvyCat Web Services', 'type': 'product'}, {'id': 'version:n/a through 2.14.1', 'keyphrase': 'n/a through 2.14.1', 'type': 'version'}, {'id': 'component:Simple Page Specific Sidebars', 'keyphrase': 'Simple Page Specific Sidebars', 'type': 'component'}]}, 'similarity': np.float64(227.15688758534634)}, {'metadata': {'doc_id': '434', 'name': 'Unrestricted Upload of File with Dangerous Type', 'source': 'sparse', 'original_content': 'The product allows the upload or transfer of dangerous file types that are automatically processed within its environment.', 'keyphrase_sources': [{'id': 'rootcause:lack of CSRF protection', 'keyphrase': 'lack of CSRF protection', 'type': 'rootcause'}, {'id': 'weakness:XSS', 'keyphrase': 'XSS', 'type': 'weakness'}]}, 'similarity': np.float64(224.68152963647918)}, {'metadata': {'doc_id': '89', 'name': \"Improper Neutralization of Special Elements used in an SQL Command ('SQL Injection')\", 'source': 'sparse', 'original_content': 'The product constructs all or part of an SQL command using externally-influenced input from an upstream component, but it does not neutralize or incorrectly neutralizes special elements that could modify the intended SQL command when it is sent to a downstream component. Without sufficient removal or quoting of SQL syntax in user-controllable inputs, the generated SQL query can cause those inputs to be interpreted as SQL instead of ordinary user data.', 'keyphrase_sources': [{'id': 'weakness:cross-site scripting', 'keyphrase': 'cross-site scripting', 'type': 'weakness'}, {'id': 'component:Simple Page Specific Sidebars', 'keyphrase': 'Simple Page Specific Sidebars', 'type': 'component'}]}, 'similarity': np.float64(209.74367475690588)}, {'metadata': {'doc_id': '862', 'name': 'Missing Authorization', 'source': 'sparse', 'original_content': 'The product does not perform an authorization check when an actor attempts to access a resource or perform an action.', 'keyphrase_sources': [{'id': 'rootcause:lack of CSRF protection', 'keyphrase': 'lack of CSRF protection', 'type': 'rootcause'}]}, 'similarity': np.float64(208.8803733126899)}, {'metadata': {'doc_id': '80', 'name': 'Improper Neutralization of Script-Related HTML Tags in a Web Page (Basic XSS)', 'source': 'sparse', 'original_content': 'The product receives input from an upstream component, but it does not neutralize or incorrectly neutralizes special characters such as \"<\", \">\", and \"&\" that could be interpreted as web-scripting elements when they are sent to a downstream component that processes web pages.', 'keyphrase_sources': [{'id': 'weakness:XSS', 'keyphrase': 'XSS', 'type': 'weakness'}, {'id': 'weakness:cross-site scripting', 'keyphrase': 'cross-site scripting', 'type': 'weakness'}]}, 'similarity': np.float64(161.52229367274072)}, {'metadata': {'doc_id': '93', 'name': \"Improper Neutralization of CRLF Sequences ('CRLF Injection')\", 'source': 'sparse', 'original_content': 'The product uses CRLF (carriage return line feeds) as a special element, e.g. to separate lines or records, but it does not neutralize or incorrectly neutralizes CRLF sequences from inputs.', 'keyphrase_sources': [{'id': 'version:n/a through 2.14.1', 'keyphrase': 'n/a through 2.14.1', 'type': 'version'}]}, 'similarity': np.float64(69.17337030766153)}, {'metadata': {'doc_id': '22', 'name': \"Improper Limitation of a Pathname to a Restricted Directory ('Path Traversal')\", 'source': 'sparse', 'original_content': 'The product uses external input to construct a pathname that is intended to identify a file or directory that is located underneath a restricted parent directory, but the product does not properly neutralize special elements within the pathname that can cause the pathname to resolve to a location that is outside of the restricted directory.', 'keyphrase_sources': [{'id': 'version:n/a through 2.14.1', 'keyphrase': 'n/a through 2.14.1', 'type': 'version'}]}, 'similarity': np.float64(69.06035166978945)}, {'metadata': {'doc_id': '639', 'name': 'Authorization Bypass Through User-Controlled Key', 'source': 'sparse', 'original_content': \"The system's authorization functionality does not prevent one user from gaining access to another user's data or record by modifying the key value identifying the data.\", 'keyphrase_sources': [{'id': 'component:Simple Page Specific Sidebars', 'keyphrase': 'Simple Page Specific Sidebars', 'type': 'component'}]}, 'similarity': np.float64(60.57546033437722)}, {'metadata': {'doc_id': '918', 'name': 'Server-Side Request Forgery (SSRF)', 'source': 'sparse', 'original_content': 'The web server receives a URL or similar request from an upstream component and retrieves the contents of this URL, but it does not sufficiently ensure that the request is being sent to the expected destination.', 'keyphrase_sources': [{'id': 'product:IvyCat Web Services', 'keyphrase': 'IvyCat Web Services', 'type': 'product'}]}, 'similarity': np.float64(57.29248055222364)}, {'metadata': {'doc_id': '502', 'name': 'Deserialization of Untrusted Data', 'source': 'sparse', 'original_content': 'The product deserializes untrusted data without sufficiently ensuring that the resulting data will be valid.', 'keyphrase_sources': [{'id': 'product:IvyCat Web Services', 'keyphrase': 'IvyCat Web Services', 'type': 'product'}]}, 'similarity': np.float64(56.08537106132949)}], identified_cwes={'analyzer': [], 'critic_additional': []})",
  "retrieval_results": {
    "has_multiple_keyphrases": true,
    "keyphrase_cwe_sets": {
      "rootcause:lack of CSRF protection": {
        "keyphrase": "lack of CSRF protection",
        "type": "rootcause",
        "cwes": [
          {
            "metadata": {
              "doc_id": "352",
              "name": "Cross-Site Request Forgery (CSRF)",
              "source": "sparse",
              "original_content": "The web application does not, or can not, sufficiently verify whether a well-formed, valid, consistent request was intentionally provided by the user who submitted the request.",
              "keyphrase_sources": [
                {
                  "id": "rootcause:lack of CSRF protection",
                  "keyphrase": "lack of CSRF protection",
                  "type": "rootcause"
                },
                {
                  "id": "weakness:XSS",
                  "keyphrase": "XSS",
                  "type": "weakness"
                },
                {
                  "id": "weakness:cross-site scripting",
                  "keyphrase": "cross-site scripting",
                  "type": "weakness"
                },
                {
                  "id": "product:IvyCat Web Services",
                  "keyphrase": "IvyCat Web Services",
                  "type": "product"
                },
                {
                  "id": "version:n/a through 2.14.1",
                  "keyphrase": "n/a through 2.14.1",
                  "type": "version"
                },
                {
                  "id": "component:Simple Page Specific Sidebars",
                  "keyphrase": "Simple Page Specific Sidebars",
                  "type": "component"
                }
              ]
            },
            "similarity": 307.63449020867574
          },
          {
            "metadata": {
              "doc_id": "116",
              "name": "Improper Encoding or Escaping of Output",
              "source": "sparse",
              "original_content": "The product prepares a structured message for communication with another component, but encoding or escaping of the data is either missing or done incorrectly. As a result, the intended structure of the message is not preserved.",
              "keyphrase_sources": [
                {
                  "id": "rootcause:lack of CSRF protection",
                  "keyphrase": "lack of CSRF protection",
                  "type": "rootcause"
                },
                {
                  "id": "weakness:XSS",
                  "keyphrase": "XSS",
                  "type": "weakness"
                },
                {
                  "id": "weakness:cross-site scripting",
                  "keyphrase": "cross-site scripting",
                  "type": "weakness"
                },
                {
                  "id": "product:IvyCat Web Services",
                  "keyphrase": "IvyCat Web Services",
                  "type": "product"
                },
                {
                  "id": "version:n/a through 2.14.1",
                  "keyphrase": "n/a through 2.14.1",
                  "type": "version"
                },
                {
                  "id": "component:Simple Page Specific Sidebars",
                  "keyphrase": "Simple Page Specific Sidebars",
                  "type": "component"
                }
              ]
            },
            "similarity": 236.2106826157256
          },
          {
            "metadata": {
              "doc_id": "79",
              "name": "Improper Neutralization of Input During Web Page Generation ('Cross-site Scripting')",
              "source": "sparse",
              "original_content": "The product does not neutralize or incorrectly neutralizes user-controllable input before it is placed in output that is used as a web page that is served to other users.",
              "keyphrase_sources": [
                {
                  "id": "rootcause:lack of CSRF protection",
                  "keyphrase": "lack of CSRF protection",
                  "type": "rootcause"
                },
                {
                  "id": "weakness:XSS",
                  "keyphrase": "XSS",
                  "type": "weakness"
                },
                {
                  "id": "weakness:cross-site scripting",
                  "keyphrase": "cross-site scripting",
                  "type": "weakness"
                },
                {
                  "id": "product:IvyCat Web Services",
                  "keyphrase": "IvyCat Web Services",
                  "type": "product"
                },
                {
                  "id": "version:n/a through 2.14.1",
                  "keyphrase": "n/a through 2.14.1",
                  "type": "version"
                },
                {
                  "id": "component:Simple Page Specific Sidebars",
                  "keyphrase": "Simple Page Specific Sidebars",
                  "type": "component"
                }
              ]
            },
            "similarity": 227.15688758534634
          },
          {
            "metadata": {
              "doc_id": "434",
              "name": "Unrestricted Upload of File with Dangerous Type",
              "source": "sparse",
              "original_content": "The product allows the upload or transfer of dangerous file types that are automatically processed within its environment.",
              "keyphrase_sources": [
                {
                  "id": "rootcause:lack of CSRF protection",
                  "keyphrase": "lack of CSRF protection",
                  "type": "rootcause"
                },
                {
                  "id": "weakness:XSS",
                  "keyphrase": "XSS",
                  "type": "weakness"
                }
              ]
            },
            "similarity": 224.68152963647918
          },
          {
            "metadata": {
              "doc_id": "862",
              "name": "Missing Authorization",
              "source": "sparse",
              "original_content": "The product does not perform an authorization check when an actor attempts to access a resource or perform an action.",
              "keyphrase_sources": [
                {
                  "id": "rootcause:lack of CSRF protection",
                  "keyphrase": "lack of CSRF protection",
                  "type": "rootcause"
                }
              ]
            },
            "similarity": 208.8803733126899
          }
        ]
      },
      "weakness:XSS": {
        "keyphrase": "XSS",
        "type": "weakness",
        "cwes": [
          {
            "metadata": {
              "doc_id": "352",
              "name": "Cross-Site Request Forgery (CSRF)",
              "source": "sparse",
              "original_content": "The web application does not, or can not, sufficiently verify whether a well-formed, valid, consistent request was intentionally provided by the user who submitted the request."
            },
            "similarity": 214.8839686373836
          },
          {
            "metadata": {
              "doc_id": "79",
              "name": "Improper Neutralization of Input During Web Page Generation ('Cross-site Scripting')",
              "source": "sparse",
              "original_content": "The product does not neutralize or incorrectly neutralizes user-controllable input before it is placed in output that is used as a web page that is served to other users."
            },
            "similarity": 193.77548641329787
          },
          {
            "metadata": {
              "doc_id": "116",
              "name": "Improper Encoding or Escaping of Output",
              "source": "sparse",
              "original_content": "The product prepares a structured message for communication with another component, but encoding or escaping of the data is either missing or done incorrectly. As a result, the intended structure of the message is not preserved."
            },
            "similarity": 179.90001818895794
          },
          {
            "metadata": {
              "doc_id": "80",
              "name": "Improper Neutralization of Script-Related HTML Tags in a Web Page (Basic XSS)",
              "source": "sparse",
              "original_content": "The product receives input from an upstream component, but it does not neutralize or incorrectly neutralizes special characters such as \"<\", \">\", and \"&\" that could be interpreted as web-scripting elements when they are sent to a downstream component that processes web pages.",
              "keyphrase_sources": [
                {
                  "id": "weakness:XSS",
                  "keyphrase": "XSS",
                  "type": "weakness"
                },
                {
                  "id": "weakness:cross-site scripting",
                  "keyphrase": "cross-site scripting",
                  "type": "weakness"
                }
              ]
            },
            "similarity": 161.52229367274072
          },
          {
            "metadata": {
              "doc_id": "434",
              "name": "Unrestricted Upload of File with Dangerous Type",
              "source": "sparse",
              "original_content": "The product allows the upload or transfer of dangerous file types that are automatically processed within its environment."
            },
            "similarity": 159.89378857053552
          }
        ]
      },
      "weakness:cross-site scripting": {
        "keyphrase": "cross-site scripting",
        "type": "weakness",
        "cwes": [
          {
            "metadata": {
              "doc_id": "352",
              "name": "Cross-Site Request Forgery (CSRF)",
              "source": "sparse",
              "original_content": "The web application does not, or can not, sufficiently verify whether a well-formed, valid, consistent request was intentionally provided by the user who submitted the request."
            },
            "similarity": 282.90711391351954
          },
          {
            "metadata": {
              "doc_id": "79",
              "name": "Improper Neutralization of Input During Web Page Generation ('Cross-site Scripting')",
              "source": "sparse",
              "original_content": "The product does not neutralize or incorrectly neutralizes user-controllable input before it is placed in output that is used as a web page that is served to other users."
            },
            "similarity": 255.740277770184
          },
          {
            "metadata": {
              "doc_id": "116",
              "name": "Improper Encoding or Escaping of Output",
              "source": "sparse",
              "original_content": "The product prepares a structured message for communication with another component, but encoding or escaping of the data is either missing or done incorrectly. As a result, the intended structure of the message is not preserved."
            },
            "similarity": 227.07024607311843
          },
          {
            "metadata": {
              "doc_id": "80",
              "name": "Improper Neutralization of Script-Related HTML Tags in a Web Page (Basic XSS)",
              "source": "sparse",
              "original_content": "The product receives input from an upstream component, but it does not neutralize or incorrectly neutralizes special characters such as \"<\", \">\", and \"&\" that could be interpreted as web-scripting elements when they are sent to a downstream component that processes web pages."
            },
            "similarity": 218.20079689121903
          },
          {
            "metadata": {
              "doc_id": "89",
              "name": "Improper Neutralization of Special Elements used in an SQL Command ('SQL Injection')",
              "source": "sparse",
              "original_content": "The product constructs all or part of an SQL command using externally-influenced input from an upstream component, but it does not neutralize or incorrectly neutralizes special elements that could modify the intended SQL command when it is sent to a downstream component. Without sufficient removal or quoting of SQL syntax in user-controllable inputs, the generated SQL query can cause those inputs to be interpreted as SQL instead of ordinary user data.",
              "keyphrase_sources": [
                {
                  "id": "weakness:cross-site scripting",
                  "keyphrase": "cross-site scripting",
                  "type": "weakness"
                },
                {
                  "id": "component:Simple Page Specific Sidebars",
                  "keyphrase": "Simple Page Specific Sidebars",
                  "type": "component"
                }
              ]
            },
            "similarity": 209.74367475690588
          }
        ]
      },
      "product:IvyCat Web Services": {
        "keyphrase": "IvyCat Web Services",
        "type": "product",
        "cwes": [
          {
            "metadata": {
              "doc_id": "352",
              "name": "Cross-Site Request Forgery (CSRF)",
              "source": "sparse",
              "original_content": "The web application does not, or can not, sufficiently verify whether a well-formed, valid, consistent request was intentionally provided by the user who submitted the request."
            },
            "similarity": 70.3075956512732
          },
          {
            "metadata": {
              "doc_id": "79",
              "name": "Improper Neutralization of Input During Web Page Generation ('Cross-site Scripting')",
              "source": "sparse",
              "original_content": "The product does not neutralize or incorrectly neutralizes user-controllable input before it is placed in output that is used as a web page that is served to other users."
            },
            "similarity": 63.8129751453496
          },
          {
            "metadata": {
              "doc_id": "116",
              "name": "Improper Encoding or Escaping of Output",
              "source": "sparse",
              "original_content": "The product prepares a structured message for communication with another component, but encoding or escaping of the data is either missing or done incorrectly. As a result, the intended structure of the message is not preserved."
            },
            "similarity": 61.74992597481397
          },
          {
            "metadata": {
              "doc_id": "918",
              "name": "Server-Side Request Forgery (SSRF)",
              "source": "sparse",
              "original_content": "The web server receives a URL or similar request from an upstream component and retrieves the contents of this URL, but it does not sufficiently ensure that the request is being sent to the expected destination.",
              "keyphrase_sources": [
                {
                  "id": "product:IvyCat Web Services",
                  "keyphrase": "IvyCat Web Services",
                  "type": "product"
                }
              ]
            },
            "similarity": 57.29248055222364
          },
          {
            "metadata": {
              "doc_id": "502",
              "name": "Deserialization of Untrusted Data",
              "source": "sparse",
              "original_content": "The product deserializes untrusted data without sufficiently ensuring that the resulting data will be valid.",
              "keyphrase_sources": [
                {
                  "id": "product:IvyCat Web Services",
                  "keyphrase": "IvyCat Web Services",
                  "type": "product"
                }
              ]
            },
            "similarity": 56.08537106132949
          }
        ]
      },
      "version:n/a through 2.14.1": {
        "keyphrase": "n/a through 2.14.1",
        "type": "version",
        "cwes": [
          {
            "metadata": {
              "doc_id": "352",
              "name": "Cross-Site Request Forgery (CSRF)",
              "source": "sparse",
              "original_content": "The web application does not, or can not, sufficiently verify whether a well-formed, valid, consistent request was intentionally provided by the user who submitted the request."
            },
            "similarity": 81.46239818963787
          },
          {
            "metadata": {
              "doc_id": "79",
              "name": "Improper Neutralization of Input During Web Page Generation ('Cross-site Scripting')",
              "source": "sparse",
              "original_content": "The product does not neutralize or incorrectly neutralizes user-controllable input before it is placed in output that is used as a web page that is served to other users."
            },
            "similarity": 76.26657871035962
          },
          {
            "metadata": {
              "doc_id": "116",
              "name": "Improper Encoding or Escaping of Output",
              "source": "sparse",
              "original_content": "The product prepares a structured message for communication with another component, but encoding or escaping of the data is either missing or done incorrectly. As a result, the intended structure of the message is not preserved."
            },
            "similarity": 74.98041709285054
          },
          {
            "metadata": {
              "doc_id": "93",
              "name": "Improper Neutralization of CRLF Sequences ('CRLF Injection')",
              "source": "sparse",
              "original_content": "The product uses CRLF (carriage return line feeds) as a special element, e.g. to separate lines or records, but it does not neutralize or incorrectly neutralizes CRLF sequences from inputs.",
              "keyphrase_sources": [
                {
                  "id": "version:n/a through 2.14.1",
                  "keyphrase": "n/a through 2.14.1",
                  "type": "version"
                }
              ]
            },
            "similarity": 69.17337030766153
          },
          {
            "metadata": {
              "doc_id": "22",
              "name": "Improper Limitation of a Pathname to a Restricted Directory ('Path Traversal')",
              "source": "sparse",
              "original_content": "The product uses external input to construct a pathname that is intended to identify a file or directory that is located underneath a restricted parent directory, but the product does not properly neutralize special elements within the pathname that can cause the pathname to resolve to a location that is outside of the restricted directory.",
              "keyphrase_sources": [
                {
                  "id": "version:n/a through 2.14.1",
                  "keyphrase": "n/a through 2.14.1",
                  "type": "version"
                }
              ]
            },
            "similarity": 69.06035166978945
          }
        ]
      },
      "component:Simple Page Specific Sidebars": {
        "keyphrase": "Simple Page Specific Sidebars",
        "type": "component",
        "cwes": [
          {
            "metadata": {
              "doc_id": "352",
              "name": "Cross-Site Request Forgery (CSRF)",
              "source": "sparse",
              "original_content": "The web application does not, or can not, sufficiently verify whether a well-formed, valid, consistent request was intentionally provided by the user who submitted the request."
            },
            "similarity": 78.8986991813089
          },
          {
            "metadata": {
              "doc_id": "79",
              "name": "Improper Neutralization of Input During Web Page Generation ('Cross-site Scripting')",
              "source": "sparse",
              "original_content": "The product does not neutralize or incorrectly neutralizes user-controllable input before it is placed in output that is used as a web page that is served to other users."
            },
            "similarity": 67.46835983105954
          },
          {
            "metadata": {
              "doc_id": "116",
              "name": "Improper Encoding or Escaping of Output",
              "source": "sparse",
              "original_content": "The product prepares a structured message for communication with another component, but encoding or escaping of the data is either missing or done incorrectly. As a result, the intended structure of the message is not preserved."
            },
            "similarity": 64.27785006242043
          },
          {
            "metadata": {
              "doc_id": "639",
              "name": "Authorization Bypass Through User-Controlled Key",
              "source": "sparse",
              "original_content": "The system's authorization functionality does not prevent one user from gaining access to another user's data or record by modifying the key value identifying the data.",
              "keyphrase_sources": [
                {
                  "id": "component:Simple Page Specific Sidebars",
                  "keyphrase": "Simple Page Specific Sidebars",
                  "type": "component"
                }
              ]
            },
            "similarity": 60.57546033437722
          },
          {
            "metadata": {
              "doc_id": "89",
              "name": "Improper Neutralization of Special Elements used in an SQL Command ('SQL Injection')",
              "source": "sparse",
              "original_content": "The product constructs all or part of an SQL command using externally-influenced input from an upstream component, but it does not neutralize or incorrectly neutralizes special elements that could modify the intended SQL command when it is sent to a downstream component. Without sufficient removal or quoting of SQL syntax in user-controllable inputs, the generated SQL query can cause those inputs to be interpreted as SQL instead of ordinary user data."
            },
            "similarity": 60.12903095564709
          }
        ]
      }
    },
    "keyphrase_mapping": {
      "352": [
        {
          "id": "rootcause:lack of CSRF protection",
          "keyphrase": "lack of CSRF protection",
          "type": "rootcause"
        },
        {
          "id": "weakness:XSS",
          "keyphrase": "XSS",
          "type": "weakness"
        },
        {
          "id": "weakness:cross-site scripting",
          "keyphrase": "cross-site scripting",
          "type": "weakness"
        },
        {
          "id": "product:IvyCat Web Services",
          "keyphrase": "IvyCat Web Services",
          "type": "product"
        },
        {
          "id": "version:n/a through 2.14.1",
          "keyphrase": "n/a through 2.14.1",
          "type": "version"
        },
        {
          "id": "component:Simple Page Specific Sidebars",
          "keyphrase": "Simple Page Specific Sidebars",
          "type": "component"
        }
      ],
      "116": [
        {
          "id": "rootcause:lack of CSRF protection",
          "keyphrase": "lack of CSRF protection",
          "type": "rootcause"
        },
        {
          "id": "weakness:XSS",
          "keyphrase": "XSS",
          "type": "weakness"
        },
        {
          "id": "weakness:cross-site scripting",
          "keyphrase": "cross-site scripting",
          "type": "weakness"
        },
        {
          "id": "product:IvyCat Web Services",
          "keyphrase": "IvyCat Web Services",
          "type": "product"
        },
        {
          "id": "version:n/a through 2.14.1",
          "keyphrase": "n/a through 2.14.1",
          "type": "version"
        },
        {
          "id": "component:Simple Page Specific Sidebars",
          "keyphrase": "Simple Page Specific Sidebars",
          "type": "component"
        }
      ],
      "79": [
        {
          "id": "rootcause:lack of CSRF protection",
          "keyphrase": "lack of CSRF protection",
          "type": "rootcause"
        },
        {
          "id": "weakness:XSS",
          "keyphrase": "XSS",
          "type": "weakness"
        },
        {
          "id": "weakness:cross-site scripting",
          "keyphrase": "cross-site scripting",
          "type": "weakness"
        },
        {
          "id": "product:IvyCat Web Services",
          "keyphrase": "IvyCat Web Services",
          "type": "product"
        },
        {
          "id": "version:n/a through 2.14.1",
          "keyphrase": "n/a through 2.14.1",
          "type": "version"
        },
        {
          "id": "component:Simple Page Specific Sidebars",
          "keyphrase": "Simple Page Specific Sidebars",
          "type": "component"
        }
      ],
      "434": [
        {
          "id": "rootcause:lack of CSRF protection",
          "keyphrase": "lack of CSRF protection",
          "type": "rootcause"
        },
        {
          "id": "weakness:XSS",
          "keyphrase": "XSS",
          "type": "weakness"
        }
      ],
      "862": [
        {
          "id": "rootcause:lack of CSRF protection",
          "keyphrase": "lack of CSRF protection",
          "type": "rootcause"
        }
      ],
      "80": [
        {
          "id": "weakness:XSS",
          "keyphrase": "XSS",
          "type": "weakness"
        },
        {
          "id": "weakness:cross-site scripting",
          "keyphrase": "cross-site scripting",
          "type": "weakness"
        }
      ],
      "89": [
        {
          "id": "weakness:cross-site scripting",
          "keyphrase": "cross-site scripting",
          "type": "weakness"
        },
        {
          "id": "component:Simple Page Specific Sidebars",
          "keyphrase": "Simple Page Specific Sidebars",
          "type": "component"
        }
      ],
      "918": [
        {
          "id": "product:IvyCat Web Services",
          "keyphrase": "IvyCat Web Services",
          "type": "product"
        }
      ],
      "502": [
        {
          "id": "product:IvyCat Web Services",
          "keyphrase": "IvyCat Web Services",
          "type": "product"
        }
      ],
      "93": [
        {
          "id": "version:n/a through 2.14.1",
          "keyphrase": "n/a through 2.14.1",
          "type": "version"
        }
      ],
      "22": [
        {
          "id": "version:n/a through 2.14.1",
          "keyphrase": "n/a through 2.14.1",
          "type": "version"
        }
      ],
      "639": [
        {
          "id": "component:Simple Page Specific Sidebars",
          "keyphrase": "Simple Page Specific Sidebars",
          "type": "component"
        }
      ]
    },
    "relevant_cwes": [
      {
        "metadata": {
          "doc_id": "352",
          "name": "Cross-Site Request Forgery (CSRF)",
          "source": "sparse",
          "original_content": "The web application does not, or can not, sufficiently verify whether a well-formed, valid, consistent request was intentionally provided by the user who submitted the request.",
          "keyphrase_sources": [
            {
              "id": "rootcause:lack of CSRF protection",
              "keyphrase": "lack of CSRF protection",
              "type": "rootcause"
            },
            {
              "id": "weakness:XSS",
              "keyphrase": "XSS",
              "type": "weakness"
            },
            {
              "id": "weakness:cross-site scripting",
              "keyphrase": "cross-site scripting",
              "type": "weakness"
            },
            {
              "id": "product:IvyCat Web Services",
              "keyphrase": "IvyCat Web Services",
              "type": "product"
            },
            {
              "id": "version:n/a through 2.14.1",
              "keyphrase": "n/a through 2.14.1",
              "type": "version"
            },
            {
              "id": "component:Simple Page Specific Sidebars",
              "keyphrase": "Simple Page Specific Sidebars",
              "type": "component"
            }
          ]
        },
        "similarity": 307.63449020867574
      },
      {
        "metadata": {
          "doc_id": "116",
          "name": "Improper Encoding or Escaping of Output",
          "source": "sparse",
          "original_content": "The product prepares a structured message for communication with another component, but encoding or escaping of the data is either missing or done incorrectly. As a result, the intended structure of the message is not preserved.",
          "keyphrase_sources": [
            {
              "id": "rootcause:lack of CSRF protection",
              "keyphrase": "lack of CSRF protection",
              "type": "rootcause"
            },
            {
              "id": "weakness:XSS",
              "keyphrase": "XSS",
              "type": "weakness"
            },
            {
              "id": "weakness:cross-site scripting",
              "keyphrase": "cross-site scripting",
              "type": "weakness"
            },
            {
              "id": "product:IvyCat Web Services",
              "keyphrase": "IvyCat Web Services",
              "type": "product"
            },
            {
              "id": "version:n/a through 2.14.1",
              "keyphrase": "n/a through 2.14.1",
              "type": "version"
            },
            {
              "id": "component:Simple Page Specific Sidebars",
              "keyphrase": "Simple Page Specific Sidebars",
              "type": "component"
            }
          ]
        },
        "similarity": 236.2106826157256
      },
      {
        "metadata": {
          "doc_id": "79",
          "name": "Improper Neutralization of Input During Web Page Generation ('Cross-site Scripting')",
          "source": "sparse",
          "original_content": "The product does not neutralize or incorrectly neutralizes user-controllable input before it is placed in output that is used as a web page that is served to other users.",
          "keyphrase_sources": [
            {
              "id": "rootcause:lack of CSRF protection",
              "keyphrase": "lack of CSRF protection",
              "type": "rootcause"
            },
            {
              "id": "weakness:XSS",
              "keyphrase": "XSS",
              "type": "weakness"
            },
            {
              "id": "weakness:cross-site scripting",
              "keyphrase": "cross-site scripting",
              "type": "weakness"
            },
            {
              "id": "product:IvyCat Web Services",
              "keyphrase": "IvyCat Web Services",
              "type": "product"
            },
            {
              "id": "version:n/a through 2.14.1",
              "keyphrase": "n/a through 2.14.1",
              "type": "version"
            },
            {
              "id": "component:Simple Page Specific Sidebars",
              "keyphrase": "Simple Page Specific Sidebars",
              "type": "component"
            }
          ]
        },
        "similarity": 227.15688758534634
      },
      {
        "metadata": {
          "doc_id": "434",
          "name": "Unrestricted Upload of File with Dangerous Type",
          "source": "sparse",
          "original_content": "The product allows the upload or transfer of dangerous file types that are automatically processed within its environment.",
          "keyphrase_sources": [
            {
              "id": "rootcause:lack of CSRF protection",
              "keyphrase": "lack of CSRF protection",
              "type": "rootcause"
            },
            {
              "id": "weakness:XSS",
              "keyphrase": "XSS",
              "type": "weakness"
            }
          ]
        },
        "similarity": 224.68152963647918
      },
      {
        "metadata": {
          "doc_id": "89",
          "name": "Improper Neutralization of Special Elements used in an SQL Command ('SQL Injection')",
          "source": "sparse",
          "original_content": "The product constructs all or part of an SQL command using externally-influenced input from an upstream component, but it does not neutralize or incorrectly neutralizes special elements that could modify the intended SQL command when it is sent to a downstream component. Without sufficient removal or quoting of SQL syntax in user-controllable inputs, the generated SQL query can cause those inputs to be interpreted as SQL instead of ordinary user data.",
          "keyphrase_sources": [
            {
              "id": "weakness:cross-site scripting",
              "keyphrase": "cross-site scripting",
              "type": "weakness"
            },
            {
              "id": "component:Simple Page Specific Sidebars",
              "keyphrase": "Simple Page Specific Sidebars",
              "type": "component"
            }
          ]
        },
        "similarity": 209.74367475690588
      },
      {
        "metadata": {
          "doc_id": "862",
          "name": "Missing Authorization",
          "source": "sparse",
          "original_content": "The product does not perform an authorization check when an actor attempts to access a resource or perform an action.",
          "keyphrase_sources": [
            {
              "id": "rootcause:lack of CSRF protection",
              "keyphrase": "lack of CSRF protection",
              "type": "rootcause"
            }
          ]
        },
        "similarity": 208.8803733126899
      },
      {
        "metadata": {
          "doc_id": "80",
          "name": "Improper Neutralization of Script-Related HTML Tags in a Web Page (Basic XSS)",
          "source": "sparse",
          "original_content": "The product receives input from an upstream component, but it does not neutralize or incorrectly neutralizes special characters such as \"<\", \">\", and \"&\" that could be interpreted as web-scripting elements when they are sent to a downstream component that processes web pages.",
          "keyphrase_sources": [
            {
              "id": "weakness:XSS",
              "keyphrase": "XSS",
              "type": "weakness"
            },
            {
              "id": "weakness:cross-site scripting",
              "keyphrase": "cross-site scripting",
              "type": "weakness"
            }
          ]
        },
        "similarity": 161.52229367274072
      },
      {
        "metadata": {
          "doc_id": "93",
          "name": "Improper Neutralization of CRLF Sequences ('CRLF Injection')",
          "source": "sparse",
          "original_content": "The product uses CRLF (carriage return line feeds) as a special element, e.g. to separate lines or records, but it does not neutralize or incorrectly neutralizes CRLF sequences from inputs.",
          "keyphrase_sources": [
            {
              "id": "version:n/a through 2.14.1",
              "keyphrase": "n/a through 2.14.1",
              "type": "version"
            }
          ]
        },
        "similarity": 69.17337030766153
      },
      {
        "metadata": {
          "doc_id": "22",
          "name": "Improper Limitation of a Pathname to a Restricted Directory ('Path Traversal')",
          "source": "sparse",
          "original_content": "The product uses external input to construct a pathname that is intended to identify a file or directory that is located underneath a restricted parent directory, but the product does not properly neutralize special elements within the pathname that can cause the pathname to resolve to a location that is outside of the restricted directory.",
          "keyphrase_sources": [
            {
              "id": "version:n/a through 2.14.1",
              "keyphrase": "n/a through 2.14.1",
              "type": "version"
            }
          ]
        },
        "similarity": 69.06035166978945
      },
      {
        "metadata": {
          "doc_id": "639",
          "name": "Authorization Bypass Through User-Controlled Key",
          "source": "sparse",
          "original_content": "The system's authorization functionality does not prevent one user from gaining access to another user's data or record by modifying the key value identifying the data.",
          "keyphrase_sources": [
            {
              "id": "component:Simple Page Specific Sidebars",
              "keyphrase": "Simple Page Specific Sidebars",
              "type": "component"
            }
          ]
        },
        "similarity": 60.57546033437722
      },
      {
        "metadata": {
          "doc_id": "918",
          "name": "Server-Side Request Forgery (SSRF)",
          "source": "sparse",
          "original_content": "The web server receives a URL or similar request from an upstream component and retrieves the contents of this URL, but it does not sufficiently ensure that the request is being sent to the expected destination.",
          "keyphrase_sources": [
            {
              "id": "product:IvyCat Web Services",
              "keyphrase": "IvyCat Web Services",
              "type": "product"
            }
          ]
        },
        "similarity": 57.29248055222364
      },
      {
        "metadata": {
          "doc_id": "502",
          "name": "Deserialization of Untrusted Data",
          "source": "sparse",
          "original_content": "The product deserializes untrusted data without sufficiently ensuring that the resulting data will be valid.",
          "keyphrase_sources": [
            {
              "id": "product:IvyCat Web Services",
              "keyphrase": "IvyCat Web Services",
              "type": "product"
            }
          ]
        },
        "similarity": 56.08537106132949
      }
    ],
    "enhanced_query": "# Vulnerability Description\n\n    Cross-Site Request Forgery (CSRF) vulnerability in IvyCat Web Services Simple Page Specific Sidebars allows Stored **XSS**.This issue affects Simple Page Specific Sidebars from n/a through 2.14.1.\n\n    # Keyphrase-Specific CWE Analysis\n    This vulnerability contains multiple keyphrases that may map to different CWEs. \n    Please analyze each keyphrase separately and determine the most appropriate CWE(s) for each.\n\n    ## ROOTCAUSE: 'lack of CSRF protection'\n\nRelevant CWEs for this ROOTCAUSE:\n\n### 1. CWE-352: Cross-Site Request Forgery (CSRF) (Score: 307.63)\n\nThe web application does not, or can not, sufficiently verify whether a well-formed, valid, consistent request was intentionally provided by the user who submitted the request....\n\n### 2. CWE-116: Improper Encoding or Escaping of Output (Score: 236.21)\n\nThe product prepares a structured message for communication with another component, but encoding or escaping of the data is either missing or done incorrectly. As a result, the intended structure of the message is not preserved....\n\n### 3. CWE-79: Improper Neutralization of Input During Web Page Generation ('Cross-site Scripting') (Score: 227.16)\n\nThe product does not neutralize or incorrectly neutralizes user-controllable input before it is placed in output that is used as a web page that is served to other users....\n\n### 4. CWE-434: Unrestricted Upload of File with Dangerous Type (Score: 224.68)\n\nThe product allows the upload or transfer of dangerous file types that are automatically processed within its environment....\n\n### 5. CWE-862: Missing Authorization (Score: 208.88)\n\nThe product does not perform an authorization check when an actor attempts to access a resource or perform an action....\n\n## WEAKNESS: 'XSS'\n\nRelevant CWEs for this WEAKNESS:\n\n### 1. CWE-352: Cross-Site Request Forgery (CSRF) (Score: 307.63)\n\nThe web application does not, or can not, sufficiently verify whether a well-formed, valid, consistent request was intentionally provided by the user who submitted the request....\n\n### 2. CWE-116: Improper Encoding or Escaping of Output (Score: 236.21)\n\nThe product prepares a structured message for communication with another component, but encoding or escaping of the data is either missing or done incorrectly. As a result, the intended structure of the message is not preserved....\n\n### 3. CWE-79: Improper Neutralization of Input During Web Page Generation ('Cross-site Scripting') (Score: 227.16)\n\nThe product does not neutralize or incorrectly neutralizes user-controllable input before it is placed in output that is used as a web page that is served to other users....\n\n### 4. CWE-434: Unrestricted Upload of File with Dangerous Type (Score: 224.68)\n\nThe product allows the upload or transfer of dangerous file types that are automatically processed within its environment....\n\n### 5. CWE-80: Improper Neutralization of Script-Related HTML Tags in a Web Page (Basic XSS) (Score: 161.52)\n\nThe product receives input from an upstream component, but it does not neutralize or incorrectly neutralizes special characters such as \"<\", \">\", and \"&\" that could be interpreted as web-scripting elements when they are sent to a downstream component that processes web pages....\n\n## WEAKNESS: 'cross-site scripting'\n\nRelevant CWEs for this WEAKNESS:\n\n### 1. CWE-352: Cross-Site Request Forgery (CSRF) (Score: 307.63)\n\nThe web application does not, or can not, sufficiently verify whether a well-formed, valid, consistent request was intentionally provided by the user who submitted the request....\n\n### 2. CWE-116: Improper Encoding or Escaping of Output (Score: 236.21)\n\nThe product prepares a structured message for communication with another component, but encoding or escaping of the data is either missing or done incorrectly. As a result, the intended structure of the message is not preserved....\n\n### 3. CWE-79: Improper Neutralization of Input During Web Page Generation ('Cross-site Scripting') (Score: 227.16)\n\nThe product does not neutralize or incorrectly neutralizes user-controllable input before it is placed in output that is used as a web page that is served to other users....\n\n### 4. CWE-89: Improper Neutralization of Special Elements used in an SQL Command ('SQL Injection') (Score: 209.74)\n\nThe product constructs all or part of an SQL command using externally-influenced input from an upstream component, but it does not neutralize or incorrectly neutralizes special elements that could modify the intended SQL command when it is sent to a downstream component. Without sufficient removal o...\n\n### 5. CWE-80: Improper Neutralization of Script-Related HTML Tags in a Web Page (Basic XSS) (Score: 161.52)\n\nThe product receives input from an upstream component, but it does not neutralize or incorrectly neutralizes special characters such as \"<\", \">\", and \"&\" that could be interpreted as web-scripting elements when they are sent to a downstream component that processes web pages....\n\n## PRODUCT: 'IvyCat Web Services'\n\nRelevant CWEs for this PRODUCT:\n\n### 1. CWE-352: Cross-Site Request Forgery (CSRF) (Score: 307.63)\n\nThe web application does not, or can not, sufficiently verify whether a well-formed, valid, consistent request was intentionally provided by the user who submitted the request....\n\n### 2. CWE-116: Improper Encoding or Escaping of Output (Score: 236.21)\n\nThe product prepares a structured message for communication with another component, but encoding or escaping of the data is either missing or done incorrectly. As a result, the intended structure of the message is not preserved....\n\n### 3. CWE-79: Improper Neutralization of Input During Web Page Generation ('Cross-site Scripting') (Score: 227.16)\n\nThe product does not neutralize or incorrectly neutralizes user-controllable input before it is placed in output that is used as a web page that is served to other users....\n\n### 4. CWE-918: Server-Side Request Forgery (SSRF) (Score: 57.29)\n\nThe web server receives a URL or similar request from an upstream component and retrieves the contents of this URL, but it does not sufficiently ensure that the request is being sent to the expected destination....\n\n### 5. CWE-502: Deserialization of Untrusted Data (Score: 56.09)\n\nThe product deserializes untrusted data without sufficiently ensuring that the resulting data will be valid....\n\n## VERSION: 'n/a through 2.14.1'\n\nRelevant CWEs for this VERSION:\n\n### 1. CWE-352: Cross-Site Request Forgery (CSRF) (Score: 307.63)\n\nThe web application does not, or can not, sufficiently verify whether a well-formed, valid, consistent request was intentionally provided by the user who submitted the request....\n\n### 2. CWE-116: Improper Encoding or Escaping of Output (Score: 236.21)\n\nThe product prepares a structured message for communication with another component, but encoding or escaping of the data is either missing or done incorrectly. As a result, the intended structure of the message is not preserved....\n\n### 3. CWE-79: Improper Neutralization of Input During Web Page Generation ('Cross-site Scripting') (Score: 227.16)\n\nThe product does not neutralize or incorrectly neutralizes user-controllable input before it is placed in output that is used as a web page that is served to other users....\n\n### 4. CWE-93: Improper Neutralization of CRLF Sequences ('CRLF Injection') (Score: 69.17)\n\nThe product uses CRLF (carriage return line feeds) as a special element, e.g. to separate lines or records, but it does not neutralize or incorrectly neutralizes CRLF sequences from inputs....\n\n### 5. CWE-22: Improper Limitation of a Pathname to a Restricted Directory ('Path Traversal') (Score: 69.06)\n\nThe product uses external input to construct a pathname that is intended to identify a file or directory that is located underneath a restricted parent directory, but the product does not properly neutralize special elements within the pathname that can cause the pathname to resolve to a location th...\n\n## COMPONENT: 'Simple Page Specific Sidebars'\n\nRelevant CWEs for this COMPONENT:\n\n### 1. CWE-352: Cross-Site Request Forgery (CSRF) (Score: 307.63)\n\nThe web application does not, or can not, sufficiently verify whether a well-formed, valid, consistent request was intentionally provided by the user who submitted the request....\n\n### 2. CWE-116: Improper Encoding or Escaping of Output (Score: 236.21)\n\nThe product prepares a structured message for communication with another component, but encoding or escaping of the data is either missing or done incorrectly. As a result, the intended structure of the message is not preserved....\n\n### 3. CWE-79: Improper Neutralization of Input During Web Page Generation ('Cross-site Scripting') (Score: 227.16)\n\nThe product does not neutralize or incorrectly neutralizes user-controllable input before it is placed in output that is used as a web page that is served to other users....\n\n### 4. CWE-89: Improper Neutralization of Special Elements used in an SQL Command ('SQL Injection') (Score: 209.74)\n\nThe product constructs all or part of an SQL command using externally-influenced input from an upstream component, but it does not neutralize or incorrectly neutralizes special elements that could modify the intended SQL command when it is sent to a downstream component. Without sufficient removal o...\n\n### 5. CWE-639: Authorization Bypass Through User-Controlled Key (Score: 60.58)\n\nThe system's authorization functionality does not prevent one user from gaining access to another user's data or record by modifying the key value identifying the data....\n\n\n    # Analysis Instructions\n    1. For each keyphrase, identify the most appropriate CWE(s) that represent the weakness.\n    2. Consider how the different keyphrases might relate to each other in the vulnerability chain.\n    3. Provide a final determination of primary CWE(s) and any secondary CWEs.\n    4. Format your response using the standard analysis template.\n\n    Please analyze how these different weaknesses interact and provide a comprehensive CWE classification.\n    "
  },
  "retrieval_time": 1.0038237571716309
}