{
  "cve_id": "CVE-2024-56898",
  "description": "**Broken access control** vulnerability in Geovision GV-ASWeb with version v6.1.0.0 or less. This vulnerability allows low privilege users perform actions that they arent authorized to, which can be leveraged to escalate privileges, create, modify or delete accounts.",
  "key_phrases": {
    "rootcause": "Broken access control",
    "weakness": "access control vulnerability",
    "impact": "escalate privileges, create, modify or delete accounts",
    "vector": "",
    "attacker": "low privilege users",
    "product": "Geovision GV-ASWeb",
    "version": "v6.1.0.0 or less",
    "component": ""
  },
  "reference_content": "```text\n**UNRELATE**\n```",
  "similar_info": {
    "cwe_distribution": {},
    "cwe_consensus": "",
    "similarity_stats": {
      "thresholds": [],
      "total_samples_by_threshold": {},
      "top_cwes_by_threshold": {}
    }
  },
  "similarity_summary": {
    "consensus_cwe": "",
    "top_cwes": [],
    "confidence_levels": {},
    "total_samples": 0
  },
  "analysis": "# Summary\n| CWE ID  | CWE Name                                            | Confidence | CWE Abstraction Level | CWE Vulnerability Mapping Label | CWE-Vulnerability Mapping Notes |\n| :-------- | :-------------------------------------------------- | :--------- | :-------------------- | :------------------------------ | :------------------------------ |\n| CWE-863 | Incorrect Authorization  | 0.9  | Class |   |   |\n| CWE-284 | Improper Access Control | 0.7 | Pillar |   |   |\n\n## Evidence and Confidence\n\n*   **Confidence Score:** 0.9\n*   **Evidence Strength:** MEDIUM\n\n## Relationship Analysis\nThe primary CWE is CWE-863 (Incorrect Authorization), which is a Class-level CWE. CWE-863 has child CWEs that could provide more specific details, but the description does not contain enough information to definitively choose one. CWE-284 (Improper Access Control) is a higher-level Pillar CWE that is related to authorization issues, but less specific.\n\n```mermaid\ngraph TD\n    cwe863[\"CWE-863: Incorrect Authorization\"]\n    cwe284[\"CWE-284: Improper Access Control\"]\n    \n    cwe863 -->|CHILDOF| cwe284\n    \n    classDef primary fill:#f96,stroke:#333,stroke-width:2px\n    classDef secondary fill:#69f,stroke:#333\n    class cwe863 primary\n    class cwe284 secondary\n```\n\n## Vulnerability Chain\nThe vulnerability chain starts with **broken access control**, leading to unauthorized actions by low-privilege users. This allows them to escalate privileges and manipulate accounts.\n  - **Root Cause:** **Broken Access Control**\n  - **Weakness:** **Incorrect Authorization** (CWE-863)\n  - **Impact:** Privilege escalation, account manipulation\n\n## Summary of Analysis\nThe initial analysis identified **broken access control** as the root cause, with the impact being privilege escalation and account manipulation. The Retriever Results suggested several CWEs related to access control and authorization.\n\nGiven the available evidence and the CWE guidance, CWE-863 (Incorrect Authorization) is chosen as the primary CWE because it reflects the **incorrect** authorization checks that lead to the vulnerability. CWE-284 (Improper Access Control) is included as a secondary CWE because it's a broader category that applies when the root cause is a general access control issue.\n\nThe choice of CWE-863 is based on the vulnerability description stating that low privilege users can perform actions they aren't authorized to, indicating a problem with authorization checks. This aligns with the definition of CWE-863.\n\nRelevant CWE Information:\n\n# Enhanced Context (25 CWEs)\nThe following CWEs were identified as potentially relevant to this vulnerability:\n\n## CWE-284: Improper Access Control\n**Abstraction Level**: Pillar\n**Similarity Score**: 0.238\n**Source**: sparse\n\n**Description**:\nThe product does not properly control access to resources.\n\n**Mapping Guidance**:\n- Usage: Discouraged\n- Rationale: This CWE entry is very high-level and should only be used when a more specific child is not available. It is a level-0 Class (i.e., a child of a Pillar).\n\n**Relationships**:\n- PARENTOF -> CWE-200\n- PARENTOF -> CWE-264\n- PARENTOF -> CWE-266\n- PARENTOF -> CWE-269\n- PARENTOF -> CWE-280\n- PARENTOF -> CWE-281\n- PARENTOF -> CWE-282\n- PARENTOF -> CWE-285\n- PARENTOF -> CWE-287\n- PARENTOF -> CWE-288\n- PARENTOF -> CWE-290\n- PARENTOF -> CWE-291\n- PARENTOF -> CWE-294\n- PARENTOF -> CWE-298\n- PARENTOF -> CWE-300\n- PARENTOF -> CWE-301\n- PARENTOF -> CWE-302\n- PARENTOF -> CWE-303\n- PARENTOF -> CWE-304\n- PARENTOF -> CWE-305\n- PARENTOF -> CWE-306\n- PARENTOF -> CWE-307\n- PARENTOF -> CWE-308\n- PARENTOF -> CWE-309\n- PARENTOF -> CWE-310\n- PARENTOF -> CWE-311\n- PARENTOF -> CWE-312\n- PARENTOF -> CWE-313\n- PARENTOF -> CWE-314\n- PARENTOF -> CWE-315\n- PARENTOF -> CWE-316\n- PARENTOF -> CWE-317\n- PARENTOF -> CWE-318\n- PARENTOF -> CWE-319\n- PARENTOF -> CWE-320\n- PARENTOF -> CWE-321\n- PARENTOF -> CWE-322\n- PARENTOF -> CWE-323\n- PARENTOF -> CWE-324\n- PARENTOF -> CWE-325\n- PARENTOF -> CWE-326\n- PARENTOF -> CWE-327\n- PARENTOF -> CWE-328\n- PARENTOF -> CWE-329\n- PARENTOF -> CWE-330\n- PARENTOF -> CWE-331\n- PARENTOF -> CWE-332\n- PARENTOF -> CWE-333\n- PARENTOF -> CWE-334\n- PARENTOF -> CWE-335\n- PARENTOF -> CWE-336\n- PARENTOF -> CWE-337\n- PARENTOF -> CWE-338\n- PARENTOF -> CWE-339\n- PARENTOF -> CWE-340\n- PARENTOF -> CWE-341\n- PARENTOF -> CWE-342\n- PARENTOF -> CWE-343\n- PARENTOF -> CWE-344\n- PARENTOF -> CWE-345\n- PARENTOF -> CWE-346\n- PARENTOF -> CWE-347\n- PARENTOF -> CWE-348\n- PARENTOF -> CWE-349\n- PARENTOF -> CWE-350\n- PARENTOF -> CWE-351\n- PARENTOF -> CWE-352\n- PARENTOF -> CWE-353\n- PARENTOF -> CWE-354\n- PARENTOF -> CWE-355\n- PARENTOF -> CWE-356\n- PARENTOF -> CWE-357\n- PARENTOF -> CWE-358\n- PARENTOF -> CWE-359\n- PARENTOF -> CWE-360\n- PARENTOF -> CWE-361\n- PARENTOF -> CWE-362\n- PARENTOF -> CWE-363\n- PARENTOF -> CWE-364\n- PARENTOF -> CWE-365\n- PARENTOF -> CWE-366\n- PARENTOF -> CWE-367\n- PARENTOF -> CWE-368\n- PARENTOF -> CWE-369\n- PARENTOF -> CWE-370\n- PARENTOF -> CWE-371\n- PARENTOF -> CWE-372\n- PARENTOF -> CWE-373\n- PARENTOF -> CWE-374\n- PARENTOF -> CWE-375\n- PARENTOF -> CWE-376\n- PARENTOF -> CWE-377\n- PARENTOF -> CWE-378\n- PARENTOF -> CWE-379\n- PARENTOF -> CWE-380\n- PARENTOF -> CWE-381\n- PARENTOF -> CWE-382\n- PARENTOF -> CWE-383\n- PARENTOF -> CWE-384\n- PARENTOF -> CWE-385\n- PARENTOF -> CWE-386\n- PARENTOF -> CWE-387\n- PARENTOF -> CWE-388\n- PARENTOF -> CWE-389\n- PARENTOF -> CWE-390\n- PARENTOF -> CWE-391\n- PARENTOF -> CWE-392\n- PARENTOF -> CWE-393\n- PARENTOF -> CWE-394\n- PARENTOF -> CWE-395\n- PARENTOF -> CWE-396\n- PARENTOF -> CWE-397\n- PARENTOF -> CWE-398\n- PARENTOF -> CWE-399\n- PARENTOF -> CWE-400\n- PARENTOF -> CWE-401\n- PARENTOF -> CWE-402\n- PARENTOF -> CWE-403\n- PARENTOF -> CWE-404\n- PARENTOF -> CWE-405\n- PA",
  "analysis_with_relationships": "# Summary\n| CWE ID  | CWE Name                                            | Confidence | CWE Abstraction Level | CWE Vulnerability Mapping Label | CWE-Vulnerability Mapping Notes |\n| :-------- | :-------------------------------------------------- | :--------- | :-------------------- | :------------------------------ | :------------------------------ |\n| CWE-863 | Incorrect Authorization  | 0.9  | Class |   |   |\n| CWE-284 | Improper Access Control | 0.7 | Pillar |   |   |\n\n## Evidence and Confidence\n\n*   **Confidence Score:** 0.9\n*   **Evidence Strength:** MEDIUM\n\n## Relationship Analysis\nThe primary CWE is CWE-863 (Incorrect Authorization), which is a Class-level CWE. CWE-863 has child CWEs that could provide more specific details, but the description does not contain enough information to definitively choose one. CWE-284 (Improper Access Control) is a higher-level Pillar CWE that is related to authorization issues, but less specific.\n\n```mermaid\ngraph TD\n    cwe863[\"CWE-863: Incorrect Authorization\"]\n    cwe284[\"CWE-284: Improper Access Control\"]\n    \n    cwe863 -->|CHILDOF| cwe284\n    \n    classDef primary fill:#f96,stroke:#333,stroke-width:2px\n    classDef secondary fill:#69f,stroke:#333\n    class cwe863 primary\n    class cwe284 secondary\n```\n\n## Vulnerability Chain\nThe vulnerability chain starts with **broken access control**, leading to unauthorized actions by low-privilege users. This allows them to escalate privileges and manipulate accounts.\n  - **Root Cause:** **Broken Access Control**\n  - **Weakness:** **Incorrect Authorization** (CWE-863)\n  - **Impact:** Privilege escalation, account manipulation\n\n## Summary of Analysis\nThe initial analysis identified **broken access control** as the root cause, with the impact being privilege escalation and account manipulation. The Retriever Results suggested several CWEs related to access control and authorization.\n\nGiven the available evidence and the CWE guidance, CWE-863 (Incorrect Authorization) is chosen as the primary CWE because it reflects the **incorrect** authorization checks that lead to the vulnerability. CWE-284 (Improper Access Control) is included as a secondary CWE because it's a broader category that applies when the root cause is a general access control issue.\n\nThe choice of CWE-863 is based on the vulnerability description stating that low privilege users can perform actions they aren't authorized to, indicating a problem with authorization checks. This aligns with the definition of CWE-863.\n\nRelevant CWE Information:\n\n# Enhanced Context (25 CWEs)\nThe following CWEs were identified as potentially relevant to this vulnerability:\n\n## CWE-284: Improper Access Control\n**Abstraction Level**: Pillar\n**Similarity Score**: 0.238\n**Source**: sparse\n\n**Description**:\nThe product does not properly control access to resources.\n\n**Mapping Guidance**:\n- Usage: Discouraged\n- Rationale: This CWE entry is very high-level and should only be used when a more specific child is not available. It is a level-0 Class (i.e., a child of a Pillar).\n\n**Relationships**:\n- PARENTOF -> CWE-200\n- PARENTOF -> CWE-264\n- PARENTOF -> CWE-266\n- PARENTOF -> CWE-269\n- PARENTOF -> CWE-280\n- PARENTOF -> CWE-281\n- PARENTOF -> CWE-282\n- PARENTOF -> CWE-285\n- PARENTOF -> CWE-287\n- PARENTOF -> CWE-288\n- PARENTOF -> CWE-290\n- PARENTOF -> CWE-291\n- PARENTOF -> CWE-294\n- PARENTOF -> CWE-298\n- PARENTOF -> CWE-300\n- PARENTOF -> CWE-301\n- PARENTOF -> CWE-302\n- PARENTOF -> CWE-303\n- PARENTOF -> CWE-304\n- PARENTOF -> CWE-305\n- PARENTOF -> CWE-306\n- PARENTOF -> CWE-307\n- PARENTOF -> CWE-308\n- PARENTOF -> CWE-309\n- PARENTOF -> CWE-310\n- PARENTOF -> CWE-311\n- PARENTOF -> CWE-312\n- PARENTOF -> CWE-313\n- PARENTOF -> CWE-314\n- PARENTOF -> CWE-315\n- PARENTOF -> CWE-316\n- PARENTOF -> CWE-317\n- PARENTOF -> CWE-318\n- PARENTOF -> CWE-319\n- PARENTOF -> CWE-320\n- PARENTOF -> CWE-321\n- PARENTOF -> CWE-322\n- PARENTOF -> CWE-323\n- PARENTOF -> CWE-324\n- PARENTOF -> CWE-325\n- PARENTOF -> CWE-326\n- PARENTOF -> CWE-327\n- PARENTOF -> CWE-328\n- PARENTOF -> CWE-329\n- PARENTOF -> CWE-330\n- PARENTOF -> CWE-331\n- PARENTOF -> CWE-332\n- PARENTOF -> CWE-333\n- PARENTOF -> CWE-334\n- PARENTOF -> CWE-335\n- PARENTOF -> CWE-336\n- PARENTOF -> CWE-337\n- PARENTOF -> CWE-338\n- PARENTOF -> CWE-339\n- PARENTOF -> CWE-340\n- PARENTOF -> CWE-341\n- PARENTOF -> CWE-342\n- PARENTOF -> CWE-343\n- PARENTOF -> CWE-344\n- PARENTOF -> CWE-345\n- PARENTOF -> CWE-346\n- PARENTOF -> CWE-347\n- PARENTOF -> CWE-348\n- PARENTOF -> CWE-349\n- PARENTOF -> CWE-350\n- PARENTOF -> CWE-351\n- PARENTOF -> CWE-352\n- PARENTOF -> CWE-353\n- PARENTOF -> CWE-354\n- PARENTOF -> CWE-355\n- PARENTOF -> CWE-356\n- PARENTOF -> CWE-357\n- PARENTOF -> CWE-358\n- PARENTOF -> CWE-359\n- PARENTOF -> CWE-360\n- PARENTOF -> CWE-361\n- PARENTOF -> CWE-362\n- PARENTOF -> CWE-363\n- PARENTOF -> CWE-364\n- PARENTOF -> CWE-365\n- PARENTOF -> CWE-366\n- PARENTOF -> CWE-367\n- PARENTOF -> CWE-368\n- PARENTOF -> CWE-369\n- PARENTOF -> CWE-370\n- PARENTOF -> CWE-371\n- PARENTOF -> CWE-372\n- PARENTOF -> CWE-373\n- PARENTOF -> CWE-374\n- PARENTOF -> CWE-375\n- PARENTOF -> CWE-376\n- PARENTOF -> CWE-377\n- PARENTOF -> CWE-378\n- PARENTOF -> CWE-379\n- PARENTOF -> CWE-380\n- PARENTOF -> CWE-381\n- PARENTOF -> CWE-382\n- PARENTOF -> CWE-383\n- PARENTOF -> CWE-384\n- PARENTOF -> CWE-385\n- PARENTOF -> CWE-386\n- PARENTOF -> CWE-387\n- PARENTOF -> CWE-388\n- PARENTOF -> CWE-389\n- PARENTOF -> CWE-390\n- PARENTOF -> CWE-391\n- PARENTOF -> CWE-392\n- PARENTOF -> CWE-393\n- PARENTOF -> CWE-394\n- PARENTOF -> CWE-395\n- PARENTOF -> CWE-396\n- PARENTOF -> CWE-397\n- PARENTOF -> CWE-398\n- PARENTOF -> CWE-399\n- PARENTOF -> CWE-400\n- PARENTOF -> CWE-401\n- PARENTOF -> CWE-402\n- PARENTOF -> CWE-403\n- PARENTOF -> CWE-404\n- PARENTOF -> CWE-405\n- PA\n\n\n## CWE Relationship Analysis\n\nCurrent CWEs represent these abstraction levels: .\n\n\n### Vulnerability Chain Analysis\n\n**Chain starting from CWE-390:**\n- 390 (Detection of Error Condition Without Action) - ROOT\n\n\n**Chain starting from CWE-358:**\n- 358 (Improperly Implemented Security Check for Standard) - ROOT\n\n\n\n### CWE Relationship Diagram\n\n```mermaid\ngraph TD\n    classDef primary fill:#f96,stroke:#333,stroke-width:2px\n    classDef secondary fill:#69f,stroke:#333\n    classDef tertiary fill:#9e9,stroke:#333\n```",
  "criticism": "",
  "resolution": "",
  "relevant_cwes": [
    {
      "metadata": {
        "doc_id": "284",
        "name": "Improper Access Control",
        "source": "sparse"
      },
      "similarity": 238.26940236058903
    },
    {
      "metadata": {
        "doc_id": "269",
        "name": "Improper Privilege Management",
        "source": "sparse"
      },
      "similarity": 235.7455754802957
    },
    {
      "metadata": {
        "doc_id": "863",
        "name": "Incorrect Authorization",
        "source": "sparse"
      },
      "similarity": 231.24147252974575
    },
    {
      "metadata": {
        "doc_id": "285",
        "name": "Improper Authorization",
        "source": "sparse"
      },
      "similarity": 230.14070334177245
    },
    {
      "metadata": {
        "doc_id": "732",
        "name": "Incorrect Permission Assignment for Critical Resource",
        "source": "sparse"
      },
      "similarity": 220.41480287203655
    },
    {
      "metadata": {
        "doc_id": "639",
        "name": "Authorization Bypass Through User-Controlled Key",
        "source": "sparse"
      },
      "similarity": 219.34229427923907
    },
    {
      "metadata": {
        "doc_id": "1390",
        "name": "Weak Authentication",
        "source": "sparse"
      },
      "similarity": 212.29001079442781
    },
    {
      "metadata": {
        "doc_id": "287",
        "name": "Improper Authentication",
        "source": "sparse"
      },
      "similarity": 208.98796738896579
    },
    {
      "metadata": {
        "doc_id": "472",
        "name": "External Control of Assumed-Immutable Web Parameter",
        "type": "Base",
        "original_content": "The web application does not sufficiently verify inputs that are assumed to be immutable but are actually externally controllable, such as hidden form fields.",
        "keyphrase_source": "weakness:access control vulnerability",
        "source": "dense",
        "mapping_notes": {
          "usage": "Allowed",
          "rationale": "This CWE entry is at the Base level of abstraction, which is a preferred level of abstraction for mapping to the root causes of vulnerabilities.",
          "comments": "Carefully read both the name and description to ensure that this mapping is an appropriate fit. Do not try to 'force' a mapping to a lower-level Base/Variant simply to comply with this preferred level of abstraction.",
          "reasons": [
            "Acceptable-Use"
          ]
        },
        "score_info": {
          "retrievers": [
            "dense",
            "sparse",
            "graph"
          ],
          "retriever_count": 3,
          "normalized_scores": {
            "dense": 0.5744021295445478,
            "sparse": 189.59345040623248,
            "graph": 1.690599836229147
          }
        }
      },
      "similarity": 0.5744021295445478
    },
    {
      "doc_id": "471",
      "text": "CWE-471: Modification of Assumed-Immutable Data (MAID)",
      "score": 2.7196000000000002,
      "metadata": {
        "doc_id": "471",
        "name": "Modification of Assumed-Immutable Data (MAID)",
        "type": "base",
        "original_content": "CWE-471: Modification of Assumed-Immutable Data (MAID)",
        "relationships": [
          {
            "source_id": "471",
            "target_id": "621",
            "label": "CANFOLLOW",
            "properties": {
              "view_id": "1000"
            }
          },
          {
            "source_id": "471",
            "target_id": "607",
            "label": "PARENTOF",
            "properties": {
              "ordinal": "Primary",
              "view_id": "1000"
            }
          },
          {
            "source_id": "471",
            "target_id": "602",
            "label": "CANFOLLOW",
            "properties": {
              "view_id": "1000"
            }
          },
          {
            "source_id": "471",
            "target_id": "473",
            "label": "PARENTOF",
            "properties": {
              "ordinal": "Primary",
              "view_id": "1000"
            }
          },
          {
            "source_id": "471",
            "target_id": "472",
            "label": "PARENTOF",
            "properties": {
              "view_id": "1000"
            }
          },
          {
            "source_id": "471",
            "target_id": "425",
            "label": "CANFOLLOW",
            "properties": {
              "view_id": "1000"
            }
          },
          {
            "source_id": "471",
            "target_id": "291",
            "label": "PARENTOF",
            "properties": {
              "view_id": "1000"
            }
          },
          {
            "source_id": "471",
            "target_id": "1321",
            "label": "CANFOLLOW",
            "properties": {
              "ordinal": "Primary",
              "view_id": "1000"
            }
          },
          {
            "source_id": "471",
            "target_id": "1282",
            "label": "CANFOLLOW",
            "properties": {
              "view_id": "1000"
            }
          },
          {
            "source_id": "471",
            "target_id": "664",
            "label": "CHILDOF",
            "properties": {
              "ordinal": "Primary",
              "view_id": "1000"
            }
          },
          {
            "source_id": "664",
            "target_id": "471",
            "label": "PARENTOF",
            "properties": {
              "ordinal": "Primary",
              "view_id": "1000"
            }
          },
          {
            "source_id": "621",
            "target_id": "471",
            "label": "CANPRECEDE",
            "properties": {
              "view_id": "1000"
            }
          },
          {
            "source_id": "607",
            "target_id": "471",
            "label": "CHILDOF",
            "properties": {
              "ordinal": "Primary",
              "view_id": "1000"
            }
          },
          {
            "source_id": "602",
            "target_id": "471",
            "label": "CANPRECEDE",
            "properties": {
              "view_id": "1000"
            }
          },
          {
            "source_id": "473",
            "target_id": "471",
            "label": "CHILDOF",
            "properties": {
              "ordinal": "Primary",
              "view_id": "1000"
            }
          },
          {
            "source_id": "472",
            "target_id": "471",
            "label": "CHILDOF",
            "properties": {
              "view_id": "1000"
            }
          },
          {
            "source_id": "425",
            "target_id": "471",
            "label": "CANPRECEDE",
            "properties": {
              "view_id": "1000"
            }
          },
          {
            "source_id": "291",
            "target_id": "471",
            "label": "CHILDOF",
            "properties": {
              "view_id": "1000"
            }
          },
          {
            "source_id": "1321",
            "target_id": "471",
            "label": "CANPRECEDE",
            "properties": {
              "ordinal": "Primary",
              "view_id": "1000"
            }
          },
          {
            "source_id": "1282",
            "target_id": "471",
            "label": "CANPRECEDE",
            "properties": {
              "view_id": "1000"
            }
          }
        ],
        "score_components": {
          "relationship_chain": 1.0,
          "abstraction_path": 0.5599999999999999,
          "sequence_path": 1.0
        },
        "abstraction_factor": 1.3,
        "graph_path_info": {
          "path_types": [
            "relationship_chain",
            "abstraction_path_up",
            "vulnerability_sequence_forward"
          ],
          "best_paths": {
            "relationship_chain": {
              "path": [
                [
                  "425",
                  "471",
                  "CANPRECEDE"
                ]
              ],
              "score": 1.0,
              "type": "relationship_chain",
              "source": "425"
            },
            "abstraction_path_up": {
              "path": [
                [
                  "472",
                  "471",
                  "CHILDOF"
                ]
              ],
              "score": 0.5599999999999999,
              "type": "abstraction_path_up",
              "source": "472"
            },
            "vulnerability_sequence_forward": {
              "path": [
                [
                  "425",
                  "471",
                  "CANPRECEDE"
                ]
              ],
              "score": 1.0,
              "type": "vulnerability_sequence_forward",
              "source": "425"
            }
          }
        },
        "abstraction_level": "base",
        "position": "after",
        "sources": [
          "graph"
        ],
        "source": "graph",
        "mapping_notes": {
          "usage": "Allowed",
          "rationale": "This CWE entry is at the Base level of abstraction, which is a preferred level of abstraction for mapping to the root causes of vulnerabilities.",
          "comments": "Carefully read both the name and description to ensure that this mapping is an appropriate fit. Do not try to 'force' a mapping to a lower-level Base/Variant simply to comply with this preferred level of abstraction.",
          "reasons": [
            "Acceptable-Use"
          ]
        },
        "score_info": {
          "retrievers": [
            "graph"
          ],
          "retriever_count": 1,
          "normalized_scores": {
            "graph": 2.7196000000000002
          }
        }
      },
      "similarity": 2.7196000000000002
    }
  ],
  "identified_cwes": {
    "analyzer": [
      "CWE-390",
      "CWE-358",
      "CWE-316",
      "CWE-363",
      "CWE-398",
      "CWE-314",
      "CWE-269",
      "CWE-285",
      "CWE-364",
      "CWE-365",
      "CWE-396",
      "CWE-380",
      "CWE-290",
      "CWE-306",
      "CWE-326",
      "CWE-347",
      "CWE-266",
      "CWE-330",
      "CWE-361",
      "CWE-294",
      "CWE-392",
      "CWE-327",
      "CWE-344",
      "CWE-310",
      "CWE-362",
      "CWE-200",
      "CWE-308",
      "CWE-400",
      "CWE-391",
      "CWE-393",
      "CWE-355",
      "CWE-382",
      "CWE-329",
      "CWE-379",
      "CWE-378",
      "CWE-405",
      "CWE-320",
      "CWE-386",
      "CWE-337",
      "CWE-313",
      "CWE-384",
      "CWE-351",
      "CWE-288",
      "CWE-863",
      "CWE-280",
      "CWE-389",
      "CWE-291",
      "CWE-356",
      "CWE-401",
      "CWE-360",
      "CWE-397",
      "CWE-284",
      "CWE-304",
      "CWE-359",
      "CWE-317",
      "CWE-349",
      "CWE-323",
      "CWE-311",
      "CWE-309",
      "CWE-367",
      "CWE-264",
      "CWE-394",
      "CWE-332",
      "CWE-345",
      "CWE-350",
      "CWE-301",
      "CWE-331",
      "CWE-312",
      "CWE-322",
      "CWE-385",
      "CWE-328",
      "CWE-325",
      "CWE-388",
      "CWE-346",
      "CWE-368",
      "CWE-357",
      "CWE-319",
      "CWE-399",
      "CWE-318",
      "CWE-352",
      "CWE-336",
      "CWE-321",
      "CWE-338",
      "CWE-402",
      "CWE-369",
      "CWE-370",
      "CWE-372",
      "CWE-403",
      "CWE-374",
      "CWE-334",
      "CWE-395",
      "CWE-383",
      "CWE-404",
      "CWE-348",
      "CWE-303",
      "CWE-366",
      "CWE-307",
      "CWE-381",
      "CWE-339",
      "CWE-302",
      "CWE-298",
      "CWE-324",
      "CWE-315",
      "CWE-340",
      "CWE-305",
      "CWE-376",
      "CWE-377",
      "CWE-282",
      "CWE-375",
      "CWE-354",
      "CWE-333",
      "CWE-335",
      "CWE-373",
      "CWE-287",
      "CWE-371",
      "CWE-341",
      "CWE-387",
      "CWE-353",
      "CWE-343",
      "CWE-300",
      "CWE-342",
      "CWE-281"
    ],
    "critic_additional": []
  },
  "keyphrase_cwe_mapping": {}
}