{
  "cve_id": "CVE-2024-39339",
  "description": "A vulnerability has been discovered in all versions of Smartplay headunits, which are widely used in Suzuki and Toyota cars. This **misconfiguration** can lead to information disclosure, leaking sensitive details such as diagnostic log traces, system logs, headunit passwords, and personally identifiable information (PII). The exposure of such information may have serious implications for user privacy and system integrity.",
  "key_phrases": {
    "rootcause": "misconfiguration",
    "weakness": "",
    "impact": [
      "and personally identifiable information (PII)",
      "headunit passwords",
      "information disclosure",
      "integrity",
      "leaking sensitive details such as diagnostic log traces",
      "system logs"
    ],
    "vector": "",
    "attacker": "",
    "product": "Smartplay headunits",
    "version": "all versions",
    "component": ""
  },
  "reference_content": "- **Root cause of vulnerability:** A misconfiguration within the Smartplay headunit software that does not adequately secure sensitive information.\n- **Weaknesses/vulnerabilities present:** Information disclosure vulnerability due to misconfiguration.\n- **Impact of exploitation:**\n    - Privacy breach through exposure of PII.\n    - Unauthorized access to headunit functions and potentially vehicle systems.\n    - Potential for further security breaches.\n- **Attack vectors:** Exploiting the misconfiguration via the headunit software to access exposed data.\n- **Required attacker capabilities/position:** The attacker needs to be able to interact with the vulnerable headunit software to exploit the misconfiguration.",
  "similar_info": {
    "cwe_distribution": {},
    "cwe_consensus": "",
    "similarity_stats": {
      "thresholds": [],
      "total_samples_by_threshold": {},
      "top_cwes_by_threshold": {}
    }
  },
  "similarity_summary": {
    "consensus_cwe": "",
    "top_cwes": [],
    "confidence_levels": {},
    "total_samples": 0
  },
  "analysis": "# Summary\n| CWE ID | CWE Name | Confidence | CWE Abstraction Level | CWE Vulnerability Mapping Label | CWE-Vulnerability Mapping Notes |\n|---|---|---|---|---|---|\n| **CWE-200** | Exposure of Sensitive Information to an Unauthorized Actor | 0.8 | Class | Allowed-with-Review | Primary CWE |\n| CWE-497 | Exposure of Sensitive System Information to an Unauthorized Control Sphere | 0.6 | Base | Allowed | Secondary Candidate |\n| CWE-532 | Insertion of Sensitive Information into Log File | 0.5 | Base | Allowed | Secondary Candidate |\n\n## Evidence and Confidence\n\n*   **Confidence Score:** 0.8\n*   **Evidence Strength:** MEDIUM\n\n## Relationship Analysis\nThe primary relationship considered was the hierarchical structure, specifically the parent-child relationship. While CWE-497 is a more specific \"Base\" weakness, CWE-200, a \"Class\" weakness, directly addresses the **information disclosure** aspect emphasized in the vulnerability description. This vulnerability leads to the exposure of sensitive data, thus matching the definition of CWE-200. The other CWEs have a weaker direct linkage to the vulnerability.\n\n```mermaid\ngraph TD\n    cwe200[\"CWE-200: Exposure of Sensitive Information to an Unauthorized Actor\"]\n    cwe497[\"CWE-497: Exposure of Sensitive System Information to an Unauthorized Control Sphere\"]\n    cwe532[\"CWE-532: Insertion of Sensitive Information into Log File\"]\n    \n    cwe497 -->|CHILDOF| cwe200\n    cwe532 -->|SIMILAR| cwe200\n\n    classDef primary fill:#f96,stroke:#333,stroke-width:2px\n    classDef secondary fill:#69f,stroke:#333\n    classDef tertiary fill:#9e9,stroke:#333\n    class cwe200 primary\n    class cwe497,cwe532 secondary\n```\n\n## Vulnerability Chain\nThe vulnerability chain begins with a **misconfiguration**, leading to the **disclosure of sensitive information** such as diagnostic logs, system logs, headunit passwords, and PII.\n  - **Root Cause:** **Misconfiguration**\n  - **Weakness:** Information Disclosure\n  - **Impact:** Privacy breach, unauthorized access, potential further security breaches\n\n## Summary of Analysis\nThe initial assessment focused on identifying the **root cause** and the resulting impact. The vulnerability description clearly states that a **misconfiguration** leads to **information disclosure**.\n\nCWE-200 (Exposure of Sensitive Information to an Unauthorized Actor) directly aligns with the vulnerability's description and impact. While CWE-497 (Exposure of Sensitive System Information to an Unauthorized Control Sphere) is also relevant, CWE-200 serves as a broader, more encompassing classification for the **information disclosure** aspect. I am overriding the general mapping guidance to map to CWE-200.\n\nCWE-532 (Insertion of Sensitive Information into Log File) was considered, but the vulnerability extends beyond just log files. The exposed information also includes headunit passwords and other PII, making CWE-200 a more appropriate choice.\n\nThe selection of CWE-200 is based on the evidence provided in the vulnerability description and the CVE reference links, which emphasize the **misconfiguration** leading to **information disclosure** of various sensitive data types.\n\nRelevant CWE Information:\n\n# Enhanced Context (25 CWEs)\n\n## CWE-200: Exposure of Sensitive Information to an Unauthorized Actor\n**Abstraction Level**: Class\n**Similarity Score**: 0.72\n**Source**: dense\n\n**Description**:\nThe product exposes sensitive information to an actor that is not explicitly authorized to have access to that information.\n\n**Mapping Guidance**:\n- Usage: Discouraged\n- Rationale: CWE-200 is commonly misused to represent the loss of confidentiality in a vulnerability, but confidentiality loss is a technical impact - not a root cause error. As of CWE 4.9, over 400 CWE entries can lead to a loss of confidentiality. Other options are often available. [REF-1287].\n\n*Technical Explanation:*\nThe Smartplay headunits have a **misconfiguration** that results in the exposure of PII, diagnostic log traces, system logs, and headunit passwords. This directly matches the description of CWE-200, as the system exposes sensitive information to unauthorized actors due to the incorrect configuration.\n\n*Security Implications:*\nThe exposure of sensitive information can lead to privacy breaches, unauthorized access to headunit functions and vehicle systems, and potential for further security breaches.\n\n*Relationship Analysis:*\nCWE-200 is a class-level CWE. Child CWEs like CWE-497 (Exposure of Sensitive System Information to an Unauthorized Control Sphere) are more specific. However, the broader scope of exposed information (PII, system logs, etc.) makes CWE-200 a more fitting primary classification.\n\n*Primary or Secondary Weakness:*\nPrimary weakness due to the direct impact of **information disclosure**.\n\n## CWE-497: Exposure of Sensitive System Information to an Unauthorized Control Sphere\n**Abstraction Level**: Base\n**Similarity Score**: 0.71\n**Source**: dense\n\n**Description**:\nThe product does not properly prevent sensitive system-level information from being accessed by unauthorized actors who do not have the same level of access to the underlying system as the product does.\n\n**Mapping Guidance**:\n- Usage: Allowed\n- Rationale: This CWE entry is at the Base level of abstraction, which is a preferred level of abstraction for mapping to the root causes of vulnerabilities.\n\n*Technical Explanation:*\nThe vulnerability allows unauthorized access to sensitive system information, aligning with CWE-497.\n\n*Security Implications:*\nUnauthorized access to system-level information can compromise the integrity and security of the headunit and potentially connected vehicle systems.\n\n*Relationship Analysis:*\nCWE-497 is a child of CWE-200. It is more specific than CWE-200.\n\n*Primary or Secondary Weakness:*\nSecondary weakness. It is a specific type of **information disclosure**.\n\n## CWE-532: Insertion of Sensitive Information into Log File\n**Abstraction Level**: Base\n**Similarity Score**: 0.71\n**Source**: dense\n\n**Description**:\nThe product writes sensitive information to a log file.\n\n**Mapping Guidance**:\n- Usage: Allowed\n- Rationale: This CWE entry is at the Base level of abstraction, which is a preferred level of abstraction for mapping to the root causes of vulnerabilities.\n\n*Technical Explanation:*\nA part of the disclosed information comes from diagnostic log traces and system logs, aligning with CWE-532.\n\n*Security Implications:*\nIf sensitive information is written to log files, it becomes accessible to unauthorized users, which can lead to privacy breaches and potential exploitation.\n\n*Relationship Analysis:*\nCWE-532 is a base-level CWE related to logging practices.\n\n*Primary or Secondary Weakness:*\nSecondary weakness as it describes only one facet of the **information disclosure**.\n\n## Other CWEs Considered But Not Used:\n\n*   **CWE-798: Use of Hard-coded Credentials, CWE-259: Use of Hard-coded Password, CWE-321: Use of Hard-coded Cryptographic Key**: While the description mentions \"headunit passwords,\" there is no explicit evidence that these passwords are hard-coded. Therefore, these CWEs are not appropriate.\n*   **CWE-209: Generation of Error Message Containing Sensitive Information**: There is no evidence of error messages being the source of **information disclosure**.\n*   **CWE-201: Insertion of Sensitive Information Into Sent Data**: This is not about sending data but rather exposing it due to misconfiguration.\n*   **CWE-613: Insufficient Session Expiration**: No evidence supports session management issues.\n*   **CWE-319: Cleartext Transmission of Sensitive Information**: There is no evidence of cleartext transmission.\n*   **CWE-345: Insufficient Verification of Data Authenticity**: This is not about verifying data authenticity.\n*   **CWE-538: Insertion of Sensitive Information into Externally-Accessible File or Directory**: While related, CWE-200 is more encompassing.\n*   **CWE-294: Authentication Bypass by Capture-replay**: No evidence supports this.\n*   **CWE-213: Exposure of Sensitive Information Due to Incompatible Policies**: There is no discussion of incompatible policies.\n*   **CWE-941: Incorrectly Specified Destination in a Communication Channel**: This CWE is not applicable.\n*   **CWE-1272: Sensitive Information Uncleared Before Debug/Power State Transition**: Not directly applicable to the described vulnerability.\n*   **CWE-756: Missing Custom Error Page**: Not directly applicable to the described vulnerability.\n*   **CWE-226: Sensitive Information in Resource Not Removed Before Reuse**: Not directly applicable to the described vulnerability.\n*   **CWE-212: Improper Removal of Sensitive Information Before Storage or Transfer**: Not directly applicable to the described vulnerability.\n*   **CWE-1295: Debug Messages Revealing Unnecessary Information**: While related, CWE-200 is more encompassing.",
  "analysis_with_relationships": "# Summary\n| CWE ID | CWE Name | Confidence | CWE Abstraction Level | CWE Vulnerability Mapping Label | CWE-Vulnerability Mapping Notes |\n|---|---|---|---|---|---|\n| **CWE-200** | Exposure of Sensitive Information to an Unauthorized Actor | 0.8 | Class | Allowed-with-Review | Primary CWE |\n| CWE-497 | Exposure of Sensitive System Information to an Unauthorized Control Sphere | 0.6 | Base | Allowed | Secondary Candidate |\n| CWE-532 | Insertion of Sensitive Information into Log File | 0.5 | Base | Allowed | Secondary Candidate |\n\n## Evidence and Confidence\n\n*   **Confidence Score:** 0.8\n*   **Evidence Strength:** MEDIUM\n\n## Relationship Analysis\nThe primary relationship considered was the hierarchical structure, specifically the parent-child relationship. While CWE-497 is a more specific \"Base\" weakness, CWE-200, a \"Class\" weakness, directly addresses the **information disclosure** aspect emphasized in the vulnerability description. This vulnerability leads to the exposure of sensitive data, thus matching the definition of CWE-200. The other CWEs have a weaker direct linkage to the vulnerability.\n\n```mermaid\ngraph TD\n    cwe200[\"CWE-200: Exposure of Sensitive Information to an Unauthorized Actor\"]\n    cwe497[\"CWE-497: Exposure of Sensitive System Information to an Unauthorized Control Sphere\"]\n    cwe532[\"CWE-532: Insertion of Sensitive Information into Log File\"]\n    \n    cwe497 -->|CHILDOF| cwe200\n    cwe532 -->|SIMILAR| cwe200\n\n    classDef primary fill:#f96,stroke:#333,stroke-width:2px\n    classDef secondary fill:#69f,stroke:#333\n    classDef tertiary fill:#9e9,stroke:#333\n    class cwe200 primary\n    class cwe497,cwe532 secondary\n```\n\n## Vulnerability Chain\nThe vulnerability chain begins with a **misconfiguration**, leading to the **disclosure of sensitive information** such as diagnostic logs, system logs, headunit passwords, and PII.\n  - **Root Cause:** **Misconfiguration**\n  - **Weakness:** Information Disclosure\n  - **Impact:** Privacy breach, unauthorized access, potential further security breaches\n\n## Summary of Analysis\nThe initial assessment focused on identifying the **root cause** and the resulting impact. The vulnerability description clearly states that a **misconfiguration** leads to **information disclosure**.\n\nCWE-200 (Exposure of Sensitive Information to an Unauthorized Actor) directly aligns with the vulnerability's description and impact. While CWE-497 (Exposure of Sensitive System Information to an Unauthorized Control Sphere) is also relevant, CWE-200 serves as a broader, more encompassing classification for the **information disclosure** aspect. I am overriding the general mapping guidance to map to CWE-200.\n\nCWE-532 (Insertion of Sensitive Information into Log File) was considered, but the vulnerability extends beyond just log files. The exposed information also includes headunit passwords and other PII, making CWE-200 a more appropriate choice.\n\nThe selection of CWE-200 is based on the evidence provided in the vulnerability description and the CVE reference links, which emphasize the **misconfiguration** leading to **information disclosure** of various sensitive data types.\n\nRelevant CWE Information:\n\n# Enhanced Context (25 CWEs)\n\n## CWE-200: Exposure of Sensitive Information to an Unauthorized Actor\n**Abstraction Level**: Class\n**Similarity Score**: 0.72\n**Source**: dense\n\n**Description**:\nThe product exposes sensitive information to an actor that is not explicitly authorized to have access to that information.\n\n**Mapping Guidance**:\n- Usage: Discouraged\n- Rationale: CWE-200 is commonly misused to represent the loss of confidentiality in a vulnerability, but confidentiality loss is a technical impact - not a root cause error. As of CWE 4.9, over 400 CWE entries can lead to a loss of confidentiality. Other options are often available. [REF-1287].\n\n*Technical Explanation:*\nThe Smartplay headunits have a **misconfiguration** that results in the exposure of PII, diagnostic log traces, system logs, and headunit passwords. This directly matches the description of CWE-200, as the system exposes sensitive information to unauthorized actors due to the incorrect configuration.\n\n*Security Implications:*\nThe exposure of sensitive information can lead to privacy breaches, unauthorized access to headunit functions and vehicle systems, and potential for further security breaches.\n\n*Relationship Analysis:*\nCWE-200 is a class-level CWE. Child CWEs like CWE-497 (Exposure of Sensitive System Information to an Unauthorized Control Sphere) are more specific. However, the broader scope of exposed information (PII, system logs, etc.) makes CWE-200 a more fitting primary classification.\n\n*Primary or Secondary Weakness:*\nPrimary weakness due to the direct impact of **information disclosure**.\n\n## CWE-497: Exposure of Sensitive System Information to an Unauthorized Control Sphere\n**Abstraction Level**: Base\n**Similarity Score**: 0.71\n**Source**: dense\n\n**Description**:\nThe product does not properly prevent sensitive system-level information from being accessed by unauthorized actors who do not have the same level of access to the underlying system as the product does.\n\n**Mapping Guidance**:\n- Usage: Allowed\n- Rationale: This CWE entry is at the Base level of abstraction, which is a preferred level of abstraction for mapping to the root causes of vulnerabilities.\n\n*Technical Explanation:*\nThe vulnerability allows unauthorized access to sensitive system information, aligning with CWE-497.\n\n*Security Implications:*\nUnauthorized access to system-level information can compromise the integrity and security of the headunit and potentially connected vehicle systems.\n\n*Relationship Analysis:*\nCWE-497 is a child of CWE-200. It is more specific than CWE-200.\n\n*Primary or Secondary Weakness:*\nSecondary weakness. It is a specific type of **information disclosure**.\n\n## CWE-532: Insertion of Sensitive Information into Log File\n**Abstraction Level**: Base\n**Similarity Score**: 0.71\n**Source**: dense\n\n**Description**:\nThe product writes sensitive information to a log file.\n\n**Mapping Guidance**:\n- Usage: Allowed\n- Rationale: This CWE entry is at the Base level of abstraction, which is a preferred level of abstraction for mapping to the root causes of vulnerabilities.\n\n*Technical Explanation:*\nA part of the disclosed information comes from diagnostic log traces and system logs, aligning with CWE-532.\n\n*Security Implications:*\nIf sensitive information is written to log files, it becomes accessible to unauthorized users, which can lead to privacy breaches and potential exploitation.\n\n*Relationship Analysis:*\nCWE-532 is a base-level CWE related to logging practices.\n\n*Primary or Secondary Weakness:*\nSecondary weakness as it describes only one facet of the **information disclosure**.\n\n## Other CWEs Considered But Not Used:\n\n*   **CWE-798: Use of Hard-coded Credentials, CWE-259: Use of Hard-coded Password, CWE-321: Use of Hard-coded Cryptographic Key**: While the description mentions \"headunit passwords,\" there is no explicit evidence that these passwords are hard-coded. Therefore, these CWEs are not appropriate.\n*   **CWE-209: Generation of Error Message Containing Sensitive Information**: There is no evidence of error messages being the source of **information disclosure**.\n*   **CWE-201: Insertion of Sensitive Information Into Sent Data**: This is not about sending data but rather exposing it due to misconfiguration.\n*   **CWE-613: Insufficient Session Expiration**: No evidence supports session management issues.\n*   **CWE-319: Cleartext Transmission of Sensitive Information**: There is no evidence of cleartext transmission.\n*   **CWE-345: Insufficient Verification of Data Authenticity**: This is not about verifying data authenticity.\n*   **CWE-538: Insertion of Sensitive Information into Externally-Accessible File or Directory**: While related, CWE-200 is more encompassing.\n*   **CWE-294: Authentication Bypass by Capture-replay**: No evidence supports this.\n*   **CWE-213: Exposure of Sensitive Information Due to Incompatible Policies**: There is no discussion of incompatible policies.\n*   **CWE-941: Incorrectly Specified Destination in a Communication Channel**: This CWE is not applicable.\n*   **CWE-1272: Sensitive Information Uncleared Before Debug/Power State Transition**: Not directly applicable to the described vulnerability.\n*   **CWE-756: Missing Custom Error Page**: Not directly applicable to the described vulnerability.\n*   **CWE-226: Sensitive Information in Resource Not Removed Before Reuse**: Not directly applicable to the described vulnerability.\n*   **CWE-212: Improper Removal of Sensitive Information Before Storage or Transfer**: Not directly applicable to the described vulnerability.\n*   **CWE-1295: Debug Messages Revealing Unnecessary Information**: While related, CWE-200 is more encompassing.\n\n\n## CWE Relationship Analysis\n\nCurrent CWEs represent these abstraction levels: .\n\n\n### Vulnerability Chain Analysis\n\n**Chain starting from CWE-345:**\n- 345 (Insufficient Verification of Data Authenticity) - ROOT\n\n\n**Chain starting from CWE-226:**\n- 226 (Sensitive Information in Resource Not Removed Before Reuse) - ROOT\n\n\n\n### CWE Relationship Diagram\n\n```mermaid\ngraph TD\n    classDef primary fill:#f96,stroke:#333,stroke-width:2px\n    classDef secondary fill:#69f,stroke:#333\n    classDef tertiary fill:#9e9,stroke:#333\n```",
  "criticism": "",
  "resolution": "",
  "relevant_cwes": [
    {
      "metadata": {
        "doc_id": "532",
        "name": "Insertion of Sensitive Information into Log File",
        "source": "sparse"
      },
      "similarity": 285.3560939461089
    },
    {
      "metadata": {
        "doc_id": "798",
        "name": "Use of Hard-coded Credentials",
        "source": "sparse"
      },
      "similarity": 279.2937747640768
    },
    {
      "metadata": {
        "doc_id": "209",
        "name": "Generation of Error Message Containing Sensitive Information",
        "source": "sparse"
      },
      "similarity": 278.18848720167125
    },
    {
      "metadata": {
        "doc_id": "497",
        "name": "Exposure of Sensitive System Information to an Unauthorized Control Sphere",
        "source": "sparse"
      },
      "similarity": 277.6632957442919
    },
    {
      "metadata": {
        "doc_id": "319",
        "name": "Cleartext Transmission of Sensitive Information",
        "source": "sparse"
      },
      "similarity": 272.4034468371714
    },
    {
      "metadata": {
        "doc_id": "200",
        "name": "Exposure of Sensitive Information to an Unauthorized Actor",
        "source": "sparse"
      },
      "similarity": 265.0816543340628
    },
    {
      "metadata": {
        "doc_id": "321",
        "name": "Use of Hard-coded Cryptographic Key",
        "source": "sparse"
      },
      "similarity": 264.9769479427026
    },
    {
      "metadata": {
        "doc_id": "201",
        "name": "Insertion of Sensitive Information Into Sent Data",
        "source": "sparse"
      },
      "similarity": 254.69215312034953
    },
    {
      "metadata": {
        "doc_id": "259",
        "name": "Use of Hard-coded Password",
        "type": "Variant",
        "original_content": "The product contains a hard-coded password, which it uses for its own inbound authentication or for outbound communication to external components.",
        "keyphrase_source": "rootcause:misconfiguration",
        "source": "dense",
        "mapping_notes": {
          "usage": "Allowed",
          "rationale": "This CWE entry is at the Variant level of abstraction, which is a preferred level of abstraction for mapping to the root causes of vulnerabilities.",
          "comments": "Carefully read both the name and description to ensure that this mapping is an appropriate fit. Do not try to 'force' a mapping to a lower-level Base/Variant simply to comply with this preferred level of abstraction.",
          "reasons": [
            "Acceptable-Use"
          ]
        },
        "score_info": {
          "retrievers": [
            "dense",
            "graph"
          ],
          "retriever_count": 2,
          "normalized_scores": {
            "dense": 0.5180282132797955,
            "graph": 1.7948107295558389
          }
        }
      },
      "similarity": 0.5180282132797955
    },
    {
      "doc_id": "613",
      "text": "CWE-613: Insufficient Session Expiration",
      "score": 2.2100000000000004,
      "metadata": {
        "doc_id": "613",
        "name": "Insufficient Session Expiration",
        "type": "base",
        "original_content": "CWE-613: Insufficient Session Expiration",
        "relationships": [
          {
            "source_id": "613",
            "target_id": "352",
            "label": "REQUIREDBY",
            "properties": {
              "view_id": "1000"
            }
          },
          {
            "source_id": "613",
            "target_id": "287",
            "label": "CANPRECEDE",
            "properties": {
              "view_id": "1000"
            }
          },
          {
            "source_id": "613",
            "target_id": "672",
            "label": "CHILDOF",
            "properties": {
              "ordinal": "Primary",
              "view_id": "1003"
            }
          },
          {
            "source_id": "613",
            "target_id": "672",
            "label": "CHILDOF",
            "properties": {
              "ordinal": "Primary",
              "view_id": "1000"
            }
          },
          {
            "source_id": "672",
            "target_id": "613",
            "label": "PARENTOF",
            "properties": {
              "ordinal": "Primary",
              "view_id": "1000"
            }
          },
          {
            "source_id": "352",
            "target_id": "613",
            "label": "REQUIRES",
            "properties": {
              "view_id": "1000"
            }
          },
          {
            "source_id": "287",
            "target_id": "613",
            "label": "CANFOLLOW",
            "properties": {
              "view_id": "1000"
            }
          }
        ],
        "score_components": {
          "relationship_chain": 1.0,
          "sequence_path": 1.0
        },
        "abstraction_factor": 1.3,
        "graph_path_info": {
          "path_types": [
            "relationship_chain",
            "vulnerability_sequence_forward",
            "vulnerability_sequence_backward"
          ],
          "best_paths": {
            "relationship_chain": {
              "path": [
                [
                  "287",
                  "613",
                  "CANFOLLOW"
                ]
              ],
              "score": 1.0,
              "type": "relationship_chain",
              "source": "287"
            },
            "vulnerability_sequence_forward": {
              "path": [
                [
                  "287",
                  "613",
                  "CANFOLLOW"
                ]
              ],
              "score": 0.9,
              "type": "vulnerability_sequence_forward",
              "source": "287"
            },
            "vulnerability_sequence_backward": {
              "path": [
                [
                  "613",
                  "287",
                  "CANPRECEDE"
                ]
              ],
              "score": 1.0,
              "type": "vulnerability_sequence_backward",
              "source": "287"
            }
          }
        },
        "position": "before",
        "sources": [
          "graph"
        ],
        "source": "graph",
        "mapping_notes": {
          "usage": "Allowed",
          "rationale": "This CWE entry is at the Base level of abstraction, which is a preferred level of abstraction for mapping to the root causes of vulnerabilities.",
          "comments": "Carefully read both the name and description to ensure that this mapping is an appropriate fit. Do not try to 'force' a mapping to a lower-level Base/Variant simply to comply with this preferred level of abstraction.",
          "reasons": [
            "Acceptable-Use"
          ]
        },
        "score_info": {
          "retrievers": [
            "sparse",
            "graph"
          ],
          "retriever_count": 2,
          "normalized_scores": {
            "sparse": 251.49679089399427,
            "graph": 2.2100000000000004
          }
        }
      },
      "similarity": 2.2100000000000004
    }
  ],
  "identified_cwes": {
    "analyzer": [
      "CWE-345",
      "CWE-226",
      "CWE-201",
      "CWE-209",
      "CWE-200",
      "CWE-319",
      "CWE-613",
      "CWE-213",
      "CWE-1272",
      "CWE-532",
      "CWE-321",
      "CWE-294",
      "CWE-798",
      "CWE-941",
      "CWE-212",
      "CWE-1295",
      "CWE-538",
      "CWE-756",
      "CWE-259",
      "CWE-497"
    ],
    "critic_additional": []
  },
  "keyphrase_cwe_mapping": {}
}