{
  "cve_id": "CVE-2025-0445",
  "description": "**Use after free** in V8 in Google Chrome prior to 133.0.6943.53 allowed a remote attacker to potentially exploit heap corruption via a crafted HTML page. (Chromium security severity High)",
  "key_phrases": {
    "rootcause": [
      "Use after free",
      "use-after-free"
    ],
    "weakness": "use-after-free",
    "impact": "potentially exploit heap corruption",
    "vector": "crafted HTML page",
    "attacker": "remote attacker",
    "product": "Google Chrome",
    "version": "prior to 133.0.6943.53",
    "component": "V8"
  },
  "reference_content": "## CVE-2025-0445 Analysis\n\nThe provided content relates to CVE-2025-0445. Here's the extracted information:\n\n**Root cause of vulnerability:** Use after free in V8.\n**Weaknesses/vulnerabilities present:** Use-after-free\n**Impact of exploitation:** Not specified in the provided content.\n**Attack vectors:** Not specified in the provided content.\n**Required attacker capabilities/position:** Not specified in the provided content.\n**Mitigation or fix:** This update includes a fix. Access to bug details may be restricted.\n\n**Additional Details (more than official CVE description):**\n\n*   **Reported by:** 303f06e3 on 2025-01-27\n*   **Reward:** TBD (To Be Determined)\n*   **Issue Link:** [https://issues.chromium.org/issues/392521083](https://issues.chromium.org/issues/392521083)\n*   The vulnerability is in the V8 JavaScript engine.\n*   The fix is included in Chrome version 133.0.6943.53 (Linux) and 133.0.6943.53/54 (Windows, Mac).",
  "similar_info": {
    "cwe_distribution": {},
    "cwe_consensus": "",
    "similarity_stats": {
      "thresholds": [],
      "total_samples_by_threshold": {},
      "top_cwes_by_threshold": {}
    }
  },
  "similarity_summary": {
    "consensus_cwe": "",
    "top_cwes": [],
    "confidence_levels": {},
    "total_samples": 0
  },
  "analysis": "```markdown\n# Summary\n| CWE ID  | CWE Name                                                                 | Confidence | CWE Abstraction Level | CWE Vulnerability Mapping Label | CWE-Vulnerability Mapping Notes |\n| :-------- | :----------------------------------------------------------------------- | :--------- | :---------------------- | :------------------------------ | :------------------------------ |\n| CWE-416 | Use After Free                                                         | 1          | Variant               | Primary                         | Allowed                         |\n| CWE-787 | Out-of-bounds Write                                                  | 0.5        | Base                   | Secondary                       | Allowed                         |\n| CWE-122 | Heap-based Buffer Overflow                                             | 0.4        | Base                   | Secondary                       | Allowed                         |\n\n## Evidence and Confidence\n\n*   **Confidence Score:** 0.8\n*   **Evidence Strength:** HIGH\n\n## Relationship Analysis\nThe primary CWE is CWE-416, which directly reflects the vulnerability description. CWE-787 (Out-of-bounds Write) and CWE-122 (Heap-based Buffer Overflow) are considered as potential consequences or related issues that could arise from a use-after-free condition, but they are not the direct root cause described in the vulnerability. CWE-416 can lead to memory corruption which in turn can lead to out-of-bounds write.\n\n```mermaid\ngraph TD\n    cwe416[\"CWE-416: Use After Free\"]\n    cwe787[\"CWE-787: Out-of-bounds Write\"]\n    cwe122[\"CWE-122: Heap-based Buffer Overflow\"]\n    cwe119[\"CWE-119: Improper Restriction of Operations\"]\n\n    cwe416 -- CAN_RESULT_IN --> cwe787\n    cwe787 -->|CHILDOF| cwe119\n    cwe122 -->|CHILDOF| cwe119\n\n    classDef primary fill:#f96,stroke:#333,stroke-width:2px\n    classDef secondary fill:#69f,stroke:#333\n    class cwe416 primary\n    class cwe787,cwe122 secondary\n```\n\n## Vulnerability Chain\nThe vulnerability chain starts with the **use-after-free** condition (CWE-416). This can lead to heap corruption, which may then result in other issues like out-of-bounds write (CWE-787) or heap-based buffer overflow (CWE-122). The initial **flaw** is the **use-after-free**, and the impact is potential exploitation through heap corruption.\n\n## Summary of Analysis\nThe primary weakness is clearly a **use-after-free** condition. The vulnerability description explicitly states \"**Use after free** in V8 in Google Chrome...allowed a remote attacker to potentially exploit heap corruption via a crafted HTML page.\" Therefore, CWE-416 is the most appropriate primary CWE. While heap corruption can have other consequences such as out-of-bounds writes or heap overflows, these are secondary to the initial **use-after-free** condition. The retriever results also strongly suggest CWE-416 as the primary candidate.\n\nI considered other CWEs such as CWE-366, CWE-843, CWE-911, and CWE-415, but these are less directly related to the **use-after-free** condition. CWE-366 (Race Condition within a Thread) might be a contributing factor in some **use-after-free** scenarios, but it is not explicitly mentioned in the description. CWE-843 (Access of Resource Using Incompatible Type) and CWE-911 (Improper Update of Reference Count) are also less directly applicable. CWE-415 (Double Free) is similar to **use-after-free**, but the description specifically mentions reuse after free, not a double free. CWE-122 (Heap-based Buffer Overflow) and CWE-787 (Out-of-bounds Write) are potential consequences of the **use-after-free**, but not the root cause.\n\nThe selection of CWE-416 is at the Variant level, which is a preferred level of abstraction for mapping to the root causes of vulnerabilities. The other considered CWEs were at the Base or Class level, making CWE-416 the most specific and accurate choice.\n\nRelevant CWE Information:\n\n# Enhanced Context (25 CWEs)\nThe following CWEs were identified as potentially relevant to this vulnerability:\n\n## CWE-451: User Interface (UI) Misrepresentation of Critical Information\n**Abstraction Level**: Class\n**Similarity Score**: 0.76\n**Source**: dense\n\n**Description**:\nThe user interface (UI) does not properly represent critical information to the user, allowing the information - or its source - to be obscured or spoofed. This is often a component in phishing attacks.\n\n**Mapping Guidance**:\n- Usage: Allowed-with-Review\n- Rationale: This CWE entry is a Class and might have Base-level children that would be more appropriate\n\n## CWE-416: Use After Free\n**Abstraction Level**: Variant\n**Similarity Score**: 0.75\n**Source**: dense\n\n**Description**:\nThe product reuses or references memory after it has been freed. At some point afterward, the memory may be allocated again and saved in another pointer, while the original pointer references a location somewhere within the new allocation. Any operations using the original pointer are no longer valid because the memory \"belongs\" to the code that operates on the new pointer.\n\n**Mapping Guidance**:\n- Usage: Allowed\n- Rationale: This CWE entry is at the Variant level of abstraction, which is a preferred level of abstraction for mapping to the root causes of vulnerabilities.\n\n## CWE-366: Race Condition within a Thread\n**Abstraction Level**: Base\n**Similarity Score**: 0.75\n**Source**: dense\n\n**Description**:\nIf two threads of execution use a resource simultaneously, there exists the possibility that resources may be used while invalid, in turn making the state of execution undefined.\n\n**Mapping Guidance**:\n- Usage: Allowed\n- Rationale: This CWE entry is at the Base level of abstraction, which is a preferred level of abstraction for mapping to the root causes of vulnerabilities.\n\n## CWE-843: Access of Resource Using Incompatible Type ('Type Confusion')\n**Abstraction Level**: Base\n**Similarity Score**: 0.75\n**Source**: dense\n\n**Description**:\nThe product allocates or initializes a resource such as a pointer, object, or variable using one type, but it later accesses that resource using a type that is incompatible with the original type.\n\n**Mapping Guidance**:\n- Usage: Allowed\n- Rationale: This CWE entry is at the Base level of abstraction, which is a preferred level of abstraction for mapping to the root causes of vulnerabilities.\n\n## CWE-824: Access of Uninitialized Pointer\n**Abstraction Level**: Base\n**Similarity Score**: 0.74\n**Source**: dense\n\n**Description**:\nThe product accesses or uses a pointer that has not been initialized.\n\n**Mapping Guidance**:\n- Usage: Allowed\n- Rationale: This CWE entry is at the Base level of abstraction, which is a preferred level of abstraction for mapping to the root causes of vulnerabilities.\n\n## CWE-667: Improper Locking\n**Abstraction Level**: Class\n**Similarity Score**: 0.73\n**Source**: dense\n\n**Description**:\nThe product does not properly acquire or release a lock on a resource, leading to unexpected resource state changes and behaviors.\n\n**Mapping Guidance**:\n- Usage: Allowed-with-Review\n- Rationale: This CWE entry is a Class and might have Base-level children that would be more appropriate\n\n## CWE-367: Time-of-check Time-of-use (TOCTOU) Race Condition\n**Abstraction Level**: Base\n**Similarity Score**: 0.73\n**Source**: dense\n\n**Description**:\nThe product checks the state of a resource before using that resource, but the resource's state can change between the check and the use in a way that invalidates the results of the check. This can cause the product to perform invalid actions when the resource is in an unexpected state.\n\n**Mapping Guidance**:\n- Usage: Allowed\n- Rationale: This CWE entry is at the Base level of abstraction, which is a preferred level of abstraction for mapping to the root causes of vulnerabilities.\n\n## CWE-356: Product UI does not Warn User of Unsafe Actions\n**Abstraction Level**: Base\n**Similarity Score**: 0.73\n**Source**: dense\n\n**Description**:\nThe product's user interface does not warn the user before undertaking an unsafe action on behalf of that user. This makes it easier for attackers to trick users into inflicting damage to their system.\n\n**Mapping Guidance**:\n- Usage: Allowed\n- Rationale: This CWE entry is at the Base level of abstraction, which is a preferred level of abstraction for mapping to the root causes of vulnerabilities.\n\n## CWE-665: Improper Initialization\n**Abstraction Level**: Class\n**Similarity Score**: 0.73\n**Source**: dense\n\n**Description**:\nThe product does not initialize or incorrectly initializes a resource, which might leave the resource in an unexpected state when it is accessed or used.\n\n**Mapping Guidance**:\n- Usage: Discouraged\n- Rationale: This CWE entry is a level-1 Class (i",
  "analysis_with_relationships": "# Summary\n| CWE ID  | CWE Name                                                                 | Confidence | CWE Abstraction Level | CWE Vulnerability Mapping Label | CWE-Vulnerability Mapping Notes |\n| :-------- | :----------------------------------------------------------------------- | :--------- | :---------------------- | :------------------------------ | :------------------------------ |\n| CWE-416 | Use After Free                                                         | 1          | Variant               | Primary                         | Allowed                         |\n| CWE-787 | Out-of-bounds Write                                                  | 0.5        | Base                   | Secondary                       | Allowed                         |\n| CWE-122 | Heap-based Buffer Overflow                                             | 0.4        | Base                   | Secondary                       | Allowed                         |\n\n## Evidence and Confidence\n\n*   **Confidence Score:** 0.8\n*   **Evidence Strength:** HIGH\n\n## Relationship Analysis\nThe primary CWE is CWE-416, which directly reflects the vulnerability description. CWE-787 (Out-of-bounds Write) and CWE-122 (Heap-based Buffer Overflow) are considered as potential consequences or related issues that could arise from a use-after-free condition, but they are not the direct root cause described in the vulnerability. CWE-416 can lead to memory corruption which in turn can lead to out-of-bounds write.mermaid\n```mermaid\ngraph TD\n    cwe416[\"CWE-416: Use After Free\"]\n    cwe787[\"CWE-787: Out-of-bounds Write\"]\n    cwe122[\"CWE-122: Heap-based Buffer Overflow\"]\n    cwe119[\"CWE-119: Improper Restriction of Operations\"]\n\n    cwe416 -- CAN_RESULT_IN --> cwe787\n    cwe787 -->|CHILDOF| cwe119\n    cwe122 -->|CHILDOF| cwe119\n\n    classDef primary fill:#f96,stroke:#333,stroke-width:2px\n    classDef secondary fill:#69f,stroke:#333\n    class cwe416 primary\n    class cwe787,cwe122 secondary\n\n```\n\n\n## Vulnerability Chain\nThe vulnerability chain starts with the **use-after-free** condition (CWE-416). This can lead to heap corruption, which may then result in other issues like out-of-bounds write (CWE-787) or heap-based buffer overflow (CWE-122). The initial **flaw** is the **use-after-free**, and the impact is potential exploitation through heap corruption.\n\n## Summary of Analysis\nThe primary weakness is clearly a **use-after-free** condition. The vulnerability description explicitly states \"**Use after free** in V8 in Google Chrome...allowed a remote attacker to potentially exploit heap corruption via a crafted HTML page.\" Therefore, CWE-416 is the most appropriate primary CWE. While heap corruption can have other consequences such as out-of-bounds writes or heap overflows, these are secondary to the initial **use-after-free** condition. The retriever results also strongly suggest CWE-416 as the primary candidate.\n\nI considered other CWEs such as CWE-366, CWE-843, CWE-911, and CWE-415, but these are less directly related to the **use-after-free** condition. CWE-366 (Race Condition within a Thread) might be a contributing factor in some **use-after-free** scenarios, but it is not explicitly mentioned in the description. CWE-843 (Access of Resource Using Incompatible Type) and CWE-911 (Improper Update of Reference Count) are also less directly applicable. CWE-415 (Double Free) is similar to **use-after-free**, but the description specifically mentions reuse after free, not a double free. CWE-122 (Heap-based Buffer Overflow) and CWE-787 (Out-of-bounds Write) are potential consequences of the **use-after-free**, but not the root cause.\n\nThe selection of CWE-416 is at the Variant level, which is a preferred level of abstraction for mapping to the root causes of vulnerabilities. The other considered CWEs were at the Base or Class level, making CWE-416 the most specific and accurate choice.\n\nRelevant CWE Information:\n\n# Enhanced Context (25 CWEs)\nThe following CWEs were identified as potentially relevant to this vulnerability:\n\n## CWE-451: User Interface (UI) Misrepresentation of Critical Information\n**Abstraction Level**: Class\n**Similarity Score**: 0.76\n**Source**: dense\n\n**Description**:\nThe user interface (UI) does not properly represent critical information to the user, allowing the information - or its source - to be obscured or spoofed. This is often a component in phishing attacks.\n\n**Mapping Guidance**:\n- Usage: Allowed-with-Review\n- Rationale: This CWE entry is a Class and might have Base-level children that would be more appropriate\n\n## CWE-416: Use After Free\n**Abstraction Level**: Variant\n**Similarity Score**: 0.75\n**Source**: dense\n\n**Description**:\nThe product reuses or references memory after it has been freed. At some point afterward, the memory may be allocated again and saved in another pointer, while the original pointer references a location somewhere within the new allocation. Any operations using the original pointer are no longer valid because the memory \"belongs\" to the code that operates on the new pointer.\n\n**Mapping Guidance**:\n- Usage: Allowed\n- Rationale: This CWE entry is at the Variant level of abstraction, which is a preferred level of abstraction for mapping to the root causes of vulnerabilities.\n\n## CWE-366: Race Condition within a Thread\n**Abstraction Level**: Base\n**Similarity Score**: 0.75\n**Source**: dense\n\n**Description**:\nIf two threads of execution use a resource simultaneously, there exists the possibility that resources may be used while invalid, in turn making the state of execution undefined.\n\n**Mapping Guidance**:\n- Usage: Allowed\n- Rationale: This CWE entry is at the Base level of abstraction, which is a preferred level of abstraction for mapping to the root causes of vulnerabilities.\n\n## CWE-843: Access of Resource Using Incompatible Type ('Type Confusion')\n**Abstraction Level**: Base\n**Similarity Score**: 0.75\n**Source**: dense\n\n**Description**:\nThe product allocates or initializes a resource such as a pointer, object, or variable using one type, but it later accesses that resource using a type that is incompatible with the original type.\n\n**Mapping Guidance**:\n- Usage: Allowed\n- Rationale: This CWE entry is at the Base level of abstraction, which is a preferred level of abstraction for mapping to the root causes of vulnerabilities.\n\n## CWE-824: Access of Uninitialized Pointer\n**Abstraction Level**: Base\n**Similarity Score**: 0.74\n**Source**: dense\n\n**Description**:\nThe product accesses or uses a pointer that has not been initialized.\n\n**Mapping Guidance**:\n- Usage: Allowed\n- Rationale: This CWE entry is at the Base level of abstraction, which is a preferred level of abstraction for mapping to the root causes of vulnerabilities.\n\n## CWE-667: Improper Locking\n**Abstraction Level**: Class\n**Similarity Score**: 0.73\n**Source**: dense\n\n**Description**:\nThe product does not properly acquire or release a lock on a resource, leading to unexpected resource state changes and behaviors.\n\n**Mapping Guidance**:\n- Usage: Allowed-with-Review\n- Rationale: This CWE entry is a Class and might have Base-level children that would be more appropriate\n\n## CWE-367: Time-of-check Time-of-use (TOCTOU) Race Condition\n**Abstraction Level**: Base\n**Similarity Score**: 0.73\n**Source**: dense\n\n**Description**:\nThe product checks the state of a resource before using that resource, but the resource's state can change between the check and the use in a way that invalidates the results of the check. This can cause the product to perform invalid actions when the resource is in an unexpected state.\n\n**Mapping Guidance**:\n- Usage: Allowed\n- Rationale: This CWE entry is at the Base level of abstraction, which is a preferred level of abstraction for mapping to the root causes of vulnerabilities.\n\n## CWE-356: Product UI does not Warn User of Unsafe Actions\n**Abstraction Level**: Base\n**Similarity Score**: 0.73\n**Source**: dense\n\n**Description**:\nThe product's user interface does not warn the user before undertaking an unsafe action on behalf of that user. This makes it easier for attackers to trick users into inflicting damage to their system.\n\n**Mapping Guidance**:\n- Usage: Allowed\n- Rationale: This CWE entry is at the Base level of abstraction, which is a preferred level of abstraction for mapping to the root causes of vulnerabilities.\n\n## CWE-665: Improper Initialization\n**Abstraction Level**: Class\n**Similarity Score**: 0.73\n**Source**: dense\n\n**Description**:\nThe product does not initialize or incorrectly initializes a resource, which might leave the resource in an unexpected state when it is accessed or used.\n\n**Mapping Guidance**:\n- Usage: Discouraged\n- Rationale: This CWE entry is a level-1 Class (i\n\n\n## CWE Relationship Analysis\n\nCurrent CWEs represent these abstraction levels: .\n\n\n### Vulnerability Chain Analysis\n\n**Chain starting from CWE-416:**\n- 416 (Use After Free) - ROOT\n\n\n**Chain starting from CWE-911:**\n- 911 (Improper Update of Reference Count) - ROOT\n\n\n\n### CWE Relationship Diagram\n\n```mermaid\ngraph TD\n    classDef primary fill:#f96,stroke:#333,stroke-width:2px\n    classDef secondary fill:#69f,stroke:#333\n    classDef tertiary fill:#9e9,stroke:#333\n```",
  "criticism": "",
  "resolution": "",
  "relevant_cwes": [
    {
      "metadata": {
        "doc_id": "416",
        "name": "Use After Free",
        "source": "sparse",
        "original_content": "The product reuses or references memory after it has been freed. At some point afterward, the memory may be allocated again and saved in another pointer, while the original pointer references a location somewhere within the new allocation. Any operations using the original pointer are no longer valid because the memory \"belongs\" to the code that operates on the new pointer.",
        "keyphrase_sources": [
          {
            "id": "rootcause:Use after free",
            "keyphrase": "Use after free",
            "type": "rootcause"
          },
          {
            "id": "rootcause:use-after-free",
            "keyphrase": "use-after-free",
            "type": "rootcause"
          },
          {
            "id": "weakness:use-after-free",
            "keyphrase": "use-after-free",
            "type": "weakness"
          },
          {
            "id": "impact:potentially exploit heap corruption",
            "keyphrase": "potentially exploit heap corruption",
            "type": "impact"
          },
          {
            "id": "vector:crafted HTML page",
            "keyphrase": "crafted HTML page",
            "type": "vector"
          },
          {
            "id": "attacker:remote attacker",
            "keyphrase": "remote attacker",
            "type": "attacker"
          },
          {
            "id": "product:Google Chrome",
            "keyphrase": "Google Chrome",
            "type": "product"
          },
          {
            "id": "version:prior to 133.0.6943.53",
            "keyphrase": "prior to 133.0.6943.53",
            "type": "version"
          },
          {
            "id": "component:V8",
            "keyphrase": "V8",
            "type": "component"
          }
        ]
      },
      "similarity": 376.1066461567873
    },
    {
      "metadata": {
        "doc_id": "366",
        "name": "Race Condition within a Thread",
        "source": "sparse",
        "original_content": "If two threads of execution use a resource simultaneously, there exists the possibility that resources may be used while invalid, in turn making the state of execution undefined.",
        "keyphrase_sources": [
          {
            "id": "rootcause:Use after free",
            "keyphrase": "Use after free",
            "type": "rootcause"
          },
          {
            "id": "rootcause:use-after-free",
            "keyphrase": "use-after-free",
            "type": "rootcause"
          },
          {
            "id": "weakness:use-after-free",
            "keyphrase": "use-after-free",
            "type": "weakness"
          },
          {
            "id": "impact:potentially exploit heap corruption",
            "keyphrase": "potentially exploit heap corruption",
            "type": "impact"
          },
          {
            "id": "vector:crafted HTML page",
            "keyphrase": "crafted HTML page",
            "type": "vector"
          },
          {
            "id": "attacker:remote attacker",
            "keyphrase": "remote attacker",
            "type": "attacker"
          },
          {
            "id": "product:Google Chrome",
            "keyphrase": "Google Chrome",
            "type": "product"
          },
          {
            "id": "version:prior to 133.0.6943.53",
            "keyphrase": "prior to 133.0.6943.53",
            "type": "version"
          },
          {
            "id": "component:V8",
            "keyphrase": "V8",
            "type": "component"
          }
        ]
      },
      "similarity": 311.85831012143603
    },
    {
      "metadata": {
        "doc_id": "843",
        "name": "Access of Resource Using Incompatible Type ('Type Confusion')",
        "source": "sparse",
        "original_content": "The product allocates or initializes a resource such as a pointer, object, or variable using one type, but it later accesses that resource using a type that is incompatible with the original type.",
        "keyphrase_sources": [
          {
            "id": "rootcause:Use after free",
            "keyphrase": "Use after free",
            "type": "rootcause"
          },
          {
            "id": "rootcause:use-after-free",
            "keyphrase": "use-after-free",
            "type": "rootcause"
          },
          {
            "id": "weakness:use-after-free",
            "keyphrase": "use-after-free",
            "type": "weakness"
          },
          {
            "id": "impact:potentially exploit heap corruption",
            "keyphrase": "potentially exploit heap corruption",
            "type": "impact"
          },
          {
            "id": "vector:crafted HTML page",
            "keyphrase": "crafted HTML page",
            "type": "vector"
          },
          {
            "id": "attacker:remote attacker",
            "keyphrase": "remote attacker",
            "type": "attacker"
          },
          {
            "id": "product:Google Chrome",
            "keyphrase": "Google Chrome",
            "type": "product"
          },
          {
            "id": "version:prior to 133.0.6943.53",
            "keyphrase": "prior to 133.0.6943.53",
            "type": "version"
          },
          {
            "id": "component:V8",
            "keyphrase": "V8",
            "type": "component"
          }
        ]
      },
      "similarity": 297.7986455325563
    },
    {
      "metadata": {
        "doc_id": "911",
        "name": "Improper Update of Reference Count",
        "source": "sparse",
        "original_content": "The product uses a reference count to manage a resource, but it does not update or incorrectly updates the reference count.",
        "keyphrase_sources": [
          {
            "id": "rootcause:Use after free",
            "keyphrase": "Use after free",
            "type": "rootcause"
          },
          {
            "id": "rootcause:use-after-free",
            "keyphrase": "use-after-free",
            "type": "rootcause"
          },
          {
            "id": "weakness:use-after-free",
            "keyphrase": "use-after-free",
            "type": "weakness"
          },
          {
            "id": "component:V8",
            "keyphrase": "V8",
            "type": "component"
          }
        ]
      },
      "similarity": 261.6395309782629
    },
    {
      "metadata": {
        "doc_id": "415",
        "name": "Double Free",
        "source": "sparse",
        "original_content": "The product calls free() twice on the same memory address, potentially leading to modification of unexpected memory locations.",
        "keyphrase_sources": [
          {
            "id": "rootcause:Use after free",
            "keyphrase": "Use after free",
            "type": "rootcause"
          },
          {
            "id": "rootcause:use-after-free",
            "keyphrase": "use-after-free",
            "type": "rootcause"
          },
          {
            "id": "weakness:use-after-free",
            "keyphrase": "use-after-free",
            "type": "weakness"
          },
          {
            "id": "impact:potentially exploit heap corruption",
            "keyphrase": "potentially exploit heap corruption",
            "type": "impact"
          }
        ]
      },
      "similarity": 248.36505104677587
    },
    {
      "metadata": {
        "doc_id": "122",
        "name": "Heap-based Buffer Overflow",
        "source": "sparse",
        "original_content": "A heap overflow condition is a buffer overflow, where the buffer that can be overwritten is allocated in the heap portion of memory, generally meaning that the buffer was allocated using a routine such as malloc().",
        "keyphrase_sources": [
          {
            "id": "impact:potentially exploit heap corruption",
            "keyphrase": "potentially exploit heap corruption",
            "type": "impact"
          },
          {
            "id": "vector:crafted HTML page",
            "keyphrase": "crafted HTML page",
            "type": "vector"
          },
          {
            "id": "attacker:remote attacker",
            "keyphrase": "remote attacker",
            "type": "attacker"
          },
          {
            "id": "product:Google Chrome",
            "keyphrase": "Google Chrome",
            "type": "product"
          },
          {
            "id": "version:prior to 133.0.6943.53",
            "keyphrase": "prior to 133.0.6943.53",
            "type": "version"
          },
          {
            "id": "component:V8",
            "keyphrase": "V8",
            "type": "component"
          }
        ]
      },
      "similarity": 104.65505906703211
    },
    {
      "metadata": {
        "doc_id": "356",
        "name": "Product UI does not Warn User of Unsafe Actions",
        "source": "sparse",
        "original_content": "The product's user interface does not warn the user before undertaking an unsafe action on behalf of that user. This makes it easier for attackers to trick users into inflicting damage to their system.",
        "keyphrase_sources": [
          {
            "id": "vector:crafted HTML page",
            "keyphrase": "crafted HTML page",
            "type": "vector"
          },
          {
            "id": "attacker:remote attacker",
            "keyphrase": "remote attacker",
            "type": "attacker"
          },
          {
            "id": "product:Google Chrome",
            "keyphrase": "Google Chrome",
            "type": "product"
          },
          {
            "id": "version:prior to 133.0.6943.53",
            "keyphrase": "prior to 133.0.6943.53",
            "type": "version"
          }
        ]
      },
      "similarity": 87.31632366067959
    }
  ],
  "identified_cwes": {
    "analyzer": [
      "CWE-416",
      "CWE-911",
      "CWE-787",
      "CWE-667",
      "CWE-356",
      "CWE-843",
      "CWE-122",
      "CWE-451",
      "CWE-824",
      "CWE-119",
      "CWE-366",
      "CWE-367",
      "CWE-415",
      "CWE-665"
    ],
    "critic_additional": []
  },
  "keyphrase_cwe_mapping": {
    "416": [
      {
        "id": "rootcause:Use after free",
        "keyphrase": "Use after free",
        "type": "rootcause"
      },
      {
        "id": "rootcause:use-after-free",
        "keyphrase": "use-after-free",
        "type": "rootcause"
      },
      {
        "id": "weakness:use-after-free",
        "keyphrase": "use-after-free",
        "type": "weakness"
      },
      {
        "id": "impact:potentially exploit heap corruption",
        "keyphrase": "potentially exploit heap corruption",
        "type": "impact"
      },
      {
        "id": "vector:crafted HTML page",
        "keyphrase": "crafted HTML page",
        "type": "vector"
      },
      {
        "id": "attacker:remote attacker",
        "keyphrase": "remote attacker",
        "type": "attacker"
      },
      {
        "id": "product:Google Chrome",
        "keyphrase": "Google Chrome",
        "type": "product"
      },
      {
        "id": "version:prior to 133.0.6943.53",
        "keyphrase": "prior to 133.0.6943.53",
        "type": "version"
      },
      {
        "id": "component:V8",
        "keyphrase": "V8",
        "type": "component"
      }
    ],
    "366": [
      {
        "id": "rootcause:Use after free",
        "keyphrase": "Use after free",
        "type": "rootcause"
      },
      {
        "id": "rootcause:use-after-free",
        "keyphrase": "use-after-free",
        "type": "rootcause"
      },
      {
        "id": "weakness:use-after-free",
        "keyphrase": "use-after-free",
        "type": "weakness"
      },
      {
        "id": "impact:potentially exploit heap corruption",
        "keyphrase": "potentially exploit heap corruption",
        "type": "impact"
      },
      {
        "id": "vector:crafted HTML page",
        "keyphrase": "crafted HTML page",
        "type": "vector"
      },
      {
        "id": "attacker:remote attacker",
        "keyphrase": "remote attacker",
        "type": "attacker"
      },
      {
        "id": "product:Google Chrome",
        "keyphrase": "Google Chrome",
        "type": "product"
      },
      {
        "id": "version:prior to 133.0.6943.53",
        "keyphrase": "prior to 133.0.6943.53",
        "type": "version"
      },
      {
        "id": "component:V8",
        "keyphrase": "V8",
        "type": "component"
      }
    ],
    "843": [
      {
        "id": "rootcause:Use after free",
        "keyphrase": "Use after free",
        "type": "rootcause"
      },
      {
        "id": "rootcause:use-after-free",
        "keyphrase": "use-after-free",
        "type": "rootcause"
      },
      {
        "id": "weakness:use-after-free",
        "keyphrase": "use-after-free",
        "type": "weakness"
      },
      {
        "id": "impact:potentially exploit heap corruption",
        "keyphrase": "potentially exploit heap corruption",
        "type": "impact"
      },
      {
        "id": "vector:crafted HTML page",
        "keyphrase": "crafted HTML page",
        "type": "vector"
      },
      {
        "id": "attacker:remote attacker",
        "keyphrase": "remote attacker",
        "type": "attacker"
      },
      {
        "id": "product:Google Chrome",
        "keyphrase": "Google Chrome",
        "type": "product"
      },
      {
        "id": "version:prior to 133.0.6943.53",
        "keyphrase": "prior to 133.0.6943.53",
        "type": "version"
      },
      {
        "id": "component:V8",
        "keyphrase": "V8",
        "type": "component"
      }
    ],
    "911": [
      {
        "id": "rootcause:Use after free",
        "keyphrase": "Use after free",
        "type": "rootcause"
      },
      {
        "id": "rootcause:use-after-free",
        "keyphrase": "use-after-free",
        "type": "rootcause"
      },
      {
        "id": "weakness:use-after-free",
        "keyphrase": "use-after-free",
        "type": "weakness"
      },
      {
        "id": "component:V8",
        "keyphrase": "V8",
        "type": "component"
      }
    ],
    "415": [
      {
        "id": "rootcause:Use after free",
        "keyphrase": "Use after free",
        "type": "rootcause"
      },
      {
        "id": "rootcause:use-after-free",
        "keyphrase": "use-after-free",
        "type": "rootcause"
      },
      {
        "id": "weakness:use-after-free",
        "keyphrase": "use-after-free",
        "type": "weakness"
      },
      {
        "id": "impact:potentially exploit heap corruption",
        "keyphrase": "potentially exploit heap corruption",
        "type": "impact"
      }
    ],
    "122": [
      {
        "id": "impact:potentially exploit heap corruption",
        "keyphrase": "potentially exploit heap corruption",
        "type": "impact"
      },
      {
        "id": "vector:crafted HTML page",
        "keyphrase": "crafted HTML page",
        "type": "vector"
      },
      {
        "id": "attacker:remote attacker",
        "keyphrase": "remote attacker",
        "type": "attacker"
      },
      {
        "id": "product:Google Chrome",
        "keyphrase": "Google Chrome",
        "type": "product"
      },
      {
        "id": "version:prior to 133.0.6943.53",
        "keyphrase": "prior to 133.0.6943.53",
        "type": "version"
      },
      {
        "id": "component:V8",
        "keyphrase": "V8",
        "type": "component"
      }
    ],
    "356": [
      {
        "id": "vector:crafted HTML page",
        "keyphrase": "crafted HTML page",
        "type": "vector"
      },
      {
        "id": "attacker:remote attacker",
        "keyphrase": "remote attacker",
        "type": "attacker"
      },
      {
        "id": "product:Google Chrome",
        "keyphrase": "Google Chrome",
        "type": "product"
      },
      {
        "id": "version:prior to 133.0.6943.53",
        "keyphrase": "prior to 133.0.6943.53",
        "type": "version"
      }
    ]
  }
}