{
  "cve_id": "CVE-2025-21352",
  "description": "Internet Connection Sharing (ICS) Denial of Service Vulnerability",
  "key_phrases": {
    "rootcause": "",
    "weakness": "",
    "impact": "Denial of Service",
    "vector": "",
    "attacker": "",
    "product": "",
    "version": "",
    "component": "Internet Connection Sharing"
  },
  "reference_content": "UNRELATED",
  "similar_info": {
    "cwe_distribution": {},
    "cwe_consensus": "",
    "similarity_stats": {
      "thresholds": [],
      "total_samples_by_threshold": {},
      "top_cwes_by_threshold": {}
    }
  },
  "similarity_summary": {
    "consensus_cwe": "",
    "top_cwes": [],
    "confidence_levels": {},
    "total_samples": 0
  },
  "analysis": "# Summary\n| CWE ID | CWE Name | Confidence | CWE Abstraction Level | CWE Vulnerability Mapping Label | CWE-Vulnerability Mapping Notes |\n|---|---|---|---|---|---|\n| CWE-400 | Uncontrolled Resource Consumption | 0.7 | Class | Primary | Allowed-with-Review |\n| CWE-770 | Allocation of Resources Without Limits or Throttling | 0.5 | Base | Secondary Candidate | Allowed |\n| CWE-406 | Insufficient Control of Network Message Volume (Network Amplification) | 0.4 | Class | Secondary Candidate | Allowed-with-Review |\n\n## Evidence and Confidence\n\n*   **Confidence Score:** 0.7\n*   **Evidence Strength:** LOW\n\n## Relationship Analysis\nThe primary CWE selected is CWE-400 **Uncontrolled Resource Consumption**. It's a Class-level CWE, and the Retriever suggests that more specific Base-level children might be more appropriate. CWE-770 **Allocation of Resources Without Limits or Throttling** is a child of CWE-400 and a possible candidate, but there's not enough evidence to confirm whether resources are being allocated without limits. CWE-406 **Insufficient Control of Network Message Volume (Network Amplification)** is another Class-level CWE. CWE-941 **Incorrectly Specified Destination in a Communication Channel** is a child of CWE-923 and can precede CWE-406, but the provided information doesn't show the communication channel to be the issue.\n\n```mermaid\ngraph TD\n    cwe400[\"CWE-400: Uncontrolled Resource Consumption\"]\n    cwe770[\"CWE-770: Allocation of Resources Without Limits or Throttling\"]\n    cwe406[\"CWE-406: Insufficient Control of Network Message Volume (Network Amplification)\"]\n    cwe941[\"CWE-941: Incorrectly Specified Destination in a Communication Channel\"]\n    cwe923[\"CWE-923: Improper Restriction of Communication Channel to Intended Endpoints\"]\n\n    cwe770 -->|CHILDOF| cwe400\n    cwe406 -->|PEEROF| cwe400\n    cwe941 -->|CANPRECEDE| cwe406\n    cwe941 -->|CHILDOF| cwe923\n    \n\n    classDef primary fill:#f96,stroke:#333,stroke-width:2px\n    classDef secondary fill:#69f,stroke:#333\n    classDef tertiary fill:#9e9,stroke:#333\n    class cwe400 primary\n    class cwe770,cwe406 secondary\n```\n\n## Vulnerability Chain\nThe vulnerability chain starts with the Internet Connection Sharing (ICS) component and leads to a **Denial of Service** **impact**. Due to the lack of information, it's difficult to pinpoint the exact root cause, but the most likely scenario is **Uncontrolled Resource Consumption (CWE-400)**, where the ICS component consumes excessive resources, leading to the denial of service.\n\n## Summary of Analysis\nThe assessment is based on the limited information provided in the vulnerability description. The primary indicator is the \"Denial of Service\" **impact** on the \"Internet Connection Sharing\" component.\n\nGiven the limited evidence, the selection of CWE-400 is a reasonable initial classification. Further investigation would be needed to identify a more precise root cause and select a more specific CWE. The graph relationships highlight potential related weaknesses, but the absence of details prevents a more definitive mapping.\n\nRelevant CWE Information:\n\n# Enhanced Context (25 CWEs)\nThe following CWEs were identified as potentially relevant to this vulnerability:\n\n## CWE-799: Improper Control of Interaction Frequency\n**Abstraction Level**: Class\n**Similarity Score**: 0.71\n**Source**: dense\n\n**Description**:\nThe product does not properly limit the number or frequency of interactions that it has with an actor, such as the number of incoming requests.\n\n**Mapping Guidance**:\n- Usage: Allowed-with-Review\n- Rationale: This CWE entry is a Class and might have Base-level children that would be more appropriate\n\n\n\n## CWE-405: Asymmetric Resource Consumption (Amplification)\n**Abstraction Level**: Class\n**Similarity Score**: 0.70\n**Source**: dense\n\n**Description**:\nThe product does not properly control situations in which an adversary can cause the product to consume or produce excessive resources without requiring the adversary to invest equivalent work or otherwise prove authorization, i.e., the adversary's influence is \"asymmetric.\"\n\n**Mapping Guidance**:\n- Usage: Allowed-with-Review\n- Rationale: This CWE entry is a Class and might have Base-level children that would be more appropriate\n\n\n\n## CWE-755: Improper Handling of Exceptional Conditions\n**Abstraction Level**: Class\n**Similarity Score**: 0.69\n**Source**: dense\n\n**Description**:\nThe product does not handle or incorrectly handles an exceptional condition.\n\n**Mapping Guidance**:\n- Usage: Discouraged\n- Rationale: This CWE entry is a level-1 Class (i.e., a child of a Pillar). It might have lower-level children that would be more appropriate\n\n\n\n## CWE-134: Use of Externally-Controlled Format String\n**Abstraction Level**: Base\n**Similarity Score**: 0.69\n**Source**: dense\n\n**Description**:\nThe product uses a function that accepts a format string as an argument, but the format string originates from an external source.\n\n**Mapping Guidance**:\n- Usage: Allowed\n- Rationale: This CWE entry is at the Base level of abstraction, which is a preferred level of abstraction for mapping to the root causes of vulnerabilities.\n\n\n\n## CWE-653: Improper Isolation or Compartmentalization\n**Abstraction Level**: Class\n**Similarity Score**: 0.69\n**Source**: dense\n\n**Description**:\nThe product does not properly compartmentalize or isolate functionality, processes, or resources that require different privilege levels, rights, or permissions.\n\n**Mapping Guidance**:\n- Usage: Allowed\n- Rationale: This CWE entry is at the Base level of abstraction, which is a preferred level of abstraction for mapping to the root causes of vulnerabilities.\n\n\n\n## CWE-406: Insufficient Control of Network Message Volume (Network Amplification)\n**Abstraction Level**: Class\n**Similarity Score**: 0.69\n**Source**: dense\n\n**Description**:\nThe product does not sufficiently monitor or control transmitted network traffic volume, so that an actor can cause the product to transmit more traffic than should be allowed for that actor.\n\n**Mapping Guidance**:\n- Usage: Allowed-with-Review\n- Rationale: This CWE entry is a Class and might have Base-level children that would be more appropriate\n\n\n\n## CWE-941: Incorrectly Specified Destination in a Communication Channel\n**Abstraction Level**: Base\n**Similarity Score**: 0.69\n**Source**: dense\n\n**Description**:\nThe product creates a communication channel to initiate an outgoing request to an actor, but it does not correctly specify the intended destination for that actor.\n\n**Mapping Guidance**:\n- Usage: Allowed\n- Rationale: This CWE entry is at the Base level of abstraction, which is a preferred level of abstraction for mapping to the root causes of vulnerabilities.\n\n\n\n## CWE-754: Improper Check for Unusual or Exceptional Conditions\n**Abstraction Level**: Class\n**Similarity Score**: 0.69\n**Source**: dense\n\n**Description**:\nThe product does not check or incorrectly checks for unusual or exceptional conditions that are not expected to occur frequently during day to day operation of the product.\n\n**Mapping Guidance**:\n- Usage: Allowed-with-Review\n- Rationale: This CWE entry is a Class and might have Base-level children that would be more appropriate\n\n\n\n## CWE-410: Insufficient Resource Pool\n**Abstraction Level**: Base\n**Similarity Score**: 0.69\n**Source**: dense\n\n**Description**:\nThe product's resource pool is not large enough to handle peak demand, which allows an attacker to prevent others from accessing the resource by using a (relatively) large number of requests for resources.\n\n**Mapping Guidance**:\n- Usage: Allowed\n- Rationale: This CWE entry is at the Base level of abstraction, which is a preferred level of abstraction for mapping to the root causes of vulnerabilities.\n\n\n\n## CWE-280: Improper Handling of Insufficient Permissions or Privileges \n**Abstraction Level**: Base\n**Similarity Score**: 0.69\n**Source**: dense\n\n**Description**:\nThe product does not handle or incorrectly handles when it has insufficient privileges to access resources or functionality as specified by their permissions. This may cause it to follow unexpected code paths that may leave the product in an invalid state.\n\n**Mapping Guidance**:\n- Usage: Allowed\n- Rationale: This CWE entry is at the Base level of abstraction, which is a preferred level of abstraction for mapping to the root causes of vulnerabilities.\n\n\n\n## CWE-1331: Improper Isolation of Shared Resources in Network On Chip (NoC)\n**Abstraction Level**: Base\n**Similarity Score**: 332.02\n**Source**: sparse\n\n**Description**:\nThe Network On Chip (NoC) does not isolate or incorrectly isolates its on-chip-fabric and internal resources such that they are shared between trusted and untrusted agents, creating timing channels.\n\n**Mapping Guidance**:\n- Usage",
  "analysis_with_relationships": "# Summary\n| CWE ID | CWE Name | Confidence | CWE Abstraction Level | CWE Vulnerability Mapping Label | CWE-Vulnerability Mapping Notes |\n|---|---|---|---|---|---|\n| CWE-400 | Uncontrolled Resource Consumption | 0.7 | Class | Primary | Allowed-with-Review |\n| CWE-770 | Allocation of Resources Without Limits or Throttling | 0.5 | Base | Secondary Candidate | Allowed |\n| CWE-406 | Insufficient Control of Network Message Volume (Network Amplification) | 0.4 | Class | Secondary Candidate | Allowed-with-Review |\n\n## Evidence and Confidence\n\n*   **Confidence Score:** 0.7\n*   **Evidence Strength:** LOW\n\n## Relationship Analysis\nThe primary CWE selected is CWE-400 **Uncontrolled Resource Consumption**. It's a Class-level CWE, and the Retriever suggests that more specific Base-level children might be more appropriate. CWE-770 **Allocation of Resources Without Limits or Throttling** is a child of CWE-400 and a possible candidate, but there's not enough evidence to confirm whether resources are being allocated without limits. CWE-406 **Insufficient Control of Network Message Volume (Network Amplification)** is another Class-level CWE. CWE-941 **Incorrectly Specified Destination in a Communication Channel** is a child of CWE-923 and can precede CWE-406, but the provided information doesn't show the communication channel to be the issue.\n\n```mermaid\ngraph TD\n    cwe400[\"CWE-400: Uncontrolled Resource Consumption\"]\n    cwe770[\"CWE-770: Allocation of Resources Without Limits or Throttling\"]\n    cwe406[\"CWE-406: Insufficient Control of Network Message Volume (Network Amplification)\"]\n    cwe941[\"CWE-941: Incorrectly Specified Destination in a Communication Channel\"]\n    cwe923[\"CWE-923: Improper Restriction of Communication Channel to Intended Endpoints\"]\n\n    cwe770 -->|CHILDOF| cwe400\n    cwe406 -->|PEEROF| cwe400\n    cwe941 -->|CANPRECEDE| cwe406\n    cwe941 -->|CHILDOF| cwe923\n    \n\n    classDef primary fill:#f96,stroke:#333,stroke-width:2px\n    classDef secondary fill:#69f,stroke:#333\n    classDef tertiary fill:#9e9,stroke:#333\n    class cwe400 primary\n    class cwe770,cwe406 secondary\n```\n\n## Vulnerability Chain\nThe vulnerability chain starts with the Internet Connection Sharing (ICS) component and leads to a **Denial of Service** **impact**. Due to the lack of information, it's difficult to pinpoint the exact root cause, but the most likely scenario is **Uncontrolled Resource Consumption (CWE-400)**, where the ICS component consumes excessive resources, leading to the denial of service.\n\n## Summary of Analysis\nThe assessment is based on the limited information provided in the vulnerability description. The primary indicator is the \"Denial of Service\" **impact** on the \"Internet Connection Sharing\" component.\n\nGiven the limited evidence, the selection of CWE-400 is a reasonable initial classification. Further investigation would be needed to identify a more precise root cause and select a more specific CWE. The graph relationships highlight potential related weaknesses, but the absence of details prevents a more definitive mapping.\n\nRelevant CWE Information:\n\n# Enhanced Context (25 CWEs)\nThe following CWEs were identified as potentially relevant to this vulnerability:\n\n## CWE-799: Improper Control of Interaction Frequency\n**Abstraction Level**: Class\n**Similarity Score**: 0.71\n**Source**: dense\n\n**Description**:\nThe product does not properly limit the number or frequency of interactions that it has with an actor, such as the number of incoming requests.\n\n**Mapping Guidance**:\n- Usage: Allowed-with-Review\n- Rationale: This CWE entry is a Class and might have Base-level children that would be more appropriate\n\n\n\n## CWE-405: Asymmetric Resource Consumption (Amplification)\n**Abstraction Level**: Class\n**Similarity Score**: 0.70\n**Source**: dense\n\n**Description**:\nThe product does not properly control situations in which an adversary can cause the product to consume or produce excessive resources without requiring the adversary to invest equivalent work or otherwise prove authorization, i.e., the adversary's influence is \"asymmetric.\"\n\n**Mapping Guidance**:\n- Usage: Allowed-with-Review\n- Rationale: This CWE entry is a Class and might have Base-level children that would be more appropriate\n\n\n\n## CWE-755: Improper Handling of Exceptional Conditions\n**Abstraction Level**: Class\n**Similarity Score**: 0.69\n**Source**: dense\n\n**Description**:\nThe product does not handle or incorrectly handles an exceptional condition.\n\n**Mapping Guidance**:\n- Usage: Discouraged\n- Rationale: This CWE entry is a level-1 Class (i.e., a child of a Pillar). It might have lower-level children that would be more appropriate\n\n\n\n## CWE-134: Use of Externally-Controlled Format String\n**Abstraction Level**: Base\n**Similarity Score**: 0.69\n**Source**: dense\n\n**Description**:\nThe product uses a function that accepts a format string as an argument, but the format string originates from an external source.\n\n**Mapping Guidance**:\n- Usage: Allowed\n- Rationale: This CWE entry is at the Base level of abstraction, which is a preferred level of abstraction for mapping to the root causes of vulnerabilities.\n\n\n\n## CWE-653: Improper Isolation or Compartmentalization\n**Abstraction Level**: Class\n**Similarity Score**: 0.69\n**Source**: dense\n\n**Description**:\nThe product does not properly compartmentalize or isolate functionality, processes, or resources that require different privilege levels, rights, or permissions.\n\n**Mapping Guidance**:\n- Usage: Allowed\n- Rationale: This CWE entry is at the Base level of abstraction, which is a preferred level of abstraction for mapping to the root causes of vulnerabilities.\n\n\n\n## CWE-406: Insufficient Control of Network Message Volume (Network Amplification)\n**Abstraction Level**: Class\n**Similarity Score**: 0.69\n**Source**: dense\n\n**Description**:\nThe product does not sufficiently monitor or control transmitted network traffic volume, so that an actor can cause the product to transmit more traffic than should be allowed for that actor.\n\n**Mapping Guidance**:\n- Usage: Allowed-with-Review\n- Rationale: This CWE entry is a Class and might have Base-level children that would be more appropriate\n\n\n\n## CWE-941: Incorrectly Specified Destination in a Communication Channel\n**Abstraction Level**: Base\n**Similarity Score**: 0.69\n**Source**: dense\n\n**Description**:\nThe product creates a communication channel to initiate an outgoing request to an actor, but it does not correctly specify the intended destination for that actor.\n\n**Mapping Guidance**:\n- Usage: Allowed\n- Rationale: This CWE entry is at the Base level of abstraction, which is a preferred level of abstraction for mapping to the root causes of vulnerabilities.\n\n\n\n## CWE-754: Improper Check for Unusual or Exceptional Conditions\n**Abstraction Level**: Class\n**Similarity Score**: 0.69\n**Source**: dense\n\n**Description**:\nThe product does not check or incorrectly checks for unusual or exceptional conditions that are not expected to occur frequently during day to day operation of the product.\n\n**Mapping Guidance**:\n- Usage: Allowed-with-Review\n- Rationale: This CWE entry is a Class and might have Base-level children that would be more appropriate\n\n\n\n## CWE-410: Insufficient Resource Pool\n**Abstraction Level**: Base\n**Similarity Score**: 0.69\n**Source**: dense\n\n**Description**:\nThe product's resource pool is not large enough to handle peak demand, which allows an attacker to prevent others from accessing the resource by using a (relatively) large number of requests for resources.\n\n**Mapping Guidance**:\n- Usage: Allowed\n- Rationale: This CWE entry is at the Base level of abstraction, which is a preferred level of abstraction for mapping to the root causes of vulnerabilities.\n\n\n\n## CWE-280: Improper Handling of Insufficient Permissions or Privileges \n**Abstraction Level**: Base\n**Similarity Score**: 0.69\n**Source**: dense\n\n**Description**:\nThe product does not handle or incorrectly handles when it has insufficient privileges to access resources or functionality as specified by their permissions. This may cause it to follow unexpected code paths that may leave the product in an invalid state.\n\n**Mapping Guidance**:\n- Usage: Allowed\n- Rationale: This CWE entry is at the Base level of abstraction, which is a preferred level of abstraction for mapping to the root causes of vulnerabilities.\n\n\n\n## CWE-1331: Improper Isolation of Shared Resources in Network On Chip (NoC)\n**Abstraction Level**: Base\n**Similarity Score**: 332.02\n**Source**: sparse\n\n**Description**:\nThe Network On Chip (NoC) does not isolate or incorrectly isolates its on-chip-fabric and internal resources such that they are shared between trusted and untrusted agents, creating timing channels.\n\n**Mapping Guidance**:\n- Usage\n\n\n## CWE Relationship Analysis\n\nCurrent CWEs represent these abstraction levels: .\n\n\n### Vulnerability Chain Analysis\n\n**Chain starting from CWE-280:**\n- 280 (Improper Handling of Insufficient Permissions or Privileges ) - ROOT\n\n\n**Chain starting from CWE-400:**\n- 400 (Uncontrolled Resource Consumption) - ROOT\n\n\n\n### CWE Relationship Diagram\n\n```mermaid\ngraph TD\n    classDef primary fill:#f96,stroke:#333,stroke-width:2px\n    classDef secondary fill:#69f,stroke:#333\n    classDef tertiary fill:#9e9,stroke:#333\n```",
  "criticism": "",
  "resolution": "",
  "relevant_cwes": [
    {
      "metadata": {
        "doc_id": "926",
        "name": "Improper Export of Android Application Components",
        "source": "sparse"
      },
      "similarity": 13.585847172191324
    },
    {
      "metadata": {
        "doc_id": "770",
        "name": "Allocation of Resources Without Limits or Throttling",
        "source": "sparse"
      },
      "similarity": 13.528539028020237
    },
    {
      "metadata": {
        "doc_id": "923",
        "name": "Improper Restriction of Communication Channel to Intended Endpoints",
        "source": "sparse"
      },
      "similarity": 12.767704795799812
    },
    {
      "metadata": {
        "doc_id": "841",
        "name": "Improper Enforcement of Behavioral Workflow",
        "source": "sparse"
      },
      "similarity": 12.735864300672079
    },
    {
      "metadata": {
        "doc_id": "400",
        "name": "Uncontrolled Resource Consumption",
        "source": "sparse"
      },
      "similarity": 12.569340111722829
    },
    {
      "metadata": {
        "doc_id": "410",
        "name": "Insufficient Resource Pool",
        "source": "sparse"
      },
      "similarity": 12.554965432069354
    },
    {
      "metadata": {
        "doc_id": "1331",
        "name": "Improper Isolation of Shared Resources in Network On Chip (NoC)",
        "source": "sparse"
      },
      "similarity": 12.54778531499002
    },
    {
      "metadata": {
        "doc_id": "290",
        "name": "Authentication Bypass by Spoofing",
        "source": "sparse"
      },
      "similarity": 12.444929612626224
    },
    {
      "metadata": {
        "doc_id": "406",
        "name": "Insufficient Control of Network Message Volume (Network Amplification)",
        "type": "Class",
        "original_content": "The product does not sufficiently monitor or control transmitted network traffic volume, so that an actor can cause the product to transmit more traffic than should be allowed for that actor.",
        "source": "dense",
        "mapping_notes": {
          "usage": "Allowed-with-Review",
          "rationale": "This CWE entry is a Class and might have Base-level children that would be more appropriate",
          "comments": "Examine children of this entry to see if there is a better fit",
          "reasons": [
            "Abstraction"
          ]
        },
        "score_info": {
          "retrievers": [
            "dense"
          ],
          "retriever_count": 1,
          "normalized_scores": {
            "dense": 0.5005599996644878
          }
        }
      },
      "similarity": 0.5005599996644878
    },
    {
      "doc_id": "941",
      "text": "CWE-941: Incorrectly Specified Destination in a Communication Channel",
      "score": 2.8651999999999997,
      "metadata": {
        "doc_id": "941",
        "name": "Incorrectly Specified Destination in a Communication Channel",
        "type": "base",
        "original_content": "CWE-941: Incorrectly Specified Destination in a Communication Channel",
        "relationships": [
          {
            "source_id": "941",
            "target_id": "406",
            "label": "CANPRECEDE",
            "properties": {
              "view_id": "1000"
            }
          },
          {
            "source_id": "941",
            "target_id": "923",
            "label": "CHILDOF",
            "properties": {
              "ordinal": "Primary",
              "view_id": "1000"
            }
          },
          {
            "source_id": "923",
            "target_id": "941",
            "label": "PARENTOF",
            "properties": {
              "ordinal": "Primary",
              "view_id": "1000"
            }
          },
          {
            "source_id": "406",
            "target_id": "941",
            "label": "CANFOLLOW",
            "properties": {
              "view_id": "1000"
            }
          }
        ],
        "score_components": {
          "relationship_chain": 1.0,
          "abstraction_path": 0.7200000000000001,
          "sequence_path": 1.0
        },
        "abstraction_factor": 1.3,
        "graph_path_info": {
          "path_types": [
            "relationship_chain",
            "abstraction_path_down",
            "vulnerability_sequence_forward",
            "vulnerability_sequence_backward"
          ],
          "best_paths": {
            "relationship_chain": {
              "path": [
                [
                  "406",
                  "941",
                  "CANFOLLOW"
                ]
              ],
              "score": 1.0,
              "type": "relationship_chain",
              "source": "406"
            },
            "abstraction_path_down": {
              "path": [
                [
                  "923",
                  "941",
                  "PARENTOF"
                ]
              ],
              "score": 0.7200000000000001,
              "type": "abstraction_path_down",
              "source": "923"
            },
            "vulnerability_sequence_forward": {
              "path": [
                [
                  "406",
                  "941",
                  "CANFOLLOW"
                ]
              ],
              "score": 0.9,
              "type": "vulnerability_sequence_forward",
              "source": "406"
            },
            "vulnerability_sequence_backward": {
              "path": [
                [
                  "941",
                  "406",
                  "CANPRECEDE"
                ]
              ],
              "score": 1.0,
              "type": "vulnerability_sequence_backward",
              "source": "406"
            }
          }
        },
        "abstraction_level": "base",
        "position": "before",
        "sources": [
          "graph"
        ],
        "source": "graph",
        "mapping_notes": {
          "usage": "Allowed",
          "rationale": "This CWE entry is at the Base level of abstraction, which is a preferred level of abstraction for mapping to the root causes of vulnerabilities.",
          "comments": "Carefully read both the name and description to ensure that this mapping is an appropriate fit. Do not try to 'force' a mapping to a lower-level Base/Variant simply to comply with this preferred level of abstraction.",
          "reasons": [
            "Acceptable-Use"
          ]
        },
        "score_info": {
          "retrievers": [
            "graph"
          ],
          "retriever_count": 1,
          "normalized_scores": {
            "graph": 2.8651999999999997
          }
        }
      },
      "similarity": 2.8651999999999997
    }
  ],
  "identified_cwes": {
    "analyzer": [
      "CWE-280",
      "CWE-400",
      "CWE-653",
      "CWE-770",
      "CWE-406",
      "CWE-923",
      "CWE-799",
      "CWE-1331",
      "CWE-405",
      "CWE-410",
      "CWE-755",
      "CWE-941",
      "CWE-134",
      "CWE-754"
    ],
    "critic_additional": []
  },
  "keyphrase_cwe_mapping": {}
}