{
  "cve_id": "CVE-2024-31311",
  "description": "In increment_annotation_count of stats_event.c, there is a possible **out of bounds write** due to a **missing bounds check**. This could lead to local escalation of privilege with no additional execution privileges needed. User interaction is not needed for exploitation.",
  "key_phrases": {
    "rootcause": "missing bounds check",
    "weakness": "out of bounds write",
    "impact": "local escalation of privilege",
    "vector": "",
    "attacker": "",
    "product": "",
    "version": "",
    "component": "increment_annotation_count of stats_event.c"
  },
  "reference_content": "Based on the provided information, here's an analysis of CVE-2024-31311:\n\n**Root Cause of Vulnerability:**\nThe vulnerability lies within the `libstatssocket` component, specifically related to how new data is added into `StatsEvent`. There was a lack of proper validation when adding new data, which could lead to a heap buffer overflow.\n\n**Weaknesses/Vulnerabilities Present:**\n- Heap buffer overflow: The absence of input validation allows an attacker to write beyond the allocated memory buffer for `StatsEvent`, leading to potential memory corruption.\n\n**Impact of Exploitation:**\n- Local privilege escalation: The vulnerability can be exploited to achieve local privilege escalation, meaning an attacker could gain elevated access on the affected device.\n\n**Attack Vectors:**\n- The attack vector is local, meaning an attacker needs to have local access to the device in order to exploit the vulnerability.\n\n**Required Attacker Capabilities/Position:**\n- Local access to the device is required.\n- No additional execution privileges are needed for exploitation.\n\n**Additional Notes:**\n- The provided commit message indicates that a fix was implemented by adding validation for adding new data into `StatsEvent`.\n- The fix was tested by `atest StatsEventTest#TestHeapBufferOverflowErrorIgnore`.\n- The vulnerability affects Android versions 12, 12L, 13, and 14.",
  "similar_info": {
    "cwe_distribution": {},
    "cwe_consensus": "",
    "similarity_stats": {
      "thresholds": [],
      "total_samples_by_threshold": {},
      "top_cwes_by_threshold": {}
    }
  },
  "similarity_summary": {
    "consensus_cwe": "",
    "top_cwes": [],
    "confidence_levels": {},
    "total_samples": 0
  },
  "analysis": "# Summary\n| CWE ID | CWE Name | Confidence | CWE Abstraction Level | CWE Vulnerability Mapping Label | CWE-Vulnerability Mapping Notes |\n|---|---|---|---|---|---|\n| CWE-125 | Out-of-bounds Read | 1.0 | Base | Primary | Allowed |\n| CWE-787 | Out-of-bounds Write | 1.0 | Base | Secondary | Allowed |\n\n## Evidence and Confidence\n\n*   **Confidence Score:** 1.0\n*   **Evidence Strength:** HIGH\n\n## Relationship Analysis\nThe primary relationship impacting the decision is the child-of relationship between CWE-125/CWE-787 and CWE-119 (Improper Restriction of Operations within the Bounds of a Memory Buffer). The vulnerability involves writing beyond the intended buffer, directly aligning with CWE-787. The **missing bounds check** is the root cause which leads to an out of bounds write. Since the description specifically mentions an **out of bounds write** vulnerability, CWE-787 is the most precise choice. Also because of the possibility of reading out of bounds, CWE-125 is included as a secondary candidate.\n\n```mermaid\ngraph TD\n    cwe787[\"CWE-787: Out-of-bounds Write\"]\n    cwe125[\"CWE-125: Out-of-bounds Read\"]\n    cwe119[\"CWE-119: Improper Restriction of Operations\"]\n    \n    cwe787 -->|CHILDOF| cwe119\n    cwe125 -->|CHILDOF| cwe119\n\n    classDef primary fill:#f96,stroke:#333,stroke-width:2px\n    classDef secondary fill:#69f,stroke:#333\n    classDef tertiary fill:#9e9,stroke:#333\n    class cwe787 primary\n    class cwe125 secondary\n```\n\n## Vulnerability Chain\nThe vulnerability chain starts with the **missing bounds check** which allows data to be written beyond the allocated buffer (CWE-787). This could lead to local privilege escalation.\n\n## Summary of Analysis\nThe initial assessment focused on the provided vulnerability description and the additional context from the CVE reference. The description clearly states an **out of bounds write** due to a **missing bounds check** in `increment_annotation_count` function. This immediately points to CWE-787 (Out-of-bounds Write) as the primary weakness.\n\nThe relationship analysis reinforces this choice. CWE-787 is a child of CWE-119 (Improper Restriction of Operations within the Bounds of a Memory Buffer), which is a more general case of buffer overflow vulnerabilities. Since the description is specific about writing out of bounds, CWE-787 is the more accurate and specific choice. Also because of the possibility of reading out of bounds, CWE-125 is included as a secondary candidate.\n\nThe evidence from the \"CVE Reference Links Content Summary\" further supports this, mentioning \"heap buffer overflow\" as the weakness.\n\nThe selected CWEs are at the optimal level of specificity because they directly represent the **rootcause** and **weakness** described in the vulnerability report, making them the most accurate representation of the identified issue.\n\nRelevant CWE Information:\n\n# Enhanced Context (25 CWEs)\n\n## CWE-125: Out-of-bounds Read\n**Abstraction Level**: Base\n**Similarity Score**: N/A\n\n**Description**:\nThe product reads data past the end, or before the beginning, of the intended buffer. This can cause a crash, denial of service, or potentially the disclosure of sensitive information.\n\n**Mapping Guidance**:\n- Usage: Allowed\n- Rationale: This CWE entry is at the Base level of abstraction, which is a preferred level of abstraction for mapping to the root causes of vulnerabilities.\n\n## CWE-787: Out-of-bounds Write\n**Abstraction Level**: Base\n**Similarity Score**: N/A\n\n**Description**:\nThe product writes data past the end, or before the beginning, of the intended buffer. This can cause a crash, denial of service, or potentially the execution of arbitrary code.\n\n**Mapping Guidance**:\n- Usage: Allowed\n- Rationale: This CWE entry is at the Base level of abstraction, which is a preferred level of abstraction for mapping to the root causes of vulnerabilities.\n\n## Other CWEs Considered and Rejected\n\n*   CWE-863: Incorrect Authorization, CWE-266: Incorrect Privilege Assignment, CWE-250: Execution with Unnecessary Privileges, CWE-285: Improper Authorization: These CWEs relate to privilege and permission issues. While the impact of the vulnerability is local escalation of privilege, the root cause is not related to incorrect privilege management, but rather a buffer overflow due to a **missing bounds check**. Therefore, these CWEs are not appropriate.\n*   CWE-131: Incorrect Calculation of Buffer Size: This CWE is related to calculating the buffer size incorrectly, which is not explicitly mentioned in the description. The issue is a **missing bounds check**, not necessarily an incorrect calculation.\n*   CWE-20: Improper Input Validation and CWE-1284: Improper Validation of Specified Quantity in Input: While the **missing bounds check** can be seen as a form of improper input validation, the specific problem is writing beyond the buffer, making CWE-787 more accurate.\n*   CWE-823: Use of Out-of-range Pointer Offset: This CWE is related to pointer offsets. It is related but the overall issue is an out of bounds write due to missing bounds check.\n*   CWE-1260: Improper Handling of Overlap Between Protected Memory Ranges: This is not directly related to the **missing bounds check** and **out of bounds write** situation described.\n*   CWE-367: Time-of-check Time-of-use (TOCTOU) Race Condition, CWE-362: Concurrent Execution using Shared Resource with Improper Synchronization ('Race Condition'): These CWEs involve race conditions, which are not mentioned or implied in the vulnerability description.\n*   CWE-476: NULL Pointer Dereference: This CWE is not relevant as the vulnerability is about writing beyond the buffer, not dereferencing a null pointer.\n*   CWE-609: Double-Checked Locking, CWE-667: Improper Locking: These CWEs are related to locking mechanisms, which are not relevant to the vulnerability.\n*   CWE-703: Improper Check or Handling of Exceptional Conditions, CWE-754: Improper Check for Unusual or Exceptional Conditions: These CWEs are too high level and not specific to the **missing bounds check** that causes the **out of bounds write**.\n*   CWE-129: Improper Validation of Array Index: This CWE is more specific to array indices, while the provided description is broader.\n*   CWE-908: Use of Uninitialized Resource: This CWE does not apply because the vulnerability is related to writing beyond the boundaries of a buffer, not using an uninitialized resource.\n*   CWE-191: Integer Underflow (Wrap or Wraparound): This CWE is not relevant because there's no mention of integer underflow or wraparound in the vulnerability description.",
  "analysis_with_relationships": "# Summary\n| CWE ID | CWE Name | Confidence | CWE Abstraction Level | CWE Vulnerability Mapping Label | CWE-Vulnerability Mapping Notes |\n|---|---|---|---|---|---|\n| CWE-125 | Out-of-bounds Read | 1.0 | Base | Primary | Allowed |\n| CWE-787 | Out-of-bounds Write | 1.0 | Base | Secondary | Allowed |\n\n## Evidence and Confidence\n\n*   **Confidence Score:** 1.0\n*   **Evidence Strength:** HIGH\n\n## Relationship Analysis\nThe primary relationship impacting the decision is the child-of relationship between CWE-125/CWE-787 and CWE-119 (Improper Restriction of Operations within the Bounds of a Memory Buffer). The vulnerability involves writing beyond the intended buffer, directly aligning with CWE-787. The **missing bounds check** is the root cause which leads to an out of bounds write. Since the description specifically mentions an **out of bounds write** vulnerability, CWE-787 is the most precise choice. Also because of the possibility of reading out of bounds, CWE-125 is included as a secondary candidate.\n\n```mermaid\ngraph TD\n    cwe787[\"CWE-787: Out-of-bounds Write\"]\n    cwe125[\"CWE-125: Out-of-bounds Read\"]\n    cwe119[\"CWE-119: Improper Restriction of Operations\"]\n    \n    cwe787 -->|CHILDOF| cwe119\n    cwe125 -->|CHILDOF| cwe119\n\n    classDef primary fill:#f96,stroke:#333,stroke-width:2px\n    classDef secondary fill:#69f,stroke:#333\n    classDef tertiary fill:#9e9,stroke:#333\n    class cwe787 primary\n    class cwe125 secondary\n```\n\n## Vulnerability Chain\nThe vulnerability chain starts with the **missing bounds check** which allows data to be written beyond the allocated buffer (CWE-787). This could lead to local privilege escalation.\n\n## Summary of Analysis\nThe initial assessment focused on the provided vulnerability description and the additional context from the CVE reference. The description clearly states an **out of bounds write** due to a **missing bounds check** in `increment_annotation_count` function. This immediately points to CWE-787 (Out-of-bounds Write) as the primary weakness.\n\nThe relationship analysis reinforces this choice. CWE-787 is a child of CWE-119 (Improper Restriction of Operations within the Bounds of a Memory Buffer), which is a more general case of buffer overflow vulnerabilities. Since the description is specific about writing out of bounds, CWE-787 is the more accurate and specific choice. Also because of the possibility of reading out of bounds, CWE-125 is included as a secondary candidate.\n\nThe evidence from the \"CVE Reference Links Content Summary\" further supports this, mentioning \"heap buffer overflow\" as the weakness.\n\nThe selected CWEs are at the optimal level of specificity because they directly represent the **rootcause** and **weakness** described in the vulnerability report, making them the most accurate representation of the identified issue.\n\nRelevant CWE Information:\n\n# Enhanced Context (25 CWEs)\n\n## CWE-125: Out-of-bounds Read\n**Abstraction Level**: Base\n**Similarity Score**: N/A\n\n**Description**:\nThe product reads data past the end, or before the beginning, of the intended buffer. This can cause a crash, denial of service, or potentially the disclosure of sensitive information.\n\n**Mapping Guidance**:\n- Usage: Allowed\n- Rationale: This CWE entry is at the Base level of abstraction, which is a preferred level of abstraction for mapping to the root causes of vulnerabilities.\n\n## CWE-787: Out-of-bounds Write\n**Abstraction Level**: Base\n**Similarity Score**: N/A\n\n**Description**:\nThe product writes data past the end, or before the beginning, of the intended buffer. This can cause a crash, denial of service, or potentially the execution of arbitrary code.\n\n**Mapping Guidance**:\n- Usage: Allowed\n- Rationale: This CWE entry is at the Base level of abstraction, which is a preferred level of abstraction for mapping to the root causes of vulnerabilities.\n\n## Other CWEs Considered and Rejected\n\n*   CWE-863: Incorrect Authorization, CWE-266: Incorrect Privilege Assignment, CWE-250: Execution with Unnecessary Privileges, CWE-285: Improper Authorization: These CWEs relate to privilege and permission issues. While the impact of the vulnerability is local escalation of privilege, the root cause is not related to incorrect privilege management, but rather a buffer overflow due to a **missing bounds check**. Therefore, these CWEs are not appropriate.\n*   CWE-131: Incorrect Calculation of Buffer Size: This CWE is related to calculating the buffer size incorrectly, which is not explicitly mentioned in the description. The issue is a **missing bounds check**, not necessarily an incorrect calculation.\n*   CWE-20: Improper Input Validation and CWE-1284: Improper Validation of Specified Quantity in Input: While the **missing bounds check** can be seen as a form of improper input validation, the specific problem is writing beyond the buffer, making CWE-787 more accurate.\n*   CWE-823: Use of Out-of-range Pointer Offset: This CWE is related to pointer offsets. It is related but the overall issue is an out of bounds write due to missing bounds check.\n*   CWE-1260: Improper Handling of Overlap Between Protected Memory Ranges: This is not directly related to the **missing bounds check** and **out of bounds write** situation described.\n*   CWE-367: Time-of-check Time-of-use (TOCTOU) Race Condition, CWE-362: Concurrent Execution using Shared Resource with Improper Synchronization ('Race Condition'): These CWEs involve race conditions, which are not mentioned or implied in the vulnerability description.\n*   CWE-476: NULL Pointer Dereference: This CWE is not relevant as the vulnerability is about writing beyond the buffer, not dereferencing a null pointer.\n*   CWE-609: Double-Checked Locking, CWE-667: Improper Locking: These CWEs are related to locking mechanisms, which are not relevant to the vulnerability.\n*   CWE-703: Improper Check or Handling of Exceptional Conditions, CWE-754: Improper Check for Unusual or Exceptional Conditions: These CWEs are too high level and not specific to the **missing bounds check** that causes the **out of bounds write**.\n*   CWE-129: Improper Validation of Array Index: This CWE is more specific to array indices, while the provided description is broader.\n*   CWE-908: Use of Uninitialized Resource: This CWE does not apply because the vulnerability is related to writing beyond the boundaries of a buffer, not using an uninitialized resource.\n*   CWE-191: Integer Underflow (Wrap or Wraparound): This CWE is not relevant because there's no mention of integer underflow or wraparound in the vulnerability description.\n\n\n## CWE Relationship Analysis\n\nCurrent CWEs represent these abstraction levels: .\n\n\n### Vulnerability Chain Analysis\n\n**Chain starting from CWE-476:**\n- 476 (NULL Pointer Dereference) - ROOT\n\n\n**Chain starting from CWE-125:**\n- 125 (Out-of-bounds Read) - ROOT\n\n\n\n### CWE Relationship Diagram\n\n```mermaid\ngraph TD\n    classDef primary fill:#f96,stroke:#333,stroke-width:2px\n    classDef secondary fill:#69f,stroke:#333\n    classDef tertiary fill:#9e9,stroke:#333\n```",
  "criticism": "",
  "resolution": "",
  "relevant_cwes": [
    {
      "metadata": {
        "doc_id": "908",
        "name": "Use of Uninitialized Resource",
        "source": "sparse"
      },
      "similarity": 345.63775881763104
    },
    {
      "metadata": {
        "doc_id": "131",
        "name": "Incorrect Calculation of Buffer Size",
        "source": "sparse"
      },
      "similarity": 342.621629635547
    },
    {
      "metadata": {
        "doc_id": "191",
        "name": "Integer Underflow (Wrap or Wraparound)",
        "source": "sparse"
      },
      "similarity": 339.17453974692313
    },
    {
      "metadata": {
        "doc_id": "667",
        "name": "Improper Locking",
        "source": "sparse"
      },
      "similarity": 336.1722767759926
    },
    {
      "metadata": {
        "doc_id": "862",
        "name": "Missing Authorization",
        "source": "sparse"
      },
      "similarity": 328.4488327885615
    },
    {
      "metadata": {
        "doc_id": "362",
        "name": "Concurrent Execution using Shared Resource with Improper Synchronization ('Race Condition')",
        "source": "sparse"
      },
      "similarity": 328.35809329238833
    },
    {
      "metadata": {
        "doc_id": "20",
        "name": "Improper Input Validation",
        "source": "sparse"
      },
      "similarity": 324.34714217559946
    },
    {
      "metadata": {
        "doc_id": "1284",
        "name": "Improper Validation of Specified Quantity in Input",
        "source": "sparse"
      },
      "similarity": 316.8315667875938
    },
    {
      "metadata": {
        "doc_id": "823",
        "name": "Use of Out-of-range Pointer Offset",
        "type": "Base",
        "original_content": "The product performs pointer arithmetic on a valid pointer, but it uses an offset that can point outside of the intended range of valid memory locations for the resulting pointer.",
        "keyphrase_source": "weakness:out of bounds write",
        "source": "dense",
        "mapping_notes": {
          "usage": "Allowed",
          "rationale": "This CWE entry is at the Base level of abstraction, which is a preferred level of abstraction for mapping to the root causes of vulnerabilities.",
          "comments": "Carefully read both the name and description to ensure that this mapping is an appropriate fit. Do not try to 'force' a mapping to a lower-level Base/Variant simply to comply with this preferred level of abstraction.",
          "reasons": [
            "Acceptable-Use"
          ]
        },
        "score_info": {
          "retrievers": [
            "dense",
            "graph"
          ],
          "retriever_count": 2,
          "normalized_scores": {
            "dense": 0.5743903171322198,
            "graph": 2.088735396657811
          }
        }
      },
      "similarity": 0.5743903171322198
    },
    {
      "doc_id": "1260",
      "text": "The product allows address regions to overlap, which can result in the bypassing of intended memory protection.",
      "score": 0.603786166701323,
      "metadata": {
        "doc_id": "1260",
        "name": "Improper Handling of Overlap Between Protected Memory Ranges",
        "type": "Base",
        "extended_description": "\n\nIsolated memory regions and access control (read/write) policies are used by hardware to protect privileged software. Software components are often allowed to change or remap memory region definitions in order to enable flexible and dynamically changeable memory management by system software.\n\n\nIf a software component running at lower privilege can program a memory address region to overlap with other memory regions used by software running at higher privilege, privilege escalation may be available to attackers. The memory protection unit (MPU) logic can incorrectly handle such an address overlap and allow the lower-privilege software to read or write into the protected memory region, resulting in privilege escalation attack. An address overlap weakness can also be used to launch a denial of service attack on the higher-privilege software memory regions.\n",
        "alternate_terms": [],
        "original_content": "The product allows address regions to overlap, which can result in the bypassing of intended memory protection.",
        "relationships": [
          {
            "source_id": "1260",
            "target_id": "119",
            "label": "CANPRECEDE",
            "properties": {
              "ordinal": "Primary",
              "view_id": "1000"
            }
          },
          {
            "source_id": "1260",
            "target_id": "284",
            "label": "CHILDOF",
            "properties": {
              "ordinal": "Primary",
              "view_id": "1000"
            }
          },
          {
            "source_id": "284",
            "target_id": "1260",
            "label": "PARENTOF",
            "properties": {
              "ordinal": "Primary",
              "view_id": "1000"
            }
          },
          {
            "source_id": "119",
            "target_id": "1260",
            "label": "CANFOLLOW",
            "properties": {
              "ordinal": "Primary",
              "view_id": "1000"
            }
          }
        ],
        "source": "graph",
        "sources": [
          "vector",
          "graph"
        ],
        "vector_score": 0.603786166701323,
        "graph_score": 3.8038000000000003,
        "score_components": {
          "relationship_chain": 0.8,
          "explicit_mention": 1.0,
          "abstraction_path": 0.9,
          "sequence_path": 0.7200000000000001
        },
        "abstraction_factor": 1.3,
        "graph_path_info": {
          "path_types": [
            "relationship_chain",
            "vulnerability_sequence_forward"
          ],
          "best_paths": {
            "relationship_chain": {
              "path": [
                [
                  "823",
                  "119",
                  "CHILDOF"
                ],
                [
                  "119",
                  "1260",
                  "CANFOLLOW"
                ]
              ],
              "score": 0.8,
              "type": "relationship_chain",
              "source": "823"
            },
            "vulnerability_sequence_forward": {
              "path": [
                [
                  "131",
                  "119",
                  "CANPRECEDE"
                ],
                [
                  "119",
                  "1260",
                  "CANFOLLOW"
                ]
              ],
              "score": 0.7200000000000001,
              "type": "vulnerability_sequence_forward",
              "source": "131"
            }
          }
        },
        "is_explicit": true,
        "abstraction_level": "base",
        "position": "after",
        "mapping_notes": {
          "usage": "Allowed",
          "rationale": "This CWE entry is at the Base level of abstraction, which is a preferred level of abstraction for mapping to the root causes of vulnerabilities.",
          "comments": "Carefully read both the name and description to ensure that this mapping is an appropriate fit. Do not try to 'force' a mapping to a lower-level Base/Variant simply to comply with this preferred level of abstraction.",
          "reasons": [
            "Acceptable-Use"
          ]
        },
        "score_info": {
          "retrievers": [
            "dense",
            "graph"
          ],
          "retriever_count": 2,
          "normalized_scores": {
            "dense": 0.5449549056929096,
            "graph": 2.5237944666805294
          }
        }
      },
      "similarity": 2.5237944666805294
    }
  ],
  "identified_cwes": {
    "analyzer": [
      "CWE-476",
      "CWE-125",
      "CWE-131",
      "CWE-787",
      "CWE-285",
      "CWE-191",
      "CWE-20",
      "CWE-609",
      "CWE-266",
      "CWE-129",
      "CWE-1260",
      "CWE-863",
      "CWE-823",
      "CWE-667",
      "CWE-703",
      "CWE-1284",
      "CWE-362",
      "CWE-250",
      "CWE-119",
      "CWE-367",
      "CWE-908",
      "CWE-754"
    ],
    "critic_additional": []
  },
  "keyphrase_cwe_mapping": {}
}