{
  "cve_id": "CVE-2024-37917",
  "description": "Pexip Infinity before 35.0 has **improper input validation** that allows remote attackers to trigger a denial of service (software abort) via a crafted signalling message.",
  "key_phrases": {
    "rootcause": "improper input validation",
    "weakness": "",
    "impact": "denial of service (software abort)",
    "vector": "crafted signalling message",
    "attacker": "remote attackers",
    "product": "Pexip Infinity",
    "version": "before 35.0",
    "component": ""
  },
  "reference_content": "## Analysis of CVE-2024-37917 based on provided content:\n\nThe content is directly relevant to CVE-2024-37917. It provides detailed information about the vulnerability.\n\n**Root cause of vulnerability:**\n\nInsufficient input validation in the signalling implementation(s).\n\n**Weaknesses/vulnerabilities present:**\n\nInsufficient input validation leading to a software abort.\n\n**Impact of exploitation:**\n\nDenial of service.\n\n**Attack vectors:**\n\nA crafted signalling message from a remote attacker.\n\n**Required attacker capabilities/position:**\n\nRemote, unauthenticated attacker.\n\n**Mitigation or fix:**\n\nUpgrade to Pexip Infinity v35.0 or later.\n\n**Additional details (more than official CVE description):**\n\n*   CVSS3.1 base score: 7.5 (AV:N/AC:L/PR:N/UI:N/S:U/C:N/I:N/A:H)\n*   Impacted versions: All before 35.0\n*   Addressed in version: 35.0\n*   The vulnerability was discussed and a resolution was provided in July 2024.",
  "similar_info": {
    "cwe_distribution": {},
    "cwe_consensus": "",
    "similarity_stats": {
      "thresholds": [],
      "total_samples_by_threshold": {},
      "top_cwes_by_threshold": {}
    }
  },
  "similarity_summary": {
    "consensus_cwe": "",
    "top_cwes": [],
    "confidence_levels": {},
    "total_samples": 0
  },
  "analysis": "# Summary\n| CWE ID | CWE Name | Confidence | CWE Abstraction Level | CWE Vulnerability Mapping Label | CWE-Vulnerability Mapping Notes |\n|---|---|---|---|---|---|\n| CWE-20 | Improper Input Validation | 1.0 | Class | Primary | Allowed |\n| CWE-770 | Allocation of Resources Without Limits or Throttling | 0.5 | Base | Secondary Candidate | Allowed |\n\n## Evidence and Confidence\n\n*   **Confidence Score:** 0.8\n*   **Evidence Strength:** HIGH\n\n## Relationship Analysis\nThe primary relationship considered was the parent-child relationship, specifically how CWE-20 serves as a high-level classification. The retriever results suggested more specific Base and Variant level CWEs, such as CWE-1284, CWE-789, CWE-1285, CWE-1325, and CWE-770. However, given the limited detail in the description, the broader CWE-20 seems more appropriate. There's also a chain relationship to consider, where improper input validation (CWE-20) can lead to resource exhaustion issues addressed by CWE-770.\n\n```mermaid\ngraph TD\n    cwe20[\"CWE-20: Improper Input Validation\"]\n    cwe770[\"CWE-770: Allocation of Resources Without Limits or Throttling\"]\n    cwe1284[\"CWE-1284: Improper Validation of Specified Quantity in Input\"]\n    cwe789[\"CWE-789: Memory Allocation with Excessive Size Value\"]\n    cwe1285[\"CWE-1285: Improper Validation of Specified Index, Position, or Offset in Input\"]\n    cwe1325[\"CWE-1325: Improperly Controlled Sequential Memory Allocation\"]\n\n    cwe1284 -->|CHILDOF| cwe20\n    cwe1285 -->|CHILDOF| cwe20\n    cwe1287 -->|CHILDOF| cwe20\n    cwe770 -->|CHILDOF| cwe400\n    cwe789 -->|CHILDOF| cwe770\n    cwe1325 -->|CHILDOF| cwe770\n    cwe20 -->|CANLEADTO| cwe770\n\n    classDef primary fill:#f96,stroke:#333,stroke-width:2px\n    classDef secondary fill:#69f,stroke:#333\n    classDef tertiary fill:#9e9,stroke:#333\n    class cwe20 primary\n    class cwe770 secondary\n    class cwe1284,cwe789,cwe1285,cwe1325 tertiary\n```\n\n## Vulnerability Chain\nThe vulnerability chain begins with **improper input validation** (CWE-20), which allows a remote attacker to send a crafted signalling message. This leads to a denial of service (software abort). While the description doesn't explicitly state the mechanism causing the denial of service, it could involve resource exhaustion or an unhandled exception. Therefore, CWE-20 is the root cause. A secondary effect could be CWE-770 (Allocation of Resources Without Limits or Throttling) contributing to the DoS.\n\n## Summary of Analysis\nThe primary assessment is heavily based on the **rootcause** identified as \"**improper input validation**\" in both the vulnerability description and the CVE reference summary.\n\nThe vulnerability description states: \"Pexip Infinity before 35.0 has **improper input validation** that allows remote attackers to trigger a denial of service (software abort) via a crafted signalling message.\"\n\nThe CVE Reference Links Content Summary states: \"**Root cause of vulnerability:** Insufficient input validation in the signalling implementation(s).\"\n\nGiven this direct evidence, CWE-20 (Improper Input Validation) is the most appropriate primary classification, despite its Class level of abstraction. The retriever results suggested more specific CWEs. However, lacking further details on *how* the input validation is flawed, opting for a more specific CWE would be speculative. The potential for resource exhaustion due to **improper input validation** makes CWE-770 a possible secondary classification.\n\nOther CWEs considered:\n*   CWE-1284, CWE-1285, CWE-1286, CWE-1287, CWE-789, CWE-1325: These are more specific input validation CWEs, but the description doesn't provide enough detail to confirm they apply.\n*   CWE-770: Allocation of Resources Without Limits or Throttling: This is a possible consequence of the **improper input validation**, but without more information, it's a secondary consideration.\n*   CWE-835: Loop with Unreachable Exit Condition ('Infinite Loop'): This is unlikely given the input-driven nature of the vulnerability.\n*   CWE-617: Reachable Assertion: There is no evidence to suggest that this vulnerability involves hitting a reachable assertion.\n*   CWE-770, CWE-1325: Given that a denial-of-service is possible, these resource exhaustion CWEs were considered.\n\nIn summary, the evidence points strongly to CWE-20 as the primary weakness, with potential secondary weaknesses related to resource management. The final selection prioritizes accuracy based on the available information and avoids over-speculation.\n\nRelevant CWE Information:\n\n# Enhanced Context (25 CWEs)\nThe following CWEs were identified as potentially relevant to this vulnerability:\n\n## CWE-1285: Improper Validation of Specified Index, Position, or Offset in Input\n**Abstraction Level**: Base\n**Similarity Score**: 0.71\n**Source**: dense\n\n**Description**:\nThe product receives input that is expected to specify an index, position, or offset into an indexable resource such as a buffer or file, but it does not validate or incorrectly validates that the specified index/position/offset has the required properties.\n\n**Mapping Guidance**:\n- Usage: Allowed\n- Rationale: This CWE entry is at the Base level of abstraction, which is a preferred level of abstraction for mapping to the root causes of vulnerabilities.\n\n\n\n## CWE-20: Improper Input Validation\n**Abstraction Level**: Class\n**Similarity Score**: 0.70\n**Source**: dense\n\n**Description**:\nThe product receives input or data, but it does\n        not validate or incorrectly validates that the input has the\n        properties that are required to process the data safely and\n        correctly.\n\n**Mapping Guidance**:\n- Usage: Discouraged\n- Rationale: CWE-20 is commonly misused in low-information vulnerability reports when lower-level CWEs could be used instead, or when more details about the vulnerability are available [REF-1287]. It is not useful for trend analysis. It is also a level-1 Class (i.e., a child of a Pillar).\n\n\n\n## CWE-346: Origin Validation Error\n**Abstraction Level**: Class\n**Similarity Score**: 0.70\n**Source**: dense\n\n**Description**:\nThe product does not properly verify that the source of data or communication is valid.\n\n**Mapping Guidance**:\n- Usage: Allowed-with-Review\n- Rationale: This CWE entry is a Class and might have Base-level children that would be more appropriate\n\n\n\n## CWE-755: Improper Handling of Exceptional Conditions\n**Abstraction Level**: Class\n**Similarity Score**: 0.70\n**Source**: dense\n\n**Description**:\nThe product does not handle or incorrectly handles an exceptional condition.\n\n**Mapping Guidance**:\n- Usage: Discouraged\n- Rationale: This CWE entry is a level-1 Class (i.e., a child of a Pillar). It might have lower-level children that would be more appropriate\n\n\n\n## CWE-345: Insufficient Verification of Data Authenticity\n**Abstraction Level**: Class\n**Similarity Score**: 0.69\n**Source**: dense\n\n**Description**:\nThe product does not sufficiently verify the origin or authenticity of data, in a way that causes it to accept invalid data.\n\n**Mapping Guidance**:\n- Usage: Discouraged\n- Rationale: This CWE entry is a level-1 Class (i.e., a child of a Pillar). It might have lower-level children that would be more appropriate\n\n\n\n## CWE-754: Improper Check for Unusual or Exceptional Conditions\n**Abstraction Level**: Class\n**Similarity Score**: 0.69\n**Source**: dense\n\n**Description**:\nThe product does not check or incorrectly checks for unusual or exceptional conditions that are not expected to occur frequently during day to day operation of the product.\n\n**Mapping Guidance**:\n- Usage: Allowed-with-Review\n- Rationale: This CWE entry is a Class and might have Base-level children that would be more appropriate\n\n\n\n## CWE-807: Reliance on Untrusted Inputs in a Security Decision\n**Abstraction Level**: Base\n**Similarity Score**: 0.68\n**Source**: dense\n\n**Description**:\nThe product uses a protection mechanism that relies on the existence or values of an input, but the input can be modified by an untrusted actor in a way that bypasses the protection mechanism.\n\n**Mapping Guidance**:\n- Usage: Allowed\n- Rationale: This CWE entry is at the Base level of abstraction, which is a preferred level",
  "analysis_with_relationships": "# Summary\n| CWE ID | CWE Name | Confidence | CWE Abstraction Level | CWE Vulnerability Mapping Label | CWE-Vulnerability Mapping Notes |\n|---|---|---|---|---|---|\n| CWE-20 | Improper Input Validation | 1.0 | Class | Primary | Allowed |\n| CWE-770 | Allocation of Resources Without Limits or Throttling | 0.5 | Base | Secondary Candidate | Allowed |\n\n## Evidence and Confidence\n\n*   **Confidence Score:** 0.8\n*   **Evidence Strength:** HIGH\n\n## Relationship Analysis\nThe primary relationship considered was the parent-child relationship, specifically how CWE-20 serves as a high-level classification. The retriever results suggested more specific Base and Variant level CWEs, such as CWE-1284, CWE-789, CWE-1285, CWE-1325, and CWE-770. However, given the limited detail in the description, the broader CWE-20 seems more appropriate. There's also a chain relationship to consider, where improper input validation (CWE-20) can lead to resource exhaustion issues addressed by CWE-770.\n\n```mermaid\ngraph TD\n    cwe20[\"CWE-20: Improper Input Validation\"]\n    cwe770[\"CWE-770: Allocation of Resources Without Limits or Throttling\"]\n    cwe1284[\"CWE-1284: Improper Validation of Specified Quantity in Input\"]\n    cwe789[\"CWE-789: Memory Allocation with Excessive Size Value\"]\n    cwe1285[\"CWE-1285: Improper Validation of Specified Index, Position, or Offset in Input\"]\n    cwe1325[\"CWE-1325: Improperly Controlled Sequential Memory Allocation\"]\n\n    cwe1284 -->|CHILDOF| cwe20\n    cwe1285 -->|CHILDOF| cwe20\n    cwe1287 -->|CHILDOF| cwe20\n    cwe770 -->|CHILDOF| cwe400\n    cwe789 -->|CHILDOF| cwe770\n    cwe1325 -->|CHILDOF| cwe770\n    cwe20 -->|CANLEADTO| cwe770\n\n    classDef primary fill:#f96,stroke:#333,stroke-width:2px\n    classDef secondary fill:#69f,stroke:#333\n    classDef tertiary fill:#9e9,stroke:#333\n    class cwe20 primary\n    class cwe770 secondary\n    class cwe1284,cwe789,cwe1285,cwe1325 tertiary\n```\n\n## Vulnerability Chain\nThe vulnerability chain begins with **improper input validation** (CWE-20), which allows a remote attacker to send a crafted signalling message. This leads to a denial of service (software abort). While the description doesn't explicitly state the mechanism causing the denial of service, it could involve resource exhaustion or an unhandled exception. Therefore, CWE-20 is the root cause. A secondary effect could be CWE-770 (Allocation of Resources Without Limits or Throttling) contributing to the DoS.\n\n## Summary of Analysis\nThe primary assessment is heavily based on the **rootcause** identified as \"**improper input validation**\" in both the vulnerability description and the CVE reference summary.\n\nThe vulnerability description states: \"Pexip Infinity before 35.0 has **improper input validation** that allows remote attackers to trigger a denial of service (software abort) via a crafted signalling message.\"\n\nThe CVE Reference Links Content Summary states: \"**Root cause of vulnerability:** Insufficient input validation in the signalling implementation(s).\"\n\nGiven this direct evidence, CWE-20 (Improper Input Validation) is the most appropriate primary classification, despite its Class level of abstraction. The retriever results suggested more specific CWEs. However, lacking further details on *how* the input validation is flawed, opting for a more specific CWE would be speculative. The potential for resource exhaustion due to **improper input validation** makes CWE-770 a possible secondary classification.\n\nOther CWEs considered:\n*   CWE-1284, CWE-1285, CWE-1286, CWE-1287, CWE-789, CWE-1325: These are more specific input validation CWEs, but the description doesn't provide enough detail to confirm they apply.\n*   CWE-770: Allocation of Resources Without Limits or Throttling: This is a possible consequence of the **improper input validation**, but without more information, it's a secondary consideration.\n*   CWE-835: Loop with Unreachable Exit Condition ('Infinite Loop'): This is unlikely given the input-driven nature of the vulnerability.\n*   CWE-617: Reachable Assertion: There is no evidence to suggest that this vulnerability involves hitting a reachable assertion.\n*   CWE-770, CWE-1325: Given that a denial-of-service is possible, these resource exhaustion CWEs were considered.\n\nIn summary, the evidence points strongly to CWE-20 as the primary weakness, with potential secondary weaknesses related to resource management. The final selection prioritizes accuracy based on the available information and avoids over-speculation.\n\nRelevant CWE Information:\n\n# Enhanced Context (25 CWEs)\nThe following CWEs were identified as potentially relevant to this vulnerability:\n\n## CWE-1285: Improper Validation of Specified Index, Position, or Offset in Input\n**Abstraction Level**: Base\n**Similarity Score**: 0.71\n**Source**: dense\n\n**Description**:\nThe product receives input that is expected to specify an index, position, or offset into an indexable resource such as a buffer or file, but it does not validate or incorrectly validates that the specified index/position/offset has the required properties.\n\n**Mapping Guidance**:\n- Usage: Allowed\n- Rationale: This CWE entry is at the Base level of abstraction, which is a preferred level of abstraction for mapping to the root causes of vulnerabilities.\n\n\n\n## CWE-20: Improper Input Validation\n**Abstraction Level**: Class\n**Similarity Score**: 0.70\n**Source**: dense\n\n**Description**:\nThe product receives input or data, but it does\n        not validate or incorrectly validates that the input has the\n        properties that are required to process the data safely and\n        correctly.\n\n**Mapping Guidance**:\n- Usage: Discouraged\n- Rationale: CWE-20 is commonly misused in low-information vulnerability reports when lower-level CWEs could be used instead, or when more details about the vulnerability are available [REF-1287]. It is not useful for trend analysis. It is also a level-1 Class (i.e., a child of a Pillar).\n\n\n\n## CWE-346: Origin Validation Error\n**Abstraction Level**: Class\n**Similarity Score**: 0.70\n**Source**: dense\n\n**Description**:\nThe product does not properly verify that the source of data or communication is valid.\n\n**Mapping Guidance**:\n- Usage: Allowed-with-Review\n- Rationale: This CWE entry is a Class and might have Base-level children that would be more appropriate\n\n\n\n## CWE-755: Improper Handling of Exceptional Conditions\n**Abstraction Level**: Class\n**Similarity Score**: 0.70\n**Source**: dense\n\n**Description**:\nThe product does not handle or incorrectly handles an exceptional condition.\n\n**Mapping Guidance**:\n- Usage: Discouraged\n- Rationale: This CWE entry is a level-1 Class (i.e., a child of a Pillar). It might have lower-level children that would be more appropriate\n\n\n\n## CWE-345: Insufficient Verification of Data Authenticity\n**Abstraction Level**: Class\n**Similarity Score**: 0.69\n**Source**: dense\n\n**Description**:\nThe product does not sufficiently verify the origin or authenticity of data, in a way that causes it to accept invalid data.\n\n**Mapping Guidance**:\n- Usage: Discouraged\n- Rationale: This CWE entry is a level-1 Class (i.e., a child of a Pillar). It might have lower-level children that would be more appropriate\n\n\n\n## CWE-754: Improper Check for Unusual or Exceptional Conditions\n**Abstraction Level**: Class\n**Similarity Score**: 0.69\n**Source**: dense\n\n**Description**:\nThe product does not check or incorrectly checks for unusual or exceptional conditions that are not expected to occur frequently during day to day operation of the product.\n\n**Mapping Guidance**:\n- Usage: Allowed-with-Review\n- Rationale: This CWE entry is a Class and might have Base-level children that would be more appropriate\n\n\n\n## CWE-807: Reliance on Untrusted Inputs in a Security Decision\n**Abstraction Level**: Base\n**Similarity Score**: 0.68\n**Source**: dense\n\n**Description**:\nThe product uses a protection mechanism that relies on the existence or values of an input, but the input can be modified by an untrusted actor in a way that bypasses the protection mechanism.\n\n**Mapping Guidance**:\n- Usage: Allowed\n- Rationale: This CWE entry is at the Base level of abstraction, which is a preferred level\n\n\n## CWE Relationship Analysis\n\nCurrent CWEs represent these abstraction levels: .\n\n\n### Vulnerability Chain Analysis\n\n**Chain starting from CWE-1284:**\n- 1284 (Improper Validation of Specified Quantity in Input) - ROOT\n\n\n**Chain starting from CWE-807:**\n- 807 (Reliance on Untrusted Inputs in a Security Decision) - ROOT\n\n\n\n### CWE Relationship Diagram\n\n```mermaid\ngraph TD\n    classDef primary fill:#f96,stroke:#333,stroke-width:2px\n    classDef secondary fill:#69f,stroke:#333\n    classDef tertiary fill:#9e9,stroke:#333\n```",
  "criticism": "",
  "resolution": "",
  "relevant_cwes": [
    {
      "metadata": {
        "doc_id": "1284",
        "name": "Improper Validation of Specified Quantity in Input",
        "source": "sparse"
      },
      "similarity": 150.19228028863193
    },
    {
      "metadata": {
        "doc_id": "20",
        "name": "Improper Input Validation",
        "source": "sparse"
      },
      "similarity": 147.876548915978
    },
    {
      "metadata": {
        "doc_id": "617",
        "name": "Reachable Assertion",
        "source": "sparse"
      },
      "similarity": 134.89552029387687
    },
    {
      "metadata": {
        "doc_id": "1286",
        "name": "Improper Validation of Syntactic Correctness of Input",
        "source": "sparse"
      },
      "similarity": 134.52734811837158
    },
    {
      "metadata": {
        "doc_id": "789",
        "name": "Memory Allocation with Excessive Size Value",
        "source": "sparse"
      },
      "similarity": 134.11136534701532
    },
    {
      "metadata": {
        "doc_id": "1285",
        "name": "Improper Validation of Specified Index, Position, or Offset in Input",
        "source": "sparse"
      },
      "similarity": 131.59202572757334
    },
    {
      "metadata": {
        "doc_id": "835",
        "name": "Loop with Unreachable Exit Condition ('Infinite Loop')",
        "source": "sparse"
      },
      "similarity": 128.83657667725151
    },
    {
      "metadata": {
        "doc_id": "1287",
        "name": "Improper Validation of Specified Type of Input",
        "source": "sparse"
      },
      "similarity": 128.4568657456803
    },
    {
      "metadata": {
        "doc_id": "770",
        "name": "Allocation of Resources Without Limits or Throttling",
        "type": "Base",
        "original_content": "The product allocates a reusable resource or group of resources on behalf of an actor without imposing any restrictions on the size or number of resources that can be allocated, in violation of the intended security policy for that actor.",
        "keyphrase_source": "rootcause:improper input validation",
        "source": "dense",
        "mapping_notes": {
          "usage": "Allowed",
          "rationale": "This CWE entry is at the Base level of abstraction, which is a preferred level of abstraction for mapping to the root causes of vulnerabilities.",
          "comments": "Carefully read both the name and description to ensure that this mapping is an appropriate fit. Do not try to 'force' a mapping to a lower-level Base/Variant simply to comply with this preferred level of abstraction.",
          "reasons": [
            "Acceptable-Use"
          ]
        },
        "score_info": {
          "retrievers": [
            "dense",
            "graph"
          ],
          "retriever_count": 2,
          "normalized_scores": {
            "dense": 0.5381194122427253,
            "graph": 2.8313822121384282
          }
        }
      },
      "similarity": 0.5381194122427253
    },
    {
      "doc_id": "1325",
      "text": "CWE-1325: Improperly Controlled Sequential Memory Allocation",
      "score": 2.9250000000000003,
      "metadata": {
        "doc_id": "1325",
        "name": "Improperly Controlled Sequential Memory Allocation",
        "type": "base",
        "original_content": "CWE-1325: Improperly Controlled Sequential Memory Allocation",
        "relationships": [
          {
            "source_id": "1325",
            "target_id": "476",
            "label": "CANPRECEDE",
            "properties": {
              "view_id": "1000"
            }
          },
          {
            "source_id": "1325",
            "target_id": "789",
            "label": "PEEROF",
            "properties": {
              "ordinal": "Primary",
              "view_id": "1000"
            }
          },
          {
            "source_id": "1325",
            "target_id": "770",
            "label": "CHILDOF",
            "properties": {
              "ordinal": "Primary",
              "view_id": "1000"
            }
          },
          {
            "source_id": "770",
            "target_id": "1325",
            "label": "PARENTOF",
            "properties": {
              "ordinal": "Primary",
              "view_id": "1000"
            }
          },
          {
            "source_id": "476",
            "target_id": "1325",
            "label": "CANFOLLOW",
            "properties": {
              "view_id": "1000"
            }
          }
        ],
        "score_components": {
          "relationship_chain": 0.7,
          "abstraction_path": 0.7200000000000001,
          "sequence_path": 0.7200000000000001,
          "peer_group": 0.9
        },
        "abstraction_factor": 1.3,
        "graph_path_info": {
          "path_types": [
            "relationship_chain",
            "abstraction_path_down",
            "vulnerability_sequence_forward",
            "peer_relationship"
          ],
          "best_paths": {
            "relationship_chain": {
              "path": [
                [
                  "1325",
                  "789",
                  "PEEROF"
                ]
              ],
              "score": 0.7,
              "type": "relationship_chain",
              "source": "789"
            },
            "abstraction_path_down": {
              "path": [
                [
                  "770",
                  "1325",
                  "PARENTOF"
                ]
              ],
              "score": 0.7200000000000001,
              "type": "abstraction_path_down",
              "source": "770"
            },
            "vulnerability_sequence_forward": {
              "path": [
                [
                  "789",
                  "476",
                  "CANPRECEDE"
                ],
                [
                  "476",
                  "1325",
                  "CANFOLLOW"
                ]
              ],
              "score": 0.7200000000000001,
              "type": "vulnerability_sequence_forward",
              "source": "789"
            },
            "peer_relationship": {
              "path": [
                [
                  "1325",
                  "789",
                  "PEEROF"
                ]
              ],
              "score": 0.9,
              "type": "peer_relationship",
              "source": "789"
            }
          }
        },
        "abstraction_level": "base",
        "position": "after",
        "sources": [
          "graph"
        ],
        "source": "graph",
        "mapping_notes": {
          "usage": "Allowed",
          "rationale": "This CWE entry is at the Base level of abstraction, which is a preferred level of abstraction for mapping to the root causes of vulnerabilities.",
          "comments": "Carefully read both the name and description to ensure that this mapping is an appropriate fit. Do not try to 'force' a mapping to a lower-level Base/Variant simply to comply with this preferred level of abstraction.",
          "reasons": [
            "Acceptable-Use"
          ]
        },
        "score_info": {
          "retrievers": [
            "graph"
          ],
          "retriever_count": 1,
          "normalized_scores": {
            "graph": 2.9250000000000003
          }
        }
      },
      "similarity": 2.9250000000000003
    }
  ],
  "identified_cwes": {
    "analyzer": [
      "CWE-1284",
      "CWE-807",
      "CWE-345",
      "CWE-770",
      "CWE-346",
      "CWE-1286",
      "CWE-1285",
      "CWE-1287",
      "CWE-835",
      "CWE-755",
      "CWE-20",
      "CWE-617",
      "CWE-789",
      "CWE-1325",
      "CWE-754"
    ],
    "critic_additional": []
  },
  "keyphrase_cwe_mapping": {}
}