{
  "vulnerability_info": "VulnerabilityInfo(cve_id='CVE-2024-42339', description='CyberArk - **CWE-200 Exposure of Sensitive Information to an Unauthorized Actor**', key_phrases={'rootcause': ['The software does not properly restrict access to sensitive information', 'potentially allowing unauthorized users to view it.'], 'weakness': 'CWE-200 Exposure of Sensitive Information to an Unauthorized Actor', 'impact': ['Exposure of Sensitive Information to an Unauthorized Actor', 'Unauthorized disclosure of sensitive information.'], 'vector': 'Network or Local Access', 'attacker': 'An unauthorized user or malicious actor.', 'product': 'CyberArk', 'version': 'Not specified', 'component': 'Not specified'}, reference_content=None, similar_info={'cwe_distribution': {95: {'cwe_counts': defaultdict(<class 'int'>, {'CWE-200': 2}), 'total_samples': 3, 'distribution': [{'cwes': ['CWE-200'], 'frequency': 2, 'proportion': 0.667}, {'cwes': [], 'frequency': 1, 'proportion': 0.333}]}, 90: {'cwe_counts': defaultdict(<class 'int'>, {'CWE-200': 2}), 'total_samples': 3, 'distribution': [{'cwes': ['CWE-200'], 'frequency': 2, 'proportion': 0.667}, {'cwes': [], 'frequency': 1, 'proportion': 0.333}]}, 85: {'cwe_counts': defaultdict(<class 'int'>, {'CWE-200': 2}), 'total_samples': 3, 'distribution': [{'cwes': ['CWE-200'], 'frequency': 2, 'proportion': 0.667}, {'cwes': [], 'frequency': 1, 'proportion': 0.333}]}, 80: {'cwe_counts': defaultdict(<class 'int'>, {'CWE-200': 2}), 'total_samples': 3, 'distribution': [{'cwes': ['CWE-200'], 'frequency': 2, 'proportion': 0.667}, {'cwes': [], 'frequency': 1, 'proportion': 0.333}]}, 75: {'cwe_counts': defaultdict(<class 'int'>, {'CWE-200': 2}), 'total_samples': 3, 'distribution': [{'cwes': ['CWE-200'], 'frequency': 2, 'proportion': 0.667}, {'cwes': [], 'frequency': 1, 'proportion': 0.333}]}, 70: {'cwe_counts': defaultdict(<class 'int'>, {'CWE-200': 2}), 'total_samples': 3, 'distribution': [{'cwes': ['CWE-200'], 'frequency': 2, 'proportion': 0.667}, {'cwes': [], 'frequency': 1, 'proportion': 0.333}]}}, 'cwe_consensus': 'CWE-200', 'similarity_stats': {'thresholds': [95, 90, 85, 80, 75, 70], 'total_samples_by_threshold': {95: 3, 90: 3, 85: 3, 80: 3, 75: 3, 70: 3}, 'top_cwes_by_threshold': {95: [('CWE-200', 2)], 90: [('CWE-200', 2)], 85: [('CWE-200', 2)], 80: [('CWE-200', 2)], 75: [('CWE-200', 2)], 70: [('CWE-200', 2)]}}, 'raw_matches': [{'similarity': 95, 'cwes': ['200'], 'total': 3, 'frequency': 2, 'proportion': 0.667}, {'similarity': 95, 'cwes': [], 'total': 3, 'frequency': 1, 'proportion': 0.333}, {'similarity': 90, 'cwes': ['200'], 'total': 3, 'frequency': 2, 'proportion': 0.667}, {'similarity': 90, 'cwes': [], 'total': 3, 'frequency': 1, 'proportion': 0.333}, {'similarity': 85, 'cwes': ['200'], 'total': 3, 'frequency': 2, 'proportion': 0.667}, {'similarity': 85, 'cwes': [], 'total': 3, 'frequency': 1, 'proportion': 0.333}, {'similarity': 80, 'cwes': ['200'], 'total': 3, 'frequency': 2, 'proportion': 0.667}, {'similarity': 80, 'cwes': [], 'total': 3, 'frequency': 1, 'proportion': 0.333}, {'similarity': 75, 'cwes': ['200'], 'total': 3, 'frequency': 2, 'proportion': 0.667}, {'similarity': 75, 'cwes': [], 'total': 3, 'frequency': 1, 'proportion': 0.333}, {'similarity': 70, 'cwes': ['200'], 'total': 3, 'frequency': 2, 'proportion': 0.667}, {'similarity': 70, 'cwes': [], 'total': 3, 'frequency': 1, 'proportion': 0.333}]}, similarity_summary=SimilarityInsight(consensus_cwe='CWE-200', top_cwes=[('CWE-200', 12)], confidence_levels={'high': [], 'medium': [], 'low': []}, total_samples=18), analysis='', analysis_with_relationships='', criticism='', resolution='', relevant_cwes=[{'metadata': {'doc_id': '200', 'name': 'Exposure of Sensitive Information to an Unauthorized Actor', 'source': 'sparse', 'original_content': 'The product exposes sensitive information to an actor that is not explicitly authorized to have access to that information.', 'keyphrase_sources': [{'id': 'rootcause:The software does not properly restrict access to sensitive information', 'keyphrase': 'The software does not properly restrict access to sensitive information', 'type': 'rootcause'}, {'id': 'rootcause:potentially allowing unauthorized users to view it.', 'keyphrase': 'potentially allowing unauthorized users to view it.', 'type': 'rootcause'}, {'id': 'weakness:CWE-200 Exposure of Sensitive Information to an Unauthorized Actor', 'keyphrase': 'CWE-200 Exposure of Sensitive Information to an Unauthorized Actor', 'type': 'weakness'}, {'id': 'impact:Exposure of Sensitive Information to an Unauthorized Actor', 'keyphrase': 'Exposure of Sensitive Information to an Unauthorized Actor', 'type': 'impact'}, {'id': 'impact:Unauthorized disclosure of sensitive information.', 'keyphrase': 'Unauthorized disclosure of sensitive information.', 'type': 'impact'}, {'id': 'vector:Network or Local Access', 'keyphrase': 'Network or Local Access', 'type': 'vector'}, {'id': 'attacker:An unauthorized user or malicious actor.', 'keyphrase': 'An unauthorized user or malicious actor.', 'type': 'attacker'}, {'id': 'product:CyberArk', 'keyphrase': 'CyberArk', 'type': 'product'}, {'id': 'version:Not specified', 'keyphrase': 'Not specified', 'type': 'version'}, {'id': 'component:Not specified', 'keyphrase': 'Not specified', 'type': 'component'}]}, 'similarity': np.float64(217.69855044663183)}, {'metadata': {'doc_id': '497', 'name': 'Exposure of Sensitive System Information to an Unauthorized Control Sphere', 'source': 'sparse', 'original_content': 'The product does not properly prevent sensitive system-level information from being accessed by unauthorized actors who do not have the same level of access to the underlying system as the product does.', 'keyphrase_sources': [{'id': 'rootcause:The software does not properly restrict access to sensitive information', 'keyphrase': 'The software does not properly restrict access to sensitive information', 'type': 'rootcause'}, {'id': 'rootcause:potentially allowing unauthorized users to view it.', 'keyphrase': 'potentially allowing unauthorized users to view it.', 'type': 'rootcause'}, {'id': 'weakness:CWE-200 Exposure of Sensitive Information to an Unauthorized Actor', 'keyphrase': 'CWE-200 Exposure of Sensitive Information to an Unauthorized Actor', 'type': 'weakness'}, {'id': 'impact:Exposure of Sensitive Information to an Unauthorized Actor', 'keyphrase': 'Exposure of Sensitive Information to an Unauthorized Actor', 'type': 'impact'}, {'id': 'impact:Unauthorized disclosure of sensitive information.', 'keyphrase': 'Unauthorized disclosure of sensitive information.', 'type': 'impact'}, {'id': 'vector:Network or Local Access', 'keyphrase': 'Network or Local Access', 'type': 'vector'}, {'id': 'attacker:An unauthorized user or malicious actor.', 'keyphrase': 'An unauthorized user or malicious actor.', 'type': 'attacker'}, {'id': 'product:CyberArk', 'keyphrase': 'CyberArk', 'type': 'product'}, {'id': 'version:Not specified', 'keyphrase': 'Not specified', 'type': 'version'}, {'id': 'component:Not specified', 'keyphrase': 'Not specified', 'type': 'component'}]}, 'similarity': np.float64(212.77791722666683)}, {'metadata': {'doc_id': '209', 'name': 'Generation of Error Message Containing Sensitive Information', 'source': 'sparse', 'original_content': 'The product generates an error message that includes sensitive information about its environment, users, or associated data.', 'keyphrase_sources': [{'id': 'weakness:CWE-200 Exposure of Sensitive Information to an Unauthorized Actor', 'keyphrase': 'CWE-200 Exposure of Sensitive Information to an Unauthorized Actor', 'type': 'weakness'}, {'id': 'impact:Unauthorized disclosure of sensitive information.', 'keyphrase': 'Unauthorized disclosure of sensitive information.', 'type': 'impact'}]}, 'similarity': np.float64(211.37037056281508)}, {'metadata': {'doc_id': '524', 'name': 'Use of Cache Containing Sensitive Information', 'source': 'sparse', 'original_content': 'The code uses a cache that contains sensitive information, but the cache can be read by an actor outside of the intended control sphere.', 'keyphrase_sources': [{'id': 'weakness:CWE-200 Exposure of Sensitive Information to an Unauthorized Actor', 'keyphrase': 'CWE-200 Exposure of Sensitive Information to an Unauthorized Actor', 'type': 'weakness'}, {'id': 'impact:Exposure of Sensitive Information to an Unauthorized Actor', 'keyphrase': 'Exposure of Sensitive Information to an Unauthorized Actor', 'type': 'impact'}]}, 'similarity': np.float64(208.29963515510465)}, {'metadata': {'doc_id': '359', 'name': 'Exposure of Private Personal Information to an Unauthorized Actor', 'source': 'sparse', 'original_content': \"The product does not properly prevent a person's private, personal information from being accessed by actors who either (1) are not explicitly authorized to access the information or (2) do not have the implicit consent of the person about whom the information is collected.\", 'keyphrase_sources': [{'id': 'rootcause:The software does not properly restrict access to sensitive information', 'keyphrase': 'The software does not properly restrict access to sensitive information', 'type': 'rootcause'}, {'id': 'rootcause:potentially allowing unauthorized users to view it.', 'keyphrase': 'potentially allowing unauthorized users to view it.', 'type': 'rootcause'}, {'id': 'weakness:CWE-200 Exposure of Sensitive Information to an Unauthorized Actor', 'keyphrase': 'CWE-200 Exposure of Sensitive Information to an Unauthorized Actor', 'type': 'weakness'}, {'id': 'impact:Exposure of Sensitive Information to an Unauthorized Actor', 'keyphrase': 'Exposure of Sensitive Information to an Unauthorized Actor', 'type': 'impact'}, {'id': 'impact:Unauthorized disclosure of sensitive information.', 'keyphrase': 'Unauthorized disclosure of sensitive information.', 'type': 'impact'}, {'id': 'attacker:An unauthorized user or malicious actor.', 'keyphrase': 'An unauthorized user or malicious actor.', 'type': 'attacker'}, {'id': 'product:CyberArk', 'keyphrase': 'CyberArk', 'type': 'product'}, {'id': 'version:Not specified', 'keyphrase': 'Not specified', 'type': 'version'}, {'id': 'component:Not specified', 'keyphrase': 'Not specified', 'type': 'component'}]}, 'similarity': np.float64(201.51513421846408)}, {'metadata': {'doc_id': '612', 'name': 'Improper Authorization of Index Containing Sensitive Information', 'source': 'sparse', 'original_content': 'The product creates a search index of private or sensitive documents, but it does not properly limit index access to actors who are authorized to see the original information.', 'keyphrase_sources': [{'id': 'rootcause:The software does not properly restrict access to sensitive information', 'keyphrase': 'The software does not properly restrict access to sensitive information', 'type': 'rootcause'}]}, 'similarity': np.float64(197.88867415802792)}, {'metadata': {'doc_id': '942', 'name': 'Permissive Cross-domain Policy with Untrusted Domains', 'source': 'sparse', 'original_content': 'The product uses a cross-domain policy file that includes domains that should not be trusted.', 'keyphrase_sources': [{'id': 'rootcause:The software does not properly restrict access to sensitive information', 'keyphrase': 'The software does not properly restrict access to sensitive information', 'type': 'rootcause'}]}, 'similarity': np.float64(194.91716736471597)}, {'metadata': {'doc_id': '214', 'name': 'Invocation of Process Using Visible Sensitive Information', 'source': 'sparse', 'original_content': 'A process is invoked with sensitive command-line arguments, environment variables, or other elements that can be seen by other processes on the operating system.', 'keyphrase_sources': [{'id': 'rootcause:potentially allowing unauthorized users to view it.', 'keyphrase': 'potentially allowing unauthorized users to view it.', 'type': 'rootcause'}]}, 'similarity': np.float64(174.31829719553724)}, {'metadata': {'doc_id': '532', 'name': 'Insertion of Sensitive Information into Log File', 'source': 'sparse', 'original_content': 'The product writes sensitive information to a log file.', 'keyphrase_sources': [{'id': 'rootcause:potentially allowing unauthorized users to view it.', 'keyphrase': 'potentially allowing unauthorized users to view it.', 'type': 'rootcause'}, {'id': 'vector:Network or Local Access', 'keyphrase': 'Network or Local Access', 'type': 'vector'}]}, 'similarity': np.float64(156.53950126924084)}, {'metadata': {'doc_id': '15', 'name': 'External Control of System or Configuration Setting', 'source': 'sparse', 'original_content': 'One or more system settings or configuration elements can be externally controlled by a user.', 'keyphrase_sources': [{'id': 'impact:Exposure of Sensitive Information to an Unauthorized Actor', 'keyphrase': 'Exposure of Sensitive Information to an Unauthorized Actor', 'type': 'impact'}, {'id': 'attacker:An unauthorized user or malicious actor.', 'keyphrase': 'An unauthorized user or malicious actor.', 'type': 'attacker'}]}, 'similarity': np.float64(66.6835177997094)}, {'metadata': {'doc_id': '203', 'name': 'Observable Discrepancy', 'source': 'sparse', 'original_content': 'The product behaves differently or sends different responses under different circumstances in a way that is observable to an unauthorized actor, which exposes security-relevant information about the state of the product, such as whether a particular operation was successful or not.', 'keyphrase_sources': [{'id': 'attacker:An unauthorized user or malicious actor.', 'keyphrase': 'An unauthorized user or malicious actor.', 'type': 'attacker'}, {'id': 'version:Not specified', 'keyphrase': 'Not specified', 'type': 'version'}, {'id': 'component:Not specified', 'keyphrase': 'Not specified', 'type': 'component'}]}, 'similarity': np.float64(50.76395948227883)}, {'metadata': {'doc_id': '598', 'name': 'Use of GET Request Method With Sensitive Query Strings', 'source': 'sparse', 'original_content': 'The web application uses the HTTP GET method to process a request and includes sensitive information in the query string of that request.', 'keyphrase_sources': [{'id': 'impact:Unauthorized disclosure of sensitive information.', 'keyphrase': 'Unauthorized disclosure of sensitive information.', 'type': 'impact'}]}, 'similarity': np.float64(49.235447032081595)}, {'metadata': {'doc_id': '331', 'name': 'Insufficient Entropy', 'source': 'sparse', 'original_content': 'The product uses an algorithm or scheme that produces insufficient entropy, leaving patterns or clusters of values that are more likely to occur than others.', 'keyphrase_sources': [{'id': 'vector:Network or Local Access', 'keyphrase': 'Network or Local Access', 'type': 'vector'}, {'id': 'product:CyberArk', 'keyphrase': 'CyberArk', 'type': 'product'}]}, 'similarity': np.float64(42.192658301704455)}, {'metadata': {'doc_id': '441', 'name': \"Unintended Proxy or Intermediary ('Confused Deputy')\", 'source': 'sparse', 'original_content': \"The product receives a request, message, or directive from an upstream component, but the product does not sufficiently preserve the original source of the request before forwarding the request to an external actor that is outside of the product's control sphere. This causes the product to appear to be the source of the request, leading it to act as a proxy or other intermediary between the upstream component and the external actor.\", 'keyphrase_sources': [{'id': 'vector:Network or Local Access', 'keyphrase': 'Network or Local Access', 'type': 'vector'}]}, 'similarity': np.float64(40.655699547286105)}, {'metadata': {'doc_id': '941', 'name': 'Incorrectly Specified Destination in a Communication Channel', 'source': 'sparse', 'original_content': 'The product creates a communication channel to initiate an outgoing request to an actor, but it does not correctly specify the intended destination for that actor.', 'keyphrase_sources': [{'id': 'version:Not specified', 'keyphrase': 'Not specified', 'type': 'version'}, {'id': 'component:Not specified', 'keyphrase': 'Not specified', 'type': 'component'}]}, 'similarity': np.float64(33.90884440651428)}, {'metadata': {'doc_id': '204', 'name': 'Observable Response Discrepancy', 'source': 'sparse', 'original_content': 'The product provides different responses to incoming requests in a way that reveals internal state information to an unauthorized actor outside of the intended control sphere.', 'keyphrase_sources': [{'id': 'product:CyberArk', 'keyphrase': 'CyberArk', 'type': 'product'}]}, 'similarity': np.float64(31.73919536860368)}], identified_cwes={'analyzer': [], 'critic_additional': []})",
  "retrieval_results": {
    "has_multiple_keyphrases": true,
    "keyphrase_cwe_sets": {
      "rootcause:The software does not properly restrict access to sensitive information": {
        "keyphrase": "The software does not properly restrict access to sensitive information",
        "type": "rootcause",
        "cwes": [
          {
            "metadata": {
              "doc_id": "200",
              "name": "Exposure of Sensitive Information to an Unauthorized Actor",
              "source": "sparse",
              "original_content": "The product exposes sensitive information to an actor that is not explicitly authorized to have access to that information.",
              "keyphrase_sources": [
                {
                  "id": "rootcause:The software does not properly restrict access to sensitive information",
                  "keyphrase": "The software does not properly restrict access to sensitive information",
                  "type": "rootcause"
                },
                {
                  "id": "rootcause:potentially allowing unauthorized users to view it.",
                  "keyphrase": "potentially allowing unauthorized users to view it.",
                  "type": "rootcause"
                },
                {
                  "id": "weakness:CWE-200 Exposure of Sensitive Information to an Unauthorized Actor",
                  "keyphrase": "CWE-200 Exposure of Sensitive Information to an Unauthorized Actor",
                  "type": "weakness"
                },
                {
                  "id": "impact:Exposure of Sensitive Information to an Unauthorized Actor",
                  "keyphrase": "Exposure of Sensitive Information to an Unauthorized Actor",
                  "type": "impact"
                },
                {
                  "id": "impact:Unauthorized disclosure of sensitive information.",
                  "keyphrase": "Unauthorized disclosure of sensitive information.",
                  "type": "impact"
                },
                {
                  "id": "vector:Network or Local Access",
                  "keyphrase": "Network or Local Access",
                  "type": "vector"
                },
                {
                  "id": "attacker:An unauthorized user or malicious actor.",
                  "keyphrase": "An unauthorized user or malicious actor.",
                  "type": "attacker"
                },
                {
                  "id": "product:CyberArk",
                  "keyphrase": "CyberArk",
                  "type": "product"
                },
                {
                  "id": "version:Not specified",
                  "keyphrase": "Not specified",
                  "type": "version"
                },
                {
                  "id": "component:Not specified",
                  "keyphrase": "Not specified",
                  "type": "component"
                }
              ]
            },
            "similarity": 217.69855044663183
          },
          {
            "metadata": {
              "doc_id": "497",
              "name": "Exposure of Sensitive System Information to an Unauthorized Control Sphere",
              "source": "sparse",
              "original_content": "The product does not properly prevent sensitive system-level information from being accessed by unauthorized actors who do not have the same level of access to the underlying system as the product does.",
              "keyphrase_sources": [
                {
                  "id": "rootcause:The software does not properly restrict access to sensitive information",
                  "keyphrase": "The software does not properly restrict access to sensitive information",
                  "type": "rootcause"
                },
                {
                  "id": "rootcause:potentially allowing unauthorized users to view it.",
                  "keyphrase": "potentially allowing unauthorized users to view it.",
                  "type": "rootcause"
                },
                {
                  "id": "weakness:CWE-200 Exposure of Sensitive Information to an Unauthorized Actor",
                  "keyphrase": "CWE-200 Exposure of Sensitive Information to an Unauthorized Actor",
                  "type": "weakness"
                },
                {
                  "id": "impact:Exposure of Sensitive Information to an Unauthorized Actor",
                  "keyphrase": "Exposure of Sensitive Information to an Unauthorized Actor",
                  "type": "impact"
                },
                {
                  "id": "impact:Unauthorized disclosure of sensitive information.",
                  "keyphrase": "Unauthorized disclosure of sensitive information.",
                  "type": "impact"
                },
                {
                  "id": "vector:Network or Local Access",
                  "keyphrase": "Network or Local Access",
                  "type": "vector"
                },
                {
                  "id": "attacker:An unauthorized user or malicious actor.",
                  "keyphrase": "An unauthorized user or malicious actor.",
                  "type": "attacker"
                },
                {
                  "id": "product:CyberArk",
                  "keyphrase": "CyberArk",
                  "type": "product"
                },
                {
                  "id": "version:Not specified",
                  "keyphrase": "Not specified",
                  "type": "version"
                },
                {
                  "id": "component:Not specified",
                  "keyphrase": "Not specified",
                  "type": "component"
                }
              ]
            },
            "similarity": 212.77791722666683
          },
          {
            "metadata": {
              "doc_id": "359",
              "name": "Exposure of Private Personal Information to an Unauthorized Actor",
              "source": "sparse",
              "original_content": "The product does not properly prevent a person's private, personal information from being accessed by actors who either (1) are not explicitly authorized to access the information or (2) do not have the implicit consent of the person about whom the information is collected.",
              "keyphrase_sources": [
                {
                  "id": "rootcause:The software does not properly restrict access to sensitive information",
                  "keyphrase": "The software does not properly restrict access to sensitive information",
                  "type": "rootcause"
                },
                {
                  "id": "rootcause:potentially allowing unauthorized users to view it.",
                  "keyphrase": "potentially allowing unauthorized users to view it.",
                  "type": "rootcause"
                },
                {
                  "id": "weakness:CWE-200 Exposure of Sensitive Information to an Unauthorized Actor",
                  "keyphrase": "CWE-200 Exposure of Sensitive Information to an Unauthorized Actor",
                  "type": "weakness"
                },
                {
                  "id": "impact:Exposure of Sensitive Information to an Unauthorized Actor",
                  "keyphrase": "Exposure of Sensitive Information to an Unauthorized Actor",
                  "type": "impact"
                },
                {
                  "id": "impact:Unauthorized disclosure of sensitive information.",
                  "keyphrase": "Unauthorized disclosure of sensitive information.",
                  "type": "impact"
                },
                {
                  "id": "attacker:An unauthorized user or malicious actor.",
                  "keyphrase": "An unauthorized user or malicious actor.",
                  "type": "attacker"
                },
                {
                  "id": "product:CyberArk",
                  "keyphrase": "CyberArk",
                  "type": "product"
                },
                {
                  "id": "version:Not specified",
                  "keyphrase": "Not specified",
                  "type": "version"
                },
                {
                  "id": "component:Not specified",
                  "keyphrase": "Not specified",
                  "type": "component"
                }
              ]
            },
            "similarity": 201.51513421846408
          },
          {
            "metadata": {
              "doc_id": "612",
              "name": "Improper Authorization of Index Containing Sensitive Information",
              "source": "sparse",
              "original_content": "The product creates a search index of private or sensitive documents, but it does not properly limit index access to actors who are authorized to see the original information.",
              "keyphrase_sources": [
                {
                  "id": "rootcause:The software does not properly restrict access to sensitive information",
                  "keyphrase": "The software does not properly restrict access to sensitive information",
                  "type": "rootcause"
                }
              ]
            },
            "similarity": 197.88867415802792
          },
          {
            "metadata": {
              "doc_id": "942",
              "name": "Permissive Cross-domain Policy with Untrusted Domains",
              "source": "sparse",
              "original_content": "The product uses a cross-domain policy file that includes domains that should not be trusted.",
              "keyphrase_sources": [
                {
                  "id": "rootcause:The software does not properly restrict access to sensitive information",
                  "keyphrase": "The software does not properly restrict access to sensitive information",
                  "type": "rootcause"
                }
              ]
            },
            "similarity": 194.91716736471597
          }
        ]
      },
      "rootcause:potentially allowing unauthorized users to view it.": {
        "keyphrase": "potentially allowing unauthorized users to view it.",
        "type": "rootcause",
        "cwes": [
          {
            "metadata": {
              "doc_id": "200",
              "name": "Exposure of Sensitive Information to an Unauthorized Actor",
              "source": "sparse",
              "original_content": "The product exposes sensitive information to an actor that is not explicitly authorized to have access to that information."
            },
            "similarity": 194.65663432868382
          },
          {
            "metadata": {
              "doc_id": "497",
              "name": "Exposure of Sensitive System Information to an Unauthorized Control Sphere",
              "source": "sparse",
              "original_content": "The product does not properly prevent sensitive system-level information from being accessed by unauthorized actors who do not have the same level of access to the underlying system as the product does."
            },
            "similarity": 182.1433245214023
          },
          {
            "metadata": {
              "doc_id": "214",
              "name": "Invocation of Process Using Visible Sensitive Information",
              "source": "sparse",
              "original_content": "A process is invoked with sensitive command-line arguments, environment variables, or other elements that can be seen by other processes on the operating system.",
              "keyphrase_sources": [
                {
                  "id": "rootcause:potentially allowing unauthorized users to view it.",
                  "keyphrase": "potentially allowing unauthorized users to view it.",
                  "type": "rootcause"
                }
              ]
            },
            "similarity": 174.31829719553724
          },
          {
            "metadata": {
              "doc_id": "359",
              "name": "Exposure of Private Personal Information to an Unauthorized Actor",
              "source": "sparse",
              "original_content": "The product does not properly prevent a person's private, personal information from being accessed by actors who either (1) are not explicitly authorized to access the information or (2) do not have the implicit consent of the person about whom the information is collected."
            },
            "similarity": 172.59253535494037
          },
          {
            "metadata": {
              "doc_id": "532",
              "name": "Insertion of Sensitive Information into Log File",
              "source": "sparse",
              "original_content": "The product writes sensitive information to a log file.",
              "keyphrase_sources": [
                {
                  "id": "rootcause:potentially allowing unauthorized users to view it.",
                  "keyphrase": "potentially allowing unauthorized users to view it.",
                  "type": "rootcause"
                },
                {
                  "id": "vector:Network or Local Access",
                  "keyphrase": "Network or Local Access",
                  "type": "vector"
                }
              ]
            },
            "similarity": 156.53950126924084
          }
        ]
      },
      "weakness:CWE-200 Exposure of Sensitive Information to an Unauthorized Actor": {
        "keyphrase": "CWE-200 Exposure of Sensitive Information to an Unauthorized Actor",
        "type": "weakness",
        "cwes": [
          {
            "metadata": {
              "doc_id": "200",
              "name": "Exposure of Sensitive Information to an Unauthorized Actor",
              "source": "sparse",
              "original_content": "The product exposes sensitive information to an actor that is not explicitly authorized to have access to that information."
            },
            "similarity": 285.56402593055634
          },
          {
            "metadata": {
              "doc_id": "359",
              "name": "Exposure of Private Personal Information to an Unauthorized Actor",
              "source": "sparse",
              "original_content": "The product does not properly prevent a person's private, personal information from being accessed by actors who either (1) are not explicitly authorized to access the information or (2) do not have the implicit consent of the person about whom the information is collected."
            },
            "similarity": 256.2931793961967
          },
          {
            "metadata": {
              "doc_id": "497",
              "name": "Exposure of Sensitive System Information to an Unauthorized Control Sphere",
              "source": "sparse",
              "original_content": "The product does not properly prevent sensitive system-level information from being accessed by unauthorized actors who do not have the same level of access to the underlying system as the product does."
            },
            "similarity": 245.69001872303227
          },
          {
            "metadata": {
              "doc_id": "209",
              "name": "Generation of Error Message Containing Sensitive Information",
              "source": "sparse",
              "original_content": "The product generates an error message that includes sensitive information about its environment, users, or associated data.",
              "keyphrase_sources": [
                {
                  "id": "weakness:CWE-200 Exposure of Sensitive Information to an Unauthorized Actor",
                  "keyphrase": "CWE-200 Exposure of Sensitive Information to an Unauthorized Actor",
                  "type": "weakness"
                },
                {
                  "id": "impact:Unauthorized disclosure of sensitive information.",
                  "keyphrase": "Unauthorized disclosure of sensitive information.",
                  "type": "impact"
                }
              ]
            },
            "similarity": 211.37037056281508
          },
          {
            "metadata": {
              "doc_id": "524",
              "name": "Use of Cache Containing Sensitive Information",
              "source": "sparse",
              "original_content": "The code uses a cache that contains sensitive information, but the cache can be read by an actor outside of the intended control sphere.",
              "keyphrase_sources": [
                {
                  "id": "weakness:CWE-200 Exposure of Sensitive Information to an Unauthorized Actor",
                  "keyphrase": "CWE-200 Exposure of Sensitive Information to an Unauthorized Actor",
                  "type": "weakness"
                },
                {
                  "id": "impact:Exposure of Sensitive Information to an Unauthorized Actor",
                  "keyphrase": "Exposure of Sensitive Information to an Unauthorized Actor",
                  "type": "impact"
                }
              ]
            },
            "similarity": 208.29963515510465
          }
        ]
      },
      "impact:Exposure of Sensitive Information to an Unauthorized Actor": {
        "keyphrase": "Exposure of Sensitive Information to an Unauthorized Actor",
        "type": "impact",
        "cwes": [
          {
            "metadata": {
              "doc_id": "200",
              "name": "Exposure of Sensitive Information to an Unauthorized Actor",
              "source": "sparse",
              "original_content": "The product exposes sensitive information to an actor that is not explicitly authorized to have access to that information."
            },
            "similarity": 86.98954005561967
          },
          {
            "metadata": {
              "doc_id": "359",
              "name": "Exposure of Private Personal Information to an Unauthorized Actor",
              "source": "sparse",
              "original_content": "The product does not properly prevent a person's private, personal information from being accessed by actors who either (1) are not explicitly authorized to access the information or (2) do not have the implicit consent of the person about whom the information is collected."
            },
            "similarity": 79.60029215039928
          },
          {
            "metadata": {
              "doc_id": "497",
              "name": "Exposure of Sensitive System Information to an Unauthorized Control Sphere",
              "source": "sparse",
              "original_content": "The product does not properly prevent sensitive system-level information from being accessed by unauthorized actors who do not have the same level of access to the underlying system as the product does."
            },
            "similarity": 76.72096831135677
          },
          {
            "metadata": {
              "doc_id": "524",
              "name": "Use of Cache Containing Sensitive Information",
              "source": "sparse",
              "original_content": "The code uses a cache that contains sensitive information, but the cache can be read by an actor outside of the intended control sphere."
            },
            "similarity": 68.40257313768505
          },
          {
            "metadata": {
              "doc_id": "15",
              "name": "External Control of System or Configuration Setting",
              "source": "sparse",
              "original_content": "One or more system settings or configuration elements can be externally controlled by a user.",
              "keyphrase_sources": [
                {
                  "id": "impact:Exposure of Sensitive Information to an Unauthorized Actor",
                  "keyphrase": "Exposure of Sensitive Information to an Unauthorized Actor",
                  "type": "impact"
                },
                {
                  "id": "attacker:An unauthorized user or malicious actor.",
                  "keyphrase": "An unauthorized user or malicious actor.",
                  "type": "attacker"
                }
              ]
            },
            "similarity": 66.6835177997094
          }
        ]
      },
      "impact:Unauthorized disclosure of sensitive information.": {
        "keyphrase": "Unauthorized disclosure of sensitive information.",
        "type": "impact",
        "cwes": [
          {
            "metadata": {
              "doc_id": "200",
              "name": "Exposure of Sensitive Information to an Unauthorized Actor",
              "source": "sparse",
              "original_content": "The product exposes sensitive information to an actor that is not explicitly authorized to have access to that information."
            },
            "similarity": 61.379047554204995
          },
          {
            "metadata": {
              "doc_id": "497",
              "name": "Exposure of Sensitive System Information to an Unauthorized Control Sphere",
              "source": "sparse",
              "original_content": "The product does not properly prevent sensitive system-level information from being accessed by unauthorized actors who do not have the same level of access to the underlying system as the product does."
            },
            "similarity": 55.533061572346085
          },
          {
            "metadata": {
              "doc_id": "598",
              "name": "Use of GET Request Method With Sensitive Query Strings",
              "source": "sparse",
              "original_content": "The web application uses the HTTP GET method to process a request and includes sensitive information in the query string of that request.",
              "keyphrase_sources": [
                {
                  "id": "impact:Unauthorized disclosure of sensitive information.",
                  "keyphrase": "Unauthorized disclosure of sensitive information.",
                  "type": "impact"
                }
              ]
            },
            "similarity": 49.235447032081595
          },
          {
            "metadata": {
              "doc_id": "359",
              "name": "Exposure of Private Personal Information to an Unauthorized Actor",
              "source": "sparse",
              "original_content": "The product does not properly prevent a person's private, personal information from being accessed by actors who either (1) are not explicitly authorized to access the information or (2) do not have the implicit consent of the person about whom the information is collected."
            },
            "similarity": 48.98539897906357
          },
          {
            "metadata": {
              "doc_id": "209",
              "name": "Generation of Error Message Containing Sensitive Information",
              "source": "sparse",
              "original_content": "The product generates an error message that includes sensitive information about its environment, users, or associated data."
            },
            "similarity": 46.634053133094845
          }
        ]
      },
      "vector:Network or Local Access": {
        "keyphrase": "Network or Local Access",
        "type": "vector",
        "cwes": [
          {
            "metadata": {
              "doc_id": "200",
              "name": "Exposure of Sensitive Information to an Unauthorized Actor",
              "source": "sparse",
              "original_content": "The product exposes sensitive information to an actor that is not explicitly authorized to have access to that information."
            },
            "similarity": 53.28488687626855
          },
          {
            "metadata": {
              "doc_id": "497",
              "name": "Exposure of Sensitive System Information to an Unauthorized Control Sphere",
              "source": "sparse",
              "original_content": "The product does not properly prevent sensitive system-level information from being accessed by unauthorized actors who do not have the same level of access to the underlying system as the product does."
            },
            "similarity": 47.2732218764821
          },
          {
            "metadata": {
              "doc_id": "331",
              "name": "Insufficient Entropy",
              "source": "sparse",
              "original_content": "The product uses an algorithm or scheme that produces insufficient entropy, leaving patterns or clusters of values that are more likely to occur than others.",
              "keyphrase_sources": [
                {
                  "id": "vector:Network or Local Access",
                  "keyphrase": "Network or Local Access",
                  "type": "vector"
                },
                {
                  "id": "product:CyberArk",
                  "keyphrase": "CyberArk",
                  "type": "product"
                }
              ]
            },
            "similarity": 42.192658301704455
          },
          {
            "metadata": {
              "doc_id": "532",
              "name": "Insertion of Sensitive Information into Log File",
              "source": "sparse",
              "original_content": "The product writes sensitive information to a log file."
            },
            "similarity": 41.16575835952727
          },
          {
            "metadata": {
              "doc_id": "441",
              "name": "Unintended Proxy or Intermediary ('Confused Deputy')",
              "source": "sparse",
              "original_content": "The product receives a request, message, or directive from an upstream component, but the product does not sufficiently preserve the original source of the request before forwarding the request to an external actor that is outside of the product's control sphere. This causes the product to appear to be the source of the request, leading it to act as a proxy or other intermediary between the upstream component and the external actor.",
              "keyphrase_sources": [
                {
                  "id": "vector:Network or Local Access",
                  "keyphrase": "Network or Local Access",
                  "type": "vector"
                }
              ]
            },
            "similarity": 40.655699547286105
          }
        ]
      },
      "attacker:An unauthorized user or malicious actor.": {
        "keyphrase": "An unauthorized user or malicious actor.",
        "type": "attacker",
        "cwes": [
          {
            "metadata": {
              "doc_id": "200",
              "name": "Exposure of Sensitive Information to an Unauthorized Actor",
              "source": "sparse",
              "original_content": "The product exposes sensitive information to an actor that is not explicitly authorized to have access to that information."
            },
            "similarity": 64.39053599717943
          },
          {
            "metadata": {
              "doc_id": "497",
              "name": "Exposure of Sensitive System Information to an Unauthorized Control Sphere",
              "source": "sparse",
              "original_content": "The product does not properly prevent sensitive system-level information from being accessed by unauthorized actors who do not have the same level of access to the underlying system as the product does."
            },
            "similarity": 56.63137868765537
          },
          {
            "metadata": {
              "doc_id": "359",
              "name": "Exposure of Private Personal Information to an Unauthorized Actor",
              "source": "sparse",
              "original_content": "The product does not properly prevent a person's private, personal information from being accessed by actors who either (1) are not explicitly authorized to access the information or (2) do not have the implicit consent of the person about whom the information is collected."
            },
            "similarity": 56.47403604989409
          },
          {
            "metadata": {
              "doc_id": "15",
              "name": "External Control of System or Configuration Setting",
              "source": "sparse",
              "original_content": "One or more system settings or configuration elements can be externally controlled by a user."
            },
            "similarity": 52.13748397087707
          },
          {
            "metadata": {
              "doc_id": "203",
              "name": "Observable Discrepancy",
              "source": "sparse",
              "original_content": "The product behaves differently or sends different responses under different circumstances in a way that is observable to an unauthorized actor, which exposes security-relevant information about the state of the product, such as whether a particular operation was successful or not.",
              "keyphrase_sources": [
                {
                  "id": "attacker:An unauthorized user or malicious actor.",
                  "keyphrase": "An unauthorized user or malicious actor.",
                  "type": "attacker"
                },
                {
                  "id": "version:Not specified",
                  "keyphrase": "Not specified",
                  "type": "version"
                },
                {
                  "id": "component:Not specified",
                  "keyphrase": "Not specified",
                  "type": "component"
                }
              ]
            },
            "similarity": 50.76395948227883
          }
        ]
      },
      "product:CyberArk": {
        "keyphrase": "CyberArk",
        "type": "product",
        "cwes": [
          {
            "metadata": {
              "doc_id": "331",
              "name": "Insufficient Entropy",
              "source": "sparse",
              "original_content": "The product uses an algorithm or scheme that produces insufficient entropy, leaving patterns or clusters of values that are more likely to occur than others."
            },
            "similarity": 39.49892706315044
          },
          {
            "metadata": {
              "doc_id": "200",
              "name": "Exposure of Sensitive Information to an Unauthorized Actor",
              "source": "sparse",
              "original_content": "The product exposes sensitive information to an actor that is not explicitly authorized to have access to that information."
            },
            "similarity": 33.995717372685284
          },
          {
            "metadata": {
              "doc_id": "204",
              "name": "Observable Response Discrepancy",
              "source": "sparse",
              "original_content": "The product provides different responses to incoming requests in a way that reveals internal state information to an unauthorized actor outside of the intended control sphere.",
              "keyphrase_sources": [
                {
                  "id": "product:CyberArk",
                  "keyphrase": "CyberArk",
                  "type": "product"
                }
              ]
            },
            "similarity": 31.73919536860368
          },
          {
            "metadata": {
              "doc_id": "359",
              "name": "Exposure of Private Personal Information to an Unauthorized Actor",
              "source": "sparse",
              "original_content": "The product does not properly prevent a person's private, personal information from being accessed by actors who either (1) are not explicitly authorized to access the information or (2) do not have the implicit consent of the person about whom the information is collected."
            },
            "similarity": 30.51109278526151
          },
          {
            "metadata": {
              "doc_id": "497",
              "name": "Exposure of Sensitive System Information to an Unauthorized Control Sphere",
              "source": "sparse",
              "original_content": "The product does not properly prevent sensitive system-level information from being accessed by unauthorized actors who do not have the same level of access to the underlying system as the product does."
            },
            "similarity": 29.248811752741943
          }
        ]
      },
      "version:Not specified": {
        "keyphrase": "Not specified",
        "type": "version",
        "cwes": [
          {
            "metadata": {
              "doc_id": "200",
              "name": "Exposure of Sensitive Information to an Unauthorized Actor",
              "source": "sparse",
              "original_content": "The product exposes sensitive information to an actor that is not explicitly authorized to have access to that information."
            },
            "similarity": 40.424050102024246
          },
          {
            "metadata": {
              "doc_id": "359",
              "name": "Exposure of Private Personal Information to an Unauthorized Actor",
              "source": "sparse",
              "original_content": "The product does not properly prevent a person's private, personal information from being accessed by actors who either (1) are not explicitly authorized to access the information or (2) do not have the implicit consent of the person about whom the information is collected."
            },
            "similarity": 36.754997594796976
          },
          {
            "metadata": {
              "doc_id": "497",
              "name": "Exposure of Sensitive System Information to an Unauthorized Control Sphere",
              "source": "sparse",
              "original_content": "The product does not properly prevent sensitive system-level information from being accessed by unauthorized actors who do not have the same level of access to the underlying system as the product does."
            },
            "similarity": 35.22327766152732
          },
          {
            "metadata": {
              "doc_id": "941",
              "name": "Incorrectly Specified Destination in a Communication Channel",
              "source": "sparse",
              "original_content": "The product creates a communication channel to initiate an outgoing request to an actor, but it does not correctly specify the intended destination for that actor.",
              "keyphrase_sources": [
                {
                  "id": "version:Not specified",
                  "keyphrase": "Not specified",
                  "type": "version"
                },
                {
                  "id": "component:Not specified",
                  "keyphrase": "Not specified",
                  "type": "component"
                }
              ]
            },
            "similarity": 33.90884440651428
          },
          {
            "metadata": {
              "doc_id": "203",
              "name": "Observable Discrepancy",
              "source": "sparse",
              "original_content": "The product behaves differently or sends different responses under different circumstances in a way that is observable to an unauthorized actor, which exposes security-relevant information about the state of the product, such as whether a particular operation was successful or not."
            },
            "similarity": 33.362233290460864
          }
        ]
      },
      "component:Not specified": {
        "keyphrase": "Not specified",
        "type": "component",
        "cwes": [
          {
            "metadata": {
              "doc_id": "200",
              "name": "Exposure of Sensitive Information to an Unauthorized Actor",
              "source": "sparse",
              "original_content": "The product exposes sensitive information to an actor that is not explicitly authorized to have access to that information."
            },
            "similarity": 40.424050102024246
          },
          {
            "metadata": {
              "doc_id": "359",
              "name": "Exposure of Private Personal Information to an Unauthorized Actor",
              "source": "sparse",
              "original_content": "The product does not properly prevent a person's private, personal information from being accessed by actors who either (1) are not explicitly authorized to access the information or (2) do not have the implicit consent of the person about whom the information is collected."
            },
            "similarity": 36.754997594796976
          },
          {
            "metadata": {
              "doc_id": "497",
              "name": "Exposure of Sensitive System Information to an Unauthorized Control Sphere",
              "source": "sparse",
              "original_content": "The product does not properly prevent sensitive system-level information from being accessed by unauthorized actors who do not have the same level of access to the underlying system as the product does."
            },
            "similarity": 35.22327766152732
          },
          {
            "metadata": {
              "doc_id": "941",
              "name": "Incorrectly Specified Destination in a Communication Channel",
              "source": "sparse",
              "original_content": "The product creates a communication channel to initiate an outgoing request to an actor, but it does not correctly specify the intended destination for that actor."
            },
            "similarity": 33.90884440651428
          },
          {
            "metadata": {
              "doc_id": "203",
              "name": "Observable Discrepancy",
              "source": "sparse",
              "original_content": "The product behaves differently or sends different responses under different circumstances in a way that is observable to an unauthorized actor, which exposes security-relevant information about the state of the product, such as whether a particular operation was successful or not."
            },
            "similarity": 33.362233290460864
          }
        ]
      }
    },
    "keyphrase_mapping": {
      "200": [
        {
          "id": "rootcause:The software does not properly restrict access to sensitive information",
          "keyphrase": "The software does not properly restrict access to sensitive information",
          "type": "rootcause"
        },
        {
          "id": "rootcause:potentially allowing unauthorized users to view it.",
          "keyphrase": "potentially allowing unauthorized users to view it.",
          "type": "rootcause"
        },
        {
          "id": "weakness:CWE-200 Exposure of Sensitive Information to an Unauthorized Actor",
          "keyphrase": "CWE-200 Exposure of Sensitive Information to an Unauthorized Actor",
          "type": "weakness"
        },
        {
          "id": "impact:Exposure of Sensitive Information to an Unauthorized Actor",
          "keyphrase": "Exposure of Sensitive Information to an Unauthorized Actor",
          "type": "impact"
        },
        {
          "id": "impact:Unauthorized disclosure of sensitive information.",
          "keyphrase": "Unauthorized disclosure of sensitive information.",
          "type": "impact"
        },
        {
          "id": "vector:Network or Local Access",
          "keyphrase": "Network or Local Access",
          "type": "vector"
        },
        {
          "id": "attacker:An unauthorized user or malicious actor.",
          "keyphrase": "An unauthorized user or malicious actor.",
          "type": "attacker"
        },
        {
          "id": "product:CyberArk",
          "keyphrase": "CyberArk",
          "type": "product"
        },
        {
          "id": "version:Not specified",
          "keyphrase": "Not specified",
          "type": "version"
        },
        {
          "id": "component:Not specified",
          "keyphrase": "Not specified",
          "type": "component"
        }
      ],
      "497": [
        {
          "id": "rootcause:The software does not properly restrict access to sensitive information",
          "keyphrase": "The software does not properly restrict access to sensitive information",
          "type": "rootcause"
        },
        {
          "id": "rootcause:potentially allowing unauthorized users to view it.",
          "keyphrase": "potentially allowing unauthorized users to view it.",
          "type": "rootcause"
        },
        {
          "id": "weakness:CWE-200 Exposure of Sensitive Information to an Unauthorized Actor",
          "keyphrase": "CWE-200 Exposure of Sensitive Information to an Unauthorized Actor",
          "type": "weakness"
        },
        {
          "id": "impact:Exposure of Sensitive Information to an Unauthorized Actor",
          "keyphrase": "Exposure of Sensitive Information to an Unauthorized Actor",
          "type": "impact"
        },
        {
          "id": "impact:Unauthorized disclosure of sensitive information.",
          "keyphrase": "Unauthorized disclosure of sensitive information.",
          "type": "impact"
        },
        {
          "id": "vector:Network or Local Access",
          "keyphrase": "Network or Local Access",
          "type": "vector"
        },
        {
          "id": "attacker:An unauthorized user or malicious actor.",
          "keyphrase": "An unauthorized user or malicious actor.",
          "type": "attacker"
        },
        {
          "id": "product:CyberArk",
          "keyphrase": "CyberArk",
          "type": "product"
        },
        {
          "id": "version:Not specified",
          "keyphrase": "Not specified",
          "type": "version"
        },
        {
          "id": "component:Not specified",
          "keyphrase": "Not specified",
          "type": "component"
        }
      ],
      "359": [
        {
          "id": "rootcause:The software does not properly restrict access to sensitive information",
          "keyphrase": "The software does not properly restrict access to sensitive information",
          "type": "rootcause"
        },
        {
          "id": "rootcause:potentially allowing unauthorized users to view it.",
          "keyphrase": "potentially allowing unauthorized users to view it.",
          "type": "rootcause"
        },
        {
          "id": "weakness:CWE-200 Exposure of Sensitive Information to an Unauthorized Actor",
          "keyphrase": "CWE-200 Exposure of Sensitive Information to an Unauthorized Actor",
          "type": "weakness"
        },
        {
          "id": "impact:Exposure of Sensitive Information to an Unauthorized Actor",
          "keyphrase": "Exposure of Sensitive Information to an Unauthorized Actor",
          "type": "impact"
        },
        {
          "id": "impact:Unauthorized disclosure of sensitive information.",
          "keyphrase": "Unauthorized disclosure of sensitive information.",
          "type": "impact"
        },
        {
          "id": "attacker:An unauthorized user or malicious actor.",
          "keyphrase": "An unauthorized user or malicious actor.",
          "type": "attacker"
        },
        {
          "id": "product:CyberArk",
          "keyphrase": "CyberArk",
          "type": "product"
        },
        {
          "id": "version:Not specified",
          "keyphrase": "Not specified",
          "type": "version"
        },
        {
          "id": "component:Not specified",
          "keyphrase": "Not specified",
          "type": "component"
        }
      ],
      "612": [
        {
          "id": "rootcause:The software does not properly restrict access to sensitive information",
          "keyphrase": "The software does not properly restrict access to sensitive information",
          "type": "rootcause"
        }
      ],
      "942": [
        {
          "id": "rootcause:The software does not properly restrict access to sensitive information",
          "keyphrase": "The software does not properly restrict access to sensitive information",
          "type": "rootcause"
        }
      ],
      "214": [
        {
          "id": "rootcause:potentially allowing unauthorized users to view it.",
          "keyphrase": "potentially allowing unauthorized users to view it.",
          "type": "rootcause"
        }
      ],
      "532": [
        {
          "id": "rootcause:potentially allowing unauthorized users to view it.",
          "keyphrase": "potentially allowing unauthorized users to view it.",
          "type": "rootcause"
        },
        {
          "id": "vector:Network or Local Access",
          "keyphrase": "Network or Local Access",
          "type": "vector"
        }
      ],
      "209": [
        {
          "id": "weakness:CWE-200 Exposure of Sensitive Information to an Unauthorized Actor",
          "keyphrase": "CWE-200 Exposure of Sensitive Information to an Unauthorized Actor",
          "type": "weakness"
        },
        {
          "id": "impact:Unauthorized disclosure of sensitive information.",
          "keyphrase": "Unauthorized disclosure of sensitive information.",
          "type": "impact"
        }
      ],
      "524": [
        {
          "id": "weakness:CWE-200 Exposure of Sensitive Information to an Unauthorized Actor",
          "keyphrase": "CWE-200 Exposure of Sensitive Information to an Unauthorized Actor",
          "type": "weakness"
        },
        {
          "id": "impact:Exposure of Sensitive Information to an Unauthorized Actor",
          "keyphrase": "Exposure of Sensitive Information to an Unauthorized Actor",
          "type": "impact"
        }
      ],
      "15": [
        {
          "id": "impact:Exposure of Sensitive Information to an Unauthorized Actor",
          "keyphrase": "Exposure of Sensitive Information to an Unauthorized Actor",
          "type": "impact"
        },
        {
          "id": "attacker:An unauthorized user or malicious actor.",
          "keyphrase": "An unauthorized user or malicious actor.",
          "type": "attacker"
        }
      ],
      "598": [
        {
          "id": "impact:Unauthorized disclosure of sensitive information.",
          "keyphrase": "Unauthorized disclosure of sensitive information.",
          "type": "impact"
        }
      ],
      "331": [
        {
          "id": "vector:Network or Local Access",
          "keyphrase": "Network or Local Access",
          "type": "vector"
        },
        {
          "id": "product:CyberArk",
          "keyphrase": "CyberArk",
          "type": "product"
        }
      ],
      "441": [
        {
          "id": "vector:Network or Local Access",
          "keyphrase": "Network or Local Access",
          "type": "vector"
        }
      ],
      "203": [
        {
          "id": "attacker:An unauthorized user or malicious actor.",
          "keyphrase": "An unauthorized user or malicious actor.",
          "type": "attacker"
        },
        {
          "id": "version:Not specified",
          "keyphrase": "Not specified",
          "type": "version"
        },
        {
          "id": "component:Not specified",
          "keyphrase": "Not specified",
          "type": "component"
        }
      ],
      "204": [
        {
          "id": "product:CyberArk",
          "keyphrase": "CyberArk",
          "type": "product"
        }
      ],
      "941": [
        {
          "id": "version:Not specified",
          "keyphrase": "Not specified",
          "type": "version"
        },
        {
          "id": "component:Not specified",
          "keyphrase": "Not specified",
          "type": "component"
        }
      ]
    },
    "relevant_cwes": [
      {
        "metadata": {
          "doc_id": "200",
          "name": "Exposure of Sensitive Information to an Unauthorized Actor",
          "source": "sparse",
          "original_content": "The product exposes sensitive information to an actor that is not explicitly authorized to have access to that information.",
          "keyphrase_sources": [
            {
              "id": "rootcause:The software does not properly restrict access to sensitive information",
              "keyphrase": "The software does not properly restrict access to sensitive information",
              "type": "rootcause"
            },
            {
              "id": "rootcause:potentially allowing unauthorized users to view it.",
              "keyphrase": "potentially allowing unauthorized users to view it.",
              "type": "rootcause"
            },
            {
              "id": "weakness:CWE-200 Exposure of Sensitive Information to an Unauthorized Actor",
              "keyphrase": "CWE-200 Exposure of Sensitive Information to an Unauthorized Actor",
              "type": "weakness"
            },
            {
              "id": "impact:Exposure of Sensitive Information to an Unauthorized Actor",
              "keyphrase": "Exposure of Sensitive Information to an Unauthorized Actor",
              "type": "impact"
            },
            {
              "id": "impact:Unauthorized disclosure of sensitive information.",
              "keyphrase": "Unauthorized disclosure of sensitive information.",
              "type": "impact"
            },
            {
              "id": "vector:Network or Local Access",
              "keyphrase": "Network or Local Access",
              "type": "vector"
            },
            {
              "id": "attacker:An unauthorized user or malicious actor.",
              "keyphrase": "An unauthorized user or malicious actor.",
              "type": "attacker"
            },
            {
              "id": "product:CyberArk",
              "keyphrase": "CyberArk",
              "type": "product"
            },
            {
              "id": "version:Not specified",
              "keyphrase": "Not specified",
              "type": "version"
            },
            {
              "id": "component:Not specified",
              "keyphrase": "Not specified",
              "type": "component"
            }
          ]
        },
        "similarity": 217.69855044663183
      },
      {
        "metadata": {
          "doc_id": "497",
          "name": "Exposure of Sensitive System Information to an Unauthorized Control Sphere",
          "source": "sparse",
          "original_content": "The product does not properly prevent sensitive system-level information from being accessed by unauthorized actors who do not have the same level of access to the underlying system as the product does.",
          "keyphrase_sources": [
            {
              "id": "rootcause:The software does not properly restrict access to sensitive information",
              "keyphrase": "The software does not properly restrict access to sensitive information",
              "type": "rootcause"
            },
            {
              "id": "rootcause:potentially allowing unauthorized users to view it.",
              "keyphrase": "potentially allowing unauthorized users to view it.",
              "type": "rootcause"
            },
            {
              "id": "weakness:CWE-200 Exposure of Sensitive Information to an Unauthorized Actor",
              "keyphrase": "CWE-200 Exposure of Sensitive Information to an Unauthorized Actor",
              "type": "weakness"
            },
            {
              "id": "impact:Exposure of Sensitive Information to an Unauthorized Actor",
              "keyphrase": "Exposure of Sensitive Information to an Unauthorized Actor",
              "type": "impact"
            },
            {
              "id": "impact:Unauthorized disclosure of sensitive information.",
              "keyphrase": "Unauthorized disclosure of sensitive information.",
              "type": "impact"
            },
            {
              "id": "vector:Network or Local Access",
              "keyphrase": "Network or Local Access",
              "type": "vector"
            },
            {
              "id": "attacker:An unauthorized user or malicious actor.",
              "keyphrase": "An unauthorized user or malicious actor.",
              "type": "attacker"
            },
            {
              "id": "product:CyberArk",
              "keyphrase": "CyberArk",
              "type": "product"
            },
            {
              "id": "version:Not specified",
              "keyphrase": "Not specified",
              "type": "version"
            },
            {
              "id": "component:Not specified",
              "keyphrase": "Not specified",
              "type": "component"
            }
          ]
        },
        "similarity": 212.77791722666683
      },
      {
        "metadata": {
          "doc_id": "209",
          "name": "Generation of Error Message Containing Sensitive Information",
          "source": "sparse",
          "original_content": "The product generates an error message that includes sensitive information about its environment, users, or associated data.",
          "keyphrase_sources": [
            {
              "id": "weakness:CWE-200 Exposure of Sensitive Information to an Unauthorized Actor",
              "keyphrase": "CWE-200 Exposure of Sensitive Information to an Unauthorized Actor",
              "type": "weakness"
            },
            {
              "id": "impact:Unauthorized disclosure of sensitive information.",
              "keyphrase": "Unauthorized disclosure of sensitive information.",
              "type": "impact"
            }
          ]
        },
        "similarity": 211.37037056281508
      },
      {
        "metadata": {
          "doc_id": "524",
          "name": "Use of Cache Containing Sensitive Information",
          "source": "sparse",
          "original_content": "The code uses a cache that contains sensitive information, but the cache can be read by an actor outside of the intended control sphere.",
          "keyphrase_sources": [
            {
              "id": "weakness:CWE-200 Exposure of Sensitive Information to an Unauthorized Actor",
              "keyphrase": "CWE-200 Exposure of Sensitive Information to an Unauthorized Actor",
              "type": "weakness"
            },
            {
              "id": "impact:Exposure of Sensitive Information to an Unauthorized Actor",
              "keyphrase": "Exposure of Sensitive Information to an Unauthorized Actor",
              "type": "impact"
            }
          ]
        },
        "similarity": 208.29963515510465
      },
      {
        "metadata": {
          "doc_id": "359",
          "name": "Exposure of Private Personal Information to an Unauthorized Actor",
          "source": "sparse",
          "original_content": "The product does not properly prevent a person's private, personal information from being accessed by actors who either (1) are not explicitly authorized to access the information or (2) do not have the implicit consent of the person about whom the information is collected.",
          "keyphrase_sources": [
            {
              "id": "rootcause:The software does not properly restrict access to sensitive information",
              "keyphrase": "The software does not properly restrict access to sensitive information",
              "type": "rootcause"
            },
            {
              "id": "rootcause:potentially allowing unauthorized users to view it.",
              "keyphrase": "potentially allowing unauthorized users to view it.",
              "type": "rootcause"
            },
            {
              "id": "weakness:CWE-200 Exposure of Sensitive Information to an Unauthorized Actor",
              "keyphrase": "CWE-200 Exposure of Sensitive Information to an Unauthorized Actor",
              "type": "weakness"
            },
            {
              "id": "impact:Exposure of Sensitive Information to an Unauthorized Actor",
              "keyphrase": "Exposure of Sensitive Information to an Unauthorized Actor",
              "type": "impact"
            },
            {
              "id": "impact:Unauthorized disclosure of sensitive information.",
              "keyphrase": "Unauthorized disclosure of sensitive information.",
              "type": "impact"
            },
            {
              "id": "attacker:An unauthorized user or malicious actor.",
              "keyphrase": "An unauthorized user or malicious actor.",
              "type": "attacker"
            },
            {
              "id": "product:CyberArk",
              "keyphrase": "CyberArk",
              "type": "product"
            },
            {
              "id": "version:Not specified",
              "keyphrase": "Not specified",
              "type": "version"
            },
            {
              "id": "component:Not specified",
              "keyphrase": "Not specified",
              "type": "component"
            }
          ]
        },
        "similarity": 201.51513421846408
      },
      {
        "metadata": {
          "doc_id": "612",
          "name": "Improper Authorization of Index Containing Sensitive Information",
          "source": "sparse",
          "original_content": "The product creates a search index of private or sensitive documents, but it does not properly limit index access to actors who are authorized to see the original information.",
          "keyphrase_sources": [
            {
              "id": "rootcause:The software does not properly restrict access to sensitive information",
              "keyphrase": "The software does not properly restrict access to sensitive information",
              "type": "rootcause"
            }
          ]
        },
        "similarity": 197.88867415802792
      },
      {
        "metadata": {
          "doc_id": "942",
          "name": "Permissive Cross-domain Policy with Untrusted Domains",
          "source": "sparse",
          "original_content": "The product uses a cross-domain policy file that includes domains that should not be trusted.",
          "keyphrase_sources": [
            {
              "id": "rootcause:The software does not properly restrict access to sensitive information",
              "keyphrase": "The software does not properly restrict access to sensitive information",
              "type": "rootcause"
            }
          ]
        },
        "similarity": 194.91716736471597
      },
      {
        "metadata": {
          "doc_id": "214",
          "name": "Invocation of Process Using Visible Sensitive Information",
          "source": "sparse",
          "original_content": "A process is invoked with sensitive command-line arguments, environment variables, or other elements that can be seen by other processes on the operating system.",
          "keyphrase_sources": [
            {
              "id": "rootcause:potentially allowing unauthorized users to view it.",
              "keyphrase": "potentially allowing unauthorized users to view it.",
              "type": "rootcause"
            }
          ]
        },
        "similarity": 174.31829719553724
      },
      {
        "metadata": {
          "doc_id": "532",
          "name": "Insertion of Sensitive Information into Log File",
          "source": "sparse",
          "original_content": "The product writes sensitive information to a log file.",
          "keyphrase_sources": [
            {
              "id": "rootcause:potentially allowing unauthorized users to view it.",
              "keyphrase": "potentially allowing unauthorized users to view it.",
              "type": "rootcause"
            },
            {
              "id": "vector:Network or Local Access",
              "keyphrase": "Network or Local Access",
              "type": "vector"
            }
          ]
        },
        "similarity": 156.53950126924084
      },
      {
        "metadata": {
          "doc_id": "15",
          "name": "External Control of System or Configuration Setting",
          "source": "sparse",
          "original_content": "One or more system settings or configuration elements can be externally controlled by a user.",
          "keyphrase_sources": [
            {
              "id": "impact:Exposure of Sensitive Information to an Unauthorized Actor",
              "keyphrase": "Exposure of Sensitive Information to an Unauthorized Actor",
              "type": "impact"
            },
            {
              "id": "attacker:An unauthorized user or malicious actor.",
              "keyphrase": "An unauthorized user or malicious actor.",
              "type": "attacker"
            }
          ]
        },
        "similarity": 66.6835177997094
      },
      {
        "metadata": {
          "doc_id": "203",
          "name": "Observable Discrepancy",
          "source": "sparse",
          "original_content": "The product behaves differently or sends different responses under different circumstances in a way that is observable to an unauthorized actor, which exposes security-relevant information about the state of the product, such as whether a particular operation was successful or not.",
          "keyphrase_sources": [
            {
              "id": "attacker:An unauthorized user or malicious actor.",
              "keyphrase": "An unauthorized user or malicious actor.",
              "type": "attacker"
            },
            {
              "id": "version:Not specified",
              "keyphrase": "Not specified",
              "type": "version"
            },
            {
              "id": "component:Not specified",
              "keyphrase": "Not specified",
              "type": "component"
            }
          ]
        },
        "similarity": 50.76395948227883
      },
      {
        "metadata": {
          "doc_id": "598",
          "name": "Use of GET Request Method With Sensitive Query Strings",
          "source": "sparse",
          "original_content": "The web application uses the HTTP GET method to process a request and includes sensitive information in the query string of that request.",
          "keyphrase_sources": [
            {
              "id": "impact:Unauthorized disclosure of sensitive information.",
              "keyphrase": "Unauthorized disclosure of sensitive information.",
              "type": "impact"
            }
          ]
        },
        "similarity": 49.235447032081595
      },
      {
        "metadata": {
          "doc_id": "331",
          "name": "Insufficient Entropy",
          "source": "sparse",
          "original_content": "The product uses an algorithm or scheme that produces insufficient entropy, leaving patterns or clusters of values that are more likely to occur than others.",
          "keyphrase_sources": [
            {
              "id": "vector:Network or Local Access",
              "keyphrase": "Network or Local Access",
              "type": "vector"
            },
            {
              "id": "product:CyberArk",
              "keyphrase": "CyberArk",
              "type": "product"
            }
          ]
        },
        "similarity": 42.192658301704455
      },
      {
        "metadata": {
          "doc_id": "441",
          "name": "Unintended Proxy or Intermediary ('Confused Deputy')",
          "source": "sparse",
          "original_content": "The product receives a request, message, or directive from an upstream component, but the product does not sufficiently preserve the original source of the request before forwarding the request to an external actor that is outside of the product's control sphere. This causes the product to appear to be the source of the request, leading it to act as a proxy or other intermediary between the upstream component and the external actor.",
          "keyphrase_sources": [
            {
              "id": "vector:Network or Local Access",
              "keyphrase": "Network or Local Access",
              "type": "vector"
            }
          ]
        },
        "similarity": 40.655699547286105
      },
      {
        "metadata": {
          "doc_id": "941",
          "name": "Incorrectly Specified Destination in a Communication Channel",
          "source": "sparse",
          "original_content": "The product creates a communication channel to initiate an outgoing request to an actor, but it does not correctly specify the intended destination for that actor.",
          "keyphrase_sources": [
            {
              "id": "version:Not specified",
              "keyphrase": "Not specified",
              "type": "version"
            },
            {
              "id": "component:Not specified",
              "keyphrase": "Not specified",
              "type": "component"
            }
          ]
        },
        "similarity": 33.90884440651428
      },
      {
        "metadata": {
          "doc_id": "204",
          "name": "Observable Response Discrepancy",
          "source": "sparse",
          "original_content": "The product provides different responses to incoming requests in a way that reveals internal state information to an unauthorized actor outside of the intended control sphere.",
          "keyphrase_sources": [
            {
              "id": "product:CyberArk",
              "keyphrase": "CyberArk",
              "type": "product"
            }
          ]
        },
        "similarity": 31.73919536860368
      }
    ],
    "enhanced_query": "# Vulnerability Description\n\n    CyberArk - **CWE-200 Exposure of Sensitive Information to an Unauthorized Actor**\n\n    # Keyphrase-Specific CWE Analysis\n    This vulnerability contains multiple keyphrases that may map to different CWEs. \n    Please analyze each keyphrase separately and determine the most appropriate CWE(s) for each.\n\n    ## ROOTCAUSE: 'The software does not properly restrict access to sensitive information'\n\nRelevant CWEs for this ROOTCAUSE:\n\n### 1. CWE-200: Exposure of Sensitive Information to an Unauthorized Actor (Score: 217.70)\n\nThe product exposes sensitive information to an actor that is not explicitly authorized to have access to that information....\n\n### 2. CWE-497: Exposure of Sensitive System Information to an Unauthorized Control Sphere (Score: 212.78)\n\nThe product does not properly prevent sensitive system-level information from being accessed by unauthorized actors who do not have the same level of access to the underlying system as the product does....\n\n### 3. CWE-359: Exposure of Private Personal Information to an Unauthorized Actor (Score: 201.52)\n\nThe product does not properly prevent a person's private, personal information from being accessed by actors who either (1) are not explicitly authorized to access the information or (2) do not have the implicit consent of the person about whom the information is collected....\n\n### 4. CWE-612: Improper Authorization of Index Containing Sensitive Information (Score: 197.89)\n\nThe product creates a search index of private or sensitive documents, but it does not properly limit index access to actors who are authorized to see the original information....\n\n### 5. CWE-942: Permissive Cross-domain Policy with Untrusted Domains (Score: 194.92)\n\nThe product uses a cross-domain policy file that includes domains that should not be trusted....\n\n## ROOTCAUSE: 'potentially allowing unauthorized users to view it.'\n\nRelevant CWEs for this ROOTCAUSE:\n\n### 1. CWE-200: Exposure of Sensitive Information to an Unauthorized Actor (Score: 217.70)\n\nThe product exposes sensitive information to an actor that is not explicitly authorized to have access to that information....\n\n### 2. CWE-497: Exposure of Sensitive System Information to an Unauthorized Control Sphere (Score: 212.78)\n\nThe product does not properly prevent sensitive system-level information from being accessed by unauthorized actors who do not have the same level of access to the underlying system as the product does....\n\n### 3. CWE-359: Exposure of Private Personal Information to an Unauthorized Actor (Score: 201.52)\n\nThe product does not properly prevent a person's private, personal information from being accessed by actors who either (1) are not explicitly authorized to access the information or (2) do not have the implicit consent of the person about whom the information is collected....\n\n### 4. CWE-214: Invocation of Process Using Visible Sensitive Information (Score: 174.32)\n\nA process is invoked with sensitive command-line arguments, environment variables, or other elements that can be seen by other processes on the operating system....\n\n### 5. CWE-532: Insertion of Sensitive Information into Log File (Score: 156.54)\n\nThe product writes sensitive information to a log file....\n\n## WEAKNESS: 'CWE-200 Exposure of Sensitive Information to an Unauthorized Actor'\n\nRelevant CWEs for this WEAKNESS:\n\n### 1. CWE-200: Exposure of Sensitive Information to an Unauthorized Actor (Score: 217.70)\n\nThe product exposes sensitive information to an actor that is not explicitly authorized to have access to that information....\n\n### 2. CWE-497: Exposure of Sensitive System Information to an Unauthorized Control Sphere (Score: 212.78)\n\nThe product does not properly prevent sensitive system-level information from being accessed by unauthorized actors who do not have the same level of access to the underlying system as the product does....\n\n### 3. CWE-209: Generation of Error Message Containing Sensitive Information (Score: 211.37)\n\nThe product generates an error message that includes sensitive information about its environment, users, or associated data....\n\n### 4. CWE-524: Use of Cache Containing Sensitive Information (Score: 208.30)\n\nThe code uses a cache that contains sensitive information, but the cache can be read by an actor outside of the intended control sphere....\n\n### 5. CWE-359: Exposure of Private Personal Information to an Unauthorized Actor (Score: 201.52)\n\nThe product does not properly prevent a person's private, personal information from being accessed by actors who either (1) are not explicitly authorized to access the information or (2) do not have the implicit consent of the person about whom the information is collected....\n\n## IMPACT: 'Exposure of Sensitive Information to an Unauthorized Actor'\n\nRelevant CWEs for this IMPACT:\n\n### 1. CWE-200: Exposure of Sensitive Information to an Unauthorized Actor (Score: 217.70)\n\nThe product exposes sensitive information to an actor that is not explicitly authorized to have access to that information....\n\n### 2. CWE-497: Exposure of Sensitive System Information to an Unauthorized Control Sphere (Score: 212.78)\n\nThe product does not properly prevent sensitive system-level information from being accessed by unauthorized actors who do not have the same level of access to the underlying system as the product does....\n\n### 3. CWE-524: Use of Cache Containing Sensitive Information (Score: 208.30)\n\nThe code uses a cache that contains sensitive information, but the cache can be read by an actor outside of the intended control sphere....\n\n### 4. CWE-359: Exposure of Private Personal Information to an Unauthorized Actor (Score: 201.52)\n\nThe product does not properly prevent a person's private, personal information from being accessed by actors who either (1) are not explicitly authorized to access the information or (2) do not have the implicit consent of the person about whom the information is collected....\n\n### 5. CWE-15: External Control of System or Configuration Setting (Score: 66.68)\n\nOne or more system settings or configuration elements can be externally controlled by a user....\n\n## IMPACT: 'Unauthorized disclosure of sensitive information.'\n\nRelevant CWEs for this IMPACT:\n\n### 1. CWE-200: Exposure of Sensitive Information to an Unauthorized Actor (Score: 217.70)\n\nThe product exposes sensitive information to an actor that is not explicitly authorized to have access to that information....\n\n### 2. CWE-497: Exposure of Sensitive System Information to an Unauthorized Control Sphere (Score: 212.78)\n\nThe product does not properly prevent sensitive system-level information from being accessed by unauthorized actors who do not have the same level of access to the underlying system as the product does....\n\n### 3. CWE-209: Generation of Error Message Containing Sensitive Information (Score: 211.37)\n\nThe product generates an error message that includes sensitive information about its environment, users, or associated data....\n\n### 4. CWE-359: Exposure of Private Personal Information to an Unauthorized Actor (Score: 201.52)\n\nThe product does not properly prevent a person's private, personal information from being accessed by actors who either (1) are not explicitly authorized to access the information or (2) do not have the implicit consent of the person about whom the information is collected....\n\n### 5. CWE-598: Use of GET Request Method With Sensitive Query Strings (Score: 49.24)\n\nThe web application uses the HTTP GET method to process a request and includes sensitive information in the query string of that request....\n\n## VECTOR: 'Network or Local Access'\n\nRelevant CWEs for this VECTOR:\n\n### 1. CWE-200: Exposure of Sensitive Information to an Unauthorized Actor (Score: 217.70)\n\nThe product exposes sensitive information to an actor that is not explicitly authorized to have access to that information....\n\n### 2. CWE-497: Exposure of Sensitive System Information to an Unauthorized Control Sphere (Score: 212.78)\n\nThe product does not properly prevent sensitive system-level information from being accessed by unauthorized actors who do not have the same level of access to the underlying system as the product does....\n\n### 3. CWE-532: Insertion of Sensitive Information into Log File (Score: 156.54)\n\nThe product writes sensitive information to a log file....\n\n### 4. CWE-331: Insufficient Entropy (Score: 42.19)\n\nThe product uses an algorithm or scheme that produces insufficient entropy, leaving patterns or clusters of values that are more likely to occur than others....\n\n### 5. CWE-441: Unintended Proxy or Intermediary ('Confused Deputy') (Score: 40.66)\n\nThe product receives a request, message, or directive from an upstream component, but the product does not sufficiently preserve the original source of the request before forwarding the request to an external actor that is outside of the product's control sphere. This causes the product to appear to...\n\n## ATTACKER: 'An unauthorized user or malicious actor.'\n\nRelevant CWEs for this ATTACKER:\n\n### 1. CWE-200: Exposure of Sensitive Information to an Unauthorized Actor (Score: 217.70)\n\nThe product exposes sensitive information to an actor that is not explicitly authorized to have access to that information....\n\n### 2. CWE-497: Exposure of Sensitive System Information to an Unauthorized Control Sphere (Score: 212.78)\n\nThe product does not properly prevent sensitive system-level information from being accessed by unauthorized actors who do not have the same level of access to the underlying system as the product does....\n\n### 3. CWE-359: Exposure of Private Personal Information to an Unauthorized Actor (Score: 201.52)\n\nThe product does not properly prevent a person's private, personal information from being accessed by actors who either (1) are not explicitly authorized to access the information or (2) do not have the implicit consent of the person about whom the information is collected....\n\n### 4. CWE-15: External Control of System or Configuration Setting (Score: 66.68)\n\nOne or more system settings or configuration elements can be externally controlled by a user....\n\n### 5. CWE-203: Observable Discrepancy (Score: 50.76)\n\nThe product behaves differently or sends different responses under different circumstances in a way that is observable to an unauthorized actor, which exposes security-relevant information about the state of the product, such as whether a particular operation was successful or not....\n\n## PRODUCT: 'CyberArk'\n\nRelevant CWEs for this PRODUCT:\n\n### 1. CWE-200: Exposure of Sensitive Information to an Unauthorized Actor (Score: 217.70)\n\nThe product exposes sensitive information to an actor that is not explicitly authorized to have access to that information....\n\n### 2. CWE-497: Exposure of Sensitive System Information to an Unauthorized Control Sphere (Score: 212.78)\n\nThe product does not properly prevent sensitive system-level information from being accessed by unauthorized actors who do not have the same level of access to the underlying system as the product does....\n\n### 3. CWE-359: Exposure of Private Personal Information to an Unauthorized Actor (Score: 201.52)\n\nThe product does not properly prevent a person's private, personal information from being accessed by actors who either (1) are not explicitly authorized to access the information or (2) do not have the implicit consent of the person about whom the information is collected....\n\n### 4. CWE-331: Insufficient Entropy (Score: 42.19)\n\nThe product uses an algorithm or scheme that produces insufficient entropy, leaving patterns or clusters of values that are more likely to occur than others....\n\n### 5. CWE-204: Observable Response Discrepancy (Score: 31.74)\n\nThe product provides different responses to incoming requests in a way that reveals internal state information to an unauthorized actor outside of the intended control sphere....\n\n## VERSION: 'Not specified'\n\nRelevant CWEs for this VERSION:\n\n### 1. CWE-200: Exposure of Sensitive Information to an Unauthorized Actor (Score: 217.70)\n\nThe product exposes sensitive information to an actor that is not explicitly authorized to have access to that information....\n\n### 2. CWE-497: Exposure of Sensitive System Information to an Unauthorized Control Sphere (Score: 212.78)\n\nThe product does not properly prevent sensitive system-level information from being accessed by unauthorized actors who do not have the same level of access to the underlying system as the product does....\n\n### 3. CWE-359: Exposure of Private Personal Information to an Unauthorized Actor (Score: 201.52)\n\nThe product does not properly prevent a person's private, personal information from being accessed by actors who either (1) are not explicitly authorized to access the information or (2) do not have the implicit consent of the person about whom the information is collected....\n\n### 4. CWE-203: Observable Discrepancy (Score: 50.76)\n\nThe product behaves differently or sends different responses under different circumstances in a way that is observable to an unauthorized actor, which exposes security-relevant information about the state of the product, such as whether a particular operation was successful or not....\n\n### 5. CWE-941: Incorrectly Specified Destination in a Communication Channel (Score: 33.91)\n\nThe product creates a communication channel to initiate an outgoing request to an actor, but it does not correctly specify the intended destination for that actor....\n\n## COMPONENT: 'Not specified'\n\nRelevant CWEs for this COMPONENT:\n\n### 1. CWE-200: Exposure of Sensitive Information to an Unauthorized Actor (Score: 217.70)\n\nThe product exposes sensitive information to an actor that is not explicitly authorized to have access to that information....\n\n### 2. CWE-497: Exposure of Sensitive System Information to an Unauthorized Control Sphere (Score: 212.78)\n\nThe product does not properly prevent sensitive system-level information from being accessed by unauthorized actors who do not have the same level of access to the underlying system as the product does....\n\n### 3. CWE-359: Exposure of Private Personal Information to an Unauthorized Actor (Score: 201.52)\n\nThe product does not properly prevent a person's private, personal information from being accessed by actors who either (1) are not explicitly authorized to access the information or (2) do not have the implicit consent of the person about whom the information is collected....\n\n### 4. CWE-203: Observable Discrepancy (Score: 50.76)\n\nThe product behaves differently or sends different responses under different circumstances in a way that is observable to an unauthorized actor, which exposes security-relevant information about the state of the product, such as whether a particular operation was successful or not....\n\n### 5. CWE-941: Incorrectly Specified Destination in a Communication Channel (Score: 33.91)\n\nThe product creates a communication channel to initiate an outgoing request to an actor, but it does not correctly specify the intended destination for that actor....\n\n\n    # Analysis Instructions\n    1. For each keyphrase, identify the most appropriate CWE(s) that represent the weakness.\n    2. Consider how the different keyphrases might relate to each other in the vulnerability chain.\n    3. Provide a final determination of primary CWE(s) and any secondary CWEs.\n    4. Format your response using the standard analysis template.\n\n    Please analyze how these different weaknesses interact and provide a comprehensive CWE classification.\n    "
  },
  "retrieval_time": 1.0959413051605225
}