{
  "cve_id": "CVE-2024-41084",
  "description": "In the Linux kernel, the following vulnerability has been resolved cxl/region Avoid **null pointer dereference** in region lookup cxl_dpa_to_region() looks up a region based on a memdev and DPA. It wrongly assumes an endpoint found mapping the DPA is also of a fully assembled region. When not true it leads to a **null pointer dereference** looking up the region name. This appears during testing of region lookup after a failure to assemble a BIOS defined region or if the lookup raced with the assembly of the BIOS defined region. Failure to clean up BIOS defined regions that fail assembly is an issue in itself and a fix to that problem will alleviate some of the impact. It will not alleviate the **race condition** so lets harden this path. The behavior change is that the kernel oops due to a **null pointer dereference** is replaced with a dev_dbg() message noting that an endpoint was mapped. Additional comments are added so that future users of this function can more clearly understand what it provides.",
  "key_phrases": {
    "rootcause": [
      "race condition",
      "wrong assumption that an endpoint is a fully assembled region"
    ],
    "weakness": "null pointer dereference",
    "impact": "kernel oops",
    "vector": "",
    "attacker": "",
    "product": "Linux kernel",
    "version": "",
    "component": "cxl/region"
  },
  "reference_content": "Based on the provided information, here's an analysis of the vulnerability:\n\n**Root Cause:**\n\nThe vulnerability lies in the `cxl_dpa_to_region()` function within the Linux kernel's CXL (Compute Express Link) subsystem. This function is responsible for looking up a memory region based on a Device-Private Address (DPA) and a memory device. The root cause is that the function incorrectly assumes that any endpoint mapping a DPA also belongs to a fully assembled region. When this assumption is false, the code attempts to access the region name via a null pointer, causing a kernel panic.\n\n**Weaknesses/Vulnerabilities:**\n\n- **Null Pointer Dereference:** The primary vulnerability is a null pointer dereference. The code accesses `cxled->cxld.region->dev` without verifying if `cxled->cxld.region` is valid. In cases where the region is not fully assembled (e.g., due to a failed assembly, or race conditions during assembly) `cxled->cxld.region` can be null.\n\n**Impact of Exploitation:**\n\n- **Kernel Panic/Crash:** The impact of this vulnerability is a kernel panic (oops) due to the null pointer dereference. This can lead to a denial-of-service (DoS) scenario where the system crashes.\n\n**Attack Vectors:**\n\n- **Triggering a Region Lookup on a Partially Assembled Region:** The vulnerability can be triggered during region lookup attempts after a failure to assemble a BIOS-defined region, or if the lookup raced with the assembly of the BIOS defined region.\n\n**Required Attacker Capabilities/Position:**\n\n- To exploit this vulnerability, an attacker needs a way to trigger a region lookup under the conditions described in the \"Attack Vectors\" section. The attacker would need some level of interaction with the CXL subsystem, which could involve specific hardware configurations or interactions with the driver interface.\n\n**Additional Notes:**\n\n- The provided code diffs show the fix for the vulnerability. Instead of causing a kernel panic, the code now logs a debug message if the region is not fully assembled and the `cxlr` pointer is null.\n- The fix also introduces additional comments to improve code clarity.\n- The vulnerability exists due to a logical flaw in the assumption that an endpoint mapping a DPA always implies a fully assembled region.\n- The fix hardens the code by explicitly checking if the `cxlr` is null before attempting to dereference it.\n\n**Summary of the Fix:**\nThe fix addresses the null pointer dereference by:\n1.  Adding a check to see if `cxlr = cxled->cxld.region` is null or not.\n2.  If it is not null, it will proceed with printing the debug message with the region's device name.\n3. If it is null, it prints a debug message indicating the dpa was mapped to an endpoint rather than a region.\n4.  The code now also sets `ctx->cxlr = cxlr` where cxlr can be a null value.",
  "similar_info": {
    "cwe_distribution": {},
    "cwe_consensus": "",
    "similarity_stats": {
      "thresholds": [],
      "total_samples_by_threshold": {},
      "top_cwes_by_threshold": {}
    }
  },
  "similarity_summary": {
    "consensus_cwe": "",
    "top_cwes": [],
    "confidence_levels": {},
    "total_samples": 0
  },
  "analysis": "# Summary\n| CWE ID  | CWE Name                                                                    | Confidence | CWE Abstraction Level | CWE Vulnerability Mapping Label | CWE-Vulnerability Mapping Notes |\n| :-------- | :-------------------------------------------------------------------------- | :---------- | :---------------------- | :------------------------------ | :------------------------------ |\n| CWE-476   | NULL Pointer Dereference                                                    | 0.9         | Base                    | Primary                         | Allowed                         |\n| CWE-362   | Concurrent Execution using Shared Resource with Improper Synchronization | 0.7         | Class                   | Secondary                       | Allowed-with-Review             |\n\n## Evidence and Confidence\n\n*   **Confidence Score:** 0.8\n*   **Evidence Strength:** HIGH\n\n## Relationship Analysis\nThe primary weakness is a **NULL Pointer Dereference** (CWE-476), which is a Base level CWE. It occurs because of a **race condition** (CWE-362) where a resource state changes between a check and use, thus there's an improper synchronization. CWE-476 is a child of CWE-754 (Improper Check for Unusual or Exceptional Conditions). CWE-362 is a Class level CWE, and might have Base-level children that would be more appropriate but is not applicable here.\n\n```mermaid\ngraph TD\n    cwe476[\"CWE-476: NULL Pointer Dereference\"]\n    cwe362[\"CWE-362: Concurrent Execution using Shared Resource with Improper Synchronization ('Race Condition')\"]\n    cwe754[\"CWE-754: Improper Check for Unusual or Exceptional Conditions\"]\n\n    cwe476 -->|CHILDOF| cwe754\n    cwe476 -->|CANFOLLOW| cwe362\n    \n    classDef primary fill:#f96,stroke:#333,stroke-width:2px\n    classDef secondary fill:#69f,stroke:#333\n    classDef tertiary fill:#9e9,stroke:#333\n    class cwe476 primary\n    class cwe362 secondary\n```\n\n## Vulnerability Chain\nThe vulnerability chain starts with a **race condition** (CWE-362), leading to a **null pointer dereference** (CWE-476), which then results in a kernel oops.\n  - Root Cause: CWE-362 Concurrent Execution using Shared Resource with Improper Synchronization ('Race Condition')\n  - Weakness: CWE-476 NULL Pointer Dereference\n  - Impact: Kernel Oops\n\n## Summary of Analysis\nThe primary cause is a **NULL Pointer Dereference** (CWE-476) that occurs due to a **race condition** (CWE-362). The vulnerability description clearly states: \"Avoid **null pointer dereference** in region lookup cxl_dpa_to_region() looks up a region based on a memdev and DPA. It wrongly assumes an endpoint found mapping the DPA is also of a fully assembled region. When not true it leads to a **null pointer dereference** looking up the region name... It will not alleviate the **race condition** so lets harden this path.\"\n\nCWE-476 is the most specific and accurate representation of the vulnerability, as it directly describes the **null pointer dereference**. CWE-362 explains the concurrent execution and lack of proper synchronization that leads to this condition.\n\nI considered other CWEs, such as CWE-252 (Unchecked Return Value), CWE-665 (Improper Initialization), and CWE-822 (Untrusted Pointer Dereference), but these did not accurately represent the specific vulnerability described. CWE-252 was considered because of the potential for a missing check, but the core issue is the dereference of a null pointer, not the missing check itself.\n\nRelevant CWE Information:\n# Enhanced Context (25 CWEs)\nThe following CWEs were identified as potentially relevant to this vulnerability:\n\n## CWE-667: Improper Locking\n**Abstraction Level**: Class\n**Similarity Score**: 0.77\n**Source**: dense\n\n**Description**:\nThe product does not properly acquire or release a lock on a resource, leading to unexpected resource state changes and behaviors.\n\n**Mapping Guidance**:\n- Usage: Allowed-with-Review\n- Rationale: This CWE entry is a Class and might have Base-level children that would be more appropriate\n\n## CWE-703: Improper Check or Handling of Exceptional Conditions\n**Abstraction Level**: Pillar\n**Similarity Score**: 0.75\n**Source**: dense\n\n**Description**:\nThe product does not properly anticipate or handle exceptional conditions that rarely occur during normal operation of the product.\n\n**Mapping Guidance**:\n- Usage: Discouraged\n- Rationale: This CWE entry is extremely high-level, a Pillar.\n\n## CWE-824: Access of Uninitialized Pointer\n**Abstraction Level**: Base\n**Similarity Score**: 0.75\n**Source**: dense\n\n**Description**:\nThe product accesses or uses a pointer that has not been initialized.\n\n**Mapping Guidance**:\n- Usage: Allowed\n- Rationale: This CWE entry is at the Base level of abstraction, which is a preferred level of abstraction for mapping to the root causes of vulnerabilities.\n\n## CWE-362: Concurrent Execution using Shared Resource with Improper Synchronization ('Race Condition')\n**Abstraction Level**: Class\n**Similarity Score**: 0.74\n**Source**: dense\n\n**Description**:\nThe product contains a concurrent code sequence that requires temporary, exclusive access to a shared resource, but a timing window exists in which the shared resource can be modified by another code sequence operating concurrently.\n\n**Mapping Guidance**:\n- Usage: Allowed-with-Review\n- Rationale: This CWE entry is a Class and might have Base-level children that would be more appropriate\n\n## CWE-665: Improper Initialization\n**Abstraction Level**: Class\n**Similarity Score**: 0.74\n**Source**: dense\n\n**Description**:\nThe product does not initialize or incorrectly initializes a resource, which might leave the resource in an unexpected state when it is accessed or used.\n\n**Mapping Guidance**:\n- Usage: Discouraged\n- Rationale: This CWE entry is a level-1 Class (i.e., a child of a Pillar). It might have lower-level children that would be more appropriate\n\n## CWE-367: Time-of-check Time-of-use (TOCTOU) Race Condition\n**Abstraction Level**: Base\n**Similarity Score**: 0.74\n**Source**: dense\n\n**Description**:\nThe product checks the state of a resource before using that resource, but the resource's state can change between the check and the use in a way that invalidates the results of the check. This can cause the product to perform invalid actions when the resource is in an unexpected state.\n\n**Mapping Guidance**:\n- Usage: Allowed\n- Rationale: This CWE entry is at the Base level of abstraction, which is a preferred level of abstraction for mapping to the root causes of vulnerabilities.\n\n## CWE-754: Improper Check for Unusual or Exceptional Conditions\n**Abstraction Level**: Class\n**Similarity Score**: 0.73\n**Source**: dense\n\n**Description**:\nThe product does not check or incorrectly checks for unusual or exceptional conditions that are not expected to occur frequently during day to day operation of the product.\n\n**Mapping Guidance**:\n- Usage: Allowed-with-Review\n- Rationale: This CWE entry is a Class and might have Base-level children that would be more appropriate\n\n## CWE-696: Incorrect Behavior Order\n**Abstraction Level**: Class\n**Similarity Score**: 0.73\n**Source**: dense\n\n**Description**:\nThe product performs multiple related behaviors, but the behaviors are performed in the wrong order in ways which may produce resultant weaknesses.\n\n**Mapping Guidance**:\n- Usage: Allowed-with-Review\n- Rationale: This CWE entry is a Class and might have Base-level children that would be more appropriate\n\n## CWE-755: Improper Handling of Exceptional Conditions\n**Abstraction Level**: Class\n**Similarity Score**: 0.73\n**Source**: dense\n\n**Description**:\nThe product does not handle or incorrectly handles an exceptional condition.\n\n**Mapping Guidance**:\n- Usage: Discouraged\n- Rationale: This CWE entry is a level-1 Class (i.e., a child of a Pillar). It might have lower-level children that would be more appropriate\n\n## CWE-909: Missing Initialization of Resource\n**Abstraction Level**: Class\n**Similarity Score**: 0.73\n**Source**: dense\n\n**Description**:\nThe product does not initialize a critical resource.\n\n**Mapping Guidance**:\n- Usage: Allowed-with-Review\n- Rationale: This CWE entry is a Class and might have Base-level children that would be more appropriate\n\n## CWE-1257: Improper Access Control Applied to Mirrored or Aliased Memory Regions\n**Abstraction Level**: Base\n**Similarity Score**: 2878.76\n**Source**: sparse\n\n**Description**:\nAliased or mirrored memory regions in hardware designs may have inconsistent read/write permissions enforced by the hardware. A possible result is that an untrusted agent is blocked from accessing a memory region but is not blocked from accessing the corresponding aliased memory region.\n\n**Mapping Guidance**:\n- Usage: Allowed\n- Rationale: This CWE entry is at the Base level of abstraction, which is a preferred level of abstraction for mapping to the root causes",
  "analysis_with_relationships": "# Summary\n| CWE ID  | CWE Name                                                                    | Confidence | CWE Abstraction Level | CWE Vulnerability Mapping Label | CWE-Vulnerability Mapping Notes |\n| :-------- | :-------------------------------------------------------------------------- | :---------- | :---------------------- | :------------------------------ | :------------------------------ |\n| CWE-476   | NULL Pointer Dereference                                                    | 0.9         | Base                    | Primary                         | Allowed                         |\n| CWE-362   | Concurrent Execution using Shared Resource with Improper Synchronization | 0.7         | Class                   | Secondary                       | Allowed-with-Review             |\n\n## Evidence and Confidence\n\n*   **Confidence Score:** 0.8\n*   **Evidence Strength:** HIGH\n\n## Relationship Analysis\nThe primary weakness is a **NULL Pointer Dereference** (CWE-476), which is a Base level CWE. It occurs because of a **race condition** (CWE-362) where a resource state changes between a check and use, thus there's an improper synchronization. CWE-476 is a child of CWE-754 (Improper Check for Unusual or Exceptional Conditions). CWE-362 is a Class level CWE, and might have Base-level children that would be more appropriate but is not applicable here.\n\n```mermaid\ngraph TD\n    cwe476[\"CWE-476: NULL Pointer Dereference\"]\n    cwe362[\"CWE-362: Concurrent Execution using Shared Resource with Improper Synchronization ('Race Condition')\"]\n    cwe754[\"CWE-754: Improper Check for Unusual or Exceptional Conditions\"]\n\n    cwe476 -->|CHILDOF| cwe754\n    cwe476 -->|CANFOLLOW| cwe362\n    \n    classDef primary fill:#f96,stroke:#333,stroke-width:2px\n    classDef secondary fill:#69f,stroke:#333\n    classDef tertiary fill:#9e9,stroke:#333\n    class cwe476 primary\n    class cwe362 secondary\n```\n\n## Vulnerability Chain\nThe vulnerability chain starts with a **race condition** (CWE-362), leading to a **null pointer dereference** (CWE-476), which then results in a kernel oops.\n  - Root Cause: CWE-362 Concurrent Execution using Shared Resource with Improper Synchronization ('Race Condition')\n  - Weakness: CWE-476 NULL Pointer Dereference\n  - Impact: Kernel Oops\n\n## Summary of Analysis\nThe primary cause is a **NULL Pointer Dereference** (CWE-476) that occurs due to a **race condition** (CWE-362). The vulnerability description clearly states: \"Avoid **null pointer dereference** in region lookup cxl_dpa_to_region() looks up a region based on a memdev and DPA. It wrongly assumes an endpoint found mapping the DPA is also of a fully assembled region. When not true it leads to a **null pointer dereference** looking up the region name... It will not alleviate the **race condition** so lets harden this path.\"\n\nCWE-476 is the most specific and accurate representation of the vulnerability, as it directly describes the **null pointer dereference**. CWE-362 explains the concurrent execution and lack of proper synchronization that leads to this condition.\n\nI considered other CWEs, such as CWE-252 (Unchecked Return Value), CWE-665 (Improper Initialization), and CWE-822 (Untrusted Pointer Dereference), but these did not accurately represent the specific vulnerability described. CWE-252 was considered because of the potential for a missing check, but the core issue is the dereference of a null pointer, not the missing check itself.\n\nRelevant CWE Information:\n# Enhanced Context (25 CWEs)\nThe following CWEs were identified as potentially relevant to this vulnerability:\n\n## CWE-667: Improper Locking\n**Abstraction Level**: Class\n**Similarity Score**: 0.77\n**Source**: dense\n\n**Description**:\nThe product does not properly acquire or release a lock on a resource, leading to unexpected resource state changes and behaviors.\n\n**Mapping Guidance**:\n- Usage: Allowed-with-Review\n- Rationale: This CWE entry is a Class and might have Base-level children that would be more appropriate\n\n## CWE-703: Improper Check or Handling of Exceptional Conditions\n**Abstraction Level**: Pillar\n**Similarity Score**: 0.75\n**Source**: dense\n\n**Description**:\nThe product does not properly anticipate or handle exceptional conditions that rarely occur during normal operation of the product.\n\n**Mapping Guidance**:\n- Usage: Discouraged\n- Rationale: This CWE entry is extremely high-level, a Pillar.\n\n## CWE-824: Access of Uninitialized Pointer\n**Abstraction Level**: Base\n**Similarity Score**: 0.75\n**Source**: dense\n\n**Description**:\nThe product accesses or uses a pointer that has not been initialized.\n\n**Mapping Guidance**:\n- Usage: Allowed\n- Rationale: This CWE entry is at the Base level of abstraction, which is a preferred level of abstraction for mapping to the root causes of vulnerabilities.\n\n## CWE-362: Concurrent Execution using Shared Resource with Improper Synchronization ('Race Condition')\n**Abstraction Level**: Class\n**Similarity Score**: 0.74\n**Source**: dense\n\n**Description**:\nThe product contains a concurrent code sequence that requires temporary, exclusive access to a shared resource, but a timing window exists in which the shared resource can be modified by another code sequence operating concurrently.\n\n**Mapping Guidance**:\n- Usage: Allowed-with-Review\n- Rationale: This CWE entry is a Class and might have Base-level children that would be more appropriate\n\n## CWE-665: Improper Initialization\n**Abstraction Level**: Class\n**Similarity Score**: 0.74\n**Source**: dense\n\n**Description**:\nThe product does not initialize or incorrectly initializes a resource, which might leave the resource in an unexpected state when it is accessed or used.\n\n**Mapping Guidance**:\n- Usage: Discouraged\n- Rationale: This CWE entry is a level-1 Class (i.e., a child of a Pillar). It might have lower-level children that would be more appropriate\n\n## CWE-367: Time-of-check Time-of-use (TOCTOU) Race Condition\n**Abstraction Level**: Base\n**Similarity Score**: 0.74\n**Source**: dense\n\n**Description**:\nThe product checks the state of a resource before using that resource, but the resource's state can change between the check and the use in a way that invalidates the results of the check. This can cause the product to perform invalid actions when the resource is in an unexpected state.\n\n**Mapping Guidance**:\n- Usage: Allowed\n- Rationale: This CWE entry is at the Base level of abstraction, which is a preferred level of abstraction for mapping to the root causes of vulnerabilities.\n\n## CWE-754: Improper Check for Unusual or Exceptional Conditions\n**Abstraction Level**: Class\n**Similarity Score**: 0.73\n**Source**: dense\n\n**Description**:\nThe product does not check or incorrectly checks for unusual or exceptional conditions that are not expected to occur frequently during day to day operation of the product.\n\n**Mapping Guidance**:\n- Usage: Allowed-with-Review\n- Rationale: This CWE entry is a Class and might have Base-level children that would be more appropriate\n\n## CWE-696: Incorrect Behavior Order\n**Abstraction Level**: Class\n**Similarity Score**: 0.73\n**Source**: dense\n\n**Description**:\nThe product performs multiple related behaviors, but the behaviors are performed in the wrong order in ways which may produce resultant weaknesses.\n\n**Mapping Guidance**:\n- Usage: Allowed-with-Review\n- Rationale: This CWE entry is a Class and might have Base-level children that would be more appropriate\n\n## CWE-755: Improper Handling of Exceptional Conditions\n**Abstraction Level**: Class\n**Similarity Score**: 0.73\n**Source**: dense\n\n**Description**:\nThe product does not handle or incorrectly handles an exceptional condition.\n\n**Mapping Guidance**:\n- Usage: Discouraged\n- Rationale: This CWE entry is a level-1 Class (i.e., a child of a Pillar). It might have lower-level children that would be more appropriate\n\n## CWE-909: Missing Initialization of Resource\n**Abstraction Level**: Class\n**Similarity Score**: 0.73\n**Source**: dense\n\n**Description**:\nThe product does not initialize a critical resource.\n\n**Mapping Guidance**:\n- Usage: Allowed-with-Review\n- Rationale: This CWE entry is a Class and might have Base-level children that would be more appropriate\n\n## CWE-1257: Improper Access Control Applied to Mirrored or Aliased Memory Regions\n**Abstraction Level**: Base\n**Similarity Score**: 2878.76\n**Source**: sparse\n\n**Description**:\nAliased or mirrored memory regions in hardware designs may have inconsistent read/write permissions enforced by the hardware. A possible result is that an untrusted agent is blocked from accessing a memory region but is not blocked from accessing the corresponding aliased memory region.\n\n**Mapping Guidance**:\n- Usage: Allowed\n- Rationale: This CWE entry is at the Base level of abstraction, which is a preferred level of abstraction for mapping to the root causes\n\n\n## CWE Relationship Analysis\n\nCurrent CWEs represent these abstraction levels: .\n\n\n### Vulnerability Chain Analysis\n\n**Chain starting from CWE-476:**\n- 476 (NULL Pointer Dereference) - ROOT\n\n\n**Chain starting from CWE-667:**\n- 667 (Improper Locking) - ROOT\n\n\n\n### CWE Relationship Diagram\n\n```mermaid\ngraph TD\n    classDef primary fill:#f96,stroke:#333,stroke-width:2px\n    classDef secondary fill:#69f,stroke:#333\n    classDef tertiary fill:#9e9,stroke:#333\n```",
  "criticism": "",
  "resolution": "",
  "relevant_cwes": [
    {
      "metadata": {
        "doc_id": "252",
        "name": "Unchecked Return Value",
        "source": "sparse",
        "original_content": "The product does not check the return value from a method or function, which can prevent it from detecting unexpected states and conditions.",
        "keyphrase_sources": [
          {
            "id": "rootcause:wrong assumption that an endpoint is a fully assembled region",
            "keyphrase": "wrong assumption that an endpoint is a fully assembled region",
            "type": "rootcause"
          },
          {
            "id": "weakness:null pointer dereference",
            "keyphrase": "null pointer dereference",
            "type": "weakness"
          },
          {
            "id": "impact:kernel oops",
            "keyphrase": "kernel oops",
            "type": "impact"
          },
          {
            "id": "product:Linux kernel",
            "keyphrase": "Linux kernel",
            "type": "product"
          },
          {
            "id": "component:cxl/region",
            "keyphrase": "cxl/region",
            "type": "component"
          }
        ]
      },
      "similarity": 979.3707259233393
    },
    {
      "metadata": {
        "doc_id": "362",
        "name": "Concurrent Execution using Shared Resource with Improper Synchronization ('Race Condition')",
        "source": "sparse",
        "original_content": "The product contains a concurrent code sequence that requires temporary, exclusive access to a shared resource, but a timing window exists in which the shared resource can be modified by another code sequence operating concurrently.",
        "keyphrase_sources": [
          {
            "id": "rootcause:race condition",
            "keyphrase": "race condition",
            "type": "rootcause"
          },
          {
            "id": "rootcause:wrong assumption that an endpoint is a fully assembled region",
            "keyphrase": "wrong assumption that an endpoint is a fully assembled region",
            "type": "rootcause"
          },
          {
            "id": "weakness:null pointer dereference",
            "keyphrase": "null pointer dereference",
            "type": "weakness"
          },
          {
            "id": "impact:kernel oops",
            "keyphrase": "kernel oops",
            "type": "impact"
          },
          {
            "id": "product:Linux kernel",
            "keyphrase": "Linux kernel",
            "type": "product"
          },
          {
            "id": "component:cxl/region",
            "keyphrase": "cxl/region",
            "type": "component"
          }
        ]
      },
      "similarity": 972.5998177273964
    },
    {
      "metadata": {
        "doc_id": "476",
        "name": "NULL Pointer Dereference",
        "source": "sparse",
        "original_content": "The product dereferences a pointer that it expects to be valid but is NULL.",
        "keyphrase_sources": [
          {
            "id": "rootcause:race condition",
            "keyphrase": "race condition",
            "type": "rootcause"
          },
          {
            "id": "rootcause:wrong assumption that an endpoint is a fully assembled region",
            "keyphrase": "wrong assumption that an endpoint is a fully assembled region",
            "type": "rootcause"
          },
          {
            "id": "weakness:null pointer dereference",
            "keyphrase": "null pointer dereference",
            "type": "weakness"
          },
          {
            "id": "impact:kernel oops",
            "keyphrase": "kernel oops",
            "type": "impact"
          },
          {
            "id": "product:Linux kernel",
            "keyphrase": "Linux kernel",
            "type": "product"
          },
          {
            "id": "component:cxl/region",
            "keyphrase": "cxl/region",
            "type": "component"
          }
        ]
      },
      "similarity": 969.6225996477124
    },
    {
      "metadata": {
        "doc_id": "367",
        "name": "Time-of-check Time-of-use (TOCTOU) Race Condition",
        "source": "sparse",
        "original_content": "The product checks the state of a resource before using that resource, but the resource's state can change between the check and the use in a way that invalidates the results of the check. This can cause the product to perform invalid actions when the resource is in an unexpected state.",
        "keyphrase_sources": [
          {
            "id": "rootcause:race condition",
            "keyphrase": "race condition",
            "type": "rootcause"
          }
        ]
      },
      "similarity": 938.6352242776663
    },
    {
      "metadata": {
        "doc_id": "667",
        "name": "Improper Locking",
        "source": "sparse",
        "original_content": "The product does not properly acquire or release a lock on a resource, leading to unexpected resource state changes and behaviors.",
        "keyphrase_sources": [
          {
            "id": "rootcause:race condition",
            "keyphrase": "race condition",
            "type": "rootcause"
          },
          {
            "id": "rootcause:wrong assumption that an endpoint is a fully assembled region",
            "keyphrase": "wrong assumption that an endpoint is a fully assembled region",
            "type": "rootcause"
          },
          {
            "id": "impact:kernel oops",
            "keyphrase": "kernel oops",
            "type": "impact"
          },
          {
            "id": "product:Linux kernel",
            "keyphrase": "Linux kernel",
            "type": "product"
          },
          {
            "id": "component:cxl/region",
            "keyphrase": "cxl/region",
            "type": "component"
          }
        ]
      },
      "similarity": 937.9063851602962
    },
    {
      "metadata": {
        "doc_id": "1257",
        "name": "Improper Access Control Applied to Mirrored or Aliased Memory Regions",
        "source": "sparse",
        "original_content": "Aliased or mirrored memory regions in hardware designs may have inconsistent read/write permissions enforced by the hardware. A possible result is that an untrusted agent is blocked from accessing a memory region but is not blocked from accessing the corresponding aliased memory region.\n\t\t\t",
        "keyphrase_sources": [
          {
            "id": "rootcause:race condition",
            "keyphrase": "race condition",
            "type": "rootcause"
          },
          {
            "id": "rootcause:wrong assumption that an endpoint is a fully assembled region",
            "keyphrase": "wrong assumption that an endpoint is a fully assembled region",
            "type": "rootcause"
          },
          {
            "id": "impact:kernel oops",
            "keyphrase": "kernel oops",
            "type": "impact"
          },
          {
            "id": "product:Linux kernel",
            "keyphrase": "Linux kernel",
            "type": "product"
          },
          {
            "id": "component:cxl/region",
            "keyphrase": "cxl/region",
            "type": "component"
          }
        ]
      },
      "similarity": 914.2980751741234
    },
    {
      "metadata": {
        "doc_id": "665",
        "name": "Improper Initialization",
        "source": "sparse",
        "original_content": "The product does not initialize or incorrectly initializes a resource, which might leave the resource in an unexpected state when it is accessed or used.",
        "keyphrase_sources": [
          {
            "id": "weakness:null pointer dereference",
            "keyphrase": "null pointer dereference",
            "type": "weakness"
          }
        ]
      },
      "similarity": 882.6053589369687
    },
    {
      "metadata": {
        "doc_id": "822",
        "name": "Untrusted Pointer Dereference",
        "source": "sparse",
        "original_content": "The product obtains a value from an untrusted source, converts this value to a pointer, and dereferences the resulting pointer.",
        "keyphrase_sources": [
          {
            "id": "weakness:null pointer dereference",
            "keyphrase": "null pointer dereference",
            "type": "weakness"
          }
        ]
      },
      "similarity": 873.6390352804843
    }
  ],
  "identified_cwes": {
    "analyzer": [
      "CWE-476",
      "CWE-667",
      "CWE-909",
      "CWE-1257",
      "CWE-696",
      "CWE-362",
      "CWE-367",
      "CWE-822",
      "CWE-755",
      "CWE-824",
      "CWE-252",
      "CWE-754",
      "CWE-703",
      "CWE-665"
    ],
    "critic_additional": []
  },
  "keyphrase_cwe_mapping": {
    "362": [
      {
        "id": "rootcause:race condition",
        "keyphrase": "race condition",
        "type": "rootcause"
      },
      {
        "id": "rootcause:wrong assumption that an endpoint is a fully assembled region",
        "keyphrase": "wrong assumption that an endpoint is a fully assembled region",
        "type": "rootcause"
      },
      {
        "id": "weakness:null pointer dereference",
        "keyphrase": "null pointer dereference",
        "type": "weakness"
      },
      {
        "id": "impact:kernel oops",
        "keyphrase": "kernel oops",
        "type": "impact"
      },
      {
        "id": "product:Linux kernel",
        "keyphrase": "Linux kernel",
        "type": "product"
      },
      {
        "id": "component:cxl/region",
        "keyphrase": "cxl/region",
        "type": "component"
      }
    ],
    "476": [
      {
        "id": "rootcause:race condition",
        "keyphrase": "race condition",
        "type": "rootcause"
      },
      {
        "id": "rootcause:wrong assumption that an endpoint is a fully assembled region",
        "keyphrase": "wrong assumption that an endpoint is a fully assembled region",
        "type": "rootcause"
      },
      {
        "id": "weakness:null pointer dereference",
        "keyphrase": "null pointer dereference",
        "type": "weakness"
      },
      {
        "id": "impact:kernel oops",
        "keyphrase": "kernel oops",
        "type": "impact"
      },
      {
        "id": "product:Linux kernel",
        "keyphrase": "Linux kernel",
        "type": "product"
      },
      {
        "id": "component:cxl/region",
        "keyphrase": "cxl/region",
        "type": "component"
      }
    ],
    "367": [
      {
        "id": "rootcause:race condition",
        "keyphrase": "race condition",
        "type": "rootcause"
      }
    ],
    "667": [
      {
        "id": "rootcause:race condition",
        "keyphrase": "race condition",
        "type": "rootcause"
      },
      {
        "id": "rootcause:wrong assumption that an endpoint is a fully assembled region",
        "keyphrase": "wrong assumption that an endpoint is a fully assembled region",
        "type": "rootcause"
      },
      {
        "id": "impact:kernel oops",
        "keyphrase": "kernel oops",
        "type": "impact"
      },
      {
        "id": "product:Linux kernel",
        "keyphrase": "Linux kernel",
        "type": "product"
      },
      {
        "id": "component:cxl/region",
        "keyphrase": "cxl/region",
        "type": "component"
      }
    ],
    "1257": [
      {
        "id": "rootcause:race condition",
        "keyphrase": "race condition",
        "type": "rootcause"
      },
      {
        "id": "rootcause:wrong assumption that an endpoint is a fully assembled region",
        "keyphrase": "wrong assumption that an endpoint is a fully assembled region",
        "type": "rootcause"
      },
      {
        "id": "impact:kernel oops",
        "keyphrase": "kernel oops",
        "type": "impact"
      },
      {
        "id": "product:Linux kernel",
        "keyphrase": "Linux kernel",
        "type": "product"
      },
      {
        "id": "component:cxl/region",
        "keyphrase": "cxl/region",
        "type": "component"
      }
    ],
    "252": [
      {
        "id": "rootcause:wrong assumption that an endpoint is a fully assembled region",
        "keyphrase": "wrong assumption that an endpoint is a fully assembled region",
        "type": "rootcause"
      },
      {
        "id": "weakness:null pointer dereference",
        "keyphrase": "null pointer dereference",
        "type": "weakness"
      },
      {
        "id": "impact:kernel oops",
        "keyphrase": "kernel oops",
        "type": "impact"
      },
      {
        "id": "product:Linux kernel",
        "keyphrase": "Linux kernel",
        "type": "product"
      },
      {
        "id": "component:cxl/region",
        "keyphrase": "cxl/region",
        "type": "component"
      }
    ],
    "665": [
      {
        "id": "weakness:null pointer dereference",
        "keyphrase": "null pointer dereference",
        "type": "weakness"
      }
    ],
    "822": [
      {
        "id": "weakness:null pointer dereference",
        "keyphrase": "null pointer dereference",
        "type": "weakness"
      }
    ]
  }
}