{
  "cve_id": "CVE-2025-1828",
  "description": "CryptRandom Perl package 1.05 through 1.55 may use rand() function, which is not cryptographically strong, for cryptographic functions. If the Provider is not specified and /dev/urandom or an Entropy Gathering Daemon (egd) service is not available CryptRandom will default to use the **insecure CryptRandomrand provider**. In particular, Windows versions of perl will encounter this issue by default.",
  "key_phrases": {
    "rootcause": "use of rand() function",
    "weakness": "insecure CryptRandomrand provider",
    "impact": "",
    "vector": "",
    "attacker": "",
    "product": "CryptRandom Perl package",
    "version": "1.05 through 1.55",
    "component": "cryptographic functions"
  },
  "reference_content": "## Analysis of CVE-2025-1828 related content:\n\nBased on the provided content, here's an extraction of relevant information, focusing on the commit messages and documentation related to `Crypt::Random`:\n\n**Root cause of vulnerability:**\n\nThe `rand` provider in `Crypt::Random` was identified as insecure for cryptographic purposes. It relied on Perl's internal `rand` function, which is not a cryptographically secure random number generator (CSPRNG).\n\n**Weaknesses/vulnerabilities present:**\n\n*   Use of a non-cryptographically secure random number generator (`rand`) as a default or available option.\n*   Potential for predictable or biased random numbers when using the `rand` provider.\n\n**Impact of exploitation:**\n\nUsing the insecure `rand` provider could compromise the security of applications relying on `Crypt::Random` for generating random numbers, especially in cryptographic contexts. This could lead to vulnerabilities such as:\n\n*   Predictable keys or initialization vectors.\n*   Weakened encryption.\n*   Successful attacks against systems relying on randomness for security.\n\n**Attack vectors:**\n\nAn attacker could exploit the vulnerability by:\n\n*   Forcing the application to use the `rand` provider.\n*   Predicting the output of the `rand` function and using this information to compromise the system.\n\n**Required attacker capabilities/position:**\n\nThe attacker would need to be able to influence the application to use the insecure `rand` provider. This could involve:\n\n*   Controlling the application's configuration.\n*   Exploiting a vulnerability that allows them to specify the random number generator.\n\n**Mitigation or fix:**\n\nThe following steps were taken to mitigate the vulnerability:\n\n1.  **Switch to `Crypt::URandom`:** The `rand` provider was updated to use `Crypt::URandom::urandom` instead of Perl's internal `rand` function. This provides a more secure random number generation mechanism.\n2.  **Move `rand` and `egd` to low strength list:** The `rand` and `egd` providers were moved to the low strength provider list.\n3.  **Default to strong randomness:** The code now defaults to using strong randomness (using `/dev/urandom` or `Crypt::URandom::urandom`) if the `Strength` parameter is not explicitly specified.\n4.  **Added Win32API Provider:** A new Win32API Provider was added for Windows.\n5.  **Documentation update:** The documentation for `rand` explicitly states that it is *not* cryptographically secure and recommends using other modules for security-sensitive applications.\n\n**Additional details:**\n\n*   The commit messages indicate a broader effort to modernize the `Crypt::Random` module, including moving to `Dist::Zilla` for building, adding GitHub Actions for testing, and updating copyright information.\n*   The perldoc.perl.org documentation for `rand` also explicitly warns against using it in security-sensitive situations and lists alternative modules for cryptographically secure random number generation.\n\n**Note:** This analysis is based solely on the provided content. The official CVE description may contain additional details or context.",
  "similar_info": {
    "cwe_distribution": {},
    "cwe_consensus": "",
    "similarity_stats": {
      "thresholds": [],
      "total_samples_by_threshold": {},
      "top_cwes_by_threshold": {}
    }
  },
  "similarity_summary": {
    "consensus_cwe": "",
    "top_cwes": [],
    "confidence_levels": {},
    "total_samples": 0
  },
  "analysis": "# Summary\n| CWE ID | CWE Name | Confidence | CWE Abstraction Level | CWE Vulnerability Mapping Label | CWE-Vulnerability Mapping Notes |\n|---|---|---|---|---|---|\n| CWE-338 | Use of Cryptographically Weak Pseudo-Random Number Generator (PRNG) | 0.9 | Base | Primary CWE | Allowed |\n| CWE-330 | Use of Insufficiently Random Values | 0.7 | Class | Secondary Candidate | Discouraged |\n\n## Evidence and Confidence\n\n*   **Confidence Score:** 0.9\n*   **Evidence Strength:** HIGH\n\n## Relationship Analysis\nThe primary CWE is CWE-338 which is a child of CWE-330. Choosing CWE-338 provides a more specific classification than its parent.\n\n```mermaid\ngraph TD\n    cwe338[\"CWE-338: Use of Cryptographically Weak Pseudo-Random Number Generator (PRNG)\"]\n    cwe330[\"CWE-330: Use of Insufficiently Random Values\"]\n    \n    cwe338 -->|CHILDOF| cwe330\n    \n    classDef primary fill:#f96,stroke:#333,stroke-width:2px\n    classDef secondary fill:#69f,stroke:#333\n    class cwe338 primary\n    class cwe330 secondary\n```\n\n## Vulnerability Chain\nThe vulnerability chain starts with the **use of rand() function** which is **insecure CryptRandomrand provider**. This results in the use of a cryptographically weak PRNG.\n\n## Summary of Analysis\nThe analysis is based on the provided vulnerability description and CVE reference content. The description explicitly mentions the **use of rand() function**, which is not cryptographically strong, leading to the selection of CWE-338. The CVE reference confirms this by stating the root cause is the use of a non-cryptographically secure random number generator. This evidence supports the choice of CWE-338 as the primary weakness. The retriever results also list CWE-338 with a high score, further validating the choice. CWE-338 is at the Base level of abstraction, which is preferred.\n\nRelevant CWE Information:\n\n# Enhanced Context (25 CWEs)\nThe following CWEs were identified as potentially relevant to this vulnerability:\n\n## CWE-338: Use of Cryptographically Weak Pseudo-Random Number Generator (PRNG)\n**Abstraction Level**: Base\n**Similarity Score**: 0.83\n**Source**: dense\n\n**Description**:\nThe product uses a Pseudo-Random Number Generator (PRNG) in a security context, but the PRNG's algorithm is not cryptographically strong.\n\n**Mapping Guidance**:\n- Usage: Allowed\n- Rationale: This CWE entry is at the Base level of abstraction, which is a preferred level of abstraction for mapping to the root causes of vulnerabilities.\n\n**Relationships**:\n- CHILDOF -> CWE-330\n- CHILDOF -> CWE-330\n- PARENTOF -> CWE-338\n\n## CWE-330: Use of Insufficiently Random Values\n**Abstraction Level**: Class\n**Similarity Score**: 0.80\n**Source**: dense\n\n**Description**:\nThe product uses insufficiently random numbers or values in a security context that depends on unpredictable numbers.\n\n**Mapping Guidance**:\n- Usage: Discouraged\n- Rationale: This CWE entry is a level-1 Class (i.e., a child of a Pillar). It might have lower-level children that would be more appropriate\n\n**Relationships**:\n- PARENTOF -> CWE-804\n- CHILDOF -> CWE-1390\n- CHILDOF -> CWE-863\n- CHILDOF -> CWE-331\n- CHILDOF -> CWE-331\n- CHILDOF -> CWE-335\n- CHILDOF -> CWE-335\n- CHILDOF -> CWE-338\n- CHILDOF -> CWE-338\n- CHILDOF -> CWE-1204\n- CHILDOF -> CWE-1204\n- PARENTOF -> CWE-330\n- PARENTOF -> CWE-330\n\n### Detailed Analysis of Selected CWEs:\n\n*   **CWE-338: Use of Cryptographically Weak Pseudo-Random Number Generator (PRNG)**\n    *   **Explanation:** The vulnerability description explicitly states that the `rand()` function, used by the CryptRandom Perl package, is not cryptographically strong. This directly aligns with the definition of CWE-338, which focuses on the use of PRNGs that are inadequate for security-sensitive contexts.\n    *   **Security Implications:** Using a weak PRNG can lead to predictable or biased random numbers, compromising cryptographic operations that rely on randomness. This can result in weakened encryption, predictable keys, and potential compromise of security protocols.\n    *   **Relationships:** CWE-338 is a child of CWE-330 (Use of Insufficiently Random Values). While CWE-330 is more general, CWE-338 is more specific because it explicitly refers to cryptographic contexts and PRNGs.\n    *   **Mapping Guidance:** The mapping guidance for CWE-338 allows its use, and the rationale states that it is at the Base level of abstraction.\n    *   **Evidence:** \"CryptRandom Perl package 1.05 through 1.55 may use rand() function, which is not cryptographically strong, for cryptographic functions.\"\n    *   **Confidence:** 0.9\n\n*   **CWE-330: Use of Insufficiently Random Values**\n    *   **Explanation:** This CWE broadly covers the use of values that are not random enough for their intended purpose. While the primary issue is the use of a cryptographically weak PRNG, CWE-330 could be considered as a broader categorization.\n    *   **Security Implications:** If random values are predictable, attackers can potentially bypass security mechanisms that rely on unpredictability, such as generating session IDs, nonces, or salts.\n    *   **Relationships:** CWE-330 is a parent of CWE-338.\n    *   **Mapping Guidance:** The mapping guidance for CWE-330 discourages its use directly because it might have more specific children.\n    *   **Evidence:** The problem is the **use of rand() function** for cryptographic functions, so the the random values are not sufficiently random.\n    *   **Confidence:** 0.7\n\n### CWEs Considered but Not Used:\n\n*   **CWE-335: Incorrect Usage of Seeds in Pseudo-Random Number Generator (PRNG):** While the vulnerability involves a PRNG, there is no specific mention of incorrect seed usage. The primary issue is the weakness of the `rand()` function itself, not how it's seeded.\n*   **CWE-1204: Generation of Weak Initialization Vector (IV):** The vulnerability description does not mention initialization vectors directly. While a weak PRNG *could* lead to weak IVs, the description focuses on the PRNG itself, not its specific application to IV generation.\n*   **CWE-327: Use of a Broken or Risky Cryptographic Algorithm:** This is too broad. The specific issue is the PRNG, not a general cryptographic algorithm.\n*   **CWE-1391: Use of Weak Credentials:** Not relevant as the vulnerability doesn't involve credentials.\n*   **CWE-347: Improper Verification of Cryptographic Signature:** Not relevant as the vulnerability doesn't involve cryptographic signatures.\n*   **CWE-95: Improper Neutralization of Directives in Dynamically Evaluated Code ('Eval Injection'):** Not relevant.\n*   **CWE-1241: Use of Predictable Algorithm in Random Number Generator:** This is similar to CWE-338, but CWE-338 is more specific to *cryptographically weak* PRNGs.\n*   **CWE-208: Observable Timing Discrepancy:** Not relevant.",
  "analysis_with_relationships": "# Summary\n| CWE ID | CWE Name | Confidence | CWE Abstraction Level | CWE Vulnerability Mapping Label | CWE-Vulnerability Mapping Notes |\n|---|---|---|---|---|---|\n| CWE-338 | Use of Cryptographically Weak Pseudo-Random Number Generator (PRNG) | 0.9 | Base | Primary CWE | Allowed |\n| CWE-330 | Use of Insufficiently Random Values | 0.7 | Class | Secondary Candidate | Discouraged |\n\n## Evidence and Confidence\n\n*   **Confidence Score:** 0.9\n*   **Evidence Strength:** HIGH\n\n## Relationship Analysis\nThe primary CWE is CWE-338 which is a child of CWE-330. Choosing CWE-338 provides a more specific classification than its parent.\n\n```mermaid\ngraph TD\n    cwe338[\"CWE-338: Use of Cryptographically Weak Pseudo-Random Number Generator (PRNG)\"]\n    cwe330[\"CWE-330: Use of Insufficiently Random Values\"]\n    \n    cwe338 -->|CHILDOF| cwe330\n    \n    classDef primary fill:#f96,stroke:#333,stroke-width:2px\n    classDef secondary fill:#69f,stroke:#333\n    class cwe338 primary\n    class cwe330 secondary\n```\n\n## Vulnerability Chain\nThe vulnerability chain starts with the **use of rand() function** which is **insecure CryptRandomrand provider**. This results in the use of a cryptographically weak PRNG.\n\n## Summary of Analysis\nThe analysis is based on the provided vulnerability description and CVE reference content. The description explicitly mentions the **use of rand() function**, which is not cryptographically strong, leading to the selection of CWE-338. The CVE reference confirms this by stating the root cause is the use of a non-cryptographically secure random number generator. This evidence supports the choice of CWE-338 as the primary weakness. The retriever results also list CWE-338 with a high score, further validating the choice. CWE-338 is at the Base level of abstraction, which is preferred.\n\nRelevant CWE Information:\n\n# Enhanced Context (25 CWEs)\nThe following CWEs were identified as potentially relevant to this vulnerability:\n\n## CWE-338: Use of Cryptographically Weak Pseudo-Random Number Generator (PRNG)\n**Abstraction Level**: Base\n**Similarity Score**: 0.83\n**Source**: dense\n\n**Description**:\nThe product uses a Pseudo-Random Number Generator (PRNG) in a security context, but the PRNG's algorithm is not cryptographically strong.\n\n**Mapping Guidance**:\n- Usage: Allowed\n- Rationale: This CWE entry is at the Base level of abstraction, which is a preferred level of abstraction for mapping to the root causes of vulnerabilities.\n\n**Relationships**:\n- CHILDOF -> CWE-330\n- CHILDOF -> CWE-330\n- PARENTOF -> CWE-338\n\n## CWE-330: Use of Insufficiently Random Values\n**Abstraction Level**: Class\n**Similarity Score**: 0.80\n**Source**: dense\n\n**Description**:\nThe product uses insufficiently random numbers or values in a security context that depends on unpredictable numbers.\n\n**Mapping Guidance**:\n- Usage: Discouraged\n- Rationale: This CWE entry is a level-1 Class (i.e., a child of a Pillar). It might have lower-level children that would be more appropriate\n\n**Relationships**:\n- PARENTOF -> CWE-804\n- CHILDOF -> CWE-1390\n- CHILDOF -> CWE-863\n- CHILDOF -> CWE-331\n- CHILDOF -> CWE-331\n- CHILDOF -> CWE-335\n- CHILDOF -> CWE-335\n- CHILDOF -> CWE-338\n- CHILDOF -> CWE-338\n- CHILDOF -> CWE-1204\n- CHILDOF -> CWE-1204\n- PARENTOF -> CWE-330\n- PARENTOF -> CWE-330\n\n### Detailed Analysis of Selected CWEs:\n\n*   **CWE-338: Use of Cryptographically Weak Pseudo-Random Number Generator (PRNG)**\n    *   **Explanation:** The vulnerability description explicitly states that the `rand()` function, used by the CryptRandom Perl package, is not cryptographically strong. This directly aligns with the definition of CWE-338, which focuses on the use of PRNGs that are inadequate for security-sensitive contexts.\n    *   **Security Implications:** Using a weak PRNG can lead to predictable or biased random numbers, compromising cryptographic operations that rely on randomness. This can result in weakened encryption, predictable keys, and potential compromise of security protocols.\n    *   **Relationships:** CWE-338 is a child of CWE-330 (Use of Insufficiently Random Values). While CWE-330 is more general, CWE-338 is more specific because it explicitly refers to cryptographic contexts and PRNGs.\n    *   **Mapping Guidance:** The mapping guidance for CWE-338 allows its use, and the rationale states that it is at the Base level of abstraction.\n    *   **Evidence:** \"CryptRandom Perl package 1.05 through 1.55 may use rand() function, which is not cryptographically strong, for cryptographic functions.\"\n    *   **Confidence:** 0.9\n\n*   **CWE-330: Use of Insufficiently Random Values**\n    *   **Explanation:** This CWE broadly covers the use of values that are not random enough for their intended purpose. While the primary issue is the use of a cryptographically weak PRNG, CWE-330 could be considered as a broader categorization.\n    *   **Security Implications:** If random values are predictable, attackers can potentially bypass security mechanisms that rely on unpredictability, such as generating session IDs, nonces, or salts.\n    *   **Relationships:** CWE-330 is a parent of CWE-338.\n    *   **Mapping Guidance:** The mapping guidance for CWE-330 discourages its use directly because it might have more specific children.\n    *   **Evidence:** The problem is the **use of rand() function** for cryptographic functions, so the the random values are not sufficiently random.\n    *   **Confidence:** 0.7\n\n### CWEs Considered but Not Used:\n\n*   **CWE-335: Incorrect Usage of Seeds in Pseudo-Random Number Generator (PRNG):** While the vulnerability involves a PRNG, there is no specific mention of incorrect seed usage. The primary issue is the weakness of the `rand()` function itself, not how it's seeded.\n*   **CWE-1204: Generation of Weak Initialization Vector (IV):** The vulnerability description does not mention initialization vectors directly. While a weak PRNG *could* lead to weak IVs, the description focuses on the PRNG itself, not its specific application to IV generation.\n*   **CWE-327: Use of a Broken or Risky Cryptographic Algorithm:** This is too broad. The specific issue is the PRNG, not a general cryptographic algorithm.\n*   **CWE-1391: Use of Weak Credentials:** Not relevant as the vulnerability doesn't involve credentials.\n*   **CWE-347: Improper Verification of Cryptographic Signature:** Not relevant as the vulnerability doesn't involve cryptographic signatures.\n*   **CWE-95: Improper Neutralization of Directives in Dynamically Evaluated Code ('Eval Injection'):** Not relevant.\n*   **CWE-1241: Use of Predictable Algorithm in Random Number Generator:** This is similar to CWE-338, but CWE-338 is more specific to *cryptographically weak* PRNGs.\n*   **CWE-208: Observable Timing Discrepancy:** Not relevant.\n\n\n## CWE Relationship Analysis\n\nCurrent CWEs represent these abstraction levels: .\n\n\n### Vulnerability Chain Analysis\n\n**Chain starting from CWE-1390:**\n- 1390 (Weak Authentication) - ROOT\n\n\n**Chain starting from CWE-863:**\n- 863 (Incorrect Authorization) - ROOT\n\n\n\n### CWE Relationship Diagram\n\n```mermaid\ngraph TD\n    classDef primary fill:#f96,stroke:#333,stroke-width:2px\n    classDef secondary fill:#69f,stroke:#333\n    classDef tertiary fill:#9e9,stroke:#333\n```",
  "criticism": "",
  "resolution": "",
  "relevant_cwes": [
    {
      "metadata": {
        "doc_id": "338",
        "name": "Use of Cryptographically Weak Pseudo-Random Number Generator (PRNG)",
        "source": "sparse"
      },
      "similarity": 373.8561723871081
    },
    {
      "metadata": {
        "doc_id": "335",
        "name": "Incorrect Usage of Seeds in Pseudo-Random Number Generator (PRNG)",
        "source": "sparse"
      },
      "similarity": 342.22244121717756
    },
    {
      "metadata": {
        "doc_id": "1204",
        "name": "Generation of Weak Initialization Vector (IV)",
        "source": "sparse"
      },
      "similarity": 330.124102901362
    },
    {
      "metadata": {
        "doc_id": "327",
        "name": "Use of a Broken or Risky Cryptographic Algorithm",
        "source": "sparse"
      },
      "similarity": 328.2023813483419
    },
    {
      "metadata": {
        "doc_id": "1391",
        "name": "Use of Weak Credentials",
        "source": "sparse"
      },
      "similarity": 326.8227568203997
    },
    {
      "metadata": {
        "doc_id": "347",
        "name": "Improper Verification of Cryptographic Signature",
        "source": "sparse"
      },
      "similarity": 316.91398857994045
    },
    {
      "metadata": {
        "doc_id": "95",
        "name": "Improper Neutralization of Directives in Dynamically Evaluated Code ('Eval Injection')",
        "source": "sparse"
      },
      "similarity": 316.48739562163684
    },
    {
      "metadata": {
        "doc_id": "330",
        "name": "Use of Insufficiently Random Values",
        "source": "sparse"
      },
      "similarity": 309.0582724861419
    },
    {
      "metadata": {
        "doc_id": "1241",
        "name": "Use of Predictable Algorithm in Random Number Generator",
        "type": "Base",
        "original_content": "The device uses an algorithm that is predictable and generates a pseudo-random number.",
        "keyphrase_source": "weakness:insecure CryptRandomrand provider",
        "source": "dense",
        "mapping_notes": {
          "usage": "Allowed",
          "rationale": "This CWE entry is at the Base level of abstraction, which is a preferred level of abstraction for mapping to the root causes of vulnerabilities.",
          "comments": "Carefully read both the name and description to ensure that this mapping is an appropriate fit. Do not try to 'force' a mapping to a lower-level Base/Variant simply to comply with this preferred level of abstraction.",
          "reasons": [
            "Acceptable-Use"
          ]
        },
        "score_info": {
          "retrievers": [
            "dense",
            "graph"
          ],
          "retriever_count": 2,
          "normalized_scores": {
            "dense": 0.5851795013315267,
            "graph": 1.6837872257909938
          }
        }
      },
      "similarity": 0.5851795013315267
    },
    {
      "doc_id": "208",
      "text": "CWE-208: Observable Timing Discrepancy",
      "score": 2.2100000000000004,
      "metadata": {
        "doc_id": "208",
        "name": "Observable Timing Discrepancy",
        "type": "base",
        "original_content": "CWE-208: Observable Timing Discrepancy",
        "relationships": [
          {
            "source_id": "208",
            "target_id": "1254",
            "label": "PARENTOF",
            "properties": {
              "ordinal": "Primary",
              "view_id": "1000"
            }
          },
          {
            "source_id": "208",
            "target_id": "327",
            "label": "CANPRECEDE",
            "properties": {
              "view_id": "1000"
            }
          },
          {
            "source_id": "208",
            "target_id": "385",
            "label": "CANPRECEDE",
            "properties": {
              "view_id": "1000"
            }
          },
          {
            "source_id": "208",
            "target_id": "203",
            "label": "CHILDOF",
            "properties": {
              "ordinal": "Primary",
              "view_id": "1000"
            }
          },
          {
            "source_id": "385",
            "target_id": "208",
            "label": "CANFOLLOW",
            "properties": {
              "view_id": "1000"
            }
          },
          {
            "source_id": "327",
            "target_id": "208",
            "label": "CANFOLLOW",
            "properties": {
              "view_id": "1000"
            }
          },
          {
            "source_id": "203",
            "target_id": "208",
            "label": "PARENTOF",
            "properties": {
              "ordinal": "Primary",
              "view_id": "1000"
            }
          },
          {
            "source_id": "1254",
            "target_id": "208",
            "label": "CHILDOF",
            "properties": {
              "ordinal": "Primary",
              "view_id": "1000"
            }
          }
        ],
        "score_components": {
          "relationship_chain": 1.0,
          "sequence_path": 1.0
        },
        "abstraction_factor": 1.3,
        "graph_path_info": {
          "path_types": [
            "relationship_chain",
            "vulnerability_sequence_forward",
            "vulnerability_sequence_backward"
          ],
          "best_paths": {
            "relationship_chain": {
              "path": [
                [
                  "327",
                  "208",
                  "CANFOLLOW"
                ]
              ],
              "score": 1.0,
              "type": "relationship_chain",
              "source": "327"
            },
            "vulnerability_sequence_forward": {
              "path": [
                [
                  "327",
                  "208",
                  "CANFOLLOW"
                ]
              ],
              "score": 0.9,
              "type": "vulnerability_sequence_forward",
              "source": "327"
            },
            "vulnerability_sequence_backward": {
              "path": [
                [
                  "208",
                  "327",
                  "CANPRECEDE"
                ]
              ],
              "score": 1.0,
              "type": "vulnerability_sequence_backward",
              "source": "327"
            }
          }
        },
        "position": "before",
        "sources": [
          "graph"
        ],
        "source": "graph",
        "mapping_notes": {
          "usage": "Allowed",
          "rationale": "This CWE entry is at the Base level of abstraction, which is a preferred level of abstraction for mapping to the root causes of vulnerabilities.",
          "comments": "Carefully read both the name and description to ensure that this mapping is an appropriate fit. Do not try to 'force' a mapping to a lower-level Base/Variant simply to comply with this preferred level of abstraction.",
          "reasons": [
            "Acceptable-Use"
          ]
        },
        "score_info": {
          "retrievers": [
            "graph"
          ],
          "retriever_count": 1,
          "normalized_scores": {
            "graph": 2.2100000000000004
          }
        }
      },
      "similarity": 2.2100000000000004
    }
  ],
  "identified_cwes": {
    "analyzer": [
      "CWE-1390",
      "CWE-863",
      "CWE-338",
      "CWE-335",
      "CWE-327",
      "CWE-330",
      "CWE-804",
      "CWE-95",
      "CWE-331",
      "CWE-1241",
      "CWE-1204",
      "CWE-347",
      "CWE-208",
      "CWE-1391"
    ],
    "critic_additional": []
  },
  "keyphrase_cwe_mapping": {}
}