{
  "vulnerability_info": "VulnerabilityInfo(cve_id='CVE-2024-32859', description='Dell Client Platform BIOS contains an **Improper Input Validation** vulnerability in an externally developed component. A high privileged attacker with local access could potentially exploit this vulnerability, leading to Code execution.', key_phrases={'rootcause': ['Improper Input Validation', 'Input Validation vulnerability'], 'weakness': '', 'impact': 'Code execution', 'vector': '', 'attacker': 'high privileged attacker with local access', 'product': 'Dell Client Platform', 'version': '', 'component': 'externally developed component'}, reference_content='```\\n{\\n  \"Root cause of vulnerability\": \"The Dell Client Platform BIOS contains an Improper Input Validation vulnerability in an externally developed component.\",\\n  \"Weaknesses/vulnerabilities present\": \"Improper Input Validation vulnerability.\",\\n  \"Impact of exploitation\": \"Successful exploitation could lead to code execution.\",\\n  \"Attack vectors\": \"Local access.\",\\n  \"Required attacker capabilities/position\": \"High privileged attacker with local access.\"\\n}\\n```', similar_info={'cwe_distribution': {95: {'cwe_counts': defaultdict(<class 'int'>, {'CWE-NVD-noinfo': 3}), 'total_samples': 3, 'distribution': [{'cwes': ['CWE-NVD-noinfo'], 'frequency': 3, 'proportion': 1.0}]}, 90: {'cwe_counts': defaultdict(<class 'int'>, {'CWE-NVD-noinfo': 4, 'CWE-20': 1}), 'total_samples': 5, 'distribution': [{'cwes': ['CWE-NVD-noinfo'], 'frequency': 4, 'proportion': 0.8}, {'cwes': ['CWE-20'], 'frequency': 1, 'proportion': 0.2}]}, 85: {'cwe_counts': defaultdict(<class 'int'>, {'CWE-NVD-noinfo': 4, 'CWE-20': 1}), 'total_samples': 5, 'distribution': [{'cwes': ['CWE-NVD-noinfo'], 'frequency': 4, 'proportion': 0.8}, {'cwes': ['CWE-20'], 'frequency': 1, 'proportion': 0.2}]}, 80: {'cwe_counts': defaultdict(<class 'int'>, {'CWE-NVD-noinfo': 4, 'CWE-20': 1}), 'total_samples': 6, 'distribution': [{'cwes': ['CWE-NVD-noinfo'], 'frequency': 4, 'proportion': 0.667}, {'cwes': ['CWE-20'], 'frequency': 1, 'proportion': 0.167}, {'cwes': [], 'frequency': 1, 'proportion': 0.167}]}, 75: {'cwe_counts': defaultdict(<class 'int'>, {'CWE-NVD-noinfo': 4, 'CWE-20': 1}), 'total_samples': 6, 'distribution': [{'cwes': ['CWE-NVD-noinfo'], 'frequency': 4, 'proportion': 0.667}, {'cwes': ['CWE-20'], 'frequency': 1, 'proportion': 0.167}, {'cwes': [], 'frequency': 1, 'proportion': 0.167}]}, 70: {'cwe_counts': defaultdict(<class 'int'>, {'CWE-NVD-noinfo': 3, 'CWE-20': 2, 'CWE-NVD-Other': 1}), 'total_samples': 6, 'distribution': [{'cwes': ['CWE-NVD-noinfo'], 'frequency': 3, 'proportion': 0.5}, {'cwes': ['CWE-20'], 'frequency': 2, 'proportion': 0.333}, {'cwes': ['CWE-NVD-Other'], 'frequency': 1, 'proportion': 0.167}]}}, 'cwe_consensus': 'CWE-NVD-noinfo', 'similarity_stats': {'thresholds': [95, 90, 85, 80, 75, 70], 'total_samples_by_threshold': {95: 3, 90: 5, 85: 5, 80: 6, 75: 6, 70: 6}, 'top_cwes_by_threshold': {95: [('CWE-NVD-noinfo', 3)], 90: [('CWE-NVD-noinfo', 4), ('CWE-20', 1)], 85: [('CWE-NVD-noinfo', 4), ('CWE-20', 1)], 80: [('CWE-NVD-noinfo', 4), ('CWE-20', 1)], 75: [('CWE-NVD-noinfo', 4), ('CWE-20', 1)], 70: [('CWE-NVD-noinfo', 3), ('CWE-20', 2), ('CWE-NVD-Other', 1)]}}, 'raw_matches': [{'similarity': 95, 'cwes': ['NVD-noinfo'], 'total': 3, 'frequency': 3, 'proportion': 1.0}, {'similarity': 90, 'cwes': ['NVD-noinfo'], 'total': 5, 'frequency': 4, 'proportion': 0.8}, {'similarity': 90, 'cwes': ['20'], 'total': 5, 'frequency': 1, 'proportion': 0.2}, {'similarity': 85, 'cwes': ['NVD-noinfo'], 'total': 5, 'frequency': 4, 'proportion': 0.8}, {'similarity': 85, 'cwes': ['20'], 'total': 5, 'frequency': 1, 'proportion': 0.2}, {'similarity': 80, 'cwes': ['NVD-noinfo'], 'total': 6, 'frequency': 4, 'proportion': 0.667}, {'similarity': 80, 'cwes': ['20'], 'total': 6, 'frequency': 1, 'proportion': 0.167}, {'similarity': 80, 'cwes': [], 'total': 6, 'frequency': 1, 'proportion': 0.167}, {'similarity': 75, 'cwes': ['NVD-noinfo'], 'total': 6, 'frequency': 4, 'proportion': 0.667}, {'similarity': 75, 'cwes': ['20'], 'total': 6, 'frequency': 1, 'proportion': 0.167}, {'similarity': 75, 'cwes': [], 'total': 6, 'frequency': 1, 'proportion': 0.167}, {'similarity': 70, 'cwes': ['NVD-noinfo'], 'total': 6, 'frequency': 3, 'proportion': 0.5}, {'similarity': 70, 'cwes': ['20'], 'total': 6, 'frequency': 2, 'proportion': 0.333}, {'similarity': 70, 'cwes': ['NVD-Other'], 'total': 6, 'frequency': 1, 'proportion': 0.167}]}, similarity_summary=SimilarityInsight(consensus_cwe='CWE-NVD-noinfo', top_cwes=[('CWE-NVD-noinfo', 22), ('CWE-20', 6), ('CWE-NVD-Other', 1)], confidence_levels={'high': [], 'medium': [], 'low': []}, total_samples=31), analysis='', analysis_with_relationships='', criticism='', resolution='', relevant_cwes=[{'metadata': {'doc_id': '20', 'name': 'Improper Input Validation', 'source': 'sparse', 'original_content': 'The product receives input or data, but it does\\n        not validate or incorrectly validates that the input has the\\n        properties that are required to process the data safely and\\n        correctly.', 'keyphrase_sources': [{'id': 'rootcause:Improper Input Validation', 'keyphrase': 'Improper Input Validation', 'type': 'rootcause'}, {'id': 'rootcause:Input Validation vulnerability', 'keyphrase': 'Input Validation vulnerability', 'type': 'rootcause'}, {'id': 'impact:Code execution', 'keyphrase': 'Code execution', 'type': 'impact'}, {'id': 'attacker:high privileged attacker with local access', 'keyphrase': 'high privileged attacker with local access', 'type': 'attacker'}, {'id': 'product:Dell Client Platform', 'keyphrase': 'Dell Client Platform', 'type': 'product'}, {'id': 'component:externally developed component', 'keyphrase': 'externally developed component', 'type': 'component'}]}, 'similarity': np.float64(218.20317161019472)}, {'metadata': {'doc_id': '119', 'name': 'Improper Restriction of Operations within the Bounds of a Memory Buffer', 'source': 'sparse', 'original_content': \"The product performs operations on a memory buffer, but it reads from or writes to a memory location outside the buffer's intended boundary. This may result in read or write operations on unexpected memory locations that could be linked to other variables, data structures, or internal program data.\", 'keyphrase_sources': [{'id': 'rootcause:Improper Input Validation', 'keyphrase': 'Improper Input Validation', 'type': 'rootcause'}, {'id': 'rootcause:Input Validation vulnerability', 'keyphrase': 'Input Validation vulnerability', 'type': 'rootcause'}, {'id': 'impact:Code execution', 'keyphrase': 'Code execution', 'type': 'impact'}, {'id': 'attacker:high privileged attacker with local access', 'keyphrase': 'high privileged attacker with local access', 'type': 'attacker'}, {'id': 'product:Dell Client Platform', 'keyphrase': 'Dell Client Platform', 'type': 'product'}, {'id': 'component:externally developed component', 'keyphrase': 'externally developed component', 'type': 'component'}]}, 'similarity': np.float64(201.61318187952278)}, {'metadata': {'doc_id': '287', 'name': 'Improper Authentication', 'source': 'sparse', 'original_content': 'When an actor claims to have a given identity, the product does not prove or insufficiently proves that the claim is correct.', 'keyphrase_sources': [{'id': 'rootcause:Improper Input Validation', 'keyphrase': 'Improper Input Validation', 'type': 'rootcause'}, {'id': 'rootcause:Input Validation vulnerability', 'keyphrase': 'Input Validation vulnerability', 'type': 'rootcause'}, {'id': 'impact:Code execution', 'keyphrase': 'Code execution', 'type': 'impact'}, {'id': 'product:Dell Client Platform', 'keyphrase': 'Dell Client Platform', 'type': 'product'}]}, 'similarity': np.float64(185.3708258375666)}, {'metadata': {'doc_id': '1285', 'name': 'Improper Validation of Specified Index, Position, or Offset in Input', 'source': 'sparse', 'original_content': 'The product receives input that is expected to specify an index, position, or offset into an indexable resource such as a buffer or file, but it does not validate or incorrectly validates that the specified index/position/offset has the required properties.', 'keyphrase_sources': [{'id': 'rootcause:Improper Input Validation', 'keyphrase': 'Improper Input Validation', 'type': 'rootcause'}]}, 'similarity': np.float64(183.90574611449907)}, {'metadata': {'doc_id': '1284', 'name': 'Improper Validation of Specified Quantity in Input', 'source': 'sparse', 'original_content': 'The product receives input that is expected to specify a quantity (such as size or length), but it does not validate or incorrectly validates that the quantity has the required properties.', 'keyphrase_sources': [{'id': 'rootcause:Improper Input Validation', 'keyphrase': 'Improper Input Validation', 'type': 'rootcause'}, {'id': 'rootcause:Input Validation vulnerability', 'keyphrase': 'Input Validation vulnerability', 'type': 'rootcause'}]}, 'similarity': np.float64(182.91492163210123)}, {'metadata': {'doc_id': '125', 'name': 'Out-of-bounds Read', 'source': 'sparse', 'original_content': 'The product reads data past the end, or before the beginning, of the intended buffer.', 'keyphrase_sources': [{'id': 'rootcause:Input Validation vulnerability', 'keyphrase': 'Input Validation vulnerability', 'type': 'rootcause'}, {'id': 'impact:Code execution', 'keyphrase': 'Code execution', 'type': 'impact'}, {'id': 'component:externally developed component', 'keyphrase': 'externally developed component', 'type': 'component'}]}, 'similarity': np.float64(180.3271366357408)}, {'metadata': {'doc_id': '250', 'name': 'Execution with Unnecessary Privileges', 'source': 'sparse', 'original_content': 'The product performs an operation at a privilege level that is higher than the minimum level required, which creates new weaknesses or amplifies the consequences of other weaknesses.', 'keyphrase_sources': [{'id': 'attacker:high privileged attacker with local access', 'keyphrase': 'high privileged attacker with local access', 'type': 'attacker'}]}, 'similarity': np.float64(84.57000819505646)}, {'metadata': {'doc_id': '269', 'name': 'Improper Privilege Management', 'source': 'sparse', 'original_content': 'The product does not properly assign, modify, track, or check privileges for an actor, creating an unintended sphere of control for that actor.', 'keyphrase_sources': [{'id': 'attacker:high privileged attacker with local access', 'keyphrase': 'high privileged attacker with local access', 'type': 'attacker'}]}, 'similarity': np.float64(83.80360448688641)}, {'metadata': {'doc_id': '200', 'name': 'Exposure of Sensitive Information to an Unauthorized Actor', 'source': 'sparse', 'original_content': 'The product exposes sensitive information to an actor that is not explicitly authorized to have access to that information.', 'keyphrase_sources': [{'id': 'product:Dell Client Platform', 'keyphrase': 'Dell Client Platform', 'type': 'product'}]}, 'similarity': np.float64(65.97280117015116)}, {'metadata': {'doc_id': '256', 'name': 'Plaintext Storage of a Password', 'source': 'sparse', 'original_content': 'Storing a password in plaintext may result in a system compromise.', 'keyphrase_sources': [{'id': 'product:Dell Client Platform', 'keyphrase': 'Dell Client Platform', 'type': 'product'}]}, 'similarity': np.float64(65.42551743004844)}, {'metadata': {'doc_id': '823', 'name': 'Use of Out-of-range Pointer Offset', 'source': 'sparse', 'original_content': 'The product performs pointer arithmetic on a valid pointer, but it uses an offset that can point outside of the intended range of valid memory locations for the resulting pointer.', 'keyphrase_sources': [{'id': 'component:externally developed component', 'keyphrase': 'externally developed component', 'type': 'component'}]}, 'similarity': np.float64(60.554712390498366)}, {'metadata': {'doc_id': '732', 'name': 'Incorrect Permission Assignment for Critical Resource', 'source': 'sparse', 'original_content': 'The product specifies permissions for a security-critical resource in a way that allows that resource to be read or modified by unintended actors.', 'keyphrase_sources': [{'id': 'impact:Code execution', 'keyphrase': 'Code execution', 'type': 'impact'}, {'id': 'attacker:high privileged attacker with local access', 'keyphrase': 'high privileged attacker with local access', 'type': 'attacker'}, {'id': 'component:externally developed component', 'keyphrase': 'externally developed component', 'type': 'component'}]}, 'similarity': np.float64(57.08241399248835)}], identified_cwes={'analyzer': [], 'critic_additional': []})",
  "retrieval_results": {
    "has_multiple_keyphrases": true,
    "keyphrase_cwe_sets": {
      "rootcause:Improper Input Validation": {
        "keyphrase": "Improper Input Validation",
        "type": "rootcause",
        "cwes": [
          {
            "metadata": {
              "doc_id": "20",
              "name": "Improper Input Validation",
              "source": "sparse",
              "original_content": "The product receives input or data, but it does\n        not validate or incorrectly validates that the input has the\n        properties that are required to process the data safely and\n        correctly.",
              "keyphrase_sources": [
                {
                  "id": "rootcause:Improper Input Validation",
                  "keyphrase": "Improper Input Validation",
                  "type": "rootcause"
                },
                {
                  "id": "rootcause:Input Validation vulnerability",
                  "keyphrase": "Input Validation vulnerability",
                  "type": "rootcause"
                },
                {
                  "id": "impact:Code execution",
                  "keyphrase": "Code execution",
                  "type": "impact"
                },
                {
                  "id": "attacker:high privileged attacker with local access",
                  "keyphrase": "high privileged attacker with local access",
                  "type": "attacker"
                },
                {
                  "id": "product:Dell Client Platform",
                  "keyphrase": "Dell Client Platform",
                  "type": "product"
                },
                {
                  "id": "component:externally developed component",
                  "keyphrase": "externally developed component",
                  "type": "component"
                }
              ]
            },
            "similarity": 218.20317161019472
          },
          {
            "metadata": {
              "doc_id": "119",
              "name": "Improper Restriction of Operations within the Bounds of a Memory Buffer",
              "source": "sparse",
              "original_content": "The product performs operations on a memory buffer, but it reads from or writes to a memory location outside the buffer's intended boundary. This may result in read or write operations on unexpected memory locations that could be linked to other variables, data structures, or internal program data.",
              "keyphrase_sources": [
                {
                  "id": "rootcause:Improper Input Validation",
                  "keyphrase": "Improper Input Validation",
                  "type": "rootcause"
                },
                {
                  "id": "rootcause:Input Validation vulnerability",
                  "keyphrase": "Input Validation vulnerability",
                  "type": "rootcause"
                },
                {
                  "id": "impact:Code execution",
                  "keyphrase": "Code execution",
                  "type": "impact"
                },
                {
                  "id": "attacker:high privileged attacker with local access",
                  "keyphrase": "high privileged attacker with local access",
                  "type": "attacker"
                },
                {
                  "id": "product:Dell Client Platform",
                  "keyphrase": "Dell Client Platform",
                  "type": "product"
                },
                {
                  "id": "component:externally developed component",
                  "keyphrase": "externally developed component",
                  "type": "component"
                }
              ]
            },
            "similarity": 201.61318187952278
          },
          {
            "metadata": {
              "doc_id": "287",
              "name": "Improper Authentication",
              "source": "sparse",
              "original_content": "When an actor claims to have a given identity, the product does not prove or insufficiently proves that the claim is correct.",
              "keyphrase_sources": [
                {
                  "id": "rootcause:Improper Input Validation",
                  "keyphrase": "Improper Input Validation",
                  "type": "rootcause"
                },
                {
                  "id": "rootcause:Input Validation vulnerability",
                  "keyphrase": "Input Validation vulnerability",
                  "type": "rootcause"
                },
                {
                  "id": "impact:Code execution",
                  "keyphrase": "Code execution",
                  "type": "impact"
                },
                {
                  "id": "product:Dell Client Platform",
                  "keyphrase": "Dell Client Platform",
                  "type": "product"
                }
              ]
            },
            "similarity": 185.3708258375666
          },
          {
            "metadata": {
              "doc_id": "1285",
              "name": "Improper Validation of Specified Index, Position, or Offset in Input",
              "source": "sparse",
              "original_content": "The product receives input that is expected to specify an index, position, or offset into an indexable resource such as a buffer or file, but it does not validate or incorrectly validates that the specified index/position/offset has the required properties.",
              "keyphrase_sources": [
                {
                  "id": "rootcause:Improper Input Validation",
                  "keyphrase": "Improper Input Validation",
                  "type": "rootcause"
                }
              ]
            },
            "similarity": 183.90574611449907
          },
          {
            "metadata": {
              "doc_id": "1284",
              "name": "Improper Validation of Specified Quantity in Input",
              "source": "sparse",
              "original_content": "The product receives input that is expected to specify a quantity (such as size or length), but it does not validate or incorrectly validates that the quantity has the required properties.",
              "keyphrase_sources": [
                {
                  "id": "rootcause:Improper Input Validation",
                  "keyphrase": "Improper Input Validation",
                  "type": "rootcause"
                },
                {
                  "id": "rootcause:Input Validation vulnerability",
                  "keyphrase": "Input Validation vulnerability",
                  "type": "rootcause"
                }
              ]
            },
            "similarity": 182.91492163210123
          }
        ]
      },
      "rootcause:Input Validation vulnerability": {
        "keyphrase": "Input Validation vulnerability",
        "type": "rootcause",
        "cwes": [
          {
            "metadata": {
              "doc_id": "20",
              "name": "Improper Input Validation",
              "source": "sparse",
              "original_content": "The product receives input or data, but it does\n        not validate or incorrectly validates that the input has the\n        properties that are required to process the data safely and\n        correctly."
            },
            "similarity": 213.4501930927603
          },
          {
            "metadata": {
              "doc_id": "119",
              "name": "Improper Restriction of Operations within the Bounds of a Memory Buffer",
              "source": "sparse",
              "original_content": "The product performs operations on a memory buffer, but it reads from or writes to a memory location outside the buffer's intended boundary. This may result in read or write operations on unexpected memory locations that could be linked to other variables, data structures, or internal program data."
            },
            "similarity": 197.14863054565663
          },
          {
            "metadata": {
              "doc_id": "287",
              "name": "Improper Authentication",
              "source": "sparse",
              "original_content": "When an actor claims to have a given identity, the product does not prove or insufficiently proves that the claim is correct."
            },
            "similarity": 180.70175217664448
          },
          {
            "metadata": {
              "doc_id": "125",
              "name": "Out-of-bounds Read",
              "source": "sparse",
              "original_content": "The product reads data past the end, or before the beginning, of the intended buffer.",
              "keyphrase_sources": [
                {
                  "id": "rootcause:Input Validation vulnerability",
                  "keyphrase": "Input Validation vulnerability",
                  "type": "rootcause"
                },
                {
                  "id": "impact:Code execution",
                  "keyphrase": "Code execution",
                  "type": "impact"
                },
                {
                  "id": "component:externally developed component",
                  "keyphrase": "externally developed component",
                  "type": "component"
                }
              ]
            },
            "similarity": 180.3271366357408
          },
          {
            "metadata": {
              "doc_id": "1284",
              "name": "Improper Validation of Specified Quantity in Input",
              "source": "sparse",
              "original_content": "The product receives input that is expected to specify a quantity (such as size or length), but it does not validate or incorrectly validates that the quantity has the required properties."
            },
            "similarity": 179.86001176783145
          }
        ]
      },
      "impact:Code execution": {
        "keyphrase": "Code execution",
        "type": "impact",
        "cwes": [
          {
            "metadata": {
              "doc_id": "119",
              "name": "Improper Restriction of Operations within the Bounds of a Memory Buffer",
              "source": "sparse",
              "original_content": "The product performs operations on a memory buffer, but it reads from or writes to a memory location outside the buffer's intended boundary. This may result in read or write operations on unexpected memory locations that could be linked to other variables, data structures, or internal program data."
            },
            "similarity": 67.51837915789119
          },
          {
            "metadata": {
              "doc_id": "20",
              "name": "Improper Input Validation",
              "source": "sparse",
              "original_content": "The product receives input or data, but it does\n        not validate or incorrectly validates that the input has the\n        properties that are required to process the data safely and\n        correctly."
            },
            "similarity": 63.8503398093384
          },
          {
            "metadata": {
              "doc_id": "125",
              "name": "Out-of-bounds Read",
              "source": "sparse",
              "original_content": "The product reads data past the end, or before the beginning, of the intended buffer."
            },
            "similarity": 59.26356473569381
          },
          {
            "metadata": {
              "doc_id": "287",
              "name": "Improper Authentication",
              "source": "sparse",
              "original_content": "When an actor claims to have a given identity, the product does not prove or insufficiently proves that the claim is correct."
            },
            "similarity": 57.15203479922007
          },
          {
            "metadata": {
              "doc_id": "732",
              "name": "Incorrect Permission Assignment for Critical Resource",
              "source": "sparse",
              "original_content": "The product specifies permissions for a security-critical resource in a way that allows that resource to be read or modified by unintended actors.",
              "keyphrase_sources": [
                {
                  "id": "impact:Code execution",
                  "keyphrase": "Code execution",
                  "type": "impact"
                },
                {
                  "id": "attacker:high privileged attacker with local access",
                  "keyphrase": "high privileged attacker with local access",
                  "type": "attacker"
                },
                {
                  "id": "component:externally developed component",
                  "keyphrase": "externally developed component",
                  "type": "component"
                }
              ]
            },
            "similarity": 57.08241399248835
          }
        ]
      },
      "attacker:high privileged attacker with local access": {
        "keyphrase": "high privileged attacker with local access",
        "type": "attacker",
        "cwes": [
          {
            "metadata": {
              "doc_id": "119",
              "name": "Improper Restriction of Operations within the Bounds of a Memory Buffer",
              "source": "sparse",
              "original_content": "The product performs operations on a memory buffer, but it reads from or writes to a memory location outside the buffer's intended boundary. This may result in read or write operations on unexpected memory locations that could be linked to other variables, data structures, or internal program data."
            },
            "similarity": 96.61286693794204
          },
          {
            "metadata": {
              "doc_id": "732",
              "name": "Incorrect Permission Assignment for Critical Resource",
              "source": "sparse",
              "original_content": "The product specifies permissions for a security-critical resource in a way that allows that resource to be read or modified by unintended actors."
            },
            "similarity": 86.6204117931752
          },
          {
            "metadata": {
              "doc_id": "20",
              "name": "Improper Input Validation",
              "source": "sparse",
              "original_content": "The product receives input or data, but it does\n        not validate or incorrectly validates that the input has the\n        properties that are required to process the data safely and\n        correctly."
            },
            "similarity": 86.39330042298
          },
          {
            "metadata": {
              "doc_id": "250",
              "name": "Execution with Unnecessary Privileges",
              "source": "sparse",
              "original_content": "The product performs an operation at a privilege level that is higher than the minimum level required, which creates new weaknesses or amplifies the consequences of other weaknesses.",
              "keyphrase_sources": [
                {
                  "id": "attacker:high privileged attacker with local access",
                  "keyphrase": "high privileged attacker with local access",
                  "type": "attacker"
                }
              ]
            },
            "similarity": 84.57000819505646
          },
          {
            "metadata": {
              "doc_id": "269",
              "name": "Improper Privilege Management",
              "source": "sparse",
              "original_content": "The product does not properly assign, modify, track, or check privileges for an actor, creating an unintended sphere of control for that actor.",
              "keyphrase_sources": [
                {
                  "id": "attacker:high privileged attacker with local access",
                  "keyphrase": "high privileged attacker with local access",
                  "type": "attacker"
                }
              ]
            },
            "similarity": 83.80360448688641
          }
        ]
      },
      "product:Dell Client Platform": {
        "keyphrase": "Dell Client Platform",
        "type": "product",
        "cwes": [
          {
            "metadata": {
              "doc_id": "119",
              "name": "Improper Restriction of Operations within the Bounds of a Memory Buffer",
              "source": "sparse",
              "original_content": "The product performs operations on a memory buffer, but it reads from or writes to a memory location outside the buffer's intended boundary. This may result in read or write operations on unexpected memory locations that could be linked to other variables, data structures, or internal program data."
            },
            "similarity": 74.6737033687721
          },
          {
            "metadata": {
              "doc_id": "20",
              "name": "Improper Input Validation",
              "source": "sparse",
              "original_content": "The product receives input or data, but it does\n        not validate or incorrectly validates that the input has the\n        properties that are required to process the data safely and\n        correctly."
            },
            "similarity": 67.84784159831445
          },
          {
            "metadata": {
              "doc_id": "200",
              "name": "Exposure of Sensitive Information to an Unauthorized Actor",
              "source": "sparse",
              "original_content": "The product exposes sensitive information to an actor that is not explicitly authorized to have access to that information.",
              "keyphrase_sources": [
                {
                  "id": "product:Dell Client Platform",
                  "keyphrase": "Dell Client Platform",
                  "type": "product"
                }
              ]
            },
            "similarity": 65.97280117015116
          },
          {
            "metadata": {
              "doc_id": "256",
              "name": "Plaintext Storage of a Password",
              "source": "sparse",
              "original_content": "Storing a password in plaintext may result in a system compromise.",
              "keyphrase_sources": [
                {
                  "id": "product:Dell Client Platform",
                  "keyphrase": "Dell Client Platform",
                  "type": "product"
                }
              ]
            },
            "similarity": 65.42551743004844
          },
          {
            "metadata": {
              "doc_id": "287",
              "name": "Improper Authentication",
              "source": "sparse",
              "original_content": "When an actor claims to have a given identity, the product does not prove or insufficiently proves that the claim is correct."
            },
            "similarity": 63.58372378734395
          }
        ]
      },
      "component:externally developed component": {
        "keyphrase": "externally developed component",
        "type": "component",
        "cwes": [
          {
            "metadata": {
              "doc_id": "119",
              "name": "Improper Restriction of Operations within the Bounds of a Memory Buffer",
              "source": "sparse",
              "original_content": "The product performs operations on a memory buffer, but it reads from or writes to a memory location outside the buffer's intended boundary. This may result in read or write operations on unexpected memory locations that could be linked to other variables, data structures, or internal program data."
            },
            "similarity": 63.454318209570744
          },
          {
            "metadata": {
              "doc_id": "20",
              "name": "Improper Input Validation",
              "source": "sparse",
              "original_content": "The product receives input or data, but it does\n        not validate or incorrectly validates that the input has the\n        properties that are required to process the data safely and\n        correctly."
            },
            "similarity": 61.06699318016742
          },
          {
            "metadata": {
              "doc_id": "823",
              "name": "Use of Out-of-range Pointer Offset",
              "source": "sparse",
              "original_content": "The product performs pointer arithmetic on a valid pointer, but it uses an offset that can point outside of the intended range of valid memory locations for the resulting pointer.",
              "keyphrase_sources": [
                {
                  "id": "component:externally developed component",
                  "keyphrase": "externally developed component",
                  "type": "component"
                }
              ]
            },
            "similarity": 60.554712390498366
          },
          {
            "metadata": {
              "doc_id": "125",
              "name": "Out-of-bounds Read",
              "source": "sparse",
              "original_content": "The product reads data past the end, or before the beginning, of the intended buffer."
            },
            "similarity": 59.23980332063308
          },
          {
            "metadata": {
              "doc_id": "732",
              "name": "Incorrect Permission Assignment for Critical Resource",
              "source": "sparse",
              "original_content": "The product specifies permissions for a security-critical resource in a way that allows that resource to be read or modified by unintended actors."
            },
            "similarity": 58.0625461455744
          }
        ]
      }
    },
    "keyphrase_mapping": {
      "20": [
        {
          "id": "rootcause:Improper Input Validation",
          "keyphrase": "Improper Input Validation",
          "type": "rootcause"
        },
        {
          "id": "rootcause:Input Validation vulnerability",
          "keyphrase": "Input Validation vulnerability",
          "type": "rootcause"
        },
        {
          "id": "impact:Code execution",
          "keyphrase": "Code execution",
          "type": "impact"
        },
        {
          "id": "attacker:high privileged attacker with local access",
          "keyphrase": "high privileged attacker with local access",
          "type": "attacker"
        },
        {
          "id": "product:Dell Client Platform",
          "keyphrase": "Dell Client Platform",
          "type": "product"
        },
        {
          "id": "component:externally developed component",
          "keyphrase": "externally developed component",
          "type": "component"
        }
      ],
      "119": [
        {
          "id": "rootcause:Improper Input Validation",
          "keyphrase": "Improper Input Validation",
          "type": "rootcause"
        },
        {
          "id": "rootcause:Input Validation vulnerability",
          "keyphrase": "Input Validation vulnerability",
          "type": "rootcause"
        },
        {
          "id": "impact:Code execution",
          "keyphrase": "Code execution",
          "type": "impact"
        },
        {
          "id": "attacker:high privileged attacker with local access",
          "keyphrase": "high privileged attacker with local access",
          "type": "attacker"
        },
        {
          "id": "product:Dell Client Platform",
          "keyphrase": "Dell Client Platform",
          "type": "product"
        },
        {
          "id": "component:externally developed component",
          "keyphrase": "externally developed component",
          "type": "component"
        }
      ],
      "287": [
        {
          "id": "rootcause:Improper Input Validation",
          "keyphrase": "Improper Input Validation",
          "type": "rootcause"
        },
        {
          "id": "rootcause:Input Validation vulnerability",
          "keyphrase": "Input Validation vulnerability",
          "type": "rootcause"
        },
        {
          "id": "impact:Code execution",
          "keyphrase": "Code execution",
          "type": "impact"
        },
        {
          "id": "product:Dell Client Platform",
          "keyphrase": "Dell Client Platform",
          "type": "product"
        }
      ],
      "1285": [
        {
          "id": "rootcause:Improper Input Validation",
          "keyphrase": "Improper Input Validation",
          "type": "rootcause"
        }
      ],
      "1284": [
        {
          "id": "rootcause:Improper Input Validation",
          "keyphrase": "Improper Input Validation",
          "type": "rootcause"
        },
        {
          "id": "rootcause:Input Validation vulnerability",
          "keyphrase": "Input Validation vulnerability",
          "type": "rootcause"
        }
      ],
      "125": [
        {
          "id": "rootcause:Input Validation vulnerability",
          "keyphrase": "Input Validation vulnerability",
          "type": "rootcause"
        },
        {
          "id": "impact:Code execution",
          "keyphrase": "Code execution",
          "type": "impact"
        },
        {
          "id": "component:externally developed component",
          "keyphrase": "externally developed component",
          "type": "component"
        }
      ],
      "732": [
        {
          "id": "impact:Code execution",
          "keyphrase": "Code execution",
          "type": "impact"
        },
        {
          "id": "attacker:high privileged attacker with local access",
          "keyphrase": "high privileged attacker with local access",
          "type": "attacker"
        },
        {
          "id": "component:externally developed component",
          "keyphrase": "externally developed component",
          "type": "component"
        }
      ],
      "250": [
        {
          "id": "attacker:high privileged attacker with local access",
          "keyphrase": "high privileged attacker with local access",
          "type": "attacker"
        }
      ],
      "269": [
        {
          "id": "attacker:high privileged attacker with local access",
          "keyphrase": "high privileged attacker with local access",
          "type": "attacker"
        }
      ],
      "200": [
        {
          "id": "product:Dell Client Platform",
          "keyphrase": "Dell Client Platform",
          "type": "product"
        }
      ],
      "256": [
        {
          "id": "product:Dell Client Platform",
          "keyphrase": "Dell Client Platform",
          "type": "product"
        }
      ],
      "823": [
        {
          "id": "component:externally developed component",
          "keyphrase": "externally developed component",
          "type": "component"
        }
      ]
    },
    "relevant_cwes": [
      {
        "metadata": {
          "doc_id": "20",
          "name": "Improper Input Validation",
          "source": "sparse",
          "original_content": "The product receives input or data, but it does\n        not validate or incorrectly validates that the input has the\n        properties that are required to process the data safely and\n        correctly.",
          "keyphrase_sources": [
            {
              "id": "rootcause:Improper Input Validation",
              "keyphrase": "Improper Input Validation",
              "type": "rootcause"
            },
            {
              "id": "rootcause:Input Validation vulnerability",
              "keyphrase": "Input Validation vulnerability",
              "type": "rootcause"
            },
            {
              "id": "impact:Code execution",
              "keyphrase": "Code execution",
              "type": "impact"
            },
            {
              "id": "attacker:high privileged attacker with local access",
              "keyphrase": "high privileged attacker with local access",
              "type": "attacker"
            },
            {
              "id": "product:Dell Client Platform",
              "keyphrase": "Dell Client Platform",
              "type": "product"
            },
            {
              "id": "component:externally developed component",
              "keyphrase": "externally developed component",
              "type": "component"
            }
          ]
        },
        "similarity": 218.20317161019472
      },
      {
        "metadata": {
          "doc_id": "119",
          "name": "Improper Restriction of Operations within the Bounds of a Memory Buffer",
          "source": "sparse",
          "original_content": "The product performs operations on a memory buffer, but it reads from or writes to a memory location outside the buffer's intended boundary. This may result in read or write operations on unexpected memory locations that could be linked to other variables, data structures, or internal program data.",
          "keyphrase_sources": [
            {
              "id": "rootcause:Improper Input Validation",
              "keyphrase": "Improper Input Validation",
              "type": "rootcause"
            },
            {
              "id": "rootcause:Input Validation vulnerability",
              "keyphrase": "Input Validation vulnerability",
              "type": "rootcause"
            },
            {
              "id": "impact:Code execution",
              "keyphrase": "Code execution",
              "type": "impact"
            },
            {
              "id": "attacker:high privileged attacker with local access",
              "keyphrase": "high privileged attacker with local access",
              "type": "attacker"
            },
            {
              "id": "product:Dell Client Platform",
              "keyphrase": "Dell Client Platform",
              "type": "product"
            },
            {
              "id": "component:externally developed component",
              "keyphrase": "externally developed component",
              "type": "component"
            }
          ]
        },
        "similarity": 201.61318187952278
      },
      {
        "metadata": {
          "doc_id": "287",
          "name": "Improper Authentication",
          "source": "sparse",
          "original_content": "When an actor claims to have a given identity, the product does not prove or insufficiently proves that the claim is correct.",
          "keyphrase_sources": [
            {
              "id": "rootcause:Improper Input Validation",
              "keyphrase": "Improper Input Validation",
              "type": "rootcause"
            },
            {
              "id": "rootcause:Input Validation vulnerability",
              "keyphrase": "Input Validation vulnerability",
              "type": "rootcause"
            },
            {
              "id": "impact:Code execution",
              "keyphrase": "Code execution",
              "type": "impact"
            },
            {
              "id": "product:Dell Client Platform",
              "keyphrase": "Dell Client Platform",
              "type": "product"
            }
          ]
        },
        "similarity": 185.3708258375666
      },
      {
        "metadata": {
          "doc_id": "1285",
          "name": "Improper Validation of Specified Index, Position, or Offset in Input",
          "source": "sparse",
          "original_content": "The product receives input that is expected to specify an index, position, or offset into an indexable resource such as a buffer or file, but it does not validate or incorrectly validates that the specified index/position/offset has the required properties.",
          "keyphrase_sources": [
            {
              "id": "rootcause:Improper Input Validation",
              "keyphrase": "Improper Input Validation",
              "type": "rootcause"
            }
          ]
        },
        "similarity": 183.90574611449907
      },
      {
        "metadata": {
          "doc_id": "1284",
          "name": "Improper Validation of Specified Quantity in Input",
          "source": "sparse",
          "original_content": "The product receives input that is expected to specify a quantity (such as size or length), but it does not validate or incorrectly validates that the quantity has the required properties.",
          "keyphrase_sources": [
            {
              "id": "rootcause:Improper Input Validation",
              "keyphrase": "Improper Input Validation",
              "type": "rootcause"
            },
            {
              "id": "rootcause:Input Validation vulnerability",
              "keyphrase": "Input Validation vulnerability",
              "type": "rootcause"
            }
          ]
        },
        "similarity": 182.91492163210123
      },
      {
        "metadata": {
          "doc_id": "125",
          "name": "Out-of-bounds Read",
          "source": "sparse",
          "original_content": "The product reads data past the end, or before the beginning, of the intended buffer.",
          "keyphrase_sources": [
            {
              "id": "rootcause:Input Validation vulnerability",
              "keyphrase": "Input Validation vulnerability",
              "type": "rootcause"
            },
            {
              "id": "impact:Code execution",
              "keyphrase": "Code execution",
              "type": "impact"
            },
            {
              "id": "component:externally developed component",
              "keyphrase": "externally developed component",
              "type": "component"
            }
          ]
        },
        "similarity": 180.3271366357408
      },
      {
        "metadata": {
          "doc_id": "250",
          "name": "Execution with Unnecessary Privileges",
          "source": "sparse",
          "original_content": "The product performs an operation at a privilege level that is higher than the minimum level required, which creates new weaknesses or amplifies the consequences of other weaknesses.",
          "keyphrase_sources": [
            {
              "id": "attacker:high privileged attacker with local access",
              "keyphrase": "high privileged attacker with local access",
              "type": "attacker"
            }
          ]
        },
        "similarity": 84.57000819505646
      },
      {
        "metadata": {
          "doc_id": "269",
          "name": "Improper Privilege Management",
          "source": "sparse",
          "original_content": "The product does not properly assign, modify, track, or check privileges for an actor, creating an unintended sphere of control for that actor.",
          "keyphrase_sources": [
            {
              "id": "attacker:high privileged attacker with local access",
              "keyphrase": "high privileged attacker with local access",
              "type": "attacker"
            }
          ]
        },
        "similarity": 83.80360448688641
      },
      {
        "metadata": {
          "doc_id": "200",
          "name": "Exposure of Sensitive Information to an Unauthorized Actor",
          "source": "sparse",
          "original_content": "The product exposes sensitive information to an actor that is not explicitly authorized to have access to that information.",
          "keyphrase_sources": [
            {
              "id": "product:Dell Client Platform",
              "keyphrase": "Dell Client Platform",
              "type": "product"
            }
          ]
        },
        "similarity": 65.97280117015116
      },
      {
        "metadata": {
          "doc_id": "256",
          "name": "Plaintext Storage of a Password",
          "source": "sparse",
          "original_content": "Storing a password in plaintext may result in a system compromise.",
          "keyphrase_sources": [
            {
              "id": "product:Dell Client Platform",
              "keyphrase": "Dell Client Platform",
              "type": "product"
            }
          ]
        },
        "similarity": 65.42551743004844
      },
      {
        "metadata": {
          "doc_id": "823",
          "name": "Use of Out-of-range Pointer Offset",
          "source": "sparse",
          "original_content": "The product performs pointer arithmetic on a valid pointer, but it uses an offset that can point outside of the intended range of valid memory locations for the resulting pointer.",
          "keyphrase_sources": [
            {
              "id": "component:externally developed component",
              "keyphrase": "externally developed component",
              "type": "component"
            }
          ]
        },
        "similarity": 60.554712390498366
      },
      {
        "metadata": {
          "doc_id": "732",
          "name": "Incorrect Permission Assignment for Critical Resource",
          "source": "sparse",
          "original_content": "The product specifies permissions for a security-critical resource in a way that allows that resource to be read or modified by unintended actors.",
          "keyphrase_sources": [
            {
              "id": "impact:Code execution",
              "keyphrase": "Code execution",
              "type": "impact"
            },
            {
              "id": "attacker:high privileged attacker with local access",
              "keyphrase": "high privileged attacker with local access",
              "type": "attacker"
            },
            {
              "id": "component:externally developed component",
              "keyphrase": "externally developed component",
              "type": "component"
            }
          ]
        },
        "similarity": 57.08241399248835
      }
    ],
    "enhanced_query": "# Vulnerability Description\n\n    Dell Client Platform BIOS contains an **Improper Input Validation** vulnerability in an externally developed component. A high privileged attacker with local access could potentially exploit this vulnerability, leading to Code execution.\n\n    # Keyphrase-Specific CWE Analysis\n    This vulnerability contains multiple keyphrases that may map to different CWEs. \n    Please analyze each keyphrase separately and determine the most appropriate CWE(s) for each.\n\n    ## ROOTCAUSE: 'Improper Input Validation'\n\nRelevant CWEs for this ROOTCAUSE:\n\n### 1. CWE-20: Improper Input Validation (Score: 218.20)\n\nThe product receives input or data, but it does\n        not validate or incorrectly validates that the input has the\n        properties that are required to process the data safely and\n        correctly....\n\n### 2. CWE-119: Improper Restriction of Operations within the Bounds of a Memory Buffer (Score: 201.61)\n\nThe product performs operations on a memory buffer, but it reads from or writes to a memory location outside the buffer's intended boundary. This may result in read or write operations on unexpected memory locations that could be linked to other variables, data structures, or internal program data....\n\n### 3. CWE-287: Improper Authentication (Score: 185.37)\n\nWhen an actor claims to have a given identity, the product does not prove or insufficiently proves that the claim is correct....\n\n### 4. CWE-1285: Improper Validation of Specified Index, Position, or Offset in Input (Score: 183.91)\n\nThe product receives input that is expected to specify an index, position, or offset into an indexable resource such as a buffer or file, but it does not validate or incorrectly validates that the specified index/position/offset has the required properties....\n\n### 5. CWE-1284: Improper Validation of Specified Quantity in Input (Score: 182.91)\n\nThe product receives input that is expected to specify a quantity (such as size or length), but it does not validate or incorrectly validates that the quantity has the required properties....\n\n## ROOTCAUSE: 'Input Validation vulnerability'\n\nRelevant CWEs for this ROOTCAUSE:\n\n### 1. CWE-20: Improper Input Validation (Score: 218.20)\n\nThe product receives input or data, but it does\n        not validate or incorrectly validates that the input has the\n        properties that are required to process the data safely and\n        correctly....\n\n### 2. CWE-119: Improper Restriction of Operations within the Bounds of a Memory Buffer (Score: 201.61)\n\nThe product performs operations on a memory buffer, but it reads from or writes to a memory location outside the buffer's intended boundary. This may result in read or write operations on unexpected memory locations that could be linked to other variables, data structures, or internal program data....\n\n### 3. CWE-287: Improper Authentication (Score: 185.37)\n\nWhen an actor claims to have a given identity, the product does not prove or insufficiently proves that the claim is correct....\n\n### 4. CWE-1284: Improper Validation of Specified Quantity in Input (Score: 182.91)\n\nThe product receives input that is expected to specify a quantity (such as size or length), but it does not validate or incorrectly validates that the quantity has the required properties....\n\n### 5. CWE-125: Out-of-bounds Read (Score: 180.33)\n\nThe product reads data past the end, or before the beginning, of the intended buffer....\n\n## IMPACT: 'Code execution'\n\nRelevant CWEs for this IMPACT:\n\n### 1. CWE-20: Improper Input Validation (Score: 218.20)\n\nThe product receives input or data, but it does\n        not validate or incorrectly validates that the input has the\n        properties that are required to process the data safely and\n        correctly....\n\n### 2. CWE-119: Improper Restriction of Operations within the Bounds of a Memory Buffer (Score: 201.61)\n\nThe product performs operations on a memory buffer, but it reads from or writes to a memory location outside the buffer's intended boundary. This may result in read or write operations on unexpected memory locations that could be linked to other variables, data structures, or internal program data....\n\n### 3. CWE-287: Improper Authentication (Score: 185.37)\n\nWhen an actor claims to have a given identity, the product does not prove or insufficiently proves that the claim is correct....\n\n### 4. CWE-125: Out-of-bounds Read (Score: 180.33)\n\nThe product reads data past the end, or before the beginning, of the intended buffer....\n\n### 5. CWE-732: Incorrect Permission Assignment for Critical Resource (Score: 57.08)\n\nThe product specifies permissions for a security-critical resource in a way that allows that resource to be read or modified by unintended actors....\n\n## ATTACKER: 'high privileged attacker with local access'\n\nRelevant CWEs for this ATTACKER:\n\n### 1. CWE-20: Improper Input Validation (Score: 218.20)\n\nThe product receives input or data, but it does\n        not validate or incorrectly validates that the input has the\n        properties that are required to process the data safely and\n        correctly....\n\n### 2. CWE-119: Improper Restriction of Operations within the Bounds of a Memory Buffer (Score: 201.61)\n\nThe product performs operations on a memory buffer, but it reads from or writes to a memory location outside the buffer's intended boundary. This may result in read or write operations on unexpected memory locations that could be linked to other variables, data structures, or internal program data....\n\n### 3. CWE-250: Execution with Unnecessary Privileges (Score: 84.57)\n\nThe product performs an operation at a privilege level that is higher than the minimum level required, which creates new weaknesses or amplifies the consequences of other weaknesses....\n\n### 4. CWE-269: Improper Privilege Management (Score: 83.80)\n\nThe product does not properly assign, modify, track, or check privileges for an actor, creating an unintended sphere of control for that actor....\n\n### 5. CWE-732: Incorrect Permission Assignment for Critical Resource (Score: 57.08)\n\nThe product specifies permissions for a security-critical resource in a way that allows that resource to be read or modified by unintended actors....\n\n## PRODUCT: 'Dell Client Platform'\n\nRelevant CWEs for this PRODUCT:\n\n### 1. CWE-20: Improper Input Validation (Score: 218.20)\n\nThe product receives input or data, but it does\n        not validate or incorrectly validates that the input has the\n        properties that are required to process the data safely and\n        correctly....\n\n### 2. CWE-119: Improper Restriction of Operations within the Bounds of a Memory Buffer (Score: 201.61)\n\nThe product performs operations on a memory buffer, but it reads from or writes to a memory location outside the buffer's intended boundary. This may result in read or write operations on unexpected memory locations that could be linked to other variables, data structures, or internal program data....\n\n### 3. CWE-287: Improper Authentication (Score: 185.37)\n\nWhen an actor claims to have a given identity, the product does not prove or insufficiently proves that the claim is correct....\n\n### 4. CWE-200: Exposure of Sensitive Information to an Unauthorized Actor (Score: 65.97)\n\nThe product exposes sensitive information to an actor that is not explicitly authorized to have access to that information....\n\n### 5. CWE-256: Plaintext Storage of a Password (Score: 65.43)\n\nStoring a password in plaintext may result in a system compromise....\n\n## COMPONENT: 'externally developed component'\n\nRelevant CWEs for this COMPONENT:\n\n### 1. CWE-20: Improper Input Validation (Score: 218.20)\n\nThe product receives input or data, but it does\n        not validate or incorrectly validates that the input has the\n        properties that are required to process the data safely and\n        correctly....\n\n### 2. CWE-119: Improper Restriction of Operations within the Bounds of a Memory Buffer (Score: 201.61)\n\nThe product performs operations on a memory buffer, but it reads from or writes to a memory location outside the buffer's intended boundary. This may result in read or write operations on unexpected memory locations that could be linked to other variables, data structures, or internal program data....\n\n### 3. CWE-125: Out-of-bounds Read (Score: 180.33)\n\nThe product reads data past the end, or before the beginning, of the intended buffer....\n\n### 4. CWE-823: Use of Out-of-range Pointer Offset (Score: 60.55)\n\nThe product performs pointer arithmetic on a valid pointer, but it uses an offset that can point outside of the intended range of valid memory locations for the resulting pointer....\n\n### 5. CWE-732: Incorrect Permission Assignment for Critical Resource (Score: 57.08)\n\nThe product specifies permissions for a security-critical resource in a way that allows that resource to be read or modified by unintended actors....\n\n\n    # Analysis Instructions\n    1. For each keyphrase, identify the most appropriate CWE(s) that represent the weakness.\n    2. Consider how the different keyphrases might relate to each other in the vulnerability chain.\n    3. Provide a final determination of primary CWE(s) and any secondary CWEs.\n    4. Format your response using the standard analysis template.\n\n    Please analyze how these different weaknesses interact and provide a comprehensive CWE classification.\n    "
  },
  "retrieval_time": 1.8731980323791504
}