{
  "vulnerability_info": "VulnerabilityInfo(cve_id='CVE-2024-31201', description='A **CWE-428 Unquoted Search Path or Element** affects the ThermoscanIP_Scrutation service. Such **misconfiguration** could be abused in scenarios where **incorrect permissions** were assigned to the C\\\\ path to attempt a privilege escalation on the local machine.', key_phrases={'rootcause': ['CWE-428 Unquoted Search Path or Element', 'misconfiguration'], 'weakness': 'incorrect permissions', 'impact': 'privilege escalation', 'vector': '', 'attacker': '', 'product': 'ThermoscanIP_Scrutation service', 'version': '', 'component': 'C path'}, reference_content='Based on the provided content, here\\'s a breakdown of the vulnerability:\\n\\n**Root Cause of Vulnerability:**\\n- The root cause is an \"Unquoted Search Path or Element\" vulnerability (CWE-428) in the ThermoscanIP_Scrutation service. This means that the service attempts to load or execute a program or library using a search path that is not enclosed in quotation marks.\\n\\n**Weaknesses/Vulnerabilities Present:**\\n- **Unquoted Search Path:** The primary vulnerability is the use of an unquoted search path, allowing an attacker to inject malicious files into the search path.\\n- **Incorrect Permissions:** The vulnerability is exploitable when incorrect permissions are assigned to the C:\\\\ path, allowing the attacker to place a malicious executable in that path.\\n\\n**Impact of Exploitation:**\\n- **Privilege Escalation:** Successful exploitation can lead to privilege escalation, granting the attacker the highest level of privileges on the local machine (NT AUTHORITY\\\\SYSTEM).\\n\\n**Attack Vectors:**\\n- The vulnerability is local, requiring the attacker to have access to the target system.\\n- The attack involves placing a malicious executable in a directory within the unquoted search path that will be executed by the vulnerable service.\\n\\n**Required Attacker Capabilities/Position:**\\n- The attacker needs to have at least high privileges on the system, as indicated by \"PR:H\" in the CVSS vector. They also need to have a user interface interaction indicated by \"UI:R\".\\n- The attacker must be able to write files to locations within the search path (e.g., C:\\\\ if the permissions are misconfigured)\\n- The attacker must be able to initiate the execution of the vulnerable service in order for the malicious file to be executed.\\n\\n**Additional Notes:**\\n- The vulnerability is dependent on end-user misconfiguration (incorrect permissions on C:\\\\). It is not enabled by default in Windows, but could be a result of improper setup.\\n- There is no official patch from the vendor for this vulnerability.\\n- The recommended solutions and mitigations include implementing strict access controls and regular log reviews', similar_info={'cwe_distribution': {}, 'cwe_consensus': '', 'similarity_stats': {'thresholds': [], 'total_samples_by_threshold': {}, 'top_cwes_by_threshold': {}}}, similarity_summary=SimilarityInsight(consensus_cwe='', top_cwes=[], confidence_levels={}, total_samples=0), analysis='', analysis_with_relationships='', criticism='', resolution='', relevant_cwes=[{'metadata': {'doc_id': '428', 'name': 'Unquoted Search Path or Element', 'source': 'sparse', 'original_content': 'The product uses a search path that contains an unquoted element, in which the element contains whitespace or other separators. This can cause the product to access resources in a parent path.', 'keyphrase_sources': [{'id': 'rootcause:CWE-428 Unquoted Search Path or Element', 'keyphrase': 'CWE-428 Unquoted Search Path or Element', 'type': 'rootcause'}, {'id': 'rootcause:misconfiguration', 'keyphrase': 'misconfiguration', 'type': 'rootcause'}, {'id': 'weakness:incorrect permissions', 'keyphrase': 'incorrect permissions', 'type': 'weakness'}, {'id': 'impact:privilege escalation', 'keyphrase': 'privilege escalation', 'type': 'impact'}, {'id': 'product:ThermoscanIP_Scrutation service', 'keyphrase': 'ThermoscanIP_Scrutation service', 'type': 'product'}, {'id': 'component:C path', 'keyphrase': 'C path', 'type': 'component'}]}, 'similarity': np.float64(516.0748576587849)}, {'metadata': {'doc_id': '426', 'name': 'Untrusted Search Path', 'source': 'sparse', 'original_content': \"The product searches for critical resources using an externally-supplied search path that can point to resources that are not under the product's direct control.\", 'keyphrase_sources': [{'id': 'rootcause:CWE-428 Unquoted Search Path or Element', 'keyphrase': 'CWE-428 Unquoted Search Path or Element', 'type': 'rootcause'}, {'id': 'rootcause:misconfiguration', 'keyphrase': 'misconfiguration', 'type': 'rootcause'}, {'id': 'weakness:incorrect permissions', 'keyphrase': 'incorrect permissions', 'type': 'weakness'}, {'id': 'impact:privilege escalation', 'keyphrase': 'privilege escalation', 'type': 'impact'}, {'id': 'product:ThermoscanIP_Scrutation service', 'keyphrase': 'ThermoscanIP_Scrutation service', 'type': 'product'}, {'id': 'component:C path', 'keyphrase': 'C path', 'type': 'component'}]}, 'similarity': np.float64(352.9007286009371)}, {'metadata': {'doc_id': '427', 'name': 'Uncontrolled Search Path Element', 'source': 'sparse', 'original_content': 'The product uses a fixed or controlled search path to find resources, but one or more locations in that path can be under the control of unintended actors.', 'keyphrase_sources': [{'id': 'rootcause:CWE-428 Unquoted Search Path or Element', 'keyphrase': 'CWE-428 Unquoted Search Path or Element', 'type': 'rootcause'}, {'id': 'rootcause:misconfiguration', 'keyphrase': 'misconfiguration', 'type': 'rootcause'}, {'id': 'weakness:incorrect permissions', 'keyphrase': 'incorrect permissions', 'type': 'weakness'}, {'id': 'impact:privilege escalation', 'keyphrase': 'privilege escalation', 'type': 'impact'}, {'id': 'product:ThermoscanIP_Scrutation service', 'keyphrase': 'ThermoscanIP_Scrutation service', 'type': 'product'}, {'id': 'component:C path', 'keyphrase': 'C path', 'type': 'component'}]}, 'similarity': np.float64(346.29063743353066)}, {'metadata': {'doc_id': '697', 'name': 'Incorrect Comparison', 'source': 'sparse', 'original_content': 'The product compares two entities in a security-relevant context, but the comparison is incorrect, which may lead to resultant weaknesses.', 'keyphrase_sources': [{'id': 'rootcause:CWE-428 Unquoted Search Path or Element', 'keyphrase': 'CWE-428 Unquoted Search Path or Element', 'type': 'rootcause'}]}, 'similarity': np.float64(297.24279251347343)}, {'metadata': {'doc_id': '1419', 'name': 'Incorrect Initialization of Resource', 'source': 'sparse', 'original_content': 'The product attempts to initialize a resource but does not correctly do so, which might leave the resource in an unexpected, incorrect, or insecure state when it is accessed.', 'keyphrase_sources': [{'id': 'rootcause:CWE-428 Unquoted Search Path or Element', 'keyphrase': 'CWE-428 Unquoted Search Path or Element', 'type': 'rootcause'}]}, 'similarity': np.float64(284.0473904664767)}, {'metadata': {'doc_id': '732', 'name': 'Incorrect Permission Assignment for Critical Resource', 'source': 'sparse', 'original_content': 'The product specifies permissions for a security-critical resource in a way that allows that resource to be read or modified by unintended actors.', 'keyphrase_sources': [{'id': 'rootcause:misconfiguration', 'keyphrase': 'misconfiguration', 'type': 'rootcause'}, {'id': 'weakness:incorrect permissions', 'keyphrase': 'incorrect permissions', 'type': 'weakness'}, {'id': 'impact:privilege escalation', 'keyphrase': 'privilege escalation', 'type': 'impact'}, {'id': 'product:ThermoscanIP_Scrutation service', 'keyphrase': 'ThermoscanIP_Scrutation service', 'type': 'product'}, {'id': 'component:C path', 'keyphrase': 'C path', 'type': 'component'}]}, 'similarity': np.float64(210.77305607286812)}, {'metadata': {'doc_id': '276', 'name': 'Incorrect Default Permissions', 'source': 'sparse', 'original_content': 'During installation, installed file permissions are set to allow anyone to modify those files.', 'keyphrase_sources': [{'id': 'rootcause:misconfiguration', 'keyphrase': 'misconfiguration', 'type': 'rootcause'}, {'id': 'weakness:incorrect permissions', 'keyphrase': 'incorrect permissions', 'type': 'weakness'}, {'id': 'impact:privilege escalation', 'keyphrase': 'privilege escalation', 'type': 'impact'}, {'id': 'product:ThermoscanIP_Scrutation service', 'keyphrase': 'ThermoscanIP_Scrutation service', 'type': 'product'}]}, 'similarity': np.float64(200.7069377377008)}, {'metadata': {'doc_id': '278', 'name': 'Insecure Preserved Inherited Permissions', 'source': 'sparse', 'original_content': 'A product inherits a set of insecure permissions for an object, e.g. when copying from an archive file, without user awareness or involvement.', 'keyphrase_sources': [{'id': 'component:C path', 'keyphrase': 'C path', 'type': 'component'}]}, 'similarity': np.float64(74.86528890200734)}], identified_cwes={'analyzer': [], 'critic_additional': []})",
  "retrieval_results": {
    "has_multiple_keyphrases": true,
    "keyphrase_cwe_sets": {
      "rootcause:CWE-428 Unquoted Search Path or Element": {
        "keyphrase": "CWE-428 Unquoted Search Path or Element",
        "type": "rootcause",
        "cwes": [
          {
            "metadata": {
              "doc_id": "428",
              "name": "Unquoted Search Path or Element",
              "source": "sparse",
              "original_content": "The product uses a search path that contains an unquoted element, in which the element contains whitespace or other separators. This can cause the product to access resources in a parent path.",
              "keyphrase_sources": [
                {
                  "id": "rootcause:CWE-428 Unquoted Search Path or Element",
                  "keyphrase": "CWE-428 Unquoted Search Path or Element",
                  "type": "rootcause"
                },
                {
                  "id": "rootcause:misconfiguration",
                  "keyphrase": "misconfiguration",
                  "type": "rootcause"
                },
                {
                  "id": "weakness:incorrect permissions",
                  "keyphrase": "incorrect permissions",
                  "type": "weakness"
                },
                {
                  "id": "impact:privilege escalation",
                  "keyphrase": "privilege escalation",
                  "type": "impact"
                },
                {
                  "id": "product:ThermoscanIP_Scrutation service",
                  "keyphrase": "ThermoscanIP_Scrutation service",
                  "type": "product"
                },
                {
                  "id": "component:C path",
                  "keyphrase": "C path",
                  "type": "component"
                }
              ]
            },
            "similarity": 516.0748576587849
          },
          {
            "metadata": {
              "doc_id": "426",
              "name": "Untrusted Search Path",
              "source": "sparse",
              "original_content": "The product searches for critical resources using an externally-supplied search path that can point to resources that are not under the product's direct control.",
              "keyphrase_sources": [
                {
                  "id": "rootcause:CWE-428 Unquoted Search Path or Element",
                  "keyphrase": "CWE-428 Unquoted Search Path or Element",
                  "type": "rootcause"
                },
                {
                  "id": "rootcause:misconfiguration",
                  "keyphrase": "misconfiguration",
                  "type": "rootcause"
                },
                {
                  "id": "weakness:incorrect permissions",
                  "keyphrase": "incorrect permissions",
                  "type": "weakness"
                },
                {
                  "id": "impact:privilege escalation",
                  "keyphrase": "privilege escalation",
                  "type": "impact"
                },
                {
                  "id": "product:ThermoscanIP_Scrutation service",
                  "keyphrase": "ThermoscanIP_Scrutation service",
                  "type": "product"
                },
                {
                  "id": "component:C path",
                  "keyphrase": "C path",
                  "type": "component"
                }
              ]
            },
            "similarity": 352.9007286009371
          },
          {
            "metadata": {
              "doc_id": "427",
              "name": "Uncontrolled Search Path Element",
              "source": "sparse",
              "original_content": "The product uses a fixed or controlled search path to find resources, but one or more locations in that path can be under the control of unintended actors.",
              "keyphrase_sources": [
                {
                  "id": "rootcause:CWE-428 Unquoted Search Path or Element",
                  "keyphrase": "CWE-428 Unquoted Search Path or Element",
                  "type": "rootcause"
                },
                {
                  "id": "rootcause:misconfiguration",
                  "keyphrase": "misconfiguration",
                  "type": "rootcause"
                },
                {
                  "id": "weakness:incorrect permissions",
                  "keyphrase": "incorrect permissions",
                  "type": "weakness"
                },
                {
                  "id": "impact:privilege escalation",
                  "keyphrase": "privilege escalation",
                  "type": "impact"
                },
                {
                  "id": "product:ThermoscanIP_Scrutation service",
                  "keyphrase": "ThermoscanIP_Scrutation service",
                  "type": "product"
                },
                {
                  "id": "component:C path",
                  "keyphrase": "C path",
                  "type": "component"
                }
              ]
            },
            "similarity": 346.29063743353066
          },
          {
            "metadata": {
              "doc_id": "697",
              "name": "Incorrect Comparison",
              "source": "sparse",
              "original_content": "The product compares two entities in a security-relevant context, but the comparison is incorrect, which may lead to resultant weaknesses.",
              "keyphrase_sources": [
                {
                  "id": "rootcause:CWE-428 Unquoted Search Path or Element",
                  "keyphrase": "CWE-428 Unquoted Search Path or Element",
                  "type": "rootcause"
                }
              ]
            },
            "similarity": 297.24279251347343
          },
          {
            "metadata": {
              "doc_id": "1419",
              "name": "Incorrect Initialization of Resource",
              "source": "sparse",
              "original_content": "The product attempts to initialize a resource but does not correctly do so, which might leave the resource in an unexpected, incorrect, or insecure state when it is accessed.",
              "keyphrase_sources": [
                {
                  "id": "rootcause:CWE-428 Unquoted Search Path or Element",
                  "keyphrase": "CWE-428 Unquoted Search Path or Element",
                  "type": "rootcause"
                }
              ]
            },
            "similarity": 284.0473904664767
          }
        ]
      },
      "rootcause:misconfiguration": {
        "keyphrase": "misconfiguration",
        "type": "rootcause",
        "cwes": [
          {
            "metadata": {
              "doc_id": "428",
              "name": "Unquoted Search Path or Element",
              "source": "sparse",
              "original_content": "The product uses a search path that contains an unquoted element, in which the element contains whitespace or other separators. This can cause the product to access resources in a parent path."
            },
            "similarity": 265.3871003685131
          },
          {
            "metadata": {
              "doc_id": "426",
              "name": "Untrusted Search Path",
              "source": "sparse",
              "original_content": "The product searches for critical resources using an externally-supplied search path that can point to resources that are not under the product's direct control."
            },
            "similarity": 246.15598224595223
          },
          {
            "metadata": {
              "doc_id": "427",
              "name": "Uncontrolled Search Path Element",
              "source": "sparse",
              "original_content": "The product uses a fixed or controlled search path to find resources, but one or more locations in that path can be under the control of unintended actors."
            },
            "similarity": 228.44744506651386
          },
          {
            "metadata": {
              "doc_id": "732",
              "name": "Incorrect Permission Assignment for Critical Resource",
              "source": "sparse",
              "original_content": "The product specifies permissions for a security-critical resource in a way that allows that resource to be read or modified by unintended actors.",
              "keyphrase_sources": [
                {
                  "id": "rootcause:misconfiguration",
                  "keyphrase": "misconfiguration",
                  "type": "rootcause"
                },
                {
                  "id": "weakness:incorrect permissions",
                  "keyphrase": "incorrect permissions",
                  "type": "weakness"
                },
                {
                  "id": "impact:privilege escalation",
                  "keyphrase": "privilege escalation",
                  "type": "impact"
                },
                {
                  "id": "product:ThermoscanIP_Scrutation service",
                  "keyphrase": "ThermoscanIP_Scrutation service",
                  "type": "product"
                },
                {
                  "id": "component:C path",
                  "keyphrase": "C path",
                  "type": "component"
                }
              ]
            },
            "similarity": 210.77305607286812
          },
          {
            "metadata": {
              "doc_id": "276",
              "name": "Incorrect Default Permissions",
              "source": "sparse",
              "original_content": "During installation, installed file permissions are set to allow anyone to modify those files.",
              "keyphrase_sources": [
                {
                  "id": "rootcause:misconfiguration",
                  "keyphrase": "misconfiguration",
                  "type": "rootcause"
                },
                {
                  "id": "weakness:incorrect permissions",
                  "keyphrase": "incorrect permissions",
                  "type": "weakness"
                },
                {
                  "id": "impact:privilege escalation",
                  "keyphrase": "privilege escalation",
                  "type": "impact"
                },
                {
                  "id": "product:ThermoscanIP_Scrutation service",
                  "keyphrase": "ThermoscanIP_Scrutation service",
                  "type": "product"
                }
              ]
            },
            "similarity": 200.7069377377008
          }
        ]
      },
      "weakness:incorrect permissions": {
        "keyphrase": "incorrect permissions",
        "type": "weakness",
        "cwes": [
          {
            "metadata": {
              "doc_id": "428",
              "name": "Unquoted Search Path or Element",
              "source": "sparse",
              "original_content": "The product uses a search path that contains an unquoted element, in which the element contains whitespace or other separators. This can cause the product to access resources in a parent path."
            },
            "similarity": 247.69462701061218
          },
          {
            "metadata": {
              "doc_id": "732",
              "name": "Incorrect Permission Assignment for Critical Resource",
              "source": "sparse",
              "original_content": "The product specifies permissions for a security-critical resource in a way that allows that resource to be read or modified by unintended actors."
            },
            "similarity": 229.49492913956715
          },
          {
            "metadata": {
              "doc_id": "427",
              "name": "Uncontrolled Search Path Element",
              "source": "sparse",
              "original_content": "The product uses a fixed or controlled search path to find resources, but one or more locations in that path can be under the control of unintended actors."
            },
            "similarity": 226.38339704747642
          },
          {
            "metadata": {
              "doc_id": "276",
              "name": "Incorrect Default Permissions",
              "source": "sparse",
              "original_content": "During installation, installed file permissions are set to allow anyone to modify those files."
            },
            "similarity": 221.99530170426763
          },
          {
            "metadata": {
              "doc_id": "426",
              "name": "Untrusted Search Path",
              "source": "sparse",
              "original_content": "The product searches for critical resources using an externally-supplied search path that can point to resources that are not under the product's direct control."
            },
            "similarity": 220.4516734935343
          }
        ]
      },
      "impact:privilege escalation": {
        "keyphrase": "privilege escalation",
        "type": "impact",
        "cwes": [
          {
            "metadata": {
              "doc_id": "428",
              "name": "Unquoted Search Path or Element",
              "source": "sparse",
              "original_content": "The product uses a search path that contains an unquoted element, in which the element contains whitespace or other separators. This can cause the product to access resources in a parent path."
            },
            "similarity": 97.2162009700215
          },
          {
            "metadata": {
              "doc_id": "427",
              "name": "Uncontrolled Search Path Element",
              "source": "sparse",
              "original_content": "The product uses a fixed or controlled search path to find resources, but one or more locations in that path can be under the control of unintended actors."
            },
            "similarity": 85.82890022337563
          },
          {
            "metadata": {
              "doc_id": "426",
              "name": "Untrusted Search Path",
              "source": "sparse",
              "original_content": "The product searches for critical resources using an externally-supplied search path that can point to resources that are not under the product's direct control."
            },
            "similarity": 85.56127561182448
          },
          {
            "metadata": {
              "doc_id": "732",
              "name": "Incorrect Permission Assignment for Critical Resource",
              "source": "sparse",
              "original_content": "The product specifies permissions for a security-critical resource in a way that allows that resource to be read or modified by unintended actors."
            },
            "similarity": 80.77972949380862
          },
          {
            "metadata": {
              "doc_id": "276",
              "name": "Incorrect Default Permissions",
              "source": "sparse",
              "original_content": "During installation, installed file permissions are set to allow anyone to modify those files."
            },
            "similarity": 79.08872143581827
          }
        ]
      },
      "product:ThermoscanIP_Scrutation service": {
        "keyphrase": "ThermoscanIP_Scrutation service",
        "type": "product",
        "cwes": [
          {
            "metadata": {
              "doc_id": "428",
              "name": "Unquoted Search Path or Element",
              "source": "sparse",
              "original_content": "The product uses a search path that contains an unquoted element, in which the element contains whitespace or other separators. This can cause the product to access resources in a parent path."
            },
            "similarity": 91.69031170810175
          },
          {
            "metadata": {
              "doc_id": "427",
              "name": "Uncontrolled Search Path Element",
              "source": "sparse",
              "original_content": "The product uses a fixed or controlled search path to find resources, but one or more locations in that path can be under the control of unintended actors."
            },
            "similarity": 78.17453185648688
          },
          {
            "metadata": {
              "doc_id": "426",
              "name": "Untrusted Search Path",
              "source": "sparse",
              "original_content": "The product searches for critical resources using an externally-supplied search path that can point to resources that are not under the product's direct control."
            },
            "similarity": 74.36449623495325
          },
          {
            "metadata": {
              "doc_id": "732",
              "name": "Incorrect Permission Assignment for Critical Resource",
              "source": "sparse",
              "original_content": "The product specifies permissions for a security-critical resource in a way that allows that resource to be read or modified by unintended actors."
            },
            "similarity": 72.45676805154733
          },
          {
            "metadata": {
              "doc_id": "276",
              "name": "Incorrect Default Permissions",
              "source": "sparse",
              "original_content": "During installation, installed file permissions are set to allow anyone to modify those files."
            },
            "similarity": 70.12815879554297
          }
        ]
      },
      "component:C path": {
        "keyphrase": "C path",
        "type": "component",
        "cwes": [
          {
            "metadata": {
              "doc_id": "428",
              "name": "Unquoted Search Path or Element",
              "source": "sparse",
              "original_content": "The product uses a search path that contains an unquoted element, in which the element contains whitespace or other separators. This can cause the product to access resources in a parent path."
            },
            "similarity": 103.54679088214948
          },
          {
            "metadata": {
              "doc_id": "427",
              "name": "Uncontrolled Search Path Element",
              "source": "sparse",
              "original_content": "The product uses a fixed or controlled search path to find resources, but one or more locations in that path can be under the control of unintended actors."
            },
            "similarity": 89.15612841410979
          },
          {
            "metadata": {
              "doc_id": "426",
              "name": "Untrusted Search Path",
              "source": "sparse",
              "original_content": "The product searches for critical resources using an externally-supplied search path that can point to resources that are not under the product's direct control."
            },
            "similarity": 81.85921429625238
          },
          {
            "metadata": {
              "doc_id": "732",
              "name": "Incorrect Permission Assignment for Critical Resource",
              "source": "sparse",
              "original_content": "The product specifies permissions for a security-critical resource in a way that allows that resource to be read or modified by unintended actors."
            },
            "similarity": 76.29003116821713
          },
          {
            "metadata": {
              "doc_id": "278",
              "name": "Insecure Preserved Inherited Permissions",
              "source": "sparse",
              "original_content": "A product inherits a set of insecure permissions for an object, e.g. when copying from an archive file, without user awareness or involvement.",
              "keyphrase_sources": [
                {
                  "id": "component:C path",
                  "keyphrase": "C path",
                  "type": "component"
                }
              ]
            },
            "similarity": 74.86528890200734
          }
        ]
      }
    },
    "keyphrase_mapping": {
      "428": [
        {
          "id": "rootcause:CWE-428 Unquoted Search Path or Element",
          "keyphrase": "CWE-428 Unquoted Search Path or Element",
          "type": "rootcause"
        },
        {
          "id": "rootcause:misconfiguration",
          "keyphrase": "misconfiguration",
          "type": "rootcause"
        },
        {
          "id": "weakness:incorrect permissions",
          "keyphrase": "incorrect permissions",
          "type": "weakness"
        },
        {
          "id": "impact:privilege escalation",
          "keyphrase": "privilege escalation",
          "type": "impact"
        },
        {
          "id": "product:ThermoscanIP_Scrutation service",
          "keyphrase": "ThermoscanIP_Scrutation service",
          "type": "product"
        },
        {
          "id": "component:C path",
          "keyphrase": "C path",
          "type": "component"
        }
      ],
      "426": [
        {
          "id": "rootcause:CWE-428 Unquoted Search Path or Element",
          "keyphrase": "CWE-428 Unquoted Search Path or Element",
          "type": "rootcause"
        },
        {
          "id": "rootcause:misconfiguration",
          "keyphrase": "misconfiguration",
          "type": "rootcause"
        },
        {
          "id": "weakness:incorrect permissions",
          "keyphrase": "incorrect permissions",
          "type": "weakness"
        },
        {
          "id": "impact:privilege escalation",
          "keyphrase": "privilege escalation",
          "type": "impact"
        },
        {
          "id": "product:ThermoscanIP_Scrutation service",
          "keyphrase": "ThermoscanIP_Scrutation service",
          "type": "product"
        },
        {
          "id": "component:C path",
          "keyphrase": "C path",
          "type": "component"
        }
      ],
      "427": [
        {
          "id": "rootcause:CWE-428 Unquoted Search Path or Element",
          "keyphrase": "CWE-428 Unquoted Search Path or Element",
          "type": "rootcause"
        },
        {
          "id": "rootcause:misconfiguration",
          "keyphrase": "misconfiguration",
          "type": "rootcause"
        },
        {
          "id": "weakness:incorrect permissions",
          "keyphrase": "incorrect permissions",
          "type": "weakness"
        },
        {
          "id": "impact:privilege escalation",
          "keyphrase": "privilege escalation",
          "type": "impact"
        },
        {
          "id": "product:ThermoscanIP_Scrutation service",
          "keyphrase": "ThermoscanIP_Scrutation service",
          "type": "product"
        },
        {
          "id": "component:C path",
          "keyphrase": "C path",
          "type": "component"
        }
      ],
      "697": [
        {
          "id": "rootcause:CWE-428 Unquoted Search Path or Element",
          "keyphrase": "CWE-428 Unquoted Search Path or Element",
          "type": "rootcause"
        }
      ],
      "1419": [
        {
          "id": "rootcause:CWE-428 Unquoted Search Path or Element",
          "keyphrase": "CWE-428 Unquoted Search Path or Element",
          "type": "rootcause"
        }
      ],
      "732": [
        {
          "id": "rootcause:misconfiguration",
          "keyphrase": "misconfiguration",
          "type": "rootcause"
        },
        {
          "id": "weakness:incorrect permissions",
          "keyphrase": "incorrect permissions",
          "type": "weakness"
        },
        {
          "id": "impact:privilege escalation",
          "keyphrase": "privilege escalation",
          "type": "impact"
        },
        {
          "id": "product:ThermoscanIP_Scrutation service",
          "keyphrase": "ThermoscanIP_Scrutation service",
          "type": "product"
        },
        {
          "id": "component:C path",
          "keyphrase": "C path",
          "type": "component"
        }
      ],
      "276": [
        {
          "id": "rootcause:misconfiguration",
          "keyphrase": "misconfiguration",
          "type": "rootcause"
        },
        {
          "id": "weakness:incorrect permissions",
          "keyphrase": "incorrect permissions",
          "type": "weakness"
        },
        {
          "id": "impact:privilege escalation",
          "keyphrase": "privilege escalation",
          "type": "impact"
        },
        {
          "id": "product:ThermoscanIP_Scrutation service",
          "keyphrase": "ThermoscanIP_Scrutation service",
          "type": "product"
        }
      ],
      "278": [
        {
          "id": "component:C path",
          "keyphrase": "C path",
          "type": "component"
        }
      ]
    },
    "relevant_cwes": [
      {
        "metadata": {
          "doc_id": "428",
          "name": "Unquoted Search Path or Element",
          "source": "sparse",
          "original_content": "The product uses a search path that contains an unquoted element, in which the element contains whitespace or other separators. This can cause the product to access resources in a parent path.",
          "keyphrase_sources": [
            {
              "id": "rootcause:CWE-428 Unquoted Search Path or Element",
              "keyphrase": "CWE-428 Unquoted Search Path or Element",
              "type": "rootcause"
            },
            {
              "id": "rootcause:misconfiguration",
              "keyphrase": "misconfiguration",
              "type": "rootcause"
            },
            {
              "id": "weakness:incorrect permissions",
              "keyphrase": "incorrect permissions",
              "type": "weakness"
            },
            {
              "id": "impact:privilege escalation",
              "keyphrase": "privilege escalation",
              "type": "impact"
            },
            {
              "id": "product:ThermoscanIP_Scrutation service",
              "keyphrase": "ThermoscanIP_Scrutation service",
              "type": "product"
            },
            {
              "id": "component:C path",
              "keyphrase": "C path",
              "type": "component"
            }
          ]
        },
        "similarity": 516.0748576587849
      },
      {
        "metadata": {
          "doc_id": "426",
          "name": "Untrusted Search Path",
          "source": "sparse",
          "original_content": "The product searches for critical resources using an externally-supplied search path that can point to resources that are not under the product's direct control.",
          "keyphrase_sources": [
            {
              "id": "rootcause:CWE-428 Unquoted Search Path or Element",
              "keyphrase": "CWE-428 Unquoted Search Path or Element",
              "type": "rootcause"
            },
            {
              "id": "rootcause:misconfiguration",
              "keyphrase": "misconfiguration",
              "type": "rootcause"
            },
            {
              "id": "weakness:incorrect permissions",
              "keyphrase": "incorrect permissions",
              "type": "weakness"
            },
            {
              "id": "impact:privilege escalation",
              "keyphrase": "privilege escalation",
              "type": "impact"
            },
            {
              "id": "product:ThermoscanIP_Scrutation service",
              "keyphrase": "ThermoscanIP_Scrutation service",
              "type": "product"
            },
            {
              "id": "component:C path",
              "keyphrase": "C path",
              "type": "component"
            }
          ]
        },
        "similarity": 352.9007286009371
      },
      {
        "metadata": {
          "doc_id": "427",
          "name": "Uncontrolled Search Path Element",
          "source": "sparse",
          "original_content": "The product uses a fixed or controlled search path to find resources, but one or more locations in that path can be under the control of unintended actors.",
          "keyphrase_sources": [
            {
              "id": "rootcause:CWE-428 Unquoted Search Path or Element",
              "keyphrase": "CWE-428 Unquoted Search Path or Element",
              "type": "rootcause"
            },
            {
              "id": "rootcause:misconfiguration",
              "keyphrase": "misconfiguration",
              "type": "rootcause"
            },
            {
              "id": "weakness:incorrect permissions",
              "keyphrase": "incorrect permissions",
              "type": "weakness"
            },
            {
              "id": "impact:privilege escalation",
              "keyphrase": "privilege escalation",
              "type": "impact"
            },
            {
              "id": "product:ThermoscanIP_Scrutation service",
              "keyphrase": "ThermoscanIP_Scrutation service",
              "type": "product"
            },
            {
              "id": "component:C path",
              "keyphrase": "C path",
              "type": "component"
            }
          ]
        },
        "similarity": 346.29063743353066
      },
      {
        "metadata": {
          "doc_id": "697",
          "name": "Incorrect Comparison",
          "source": "sparse",
          "original_content": "The product compares two entities in a security-relevant context, but the comparison is incorrect, which may lead to resultant weaknesses.",
          "keyphrase_sources": [
            {
              "id": "rootcause:CWE-428 Unquoted Search Path or Element",
              "keyphrase": "CWE-428 Unquoted Search Path or Element",
              "type": "rootcause"
            }
          ]
        },
        "similarity": 297.24279251347343
      },
      {
        "metadata": {
          "doc_id": "1419",
          "name": "Incorrect Initialization of Resource",
          "source": "sparse",
          "original_content": "The product attempts to initialize a resource but does not correctly do so, which might leave the resource in an unexpected, incorrect, or insecure state when it is accessed.",
          "keyphrase_sources": [
            {
              "id": "rootcause:CWE-428 Unquoted Search Path or Element",
              "keyphrase": "CWE-428 Unquoted Search Path or Element",
              "type": "rootcause"
            }
          ]
        },
        "similarity": 284.0473904664767
      },
      {
        "metadata": {
          "doc_id": "732",
          "name": "Incorrect Permission Assignment for Critical Resource",
          "source": "sparse",
          "original_content": "The product specifies permissions for a security-critical resource in a way that allows that resource to be read or modified by unintended actors.",
          "keyphrase_sources": [
            {
              "id": "rootcause:misconfiguration",
              "keyphrase": "misconfiguration",
              "type": "rootcause"
            },
            {
              "id": "weakness:incorrect permissions",
              "keyphrase": "incorrect permissions",
              "type": "weakness"
            },
            {
              "id": "impact:privilege escalation",
              "keyphrase": "privilege escalation",
              "type": "impact"
            },
            {
              "id": "product:ThermoscanIP_Scrutation service",
              "keyphrase": "ThermoscanIP_Scrutation service",
              "type": "product"
            },
            {
              "id": "component:C path",
              "keyphrase": "C path",
              "type": "component"
            }
          ]
        },
        "similarity": 210.77305607286812
      },
      {
        "metadata": {
          "doc_id": "276",
          "name": "Incorrect Default Permissions",
          "source": "sparse",
          "original_content": "During installation, installed file permissions are set to allow anyone to modify those files.",
          "keyphrase_sources": [
            {
              "id": "rootcause:misconfiguration",
              "keyphrase": "misconfiguration",
              "type": "rootcause"
            },
            {
              "id": "weakness:incorrect permissions",
              "keyphrase": "incorrect permissions",
              "type": "weakness"
            },
            {
              "id": "impact:privilege escalation",
              "keyphrase": "privilege escalation",
              "type": "impact"
            },
            {
              "id": "product:ThermoscanIP_Scrutation service",
              "keyphrase": "ThermoscanIP_Scrutation service",
              "type": "product"
            }
          ]
        },
        "similarity": 200.7069377377008
      },
      {
        "metadata": {
          "doc_id": "278",
          "name": "Insecure Preserved Inherited Permissions",
          "source": "sparse",
          "original_content": "A product inherits a set of insecure permissions for an object, e.g. when copying from an archive file, without user awareness or involvement.",
          "keyphrase_sources": [
            {
              "id": "component:C path",
              "keyphrase": "C path",
              "type": "component"
            }
          ]
        },
        "similarity": 74.86528890200734
      }
    ],
    "enhanced_query": "# Vulnerability Description\n\n    A **CWE-428 Unquoted Search Path or Element** affects the ThermoscanIP_Scrutation service. Such **misconfiguration** could be abused in scenarios where **incorrect permissions** were assigned to the C\\ path to attempt a privilege escalation on the local machine.\n\n    # Keyphrase-Specific CWE Analysis\n    This vulnerability contains multiple keyphrases that may map to different CWEs. \n    Please analyze each keyphrase separately and determine the most appropriate CWE(s) for each.\n\n    ## ROOTCAUSE: 'CWE-428 Unquoted Search Path or Element'\n\nRelevant CWEs for this ROOTCAUSE:\n\n### 1. CWE-428: Unquoted Search Path or Element (Score: 516.07)\n\nThe product uses a search path that contains an unquoted element, in which the element contains whitespace or other separators. This can cause the product to access resources in a parent path....\n\n### 2. CWE-426: Untrusted Search Path (Score: 352.90)\n\nThe product searches for critical resources using an externally-supplied search path that can point to resources that are not under the product's direct control....\n\n### 3. CWE-427: Uncontrolled Search Path Element (Score: 346.29)\n\nThe product uses a fixed or controlled search path to find resources, but one or more locations in that path can be under the control of unintended actors....\n\n### 4. CWE-697: Incorrect Comparison (Score: 297.24)\n\nThe product compares two entities in a security-relevant context, but the comparison is incorrect, which may lead to resultant weaknesses....\n\n### 5. CWE-1419: Incorrect Initialization of Resource (Score: 284.05)\n\nThe product attempts to initialize a resource but does not correctly do so, which might leave the resource in an unexpected, incorrect, or insecure state when it is accessed....\n\n## ROOTCAUSE: 'misconfiguration'\n\nRelevant CWEs for this ROOTCAUSE:\n\n### 1. CWE-428: Unquoted Search Path or Element (Score: 516.07)\n\nThe product uses a search path that contains an unquoted element, in which the element contains whitespace or other separators. This can cause the product to access resources in a parent path....\n\n### 2. CWE-426: Untrusted Search Path (Score: 352.90)\n\nThe product searches for critical resources using an externally-supplied search path that can point to resources that are not under the product's direct control....\n\n### 3. CWE-427: Uncontrolled Search Path Element (Score: 346.29)\n\nThe product uses a fixed or controlled search path to find resources, but one or more locations in that path can be under the control of unintended actors....\n\n### 4. CWE-732: Incorrect Permission Assignment for Critical Resource (Score: 210.77)\n\nThe product specifies permissions for a security-critical resource in a way that allows that resource to be read or modified by unintended actors....\n\n### 5. CWE-276: Incorrect Default Permissions (Score: 200.71)\n\nDuring installation, installed file permissions are set to allow anyone to modify those files....\n\n## WEAKNESS: 'incorrect permissions'\n\nRelevant CWEs for this WEAKNESS:\n\n### 1. CWE-428: Unquoted Search Path or Element (Score: 516.07)\n\nThe product uses a search path that contains an unquoted element, in which the element contains whitespace or other separators. This can cause the product to access resources in a parent path....\n\n### 2. CWE-426: Untrusted Search Path (Score: 352.90)\n\nThe product searches for critical resources using an externally-supplied search path that can point to resources that are not under the product's direct control....\n\n### 3. CWE-427: Uncontrolled Search Path Element (Score: 346.29)\n\nThe product uses a fixed or controlled search path to find resources, but one or more locations in that path can be under the control of unintended actors....\n\n### 4. CWE-732: Incorrect Permission Assignment for Critical Resource (Score: 210.77)\n\nThe product specifies permissions for a security-critical resource in a way that allows that resource to be read or modified by unintended actors....\n\n### 5. CWE-276: Incorrect Default Permissions (Score: 200.71)\n\nDuring installation, installed file permissions are set to allow anyone to modify those files....\n\n## IMPACT: 'privilege escalation'\n\nRelevant CWEs for this IMPACT:\n\n### 1. CWE-428: Unquoted Search Path or Element (Score: 516.07)\n\nThe product uses a search path that contains an unquoted element, in which the element contains whitespace or other separators. This can cause the product to access resources in a parent path....\n\n### 2. CWE-426: Untrusted Search Path (Score: 352.90)\n\nThe product searches for critical resources using an externally-supplied search path that can point to resources that are not under the product's direct control....\n\n### 3. CWE-427: Uncontrolled Search Path Element (Score: 346.29)\n\nThe product uses a fixed or controlled search path to find resources, but one or more locations in that path can be under the control of unintended actors....\n\n### 4. CWE-732: Incorrect Permission Assignment for Critical Resource (Score: 210.77)\n\nThe product specifies permissions for a security-critical resource in a way that allows that resource to be read or modified by unintended actors....\n\n### 5. CWE-276: Incorrect Default Permissions (Score: 200.71)\n\nDuring installation, installed file permissions are set to allow anyone to modify those files....\n\n## PRODUCT: 'ThermoscanIP_Scrutation service'\n\nRelevant CWEs for this PRODUCT:\n\n### 1. CWE-428: Unquoted Search Path or Element (Score: 516.07)\n\nThe product uses a search path that contains an unquoted element, in which the element contains whitespace or other separators. This can cause the product to access resources in a parent path....\n\n### 2. CWE-426: Untrusted Search Path (Score: 352.90)\n\nThe product searches for critical resources using an externally-supplied search path that can point to resources that are not under the product's direct control....\n\n### 3. CWE-427: Uncontrolled Search Path Element (Score: 346.29)\n\nThe product uses a fixed or controlled search path to find resources, but one or more locations in that path can be under the control of unintended actors....\n\n### 4. CWE-732: Incorrect Permission Assignment for Critical Resource (Score: 210.77)\n\nThe product specifies permissions for a security-critical resource in a way that allows that resource to be read or modified by unintended actors....\n\n### 5. CWE-276: Incorrect Default Permissions (Score: 200.71)\n\nDuring installation, installed file permissions are set to allow anyone to modify those files....\n\n## COMPONENT: 'C path'\n\nRelevant CWEs for this COMPONENT:\n\n### 1. CWE-428: Unquoted Search Path or Element (Score: 516.07)\n\nThe product uses a search path that contains an unquoted element, in which the element contains whitespace or other separators. This can cause the product to access resources in a parent path....\n\n### 2. CWE-426: Untrusted Search Path (Score: 352.90)\n\nThe product searches for critical resources using an externally-supplied search path that can point to resources that are not under the product's direct control....\n\n### 3. CWE-427: Uncontrolled Search Path Element (Score: 346.29)\n\nThe product uses a fixed or controlled search path to find resources, but one or more locations in that path can be under the control of unintended actors....\n\n### 4. CWE-732: Incorrect Permission Assignment for Critical Resource (Score: 210.77)\n\nThe product specifies permissions for a security-critical resource in a way that allows that resource to be read or modified by unintended actors....\n\n### 5. CWE-278: Insecure Preserved Inherited Permissions (Score: 74.87)\n\nA product inherits a set of insecure permissions for an object, e.g. when copying from an archive file, without user awareness or involvement....\n\n\n    # Analysis Instructions\n    1. For each keyphrase, identify the most appropriate CWE(s) that represent the weakness.\n    2. Consider how the different keyphrases might relate to each other in the vulnerability chain.\n    3. Provide a final determination of primary CWE(s) and any secondary CWEs.\n    4. Format your response using the standard analysis template.\n\n    Please analyze how these different weaknesses interact and provide a comprehensive CWE classification.\n    "
  },
  "retrieval_time": 2.027803897857666
}