{
  "vulnerability_info": "VulnerabilityInfo(cve_id='CVE-2025-32076', description='Improper **Input Validation vulnerability** in The Wikimedia Foundation Mediawiki - Visual Data Extension allows HTTP DoS.This issue affects Mediawiki - Visual Data Extension from 1.39 through 1.43.', key_phrases={'rootcause': ['Input Validation vulnerability', 'Improper Input Validation'], 'weakness': '', 'impact': 'HTTP DoS', 'vector': '', 'attacker': '', 'product': 'Wikimedia Foundation Mediawiki - Visual Data Extension', 'version': '1.39 through 1.43', 'component': ''}, reference_content=\"## CVE-2025-32076 Analysis\\n\\nThis content is directly related to CVE-2025-32076. It provides detailed information about the vulnerability.\\n\\n**Root cause of vulnerability:**\\n\\nThe vulnerability lies in a regular expression `/<\\\\s\\\\*([^<>]+)\\\\s\\\\*>/` used to process user-provided data in the `SubmitForm` function within the VisualData extension. This regex has a third-degree polynomial complexity, making it susceptible to Regular Expression Denial-of-Service (ReDoS) attacks.\\n\\n**Weaknesses/vulnerabilities present:**\\n\\n*   **Regular Expression Denial of Service (ReDoS):** The vulnerable regex can cause excessive CPU consumption when processing crafted input, leading to a denial of service.\\n\\n**Impact of exploitation:**\\n\\n*   **Denial of Service (DoS):** An attacker can craft malicious input that causes the server to spend excessive time processing the regex, potentially leading to a denial of service.\\n\\n**Attack vectors:**\\n\\n*   Providing specially crafted input containing malicious patterns that exploit the regex's complexity.\\n\\n**Required attacker capabilities/position:**\\n\\n*   An attacker needs to be able to provide user-controlled data that is processed by the vulnerable regex.\\n\\n**Mitigation or fix:**\\n\\n*   The regex was initially proposed to be fixed with a non-greedy quantifier: `/<\\\\s*([^<>]+?)\\\\s*>/`. However, this was deemed insufficient.\\n*   The fix implemented was `/<\\\\s\\\\*+([^<>]++)\\\\s\\\\*+>/`.\\n*   A separate bug was filed to address the same regex being used in `replaceFormula`.\\n*   The fix was applied in the following commits:\\n    *   [https://gerrit.wikimedia.org/r/plugins/gitiles/mediawiki/extensions/VisualData/+/fc7c0257b7d7c11f11bd750ee1225854b02ea9f5](https://gerrit.wikimedia.org/r/plugins/gitiles/mediawiki/extensions/VisualData/%2B/fc7c0257b7d7c11f11bd750ee1225854b02ea9f5)\\n    *   [https://gerrit.wikimedia.org/r/plugins/gitiles/mediawiki/extensions/VisualData/+/2b7094da7bba630fb142690379fa7049b8f1edb5%5E%21/](https://gerrit.wikimedia.org/r/plugins/gitiles/mediawiki/extensions/VisualData/%2B/2b7094da7bba630fb142690379fa7049b8f1edb5%5E%21/)\\n\\n**Additional Details (more than official CVE description):**\\n\\n*   The vulnerability affects the VisualData extension.\\n*   The issue was initially reported by R4356th.\\n*   The fix was tested and confirmed by Thomas-topway-it and Brian (Bawolff).\\n*   The vulnerability is tagged with `Vuln-DoS` and `Security`.\\n*   The issue affects Miraheze.\\n*   There was discussion about reporting the bug on the public Talk page versus Phabricator.\\n*   The use of possessive quantifiers (`++`) was discussed as part of the fix.\\n*   A related issue exists in the `replaceFormula` function.\", similar_info={'cwe_distribution': {}, 'cwe_consensus': '', 'similarity_stats': {'thresholds': [], 'total_samples_by_threshold': {}, 'top_cwes_by_threshold': {}}}, similarity_summary=SimilarityInsight(consensus_cwe='', top_cwes=[], confidence_levels={}, total_samples=0), analysis='', analysis_with_relationships='', criticism='', resolution='', relevant_cwes=[{'metadata': {'doc_id': '20', 'name': 'Improper Input Validation', 'source': 'sparse', 'original_content': 'The product receives input or data, but it does\\n        not validate or incorrectly validates that the input has the\\n        properties that are required to process the data safely and\\n        correctly.', 'keyphrase_sources': [{'id': 'rootcause:Input Validation vulnerability', 'keyphrase': 'Input Validation vulnerability', 'type': 'rootcause'}, {'id': 'rootcause:Improper Input Validation', 'keyphrase': 'Improper Input Validation', 'type': 'rootcause'}, {'id': 'impact:HTTP DoS', 'keyphrase': 'HTTP DoS', 'type': 'impact'}]}, 'similarity': np.float64(152.78790090427444)}, {'metadata': {'doc_id': '451', 'name': 'User Interface (UI) Misrepresentation of Critical Information', 'source': 'sparse', 'original_content': 'The user interface (UI) does not properly represent critical information to the user, allowing the information - or its source - to be obscured or spoofed. This is often a component in phishing attacks.', 'keyphrase_sources': [{'id': 'rootcause:Input Validation vulnerability', 'keyphrase': 'Input Validation vulnerability', 'type': 'rootcause'}, {'id': 'rootcause:Improper Input Validation', 'keyphrase': 'Improper Input Validation', 'type': 'rootcause'}, {'id': 'product:Wikimedia Foundation Mediawiki - Visual Data Extension', 'keyphrase': 'Wikimedia Foundation Mediawiki - Visual Data Extension', 'type': 'product'}]}, 'similarity': np.float64(146.51969020925807)}, {'metadata': {'doc_id': '1289', 'name': 'Improper Validation of Unsafe Equivalence in Input', 'source': 'sparse', 'original_content': 'The product receives an input value that is used as a resource identifier or other type of reference, but it does not validate or incorrectly validates that the input is equivalent to a potentially-unsafe value.', 'keyphrase_sources': [{'id': 'rootcause:Input Validation vulnerability', 'keyphrase': 'Input Validation vulnerability', 'type': 'rootcause'}, {'id': 'rootcause:Improper Input Validation', 'keyphrase': 'Improper Input Validation', 'type': 'rootcause'}, {'id': 'product:Wikimedia Foundation Mediawiki - Visual Data Extension', 'keyphrase': 'Wikimedia Foundation Mediawiki - Visual Data Extension', 'type': 'product'}]}, 'similarity': np.float64(145.23534896233457)}, {'metadata': {'doc_id': '1284', 'name': 'Improper Validation of Specified Quantity in Input', 'source': 'sparse', 'original_content': 'The product receives input that is expected to specify a quantity (such as size or length), but it does not validate or incorrectly validates that the quantity has the required properties.', 'keyphrase_sources': [{'id': 'rootcause:Input Validation vulnerability', 'keyphrase': 'Input Validation vulnerability', 'type': 'rootcause'}, {'id': 'rootcause:Improper Input Validation', 'keyphrase': 'Improper Input Validation', 'type': 'rootcause'}]}, 'similarity': np.float64(134.24333104114592)}, {'metadata': {'doc_id': '472', 'name': 'External Control of Assumed-Immutable Web Parameter', 'source': 'sparse', 'original_content': 'The web application does not sufficiently verify inputs that are assumed to be immutable but are actually externally controllable, such as hidden form fields.', 'keyphrase_sources': [{'id': 'rootcause:Input Validation vulnerability', 'keyphrase': 'Input Validation vulnerability', 'type': 'rootcause'}, {'id': 'rootcause:Improper Input Validation', 'keyphrase': 'Improper Input Validation', 'type': 'rootcause'}, {'id': 'version:1.39 through 1.43', 'keyphrase': '1.39 through 1.43', 'type': 'version'}]}, 'similarity': np.float64(126.793104923171)}, {'metadata': {'doc_id': '288', 'name': 'Authentication Bypass Using an Alternate Path or Channel', 'source': 'sparse', 'original_content': 'The product requires authentication, but the product has an alternate path or channel that does not require authentication.', 'keyphrase_sources': [{'id': 'version:1.39 through 1.43', 'keyphrase': '1.39 through 1.43', 'type': 'version'}]}, 'similarity': np.float64(52.66900390190798)}, {'metadata': {'doc_id': '267', 'name': 'Privilege Defined With Unsafe Actions', 'source': 'sparse', 'original_content': 'A particular privilege, role, capability, or right can be used to perform unsafe actions that were not intended, even when it is assigned to the correct entity.', 'keyphrase_sources': [{'id': 'product:Wikimedia Foundation Mediawiki - Visual Data Extension', 'keyphrase': 'Wikimedia Foundation Mediawiki - Visual Data Extension', 'type': 'product'}]}, 'similarity': np.float64(49.97394191570476)}, {'metadata': {'doc_id': '820', 'name': 'Missing Synchronization', 'source': 'sparse', 'original_content': 'The product utilizes a shared resource in a concurrent manner but does not attempt to synchronize access to the resource.', 'keyphrase_sources': [{'id': 'version:1.39 through 1.43', 'keyphrase': '1.39 through 1.43', 'type': 'version'}]}, 'similarity': np.float64(48.52171380283861)}, {'metadata': {'doc_id': '291', 'name': 'Reliance on IP Address for Authentication', 'source': 'sparse', 'original_content': 'The product uses an IP address for authentication.', 'keyphrase_sources': [{'id': 'version:1.39 through 1.43', 'keyphrase': '1.39 through 1.43', 'type': 'version'}]}, 'similarity': np.float64(47.84910872821821)}, {'metadata': {'doc_id': '121', 'name': 'Stack-based Buffer Overflow', 'source': 'sparse', 'original_content': 'A stack-based buffer overflow condition is a condition where the buffer being overwritten is allocated on the stack (i.e., is a local variable or, rarely, a parameter to a function).', 'keyphrase_sources': [{'id': 'impact:HTTP DoS', 'keyphrase': 'HTTP DoS', 'type': 'impact'}]}, 'similarity': np.float64(47.32870663776141)}, {'metadata': {'doc_id': '674', 'name': 'Uncontrolled Recursion', 'source': 'sparse', 'original_content': 'The product does not properly control the amount of recursion that takes place,  consuming excessive resources, such as allocated memory or the program stack.', 'keyphrase_sources': [{'id': 'impact:HTTP DoS', 'keyphrase': 'HTTP DoS', 'type': 'impact'}]}, 'similarity': np.float64(45.31722695132934)}, {'metadata': {'doc_id': '119', 'name': 'Improper Restriction of Operations within the Bounds of a Memory Buffer', 'source': 'sparse', 'original_content': \"The product performs operations on a memory buffer, but it reads from or writes to a memory location outside the buffer's intended boundary. This may result in read or write operations on unexpected memory locations that could be linked to other variables, data structures, or internal program data.\", 'keyphrase_sources': [{'id': 'impact:HTTP DoS', 'keyphrase': 'HTTP DoS', 'type': 'impact'}, {'id': 'product:Wikimedia Foundation Mediawiki - Visual Data Extension', 'keyphrase': 'Wikimedia Foundation Mediawiki - Visual Data Extension', 'type': 'product'}]}, 'similarity': np.float64(45.28356509392502)}, {'metadata': {'doc_id': '201', 'name': 'Insertion of Sensitive Information Into Sent Data', 'source': 'sparse', 'original_content': 'The code transmits data to another actor, but a portion of the data includes sensitive information that should not be accessible to that actor.', 'keyphrase_sources': [{'id': 'impact:HTTP DoS', 'keyphrase': 'HTTP DoS', 'type': 'impact'}, {'id': 'product:Wikimedia Foundation Mediawiki - Visual Data Extension', 'keyphrase': 'Wikimedia Foundation Mediawiki - Visual Data Extension', 'type': 'product'}, {'id': 'version:1.39 through 1.43', 'keyphrase': '1.39 through 1.43', 'type': 'version'}]}, 'similarity': np.float64(44.768385255109216)}], identified_cwes={'analyzer': [], 'critic_additional': []})",
  "retrieval_results": {
    "has_multiple_keyphrases": true,
    "keyphrase_cwe_sets": {
      "rootcause:Input Validation vulnerability": {
        "keyphrase": "Input Validation vulnerability",
        "type": "rootcause",
        "cwes": [
          {
            "metadata": {
              "doc_id": "20",
              "name": "Improper Input Validation",
              "source": "sparse",
              "original_content": "The product receives input or data, but it does\n        not validate or incorrectly validates that the input has the\n        properties that are required to process the data safely and\n        correctly.",
              "keyphrase_sources": [
                {
                  "id": "rootcause:Input Validation vulnerability",
                  "keyphrase": "Input Validation vulnerability",
                  "type": "rootcause"
                },
                {
                  "id": "rootcause:Improper Input Validation",
                  "keyphrase": "Improper Input Validation",
                  "type": "rootcause"
                },
                {
                  "id": "impact:HTTP DoS",
                  "keyphrase": "HTTP DoS",
                  "type": "impact"
                }
              ]
            },
            "similarity": 152.78790090427444
          },
          {
            "metadata": {
              "doc_id": "451",
              "name": "User Interface (UI) Misrepresentation of Critical Information",
              "source": "sparse",
              "original_content": "The user interface (UI) does not properly represent critical information to the user, allowing the information - or its source - to be obscured or spoofed. This is often a component in phishing attacks.",
              "keyphrase_sources": [
                {
                  "id": "rootcause:Input Validation vulnerability",
                  "keyphrase": "Input Validation vulnerability",
                  "type": "rootcause"
                },
                {
                  "id": "rootcause:Improper Input Validation",
                  "keyphrase": "Improper Input Validation",
                  "type": "rootcause"
                },
                {
                  "id": "product:Wikimedia Foundation Mediawiki - Visual Data Extension",
                  "keyphrase": "Wikimedia Foundation Mediawiki - Visual Data Extension",
                  "type": "product"
                }
              ]
            },
            "similarity": 146.51969020925807
          },
          {
            "metadata": {
              "doc_id": "1289",
              "name": "Improper Validation of Unsafe Equivalence in Input",
              "source": "sparse",
              "original_content": "The product receives an input value that is used as a resource identifier or other type of reference, but it does not validate or incorrectly validates that the input is equivalent to a potentially-unsafe value.",
              "keyphrase_sources": [
                {
                  "id": "rootcause:Input Validation vulnerability",
                  "keyphrase": "Input Validation vulnerability",
                  "type": "rootcause"
                },
                {
                  "id": "rootcause:Improper Input Validation",
                  "keyphrase": "Improper Input Validation",
                  "type": "rootcause"
                },
                {
                  "id": "product:Wikimedia Foundation Mediawiki - Visual Data Extension",
                  "keyphrase": "Wikimedia Foundation Mediawiki - Visual Data Extension",
                  "type": "product"
                }
              ]
            },
            "similarity": 145.23534896233457
          },
          {
            "metadata": {
              "doc_id": "1284",
              "name": "Improper Validation of Specified Quantity in Input",
              "source": "sparse",
              "original_content": "The product receives input that is expected to specify a quantity (such as size or length), but it does not validate or incorrectly validates that the quantity has the required properties.",
              "keyphrase_sources": [
                {
                  "id": "rootcause:Input Validation vulnerability",
                  "keyphrase": "Input Validation vulnerability",
                  "type": "rootcause"
                },
                {
                  "id": "rootcause:Improper Input Validation",
                  "keyphrase": "Improper Input Validation",
                  "type": "rootcause"
                }
              ]
            },
            "similarity": 134.24333104114592
          },
          {
            "metadata": {
              "doc_id": "472",
              "name": "External Control of Assumed-Immutable Web Parameter",
              "source": "sparse",
              "original_content": "The web application does not sufficiently verify inputs that are assumed to be immutable but are actually externally controllable, such as hidden form fields.",
              "keyphrase_sources": [
                {
                  "id": "rootcause:Input Validation vulnerability",
                  "keyphrase": "Input Validation vulnerability",
                  "type": "rootcause"
                },
                {
                  "id": "rootcause:Improper Input Validation",
                  "keyphrase": "Improper Input Validation",
                  "type": "rootcause"
                },
                {
                  "id": "version:1.39 through 1.43",
                  "keyphrase": "1.39 through 1.43",
                  "type": "version"
                }
              ]
            },
            "similarity": 126.793104923171
          }
        ]
      },
      "rootcause:Improper Input Validation": {
        "keyphrase": "Improper Input Validation",
        "type": "rootcause",
        "cwes": [
          {
            "metadata": {
              "doc_id": "20",
              "name": "Improper Input Validation",
              "source": "sparse",
              "original_content": "The product receives input or data, but it does\n        not validate or incorrectly validates that the input has the\n        properties that are required to process the data safely and\n        correctly."
            },
            "similarity": 157.5408794217089
          },
          {
            "metadata": {
              "doc_id": "1289",
              "name": "Improper Validation of Unsafe Equivalence in Input",
              "source": "sparse",
              "original_content": "The product receives an input value that is used as a resource identifier or other type of reference, but it does not validate or incorrectly validates that the input is equivalent to a potentially-unsafe value."
            },
            "similarity": 147.1743911160395
          },
          {
            "metadata": {
              "doc_id": "451",
              "name": "User Interface (UI) Misrepresentation of Critical Information",
              "source": "sparse",
              "original_content": "The user interface (UI) does not properly represent critical information to the user, allowing the information - or its source - to be obscured or spoofed. This is often a component in phishing attacks."
            },
            "similarity": 144.45687761352872
          },
          {
            "metadata": {
              "doc_id": "1284",
              "name": "Improper Validation of Specified Quantity in Input",
              "source": "sparse",
              "original_content": "The product receives input that is expected to specify a quantity (such as size or length), but it does not validate or incorrectly validates that the quantity has the required properties."
            },
            "similarity": 137.2982409054157
          },
          {
            "metadata": {
              "doc_id": "472",
              "name": "External Control of Assumed-Immutable Web Parameter",
              "source": "sparse",
              "original_content": "The web application does not sufficiently verify inputs that are assumed to be immutable but are actually externally controllable, such as hidden form fields."
            },
            "similarity": 130.9878267735692
          }
        ]
      },
      "impact:HTTP DoS": {
        "keyphrase": "HTTP DoS",
        "type": "impact",
        "cwes": [
          {
            "metadata": {
              "doc_id": "20",
              "name": "Improper Input Validation",
              "source": "sparse",
              "original_content": "The product receives input or data, but it does\n        not validate or incorrectly validates that the input has the\n        properties that are required to process the data safely and\n        correctly."
            },
            "similarity": 48.72666467498401
          },
          {
            "metadata": {
              "doc_id": "121",
              "name": "Stack-based Buffer Overflow",
              "source": "sparse",
              "original_content": "A stack-based buffer overflow condition is a condition where the buffer being overwritten is allocated on the stack (i.e., is a local variable or, rarely, a parameter to a function).",
              "keyphrase_sources": [
                {
                  "id": "impact:HTTP DoS",
                  "keyphrase": "HTTP DoS",
                  "type": "impact"
                }
              ]
            },
            "similarity": 47.32870663776141
          },
          {
            "metadata": {
              "doc_id": "674",
              "name": "Uncontrolled Recursion",
              "source": "sparse",
              "original_content": "The product does not properly control the amount of recursion that takes place,  consuming excessive resources, such as allocated memory or the program stack.",
              "keyphrase_sources": [
                {
                  "id": "impact:HTTP DoS",
                  "keyphrase": "HTTP DoS",
                  "type": "impact"
                }
              ]
            },
            "similarity": 45.31722695132934
          },
          {
            "metadata": {
              "doc_id": "119",
              "name": "Improper Restriction of Operations within the Bounds of a Memory Buffer",
              "source": "sparse",
              "original_content": "The product performs operations on a memory buffer, but it reads from or writes to a memory location outside the buffer's intended boundary. This may result in read or write operations on unexpected memory locations that could be linked to other variables, data structures, or internal program data.",
              "keyphrase_sources": [
                {
                  "id": "impact:HTTP DoS",
                  "keyphrase": "HTTP DoS",
                  "type": "impact"
                },
                {
                  "id": "product:Wikimedia Foundation Mediawiki - Visual Data Extension",
                  "keyphrase": "Wikimedia Foundation Mediawiki - Visual Data Extension",
                  "type": "product"
                }
              ]
            },
            "similarity": 45.28356509392502
          },
          {
            "metadata": {
              "doc_id": "201",
              "name": "Insertion of Sensitive Information Into Sent Data",
              "source": "sparse",
              "original_content": "The code transmits data to another actor, but a portion of the data includes sensitive information that should not be accessible to that actor.",
              "keyphrase_sources": [
                {
                  "id": "impact:HTTP DoS",
                  "keyphrase": "HTTP DoS",
                  "type": "impact"
                },
                {
                  "id": "product:Wikimedia Foundation Mediawiki - Visual Data Extension",
                  "keyphrase": "Wikimedia Foundation Mediawiki - Visual Data Extension",
                  "type": "product"
                },
                {
                  "id": "version:1.39 through 1.43",
                  "keyphrase": "1.39 through 1.43",
                  "type": "version"
                }
              ]
            },
            "similarity": 44.768385255109216
          }
        ]
      },
      "product:Wikimedia Foundation Mediawiki - Visual Data Extension": {
        "keyphrase": "Wikimedia Foundation Mediawiki - Visual Data Extension",
        "type": "product",
        "cwes": [
          {
            "metadata": {
              "doc_id": "451",
              "name": "User Interface (UI) Misrepresentation of Critical Information",
              "source": "sparse",
              "original_content": "The user interface (UI) does not properly represent critical information to the user, allowing the information - or its source - to be obscured or spoofed. This is often a component in phishing attacks."
            },
            "similarity": 63.246129996828635
          },
          {
            "metadata": {
              "doc_id": "201",
              "name": "Insertion of Sensitive Information Into Sent Data",
              "source": "sparse",
              "original_content": "The code transmits data to another actor, but a portion of the data includes sensitive information that should not be accessible to that actor."
            },
            "similarity": 55.47567196472743
          },
          {
            "metadata": {
              "doc_id": "1289",
              "name": "Improper Validation of Unsafe Equivalence in Input",
              "source": "sparse",
              "original_content": "The product receives an input value that is used as a resource identifier or other type of reference, but it does not validate or incorrectly validates that the input is equivalent to a potentially-unsafe value."
            },
            "similarity": 52.948428796993426
          },
          {
            "metadata": {
              "doc_id": "267",
              "name": "Privilege Defined With Unsafe Actions",
              "source": "sparse",
              "original_content": "A particular privilege, role, capability, or right can be used to perform unsafe actions that were not intended, even when it is assigned to the correct entity.",
              "keyphrase_sources": [
                {
                  "id": "product:Wikimedia Foundation Mediawiki - Visual Data Extension",
                  "keyphrase": "Wikimedia Foundation Mediawiki - Visual Data Extension",
                  "type": "product"
                }
              ]
            },
            "similarity": 49.97394191570476
          },
          {
            "metadata": {
              "doc_id": "119",
              "name": "Improper Restriction of Operations within the Bounds of a Memory Buffer",
              "source": "sparse",
              "original_content": "The product performs operations on a memory buffer, but it reads from or writes to a memory location outside the buffer's intended boundary. This may result in read or write operations on unexpected memory locations that could be linked to other variables, data structures, or internal program data."
            },
            "similarity": 49.37313443657538
          }
        ]
      },
      "version:1.39 through 1.43": {
        "keyphrase": "1.39 through 1.43",
        "type": "version",
        "cwes": [
          {
            "metadata": {
              "doc_id": "288",
              "name": "Authentication Bypass Using an Alternate Path or Channel",
              "source": "sparse",
              "original_content": "The product requires authentication, but the product has an alternate path or channel that does not require authentication.",
              "keyphrase_sources": [
                {
                  "id": "version:1.39 through 1.43",
                  "keyphrase": "1.39 through 1.43",
                  "type": "version"
                }
              ]
            },
            "similarity": 52.66900390190798
          },
          {
            "metadata": {
              "doc_id": "820",
              "name": "Missing Synchronization",
              "source": "sparse",
              "original_content": "The product utilizes a shared resource in a concurrent manner but does not attempt to synchronize access to the resource.",
              "keyphrase_sources": [
                {
                  "id": "version:1.39 through 1.43",
                  "keyphrase": "1.39 through 1.43",
                  "type": "version"
                }
              ]
            },
            "similarity": 48.52171380283861
          },
          {
            "metadata": {
              "doc_id": "201",
              "name": "Insertion of Sensitive Information Into Sent Data",
              "source": "sparse",
              "original_content": "The code transmits data to another actor, but a portion of the data includes sensitive information that should not be accessible to that actor."
            },
            "similarity": 48.44422480617262
          },
          {
            "metadata": {
              "doc_id": "472",
              "name": "External Control of Assumed-Immutable Web Parameter",
              "source": "sparse",
              "original_content": "The web application does not sufficiently verify inputs that are assumed to be immutable but are actually externally controllable, such as hidden form fields."
            },
            "similarity": 48.40872957483513
          },
          {
            "metadata": {
              "doc_id": "291",
              "name": "Reliance on IP Address for Authentication",
              "source": "sparse",
              "original_content": "The product uses an IP address for authentication.",
              "keyphrase_sources": [
                {
                  "id": "version:1.39 through 1.43",
                  "keyphrase": "1.39 through 1.43",
                  "type": "version"
                }
              ]
            },
            "similarity": 47.84910872821821
          }
        ]
      }
    },
    "keyphrase_mapping": {
      "20": [
        {
          "id": "rootcause:Input Validation vulnerability",
          "keyphrase": "Input Validation vulnerability",
          "type": "rootcause"
        },
        {
          "id": "rootcause:Improper Input Validation",
          "keyphrase": "Improper Input Validation",
          "type": "rootcause"
        },
        {
          "id": "impact:HTTP DoS",
          "keyphrase": "HTTP DoS",
          "type": "impact"
        }
      ],
      "451": [
        {
          "id": "rootcause:Input Validation vulnerability",
          "keyphrase": "Input Validation vulnerability",
          "type": "rootcause"
        },
        {
          "id": "rootcause:Improper Input Validation",
          "keyphrase": "Improper Input Validation",
          "type": "rootcause"
        },
        {
          "id": "product:Wikimedia Foundation Mediawiki - Visual Data Extension",
          "keyphrase": "Wikimedia Foundation Mediawiki - Visual Data Extension",
          "type": "product"
        }
      ],
      "1289": [
        {
          "id": "rootcause:Input Validation vulnerability",
          "keyphrase": "Input Validation vulnerability",
          "type": "rootcause"
        },
        {
          "id": "rootcause:Improper Input Validation",
          "keyphrase": "Improper Input Validation",
          "type": "rootcause"
        },
        {
          "id": "product:Wikimedia Foundation Mediawiki - Visual Data Extension",
          "keyphrase": "Wikimedia Foundation Mediawiki - Visual Data Extension",
          "type": "product"
        }
      ],
      "1284": [
        {
          "id": "rootcause:Input Validation vulnerability",
          "keyphrase": "Input Validation vulnerability",
          "type": "rootcause"
        },
        {
          "id": "rootcause:Improper Input Validation",
          "keyphrase": "Improper Input Validation",
          "type": "rootcause"
        }
      ],
      "472": [
        {
          "id": "rootcause:Input Validation vulnerability",
          "keyphrase": "Input Validation vulnerability",
          "type": "rootcause"
        },
        {
          "id": "rootcause:Improper Input Validation",
          "keyphrase": "Improper Input Validation",
          "type": "rootcause"
        },
        {
          "id": "version:1.39 through 1.43",
          "keyphrase": "1.39 through 1.43",
          "type": "version"
        }
      ],
      "121": [
        {
          "id": "impact:HTTP DoS",
          "keyphrase": "HTTP DoS",
          "type": "impact"
        }
      ],
      "674": [
        {
          "id": "impact:HTTP DoS",
          "keyphrase": "HTTP DoS",
          "type": "impact"
        }
      ],
      "119": [
        {
          "id": "impact:HTTP DoS",
          "keyphrase": "HTTP DoS",
          "type": "impact"
        },
        {
          "id": "product:Wikimedia Foundation Mediawiki - Visual Data Extension",
          "keyphrase": "Wikimedia Foundation Mediawiki - Visual Data Extension",
          "type": "product"
        }
      ],
      "201": [
        {
          "id": "impact:HTTP DoS",
          "keyphrase": "HTTP DoS",
          "type": "impact"
        },
        {
          "id": "product:Wikimedia Foundation Mediawiki - Visual Data Extension",
          "keyphrase": "Wikimedia Foundation Mediawiki - Visual Data Extension",
          "type": "product"
        },
        {
          "id": "version:1.39 through 1.43",
          "keyphrase": "1.39 through 1.43",
          "type": "version"
        }
      ],
      "267": [
        {
          "id": "product:Wikimedia Foundation Mediawiki - Visual Data Extension",
          "keyphrase": "Wikimedia Foundation Mediawiki - Visual Data Extension",
          "type": "product"
        }
      ],
      "288": [
        {
          "id": "version:1.39 through 1.43",
          "keyphrase": "1.39 through 1.43",
          "type": "version"
        }
      ],
      "820": [
        {
          "id": "version:1.39 through 1.43",
          "keyphrase": "1.39 through 1.43",
          "type": "version"
        }
      ],
      "291": [
        {
          "id": "version:1.39 through 1.43",
          "keyphrase": "1.39 through 1.43",
          "type": "version"
        }
      ]
    },
    "relevant_cwes": [
      {
        "metadata": {
          "doc_id": "20",
          "name": "Improper Input Validation",
          "source": "sparse",
          "original_content": "The product receives input or data, but it does\n        not validate or incorrectly validates that the input has the\n        properties that are required to process the data safely and\n        correctly.",
          "keyphrase_sources": [
            {
              "id": "rootcause:Input Validation vulnerability",
              "keyphrase": "Input Validation vulnerability",
              "type": "rootcause"
            },
            {
              "id": "rootcause:Improper Input Validation",
              "keyphrase": "Improper Input Validation",
              "type": "rootcause"
            },
            {
              "id": "impact:HTTP DoS",
              "keyphrase": "HTTP DoS",
              "type": "impact"
            }
          ]
        },
        "similarity": 152.78790090427444
      },
      {
        "metadata": {
          "doc_id": "451",
          "name": "User Interface (UI) Misrepresentation of Critical Information",
          "source": "sparse",
          "original_content": "The user interface (UI) does not properly represent critical information to the user, allowing the information - or its source - to be obscured or spoofed. This is often a component in phishing attacks.",
          "keyphrase_sources": [
            {
              "id": "rootcause:Input Validation vulnerability",
              "keyphrase": "Input Validation vulnerability",
              "type": "rootcause"
            },
            {
              "id": "rootcause:Improper Input Validation",
              "keyphrase": "Improper Input Validation",
              "type": "rootcause"
            },
            {
              "id": "product:Wikimedia Foundation Mediawiki - Visual Data Extension",
              "keyphrase": "Wikimedia Foundation Mediawiki - Visual Data Extension",
              "type": "product"
            }
          ]
        },
        "similarity": 146.51969020925807
      },
      {
        "metadata": {
          "doc_id": "1289",
          "name": "Improper Validation of Unsafe Equivalence in Input",
          "source": "sparse",
          "original_content": "The product receives an input value that is used as a resource identifier or other type of reference, but it does not validate or incorrectly validates that the input is equivalent to a potentially-unsafe value.",
          "keyphrase_sources": [
            {
              "id": "rootcause:Input Validation vulnerability",
              "keyphrase": "Input Validation vulnerability",
              "type": "rootcause"
            },
            {
              "id": "rootcause:Improper Input Validation",
              "keyphrase": "Improper Input Validation",
              "type": "rootcause"
            },
            {
              "id": "product:Wikimedia Foundation Mediawiki - Visual Data Extension",
              "keyphrase": "Wikimedia Foundation Mediawiki - Visual Data Extension",
              "type": "product"
            }
          ]
        },
        "similarity": 145.23534896233457
      },
      {
        "metadata": {
          "doc_id": "1284",
          "name": "Improper Validation of Specified Quantity in Input",
          "source": "sparse",
          "original_content": "The product receives input that is expected to specify a quantity (such as size or length), but it does not validate or incorrectly validates that the quantity has the required properties.",
          "keyphrase_sources": [
            {
              "id": "rootcause:Input Validation vulnerability",
              "keyphrase": "Input Validation vulnerability",
              "type": "rootcause"
            },
            {
              "id": "rootcause:Improper Input Validation",
              "keyphrase": "Improper Input Validation",
              "type": "rootcause"
            }
          ]
        },
        "similarity": 134.24333104114592
      },
      {
        "metadata": {
          "doc_id": "472",
          "name": "External Control of Assumed-Immutable Web Parameter",
          "source": "sparse",
          "original_content": "The web application does not sufficiently verify inputs that are assumed to be immutable but are actually externally controllable, such as hidden form fields.",
          "keyphrase_sources": [
            {
              "id": "rootcause:Input Validation vulnerability",
              "keyphrase": "Input Validation vulnerability",
              "type": "rootcause"
            },
            {
              "id": "rootcause:Improper Input Validation",
              "keyphrase": "Improper Input Validation",
              "type": "rootcause"
            },
            {
              "id": "version:1.39 through 1.43",
              "keyphrase": "1.39 through 1.43",
              "type": "version"
            }
          ]
        },
        "similarity": 126.793104923171
      },
      {
        "metadata": {
          "doc_id": "288",
          "name": "Authentication Bypass Using an Alternate Path or Channel",
          "source": "sparse",
          "original_content": "The product requires authentication, but the product has an alternate path or channel that does not require authentication.",
          "keyphrase_sources": [
            {
              "id": "version:1.39 through 1.43",
              "keyphrase": "1.39 through 1.43",
              "type": "version"
            }
          ]
        },
        "similarity": 52.66900390190798
      },
      {
        "metadata": {
          "doc_id": "267",
          "name": "Privilege Defined With Unsafe Actions",
          "source": "sparse",
          "original_content": "A particular privilege, role, capability, or right can be used to perform unsafe actions that were not intended, even when it is assigned to the correct entity.",
          "keyphrase_sources": [
            {
              "id": "product:Wikimedia Foundation Mediawiki - Visual Data Extension",
              "keyphrase": "Wikimedia Foundation Mediawiki - Visual Data Extension",
              "type": "product"
            }
          ]
        },
        "similarity": 49.97394191570476
      },
      {
        "metadata": {
          "doc_id": "820",
          "name": "Missing Synchronization",
          "source": "sparse",
          "original_content": "The product utilizes a shared resource in a concurrent manner but does not attempt to synchronize access to the resource.",
          "keyphrase_sources": [
            {
              "id": "version:1.39 through 1.43",
              "keyphrase": "1.39 through 1.43",
              "type": "version"
            }
          ]
        },
        "similarity": 48.52171380283861
      },
      {
        "metadata": {
          "doc_id": "291",
          "name": "Reliance on IP Address for Authentication",
          "source": "sparse",
          "original_content": "The product uses an IP address for authentication.",
          "keyphrase_sources": [
            {
              "id": "version:1.39 through 1.43",
              "keyphrase": "1.39 through 1.43",
              "type": "version"
            }
          ]
        },
        "similarity": 47.84910872821821
      },
      {
        "metadata": {
          "doc_id": "121",
          "name": "Stack-based Buffer Overflow",
          "source": "sparse",
          "original_content": "A stack-based buffer overflow condition is a condition where the buffer being overwritten is allocated on the stack (i.e., is a local variable or, rarely, a parameter to a function).",
          "keyphrase_sources": [
            {
              "id": "impact:HTTP DoS",
              "keyphrase": "HTTP DoS",
              "type": "impact"
            }
          ]
        },
        "similarity": 47.32870663776141
      },
      {
        "metadata": {
          "doc_id": "674",
          "name": "Uncontrolled Recursion",
          "source": "sparse",
          "original_content": "The product does not properly control the amount of recursion that takes place,  consuming excessive resources, such as allocated memory or the program stack.",
          "keyphrase_sources": [
            {
              "id": "impact:HTTP DoS",
              "keyphrase": "HTTP DoS",
              "type": "impact"
            }
          ]
        },
        "similarity": 45.31722695132934
      },
      {
        "metadata": {
          "doc_id": "119",
          "name": "Improper Restriction of Operations within the Bounds of a Memory Buffer",
          "source": "sparse",
          "original_content": "The product performs operations on a memory buffer, but it reads from or writes to a memory location outside the buffer's intended boundary. This may result in read or write operations on unexpected memory locations that could be linked to other variables, data structures, or internal program data.",
          "keyphrase_sources": [
            {
              "id": "impact:HTTP DoS",
              "keyphrase": "HTTP DoS",
              "type": "impact"
            },
            {
              "id": "product:Wikimedia Foundation Mediawiki - Visual Data Extension",
              "keyphrase": "Wikimedia Foundation Mediawiki - Visual Data Extension",
              "type": "product"
            }
          ]
        },
        "similarity": 45.28356509392502
      },
      {
        "metadata": {
          "doc_id": "201",
          "name": "Insertion of Sensitive Information Into Sent Data",
          "source": "sparse",
          "original_content": "The code transmits data to another actor, but a portion of the data includes sensitive information that should not be accessible to that actor.",
          "keyphrase_sources": [
            {
              "id": "impact:HTTP DoS",
              "keyphrase": "HTTP DoS",
              "type": "impact"
            },
            {
              "id": "product:Wikimedia Foundation Mediawiki - Visual Data Extension",
              "keyphrase": "Wikimedia Foundation Mediawiki - Visual Data Extension",
              "type": "product"
            },
            {
              "id": "version:1.39 through 1.43",
              "keyphrase": "1.39 through 1.43",
              "type": "version"
            }
          ]
        },
        "similarity": 44.768385255109216
      }
    ],
    "enhanced_query": "# Vulnerability Description\n\n    Improper **Input Validation vulnerability** in The Wikimedia Foundation Mediawiki - Visual Data Extension allows HTTP DoS.This issue affects Mediawiki - Visual Data Extension from 1.39 through 1.43.\n\n    # Keyphrase-Specific CWE Analysis\n    This vulnerability contains multiple keyphrases that may map to different CWEs. \n    Please analyze each keyphrase separately and determine the most appropriate CWE(s) for each.\n\n    ## ROOTCAUSE: 'Input Validation vulnerability'\n\nRelevant CWEs for this ROOTCAUSE:\n\n### 1. CWE-20: Improper Input Validation (Score: 152.79)\n\nThe product receives input or data, but it does\n        not validate or incorrectly validates that the input has the\n        properties that are required to process the data safely and\n        correctly....\n\n### 2. CWE-451: User Interface (UI) Misrepresentation of Critical Information (Score: 146.52)\n\nThe user interface (UI) does not properly represent critical information to the user, allowing the information - or its source - to be obscured or spoofed. This is often a component in phishing attacks....\n\n### 3. CWE-1289: Improper Validation of Unsafe Equivalence in Input (Score: 145.24)\n\nThe product receives an input value that is used as a resource identifier or other type of reference, but it does not validate or incorrectly validates that the input is equivalent to a potentially-unsafe value....\n\n### 4. CWE-1284: Improper Validation of Specified Quantity in Input (Score: 134.24)\n\nThe product receives input that is expected to specify a quantity (such as size or length), but it does not validate or incorrectly validates that the quantity has the required properties....\n\n### 5. CWE-472: External Control of Assumed-Immutable Web Parameter (Score: 126.79)\n\nThe web application does not sufficiently verify inputs that are assumed to be immutable but are actually externally controllable, such as hidden form fields....\n\n## ROOTCAUSE: 'Improper Input Validation'\n\nRelevant CWEs for this ROOTCAUSE:\n\n### 1. CWE-20: Improper Input Validation (Score: 152.79)\n\nThe product receives input or data, but it does\n        not validate or incorrectly validates that the input has the\n        properties that are required to process the data safely and\n        correctly....\n\n### 2. CWE-451: User Interface (UI) Misrepresentation of Critical Information (Score: 146.52)\n\nThe user interface (UI) does not properly represent critical information to the user, allowing the information - or its source - to be obscured or spoofed. This is often a component in phishing attacks....\n\n### 3. CWE-1289: Improper Validation of Unsafe Equivalence in Input (Score: 145.24)\n\nThe product receives an input value that is used as a resource identifier or other type of reference, but it does not validate or incorrectly validates that the input is equivalent to a potentially-unsafe value....\n\n### 4. CWE-1284: Improper Validation of Specified Quantity in Input (Score: 134.24)\n\nThe product receives input that is expected to specify a quantity (such as size or length), but it does not validate or incorrectly validates that the quantity has the required properties....\n\n### 5. CWE-472: External Control of Assumed-Immutable Web Parameter (Score: 126.79)\n\nThe web application does not sufficiently verify inputs that are assumed to be immutable but are actually externally controllable, such as hidden form fields....\n\n## IMPACT: 'HTTP DoS'\n\nRelevant CWEs for this IMPACT:\n\n### 1. CWE-20: Improper Input Validation (Score: 152.79)\n\nThe product receives input or data, but it does\n        not validate or incorrectly validates that the input has the\n        properties that are required to process the data safely and\n        correctly....\n\n### 2. CWE-121: Stack-based Buffer Overflow (Score: 47.33)\n\nA stack-based buffer overflow condition is a condition where the buffer being overwritten is allocated on the stack (i.e., is a local variable or, rarely, a parameter to a function)....\n\n### 3. CWE-674: Uncontrolled Recursion (Score: 45.32)\n\nThe product does not properly control the amount of recursion that takes place,  consuming excessive resources, such as allocated memory or the program stack....\n\n### 4. CWE-119: Improper Restriction of Operations within the Bounds of a Memory Buffer (Score: 45.28)\n\nThe product performs operations on a memory buffer, but it reads from or writes to a memory location outside the buffer's intended boundary. This may result in read or write operations on unexpected memory locations that could be linked to other variables, data structures, or internal program data....\n\n### 5. CWE-201: Insertion of Sensitive Information Into Sent Data (Score: 44.77)\n\nThe code transmits data to another actor, but a portion of the data includes sensitive information that should not be accessible to that actor....\n\n## PRODUCT: 'Wikimedia Foundation Mediawiki - Visual Data Extension'\n\nRelevant CWEs for this PRODUCT:\n\n### 1. CWE-451: User Interface (UI) Misrepresentation of Critical Information (Score: 146.52)\n\nThe user interface (UI) does not properly represent critical information to the user, allowing the information - or its source - to be obscured or spoofed. This is often a component in phishing attacks....\n\n### 2. CWE-1289: Improper Validation of Unsafe Equivalence in Input (Score: 145.24)\n\nThe product receives an input value that is used as a resource identifier or other type of reference, but it does not validate or incorrectly validates that the input is equivalent to a potentially-unsafe value....\n\n### 3. CWE-267: Privilege Defined With Unsafe Actions (Score: 49.97)\n\nA particular privilege, role, capability, or right can be used to perform unsafe actions that were not intended, even when it is assigned to the correct entity....\n\n### 4. CWE-119: Improper Restriction of Operations within the Bounds of a Memory Buffer (Score: 45.28)\n\nThe product performs operations on a memory buffer, but it reads from or writes to a memory location outside the buffer's intended boundary. This may result in read or write operations on unexpected memory locations that could be linked to other variables, data structures, or internal program data....\n\n### 5. CWE-201: Insertion of Sensitive Information Into Sent Data (Score: 44.77)\n\nThe code transmits data to another actor, but a portion of the data includes sensitive information that should not be accessible to that actor....\n\n## VERSION: '1.39 through 1.43'\n\nRelevant CWEs for this VERSION:\n\n### 1. CWE-472: External Control of Assumed-Immutable Web Parameter (Score: 126.79)\n\nThe web application does not sufficiently verify inputs that are assumed to be immutable but are actually externally controllable, such as hidden form fields....\n\n### 2. CWE-288: Authentication Bypass Using an Alternate Path or Channel (Score: 52.67)\n\nThe product requires authentication, but the product has an alternate path or channel that does not require authentication....\n\n### 3. CWE-820: Missing Synchronization (Score: 48.52)\n\nThe product utilizes a shared resource in a concurrent manner but does not attempt to synchronize access to the resource....\n\n### 4. CWE-291: Reliance on IP Address for Authentication (Score: 47.85)\n\nThe product uses an IP address for authentication....\n\n### 5. CWE-201: Insertion of Sensitive Information Into Sent Data (Score: 44.77)\n\nThe code transmits data to another actor, but a portion of the data includes sensitive information that should not be accessible to that actor....\n\n\n    # Analysis Instructions\n    1. For each keyphrase, identify the most appropriate CWE(s) that represent the weakness.\n    2. Consider how the different keyphrases might relate to each other in the vulnerability chain.\n    3. Provide a final determination of primary CWE(s) and any secondary CWEs.\n    4. Format your response using the standard analysis template.\n\n    Please analyze how these different weaknesses interact and provide a comprehensive CWE classification.\n    "
  },
  "retrieval_time": 1.0467207431793213
}