{
  "vulnerability_info": "VulnerabilityInfo(cve_id='CVE-2025-3923', description='The Prevent Direct Access Protect WordPress Files plugin for WordPress is vulnerable to **Sensitive Information Exposure** in all versions up to, and including, 2.8.8 via the **generate_unique_string** due to **insufficient randomness** of the generated file name. This makes it possible for unauthenticated attackers to extract sensitive data including files protected by the plugin if the attacker can determine the file name.', key_phrases={'rootcause': ['insufficient randomness', 'generate_unique_string'], 'weakness': 'Sensitive Information Exposure', 'impact': 'extract sensitive data', 'vector': '', 'attacker': 'unauthenticated attackers', 'product': 'Prevent Direct Access Protect WordPress Files plugin', 'version': 'all versions up to and including 2.8.8', 'component': ''}, reference_content=\"Based on the provided content, here's an analysis related to CVE-2025-3923 (assuming the CVE description involves direct access prevention):\\n\\n**Root cause of vulnerability:**\\n\\nThe code aims to prevent direct access to uploaded files. However, the Nginx rewrite rules and IIS rules appear to be attempting to redirect requests for protected files to `index.php` with a `pda_v3_pf` parameter.  The regex used in the Nginx rules (`(\\\\/[A-Za-z0-9\\\\_@.\\\\/&+-]+)+\\\\.([A-Za-z0-9\\\\_@.\\\\/&+-]+)$`) might be vulnerable to bypasses, allowing direct access to files if crafted URLs are used. The IIS rule also appears to be attempting to rewrite requests to `index.php`.\\n\\n**Weaknesses/vulnerabilities present:**\\n\\n*   **Insecure Direct Object Reference (IDOR):** The `pda_v3_pf` parameter in the rewrite rules could be exploited if not properly validated, potentially allowing an attacker to access arbitrary files.\\n*   **Regex Bypass:** The regular expression used in the Nginx rules might be susceptible to bypasses, allowing attackers to craft URLs that circumvent the protection mechanism.\\n*   **Reliance on Rewrites:**  Relying solely on web server rewrites for access control can be fragile and prone to misconfiguration or bypass.\\n\\n**Impact of exploitation:**\\n\\nSuccessful exploitation could allow an attacker to bypass the intended access restrictions and directly access uploaded files, potentially leading to:\\n\\n*   **Information Disclosure:** Sensitive files could be downloaded and viewed by unauthorized users.\\n*   **Code Execution:** If uploaded files include executable code (e.g., PHP scripts), an attacker could potentially execute arbitrary code on the server.\\n\\n**Attack vectors:**\\n\\n*   **Crafted URLs:** An attacker could craft a URL that bypasses the regex in the Nginx rules or exploits vulnerabilities in the `pda_v3_pf` parameter handling.\\n*   **Direct Access Attempts:** Attempting to access files directly through their URL, hoping to bypass the rewrite rules.\\n\\n**Required attacker capabilities/position:**\\n\\n*   **Unauthenticated:** The attack vector appears to be exploitable without authentication.\\n*   **Knowledge of File Structure:**  The attacker needs some knowledge of the file upload directory structure to craft effective URLs.\\n*   **Understanding of Regex (for Nginx bypass):**  Understanding regular expressions is helpful for crafting bypasses.\\n\\n**Mitigation or fix:**\\n\\n*   **Stronger Access Control:** Implement more robust access control mechanisms beyond relying solely on web server rewrites.  Consider using server-side checks to verify file access permissions before serving files.\\n*   **Input Validation:** Thoroughly validate the `pda_v3_pf` parameter to prevent access to unauthorized files.\\n*   **Secure Regex:**  Review and strengthen the regular expression used in the Nginx rules to prevent bypasses.\\n*   **File Serving Restrictions:** Configure the web server to prevent direct execution of uploaded files.\\n*   **Principle of Least Privilege:** Ensure that the web server user has only the necessary permissions to access files.\\n\\n**Note:** This analysis provides more detail than a typical CVE description, as it delves into the code's implementation and potential vulnerabilities. The content focuses on the `helper.php` file and its role in preventing direct access to files.\", similar_info={'cwe_distribution': {}, 'cwe_consensus': '', 'similarity_stats': {'thresholds': [], 'total_samples_by_threshold': {}, 'top_cwes_by_threshold': {}}}, similarity_summary=SimilarityInsight(consensus_cwe='', top_cwes=[], confidence_levels={}, total_samples=0), analysis='', analysis_with_relationships='', criticism='', resolution='', relevant_cwes=[{'metadata': {'doc_id': '200', 'name': 'Exposure of Sensitive Information to an Unauthorized Actor', 'source': 'sparse', 'original_content': 'The product exposes sensitive information to an actor that is not explicitly authorized to have access to that information.', 'keyphrase_sources': [{'id': 'weakness:Sensitive Information Exposure', 'keyphrase': 'Sensitive Information Exposure', 'type': 'weakness'}, {'id': 'impact:extract sensitive data', 'keyphrase': 'extract sensitive data', 'type': 'impact'}, {'id': 'attacker:unauthenticated attackers', 'keyphrase': 'unauthenticated attackers', 'type': 'attacker'}]}, 'similarity': np.float64(405.6778236148703)}, {'metadata': {'doc_id': '863', 'name': 'Incorrect Authorization', 'source': 'sparse', 'original_content': 'The product performs an authorization check when an actor attempts to access a resource or perform an action, but it does not correctly perform the check.', 'keyphrase_sources': [{'id': 'rootcause:insufficient randomness', 'keyphrase': 'insufficient randomness', 'type': 'rootcause'}, {'id': 'rootcause:generate_unique_string', 'keyphrase': 'generate_unique_string', 'type': 'rootcause'}, {'id': 'weakness:Sensitive Information Exposure', 'keyphrase': 'Sensitive Information Exposure', 'type': 'weakness'}, {'id': 'version:all versions up to and including 2.8.8', 'keyphrase': 'all versions up to and including 2.8.8', 'type': 'version'}]}, 'similarity': np.float64(400.3018902082541)}, {'metadata': {'doc_id': '138', 'name': 'Improper Neutralization of Special Elements', 'source': 'sparse', 'original_content': 'The product receives input from an upstream component, but it does not neutralize or incorrectly neutralizes special elements that could be interpreted as control elements or syntactic markers when they are sent to a downstream component.', 'keyphrase_sources': [{'id': 'rootcause:insufficient randomness', 'keyphrase': 'insufficient randomness', 'type': 'rootcause'}, {'id': 'version:all versions up to and including 2.8.8', 'keyphrase': 'all versions up to and including 2.8.8', 'type': 'version'}]}, 'similarity': np.float64(396.81141621664585)}, {'metadata': {'doc_id': '862', 'name': 'Missing Authorization', 'source': 'sparse', 'original_content': 'The product does not perform an authorization check when an actor attempts to access a resource or perform an action.', 'keyphrase_sources': [{'id': 'rootcause:insufficient randomness', 'keyphrase': 'insufficient randomness', 'type': 'rootcause'}, {'id': 'rootcause:generate_unique_string', 'keyphrase': 'generate_unique_string', 'type': 'rootcause'}, {'id': 'weakness:Sensitive Information Exposure', 'keyphrase': 'Sensitive Information Exposure', 'type': 'weakness'}, {'id': 'impact:extract sensitive data', 'keyphrase': 'extract sensitive data', 'type': 'impact'}, {'id': 'attacker:unauthenticated attackers', 'keyphrase': 'unauthenticated attackers', 'type': 'attacker'}, {'id': 'product:Prevent Direct Access Protect WordPress Files plugin', 'keyphrase': 'Prevent Direct Access Protect WordPress Files plugin', 'type': 'product'}, {'id': 'version:all versions up to and including 2.8.8', 'keyphrase': 'all versions up to and including 2.8.8', 'type': 'version'}]}, 'similarity': np.float64(393.75331643817884)}, {'metadata': {'doc_id': '352', 'name': 'Cross-Site Request Forgery (CSRF)', 'source': 'sparse', 'original_content': 'The web application does not, or can not, sufficiently verify whether a well-formed, valid, consistent request was intentionally provided by the user who submitted the request.', 'keyphrase_sources': [{'id': 'rootcause:insufficient randomness', 'keyphrase': 'insufficient randomness', 'type': 'rootcause'}, {'id': 'rootcause:generate_unique_string', 'keyphrase': 'generate_unique_string', 'type': 'rootcause'}, {'id': 'attacker:unauthenticated attackers', 'keyphrase': 'unauthenticated attackers', 'type': 'attacker'}, {'id': 'product:Prevent Direct Access Protect WordPress Files plugin', 'keyphrase': 'Prevent Direct Access Protect WordPress Files plugin', 'type': 'product'}]}, 'similarity': np.float64(393.4446426862223)}, {'metadata': {'doc_id': '284', 'name': 'Improper Access Control', 'source': 'sparse', 'original_content': 'The product does not restrict or incorrectly restricts access to a resource from an unauthorized actor.', 'keyphrase_sources': [{'id': 'rootcause:insufficient randomness', 'keyphrase': 'insufficient randomness', 'type': 'rootcause'}]}, 'similarity': np.float64(391.3270605378732)}, {'metadata': {'doc_id': '639', 'name': 'Authorization Bypass Through User-Controlled Key', 'source': 'sparse', 'original_content': \"The system's authorization functionality does not prevent one user from gaining access to another user's data or record by modifying the key value identifying the data.\", 'keyphrase_sources': [{'id': 'rootcause:generate_unique_string', 'keyphrase': 'generate_unique_string', 'type': 'rootcause'}, {'id': 'weakness:Sensitive Information Exposure', 'keyphrase': 'Sensitive Information Exposure', 'type': 'weakness'}, {'id': 'impact:extract sensitive data', 'keyphrase': 'extract sensitive data', 'type': 'impact'}, {'id': 'attacker:unauthenticated attackers', 'keyphrase': 'unauthenticated attackers', 'type': 'attacker'}, {'id': 'product:Prevent Direct Access Protect WordPress Files plugin', 'keyphrase': 'Prevent Direct Access Protect WordPress Files plugin', 'type': 'product'}]}, 'similarity': np.float64(389.34185355478144)}, {'metadata': {'doc_id': '306', 'name': 'Missing Authentication for Critical Function', 'source': 'sparse', 'original_content': 'The product does not perform any authentication for functionality that requires a provable user identity or consumes a significant amount of resources.', 'keyphrase_sources': [{'id': 'rootcause:generate_unique_string', 'keyphrase': 'generate_unique_string', 'type': 'rootcause'}, {'id': 'weakness:Sensitive Information Exposure', 'keyphrase': 'Sensitive Information Exposure', 'type': 'weakness'}, {'id': 'impact:extract sensitive data', 'keyphrase': 'extract sensitive data', 'type': 'impact'}, {'id': 'attacker:unauthenticated attackers', 'keyphrase': 'unauthenticated attackers', 'type': 'attacker'}, {'id': 'version:all versions up to and including 2.8.8', 'keyphrase': 'all versions up to and including 2.8.8', 'type': 'version'}]}, 'similarity': np.float64(388.44511356788684)}, {'metadata': {'doc_id': '425', 'name': \"Direct Request ('Forced Browsing')\", 'source': 'sparse', 'original_content': 'The web application does not adequately enforce appropriate authorization on all restricted URLs, scripts, or files.', 'keyphrase_sources': [{'id': 'product:Prevent Direct Access Protect WordPress Files plugin', 'keyphrase': 'Prevent Direct Access Protect WordPress Files plugin', 'type': 'product'}]}, 'similarity': np.float64(167.69558634606562)}, {'metadata': {'doc_id': '285', 'name': 'Improper Authorization', 'source': 'sparse', 'original_content': 'The product does not perform or incorrectly performs an authorization check when an actor attempts to access a resource or perform an action.', 'keyphrase_sources': [{'id': 'product:Prevent Direct Access Protect WordPress Files plugin', 'keyphrase': 'Prevent Direct Access Protect WordPress Files plugin', 'type': 'product'}]}, 'similarity': np.float64(158.1413540697226)}, {'metadata': {'doc_id': '522', 'name': 'Insufficiently Protected Credentials', 'source': 'sparse', 'original_content': 'The product transmits or stores authentication credentials, but it uses an insecure method that is susceptible to unauthorized interception and/or retrieval.', 'keyphrase_sources': [{'id': 'impact:extract sensitive data', 'keyphrase': 'extract sensitive data', 'type': 'impact'}, {'id': 'version:all versions up to and including 2.8.8', 'keyphrase': 'all versions up to and including 2.8.8', 'type': 'version'}]}, 'similarity': np.float64(132.97906946238882)}], identified_cwes={'analyzer': [], 'critic_additional': []})",
  "retrieval_results": {
    "has_multiple_keyphrases": true,
    "keyphrase_cwe_sets": {
      "rootcause:insufficient randomness": {
        "keyphrase": "insufficient randomness",
        "type": "rootcause",
        "cwes": [
          {
            "metadata": {
              "doc_id": "863",
              "name": "Incorrect Authorization",
              "source": "sparse",
              "original_content": "The product performs an authorization check when an actor attempts to access a resource or perform an action, but it does not correctly perform the check.",
              "keyphrase_sources": [
                {
                  "id": "rootcause:insufficient randomness",
                  "keyphrase": "insufficient randomness",
                  "type": "rootcause"
                },
                {
                  "id": "rootcause:generate_unique_string",
                  "keyphrase": "generate_unique_string",
                  "type": "rootcause"
                },
                {
                  "id": "weakness:Sensitive Information Exposure",
                  "keyphrase": "Sensitive Information Exposure",
                  "type": "weakness"
                },
                {
                  "id": "version:all versions up to and including 2.8.8",
                  "keyphrase": "all versions up to and including 2.8.8",
                  "type": "version"
                }
              ]
            },
            "similarity": 400.3018902082541
          },
          {
            "metadata": {
              "doc_id": "138",
              "name": "Improper Neutralization of Special Elements",
              "source": "sparse",
              "original_content": "The product receives input from an upstream component, but it does not neutralize or incorrectly neutralizes special elements that could be interpreted as control elements or syntactic markers when they are sent to a downstream component.",
              "keyphrase_sources": [
                {
                  "id": "rootcause:insufficient randomness",
                  "keyphrase": "insufficient randomness",
                  "type": "rootcause"
                },
                {
                  "id": "version:all versions up to and including 2.8.8",
                  "keyphrase": "all versions up to and including 2.8.8",
                  "type": "version"
                }
              ]
            },
            "similarity": 396.81141621664585
          },
          {
            "metadata": {
              "doc_id": "862",
              "name": "Missing Authorization",
              "source": "sparse",
              "original_content": "The product does not perform an authorization check when an actor attempts to access a resource or perform an action.",
              "keyphrase_sources": [
                {
                  "id": "rootcause:insufficient randomness",
                  "keyphrase": "insufficient randomness",
                  "type": "rootcause"
                },
                {
                  "id": "rootcause:generate_unique_string",
                  "keyphrase": "generate_unique_string",
                  "type": "rootcause"
                },
                {
                  "id": "weakness:Sensitive Information Exposure",
                  "keyphrase": "Sensitive Information Exposure",
                  "type": "weakness"
                },
                {
                  "id": "impact:extract sensitive data",
                  "keyphrase": "extract sensitive data",
                  "type": "impact"
                },
                {
                  "id": "attacker:unauthenticated attackers",
                  "keyphrase": "unauthenticated attackers",
                  "type": "attacker"
                },
                {
                  "id": "product:Prevent Direct Access Protect WordPress Files plugin",
                  "keyphrase": "Prevent Direct Access Protect WordPress Files plugin",
                  "type": "product"
                },
                {
                  "id": "version:all versions up to and including 2.8.8",
                  "keyphrase": "all versions up to and including 2.8.8",
                  "type": "version"
                }
              ]
            },
            "similarity": 393.75331643817884
          },
          {
            "metadata": {
              "doc_id": "352",
              "name": "Cross-Site Request Forgery (CSRF)",
              "source": "sparse",
              "original_content": "The web application does not, or can not, sufficiently verify whether a well-formed, valid, consistent request was intentionally provided by the user who submitted the request.",
              "keyphrase_sources": [
                {
                  "id": "rootcause:insufficient randomness",
                  "keyphrase": "insufficient randomness",
                  "type": "rootcause"
                },
                {
                  "id": "rootcause:generate_unique_string",
                  "keyphrase": "generate_unique_string",
                  "type": "rootcause"
                },
                {
                  "id": "attacker:unauthenticated attackers",
                  "keyphrase": "unauthenticated attackers",
                  "type": "attacker"
                },
                {
                  "id": "product:Prevent Direct Access Protect WordPress Files plugin",
                  "keyphrase": "Prevent Direct Access Protect WordPress Files plugin",
                  "type": "product"
                }
              ]
            },
            "similarity": 393.4446426862223
          },
          {
            "metadata": {
              "doc_id": "284",
              "name": "Improper Access Control",
              "source": "sparse",
              "original_content": "The product does not restrict or incorrectly restricts access to a resource from an unauthorized actor.",
              "keyphrase_sources": [
                {
                  "id": "rootcause:insufficient randomness",
                  "keyphrase": "insufficient randomness",
                  "type": "rootcause"
                }
              ]
            },
            "similarity": 391.3270605378732
          }
        ]
      },
      "rootcause:generate_unique_string": {
        "keyphrase": "generate_unique_string",
        "type": "rootcause",
        "cwes": [
          {
            "metadata": {
              "doc_id": "862",
              "name": "Missing Authorization",
              "source": "sparse",
              "original_content": "The product does not perform an authorization check when an actor attempts to access a resource or perform an action."
            },
            "similarity": 390.6547300315255
          },
          {
            "metadata": {
              "doc_id": "639",
              "name": "Authorization Bypass Through User-Controlled Key",
              "source": "sparse",
              "original_content": "The system's authorization functionality does not prevent one user from gaining access to another user's data or record by modifying the key value identifying the data.",
              "keyphrase_sources": [
                {
                  "id": "rootcause:generate_unique_string",
                  "keyphrase": "generate_unique_string",
                  "type": "rootcause"
                },
                {
                  "id": "weakness:Sensitive Information Exposure",
                  "keyphrase": "Sensitive Information Exposure",
                  "type": "weakness"
                },
                {
                  "id": "impact:extract sensitive data",
                  "keyphrase": "extract sensitive data",
                  "type": "impact"
                },
                {
                  "id": "attacker:unauthenticated attackers",
                  "keyphrase": "unauthenticated attackers",
                  "type": "attacker"
                },
                {
                  "id": "product:Prevent Direct Access Protect WordPress Files plugin",
                  "keyphrase": "Prevent Direct Access Protect WordPress Files plugin",
                  "type": "product"
                }
              ]
            },
            "similarity": 389.34185355478144
          },
          {
            "metadata": {
              "doc_id": "306",
              "name": "Missing Authentication for Critical Function",
              "source": "sparse",
              "original_content": "The product does not perform any authentication for functionality that requires a provable user identity or consumes a significant amount of resources.",
              "keyphrase_sources": [
                {
                  "id": "rootcause:generate_unique_string",
                  "keyphrase": "generate_unique_string",
                  "type": "rootcause"
                },
                {
                  "id": "weakness:Sensitive Information Exposure",
                  "keyphrase": "Sensitive Information Exposure",
                  "type": "weakness"
                },
                {
                  "id": "impact:extract sensitive data",
                  "keyphrase": "extract sensitive data",
                  "type": "impact"
                },
                {
                  "id": "attacker:unauthenticated attackers",
                  "keyphrase": "unauthenticated attackers",
                  "type": "attacker"
                },
                {
                  "id": "version:all versions up to and including 2.8.8",
                  "keyphrase": "all versions up to and including 2.8.8",
                  "type": "version"
                }
              ]
            },
            "similarity": 388.44511356788684
          },
          {
            "metadata": {
              "doc_id": "352",
              "name": "Cross-Site Request Forgery (CSRF)",
              "source": "sparse",
              "original_content": "The web application does not, or can not, sufficiently verify whether a well-formed, valid, consistent request was intentionally provided by the user who submitted the request."
            },
            "similarity": 388.3800335741828
          },
          {
            "metadata": {
              "doc_id": "863",
              "name": "Incorrect Authorization",
              "source": "sparse",
              "original_content": "The product performs an authorization check when an actor attempts to access a resource or perform an action, but it does not correctly perform the check."
            },
            "similarity": 386.7380182733057
          }
        ]
      },
      "weakness:Sensitive Information Exposure": {
        "keyphrase": "Sensitive Information Exposure",
        "type": "weakness",
        "cwes": [
          {
            "metadata": {
              "doc_id": "200",
              "name": "Exposure of Sensitive Information to an Unauthorized Actor",
              "source": "sparse",
              "original_content": "The product exposes sensitive information to an actor that is not explicitly authorized to have access to that information.",
              "keyphrase_sources": [
                {
                  "id": "weakness:Sensitive Information Exposure",
                  "keyphrase": "Sensitive Information Exposure",
                  "type": "weakness"
                },
                {
                  "id": "impact:extract sensitive data",
                  "keyphrase": "extract sensitive data",
                  "type": "impact"
                },
                {
                  "id": "attacker:unauthenticated attackers",
                  "keyphrase": "unauthenticated attackers",
                  "type": "attacker"
                }
              ]
            },
            "similarity": 405.6778236148703
          },
          {
            "metadata": {
              "doc_id": "639",
              "name": "Authorization Bypass Through User-Controlled Key",
              "source": "sparse",
              "original_content": "The system's authorization functionality does not prevent one user from gaining access to another user's data or record by modifying the key value identifying the data."
            },
            "similarity": 383.2938162432469
          },
          {
            "metadata": {
              "doc_id": "862",
              "name": "Missing Authorization",
              "source": "sparse",
              "original_content": "The product does not perform an authorization check when an actor attempts to access a resource or perform an action."
            },
            "similarity": 380.8651997604949
          },
          {
            "metadata": {
              "doc_id": "863",
              "name": "Incorrect Authorization",
              "source": "sparse",
              "original_content": "The product performs an authorization check when an actor attempts to access a resource or perform an action, but it does not correctly perform the check."
            },
            "similarity": 379.63845577274924
          },
          {
            "metadata": {
              "doc_id": "306",
              "name": "Missing Authentication for Critical Function",
              "source": "sparse",
              "original_content": "The product does not perform any authentication for functionality that requires a provable user identity or consumes a significant amount of resources."
            },
            "similarity": 379.5387045454948
          }
        ]
      },
      "impact:extract sensitive data": {
        "keyphrase": "extract sensitive data",
        "type": "impact",
        "cwes": [
          {
            "metadata": {
              "doc_id": "200",
              "name": "Exposure of Sensitive Information to an Unauthorized Actor",
              "source": "sparse",
              "original_content": "The product exposes sensitive information to an actor that is not explicitly authorized to have access to that information."
            },
            "similarity": 134.65983899477797
          },
          {
            "metadata": {
              "doc_id": "306",
              "name": "Missing Authentication for Critical Function",
              "source": "sparse",
              "original_content": "The product does not perform any authentication for functionality that requires a provable user identity or consumes a significant amount of resources."
            },
            "similarity": 134.42917302294848
          },
          {
            "metadata": {
              "doc_id": "639",
              "name": "Authorization Bypass Through User-Controlled Key",
              "source": "sparse",
              "original_content": "The system's authorization functionality does not prevent one user from gaining access to another user's data or record by modifying the key value identifying the data."
            },
            "similarity": 133.8252467761457
          },
          {
            "metadata": {
              "doc_id": "862",
              "name": "Missing Authorization",
              "source": "sparse",
              "original_content": "The product does not perform an authorization check when an actor attempts to access a resource or perform an action."
            },
            "similarity": 133.16321305631323
          },
          {
            "metadata": {
              "doc_id": "522",
              "name": "Insufficiently Protected Credentials",
              "source": "sparse",
              "original_content": "The product transmits or stores authentication credentials, but it uses an insecure method that is susceptible to unauthorized interception and/or retrieval.",
              "keyphrase_sources": [
                {
                  "id": "impact:extract sensitive data",
                  "keyphrase": "extract sensitive data",
                  "type": "impact"
                },
                {
                  "id": "version:all versions up to and including 2.8.8",
                  "keyphrase": "all versions up to and including 2.8.8",
                  "type": "version"
                }
              ]
            },
            "similarity": 132.97906946238882
          }
        ]
      },
      "attacker:unauthenticated attackers": {
        "keyphrase": "unauthenticated attackers",
        "type": "attacker",
        "cwes": [
          {
            "metadata": {
              "doc_id": "306",
              "name": "Missing Authentication for Critical Function",
              "source": "sparse",
              "original_content": "The product does not perform any authentication for functionality that requires a provable user identity or consumes a significant amount of resources."
            },
            "similarity": 136.64790114864417
          },
          {
            "metadata": {
              "doc_id": "862",
              "name": "Missing Authorization",
              "source": "sparse",
              "original_content": "The product does not perform an authorization check when an actor attempts to access a resource or perform an action."
            },
            "similarity": 136.15824160793733
          },
          {
            "metadata": {
              "doc_id": "352",
              "name": "Cross-Site Request Forgery (CSRF)",
              "source": "sparse",
              "original_content": "The web application does not, or can not, sufficiently verify whether a well-formed, valid, consistent request was intentionally provided by the user who submitted the request."
            },
            "similarity": 136.00898598027808
          },
          {
            "metadata": {
              "doc_id": "639",
              "name": "Authorization Bypass Through User-Controlled Key",
              "source": "sparse",
              "original_content": "The system's authorization functionality does not prevent one user from gaining access to another user's data or record by modifying the key value identifying the data."
            },
            "similarity": 135.66632889148977
          },
          {
            "metadata": {
              "doc_id": "200",
              "name": "Exposure of Sensitive Information to an Unauthorized Actor",
              "source": "sparse",
              "original_content": "The product exposes sensitive information to an actor that is not explicitly authorized to have access to that information."
            },
            "similarity": 134.32918475023476
          }
        ]
      },
      "product:Prevent Direct Access Protect WordPress Files plugin": {
        "keyphrase": "Prevent Direct Access Protect WordPress Files plugin",
        "type": "product",
        "cwes": [
          {
            "metadata": {
              "doc_id": "425",
              "name": "Direct Request ('Forced Browsing')",
              "source": "sparse",
              "original_content": "The web application does not adequately enforce appropriate authorization on all restricted URLs, scripts, or files.",
              "keyphrase_sources": [
                {
                  "id": "product:Prevent Direct Access Protect WordPress Files plugin",
                  "keyphrase": "Prevent Direct Access Protect WordPress Files plugin",
                  "type": "product"
                }
              ]
            },
            "similarity": 167.69558634606562
          },
          {
            "metadata": {
              "doc_id": "352",
              "name": "Cross-Site Request Forgery (CSRF)",
              "source": "sparse",
              "original_content": "The web application does not, or can not, sufficiently verify whether a well-formed, valid, consistent request was intentionally provided by the user who submitted the request."
            },
            "similarity": 163.88490879489606
          },
          {
            "metadata": {
              "doc_id": "639",
              "name": "Authorization Bypass Through User-Controlled Key",
              "source": "sparse",
              "original_content": "The system's authorization functionality does not prevent one user from gaining access to another user's data or record by modifying the key value identifying the data."
            },
            "similarity": 161.15134422549886
          },
          {
            "metadata": {
              "doc_id": "862",
              "name": "Missing Authorization",
              "source": "sparse",
              "original_content": "The product does not perform an authorization check when an actor attempts to access a resource or perform an action."
            },
            "similarity": 160.70052486687348
          },
          {
            "metadata": {
              "doc_id": "285",
              "name": "Improper Authorization",
              "source": "sparse",
              "original_content": "The product does not perform or incorrectly performs an authorization check when an actor attempts to access a resource or perform an action.",
              "keyphrase_sources": [
                {
                  "id": "product:Prevent Direct Access Protect WordPress Files plugin",
                  "keyphrase": "Prevent Direct Access Protect WordPress Files plugin",
                  "type": "product"
                }
              ]
            },
            "similarity": 158.1413540697226
          }
        ]
      },
      "version:all versions up to and including 2.8.8": {
        "keyphrase": "all versions up to and including 2.8.8",
        "type": "version",
        "cwes": [
          {
            "metadata": {
              "doc_id": "306",
              "name": "Missing Authentication for Critical Function",
              "source": "sparse",
              "original_content": "The product does not perform any authentication for functionality that requires a provable user identity or consumes a significant amount of resources."
            },
            "similarity": 164.71082343366936
          },
          {
            "metadata": {
              "doc_id": "862",
              "name": "Missing Authorization",
              "source": "sparse",
              "original_content": "The product does not perform an authorization check when an actor attempts to access a resource or perform an action."
            },
            "similarity": 164.43887674536438
          },
          {
            "metadata": {
              "doc_id": "522",
              "name": "Insufficiently Protected Credentials",
              "source": "sparse",
              "original_content": "The product transmits or stores authentication credentials, but it uses an insecure method that is susceptible to unauthorized interception and/or retrieval."
            },
            "similarity": 164.16051606673446
          },
          {
            "metadata": {
              "doc_id": "138",
              "name": "Improper Neutralization of Special Elements",
              "source": "sparse",
              "original_content": "The product receives input from an upstream component, but it does not neutralize or incorrectly neutralizes special elements that could be interpreted as control elements or syntactic markers when they are sent to a downstream component."
            },
            "similarity": 164.00875971015586
          },
          {
            "metadata": {
              "doc_id": "863",
              "name": "Incorrect Authorization",
              "source": "sparse",
              "original_content": "The product performs an authorization check when an actor attempts to access a resource or perform an action, but it does not correctly perform the check."
            },
            "similarity": 163.7938267124768
          }
        ]
      }
    },
    "keyphrase_mapping": {
      "863": [
        {
          "id": "rootcause:insufficient randomness",
          "keyphrase": "insufficient randomness",
          "type": "rootcause"
        },
        {
          "id": "rootcause:generate_unique_string",
          "keyphrase": "generate_unique_string",
          "type": "rootcause"
        },
        {
          "id": "weakness:Sensitive Information Exposure",
          "keyphrase": "Sensitive Information Exposure",
          "type": "weakness"
        },
        {
          "id": "version:all versions up to and including 2.8.8",
          "keyphrase": "all versions up to and including 2.8.8",
          "type": "version"
        }
      ],
      "138": [
        {
          "id": "rootcause:insufficient randomness",
          "keyphrase": "insufficient randomness",
          "type": "rootcause"
        },
        {
          "id": "version:all versions up to and including 2.8.8",
          "keyphrase": "all versions up to and including 2.8.8",
          "type": "version"
        }
      ],
      "862": [
        {
          "id": "rootcause:insufficient randomness",
          "keyphrase": "insufficient randomness",
          "type": "rootcause"
        },
        {
          "id": "rootcause:generate_unique_string",
          "keyphrase": "generate_unique_string",
          "type": "rootcause"
        },
        {
          "id": "weakness:Sensitive Information Exposure",
          "keyphrase": "Sensitive Information Exposure",
          "type": "weakness"
        },
        {
          "id": "impact:extract sensitive data",
          "keyphrase": "extract sensitive data",
          "type": "impact"
        },
        {
          "id": "attacker:unauthenticated attackers",
          "keyphrase": "unauthenticated attackers",
          "type": "attacker"
        },
        {
          "id": "product:Prevent Direct Access Protect WordPress Files plugin",
          "keyphrase": "Prevent Direct Access Protect WordPress Files plugin",
          "type": "product"
        },
        {
          "id": "version:all versions up to and including 2.8.8",
          "keyphrase": "all versions up to and including 2.8.8",
          "type": "version"
        }
      ],
      "352": [
        {
          "id": "rootcause:insufficient randomness",
          "keyphrase": "insufficient randomness",
          "type": "rootcause"
        },
        {
          "id": "rootcause:generate_unique_string",
          "keyphrase": "generate_unique_string",
          "type": "rootcause"
        },
        {
          "id": "attacker:unauthenticated attackers",
          "keyphrase": "unauthenticated attackers",
          "type": "attacker"
        },
        {
          "id": "product:Prevent Direct Access Protect WordPress Files plugin",
          "keyphrase": "Prevent Direct Access Protect WordPress Files plugin",
          "type": "product"
        }
      ],
      "284": [
        {
          "id": "rootcause:insufficient randomness",
          "keyphrase": "insufficient randomness",
          "type": "rootcause"
        }
      ],
      "639": [
        {
          "id": "rootcause:generate_unique_string",
          "keyphrase": "generate_unique_string",
          "type": "rootcause"
        },
        {
          "id": "weakness:Sensitive Information Exposure",
          "keyphrase": "Sensitive Information Exposure",
          "type": "weakness"
        },
        {
          "id": "impact:extract sensitive data",
          "keyphrase": "extract sensitive data",
          "type": "impact"
        },
        {
          "id": "attacker:unauthenticated attackers",
          "keyphrase": "unauthenticated attackers",
          "type": "attacker"
        },
        {
          "id": "product:Prevent Direct Access Protect WordPress Files plugin",
          "keyphrase": "Prevent Direct Access Protect WordPress Files plugin",
          "type": "product"
        }
      ],
      "306": [
        {
          "id": "rootcause:generate_unique_string",
          "keyphrase": "generate_unique_string",
          "type": "rootcause"
        },
        {
          "id": "weakness:Sensitive Information Exposure",
          "keyphrase": "Sensitive Information Exposure",
          "type": "weakness"
        },
        {
          "id": "impact:extract sensitive data",
          "keyphrase": "extract sensitive data",
          "type": "impact"
        },
        {
          "id": "attacker:unauthenticated attackers",
          "keyphrase": "unauthenticated attackers",
          "type": "attacker"
        },
        {
          "id": "version:all versions up to and including 2.8.8",
          "keyphrase": "all versions up to and including 2.8.8",
          "type": "version"
        }
      ],
      "200": [
        {
          "id": "weakness:Sensitive Information Exposure",
          "keyphrase": "Sensitive Information Exposure",
          "type": "weakness"
        },
        {
          "id": "impact:extract sensitive data",
          "keyphrase": "extract sensitive data",
          "type": "impact"
        },
        {
          "id": "attacker:unauthenticated attackers",
          "keyphrase": "unauthenticated attackers",
          "type": "attacker"
        }
      ],
      "522": [
        {
          "id": "impact:extract sensitive data",
          "keyphrase": "extract sensitive data",
          "type": "impact"
        },
        {
          "id": "version:all versions up to and including 2.8.8",
          "keyphrase": "all versions up to and including 2.8.8",
          "type": "version"
        }
      ],
      "425": [
        {
          "id": "product:Prevent Direct Access Protect WordPress Files plugin",
          "keyphrase": "Prevent Direct Access Protect WordPress Files plugin",
          "type": "product"
        }
      ],
      "285": [
        {
          "id": "product:Prevent Direct Access Protect WordPress Files plugin",
          "keyphrase": "Prevent Direct Access Protect WordPress Files plugin",
          "type": "product"
        }
      ]
    },
    "relevant_cwes": [
      {
        "metadata": {
          "doc_id": "200",
          "name": "Exposure of Sensitive Information to an Unauthorized Actor",
          "source": "sparse",
          "original_content": "The product exposes sensitive information to an actor that is not explicitly authorized to have access to that information.",
          "keyphrase_sources": [
            {
              "id": "weakness:Sensitive Information Exposure",
              "keyphrase": "Sensitive Information Exposure",
              "type": "weakness"
            },
            {
              "id": "impact:extract sensitive data",
              "keyphrase": "extract sensitive data",
              "type": "impact"
            },
            {
              "id": "attacker:unauthenticated attackers",
              "keyphrase": "unauthenticated attackers",
              "type": "attacker"
            }
          ]
        },
        "similarity": 405.6778236148703
      },
      {
        "metadata": {
          "doc_id": "863",
          "name": "Incorrect Authorization",
          "source": "sparse",
          "original_content": "The product performs an authorization check when an actor attempts to access a resource or perform an action, but it does not correctly perform the check.",
          "keyphrase_sources": [
            {
              "id": "rootcause:insufficient randomness",
              "keyphrase": "insufficient randomness",
              "type": "rootcause"
            },
            {
              "id": "rootcause:generate_unique_string",
              "keyphrase": "generate_unique_string",
              "type": "rootcause"
            },
            {
              "id": "weakness:Sensitive Information Exposure",
              "keyphrase": "Sensitive Information Exposure",
              "type": "weakness"
            },
            {
              "id": "version:all versions up to and including 2.8.8",
              "keyphrase": "all versions up to and including 2.8.8",
              "type": "version"
            }
          ]
        },
        "similarity": 400.3018902082541
      },
      {
        "metadata": {
          "doc_id": "138",
          "name": "Improper Neutralization of Special Elements",
          "source": "sparse",
          "original_content": "The product receives input from an upstream component, but it does not neutralize or incorrectly neutralizes special elements that could be interpreted as control elements or syntactic markers when they are sent to a downstream component.",
          "keyphrase_sources": [
            {
              "id": "rootcause:insufficient randomness",
              "keyphrase": "insufficient randomness",
              "type": "rootcause"
            },
            {
              "id": "version:all versions up to and including 2.8.8",
              "keyphrase": "all versions up to and including 2.8.8",
              "type": "version"
            }
          ]
        },
        "similarity": 396.81141621664585
      },
      {
        "metadata": {
          "doc_id": "862",
          "name": "Missing Authorization",
          "source": "sparse",
          "original_content": "The product does not perform an authorization check when an actor attempts to access a resource or perform an action.",
          "keyphrase_sources": [
            {
              "id": "rootcause:insufficient randomness",
              "keyphrase": "insufficient randomness",
              "type": "rootcause"
            },
            {
              "id": "rootcause:generate_unique_string",
              "keyphrase": "generate_unique_string",
              "type": "rootcause"
            },
            {
              "id": "weakness:Sensitive Information Exposure",
              "keyphrase": "Sensitive Information Exposure",
              "type": "weakness"
            },
            {
              "id": "impact:extract sensitive data",
              "keyphrase": "extract sensitive data",
              "type": "impact"
            },
            {
              "id": "attacker:unauthenticated attackers",
              "keyphrase": "unauthenticated attackers",
              "type": "attacker"
            },
            {
              "id": "product:Prevent Direct Access Protect WordPress Files plugin",
              "keyphrase": "Prevent Direct Access Protect WordPress Files plugin",
              "type": "product"
            },
            {
              "id": "version:all versions up to and including 2.8.8",
              "keyphrase": "all versions up to and including 2.8.8",
              "type": "version"
            }
          ]
        },
        "similarity": 393.75331643817884
      },
      {
        "metadata": {
          "doc_id": "352",
          "name": "Cross-Site Request Forgery (CSRF)",
          "source": "sparse",
          "original_content": "The web application does not, or can not, sufficiently verify whether a well-formed, valid, consistent request was intentionally provided by the user who submitted the request.",
          "keyphrase_sources": [
            {
              "id": "rootcause:insufficient randomness",
              "keyphrase": "insufficient randomness",
              "type": "rootcause"
            },
            {
              "id": "rootcause:generate_unique_string",
              "keyphrase": "generate_unique_string",
              "type": "rootcause"
            },
            {
              "id": "attacker:unauthenticated attackers",
              "keyphrase": "unauthenticated attackers",
              "type": "attacker"
            },
            {
              "id": "product:Prevent Direct Access Protect WordPress Files plugin",
              "keyphrase": "Prevent Direct Access Protect WordPress Files plugin",
              "type": "product"
            }
          ]
        },
        "similarity": 393.4446426862223
      },
      {
        "metadata": {
          "doc_id": "284",
          "name": "Improper Access Control",
          "source": "sparse",
          "original_content": "The product does not restrict or incorrectly restricts access to a resource from an unauthorized actor.",
          "keyphrase_sources": [
            {
              "id": "rootcause:insufficient randomness",
              "keyphrase": "insufficient randomness",
              "type": "rootcause"
            }
          ]
        },
        "similarity": 391.3270605378732
      },
      {
        "metadata": {
          "doc_id": "639",
          "name": "Authorization Bypass Through User-Controlled Key",
          "source": "sparse",
          "original_content": "The system's authorization functionality does not prevent one user from gaining access to another user's data or record by modifying the key value identifying the data.",
          "keyphrase_sources": [
            {
              "id": "rootcause:generate_unique_string",
              "keyphrase": "generate_unique_string",
              "type": "rootcause"
            },
            {
              "id": "weakness:Sensitive Information Exposure",
              "keyphrase": "Sensitive Information Exposure",
              "type": "weakness"
            },
            {
              "id": "impact:extract sensitive data",
              "keyphrase": "extract sensitive data",
              "type": "impact"
            },
            {
              "id": "attacker:unauthenticated attackers",
              "keyphrase": "unauthenticated attackers",
              "type": "attacker"
            },
            {
              "id": "product:Prevent Direct Access Protect WordPress Files plugin",
              "keyphrase": "Prevent Direct Access Protect WordPress Files plugin",
              "type": "product"
            }
          ]
        },
        "similarity": 389.34185355478144
      },
      {
        "metadata": {
          "doc_id": "306",
          "name": "Missing Authentication for Critical Function",
          "source": "sparse",
          "original_content": "The product does not perform any authentication for functionality that requires a provable user identity or consumes a significant amount of resources.",
          "keyphrase_sources": [
            {
              "id": "rootcause:generate_unique_string",
              "keyphrase": "generate_unique_string",
              "type": "rootcause"
            },
            {
              "id": "weakness:Sensitive Information Exposure",
              "keyphrase": "Sensitive Information Exposure",
              "type": "weakness"
            },
            {
              "id": "impact:extract sensitive data",
              "keyphrase": "extract sensitive data",
              "type": "impact"
            },
            {
              "id": "attacker:unauthenticated attackers",
              "keyphrase": "unauthenticated attackers",
              "type": "attacker"
            },
            {
              "id": "version:all versions up to and including 2.8.8",
              "keyphrase": "all versions up to and including 2.8.8",
              "type": "version"
            }
          ]
        },
        "similarity": 388.44511356788684
      },
      {
        "metadata": {
          "doc_id": "425",
          "name": "Direct Request ('Forced Browsing')",
          "source": "sparse",
          "original_content": "The web application does not adequately enforce appropriate authorization on all restricted URLs, scripts, or files.",
          "keyphrase_sources": [
            {
              "id": "product:Prevent Direct Access Protect WordPress Files plugin",
              "keyphrase": "Prevent Direct Access Protect WordPress Files plugin",
              "type": "product"
            }
          ]
        },
        "similarity": 167.69558634606562
      },
      {
        "metadata": {
          "doc_id": "285",
          "name": "Improper Authorization",
          "source": "sparse",
          "original_content": "The product does not perform or incorrectly performs an authorization check when an actor attempts to access a resource or perform an action.",
          "keyphrase_sources": [
            {
              "id": "product:Prevent Direct Access Protect WordPress Files plugin",
              "keyphrase": "Prevent Direct Access Protect WordPress Files plugin",
              "type": "product"
            }
          ]
        },
        "similarity": 158.1413540697226
      },
      {
        "metadata": {
          "doc_id": "522",
          "name": "Insufficiently Protected Credentials",
          "source": "sparse",
          "original_content": "The product transmits or stores authentication credentials, but it uses an insecure method that is susceptible to unauthorized interception and/or retrieval.",
          "keyphrase_sources": [
            {
              "id": "impact:extract sensitive data",
              "keyphrase": "extract sensitive data",
              "type": "impact"
            },
            {
              "id": "version:all versions up to and including 2.8.8",
              "keyphrase": "all versions up to and including 2.8.8",
              "type": "version"
            }
          ]
        },
        "similarity": 132.97906946238882
      }
    ],
    "enhanced_query": "# Vulnerability Description\n\n    The Prevent Direct Access Protect WordPress Files plugin for WordPress is vulnerable to **Sensitive Information Exposure** in all versions up to, and including, 2.8.8 via the **generate_unique_string** due to **insufficient randomness** of the generated file name. This makes it possible for unauthenticated attackers to extract sensitive data including files protected by the plugin if the attacker can determine the file name.\n\n    # Keyphrase-Specific CWE Analysis\n    This vulnerability contains multiple keyphrases that may map to different CWEs. \n    Please analyze each keyphrase separately and determine the most appropriate CWE(s) for each.\n\n    ## WEAKNESS: 'Sensitive Information Exposure'\n\nRelevant CWEs for this WEAKNESS:\n\n### 1. CWE-200: Exposure of Sensitive Information to an Unauthorized Actor (Score: 405.68)\n\nThe product exposes sensitive information to an actor that is not explicitly authorized to have access to that information....\n\n### 2. CWE-863: Incorrect Authorization (Score: 400.30)\n\nThe product performs an authorization check when an actor attempts to access a resource or perform an action, but it does not correctly perform the check....\n\n### 3. CWE-862: Missing Authorization (Score: 393.75)\n\nThe product does not perform an authorization check when an actor attempts to access a resource or perform an action....\n\n### 4. CWE-639: Authorization Bypass Through User-Controlled Key (Score: 389.34)\n\nThe system's authorization functionality does not prevent one user from gaining access to another user's data or record by modifying the key value identifying the data....\n\n### 5. CWE-306: Missing Authentication for Critical Function (Score: 388.45)\n\nThe product does not perform any authentication for functionality that requires a provable user identity or consumes a significant amount of resources....\n\n## IMPACT: 'extract sensitive data'\n\nRelevant CWEs for this IMPACT:\n\n### 1. CWE-200: Exposure of Sensitive Information to an Unauthorized Actor (Score: 405.68)\n\nThe product exposes sensitive information to an actor that is not explicitly authorized to have access to that information....\n\n### 2. CWE-862: Missing Authorization (Score: 393.75)\n\nThe product does not perform an authorization check when an actor attempts to access a resource or perform an action....\n\n### 3. CWE-639: Authorization Bypass Through User-Controlled Key (Score: 389.34)\n\nThe system's authorization functionality does not prevent one user from gaining access to another user's data or record by modifying the key value identifying the data....\n\n### 4. CWE-306: Missing Authentication for Critical Function (Score: 388.45)\n\nThe product does not perform any authentication for functionality that requires a provable user identity or consumes a significant amount of resources....\n\n### 5. CWE-522: Insufficiently Protected Credentials (Score: 132.98)\n\nThe product transmits or stores authentication credentials, but it uses an insecure method that is susceptible to unauthorized interception and/or retrieval....\n\n## ATTACKER: 'unauthenticated attackers'\n\nRelevant CWEs for this ATTACKER:\n\n### 1. CWE-200: Exposure of Sensitive Information to an Unauthorized Actor (Score: 405.68)\n\nThe product exposes sensitive information to an actor that is not explicitly authorized to have access to that information....\n\n### 2. CWE-862: Missing Authorization (Score: 393.75)\n\nThe product does not perform an authorization check when an actor attempts to access a resource or perform an action....\n\n### 3. CWE-352: Cross-Site Request Forgery (CSRF) (Score: 393.44)\n\nThe web application does not, or can not, sufficiently verify whether a well-formed, valid, consistent request was intentionally provided by the user who submitted the request....\n\n### 4. CWE-639: Authorization Bypass Through User-Controlled Key (Score: 389.34)\n\nThe system's authorization functionality does not prevent one user from gaining access to another user's data or record by modifying the key value identifying the data....\n\n### 5. CWE-306: Missing Authentication for Critical Function (Score: 388.45)\n\nThe product does not perform any authentication for functionality that requires a provable user identity or consumes a significant amount of resources....\n\n## ROOTCAUSE: 'insufficient randomness'\n\nRelevant CWEs for this ROOTCAUSE:\n\n### 1. CWE-863: Incorrect Authorization (Score: 400.30)\n\nThe product performs an authorization check when an actor attempts to access a resource or perform an action, but it does not correctly perform the check....\n\n### 2. CWE-138: Improper Neutralization of Special Elements (Score: 396.81)\n\nThe product receives input from an upstream component, but it does not neutralize or incorrectly neutralizes special elements that could be interpreted as control elements or syntactic markers when they are sent to a downstream component....\n\n### 3. CWE-862: Missing Authorization (Score: 393.75)\n\nThe product does not perform an authorization check when an actor attempts to access a resource or perform an action....\n\n### 4. CWE-352: Cross-Site Request Forgery (CSRF) (Score: 393.44)\n\nThe web application does not, or can not, sufficiently verify whether a well-formed, valid, consistent request was intentionally provided by the user who submitted the request....\n\n### 5. CWE-284: Improper Access Control (Score: 391.33)\n\nThe product does not restrict or incorrectly restricts access to a resource from an unauthorized actor....\n\n## ROOTCAUSE: 'generate_unique_string'\n\nRelevant CWEs for this ROOTCAUSE:\n\n### 1. CWE-863: Incorrect Authorization (Score: 400.30)\n\nThe product performs an authorization check when an actor attempts to access a resource or perform an action, but it does not correctly perform the check....\n\n### 2. CWE-862: Missing Authorization (Score: 393.75)\n\nThe product does not perform an authorization check when an actor attempts to access a resource or perform an action....\n\n### 3. CWE-352: Cross-Site Request Forgery (CSRF) (Score: 393.44)\n\nThe web application does not, or can not, sufficiently verify whether a well-formed, valid, consistent request was intentionally provided by the user who submitted the request....\n\n### 4. CWE-639: Authorization Bypass Through User-Controlled Key (Score: 389.34)\n\nThe system's authorization functionality does not prevent one user from gaining access to another user's data or record by modifying the key value identifying the data....\n\n### 5. CWE-306: Missing Authentication for Critical Function (Score: 388.45)\n\nThe product does not perform any authentication for functionality that requires a provable user identity or consumes a significant amount of resources....\n\n## VERSION: 'all versions up to and including 2.8.8'\n\nRelevant CWEs for this VERSION:\n\n### 1. CWE-863: Incorrect Authorization (Score: 400.30)\n\nThe product performs an authorization check when an actor attempts to access a resource or perform an action, but it does not correctly perform the check....\n\n### 2. CWE-138: Improper Neutralization of Special Elements (Score: 396.81)\n\nThe product receives input from an upstream component, but it does not neutralize or incorrectly neutralizes special elements that could be interpreted as control elements or syntactic markers when they are sent to a downstream component....\n\n### 3. CWE-862: Missing Authorization (Score: 393.75)\n\nThe product does not perform an authorization check when an actor attempts to access a resource or perform an action....\n\n### 4. CWE-306: Missing Authentication for Critical Function (Score: 388.45)\n\nThe product does not perform any authentication for functionality that requires a provable user identity or consumes a significant amount of resources....\n\n### 5. CWE-522: Insufficiently Protected Credentials (Score: 132.98)\n\nThe product transmits or stores authentication credentials, but it uses an insecure method that is susceptible to unauthorized interception and/or retrieval....\n\n## PRODUCT: 'Prevent Direct Access Protect WordPress Files plugin'\n\nRelevant CWEs for this PRODUCT:\n\n### 1. CWE-862: Missing Authorization (Score: 393.75)\n\nThe product does not perform an authorization check when an actor attempts to access a resource or perform an action....\n\n### 2. CWE-352: Cross-Site Request Forgery (CSRF) (Score: 393.44)\n\nThe web application does not, or can not, sufficiently verify whether a well-formed, valid, consistent request was intentionally provided by the user who submitted the request....\n\n### 3. CWE-639: Authorization Bypass Through User-Controlled Key (Score: 389.34)\n\nThe system's authorization functionality does not prevent one user from gaining access to another user's data or record by modifying the key value identifying the data....\n\n### 4. CWE-425: Direct Request ('Forced Browsing') (Score: 167.70)\n\nThe web application does not adequately enforce appropriate authorization on all restricted URLs, scripts, or files....\n\n### 5. CWE-285: Improper Authorization (Score: 158.14)\n\nThe product does not perform or incorrectly performs an authorization check when an actor attempts to access a resource or perform an action....\n\n\n    # Analysis Instructions\n    1. For each keyphrase, identify the most appropriate CWE(s) that represent the weakness.\n    2. Consider how the different keyphrases might relate to each other in the vulnerability chain.\n    3. Provide a final determination of primary CWE(s) and any secondary CWEs.\n    4. Format your response using the standard analysis template.\n\n    Please analyze how these different weaknesses interact and provide a comprehensive CWE classification.\n    "
  },
  "retrieval_time": 1.4098730087280273
}