{
  "cve_id": "CVE-2025-29209",
  "description": "TOTOLINK X18 v9.1.0cu.2024_B20220329 has an unauthorized arbitrary command execution in the enable parameter of the sub_41105C function of cstecgi .cgi.",
  "key_phrases": {
    "rootcause": "",
    "weakness": "",
    "impact": "unauthorized arbitrary command execution",
    "vector": "",
    "attacker": "",
    "product": "TOTOLINK X18",
    "version": "v9.1.0cu.2024_B20220329",
    "component": "cstecgi .cgi"
  },
  "reference_content": null,
  "similar_info": {
    "cwe_distribution": {},
    "cwe_consensus": "",
    "similarity_stats": {
      "thresholds": [],
      "total_samples_by_threshold": {},
      "top_cwes_by_threshold": {}
    }
  },
  "similarity_summary": {
    "consensus_cwe": "",
    "top_cwes": [],
    "confidence_levels": {},
    "total_samples": 0
  },
  "analysis": "# Summary\n| CWE ID | CWE Name | Confidence | CWE Abstraction Level | CWE Vulnerability Mapping Label | CWE-Vulnerability Mapping Notes |\n|---|---|---|---|---|---|\n| CWE-78 | Improper Neutralization of Special Elements used in an OS Command ('OS Command Injection') | 1.0 | Base | Allowed | Primary CWE. The vulnerability description explicitly mentions \"unauthorized arbitrary command execution,\" indicating command injection. |\n| CWE-306 | Missing Authentication for Critical Function | 0.7 | Base | Allowed | Secondary CWE. The vulnerability description explicitly mentions unauthorized access, suggesting a lack of authentication for the vulnerable function. |\n\n## Evidence and Confidence\n\n*   **Confidence Score:** 0.9\n*   **Evidence Strength:** HIGH\n\n## Relationship Analysis\nThe primary relationship that impacted my decision was the parent-child relationship between CWE-74 (Improper Neutralization of Special Elements in Output Used by a Downstream Component ('Injection')) and CWE-78. CWE-78 is a specific type of injection related to OS commands, making it a more precise classification than the more general CWE-74.\n\n```mermaid\ngraph TD\n    cwe78[\"CWE-78: Improper Neutralization of Special Elements used in an OS Command ('OS Command Injection')\"]\n    cwe74[\"CWE-74: Improper Neutralization of Special Elements in Output Used by a Downstream Component ('Injection')\"]\n    cwe306[\"CWE-306: Missing Authentication for Critical Function\"]\n\n    cwe78 -->|CHILDOF| cwe74\n    cwe306 -->|CANPRECEDE| cwe78\n\n    classDef primary fill:#f96,stroke:#333,stroke-width:2px\n    classDef secondary fill:#69f,stroke:#333\n    class cwe78 primary\n    class cwe306 secondary\n```\n\n## Vulnerability Chain\nThe vulnerability chain starts with **missing authentication** (CWE-306), which allows an attacker to reach a vulnerable function. This function then suffers from **improper neutralization of special elements** (CWE-78) during the construction of an OS command, leading to **unauthorized arbitrary command execution**.\n\n## Summary of Analysis\nThe initial analysis strongly pointed towards CWE-78 due to the explicit mention of \"unauthorized arbitrary command execution.\" This aligns perfectly with the definition of OS Command Injection. The presence of \"unauthorized\" also suggested a potential authentication issue, leading to the inclusion of CWE-306 as a secondary weakness.\n\nThe graph relationships reinforced the selection of CWE-78 as a more specific child of CWE-74. The evidence is strong, with the vulnerability description directly mentioning the impact and the affected component. The chosen CWEs are at the optimal level of specificity, accurately reflecting both the root cause and a contributing factor to the vulnerability.\n\nRelevant CWE Information:\n\n# Enhanced Context (25 CWEs)\nThe following CWEs were identified as potentially relevant to this vulnerability:\n\n## Vulnerability Description\nTOTOLINK X18 v9.1.0cu.2024_B20220329 has an unauthorized arbitrary command execution in the enable parameter of the sub_41105C function of cstecgi .cgi.\n\n### Vulnerability Description Key Phrases\n- **impact:** unauthorized arbitrary command execution\n- **product:** TOTOLINK X18\n- **version:** v9.1.0cu.2024_B20220329\n- **component:** cstecgi .cgi\n\n## Retriever Results\n\n### Top Combined Results\n\n| Rank | CWE ID | Name | Abstraction | Usage  | Retrievers | Individual Scores |\n|------|--------|------|-------------|-------|------------|-------------------|\n| 1 | 78 | Improper Neutralization of Special Elements used in an OS Command ('OS Command Injection') | Base | Allowed | sparse | 0.057 |\n| 2 | 790 | Improper Filtering of Special Elements | Class | Allowed-with-Review | sparse | 0.052 |\n| 3 | 121 | Stack-based Buffer Overflow | Variant | Allowed | sparse | 0.047 |\n| 4 | 77 | Improper Neutralization of Special Elements used in a Command ('Command Injection') | Class | Allowed-with-Review | sparse | 0.046 |\n| 5 | 259 | Use of Hard-coded Password | Variant | Allowed | sparse | 0.040 |\n| 6 | 306 | Missing Authentication for Critical Function | Base | Allowed | sparse | 0.039 |\n| 7 | 1287 | Improper Validation of Specified Type of Input | Base | Allowed | sparse | 0.037 |\n| 8 | 138 | Improper Neutralization of Special Elements | Class | Discouraged | sparse | 0.037 |\n| 9 | 96 | Improper Neutralization of Directives in Statically Saved Code ('Static Code Injection') | Base | Allowed | dense | 0.537 |\n| 10 | 88 | Improper Neutralization of Argument Delimiters in a Command ('Argument Injection') | Base | Allowed | graph | 0.002 |\n\n**CWE-78: Improper Neutralization of Special Elements used in an OS Command ('OS Command Injection')**\n\nThe product constructs all or part of an OS command using externally-influenced input from an upstream component, but it does not neutralize or incorrectly neutralizes special elements that could modify the intended OS command when it is sent to a downstream component.\n\nThis CWE perfectly matches the vulnerability description, which indicates arbitrary command execution, a direct consequence of **improper neutralization** in OS command construction.\n\n**CWE-306: Missing Authentication for Critical Function**\n\nThe product does not perform any authentication for a critical function.\n\nThe \"unauthorized\" aspect of the vulnerability description suggests that the affected function lacks proper authentication, aligning with this CWE.\n\n**CWEs Considered But Not Used:**\n\n*   **CWE-790: Improper Filtering of Special Elements:** While filtering is a relevant concept, the description focuses on command execution, making CWE-78 more appropriate.\n*   **CWE-121: Stack-based Buffer Overflow:** There is no explicit mention of buffer overflows in the description.\n*   **CWE-77: Improper Neutralization of Special Elements used in a Command ('Command Injection'):** CWE-78 is a more specific instance of command injection dealing with OS commands.\n*   **CWE-259: Use of Hard-coded Password:** No evidence to suggest the use of hardcoded passwords.\n*   **CWE-1287: Improper Validation of Specified Type of Input:** Input validation is a general concept, but the focus is on command execution.\n*   **CWE-138: Improper Neutralization of Special Elements:** Too generic; CWE-78 is more specific.\n*   **CWE-96: Improper Neutralization of Directives in Statically Saved Code ('Static Code Injection'):** There is no indication of code injection.\n*   **CWE-88: Improper Neutralization of Argument Delimiters in a Command ('Argument Injection'):** There is no indication of argument injection.",
  "analysis_with_relationships": "# Summary\n| CWE ID | CWE Name | Confidence | CWE Abstraction Level | CWE Vulnerability Mapping Label | CWE-Vulnerability Mapping Notes |\n|---|---|---|---|---|---|\n| CWE-78 | Improper Neutralization of Special Elements used in an OS Command ('OS Command Injection') | 1.0 | Base | Allowed | Primary CWE. The vulnerability description explicitly mentions \"unauthorized arbitrary command execution,\" indicating command injection. |\n| CWE-306 | Missing Authentication for Critical Function | 0.7 | Base | Allowed | Secondary CWE. The vulnerability description explicitly mentions unauthorized access, suggesting a lack of authentication for the vulnerable function. |\n\n## Evidence and Confidence\n\n*   **Confidence Score:** 0.9\n*   **Evidence Strength:** HIGH\n\n## Relationship Analysis\nThe primary relationship that impacted my decision was the parent-child relationship between CWE-74 (Improper Neutralization of Special Elements in Output Used by a Downstream Component ('Injection')) and CWE-78. CWE-78 is a specific type of injection related to OS commands, making it a more precise classification than the more general CWE-74.\n\n```mermaid\ngraph TD\n    cwe78[\"CWE-78: Improper Neutralization of Special Elements used in an OS Command ('OS Command Injection')\"]\n    cwe74[\"CWE-74: Improper Neutralization of Special Elements in Output Used by a Downstream Component ('Injection')\"]\n    cwe306[\"CWE-306: Missing Authentication for Critical Function\"]\n\n    cwe78 -->|CHILDOF| cwe74\n    cwe306 -->|CANPRECEDE| cwe78\n\n    classDef primary fill:#f96,stroke:#333,stroke-width:2px\n    classDef secondary fill:#69f,stroke:#333\n    class cwe78 primary\n    class cwe306 secondary\n```\n\n## Vulnerability Chain\nThe vulnerability chain starts with **missing authentication** (CWE-306), which allows an attacker to reach a vulnerable function. This function then suffers from **improper neutralization of special elements** (CWE-78) during the construction of an OS command, leading to **unauthorized arbitrary command execution**.\n\n## Summary of Analysis\nThe initial analysis strongly pointed towards CWE-78 due to the explicit mention of \"unauthorized arbitrary command execution.\" This aligns perfectly with the definition of OS Command Injection. The presence of \"unauthorized\" also suggested a potential authentication issue, leading to the inclusion of CWE-306 as a secondary weakness.\n\nThe graph relationships reinforced the selection of CWE-78 as a more specific child of CWE-74. The evidence is strong, with the vulnerability description directly mentioning the impact and the affected component. The chosen CWEs are at the optimal level of specificity, accurately reflecting both the root cause and a contributing factor to the vulnerability.\n\nRelevant CWE Information:\n\n# Enhanced Context (25 CWEs)\nThe following CWEs were identified as potentially relevant to this vulnerability:\n\n## Vulnerability Description\nTOTOLINK X18 v9.1.0cu.2024_B20220329 has an unauthorized arbitrary command execution in the enable parameter of the sub_41105C function of cstecgi .cgi.\n\n### Vulnerability Description Key Phrases\n- **impact:** unauthorized arbitrary command execution\n- **product:** TOTOLINK X18\n- **version:** v9.1.0cu.2024_B20220329\n- **component:** cstecgi .cgi\n\n## Retriever Results\n\n### Top Combined Results\n\n| Rank | CWE ID | Name | Abstraction | Usage  | Retrievers | Individual Scores |\n|------|--------|------|-------------|-------|------------|-------------------|\n| 1 | 78 | Improper Neutralization of Special Elements used in an OS Command ('OS Command Injection') | Base | Allowed | sparse | 0.057 |\n| 2 | 790 | Improper Filtering of Special Elements | Class | Allowed-with-Review | sparse | 0.052 |\n| 3 | 121 | Stack-based Buffer Overflow | Variant | Allowed | sparse | 0.047 |\n| 4 | 77 | Improper Neutralization of Special Elements used in a Command ('Command Injection') | Class | Allowed-with-Review | sparse | 0.046 |\n| 5 | 259 | Use of Hard-coded Password | Variant | Allowed | sparse | 0.040 |\n| 6 | 306 | Missing Authentication for Critical Function | Base | Allowed | sparse | 0.039 |\n| 7 | 1287 | Improper Validation of Specified Type of Input | Base | Allowed | sparse | 0.037 |\n| 8 | 138 | Improper Neutralization of Special Elements | Class | Discouraged | sparse | 0.037 |\n| 9 | 96 | Improper Neutralization of Directives in Statically Saved Code ('Static Code Injection') | Base | Allowed | dense | 0.537 |\n| 10 | 88 | Improper Neutralization of Argument Delimiters in a Command ('Argument Injection') | Base | Allowed | graph | 0.002 |\n\n**CWE-78: Improper Neutralization of Special Elements used in an OS Command ('OS Command Injection')**\n\nThe product constructs all or part of an OS command using externally-influenced input from an upstream component, but it does not neutralize or incorrectly neutralizes special elements that could modify the intended OS command when it is sent to a downstream component.\n\nThis CWE perfectly matches the vulnerability description, which indicates arbitrary command execution, a direct consequence of **improper neutralization** in OS command construction.\n\n**CWE-306: Missing Authentication for Critical Function**\n\nThe product does not perform any authentication for a critical function.\n\nThe \"unauthorized\" aspect of the vulnerability description suggests that the affected function lacks proper authentication, aligning with this CWE.\n\n**CWEs Considered But Not Used:**\n\n*   **CWE-790: Improper Filtering of Special Elements:** While filtering is a relevant concept, the description focuses on command execution, making CWE-78 more appropriate.\n*   **CWE-121: Stack-based Buffer Overflow:** There is no explicit mention of buffer overflows in the description.\n*   **CWE-77: Improper Neutralization of Special Elements used in a Command ('Command Injection'):** CWE-78 is a more specific instance of command injection dealing with OS commands.\n*   **CWE-259: Use of Hard-coded Password:** No evidence to suggest the use of hardcoded passwords.\n*   **CWE-1287: Improper Validation of Specified Type of Input:** Input validation is a general concept, but the focus is on command execution.\n*   **CWE-138: Improper Neutralization of Special Elements:** Too generic; CWE-78 is more specific.\n*   **CWE-96: Improper Neutralization of Directives in Statically Saved Code ('Static Code Injection'):** There is no indication of code injection.\n*   **CWE-88: Improper Neutralization of Argument Delimiters in a Command ('Argument Injection'):** There is no indication of argument injection.\n\n\n## CWE Relationship Analysis\n\nCurrent CWEs represent these abstraction levels: .\n\n\n### Vulnerability Chain Analysis\n\n**Chain starting from CWE-121:**\n- 121 (Stack-based Buffer Overflow) - ROOT\n\n\n**Chain starting from CWE-77:**\n- 77 (Improper Neutralization of Special Elements used in a Command ('Command Injection')) - ROOT\n\n\n\n### CWE Relationship Diagram\n\n```mermaid\ngraph TD\n    classDef primary fill:#f96,stroke:#333,stroke-width:2px\n    classDef secondary fill:#69f,stroke:#333\n    classDef tertiary fill:#9e9,stroke:#333\n```",
  "criticism": "",
  "resolution": "",
  "relevant_cwes": [
    {
      "metadata": {
        "doc_id": "78",
        "name": "Improper Neutralization of Special Elements used in an OS Command ('OS Command Injection')",
        "source": "sparse"
      },
      "similarity": 56.56031679449868
    },
    {
      "metadata": {
        "doc_id": "790",
        "name": "Improper Filtering of Special Elements",
        "source": "sparse"
      },
      "similarity": 51.668058191768495
    },
    {
      "metadata": {
        "doc_id": "121",
        "name": "Stack-based Buffer Overflow",
        "source": "sparse"
      },
      "similarity": 46.533953604140954
    },
    {
      "metadata": {
        "doc_id": "77",
        "name": "Improper Neutralization of Special Elements used in a Command ('Command Injection')",
        "source": "sparse"
      },
      "similarity": 45.56757101491445
    },
    {
      "metadata": {
        "doc_id": "259",
        "name": "Use of Hard-coded Password",
        "source": "sparse"
      },
      "similarity": 39.762783908506954
    },
    {
      "metadata": {
        "doc_id": "306",
        "name": "Missing Authentication for Critical Function",
        "source": "sparse"
      },
      "similarity": 38.66700817759837
    },
    {
      "metadata": {
        "doc_id": "1287",
        "name": "Improper Validation of Specified Type of Input",
        "source": "sparse"
      },
      "similarity": 37.12356072682372
    },
    {
      "metadata": {
        "doc_id": "138",
        "name": "Improper Neutralization of Special Elements",
        "source": "sparse"
      },
      "similarity": 36.77249496778696
    },
    {
      "metadata": {
        "doc_id": "96",
        "name": "Improper Neutralization of Directives in Statically Saved Code ('Static Code Injection')",
        "type": "Base",
        "original_content": "The product receives input from an upstream component, but it does not neutralize or incorrectly neutralizes code syntax before inserting the input into an executable resource, such as a library, configuration file, or template.",
        "source": "dense",
        "mapping_notes": {
          "usage": "Allowed",
          "rationale": "This CWE entry is at the Base level of abstraction, which is a preferred level of abstraction for mapping to the root causes of vulnerabilities.",
          "comments": "Carefully read both the name and description to ensure that this mapping is an appropriate fit. Do not try to 'force' a mapping to a lower-level Base/Variant simply to comply with this preferred level of abstraction.",
          "reasons": [
            "Acceptable-Use"
          ]
        },
        "score_info": {
          "retrievers": [
            "dense",
            "sparse",
            "graph"
          ],
          "retriever_count": 3,
          "normalized_scores": {
            "dense": 0.5368232327366049,
            "sparse": 35.7780697080618,
            "graph": 1.6386391591674951
          }
        }
      },
      "similarity": 0.5368232327366049
    },
    {
      "doc_id": "88",
      "text": "CWE-88: Improper Neutralization of Argument Delimiters in a Command ('Argument Injection')",
      "score": 2.1762,
      "metadata": {
        "doc_id": "88",
        "name": "Improper Neutralization of Argument Delimiters in a Command ('Argument Injection')",
        "type": "base",
        "original_content": "CWE-88: Improper Neutralization of Argument Delimiters in a Command ('Argument Injection')",
        "relationships": [
          {
            "source_id": "88",
            "target_id": "77",
            "label": "CHILDOF",
            "properties": {
              "ordinal": "Primary",
              "view_id": "1340"
            }
          },
          {
            "source_id": "88",
            "target_id": "77",
            "label": "CHILDOF",
            "properties": {
              "ordinal": "Primary",
              "view_id": "1305"
            }
          },
          {
            "source_id": "88",
            "target_id": "74",
            "label": "CHILDOF",
            "properties": {
              "ordinal": "Primary",
              "view_id": "1003"
            }
          },
          {
            "source_id": "88",
            "target_id": "77",
            "label": "CHILDOF",
            "properties": {
              "ordinal": "Primary",
              "view_id": "1000"
            }
          },
          {
            "source_id": "78",
            "target_id": "88",
            "label": "CANALSOBE",
            "properties": {
              "view_id": "1000"
            }
          },
          {
            "source_id": "77",
            "target_id": "88",
            "label": "PARENTOF",
            "properties": {
              "ordinal": "Primary",
              "view_id": "1000"
            }
          },
          {
            "source_id": "74",
            "target_id": "88",
            "label": "PARENTOF",
            "properties": {
              "ordinal": "Primary",
              "view_id": "1003"
            }
          }
        ],
        "score_components": {
          "relationship_chain": 0.7,
          "abstraction_path": 0.7200000000000001,
          "peer_group": 0.9
        },
        "abstraction_factor": 1.3,
        "graph_path_info": {
          "path_types": [
            "relationship_chain",
            "abstraction_path_down",
            "peer_relationship"
          ],
          "best_paths": {
            "relationship_chain": {
              "path": [
                [
                  "78",
                  "88",
                  "CANALSOBE"
                ]
              ],
              "score": 0.7,
              "type": "relationship_chain",
              "source": "78"
            },
            "abstraction_path_down": {
              "path": [
                [
                  "77",
                  "88",
                  "PARENTOF"
                ]
              ],
              "score": 0.7200000000000001,
              "type": "abstraction_path_down",
              "source": "77"
            },
            "peer_relationship": {
              "path": [
                [
                  "78",
                  "88",
                  "CANALSOBE"
                ]
              ],
              "score": 0.9,
              "type": "peer_relationship",
              "source": "78"
            }
          }
        },
        "abstraction_level": "base",
        "sources": [
          "graph"
        ],
        "source": "graph",
        "mapping_notes": {
          "usage": "Allowed",
          "rationale": "This CWE entry is at the Base level of abstraction, which is a preferred level of abstraction for mapping to the root causes of vulnerabilities.",
          "comments": "Carefully read both the name and description to ensure that this mapping is an appropriate fit. Do not try to 'force' a mapping to a lower-level Base/Variant simply to comply with this preferred level of abstraction.",
          "reasons": [
            "Acceptable-Use"
          ]
        },
        "score_info": {
          "retrievers": [
            "graph"
          ],
          "retriever_count": 1,
          "normalized_scores": {
            "graph": 2.1762
          }
        }
      },
      "similarity": 2.1762
    }
  ],
  "identified_cwes": {
    "analyzer": [
      "CWE-121",
      "CWE-77",
      "CWE-88",
      "CWE-306",
      "CWE-790",
      "CWE-1287",
      "CWE-74",
      "CWE-78",
      "CWE-138",
      "CWE-96",
      "CWE-259"
    ],
    "critic_additional": []
  },
  "keyphrase_cwe_mapping": {}
}