{
  "cve_id": "CVE-2024-38241",
  "description": "Kernel Streaming Service Driver Elevation of Privilege Vulnerability",
  "key_phrases": {
    "rootcause": "",
    "weakness": "",
    "impact": "Elevation of Privilege",
    "vector": "",
    "attacker": "",
    "product": "",
    "version": "",
    "component": "Kernel Streaming Service Driver"
  },
  "reference_content": "UNRELATED",
  "similar_info": {
    "cwe_distribution": {
      "95": {
        "cwe_counts": {
          "CWE-NVD-noinfo": 6
        },
        "total_samples": 6,
        "distribution": [
          {
            "cwes": [
              "CWE-NVD-noinfo"
            ],
            "frequency": 6,
            "proportion": 1.0
          }
        ]
      },
      "90": {
        "cwe_counts": {
          "CWE-NVD-noinfo": 11,
          "CWE-125": 1,
          "CWE-787": 1
        },
        "total_samples": 13,
        "distribution": [
          {
            "cwes": [
              "CWE-NVD-noinfo"
            ],
            "frequency": 11,
            "proportion": 0.846
          },
          {
            "cwes": [
              "CWE-125"
            ],
            "frequency": 1,
            "proportion": 0.077
          },
          {
            "cwes": [
              "CWE-787"
            ],
            "frequency": 1,
            "proportion": 0.077
          }
        ]
      },
      "85": {
        "cwe_counts": {
          "CWE-NVD-noinfo": 11,
          "CWE-125": 1,
          "CWE-787": 1
        },
        "total_samples": 13,
        "distribution": [
          {
            "cwes": [
              "CWE-NVD-noinfo"
            ],
            "frequency": 11,
            "proportion": 0.846
          },
          {
            "cwes": [
              "CWE-125"
            ],
            "frequency": 1,
            "proportion": 0.077
          },
          {
            "cwes": [
              "CWE-787"
            ],
            "frequency": 1,
            "proportion": 0.077
          }
        ]
      },
      "80": {
        "cwe_counts": {
          "CWE-NVD-noinfo": 11,
          "CWE-125": 1,
          "CWE-787": 1
        },
        "total_samples": 13,
        "distribution": [
          {
            "cwes": [
              "CWE-NVD-noinfo"
            ],
            "frequency": 11,
            "proportion": 0.846
          },
          {
            "cwes": [
              "CWE-125"
            ],
            "frequency": 1,
            "proportion": 0.077
          },
          {
            "cwes": [
              "CWE-787"
            ],
            "frequency": 1,
            "proportion": 0.077
          }
        ]
      },
      "75": {
        "cwe_counts": {
          "CWE-NVD-noinfo": 11,
          "CWE-125": 1,
          "CWE-787": 1
        },
        "total_samples": 13,
        "distribution": [
          {
            "cwes": [
              "CWE-NVD-noinfo"
            ],
            "frequency": 11,
            "proportion": 0.846
          },
          {
            "cwes": [
              "CWE-125"
            ],
            "frequency": 1,
            "proportion": 0.077
          },
          {
            "cwes": [
              "CWE-787"
            ],
            "frequency": 1,
            "proportion": 0.077
          }
        ]
      },
      "70": {
        "cwe_counts": {
          "CWE-NVD-noinfo": 11,
          "CWE-125": 1,
          "CWE-787": 1
        },
        "total_samples": 13,
        "distribution": [
          {
            "cwes": [
              "CWE-NVD-noinfo"
            ],
            "frequency": 11,
            "proportion": 0.846
          },
          {
            "cwes": [
              "CWE-125"
            ],
            "frequency": 1,
            "proportion": 0.077
          },
          {
            "cwes": [
              "CWE-787"
            ],
            "frequency": 1,
            "proportion": 0.077
          }
        ]
      }
    },
    "cwe_consensus": "CWE-NVD-noinfo",
    "similarity_stats": {
      "thresholds": [
        95,
        90,
        85,
        80,
        75,
        70
      ],
      "total_samples_by_threshold": {
        "95": 6,
        "90": 13,
        "85": 13,
        "80": 13,
        "75": 13,
        "70": 13
      },
      "top_cwes_by_threshold": {
        "95": [
          [
            "CWE-NVD-noinfo",
            6
          ]
        ],
        "90": [
          [
            "CWE-NVD-noinfo",
            11
          ],
          [
            "CWE-125",
            1
          ],
          [
            "CWE-787",
            1
          ]
        ],
        "85": [
          [
            "CWE-NVD-noinfo",
            11
          ],
          [
            "CWE-125",
            1
          ],
          [
            "CWE-787",
            1
          ]
        ],
        "80": [
          [
            "CWE-NVD-noinfo",
            11
          ],
          [
            "CWE-125",
            1
          ],
          [
            "CWE-787",
            1
          ]
        ],
        "75": [
          [
            "CWE-NVD-noinfo",
            11
          ],
          [
            "CWE-125",
            1
          ],
          [
            "CWE-787",
            1
          ]
        ],
        "70": [
          [
            "CWE-NVD-noinfo",
            11
          ],
          [
            "CWE-125",
            1
          ],
          [
            "CWE-787",
            1
          ]
        ]
      }
    },
    "raw_matches": [
      {
        "similarity": 95,
        "cwes": [
          "NVD-noinfo"
        ],
        "total": 6,
        "frequency": 6,
        "proportion": 1.0
      },
      {
        "similarity": 90,
        "cwes": [
          "NVD-noinfo"
        ],
        "total": 13,
        "frequency": 11,
        "proportion": 0.846
      },
      {
        "similarity": 90,
        "cwes": [
          "125"
        ],
        "total": 13,
        "frequency": 1,
        "proportion": 0.077
      },
      {
        "similarity": 90,
        "cwes": [
          "787"
        ],
        "total": 13,
        "frequency": 1,
        "proportion": 0.077
      },
      {
        "similarity": 85,
        "cwes": [
          "NVD-noinfo"
        ],
        "total": 13,
        "frequency": 11,
        "proportion": 0.846
      },
      {
        "similarity": 85,
        "cwes": [
          "125"
        ],
        "total": 13,
        "frequency": 1,
        "proportion": 0.077
      },
      {
        "similarity": 85,
        "cwes": [
          "787"
        ],
        "total": 13,
        "frequency": 1,
        "proportion": 0.077
      },
      {
        "similarity": 80,
        "cwes": [
          "NVD-noinfo"
        ],
        "total": 13,
        "frequency": 11,
        "proportion": 0.846
      },
      {
        "similarity": 80,
        "cwes": [
          "125"
        ],
        "total": 13,
        "frequency": 1,
        "proportion": 0.077
      },
      {
        "similarity": 80,
        "cwes": [
          "787"
        ],
        "total": 13,
        "frequency": 1,
        "proportion": 0.077
      },
      {
        "similarity": 75,
        "cwes": [
          "NVD-noinfo"
        ],
        "total": 13,
        "frequency": 11,
        "proportion": 0.846
      },
      {
        "similarity": 75,
        "cwes": [
          "125"
        ],
        "total": 13,
        "frequency": 1,
        "proportion": 0.077
      },
      {
        "similarity": 75,
        "cwes": [
          "787"
        ],
        "total": 13,
        "frequency": 1,
        "proportion": 0.077
      },
      {
        "similarity": 70,
        "cwes": [
          "NVD-noinfo"
        ],
        "total": 13,
        "frequency": 11,
        "proportion": 0.846
      },
      {
        "similarity": 70,
        "cwes": [
          "125"
        ],
        "total": 13,
        "frequency": 1,
        "proportion": 0.077
      },
      {
        "similarity": 70,
        "cwes": [
          "787"
        ],
        "total": 13,
        "frequency": 1,
        "proportion": 0.077
      }
    ]
  },
  "similarity_summary": {
    "consensus_cwe": "CWE-NVD-noinfo",
    "top_cwes": [
      [
        "CWE-NVD-noinfo",
        61
      ],
      [
        "CWE-125",
        5
      ],
      [
        "CWE-787",
        5
      ]
    ],
    "confidence_levels": {
      "high": [],
      "medium": [],
      "low": []
    },
    "total_samples": 71
  },
  "analysis": "# Summary\n| CWE ID | CWE Name | Confidence | CWE Abstraction Level | CWE Vulnerability Mapping Label | CWE-Vulnerability Mapping Notes |\n|---|---|---|---|---|---|\n| CWE-782 | Exposed IOCTL with Insufficient Access Control | 0.75 | Variant |  | Allowed |\n\n## Evidence and Confidence\n\n*   **Confidence Score:** 0.75\n*   **Evidence Strength:** LOW\n\n## Relationship Analysis\nThe primary relationship influencing the decision was the hierarchical one. CWE-782 is a variant of CWE-749 (which wasn't in the retriever results), and the vulnerability description hints at an issue related to access control within an IOCTL context. However, due to the lack of detailed information, this relationship serves more as a guiding factor than a definitive confirmation.\n\n```mermaid\ngraph TD\n    cwe782[\"CWE-782: Exposed IOCTL with Insufficient Access Control\"]\n    cwe749[\"CWE-749: Exposed Direct Memory Access to Unauthorized Control Sphere\"]\n    \n    cwe782 -->|CHILDOF| cwe749\n    \n    classDef primary fill:#f96,stroke:#333,stroke-width:2px\n    classDef secondary fill:#69f,stroke:#333\n    class cwe782 primary\n    class cwe749 secondary\n```\n\n## Vulnerability Chain\nThe chain of events is not fully evident from the limited information. The assumed chain is:\n1.  Exposed IOCTL with Insufficient Access Control (CWE-782)\n2.  Elevation of Privilege (Impact)\n\nMissing links: The exact mechanism by which the insufficient access control leads to elevation of privilege is not specified.\n\n## Summary of Analysis\nThe initial assessment focused on the limited information available: \"Kernel Streaming Service Driver Elevation of Privilege Vulnerability\". The primary challenge is the lack of specific details regarding the vulnerability's root cause. The phrase \"Elevation of Privilege\" suggests an access control or privilege management issue.\n\nGiven the limited evidence, CWE-782 \"Exposed IOCTL with Insufficient Access Control\" seems to be the most relevant based on the retriever results and the relationships between the CWEs. It directly relates to a driver context (Kernel Streaming Service Driver) and access control issues. However, the confidence remains relatively low due to the lack of explicit confirmation in the provided information.\n\nRelevant CWE Information:\n\n# Enhanced Context (25 CWEs)\nThe following CWEs were identified as potentially relevant to this vulnerability:\n\n## CWE Classification Guidance\n\nThe following guidance has been automatically included because relevant keywords were detected in the vulnerability description:\n\n### Privileges vs Permissions Guidance\n\n# Complete CWE Specifications\n\nCWE-667: Improper Locking\n\nCWE-1285: Improper Validation of Specified Index, Position, or Offset in Input\n\nCWE-362: Concurrent Execution using Shared Resource with Improper Synchronization ('Race Condition')\n\nCWE-787: Out-of-bounds Write\n\nCWE-59: Improper Link Resolution Before File Access ('Link Following')\n\nCWE-415: Double Free\n\nCWE-367: Time-of-check Time-of-use (TOCTOU) Race Condition\n\nCWE-197: Numeric Truncation Error\n\nCWE-782: Exposed IOCTL with Insufficient Access Control\n\nCWE-363: Race Condition Enabling Link Following\n\nCWE-782 is chosen because it is the most descriptive based on the term \"Kernel Streaming Service Driver\".\n\n**CWE-782: Exposed IOCTL with Insufficient Access Control**\n*   **How the vulnerability's details match the CWE's characteristics:** The vulnerability description mentions a \"Kernel Streaming Service Driver\" and an \"Elevation of Privilege\". IOCTLs (Input/Output Control codes) are a common mechanism for user-mode applications to interact with kernel-mode drivers. If an IOCTL is exposed without proper access control, it could allow unauthorized users to perform privileged operations, leading to elevation of privilege.\n*   **The security implications and potential impact:** An attacker could exploit this vulnerability to gain elevated privileges on the system, potentially leading to arbitrary code execution, data theft, or denial of service.\n*   **Any parent-child relationships or chain patterns that influenced your mapping:** CWE-782 is a Variant of CWE-749 (Exposed Direct Memory Access to Unauthorized Control Sphere) and a child of CWE-749.\n*   **Whether the weakness is primary or secondary in the vulnerability:** This is considered the primary weakness due to its direct relationship to the exposed IOCTL and the resulting elevation of privilege.\n*   **How the official MITRE mapping guidance influenced your decision:** The allowed usage and variant abstraction level makes it a good candidate.\n\n**Other CWEs Considered and Rejected:**\n\n*   CWE-NVD-noinfo: This is too generic and doesn't provide any specific information about the vulnerability.\n*   CWE-787: Out-of-bounds Write: While out-of-bounds writes can lead to elevation of privilege, there's no direct evidence in the description to suggest this is the root cause.\n*   CWE-125: Out-of-bounds Read: Similar to CWE-787, there is no direct evidence.\n*   CWE-667: Improper Locking & CWE-362: Concurrent Execution using Shared Resource with Improper Synchronization ('Race Condition'): These are related to concurrency issues, but there's no information to suggest a race condition is involved.\n*   CWE-59: Improper Link Resolution Before File Access ('Link Following'): This is related to file access issues, and does not fit the vulnerability description.\n*   CWE-415: Double Free: Memory corruption issues are possible but lack direct evidence.\n*   CWE-367: Time-of-check Time-of-use (TOCTOU) Race Condition: Similar to the above race condition CWEs, it lacks specific evidence.\n*   CWE-197: Numeric Truncation Error: There's no indication of numeric truncation.\n*   CWE-363: Race Condition Enabling Link Following: This is related to race conditions and link following, which does not fit the vulnerability description.\n*   CWE-1285: Improper Validation of Specified Index, Position, or Offset in Input: This could be relevant if input validation within the IOCTL is missing, but there isn't enough evidence.",
  "analysis_with_relationships": "# Summary\n| CWE ID | CWE Name | Confidence | CWE Abstraction Level | CWE Vulnerability Mapping Label | CWE-Vulnerability Mapping Notes |\n|---|---|---|---|---|---|\n| CWE-782 | Exposed IOCTL with Insufficient Access Control | 0.75 | Variant |  | Allowed |\n\n## Evidence and Confidence\n\n*   **Confidence Score:** 0.75\n*   **Evidence Strength:** LOW\n\n## Relationship Analysis\nThe primary relationship influencing the decision was the hierarchical one. CWE-782 is a variant of CWE-749 (which wasn't in the retriever results), and the vulnerability description hints at an issue related to access control within an IOCTL context. However, due to the lack of detailed information, this relationship serves more as a guiding factor than a definitive confirmation.\n\n```mermaid\ngraph TD\n    cwe782[\"CWE-782: Exposed IOCTL with Insufficient Access Control\"]\n    cwe749[\"CWE-749: Exposed Direct Memory Access to Unauthorized Control Sphere\"]\n    \n    cwe782 -->|CHILDOF| cwe749\n    \n    classDef primary fill:#f96,stroke:#333,stroke-width:2px\n    classDef secondary fill:#69f,stroke:#333\n    class cwe782 primary\n    class cwe749 secondary\n```\n\n## Vulnerability Chain\nThe chain of events is not fully evident from the limited information. The assumed chain is:\n1.  Exposed IOCTL with Insufficient Access Control (CWE-782)\n2.  Elevation of Privilege (Impact)\n\nMissing links: The exact mechanism by which the insufficient access control leads to elevation of privilege is not specified.\n\n## Summary of Analysis\nThe initial assessment focused on the limited information available: \"Kernel Streaming Service Driver Elevation of Privilege Vulnerability\". The primary challenge is the lack of specific details regarding the vulnerability's root cause. The phrase \"Elevation of Privilege\" suggests an access control or privilege management issue.\n\nGiven the limited evidence, CWE-782 \"Exposed IOCTL with Insufficient Access Control\" seems to be the most relevant based on the retriever results and the relationships between the CWEs. It directly relates to a driver context (Kernel Streaming Service Driver) and access control issues. However, the confidence remains relatively low due to the lack of explicit confirmation in the provided information.\n\nRelevant CWE Information:\n\n# Enhanced Context (25 CWEs)\nThe following CWEs were identified as potentially relevant to this vulnerability:\n\n## CWE Classification Guidance\n\nThe following guidance has been automatically included because relevant keywords were detected in the vulnerability description:\n\n### Privileges vs Permissions Guidance\n\n# Complete CWE Specifications\n\nCWE-667: Improper Locking\n\nCWE-1285: Improper Validation of Specified Index, Position, or Offset in Input\n\nCWE-362: Concurrent Execution using Shared Resource with Improper Synchronization ('Race Condition')\n\nCWE-787: Out-of-bounds Write\n\nCWE-59: Improper Link Resolution Before File Access ('Link Following')\n\nCWE-415: Double Free\n\nCWE-367: Time-of-check Time-of-use (TOCTOU) Race Condition\n\nCWE-197: Numeric Truncation Error\n\nCWE-782: Exposed IOCTL with Insufficient Access Control\n\nCWE-363: Race Condition Enabling Link Following\n\nCWE-782 is chosen because it is the most descriptive based on the term \"Kernel Streaming Service Driver\".\n\n**CWE-782: Exposed IOCTL with Insufficient Access Control**\n*   **How the vulnerability's details match the CWE's characteristics:** The vulnerability description mentions a \"Kernel Streaming Service Driver\" and an \"Elevation of Privilege\". IOCTLs (Input/Output Control codes) are a common mechanism for user-mode applications to interact with kernel-mode drivers. If an IOCTL is exposed without proper access control, it could allow unauthorized users to perform privileged operations, leading to elevation of privilege.\n*   **The security implications and potential impact:** An attacker could exploit this vulnerability to gain elevated privileges on the system, potentially leading to arbitrary code execution, data theft, or denial of service.\n*   **Any parent-child relationships or chain patterns that influenced your mapping:** CWE-782 is a Variant of CWE-749 (Exposed Direct Memory Access to Unauthorized Control Sphere) and a child of CWE-749.\n*   **Whether the weakness is primary or secondary in the vulnerability:** This is considered the primary weakness due to its direct relationship to the exposed IOCTL and the resulting elevation of privilege.\n*   **How the official MITRE mapping guidance influenced your decision:** The allowed usage and variant abstraction level makes it a good candidate.\n\n**Other CWEs Considered and Rejected:**\n\n*   CWE-NVD-noinfo: This is too generic and doesn't provide any specific information about the vulnerability.\n*   CWE-787: Out-of-bounds Write: While out-of-bounds writes can lead to elevation of privilege, there's no direct evidence in the description to suggest this is the root cause.\n*   CWE-125: Out-of-bounds Read: Similar to CWE-787, there is no direct evidence.\n*   CWE-667: Improper Locking & CWE-362: Concurrent Execution using Shared Resource with Improper Synchronization ('Race Condition'): These are related to concurrency issues, but there's no information to suggest a race condition is involved.\n*   CWE-59: Improper Link Resolution Before File Access ('Link Following'): This is related to file access issues, and does not fit the vulnerability description.\n*   CWE-415: Double Free: Memory corruption issues are possible but lack direct evidence.\n*   CWE-367: Time-of-check Time-of-use (TOCTOU) Race Condition: Similar to the above race condition CWEs, it lacks specific evidence.\n*   CWE-197: Numeric Truncation Error: There's no indication of numeric truncation.\n*   CWE-363: Race Condition Enabling Link Following: This is related to race conditions and link following, which does not fit the vulnerability description.\n*   CWE-1285: Improper Validation of Specified Index, Position, or Offset in Input: This could be relevant if input validation within the IOCTL is missing, but there isn't enough evidence.\n\n\n## CWE Relationship Analysis\n\nCurrent CWEs represent these abstraction levels: .\n\n\n### Vulnerability Chain Analysis\n\n**Chain starting from CWE-125:**\n- 125 (Out-of-bounds Read) - ROOT\n\n\n**Chain starting from CWE-59:**\n- 59 (Improper Link Resolution Before File Access ('Link Following')) - ROOT\n\n\n\n### CWE Relationship Diagram\n\n```mermaid\ngraph TD\n    classDef primary fill:#f96,stroke:#333,stroke-width:2px\n    classDef secondary fill:#69f,stroke:#333\n    classDef tertiary fill:#9e9,stroke:#333\n```",
  "criticism": "",
  "resolution": "",
  "relevant_cwes": [
    {
      "metadata": {
        "doc_id": "667",
        "name": "Improper Locking",
        "source": "sparse"
      },
      "similarity": 19.213036521058736
    },
    {
      "metadata": {
        "doc_id": "1285",
        "name": "Improper Validation of Specified Index, Position, or Offset in Input",
        "source": "sparse"
      },
      "similarity": 18.88627128716963
    },
    {
      "metadata": {
        "doc_id": "362",
        "name": "Concurrent Execution using Shared Resource with Improper Synchronization ('Race Condition')",
        "source": "sparse"
      },
      "similarity": 18.37764864082956
    },
    {
      "metadata": {
        "doc_id": "787",
        "name": "Out-of-bounds Write",
        "source": "sparse"
      },
      "similarity": 17.24869656305397
    },
    {
      "metadata": {
        "doc_id": "59",
        "name": "Improper Link Resolution Before File Access ('Link Following')",
        "source": "sparse"
      },
      "similarity": 16.680238896978437
    },
    {
      "metadata": {
        "doc_id": "415",
        "name": "Double Free",
        "source": "sparse"
      },
      "similarity": 16.570127707921202
    },
    {
      "metadata": {
        "doc_id": "367",
        "name": "Time-of-check Time-of-use (TOCTOU) Race Condition",
        "source": "sparse"
      },
      "similarity": 16.29812708344979
    },
    {
      "metadata": {
        "doc_id": "197",
        "name": "Numeric Truncation Error",
        "source": "sparse"
      },
      "similarity": 15.743488782157312
    },
    {
      "metadata": {
        "doc_id": "782",
        "name": "Exposed IOCTL with Insufficient Access Control",
        "type": "Variant",
        "original_content": "The product implements an IOCTL with functionality that should be restricted, but it does not properly enforce access control for the IOCTL.",
        "source": "dense",
        "mapping_notes": {
          "usage": "Allowed",
          "rationale": "This CWE entry is at the Variant level of abstraction, which is a preferred level of abstraction for mapping to the root causes of vulnerabilities.",
          "comments": "Carefully read both the name and description to ensure that this mapping is an appropriate fit. Do not try to 'force' a mapping to a lower-level Base/Variant simply to comply with this preferred level of abstraction.",
          "reasons": [
            "Acceptable-Use"
          ]
        },
        "score_info": {
          "retrievers": [
            "dense"
          ],
          "retriever_count": 1,
          "normalized_scores": {
            "dense": 0.5429865315788126
          }
        }
      },
      "similarity": 0.5429865315788126
    },
    {
      "doc_id": "363",
      "text": "CWE-363: Race Condition Enabling Link Following",
      "score": 2.73416,
      "metadata": {
        "doc_id": "363",
        "name": "Race Condition Enabling Link Following",
        "type": "base",
        "original_content": "CWE-363: Race Condition Enabling Link Following",
        "relationships": [
          {
            "source_id": "363",
            "target_id": "59",
            "label": "CANPRECEDE",
            "properties": {
              "view_id": "1000"
            }
          },
          {
            "source_id": "363",
            "target_id": "367",
            "label": "CHILDOF",
            "properties": {
              "ordinal": "Primary",
              "view_id": "1000"
            }
          },
          {
            "source_id": "59",
            "target_id": "363",
            "label": "CANFOLLOW",
            "properties": {
              "view_id": "1000"
            }
          },
          {
            "source_id": "367",
            "target_id": "363",
            "label": "PARENTOF",
            "properties": {
              "ordinal": "Primary",
              "view_id": "1000"
            }
          }
        ],
        "score_components": {
          "relationship_chain": 1.0,
          "abstraction_path": 0.5760000000000002,
          "sequence_path": 1.0
        },
        "abstraction_factor": 1.3,
        "graph_path_info": {
          "path_types": [
            "relationship_chain",
            "abstraction_path_down",
            "vulnerability_sequence_forward",
            "vulnerability_sequence_backward"
          ],
          "best_paths": {
            "relationship_chain": {
              "path": [
                [
                  "59",
                  "363",
                  "CANFOLLOW"
                ]
              ],
              "score": 1.0,
              "type": "relationship_chain",
              "source": "59"
            },
            "abstraction_path_down": {
              "path": [
                [
                  "362",
                  "367",
                  "PARENTOF"
                ],
                [
                  "367",
                  "363",
                  "PARENTOF"
                ]
              ],
              "score": 0.5760000000000002,
              "type": "abstraction_path_down",
              "source": "362"
            },
            "vulnerability_sequence_forward": {
              "path": [
                [
                  "59",
                  "363",
                  "CANFOLLOW"
                ]
              ],
              "score": 0.9,
              "type": "vulnerability_sequence_forward",
              "source": "59"
            },
            "vulnerability_sequence_backward": {
              "path": [
                [
                  "363",
                  "59",
                  "CANPRECEDE"
                ]
              ],
              "score": 1.0,
              "type": "vulnerability_sequence_backward",
              "source": "59"
            }
          }
        },
        "abstraction_level": "base",
        "position": "before",
        "sources": [
          "graph"
        ],
        "source": "graph",
        "mapping_notes": {
          "usage": "Allowed",
          "rationale": "This CWE entry is at the Base level of abstraction, which is a preferred level of abstraction for mapping to the root causes of vulnerabilities.",
          "comments": "Carefully read both the name and description to ensure that this mapping is an appropriate fit. Do not try to 'force' a mapping to a lower-level Base/Variant simply to comply with this preferred level of abstraction.",
          "reasons": [
            "Acceptable-Use"
          ]
        },
        "score_info": {
          "retrievers": [
            "graph"
          ],
          "retriever_count": 1,
          "normalized_scores": {
            "graph": 2.73416
          }
        }
      },
      "similarity": 2.73416
    }
  ],
  "identified_cwes": {
    "analyzer": [
      "CWE-125",
      "CWE-59",
      "CWE-667",
      "CWE-787",
      "CWE-197",
      "CWE-1285",
      "CWE-363",
      "CWE-782",
      "CWE-362",
      "CWE-749",
      "CWE-367",
      "CWE-415"
    ],
    "critic_additional": []
  },
  "keyphrase_cwe_mapping": {}
}