{
  "vulnerability_info": "VulnerabilityInfo(cve_id='CVE-2024-4641', description='OnCell G3470A-LTE Series firmware versions v1.7.7 and prior have been identified as vulnerable due to accepting a format string from an external source as an argument. An attacker could modify an externally controlled format string to cause a **memory leak** and denial of service.', key_phrases={'rootcause': '', 'weakness': ['format string vulnerability', 'memory leak'], 'impact': 'denial of service', 'vector': 'accepting a format string from an external source as an argument', 'attacker': 'attacker', 'product': 'OnCell G3470A-LTE Series', 'version': 'v1.7.7 and prior', 'component': ''}, reference_content='Based on the provided document, here\\'s the breakdown of CVE-2024-4641:\\n\\n*   **Root cause of vulnerability:** The vulnerability arises from the use of an externally controlled format string. The web application doesn\\'t properly validate or sanitize format strings received from external sources.\\n*   **Weaknesses/vulnerabilities present:** The primary weakness is the lack of proper input validation and the direct use of an external format string in a function that uses format specifiers. This is a classic instance of CWE-134, \"Use of Externally-Controlled Format String.\"\\n*   **Impact of exploitation:** Successful exploitation of this vulnerability could lead to memory leaks, and denial-of-service (DoS) attacks.\\n*   **Attack vectors:** An attacker can exploit this vulnerability by sending crafted input containing malicious format string specifiers to the web service of the affected device.\\n*   **Required attacker capabilities/position:** The attacker needs to have network access to the web service of the OnCell G3470A-LTE device. The vulnerability is exploitable by a low privileged user, and authentication is needed.\\n\\n**Summary:**\\n\\nCVE-2024-4641 is a format string vulnerability found in the web application of Moxa\\'s OnCell G3470A-LTE Series devices. By sending malicious format strings to the vulnerable web service, an attacker with network access can cause a memory leak and a denial-of-service attack.', similar_info={'cwe_distribution': {}, 'cwe_consensus': '', 'similarity_stats': {'thresholds': [], 'total_samples_by_threshold': {}, 'top_cwes_by_threshold': {}}}, similarity_summary=SimilarityInsight(consensus_cwe='', top_cwes=[], confidence_levels={}, total_samples=0), analysis='', analysis_with_relationships='', criticism='', resolution='', relevant_cwes=[{'metadata': {'doc_id': '134', 'name': 'Use of Externally-Controlled Format String', 'source': 'sparse', 'original_content': 'The product uses a function that accepts a format string as an argument, but the format string originates from an external source.', 'keyphrase_sources': [{'id': 'weakness:format string vulnerability', 'keyphrase': 'format string vulnerability', 'type': 'weakness'}, {'id': 'weakness:memory leak', 'keyphrase': 'memory leak', 'type': 'weakness'}, {'id': 'impact:denial of service', 'keyphrase': 'denial of service', 'type': 'impact'}, {'id': 'vector:accepting a format string from an external source as an argument', 'keyphrase': 'accepting a format string from an external source as an argument', 'type': 'vector'}, {'id': 'attacker:attacker', 'keyphrase': 'attacker', 'type': 'attacker'}, {'id': 'product:OnCell G3470A-LTE Series', 'keyphrase': 'OnCell G3470A-LTE Series', 'type': 'product'}, {'id': 'version:v1.7.7 and prior', 'keyphrase': 'v1.7.7 and prior', 'type': 'version'}]}, 'similarity': np.float64(354.12553215049235)}, {'metadata': {'doc_id': '193', 'name': 'Off-by-one Error', 'source': 'sparse', 'original_content': 'A product calculates or uses an incorrect maximum or minimum value that is 1 more, or 1 less, than the correct value.', 'keyphrase_sources': [{'id': 'weakness:format string vulnerability', 'keyphrase': 'format string vulnerability', 'type': 'weakness'}, {'id': 'weakness:memory leak', 'keyphrase': 'memory leak', 'type': 'weakness'}, {'id': 'impact:denial of service', 'keyphrase': 'denial of service', 'type': 'impact'}, {'id': 'vector:accepting a format string from an external source as an argument', 'keyphrase': 'accepting a format string from an external source as an argument', 'type': 'vector'}, {'id': 'attacker:attacker', 'keyphrase': 'attacker', 'type': 'attacker'}]}, 'similarity': np.float64(277.5834332812471)}, {'metadata': {'doc_id': '1286', 'name': 'Improper Validation of Syntactic Correctness of Input', 'source': 'sparse', 'original_content': 'The product receives input that is expected to be well-formed - i.e., to comply with a certain syntax - but it does not validate or incorrectly validates that the input complies with the syntax.', 'keyphrase_sources': [{'id': 'weakness:format string vulnerability', 'keyphrase': 'format string vulnerability', 'type': 'weakness'}, {'id': 'vector:accepting a format string from an external source as an argument', 'keyphrase': 'accepting a format string from an external source as an argument', 'type': 'vector'}, {'id': 'product:OnCell G3470A-LTE Series', 'keyphrase': 'OnCell G3470A-LTE Series', 'type': 'product'}]}, 'similarity': np.float64(272.7335973146869)}, {'metadata': {'doc_id': '1333', 'name': 'Inefficient Regular Expression Complexity', 'source': 'sparse', 'original_content': 'The product uses a regular expression with an inefficient, possibly exponential worst-case computational complexity that consumes excessive CPU cycles.', 'keyphrase_sources': [{'id': 'weakness:format string vulnerability', 'keyphrase': 'format string vulnerability', 'type': 'weakness'}, {'id': 'impact:denial of service', 'keyphrase': 'denial of service', 'type': 'impact'}, {'id': 'vector:accepting a format string from an external source as an argument', 'keyphrase': 'accepting a format string from an external source as an argument', 'type': 'vector'}, {'id': 'attacker:attacker', 'keyphrase': 'attacker', 'type': 'attacker'}, {'id': 'version:v1.7.7 and prior', 'keyphrase': 'v1.7.7 and prior', 'type': 'version'}]}, 'similarity': np.float64(265.6826243400667)}, {'metadata': {'doc_id': '401', 'name': 'Missing Release of Memory after Effective Lifetime', 'source': 'sparse', 'original_content': 'The product does not sufficiently track and release allocated memory after it has been used, which slowly consumes remaining memory.', 'keyphrase_sources': [{'id': 'weakness:memory leak', 'keyphrase': 'memory leak', 'type': 'weakness'}]}, 'similarity': np.float64(265.46865028774977)}, {'metadata': {'doc_id': '125', 'name': 'Out-of-bounds Read', 'source': 'sparse', 'original_content': 'The product reads data past the end, or before the beginning, of the intended buffer.', 'keyphrase_sources': [{'id': 'weakness:memory leak', 'keyphrase': 'memory leak', 'type': 'weakness'}]}, 'similarity': np.float64(261.77318113211845)}, {'metadata': {'doc_id': '88', 'name': \"Improper Neutralization of Argument Delimiters in a Command ('Argument Injection')\", 'source': 'sparse', 'original_content': 'The product constructs a string for a command to be executed by a separate component\\nin another control sphere, but it does not properly delimit the\\nintended arguments, options, or switches within that command string.', 'keyphrase_sources': [{'id': 'weakness:format string vulnerability', 'keyphrase': 'format string vulnerability', 'type': 'weakness'}, {'id': 'vector:accepting a format string from an external source as an argument', 'keyphrase': 'accepting a format string from an external source as an argument', 'type': 'vector'}]}, 'similarity': np.float64(256.9574923294232)}, {'metadata': {'doc_id': '200', 'name': 'Exposure of Sensitive Information to an Unauthorized Actor', 'source': 'sparse', 'original_content': 'The product exposes sensitive information to an actor that is not explicitly authorized to have access to that information.', 'keyphrase_sources': [{'id': 'weakness:memory leak', 'keyphrase': 'memory leak', 'type': 'weakness'}]}, 'similarity': np.float64(255.64964085973511)}, {'metadata': {'doc_id': '284', 'name': 'Improper Access Control', 'source': 'sparse', 'original_content': 'The product does not restrict or incorrectly restricts access to a resource from an unauthorized actor.', 'keyphrase_sources': [{'id': 'version:v1.7.7 and prior', 'keyphrase': 'v1.7.7 and prior', 'type': 'version'}]}, 'similarity': np.float64(107.55804431458938)}, {'metadata': {'doc_id': '121', 'name': 'Stack-based Buffer Overflow', 'source': 'sparse', 'original_content': 'A stack-based buffer overflow condition is a condition where the buffer being overwritten is allocated on the stack (i.e., is a local variable or, rarely, a parameter to a function).', 'keyphrase_sources': [{'id': 'version:v1.7.7 and prior', 'keyphrase': 'v1.7.7 and prior', 'type': 'version'}]}, 'similarity': np.float64(106.37047693719389)}, {'metadata': {'doc_id': '1284', 'name': 'Improper Validation of Specified Quantity in Input', 'source': 'sparse', 'original_content': 'The product receives input that is expected to specify a quantity (such as size or length), but it does not validate or incorrectly validates that the quantity has the required properties.', 'keyphrase_sources': [{'id': 'impact:denial of service', 'keyphrase': 'denial of service', 'type': 'impact'}, {'id': 'attacker:attacker', 'keyphrase': 'attacker', 'type': 'attacker'}]}, 'similarity': np.float64(100.935011574747)}, {'metadata': {'doc_id': '119', 'name': 'Improper Restriction of Operations within the Bounds of a Memory Buffer', 'source': 'sparse', 'original_content': \"The product performs operations on a memory buffer, but it reads from or writes to a memory location outside the buffer's intended boundary. This may result in read or write operations on unexpected memory locations that could be linked to other variables, data structures, or internal program data.\", 'keyphrase_sources': [{'id': 'impact:denial of service', 'keyphrase': 'denial of service', 'type': 'impact'}]}, 'similarity': np.float64(99.97939198629247)}, {'metadata': {'doc_id': '78', 'name': \"Improper Neutralization of Special Elements used in an OS Command ('OS Command Injection')\", 'source': 'sparse', 'original_content': 'The product constructs all or part of an OS command using externally-influenced input from an upstream component, but it does not neutralize or incorrectly neutralizes special elements that could modify the intended OS command when it is sent to a downstream component.', 'keyphrase_sources': [{'id': 'product:OnCell G3470A-LTE Series', 'keyphrase': 'OnCell G3470A-LTE Series', 'type': 'product'}, {'id': 'version:v1.7.7 and prior', 'keyphrase': 'v1.7.7 and prior', 'type': 'version'}]}, 'similarity': np.float64(93.07101432676487)}, {'metadata': {'doc_id': '94', 'name': \"Improper Control of Generation of Code ('Code Injection')\", 'source': 'sparse', 'original_content': 'The product constructs all or part of a code segment using externally-influenced input from an upstream component, but it does not neutralize or incorrectly neutralizes special elements that could modify the syntax or behavior of the intended code segment.', 'keyphrase_sources': [{'id': 'product:OnCell G3470A-LTE Series', 'keyphrase': 'OnCell G3470A-LTE Series', 'type': 'product'}]}, 'similarity': np.float64(92.15935205087544)}, {'metadata': {'doc_id': '20', 'name': 'Improper Input Validation', 'source': 'sparse', 'original_content': 'The product receives input or data, but it does\\n        not validate or incorrectly validates that the input has the\\n        properties that are required to process the data safely and\\n        correctly.', 'keyphrase_sources': [{'id': 'attacker:attacker', 'keyphrase': 'attacker', 'type': 'attacker'}]}, 'similarity': np.float64(91.3138686276623)}, {'metadata': {'doc_id': '345', 'name': 'Insufficient Verification of Data Authenticity', 'source': 'sparse', 'original_content': 'The product does not sufficiently verify the origin or authenticity of data, in a way that causes it to accept invalid data.', 'keyphrase_sources': [{'id': 'product:OnCell G3470A-LTE Series', 'keyphrase': 'OnCell G3470A-LTE Series', 'type': 'product'}]}, 'similarity': np.float64(90.6039203319204)}], identified_cwes={'analyzer': [], 'critic_additional': []})",
  "retrieval_results": {
    "has_multiple_keyphrases": true,
    "keyphrase_cwe_sets": {
      "weakness:format string vulnerability": {
        "keyphrase": "format string vulnerability",
        "type": "weakness",
        "cwes": [
          {
            "metadata": {
              "doc_id": "134",
              "name": "Use of Externally-Controlled Format String",
              "source": "sparse",
              "original_content": "The product uses a function that accepts a format string as an argument, but the format string originates from an external source.",
              "keyphrase_sources": [
                {
                  "id": "weakness:format string vulnerability",
                  "keyphrase": "format string vulnerability",
                  "type": "weakness"
                },
                {
                  "id": "weakness:memory leak",
                  "keyphrase": "memory leak",
                  "type": "weakness"
                },
                {
                  "id": "impact:denial of service",
                  "keyphrase": "denial of service",
                  "type": "impact"
                },
                {
                  "id": "vector:accepting a format string from an external source as an argument",
                  "keyphrase": "accepting a format string from an external source as an argument",
                  "type": "vector"
                },
                {
                  "id": "attacker:attacker",
                  "keyphrase": "attacker",
                  "type": "attacker"
                },
                {
                  "id": "product:OnCell G3470A-LTE Series",
                  "keyphrase": "OnCell G3470A-LTE Series",
                  "type": "product"
                },
                {
                  "id": "version:v1.7.7 and prior",
                  "keyphrase": "v1.7.7 and prior",
                  "type": "version"
                }
              ]
            },
            "similarity": 354.12553215049235
          },
          {
            "metadata": {
              "doc_id": "193",
              "name": "Off-by-one Error",
              "source": "sparse",
              "original_content": "A product calculates or uses an incorrect maximum or minimum value that is 1 more, or 1 less, than the correct value.",
              "keyphrase_sources": [
                {
                  "id": "weakness:format string vulnerability",
                  "keyphrase": "format string vulnerability",
                  "type": "weakness"
                },
                {
                  "id": "weakness:memory leak",
                  "keyphrase": "memory leak",
                  "type": "weakness"
                },
                {
                  "id": "impact:denial of service",
                  "keyphrase": "denial of service",
                  "type": "impact"
                },
                {
                  "id": "vector:accepting a format string from an external source as an argument",
                  "keyphrase": "accepting a format string from an external source as an argument",
                  "type": "vector"
                },
                {
                  "id": "attacker:attacker",
                  "keyphrase": "attacker",
                  "type": "attacker"
                }
              ]
            },
            "similarity": 277.5834332812471
          },
          {
            "metadata": {
              "doc_id": "1286",
              "name": "Improper Validation of Syntactic Correctness of Input",
              "source": "sparse",
              "original_content": "The product receives input that is expected to be well-formed - i.e., to comply with a certain syntax - but it does not validate or incorrectly validates that the input complies with the syntax.",
              "keyphrase_sources": [
                {
                  "id": "weakness:format string vulnerability",
                  "keyphrase": "format string vulnerability",
                  "type": "weakness"
                },
                {
                  "id": "vector:accepting a format string from an external source as an argument",
                  "keyphrase": "accepting a format string from an external source as an argument",
                  "type": "vector"
                },
                {
                  "id": "product:OnCell G3470A-LTE Series",
                  "keyphrase": "OnCell G3470A-LTE Series",
                  "type": "product"
                }
              ]
            },
            "similarity": 272.7335973146869
          },
          {
            "metadata": {
              "doc_id": "1333",
              "name": "Inefficient Regular Expression Complexity",
              "source": "sparse",
              "original_content": "The product uses a regular expression with an inefficient, possibly exponential worst-case computational complexity that consumes excessive CPU cycles.",
              "keyphrase_sources": [
                {
                  "id": "weakness:format string vulnerability",
                  "keyphrase": "format string vulnerability",
                  "type": "weakness"
                },
                {
                  "id": "impact:denial of service",
                  "keyphrase": "denial of service",
                  "type": "impact"
                },
                {
                  "id": "vector:accepting a format string from an external source as an argument",
                  "keyphrase": "accepting a format string from an external source as an argument",
                  "type": "vector"
                },
                {
                  "id": "attacker:attacker",
                  "keyphrase": "attacker",
                  "type": "attacker"
                },
                {
                  "id": "version:v1.7.7 and prior",
                  "keyphrase": "v1.7.7 and prior",
                  "type": "version"
                }
              ]
            },
            "similarity": 265.6826243400667
          },
          {
            "metadata": {
              "doc_id": "88",
              "name": "Improper Neutralization of Argument Delimiters in a Command ('Argument Injection')",
              "source": "sparse",
              "original_content": "The product constructs a string for a command to be executed by a separate component\nin another control sphere, but it does not properly delimit the\nintended arguments, options, or switches within that command string.",
              "keyphrase_sources": [
                {
                  "id": "weakness:format string vulnerability",
                  "keyphrase": "format string vulnerability",
                  "type": "weakness"
                },
                {
                  "id": "vector:accepting a format string from an external source as an argument",
                  "keyphrase": "accepting a format string from an external source as an argument",
                  "type": "vector"
                }
              ]
            },
            "similarity": 256.9574923294232
          }
        ]
      },
      "weakness:memory leak": {
        "keyphrase": "memory leak",
        "type": "weakness",
        "cwes": [
          {
            "metadata": {
              "doc_id": "134",
              "name": "Use of Externally-Controlled Format String",
              "source": "sparse",
              "original_content": "The product uses a function that accepts a format string as an argument, but the format string originates from an external source."
            },
            "similarity": 302.9918913780064
          },
          {
            "metadata": {
              "doc_id": "193",
              "name": "Off-by-one Error",
              "source": "sparse",
              "original_content": "A product calculates or uses an incorrect maximum or minimum value that is 1 more, or 1 less, than the correct value."
            },
            "similarity": 269.7857388118418
          },
          {
            "metadata": {
              "doc_id": "401",
              "name": "Missing Release of Memory after Effective Lifetime",
              "source": "sparse",
              "original_content": "The product does not sufficiently track and release allocated memory after it has been used, which slowly consumes remaining memory.",
              "keyphrase_sources": [
                {
                  "id": "weakness:memory leak",
                  "keyphrase": "memory leak",
                  "type": "weakness"
                }
              ]
            },
            "similarity": 265.46865028774977
          },
          {
            "metadata": {
              "doc_id": "125",
              "name": "Out-of-bounds Read",
              "source": "sparse",
              "original_content": "The product reads data past the end, or before the beginning, of the intended buffer.",
              "keyphrase_sources": [
                {
                  "id": "weakness:memory leak",
                  "keyphrase": "memory leak",
                  "type": "weakness"
                }
              ]
            },
            "similarity": 261.77318113211845
          },
          {
            "metadata": {
              "doc_id": "200",
              "name": "Exposure of Sensitive Information to an Unauthorized Actor",
              "source": "sparse",
              "original_content": "The product exposes sensitive information to an actor that is not explicitly authorized to have access to that information.",
              "keyphrase_sources": [
                {
                  "id": "weakness:memory leak",
                  "keyphrase": "memory leak",
                  "type": "weakness"
                }
              ]
            },
            "similarity": 255.64964085973511
          }
        ]
      },
      "impact:denial of service": {
        "keyphrase": "denial of service",
        "type": "impact",
        "cwes": [
          {
            "metadata": {
              "doc_id": "134",
              "name": "Use of Externally-Controlled Format String",
              "source": "sparse",
              "original_content": "The product uses a function that accepts a format string as an argument, but the format string originates from an external source."
            },
            "similarity": 119.41910671287332
          },
          {
            "metadata": {
              "doc_id": "1333",
              "name": "Inefficient Regular Expression Complexity",
              "source": "sparse",
              "original_content": "The product uses a regular expression with an inefficient, possibly exponential worst-case computational complexity that consumes excessive CPU cycles."
            },
            "similarity": 102.95122318729696
          },
          {
            "metadata": {
              "doc_id": "193",
              "name": "Off-by-one Error",
              "source": "sparse",
              "original_content": "A product calculates or uses an incorrect maximum or minimum value that is 1 more, or 1 less, than the correct value."
            },
            "similarity": 102.42231302166894
          },
          {
            "metadata": {
              "doc_id": "1284",
              "name": "Improper Validation of Specified Quantity in Input",
              "source": "sparse",
              "original_content": "The product receives input that is expected to specify a quantity (such as size or length), but it does not validate or incorrectly validates that the quantity has the required properties.",
              "keyphrase_sources": [
                {
                  "id": "impact:denial of service",
                  "keyphrase": "denial of service",
                  "type": "impact"
                },
                {
                  "id": "attacker:attacker",
                  "keyphrase": "attacker",
                  "type": "attacker"
                }
              ]
            },
            "similarity": 100.935011574747
          },
          {
            "metadata": {
              "doc_id": "119",
              "name": "Improper Restriction of Operations within the Bounds of a Memory Buffer",
              "source": "sparse",
              "original_content": "The product performs operations on a memory buffer, but it reads from or writes to a memory location outside the buffer's intended boundary. This may result in read or write operations on unexpected memory locations that could be linked to other variables, data structures, or internal program data.",
              "keyphrase_sources": [
                {
                  "id": "impact:denial of service",
                  "keyphrase": "denial of service",
                  "type": "impact"
                }
              ]
            },
            "similarity": 99.97939198629247
          }
        ]
      },
      "vector:accepting a format string from an external source as an argument": {
        "keyphrase": "accepting a format string from an external source as an argument",
        "type": "vector",
        "cwes": [
          {
            "metadata": {
              "doc_id": "134",
              "name": "Use of Externally-Controlled Format String",
              "source": "sparse",
              "original_content": "The product uses a function that accepts a format string as an argument, but the format string originates from an external source."
            },
            "similarity": 174.9645847956627
          },
          {
            "metadata": {
              "doc_id": "88",
              "name": "Improper Neutralization of Argument Delimiters in a Command ('Argument Injection')",
              "source": "sparse",
              "original_content": "The product constructs a string for a command to be executed by a separate component\nin another control sphere, but it does not properly delimit the\nintended arguments, options, or switches within that command string."
            },
            "similarity": 139.53071264145814
          },
          {
            "metadata": {
              "doc_id": "1333",
              "name": "Inefficient Regular Expression Complexity",
              "source": "sparse",
              "original_content": "The product uses a regular expression with an inefficient, possibly exponential worst-case computational complexity that consumes excessive CPU cycles."
            },
            "similarity": 134.44291890492528
          },
          {
            "metadata": {
              "doc_id": "193",
              "name": "Off-by-one Error",
              "source": "sparse",
              "original_content": "A product calculates or uses an incorrect maximum or minimum value that is 1 more, or 1 less, than the correct value."
            },
            "similarity": 133.5890166086683
          },
          {
            "metadata": {
              "doc_id": "1286",
              "name": "Improper Validation of Syntactic Correctness of Input",
              "source": "sparse",
              "original_content": "The product receives input that is expected to be well-formed - i.e., to comply with a certain syntax - but it does not validate or incorrectly validates that the input complies with the syntax."
            },
            "similarity": 132.00222200659582
          }
        ]
      },
      "attacker:attacker": {
        "keyphrase": "attacker",
        "type": "attacker",
        "cwes": [
          {
            "metadata": {
              "doc_id": "134",
              "name": "Use of Externally-Controlled Format String",
              "source": "sparse",
              "original_content": "The product uses a function that accepts a format string as an argument, but the format string originates from an external source."
            },
            "similarity": 109.31411390208703
          },
          {
            "metadata": {
              "doc_id": "193",
              "name": "Off-by-one Error",
              "source": "sparse",
              "original_content": "A product calculates or uses an incorrect maximum or minimum value that is 1 more, or 1 less, than the correct value."
            },
            "similarity": 92.71758298084316
          },
          {
            "metadata": {
              "doc_id": "1333",
              "name": "Inefficient Regular Expression Complexity",
              "source": "sparse",
              "original_content": "The product uses a regular expression with an inefficient, possibly exponential worst-case computational complexity that consumes excessive CPU cycles."
            },
            "similarity": 91.51101240163237
          },
          {
            "metadata": {
              "doc_id": "20",
              "name": "Improper Input Validation",
              "source": "sparse",
              "original_content": "The product receives input or data, but it does\n        not validate or incorrectly validates that the input has the\n        properties that are required to process the data safely and\n        correctly.",
              "keyphrase_sources": [
                {
                  "id": "attacker:attacker",
                  "keyphrase": "attacker",
                  "type": "attacker"
                }
              ]
            },
            "similarity": 91.3138686276623
          },
          {
            "metadata": {
              "doc_id": "1284",
              "name": "Improper Validation of Specified Quantity in Input",
              "source": "sparse",
              "original_content": "The product receives input that is expected to specify a quantity (such as size or length), but it does not validate or incorrectly validates that the quantity has the required properties."
            },
            "similarity": 91.20333296024637
          }
        ]
      },
      "product:OnCell G3470A-LTE Series": {
        "keyphrase": "OnCell G3470A-LTE Series",
        "type": "product",
        "cwes": [
          {
            "metadata": {
              "doc_id": "134",
              "name": "Use of Externally-Controlled Format String",
              "source": "sparse",
              "original_content": "The product uses a function that accepts a format string as an argument, but the format string originates from an external source."
            },
            "similarity": 102.72135148903018
          },
          {
            "metadata": {
              "doc_id": "78",
              "name": "Improper Neutralization of Special Elements used in an OS Command ('OS Command Injection')",
              "source": "sparse",
              "original_content": "The product constructs all or part of an OS command using externally-influenced input from an upstream component, but it does not neutralize or incorrectly neutralizes special elements that could modify the intended OS command when it is sent to a downstream component.",
              "keyphrase_sources": [
                {
                  "id": "product:OnCell G3470A-LTE Series",
                  "keyphrase": "OnCell G3470A-LTE Series",
                  "type": "product"
                },
                {
                  "id": "version:v1.7.7 and prior",
                  "keyphrase": "v1.7.7 and prior",
                  "type": "version"
                }
              ]
            },
            "similarity": 93.07101432676487
          },
          {
            "metadata": {
              "doc_id": "1286",
              "name": "Improper Validation of Syntactic Correctness of Input",
              "source": "sparse",
              "original_content": "The product receives input that is expected to be well-formed - i.e., to comply with a certain syntax - but it does not validate or incorrectly validates that the input complies with the syntax."
            },
            "similarity": 92.34265306702429
          },
          {
            "metadata": {
              "doc_id": "94",
              "name": "Improper Control of Generation of Code ('Code Injection')",
              "source": "sparse",
              "original_content": "The product constructs all or part of a code segment using externally-influenced input from an upstream component, but it does not neutralize or incorrectly neutralizes special elements that could modify the syntax or behavior of the intended code segment.",
              "keyphrase_sources": [
                {
                  "id": "product:OnCell G3470A-LTE Series",
                  "keyphrase": "OnCell G3470A-LTE Series",
                  "type": "product"
                }
              ]
            },
            "similarity": 92.15935205087544
          },
          {
            "metadata": {
              "doc_id": "345",
              "name": "Insufficient Verification of Data Authenticity",
              "source": "sparse",
              "original_content": "The product does not sufficiently verify the origin or authenticity of data, in a way that causes it to accept invalid data.",
              "keyphrase_sources": [
                {
                  "id": "product:OnCell G3470A-LTE Series",
                  "keyphrase": "OnCell G3470A-LTE Series",
                  "type": "product"
                }
              ]
            },
            "similarity": 90.6039203319204
          }
        ]
      },
      "version:v1.7.7 and prior": {
        "keyphrase": "v1.7.7 and prior",
        "type": "version",
        "cwes": [
          {
            "metadata": {
              "doc_id": "134",
              "name": "Use of Externally-Controlled Format String",
              "source": "sparse",
              "original_content": "The product uses a function that accepts a format string as an argument, but the format string originates from an external source."
            },
            "similarity": 111.50800258975553
          },
          {
            "metadata": {
              "doc_id": "1333",
              "name": "Inefficient Regular Expression Complexity",
              "source": "sparse",
              "original_content": "The product uses a regular expression with an inefficient, possibly exponential worst-case computational complexity that consumes excessive CPU cycles."
            },
            "similarity": 108.04158672028149
          },
          {
            "metadata": {
              "doc_id": "284",
              "name": "Improper Access Control",
              "source": "sparse",
              "original_content": "The product does not restrict or incorrectly restricts access to a resource from an unauthorized actor.",
              "keyphrase_sources": [
                {
                  "id": "version:v1.7.7 and prior",
                  "keyphrase": "v1.7.7 and prior",
                  "type": "version"
                }
              ]
            },
            "similarity": 107.55804431458938
          },
          {
            "metadata": {
              "doc_id": "121",
              "name": "Stack-based Buffer Overflow",
              "source": "sparse",
              "original_content": "A stack-based buffer overflow condition is a condition where the buffer being overwritten is allocated on the stack (i.e., is a local variable or, rarely, a parameter to a function).",
              "keyphrase_sources": [
                {
                  "id": "version:v1.7.7 and prior",
                  "keyphrase": "v1.7.7 and prior",
                  "type": "version"
                }
              ]
            },
            "similarity": 106.37047693719389
          },
          {
            "metadata": {
              "doc_id": "78",
              "name": "Improper Neutralization of Special Elements used in an OS Command ('OS Command Injection')",
              "source": "sparse",
              "original_content": "The product constructs all or part of an OS command using externally-influenced input from an upstream component, but it does not neutralize or incorrectly neutralizes special elements that could modify the intended OS command when it is sent to a downstream component."
            },
            "similarity": 106.04996111716676
          }
        ]
      }
    },
    "keyphrase_mapping": {
      "134": [
        {
          "id": "weakness:format string vulnerability",
          "keyphrase": "format string vulnerability",
          "type": "weakness"
        },
        {
          "id": "weakness:memory leak",
          "keyphrase": "memory leak",
          "type": "weakness"
        },
        {
          "id": "impact:denial of service",
          "keyphrase": "denial of service",
          "type": "impact"
        },
        {
          "id": "vector:accepting a format string from an external source as an argument",
          "keyphrase": "accepting a format string from an external source as an argument",
          "type": "vector"
        },
        {
          "id": "attacker:attacker",
          "keyphrase": "attacker",
          "type": "attacker"
        },
        {
          "id": "product:OnCell G3470A-LTE Series",
          "keyphrase": "OnCell G3470A-LTE Series",
          "type": "product"
        },
        {
          "id": "version:v1.7.7 and prior",
          "keyphrase": "v1.7.7 and prior",
          "type": "version"
        }
      ],
      "193": [
        {
          "id": "weakness:format string vulnerability",
          "keyphrase": "format string vulnerability",
          "type": "weakness"
        },
        {
          "id": "weakness:memory leak",
          "keyphrase": "memory leak",
          "type": "weakness"
        },
        {
          "id": "impact:denial of service",
          "keyphrase": "denial of service",
          "type": "impact"
        },
        {
          "id": "vector:accepting a format string from an external source as an argument",
          "keyphrase": "accepting a format string from an external source as an argument",
          "type": "vector"
        },
        {
          "id": "attacker:attacker",
          "keyphrase": "attacker",
          "type": "attacker"
        }
      ],
      "1286": [
        {
          "id": "weakness:format string vulnerability",
          "keyphrase": "format string vulnerability",
          "type": "weakness"
        },
        {
          "id": "vector:accepting a format string from an external source as an argument",
          "keyphrase": "accepting a format string from an external source as an argument",
          "type": "vector"
        },
        {
          "id": "product:OnCell G3470A-LTE Series",
          "keyphrase": "OnCell G3470A-LTE Series",
          "type": "product"
        }
      ],
      "1333": [
        {
          "id": "weakness:format string vulnerability",
          "keyphrase": "format string vulnerability",
          "type": "weakness"
        },
        {
          "id": "impact:denial of service",
          "keyphrase": "denial of service",
          "type": "impact"
        },
        {
          "id": "vector:accepting a format string from an external source as an argument",
          "keyphrase": "accepting a format string from an external source as an argument",
          "type": "vector"
        },
        {
          "id": "attacker:attacker",
          "keyphrase": "attacker",
          "type": "attacker"
        },
        {
          "id": "version:v1.7.7 and prior",
          "keyphrase": "v1.7.7 and prior",
          "type": "version"
        }
      ],
      "88": [
        {
          "id": "weakness:format string vulnerability",
          "keyphrase": "format string vulnerability",
          "type": "weakness"
        },
        {
          "id": "vector:accepting a format string from an external source as an argument",
          "keyphrase": "accepting a format string from an external source as an argument",
          "type": "vector"
        }
      ],
      "401": [
        {
          "id": "weakness:memory leak",
          "keyphrase": "memory leak",
          "type": "weakness"
        }
      ],
      "125": [
        {
          "id": "weakness:memory leak",
          "keyphrase": "memory leak",
          "type": "weakness"
        }
      ],
      "200": [
        {
          "id": "weakness:memory leak",
          "keyphrase": "memory leak",
          "type": "weakness"
        }
      ],
      "1284": [
        {
          "id": "impact:denial of service",
          "keyphrase": "denial of service",
          "type": "impact"
        },
        {
          "id": "attacker:attacker",
          "keyphrase": "attacker",
          "type": "attacker"
        }
      ],
      "119": [
        {
          "id": "impact:denial of service",
          "keyphrase": "denial of service",
          "type": "impact"
        }
      ],
      "20": [
        {
          "id": "attacker:attacker",
          "keyphrase": "attacker",
          "type": "attacker"
        }
      ],
      "78": [
        {
          "id": "product:OnCell G3470A-LTE Series",
          "keyphrase": "OnCell G3470A-LTE Series",
          "type": "product"
        },
        {
          "id": "version:v1.7.7 and prior",
          "keyphrase": "v1.7.7 and prior",
          "type": "version"
        }
      ],
      "94": [
        {
          "id": "product:OnCell G3470A-LTE Series",
          "keyphrase": "OnCell G3470A-LTE Series",
          "type": "product"
        }
      ],
      "345": [
        {
          "id": "product:OnCell G3470A-LTE Series",
          "keyphrase": "OnCell G3470A-LTE Series",
          "type": "product"
        }
      ],
      "284": [
        {
          "id": "version:v1.7.7 and prior",
          "keyphrase": "v1.7.7 and prior",
          "type": "version"
        }
      ],
      "121": [
        {
          "id": "version:v1.7.7 and prior",
          "keyphrase": "v1.7.7 and prior",
          "type": "version"
        }
      ]
    },
    "relevant_cwes": [
      {
        "metadata": {
          "doc_id": "134",
          "name": "Use of Externally-Controlled Format String",
          "source": "sparse",
          "original_content": "The product uses a function that accepts a format string as an argument, but the format string originates from an external source.",
          "keyphrase_sources": [
            {
              "id": "weakness:format string vulnerability",
              "keyphrase": "format string vulnerability",
              "type": "weakness"
            },
            {
              "id": "weakness:memory leak",
              "keyphrase": "memory leak",
              "type": "weakness"
            },
            {
              "id": "impact:denial of service",
              "keyphrase": "denial of service",
              "type": "impact"
            },
            {
              "id": "vector:accepting a format string from an external source as an argument",
              "keyphrase": "accepting a format string from an external source as an argument",
              "type": "vector"
            },
            {
              "id": "attacker:attacker",
              "keyphrase": "attacker",
              "type": "attacker"
            },
            {
              "id": "product:OnCell G3470A-LTE Series",
              "keyphrase": "OnCell G3470A-LTE Series",
              "type": "product"
            },
            {
              "id": "version:v1.7.7 and prior",
              "keyphrase": "v1.7.7 and prior",
              "type": "version"
            }
          ]
        },
        "similarity": 354.12553215049235
      },
      {
        "metadata": {
          "doc_id": "193",
          "name": "Off-by-one Error",
          "source": "sparse",
          "original_content": "A product calculates or uses an incorrect maximum or minimum value that is 1 more, or 1 less, than the correct value.",
          "keyphrase_sources": [
            {
              "id": "weakness:format string vulnerability",
              "keyphrase": "format string vulnerability",
              "type": "weakness"
            },
            {
              "id": "weakness:memory leak",
              "keyphrase": "memory leak",
              "type": "weakness"
            },
            {
              "id": "impact:denial of service",
              "keyphrase": "denial of service",
              "type": "impact"
            },
            {
              "id": "vector:accepting a format string from an external source as an argument",
              "keyphrase": "accepting a format string from an external source as an argument",
              "type": "vector"
            },
            {
              "id": "attacker:attacker",
              "keyphrase": "attacker",
              "type": "attacker"
            }
          ]
        },
        "similarity": 277.5834332812471
      },
      {
        "metadata": {
          "doc_id": "1286",
          "name": "Improper Validation of Syntactic Correctness of Input",
          "source": "sparse",
          "original_content": "The product receives input that is expected to be well-formed - i.e., to comply with a certain syntax - but it does not validate or incorrectly validates that the input complies with the syntax.",
          "keyphrase_sources": [
            {
              "id": "weakness:format string vulnerability",
              "keyphrase": "format string vulnerability",
              "type": "weakness"
            },
            {
              "id": "vector:accepting a format string from an external source as an argument",
              "keyphrase": "accepting a format string from an external source as an argument",
              "type": "vector"
            },
            {
              "id": "product:OnCell G3470A-LTE Series",
              "keyphrase": "OnCell G3470A-LTE Series",
              "type": "product"
            }
          ]
        },
        "similarity": 272.7335973146869
      },
      {
        "metadata": {
          "doc_id": "1333",
          "name": "Inefficient Regular Expression Complexity",
          "source": "sparse",
          "original_content": "The product uses a regular expression with an inefficient, possibly exponential worst-case computational complexity that consumes excessive CPU cycles.",
          "keyphrase_sources": [
            {
              "id": "weakness:format string vulnerability",
              "keyphrase": "format string vulnerability",
              "type": "weakness"
            },
            {
              "id": "impact:denial of service",
              "keyphrase": "denial of service",
              "type": "impact"
            },
            {
              "id": "vector:accepting a format string from an external source as an argument",
              "keyphrase": "accepting a format string from an external source as an argument",
              "type": "vector"
            },
            {
              "id": "attacker:attacker",
              "keyphrase": "attacker",
              "type": "attacker"
            },
            {
              "id": "version:v1.7.7 and prior",
              "keyphrase": "v1.7.7 and prior",
              "type": "version"
            }
          ]
        },
        "similarity": 265.6826243400667
      },
      {
        "metadata": {
          "doc_id": "401",
          "name": "Missing Release of Memory after Effective Lifetime",
          "source": "sparse",
          "original_content": "The product does not sufficiently track and release allocated memory after it has been used, which slowly consumes remaining memory.",
          "keyphrase_sources": [
            {
              "id": "weakness:memory leak",
              "keyphrase": "memory leak",
              "type": "weakness"
            }
          ]
        },
        "similarity": 265.46865028774977
      },
      {
        "metadata": {
          "doc_id": "125",
          "name": "Out-of-bounds Read",
          "source": "sparse",
          "original_content": "The product reads data past the end, or before the beginning, of the intended buffer.",
          "keyphrase_sources": [
            {
              "id": "weakness:memory leak",
              "keyphrase": "memory leak",
              "type": "weakness"
            }
          ]
        },
        "similarity": 261.77318113211845
      },
      {
        "metadata": {
          "doc_id": "88",
          "name": "Improper Neutralization of Argument Delimiters in a Command ('Argument Injection')",
          "source": "sparse",
          "original_content": "The product constructs a string for a command to be executed by a separate component\nin another control sphere, but it does not properly delimit the\nintended arguments, options, or switches within that command string.",
          "keyphrase_sources": [
            {
              "id": "weakness:format string vulnerability",
              "keyphrase": "format string vulnerability",
              "type": "weakness"
            },
            {
              "id": "vector:accepting a format string from an external source as an argument",
              "keyphrase": "accepting a format string from an external source as an argument",
              "type": "vector"
            }
          ]
        },
        "similarity": 256.9574923294232
      },
      {
        "metadata": {
          "doc_id": "200",
          "name": "Exposure of Sensitive Information to an Unauthorized Actor",
          "source": "sparse",
          "original_content": "The product exposes sensitive information to an actor that is not explicitly authorized to have access to that information.",
          "keyphrase_sources": [
            {
              "id": "weakness:memory leak",
              "keyphrase": "memory leak",
              "type": "weakness"
            }
          ]
        },
        "similarity": 255.64964085973511
      },
      {
        "metadata": {
          "doc_id": "284",
          "name": "Improper Access Control",
          "source": "sparse",
          "original_content": "The product does not restrict or incorrectly restricts access to a resource from an unauthorized actor.",
          "keyphrase_sources": [
            {
              "id": "version:v1.7.7 and prior",
              "keyphrase": "v1.7.7 and prior",
              "type": "version"
            }
          ]
        },
        "similarity": 107.55804431458938
      },
      {
        "metadata": {
          "doc_id": "121",
          "name": "Stack-based Buffer Overflow",
          "source": "sparse",
          "original_content": "A stack-based buffer overflow condition is a condition where the buffer being overwritten is allocated on the stack (i.e., is a local variable or, rarely, a parameter to a function).",
          "keyphrase_sources": [
            {
              "id": "version:v1.7.7 and prior",
              "keyphrase": "v1.7.7 and prior",
              "type": "version"
            }
          ]
        },
        "similarity": 106.37047693719389
      },
      {
        "metadata": {
          "doc_id": "1284",
          "name": "Improper Validation of Specified Quantity in Input",
          "source": "sparse",
          "original_content": "The product receives input that is expected to specify a quantity (such as size or length), but it does not validate or incorrectly validates that the quantity has the required properties.",
          "keyphrase_sources": [
            {
              "id": "impact:denial of service",
              "keyphrase": "denial of service",
              "type": "impact"
            },
            {
              "id": "attacker:attacker",
              "keyphrase": "attacker",
              "type": "attacker"
            }
          ]
        },
        "similarity": 100.935011574747
      },
      {
        "metadata": {
          "doc_id": "119",
          "name": "Improper Restriction of Operations within the Bounds of a Memory Buffer",
          "source": "sparse",
          "original_content": "The product performs operations on a memory buffer, but it reads from or writes to a memory location outside the buffer's intended boundary. This may result in read or write operations on unexpected memory locations that could be linked to other variables, data structures, or internal program data.",
          "keyphrase_sources": [
            {
              "id": "impact:denial of service",
              "keyphrase": "denial of service",
              "type": "impact"
            }
          ]
        },
        "similarity": 99.97939198629247
      },
      {
        "metadata": {
          "doc_id": "78",
          "name": "Improper Neutralization of Special Elements used in an OS Command ('OS Command Injection')",
          "source": "sparse",
          "original_content": "The product constructs all or part of an OS command using externally-influenced input from an upstream component, but it does not neutralize or incorrectly neutralizes special elements that could modify the intended OS command when it is sent to a downstream component.",
          "keyphrase_sources": [
            {
              "id": "product:OnCell G3470A-LTE Series",
              "keyphrase": "OnCell G3470A-LTE Series",
              "type": "product"
            },
            {
              "id": "version:v1.7.7 and prior",
              "keyphrase": "v1.7.7 and prior",
              "type": "version"
            }
          ]
        },
        "similarity": 93.07101432676487
      },
      {
        "metadata": {
          "doc_id": "94",
          "name": "Improper Control of Generation of Code ('Code Injection')",
          "source": "sparse",
          "original_content": "The product constructs all or part of a code segment using externally-influenced input from an upstream component, but it does not neutralize or incorrectly neutralizes special elements that could modify the syntax or behavior of the intended code segment.",
          "keyphrase_sources": [
            {
              "id": "product:OnCell G3470A-LTE Series",
              "keyphrase": "OnCell G3470A-LTE Series",
              "type": "product"
            }
          ]
        },
        "similarity": 92.15935205087544
      },
      {
        "metadata": {
          "doc_id": "20",
          "name": "Improper Input Validation",
          "source": "sparse",
          "original_content": "The product receives input or data, but it does\n        not validate or incorrectly validates that the input has the\n        properties that are required to process the data safely and\n        correctly.",
          "keyphrase_sources": [
            {
              "id": "attacker:attacker",
              "keyphrase": "attacker",
              "type": "attacker"
            }
          ]
        },
        "similarity": 91.3138686276623
      },
      {
        "metadata": {
          "doc_id": "345",
          "name": "Insufficient Verification of Data Authenticity",
          "source": "sparse",
          "original_content": "The product does not sufficiently verify the origin or authenticity of data, in a way that causes it to accept invalid data.",
          "keyphrase_sources": [
            {
              "id": "product:OnCell G3470A-LTE Series",
              "keyphrase": "OnCell G3470A-LTE Series",
              "type": "product"
            }
          ]
        },
        "similarity": 90.6039203319204
      }
    ],
    "enhanced_query": "# Vulnerability Description\n\n    OnCell G3470A-LTE Series firmware versions v1.7.7 and prior have been identified as vulnerable due to accepting a format string from an external source as an argument. An attacker could modify an externally controlled format string to cause a **memory leak** and denial of service.\n\n    # Keyphrase-Specific CWE Analysis\n    This vulnerability contains multiple keyphrases that may map to different CWEs. \n    Please analyze each keyphrase separately and determine the most appropriate CWE(s) for each.\n\n    ## WEAKNESS: 'format string vulnerability'\n\nRelevant CWEs for this WEAKNESS:\n\n### 1. CWE-134: Use of Externally-Controlled Format String (Score: 354.13)\n\nThe product uses a function that accepts a format string as an argument, but the format string originates from an external source....\n\n### 2. CWE-193: Off-by-one Error (Score: 277.58)\n\nA product calculates or uses an incorrect maximum or minimum value that is 1 more, or 1 less, than the correct value....\n\n### 3. CWE-1286: Improper Validation of Syntactic Correctness of Input (Score: 272.73)\n\nThe product receives input that is expected to be well-formed - i.e., to comply with a certain syntax - but it does not validate or incorrectly validates that the input complies with the syntax....\n\n### 4. CWE-1333: Inefficient Regular Expression Complexity (Score: 265.68)\n\nThe product uses a regular expression with an inefficient, possibly exponential worst-case computational complexity that consumes excessive CPU cycles....\n\n### 5. CWE-88: Improper Neutralization of Argument Delimiters in a Command ('Argument Injection') (Score: 256.96)\n\nThe product constructs a string for a command to be executed by a separate component\nin another control sphere, but it does not properly delimit the\nintended arguments, options, or switches within that command string....\n\n## WEAKNESS: 'memory leak'\n\nRelevant CWEs for this WEAKNESS:\n\n### 1. CWE-134: Use of Externally-Controlled Format String (Score: 354.13)\n\nThe product uses a function that accepts a format string as an argument, but the format string originates from an external source....\n\n### 2. CWE-193: Off-by-one Error (Score: 277.58)\n\nA product calculates or uses an incorrect maximum or minimum value that is 1 more, or 1 less, than the correct value....\n\n### 3. CWE-401: Missing Release of Memory after Effective Lifetime (Score: 265.47)\n\nThe product does not sufficiently track and release allocated memory after it has been used, which slowly consumes remaining memory....\n\n### 4. CWE-125: Out-of-bounds Read (Score: 261.77)\n\nThe product reads data past the end, or before the beginning, of the intended buffer....\n\n### 5. CWE-200: Exposure of Sensitive Information to an Unauthorized Actor (Score: 255.65)\n\nThe product exposes sensitive information to an actor that is not explicitly authorized to have access to that information....\n\n## IMPACT: 'denial of service'\n\nRelevant CWEs for this IMPACT:\n\n### 1. CWE-134: Use of Externally-Controlled Format String (Score: 354.13)\n\nThe product uses a function that accepts a format string as an argument, but the format string originates from an external source....\n\n### 2. CWE-193: Off-by-one Error (Score: 277.58)\n\nA product calculates or uses an incorrect maximum or minimum value that is 1 more, or 1 less, than the correct value....\n\n### 3. CWE-1333: Inefficient Regular Expression Complexity (Score: 265.68)\n\nThe product uses a regular expression with an inefficient, possibly exponential worst-case computational complexity that consumes excessive CPU cycles....\n\n### 4. CWE-1284: Improper Validation of Specified Quantity in Input (Score: 100.94)\n\nThe product receives input that is expected to specify a quantity (such as size or length), but it does not validate or incorrectly validates that the quantity has the required properties....\n\n### 5. CWE-119: Improper Restriction of Operations within the Bounds of a Memory Buffer (Score: 99.98)\n\nThe product performs operations on a memory buffer, but it reads from or writes to a memory location outside the buffer's intended boundary. This may result in read or write operations on unexpected memory locations that could be linked to other variables, data structures, or internal program data....\n\n## VECTOR: 'accepting a format string from an external source as an argument'\n\nRelevant CWEs for this VECTOR:\n\n### 1. CWE-134: Use of Externally-Controlled Format String (Score: 354.13)\n\nThe product uses a function that accepts a format string as an argument, but the format string originates from an external source....\n\n### 2. CWE-193: Off-by-one Error (Score: 277.58)\n\nA product calculates or uses an incorrect maximum or minimum value that is 1 more, or 1 less, than the correct value....\n\n### 3. CWE-1286: Improper Validation of Syntactic Correctness of Input (Score: 272.73)\n\nThe product receives input that is expected to be well-formed - i.e., to comply with a certain syntax - but it does not validate or incorrectly validates that the input complies with the syntax....\n\n### 4. CWE-1333: Inefficient Regular Expression Complexity (Score: 265.68)\n\nThe product uses a regular expression with an inefficient, possibly exponential worst-case computational complexity that consumes excessive CPU cycles....\n\n### 5. CWE-88: Improper Neutralization of Argument Delimiters in a Command ('Argument Injection') (Score: 256.96)\n\nThe product constructs a string for a command to be executed by a separate component\nin another control sphere, but it does not properly delimit the\nintended arguments, options, or switches within that command string....\n\n## ATTACKER: 'attacker'\n\nRelevant CWEs for this ATTACKER:\n\n### 1. CWE-134: Use of Externally-Controlled Format String (Score: 354.13)\n\nThe product uses a function that accepts a format string as an argument, but the format string originates from an external source....\n\n### 2. CWE-193: Off-by-one Error (Score: 277.58)\n\nA product calculates or uses an incorrect maximum or minimum value that is 1 more, or 1 less, than the correct value....\n\n### 3. CWE-1333: Inefficient Regular Expression Complexity (Score: 265.68)\n\nThe product uses a regular expression with an inefficient, possibly exponential worst-case computational complexity that consumes excessive CPU cycles....\n\n### 4. CWE-1284: Improper Validation of Specified Quantity in Input (Score: 100.94)\n\nThe product receives input that is expected to specify a quantity (such as size or length), but it does not validate or incorrectly validates that the quantity has the required properties....\n\n### 5. CWE-20: Improper Input Validation (Score: 91.31)\n\nThe product receives input or data, but it does\n        not validate or incorrectly validates that the input has the\n        properties that are required to process the data safely and\n        correctly....\n\n## PRODUCT: 'OnCell G3470A-LTE Series'\n\nRelevant CWEs for this PRODUCT:\n\n### 1. CWE-134: Use of Externally-Controlled Format String (Score: 354.13)\n\nThe product uses a function that accepts a format string as an argument, but the format string originates from an external source....\n\n### 2. CWE-1286: Improper Validation of Syntactic Correctness of Input (Score: 272.73)\n\nThe product receives input that is expected to be well-formed - i.e., to comply with a certain syntax - but it does not validate or incorrectly validates that the input complies with the syntax....\n\n### 3. CWE-78: Improper Neutralization of Special Elements used in an OS Command ('OS Command Injection') (Score: 93.07)\n\nThe product constructs all or part of an OS command using externally-influenced input from an upstream component, but it does not neutralize or incorrectly neutralizes special elements that could modify the intended OS command when it is sent to a downstream component....\n\n### 4. CWE-94: Improper Control of Generation of Code ('Code Injection') (Score: 92.16)\n\nThe product constructs all or part of a code segment using externally-influenced input from an upstream component, but it does not neutralize or incorrectly neutralizes special elements that could modify the syntax or behavior of the intended code segment....\n\n### 5. CWE-345: Insufficient Verification of Data Authenticity (Score: 90.60)\n\nThe product does not sufficiently verify the origin or authenticity of data, in a way that causes it to accept invalid data....\n\n## VERSION: 'v1.7.7 and prior'\n\nRelevant CWEs for this VERSION:\n\n### 1. CWE-134: Use of Externally-Controlled Format String (Score: 354.13)\n\nThe product uses a function that accepts a format string as an argument, but the format string originates from an external source....\n\n### 2. CWE-1333: Inefficient Regular Expression Complexity (Score: 265.68)\n\nThe product uses a regular expression with an inefficient, possibly exponential worst-case computational complexity that consumes excessive CPU cycles....\n\n### 3. CWE-284: Improper Access Control (Score: 107.56)\n\nThe product does not restrict or incorrectly restricts access to a resource from an unauthorized actor....\n\n### 4. CWE-121: Stack-based Buffer Overflow (Score: 106.37)\n\nA stack-based buffer overflow condition is a condition where the buffer being overwritten is allocated on the stack (i.e., is a local variable or, rarely, a parameter to a function)....\n\n### 5. CWE-78: Improper Neutralization of Special Elements used in an OS Command ('OS Command Injection') (Score: 93.07)\n\nThe product constructs all or part of an OS command using externally-influenced input from an upstream component, but it does not neutralize or incorrectly neutralizes special elements that could modify the intended OS command when it is sent to a downstream component....\n\n\n    # Analysis Instructions\n    1. For each keyphrase, identify the most appropriate CWE(s) that represent the weakness.\n    2. Consider how the different keyphrases might relate to each other in the vulnerability chain.\n    3. Provide a final determination of primary CWE(s) and any secondary CWEs.\n    4. Format your response using the standard analysis template.\n\n    Please analyze how these different weaknesses interact and provide a comprehensive CWE classification.\n    "
  },
  "retrieval_time": 1.1732597351074219
}