{
  "vulnerability_info": "VulnerabilityInfo(cve_id='CVE-2024-28992', description='The SolarWinds Access Rights Manager was susceptible to a Directory Traversal and **Information Disclosure Vulnerability**. This vulnerability allows an unauthenticated user to perform arbitrary file deletion and leak sensitive information.', key_phrases={'rootcause': '', 'weakness': ['Information Disclosure Vulnerability', 'directory traversal'], 'impact': [\"['arbitrary file deletion'\", \"'information disclosure']\"], 'vector': '', 'attacker': 'unauthenticated user', 'product': 'SolarWinds Access Rights Manager', 'version': '', 'component': ''}, reference_content=\"Based on the provided document, here's the information regarding CVE-2024-28992:\\n\\n**Root cause of vulnerability:**\\n- The vulnerability is due to a directory traversal issue in SolarWinds Access Rights Manager (ARM).\\n\\n**Weaknesses/vulnerabilities present:**\\n- Directory Traversal\\n- Information Disclosure\\n- Arbitrary file deletion\\n\\n**Impact of exploitation:**\\n- An unauthenticated user can perform arbitrary file deletion and leak sensitive information\\n\\n**Attack vectors:**\\n- Network-based attacks\\n- Exploitation can occur through unauthenticated access\\n\\n**Required attacker capabilities/position:**\\n- The attacker does not need to be authenticated to exploit this vulnerability.\", similar_info={'cwe_distribution': {95: {'cwe_counts': defaultdict(<class 'int'>, {}), 'total_samples': 3, 'distribution': [{'cwes': [], 'frequency': 3, 'proportion': 1.0}]}, 90: {'cwe_counts': defaultdict(<class 'int'>, {}), 'total_samples': 3, 'distribution': [{'cwes': [], 'frequency': 3, 'proportion': 1.0}]}, 85: {'cwe_counts': defaultdict(<class 'int'>, {}), 'total_samples': 4, 'distribution': [{'cwes': [], 'frequency': 4, 'proportion': 1.0}]}, 80: {'cwe_counts': defaultdict(<class 'int'>, {}), 'total_samples': 3, 'distribution': [{'cwes': [], 'frequency': 3, 'proportion': 1.0}]}, 75: {'cwe_counts': defaultdict(<class 'int'>, {}), 'total_samples': 3, 'distribution': [{'cwes': [], 'frequency': 3, 'proportion': 1.0}]}, 70: {'cwe_counts': defaultdict(<class 'int'>, {'CWE-22': 1, 'CWE-287': 1}), 'total_samples': 17, 'distribution': [{'cwes': [], 'frequency': 15, 'proportion': 0.882}, {'cwes': ['CWE-22'], 'frequency': 1, 'proportion': 0.059}, {'cwes': ['CWE-287'], 'frequency': 1, 'proportion': 0.059}]}}, 'cwe_consensus': 'CWE-22', 'similarity_stats': {'thresholds': [95, 90, 85, 80, 75, 70], 'total_samples_by_threshold': {95: 3, 90: 3, 85: 4, 80: 3, 75: 3, 70: 17}, 'top_cwes_by_threshold': {95: [], 90: [], 85: [], 80: [], 75: [], 70: [('CWE-22', 1), ('CWE-287', 1)]}}, 'raw_matches': [{'similarity': 95, 'cwes': [], 'total': 3, 'frequency': 3, 'proportion': 1.0}, {'similarity': 90, 'cwes': [], 'total': 3, 'frequency': 3, 'proportion': 1.0}, {'similarity': 85, 'cwes': [], 'total': 4, 'frequency': 4, 'proportion': 1.0}, {'similarity': 80, 'cwes': [], 'total': 3, 'frequency': 3, 'proportion': 1.0}, {'similarity': 75, 'cwes': [], 'total': 3, 'frequency': 3, 'proportion': 1.0}, {'similarity': 70, 'cwes': [], 'total': 17, 'frequency': 15, 'proportion': 0.882}, {'similarity': 70, 'cwes': ['22'], 'total': 17, 'frequency': 1, 'proportion': 0.059}, {'similarity': 70, 'cwes': ['287'], 'total': 17, 'frequency': 1, 'proportion': 0.059}]}, similarity_summary=SimilarityInsight(consensus_cwe='CWE-22', top_cwes=[('CWE-22', 1), ('CWE-287', 1)], confidence_levels={'high': [], 'medium': [], 'low': []}, total_samples=33), analysis='', analysis_with_relationships='', criticism='', resolution='', relevant_cwes=[{'metadata': {'doc_id': '59', 'name': \"Improper Link Resolution Before File Access ('Link Following')\", 'source': 'sparse', 'original_content': 'The product attempts to access a file based on the filename, but it does not properly prevent that filename from identifying a link or shortcut that resolves to an unintended resource.', 'keyphrase_sources': [{'id': 'weakness:directory traversal', 'keyphrase': 'directory traversal', 'type': 'weakness'}, {'id': \"impact:['arbitrary file deletion'\", 'keyphrase': \"['arbitrary file deletion'\", 'type': 'impact'}]}, 'similarity': np.float64(198.71820540170975)}, {'metadata': {'doc_id': '36', 'name': 'Absolute Path Traversal', 'source': 'sparse', 'original_content': 'The product uses external input to construct a pathname that should be within a restricted directory, but it does not properly neutralize absolute path sequences such as \"/abs/path\" that can resolve to a location that is outside of that directory.', 'keyphrase_sources': [{'id': 'weakness:directory traversal', 'keyphrase': 'directory traversal', 'type': 'weakness'}]}, 'similarity': np.float64(194.80183821471448)}, {'metadata': {'doc_id': '22', 'name': \"Improper Limitation of a Pathname to a Restricted Directory ('Path Traversal')\", 'source': 'sparse', 'original_content': 'The product uses external input to construct a pathname that is intended to identify a file or directory that is located underneath a restricted parent directory, but the product does not properly neutralize special elements within the pathname that can cause the pathname to resolve to a location that is outside of the restricted directory.', 'keyphrase_sources': [{'id': 'weakness:Information Disclosure Vulnerability', 'keyphrase': 'Information Disclosure Vulnerability', 'type': 'weakness'}, {'id': 'weakness:directory traversal', 'keyphrase': 'directory traversal', 'type': 'weakness'}, {'id': \"impact:['arbitrary file deletion'\", 'keyphrase': \"['arbitrary file deletion'\", 'type': 'impact'}, {'id': \"impact:'information disclosure']\", 'keyphrase': \"'information disclosure']\", 'type': 'impact'}, {'id': 'attacker:unauthenticated user', 'keyphrase': 'unauthenticated user', 'type': 'attacker'}, {'id': 'product:SolarWinds Access Rights Manager', 'keyphrase': 'SolarWinds Access Rights Manager', 'type': 'product'}]}, 'similarity': np.float64(189.09779075885388)}, {'metadata': {'doc_id': '41', 'name': 'Improper Resolution of Path Equivalence', 'source': 'sparse', 'original_content': 'The product is vulnerable to file system contents disclosure through path equivalence. Path equivalence involves the use of special characters in file and directory names. The associated manipulations are intended to generate multiple names for the same object.', 'keyphrase_sources': [{'id': 'weakness:Information Disclosure Vulnerability', 'keyphrase': 'Information Disclosure Vulnerability', 'type': 'weakness'}, {'id': 'weakness:directory traversal', 'keyphrase': 'directory traversal', 'type': 'weakness'}, {'id': \"impact:['arbitrary file deletion'\", 'keyphrase': \"['arbitrary file deletion'\", 'type': 'impact'}, {'id': \"impact:'information disclosure']\", 'keyphrase': \"'information disclosure']\", 'type': 'impact'}]}, 'similarity': np.float64(175.22532685607035)}, {'metadata': {'doc_id': '200', 'name': 'Exposure of Sensitive Information to an Unauthorized Actor', 'source': 'sparse', 'original_content': 'The product exposes sensitive information to an actor that is not explicitly authorized to have access to that information.', 'keyphrase_sources': [{'id': 'weakness:Information Disclosure Vulnerability', 'keyphrase': 'Information Disclosure Vulnerability', 'type': 'weakness'}, {'id': \"impact:'information disclosure']\", 'keyphrase': \"'information disclosure']\", 'type': 'impact'}]}, 'similarity': np.float64(172.20045248746496)}, {'metadata': {'doc_id': '23', 'name': 'Relative Path Traversal', 'source': 'sparse', 'original_content': 'The product uses external input to construct a pathname that should be within a restricted directory, but it does not properly neutralize sequences such as \"..\" that can resolve to a location that is outside of that directory.', 'keyphrase_sources': [{'id': 'weakness:Information Disclosure Vulnerability', 'keyphrase': 'Information Disclosure Vulnerability', 'type': 'weakness'}, {'id': 'weakness:directory traversal', 'keyphrase': 'directory traversal', 'type': 'weakness'}, {'id': \"impact:['arbitrary file deletion'\", 'keyphrase': \"['arbitrary file deletion'\", 'type': 'impact'}, {'id': \"impact:'information disclosure']\", 'keyphrase': \"'information disclosure']\", 'type': 'impact'}, {'id': 'attacker:unauthenticated user', 'keyphrase': 'unauthenticated user', 'type': 'attacker'}, {'id': 'product:SolarWinds Access Rights Manager', 'keyphrase': 'SolarWinds Access Rights Manager', 'type': 'product'}]}, 'similarity': np.float64(172.0549219856185)}, {'metadata': {'doc_id': '862', 'name': 'Missing Authorization', 'source': 'sparse', 'original_content': 'The product does not perform an authorization check when an actor attempts to access a resource or perform an action.', 'keyphrase_sources': [{'id': 'weakness:Information Disclosure Vulnerability', 'keyphrase': 'Information Disclosure Vulnerability', 'type': 'weakness'}, {'id': \"impact:'information disclosure']\", 'keyphrase': \"'information disclosure']\", 'type': 'impact'}]}, 'similarity': np.float64(169.41072374366516)}, {'metadata': {'doc_id': '732', 'name': 'Incorrect Permission Assignment for Critical Resource', 'source': 'sparse', 'original_content': 'The product specifies permissions for a security-critical resource in a way that allows that resource to be read or modified by unintended actors.', 'keyphrase_sources': [{'id': 'product:SolarWinds Access Rights Manager', 'keyphrase': 'SolarWinds Access Rights Manager', 'type': 'product'}]}, 'similarity': np.float64(71.47329999379404)}, {'metadata': {'doc_id': '288', 'name': 'Authentication Bypass Using an Alternate Path or Channel', 'source': 'sparse', 'original_content': 'The product requires authentication, but the product has an alternate path or channel that does not require authentication.', 'keyphrase_sources': [{'id': 'product:SolarWinds Access Rights Manager', 'keyphrase': 'SolarWinds Access Rights Manager', 'type': 'product'}]}, 'similarity': np.float64(68.26897849925365)}, {'metadata': {'doc_id': '434', 'name': 'Unrestricted Upload of File with Dangerous Type', 'source': 'sparse', 'original_content': 'The product allows the upload or transfer of dangerous file types that are automatically processed within its environment.', 'keyphrase_sources': [{'id': \"impact:['arbitrary file deletion'\", 'keyphrase': \"['arbitrary file deletion'\", 'type': 'impact'}, {'id': 'attacker:unauthenticated user', 'keyphrase': 'unauthenticated user', 'type': 'attacker'}, {'id': 'product:SolarWinds Access Rights Manager', 'keyphrase': 'SolarWinds Access Rights Manager', 'type': 'product'}]}, 'similarity': np.float64(65.43599629219747)}, {'metadata': {'doc_id': '306', 'name': 'Missing Authentication for Critical Function', 'source': 'sparse', 'original_content': 'The product does not perform any authentication for functionality that requires a provable user identity or consumes a significant amount of resources.', 'keyphrase_sources': [{'id': 'attacker:unauthenticated user', 'keyphrase': 'unauthenticated user', 'type': 'attacker'}]}, 'similarity': np.float64(57.91034867206367)}, {'metadata': {'doc_id': '284', 'name': 'Improper Access Control', 'source': 'sparse', 'original_content': 'The product does not restrict or incorrectly restricts access to a resource from an unauthorized actor.', 'keyphrase_sources': [{'id': 'attacker:unauthenticated user', 'keyphrase': 'unauthenticated user', 'type': 'attacker'}]}, 'similarity': np.float64(57.40222466997366)}], identified_cwes={'analyzer': [], 'critic_additional': []})",
  "retrieval_results": {
    "has_multiple_keyphrases": true,
    "keyphrase_cwe_sets": {
      "weakness:Information Disclosure Vulnerability": {
        "keyphrase": "Information Disclosure Vulnerability",
        "type": "weakness",
        "cwes": [
          {
            "metadata": {
              "doc_id": "22",
              "name": "Improper Limitation of a Pathname to a Restricted Directory ('Path Traversal')",
              "source": "sparse",
              "original_content": "The product uses external input to construct a pathname that is intended to identify a file or directory that is located underneath a restricted parent directory, but the product does not properly neutralize special elements within the pathname that can cause the pathname to resolve to a location that is outside of the restricted directory.",
              "keyphrase_sources": [
                {
                  "id": "weakness:Information Disclosure Vulnerability",
                  "keyphrase": "Information Disclosure Vulnerability",
                  "type": "weakness"
                },
                {
                  "id": "weakness:directory traversal",
                  "keyphrase": "directory traversal",
                  "type": "weakness"
                },
                {
                  "id": "impact:['arbitrary file deletion'",
                  "keyphrase": "['arbitrary file deletion'",
                  "type": "impact"
                },
                {
                  "id": "impact:'information disclosure']",
                  "keyphrase": "'information disclosure']",
                  "type": "impact"
                },
                {
                  "id": "attacker:unauthenticated user",
                  "keyphrase": "unauthenticated user",
                  "type": "attacker"
                },
                {
                  "id": "product:SolarWinds Access Rights Manager",
                  "keyphrase": "SolarWinds Access Rights Manager",
                  "type": "product"
                }
              ]
            },
            "similarity": 189.09779075885388
          },
          {
            "metadata": {
              "doc_id": "41",
              "name": "Improper Resolution of Path Equivalence",
              "source": "sparse",
              "original_content": "The product is vulnerable to file system contents disclosure through path equivalence. Path equivalence involves the use of special characters in file and directory names. The associated manipulations are intended to generate multiple names for the same object.",
              "keyphrase_sources": [
                {
                  "id": "weakness:Information Disclosure Vulnerability",
                  "keyphrase": "Information Disclosure Vulnerability",
                  "type": "weakness"
                },
                {
                  "id": "weakness:directory traversal",
                  "keyphrase": "directory traversal",
                  "type": "weakness"
                },
                {
                  "id": "impact:['arbitrary file deletion'",
                  "keyphrase": "['arbitrary file deletion'",
                  "type": "impact"
                },
                {
                  "id": "impact:'information disclosure']",
                  "keyphrase": "'information disclosure']",
                  "type": "impact"
                }
              ]
            },
            "similarity": 175.22532685607035
          },
          {
            "metadata": {
              "doc_id": "200",
              "name": "Exposure of Sensitive Information to an Unauthorized Actor",
              "source": "sparse",
              "original_content": "The product exposes sensitive information to an actor that is not explicitly authorized to have access to that information.",
              "keyphrase_sources": [
                {
                  "id": "weakness:Information Disclosure Vulnerability",
                  "keyphrase": "Information Disclosure Vulnerability",
                  "type": "weakness"
                },
                {
                  "id": "impact:'information disclosure']",
                  "keyphrase": "'information disclosure']",
                  "type": "impact"
                }
              ]
            },
            "similarity": 172.20045248746496
          },
          {
            "metadata": {
              "doc_id": "23",
              "name": "Relative Path Traversal",
              "source": "sparse",
              "original_content": "The product uses external input to construct a pathname that should be within a restricted directory, but it does not properly neutralize sequences such as \"..\" that can resolve to a location that is outside of that directory.",
              "keyphrase_sources": [
                {
                  "id": "weakness:Information Disclosure Vulnerability",
                  "keyphrase": "Information Disclosure Vulnerability",
                  "type": "weakness"
                },
                {
                  "id": "weakness:directory traversal",
                  "keyphrase": "directory traversal",
                  "type": "weakness"
                },
                {
                  "id": "impact:['arbitrary file deletion'",
                  "keyphrase": "['arbitrary file deletion'",
                  "type": "impact"
                },
                {
                  "id": "impact:'information disclosure']",
                  "keyphrase": "'information disclosure']",
                  "type": "impact"
                },
                {
                  "id": "attacker:unauthenticated user",
                  "keyphrase": "unauthenticated user",
                  "type": "attacker"
                },
                {
                  "id": "product:SolarWinds Access Rights Manager",
                  "keyphrase": "SolarWinds Access Rights Manager",
                  "type": "product"
                }
              ]
            },
            "similarity": 172.0549219856185
          },
          {
            "metadata": {
              "doc_id": "862",
              "name": "Missing Authorization",
              "source": "sparse",
              "original_content": "The product does not perform an authorization check when an actor attempts to access a resource or perform an action.",
              "keyphrase_sources": [
                {
                  "id": "weakness:Information Disclosure Vulnerability",
                  "keyphrase": "Information Disclosure Vulnerability",
                  "type": "weakness"
                },
                {
                  "id": "impact:'information disclosure']",
                  "keyphrase": "'information disclosure']",
                  "type": "impact"
                }
              ]
            },
            "similarity": 169.41072374366516
          }
        ]
      },
      "weakness:directory traversal": {
        "keyphrase": "directory traversal",
        "type": "weakness",
        "cwes": [
          {
            "metadata": {
              "doc_id": "22",
              "name": "Improper Limitation of a Pathname to a Restricted Directory ('Path Traversal')",
              "source": "sparse",
              "original_content": "The product uses external input to construct a pathname that is intended to identify a file or directory that is located underneath a restricted parent directory, but the product does not properly neutralize special elements within the pathname that can cause the pathname to resolve to a location that is outside of the restricted directory."
            },
            "similarity": 230.36016045305087
          },
          {
            "metadata": {
              "doc_id": "23",
              "name": "Relative Path Traversal",
              "source": "sparse",
              "original_content": "The product uses external input to construct a pathname that should be within a restricted directory, but it does not properly neutralize sequences such as \"..\" that can resolve to a location that is outside of that directory."
            },
            "similarity": 218.1216522143383
          },
          {
            "metadata": {
              "doc_id": "59",
              "name": "Improper Link Resolution Before File Access ('Link Following')",
              "source": "sparse",
              "original_content": "The product attempts to access a file based on the filename, but it does not properly prevent that filename from identifying a link or shortcut that resolves to an unintended resource.",
              "keyphrase_sources": [
                {
                  "id": "weakness:directory traversal",
                  "keyphrase": "directory traversal",
                  "type": "weakness"
                },
                {
                  "id": "impact:['arbitrary file deletion'",
                  "keyphrase": "['arbitrary file deletion'",
                  "type": "impact"
                }
              ]
            },
            "similarity": 198.71820540170975
          },
          {
            "metadata": {
              "doc_id": "36",
              "name": "Absolute Path Traversal",
              "source": "sparse",
              "original_content": "The product uses external input to construct a pathname that should be within a restricted directory, but it does not properly neutralize absolute path sequences such as \"/abs/path\" that can resolve to a location that is outside of that directory.",
              "keyphrase_sources": [
                {
                  "id": "weakness:directory traversal",
                  "keyphrase": "directory traversal",
                  "type": "weakness"
                }
              ]
            },
            "similarity": 194.80183821471448
          },
          {
            "metadata": {
              "doc_id": "41",
              "name": "Improper Resolution of Path Equivalence",
              "source": "sparse",
              "original_content": "The product is vulnerable to file system contents disclosure through path equivalence. Path equivalence involves the use of special characters in file and directory names. The associated manipulations are intended to generate multiple names for the same object."
            },
            "similarity": 193.93894763657704
          }
        ]
      },
      "impact:['arbitrary file deletion'": {
        "keyphrase": "['arbitrary file deletion'",
        "type": "impact",
        "cwes": [
          {
            "metadata": {
              "doc_id": "22",
              "name": "Improper Limitation of a Pathname to a Restricted Directory ('Path Traversal')",
              "source": "sparse",
              "original_content": "The product uses external input to construct a pathname that is intended to identify a file or directory that is located underneath a restricted parent directory, but the product does not properly neutralize special elements within the pathname that can cause the pathname to resolve to a location that is outside of the restricted directory."
            },
            "similarity": 74.17438543106104
          },
          {
            "metadata": {
              "doc_id": "23",
              "name": "Relative Path Traversal",
              "source": "sparse",
              "original_content": "The product uses external input to construct a pathname that should be within a restricted directory, but it does not properly neutralize sequences such as \"..\" that can resolve to a location that is outside of that directory."
            },
            "similarity": 71.04483993738742
          },
          {
            "metadata": {
              "doc_id": "41",
              "name": "Improper Resolution of Path Equivalence",
              "source": "sparse",
              "original_content": "The product is vulnerable to file system contents disclosure through path equivalence. Path equivalence involves the use of special characters in file and directory names. The associated manipulations are intended to generate multiple names for the same object."
            },
            "similarity": 65.71187741389352
          },
          {
            "metadata": {
              "doc_id": "59",
              "name": "Improper Link Resolution Before File Access ('Link Following')",
              "source": "sparse",
              "original_content": "The product attempts to access a file based on the filename, but it does not properly prevent that filename from identifying a link or shortcut that resolves to an unintended resource."
            },
            "similarity": 65.55498567416315
          },
          {
            "metadata": {
              "doc_id": "434",
              "name": "Unrestricted Upload of File with Dangerous Type",
              "source": "sparse",
              "original_content": "The product allows the upload or transfer of dangerous file types that are automatically processed within its environment.",
              "keyphrase_sources": [
                {
                  "id": "impact:['arbitrary file deletion'",
                  "keyphrase": "['arbitrary file deletion'",
                  "type": "impact"
                },
                {
                  "id": "attacker:unauthenticated user",
                  "keyphrase": "unauthenticated user",
                  "type": "attacker"
                },
                {
                  "id": "product:SolarWinds Access Rights Manager",
                  "keyphrase": "SolarWinds Access Rights Manager",
                  "type": "product"
                }
              ]
            },
            "similarity": 65.43599629219747
          }
        ]
      },
      "impact:'information disclosure']": {
        "keyphrase": "'information disclosure']",
        "type": "impact",
        "cwes": [
          {
            "metadata": {
              "doc_id": "22",
              "name": "Improper Limitation of a Pathname to a Restricted Directory ('Path Traversal')",
              "source": "sparse",
              "original_content": "The product uses external input to construct a pathname that is intended to identify a file or directory that is located underneath a restricted parent directory, but the product does not properly neutralize special elements within the pathname that can cause the pathname to resolve to a location that is outside of the restricted directory."
            },
            "similarity": 66.43566834649529
          },
          {
            "metadata": {
              "doc_id": "41",
              "name": "Improper Resolution of Path Equivalence",
              "source": "sparse",
              "original_content": "The product is vulnerable to file system contents disclosure through path equivalence. Path equivalence involves the use of special characters in file and directory names. The associated manipulations are intended to generate multiple names for the same object."
            },
            "similarity": 61.61475703913846
          },
          {
            "metadata": {
              "doc_id": "200",
              "name": "Exposure of Sensitive Information to an Unauthorized Actor",
              "source": "sparse",
              "original_content": "The product exposes sensitive information to an actor that is not explicitly authorized to have access to that information."
            },
            "similarity": 60.3609024844984
          },
          {
            "metadata": {
              "doc_id": "23",
              "name": "Relative Path Traversal",
              "source": "sparse",
              "original_content": "The product uses external input to construct a pathname that should be within a restricted directory, but it does not properly neutralize sequences such as \"..\" that can resolve to a location that is outside of that directory."
            },
            "similarity": 60.33970428618843
          },
          {
            "metadata": {
              "doc_id": "862",
              "name": "Missing Authorization",
              "source": "sparse",
              "original_content": "The product does not perform an authorization check when an actor attempts to access a resource or perform an action."
            },
            "similarity": 59.656604547067126
          }
        ]
      },
      "attacker:unauthenticated user": {
        "keyphrase": "unauthenticated user",
        "type": "attacker",
        "cwes": [
          {
            "metadata": {
              "doc_id": "22",
              "name": "Improper Limitation of a Pathname to a Restricted Directory ('Path Traversal')",
              "source": "sparse",
              "original_content": "The product uses external input to construct a pathname that is intended to identify a file or directory that is located underneath a restricted parent directory, but the product does not properly neutralize special elements within the pathname that can cause the pathname to resolve to a location that is outside of the restricted directory."
            },
            "similarity": 67.59553507837134
          },
          {
            "metadata": {
              "doc_id": "23",
              "name": "Relative Path Traversal",
              "source": "sparse",
              "original_content": "The product uses external input to construct a pathname that should be within a restricted directory, but it does not properly neutralize sequences such as \"..\" that can resolve to a location that is outside of that directory."
            },
            "similarity": 62.64626631662754
          },
          {
            "metadata": {
              "doc_id": "434",
              "name": "Unrestricted Upload of File with Dangerous Type",
              "source": "sparse",
              "original_content": "The product allows the upload or transfer of dangerous file types that are automatically processed within its environment."
            },
            "similarity": 58.71858645127394
          },
          {
            "metadata": {
              "doc_id": "306",
              "name": "Missing Authentication for Critical Function",
              "source": "sparse",
              "original_content": "The product does not perform any authentication for functionality that requires a provable user identity or consumes a significant amount of resources.",
              "keyphrase_sources": [
                {
                  "id": "attacker:unauthenticated user",
                  "keyphrase": "unauthenticated user",
                  "type": "attacker"
                }
              ]
            },
            "similarity": 57.91034867206367
          },
          {
            "metadata": {
              "doc_id": "284",
              "name": "Improper Access Control",
              "source": "sparse",
              "original_content": "The product does not restrict or incorrectly restricts access to a resource from an unauthorized actor.",
              "keyphrase_sources": [
                {
                  "id": "attacker:unauthenticated user",
                  "keyphrase": "unauthenticated user",
                  "type": "attacker"
                }
              ]
            },
            "similarity": 57.40222466997366
          }
        ]
      },
      "product:SolarWinds Access Rights Manager": {
        "keyphrase": "SolarWinds Access Rights Manager",
        "type": "product",
        "cwes": [
          {
            "metadata": {
              "doc_id": "22",
              "name": "Improper Limitation of a Pathname to a Restricted Directory ('Path Traversal')",
              "source": "sparse",
              "original_content": "The product uses external input to construct a pathname that is intended to identify a file or directory that is located underneath a restricted parent directory, but the product does not properly neutralize special elements within the pathname that can cause the pathname to resolve to a location that is outside of the restricted directory."
            },
            "similarity": 79.33481544194095
          },
          {
            "metadata": {
              "doc_id": "23",
              "name": "Relative Path Traversal",
              "source": "sparse",
              "original_content": "The product uses external input to construct a pathname that should be within a restricted directory, but it does not properly neutralize sequences such as \"..\" that can resolve to a location that is outside of that directory."
            },
            "similarity": 75.9036119939783
          },
          {
            "metadata": {
              "doc_id": "732",
              "name": "Incorrect Permission Assignment for Critical Resource",
              "source": "sparse",
              "original_content": "The product specifies permissions for a security-critical resource in a way that allows that resource to be read or modified by unintended actors.",
              "keyphrase_sources": [
                {
                  "id": "product:SolarWinds Access Rights Manager",
                  "keyphrase": "SolarWinds Access Rights Manager",
                  "type": "product"
                }
              ]
            },
            "similarity": 71.47329999379404
          },
          {
            "metadata": {
              "doc_id": "434",
              "name": "Unrestricted Upload of File with Dangerous Type",
              "source": "sparse",
              "original_content": "The product allows the upload or transfer of dangerous file types that are automatically processed within its environment."
            },
            "similarity": 69.33609291675262
          },
          {
            "metadata": {
              "doc_id": "288",
              "name": "Authentication Bypass Using an Alternate Path or Channel",
              "source": "sparse",
              "original_content": "The product requires authentication, but the product has an alternate path or channel that does not require authentication.",
              "keyphrase_sources": [
                {
                  "id": "product:SolarWinds Access Rights Manager",
                  "keyphrase": "SolarWinds Access Rights Manager",
                  "type": "product"
                }
              ]
            },
            "similarity": 68.26897849925365
          }
        ]
      }
    },
    "keyphrase_mapping": {
      "22": [
        {
          "id": "weakness:Information Disclosure Vulnerability",
          "keyphrase": "Information Disclosure Vulnerability",
          "type": "weakness"
        },
        {
          "id": "weakness:directory traversal",
          "keyphrase": "directory traversal",
          "type": "weakness"
        },
        {
          "id": "impact:['arbitrary file deletion'",
          "keyphrase": "['arbitrary file deletion'",
          "type": "impact"
        },
        {
          "id": "impact:'information disclosure']",
          "keyphrase": "'information disclosure']",
          "type": "impact"
        },
        {
          "id": "attacker:unauthenticated user",
          "keyphrase": "unauthenticated user",
          "type": "attacker"
        },
        {
          "id": "product:SolarWinds Access Rights Manager",
          "keyphrase": "SolarWinds Access Rights Manager",
          "type": "product"
        }
      ],
      "41": [
        {
          "id": "weakness:Information Disclosure Vulnerability",
          "keyphrase": "Information Disclosure Vulnerability",
          "type": "weakness"
        },
        {
          "id": "weakness:directory traversal",
          "keyphrase": "directory traversal",
          "type": "weakness"
        },
        {
          "id": "impact:['arbitrary file deletion'",
          "keyphrase": "['arbitrary file deletion'",
          "type": "impact"
        },
        {
          "id": "impact:'information disclosure']",
          "keyphrase": "'information disclosure']",
          "type": "impact"
        }
      ],
      "200": [
        {
          "id": "weakness:Information Disclosure Vulnerability",
          "keyphrase": "Information Disclosure Vulnerability",
          "type": "weakness"
        },
        {
          "id": "impact:'information disclosure']",
          "keyphrase": "'information disclosure']",
          "type": "impact"
        }
      ],
      "23": [
        {
          "id": "weakness:Information Disclosure Vulnerability",
          "keyphrase": "Information Disclosure Vulnerability",
          "type": "weakness"
        },
        {
          "id": "weakness:directory traversal",
          "keyphrase": "directory traversal",
          "type": "weakness"
        },
        {
          "id": "impact:['arbitrary file deletion'",
          "keyphrase": "['arbitrary file deletion'",
          "type": "impact"
        },
        {
          "id": "impact:'information disclosure']",
          "keyphrase": "'information disclosure']",
          "type": "impact"
        },
        {
          "id": "attacker:unauthenticated user",
          "keyphrase": "unauthenticated user",
          "type": "attacker"
        },
        {
          "id": "product:SolarWinds Access Rights Manager",
          "keyphrase": "SolarWinds Access Rights Manager",
          "type": "product"
        }
      ],
      "862": [
        {
          "id": "weakness:Information Disclosure Vulnerability",
          "keyphrase": "Information Disclosure Vulnerability",
          "type": "weakness"
        },
        {
          "id": "impact:'information disclosure']",
          "keyphrase": "'information disclosure']",
          "type": "impact"
        }
      ],
      "59": [
        {
          "id": "weakness:directory traversal",
          "keyphrase": "directory traversal",
          "type": "weakness"
        },
        {
          "id": "impact:['arbitrary file deletion'",
          "keyphrase": "['arbitrary file deletion'",
          "type": "impact"
        }
      ],
      "36": [
        {
          "id": "weakness:directory traversal",
          "keyphrase": "directory traversal",
          "type": "weakness"
        }
      ],
      "434": [
        {
          "id": "impact:['arbitrary file deletion'",
          "keyphrase": "['arbitrary file deletion'",
          "type": "impact"
        },
        {
          "id": "attacker:unauthenticated user",
          "keyphrase": "unauthenticated user",
          "type": "attacker"
        },
        {
          "id": "product:SolarWinds Access Rights Manager",
          "keyphrase": "SolarWinds Access Rights Manager",
          "type": "product"
        }
      ],
      "306": [
        {
          "id": "attacker:unauthenticated user",
          "keyphrase": "unauthenticated user",
          "type": "attacker"
        }
      ],
      "284": [
        {
          "id": "attacker:unauthenticated user",
          "keyphrase": "unauthenticated user",
          "type": "attacker"
        }
      ],
      "732": [
        {
          "id": "product:SolarWinds Access Rights Manager",
          "keyphrase": "SolarWinds Access Rights Manager",
          "type": "product"
        }
      ],
      "288": [
        {
          "id": "product:SolarWinds Access Rights Manager",
          "keyphrase": "SolarWinds Access Rights Manager",
          "type": "product"
        }
      ]
    },
    "relevant_cwes": [
      {
        "metadata": {
          "doc_id": "59",
          "name": "Improper Link Resolution Before File Access ('Link Following')",
          "source": "sparse",
          "original_content": "The product attempts to access a file based on the filename, but it does not properly prevent that filename from identifying a link or shortcut that resolves to an unintended resource.",
          "keyphrase_sources": [
            {
              "id": "weakness:directory traversal",
              "keyphrase": "directory traversal",
              "type": "weakness"
            },
            {
              "id": "impact:['arbitrary file deletion'",
              "keyphrase": "['arbitrary file deletion'",
              "type": "impact"
            }
          ]
        },
        "similarity": 198.71820540170975
      },
      {
        "metadata": {
          "doc_id": "36",
          "name": "Absolute Path Traversal",
          "source": "sparse",
          "original_content": "The product uses external input to construct a pathname that should be within a restricted directory, but it does not properly neutralize absolute path sequences such as \"/abs/path\" that can resolve to a location that is outside of that directory.",
          "keyphrase_sources": [
            {
              "id": "weakness:directory traversal",
              "keyphrase": "directory traversal",
              "type": "weakness"
            }
          ]
        },
        "similarity": 194.80183821471448
      },
      {
        "metadata": {
          "doc_id": "22",
          "name": "Improper Limitation of a Pathname to a Restricted Directory ('Path Traversal')",
          "source": "sparse",
          "original_content": "The product uses external input to construct a pathname that is intended to identify a file or directory that is located underneath a restricted parent directory, but the product does not properly neutralize special elements within the pathname that can cause the pathname to resolve to a location that is outside of the restricted directory.",
          "keyphrase_sources": [
            {
              "id": "weakness:Information Disclosure Vulnerability",
              "keyphrase": "Information Disclosure Vulnerability",
              "type": "weakness"
            },
            {
              "id": "weakness:directory traversal",
              "keyphrase": "directory traversal",
              "type": "weakness"
            },
            {
              "id": "impact:['arbitrary file deletion'",
              "keyphrase": "['arbitrary file deletion'",
              "type": "impact"
            },
            {
              "id": "impact:'information disclosure']",
              "keyphrase": "'information disclosure']",
              "type": "impact"
            },
            {
              "id": "attacker:unauthenticated user",
              "keyphrase": "unauthenticated user",
              "type": "attacker"
            },
            {
              "id": "product:SolarWinds Access Rights Manager",
              "keyphrase": "SolarWinds Access Rights Manager",
              "type": "product"
            }
          ]
        },
        "similarity": 189.09779075885388
      },
      {
        "metadata": {
          "doc_id": "41",
          "name": "Improper Resolution of Path Equivalence",
          "source": "sparse",
          "original_content": "The product is vulnerable to file system contents disclosure through path equivalence. Path equivalence involves the use of special characters in file and directory names. The associated manipulations are intended to generate multiple names for the same object.",
          "keyphrase_sources": [
            {
              "id": "weakness:Information Disclosure Vulnerability",
              "keyphrase": "Information Disclosure Vulnerability",
              "type": "weakness"
            },
            {
              "id": "weakness:directory traversal",
              "keyphrase": "directory traversal",
              "type": "weakness"
            },
            {
              "id": "impact:['arbitrary file deletion'",
              "keyphrase": "['arbitrary file deletion'",
              "type": "impact"
            },
            {
              "id": "impact:'information disclosure']",
              "keyphrase": "'information disclosure']",
              "type": "impact"
            }
          ]
        },
        "similarity": 175.22532685607035
      },
      {
        "metadata": {
          "doc_id": "200",
          "name": "Exposure of Sensitive Information to an Unauthorized Actor",
          "source": "sparse",
          "original_content": "The product exposes sensitive information to an actor that is not explicitly authorized to have access to that information.",
          "keyphrase_sources": [
            {
              "id": "weakness:Information Disclosure Vulnerability",
              "keyphrase": "Information Disclosure Vulnerability",
              "type": "weakness"
            },
            {
              "id": "impact:'information disclosure']",
              "keyphrase": "'information disclosure']",
              "type": "impact"
            }
          ]
        },
        "similarity": 172.20045248746496
      },
      {
        "metadata": {
          "doc_id": "23",
          "name": "Relative Path Traversal",
          "source": "sparse",
          "original_content": "The product uses external input to construct a pathname that should be within a restricted directory, but it does not properly neutralize sequences such as \"..\" that can resolve to a location that is outside of that directory.",
          "keyphrase_sources": [
            {
              "id": "weakness:Information Disclosure Vulnerability",
              "keyphrase": "Information Disclosure Vulnerability",
              "type": "weakness"
            },
            {
              "id": "weakness:directory traversal",
              "keyphrase": "directory traversal",
              "type": "weakness"
            },
            {
              "id": "impact:['arbitrary file deletion'",
              "keyphrase": "['arbitrary file deletion'",
              "type": "impact"
            },
            {
              "id": "impact:'information disclosure']",
              "keyphrase": "'information disclosure']",
              "type": "impact"
            },
            {
              "id": "attacker:unauthenticated user",
              "keyphrase": "unauthenticated user",
              "type": "attacker"
            },
            {
              "id": "product:SolarWinds Access Rights Manager",
              "keyphrase": "SolarWinds Access Rights Manager",
              "type": "product"
            }
          ]
        },
        "similarity": 172.0549219856185
      },
      {
        "metadata": {
          "doc_id": "862",
          "name": "Missing Authorization",
          "source": "sparse",
          "original_content": "The product does not perform an authorization check when an actor attempts to access a resource or perform an action.",
          "keyphrase_sources": [
            {
              "id": "weakness:Information Disclosure Vulnerability",
              "keyphrase": "Information Disclosure Vulnerability",
              "type": "weakness"
            },
            {
              "id": "impact:'information disclosure']",
              "keyphrase": "'information disclosure']",
              "type": "impact"
            }
          ]
        },
        "similarity": 169.41072374366516
      },
      {
        "metadata": {
          "doc_id": "732",
          "name": "Incorrect Permission Assignment for Critical Resource",
          "source": "sparse",
          "original_content": "The product specifies permissions for a security-critical resource in a way that allows that resource to be read or modified by unintended actors.",
          "keyphrase_sources": [
            {
              "id": "product:SolarWinds Access Rights Manager",
              "keyphrase": "SolarWinds Access Rights Manager",
              "type": "product"
            }
          ]
        },
        "similarity": 71.47329999379404
      },
      {
        "metadata": {
          "doc_id": "288",
          "name": "Authentication Bypass Using an Alternate Path or Channel",
          "source": "sparse",
          "original_content": "The product requires authentication, but the product has an alternate path or channel that does not require authentication.",
          "keyphrase_sources": [
            {
              "id": "product:SolarWinds Access Rights Manager",
              "keyphrase": "SolarWinds Access Rights Manager",
              "type": "product"
            }
          ]
        },
        "similarity": 68.26897849925365
      },
      {
        "metadata": {
          "doc_id": "434",
          "name": "Unrestricted Upload of File with Dangerous Type",
          "source": "sparse",
          "original_content": "The product allows the upload or transfer of dangerous file types that are automatically processed within its environment.",
          "keyphrase_sources": [
            {
              "id": "impact:['arbitrary file deletion'",
              "keyphrase": "['arbitrary file deletion'",
              "type": "impact"
            },
            {
              "id": "attacker:unauthenticated user",
              "keyphrase": "unauthenticated user",
              "type": "attacker"
            },
            {
              "id": "product:SolarWinds Access Rights Manager",
              "keyphrase": "SolarWinds Access Rights Manager",
              "type": "product"
            }
          ]
        },
        "similarity": 65.43599629219747
      },
      {
        "metadata": {
          "doc_id": "306",
          "name": "Missing Authentication for Critical Function",
          "source": "sparse",
          "original_content": "The product does not perform any authentication for functionality that requires a provable user identity or consumes a significant amount of resources.",
          "keyphrase_sources": [
            {
              "id": "attacker:unauthenticated user",
              "keyphrase": "unauthenticated user",
              "type": "attacker"
            }
          ]
        },
        "similarity": 57.91034867206367
      },
      {
        "metadata": {
          "doc_id": "284",
          "name": "Improper Access Control",
          "source": "sparse",
          "original_content": "The product does not restrict or incorrectly restricts access to a resource from an unauthorized actor.",
          "keyphrase_sources": [
            {
              "id": "attacker:unauthenticated user",
              "keyphrase": "unauthenticated user",
              "type": "attacker"
            }
          ]
        },
        "similarity": 57.40222466997366
      }
    ],
    "enhanced_query": "# Vulnerability Description\n\n    The SolarWinds Access Rights Manager was susceptible to a Directory Traversal and **Information Disclosure Vulnerability**. This vulnerability allows an unauthenticated user to perform arbitrary file deletion and leak sensitive information.\n\n    # Keyphrase-Specific CWE Analysis\n    This vulnerability contains multiple keyphrases that may map to different CWEs. \n    Please analyze each keyphrase separately and determine the most appropriate CWE(s) for each.\n\n    ## WEAKNESS: 'directory traversal'\n\nRelevant CWEs for this WEAKNESS:\n\n### 1. CWE-59: Improper Link Resolution Before File Access ('Link Following') (Score: 198.72)\n\nThe product attempts to access a file based on the filename, but it does not properly prevent that filename from identifying a link or shortcut that resolves to an unintended resource....\n\n### 2. CWE-36: Absolute Path Traversal (Score: 194.80)\n\nThe product uses external input to construct a pathname that should be within a restricted directory, but it does not properly neutralize absolute path sequences such as \"/abs/path\" that can resolve to a location that is outside of that directory....\n\n### 3. CWE-22: Improper Limitation of a Pathname to a Restricted Directory ('Path Traversal') (Score: 189.10)\n\nThe product uses external input to construct a pathname that is intended to identify a file or directory that is located underneath a restricted parent directory, but the product does not properly neutralize special elements within the pathname that can cause the pathname to resolve to a location th...\n\n### 4. CWE-41: Improper Resolution of Path Equivalence (Score: 175.23)\n\nThe product is vulnerable to file system contents disclosure through path equivalence. Path equivalence involves the use of special characters in file and directory names. The associated manipulations are intended to generate multiple names for the same object....\n\n### 5. CWE-23: Relative Path Traversal (Score: 172.05)\n\nThe product uses external input to construct a pathname that should be within a restricted directory, but it does not properly neutralize sequences such as \"..\" that can resolve to a location that is outside of that directory....\n\n## IMPACT: '['arbitrary file deletion''\n\nRelevant CWEs for this IMPACT:\n\n### 1. CWE-59: Improper Link Resolution Before File Access ('Link Following') (Score: 198.72)\n\nThe product attempts to access a file based on the filename, but it does not properly prevent that filename from identifying a link or shortcut that resolves to an unintended resource....\n\n### 2. CWE-22: Improper Limitation of a Pathname to a Restricted Directory ('Path Traversal') (Score: 189.10)\n\nThe product uses external input to construct a pathname that is intended to identify a file or directory that is located underneath a restricted parent directory, but the product does not properly neutralize special elements within the pathname that can cause the pathname to resolve to a location th...\n\n### 3. CWE-41: Improper Resolution of Path Equivalence (Score: 175.23)\n\nThe product is vulnerable to file system contents disclosure through path equivalence. Path equivalence involves the use of special characters in file and directory names. The associated manipulations are intended to generate multiple names for the same object....\n\n### 4. CWE-23: Relative Path Traversal (Score: 172.05)\n\nThe product uses external input to construct a pathname that should be within a restricted directory, but it does not properly neutralize sequences such as \"..\" that can resolve to a location that is outside of that directory....\n\n### 5. CWE-434: Unrestricted Upload of File with Dangerous Type (Score: 65.44)\n\nThe product allows the upload or transfer of dangerous file types that are automatically processed within its environment....\n\n## WEAKNESS: 'Information Disclosure Vulnerability'\n\nRelevant CWEs for this WEAKNESS:\n\n### 1. CWE-22: Improper Limitation of a Pathname to a Restricted Directory ('Path Traversal') (Score: 189.10)\n\nThe product uses external input to construct a pathname that is intended to identify a file or directory that is located underneath a restricted parent directory, but the product does not properly neutralize special elements within the pathname that can cause the pathname to resolve to a location th...\n\n### 2. CWE-41: Improper Resolution of Path Equivalence (Score: 175.23)\n\nThe product is vulnerable to file system contents disclosure through path equivalence. Path equivalence involves the use of special characters in file and directory names. The associated manipulations are intended to generate multiple names for the same object....\n\n### 3. CWE-200: Exposure of Sensitive Information to an Unauthorized Actor (Score: 172.20)\n\nThe product exposes sensitive information to an actor that is not explicitly authorized to have access to that information....\n\n### 4. CWE-23: Relative Path Traversal (Score: 172.05)\n\nThe product uses external input to construct a pathname that should be within a restricted directory, but it does not properly neutralize sequences such as \"..\" that can resolve to a location that is outside of that directory....\n\n### 5. CWE-862: Missing Authorization (Score: 169.41)\n\nThe product does not perform an authorization check when an actor attempts to access a resource or perform an action....\n\n## IMPACT: ''information disclosure']'\n\nRelevant CWEs for this IMPACT:\n\n### 1. CWE-22: Improper Limitation of a Pathname to a Restricted Directory ('Path Traversal') (Score: 189.10)\n\nThe product uses external input to construct a pathname that is intended to identify a file or directory that is located underneath a restricted parent directory, but the product does not properly neutralize special elements within the pathname that can cause the pathname to resolve to a location th...\n\n### 2. CWE-41: Improper Resolution of Path Equivalence (Score: 175.23)\n\nThe product is vulnerable to file system contents disclosure through path equivalence. Path equivalence involves the use of special characters in file and directory names. The associated manipulations are intended to generate multiple names for the same object....\n\n### 3. CWE-200: Exposure of Sensitive Information to an Unauthorized Actor (Score: 172.20)\n\nThe product exposes sensitive information to an actor that is not explicitly authorized to have access to that information....\n\n### 4. CWE-23: Relative Path Traversal (Score: 172.05)\n\nThe product uses external input to construct a pathname that should be within a restricted directory, but it does not properly neutralize sequences such as \"..\" that can resolve to a location that is outside of that directory....\n\n### 5. CWE-862: Missing Authorization (Score: 169.41)\n\nThe product does not perform an authorization check when an actor attempts to access a resource or perform an action....\n\n## ATTACKER: 'unauthenticated user'\n\nRelevant CWEs for this ATTACKER:\n\n### 1. CWE-22: Improper Limitation of a Pathname to a Restricted Directory ('Path Traversal') (Score: 189.10)\n\nThe product uses external input to construct a pathname that is intended to identify a file or directory that is located underneath a restricted parent directory, but the product does not properly neutralize special elements within the pathname that can cause the pathname to resolve to a location th...\n\n### 2. CWE-23: Relative Path Traversal (Score: 172.05)\n\nThe product uses external input to construct a pathname that should be within a restricted directory, but it does not properly neutralize sequences such as \"..\" that can resolve to a location that is outside of that directory....\n\n### 3. CWE-434: Unrestricted Upload of File with Dangerous Type (Score: 65.44)\n\nThe product allows the upload or transfer of dangerous file types that are automatically processed within its environment....\n\n### 4. CWE-306: Missing Authentication for Critical Function (Score: 57.91)\n\nThe product does not perform any authentication for functionality that requires a provable user identity or consumes a significant amount of resources....\n\n### 5. CWE-284: Improper Access Control (Score: 57.40)\n\nThe product does not restrict or incorrectly restricts access to a resource from an unauthorized actor....\n\n## PRODUCT: 'SolarWinds Access Rights Manager'\n\nRelevant CWEs for this PRODUCT:\n\n### 1. CWE-22: Improper Limitation of a Pathname to a Restricted Directory ('Path Traversal') (Score: 189.10)\n\nThe product uses external input to construct a pathname that is intended to identify a file or directory that is located underneath a restricted parent directory, but the product does not properly neutralize special elements within the pathname that can cause the pathname to resolve to a location th...\n\n### 2. CWE-23: Relative Path Traversal (Score: 172.05)\n\nThe product uses external input to construct a pathname that should be within a restricted directory, but it does not properly neutralize sequences such as \"..\" that can resolve to a location that is outside of that directory....\n\n### 3. CWE-732: Incorrect Permission Assignment for Critical Resource (Score: 71.47)\n\nThe product specifies permissions for a security-critical resource in a way that allows that resource to be read or modified by unintended actors....\n\n### 4. CWE-288: Authentication Bypass Using an Alternate Path or Channel (Score: 68.27)\n\nThe product requires authentication, but the product has an alternate path or channel that does not require authentication....\n\n### 5. CWE-434: Unrestricted Upload of File with Dangerous Type (Score: 65.44)\n\nThe product allows the upload or transfer of dangerous file types that are automatically processed within its environment....\n\n\n    # Analysis Instructions\n    1. For each keyphrase, identify the most appropriate CWE(s) that represent the weakness.\n    2. Consider how the different keyphrases might relate to each other in the vulnerability chain.\n    3. Provide a final determination of primary CWE(s) and any secondary CWEs.\n    4. Format your response using the standard analysis template.\n\n    Please analyze how these different weaknesses interact and provide a comprehensive CWE classification.\n    "
  },
  "retrieval_time": 2.2454569339752197
}