{
  "vulnerability_info": "VulnerabilityInfo(cve_id='CVE-2024-53712', description='Cross-Site Request Forgery (CSRF) vulnerability in Kevin McCabe Kevins allows Stored **XSS**.This issue affects Kevins from n/a through 2.0.0.', key_phrases={'rootcause': 'lack of CSRF protection', 'weakness': ['XSS', 'cross-site scripting'], 'impact': '', 'vector': '', 'attacker': '', 'product': 'Kevin McCabe Kevins', 'version': 'through 2.0.0', 'component': ''}, reference_content='Based on the provided content, here\\'s an analysis of the vulnerability:\\n\\n**Root Cause of Vulnerability:**\\nThe root cause is a lack of Cross-Site Request Forgery (CSRF) protection within the \"Kevin\\'s Plugin\" for WordPress.\\n\\n**Weaknesses/Vulnerabilities Present:**\\n- **CSRF:** The plugin is vulnerable to CSRF attacks, allowing an attacker to potentially force an authenticated user to perform unintended actions on the website.\\n\\n**Impact of Exploitation:**\\n- A successful CSRF attack could lead to a variety of impacts, depending on the actions available in the plugin and the permissions of the targeted user. This could potentially include:\\n    - Modification of plugin settings\\n    - Data manipulation\\n    - Privilege escalation (if a high-privilege user is targeted)\\n    - Other unwanted actions on the website\\n\\n**Attack Vectors:**\\n- The attacker needs to trick a logged-in user into clicking a malicious link or visiting a malicious webpage.\\n- The user\\'s browser will then automatically send a request to the vulnerable website with the user\\'s session cookies.\\n- The vulnerable plugin, lacking CSRF protection, will execute the request as if it originated from the legitimate user.\\n\\n**Required Attacker Capabilities/Position:**\\n- The attacker does not need to be authenticated to exploit this vulnerability\\n- The attacker needs the ability to trick an authenticated user into making a request.\\n- The attacker needs knowledge of the vulnerable plugin\\'s request format and the actions they want to trigger.\\n\\n**Additional Notes:**\\n- The vulnerability has a low priority and severity, as it is unlikely to be exploited.\\n- The vulnerability affects all versions of the plugin up to and including version 2.0.0.\\n- There is no official fix available for this issue.\\n- The CVSS score of 7.1 indicates a potentially significant vulnerability. However, the article mentions that CVSS scores are not ideal for CMSs and that this particular case has a low severity impact.\\n- The vulnerability was reported by SOPROBRO on 20 Oct 2024 and published by Patchstack on 24 Nov 2024.', similar_info={'cwe_distribution': {}, 'cwe_consensus': '', 'similarity_stats': {'thresholds': [], 'total_samples_by_threshold': {}, 'top_cwes_by_threshold': {}}}, similarity_summary=SimilarityInsight(consensus_cwe='', top_cwes=[], confidence_levels={}, total_samples=0), analysis='', analysis_with_relationships='', criticism='', resolution='', relevant_cwes=[{'metadata': {'doc_id': '352', 'name': 'Cross-Site Request Forgery (CSRF)', 'source': 'sparse', 'original_content': 'The web application does not, or can not, sufficiently verify whether a well-formed, valid, consistent request was intentionally provided by the user who submitted the request.', 'keyphrase_sources': [{'id': 'rootcause:lack of CSRF protection', 'keyphrase': 'lack of CSRF protection', 'type': 'rootcause'}, {'id': 'weakness:XSS', 'keyphrase': 'XSS', 'type': 'weakness'}, {'id': 'weakness:cross-site scripting', 'keyphrase': 'cross-site scripting', 'type': 'weakness'}, {'id': 'product:Kevin McCabe Kevins', 'keyphrase': 'Kevin McCabe Kevins', 'type': 'product'}, {'id': 'version:through 2.0.0', 'keyphrase': 'through 2.0.0', 'type': 'version'}]}, 'similarity': np.float64(270.89859026469003)}, {'metadata': {'doc_id': '434', 'name': 'Unrestricted Upload of File with Dangerous Type', 'source': 'sparse', 'original_content': 'The product allows the upload or transfer of dangerous file types that are automatically processed within its environment.', 'keyphrase_sources': [{'id': 'rootcause:lack of CSRF protection', 'keyphrase': 'lack of CSRF protection', 'type': 'rootcause'}]}, 'similarity': np.float64(200.26582551367963)}, {'metadata': {'doc_id': '116', 'name': 'Improper Encoding or Escaping of Output', 'source': 'sparse', 'original_content': 'The product prepares a structured message for communication with another component, but encoding or escaping of the data is either missing or done incorrectly. As a result, the intended structure of the message is not preserved.', 'keyphrase_sources': [{'id': 'rootcause:lack of CSRF protection', 'keyphrase': 'lack of CSRF protection', 'type': 'rootcause'}, {'id': 'weakness:XSS', 'keyphrase': 'XSS', 'type': 'weakness'}, {'id': 'weakness:cross-site scripting', 'keyphrase': 'cross-site scripting', 'type': 'weakness'}]}, 'similarity': np.float64(192.31333634974976)}, {'metadata': {'doc_id': '79', 'name': \"Improper Neutralization of Input During Web Page Generation ('Cross-site Scripting')\", 'source': 'sparse', 'original_content': 'The product does not neutralize or incorrectly neutralizes user-controllable input before it is placed in output that is used as a web page that is served to other users.', 'keyphrase_sources': [{'id': 'rootcause:lack of CSRF protection', 'keyphrase': 'lack of CSRF protection', 'type': 'rootcause'}, {'id': 'weakness:XSS', 'keyphrase': 'XSS', 'type': 'weakness'}, {'id': 'weakness:cross-site scripting', 'keyphrase': 'cross-site scripting', 'type': 'weakness'}, {'id': 'product:Kevin McCabe Kevins', 'keyphrase': 'Kevin McCabe Kevins', 'type': 'product'}, {'id': 'version:through 2.0.0', 'keyphrase': 'through 2.0.0', 'type': 'version'}]}, 'similarity': np.float64(188.7570207914032)}, {'metadata': {'doc_id': '1004', 'name': \"Sensitive Cookie Without 'HttpOnly' Flag\", 'source': 'sparse', 'original_content': 'The product uses a cookie to store sensitive information, but the cookie is not marked with the HttpOnly flag.', 'keyphrase_sources': [{'id': 'rootcause:lack of CSRF protection', 'keyphrase': 'lack of CSRF protection', 'type': 'rootcause'}, {'id': 'weakness:XSS', 'keyphrase': 'XSS', 'type': 'weakness'}, {'id': 'weakness:cross-site scripting', 'keyphrase': 'cross-site scripting', 'type': 'weakness'}, {'id': 'product:Kevin McCabe Kevins', 'keyphrase': 'Kevin McCabe Kevins', 'type': 'product'}, {'id': 'version:through 2.0.0', 'keyphrase': 'through 2.0.0', 'type': 'version'}]}, 'similarity': np.float64(178.93470596861016)}, {'metadata': {'doc_id': '80', 'name': 'Improper Neutralization of Script-Related HTML Tags in a Web Page (Basic XSS)', 'source': 'sparse', 'original_content': 'The product receives input from an upstream component, but it does not neutralize or incorrectly neutralizes special characters such as \"<\", \">\", and \"&\" that could be interpreted as web-scripting elements when they are sent to a downstream component that processes web pages.', 'keyphrase_sources': [{'id': 'weakness:XSS', 'keyphrase': 'XSS', 'type': 'weakness'}, {'id': 'weakness:cross-site scripting', 'keyphrase': 'cross-site scripting', 'type': 'weakness'}]}, 'similarity': np.float64(138.58371569780837)}, {'metadata': {'doc_id': '89', 'name': \"Improper Neutralization of Special Elements used in an SQL Command ('SQL Injection')\", 'source': 'sparse', 'original_content': 'The product constructs all or part of an SQL command using externally-influenced input from an upstream component, but it does not neutralize or incorrectly neutralizes special elements that could modify the intended SQL command when it is sent to a downstream component. Without sufficient removal or quoting of SQL syntax in user-controllable inputs, the generated SQL query can cause those inputs to be interpreted as SQL instead of ordinary user data.', 'keyphrase_sources': [{'id': 'product:Kevin McCabe Kevins', 'keyphrase': 'Kevin McCabe Kevins', 'type': 'product'}, {'id': 'version:through 2.0.0', 'keyphrase': 'through 2.0.0', 'type': 'version'}]}, 'similarity': np.float64(43.19611634824957)}, {'metadata': {'doc_id': '918', 'name': 'Server-Side Request Forgery (SSRF)', 'source': 'sparse', 'original_content': 'The web server receives a URL or similar request from an upstream component and retrieves the contents of this URL, but it does not sufficiently ensure that the request is being sent to the expected destination.', 'keyphrase_sources': [{'id': 'product:Kevin McCabe Kevins', 'keyphrase': 'Kevin McCabe Kevins', 'type': 'product'}, {'id': 'version:through 2.0.0', 'keyphrase': 'through 2.0.0', 'type': 'version'}]}, 'similarity': np.float64(41.8853487144726)}], identified_cwes={'analyzer': [], 'critic_additional': []})",
  "retrieval_results": {
    "has_multiple_keyphrases": true,
    "keyphrase_cwe_sets": {
      "rootcause:lack of CSRF protection": {
        "keyphrase": "lack of CSRF protection",
        "type": "rootcause",
        "cwes": [
          {
            "metadata": {
              "doc_id": "352",
              "name": "Cross-Site Request Forgery (CSRF)",
              "source": "sparse",
              "original_content": "The web application does not, or can not, sufficiently verify whether a well-formed, valid, consistent request was intentionally provided by the user who submitted the request.",
              "keyphrase_sources": [
                {
                  "id": "rootcause:lack of CSRF protection",
                  "keyphrase": "lack of CSRF protection",
                  "type": "rootcause"
                },
                {
                  "id": "weakness:XSS",
                  "keyphrase": "XSS",
                  "type": "weakness"
                },
                {
                  "id": "weakness:cross-site scripting",
                  "keyphrase": "cross-site scripting",
                  "type": "weakness"
                },
                {
                  "id": "product:Kevin McCabe Kevins",
                  "keyphrase": "Kevin McCabe Kevins",
                  "type": "product"
                },
                {
                  "id": "version:through 2.0.0",
                  "keyphrase": "through 2.0.0",
                  "type": "version"
                }
              ]
            },
            "similarity": 270.89859026469003
          },
          {
            "metadata": {
              "doc_id": "434",
              "name": "Unrestricted Upload of File with Dangerous Type",
              "source": "sparse",
              "original_content": "The product allows the upload or transfer of dangerous file types that are automatically processed within its environment.",
              "keyphrase_sources": [
                {
                  "id": "rootcause:lack of CSRF protection",
                  "keyphrase": "lack of CSRF protection",
                  "type": "rootcause"
                }
              ]
            },
            "similarity": 200.26582551367963
          },
          {
            "metadata": {
              "doc_id": "116",
              "name": "Improper Encoding or Escaping of Output",
              "source": "sparse",
              "original_content": "The product prepares a structured message for communication with another component, but encoding or escaping of the data is either missing or done incorrectly. As a result, the intended structure of the message is not preserved.",
              "keyphrase_sources": [
                {
                  "id": "rootcause:lack of CSRF protection",
                  "keyphrase": "lack of CSRF protection",
                  "type": "rootcause"
                },
                {
                  "id": "weakness:XSS",
                  "keyphrase": "XSS",
                  "type": "weakness"
                },
                {
                  "id": "weakness:cross-site scripting",
                  "keyphrase": "cross-site scripting",
                  "type": "weakness"
                }
              ]
            },
            "similarity": 192.31333634974976
          },
          {
            "metadata": {
              "doc_id": "79",
              "name": "Improper Neutralization of Input During Web Page Generation ('Cross-site Scripting')",
              "source": "sparse",
              "original_content": "The product does not neutralize or incorrectly neutralizes user-controllable input before it is placed in output that is used as a web page that is served to other users.",
              "keyphrase_sources": [
                {
                  "id": "rootcause:lack of CSRF protection",
                  "keyphrase": "lack of CSRF protection",
                  "type": "rootcause"
                },
                {
                  "id": "weakness:XSS",
                  "keyphrase": "XSS",
                  "type": "weakness"
                },
                {
                  "id": "weakness:cross-site scripting",
                  "keyphrase": "cross-site scripting",
                  "type": "weakness"
                },
                {
                  "id": "product:Kevin McCabe Kevins",
                  "keyphrase": "Kevin McCabe Kevins",
                  "type": "product"
                },
                {
                  "id": "version:through 2.0.0",
                  "keyphrase": "through 2.0.0",
                  "type": "version"
                }
              ]
            },
            "similarity": 188.7570207914032
          },
          {
            "metadata": {
              "doc_id": "1004",
              "name": "Sensitive Cookie Without 'HttpOnly' Flag",
              "source": "sparse",
              "original_content": "The product uses a cookie to store sensitive information, but the cookie is not marked with the HttpOnly flag.",
              "keyphrase_sources": [
                {
                  "id": "rootcause:lack of CSRF protection",
                  "keyphrase": "lack of CSRF protection",
                  "type": "rootcause"
                },
                {
                  "id": "weakness:XSS",
                  "keyphrase": "XSS",
                  "type": "weakness"
                },
                {
                  "id": "weakness:cross-site scripting",
                  "keyphrase": "cross-site scripting",
                  "type": "weakness"
                },
                {
                  "id": "product:Kevin McCabe Kevins",
                  "keyphrase": "Kevin McCabe Kevins",
                  "type": "product"
                },
                {
                  "id": "version:through 2.0.0",
                  "keyphrase": "through 2.0.0",
                  "type": "version"
                }
              ]
            },
            "similarity": 178.93470596861016
          }
        ]
      },
      "weakness:XSS": {
        "keyphrase": "XSS",
        "type": "weakness",
        "cwes": [
          {
            "metadata": {
              "doc_id": "352",
              "name": "Cross-Site Request Forgery (CSRF)",
              "source": "sparse",
              "original_content": "The web application does not, or can not, sufficiently verify whether a well-formed, valid, consistent request was intentionally provided by the user who submitted the request."
            },
            "similarity": 180.59712868966366
          },
          {
            "metadata": {
              "doc_id": "79",
              "name": "Improper Neutralization of Input During Web Page Generation ('Cross-site Scripting')",
              "source": "sparse",
              "original_content": "The product does not neutralize or incorrectly neutralizes user-controllable input before it is placed in output that is used as a web page that is served to other users."
            },
            "similarity": 157.93561073895094
          },
          {
            "metadata": {
              "doc_id": "1004",
              "name": "Sensitive Cookie Without 'HttpOnly' Flag",
              "source": "sparse",
              "original_content": "The product uses a cookie to store sensitive information, but the cookie is not marked with the HttpOnly flag."
            },
            "similarity": 145.90384485882072
          },
          {
            "metadata": {
              "doc_id": "116",
              "name": "Improper Encoding or Escaping of Output",
              "source": "sparse",
              "original_content": "The product prepares a structured message for communication with another component, but encoding or escaping of the data is either missing or done incorrectly. As a result, the intended structure of the message is not preserved."
            },
            "similarity": 138.92916167404726
          },
          {
            "metadata": {
              "doc_id": "80",
              "name": "Improper Neutralization of Script-Related HTML Tags in a Web Page (Basic XSS)",
              "source": "sparse",
              "original_content": "The product receives input from an upstream component, but it does not neutralize or incorrectly neutralizes special characters such as \"<\", \">\", and \"&\" that could be interpreted as web-scripting elements when they are sent to a downstream component that processes web pages.",
              "keyphrase_sources": [
                {
                  "id": "weakness:XSS",
                  "keyphrase": "XSS",
                  "type": "weakness"
                },
                {
                  "id": "weakness:cross-site scripting",
                  "keyphrase": "cross-site scripting",
                  "type": "weakness"
                }
              ]
            },
            "similarity": 138.58371569780837
          }
        ]
      },
      "weakness:cross-site scripting": {
        "keyphrase": "cross-site scripting",
        "type": "weakness",
        "cwes": [
          {
            "metadata": {
              "doc_id": "352",
              "name": "Cross-Site Request Forgery (CSRF)",
              "source": "sparse",
              "original_content": "The web application does not, or can not, sufficiently verify whether a well-formed, valid, consistent request was intentionally provided by the user who submitted the request."
            },
            "similarity": 248.6202739657996
          },
          {
            "metadata": {
              "doc_id": "79",
              "name": "Improper Neutralization of Input During Web Page Generation ('Cross-site Scripting')",
              "source": "sparse",
              "original_content": "The product does not neutralize or incorrectly neutralizes user-controllable input before it is placed in output that is used as a web page that is served to other users."
            },
            "similarity": 219.9004020958371
          },
          {
            "metadata": {
              "doc_id": "80",
              "name": "Improper Neutralization of Script-Related HTML Tags in a Web Page (Basic XSS)",
              "source": "sparse",
              "original_content": "The product receives input from an upstream component, but it does not neutralize or incorrectly neutralizes special characters such as \"<\", \">\", and \"&\" that could be interpreted as web-scripting elements when they are sent to a downstream component that processes web pages."
            },
            "similarity": 195.26221891628668
          },
          {
            "metadata": {
              "doc_id": "1004",
              "name": "Sensitive Cookie Without 'HttpOnly' Flag",
              "source": "sparse",
              "original_content": "The product uses a cookie to store sensitive information, but the cookie is not marked with the HttpOnly flag."
            },
            "similarity": 190.45562160496553
          },
          {
            "metadata": {
              "doc_id": "116",
              "name": "Improper Encoding or Escaping of Output",
              "source": "sparse",
              "original_content": "The product prepares a structured message for communication with another component, but encoding or escaping of the data is either missing or done incorrectly. As a result, the intended structure of the message is not preserved."
            },
            "similarity": 186.09938955820772
          }
        ]
      },
      "product:Kevin McCabe Kevins": {
        "keyphrase": "Kevin McCabe Kevins",
        "type": "product",
        "cwes": [
          {
            "metadata": {
              "doc_id": "352",
              "name": "Cross-Site Request Forgery (CSRF)",
              "source": "sparse",
              "original_content": "The web application does not, or can not, sufficiently verify whether a well-formed, valid, consistent request was intentionally provided by the user who submitted the request."
            },
            "similarity": 55.14167025120315
          },
          {
            "metadata": {
              "doc_id": "79",
              "name": "Improper Neutralization of Input During Web Page Generation ('Cross-site Scripting')",
              "source": "sparse",
              "original_content": "The product does not neutralize or incorrectly neutralizes user-controllable input before it is placed in output that is used as a web page that is served to other users."
            },
            "similarity": 45.83920687509285
          },
          {
            "metadata": {
              "doc_id": "1004",
              "name": "Sensitive Cookie Without 'HttpOnly' Flag",
              "source": "sparse",
              "original_content": "The product uses a cookie to store sensitive information, but the cookie is not marked with the HttpOnly flag."
            },
            "similarity": 43.24305661077844
          },
          {
            "metadata": {
              "doc_id": "89",
              "name": "Improper Neutralization of Special Elements used in an SQL Command ('SQL Injection')",
              "source": "sparse",
              "original_content": "The product constructs all or part of an SQL command using externally-influenced input from an upstream component, but it does not neutralize or incorrectly neutralizes special elements that could modify the intended SQL command when it is sent to a downstream component. Without sufficient removal or quoting of SQL syntax in user-controllable inputs, the generated SQL query can cause those inputs to be interpreted as SQL instead of ordinary user data.",
              "keyphrase_sources": [
                {
                  "id": "product:Kevin McCabe Kevins",
                  "keyphrase": "Kevin McCabe Kevins",
                  "type": "product"
                },
                {
                  "id": "version:through 2.0.0",
                  "keyphrase": "through 2.0.0",
                  "type": "version"
                }
              ]
            },
            "similarity": 43.19611634824957
          },
          {
            "metadata": {
              "doc_id": "918",
              "name": "Server-Side Request Forgery (SSRF)",
              "source": "sparse",
              "original_content": "The web server receives a URL or similar request from an upstream component and retrieves the contents of this URL, but it does not sufficiently ensure that the request is being sent to the expected destination.",
              "keyphrase_sources": [
                {
                  "id": "product:Kevin McCabe Kevins",
                  "keyphrase": "Kevin McCabe Kevins",
                  "type": "product"
                },
                {
                  "id": "version:through 2.0.0",
                  "keyphrase": "through 2.0.0",
                  "type": "version"
                }
              ]
            },
            "similarity": 41.8853487144726
          }
        ]
      },
      "version:through 2.0.0": {
        "keyphrase": "through 2.0.0",
        "type": "version",
        "cwes": [
          {
            "metadata": {
              "doc_id": "352",
              "name": "Cross-Site Request Forgery (CSRF)",
              "source": "sparse",
              "original_content": "The web application does not, or can not, sufficiently verify whether a well-formed, valid, consistent request was intentionally provided by the user who submitted the request."
            },
            "similarity": 63.614281312851844
          },
          {
            "metadata": {
              "doc_id": "79",
              "name": "Improper Neutralization of Input During Web Page Generation ('Cross-site Scripting')",
              "source": "sparse",
              "original_content": "The product does not neutralize or incorrectly neutralizes user-controllable input before it is placed in output that is used as a web page that is served to other users."
            },
            "similarity": 53.65031643166275
          },
          {
            "metadata": {
              "doc_id": "89",
              "name": "Improper Neutralization of Special Elements used in an SQL Command ('SQL Injection')",
              "source": "sparse",
              "original_content": "The product constructs all or part of an SQL command using externally-influenced input from an upstream component, but it does not neutralize or incorrectly neutralizes special elements that could modify the intended SQL command when it is sent to a downstream component. Without sufficient removal or quoting of SQL syntax in user-controllable inputs, the generated SQL query can cause those inputs to be interpreted as SQL instead of ordinary user data."
            },
            "similarity": 51.70200522140657
          },
          {
            "metadata": {
              "doc_id": "1004",
              "name": "Sensitive Cookie Without 'HttpOnly' Flag",
              "source": "sparse",
              "original_content": "The product uses a cookie to store sensitive information, but the cookie is not marked with the HttpOnly flag."
            },
            "similarity": 50.71813991688053
          },
          {
            "metadata": {
              "doc_id": "918",
              "name": "Server-Side Request Forgery (SSRF)",
              "source": "sparse",
              "original_content": "The web server receives a URL or similar request from an upstream component and retrieves the contents of this URL, but it does not sufficiently ensure that the request is being sent to the expected destination."
            },
            "similarity": 50.248031876137475
          }
        ]
      }
    },
    "keyphrase_mapping": {
      "352": [
        {
          "id": "rootcause:lack of CSRF protection",
          "keyphrase": "lack of CSRF protection",
          "type": "rootcause"
        },
        {
          "id": "weakness:XSS",
          "keyphrase": "XSS",
          "type": "weakness"
        },
        {
          "id": "weakness:cross-site scripting",
          "keyphrase": "cross-site scripting",
          "type": "weakness"
        },
        {
          "id": "product:Kevin McCabe Kevins",
          "keyphrase": "Kevin McCabe Kevins",
          "type": "product"
        },
        {
          "id": "version:through 2.0.0",
          "keyphrase": "through 2.0.0",
          "type": "version"
        }
      ],
      "434": [
        {
          "id": "rootcause:lack of CSRF protection",
          "keyphrase": "lack of CSRF protection",
          "type": "rootcause"
        }
      ],
      "116": [
        {
          "id": "rootcause:lack of CSRF protection",
          "keyphrase": "lack of CSRF protection",
          "type": "rootcause"
        },
        {
          "id": "weakness:XSS",
          "keyphrase": "XSS",
          "type": "weakness"
        },
        {
          "id": "weakness:cross-site scripting",
          "keyphrase": "cross-site scripting",
          "type": "weakness"
        }
      ],
      "79": [
        {
          "id": "rootcause:lack of CSRF protection",
          "keyphrase": "lack of CSRF protection",
          "type": "rootcause"
        },
        {
          "id": "weakness:XSS",
          "keyphrase": "XSS",
          "type": "weakness"
        },
        {
          "id": "weakness:cross-site scripting",
          "keyphrase": "cross-site scripting",
          "type": "weakness"
        },
        {
          "id": "product:Kevin McCabe Kevins",
          "keyphrase": "Kevin McCabe Kevins",
          "type": "product"
        },
        {
          "id": "version:through 2.0.0",
          "keyphrase": "through 2.0.0",
          "type": "version"
        }
      ],
      "1004": [
        {
          "id": "rootcause:lack of CSRF protection",
          "keyphrase": "lack of CSRF protection",
          "type": "rootcause"
        },
        {
          "id": "weakness:XSS",
          "keyphrase": "XSS",
          "type": "weakness"
        },
        {
          "id": "weakness:cross-site scripting",
          "keyphrase": "cross-site scripting",
          "type": "weakness"
        },
        {
          "id": "product:Kevin McCabe Kevins",
          "keyphrase": "Kevin McCabe Kevins",
          "type": "product"
        },
        {
          "id": "version:through 2.0.0",
          "keyphrase": "through 2.0.0",
          "type": "version"
        }
      ],
      "80": [
        {
          "id": "weakness:XSS",
          "keyphrase": "XSS",
          "type": "weakness"
        },
        {
          "id": "weakness:cross-site scripting",
          "keyphrase": "cross-site scripting",
          "type": "weakness"
        }
      ],
      "89": [
        {
          "id": "product:Kevin McCabe Kevins",
          "keyphrase": "Kevin McCabe Kevins",
          "type": "product"
        },
        {
          "id": "version:through 2.0.0",
          "keyphrase": "through 2.0.0",
          "type": "version"
        }
      ],
      "918": [
        {
          "id": "product:Kevin McCabe Kevins",
          "keyphrase": "Kevin McCabe Kevins",
          "type": "product"
        },
        {
          "id": "version:through 2.0.0",
          "keyphrase": "through 2.0.0",
          "type": "version"
        }
      ]
    },
    "relevant_cwes": [
      {
        "metadata": {
          "doc_id": "352",
          "name": "Cross-Site Request Forgery (CSRF)",
          "source": "sparse",
          "original_content": "The web application does not, or can not, sufficiently verify whether a well-formed, valid, consistent request was intentionally provided by the user who submitted the request.",
          "keyphrase_sources": [
            {
              "id": "rootcause:lack of CSRF protection",
              "keyphrase": "lack of CSRF protection",
              "type": "rootcause"
            },
            {
              "id": "weakness:XSS",
              "keyphrase": "XSS",
              "type": "weakness"
            },
            {
              "id": "weakness:cross-site scripting",
              "keyphrase": "cross-site scripting",
              "type": "weakness"
            },
            {
              "id": "product:Kevin McCabe Kevins",
              "keyphrase": "Kevin McCabe Kevins",
              "type": "product"
            },
            {
              "id": "version:through 2.0.0",
              "keyphrase": "through 2.0.0",
              "type": "version"
            }
          ]
        },
        "similarity": 270.89859026469003
      },
      {
        "metadata": {
          "doc_id": "434",
          "name": "Unrestricted Upload of File with Dangerous Type",
          "source": "sparse",
          "original_content": "The product allows the upload or transfer of dangerous file types that are automatically processed within its environment.",
          "keyphrase_sources": [
            {
              "id": "rootcause:lack of CSRF protection",
              "keyphrase": "lack of CSRF protection",
              "type": "rootcause"
            }
          ]
        },
        "similarity": 200.26582551367963
      },
      {
        "metadata": {
          "doc_id": "116",
          "name": "Improper Encoding or Escaping of Output",
          "source": "sparse",
          "original_content": "The product prepares a structured message for communication with another component, but encoding or escaping of the data is either missing or done incorrectly. As a result, the intended structure of the message is not preserved.",
          "keyphrase_sources": [
            {
              "id": "rootcause:lack of CSRF protection",
              "keyphrase": "lack of CSRF protection",
              "type": "rootcause"
            },
            {
              "id": "weakness:XSS",
              "keyphrase": "XSS",
              "type": "weakness"
            },
            {
              "id": "weakness:cross-site scripting",
              "keyphrase": "cross-site scripting",
              "type": "weakness"
            }
          ]
        },
        "similarity": 192.31333634974976
      },
      {
        "metadata": {
          "doc_id": "79",
          "name": "Improper Neutralization of Input During Web Page Generation ('Cross-site Scripting')",
          "source": "sparse",
          "original_content": "The product does not neutralize or incorrectly neutralizes user-controllable input before it is placed in output that is used as a web page that is served to other users.",
          "keyphrase_sources": [
            {
              "id": "rootcause:lack of CSRF protection",
              "keyphrase": "lack of CSRF protection",
              "type": "rootcause"
            },
            {
              "id": "weakness:XSS",
              "keyphrase": "XSS",
              "type": "weakness"
            },
            {
              "id": "weakness:cross-site scripting",
              "keyphrase": "cross-site scripting",
              "type": "weakness"
            },
            {
              "id": "product:Kevin McCabe Kevins",
              "keyphrase": "Kevin McCabe Kevins",
              "type": "product"
            },
            {
              "id": "version:through 2.0.0",
              "keyphrase": "through 2.0.0",
              "type": "version"
            }
          ]
        },
        "similarity": 188.7570207914032
      },
      {
        "metadata": {
          "doc_id": "1004",
          "name": "Sensitive Cookie Without 'HttpOnly' Flag",
          "source": "sparse",
          "original_content": "The product uses a cookie to store sensitive information, but the cookie is not marked with the HttpOnly flag.",
          "keyphrase_sources": [
            {
              "id": "rootcause:lack of CSRF protection",
              "keyphrase": "lack of CSRF protection",
              "type": "rootcause"
            },
            {
              "id": "weakness:XSS",
              "keyphrase": "XSS",
              "type": "weakness"
            },
            {
              "id": "weakness:cross-site scripting",
              "keyphrase": "cross-site scripting",
              "type": "weakness"
            },
            {
              "id": "product:Kevin McCabe Kevins",
              "keyphrase": "Kevin McCabe Kevins",
              "type": "product"
            },
            {
              "id": "version:through 2.0.0",
              "keyphrase": "through 2.0.0",
              "type": "version"
            }
          ]
        },
        "similarity": 178.93470596861016
      },
      {
        "metadata": {
          "doc_id": "80",
          "name": "Improper Neutralization of Script-Related HTML Tags in a Web Page (Basic XSS)",
          "source": "sparse",
          "original_content": "The product receives input from an upstream component, but it does not neutralize or incorrectly neutralizes special characters such as \"<\", \">\", and \"&\" that could be interpreted as web-scripting elements when they are sent to a downstream component that processes web pages.",
          "keyphrase_sources": [
            {
              "id": "weakness:XSS",
              "keyphrase": "XSS",
              "type": "weakness"
            },
            {
              "id": "weakness:cross-site scripting",
              "keyphrase": "cross-site scripting",
              "type": "weakness"
            }
          ]
        },
        "similarity": 138.58371569780837
      },
      {
        "metadata": {
          "doc_id": "89",
          "name": "Improper Neutralization of Special Elements used in an SQL Command ('SQL Injection')",
          "source": "sparse",
          "original_content": "The product constructs all or part of an SQL command using externally-influenced input from an upstream component, but it does not neutralize or incorrectly neutralizes special elements that could modify the intended SQL command when it is sent to a downstream component. Without sufficient removal or quoting of SQL syntax in user-controllable inputs, the generated SQL query can cause those inputs to be interpreted as SQL instead of ordinary user data.",
          "keyphrase_sources": [
            {
              "id": "product:Kevin McCabe Kevins",
              "keyphrase": "Kevin McCabe Kevins",
              "type": "product"
            },
            {
              "id": "version:through 2.0.0",
              "keyphrase": "through 2.0.0",
              "type": "version"
            }
          ]
        },
        "similarity": 43.19611634824957
      },
      {
        "metadata": {
          "doc_id": "918",
          "name": "Server-Side Request Forgery (SSRF)",
          "source": "sparse",
          "original_content": "The web server receives a URL or similar request from an upstream component and retrieves the contents of this URL, but it does not sufficiently ensure that the request is being sent to the expected destination.",
          "keyphrase_sources": [
            {
              "id": "product:Kevin McCabe Kevins",
              "keyphrase": "Kevin McCabe Kevins",
              "type": "product"
            },
            {
              "id": "version:through 2.0.0",
              "keyphrase": "through 2.0.0",
              "type": "version"
            }
          ]
        },
        "similarity": 41.8853487144726
      }
    ],
    "enhanced_query": "# Vulnerability Description\n\n    Cross-Site Request Forgery (CSRF) vulnerability in Kevin McCabe Kevins allows Stored **XSS**.This issue affects Kevins from n/a through 2.0.0.\n\n    # Keyphrase-Specific CWE Analysis\n    This vulnerability contains multiple keyphrases that may map to different CWEs. \n    Please analyze each keyphrase separately and determine the most appropriate CWE(s) for each.\n\n    ## ROOTCAUSE: 'lack of CSRF protection'\n\nRelevant CWEs for this ROOTCAUSE:\n\n### 1. CWE-352: Cross-Site Request Forgery (CSRF) (Score: 270.90)\n\nThe web application does not, or can not, sufficiently verify whether a well-formed, valid, consistent request was intentionally provided by the user who submitted the request....\n\n### 2. CWE-434: Unrestricted Upload of File with Dangerous Type (Score: 200.27)\n\nThe product allows the upload or transfer of dangerous file types that are automatically processed within its environment....\n\n### 3. CWE-116: Improper Encoding or Escaping of Output (Score: 192.31)\n\nThe product prepares a structured message for communication with another component, but encoding or escaping of the data is either missing or done incorrectly. As a result, the intended structure of the message is not preserved....\n\n### 4. CWE-79: Improper Neutralization of Input During Web Page Generation ('Cross-site Scripting') (Score: 188.76)\n\nThe product does not neutralize or incorrectly neutralizes user-controllable input before it is placed in output that is used as a web page that is served to other users....\n\n### 5. CWE-1004: Sensitive Cookie Without 'HttpOnly' Flag (Score: 178.93)\n\nThe product uses a cookie to store sensitive information, but the cookie is not marked with the HttpOnly flag....\n\n## WEAKNESS: 'XSS'\n\nRelevant CWEs for this WEAKNESS:\n\n### 1. CWE-352: Cross-Site Request Forgery (CSRF) (Score: 270.90)\n\nThe web application does not, or can not, sufficiently verify whether a well-formed, valid, consistent request was intentionally provided by the user who submitted the request....\n\n### 2. CWE-116: Improper Encoding or Escaping of Output (Score: 192.31)\n\nThe product prepares a structured message for communication with another component, but encoding or escaping of the data is either missing or done incorrectly. As a result, the intended structure of the message is not preserved....\n\n### 3. CWE-79: Improper Neutralization of Input During Web Page Generation ('Cross-site Scripting') (Score: 188.76)\n\nThe product does not neutralize or incorrectly neutralizes user-controllable input before it is placed in output that is used as a web page that is served to other users....\n\n### 4. CWE-1004: Sensitive Cookie Without 'HttpOnly' Flag (Score: 178.93)\n\nThe product uses a cookie to store sensitive information, but the cookie is not marked with the HttpOnly flag....\n\n### 5. CWE-80: Improper Neutralization of Script-Related HTML Tags in a Web Page (Basic XSS) (Score: 138.58)\n\nThe product receives input from an upstream component, but it does not neutralize or incorrectly neutralizes special characters such as \"<\", \">\", and \"&\" that could be interpreted as web-scripting elements when they are sent to a downstream component that processes web pages....\n\n## WEAKNESS: 'cross-site scripting'\n\nRelevant CWEs for this WEAKNESS:\n\n### 1. CWE-352: Cross-Site Request Forgery (CSRF) (Score: 270.90)\n\nThe web application does not, or can not, sufficiently verify whether a well-formed, valid, consistent request was intentionally provided by the user who submitted the request....\n\n### 2. CWE-116: Improper Encoding or Escaping of Output (Score: 192.31)\n\nThe product prepares a structured message for communication with another component, but encoding or escaping of the data is either missing or done incorrectly. As a result, the intended structure of the message is not preserved....\n\n### 3. CWE-79: Improper Neutralization of Input During Web Page Generation ('Cross-site Scripting') (Score: 188.76)\n\nThe product does not neutralize or incorrectly neutralizes user-controllable input before it is placed in output that is used as a web page that is served to other users....\n\n### 4. CWE-1004: Sensitive Cookie Without 'HttpOnly' Flag (Score: 178.93)\n\nThe product uses a cookie to store sensitive information, but the cookie is not marked with the HttpOnly flag....\n\n### 5. CWE-80: Improper Neutralization of Script-Related HTML Tags in a Web Page (Basic XSS) (Score: 138.58)\n\nThe product receives input from an upstream component, but it does not neutralize or incorrectly neutralizes special characters such as \"<\", \">\", and \"&\" that could be interpreted as web-scripting elements when they are sent to a downstream component that processes web pages....\n\n## PRODUCT: 'Kevin McCabe Kevins'\n\nRelevant CWEs for this PRODUCT:\n\n### 1. CWE-352: Cross-Site Request Forgery (CSRF) (Score: 270.90)\n\nThe web application does not, or can not, sufficiently verify whether a well-formed, valid, consistent request was intentionally provided by the user who submitted the request....\n\n### 2. CWE-79: Improper Neutralization of Input During Web Page Generation ('Cross-site Scripting') (Score: 188.76)\n\nThe product does not neutralize or incorrectly neutralizes user-controllable input before it is placed in output that is used as a web page that is served to other users....\n\n### 3. CWE-1004: Sensitive Cookie Without 'HttpOnly' Flag (Score: 178.93)\n\nThe product uses a cookie to store sensitive information, but the cookie is not marked with the HttpOnly flag....\n\n### 4. CWE-89: Improper Neutralization of Special Elements used in an SQL Command ('SQL Injection') (Score: 43.20)\n\nThe product constructs all or part of an SQL command using externally-influenced input from an upstream component, but it does not neutralize or incorrectly neutralizes special elements that could modify the intended SQL command when it is sent to a downstream component. Without sufficient removal o...\n\n### 5. CWE-918: Server-Side Request Forgery (SSRF) (Score: 41.89)\n\nThe web server receives a URL or similar request from an upstream component and retrieves the contents of this URL, but it does not sufficiently ensure that the request is being sent to the expected destination....\n\n## VERSION: 'through 2.0.0'\n\nRelevant CWEs for this VERSION:\n\n### 1. CWE-352: Cross-Site Request Forgery (CSRF) (Score: 270.90)\n\nThe web application does not, or can not, sufficiently verify whether a well-formed, valid, consistent request was intentionally provided by the user who submitted the request....\n\n### 2. CWE-79: Improper Neutralization of Input During Web Page Generation ('Cross-site Scripting') (Score: 188.76)\n\nThe product does not neutralize or incorrectly neutralizes user-controllable input before it is placed in output that is used as a web page that is served to other users....\n\n### 3. CWE-1004: Sensitive Cookie Without 'HttpOnly' Flag (Score: 178.93)\n\nThe product uses a cookie to store sensitive information, but the cookie is not marked with the HttpOnly flag....\n\n### 4. CWE-89: Improper Neutralization of Special Elements used in an SQL Command ('SQL Injection') (Score: 43.20)\n\nThe product constructs all or part of an SQL command using externally-influenced input from an upstream component, but it does not neutralize or incorrectly neutralizes special elements that could modify the intended SQL command when it is sent to a downstream component. Without sufficient removal o...\n\n### 5. CWE-918: Server-Side Request Forgery (SSRF) (Score: 41.89)\n\nThe web server receives a URL or similar request from an upstream component and retrieves the contents of this URL, but it does not sufficiently ensure that the request is being sent to the expected destination....\n\n\n    # Analysis Instructions\n    1. For each keyphrase, identify the most appropriate CWE(s) that represent the weakness.\n    2. Consider how the different keyphrases might relate to each other in the vulnerability chain.\n    3. Provide a final determination of primary CWE(s) and any secondary CWEs.\n    4. Format your response using the standard analysis template.\n\n    Please analyze how these different weaknesses interact and provide a comprehensive CWE classification.\n    "
  },
  "retrieval_time": 1.0239737033843994
}