{
  "vulnerability_info": "VulnerabilityInfo(cve_id='CVE-2024-51655', description='Cross-Site Request Forgery (CSRF) vulnerability in Microkid Custom Author URL allows Stored **XSS**.This issue affects Custom Author URL from n/a through 2.0.1.', key_phrases={'rootcause': 'lack of CSRF protection', 'weakness': ['XSS', 'cross-site scripting'], 'impact': '', 'vector': '', 'attacker': '', 'product': 'Microkid Custom Author URL', 'version': 'n/a through 2.0.1', 'component': ''}, reference_content=\"- **Root cause of vulnerability:** The Custom Author URL WordPress plugin versions 2.0.1 and earlier are vulnerable to Cross-Site Request Forgery (CSRF).\\n- **Weaknesses/vulnerabilities present:** The plugin lacks proper CSRF protection, allowing attackers to forge requests on behalf of authenticated users.\\n- **Impact of exploitation:** A successful CSRF attack could force higher-privileged users to execute unwanted actions within the WordPress site under their current authentication.\\n- **Attack vectors:** The attack is initiated by a malicious actor who crafts a request that, when triggered by a logged-in user, will perform an action on the user's behalf.\\n- **Required attacker capabilities/position:** The attacker needs to trick an authenticated user into clicking a malicious link or visiting a malicious page. The attacker does not require any specific privileges on the WordPress site.\", similar_info={'cwe_distribution': {}, 'cwe_consensus': '', 'similarity_stats': {'thresholds': [], 'total_samples_by_threshold': {}, 'top_cwes_by_threshold': {}}}, similarity_summary=SimilarityInsight(consensus_cwe='', top_cwes=[], confidence_levels={}, total_samples=0), analysis='', analysis_with_relationships='', criticism='', resolution='', relevant_cwes=[{'metadata': {'doc_id': '352', 'name': 'Cross-Site Request Forgery (CSRF)', 'source': 'sparse', 'original_content': 'The web application does not, or can not, sufficiently verify whether a well-formed, valid, consistent request was intentionally provided by the user who submitted the request.', 'keyphrase_sources': [{'id': 'rootcause:lack of CSRF protection', 'keyphrase': 'lack of CSRF protection', 'type': 'rootcause'}, {'id': 'weakness:XSS', 'keyphrase': 'XSS', 'type': 'weakness'}, {'id': 'weakness:cross-site scripting', 'keyphrase': 'cross-site scripting', 'type': 'weakness'}, {'id': 'product:Microkid Custom Author URL', 'keyphrase': 'Microkid Custom Author URL', 'type': 'product'}, {'id': 'version:n/a through 2.0.1', 'keyphrase': 'n/a through 2.0.1', 'type': 'version'}]}, 'similarity': np.float64(298.58861451919756)}, {'metadata': {'doc_id': '79', 'name': \"Improper Neutralization of Input During Web Page Generation ('Cross-site Scripting')\", 'source': 'sparse', 'original_content': 'The product does not neutralize or incorrectly neutralizes user-controllable input before it is placed in output that is used as a web page that is served to other users.', 'keyphrase_sources': [{'id': 'rootcause:lack of CSRF protection', 'keyphrase': 'lack of CSRF protection', 'type': 'rootcause'}, {'id': 'weakness:XSS', 'keyphrase': 'XSS', 'type': 'weakness'}, {'id': 'weakness:cross-site scripting', 'keyphrase': 'cross-site scripting', 'type': 'weakness'}, {'id': 'product:Microkid Custom Author URL', 'keyphrase': 'Microkid Custom Author URL', 'type': 'product'}, {'id': 'version:n/a through 2.0.1', 'keyphrase': 'n/a through 2.0.1', 'type': 'version'}]}, 'similarity': np.float64(215.06744507242524)}, {'metadata': {'doc_id': '116', 'name': 'Improper Encoding or Escaping of Output', 'source': 'sparse', 'original_content': 'The product prepares a structured message for communication with another component, but encoding or escaping of the data is either missing or done incorrectly. As a result, the intended structure of the message is not preserved.', 'keyphrase_sources': [{'id': 'rootcause:lack of CSRF protection', 'keyphrase': 'lack of CSRF protection', 'type': 'rootcause'}, {'id': 'weakness:XSS', 'keyphrase': 'XSS', 'type': 'weakness'}, {'id': 'weakness:cross-site scripting', 'keyphrase': 'cross-site scripting', 'type': 'weakness'}]}, 'similarity': np.float64(210.7558113990704)}, {'metadata': {'doc_id': '434', 'name': 'Unrestricted Upload of File with Dangerous Type', 'source': 'sparse', 'original_content': 'The product allows the upload or transfer of dangerous file types that are automatically processed within its environment.', 'keyphrase_sources': [{'id': 'rootcause:lack of CSRF protection', 'keyphrase': 'lack of CSRF protection', 'type': 'rootcause'}, {'id': 'weakness:XSS', 'keyphrase': 'XSS', 'type': 'weakness'}, {'id': 'version:n/a through 2.0.1', 'keyphrase': 'n/a through 2.0.1', 'type': 'version'}]}, 'similarity': np.float64(210.1104263912797)}, {'metadata': {'doc_id': '862', 'name': 'Missing Authorization', 'source': 'sparse', 'original_content': 'The product does not perform an authorization check when an actor attempts to access a resource or perform an action.', 'keyphrase_sources': [{'id': 'rootcause:lack of CSRF protection', 'keyphrase': 'lack of CSRF protection', 'type': 'rootcause'}]}, 'similarity': np.float64(197.93495937542056)}, {'metadata': {'doc_id': '80', 'name': 'Improper Neutralization of Script-Related HTML Tags in a Web Page (Basic XSS)', 'source': 'sparse', 'original_content': 'The product receives input from an upstream component, but it does not neutralize or incorrectly neutralizes special characters such as \"<\", \">\", and \"&\" that could be interpreted as web-scripting elements when they are sent to a downstream component that processes web pages.', 'keyphrase_sources': [{'id': 'weakness:cross-site scripting', 'keyphrase': 'cross-site scripting', 'type': 'weakness'}]}, 'similarity': np.float64(195.46999139934667)}, {'metadata': {'doc_id': '918', 'name': 'Server-Side Request Forgery (SSRF)', 'source': 'sparse', 'original_content': 'The web server receives a URL or similar request from an upstream component and retrieves the contents of this URL, but it does not sufficiently ensure that the request is being sent to the expected destination.', 'keyphrase_sources': [{'id': 'weakness:XSS', 'keyphrase': 'XSS', 'type': 'weakness'}, {'id': 'weakness:cross-site scripting', 'keyphrase': 'cross-site scripting', 'type': 'weakness'}, {'id': 'product:Microkid Custom Author URL', 'keyphrase': 'Microkid Custom Author URL', 'type': 'product'}]}, 'similarity': np.float64(158.81113507742512)}, {'metadata': {'doc_id': '22', 'name': \"Improper Limitation of a Pathname to a Restricted Directory ('Path Traversal')\", 'source': 'sparse', 'original_content': 'The product uses external input to construct a pathname that is intended to identify a file or directory that is located underneath a restricted parent directory, but the product does not properly neutralize special elements within the pathname that can cause the pathname to resolve to a location that is outside of the restricted directory.', 'keyphrase_sources': [{'id': 'version:n/a through 2.0.1', 'keyphrase': 'n/a through 2.0.1', 'type': 'version'}]}, 'similarity': np.float64(68.95097265862508)}, {'metadata': {'doc_id': '611', 'name': 'Improper Restriction of XML External Entity Reference', 'source': 'sparse', 'original_content': 'The product processes an XML document that can contain XML entities with URIs that resolve to documents outside of the intended sphere of control, causing the product to embed incorrect documents into its output.', 'keyphrase_sources': [{'id': 'version:n/a through 2.0.1', 'keyphrase': 'n/a through 2.0.1', 'type': 'version'}]}, 'similarity': np.float64(65.60976505850174)}, {'metadata': {'doc_id': '939', 'name': 'Improper Authorization in Handler for Custom URL Scheme', 'source': 'sparse', 'original_content': 'The product uses a handler for a custom URL scheme, but it does not properly restrict which actors can invoke the handler using the scheme.', 'keyphrase_sources': [{'id': 'product:Microkid Custom Author URL', 'keyphrase': 'Microkid Custom Author URL', 'type': 'product'}]}, 'similarity': np.float64(59.01949524650759)}, {'metadata': {'doc_id': '201', 'name': 'Insertion of Sensitive Information Into Sent Data', 'source': 'sparse', 'original_content': 'The code transmits data to another actor, but a portion of the data includes sensitive information that should not be accessible to that actor.', 'keyphrase_sources': [{'id': 'product:Microkid Custom Author URL', 'keyphrase': 'Microkid Custom Author URL', 'type': 'product'}]}, 'similarity': np.float64(58.164185613122314)}], identified_cwes={'analyzer': [], 'critic_additional': []})",
  "retrieval_results": {
    "has_multiple_keyphrases": true,
    "keyphrase_cwe_sets": {
      "rootcause:lack of CSRF protection": {
        "keyphrase": "lack of CSRF protection",
        "type": "rootcause",
        "cwes": [
          {
            "metadata": {
              "doc_id": "352",
              "name": "Cross-Site Request Forgery (CSRF)",
              "source": "sparse",
              "original_content": "The web application does not, or can not, sufficiently verify whether a well-formed, valid, consistent request was intentionally provided by the user who submitted the request.",
              "keyphrase_sources": [
                {
                  "id": "rootcause:lack of CSRF protection",
                  "keyphrase": "lack of CSRF protection",
                  "type": "rootcause"
                },
                {
                  "id": "weakness:XSS",
                  "keyphrase": "XSS",
                  "type": "weakness"
                },
                {
                  "id": "weakness:cross-site scripting",
                  "keyphrase": "cross-site scripting",
                  "type": "weakness"
                },
                {
                  "id": "product:Microkid Custom Author URL",
                  "keyphrase": "Microkid Custom Author URL",
                  "type": "product"
                },
                {
                  "id": "version:n/a through 2.0.1",
                  "keyphrase": "n/a through 2.0.1",
                  "type": "version"
                }
              ]
            },
            "similarity": 298.58861451919756
          },
          {
            "metadata": {
              "doc_id": "79",
              "name": "Improper Neutralization of Input During Web Page Generation ('Cross-site Scripting')",
              "source": "sparse",
              "original_content": "The product does not neutralize or incorrectly neutralizes user-controllable input before it is placed in output that is used as a web page that is served to other users.",
              "keyphrase_sources": [
                {
                  "id": "rootcause:lack of CSRF protection",
                  "keyphrase": "lack of CSRF protection",
                  "type": "rootcause"
                },
                {
                  "id": "weakness:XSS",
                  "keyphrase": "XSS",
                  "type": "weakness"
                },
                {
                  "id": "weakness:cross-site scripting",
                  "keyphrase": "cross-site scripting",
                  "type": "weakness"
                },
                {
                  "id": "product:Microkid Custom Author URL",
                  "keyphrase": "Microkid Custom Author URL",
                  "type": "product"
                },
                {
                  "id": "version:n/a through 2.0.1",
                  "keyphrase": "n/a through 2.0.1",
                  "type": "version"
                }
              ]
            },
            "similarity": 215.06744507242524
          },
          {
            "metadata": {
              "doc_id": "116",
              "name": "Improper Encoding or Escaping of Output",
              "source": "sparse",
              "original_content": "The product prepares a structured message for communication with another component, but encoding or escaping of the data is either missing or done incorrectly. As a result, the intended structure of the message is not preserved.",
              "keyphrase_sources": [
                {
                  "id": "rootcause:lack of CSRF protection",
                  "keyphrase": "lack of CSRF protection",
                  "type": "rootcause"
                },
                {
                  "id": "weakness:XSS",
                  "keyphrase": "XSS",
                  "type": "weakness"
                },
                {
                  "id": "weakness:cross-site scripting",
                  "keyphrase": "cross-site scripting",
                  "type": "weakness"
                }
              ]
            },
            "similarity": 210.7558113990704
          },
          {
            "metadata": {
              "doc_id": "434",
              "name": "Unrestricted Upload of File with Dangerous Type",
              "source": "sparse",
              "original_content": "The product allows the upload or transfer of dangerous file types that are automatically processed within its environment.",
              "keyphrase_sources": [
                {
                  "id": "rootcause:lack of CSRF protection",
                  "keyphrase": "lack of CSRF protection",
                  "type": "rootcause"
                },
                {
                  "id": "weakness:XSS",
                  "keyphrase": "XSS",
                  "type": "weakness"
                },
                {
                  "id": "version:n/a through 2.0.1",
                  "keyphrase": "n/a through 2.0.1",
                  "type": "version"
                }
              ]
            },
            "similarity": 210.1104263912797
          },
          {
            "metadata": {
              "doc_id": "862",
              "name": "Missing Authorization",
              "source": "sparse",
              "original_content": "The product does not perform an authorization check when an actor attempts to access a resource or perform an action.",
              "keyphrase_sources": [
                {
                  "id": "rootcause:lack of CSRF protection",
                  "keyphrase": "lack of CSRF protection",
                  "type": "rootcause"
                }
              ]
            },
            "similarity": 197.93495937542056
          }
        ]
      },
      "weakness:XSS": {
        "keyphrase": "XSS",
        "type": "weakness",
        "cwes": [
          {
            "metadata": {
              "doc_id": "352",
              "name": "Cross-Site Request Forgery (CSRF)",
              "source": "sparse",
              "original_content": "The web application does not, or can not, sufficiently verify whether a well-formed, valid, consistent request was intentionally provided by the user who submitted the request."
            },
            "similarity": 206.44115132720398
          },
          {
            "metadata": {
              "doc_id": "79",
              "name": "Improper Neutralization of Input During Web Page Generation ('Cross-site Scripting')",
              "source": "sparse",
              "original_content": "The product does not neutralize or incorrectly neutralizes user-controllable input before it is placed in output that is used as a web page that is served to other users."
            },
            "similarity": 182.49200673457148
          },
          {
            "metadata": {
              "doc_id": "918",
              "name": "Server-Side Request Forgery (SSRF)",
              "source": "sparse",
              "original_content": "The web server receives a URL or similar request from an upstream component and retrieves the contents of this URL, but it does not sufficiently ensure that the request is being sent to the expected destination.",
              "keyphrase_sources": [
                {
                  "id": "weakness:XSS",
                  "keyphrase": "XSS",
                  "type": "weakness"
                },
                {
                  "id": "weakness:cross-site scripting",
                  "keyphrase": "cross-site scripting",
                  "type": "weakness"
                },
                {
                  "id": "product:Microkid Custom Author URL",
                  "keyphrase": "Microkid Custom Author URL",
                  "type": "product"
                }
              ]
            },
            "similarity": 158.81113507742512
          },
          {
            "metadata": {
              "doc_id": "116",
              "name": "Improper Encoding or Escaping of Output",
              "source": "sparse",
              "original_content": "The product prepares a structured message for communication with another component, but encoding or escaping of the data is either missing or done incorrectly. As a result, the intended structure of the message is not preserved."
            },
            "similarity": 156.14213838674652
          },
          {
            "metadata": {
              "doc_id": "434",
              "name": "Unrestricted Upload of File with Dangerous Type",
              "source": "sparse",
              "original_content": "The product allows the upload or transfer of dangerous file types that are automatically processed within its environment."
            },
            "similarity": 146.29409220834935
          }
        ]
      },
      "weakness:cross-site scripting": {
        "keyphrase": "cross-site scripting",
        "type": "weakness",
        "cwes": [
          {
            "metadata": {
              "doc_id": "352",
              "name": "Cross-Site Request Forgery (CSRF)",
              "source": "sparse",
              "original_content": "The web application does not, or can not, sufficiently verify whether a well-formed, valid, consistent request was intentionally provided by the user who submitted the request."
            },
            "similarity": 274.4642966033399
          },
          {
            "metadata": {
              "doc_id": "79",
              "name": "Improper Neutralization of Input During Web Page Generation ('Cross-site Scripting')",
              "source": "sparse",
              "original_content": "The product does not neutralize or incorrectly neutralizes user-controllable input before it is placed in output that is used as a web page that is served to other users."
            },
            "similarity": 244.4567980914576
          },
          {
            "metadata": {
              "doc_id": "116",
              "name": "Improper Encoding or Escaping of Output",
              "source": "sparse",
              "original_content": "The product prepares a structured message for communication with another component, but encoding or escaping of the data is either missing or done incorrectly. As a result, the intended structure of the message is not preserved."
            },
            "similarity": 203.31236627090698
          },
          {
            "metadata": {
              "doc_id": "918",
              "name": "Server-Side Request Forgery (SSRF)",
              "source": "sparse",
              "original_content": "The web server receives a URL or similar request from an upstream component and retrieves the contents of this URL, but it does not sufficiently ensure that the request is being sent to the expected destination."
            },
            "similarity": 197.7852866273155
          },
          {
            "metadata": {
              "doc_id": "80",
              "name": "Improper Neutralization of Script-Related HTML Tags in a Web Page (Basic XSS)",
              "source": "sparse",
              "original_content": "The product receives input from an upstream component, but it does not neutralize or incorrectly neutralizes special characters such as \"<\", \">\", and \"&\" that could be interpreted as web-scripting elements when they are sent to a downstream component that processes web pages.",
              "keyphrase_sources": [
                {
                  "id": "weakness:cross-site scripting",
                  "keyphrase": "cross-site scripting",
                  "type": "weakness"
                }
              ]
            },
            "similarity": 195.46999139934667
          }
        ]
      },
      "product:Microkid Custom Author URL": {
        "keyphrase": "Microkid Custom Author URL",
        "type": "product",
        "cwes": [
          {
            "metadata": {
              "doc_id": "352",
              "name": "Cross-Site Request Forgery (CSRF)",
              "source": "sparse",
              "original_content": "The web application does not, or can not, sufficiently verify whether a well-formed, valid, consistent request was intentionally provided by the user who submitted the request."
            },
            "similarity": 73.55746641196306
          },
          {
            "metadata": {
              "doc_id": "79",
              "name": "Improper Neutralization of Input During Web Page Generation ('Cross-site Scripting')",
              "source": "sparse",
              "original_content": "The product does not neutralize or incorrectly neutralizes user-controllable input before it is placed in output that is used as a web page that is served to other users."
            },
            "similarity": 63.417408851041756
          },
          {
            "metadata": {
              "doc_id": "939",
              "name": "Improper Authorization in Handler for Custom URL Scheme",
              "source": "sparse",
              "original_content": "The product uses a handler for a custom URL scheme, but it does not properly restrict which actors can invoke the handler using the scheme.",
              "keyphrase_sources": [
                {
                  "id": "product:Microkid Custom Author URL",
                  "keyphrase": "Microkid Custom Author URL",
                  "type": "product"
                }
              ]
            },
            "similarity": 59.01949524650759
          },
          {
            "metadata": {
              "doc_id": "201",
              "name": "Insertion of Sensitive Information Into Sent Data",
              "source": "sparse",
              "original_content": "The code transmits data to another actor, but a portion of the data includes sensitive information that should not be accessible to that actor.",
              "keyphrase_sources": [
                {
                  "id": "product:Microkid Custom Author URL",
                  "keyphrase": "Microkid Custom Author URL",
                  "type": "product"
                }
              ]
            },
            "similarity": 58.164185613122314
          },
          {
            "metadata": {
              "doc_id": "918",
              "name": "Server-Side Request Forgery (SSRF)",
              "source": "sparse",
              "original_content": "The web server receives a URL or similar request from an upstream component and retrieves the contents of this URL, but it does not sufficiently ensure that the request is being sent to the expected destination."
            },
            "similarity": 57.06162008383566
          }
        ]
      },
      "version:n/a through 2.0.1": {
        "keyphrase": "n/a through 2.0.1",
        "type": "version",
        "cwes": [
          {
            "metadata": {
              "doc_id": "352",
              "name": "Cross-Site Request Forgery (CSRF)",
              "source": "sparse",
              "original_content": "The web application does not, or can not, sufficiently verify whether a well-formed, valid, consistent request was intentionally provided by the user who submitted the request."
            },
            "similarity": 79.98902966460749
          },
          {
            "metadata": {
              "doc_id": "79",
              "name": "Improper Neutralization of Input During Web Page Generation ('Cross-site Scripting')",
              "source": "sparse",
              "original_content": "The product does not neutralize or incorrectly neutralizes user-controllable input before it is placed in output that is used as a web page that is served to other users."
            },
            "similarity": 69.39322248780238
          },
          {
            "metadata": {
              "doc_id": "22",
              "name": "Improper Limitation of a Pathname to a Restricted Directory ('Path Traversal')",
              "source": "sparse",
              "original_content": "The product uses external input to construct a pathname that is intended to identify a file or directory that is located underneath a restricted parent directory, but the product does not properly neutralize special elements within the pathname that can cause the pathname to resolve to a location that is outside of the restricted directory.",
              "keyphrase_sources": [
                {
                  "id": "version:n/a through 2.0.1",
                  "keyphrase": "n/a through 2.0.1",
                  "type": "version"
                }
              ]
            },
            "similarity": 68.95097265862508
          },
          {
            "metadata": {
              "doc_id": "611",
              "name": "Improper Restriction of XML External Entity Reference",
              "source": "sparse",
              "original_content": "The product processes an XML document that can contain XML entities with URIs that resolve to documents outside of the intended sphere of control, causing the product to embed incorrect documents into its output.",
              "keyphrase_sources": [
                {
                  "id": "version:n/a through 2.0.1",
                  "keyphrase": "n/a through 2.0.1",
                  "type": "version"
                }
              ]
            },
            "similarity": 65.60976505850174
          },
          {
            "metadata": {
              "doc_id": "434",
              "name": "Unrestricted Upload of File with Dangerous Type",
              "source": "sparse",
              "original_content": "The product allows the upload or transfer of dangerous file types that are automatically processed within its environment."
            },
            "similarity": 65.44303044539487
          }
        ]
      }
    },
    "keyphrase_mapping": {
      "352": [
        {
          "id": "rootcause:lack of CSRF protection",
          "keyphrase": "lack of CSRF protection",
          "type": "rootcause"
        },
        {
          "id": "weakness:XSS",
          "keyphrase": "XSS",
          "type": "weakness"
        },
        {
          "id": "weakness:cross-site scripting",
          "keyphrase": "cross-site scripting",
          "type": "weakness"
        },
        {
          "id": "product:Microkid Custom Author URL",
          "keyphrase": "Microkid Custom Author URL",
          "type": "product"
        },
        {
          "id": "version:n/a through 2.0.1",
          "keyphrase": "n/a through 2.0.1",
          "type": "version"
        }
      ],
      "79": [
        {
          "id": "rootcause:lack of CSRF protection",
          "keyphrase": "lack of CSRF protection",
          "type": "rootcause"
        },
        {
          "id": "weakness:XSS",
          "keyphrase": "XSS",
          "type": "weakness"
        },
        {
          "id": "weakness:cross-site scripting",
          "keyphrase": "cross-site scripting",
          "type": "weakness"
        },
        {
          "id": "product:Microkid Custom Author URL",
          "keyphrase": "Microkid Custom Author URL",
          "type": "product"
        },
        {
          "id": "version:n/a through 2.0.1",
          "keyphrase": "n/a through 2.0.1",
          "type": "version"
        }
      ],
      "116": [
        {
          "id": "rootcause:lack of CSRF protection",
          "keyphrase": "lack of CSRF protection",
          "type": "rootcause"
        },
        {
          "id": "weakness:XSS",
          "keyphrase": "XSS",
          "type": "weakness"
        },
        {
          "id": "weakness:cross-site scripting",
          "keyphrase": "cross-site scripting",
          "type": "weakness"
        }
      ],
      "434": [
        {
          "id": "rootcause:lack of CSRF protection",
          "keyphrase": "lack of CSRF protection",
          "type": "rootcause"
        },
        {
          "id": "weakness:XSS",
          "keyphrase": "XSS",
          "type": "weakness"
        },
        {
          "id": "version:n/a through 2.0.1",
          "keyphrase": "n/a through 2.0.1",
          "type": "version"
        }
      ],
      "862": [
        {
          "id": "rootcause:lack of CSRF protection",
          "keyphrase": "lack of CSRF protection",
          "type": "rootcause"
        }
      ],
      "918": [
        {
          "id": "weakness:XSS",
          "keyphrase": "XSS",
          "type": "weakness"
        },
        {
          "id": "weakness:cross-site scripting",
          "keyphrase": "cross-site scripting",
          "type": "weakness"
        },
        {
          "id": "product:Microkid Custom Author URL",
          "keyphrase": "Microkid Custom Author URL",
          "type": "product"
        }
      ],
      "80": [
        {
          "id": "weakness:cross-site scripting",
          "keyphrase": "cross-site scripting",
          "type": "weakness"
        }
      ],
      "939": [
        {
          "id": "product:Microkid Custom Author URL",
          "keyphrase": "Microkid Custom Author URL",
          "type": "product"
        }
      ],
      "201": [
        {
          "id": "product:Microkid Custom Author URL",
          "keyphrase": "Microkid Custom Author URL",
          "type": "product"
        }
      ],
      "22": [
        {
          "id": "version:n/a through 2.0.1",
          "keyphrase": "n/a through 2.0.1",
          "type": "version"
        }
      ],
      "611": [
        {
          "id": "version:n/a through 2.0.1",
          "keyphrase": "n/a through 2.0.1",
          "type": "version"
        }
      ]
    },
    "relevant_cwes": [
      {
        "metadata": {
          "doc_id": "352",
          "name": "Cross-Site Request Forgery (CSRF)",
          "source": "sparse",
          "original_content": "The web application does not, or can not, sufficiently verify whether a well-formed, valid, consistent request was intentionally provided by the user who submitted the request.",
          "keyphrase_sources": [
            {
              "id": "rootcause:lack of CSRF protection",
              "keyphrase": "lack of CSRF protection",
              "type": "rootcause"
            },
            {
              "id": "weakness:XSS",
              "keyphrase": "XSS",
              "type": "weakness"
            },
            {
              "id": "weakness:cross-site scripting",
              "keyphrase": "cross-site scripting",
              "type": "weakness"
            },
            {
              "id": "product:Microkid Custom Author URL",
              "keyphrase": "Microkid Custom Author URL",
              "type": "product"
            },
            {
              "id": "version:n/a through 2.0.1",
              "keyphrase": "n/a through 2.0.1",
              "type": "version"
            }
          ]
        },
        "similarity": 298.58861451919756
      },
      {
        "metadata": {
          "doc_id": "79",
          "name": "Improper Neutralization of Input During Web Page Generation ('Cross-site Scripting')",
          "source": "sparse",
          "original_content": "The product does not neutralize or incorrectly neutralizes user-controllable input before it is placed in output that is used as a web page that is served to other users.",
          "keyphrase_sources": [
            {
              "id": "rootcause:lack of CSRF protection",
              "keyphrase": "lack of CSRF protection",
              "type": "rootcause"
            },
            {
              "id": "weakness:XSS",
              "keyphrase": "XSS",
              "type": "weakness"
            },
            {
              "id": "weakness:cross-site scripting",
              "keyphrase": "cross-site scripting",
              "type": "weakness"
            },
            {
              "id": "product:Microkid Custom Author URL",
              "keyphrase": "Microkid Custom Author URL",
              "type": "product"
            },
            {
              "id": "version:n/a through 2.0.1",
              "keyphrase": "n/a through 2.0.1",
              "type": "version"
            }
          ]
        },
        "similarity": 215.06744507242524
      },
      {
        "metadata": {
          "doc_id": "116",
          "name": "Improper Encoding or Escaping of Output",
          "source": "sparse",
          "original_content": "The product prepares a structured message for communication with another component, but encoding or escaping of the data is either missing or done incorrectly. As a result, the intended structure of the message is not preserved.",
          "keyphrase_sources": [
            {
              "id": "rootcause:lack of CSRF protection",
              "keyphrase": "lack of CSRF protection",
              "type": "rootcause"
            },
            {
              "id": "weakness:XSS",
              "keyphrase": "XSS",
              "type": "weakness"
            },
            {
              "id": "weakness:cross-site scripting",
              "keyphrase": "cross-site scripting",
              "type": "weakness"
            }
          ]
        },
        "similarity": 210.7558113990704
      },
      {
        "metadata": {
          "doc_id": "434",
          "name": "Unrestricted Upload of File with Dangerous Type",
          "source": "sparse",
          "original_content": "The product allows the upload or transfer of dangerous file types that are automatically processed within its environment.",
          "keyphrase_sources": [
            {
              "id": "rootcause:lack of CSRF protection",
              "keyphrase": "lack of CSRF protection",
              "type": "rootcause"
            },
            {
              "id": "weakness:XSS",
              "keyphrase": "XSS",
              "type": "weakness"
            },
            {
              "id": "version:n/a through 2.0.1",
              "keyphrase": "n/a through 2.0.1",
              "type": "version"
            }
          ]
        },
        "similarity": 210.1104263912797
      },
      {
        "metadata": {
          "doc_id": "862",
          "name": "Missing Authorization",
          "source": "sparse",
          "original_content": "The product does not perform an authorization check when an actor attempts to access a resource or perform an action.",
          "keyphrase_sources": [
            {
              "id": "rootcause:lack of CSRF protection",
              "keyphrase": "lack of CSRF protection",
              "type": "rootcause"
            }
          ]
        },
        "similarity": 197.93495937542056
      },
      {
        "metadata": {
          "doc_id": "80",
          "name": "Improper Neutralization of Script-Related HTML Tags in a Web Page (Basic XSS)",
          "source": "sparse",
          "original_content": "The product receives input from an upstream component, but it does not neutralize or incorrectly neutralizes special characters such as \"<\", \">\", and \"&\" that could be interpreted as web-scripting elements when they are sent to a downstream component that processes web pages.",
          "keyphrase_sources": [
            {
              "id": "weakness:cross-site scripting",
              "keyphrase": "cross-site scripting",
              "type": "weakness"
            }
          ]
        },
        "similarity": 195.46999139934667
      },
      {
        "metadata": {
          "doc_id": "918",
          "name": "Server-Side Request Forgery (SSRF)",
          "source": "sparse",
          "original_content": "The web server receives a URL or similar request from an upstream component and retrieves the contents of this URL, but it does not sufficiently ensure that the request is being sent to the expected destination.",
          "keyphrase_sources": [
            {
              "id": "weakness:XSS",
              "keyphrase": "XSS",
              "type": "weakness"
            },
            {
              "id": "weakness:cross-site scripting",
              "keyphrase": "cross-site scripting",
              "type": "weakness"
            },
            {
              "id": "product:Microkid Custom Author URL",
              "keyphrase": "Microkid Custom Author URL",
              "type": "product"
            }
          ]
        },
        "similarity": 158.81113507742512
      },
      {
        "metadata": {
          "doc_id": "22",
          "name": "Improper Limitation of a Pathname to a Restricted Directory ('Path Traversal')",
          "source": "sparse",
          "original_content": "The product uses external input to construct a pathname that is intended to identify a file or directory that is located underneath a restricted parent directory, but the product does not properly neutralize special elements within the pathname that can cause the pathname to resolve to a location that is outside of the restricted directory.",
          "keyphrase_sources": [
            {
              "id": "version:n/a through 2.0.1",
              "keyphrase": "n/a through 2.0.1",
              "type": "version"
            }
          ]
        },
        "similarity": 68.95097265862508
      },
      {
        "metadata": {
          "doc_id": "611",
          "name": "Improper Restriction of XML External Entity Reference",
          "source": "sparse",
          "original_content": "The product processes an XML document that can contain XML entities with URIs that resolve to documents outside of the intended sphere of control, causing the product to embed incorrect documents into its output.",
          "keyphrase_sources": [
            {
              "id": "version:n/a through 2.0.1",
              "keyphrase": "n/a through 2.0.1",
              "type": "version"
            }
          ]
        },
        "similarity": 65.60976505850174
      },
      {
        "metadata": {
          "doc_id": "939",
          "name": "Improper Authorization in Handler for Custom URL Scheme",
          "source": "sparse",
          "original_content": "The product uses a handler for a custom URL scheme, but it does not properly restrict which actors can invoke the handler using the scheme.",
          "keyphrase_sources": [
            {
              "id": "product:Microkid Custom Author URL",
              "keyphrase": "Microkid Custom Author URL",
              "type": "product"
            }
          ]
        },
        "similarity": 59.01949524650759
      },
      {
        "metadata": {
          "doc_id": "201",
          "name": "Insertion of Sensitive Information Into Sent Data",
          "source": "sparse",
          "original_content": "The code transmits data to another actor, but a portion of the data includes sensitive information that should not be accessible to that actor.",
          "keyphrase_sources": [
            {
              "id": "product:Microkid Custom Author URL",
              "keyphrase": "Microkid Custom Author URL",
              "type": "product"
            }
          ]
        },
        "similarity": 58.164185613122314
      }
    ],
    "enhanced_query": "# Vulnerability Description\n\n    Cross-Site Request Forgery (CSRF) vulnerability in Microkid Custom Author URL allows Stored **XSS**.This issue affects Custom Author URL from n/a through 2.0.1.\n\n    # Keyphrase-Specific CWE Analysis\n    This vulnerability contains multiple keyphrases that may map to different CWEs. \n    Please analyze each keyphrase separately and determine the most appropriate CWE(s) for each.\n\n    ## ROOTCAUSE: 'lack of CSRF protection'\n\nRelevant CWEs for this ROOTCAUSE:\n\n### 1. CWE-352: Cross-Site Request Forgery (CSRF) (Score: 298.59)\n\nThe web application does not, or can not, sufficiently verify whether a well-formed, valid, consistent request was intentionally provided by the user who submitted the request....\n\n### 2. CWE-79: Improper Neutralization of Input During Web Page Generation ('Cross-site Scripting') (Score: 215.07)\n\nThe product does not neutralize or incorrectly neutralizes user-controllable input before it is placed in output that is used as a web page that is served to other users....\n\n### 3. CWE-116: Improper Encoding or Escaping of Output (Score: 210.76)\n\nThe product prepares a structured message for communication with another component, but encoding or escaping of the data is either missing or done incorrectly. As a result, the intended structure of the message is not preserved....\n\n### 4. CWE-434: Unrestricted Upload of File with Dangerous Type (Score: 210.11)\n\nThe product allows the upload or transfer of dangerous file types that are automatically processed within its environment....\n\n### 5. CWE-862: Missing Authorization (Score: 197.93)\n\nThe product does not perform an authorization check when an actor attempts to access a resource or perform an action....\n\n## WEAKNESS: 'XSS'\n\nRelevant CWEs for this WEAKNESS:\n\n### 1. CWE-352: Cross-Site Request Forgery (CSRF) (Score: 298.59)\n\nThe web application does not, or can not, sufficiently verify whether a well-formed, valid, consistent request was intentionally provided by the user who submitted the request....\n\n### 2. CWE-79: Improper Neutralization of Input During Web Page Generation ('Cross-site Scripting') (Score: 215.07)\n\nThe product does not neutralize or incorrectly neutralizes user-controllable input before it is placed in output that is used as a web page that is served to other users....\n\n### 3. CWE-116: Improper Encoding or Escaping of Output (Score: 210.76)\n\nThe product prepares a structured message for communication with another component, but encoding or escaping of the data is either missing or done incorrectly. As a result, the intended structure of the message is not preserved....\n\n### 4. CWE-434: Unrestricted Upload of File with Dangerous Type (Score: 210.11)\n\nThe product allows the upload or transfer of dangerous file types that are automatically processed within its environment....\n\n### 5. CWE-918: Server-Side Request Forgery (SSRF) (Score: 158.81)\n\nThe web server receives a URL or similar request from an upstream component and retrieves the contents of this URL, but it does not sufficiently ensure that the request is being sent to the expected destination....\n\n## WEAKNESS: 'cross-site scripting'\n\nRelevant CWEs for this WEAKNESS:\n\n### 1. CWE-352: Cross-Site Request Forgery (CSRF) (Score: 298.59)\n\nThe web application does not, or can not, sufficiently verify whether a well-formed, valid, consistent request was intentionally provided by the user who submitted the request....\n\n### 2. CWE-79: Improper Neutralization of Input During Web Page Generation ('Cross-site Scripting') (Score: 215.07)\n\nThe product does not neutralize or incorrectly neutralizes user-controllable input before it is placed in output that is used as a web page that is served to other users....\n\n### 3. CWE-116: Improper Encoding or Escaping of Output (Score: 210.76)\n\nThe product prepares a structured message for communication with another component, but encoding or escaping of the data is either missing or done incorrectly. As a result, the intended structure of the message is not preserved....\n\n### 4. CWE-80: Improper Neutralization of Script-Related HTML Tags in a Web Page (Basic XSS) (Score: 195.47)\n\nThe product receives input from an upstream component, but it does not neutralize or incorrectly neutralizes special characters such as \"<\", \">\", and \"&\" that could be interpreted as web-scripting elements when they are sent to a downstream component that processes web pages....\n\n### 5. CWE-918: Server-Side Request Forgery (SSRF) (Score: 158.81)\n\nThe web server receives a URL or similar request from an upstream component and retrieves the contents of this URL, but it does not sufficiently ensure that the request is being sent to the expected destination....\n\n## PRODUCT: 'Microkid Custom Author URL'\n\nRelevant CWEs for this PRODUCT:\n\n### 1. CWE-352: Cross-Site Request Forgery (CSRF) (Score: 298.59)\n\nThe web application does not, or can not, sufficiently verify whether a well-formed, valid, consistent request was intentionally provided by the user who submitted the request....\n\n### 2. CWE-79: Improper Neutralization of Input During Web Page Generation ('Cross-site Scripting') (Score: 215.07)\n\nThe product does not neutralize or incorrectly neutralizes user-controllable input before it is placed in output that is used as a web page that is served to other users....\n\n### 3. CWE-918: Server-Side Request Forgery (SSRF) (Score: 158.81)\n\nThe web server receives a URL or similar request from an upstream component and retrieves the contents of this URL, but it does not sufficiently ensure that the request is being sent to the expected destination....\n\n### 4. CWE-939: Improper Authorization in Handler for Custom URL Scheme (Score: 59.02)\n\nThe product uses a handler for a custom URL scheme, but it does not properly restrict which actors can invoke the handler using the scheme....\n\n### 5. CWE-201: Insertion of Sensitive Information Into Sent Data (Score: 58.16)\n\nThe code transmits data to another actor, but a portion of the data includes sensitive information that should not be accessible to that actor....\n\n## VERSION: 'n/a through 2.0.1'\n\nRelevant CWEs for this VERSION:\n\n### 1. CWE-352: Cross-Site Request Forgery (CSRF) (Score: 298.59)\n\nThe web application does not, or can not, sufficiently verify whether a well-formed, valid, consistent request was intentionally provided by the user who submitted the request....\n\n### 2. CWE-79: Improper Neutralization of Input During Web Page Generation ('Cross-site Scripting') (Score: 215.07)\n\nThe product does not neutralize or incorrectly neutralizes user-controllable input before it is placed in output that is used as a web page that is served to other users....\n\n### 3. CWE-434: Unrestricted Upload of File with Dangerous Type (Score: 210.11)\n\nThe product allows the upload or transfer of dangerous file types that are automatically processed within its environment....\n\n### 4. CWE-22: Improper Limitation of a Pathname to a Restricted Directory ('Path Traversal') (Score: 68.95)\n\nThe product uses external input to construct a pathname that is intended to identify a file or directory that is located underneath a restricted parent directory, but the product does not properly neutralize special elements within the pathname that can cause the pathname to resolve to a location th...\n\n### 5. CWE-611: Improper Restriction of XML External Entity Reference (Score: 65.61)\n\nThe product processes an XML document that can contain XML entities with URIs that resolve to documents outside of the intended sphere of control, causing the product to embed incorrect documents into its output....\n\n\n    # Analysis Instructions\n    1. For each keyphrase, identify the most appropriate CWE(s) that represent the weakness.\n    2. Consider how the different keyphrases might relate to each other in the vulnerability chain.\n    3. Provide a final determination of primary CWE(s) and any secondary CWEs.\n    4. Format your response using the standard analysis template.\n\n    Please analyze how these different weaknesses interact and provide a comprehensive CWE classification.\n    "
  },
  "retrieval_time": 0.9469375610351562
}