{
  "vulnerability_info": "VulnerabilityInfo(cve_id='CVE-2025-37792', description='In the Linux kernel, the following vulnerability has been resolved Bluetooth btrtl Prevent potential **NULL dereference** The btrtl_initialize() function checks that rtl_load_file() either had an error or it loaded a zero length file. However, if it loaded a zero length file then the error code is not set correctly. It results in an **error pointer vs NULL bug**, followed by a **NULL pointer dereference**. This was detected by Smatch drivers/bluetooth/btrtl.c592 btrtl_initialize() warn passing zero to ERR_PTR', key_phrases={'rootcause': ['error pointer vs NULL bug', 'NULL dereference'], 'weakness': 'NULL pointer dereference', 'impact': '', 'vector': '', 'attacker': '', 'product': 'Linux kernel', 'version': '', 'component': 'Bluetooth btrtl'}, reference_content=None, similar_info={'cwe_distribution': {}, 'cwe_consensus': '', 'similarity_stats': {'thresholds': [], 'total_samples_by_threshold': {}, 'top_cwes_by_threshold': {}}}, similarity_summary=SimilarityInsight(consensus_cwe='', top_cwes=[], confidence_levels={}, total_samples=0), analysis='', analysis_with_relationships='', criticism='', resolution='', relevant_cwes=[{'metadata': {'doc_id': '476', 'name': 'NULL Pointer Dereference', 'source': 'sparse', 'original_content': 'The product dereferences a pointer that it expects to be valid but is NULL.', 'keyphrase_sources': [{'id': 'rootcause:error pointer vs NULL bug', 'keyphrase': 'error pointer vs NULL bug', 'type': 'rootcause'}, {'id': 'rootcause:NULL dereference', 'keyphrase': 'NULL dereference', 'type': 'rootcause'}, {'id': 'weakness:NULL pointer dereference', 'keyphrase': 'NULL pointer dereference', 'type': 'weakness'}, {'id': 'product:Linux kernel', 'keyphrase': 'Linux kernel', 'type': 'product'}, {'id': 'component:Bluetooth btrtl', 'keyphrase': 'Bluetooth btrtl', 'type': 'component'}]}, 'similarity': np.float64(530.9990378372833)}, {'metadata': {'doc_id': '194', 'name': 'Unexpected Sign Extension', 'source': 'sparse', 'original_content': 'The product performs an operation on a number that causes it to be sign extended when it is transformed into a larger data type. When the original number is negative, this can produce unexpected values that lead to resultant weaknesses.', 'keyphrase_sources': [{'id': 'rootcause:error pointer vs NULL bug', 'keyphrase': 'error pointer vs NULL bug', 'type': 'rootcause'}, {'id': 'component:Bluetooth btrtl', 'keyphrase': 'Bluetooth btrtl', 'type': 'component'}]}, 'similarity': np.float64(477.29314829086815)}, {'metadata': {'doc_id': '833', 'name': 'Deadlock', 'source': 'sparse', 'original_content': 'The product contains multiple threads or executable segments that are waiting for each other to release a necessary lock, resulting in deadlock.', 'keyphrase_sources': [{'id': 'rootcause:error pointer vs NULL bug', 'keyphrase': 'error pointer vs NULL bug', 'type': 'rootcause'}, {'id': 'rootcause:NULL dereference', 'keyphrase': 'NULL dereference', 'type': 'rootcause'}, {'id': 'product:Linux kernel', 'keyphrase': 'Linux kernel', 'type': 'product'}, {'id': 'component:Bluetooth btrtl', 'keyphrase': 'Bluetooth btrtl', 'type': 'component'}]}, 'similarity': np.float64(467.31733243101417)}, {'metadata': {'doc_id': '822', 'name': 'Untrusted Pointer Dereference', 'source': 'sparse', 'original_content': 'The product obtains a value from an untrusted source, converts this value to a pointer, and dereferences the resulting pointer.', 'keyphrase_sources': [{'id': 'rootcause:error pointer vs NULL bug', 'keyphrase': 'error pointer vs NULL bug', 'type': 'rootcause'}, {'id': 'rootcause:NULL dereference', 'keyphrase': 'NULL dereference', 'type': 'rootcause'}, {'id': 'weakness:NULL pointer dereference', 'keyphrase': 'NULL pointer dereference', 'type': 'weakness'}, {'id': 'product:Linux kernel', 'keyphrase': 'Linux kernel', 'type': 'product'}, {'id': 'component:Bluetooth btrtl', 'keyphrase': 'Bluetooth btrtl', 'type': 'component'}]}, 'similarity': np.float64(466.0221074372894)}, {'metadata': {'doc_id': '665', 'name': 'Improper Initialization', 'source': 'sparse', 'original_content': 'The product does not initialize or incorrectly initializes a resource, which might leave the resource in an unexpected state when it is accessed or used.', 'keyphrase_sources': [{'id': 'rootcause:error pointer vs NULL bug', 'keyphrase': 'error pointer vs NULL bug', 'type': 'rootcause'}, {'id': 'rootcause:NULL dereference', 'keyphrase': 'NULL dereference', 'type': 'rootcause'}, {'id': 'weakness:NULL pointer dereference', 'keyphrase': 'NULL pointer dereference', 'type': 'weakness'}, {'id': 'component:Bluetooth btrtl', 'keyphrase': 'Bluetooth btrtl', 'type': 'component'}]}, 'similarity': np.float64(452.52701148110987)}, {'metadata': {'doc_id': '252', 'name': 'Unchecked Return Value', 'source': 'sparse', 'original_content': 'The product does not check the return value from a method or function, which can prevent it from detecting unexpected states and conditions.', 'keyphrase_sources': [{'id': 'rootcause:NULL dereference', 'keyphrase': 'NULL dereference', 'type': 'rootcause'}, {'id': 'weakness:NULL pointer dereference', 'keyphrase': 'NULL pointer dereference', 'type': 'weakness'}]}, 'similarity': np.float64(438.9526218771615)}, {'metadata': {'doc_id': '690', 'name': 'Unchecked Return Value to NULL Pointer Dereference', 'source': 'sparse', 'original_content': 'The product does not check for an error after calling a function that can return with a NULL pointer if the function fails, which leads to a resultant NULL pointer dereference.', 'keyphrase_sources': [{'id': 'weakness:NULL pointer dereference', 'keyphrase': 'NULL pointer dereference', 'type': 'weakness'}]}, 'similarity': np.float64(430.18503554343795)}, {'metadata': {'doc_id': '909', 'name': 'Missing Initialization of Resource', 'source': 'sparse', 'original_content': 'The product does not initialize a critical resource.', 'keyphrase_sources': [{'id': 'product:Linux kernel', 'keyphrase': 'Linux kernel', 'type': 'product'}]}, 'similarity': np.float64(143.12789569892274)}, {'metadata': {'doc_id': '911', 'name': 'Improper Update of Reference Count', 'source': 'sparse', 'original_content': 'The product uses a reference count to manage a resource, but it does not update or incorrectly updates the reference count.', 'keyphrase_sources': [{'id': 'product:Linux kernel', 'keyphrase': 'Linux kernel', 'type': 'product'}]}, 'similarity': np.float64(139.7991384776663)}], identified_cwes={'analyzer': [], 'critic_additional': []})",
  "retrieval_results": {
    "has_multiple_keyphrases": true,
    "keyphrase_cwe_sets": {
      "rootcause:error pointer vs NULL bug": {
        "keyphrase": "error pointer vs NULL bug",
        "type": "rootcause",
        "cwes": [
          {
            "metadata": {
              "doc_id": "476",
              "name": "NULL Pointer Dereference",
              "source": "sparse",
              "original_content": "The product dereferences a pointer that it expects to be valid but is NULL.",
              "keyphrase_sources": [
                {
                  "id": "rootcause:error pointer vs NULL bug",
                  "keyphrase": "error pointer vs NULL bug",
                  "type": "rootcause"
                },
                {
                  "id": "rootcause:NULL dereference",
                  "keyphrase": "NULL dereference",
                  "type": "rootcause"
                },
                {
                  "id": "weakness:NULL pointer dereference",
                  "keyphrase": "NULL pointer dereference",
                  "type": "weakness"
                },
                {
                  "id": "product:Linux kernel",
                  "keyphrase": "Linux kernel",
                  "type": "product"
                },
                {
                  "id": "component:Bluetooth btrtl",
                  "keyphrase": "Bluetooth btrtl",
                  "type": "component"
                }
              ]
            },
            "similarity": 530.9990378372833
          },
          {
            "metadata": {
              "doc_id": "194",
              "name": "Unexpected Sign Extension",
              "source": "sparse",
              "original_content": "The product performs an operation on a number that causes it to be sign extended when it is transformed into a larger data type. When the original number is negative, this can produce unexpected values that lead to resultant weaknesses.",
              "keyphrase_sources": [
                {
                  "id": "rootcause:error pointer vs NULL bug",
                  "keyphrase": "error pointer vs NULL bug",
                  "type": "rootcause"
                },
                {
                  "id": "component:Bluetooth btrtl",
                  "keyphrase": "Bluetooth btrtl",
                  "type": "component"
                }
              ]
            },
            "similarity": 477.29314829086815
          },
          {
            "metadata": {
              "doc_id": "833",
              "name": "Deadlock",
              "source": "sparse",
              "original_content": "The product contains multiple threads or executable segments that are waiting for each other to release a necessary lock, resulting in deadlock.",
              "keyphrase_sources": [
                {
                  "id": "rootcause:error pointer vs NULL bug",
                  "keyphrase": "error pointer vs NULL bug",
                  "type": "rootcause"
                },
                {
                  "id": "rootcause:NULL dereference",
                  "keyphrase": "NULL dereference",
                  "type": "rootcause"
                },
                {
                  "id": "product:Linux kernel",
                  "keyphrase": "Linux kernel",
                  "type": "product"
                },
                {
                  "id": "component:Bluetooth btrtl",
                  "keyphrase": "Bluetooth btrtl",
                  "type": "component"
                }
              ]
            },
            "similarity": 467.31733243101417
          },
          {
            "metadata": {
              "doc_id": "822",
              "name": "Untrusted Pointer Dereference",
              "source": "sparse",
              "original_content": "The product obtains a value from an untrusted source, converts this value to a pointer, and dereferences the resulting pointer.",
              "keyphrase_sources": [
                {
                  "id": "rootcause:error pointer vs NULL bug",
                  "keyphrase": "error pointer vs NULL bug",
                  "type": "rootcause"
                },
                {
                  "id": "rootcause:NULL dereference",
                  "keyphrase": "NULL dereference",
                  "type": "rootcause"
                },
                {
                  "id": "weakness:NULL pointer dereference",
                  "keyphrase": "NULL pointer dereference",
                  "type": "weakness"
                },
                {
                  "id": "product:Linux kernel",
                  "keyphrase": "Linux kernel",
                  "type": "product"
                },
                {
                  "id": "component:Bluetooth btrtl",
                  "keyphrase": "Bluetooth btrtl",
                  "type": "component"
                }
              ]
            },
            "similarity": 466.0221074372894
          },
          {
            "metadata": {
              "doc_id": "665",
              "name": "Improper Initialization",
              "source": "sparse",
              "original_content": "The product does not initialize or incorrectly initializes a resource, which might leave the resource in an unexpected state when it is accessed or used.",
              "keyphrase_sources": [
                {
                  "id": "rootcause:error pointer vs NULL bug",
                  "keyphrase": "error pointer vs NULL bug",
                  "type": "rootcause"
                },
                {
                  "id": "rootcause:NULL dereference",
                  "keyphrase": "NULL dereference",
                  "type": "rootcause"
                },
                {
                  "id": "weakness:NULL pointer dereference",
                  "keyphrase": "NULL pointer dereference",
                  "type": "weakness"
                },
                {
                  "id": "component:Bluetooth btrtl",
                  "keyphrase": "Bluetooth btrtl",
                  "type": "component"
                }
              ]
            },
            "similarity": 452.52701148110987
          }
        ]
      },
      "rootcause:NULL dereference": {
        "keyphrase": "NULL dereference",
        "type": "rootcause",
        "cwes": [
          {
            "metadata": {
              "doc_id": "476",
              "name": "NULL Pointer Dereference",
              "source": "sparse",
              "original_content": "The product dereferences a pointer that it expects to be valid but is NULL."
            },
            "similarity": 537.8620000928925
          },
          {
            "metadata": {
              "doc_id": "822",
              "name": "Untrusted Pointer Dereference",
              "source": "sparse",
              "original_content": "The product obtains a value from an untrusted source, converts this value to a pointer, and dereferences the resulting pointer."
            },
            "similarity": 455.30082597109356
          },
          {
            "metadata": {
              "doc_id": "665",
              "name": "Improper Initialization",
              "source": "sparse",
              "original_content": "The product does not initialize or incorrectly initializes a resource, which might leave the resource in an unexpected state when it is accessed or used."
            },
            "similarity": 454.8495238179647
          },
          {
            "metadata": {
              "doc_id": "252",
              "name": "Unchecked Return Value",
              "source": "sparse",
              "original_content": "The product does not check the return value from a method or function, which can prevent it from detecting unexpected states and conditions.",
              "keyphrase_sources": [
                {
                  "id": "rootcause:NULL dereference",
                  "keyphrase": "NULL dereference",
                  "type": "rootcause"
                },
                {
                  "id": "weakness:NULL pointer dereference",
                  "keyphrase": "NULL pointer dereference",
                  "type": "weakness"
                }
              ]
            },
            "similarity": 438.9526218771615
          },
          {
            "metadata": {
              "doc_id": "833",
              "name": "Deadlock",
              "source": "sparse",
              "original_content": "The product contains multiple threads or executable segments that are waiting for each other to release a necessary lock, resulting in deadlock."
            },
            "similarity": 435.59782611395315
          }
        ]
      },
      "weakness:NULL pointer dereference": {
        "keyphrase": "NULL pointer dereference",
        "type": "weakness",
        "cwes": [
          {
            "metadata": {
              "doc_id": "476",
              "name": "NULL Pointer Dereference",
              "source": "sparse",
              "original_content": "The product dereferences a pointer that it expects to be valid but is NULL."
            },
            "similarity": 535.7901678235547
          },
          {
            "metadata": {
              "doc_id": "822",
              "name": "Untrusted Pointer Dereference",
              "source": "sparse",
              "original_content": "The product obtains a value from an untrusted source, converts this value to a pointer, and dereferences the resulting pointer."
            },
            "similarity": 458.8528916496472
          },
          {
            "metadata": {
              "doc_id": "665",
              "name": "Improper Initialization",
              "source": "sparse",
              "original_content": "The product does not initialize or incorrectly initializes a resource, which might leave the resource in an unexpected state when it is accessed or used."
            },
            "similarity": 448.8844712859642
          },
          {
            "metadata": {
              "doc_id": "252",
              "name": "Unchecked Return Value",
              "source": "sparse",
              "original_content": "The product does not check the return value from a method or function, which can prevent it from detecting unexpected states and conditions."
            },
            "similarity": 438.12781000323145
          },
          {
            "metadata": {
              "doc_id": "690",
              "name": "Unchecked Return Value to NULL Pointer Dereference",
              "source": "sparse",
              "original_content": "The product does not check for an error after calling a function that can return with a NULL pointer if the function fails, which leads to a resultant NULL pointer dereference.",
              "keyphrase_sources": [
                {
                  "id": "weakness:NULL pointer dereference",
                  "keyphrase": "NULL pointer dereference",
                  "type": "weakness"
                }
              ]
            },
            "similarity": 430.18503554343795
          }
        ]
      },
      "product:Linux kernel": {
        "keyphrase": "Linux kernel",
        "type": "product",
        "cwes": [
          {
            "metadata": {
              "doc_id": "476",
              "name": "NULL Pointer Dereference",
              "source": "sparse",
              "original_content": "The product dereferences a pointer that it expects to be valid but is NULL."
            },
            "similarity": 161.73406974967642
          },
          {
            "metadata": {
              "doc_id": "833",
              "name": "Deadlock",
              "source": "sparse",
              "original_content": "The product contains multiple threads or executable segments that are waiting for each other to release a necessary lock, resulting in deadlock."
            },
            "similarity": 146.82965934149107
          },
          {
            "metadata": {
              "doc_id": "822",
              "name": "Untrusted Pointer Dereference",
              "source": "sparse",
              "original_content": "The product obtains a value from an untrusted source, converts this value to a pointer, and dereferences the resulting pointer."
            },
            "similarity": 145.53363398726205
          },
          {
            "metadata": {
              "doc_id": "909",
              "name": "Missing Initialization of Resource",
              "source": "sparse",
              "original_content": "The product does not initialize a critical resource.",
              "keyphrase_sources": [
                {
                  "id": "product:Linux kernel",
                  "keyphrase": "Linux kernel",
                  "type": "product"
                }
              ]
            },
            "similarity": 143.12789569892274
          },
          {
            "metadata": {
              "doc_id": "911",
              "name": "Improper Update of Reference Count",
              "source": "sparse",
              "original_content": "The product uses a reference count to manage a resource, but it does not update or incorrectly updates the reference count.",
              "keyphrase_sources": [
                {
                  "id": "product:Linux kernel",
                  "keyphrase": "Linux kernel",
                  "type": "product"
                }
              ]
            },
            "similarity": 139.7991384776663
          }
        ]
      },
      "component:Bluetooth btrtl": {
        "keyphrase": "Bluetooth btrtl",
        "type": "component",
        "cwes": [
          {
            "metadata": {
              "doc_id": "476",
              "name": "NULL Pointer Dereference",
              "source": "sparse",
              "original_content": "The product dereferences a pointer that it expects to be valid but is NULL."
            },
            "similarity": 151.8154146108533
          },
          {
            "metadata": {
              "doc_id": "833",
              "name": "Deadlock",
              "source": "sparse",
              "original_content": "The product contains multiple threads or executable segments that are waiting for each other to release a necessary lock, resulting in deadlock."
            },
            "similarity": 143.4756663014263
          },
          {
            "metadata": {
              "doc_id": "194",
              "name": "Unexpected Sign Extension",
              "source": "sparse",
              "original_content": "The product performs an operation on a number that causes it to be sign extended when it is transformed into a larger data type. When the original number is negative, this can produce unexpected values that lead to resultant weaknesses."
            },
            "similarity": 139.49762401669346
          },
          {
            "metadata": {
              "doc_id": "822",
              "name": "Untrusted Pointer Dereference",
              "source": "sparse",
              "original_content": "The product obtains a value from an untrusted source, converts this value to a pointer, and dereferences the resulting pointer."
            },
            "similarity": 132.40134538822005
          },
          {
            "metadata": {
              "doc_id": "665",
              "name": "Improper Initialization",
              "source": "sparse",
              "original_content": "The product does not initialize or incorrectly initializes a resource, which might leave the resource in an unexpected state when it is accessed or used."
            },
            "similarity": 129.51325315909278
          }
        ]
      }
    },
    "keyphrase_mapping": {
      "476": [
        {
          "id": "rootcause:error pointer vs NULL bug",
          "keyphrase": "error pointer vs NULL bug",
          "type": "rootcause"
        },
        {
          "id": "rootcause:NULL dereference",
          "keyphrase": "NULL dereference",
          "type": "rootcause"
        },
        {
          "id": "weakness:NULL pointer dereference",
          "keyphrase": "NULL pointer dereference",
          "type": "weakness"
        },
        {
          "id": "product:Linux kernel",
          "keyphrase": "Linux kernel",
          "type": "product"
        },
        {
          "id": "component:Bluetooth btrtl",
          "keyphrase": "Bluetooth btrtl",
          "type": "component"
        }
      ],
      "194": [
        {
          "id": "rootcause:error pointer vs NULL bug",
          "keyphrase": "error pointer vs NULL bug",
          "type": "rootcause"
        },
        {
          "id": "component:Bluetooth btrtl",
          "keyphrase": "Bluetooth btrtl",
          "type": "component"
        }
      ],
      "833": [
        {
          "id": "rootcause:error pointer vs NULL bug",
          "keyphrase": "error pointer vs NULL bug",
          "type": "rootcause"
        },
        {
          "id": "rootcause:NULL dereference",
          "keyphrase": "NULL dereference",
          "type": "rootcause"
        },
        {
          "id": "product:Linux kernel",
          "keyphrase": "Linux kernel",
          "type": "product"
        },
        {
          "id": "component:Bluetooth btrtl",
          "keyphrase": "Bluetooth btrtl",
          "type": "component"
        }
      ],
      "822": [
        {
          "id": "rootcause:error pointer vs NULL bug",
          "keyphrase": "error pointer vs NULL bug",
          "type": "rootcause"
        },
        {
          "id": "rootcause:NULL dereference",
          "keyphrase": "NULL dereference",
          "type": "rootcause"
        },
        {
          "id": "weakness:NULL pointer dereference",
          "keyphrase": "NULL pointer dereference",
          "type": "weakness"
        },
        {
          "id": "product:Linux kernel",
          "keyphrase": "Linux kernel",
          "type": "product"
        },
        {
          "id": "component:Bluetooth btrtl",
          "keyphrase": "Bluetooth btrtl",
          "type": "component"
        }
      ],
      "665": [
        {
          "id": "rootcause:error pointer vs NULL bug",
          "keyphrase": "error pointer vs NULL bug",
          "type": "rootcause"
        },
        {
          "id": "rootcause:NULL dereference",
          "keyphrase": "NULL dereference",
          "type": "rootcause"
        },
        {
          "id": "weakness:NULL pointer dereference",
          "keyphrase": "NULL pointer dereference",
          "type": "weakness"
        },
        {
          "id": "component:Bluetooth btrtl",
          "keyphrase": "Bluetooth btrtl",
          "type": "component"
        }
      ],
      "252": [
        {
          "id": "rootcause:NULL dereference",
          "keyphrase": "NULL dereference",
          "type": "rootcause"
        },
        {
          "id": "weakness:NULL pointer dereference",
          "keyphrase": "NULL pointer dereference",
          "type": "weakness"
        }
      ],
      "690": [
        {
          "id": "weakness:NULL pointer dereference",
          "keyphrase": "NULL pointer dereference",
          "type": "weakness"
        }
      ],
      "909": [
        {
          "id": "product:Linux kernel",
          "keyphrase": "Linux kernel",
          "type": "product"
        }
      ],
      "911": [
        {
          "id": "product:Linux kernel",
          "keyphrase": "Linux kernel",
          "type": "product"
        }
      ]
    },
    "relevant_cwes": [
      {
        "metadata": {
          "doc_id": "476",
          "name": "NULL Pointer Dereference",
          "source": "sparse",
          "original_content": "The product dereferences a pointer that it expects to be valid but is NULL.",
          "keyphrase_sources": [
            {
              "id": "rootcause:error pointer vs NULL bug",
              "keyphrase": "error pointer vs NULL bug",
              "type": "rootcause"
            },
            {
              "id": "rootcause:NULL dereference",
              "keyphrase": "NULL dereference",
              "type": "rootcause"
            },
            {
              "id": "weakness:NULL pointer dereference",
              "keyphrase": "NULL pointer dereference",
              "type": "weakness"
            },
            {
              "id": "product:Linux kernel",
              "keyphrase": "Linux kernel",
              "type": "product"
            },
            {
              "id": "component:Bluetooth btrtl",
              "keyphrase": "Bluetooth btrtl",
              "type": "component"
            }
          ]
        },
        "similarity": 530.9990378372833
      },
      {
        "metadata": {
          "doc_id": "194",
          "name": "Unexpected Sign Extension",
          "source": "sparse",
          "original_content": "The product performs an operation on a number that causes it to be sign extended when it is transformed into a larger data type. When the original number is negative, this can produce unexpected values that lead to resultant weaknesses.",
          "keyphrase_sources": [
            {
              "id": "rootcause:error pointer vs NULL bug",
              "keyphrase": "error pointer vs NULL bug",
              "type": "rootcause"
            },
            {
              "id": "component:Bluetooth btrtl",
              "keyphrase": "Bluetooth btrtl",
              "type": "component"
            }
          ]
        },
        "similarity": 477.29314829086815
      },
      {
        "metadata": {
          "doc_id": "833",
          "name": "Deadlock",
          "source": "sparse",
          "original_content": "The product contains multiple threads or executable segments that are waiting for each other to release a necessary lock, resulting in deadlock.",
          "keyphrase_sources": [
            {
              "id": "rootcause:error pointer vs NULL bug",
              "keyphrase": "error pointer vs NULL bug",
              "type": "rootcause"
            },
            {
              "id": "rootcause:NULL dereference",
              "keyphrase": "NULL dereference",
              "type": "rootcause"
            },
            {
              "id": "product:Linux kernel",
              "keyphrase": "Linux kernel",
              "type": "product"
            },
            {
              "id": "component:Bluetooth btrtl",
              "keyphrase": "Bluetooth btrtl",
              "type": "component"
            }
          ]
        },
        "similarity": 467.31733243101417
      },
      {
        "metadata": {
          "doc_id": "822",
          "name": "Untrusted Pointer Dereference",
          "source": "sparse",
          "original_content": "The product obtains a value from an untrusted source, converts this value to a pointer, and dereferences the resulting pointer.",
          "keyphrase_sources": [
            {
              "id": "rootcause:error pointer vs NULL bug",
              "keyphrase": "error pointer vs NULL bug",
              "type": "rootcause"
            },
            {
              "id": "rootcause:NULL dereference",
              "keyphrase": "NULL dereference",
              "type": "rootcause"
            },
            {
              "id": "weakness:NULL pointer dereference",
              "keyphrase": "NULL pointer dereference",
              "type": "weakness"
            },
            {
              "id": "product:Linux kernel",
              "keyphrase": "Linux kernel",
              "type": "product"
            },
            {
              "id": "component:Bluetooth btrtl",
              "keyphrase": "Bluetooth btrtl",
              "type": "component"
            }
          ]
        },
        "similarity": 466.0221074372894
      },
      {
        "metadata": {
          "doc_id": "665",
          "name": "Improper Initialization",
          "source": "sparse",
          "original_content": "The product does not initialize or incorrectly initializes a resource, which might leave the resource in an unexpected state when it is accessed or used.",
          "keyphrase_sources": [
            {
              "id": "rootcause:error pointer vs NULL bug",
              "keyphrase": "error pointer vs NULL bug",
              "type": "rootcause"
            },
            {
              "id": "rootcause:NULL dereference",
              "keyphrase": "NULL dereference",
              "type": "rootcause"
            },
            {
              "id": "weakness:NULL pointer dereference",
              "keyphrase": "NULL pointer dereference",
              "type": "weakness"
            },
            {
              "id": "component:Bluetooth btrtl",
              "keyphrase": "Bluetooth btrtl",
              "type": "component"
            }
          ]
        },
        "similarity": 452.52701148110987
      },
      {
        "metadata": {
          "doc_id": "252",
          "name": "Unchecked Return Value",
          "source": "sparse",
          "original_content": "The product does not check the return value from a method or function, which can prevent it from detecting unexpected states and conditions.",
          "keyphrase_sources": [
            {
              "id": "rootcause:NULL dereference",
              "keyphrase": "NULL dereference",
              "type": "rootcause"
            },
            {
              "id": "weakness:NULL pointer dereference",
              "keyphrase": "NULL pointer dereference",
              "type": "weakness"
            }
          ]
        },
        "similarity": 438.9526218771615
      },
      {
        "metadata": {
          "doc_id": "690",
          "name": "Unchecked Return Value to NULL Pointer Dereference",
          "source": "sparse",
          "original_content": "The product does not check for an error after calling a function that can return with a NULL pointer if the function fails, which leads to a resultant NULL pointer dereference.",
          "keyphrase_sources": [
            {
              "id": "weakness:NULL pointer dereference",
              "keyphrase": "NULL pointer dereference",
              "type": "weakness"
            }
          ]
        },
        "similarity": 430.18503554343795
      },
      {
        "metadata": {
          "doc_id": "909",
          "name": "Missing Initialization of Resource",
          "source": "sparse",
          "original_content": "The product does not initialize a critical resource.",
          "keyphrase_sources": [
            {
              "id": "product:Linux kernel",
              "keyphrase": "Linux kernel",
              "type": "product"
            }
          ]
        },
        "similarity": 143.12789569892274
      },
      {
        "metadata": {
          "doc_id": "911",
          "name": "Improper Update of Reference Count",
          "source": "sparse",
          "original_content": "The product uses a reference count to manage a resource, but it does not update or incorrectly updates the reference count.",
          "keyphrase_sources": [
            {
              "id": "product:Linux kernel",
              "keyphrase": "Linux kernel",
              "type": "product"
            }
          ]
        },
        "similarity": 139.7991384776663
      }
    ],
    "enhanced_query": "# Vulnerability Description\n\n    In the Linux kernel, the following vulnerability has been resolved Bluetooth btrtl Prevent potential **NULL dereference** The btrtl_initialize() function checks that rtl_load_file() either had an error or it loaded a zero length file. However, if it loaded a zero length file then the error code is not set correctly. It results in an **error pointer vs NULL bug**, followed by a **NULL pointer dereference**. This was detected by Smatch drivers/bluetooth/btrtl.c592 btrtl_initialize() warn passing zero to ERR_PTR\n\n    # Keyphrase-Specific CWE Analysis\n    This vulnerability contains multiple keyphrases that may map to different CWEs. \n    Please analyze each keyphrase separately and determine the most appropriate CWE(s) for each.\n\n    ## ROOTCAUSE: 'error pointer vs NULL bug'\n\nRelevant CWEs for this ROOTCAUSE:\n\n### 1. CWE-476: NULL Pointer Dereference (Score: 531.00)\n\nThe product dereferences a pointer that it expects to be valid but is NULL....\n\n### 2. CWE-194: Unexpected Sign Extension (Score: 477.29)\n\nThe product performs an operation on a number that causes it to be sign extended when it is transformed into a larger data type. When the original number is negative, this can produce unexpected values that lead to resultant weaknesses....\n\n### 3. CWE-833: Deadlock (Score: 467.32)\n\nThe product contains multiple threads or executable segments that are waiting for each other to release a necessary lock, resulting in deadlock....\n\n### 4. CWE-822: Untrusted Pointer Dereference (Score: 466.02)\n\nThe product obtains a value from an untrusted source, converts this value to a pointer, and dereferences the resulting pointer....\n\n### 5. CWE-665: Improper Initialization (Score: 452.53)\n\nThe product does not initialize or incorrectly initializes a resource, which might leave the resource in an unexpected state when it is accessed or used....\n\n## ROOTCAUSE: 'NULL dereference'\n\nRelevant CWEs for this ROOTCAUSE:\n\n### 1. CWE-476: NULL Pointer Dereference (Score: 531.00)\n\nThe product dereferences a pointer that it expects to be valid but is NULL....\n\n### 2. CWE-833: Deadlock (Score: 467.32)\n\nThe product contains multiple threads or executable segments that are waiting for each other to release a necessary lock, resulting in deadlock....\n\n### 3. CWE-822: Untrusted Pointer Dereference (Score: 466.02)\n\nThe product obtains a value from an untrusted source, converts this value to a pointer, and dereferences the resulting pointer....\n\n### 4. CWE-665: Improper Initialization (Score: 452.53)\n\nThe product does not initialize or incorrectly initializes a resource, which might leave the resource in an unexpected state when it is accessed or used....\n\n### 5. CWE-252: Unchecked Return Value (Score: 438.95)\n\nThe product does not check the return value from a method or function, which can prevent it from detecting unexpected states and conditions....\n\n## WEAKNESS: 'NULL pointer dereference'\n\nRelevant CWEs for this WEAKNESS:\n\n### 1. CWE-476: NULL Pointer Dereference (Score: 531.00)\n\nThe product dereferences a pointer that it expects to be valid but is NULL....\n\n### 2. CWE-822: Untrusted Pointer Dereference (Score: 466.02)\n\nThe product obtains a value from an untrusted source, converts this value to a pointer, and dereferences the resulting pointer....\n\n### 3. CWE-665: Improper Initialization (Score: 452.53)\n\nThe product does not initialize or incorrectly initializes a resource, which might leave the resource in an unexpected state when it is accessed or used....\n\n### 4. CWE-252: Unchecked Return Value (Score: 438.95)\n\nThe product does not check the return value from a method or function, which can prevent it from detecting unexpected states and conditions....\n\n### 5. CWE-690: Unchecked Return Value to NULL Pointer Dereference (Score: 430.19)\n\nThe product does not check for an error after calling a function that can return with a NULL pointer if the function fails, which leads to a resultant NULL pointer dereference....\n\n## PRODUCT: 'Linux kernel'\n\nRelevant CWEs for this PRODUCT:\n\n### 1. CWE-476: NULL Pointer Dereference (Score: 531.00)\n\nThe product dereferences a pointer that it expects to be valid but is NULL....\n\n### 2. CWE-833: Deadlock (Score: 467.32)\n\nThe product contains multiple threads or executable segments that are waiting for each other to release a necessary lock, resulting in deadlock....\n\n### 3. CWE-822: Untrusted Pointer Dereference (Score: 466.02)\n\nThe product obtains a value from an untrusted source, converts this value to a pointer, and dereferences the resulting pointer....\n\n### 4. CWE-909: Missing Initialization of Resource (Score: 143.13)\n\nThe product does not initialize a critical resource....\n\n### 5. CWE-911: Improper Update of Reference Count (Score: 139.80)\n\nThe product uses a reference count to manage a resource, but it does not update or incorrectly updates the reference count....\n\n## COMPONENT: 'Bluetooth btrtl'\n\nRelevant CWEs for this COMPONENT:\n\n### 1. CWE-476: NULL Pointer Dereference (Score: 531.00)\n\nThe product dereferences a pointer that it expects to be valid but is NULL....\n\n### 2. CWE-194: Unexpected Sign Extension (Score: 477.29)\n\nThe product performs an operation on a number that causes it to be sign extended when it is transformed into a larger data type. When the original number is negative, this can produce unexpected values that lead to resultant weaknesses....\n\n### 3. CWE-833: Deadlock (Score: 467.32)\n\nThe product contains multiple threads or executable segments that are waiting for each other to release a necessary lock, resulting in deadlock....\n\n### 4. CWE-822: Untrusted Pointer Dereference (Score: 466.02)\n\nThe product obtains a value from an untrusted source, converts this value to a pointer, and dereferences the resulting pointer....\n\n### 5. CWE-665: Improper Initialization (Score: 452.53)\n\nThe product does not initialize or incorrectly initializes a resource, which might leave the resource in an unexpected state when it is accessed or used....\n\n\n    # Analysis Instructions\n    1. For each keyphrase, identify the most appropriate CWE(s) that represent the weakness.\n    2. Consider how the different keyphrases might relate to each other in the vulnerability chain.\n    3. Provide a final determination of primary CWE(s) and any secondary CWEs.\n    4. Format your response using the standard analysis template.\n\n    Please analyze how these different weaknesses interact and provide a comprehensive CWE classification.\n    "
  },
  "retrieval_time": 1.2043216228485107
}