{
  "vulnerability_info": "VulnerabilityInfo(cve_id='CVE-2024-13719', description='The PeproDev Ultimate Invoice plugin for WordPress is vulnerable to **Insecure Direct Object Reference** in all versions up to, and including, 2.0.8 via the invoicing viewer due to **missing validation on a user controlled key**. This makes it possible for unauthenticated attackers to view invoices for completed orders which can contain PII of users.', key_phrases={'rootcause': ['missing validation on a user controlled key', 'Insecure Direct Object Reference'], 'weakness': '', 'impact': 'view invoices for completed orders', 'vector': 'missing validation on a user controlled key', 'attacker': 'unauthenticated attackers', 'product': 'PeproDev Ultimate Invoice plugin for WordPress', 'version': 'up to and including 2.0.8', 'component': 'invoicing viewer'}, reference_content='CVE-2024-13719: PLACEHOLDER - Implement CVE description retrieval\\n\\nThe provided content details the \"PeproDev Ultimate Invoice\" WordPress plugin. Here\\'s an extraction of relevant information regarding security:\\n\\n**Root cause of vulnerability:**\\nNot explicitly stated, but the changelog mentions a \"Security Issue\" fixed in version 2.1.0 and a vulnerability reported by LVT-tholv2k fixed in version 2.0.7. Details of these issues are not provided.\\n\\n**Weaknesses/vulnerabilities present:**\\n- A security issue was present and fixed in v2.1.0 (details not provided).\\n- A vulnerability reported by LVT-tholv2k was present and fixed in v2.0.7 (details not provided).\\n\\n**Impact of exploitation:**\\nNot specified.\\n\\n**Attack vectors:**\\nNot specified.\\n\\n**Required attacker capabilities/position:**\\nNot specified.\\n\\n**Mitigation or fix:**\\n- Upgrade to version 2.1.0 or later to address the security issue.\\n- Upgrade to version 2.0.7 or later to address the vulnerability reported by LVT-tholv2k.\\n\\nThe content also provides a link to the Patchstack Vulnerability Disclosure Program for reporting security bugs: [https://patchstack.com/database/vdp/pepro-ultimate-invoice](https://patchstack.com/database/vdp/pepro-ultimate-invoice)\\n\\n**Note:** This content provides limited detail beyond the fact that vulnerabilities existed and were patched. It does *not* provide specifics about the nature of the vulnerabilities.', similar_info={'cwe_distribution': {}, 'cwe_consensus': '', 'similarity_stats': {'thresholds': [], 'total_samples_by_threshold': {}, 'top_cwes_by_threshold': {}}}, similarity_summary=SimilarityInsight(consensus_cwe='', top_cwes=[], confidence_levels={}, total_samples=0), analysis='', analysis_with_relationships='', criticism='', resolution='', relevant_cwes=[{'metadata': {'doc_id': '639', 'name': 'Authorization Bypass Through User-Controlled Key', 'source': 'sparse', 'original_content': \"The system's authorization functionality does not prevent one user from gaining access to another user's data or record by modifying the key value identifying the data.\", 'keyphrase_sources': [{'id': 'rootcause:missing validation on a user controlled key', 'keyphrase': 'missing validation on a user controlled key', 'type': 'rootcause'}, {'id': 'rootcause:Insecure Direct Object Reference', 'keyphrase': 'Insecure Direct Object Reference', 'type': 'rootcause'}, {'id': 'impact:view invoices for completed orders', 'keyphrase': 'view invoices for completed orders', 'type': 'impact'}, {'id': 'vector:missing validation on a user controlled key', 'keyphrase': 'missing validation on a user controlled key', 'type': 'vector'}, {'id': 'attacker:unauthenticated attackers', 'keyphrase': 'unauthenticated attackers', 'type': 'attacker'}, {'id': 'product:PeproDev Ultimate Invoice plugin for WordPress', 'keyphrase': 'PeproDev Ultimate Invoice plugin for WordPress', 'type': 'product'}, {'id': 'version:up to and including 2.0.8', 'keyphrase': 'up to and including 2.0.8', 'type': 'version'}, {'id': 'component:invoicing viewer', 'keyphrase': 'invoicing viewer', 'type': 'component'}]}, 'similarity': np.float64(456.89107431242894)}, {'metadata': {'doc_id': '862', 'name': 'Missing Authorization', 'source': 'sparse', 'original_content': 'The product does not perform an authorization check when an actor attempts to access a resource or perform an action.', 'keyphrase_sources': [{'id': 'rootcause:missing validation on a user controlled key', 'keyphrase': 'missing validation on a user controlled key', 'type': 'rootcause'}, {'id': 'impact:view invoices for completed orders', 'keyphrase': 'view invoices for completed orders', 'type': 'impact'}, {'id': 'vector:missing validation on a user controlled key', 'keyphrase': 'missing validation on a user controlled key', 'type': 'vector'}, {'id': 'attacker:unauthenticated attackers', 'keyphrase': 'unauthenticated attackers', 'type': 'attacker'}, {'id': 'product:PeproDev Ultimate Invoice plugin for WordPress', 'keyphrase': 'PeproDev Ultimate Invoice plugin for WordPress', 'type': 'product'}, {'id': 'version:up to and including 2.0.8', 'keyphrase': 'up to and including 2.0.8', 'type': 'version'}, {'id': 'component:invoicing viewer', 'keyphrase': 'invoicing viewer', 'type': 'component'}]}, 'similarity': np.float64(398.3074532334788)}, {'metadata': {'doc_id': '352', 'name': 'Cross-Site Request Forgery (CSRF)', 'source': 'sparse', 'original_content': 'The web application does not, or can not, sufficiently verify whether a well-formed, valid, consistent request was intentionally provided by the user who submitted the request.', 'keyphrase_sources': [{'id': 'rootcause:missing validation on a user controlled key', 'keyphrase': 'missing validation on a user controlled key', 'type': 'rootcause'}, {'id': 'rootcause:Insecure Direct Object Reference', 'keyphrase': 'Insecure Direct Object Reference', 'type': 'rootcause'}, {'id': 'vector:missing validation on a user controlled key', 'keyphrase': 'missing validation on a user controlled key', 'type': 'vector'}, {'id': 'attacker:unauthenticated attackers', 'keyphrase': 'unauthenticated attackers', 'type': 'attacker'}, {'id': 'product:PeproDev Ultimate Invoice plugin for WordPress', 'keyphrase': 'PeproDev Ultimate Invoice plugin for WordPress', 'type': 'product'}, {'id': 'version:up to and including 2.0.8', 'keyphrase': 'up to and including 2.0.8', 'type': 'version'}, {'id': 'component:invoicing viewer', 'keyphrase': 'invoicing viewer', 'type': 'component'}]}, 'similarity': np.float64(386.19569070613363)}, {'metadata': {'doc_id': '306', 'name': 'Missing Authentication for Critical Function', 'source': 'sparse', 'original_content': 'The product does not perform any authentication for functionality that requires a provable user identity or consumes a significant amount of resources.', 'keyphrase_sources': [{'id': 'rootcause:missing validation on a user controlled key', 'keyphrase': 'missing validation on a user controlled key', 'type': 'rootcause'}, {'id': 'impact:view invoices for completed orders', 'keyphrase': 'view invoices for completed orders', 'type': 'impact'}, {'id': 'vector:missing validation on a user controlled key', 'keyphrase': 'missing validation on a user controlled key', 'type': 'vector'}, {'id': 'attacker:unauthenticated attackers', 'keyphrase': 'unauthenticated attackers', 'type': 'attacker'}, {'id': 'product:PeproDev Ultimate Invoice plugin for WordPress', 'keyphrase': 'PeproDev Ultimate Invoice plugin for WordPress', 'type': 'product'}, {'id': 'version:up to and including 2.0.8', 'keyphrase': 'up to and including 2.0.8', 'type': 'version'}, {'id': 'component:invoicing viewer', 'keyphrase': 'invoicing viewer', 'type': 'component'}]}, 'similarity': np.float64(385.7580149898458)}, {'metadata': {'doc_id': '99', 'name': \"Improper Control of Resource Identifiers ('Resource Injection')\", 'source': 'sparse', 'original_content': 'The product receives input from an upstream component, but it does not restrict or incorrectly restricts the input before it is used as an identifier for a resource that may be outside the intended sphere of control.', 'keyphrase_sources': [{'id': 'rootcause:Insecure Direct Object Reference', 'keyphrase': 'Insecure Direct Object Reference', 'type': 'rootcause'}]}, 'similarity': np.float64(383.9292736769987)}, {'metadata': {'doc_id': '116', 'name': 'Improper Encoding or Escaping of Output', 'source': 'sparse', 'original_content': 'The product prepares a structured message for communication with another component, but encoding or escaping of the data is either missing or done incorrectly. As a result, the intended structure of the message is not preserved.', 'keyphrase_sources': [{'id': 'rootcause:missing validation on a user controlled key', 'keyphrase': 'missing validation on a user controlled key', 'type': 'rootcause'}, {'id': 'vector:missing validation on a user controlled key', 'keyphrase': 'missing validation on a user controlled key', 'type': 'vector'}]}, 'similarity': np.float64(381.5266565892334)}, {'metadata': {'doc_id': '425', 'name': \"Direct Request ('Forced Browsing')\", 'source': 'sparse', 'original_content': 'The web application does not adequately enforce appropriate authorization on all restricted URLs, scripts, or files.', 'keyphrase_sources': [{'id': 'rootcause:Insecure Direct Object Reference', 'keyphrase': 'Insecure Direct Object Reference', 'type': 'rootcause'}, {'id': 'attacker:unauthenticated attackers', 'keyphrase': 'unauthenticated attackers', 'type': 'attacker'}]}, 'similarity': np.float64(347.4763247585028)}, {'metadata': {'doc_id': '502', 'name': 'Deserialization of Untrusted Data', 'source': 'sparse', 'original_content': 'The product deserializes untrusted data without sufficiently ensuring that the resulting data will be valid.', 'keyphrase_sources': [{'id': 'rootcause:Insecure Direct Object Reference', 'keyphrase': 'Insecure Direct Object Reference', 'type': 'rootcause'}, {'id': 'version:up to and including 2.0.8', 'keyphrase': 'up to and including 2.0.8', 'type': 'version'}]}, 'similarity': np.float64(333.91936236180516)}, {'metadata': {'doc_id': '790', 'name': 'Improper Filtering of Special Elements', 'source': 'sparse', 'original_content': 'The product receives data from an upstream component, but does not filter or incorrectly filters special elements before sending it to a downstream component.', 'keyphrase_sources': [{'id': 'product:PeproDev Ultimate Invoice plugin for WordPress', 'keyphrase': 'PeproDev Ultimate Invoice plugin for WordPress', 'type': 'product'}]}, 'similarity': np.float64(128.58803339863027)}, {'metadata': {'doc_id': '863', 'name': 'Incorrect Authorization', 'source': 'sparse', 'original_content': 'The product performs an authorization check when an actor attempts to access a resource or perform an action, but it does not correctly perform the check.', 'keyphrase_sources': [{'id': 'impact:view invoices for completed orders', 'keyphrase': 'view invoices for completed orders', 'type': 'impact'}, {'id': 'component:invoicing viewer', 'keyphrase': 'invoicing viewer', 'type': 'component'}]}, 'similarity': np.float64(116.83844177117165)}, {'metadata': {'doc_id': '200', 'name': 'Exposure of Sensitive Information to an Unauthorized Actor', 'source': 'sparse', 'original_content': 'The product exposes sensitive information to an actor that is not explicitly authorized to have access to that information.', 'keyphrase_sources': [{'id': 'impact:view invoices for completed orders', 'keyphrase': 'view invoices for completed orders', 'type': 'impact'}]}, 'similarity': np.float64(113.3516911650521)}], identified_cwes={'analyzer': [], 'critic_additional': []})",
  "retrieval_results": {
    "has_multiple_keyphrases": true,
    "keyphrase_cwe_sets": {
      "rootcause:missing validation on a user controlled key": {
        "keyphrase": "missing validation on a user controlled key",
        "type": "rootcause",
        "cwes": [
          {
            "metadata": {
              "doc_id": "639",
              "name": "Authorization Bypass Through User-Controlled Key",
              "source": "sparse",
              "original_content": "The system's authorization functionality does not prevent one user from gaining access to another user's data or record by modifying the key value identifying the data.",
              "keyphrase_sources": [
                {
                  "id": "rootcause:missing validation on a user controlled key",
                  "keyphrase": "missing validation on a user controlled key",
                  "type": "rootcause"
                },
                {
                  "id": "rootcause:Insecure Direct Object Reference",
                  "keyphrase": "Insecure Direct Object Reference",
                  "type": "rootcause"
                },
                {
                  "id": "impact:view invoices for completed orders",
                  "keyphrase": "view invoices for completed orders",
                  "type": "impact"
                },
                {
                  "id": "vector:missing validation on a user controlled key",
                  "keyphrase": "missing validation on a user controlled key",
                  "type": "vector"
                },
                {
                  "id": "attacker:unauthenticated attackers",
                  "keyphrase": "unauthenticated attackers",
                  "type": "attacker"
                },
                {
                  "id": "product:PeproDev Ultimate Invoice plugin for WordPress",
                  "keyphrase": "PeproDev Ultimate Invoice plugin for WordPress",
                  "type": "product"
                },
                {
                  "id": "version:up to and including 2.0.8",
                  "keyphrase": "up to and including 2.0.8",
                  "type": "version"
                },
                {
                  "id": "component:invoicing viewer",
                  "keyphrase": "invoicing viewer",
                  "type": "component"
                }
              ]
            },
            "similarity": 456.89107431242894
          },
          {
            "metadata": {
              "doc_id": "862",
              "name": "Missing Authorization",
              "source": "sparse",
              "original_content": "The product does not perform an authorization check when an actor attempts to access a resource or perform an action.",
              "keyphrase_sources": [
                {
                  "id": "rootcause:missing validation on a user controlled key",
                  "keyphrase": "missing validation on a user controlled key",
                  "type": "rootcause"
                },
                {
                  "id": "impact:view invoices for completed orders",
                  "keyphrase": "view invoices for completed orders",
                  "type": "impact"
                },
                {
                  "id": "vector:missing validation on a user controlled key",
                  "keyphrase": "missing validation on a user controlled key",
                  "type": "vector"
                },
                {
                  "id": "attacker:unauthenticated attackers",
                  "keyphrase": "unauthenticated attackers",
                  "type": "attacker"
                },
                {
                  "id": "product:PeproDev Ultimate Invoice plugin for WordPress",
                  "keyphrase": "PeproDev Ultimate Invoice plugin for WordPress",
                  "type": "product"
                },
                {
                  "id": "version:up to and including 2.0.8",
                  "keyphrase": "up to and including 2.0.8",
                  "type": "version"
                },
                {
                  "id": "component:invoicing viewer",
                  "keyphrase": "invoicing viewer",
                  "type": "component"
                }
              ]
            },
            "similarity": 398.3074532334788
          },
          {
            "metadata": {
              "doc_id": "352",
              "name": "Cross-Site Request Forgery (CSRF)",
              "source": "sparse",
              "original_content": "The web application does not, or can not, sufficiently verify whether a well-formed, valid, consistent request was intentionally provided by the user who submitted the request.",
              "keyphrase_sources": [
                {
                  "id": "rootcause:missing validation on a user controlled key",
                  "keyphrase": "missing validation on a user controlled key",
                  "type": "rootcause"
                },
                {
                  "id": "rootcause:Insecure Direct Object Reference",
                  "keyphrase": "Insecure Direct Object Reference",
                  "type": "rootcause"
                },
                {
                  "id": "vector:missing validation on a user controlled key",
                  "keyphrase": "missing validation on a user controlled key",
                  "type": "vector"
                },
                {
                  "id": "attacker:unauthenticated attackers",
                  "keyphrase": "unauthenticated attackers",
                  "type": "attacker"
                },
                {
                  "id": "product:PeproDev Ultimate Invoice plugin for WordPress",
                  "keyphrase": "PeproDev Ultimate Invoice plugin for WordPress",
                  "type": "product"
                },
                {
                  "id": "version:up to and including 2.0.8",
                  "keyphrase": "up to and including 2.0.8",
                  "type": "version"
                },
                {
                  "id": "component:invoicing viewer",
                  "keyphrase": "invoicing viewer",
                  "type": "component"
                }
              ]
            },
            "similarity": 386.19569070613363
          },
          {
            "metadata": {
              "doc_id": "306",
              "name": "Missing Authentication for Critical Function",
              "source": "sparse",
              "original_content": "The product does not perform any authentication for functionality that requires a provable user identity or consumes a significant amount of resources.",
              "keyphrase_sources": [
                {
                  "id": "rootcause:missing validation on a user controlled key",
                  "keyphrase": "missing validation on a user controlled key",
                  "type": "rootcause"
                },
                {
                  "id": "impact:view invoices for completed orders",
                  "keyphrase": "view invoices for completed orders",
                  "type": "impact"
                },
                {
                  "id": "vector:missing validation on a user controlled key",
                  "keyphrase": "missing validation on a user controlled key",
                  "type": "vector"
                },
                {
                  "id": "attacker:unauthenticated attackers",
                  "keyphrase": "unauthenticated attackers",
                  "type": "attacker"
                },
                {
                  "id": "product:PeproDev Ultimate Invoice plugin for WordPress",
                  "keyphrase": "PeproDev Ultimate Invoice plugin for WordPress",
                  "type": "product"
                },
                {
                  "id": "version:up to and including 2.0.8",
                  "keyphrase": "up to and including 2.0.8",
                  "type": "version"
                },
                {
                  "id": "component:invoicing viewer",
                  "keyphrase": "invoicing viewer",
                  "type": "component"
                }
              ]
            },
            "similarity": 385.7580149898458
          },
          {
            "metadata": {
              "doc_id": "116",
              "name": "Improper Encoding or Escaping of Output",
              "source": "sparse",
              "original_content": "The product prepares a structured message for communication with another component, but encoding or escaping of the data is either missing or done incorrectly. As a result, the intended structure of the message is not preserved.",
              "keyphrase_sources": [
                {
                  "id": "rootcause:missing validation on a user controlled key",
                  "keyphrase": "missing validation on a user controlled key",
                  "type": "rootcause"
                },
                {
                  "id": "vector:missing validation on a user controlled key",
                  "keyphrase": "missing validation on a user controlled key",
                  "type": "vector"
                }
              ]
            },
            "similarity": 381.5266565892334
          }
        ]
      },
      "rootcause:Insecure Direct Object Reference": {
        "keyphrase": "Insecure Direct Object Reference",
        "type": "rootcause",
        "cwes": [
          {
            "metadata": {
              "doc_id": "639",
              "name": "Authorization Bypass Through User-Controlled Key",
              "source": "sparse",
              "original_content": "The system's authorization functionality does not prevent one user from gaining access to another user's data or record by modifying the key value identifying the data."
            },
            "similarity": 492.6201938126792
          },
          {
            "metadata": {
              "doc_id": "99",
              "name": "Improper Control of Resource Identifiers ('Resource Injection')",
              "source": "sparse",
              "original_content": "The product receives input from an upstream component, but it does not restrict or incorrectly restricts the input before it is used as an identifier for a resource that may be outside the intended sphere of control.",
              "keyphrase_sources": [
                {
                  "id": "rootcause:Insecure Direct Object Reference",
                  "keyphrase": "Insecure Direct Object Reference",
                  "type": "rootcause"
                }
              ]
            },
            "similarity": 383.9292736769987
          },
          {
            "metadata": {
              "doc_id": "425",
              "name": "Direct Request ('Forced Browsing')",
              "source": "sparse",
              "original_content": "The web application does not adequately enforce appropriate authorization on all restricted URLs, scripts, or files.",
              "keyphrase_sources": [
                {
                  "id": "rootcause:Insecure Direct Object Reference",
                  "keyphrase": "Insecure Direct Object Reference",
                  "type": "rootcause"
                },
                {
                  "id": "attacker:unauthenticated attackers",
                  "keyphrase": "unauthenticated attackers",
                  "type": "attacker"
                }
              ]
            },
            "similarity": 347.4763247585028
          },
          {
            "metadata": {
              "doc_id": "352",
              "name": "Cross-Site Request Forgery (CSRF)",
              "source": "sparse",
              "original_content": "The web application does not, or can not, sufficiently verify whether a well-formed, valid, consistent request was intentionally provided by the user who submitted the request."
            },
            "similarity": 340.5530853017963
          },
          {
            "metadata": {
              "doc_id": "502",
              "name": "Deserialization of Untrusted Data",
              "source": "sparse",
              "original_content": "The product deserializes untrusted data without sufficiently ensuring that the resulting data will be valid.",
              "keyphrase_sources": [
                {
                  "id": "rootcause:Insecure Direct Object Reference",
                  "keyphrase": "Insecure Direct Object Reference",
                  "type": "rootcause"
                },
                {
                  "id": "version:up to and including 2.0.8",
                  "keyphrase": "up to and including 2.0.8",
                  "type": "version"
                }
              ]
            },
            "similarity": 333.91936236180516
          }
        ]
      },
      "impact:view invoices for completed orders": {
        "keyphrase": "view invoices for completed orders",
        "type": "impact",
        "cwes": [
          {
            "metadata": {
              "doc_id": "639",
              "name": "Authorization Bypass Through User-Controlled Key",
              "source": "sparse",
              "original_content": "The system's authorization functionality does not prevent one user from gaining access to another user's data or record by modifying the key value identifying the data."
            },
            "similarity": 141.6465222727372
          },
          {
            "metadata": {
              "doc_id": "862",
              "name": "Missing Authorization",
              "source": "sparse",
              "original_content": "The product does not perform an authorization check when an actor attempts to access a resource or perform an action."
            },
            "similarity": 119.90512433793664
          },
          {
            "metadata": {
              "doc_id": "863",
              "name": "Incorrect Authorization",
              "source": "sparse",
              "original_content": "The product performs an authorization check when an actor attempts to access a resource or perform an action, but it does not correctly perform the check.",
              "keyphrase_sources": [
                {
                  "id": "impact:view invoices for completed orders",
                  "keyphrase": "view invoices for completed orders",
                  "type": "impact"
                },
                {
                  "id": "component:invoicing viewer",
                  "keyphrase": "invoicing viewer",
                  "type": "component"
                }
              ]
            },
            "similarity": 116.83844177117165
          },
          {
            "metadata": {
              "doc_id": "306",
              "name": "Missing Authentication for Critical Function",
              "source": "sparse",
              "original_content": "The product does not perform any authentication for functionality that requires a provable user identity or consumes a significant amount of resources."
            },
            "similarity": 116.750731039353
          },
          {
            "metadata": {
              "doc_id": "200",
              "name": "Exposure of Sensitive Information to an Unauthorized Actor",
              "source": "sparse",
              "original_content": "The product exposes sensitive information to an actor that is not explicitly authorized to have access to that information.",
              "keyphrase_sources": [
                {
                  "id": "impact:view invoices for completed orders",
                  "keyphrase": "view invoices for completed orders",
                  "type": "impact"
                }
              ]
            },
            "similarity": 113.3516911650521
          }
        ]
      },
      "vector:missing validation on a user controlled key": {
        "keyphrase": "missing validation on a user controlled key",
        "type": "vector",
        "cwes": [
          {
            "metadata": {
              "doc_id": "639",
              "name": "Authorization Bypass Through User-Controlled Key",
              "source": "sparse",
              "original_content": "The system's authorization functionality does not prevent one user from gaining access to another user's data or record by modifying the key value identifying the data."
            },
            "similarity": 152.29702477080966
          },
          {
            "metadata": {
              "doc_id": "862",
              "name": "Missing Authorization",
              "source": "sparse",
              "original_content": "The product does not perform an authorization check when an actor attempts to access a resource or perform an action."
            },
            "similarity": 132.76915107782625
          },
          {
            "metadata": {
              "doc_id": "352",
              "name": "Cross-Site Request Forgery (CSRF)",
              "source": "sparse",
              "original_content": "The web application does not, or can not, sufficiently verify whether a well-formed, valid, consistent request was intentionally provided by the user who submitted the request."
            },
            "similarity": 128.73189690204455
          },
          {
            "metadata": {
              "doc_id": "306",
              "name": "Missing Authentication for Critical Function",
              "source": "sparse",
              "original_content": "The product does not perform any authentication for functionality that requires a provable user identity or consumes a significant amount of resources."
            },
            "similarity": 128.58600499661526
          },
          {
            "metadata": {
              "doc_id": "116",
              "name": "Improper Encoding or Escaping of Output",
              "source": "sparse",
              "original_content": "The product prepares a structured message for communication with another component, but encoding or escaping of the data is either missing or done incorrectly. As a result, the intended structure of the message is not preserved."
            },
            "similarity": 127.17555219641113
          }
        ]
      },
      "attacker:unauthenticated attackers": {
        "keyphrase": "unauthenticated attackers",
        "type": "attacker",
        "cwes": [
          {
            "metadata": {
              "doc_id": "639",
              "name": "Authorization Bypass Through User-Controlled Key",
              "source": "sparse",
              "original_content": "The system's authorization functionality does not prevent one user from gaining access to another user's data or record by modifying the key value identifying the data."
            },
            "similarity": 130.23325709494054
          },
          {
            "metadata": {
              "doc_id": "862",
              "name": "Missing Authorization",
              "source": "sparse",
              "original_content": "The product does not perform an authorization check when an actor attempts to access a resource or perform an action."
            },
            "similarity": 113.36505038998838
          },
          {
            "metadata": {
              "doc_id": "352",
              "name": "Cross-Site Request Forgery (CSRF)",
              "source": "sparse",
              "original_content": "The web application does not, or can not, sufficiently verify whether a well-formed, valid, consistent request was intentionally provided by the user who submitted the request."
            },
            "similarity": 112.52916487521279
          },
          {
            "metadata": {
              "doc_id": "306",
              "name": "Missing Authentication for Critical Function",
              "source": "sparse",
              "original_content": "The product does not perform any authentication for functionality that requires a provable user identity or consumes a significant amount of resources."
            },
            "similarity": 112.05661675751726
          },
          {
            "metadata": {
              "doc_id": "425",
              "name": "Direct Request ('Forced Browsing')",
              "source": "sparse",
              "original_content": "The web application does not adequately enforce appropriate authorization on all restricted URLs, scripts, or files."
            },
            "similarity": 107.73043200598623
          }
        ]
      },
      "product:PeproDev Ultimate Invoice plugin for WordPress": {
        "keyphrase": "PeproDev Ultimate Invoice plugin for WordPress",
        "type": "product",
        "cwes": [
          {
            "metadata": {
              "doc_id": "639",
              "name": "Authorization Bypass Through User-Controlled Key",
              "source": "sparse",
              "original_content": "The system's authorization functionality does not prevent one user from gaining access to another user's data or record by modifying the key value identifying the data."
            },
            "similarity": 145.1008738903346
          },
          {
            "metadata": {
              "doc_id": "352",
              "name": "Cross-Site Request Forgery (CSRF)",
              "source": "sparse",
              "original_content": "The web application does not, or can not, sufficiently verify whether a well-formed, valid, consistent request was intentionally provided by the user who submitted the request."
            },
            "similarity": 136.46616753998725
          },
          {
            "metadata": {
              "doc_id": "862",
              "name": "Missing Authorization",
              "source": "sparse",
              "original_content": "The product does not perform an authorization check when an actor attempts to access a resource or perform an action."
            },
            "similarity": 135.2789257819438
          },
          {
            "metadata": {
              "doc_id": "306",
              "name": "Missing Authentication for Critical Function",
              "source": "sparse",
              "original_content": "The product does not perform any authentication for functionality that requires a provable user identity or consumes a significant amount of resources."
            },
            "similarity": 130.42508301262092
          },
          {
            "metadata": {
              "doc_id": "790",
              "name": "Improper Filtering of Special Elements",
              "source": "sparse",
              "original_content": "The product receives data from an upstream component, but does not filter or incorrectly filters special elements before sending it to a downstream component.",
              "keyphrase_sources": [
                {
                  "id": "product:PeproDev Ultimate Invoice plugin for WordPress",
                  "keyphrase": "PeproDev Ultimate Invoice plugin for WordPress",
                  "type": "product"
                }
              ]
            },
            "similarity": 128.58803339863027
          }
        ]
      },
      "version:up to and including 2.0.8": {
        "keyphrase": "up to and including 2.0.8",
        "type": "version",
        "cwes": [
          {
            "metadata": {
              "doc_id": "639",
              "name": "Authorization Bypass Through User-Controlled Key",
              "source": "sparse",
              "original_content": "The system's authorization functionality does not prevent one user from gaining access to another user's data or record by modifying the key value identifying the data."
            },
            "similarity": 150.42331376524416
          },
          {
            "metadata": {
              "doc_id": "862",
              "name": "Missing Authorization",
              "source": "sparse",
              "original_content": "The product does not perform an authorization check when an actor attempts to access a resource or perform an action."
            },
            "similarity": 135.71218021837498
          },
          {
            "metadata": {
              "doc_id": "352",
              "name": "Cross-Site Request Forgery (CSRF)",
              "source": "sparse",
              "original_content": "The web application does not, or can not, sufficiently verify whether a well-formed, valid, consistent request was intentionally provided by the user who submitted the request."
            },
            "similarity": 133.17942719328016
          },
          {
            "metadata": {
              "doc_id": "306",
              "name": "Missing Authentication for Critical Function",
              "source": "sparse",
              "original_content": "The product does not perform any authentication for functionality that requires a provable user identity or consumes a significant amount of resources."
            },
            "similarity": 132.88478194362986
          },
          {
            "metadata": {
              "doc_id": "502",
              "name": "Deserialization of Untrusted Data",
              "source": "sparse",
              "original_content": "The product deserializes untrusted data without sufficiently ensuring that the resulting data will be valid."
            },
            "similarity": 131.1224573260367
          }
        ]
      },
      "component:invoicing viewer": {
        "keyphrase": "invoicing viewer",
        "type": "component",
        "cwes": [
          {
            "metadata": {
              "doc_id": "639",
              "name": "Authorization Bypass Through User-Controlled Key",
              "source": "sparse",
              "original_content": "The system's authorization functionality does not prevent one user from gaining access to another user's data or record by modifying the key value identifying the data."
            },
            "similarity": 124.3475460550446
          },
          {
            "metadata": {
              "doc_id": "862",
              "name": "Missing Authorization",
              "source": "sparse",
              "original_content": "The product does not perform an authorization check when an actor attempts to access a resource or perform an action."
            },
            "similarity": 108.79748310933796
          },
          {
            "metadata": {
              "doc_id": "352",
              "name": "Cross-Site Request Forgery (CSRF)",
              "source": "sparse",
              "original_content": "The web application does not, or can not, sufficiently verify whether a well-formed, valid, consistent request was intentionally provided by the user who submitted the request."
            },
            "similarity": 105.98019008632897
          },
          {
            "metadata": {
              "doc_id": "306",
              "name": "Missing Authentication for Critical Function",
              "source": "sparse",
              "original_content": "The product does not perform any authentication for functionality that requires a provable user identity or consumes a significant amount of resources."
            },
            "similarity": 104.89042013150204
          },
          {
            "metadata": {
              "doc_id": "863",
              "name": "Incorrect Authorization",
              "source": "sparse",
              "original_content": "The product performs an authorization check when an actor attempts to access a resource or perform an action, but it does not correctly perform the check."
            },
            "similarity": 104.36799506366746
          }
        ]
      }
    },
    "keyphrase_mapping": {
      "639": [
        {
          "id": "rootcause:missing validation on a user controlled key",
          "keyphrase": "missing validation on a user controlled key",
          "type": "rootcause"
        },
        {
          "id": "rootcause:Insecure Direct Object Reference",
          "keyphrase": "Insecure Direct Object Reference",
          "type": "rootcause"
        },
        {
          "id": "impact:view invoices for completed orders",
          "keyphrase": "view invoices for completed orders",
          "type": "impact"
        },
        {
          "id": "vector:missing validation on a user controlled key",
          "keyphrase": "missing validation on a user controlled key",
          "type": "vector"
        },
        {
          "id": "attacker:unauthenticated attackers",
          "keyphrase": "unauthenticated attackers",
          "type": "attacker"
        },
        {
          "id": "product:PeproDev Ultimate Invoice plugin for WordPress",
          "keyphrase": "PeproDev Ultimate Invoice plugin for WordPress",
          "type": "product"
        },
        {
          "id": "version:up to and including 2.0.8",
          "keyphrase": "up to and including 2.0.8",
          "type": "version"
        },
        {
          "id": "component:invoicing viewer",
          "keyphrase": "invoicing viewer",
          "type": "component"
        }
      ],
      "862": [
        {
          "id": "rootcause:missing validation on a user controlled key",
          "keyphrase": "missing validation on a user controlled key",
          "type": "rootcause"
        },
        {
          "id": "impact:view invoices for completed orders",
          "keyphrase": "view invoices for completed orders",
          "type": "impact"
        },
        {
          "id": "vector:missing validation on a user controlled key",
          "keyphrase": "missing validation on a user controlled key",
          "type": "vector"
        },
        {
          "id": "attacker:unauthenticated attackers",
          "keyphrase": "unauthenticated attackers",
          "type": "attacker"
        },
        {
          "id": "product:PeproDev Ultimate Invoice plugin for WordPress",
          "keyphrase": "PeproDev Ultimate Invoice plugin for WordPress",
          "type": "product"
        },
        {
          "id": "version:up to and including 2.0.8",
          "keyphrase": "up to and including 2.0.8",
          "type": "version"
        },
        {
          "id": "component:invoicing viewer",
          "keyphrase": "invoicing viewer",
          "type": "component"
        }
      ],
      "352": [
        {
          "id": "rootcause:missing validation on a user controlled key",
          "keyphrase": "missing validation on a user controlled key",
          "type": "rootcause"
        },
        {
          "id": "rootcause:Insecure Direct Object Reference",
          "keyphrase": "Insecure Direct Object Reference",
          "type": "rootcause"
        },
        {
          "id": "vector:missing validation on a user controlled key",
          "keyphrase": "missing validation on a user controlled key",
          "type": "vector"
        },
        {
          "id": "attacker:unauthenticated attackers",
          "keyphrase": "unauthenticated attackers",
          "type": "attacker"
        },
        {
          "id": "product:PeproDev Ultimate Invoice plugin for WordPress",
          "keyphrase": "PeproDev Ultimate Invoice plugin for WordPress",
          "type": "product"
        },
        {
          "id": "version:up to and including 2.0.8",
          "keyphrase": "up to and including 2.0.8",
          "type": "version"
        },
        {
          "id": "component:invoicing viewer",
          "keyphrase": "invoicing viewer",
          "type": "component"
        }
      ],
      "306": [
        {
          "id": "rootcause:missing validation on a user controlled key",
          "keyphrase": "missing validation on a user controlled key",
          "type": "rootcause"
        },
        {
          "id": "impact:view invoices for completed orders",
          "keyphrase": "view invoices for completed orders",
          "type": "impact"
        },
        {
          "id": "vector:missing validation on a user controlled key",
          "keyphrase": "missing validation on a user controlled key",
          "type": "vector"
        },
        {
          "id": "attacker:unauthenticated attackers",
          "keyphrase": "unauthenticated attackers",
          "type": "attacker"
        },
        {
          "id": "product:PeproDev Ultimate Invoice plugin for WordPress",
          "keyphrase": "PeproDev Ultimate Invoice plugin for WordPress",
          "type": "product"
        },
        {
          "id": "version:up to and including 2.0.8",
          "keyphrase": "up to and including 2.0.8",
          "type": "version"
        },
        {
          "id": "component:invoicing viewer",
          "keyphrase": "invoicing viewer",
          "type": "component"
        }
      ],
      "116": [
        {
          "id": "rootcause:missing validation on a user controlled key",
          "keyphrase": "missing validation on a user controlled key",
          "type": "rootcause"
        },
        {
          "id": "vector:missing validation on a user controlled key",
          "keyphrase": "missing validation on a user controlled key",
          "type": "vector"
        }
      ],
      "99": [
        {
          "id": "rootcause:Insecure Direct Object Reference",
          "keyphrase": "Insecure Direct Object Reference",
          "type": "rootcause"
        }
      ],
      "425": [
        {
          "id": "rootcause:Insecure Direct Object Reference",
          "keyphrase": "Insecure Direct Object Reference",
          "type": "rootcause"
        },
        {
          "id": "attacker:unauthenticated attackers",
          "keyphrase": "unauthenticated attackers",
          "type": "attacker"
        }
      ],
      "502": [
        {
          "id": "rootcause:Insecure Direct Object Reference",
          "keyphrase": "Insecure Direct Object Reference",
          "type": "rootcause"
        },
        {
          "id": "version:up to and including 2.0.8",
          "keyphrase": "up to and including 2.0.8",
          "type": "version"
        }
      ],
      "863": [
        {
          "id": "impact:view invoices for completed orders",
          "keyphrase": "view invoices for completed orders",
          "type": "impact"
        },
        {
          "id": "component:invoicing viewer",
          "keyphrase": "invoicing viewer",
          "type": "component"
        }
      ],
      "200": [
        {
          "id": "impact:view invoices for completed orders",
          "keyphrase": "view invoices for completed orders",
          "type": "impact"
        }
      ],
      "790": [
        {
          "id": "product:PeproDev Ultimate Invoice plugin for WordPress",
          "keyphrase": "PeproDev Ultimate Invoice plugin for WordPress",
          "type": "product"
        }
      ]
    },
    "relevant_cwes": [
      {
        "metadata": {
          "doc_id": "639",
          "name": "Authorization Bypass Through User-Controlled Key",
          "source": "sparse",
          "original_content": "The system's authorization functionality does not prevent one user from gaining access to another user's data or record by modifying the key value identifying the data.",
          "keyphrase_sources": [
            {
              "id": "rootcause:missing validation on a user controlled key",
              "keyphrase": "missing validation on a user controlled key",
              "type": "rootcause"
            },
            {
              "id": "rootcause:Insecure Direct Object Reference",
              "keyphrase": "Insecure Direct Object Reference",
              "type": "rootcause"
            },
            {
              "id": "impact:view invoices for completed orders",
              "keyphrase": "view invoices for completed orders",
              "type": "impact"
            },
            {
              "id": "vector:missing validation on a user controlled key",
              "keyphrase": "missing validation on a user controlled key",
              "type": "vector"
            },
            {
              "id": "attacker:unauthenticated attackers",
              "keyphrase": "unauthenticated attackers",
              "type": "attacker"
            },
            {
              "id": "product:PeproDev Ultimate Invoice plugin for WordPress",
              "keyphrase": "PeproDev Ultimate Invoice plugin for WordPress",
              "type": "product"
            },
            {
              "id": "version:up to and including 2.0.8",
              "keyphrase": "up to and including 2.0.8",
              "type": "version"
            },
            {
              "id": "component:invoicing viewer",
              "keyphrase": "invoicing viewer",
              "type": "component"
            }
          ]
        },
        "similarity": 456.89107431242894
      },
      {
        "metadata": {
          "doc_id": "862",
          "name": "Missing Authorization",
          "source": "sparse",
          "original_content": "The product does not perform an authorization check when an actor attempts to access a resource or perform an action.",
          "keyphrase_sources": [
            {
              "id": "rootcause:missing validation on a user controlled key",
              "keyphrase": "missing validation on a user controlled key",
              "type": "rootcause"
            },
            {
              "id": "impact:view invoices for completed orders",
              "keyphrase": "view invoices for completed orders",
              "type": "impact"
            },
            {
              "id": "vector:missing validation on a user controlled key",
              "keyphrase": "missing validation on a user controlled key",
              "type": "vector"
            },
            {
              "id": "attacker:unauthenticated attackers",
              "keyphrase": "unauthenticated attackers",
              "type": "attacker"
            },
            {
              "id": "product:PeproDev Ultimate Invoice plugin for WordPress",
              "keyphrase": "PeproDev Ultimate Invoice plugin for WordPress",
              "type": "product"
            },
            {
              "id": "version:up to and including 2.0.8",
              "keyphrase": "up to and including 2.0.8",
              "type": "version"
            },
            {
              "id": "component:invoicing viewer",
              "keyphrase": "invoicing viewer",
              "type": "component"
            }
          ]
        },
        "similarity": 398.3074532334788
      },
      {
        "metadata": {
          "doc_id": "352",
          "name": "Cross-Site Request Forgery (CSRF)",
          "source": "sparse",
          "original_content": "The web application does not, or can not, sufficiently verify whether a well-formed, valid, consistent request was intentionally provided by the user who submitted the request.",
          "keyphrase_sources": [
            {
              "id": "rootcause:missing validation on a user controlled key",
              "keyphrase": "missing validation on a user controlled key",
              "type": "rootcause"
            },
            {
              "id": "rootcause:Insecure Direct Object Reference",
              "keyphrase": "Insecure Direct Object Reference",
              "type": "rootcause"
            },
            {
              "id": "vector:missing validation on a user controlled key",
              "keyphrase": "missing validation on a user controlled key",
              "type": "vector"
            },
            {
              "id": "attacker:unauthenticated attackers",
              "keyphrase": "unauthenticated attackers",
              "type": "attacker"
            },
            {
              "id": "product:PeproDev Ultimate Invoice plugin for WordPress",
              "keyphrase": "PeproDev Ultimate Invoice plugin for WordPress",
              "type": "product"
            },
            {
              "id": "version:up to and including 2.0.8",
              "keyphrase": "up to and including 2.0.8",
              "type": "version"
            },
            {
              "id": "component:invoicing viewer",
              "keyphrase": "invoicing viewer",
              "type": "component"
            }
          ]
        },
        "similarity": 386.19569070613363
      },
      {
        "metadata": {
          "doc_id": "306",
          "name": "Missing Authentication for Critical Function",
          "source": "sparse",
          "original_content": "The product does not perform any authentication for functionality that requires a provable user identity or consumes a significant amount of resources.",
          "keyphrase_sources": [
            {
              "id": "rootcause:missing validation on a user controlled key",
              "keyphrase": "missing validation on a user controlled key",
              "type": "rootcause"
            },
            {
              "id": "impact:view invoices for completed orders",
              "keyphrase": "view invoices for completed orders",
              "type": "impact"
            },
            {
              "id": "vector:missing validation on a user controlled key",
              "keyphrase": "missing validation on a user controlled key",
              "type": "vector"
            },
            {
              "id": "attacker:unauthenticated attackers",
              "keyphrase": "unauthenticated attackers",
              "type": "attacker"
            },
            {
              "id": "product:PeproDev Ultimate Invoice plugin for WordPress",
              "keyphrase": "PeproDev Ultimate Invoice plugin for WordPress",
              "type": "product"
            },
            {
              "id": "version:up to and including 2.0.8",
              "keyphrase": "up to and including 2.0.8",
              "type": "version"
            },
            {
              "id": "component:invoicing viewer",
              "keyphrase": "invoicing viewer",
              "type": "component"
            }
          ]
        },
        "similarity": 385.7580149898458
      },
      {
        "metadata": {
          "doc_id": "99",
          "name": "Improper Control of Resource Identifiers ('Resource Injection')",
          "source": "sparse",
          "original_content": "The product receives input from an upstream component, but it does not restrict or incorrectly restricts the input before it is used as an identifier for a resource that may be outside the intended sphere of control.",
          "keyphrase_sources": [
            {
              "id": "rootcause:Insecure Direct Object Reference",
              "keyphrase": "Insecure Direct Object Reference",
              "type": "rootcause"
            }
          ]
        },
        "similarity": 383.9292736769987
      },
      {
        "metadata": {
          "doc_id": "116",
          "name": "Improper Encoding or Escaping of Output",
          "source": "sparse",
          "original_content": "The product prepares a structured message for communication with another component, but encoding or escaping of the data is either missing or done incorrectly. As a result, the intended structure of the message is not preserved.",
          "keyphrase_sources": [
            {
              "id": "rootcause:missing validation on a user controlled key",
              "keyphrase": "missing validation on a user controlled key",
              "type": "rootcause"
            },
            {
              "id": "vector:missing validation on a user controlled key",
              "keyphrase": "missing validation on a user controlled key",
              "type": "vector"
            }
          ]
        },
        "similarity": 381.5266565892334
      },
      {
        "metadata": {
          "doc_id": "425",
          "name": "Direct Request ('Forced Browsing')",
          "source": "sparse",
          "original_content": "The web application does not adequately enforce appropriate authorization on all restricted URLs, scripts, or files.",
          "keyphrase_sources": [
            {
              "id": "rootcause:Insecure Direct Object Reference",
              "keyphrase": "Insecure Direct Object Reference",
              "type": "rootcause"
            },
            {
              "id": "attacker:unauthenticated attackers",
              "keyphrase": "unauthenticated attackers",
              "type": "attacker"
            }
          ]
        },
        "similarity": 347.4763247585028
      },
      {
        "metadata": {
          "doc_id": "502",
          "name": "Deserialization of Untrusted Data",
          "source": "sparse",
          "original_content": "The product deserializes untrusted data without sufficiently ensuring that the resulting data will be valid.",
          "keyphrase_sources": [
            {
              "id": "rootcause:Insecure Direct Object Reference",
              "keyphrase": "Insecure Direct Object Reference",
              "type": "rootcause"
            },
            {
              "id": "version:up to and including 2.0.8",
              "keyphrase": "up to and including 2.0.8",
              "type": "version"
            }
          ]
        },
        "similarity": 333.91936236180516
      },
      {
        "metadata": {
          "doc_id": "790",
          "name": "Improper Filtering of Special Elements",
          "source": "sparse",
          "original_content": "The product receives data from an upstream component, but does not filter or incorrectly filters special elements before sending it to a downstream component.",
          "keyphrase_sources": [
            {
              "id": "product:PeproDev Ultimate Invoice plugin for WordPress",
              "keyphrase": "PeproDev Ultimate Invoice plugin for WordPress",
              "type": "product"
            }
          ]
        },
        "similarity": 128.58803339863027
      },
      {
        "metadata": {
          "doc_id": "863",
          "name": "Incorrect Authorization",
          "source": "sparse",
          "original_content": "The product performs an authorization check when an actor attempts to access a resource or perform an action, but it does not correctly perform the check.",
          "keyphrase_sources": [
            {
              "id": "impact:view invoices for completed orders",
              "keyphrase": "view invoices for completed orders",
              "type": "impact"
            },
            {
              "id": "component:invoicing viewer",
              "keyphrase": "invoicing viewer",
              "type": "component"
            }
          ]
        },
        "similarity": 116.83844177117165
      },
      {
        "metadata": {
          "doc_id": "200",
          "name": "Exposure of Sensitive Information to an Unauthorized Actor",
          "source": "sparse",
          "original_content": "The product exposes sensitive information to an actor that is not explicitly authorized to have access to that information.",
          "keyphrase_sources": [
            {
              "id": "impact:view invoices for completed orders",
              "keyphrase": "view invoices for completed orders",
              "type": "impact"
            }
          ]
        },
        "similarity": 113.3516911650521
      }
    ],
    "enhanced_query": "# Vulnerability Description\n\n    The PeproDev Ultimate Invoice plugin for WordPress is vulnerable to **Insecure Direct Object Reference** in all versions up to, and including, 2.0.8 via the invoicing viewer due to **missing validation on a user controlled key**. This makes it possible for unauthenticated attackers to view invoices for completed orders which can contain PII of users.\n\n    # Keyphrase-Specific CWE Analysis\n    This vulnerability contains multiple keyphrases that may map to different CWEs. \n    Please analyze each keyphrase separately and determine the most appropriate CWE(s) for each.\n\n    ## ROOTCAUSE: 'missing validation on a user controlled key'\n\nRelevant CWEs for this ROOTCAUSE:\n\n### 1. CWE-639: Authorization Bypass Through User-Controlled Key (Score: 456.89)\n\nThe system's authorization functionality does not prevent one user from gaining access to another user's data or record by modifying the key value identifying the data....\n\n### 2. CWE-862: Missing Authorization (Score: 398.31)\n\nThe product does not perform an authorization check when an actor attempts to access a resource or perform an action....\n\n### 3. CWE-352: Cross-Site Request Forgery (CSRF) (Score: 386.20)\n\nThe web application does not, or can not, sufficiently verify whether a well-formed, valid, consistent request was intentionally provided by the user who submitted the request....\n\n### 4. CWE-306: Missing Authentication for Critical Function (Score: 385.76)\n\nThe product does not perform any authentication for functionality that requires a provable user identity or consumes a significant amount of resources....\n\n### 5. CWE-116: Improper Encoding or Escaping of Output (Score: 381.53)\n\nThe product prepares a structured message for communication with another component, but encoding or escaping of the data is either missing or done incorrectly. As a result, the intended structure of the message is not preserved....\n\n## ROOTCAUSE: 'Insecure Direct Object Reference'\n\nRelevant CWEs for this ROOTCAUSE:\n\n### 1. CWE-639: Authorization Bypass Through User-Controlled Key (Score: 456.89)\n\nThe system's authorization functionality does not prevent one user from gaining access to another user's data or record by modifying the key value identifying the data....\n\n### 2. CWE-352: Cross-Site Request Forgery (CSRF) (Score: 386.20)\n\nThe web application does not, or can not, sufficiently verify whether a well-formed, valid, consistent request was intentionally provided by the user who submitted the request....\n\n### 3. CWE-99: Improper Control of Resource Identifiers ('Resource Injection') (Score: 383.93)\n\nThe product receives input from an upstream component, but it does not restrict or incorrectly restricts the input before it is used as an identifier for a resource that may be outside the intended sphere of control....\n\n### 4. CWE-425: Direct Request ('Forced Browsing') (Score: 347.48)\n\nThe web application does not adequately enforce appropriate authorization on all restricted URLs, scripts, or files....\n\n### 5. CWE-502: Deserialization of Untrusted Data (Score: 333.92)\n\nThe product deserializes untrusted data without sufficiently ensuring that the resulting data will be valid....\n\n## IMPACT: 'view invoices for completed orders'\n\nRelevant CWEs for this IMPACT:\n\n### 1. CWE-639: Authorization Bypass Through User-Controlled Key (Score: 456.89)\n\nThe system's authorization functionality does not prevent one user from gaining access to another user's data or record by modifying the key value identifying the data....\n\n### 2. CWE-862: Missing Authorization (Score: 398.31)\n\nThe product does not perform an authorization check when an actor attempts to access a resource or perform an action....\n\n### 3. CWE-306: Missing Authentication for Critical Function (Score: 385.76)\n\nThe product does not perform any authentication for functionality that requires a provable user identity or consumes a significant amount of resources....\n\n### 4. CWE-863: Incorrect Authorization (Score: 116.84)\n\nThe product performs an authorization check when an actor attempts to access a resource or perform an action, but it does not correctly perform the check....\n\n### 5. CWE-200: Exposure of Sensitive Information to an Unauthorized Actor (Score: 113.35)\n\nThe product exposes sensitive information to an actor that is not explicitly authorized to have access to that information....\n\n## VECTOR: 'missing validation on a user controlled key'\n\nRelevant CWEs for this VECTOR:\n\n### 1. CWE-639: Authorization Bypass Through User-Controlled Key (Score: 456.89)\n\nThe system's authorization functionality does not prevent one user from gaining access to another user's data or record by modifying the key value identifying the data....\n\n### 2. CWE-862: Missing Authorization (Score: 398.31)\n\nThe product does not perform an authorization check when an actor attempts to access a resource or perform an action....\n\n### 3. CWE-352: Cross-Site Request Forgery (CSRF) (Score: 386.20)\n\nThe web application does not, or can not, sufficiently verify whether a well-formed, valid, consistent request was intentionally provided by the user who submitted the request....\n\n### 4. CWE-306: Missing Authentication for Critical Function (Score: 385.76)\n\nThe product does not perform any authentication for functionality that requires a provable user identity or consumes a significant amount of resources....\n\n### 5. CWE-116: Improper Encoding or Escaping of Output (Score: 381.53)\n\nThe product prepares a structured message for communication with another component, but encoding or escaping of the data is either missing or done incorrectly. As a result, the intended structure of the message is not preserved....\n\n## ATTACKER: 'unauthenticated attackers'\n\nRelevant CWEs for this ATTACKER:\n\n### 1. CWE-639: Authorization Bypass Through User-Controlled Key (Score: 456.89)\n\nThe system's authorization functionality does not prevent one user from gaining access to another user's data or record by modifying the key value identifying the data....\n\n### 2. CWE-862: Missing Authorization (Score: 398.31)\n\nThe product does not perform an authorization check when an actor attempts to access a resource or perform an action....\n\n### 3. CWE-352: Cross-Site Request Forgery (CSRF) (Score: 386.20)\n\nThe web application does not, or can not, sufficiently verify whether a well-formed, valid, consistent request was intentionally provided by the user who submitted the request....\n\n### 4. CWE-306: Missing Authentication for Critical Function (Score: 385.76)\n\nThe product does not perform any authentication for functionality that requires a provable user identity or consumes a significant amount of resources....\n\n### 5. CWE-425: Direct Request ('Forced Browsing') (Score: 347.48)\n\nThe web application does not adequately enforce appropriate authorization on all restricted URLs, scripts, or files....\n\n## PRODUCT: 'PeproDev Ultimate Invoice plugin for WordPress'\n\nRelevant CWEs for this PRODUCT:\n\n### 1. CWE-639: Authorization Bypass Through User-Controlled Key (Score: 456.89)\n\nThe system's authorization functionality does not prevent one user from gaining access to another user's data or record by modifying the key value identifying the data....\n\n### 2. CWE-862: Missing Authorization (Score: 398.31)\n\nThe product does not perform an authorization check when an actor attempts to access a resource or perform an action....\n\n### 3. CWE-352: Cross-Site Request Forgery (CSRF) (Score: 386.20)\n\nThe web application does not, or can not, sufficiently verify whether a well-formed, valid, consistent request was intentionally provided by the user who submitted the request....\n\n### 4. CWE-306: Missing Authentication for Critical Function (Score: 385.76)\n\nThe product does not perform any authentication for functionality that requires a provable user identity or consumes a significant amount of resources....\n\n### 5. CWE-790: Improper Filtering of Special Elements (Score: 128.59)\n\nThe product receives data from an upstream component, but does not filter or incorrectly filters special elements before sending it to a downstream component....\n\n## VERSION: 'up to and including 2.0.8'\n\nRelevant CWEs for this VERSION:\n\n### 1. CWE-639: Authorization Bypass Through User-Controlled Key (Score: 456.89)\n\nThe system's authorization functionality does not prevent one user from gaining access to another user's data or record by modifying the key value identifying the data....\n\n### 2. CWE-862: Missing Authorization (Score: 398.31)\n\nThe product does not perform an authorization check when an actor attempts to access a resource or perform an action....\n\n### 3. CWE-352: Cross-Site Request Forgery (CSRF) (Score: 386.20)\n\nThe web application does not, or can not, sufficiently verify whether a well-formed, valid, consistent request was intentionally provided by the user who submitted the request....\n\n### 4. CWE-306: Missing Authentication for Critical Function (Score: 385.76)\n\nThe product does not perform any authentication for functionality that requires a provable user identity or consumes a significant amount of resources....\n\n### 5. CWE-502: Deserialization of Untrusted Data (Score: 333.92)\n\nThe product deserializes untrusted data without sufficiently ensuring that the resulting data will be valid....\n\n## COMPONENT: 'invoicing viewer'\n\nRelevant CWEs for this COMPONENT:\n\n### 1. CWE-639: Authorization Bypass Through User-Controlled Key (Score: 456.89)\n\nThe system's authorization functionality does not prevent one user from gaining access to another user's data or record by modifying the key value identifying the data....\n\n### 2. CWE-862: Missing Authorization (Score: 398.31)\n\nThe product does not perform an authorization check when an actor attempts to access a resource or perform an action....\n\n### 3. CWE-352: Cross-Site Request Forgery (CSRF) (Score: 386.20)\n\nThe web application does not, or can not, sufficiently verify whether a well-formed, valid, consistent request was intentionally provided by the user who submitted the request....\n\n### 4. CWE-306: Missing Authentication for Critical Function (Score: 385.76)\n\nThe product does not perform any authentication for functionality that requires a provable user identity or consumes a significant amount of resources....\n\n### 5. CWE-863: Incorrect Authorization (Score: 116.84)\n\nThe product performs an authorization check when an actor attempts to access a resource or perform an action, but it does not correctly perform the check....\n\n\n    # Analysis Instructions\n    1. For each keyphrase, identify the most appropriate CWE(s) that represent the weakness.\n    2. Consider how the different keyphrases might relate to each other in the vulnerability chain.\n    3. Provide a final determination of primary CWE(s) and any secondary CWEs.\n    4. Format your response using the standard analysis template.\n\n    Please analyze how these different weaknesses interact and provide a comprehensive CWE classification.\n    "
  },
  "retrieval_time": 2.7522404193878174
}