{
  "cve_id": "CVE-2024-32906",
  "description": "In AcvpOnMessage of avcp.cpp, there is a possible EOP due to **uninitialized data**. This could lead to local escalation of privilege with no additional execution privileges needed. User interaction is not needed for exploitation.",
  "key_phrases": {
    "rootcause": "uninitialized data",
    "weakness": "",
    "impact": "local escalation of privilege",
    "vector": "EOP due to uninitialized data",
    "attacker": "",
    "product": "",
    "version": "",
    "component": "AcvpOnMessage of avcp.cpp"
  },
  "reference_content": "- **Root cause of vulnerability**: The provided document indicates that the vulnerability exists within the 'avcp' subcomponent.\n- **Weaknesses/vulnerabilities present**: The vulnerability is classified as an Elevation of Privilege (EoP).\n-  **Impact of exploitation**: Successful exploitation of the vulnerability could allow an attacker to gain elevated privileges.\n- **Attack vectors**: The document does not specify the attack vector, but the 'avcp' subcomponent suggests that the vulnerability may exist in the audio/video codec processing.\n- **Required attacker capabilities/position**: The document does not specify the required attacker capabilities or position, only that the exploitation results in EoP.",
  "similar_info": {
    "cwe_distribution": {},
    "cwe_consensus": "",
    "similarity_stats": {
      "thresholds": [],
      "total_samples_by_threshold": {},
      "top_cwes_by_threshold": {}
    }
  },
  "similarity_summary": {
    "consensus_cwe": "",
    "top_cwes": [],
    "confidence_levels": {},
    "total_samples": 0
  },
  "analysis": "# Summary\n| CWE ID | CWE Name | Confidence | CWE Abstraction Level | CWE Vulnerability Mapping Label | CWE-Vulnerability Mapping Notes |\n|---|---|---|---|---|---|\n| CWE-908 | Use of Uninitialized Resource | 0.9 | Base | Primary | Allowed |\n| CWE-250 | Execution with Unnecessary Privileges | 0.5 | Base | Secondary | Allowed |\n\n## Evidence and Confidence\n\n*   **Confidence Score:** 0.7\n*   **Evidence Strength:** MEDIUM\n\n## Relationship Analysis\nThe primary relationship that influenced the decision was the hierarchical relationship between CWE-665 (Improper Initialization) and its child CWE-908 (Use of Uninitialized Resource) and CWE-909 (Missing Initialization of Resource). Since the vulnerability description specifically mentions the \"use\" of **uninitialized data**, CWE-908 was chosen over the more general CWE-665 and the more specific CWE-909. Also considered and included was CWE-250 (Execution with Unnecessary Privileges) due to the \"escalation of privilege\" impact, although this is a weaker association and therefore a secondary candidate.\n\n```mermaid\ngraph TD\n    cwe908[\"CWE-908: Use of Uninitialized Resource\"]\n    cwe665[\"CWE-665: Improper Initialization\"]\n    cwe250[\"CWE-250: Execution with Unnecessary Privileges\"]\n    \n    cwe908 -->|CHILDOF| cwe665\n    cwe250 -->|CHILDOF| cwe665\n    \n    classDef primary fill:#f96,stroke:#333,stroke-width:2px\n    classDef secondary fill:#69f,stroke:#333\n    class cwe908 primary\n    class cwe250 secondary\n```\n\n## Vulnerability Chain\nThe vulnerability chain starts with the **uninitialized data** (CWE-908), which leads to a possible Elevation of Privilege (EOP). Because the vulnerable component is running with privileges to escalate privileges, CWE-250 (Execution with Unnecessary Privileges) is added to the chain.\n  - CWE-908 (Use of Uninitialized Resource) - Root Cause\n  - CWE-250 (Execution with Unnecessary Privileges) - Vulnerable component is running with privileges that can be exploited.\n  - Elevation of Privilege (EOP) - Impact\n\n## Summary of Analysis\nThe primary CWE was chosen based on the clear indication of **uninitialized data** being used, as stated in the vulnerability description: \"In AcvpOnMessage of avcp.cpp, there is a possible EOP due to **uninitialized data**.\" This directly aligns with CWE-908 (Use of Uninitialized Resource). The \"escalation of privilege\" impact suggested a secondary weakness related to privilege management, leading to the consideration of CWE-250 (Execution with Unnecessary Privileges).\n\nThe evidence supports CWE-908 as the primary weakness because it is explicitly mentioned in the vulnerability description. The relationship analysis confirms that CWE-908 is a more specific child of CWE-665, making it a more precise fit. The \"escalation of privilege\" impact also suggests a secondary weakness, CWE-250, because the vulnerable component must have sufficient privileges to permit privilege escalation, although there is no hard evidence to support that claim.\n\nThe chosen CWEs are at the optimal level of specificity, with CWE-908 being a Base-level CWE that accurately represents the **uninitialized data** issue.\n\n# Relevant CWE Information:\n\n## Vulnerability Description\nIn AcvpOnMessage of avcp.cpp, there is a possible EOP due to **uninitialized data**. This could lead to local escalation of privilege with no additional execution privileges needed. User interaction is not needed for exploitation.\n\n### Vulnerability Description Key Phrases\n- **rootcause:** **uninitialized data**\n- **impact:** local escalation of privilege\n- **vector:** EOP due to uninitialized data\n- **component:** AcvpOnMessage of avcp.cpp\n\n## CVE Reference Links Content Summary\n- **Root cause of vulnerability**: The provided document indicates that the vulnerability exists within the 'avcp' subcomponent.\n- **Weaknesses/vulnerabilities present**: The vulnerability is classified as an Elevation of Privilege (EoP).\n-  **Impact of exploitation**: Successful exploitation of the vulnerability could allow an attacker to gain elevated privileges.\n- **Attack vectors**: The document does not specify the attack vector, but the 'avcp' subcomponent suggests that the vulnerability may exist in the audio/video codec processing.\n- **Required attacker capabilities/position**: The document does not specify the required attacker capabilities or position, only that the exploitation results in EoP.\n\n## Retriever Results\n\n### Top Combined Results\n\n| Rank | CWE ID | Name | Abstraction | Usage  | Retrievers | Individual Scores |\n|------|--------|------|-------------|-------|------------|-------------------|\n| 1 | 908 | Use of Uninitialized Resource | Base | Allowed | sparse | 0.314 |\n| 2 | 665 | Improper Initialization | Class | Discouraged | sparse | 0.274 |\n| 3 | 1021 | Improper Restriction of Rendered UI Layers or Frames | Base | Allowed | sparse | 0.263 |\n| 4 | 667 | Improper Locking | Class | Allowed-with-Review | sparse | 0.260 |\n| 5 | 862 | Missing Authorization | Class | Allowed-with-Review | sparse | 0.260 |\n| 6 | 362 | Concurrent Execution using Shared Resource with Improper Synchronization ('Race Condition') | Class | Allowed-with-Review | sparse | 0.256 |\n| 7 | 909 | Missing Initialization of Resource | Class | Allowed-with-Review | sparse | 0.255 |\n| 8 | 131 | Incorrect Calculation of Buffer Size | Base | Allowed | sparse | 0.249 |\n| 9 | 1421 | Exposure of Sensitive Information in Shared Microarchitectural Structures during Transient Execution | Base | Allowed | dense | 0.514 |\n| 10 | 1422 | Exposure of Sensitive Information caused by Incorrect Data Forwarding during Transient Execution | Base | Allowed | graph | 0.002 |\n\n### CWE Analysis and Selection\n\n1.  **CWE-908: Use of Uninitialized Resource**\n    *   **Explanation:** This CWE is a direct match for the vulnerability description, which states that there is a possible EOP due to **uninitialized data**. The product uses data that has not been properly initialized, leading to a vulnerability.\n    *   **Security Implications:** Using **uninitialized data** can lead to unpredictable behavior, information leakage, or, as in this case, elevation of privilege.\n    *   **Relationships:** Child of CWE-665 (Improper Initialization).\n    *   **Mapping Guidance:** Usage is ALLOWED.\n    *   **Confidence:** 0.9\n\n2.  **CWE-250: Execution with Unnecessary Privileges**\n    *   **Explanation:** The vulnerability leads to a local escalation of privilege with no additional execution privileges needed. This suggests that the vulnerable component is already running with elevated privileges that it does not need, which allows an attacker to escalate privileges further.\n    *   **Security Implications:** Running code with unnecessary privileges increases the potential impact of a vulnerability, as an attacker can leverage those privileges to perform unauthorized actions.\n    *   **Relationships:** Child of CWE-269 (Improper Privilege Management).\n    *   **Mapping Guidance:** Usage is ALLOWED.\n    *   **Confidence:** 0.5\n\n### Rejected CWEs\n\n*   **CWE-665: Improper Initialization:** While related, CWE-908 is a more specific description of the actual problem, which is the *use* of the uninitialized resource, not just the lack of initialization.\n*   **CWE-1021: Improper Restriction of Rendered UI Layers or Frames:** This CWE is not relevant as the vulnerability does not involve UI layers or frames.\n*   **CWE-667: Improper Locking:** This CWE is not relevant as the vulnerability does not involve concurrent execution or locking issues.\n*   **CWE-862: Missing Authorization:** This CWE is not relevant as the vulnerability does not involve missing authorization checks.\n*   **CWE-362: Concurrent Execution using Shared Resource with Improper Synchronization ('Race Condition'):** This CWE is not relevant as the vulnerability does not involve concurrent execution or race conditions.\n*   **CWE-909: Missing Initialization of Resource:** While related to initialization, CWE-908 is a better fit because it highlights the *use* of the uninitialized data, which is the direct cause of the vulnerability.\n*   **CWE-131: Incorrect Calculation of Buffer Size:** This CWE is not relevant as the vulnerability does not involve buffer size calculations.\n*   **CWE-1421: Exposure of Sensitive Information in Shared Microarchitectural Structures during Transient Execution:** This CWE is not relevant as there is no evidence of microarchitectural structures or transient execution being involved in the vulnerability.\n*   **CWE",
  "analysis_with_relationships": "# Summary\n| CWE ID | CWE Name | Confidence | CWE Abstraction Level | CWE Vulnerability Mapping Label | CWE-Vulnerability Mapping Notes |\n|---|---|---|---|---|---|\n| CWE-908 | Use of Uninitialized Resource | 0.9 | Base | Primary | Allowed |\n| CWE-250 | Execution with Unnecessary Privileges | 0.5 | Base | Secondary | Allowed |\n\n## Evidence and Confidence\n\n*   **Confidence Score:** 0.7\n*   **Evidence Strength:** MEDIUM\n\n## Relationship Analysis\nThe primary relationship that influenced the decision was the hierarchical relationship between CWE-665 (Improper Initialization) and its child CWE-908 (Use of Uninitialized Resource) and CWE-909 (Missing Initialization of Resource). Since the vulnerability description specifically mentions the \"use\" of **uninitialized data**, CWE-908 was chosen over the more general CWE-665 and the more specific CWE-909. Also considered and included was CWE-250 (Execution with Unnecessary Privileges) due to the \"escalation of privilege\" impact, although this is a weaker association and therefore a secondary candidate.\n\n```mermaid\ngraph TD\n    cwe908[\"CWE-908: Use of Uninitialized Resource\"]\n    cwe665[\"CWE-665: Improper Initialization\"]\n    cwe250[\"CWE-250: Execution with Unnecessary Privileges\"]\n    \n    cwe908 -->|CHILDOF| cwe665\n    cwe250 -->|CHILDOF| cwe665\n    \n    classDef primary fill:#f96,stroke:#333,stroke-width:2px\n    classDef secondary fill:#69f,stroke:#333\n    class cwe908 primary\n    class cwe250 secondary\n```\n\n## Vulnerability Chain\nThe vulnerability chain starts with the **uninitialized data** (CWE-908), which leads to a possible Elevation of Privilege (EOP). Because the vulnerable component is running with privileges to escalate privileges, CWE-250 (Execution with Unnecessary Privileges) is added to the chain.\n  - CWE-908 (Use of Uninitialized Resource) - Root Cause\n  - CWE-250 (Execution with Unnecessary Privileges) - Vulnerable component is running with privileges that can be exploited.\n  - Elevation of Privilege (EOP) - Impact\n\n## Summary of Analysis\nThe primary CWE was chosen based on the clear indication of **uninitialized data** being used, as stated in the vulnerability description: \"In AcvpOnMessage of avcp.cpp, there is a possible EOP due to **uninitialized data**.\" This directly aligns with CWE-908 (Use of Uninitialized Resource). The \"escalation of privilege\" impact suggested a secondary weakness related to privilege management, leading to the consideration of CWE-250 (Execution with Unnecessary Privileges).\n\nThe evidence supports CWE-908 as the primary weakness because it is explicitly mentioned in the vulnerability description. The relationship analysis confirms that CWE-908 is a more specific child of CWE-665, making it a more precise fit. The \"escalation of privilege\" impact also suggests a secondary weakness, CWE-250, because the vulnerable component must have sufficient privileges to permit privilege escalation, although there is no hard evidence to support that claim.\n\nThe chosen CWEs are at the optimal level of specificity, with CWE-908 being a Base-level CWE that accurately represents the **uninitialized data** issue.\n\n# Relevant CWE Information:\n\n## Vulnerability Description\nIn AcvpOnMessage of avcp.cpp, there is a possible EOP due to **uninitialized data**. This could lead to local escalation of privilege with no additional execution privileges needed. User interaction is not needed for exploitation.\n\n### Vulnerability Description Key Phrases\n- **rootcause:** **uninitialized data**\n- **impact:** local escalation of privilege\n- **vector:** EOP due to uninitialized data\n- **component:** AcvpOnMessage of avcp.cpp\n\n## CVE Reference Links Content Summary\n- **Root cause of vulnerability**: The provided document indicates that the vulnerability exists within the 'avcp' subcomponent.\n- **Weaknesses/vulnerabilities present**: The vulnerability is classified as an Elevation of Privilege (EoP).\n-  **Impact of exploitation**: Successful exploitation of the vulnerability could allow an attacker to gain elevated privileges.\n- **Attack vectors**: The document does not specify the attack vector, but the 'avcp' subcomponent suggests that the vulnerability may exist in the audio/video codec processing.\n- **Required attacker capabilities/position**: The document does not specify the required attacker capabilities or position, only that the exploitation results in EoP.\n\n## Retriever Results\n\n### Top Combined Results\n\n| Rank | CWE ID | Name | Abstraction | Usage  | Retrievers | Individual Scores |\n|------|--------|------|-------------|-------|------------|-------------------|\n| 1 | 908 | Use of Uninitialized Resource | Base | Allowed | sparse | 0.314 |\n| 2 | 665 | Improper Initialization | Class | Discouraged | sparse | 0.274 |\n| 3 | 1021 | Improper Restriction of Rendered UI Layers or Frames | Base | Allowed | sparse | 0.263 |\n| 4 | 667 | Improper Locking | Class | Allowed-with-Review | sparse | 0.260 |\n| 5 | 862 | Missing Authorization | Class | Allowed-with-Review | sparse | 0.260 |\n| 6 | 362 | Concurrent Execution using Shared Resource with Improper Synchronization ('Race Condition') | Class | Allowed-with-Review | sparse | 0.256 |\n| 7 | 909 | Missing Initialization of Resource | Class | Allowed-with-Review | sparse | 0.255 |\n| 8 | 131 | Incorrect Calculation of Buffer Size | Base | Allowed | sparse | 0.249 |\n| 9 | 1421 | Exposure of Sensitive Information in Shared Microarchitectural Structures during Transient Execution | Base | Allowed | dense | 0.514 |\n| 10 | 1422 | Exposure of Sensitive Information caused by Incorrect Data Forwarding during Transient Execution | Base | Allowed | graph | 0.002 |\n\n### CWE Analysis and Selection\n\n1.  **CWE-908: Use of Uninitialized Resource**\n    *   **Explanation:** This CWE is a direct match for the vulnerability description, which states that there is a possible EOP due to **uninitialized data**. The product uses data that has not been properly initialized, leading to a vulnerability.\n    *   **Security Implications:** Using **uninitialized data** can lead to unpredictable behavior, information leakage, or, as in this case, elevation of privilege.\n    *   **Relationships:** Child of CWE-665 (Improper Initialization).\n    *   **Mapping Guidance:** Usage is ALLOWED.\n    *   **Confidence:** 0.9\n\n2.  **CWE-250: Execution with Unnecessary Privileges**\n    *   **Explanation:** The vulnerability leads to a local escalation of privilege with no additional execution privileges needed. This suggests that the vulnerable component is already running with elevated privileges that it does not need, which allows an attacker to escalate privileges further.\n    *   **Security Implications:** Running code with unnecessary privileges increases the potential impact of a vulnerability, as an attacker can leverage those privileges to perform unauthorized actions.\n    *   **Relationships:** Child of CWE-269 (Improper Privilege Management).\n    *   **Mapping Guidance:** Usage is ALLOWED.\n    *   **Confidence:** 0.5\n\n### Rejected CWEs\n\n*   **CWE-665: Improper Initialization:** While related, CWE-908 is a more specific description of the actual problem, which is the *use* of the uninitialized resource, not just the lack of initialization.\n*   **CWE-1021: Improper Restriction of Rendered UI Layers or Frames:** This CWE is not relevant as the vulnerability does not involve UI layers or frames.\n*   **CWE-667: Improper Locking:** This CWE is not relevant as the vulnerability does not involve concurrent execution or locking issues.\n*   **CWE-862: Missing Authorization:** This CWE is not relevant as the vulnerability does not involve missing authorization checks.\n*   **CWE-362: Concurrent Execution using Shared Resource with Improper Synchronization ('Race Condition'):** This CWE is not relevant as the vulnerability does not involve concurrent execution or race conditions.\n*   **CWE-909: Missing Initialization of Resource:** While related to initialization, CWE-908 is a better fit because it highlights the *use* of the uninitialized data, which is the direct cause of the vulnerability.\n*   **CWE-131: Incorrect Calculation of Buffer Size:** This CWE is not relevant as the vulnerability does not involve buffer size calculations.\n*   **CWE-1421: Exposure of Sensitive Information in Shared Microarchitectural Structures during Transient Execution:** This CWE is not relevant as there is no evidence of microarchitectural structures or transient execution being involved in the vulnerability.\n*   **CWE\n\n\n## CWE Relationship Analysis\n\nCurrent CWEs represent these abstraction levels: .\n\n\n### Vulnerability Chain Analysis\n\n**Chain starting from CWE-1421:**\n- 1421 (Exposure of Sensitive Information in Shared Microarchitectural Structures during Transient Execution) - ROOT\n\n\n**Chain starting from CWE-862:**\n- 862 (Missing Authorization) - ROOT\n\n\n\n### CWE Relationship Diagram\n\n```mermaid\ngraph TD\n    classDef primary fill:#f96,stroke:#333,stroke-width:2px\n    classDef secondary fill:#69f,stroke:#333\n    classDef tertiary fill:#9e9,stroke:#333\n```",
  "criticism": "",
  "resolution": "",
  "relevant_cwes": [
    {
      "metadata": {
        "doc_id": "908",
        "name": "Use of Uninitialized Resource",
        "source": "sparse"
      },
      "similarity": 314.19483304585145
    },
    {
      "metadata": {
        "doc_id": "665",
        "name": "Improper Initialization",
        "source": "sparse"
      },
      "similarity": 274.39770869674743
    },
    {
      "metadata": {
        "doc_id": "1021",
        "name": "Improper Restriction of Rendered UI Layers or Frames",
        "source": "sparse"
      },
      "similarity": 262.7564290201226
    },
    {
      "metadata": {
        "doc_id": "667",
        "name": "Improper Locking",
        "source": "sparse"
      },
      "similarity": 260.38286228737593
    },
    {
      "metadata": {
        "doc_id": "862",
        "name": "Missing Authorization",
        "source": "sparse"
      },
      "similarity": 259.5222762221732
    },
    {
      "metadata": {
        "doc_id": "362",
        "name": "Concurrent Execution using Shared Resource with Improper Synchronization ('Race Condition')",
        "source": "sparse"
      },
      "similarity": 256.45427440457354
    },
    {
      "metadata": {
        "doc_id": "909",
        "name": "Missing Initialization of Resource",
        "source": "sparse"
      },
      "similarity": 255.23246045627582
    },
    {
      "metadata": {
        "doc_id": "131",
        "name": "Incorrect Calculation of Buffer Size",
        "source": "sparse"
      },
      "similarity": 248.7299240364715
    },
    {
      "metadata": {
        "doc_id": "1421",
        "name": "Exposure of Sensitive Information in Shared Microarchitectural Structures during Transient Execution",
        "type": "Base",
        "original_content": "\n\t\t\tA processor event may allow transient operations to access\n\t\t\tarchitecturally restricted data (for example, in another address\n\t\t\tspace) in a shared microarchitectural structure (for example, a CPU\n\t\t\tcache), potentially exposing the data over a covert channel.\n\t\t  ",
        "keyphrase_source": "rootcause:uninitialized data",
        "source": "dense",
        "mapping_notes": {
          "usage": "Allowed",
          "rationale": "This CWE entry is at the Base level of abstraction, which is a preferred level of abstraction for mapping to the root causes of vulnerabilities",
          "comments": "If a weakness can potentially be exploited to infer data that is accessible inside or outside the current processor context, then the weakness could map to CWE-1421 and to another CWE such as CWE-1420.",
          "reasons": [
            "Acceptable-Use"
          ]
        },
        "score_info": {
          "retrievers": [
            "dense",
            "graph"
          ],
          "retriever_count": 2,
          "normalized_scores": {
            "dense": 0.5135557807715359,
            "graph": 1.4963216214550255
          }
        }
      },
      "similarity": 0.5135557807715359
    },
    {
      "doc_id": "1422",
      "text": "A processor event or prediction may allow incorrect or stale data to\n\t\t  be forwarded to transient operations, potentially exposing data over a\n\t\t  covert channel.",
      "score": 0.5374418288749682,
      "metadata": {
        "doc_id": "1422",
        "name": "Exposure of Sensitive Information caused by Incorrect Data Forwarding during Transient Execution",
        "type": "Base",
        "extended_description": "\n\nSoftware may use a variety of techniques to preserve the confidentiality of private data that is accessible within the current processor context. For example, the memory safety and type safety properties of some high-level programming languages help to prevent software written in those languages from exposing private data. As a second example, software sandboxes may co-locate multiple users' software within a single process. The processor's Instruction Set Architecture (ISA) may permit one user's software to access another user's data (because the software shares the same address space), but the sandbox prevents these accesses by using software techniques such as bounds checking.\n\n\nIf incorrect or stale data can be forwarded (for example, from a cache) to transient operations, then the operations' microarchitectural side effects may correspond to the data. If an attacker can trigger these transient operations and observe their side effects through a covert channel, then the attacker may be able to infer the data. For example, an attacker process may induce transient execution in a victim process that causes the victim to inadvertently access and then expose its private data via a covert channel. In the software sandbox example, an attacker sandbox may induce transient execution in its own code, allowing it to transiently access and expose data in a victim sandbox that shares the same address space.\n\n\nConsequently, weaknesses that arise from incorrect/stale data forwarding might violate users' expectations of software-based memory safety and isolation techniques. If the data forwarding behavior is not properly documented by the hardware vendor, this might violate the software vendor's expectation of how the hardware should behave.\n",
        "alternate_terms": [],
        "original_content": "A processor event or prediction may allow incorrect or stale data to\n\t\t  be forwarded to transient operations, potentially exposing data over a\n\t\t  covert channel.",
        "relationships": [
          {
            "source_id": "1422",
            "target_id": "1420",
            "label": "CHILDOF",
            "properties": {
              "ordinal": "Primary",
              "view_id": "1194"
            }
          },
          {
            "source_id": "1422",
            "target_id": "1420",
            "label": "CHILDOF",
            "properties": {
              "ordinal": "Primary",
              "view_id": "1000"
            }
          },
          {
            "source_id": "1420",
            "target_id": "1422",
            "label": "PARENTOF",
            "properties": {
              "ordinal": "Primary",
              "view_id": "1000"
            }
          }
        ],
        "source": "graph",
        "sources": [
          "vector",
          "graph"
        ],
        "vector_score": 0.5374418288749682,
        "graph_score": 2.3998000000000004,
        "score_components": {
          "relationship_chain": 0.24,
          "explicit_mention": 1.0,
          "abstraction_path": 0.9
        },
        "abstraction_factor": 1.3,
        "graph_path_info": {
          "path_types": [
            "relationship_chain"
          ],
          "best_paths": {
            "relationship_chain": {
              "path": [
                [
                  "1421",
                  "1420",
                  "CHILDOF"
                ],
                [
                  "1420",
                  "1422",
                  "PARENTOF"
                ]
              ],
              "score": 0.24,
              "type": "relationship_chain",
              "source": "1421"
            }
          }
        },
        "is_explicit": true,
        "abstraction_level": "base",
        "mapping_notes": {
          "usage": "Allowed",
          "rationale": "This CWE entry is at the Base level of abstraction, which is a preferred level of abstraction for mapping to the root causes of vulnerabilities",
          "comments": "Use only when the weakness arises from forwarding of incorrect/stale data, and the data is not architecturally restricted (that is, the forwarded data is accessible within the current processor context). \n\nIf a weakness arises from forwarding of incorrect/stale data that is not accessible within the current processor context, then CWE-1421 may be more appropriate for the mapping task.\n",
          "reasons": [
            "Acceptable-Use"
          ]
        },
        "score_info": {
          "retrievers": [
            "dense",
            "graph"
          ],
          "retriever_count": 2,
          "normalized_scores": {
            "dense": 0.4983777720606507,
            "graph": 1.6548567315499876
          }
        }
      },
      "similarity": 1.6548567315499876
    }
  ],
  "identified_cwes": {
    "analyzer": [
      "CWE-1421",
      "CWE-862",
      "CWE-131",
      "CWE-667",
      "CWE-1021",
      "CWE-909",
      "CWE-269",
      "CWE-362",
      "CWE-250",
      "CWE-908",
      "CWE-665"
    ],
    "critic_additional": []
  },
  "keyphrase_cwe_mapping": {}
}