{
  "vulnerability_info": "VulnerabilityInfo(cve_id='CVE-2025-23146', description='In the Linux kernel, the following vulnerability has been resolved mfd ene-kb3930 Fix a **potential NULL pointer dereference** The off_gpios could be NULL. Add **missing check** in the kb3930_probe(). This is similar to the issue fixed in commit b1ba8bcb2d1f (backlight hx8357 Fix **potential NULL pointer dereference**). This was detected by our static analysis tool.', key_phrases={'rootcause': ['potential NULL pointer dereference', 'missing check'], 'weakness': '', 'impact': '', 'vector': '', 'attacker': '', 'product': 'Linux kernel', 'version': '', 'component': 'mfd ene-kb3930'}, reference_content='UNRELATED', similar_info={'cwe_distribution': {}, 'cwe_consensus': '', 'similarity_stats': {'thresholds': [], 'total_samples_by_threshold': {}, 'top_cwes_by_threshold': {}}}, similarity_summary=SimilarityInsight(consensus_cwe='', top_cwes=[], confidence_levels={}, total_samples=0), analysis='', analysis_with_relationships='', criticism='', resolution='', relevant_cwes=[{'metadata': {'doc_id': '476', 'name': 'NULL Pointer Dereference', 'source': 'sparse', 'original_content': 'The product dereferences a pointer that it expects to be valid but is NULL.', 'keyphrase_sources': [{'id': 'rootcause:potential NULL pointer dereference', 'keyphrase': 'potential NULL pointer dereference', 'type': 'rootcause'}, {'id': 'rootcause:missing check', 'keyphrase': 'missing check', 'type': 'rootcause'}, {'id': 'product:Linux kernel', 'keyphrase': 'Linux kernel', 'type': 'product'}, {'id': 'component:mfd ene-kb3930', 'keyphrase': 'mfd ene-kb3930', 'type': 'component'}]}, 'similarity': np.float64(486.23655457920836)}, {'metadata': {'doc_id': '252', 'name': 'Unchecked Return Value', 'source': 'sparse', 'original_content': 'The product does not check the return value from a method or function, which can prevent it from detecting unexpected states and conditions.', 'keyphrase_sources': [{'id': 'rootcause:potential NULL pointer dereference', 'keyphrase': 'potential NULL pointer dereference', 'type': 'rootcause'}, {'id': 'rootcause:missing check', 'keyphrase': 'missing check', 'type': 'rootcause'}, {'id': 'product:Linux kernel', 'keyphrase': 'Linux kernel', 'type': 'product'}, {'id': 'component:mfd ene-kb3930', 'keyphrase': 'mfd ene-kb3930', 'type': 'component'}]}, 'similarity': np.float64(424.2711217572761)}, {'metadata': {'doc_id': '824', 'name': 'Access of Uninitialized Pointer', 'source': 'sparse', 'original_content': 'The product accesses or uses a pointer that has not been initialized.', 'keyphrase_sources': [{'id': 'rootcause:potential NULL pointer dereference', 'keyphrase': 'potential NULL pointer dereference', 'type': 'rootcause'}, {'id': 'rootcause:missing check', 'keyphrase': 'missing check', 'type': 'rootcause'}, {'id': 'component:mfd ene-kb3930', 'keyphrase': 'mfd ene-kb3930', 'type': 'component'}]}, 'similarity': np.float64(387.61894537693996)}, {'metadata': {'doc_id': '665', 'name': 'Improper Initialization', 'source': 'sparse', 'original_content': 'The product does not initialize or incorrectly initializes a resource, which might leave the resource in an unexpected state when it is accessed or used.', 'keyphrase_sources': [{'id': 'rootcause:potential NULL pointer dereference', 'keyphrase': 'potential NULL pointer dereference', 'type': 'rootcause'}, {'id': 'component:mfd ene-kb3930', 'keyphrase': 'mfd ene-kb3930', 'type': 'component'}]}, 'similarity': np.float64(383.3437601584467)}, {'metadata': {'doc_id': '690', 'name': 'Unchecked Return Value to NULL Pointer Dereference', 'source': 'sparse', 'original_content': 'The product does not check for an error after calling a function that can return with a NULL pointer if the function fails, which leads to a resultant NULL pointer dereference.', 'keyphrase_sources': [{'id': 'rootcause:potential NULL pointer dereference', 'keyphrase': 'potential NULL pointer dereference', 'type': 'rootcause'}, {'id': 'rootcause:missing check', 'keyphrase': 'missing check', 'type': 'rootcause'}]}, 'similarity': np.float64(382.68825692525166)}, {'metadata': {'doc_id': '362', 'name': \"Concurrent Execution using Shared Resource with Improper Synchronization ('Race Condition')\", 'source': 'sparse', 'original_content': 'The product contains a concurrent code sequence that requires temporary, exclusive access to a shared resource, but a timing window exists in which the shared resource can be modified by another code sequence operating concurrently.', 'keyphrase_sources': [{'id': 'rootcause:missing check', 'keyphrase': 'missing check', 'type': 'rootcause'}, {'id': 'product:Linux kernel', 'keyphrase': 'Linux kernel', 'type': 'product'}]}, 'similarity': np.float64(300.3233090220647)}, {'metadata': {'doc_id': '822', 'name': 'Untrusted Pointer Dereference', 'source': 'sparse', 'original_content': 'The product obtains a value from an untrusted source, converts this value to a pointer, and dereferences the resulting pointer.', 'keyphrase_sources': [{'id': 'product:Linux kernel', 'keyphrase': 'Linux kernel', 'type': 'product'}, {'id': 'component:mfd ene-kb3930', 'keyphrase': 'mfd ene-kb3930', 'type': 'component'}]}, 'similarity': np.float64(108.91948544398043)}, {'metadata': {'doc_id': '909', 'name': 'Missing Initialization of Resource', 'source': 'sparse', 'original_content': 'The product does not initialize a critical resource.', 'keyphrase_sources': [{'id': 'product:Linux kernel', 'keyphrase': 'Linux kernel', 'type': 'product'}]}, 'similarity': np.float64(105.425383623435)}], identified_cwes={'analyzer': [], 'critic_additional': []})",
  "retrieval_results": {
    "has_multiple_keyphrases": true,
    "keyphrase_cwe_sets": {
      "rootcause:potential NULL pointer dereference": {
        "keyphrase": "potential NULL pointer dereference",
        "type": "rootcause",
        "cwes": [
          {
            "metadata": {
              "doc_id": "476",
              "name": "NULL Pointer Dereference",
              "source": "sparse",
              "original_content": "The product dereferences a pointer that it expects to be valid but is NULL.",
              "keyphrase_sources": [
                {
                  "id": "rootcause:potential NULL pointer dereference",
                  "keyphrase": "potential NULL pointer dereference",
                  "type": "rootcause"
                },
                {
                  "id": "rootcause:missing check",
                  "keyphrase": "missing check",
                  "type": "rootcause"
                },
                {
                  "id": "product:Linux kernel",
                  "keyphrase": "Linux kernel",
                  "type": "product"
                },
                {
                  "id": "component:mfd ene-kb3930",
                  "keyphrase": "mfd ene-kb3930",
                  "type": "component"
                }
              ]
            },
            "similarity": 486.23655457920836
          },
          {
            "metadata": {
              "doc_id": "252",
              "name": "Unchecked Return Value",
              "source": "sparse",
              "original_content": "The product does not check the return value from a method or function, which can prevent it from detecting unexpected states and conditions.",
              "keyphrase_sources": [
                {
                  "id": "rootcause:potential NULL pointer dereference",
                  "keyphrase": "potential NULL pointer dereference",
                  "type": "rootcause"
                },
                {
                  "id": "rootcause:missing check",
                  "keyphrase": "missing check",
                  "type": "rootcause"
                },
                {
                  "id": "product:Linux kernel",
                  "keyphrase": "Linux kernel",
                  "type": "product"
                },
                {
                  "id": "component:mfd ene-kb3930",
                  "keyphrase": "mfd ene-kb3930",
                  "type": "component"
                }
              ]
            },
            "similarity": 424.2711217572761
          },
          {
            "metadata": {
              "doc_id": "824",
              "name": "Access of Uninitialized Pointer",
              "source": "sparse",
              "original_content": "The product accesses or uses a pointer that has not been initialized.",
              "keyphrase_sources": [
                {
                  "id": "rootcause:potential NULL pointer dereference",
                  "keyphrase": "potential NULL pointer dereference",
                  "type": "rootcause"
                },
                {
                  "id": "rootcause:missing check",
                  "keyphrase": "missing check",
                  "type": "rootcause"
                },
                {
                  "id": "component:mfd ene-kb3930",
                  "keyphrase": "mfd ene-kb3930",
                  "type": "component"
                }
              ]
            },
            "similarity": 387.61894537693996
          },
          {
            "metadata": {
              "doc_id": "665",
              "name": "Improper Initialization",
              "source": "sparse",
              "original_content": "The product does not initialize or incorrectly initializes a resource, which might leave the resource in an unexpected state when it is accessed or used.",
              "keyphrase_sources": [
                {
                  "id": "rootcause:potential NULL pointer dereference",
                  "keyphrase": "potential NULL pointer dereference",
                  "type": "rootcause"
                },
                {
                  "id": "component:mfd ene-kb3930",
                  "keyphrase": "mfd ene-kb3930",
                  "type": "component"
                }
              ]
            },
            "similarity": 383.3437601584467
          },
          {
            "metadata": {
              "doc_id": "690",
              "name": "Unchecked Return Value to NULL Pointer Dereference",
              "source": "sparse",
              "original_content": "The product does not check for an error after calling a function that can return with a NULL pointer if the function fails, which leads to a resultant NULL pointer dereference.",
              "keyphrase_sources": [
                {
                  "id": "rootcause:potential NULL pointer dereference",
                  "keyphrase": "potential NULL pointer dereference",
                  "type": "rootcause"
                },
                {
                  "id": "rootcause:missing check",
                  "keyphrase": "missing check",
                  "type": "rootcause"
                }
              ]
            },
            "similarity": 382.68825692525166
          }
        ]
      },
      "rootcause:missing check": {
        "keyphrase": "missing check",
        "type": "rootcause",
        "cwes": [
          {
            "metadata": {
              "doc_id": "476",
              "name": "NULL Pointer Dereference",
              "source": "sparse",
              "original_content": "The product dereferences a pointer that it expects to be valid but is NULL."
            },
            "similarity": 387.60809861877055
          },
          {
            "metadata": {
              "doc_id": "252",
              "name": "Unchecked Return Value",
              "source": "sparse",
              "original_content": "The product does not check the return value from a method or function, which can prevent it from detecting unexpected states and conditions."
            },
            "similarity": 354.9091635669636
          },
          {
            "metadata": {
              "doc_id": "824",
              "name": "Access of Uninitialized Pointer",
              "source": "sparse",
              "original_content": "The product accesses or uses a pointer that has not been initialized."
            },
            "similarity": 331.8391320791916
          },
          {
            "metadata": {
              "doc_id": "690",
              "name": "Unchecked Return Value to NULL Pointer Dereference",
              "source": "sparse",
              "original_content": "The product does not check for an error after calling a function that can return with a NULL pointer if the function fails, which leads to a resultant NULL pointer dereference."
            },
            "similarity": 301.2139521517091
          },
          {
            "metadata": {
              "doc_id": "362",
              "name": "Concurrent Execution using Shared Resource with Improper Synchronization ('Race Condition')",
              "source": "sparse",
              "original_content": "The product contains a concurrent code sequence that requires temporary, exclusive access to a shared resource, but a timing window exists in which the shared resource can be modified by another code sequence operating concurrently.",
              "keyphrase_sources": [
                {
                  "id": "rootcause:missing check",
                  "keyphrase": "missing check",
                  "type": "rootcause"
                },
                {
                  "id": "product:Linux kernel",
                  "keyphrase": "Linux kernel",
                  "type": "product"
                }
              ]
            },
            "similarity": 300.3233090220647
          }
        ]
      },
      "product:Linux kernel": {
        "keyphrase": "Linux kernel",
        "type": "product",
        "cwes": [
          {
            "metadata": {
              "doc_id": "476",
              "name": "NULL Pointer Dereference",
              "source": "sparse",
              "original_content": "The product dereferences a pointer that it expects to be valid but is NULL."
            },
            "similarity": 130.02940670616488
          },
          {
            "metadata": {
              "doc_id": "252",
              "name": "Unchecked Return Value",
              "source": "sparse",
              "original_content": "The product does not check the return value from a method or function, which can prevent it from detecting unexpected states and conditions."
            },
            "similarity": 114.1556134261953
          },
          {
            "metadata": {
              "doc_id": "362",
              "name": "Concurrent Execution using Shared Resource with Improper Synchronization ('Race Condition')",
              "source": "sparse",
              "original_content": "The product contains a concurrent code sequence that requires temporary, exclusive access to a shared resource, but a timing window exists in which the shared resource can be modified by another code sequence operating concurrently."
            },
            "similarity": 110.22449510855861
          },
          {
            "metadata": {
              "doc_id": "822",
              "name": "Untrusted Pointer Dereference",
              "source": "sparse",
              "original_content": "The product obtains a value from an untrusted source, converts this value to a pointer, and dereferences the resulting pointer.",
              "keyphrase_sources": [
                {
                  "id": "product:Linux kernel",
                  "keyphrase": "Linux kernel",
                  "type": "product"
                },
                {
                  "id": "component:mfd ene-kb3930",
                  "keyphrase": "mfd ene-kb3930",
                  "type": "component"
                }
              ]
            },
            "similarity": 108.91948544398043
          },
          {
            "metadata": {
              "doc_id": "909",
              "name": "Missing Initialization of Resource",
              "source": "sparse",
              "original_content": "The product does not initialize a critical resource.",
              "keyphrase_sources": [
                {
                  "id": "product:Linux kernel",
                  "keyphrase": "Linux kernel",
                  "type": "product"
                }
              ]
            },
            "similarity": 105.425383623435
          }
        ]
      },
      "component:mfd ene-kb3930": {
        "keyphrase": "mfd ene-kb3930",
        "type": "component",
        "cwes": [
          {
            "metadata": {
              "doc_id": "476",
              "name": "NULL Pointer Dereference",
              "source": "sparse",
              "original_content": "The product dereferences a pointer that it expects to be valid but is NULL."
            },
            "similarity": 120.11075156734174
          },
          {
            "metadata": {
              "doc_id": "252",
              "name": "Unchecked Return Value",
              "source": "sparse",
              "original_content": "The product does not check the return value from a method or function, which can prevent it from detecting unexpected states and conditions."
            },
            "similarity": 108.97191297745987
          },
          {
            "metadata": {
              "doc_id": "824",
              "name": "Access of Uninitialized Pointer",
              "source": "sparse",
              "original_content": "The product accesses or uses a pointer that has not been initialized."
            },
            "similarity": 102.25096462773077
          },
          {
            "metadata": {
              "doc_id": "665",
              "name": "Improper Initialization",
              "source": "sparse",
              "original_content": "The product does not initialize or incorrectly initializes a resource, which might leave the resource in an unexpected state when it is accessed or used."
            },
            "similarity": 96.97862394311164
          },
          {
            "metadata": {
              "doc_id": "822",
              "name": "Untrusted Pointer Dereference",
              "source": "sparse",
              "original_content": "The product obtains a value from an untrusted source, converts this value to a pointer, and dereferences the resulting pointer."
            },
            "similarity": 95.78719684493846
          }
        ]
      }
    },
    "keyphrase_mapping": {
      "476": [
        {
          "id": "rootcause:potential NULL pointer dereference",
          "keyphrase": "potential NULL pointer dereference",
          "type": "rootcause"
        },
        {
          "id": "rootcause:missing check",
          "keyphrase": "missing check",
          "type": "rootcause"
        },
        {
          "id": "product:Linux kernel",
          "keyphrase": "Linux kernel",
          "type": "product"
        },
        {
          "id": "component:mfd ene-kb3930",
          "keyphrase": "mfd ene-kb3930",
          "type": "component"
        }
      ],
      "252": [
        {
          "id": "rootcause:potential NULL pointer dereference",
          "keyphrase": "potential NULL pointer dereference",
          "type": "rootcause"
        },
        {
          "id": "rootcause:missing check",
          "keyphrase": "missing check",
          "type": "rootcause"
        },
        {
          "id": "product:Linux kernel",
          "keyphrase": "Linux kernel",
          "type": "product"
        },
        {
          "id": "component:mfd ene-kb3930",
          "keyphrase": "mfd ene-kb3930",
          "type": "component"
        }
      ],
      "824": [
        {
          "id": "rootcause:potential NULL pointer dereference",
          "keyphrase": "potential NULL pointer dereference",
          "type": "rootcause"
        },
        {
          "id": "rootcause:missing check",
          "keyphrase": "missing check",
          "type": "rootcause"
        },
        {
          "id": "component:mfd ene-kb3930",
          "keyphrase": "mfd ene-kb3930",
          "type": "component"
        }
      ],
      "665": [
        {
          "id": "rootcause:potential NULL pointer dereference",
          "keyphrase": "potential NULL pointer dereference",
          "type": "rootcause"
        },
        {
          "id": "component:mfd ene-kb3930",
          "keyphrase": "mfd ene-kb3930",
          "type": "component"
        }
      ],
      "690": [
        {
          "id": "rootcause:potential NULL pointer dereference",
          "keyphrase": "potential NULL pointer dereference",
          "type": "rootcause"
        },
        {
          "id": "rootcause:missing check",
          "keyphrase": "missing check",
          "type": "rootcause"
        }
      ],
      "362": [
        {
          "id": "rootcause:missing check",
          "keyphrase": "missing check",
          "type": "rootcause"
        },
        {
          "id": "product:Linux kernel",
          "keyphrase": "Linux kernel",
          "type": "product"
        }
      ],
      "822": [
        {
          "id": "product:Linux kernel",
          "keyphrase": "Linux kernel",
          "type": "product"
        },
        {
          "id": "component:mfd ene-kb3930",
          "keyphrase": "mfd ene-kb3930",
          "type": "component"
        }
      ],
      "909": [
        {
          "id": "product:Linux kernel",
          "keyphrase": "Linux kernel",
          "type": "product"
        }
      ]
    },
    "relevant_cwes": [
      {
        "metadata": {
          "doc_id": "476",
          "name": "NULL Pointer Dereference",
          "source": "sparse",
          "original_content": "The product dereferences a pointer that it expects to be valid but is NULL.",
          "keyphrase_sources": [
            {
              "id": "rootcause:potential NULL pointer dereference",
              "keyphrase": "potential NULL pointer dereference",
              "type": "rootcause"
            },
            {
              "id": "rootcause:missing check",
              "keyphrase": "missing check",
              "type": "rootcause"
            },
            {
              "id": "product:Linux kernel",
              "keyphrase": "Linux kernel",
              "type": "product"
            },
            {
              "id": "component:mfd ene-kb3930",
              "keyphrase": "mfd ene-kb3930",
              "type": "component"
            }
          ]
        },
        "similarity": 486.23655457920836
      },
      {
        "metadata": {
          "doc_id": "252",
          "name": "Unchecked Return Value",
          "source": "sparse",
          "original_content": "The product does not check the return value from a method or function, which can prevent it from detecting unexpected states and conditions.",
          "keyphrase_sources": [
            {
              "id": "rootcause:potential NULL pointer dereference",
              "keyphrase": "potential NULL pointer dereference",
              "type": "rootcause"
            },
            {
              "id": "rootcause:missing check",
              "keyphrase": "missing check",
              "type": "rootcause"
            },
            {
              "id": "product:Linux kernel",
              "keyphrase": "Linux kernel",
              "type": "product"
            },
            {
              "id": "component:mfd ene-kb3930",
              "keyphrase": "mfd ene-kb3930",
              "type": "component"
            }
          ]
        },
        "similarity": 424.2711217572761
      },
      {
        "metadata": {
          "doc_id": "824",
          "name": "Access of Uninitialized Pointer",
          "source": "sparse",
          "original_content": "The product accesses or uses a pointer that has not been initialized.",
          "keyphrase_sources": [
            {
              "id": "rootcause:potential NULL pointer dereference",
              "keyphrase": "potential NULL pointer dereference",
              "type": "rootcause"
            },
            {
              "id": "rootcause:missing check",
              "keyphrase": "missing check",
              "type": "rootcause"
            },
            {
              "id": "component:mfd ene-kb3930",
              "keyphrase": "mfd ene-kb3930",
              "type": "component"
            }
          ]
        },
        "similarity": 387.61894537693996
      },
      {
        "metadata": {
          "doc_id": "665",
          "name": "Improper Initialization",
          "source": "sparse",
          "original_content": "The product does not initialize or incorrectly initializes a resource, which might leave the resource in an unexpected state when it is accessed or used.",
          "keyphrase_sources": [
            {
              "id": "rootcause:potential NULL pointer dereference",
              "keyphrase": "potential NULL pointer dereference",
              "type": "rootcause"
            },
            {
              "id": "component:mfd ene-kb3930",
              "keyphrase": "mfd ene-kb3930",
              "type": "component"
            }
          ]
        },
        "similarity": 383.3437601584467
      },
      {
        "metadata": {
          "doc_id": "690",
          "name": "Unchecked Return Value to NULL Pointer Dereference",
          "source": "sparse",
          "original_content": "The product does not check for an error after calling a function that can return with a NULL pointer if the function fails, which leads to a resultant NULL pointer dereference.",
          "keyphrase_sources": [
            {
              "id": "rootcause:potential NULL pointer dereference",
              "keyphrase": "potential NULL pointer dereference",
              "type": "rootcause"
            },
            {
              "id": "rootcause:missing check",
              "keyphrase": "missing check",
              "type": "rootcause"
            }
          ]
        },
        "similarity": 382.68825692525166
      },
      {
        "metadata": {
          "doc_id": "362",
          "name": "Concurrent Execution using Shared Resource with Improper Synchronization ('Race Condition')",
          "source": "sparse",
          "original_content": "The product contains a concurrent code sequence that requires temporary, exclusive access to a shared resource, but a timing window exists in which the shared resource can be modified by another code sequence operating concurrently.",
          "keyphrase_sources": [
            {
              "id": "rootcause:missing check",
              "keyphrase": "missing check",
              "type": "rootcause"
            },
            {
              "id": "product:Linux kernel",
              "keyphrase": "Linux kernel",
              "type": "product"
            }
          ]
        },
        "similarity": 300.3233090220647
      },
      {
        "metadata": {
          "doc_id": "822",
          "name": "Untrusted Pointer Dereference",
          "source": "sparse",
          "original_content": "The product obtains a value from an untrusted source, converts this value to a pointer, and dereferences the resulting pointer.",
          "keyphrase_sources": [
            {
              "id": "product:Linux kernel",
              "keyphrase": "Linux kernel",
              "type": "product"
            },
            {
              "id": "component:mfd ene-kb3930",
              "keyphrase": "mfd ene-kb3930",
              "type": "component"
            }
          ]
        },
        "similarity": 108.91948544398043
      },
      {
        "metadata": {
          "doc_id": "909",
          "name": "Missing Initialization of Resource",
          "source": "sparse",
          "original_content": "The product does not initialize a critical resource.",
          "keyphrase_sources": [
            {
              "id": "product:Linux kernel",
              "keyphrase": "Linux kernel",
              "type": "product"
            }
          ]
        },
        "similarity": 105.425383623435
      }
    ],
    "enhanced_query": "# Vulnerability Description\n\n    In the Linux kernel, the following vulnerability has been resolved mfd ene-kb3930 Fix a **potential NULL pointer dereference** The off_gpios could be NULL. Add **missing check** in the kb3930_probe(). This is similar to the issue fixed in commit b1ba8bcb2d1f (backlight hx8357 Fix **potential NULL pointer dereference**). This was detected by our static analysis tool.\n\n    # Keyphrase-Specific CWE Analysis\n    This vulnerability contains multiple keyphrases that may map to different CWEs. \n    Please analyze each keyphrase separately and determine the most appropriate CWE(s) for each.\n\n    ## ROOTCAUSE: 'potential NULL pointer dereference'\n\nRelevant CWEs for this ROOTCAUSE:\n\n### 1. CWE-476: NULL Pointer Dereference (Score: 486.24)\n\nThe product dereferences a pointer that it expects to be valid but is NULL....\n\n### 2. CWE-252: Unchecked Return Value (Score: 424.27)\n\nThe product does not check the return value from a method or function, which can prevent it from detecting unexpected states and conditions....\n\n### 3. CWE-824: Access of Uninitialized Pointer (Score: 387.62)\n\nThe product accesses or uses a pointer that has not been initialized....\n\n### 4. CWE-665: Improper Initialization (Score: 383.34)\n\nThe product does not initialize or incorrectly initializes a resource, which might leave the resource in an unexpected state when it is accessed or used....\n\n### 5. CWE-690: Unchecked Return Value to NULL Pointer Dereference (Score: 382.69)\n\nThe product does not check for an error after calling a function that can return with a NULL pointer if the function fails, which leads to a resultant NULL pointer dereference....\n\n## ROOTCAUSE: 'missing check'\n\nRelevant CWEs for this ROOTCAUSE:\n\n### 1. CWE-476: NULL Pointer Dereference (Score: 486.24)\n\nThe product dereferences a pointer that it expects to be valid but is NULL....\n\n### 2. CWE-252: Unchecked Return Value (Score: 424.27)\n\nThe product does not check the return value from a method or function, which can prevent it from detecting unexpected states and conditions....\n\n### 3. CWE-824: Access of Uninitialized Pointer (Score: 387.62)\n\nThe product accesses or uses a pointer that has not been initialized....\n\n### 4. CWE-690: Unchecked Return Value to NULL Pointer Dereference (Score: 382.69)\n\nThe product does not check for an error after calling a function that can return with a NULL pointer if the function fails, which leads to a resultant NULL pointer dereference....\n\n### 5. CWE-362: Concurrent Execution using Shared Resource with Improper Synchronization ('Race Condition') (Score: 300.32)\n\nThe product contains a concurrent code sequence that requires temporary, exclusive access to a shared resource, but a timing window exists in which the shared resource can be modified by another code sequence operating concurrently....\n\n## PRODUCT: 'Linux kernel'\n\nRelevant CWEs for this PRODUCT:\n\n### 1. CWE-476: NULL Pointer Dereference (Score: 486.24)\n\nThe product dereferences a pointer that it expects to be valid but is NULL....\n\n### 2. CWE-252: Unchecked Return Value (Score: 424.27)\n\nThe product does not check the return value from a method or function, which can prevent it from detecting unexpected states and conditions....\n\n### 3. CWE-362: Concurrent Execution using Shared Resource with Improper Synchronization ('Race Condition') (Score: 300.32)\n\nThe product contains a concurrent code sequence that requires temporary, exclusive access to a shared resource, but a timing window exists in which the shared resource can be modified by another code sequence operating concurrently....\n\n### 4. CWE-822: Untrusted Pointer Dereference (Score: 108.92)\n\nThe product obtains a value from an untrusted source, converts this value to a pointer, and dereferences the resulting pointer....\n\n### 5. CWE-909: Missing Initialization of Resource (Score: 105.43)\n\nThe product does not initialize a critical resource....\n\n## COMPONENT: 'mfd ene-kb3930'\n\nRelevant CWEs for this COMPONENT:\n\n### 1. CWE-476: NULL Pointer Dereference (Score: 486.24)\n\nThe product dereferences a pointer that it expects to be valid but is NULL....\n\n### 2. CWE-252: Unchecked Return Value (Score: 424.27)\n\nThe product does not check the return value from a method or function, which can prevent it from detecting unexpected states and conditions....\n\n### 3. CWE-824: Access of Uninitialized Pointer (Score: 387.62)\n\nThe product accesses or uses a pointer that has not been initialized....\n\n### 4. CWE-665: Improper Initialization (Score: 383.34)\n\nThe product does not initialize or incorrectly initializes a resource, which might leave the resource in an unexpected state when it is accessed or used....\n\n### 5. CWE-822: Untrusted Pointer Dereference (Score: 108.92)\n\nThe product obtains a value from an untrusted source, converts this value to a pointer, and dereferences the resulting pointer....\n\n\n    # Analysis Instructions\n    1. For each keyphrase, identify the most appropriate CWE(s) that represent the weakness.\n    2. Consider how the different keyphrases might relate to each other in the vulnerability chain.\n    3. Provide a final determination of primary CWE(s) and any secondary CWEs.\n    4. Format your response using the standard analysis template.\n\n    Please analyze how these different weaknesses interact and provide a comprehensive CWE classification.\n    "
  },
  "retrieval_time": 1.0966606140136719
}