{
  "vulnerability_info": "VulnerabilityInfo(cve_id='CVE-2024-51434', description='**Inconsistent tag parsing** allows for **XSS** in Froala WYSIWYG editor 4.3.0 and earlier.', key_phrases={'rootcause': 'Inconsistent tag parsing', 'weakness': ['XSS', 'cross-site scripting'], 'impact': '', 'vector': '', 'attacker': '', 'product': 'Froala WYSIWYG editor', 'version': '4.3.0 and earlier', 'component': ''}, reference_content=None, similar_info={'cwe_distribution': {}, 'cwe_consensus': '', 'similarity_stats': {'thresholds': [], 'total_samples_by_threshold': {}, 'top_cwes_by_threshold': {}}}, similarity_summary=SimilarityInsight(consensus_cwe='', top_cwes=[], confidence_levels={}, total_samples=0), analysis='', analysis_with_relationships='', criticism='', resolution='', relevant_cwes=[{'metadata': {'doc_id': '352', 'name': 'Cross-Site Request Forgery (CSRF)', 'source': 'sparse', 'original_content': 'The web application does not, or can not, sufficiently verify whether a well-formed, valid, consistent request was intentionally provided by the user who submitted the request.', 'keyphrase_sources': [{'id': 'weakness:cross-site scripting', 'keyphrase': 'cross-site scripting', 'type': 'weakness'}]}, 'similarity': np.float64(155.96049196015875)}, {'metadata': {'doc_id': '942', 'name': 'Permissive Cross-domain Policy with Untrusted Domains', 'source': 'sparse', 'original_content': 'The product uses a cross-domain policy file that includes domains that should not be trusted.', 'keyphrase_sources': [{'id': 'weakness:cross-site scripting', 'keyphrase': 'cross-site scripting', 'type': 'weakness'}]}, 'similarity': np.float64(143.4004580697317)}, {'metadata': {'doc_id': '80', 'name': 'Improper Neutralization of Script-Related HTML Tags in a Web Page (Basic XSS)', 'source': 'sparse', 'original_content': 'The product receives input from an upstream component, but it does not neutralize or incorrectly neutralizes special characters such as \"<\", \">\", and \"&\" that could be interpreted as web-scripting elements when they are sent to a downstream component that processes web pages.', 'keyphrase_sources': [{'id': 'weakness:cross-site scripting', 'keyphrase': 'cross-site scripting', 'type': 'weakness'}]}, 'similarity': np.float64(138.9077530886258)}, {'metadata': {'doc_id': '444', 'name': \"Inconsistent Interpretation of HTTP Requests ('HTTP Request/Response Smuggling')\", 'source': 'sparse', 'original_content': 'The product acts as an intermediary HTTP agent\\n         (such as a proxy or firewall) in the data flow between two\\n         entities such as a client and server, but it does not\\n         interpret malformed HTTP requests or responses in ways that\\n         are consistent with how the messages will be processed by\\n         those entities that are at the ultimate destination.', 'keyphrase_sources': [{'id': 'rootcause:Inconsistent tag parsing', 'keyphrase': 'Inconsistent tag parsing', 'type': 'rootcause'}, {'id': 'weakness:XSS', 'keyphrase': 'XSS', 'type': 'weakness'}]}, 'similarity': np.float64(129.96134124403014)}, {'metadata': {'doc_id': '203', 'name': 'Observable Discrepancy', 'source': 'sparse', 'original_content': 'The product behaves differently or sends different responses under different circumstances in a way that is observable to an unauthorized actor, which exposes security-relevant information about the state of the product, such as whether a particular operation was successful or not.', 'keyphrase_sources': [{'id': 'rootcause:Inconsistent tag parsing', 'keyphrase': 'Inconsistent tag parsing', 'type': 'rootcause'}]}, 'similarity': np.float64(121.84409408110469)}, {'metadata': {'doc_id': '82', 'name': 'Improper Neutralization of Script in Attributes of IMG Tags in a Web Page', 'source': 'sparse', 'original_content': 'The web application does not neutralize or incorrectly neutralizes scripting elements within attributes of HTML IMG tags, such as the src attribute.', 'keyphrase_sources': [{'id': 'rootcause:Inconsistent tag parsing', 'keyphrase': 'Inconsistent tag parsing', 'type': 'rootcause'}, {'id': 'weakness:XSS', 'keyphrase': 'XSS', 'type': 'weakness'}]}, 'similarity': np.float64(110.6449936489102)}, {'metadata': {'doc_id': '1333', 'name': 'Inefficient Regular Expression Complexity', 'source': 'sparse', 'original_content': 'The product uses a regular expression with an inefficient, possibly exponential worst-case computational complexity that consumes excessive CPU cycles.', 'keyphrase_sources': [{'id': 'rootcause:Inconsistent tag parsing', 'keyphrase': 'Inconsistent tag parsing', 'type': 'rootcause'}, {'id': 'product:Froala WYSIWYG editor', 'keyphrase': 'Froala WYSIWYG editor', 'type': 'product'}]}, 'similarity': np.float64(107.96152636134796)}, {'metadata': {'doc_id': '79', 'name': \"Improper Neutralization of Input During Web Page Generation ('Cross-site Scripting')\", 'source': 'sparse', 'original_content': 'The product does not neutralize or incorrectly neutralizes user-controllable input before it is placed in output that is used as a web page that is served to other users.', 'keyphrase_sources': [{'id': 'weakness:XSS', 'keyphrase': 'XSS', 'type': 'weakness'}, {'id': 'weakness:cross-site scripting', 'keyphrase': 'cross-site scripting', 'type': 'weakness'}, {'id': 'product:Froala WYSIWYG editor', 'keyphrase': 'Froala WYSIWYG editor', 'type': 'product'}, {'id': 'version:4.3.0 and earlier', 'keyphrase': '4.3.0 and earlier', 'type': 'version'}]}, 'similarity': np.float64(106.03435816205678)}, {'metadata': {'doc_id': '116', 'name': 'Improper Encoding or Escaping of Output', 'source': 'sparse', 'original_content': 'The product prepares a structured message for communication with another component, but encoding or escaping of the data is either missing or done incorrectly. As a result, the intended structure of the message is not preserved.', 'keyphrase_sources': [{'id': 'rootcause:Inconsistent tag parsing', 'keyphrase': 'Inconsistent tag parsing', 'type': 'rootcause'}, {'id': 'weakness:XSS', 'keyphrase': 'XSS', 'type': 'weakness'}, {'id': 'weakness:cross-site scripting', 'keyphrase': 'cross-site scripting', 'type': 'weakness'}, {'id': 'version:4.3.0 and earlier', 'keyphrase': '4.3.0 and earlier', 'type': 'version'}]}, 'similarity': np.float64(103.97230695583302)}, {'metadata': {'doc_id': '918', 'name': 'Server-Side Request Forgery (SSRF)', 'source': 'sparse', 'original_content': 'The web server receives a URL or similar request from an upstream component and retrieves the contents of this URL, but it does not sufficiently ensure that the request is being sent to the expected destination.', 'keyphrase_sources': [{'id': 'weakness:XSS', 'keyphrase': 'XSS', 'type': 'weakness'}, {'id': 'product:Froala WYSIWYG editor', 'keyphrase': 'Froala WYSIWYG editor', 'type': 'product'}, {'id': 'version:4.3.0 and earlier', 'keyphrase': '4.3.0 and earlier', 'type': 'version'}]}, 'similarity': np.float64(91.38300718840969)}, {'metadata': {'doc_id': '1286', 'name': 'Improper Validation of Syntactic Correctness of Input', 'source': 'sparse', 'original_content': 'The product receives input that is expected to be well-formed - i.e., to comply with a certain syntax - but it does not validate or incorrectly validates that the input complies with the syntax.', 'keyphrase_sources': [{'id': 'version:4.3.0 and earlier', 'keyphrase': '4.3.0 and earlier', 'type': 'version'}]}, 'similarity': np.float64(45.315968581335994)}, {'metadata': {'doc_id': '200', 'name': 'Exposure of Sensitive Information to an Unauthorized Actor', 'source': 'sparse', 'original_content': 'The product exposes sensitive information to an actor that is not explicitly authorized to have access to that information.', 'keyphrase_sources': [{'id': 'version:4.3.0 and earlier', 'keyphrase': '4.3.0 and earlier', 'type': 'version'}]}, 'similarity': np.float64(42.74238128560933)}, {'metadata': {'doc_id': '1321', 'name': \"Improperly Controlled Modification of Object Prototype Attributes ('Prototype Pollution')\", 'source': 'sparse', 'original_content': 'The product receives input from an upstream component that specifies attributes that are to be initialized or updated in an object, but it does not properly control modifications of attributes of the object prototype.', 'keyphrase_sources': [{'id': 'product:Froala WYSIWYG editor', 'keyphrase': 'Froala WYSIWYG editor', 'type': 'product'}]}, 'similarity': np.float64(25.88435203347981)}, {'metadata': {'doc_id': '703', 'name': 'Improper Check or Handling of Exceptional Conditions', 'source': 'sparse', 'original_content': 'The product does not properly anticipate or handle exceptional conditions that rarely occur during normal operation of the product.', 'keyphrase_sources': [{'id': 'product:Froala WYSIWYG editor', 'keyphrase': 'Froala WYSIWYG editor', 'type': 'product'}]}, 'similarity': np.float64(25.826750979296367)}], identified_cwes={'analyzer': [], 'critic_additional': []})",
  "retrieval_results": {
    "has_multiple_keyphrases": true,
    "keyphrase_cwe_sets": {
      "rootcause:Inconsistent tag parsing": {
        "keyphrase": "Inconsistent tag parsing",
        "type": "rootcause",
        "cwes": [
          {
            "metadata": {
              "doc_id": "444",
              "name": "Inconsistent Interpretation of HTTP Requests ('HTTP Request/Response Smuggling')",
              "source": "sparse",
              "original_content": "The product acts as an intermediary HTTP agent\n         (such as a proxy or firewall) in the data flow between two\n         entities such as a client and server, but it does not\n         interpret malformed HTTP requests or responses in ways that\n         are consistent with how the messages will be processed by\n         those entities that are at the ultimate destination.",
              "keyphrase_sources": [
                {
                  "id": "rootcause:Inconsistent tag parsing",
                  "keyphrase": "Inconsistent tag parsing",
                  "type": "rootcause"
                },
                {
                  "id": "weakness:XSS",
                  "keyphrase": "XSS",
                  "type": "weakness"
                }
              ]
            },
            "similarity": 129.96134124403014
          },
          {
            "metadata": {
              "doc_id": "203",
              "name": "Observable Discrepancy",
              "source": "sparse",
              "original_content": "The product behaves differently or sends different responses under different circumstances in a way that is observable to an unauthorized actor, which exposes security-relevant information about the state of the product, such as whether a particular operation was successful or not.",
              "keyphrase_sources": [
                {
                  "id": "rootcause:Inconsistent tag parsing",
                  "keyphrase": "Inconsistent tag parsing",
                  "type": "rootcause"
                }
              ]
            },
            "similarity": 121.84409408110469
          },
          {
            "metadata": {
              "doc_id": "82",
              "name": "Improper Neutralization of Script in Attributes of IMG Tags in a Web Page",
              "source": "sparse",
              "original_content": "The web application does not neutralize or incorrectly neutralizes scripting elements within attributes of HTML IMG tags, such as the src attribute.",
              "keyphrase_sources": [
                {
                  "id": "rootcause:Inconsistent tag parsing",
                  "keyphrase": "Inconsistent tag parsing",
                  "type": "rootcause"
                },
                {
                  "id": "weakness:XSS",
                  "keyphrase": "XSS",
                  "type": "weakness"
                }
              ]
            },
            "similarity": 110.6449936489102
          },
          {
            "metadata": {
              "doc_id": "1333",
              "name": "Inefficient Regular Expression Complexity",
              "source": "sparse",
              "original_content": "The product uses a regular expression with an inefficient, possibly exponential worst-case computational complexity that consumes excessive CPU cycles.",
              "keyphrase_sources": [
                {
                  "id": "rootcause:Inconsistent tag parsing",
                  "keyphrase": "Inconsistent tag parsing",
                  "type": "rootcause"
                },
                {
                  "id": "product:Froala WYSIWYG editor",
                  "keyphrase": "Froala WYSIWYG editor",
                  "type": "product"
                }
              ]
            },
            "similarity": 107.96152636134796
          },
          {
            "metadata": {
              "doc_id": "116",
              "name": "Improper Encoding or Escaping of Output",
              "source": "sparse",
              "original_content": "The product prepares a structured message for communication with another component, but encoding or escaping of the data is either missing or done incorrectly. As a result, the intended structure of the message is not preserved.",
              "keyphrase_sources": [
                {
                  "id": "rootcause:Inconsistent tag parsing",
                  "keyphrase": "Inconsistent tag parsing",
                  "type": "rootcause"
                },
                {
                  "id": "weakness:XSS",
                  "keyphrase": "XSS",
                  "type": "weakness"
                },
                {
                  "id": "weakness:cross-site scripting",
                  "keyphrase": "cross-site scripting",
                  "type": "weakness"
                },
                {
                  "id": "version:4.3.0 and earlier",
                  "keyphrase": "4.3.0 and earlier",
                  "type": "version"
                }
              ]
            },
            "similarity": 103.97230695583302
          }
        ]
      },
      "weakness:XSS": {
        "keyphrase": "XSS",
        "type": "weakness",
        "cwes": [
          {
            "metadata": {
              "doc_id": "79",
              "name": "Improper Neutralization of Input During Web Page Generation ('Cross-site Scripting')",
              "source": "sparse",
              "original_content": "The product does not neutralize or incorrectly neutralizes user-controllable input before it is placed in output that is used as a web page that is served to other users.",
              "keyphrase_sources": [
                {
                  "id": "weakness:XSS",
                  "keyphrase": "XSS",
                  "type": "weakness"
                },
                {
                  "id": "weakness:cross-site scripting",
                  "keyphrase": "cross-site scripting",
                  "type": "weakness"
                },
                {
                  "id": "product:Froala WYSIWYG editor",
                  "keyphrase": "Froala WYSIWYG editor",
                  "type": "product"
                },
                {
                  "id": "version:4.3.0 and earlier",
                  "keyphrase": "4.3.0 and earlier",
                  "type": "version"
                }
              ]
            },
            "similarity": 106.03435816205678
          },
          {
            "metadata": {
              "doc_id": "116",
              "name": "Improper Encoding or Escaping of Output",
              "source": "sparse",
              "original_content": "The product prepares a structured message for communication with another component, but encoding or escaping of the data is either missing or done incorrectly. As a result, the intended structure of the message is not preserved."
            },
            "similarity": 93.81568246394849
          },
          {
            "metadata": {
              "doc_id": "444",
              "name": "Inconsistent Interpretation of HTTP Requests ('HTTP Request/Response Smuggling')",
              "source": "sparse",
              "original_content": "The product acts as an intermediary HTTP agent\n         (such as a proxy or firewall) in the data flow between two\n         entities such as a client and server, but it does not\n         interpret malformed HTTP requests or responses in ways that\n         are consistent with how the messages will be processed by\n         those entities that are at the ultimate destination."
            },
            "similarity": 92.41702396785367
          },
          {
            "metadata": {
              "doc_id": "918",
              "name": "Server-Side Request Forgery (SSRF)",
              "source": "sparse",
              "original_content": "The web server receives a URL or similar request from an upstream component and retrieves the contents of this URL, but it does not sufficiently ensure that the request is being sent to the expected destination.",
              "keyphrase_sources": [
                {
                  "id": "weakness:XSS",
                  "keyphrase": "XSS",
                  "type": "weakness"
                },
                {
                  "id": "product:Froala WYSIWYG editor",
                  "keyphrase": "Froala WYSIWYG editor",
                  "type": "product"
                },
                {
                  "id": "version:4.3.0 and earlier",
                  "keyphrase": "4.3.0 and earlier",
                  "type": "version"
                }
              ]
            },
            "similarity": 91.38300718840969
          },
          {
            "metadata": {
              "doc_id": "82",
              "name": "Improper Neutralization of Script in Attributes of IMG Tags in a Web Page",
              "source": "sparse",
              "original_content": "The web application does not neutralize or incorrectly neutralizes scripting elements within attributes of HTML IMG tags, such as the src attribute."
            },
            "similarity": 88.1807315191718
          }
        ]
      },
      "weakness:cross-site scripting": {
        "keyphrase": "cross-site scripting",
        "type": "weakness",
        "cwes": [
          {
            "metadata": {
              "doc_id": "79",
              "name": "Improper Neutralization of Input During Web Page Generation ('Cross-site Scripting')",
              "source": "sparse",
              "original_content": "The product does not neutralize or incorrectly neutralizes user-controllable input before it is placed in output that is used as a web page that is served to other users."
            },
            "similarity": 167.99914951894297
          },
          {
            "metadata": {
              "doc_id": "352",
              "name": "Cross-Site Request Forgery (CSRF)",
              "source": "sparse",
              "original_content": "The web application does not, or can not, sufficiently verify whether a well-formed, valid, consistent request was intentionally provided by the user who submitted the request.",
              "keyphrase_sources": [
                {
                  "id": "weakness:cross-site scripting",
                  "keyphrase": "cross-site scripting",
                  "type": "weakness"
                }
              ]
            },
            "similarity": 155.96049196015875
          },
          {
            "metadata": {
              "doc_id": "942",
              "name": "Permissive Cross-domain Policy with Untrusted Domains",
              "source": "sparse",
              "original_content": "The product uses a cross-domain policy file that includes domains that should not be trusted.",
              "keyphrase_sources": [
                {
                  "id": "weakness:cross-site scripting",
                  "keyphrase": "cross-site scripting",
                  "type": "weakness"
                }
              ]
            },
            "similarity": 143.4004580697317
          },
          {
            "metadata": {
              "doc_id": "116",
              "name": "Improper Encoding or Escaping of Output",
              "source": "sparse",
              "original_content": "The product prepares a structured message for communication with another component, but encoding or escaping of the data is either missing or done incorrectly. As a result, the intended structure of the message is not preserved."
            },
            "similarity": 140.98591034810894
          },
          {
            "metadata": {
              "doc_id": "80",
              "name": "Improper Neutralization of Script-Related HTML Tags in a Web Page (Basic XSS)",
              "source": "sparse",
              "original_content": "The product receives input from an upstream component, but it does not neutralize or incorrectly neutralizes special characters such as \"<\", \">\", and \"&\" that could be interpreted as web-scripting elements when they are sent to a downstream component that processes web pages.",
              "keyphrase_sources": [
                {
                  "id": "weakness:cross-site scripting",
                  "keyphrase": "cross-site scripting",
                  "type": "weakness"
                }
              ]
            },
            "similarity": 138.9077530886258
          }
        ]
      },
      "product:Froala WYSIWYG editor": {
        "keyphrase": "Froala WYSIWYG editor",
        "type": "product",
        "cwes": [
          {
            "metadata": {
              "doc_id": "79",
              "name": "Improper Neutralization of Input During Web Page Generation ('Cross-site Scripting')",
              "source": "sparse",
              "original_content": "The product does not neutralize or incorrectly neutralizes user-controllable input before it is placed in output that is used as a web page that is served to other users."
            },
            "similarity": 37.02208855736929
          },
          {
            "metadata": {
              "doc_id": "1333",
              "name": "Inefficient Regular Expression Complexity",
              "source": "sparse",
              "original_content": "The product uses a regular expression with an inefficient, possibly exponential worst-case computational complexity that consumes excessive CPU cycles."
            },
            "similarity": 32.41884161633308
          },
          {
            "metadata": {
              "doc_id": "918",
              "name": "Server-Side Request Forgery (SSRF)",
              "source": "sparse",
              "original_content": "The web server receives a URL or similar request from an upstream component and retrieves the contents of this URL, but it does not sufficiently ensure that the request is being sent to the expected destination."
            },
            "similarity": 29.888693115313156
          },
          {
            "metadata": {
              "doc_id": "1321",
              "name": "Improperly Controlled Modification of Object Prototype Attributes ('Prototype Pollution')",
              "source": "sparse",
              "original_content": "The product receives input from an upstream component that specifies attributes that are to be initialized or updated in an object, but it does not properly control modifications of attributes of the object prototype.",
              "keyphrase_sources": [
                {
                  "id": "product:Froala WYSIWYG editor",
                  "keyphrase": "Froala WYSIWYG editor",
                  "type": "product"
                }
              ]
            },
            "similarity": 25.88435203347981
          },
          {
            "metadata": {
              "doc_id": "703",
              "name": "Improper Check or Handling of Exceptional Conditions",
              "source": "sparse",
              "original_content": "The product does not properly anticipate or handle exceptional conditions that rarely occur during normal operation of the product.",
              "keyphrase_sources": [
                {
                  "id": "product:Froala WYSIWYG editor",
                  "keyphrase": "Froala WYSIWYG editor",
                  "type": "product"
                }
              ]
            },
            "similarity": 25.826750979296367
          }
        ]
      },
      "version:4.3.0 and earlier": {
        "keyphrase": "4.3.0 and earlier",
        "type": "version",
        "cwes": [
          {
            "metadata": {
              "doc_id": "1286",
              "name": "Improper Validation of Syntactic Correctness of Input",
              "source": "sparse",
              "original_content": "The product receives input that is expected to be well-formed - i.e., to comply with a certain syntax - but it does not validate or incorrectly validates that the input complies with the syntax.",
              "keyphrase_sources": [
                {
                  "id": "version:4.3.0 and earlier",
                  "keyphrase": "4.3.0 and earlier",
                  "type": "version"
                }
              ]
            },
            "similarity": 45.315968581335994
          },
          {
            "metadata": {
              "doc_id": "79",
              "name": "Improper Neutralization of Input During Web Page Generation ('Cross-site Scripting')",
              "source": "sparse",
              "original_content": "The product does not neutralize or incorrectly neutralizes user-controllable input before it is placed in output that is used as a web page that is served to other users."
            },
            "similarity": 43.11785185733926
          },
          {
            "metadata": {
              "doc_id": "918",
              "name": "Server-Side Request Forgery (SSRF)",
              "source": "sparse",
              "original_content": "The web server receives a URL or similar request from an upstream component and retrieves the contents of this URL, but it does not sufficiently ensure that the request is being sent to the expected destination."
            },
            "similarity": 43.09460393022798
          },
          {
            "metadata": {
              "doc_id": "200",
              "name": "Exposure of Sensitive Information to an Unauthorized Actor",
              "source": "sparse",
              "original_content": "The product exposes sensitive information to an actor that is not explicitly authorized to have access to that information.",
              "keyphrase_sources": [
                {
                  "id": "version:4.3.0 and earlier",
                  "keyphrase": "4.3.0 and earlier",
                  "type": "version"
                }
              ]
            },
            "similarity": 42.74238128560933
          },
          {
            "metadata": {
              "doc_id": "116",
              "name": "Improper Encoding or Escaping of Output",
              "source": "sparse",
              "original_content": "The product prepares a structured message for communication with another component, but encoding or escaping of the data is either missing or done incorrectly. As a result, the intended structure of the message is not preserved."
            },
            "similarity": 42.35405904119551
          }
        ]
      }
    },
    "keyphrase_mapping": {
      "444": [
        {
          "id": "rootcause:Inconsistent tag parsing",
          "keyphrase": "Inconsistent tag parsing",
          "type": "rootcause"
        },
        {
          "id": "weakness:XSS",
          "keyphrase": "XSS",
          "type": "weakness"
        }
      ],
      "203": [
        {
          "id": "rootcause:Inconsistent tag parsing",
          "keyphrase": "Inconsistent tag parsing",
          "type": "rootcause"
        }
      ],
      "82": [
        {
          "id": "rootcause:Inconsistent tag parsing",
          "keyphrase": "Inconsistent tag parsing",
          "type": "rootcause"
        },
        {
          "id": "weakness:XSS",
          "keyphrase": "XSS",
          "type": "weakness"
        }
      ],
      "1333": [
        {
          "id": "rootcause:Inconsistent tag parsing",
          "keyphrase": "Inconsistent tag parsing",
          "type": "rootcause"
        },
        {
          "id": "product:Froala WYSIWYG editor",
          "keyphrase": "Froala WYSIWYG editor",
          "type": "product"
        }
      ],
      "116": [
        {
          "id": "rootcause:Inconsistent tag parsing",
          "keyphrase": "Inconsistent tag parsing",
          "type": "rootcause"
        },
        {
          "id": "weakness:XSS",
          "keyphrase": "XSS",
          "type": "weakness"
        },
        {
          "id": "weakness:cross-site scripting",
          "keyphrase": "cross-site scripting",
          "type": "weakness"
        },
        {
          "id": "version:4.3.0 and earlier",
          "keyphrase": "4.3.0 and earlier",
          "type": "version"
        }
      ],
      "79": [
        {
          "id": "weakness:XSS",
          "keyphrase": "XSS",
          "type": "weakness"
        },
        {
          "id": "weakness:cross-site scripting",
          "keyphrase": "cross-site scripting",
          "type": "weakness"
        },
        {
          "id": "product:Froala WYSIWYG editor",
          "keyphrase": "Froala WYSIWYG editor",
          "type": "product"
        },
        {
          "id": "version:4.3.0 and earlier",
          "keyphrase": "4.3.0 and earlier",
          "type": "version"
        }
      ],
      "918": [
        {
          "id": "weakness:XSS",
          "keyphrase": "XSS",
          "type": "weakness"
        },
        {
          "id": "product:Froala WYSIWYG editor",
          "keyphrase": "Froala WYSIWYG editor",
          "type": "product"
        },
        {
          "id": "version:4.3.0 and earlier",
          "keyphrase": "4.3.0 and earlier",
          "type": "version"
        }
      ],
      "352": [
        {
          "id": "weakness:cross-site scripting",
          "keyphrase": "cross-site scripting",
          "type": "weakness"
        }
      ],
      "942": [
        {
          "id": "weakness:cross-site scripting",
          "keyphrase": "cross-site scripting",
          "type": "weakness"
        }
      ],
      "80": [
        {
          "id": "weakness:cross-site scripting",
          "keyphrase": "cross-site scripting",
          "type": "weakness"
        }
      ],
      "1321": [
        {
          "id": "product:Froala WYSIWYG editor",
          "keyphrase": "Froala WYSIWYG editor",
          "type": "product"
        }
      ],
      "703": [
        {
          "id": "product:Froala WYSIWYG editor",
          "keyphrase": "Froala WYSIWYG editor",
          "type": "product"
        }
      ],
      "1286": [
        {
          "id": "version:4.3.0 and earlier",
          "keyphrase": "4.3.0 and earlier",
          "type": "version"
        }
      ],
      "200": [
        {
          "id": "version:4.3.0 and earlier",
          "keyphrase": "4.3.0 and earlier",
          "type": "version"
        }
      ]
    },
    "relevant_cwes": [
      {
        "metadata": {
          "doc_id": "352",
          "name": "Cross-Site Request Forgery (CSRF)",
          "source": "sparse",
          "original_content": "The web application does not, or can not, sufficiently verify whether a well-formed, valid, consistent request was intentionally provided by the user who submitted the request.",
          "keyphrase_sources": [
            {
              "id": "weakness:cross-site scripting",
              "keyphrase": "cross-site scripting",
              "type": "weakness"
            }
          ]
        },
        "similarity": 155.96049196015875
      },
      {
        "metadata": {
          "doc_id": "942",
          "name": "Permissive Cross-domain Policy with Untrusted Domains",
          "source": "sparse",
          "original_content": "The product uses a cross-domain policy file that includes domains that should not be trusted.",
          "keyphrase_sources": [
            {
              "id": "weakness:cross-site scripting",
              "keyphrase": "cross-site scripting",
              "type": "weakness"
            }
          ]
        },
        "similarity": 143.4004580697317
      },
      {
        "metadata": {
          "doc_id": "80",
          "name": "Improper Neutralization of Script-Related HTML Tags in a Web Page (Basic XSS)",
          "source": "sparse",
          "original_content": "The product receives input from an upstream component, but it does not neutralize or incorrectly neutralizes special characters such as \"<\", \">\", and \"&\" that could be interpreted as web-scripting elements when they are sent to a downstream component that processes web pages.",
          "keyphrase_sources": [
            {
              "id": "weakness:cross-site scripting",
              "keyphrase": "cross-site scripting",
              "type": "weakness"
            }
          ]
        },
        "similarity": 138.9077530886258
      },
      {
        "metadata": {
          "doc_id": "444",
          "name": "Inconsistent Interpretation of HTTP Requests ('HTTP Request/Response Smuggling')",
          "source": "sparse",
          "original_content": "The product acts as an intermediary HTTP agent\n         (such as a proxy or firewall) in the data flow between two\n         entities such as a client and server, but it does not\n         interpret malformed HTTP requests or responses in ways that\n         are consistent with how the messages will be processed by\n         those entities that are at the ultimate destination.",
          "keyphrase_sources": [
            {
              "id": "rootcause:Inconsistent tag parsing",
              "keyphrase": "Inconsistent tag parsing",
              "type": "rootcause"
            },
            {
              "id": "weakness:XSS",
              "keyphrase": "XSS",
              "type": "weakness"
            }
          ]
        },
        "similarity": 129.96134124403014
      },
      {
        "metadata": {
          "doc_id": "203",
          "name": "Observable Discrepancy",
          "source": "sparse",
          "original_content": "The product behaves differently or sends different responses under different circumstances in a way that is observable to an unauthorized actor, which exposes security-relevant information about the state of the product, such as whether a particular operation was successful or not.",
          "keyphrase_sources": [
            {
              "id": "rootcause:Inconsistent tag parsing",
              "keyphrase": "Inconsistent tag parsing",
              "type": "rootcause"
            }
          ]
        },
        "similarity": 121.84409408110469
      },
      {
        "metadata": {
          "doc_id": "82",
          "name": "Improper Neutralization of Script in Attributes of IMG Tags in a Web Page",
          "source": "sparse",
          "original_content": "The web application does not neutralize or incorrectly neutralizes scripting elements within attributes of HTML IMG tags, such as the src attribute.",
          "keyphrase_sources": [
            {
              "id": "rootcause:Inconsistent tag parsing",
              "keyphrase": "Inconsistent tag parsing",
              "type": "rootcause"
            },
            {
              "id": "weakness:XSS",
              "keyphrase": "XSS",
              "type": "weakness"
            }
          ]
        },
        "similarity": 110.6449936489102
      },
      {
        "metadata": {
          "doc_id": "1333",
          "name": "Inefficient Regular Expression Complexity",
          "source": "sparse",
          "original_content": "The product uses a regular expression with an inefficient, possibly exponential worst-case computational complexity that consumes excessive CPU cycles.",
          "keyphrase_sources": [
            {
              "id": "rootcause:Inconsistent tag parsing",
              "keyphrase": "Inconsistent tag parsing",
              "type": "rootcause"
            },
            {
              "id": "product:Froala WYSIWYG editor",
              "keyphrase": "Froala WYSIWYG editor",
              "type": "product"
            }
          ]
        },
        "similarity": 107.96152636134796
      },
      {
        "metadata": {
          "doc_id": "79",
          "name": "Improper Neutralization of Input During Web Page Generation ('Cross-site Scripting')",
          "source": "sparse",
          "original_content": "The product does not neutralize or incorrectly neutralizes user-controllable input before it is placed in output that is used as a web page that is served to other users.",
          "keyphrase_sources": [
            {
              "id": "weakness:XSS",
              "keyphrase": "XSS",
              "type": "weakness"
            },
            {
              "id": "weakness:cross-site scripting",
              "keyphrase": "cross-site scripting",
              "type": "weakness"
            },
            {
              "id": "product:Froala WYSIWYG editor",
              "keyphrase": "Froala WYSIWYG editor",
              "type": "product"
            },
            {
              "id": "version:4.3.0 and earlier",
              "keyphrase": "4.3.0 and earlier",
              "type": "version"
            }
          ]
        },
        "similarity": 106.03435816205678
      },
      {
        "metadata": {
          "doc_id": "116",
          "name": "Improper Encoding or Escaping of Output",
          "source": "sparse",
          "original_content": "The product prepares a structured message for communication with another component, but encoding or escaping of the data is either missing or done incorrectly. As a result, the intended structure of the message is not preserved.",
          "keyphrase_sources": [
            {
              "id": "rootcause:Inconsistent tag parsing",
              "keyphrase": "Inconsistent tag parsing",
              "type": "rootcause"
            },
            {
              "id": "weakness:XSS",
              "keyphrase": "XSS",
              "type": "weakness"
            },
            {
              "id": "weakness:cross-site scripting",
              "keyphrase": "cross-site scripting",
              "type": "weakness"
            },
            {
              "id": "version:4.3.0 and earlier",
              "keyphrase": "4.3.0 and earlier",
              "type": "version"
            }
          ]
        },
        "similarity": 103.97230695583302
      },
      {
        "metadata": {
          "doc_id": "918",
          "name": "Server-Side Request Forgery (SSRF)",
          "source": "sparse",
          "original_content": "The web server receives a URL or similar request from an upstream component and retrieves the contents of this URL, but it does not sufficiently ensure that the request is being sent to the expected destination.",
          "keyphrase_sources": [
            {
              "id": "weakness:XSS",
              "keyphrase": "XSS",
              "type": "weakness"
            },
            {
              "id": "product:Froala WYSIWYG editor",
              "keyphrase": "Froala WYSIWYG editor",
              "type": "product"
            },
            {
              "id": "version:4.3.0 and earlier",
              "keyphrase": "4.3.0 and earlier",
              "type": "version"
            }
          ]
        },
        "similarity": 91.38300718840969
      },
      {
        "metadata": {
          "doc_id": "1286",
          "name": "Improper Validation of Syntactic Correctness of Input",
          "source": "sparse",
          "original_content": "The product receives input that is expected to be well-formed - i.e., to comply with a certain syntax - but it does not validate or incorrectly validates that the input complies with the syntax.",
          "keyphrase_sources": [
            {
              "id": "version:4.3.0 and earlier",
              "keyphrase": "4.3.0 and earlier",
              "type": "version"
            }
          ]
        },
        "similarity": 45.315968581335994
      },
      {
        "metadata": {
          "doc_id": "200",
          "name": "Exposure of Sensitive Information to an Unauthorized Actor",
          "source": "sparse",
          "original_content": "The product exposes sensitive information to an actor that is not explicitly authorized to have access to that information.",
          "keyphrase_sources": [
            {
              "id": "version:4.3.0 and earlier",
              "keyphrase": "4.3.0 and earlier",
              "type": "version"
            }
          ]
        },
        "similarity": 42.74238128560933
      },
      {
        "metadata": {
          "doc_id": "1321",
          "name": "Improperly Controlled Modification of Object Prototype Attributes ('Prototype Pollution')",
          "source": "sparse",
          "original_content": "The product receives input from an upstream component that specifies attributes that are to be initialized or updated in an object, but it does not properly control modifications of attributes of the object prototype.",
          "keyphrase_sources": [
            {
              "id": "product:Froala WYSIWYG editor",
              "keyphrase": "Froala WYSIWYG editor",
              "type": "product"
            }
          ]
        },
        "similarity": 25.88435203347981
      },
      {
        "metadata": {
          "doc_id": "703",
          "name": "Improper Check or Handling of Exceptional Conditions",
          "source": "sparse",
          "original_content": "The product does not properly anticipate or handle exceptional conditions that rarely occur during normal operation of the product.",
          "keyphrase_sources": [
            {
              "id": "product:Froala WYSIWYG editor",
              "keyphrase": "Froala WYSIWYG editor",
              "type": "product"
            }
          ]
        },
        "similarity": 25.826750979296367
      }
    ],
    "enhanced_query": "# Vulnerability Description\n\n    **Inconsistent tag parsing** allows for **XSS** in Froala WYSIWYG editor 4.3.0 and earlier.\n\n    # Keyphrase-Specific CWE Analysis\n    This vulnerability contains multiple keyphrases that may map to different CWEs. \n    Please analyze each keyphrase separately and determine the most appropriate CWE(s) for each.\n\n    ## WEAKNESS: 'cross-site scripting'\n\nRelevant CWEs for this WEAKNESS:\n\n### 1. CWE-352: Cross-Site Request Forgery (CSRF) (Score: 155.96)\n\nThe web application does not, or can not, sufficiently verify whether a well-formed, valid, consistent request was intentionally provided by the user who submitted the request....\n\n### 2. CWE-942: Permissive Cross-domain Policy with Untrusted Domains (Score: 143.40)\n\nThe product uses a cross-domain policy file that includes domains that should not be trusted....\n\n### 3. CWE-80: Improper Neutralization of Script-Related HTML Tags in a Web Page (Basic XSS) (Score: 138.91)\n\nThe product receives input from an upstream component, but it does not neutralize or incorrectly neutralizes special characters such as \"<\", \">\", and \"&\" that could be interpreted as web-scripting elements when they are sent to a downstream component that processes web pages....\n\n### 4. CWE-79: Improper Neutralization of Input During Web Page Generation ('Cross-site Scripting') (Score: 106.03)\n\nThe product does not neutralize or incorrectly neutralizes user-controllable input before it is placed in output that is used as a web page that is served to other users....\n\n### 5. CWE-116: Improper Encoding or Escaping of Output (Score: 103.97)\n\nThe product prepares a structured message for communication with another component, but encoding or escaping of the data is either missing or done incorrectly. As a result, the intended structure of the message is not preserved....\n\n## ROOTCAUSE: 'Inconsistent tag parsing'\n\nRelevant CWEs for this ROOTCAUSE:\n\n### 1. CWE-444: Inconsistent Interpretation of HTTP Requests ('HTTP Request/Response Smuggling') (Score: 129.96)\n\nThe product acts as an intermediary HTTP agent\n         (such as a proxy or firewall) in the data flow between two\n         entities such as a client and server, but it does not\n         interpret malformed HTTP requests or responses in ways that\n         are consistent with how the messages will be...\n\n### 2. CWE-203: Observable Discrepancy (Score: 121.84)\n\nThe product behaves differently or sends different responses under different circumstances in a way that is observable to an unauthorized actor, which exposes security-relevant information about the state of the product, such as whether a particular operation was successful or not....\n\n### 3. CWE-82: Improper Neutralization of Script in Attributes of IMG Tags in a Web Page (Score: 110.64)\n\nThe web application does not neutralize or incorrectly neutralizes scripting elements within attributes of HTML IMG tags, such as the src attribute....\n\n### 4. CWE-1333: Inefficient Regular Expression Complexity (Score: 107.96)\n\nThe product uses a regular expression with an inefficient, possibly exponential worst-case computational complexity that consumes excessive CPU cycles....\n\n### 5. CWE-116: Improper Encoding or Escaping of Output (Score: 103.97)\n\nThe product prepares a structured message for communication with another component, but encoding or escaping of the data is either missing or done incorrectly. As a result, the intended structure of the message is not preserved....\n\n## WEAKNESS: 'XSS'\n\nRelevant CWEs for this WEAKNESS:\n\n### 1. CWE-444: Inconsistent Interpretation of HTTP Requests ('HTTP Request/Response Smuggling') (Score: 129.96)\n\nThe product acts as an intermediary HTTP agent\n         (such as a proxy or firewall) in the data flow between two\n         entities such as a client and server, but it does not\n         interpret malformed HTTP requests or responses in ways that\n         are consistent with how the messages will be...\n\n### 2. CWE-82: Improper Neutralization of Script in Attributes of IMG Tags in a Web Page (Score: 110.64)\n\nThe web application does not neutralize or incorrectly neutralizes scripting elements within attributes of HTML IMG tags, such as the src attribute....\n\n### 3. CWE-79: Improper Neutralization of Input During Web Page Generation ('Cross-site Scripting') (Score: 106.03)\n\nThe product does not neutralize or incorrectly neutralizes user-controllable input before it is placed in output that is used as a web page that is served to other users....\n\n### 4. CWE-116: Improper Encoding or Escaping of Output (Score: 103.97)\n\nThe product prepares a structured message for communication with another component, but encoding or escaping of the data is either missing or done incorrectly. As a result, the intended structure of the message is not preserved....\n\n### 5. CWE-918: Server-Side Request Forgery (SSRF) (Score: 91.38)\n\nThe web server receives a URL or similar request from an upstream component and retrieves the contents of this URL, but it does not sufficiently ensure that the request is being sent to the expected destination....\n\n## PRODUCT: 'Froala WYSIWYG editor'\n\nRelevant CWEs for this PRODUCT:\n\n### 1. CWE-1333: Inefficient Regular Expression Complexity (Score: 107.96)\n\nThe product uses a regular expression with an inefficient, possibly exponential worst-case computational complexity that consumes excessive CPU cycles....\n\n### 2. CWE-79: Improper Neutralization of Input During Web Page Generation ('Cross-site Scripting') (Score: 106.03)\n\nThe product does not neutralize or incorrectly neutralizes user-controllable input before it is placed in output that is used as a web page that is served to other users....\n\n### 3. CWE-918: Server-Side Request Forgery (SSRF) (Score: 91.38)\n\nThe web server receives a URL or similar request from an upstream component and retrieves the contents of this URL, but it does not sufficiently ensure that the request is being sent to the expected destination....\n\n### 4. CWE-1321: Improperly Controlled Modification of Object Prototype Attributes ('Prototype Pollution') (Score: 25.88)\n\nThe product receives input from an upstream component that specifies attributes that are to be initialized or updated in an object, but it does not properly control modifications of attributes of the object prototype....\n\n### 5. CWE-703: Improper Check or Handling of Exceptional Conditions (Score: 25.83)\n\nThe product does not properly anticipate or handle exceptional conditions that rarely occur during normal operation of the product....\n\n## VERSION: '4.3.0 and earlier'\n\nRelevant CWEs for this VERSION:\n\n### 1. CWE-79: Improper Neutralization of Input During Web Page Generation ('Cross-site Scripting') (Score: 106.03)\n\nThe product does not neutralize or incorrectly neutralizes user-controllable input before it is placed in output that is used as a web page that is served to other users....\n\n### 2. CWE-116: Improper Encoding or Escaping of Output (Score: 103.97)\n\nThe product prepares a structured message for communication with another component, but encoding or escaping of the data is either missing or done incorrectly. As a result, the intended structure of the message is not preserved....\n\n### 3. CWE-918: Server-Side Request Forgery (SSRF) (Score: 91.38)\n\nThe web server receives a URL or similar request from an upstream component and retrieves the contents of this URL, but it does not sufficiently ensure that the request is being sent to the expected destination....\n\n### 4. CWE-1286: Improper Validation of Syntactic Correctness of Input (Score: 45.32)\n\nThe product receives input that is expected to be well-formed - i.e., to comply with a certain syntax - but it does not validate or incorrectly validates that the input complies with the syntax....\n\n### 5. CWE-200: Exposure of Sensitive Information to an Unauthorized Actor (Score: 42.74)\n\nThe product exposes sensitive information to an actor that is not explicitly authorized to have access to that information....\n\n\n    # Analysis Instructions\n    1. For each keyphrase, identify the most appropriate CWE(s) that represent the weakness.\n    2. Consider how the different keyphrases might relate to each other in the vulnerability chain.\n    3. Provide a final determination of primary CWE(s) and any secondary CWEs.\n    4. Format your response using the standard analysis template.\n\n    Please analyze how these different weaknesses interact and provide a comprehensive CWE classification.\n    "
  },
  "retrieval_time": 1.2545053958892822
}