{
  "cve_id": "CVE-2024-11206",
  "description": "**Unauthorized access** vulnerability in the mobile application (com.transsion.phoenix) can lead to the leakage of user information.",
  "key_phrases": {
    "rootcause": "",
    "weakness": "Unauthorized access",
    "impact": "leakage of user information",
    "vector": "",
    "attacker": "",
    "product": "mobile application",
    "version": "",
    "component": ""
  },
  "reference_content": "UNRELATED",
  "similar_info": {
    "cwe_distribution": {},
    "cwe_consensus": "",
    "similarity_stats": {
      "thresholds": [],
      "total_samples_by_threshold": {},
      "top_cwes_by_threshold": {}
    }
  },
  "similarity_summary": {
    "consensus_cwe": "",
    "top_cwes": [],
    "confidence_levels": {},
    "total_samples": 0
  },
  "analysis": "# Summary\n| CWE ID | CWE Name | Confidence | CWE Abstraction Level | CWE Vulnerability Mapping Label | CWE-Vulnerability Mapping Notes |\n|---|---|---|---|---|---|\n| CWE-926 | Improper Export of Android Application Components | 0.8 | Variant | Allowed | Primary CWE |\n| CWE-359 | Exposure of Private Personal Information to an Unauthorized Actor | 0.6 | Base | Allowed | Secondary Candidate |\n| CWE-200 | Exposure of Sensitive Information to an Unauthorized Actor | 0.5 | Class | Discouraged | Secondary Candidate |\n\n## Evidence and Confidence\n\n*   **Confidence Score:** 0.7\n*   **Evidence Strength:** MEDIUM\n\n## Relationship Analysis\nThe primary relationship influencing the CWE selection is the hierarchical structure, particularly the Variant level of CWE-926 which directly addresses the Android application component exposure. While CWE-359 and CWE-200 are related to information exposure, they are less specific. The chain relationships don't play a significant role here as the focus is on the initial access control issue.\n\n```mermaid\ngraph TD\n    cwe926[\"CWE-926: Improper Export of Android Application Components\"]\n    cwe200[\"CWE-200: Exposure of Sensitive Information to an Unauthorized Actor\"]\n    cwe359[\"CWE-359: Exposure of Private Personal Information to an Unauthorized Actor\"]\n    cwe668[\"CWE-668: Exposure of Resource to Wrong Sphere\"]\n\n    cwe926 -->|CHILDOF| cwe923[\"CWE-923: Improper Restriction of Communication Channel to Intended Endpoints\"]\n    cwe926 -->|CHILDOF| cwe863[\"CWE-863: Incorrect Authorization\"]\n    cwe926 -->|CHILDOF| cwe183[\"CWE-183: Permissive Cross-domain Policy\"]\n    cwe359 -->|CHILDOF| cwe200\n    cwe926 -->|CANPRECEDE| cwe359\n    cwe926 -->|CANPRECEDE| cwe200\n    cwe359 -->|CHILDOF| cwe668\n    cwe200 -->|CHILDOF| cwe668\n\n    classDef primary fill:#f96,stroke:#333,stroke-width:2px\n    classDef secondary fill:#69f,stroke:#333\n    classDef tertiary fill:#9e9,stroke:#333\n    class cwe926 primary\n    class cwe200,cwe359 secondary\n```\n\n## Vulnerability Chain\nThe vulnerability chain starts with **Improper Export of Android Application Components (CWE-926)**, leading to **Exposure of Private Personal Information to an Unauthorized Actor (CWE-359)**. The root cause is the misconfiguration of the Android application component, which then results in the information leakage.\n\n## Summary of Analysis\nThe analysis is based on the vulnerability description stating an **\"Unauthorized access vulnerability in the mobile application (com.transsion.phoenix) can lead to the leakage of user information.\"** The key phrase \"Unauthorized access\" points to an authorization issue, and the product being a \"mobile application\" suggests Android-specific vulnerabilities.\n\nCWE-926 is chosen as the primary CWE because it directly addresses the root cause: the improper export of Android application components, leading to unauthorized access. This is a variant level CWE, providing more specificity than broader classes like **CWE-284: Improper Access Control** or **CWE-200: Exposure of Sensitive Information to an Unauthorized Actor**.\n\nCWE-359 is included as a secondary CWE because it represents the direct consequence of the unauthorized access: the exposure of private personal information.\n\nCWE-200 was considered as a secondary option, but it is a more general class of weakness. While the vulnerability does lead to the exposure of sensitive information, the root cause is better captured by CWE-926. Additionally, CWE-200 is discouraged per its mapping guidance, which states \"CWE-200 is commonly misused to represent the loss of confidentiality in a vulnerability, but confidentiality loss is a technical impact - not a root cause error.\"\n\nOther CWEs were considered but deemed less relevant:\n\n*   **CWE-285: Improper Authorization** and **CWE-284: Improper Access Control** are too general and don't capture the Android-specific nature of the vulnerability.\n*   **CWE-639: Authorization Bypass Through User-Controlled Key** implies a user-controlled key is involved, which is not evident in the description.\n*   **CWE-287: Improper Authentication** focuses on authentication issues, which are not described.\n*   **CWE-522: Insufficiently Protected Credentials** suggests that credentials are not adequately protected, which is not mentioned.\n*   **CWE-668: Exposure of Resource to Wrong Sphere** is too high-level.\n*   **CWE-1272: Sensitive Information Uncleared Before Debug/Power State Transition** is unrelated to the provided vulnerability description.",
  "analysis_with_relationships": "# Summary\n| CWE ID | CWE Name | Confidence | CWE Abstraction Level | CWE Vulnerability Mapping Label | CWE-Vulnerability Mapping Notes |\n|---|---|---|---|---|---|\n| CWE-926 | Improper Export of Android Application Components | 0.8 | Variant | Allowed | Primary CWE |\n| CWE-359 | Exposure of Private Personal Information to an Unauthorized Actor | 0.6 | Base | Allowed | Secondary Candidate |\n| CWE-200 | Exposure of Sensitive Information to an Unauthorized Actor | 0.5 | Class | Discouraged | Secondary Candidate |\n\n## Evidence and Confidence\n\n*   **Confidence Score:** 0.7\n*   **Evidence Strength:** MEDIUM\n\n## Relationship Analysis\nThe primary relationship influencing the CWE selection is the hierarchical structure, particularly the Variant level of CWE-926 which directly addresses the Android application component exposure. While CWE-359 and CWE-200 are related to information exposure, they are less specific. The chain relationships don't play a significant role here as the focus is on the initial access control issue.\n\n```mermaid\ngraph TD\n    cwe926[\"CWE-926: Improper Export of Android Application Components\"]\n    cwe200[\"CWE-200: Exposure of Sensitive Information to an Unauthorized Actor\"]\n    cwe359[\"CWE-359: Exposure of Private Personal Information to an Unauthorized Actor\"]\n    cwe668[\"CWE-668: Exposure of Resource to Wrong Sphere\"]\n\n    cwe926 -->|CHILDOF| cwe923[\"CWE-923: Improper Restriction of Communication Channel to Intended Endpoints\"]\n    cwe926 -->|CHILDOF| cwe863[\"CWE-863: Incorrect Authorization\"]\n    cwe926 -->|CHILDOF| cwe183[\"CWE-183: Permissive Cross-domain Policy\"]\n    cwe359 -->|CHILDOF| cwe200\n    cwe926 -->|CANPRECEDE| cwe359\n    cwe926 -->|CANPRECEDE| cwe200\n    cwe359 -->|CHILDOF| cwe668\n    cwe200 -->|CHILDOF| cwe668\n\n    classDef primary fill:#f96,stroke:#333,stroke-width:2px\n    classDef secondary fill:#69f,stroke:#333\n    classDef tertiary fill:#9e9,stroke:#333\n    class cwe926 primary\n    class cwe200,cwe359 secondary\n```\n\n## Vulnerability Chain\nThe vulnerability chain starts with **Improper Export of Android Application Components (CWE-926)**, leading to **Exposure of Private Personal Information to an Unauthorized Actor (CWE-359)**. The root cause is the misconfiguration of the Android application component, which then results in the information leakage.\n\n## Summary of Analysis\nThe analysis is based on the vulnerability description stating an **\"Unauthorized access vulnerability in the mobile application (com.transsion.phoenix) can lead to the leakage of user information.\"** The key phrase \"Unauthorized access\" points to an authorization issue, and the product being a \"mobile application\" suggests Android-specific vulnerabilities.\n\nCWE-926 is chosen as the primary CWE because it directly addresses the root cause: the improper export of Android application components, leading to unauthorized access. This is a variant level CWE, providing more specificity than broader classes like **CWE-284: Improper Access Control** or **CWE-200: Exposure of Sensitive Information to an Unauthorized Actor**.\n\nCWE-359 is included as a secondary CWE because it represents the direct consequence of the unauthorized access: the exposure of private personal information.\n\nCWE-200 was considered as a secondary option, but it is a more general class of weakness. While the vulnerability does lead to the exposure of sensitive information, the root cause is better captured by CWE-926. Additionally, CWE-200 is discouraged per its mapping guidance, which states \"CWE-200 is commonly misused to represent the loss of confidentiality in a vulnerability, but confidentiality loss is a technical impact - not a root cause error.\"\n\nOther CWEs were considered but deemed less relevant:\n\n*   **CWE-285: Improper Authorization** and **CWE-284: Improper Access Control** are too general and don't capture the Android-specific nature of the vulnerability.\n*   **CWE-639: Authorization Bypass Through User-Controlled Key** implies a user-controlled key is involved, which is not evident in the description.\n*   **CWE-287: Improper Authentication** focuses on authentication issues, which are not described.\n*   **CWE-522: Insufficiently Protected Credentials** suggests that credentials are not adequately protected, which is not mentioned.\n*   **CWE-668: Exposure of Resource to Wrong Sphere** is too high-level.\n*   **CWE-1272: Sensitive Information Uncleared Before Debug/Power State Transition** is unrelated to the provided vulnerability description.\n\n\n## CWE Relationship Analysis\n\nCurrent CWEs represent these abstraction levels: .\n\n\n### Vulnerability Chain Analysis\n\n**Chain starting from CWE-183:**\n- 183 (Permissive List of Allowed Inputs) - ROOT\n\n\n**Chain starting from CWE-863:**\n- 863 (Incorrect Authorization) - ROOT\n\n\n\n### CWE Relationship Diagram\n\n```mermaid\ngraph TD\n    classDef primary fill:#f96,stroke:#333,stroke-width:2px\n    classDef secondary fill:#69f,stroke:#333\n    classDef tertiary fill:#9e9,stroke:#333\n```",
  "criticism": "",
  "resolution": "",
  "relevant_cwes": [
    {
      "metadata": {
        "doc_id": "359",
        "name": "Exposure of Private Personal Information to an Unauthorized Actor",
        "source": "sparse"
      },
      "similarity": 121.63806608062062
    },
    {
      "metadata": {
        "doc_id": "200",
        "name": "Exposure of Sensitive Information to an Unauthorized Actor",
        "source": "sparse"
      },
      "similarity": 117.33543327628949
    },
    {
      "metadata": {
        "doc_id": "285",
        "name": "Improper Authorization",
        "source": "sparse"
      },
      "similarity": 112.05067922144046
    },
    {
      "metadata": {
        "doc_id": "284",
        "name": "Improper Access Control",
        "source": "sparse"
      },
      "similarity": 110.61912332809256
    },
    {
      "metadata": {
        "doc_id": "639",
        "name": "Authorization Bypass Through User-Controlled Key",
        "source": "sparse"
      },
      "similarity": 110.44357554330712
    },
    {
      "metadata": {
        "doc_id": "287",
        "name": "Improper Authentication",
        "source": "sparse"
      },
      "similarity": 109.74382322366475
    },
    {
      "metadata": {
        "doc_id": "522",
        "name": "Insufficiently Protected Credentials",
        "source": "sparse"
      },
      "similarity": 109.13169585615319
    },
    {
      "metadata": {
        "doc_id": "668",
        "name": "Exposure of Resource to Wrong Sphere",
        "source": "sparse"
      },
      "similarity": 106.98623379905463
    },
    {
      "metadata": {
        "doc_id": "926",
        "name": "Improper Export of Android Application Components",
        "type": "Variant",
        "original_content": "The Android application exports a component for use by other applications, but does not properly restrict which applications can launch the component or access the data it contains.",
        "keyphrase_source": "weakness:Unauthorized access",
        "source": "dense",
        "mapping_notes": {
          "usage": "Allowed",
          "rationale": "This CWE entry is at the Variant level of abstraction, which is a preferred level of abstraction for mapping to the root causes of vulnerabilities.",
          "comments": "Carefully read both the name and description to ensure that this mapping is an appropriate fit. Do not try to 'force' a mapping to a lower-level Base/Variant simply to comply with this preferred level of abstraction.",
          "reasons": [
            "Acceptable-Use"
          ]
        },
        "score_info": {
          "retrievers": [
            "dense",
            "sparse",
            "graph"
          ],
          "retriever_count": 3,
          "normalized_scores": {
            "dense": 0.544120259395283,
            "sparse": 106.5442347557545,
            "graph": 1.5470144018565617
          }
        }
      },
      "similarity": 0.544120259395283
    },
    {
      "doc_id": "1272",
      "text": "CWE-1272: Sensitive Information Uncleared Before Debug/Power State Transition",
      "score": 2.2100000000000004,
      "metadata": {
        "doc_id": "1272",
        "name": "Sensitive Information Uncleared Before Debug/Power State Transition",
        "type": "base",
        "original_content": "CWE-1272: Sensitive Information Uncleared Before Debug/Power State Transition",
        "relationships": [
          {
            "source_id": "1272",
            "target_id": "200",
            "label": "CANPRECEDE",
            "properties": {
              "ordinal": "Primary",
              "view_id": "1000"
            }
          },
          {
            "source_id": "1272",
            "target_id": "226",
            "label": "CHILDOF",
            "properties": {
              "ordinal": "Primary",
              "view_id": "1000"
            }
          },
          {
            "source_id": "226",
            "target_id": "1272",
            "label": "PARENTOF",
            "properties": {
              "ordinal": "Primary",
              "view_id": "1000"
            }
          },
          {
            "source_id": "200",
            "target_id": "1272",
            "label": "CANFOLLOW",
            "properties": {
              "ordinal": "Primary",
              "view_id": "1000"
            }
          }
        ],
        "score_components": {
          "relationship_chain": 1.0,
          "sequence_path": 1.0
        },
        "abstraction_factor": 1.3,
        "graph_path_info": {
          "path_types": [
            "relationship_chain",
            "vulnerability_sequence_forward",
            "vulnerability_sequence_backward"
          ],
          "best_paths": {
            "relationship_chain": {
              "path": [
                [
                  "200",
                  "1272",
                  "CANFOLLOW"
                ]
              ],
              "score": 1.0,
              "type": "relationship_chain",
              "source": "200"
            },
            "vulnerability_sequence_forward": {
              "path": [
                [
                  "200",
                  "1272",
                  "CANFOLLOW"
                ]
              ],
              "score": 0.9,
              "type": "vulnerability_sequence_forward",
              "source": "200"
            },
            "vulnerability_sequence_backward": {
              "path": [
                [
                  "1272",
                  "200",
                  "CANPRECEDE"
                ]
              ],
              "score": 1.0,
              "type": "vulnerability_sequence_backward",
              "source": "200"
            }
          }
        },
        "position": "before",
        "sources": [
          "graph"
        ],
        "source": "graph",
        "mapping_notes": {
          "usage": "Allowed",
          "rationale": "This CWE entry is at the Base level of abstraction, which is a preferred level of abstraction for mapping to the root causes of vulnerabilities.",
          "comments": "Carefully read both the name and description to ensure that this mapping is an appropriate fit. Do not try to 'force' a mapping to a lower-level Base/Variant simply to comply with this preferred level of abstraction.",
          "reasons": [
            "Acceptable-Use"
          ]
        },
        "score_info": {
          "retrievers": [
            "graph"
          ],
          "retriever_count": 1,
          "normalized_scores": {
            "graph": 2.2100000000000004
          }
        }
      },
      "similarity": 2.2100000000000004
    }
  ],
  "identified_cwes": {
    "analyzer": [
      "CWE-183",
      "CWE-863",
      "CWE-1272",
      "CWE-359",
      "CWE-522",
      "CWE-639",
      "CWE-926",
      "CWE-923",
      "CWE-285",
      "CWE-668",
      "CWE-284",
      "CWE-200",
      "CWE-287"
    ],
    "critic_additional": []
  },
  "keyphrase_cwe_mapping": {}
}