{
  "cve_id": "CVE-2024-34677",
  "description": "Exposure of sensitive information in System UI prior to SMR Nov-2024 Release 1 allow local attackers to make malicious apps appear as legitimate.",
  "key_phrases": {
    "rootcause": "",
    "weakness": "",
    "impact": [
      "Exposure of sensitive information",
      "make malicious apps appear as legitimate"
    ],
    "vector": "",
    "attacker": "local attackers",
    "product": "System UI",
    "version": "prior to SMR Nov-2024 Release 1",
    "component": ""
  },
  "reference_content": "- **Root cause of vulnerability:** Exposure of sensitive information in System UI.\n- **Weaknesses/vulnerabilities present:**  The System UI exposes sensitive information that can be used by local attackers to make malicious apps appear as legitimate.\n- **Impact of exploitation:** Local attackers can make malicious apps appear as legitimate.\n- **Attack vectors:** The vulnerability can be exploited by local attackers.\n- **Required attacker capabilities/position:** The attacker needs to be local to the device.",
  "similar_info": {
    "cwe_distribution": {},
    "cwe_consensus": "",
    "similarity_stats": {
      "thresholds": [],
      "total_samples_by_threshold": {},
      "top_cwes_by_threshold": {}
    }
  },
  "similarity_summary": {
    "consensus_cwe": "",
    "top_cwes": [],
    "confidence_levels": {},
    "total_samples": 0
  },
  "analysis": "# Summary\n| CWE ID | CWE Name | Confidence | CWE Abstraction Level | CWE Vulnerability Mapping Label | CWE-Vulnerability Mapping Notes |\n|---|---|---|---|---|---|\n| CWE-200 | Exposure of Sensitive Information to an Unauthorized Actor | 0.8 | Class | Primary | Discouraged - but most appropriate given the available information and lack of a more specific root cause. |\n| CWE-497 | Exposure of Sensitive System Information to an Unauthorized Control Sphere | 0.6 | Base | Secondary | Allowed |\n\n## Evidence and Confidence\n\n*   **Confidence Score:** 0.7\n*   **Evidence Strength:** MEDIUM\n\n## Relationship Analysis\nThe primary relationship influencing the decision is the parent-child relationship between CWE-200 and CWE-497. CWE-497 is a child of CWE-200, providing a more specific classification related to system information. However, the description doesn't explicitly state that *system* information is exposed, but it does say that *sensitive* information is exposed, so CWE-200 is taken as the primary.\n\n```mermaid\ngraph TD\n    cwe200[\"CWE-200: Exposure of Sensitive Information to an Unauthorized Actor\"]\n    cwe497[\"CWE-497: Exposure of Sensitive System Information to an Unauthorized Control Sphere\"]\n    \n    cwe497 -->|CHILDOF| cwe200\n    \n    classDef primary fill:#f96,stroke:#333,stroke-width:2px\n    classDef secondary fill:#69f,stroke:#333\n    \n    class cwe200 primary\n    class cwe497 secondary\n```\n\n## Vulnerability Chain\nThe vulnerability chain is relatively simple:\n\n1.  **Root Cause:** **Exposure of sensitive information** in System UI (CWE-200)\n2.  **Impact:** Local attackers can make malicious apps appear as legitimate.\n\n## Summary of Analysis\nThe initial assessment identified CWE-200 as a strong candidate due to the **exposure of sensitive information**. The retriever results also listed CWE-200, but with a \"Discouraged\" usage. However, the rationale for discouraging CWE-200 is that it's often misused and a more specific root cause should be identified. While I agree with this in principle, the provided information doesn't allow for pinpointing a more specific **root cause**. The CVE Reference Links Content Summary section indicates the **root cause** is directly related to the **exposure of sensitive information** in the System UI.\n\nThe retriever results also suggested several other CWEs, including CWE-497 (Exposure of Sensitive System Information to an Unauthorized Control Sphere). CWE-497 is a child of CWE-200 and specifies that *system* information is exposed. This could be a more accurate mapping.\n\nGiven the information available, CWE-200 remains the most appropriate primary CWE. CWE-497 is a good secondary candidate.\n\nRelevant CWE Information:\n\n*   **Vulnerability Description**: Exposure of sensitive information in System UI prior to SMR Nov-2024 Release 1 allow local attackers to make malicious apps appear as legitimate.\n*   **CVE Reference Links Content Summary**: **Root cause of vulnerability**: Exposure of sensitive information in System UI.\n\nCWEs considered but not used:\n\n*   CWE-213: Exposure of Sensitive Information Due to Incompatible Policies: While relevant, the description doesn't explicitly mention incompatible policies.\n*   CWE-927: Use of Implicit Intent for Sensitive Communication: This is specific to Android applications using implicit intents, which isn't mentioned in the vulnerability description.\n*   CWE-285: Improper Authorization: This is too broad and doesn't directly relate to the exposure of information.\n*   CWE-280: Improper Handling of Insufficient Permissions or Privileges: Similar to CWE-285, this is too broad.\n*   CWE-284: Improper Access Control: This is a very high-level category and less specific than CWE-200.\n*   CWE-926: Improper Export of Android Application Components: Similar to CWE-927, this is specific to Android component exports, which isn't mentioned.\n*   CWE-287: Improper Authentication: Not relevant as the issue isn't about authentication.\n*   CWE-1021: Improper Restriction of Rendered UI Layers or Frames: While this relates to UI, it is specific to frame objects and UI layers, which are not mentioned in the description.\n*   CWE-1272: Sensitive Information Uncleared Before Debug/Power State Transition: Not relevant as there is no mention of debug or power state transition.",
  "analysis_with_relationships": "# Summary\n| CWE ID | CWE Name | Confidence | CWE Abstraction Level | CWE Vulnerability Mapping Label | CWE-Vulnerability Mapping Notes |\n|---|---|---|---|---|---|\n| CWE-200 | Exposure of Sensitive Information to an Unauthorized Actor | 0.8 | Class | Primary | Discouraged - but most appropriate given the available information and lack of a more specific root cause. |\n| CWE-497 | Exposure of Sensitive System Information to an Unauthorized Control Sphere | 0.6 | Base | Secondary | Allowed |\n\n## Evidence and Confidence\n\n*   **Confidence Score:** 0.7\n*   **Evidence Strength:** MEDIUM\n\n## Relationship Analysis\nThe primary relationship influencing the decision is the parent-child relationship between CWE-200 and CWE-497. CWE-497 is a child of CWE-200, providing a more specific classification related to system information. However, the description doesn't explicitly state that *system* information is exposed, but it does say that *sensitive* information is exposed, so CWE-200 is taken as the primary.\n\n```mermaid\ngraph TD\n    cwe200[\"CWE-200: Exposure of Sensitive Information to an Unauthorized Actor\"]\n    cwe497[\"CWE-497: Exposure of Sensitive System Information to an Unauthorized Control Sphere\"]\n    \n    cwe497 -->|CHILDOF| cwe200\n    \n    classDef primary fill:#f96,stroke:#333,stroke-width:2px\n    classDef secondary fill:#69f,stroke:#333\n    \n    class cwe200 primary\n    class cwe497 secondary\n```\n\n## Vulnerability Chain\nThe vulnerability chain is relatively simple:\n\n1.  **Root Cause:** **Exposure of sensitive information** in System UI (CWE-200)\n2.  **Impact:** Local attackers can make malicious apps appear as legitimate.\n\n## Summary of Analysis\nThe initial assessment identified CWE-200 as a strong candidate due to the **exposure of sensitive information**. The retriever results also listed CWE-200, but with a \"Discouraged\" usage. However, the rationale for discouraging CWE-200 is that it's often misused and a more specific root cause should be identified. While I agree with this in principle, the provided information doesn't allow for pinpointing a more specific **root cause**. The CVE Reference Links Content Summary section indicates the **root cause** is directly related to the **exposure of sensitive information** in the System UI.\n\nThe retriever results also suggested several other CWEs, including CWE-497 (Exposure of Sensitive System Information to an Unauthorized Control Sphere). CWE-497 is a child of CWE-200 and specifies that *system* information is exposed. This could be a more accurate mapping.\n\nGiven the information available, CWE-200 remains the most appropriate primary CWE. CWE-497 is a good secondary candidate.\n\nRelevant CWE Information:\n\n*   **Vulnerability Description**: Exposure of sensitive information in System UI prior to SMR Nov-2024 Release 1 allow local attackers to make malicious apps appear as legitimate.\n*   **CVE Reference Links Content Summary**: **Root cause of vulnerability**: Exposure of sensitive information in System UI.\n\nCWEs considered but not used:\n\n*   CWE-213: Exposure of Sensitive Information Due to Incompatible Policies: While relevant, the description doesn't explicitly mention incompatible policies.\n*   CWE-927: Use of Implicit Intent for Sensitive Communication: This is specific to Android applications using implicit intents, which isn't mentioned in the vulnerability description.\n*   CWE-285: Improper Authorization: This is too broad and doesn't directly relate to the exposure of information.\n*   CWE-280: Improper Handling of Insufficient Permissions or Privileges: Similar to CWE-285, this is too broad.\n*   CWE-284: Improper Access Control: This is a very high-level category and less specific than CWE-200.\n*   CWE-926: Improper Export of Android Application Components: Similar to CWE-927, this is specific to Android component exports, which isn't mentioned.\n*   CWE-287: Improper Authentication: Not relevant as the issue isn't about authentication.\n*   CWE-1021: Improper Restriction of Rendered UI Layers or Frames: While this relates to UI, it is specific to frame objects and UI layers, which are not mentioned in the description.\n*   CWE-1272: Sensitive Information Uncleared Before Debug/Power State Transition: Not relevant as there is no mention of debug or power state transition.\n\n\n## CWE Relationship Analysis\n\nCurrent CWEs represent these abstraction levels: .\n\n\n### Vulnerability Chain Analysis\n\n**Chain starting from CWE-1272:**\n- 1272 (Sensitive Information Uncleared Before Debug/Power State Transition) - ROOT\n\n\n**Chain starting from CWE-280:**\n- 280 (Improper Handling of Insufficient Permissions or Privileges ) - ROOT\n\n\n\n### CWE Relationship Diagram\n\n```mermaid\ngraph TD\n    classDef primary fill:#f96,stroke:#333,stroke-width:2px\n    classDef secondary fill:#69f,stroke:#333\n    classDef tertiary fill:#9e9,stroke:#333\n```",
  "criticism": "",
  "resolution": "",
  "relevant_cwes": [
    {
      "metadata": {
        "doc_id": "213",
        "name": "Exposure of Sensitive Information Due to Incompatible Policies",
        "source": "sparse"
      },
      "similarity": 43.53528279557309
    },
    {
      "metadata": {
        "doc_id": "927",
        "name": "Use of Implicit Intent for Sensitive Communication",
        "source": "sparse"
      },
      "similarity": 42.350046363073496
    },
    {
      "metadata": {
        "doc_id": "285",
        "name": "Improper Authorization",
        "source": "sparse"
      },
      "similarity": 40.156779205032606
    },
    {
      "metadata": {
        "doc_id": "280",
        "name": "Improper Handling of Insufficient Permissions or Privileges ",
        "source": "sparse"
      },
      "similarity": 39.506858873245434
    },
    {
      "metadata": {
        "doc_id": "284",
        "name": "Improper Access Control",
        "source": "sparse"
      },
      "similarity": 39.0231038933785
    },
    {
      "metadata": {
        "doc_id": "200",
        "name": "Exposure of Sensitive Information to an Unauthorized Actor",
        "source": "sparse"
      },
      "similarity": 38.72380162289204
    },
    {
      "metadata": {
        "doc_id": "926",
        "name": "Improper Export of Android Application Components",
        "source": "sparse"
      },
      "similarity": 38.13982476554597
    },
    {
      "metadata": {
        "doc_id": "287",
        "name": "Improper Authentication",
        "source": "sparse"
      },
      "similarity": 37.278553402787466
    },
    {
      "metadata": {
        "doc_id": "1021",
        "name": "Improper Restriction of Rendered UI Layers or Frames",
        "type": "Base",
        "original_content": "The web application does not restrict or incorrectly restricts frame objects or UI layers that belong to another application or domain, which can lead to user confusion about which interface the user is interacting with.",
        "source": "dense",
        "mapping_notes": {
          "usage": "Allowed",
          "rationale": "This CWE entry is at the Base level of abstraction, which is a preferred level of abstraction for mapping to the root causes of vulnerabilities.",
          "comments": "Carefully read both the name and description to ensure that this mapping is an appropriate fit. Do not try to 'force' a mapping to a lower-level Base/Variant simply to comply with this preferred level of abstraction.",
          "reasons": [
            "Acceptable-Use"
          ]
        },
        "score_info": {
          "retrievers": [
            "dense",
            "graph"
          ],
          "retriever_count": 2,
          "normalized_scores": {
            "dense": 0.5640338977560633,
            "graph": 1.5331288013977928
          }
        }
      },
      "similarity": 0.5640338977560633
    },
    {
      "doc_id": "1272",
      "text": "CWE-1272: Sensitive Information Uncleared Before Debug/Power State Transition",
      "score": 2.2100000000000004,
      "metadata": {
        "doc_id": "1272",
        "name": "Sensitive Information Uncleared Before Debug/Power State Transition",
        "type": "base",
        "original_content": "CWE-1272: Sensitive Information Uncleared Before Debug/Power State Transition",
        "relationships": [
          {
            "source_id": "1272",
            "target_id": "200",
            "label": "CANPRECEDE",
            "properties": {
              "ordinal": "Primary",
              "view_id": "1000"
            }
          },
          {
            "source_id": "1272",
            "target_id": "226",
            "label": "CHILDOF",
            "properties": {
              "ordinal": "Primary",
              "view_id": "1000"
            }
          },
          {
            "source_id": "226",
            "target_id": "1272",
            "label": "PARENTOF",
            "properties": {
              "ordinal": "Primary",
              "view_id": "1000"
            }
          },
          {
            "source_id": "200",
            "target_id": "1272",
            "label": "CANFOLLOW",
            "properties": {
              "ordinal": "Primary",
              "view_id": "1000"
            }
          }
        ],
        "score_components": {
          "relationship_chain": 1.0,
          "sequence_path": 1.0
        },
        "abstraction_factor": 1.3,
        "graph_path_info": {
          "path_types": [
            "relationship_chain",
            "vulnerability_sequence_forward",
            "vulnerability_sequence_backward"
          ],
          "best_paths": {
            "relationship_chain": {
              "path": [
                [
                  "200",
                  "1272",
                  "CANFOLLOW"
                ]
              ],
              "score": 1.0,
              "type": "relationship_chain",
              "source": "200"
            },
            "vulnerability_sequence_forward": {
              "path": [
                [
                  "200",
                  "1272",
                  "CANFOLLOW"
                ]
              ],
              "score": 0.9,
              "type": "vulnerability_sequence_forward",
              "source": "200"
            },
            "vulnerability_sequence_backward": {
              "path": [
                [
                  "1272",
                  "200",
                  "CANPRECEDE"
                ]
              ],
              "score": 1.0,
              "type": "vulnerability_sequence_backward",
              "source": "200"
            }
          }
        },
        "position": "before",
        "sources": [
          "graph"
        ],
        "source": "graph",
        "mapping_notes": {
          "usage": "Allowed",
          "rationale": "This CWE entry is at the Base level of abstraction, which is a preferred level of abstraction for mapping to the root causes of vulnerabilities.",
          "comments": "Carefully read both the name and description to ensure that this mapping is an appropriate fit. Do not try to 'force' a mapping to a lower-level Base/Variant simply to comply with this preferred level of abstraction.",
          "reasons": [
            "Acceptable-Use"
          ]
        },
        "score_info": {
          "retrievers": [
            "graph"
          ],
          "retriever_count": 1,
          "normalized_scores": {
            "graph": 2.2100000000000004
          }
        }
      },
      "similarity": 2.2100000000000004
    }
  ],
  "identified_cwes": {
    "analyzer": [
      "CWE-1272",
      "CWE-280",
      "CWE-926",
      "CWE-1021",
      "CWE-927",
      "CWE-213",
      "CWE-285",
      "CWE-284",
      "CWE-200",
      "CWE-287",
      "CWE-497"
    ],
    "critic_additional": []
  },
  "keyphrase_cwe_mapping": {}
}