{
  "vulnerability_info": "VulnerabilityInfo(cve_id='CVE-2025-1542', description='Improper **permission control vulnerability** in the OXARI ServiceDesk application could allow an attacker using a guest access or an unprivileged account to gain additional administrative permissions in the application.This issue affects OXARI ServiceDesk in versions before 2.0.324.0.', key_phrases={'rootcause': ['permission control vulnerability', 'Improper permission control'], 'weakness': '', 'impact': 'gain additional administrative permissions', 'vector': '', 'attacker': 'attacker', 'product': 'OXARI ServiceDesk', 'version': 'before 2.0.324.0', 'component': ''}, reference_content='## Analysis of CVE-2025-1542 based on provided content:\\n\\n**1. Verification:**\\n\\nThe content directly relates to CVE-2025-1542. The advisory from cert.pl explicitly references the CVE ID and describes a vulnerability in OXARI ServiceDesk software.\\n\\n**2. Extracted Information:**\\n\\n*   **Root cause of vulnerability:** Improper permission control.\\n*   **Weaknesses/vulnerabilities present:** Incorrect Authorization (CWE-863).\\n*   **Impact of exploitation:** An attacker with guest access or an unprivileged account can gain additional administrative permissions in the application.\\n*   **Attack vectors:** Not explicitly detailed, but implied to be through exploiting the improper permission control with limited privileges.\\n*   **Required attacker capabilities/position:** An attacker needs to have guest access or an unprivileged account.\\n*   **Mitigation or fix:** Upgrade to version 2.0.324.0 or later.\\n\\n**3. Additional Details (compared to a placeholder CVE description):**\\n\\nThe provided content offers significantly more detail than a placeholder CVE description would. It specifies:\\n\\n*   The affected vendor (Infonet Projekt SA).\\n*   The specific product (OXARI ServiceDesk).\\n*   The vulnerable versions (all before 2.0.324.0).\\n*   The CWE identifier (CWE-863).\\n*   The source of the report (Report to CERT Polska).\\n*   Credit to the researcher who discovered the vulnerability.\\n\\n**Overall:**\\n\\nThe content is highly relevant to CVE-2025-1542 and provides a detailed description of the vulnerability, its impact, and how to mitigate it.', similar_info={'cwe_distribution': {}, 'cwe_consensus': '', 'similarity_stats': {'thresholds': [], 'total_samples_by_threshold': {}, 'top_cwes_by_threshold': {}}}, similarity_summary=SimilarityInsight(consensus_cwe='', top_cwes=[], confidence_levels={}, total_samples=0), analysis='', analysis_with_relationships='', criticism='', resolution='', relevant_cwes=[{'metadata': {'doc_id': '732', 'name': 'Incorrect Permission Assignment for Critical Resource', 'source': 'sparse', 'original_content': 'The product specifies permissions for a security-critical resource in a way that allows that resource to be read or modified by unintended actors.', 'keyphrase_sources': [{'id': 'rootcause:permission control vulnerability', 'keyphrase': 'permission control vulnerability', 'type': 'rootcause'}, {'id': 'rootcause:Improper permission control', 'keyphrase': 'Improper permission control', 'type': 'rootcause'}, {'id': 'impact:gain additional administrative permissions', 'keyphrase': 'gain additional administrative permissions', 'type': 'impact'}, {'id': 'attacker:attacker', 'keyphrase': 'attacker', 'type': 'attacker'}, {'id': 'product:OXARI ServiceDesk', 'keyphrase': 'OXARI ServiceDesk', 'type': 'product'}, {'id': 'version:before 2.0.324.0', 'keyphrase': 'before 2.0.324.0', 'type': 'version'}]}, 'similarity': np.float64(271.0147874084002)}, {'metadata': {'doc_id': '862', 'name': 'Missing Authorization', 'source': 'sparse', 'original_content': 'The product does not perform an authorization check when an actor attempts to access a resource or perform an action.', 'keyphrase_sources': [{'id': 'rootcause:permission control vulnerability', 'keyphrase': 'permission control vulnerability', 'type': 'rootcause'}, {'id': 'rootcause:Improper permission control', 'keyphrase': 'Improper permission control', 'type': 'rootcause'}, {'id': 'impact:gain additional administrative permissions', 'keyphrase': 'gain additional administrative permissions', 'type': 'impact'}, {'id': 'attacker:attacker', 'keyphrase': 'attacker', 'type': 'attacker'}, {'id': 'version:before 2.0.324.0', 'keyphrase': 'before 2.0.324.0', 'type': 'version'}]}, 'similarity': np.float64(265.4726913453909)}, {'metadata': {'doc_id': '285', 'name': 'Improper Authorization', 'source': 'sparse', 'original_content': 'The product does not perform or incorrectly performs an authorization check when an actor attempts to access a resource or perform an action.', 'keyphrase_sources': [{'id': 'rootcause:permission control vulnerability', 'keyphrase': 'permission control vulnerability', 'type': 'rootcause'}, {'id': 'rootcause:Improper permission control', 'keyphrase': 'Improper permission control', 'type': 'rootcause'}, {'id': 'impact:gain additional administrative permissions', 'keyphrase': 'gain additional administrative permissions', 'type': 'impact'}, {'id': 'attacker:attacker', 'keyphrase': 'attacker', 'type': 'attacker'}, {'id': 'product:OXARI ServiceDesk', 'keyphrase': 'OXARI ServiceDesk', 'type': 'product'}, {'id': 'version:before 2.0.324.0', 'keyphrase': 'before 2.0.324.0', 'type': 'version'}]}, 'similarity': np.float64(261.25874639544224)}, {'metadata': {'doc_id': '269', 'name': 'Improper Privilege Management', 'source': 'sparse', 'original_content': 'The product does not properly assign, modify, track, or check privileges for an actor, creating an unintended sphere of control for that actor.', 'keyphrase_sources': [{'id': 'rootcause:permission control vulnerability', 'keyphrase': 'permission control vulnerability', 'type': 'rootcause'}, {'id': 'rootcause:Improper permission control', 'keyphrase': 'Improper permission control', 'type': 'rootcause'}, {'id': 'impact:gain additional administrative permissions', 'keyphrase': 'gain additional administrative permissions', 'type': 'impact'}, {'id': 'attacker:attacker', 'keyphrase': 'attacker', 'type': 'attacker'}, {'id': 'product:OXARI ServiceDesk', 'keyphrase': 'OXARI ServiceDesk', 'type': 'product'}, {'id': 'version:before 2.0.324.0', 'keyphrase': 'before 2.0.324.0', 'type': 'version'}]}, 'similarity': np.float64(257.6747561630914)}, {'metadata': {'doc_id': '863', 'name': 'Incorrect Authorization', 'source': 'sparse', 'original_content': 'The product performs an authorization check when an actor attempts to access a resource or perform an action, but it does not correctly perform the check.', 'keyphrase_sources': [{'id': 'rootcause:permission control vulnerability', 'keyphrase': 'permission control vulnerability', 'type': 'rootcause'}, {'id': 'rootcause:Improper permission control', 'keyphrase': 'Improper permission control', 'type': 'rootcause'}]}, 'similarity': np.float64(255.1136171920417)}, {'metadata': {'doc_id': '267', 'name': 'Privilege Defined With Unsafe Actions', 'source': 'sparse', 'original_content': 'A particular privilege, role, capability, or right can be used to perform unsafe actions that were not intended, even when it is assigned to the correct entity.', 'keyphrase_sources': [{'id': 'impact:gain additional administrative permissions', 'keyphrase': 'gain additional administrative permissions', 'type': 'impact'}, {'id': 'product:OXARI ServiceDesk', 'keyphrase': 'OXARI ServiceDesk', 'type': 'product'}, {'id': 'version:before 2.0.324.0', 'keyphrase': 'before 2.0.324.0', 'type': 'version'}]}, 'similarity': np.float64(89.33397154312156)}, {'metadata': {'doc_id': '306', 'name': 'Missing Authentication for Critical Function', 'source': 'sparse', 'original_content': 'The product does not perform any authentication for functionality that requires a provable user identity or consumes a significant amount of resources.', 'keyphrase_sources': [{'id': 'attacker:attacker', 'keyphrase': 'attacker', 'type': 'attacker'}, {'id': 'product:OXARI ServiceDesk', 'keyphrase': 'OXARI ServiceDesk', 'type': 'product'}]}, 'similarity': np.float64(79.60159246630775)}], identified_cwes={'analyzer': [], 'critic_additional': []})",
  "retrieval_results": {
    "has_multiple_keyphrases": true,
    "keyphrase_cwe_sets": {
      "rootcause:permission control vulnerability": {
        "keyphrase": "permission control vulnerability",
        "type": "rootcause",
        "cwes": [
          {
            "metadata": {
              "doc_id": "732",
              "name": "Incorrect Permission Assignment for Critical Resource",
              "source": "sparse",
              "original_content": "The product specifies permissions for a security-critical resource in a way that allows that resource to be read or modified by unintended actors.",
              "keyphrase_sources": [
                {
                  "id": "rootcause:permission control vulnerability",
                  "keyphrase": "permission control vulnerability",
                  "type": "rootcause"
                },
                {
                  "id": "rootcause:Improper permission control",
                  "keyphrase": "Improper permission control",
                  "type": "rootcause"
                },
                {
                  "id": "impact:gain additional administrative permissions",
                  "keyphrase": "gain additional administrative permissions",
                  "type": "impact"
                },
                {
                  "id": "attacker:attacker",
                  "keyphrase": "attacker",
                  "type": "attacker"
                },
                {
                  "id": "product:OXARI ServiceDesk",
                  "keyphrase": "OXARI ServiceDesk",
                  "type": "product"
                },
                {
                  "id": "version:before 2.0.324.0",
                  "keyphrase": "before 2.0.324.0",
                  "type": "version"
                }
              ]
            },
            "similarity": 271.0147874084002
          },
          {
            "metadata": {
              "doc_id": "862",
              "name": "Missing Authorization",
              "source": "sparse",
              "original_content": "The product does not perform an authorization check when an actor attempts to access a resource or perform an action.",
              "keyphrase_sources": [
                {
                  "id": "rootcause:permission control vulnerability",
                  "keyphrase": "permission control vulnerability",
                  "type": "rootcause"
                },
                {
                  "id": "rootcause:Improper permission control",
                  "keyphrase": "Improper permission control",
                  "type": "rootcause"
                },
                {
                  "id": "impact:gain additional administrative permissions",
                  "keyphrase": "gain additional administrative permissions",
                  "type": "impact"
                },
                {
                  "id": "attacker:attacker",
                  "keyphrase": "attacker",
                  "type": "attacker"
                },
                {
                  "id": "version:before 2.0.324.0",
                  "keyphrase": "before 2.0.324.0",
                  "type": "version"
                }
              ]
            },
            "similarity": 265.4726913453909
          },
          {
            "metadata": {
              "doc_id": "285",
              "name": "Improper Authorization",
              "source": "sparse",
              "original_content": "The product does not perform or incorrectly performs an authorization check when an actor attempts to access a resource or perform an action.",
              "keyphrase_sources": [
                {
                  "id": "rootcause:permission control vulnerability",
                  "keyphrase": "permission control vulnerability",
                  "type": "rootcause"
                },
                {
                  "id": "rootcause:Improper permission control",
                  "keyphrase": "Improper permission control",
                  "type": "rootcause"
                },
                {
                  "id": "impact:gain additional administrative permissions",
                  "keyphrase": "gain additional administrative permissions",
                  "type": "impact"
                },
                {
                  "id": "attacker:attacker",
                  "keyphrase": "attacker",
                  "type": "attacker"
                },
                {
                  "id": "product:OXARI ServiceDesk",
                  "keyphrase": "OXARI ServiceDesk",
                  "type": "product"
                },
                {
                  "id": "version:before 2.0.324.0",
                  "keyphrase": "before 2.0.324.0",
                  "type": "version"
                }
              ]
            },
            "similarity": 261.25874639544224
          },
          {
            "metadata": {
              "doc_id": "269",
              "name": "Improper Privilege Management",
              "source": "sparse",
              "original_content": "The product does not properly assign, modify, track, or check privileges for an actor, creating an unintended sphere of control for that actor.",
              "keyphrase_sources": [
                {
                  "id": "rootcause:permission control vulnerability",
                  "keyphrase": "permission control vulnerability",
                  "type": "rootcause"
                },
                {
                  "id": "rootcause:Improper permission control",
                  "keyphrase": "Improper permission control",
                  "type": "rootcause"
                },
                {
                  "id": "impact:gain additional administrative permissions",
                  "keyphrase": "gain additional administrative permissions",
                  "type": "impact"
                },
                {
                  "id": "attacker:attacker",
                  "keyphrase": "attacker",
                  "type": "attacker"
                },
                {
                  "id": "product:OXARI ServiceDesk",
                  "keyphrase": "OXARI ServiceDesk",
                  "type": "product"
                },
                {
                  "id": "version:before 2.0.324.0",
                  "keyphrase": "before 2.0.324.0",
                  "type": "version"
                }
              ]
            },
            "similarity": 257.6747561630914
          },
          {
            "metadata": {
              "doc_id": "863",
              "name": "Incorrect Authorization",
              "source": "sparse",
              "original_content": "The product performs an authorization check when an actor attempts to access a resource or perform an action, but it does not correctly perform the check.",
              "keyphrase_sources": [
                {
                  "id": "rootcause:permission control vulnerability",
                  "keyphrase": "permission control vulnerability",
                  "type": "rootcause"
                },
                {
                  "id": "rootcause:Improper permission control",
                  "keyphrase": "Improper permission control",
                  "type": "rootcause"
                }
              ]
            },
            "similarity": 255.1136171920417
          }
        ]
      },
      "rootcause:Improper permission control": {
        "keyphrase": "Improper permission control",
        "type": "rootcause",
        "cwes": [
          {
            "metadata": {
              "doc_id": "732",
              "name": "Incorrect Permission Assignment for Critical Resource",
              "source": "sparse",
              "original_content": "The product specifies permissions for a security-critical resource in a way that allows that resource to be read or modified by unintended actors."
            },
            "similarity": 273.1632312478546
          },
          {
            "metadata": {
              "doc_id": "862",
              "name": "Missing Authorization",
              "source": "sparse",
              "original_content": "The product does not perform an authorization check when an actor attempts to access a resource or perform an action."
            },
            "similarity": 266.34680737439567
          },
          {
            "metadata": {
              "doc_id": "285",
              "name": "Improper Authorization",
              "source": "sparse",
              "original_content": "The product does not perform or incorrectly performs an authorization check when an actor attempts to access a resource or perform an action."
            },
            "similarity": 266.12992988887885
          },
          {
            "metadata": {
              "doc_id": "269",
              "name": "Improper Privilege Management",
              "source": "sparse",
              "original_content": "The product does not properly assign, modify, track, or check privileges for an actor, creating an unintended sphere of control for that actor."
            },
            "similarity": 262.375162535915
          },
          {
            "metadata": {
              "doc_id": "863",
              "name": "Incorrect Authorization",
              "source": "sparse",
              "original_content": "The product performs an authorization check when an actor attempts to access a resource or perform an action, but it does not correctly perform the check."
            },
            "similarity": 257.74971896204755
          }
        ]
      },
      "impact:gain additional administrative permissions": {
        "keyphrase": "gain additional administrative permissions",
        "type": "impact",
        "cwes": [
          {
            "metadata": {
              "doc_id": "732",
              "name": "Incorrect Permission Assignment for Critical Resource",
              "source": "sparse",
              "original_content": "The product specifies permissions for a security-critical resource in a way that allows that resource to be read or modified by unintended actors."
            },
            "similarity": 94.44671488898321
          },
          {
            "metadata": {
              "doc_id": "862",
              "name": "Missing Authorization",
              "source": "sparse",
              "original_content": "The product does not perform an authorization check when an actor attempts to access a resource or perform an action."
            },
            "similarity": 93.49288202454251
          },
          {
            "metadata": {
              "doc_id": "269",
              "name": "Improper Privilege Management",
              "source": "sparse",
              "original_content": "The product does not properly assign, modify, track, or check privileges for an actor, creating an unintended sphere of control for that actor."
            },
            "similarity": 92.6143757014347
          },
          {
            "metadata": {
              "doc_id": "267",
              "name": "Privilege Defined With Unsafe Actions",
              "source": "sparse",
              "original_content": "A particular privilege, role, capability, or right can be used to perform unsafe actions that were not intended, even when it is assigned to the correct entity.",
              "keyphrase_sources": [
                {
                  "id": "impact:gain additional administrative permissions",
                  "keyphrase": "gain additional administrative permissions",
                  "type": "impact"
                },
                {
                  "id": "product:OXARI ServiceDesk",
                  "keyphrase": "OXARI ServiceDesk",
                  "type": "product"
                },
                {
                  "id": "version:before 2.0.324.0",
                  "keyphrase": "before 2.0.324.0",
                  "type": "version"
                }
              ]
            },
            "similarity": 89.33397154312156
          },
          {
            "metadata": {
              "doc_id": "285",
              "name": "Improper Authorization",
              "source": "sparse",
              "original_content": "The product does not perform or incorrectly performs an authorization check when an actor attempts to access a resource or perform an action."
            },
            "similarity": 88.32259673886995
          }
        ]
      },
      "attacker:attacker": {
        "keyphrase": "attacker",
        "type": "attacker",
        "cwes": [
          {
            "metadata": {
              "doc_id": "732",
              "name": "Incorrect Permission Assignment for Critical Resource",
              "source": "sparse",
              "original_content": "The product specifies permissions for a security-critical resource in a way that allows that resource to be read or modified by unintended actors."
            },
            "similarity": 83.66233782577
          },
          {
            "metadata": {
              "doc_id": "269",
              "name": "Improper Privilege Management",
              "source": "sparse",
              "original_content": "The product does not properly assign, modify, track, or check privileges for an actor, creating an unintended sphere of control for that actor."
            },
            "similarity": 82.15732397914924
          },
          {
            "metadata": {
              "doc_id": "285",
              "name": "Improper Authorization",
              "source": "sparse",
              "original_content": "The product does not perform or incorrectly performs an authorization check when an actor attempts to access a resource or perform an action."
            },
            "similarity": 81.36161482187487
          },
          {
            "metadata": {
              "doc_id": "862",
              "name": "Missing Authorization",
              "source": "sparse",
              "original_content": "The product does not perform an authorization check when an actor attempts to access a resource or perform an action."
            },
            "similarity": 80.72156610020797
          },
          {
            "metadata": {
              "doc_id": "306",
              "name": "Missing Authentication for Critical Function",
              "source": "sparse",
              "original_content": "The product does not perform any authentication for functionality that requires a provable user identity or consumes a significant amount of resources.",
              "keyphrase_sources": [
                {
                  "id": "attacker:attacker",
                  "keyphrase": "attacker",
                  "type": "attacker"
                },
                {
                  "id": "product:OXARI ServiceDesk",
                  "keyphrase": "OXARI ServiceDesk",
                  "type": "product"
                }
              ]
            },
            "similarity": 79.60159246630775
          }
        ]
      },
      "product:OXARI ServiceDesk": {
        "keyphrase": "OXARI ServiceDesk",
        "type": "product",
        "cwes": [
          {
            "metadata": {
              "doc_id": "306",
              "name": "Missing Authentication for Critical Function",
              "source": "sparse",
              "original_content": "The product does not perform any authentication for functionality that requires a provable user identity or consumes a significant amount of resources."
            },
            "similarity": 79.75950924174904
          },
          {
            "metadata": {
              "doc_id": "732",
              "name": "Incorrect Permission Assignment for Critical Resource",
              "source": "sparse",
              "original_content": "The product specifies permissions for a security-critical resource in a way that allows that resource to be read or modified by unintended actors."
            },
            "similarity": 77.15055797699456
          },
          {
            "metadata": {
              "doc_id": "269",
              "name": "Improper Privilege Management",
              "source": "sparse",
              "original_content": "The product does not properly assign, modify, track, or check privileges for an actor, creating an unintended sphere of control for that actor."
            },
            "similarity": 75.79487047574436
          },
          {
            "metadata": {
              "doc_id": "285",
              "name": "Improper Authorization",
              "source": "sparse",
              "original_content": "The product does not perform or incorrectly performs an authorization check when an actor attempts to access a resource or perform an action."
            },
            "similarity": 74.94036814887508
          },
          {
            "metadata": {
              "doc_id": "267",
              "name": "Privilege Defined With Unsafe Actions",
              "source": "sparse",
              "original_content": "A particular privilege, role, capability, or right can be used to perform unsafe actions that were not intended, even when it is assigned to the correct entity."
            },
            "similarity": 74.933541649958
          }
        ]
      },
      "version:before 2.0.324.0": {
        "keyphrase": "before 2.0.324.0",
        "type": "version",
        "cwes": [
          {
            "metadata": {
              "doc_id": "732",
              "name": "Incorrect Permission Assignment for Critical Resource",
              "source": "sparse",
              "original_content": "The product specifies permissions for a security-critical resource in a way that allows that resource to be read or modified by unintended actors."
            },
            "similarity": 84.47910657983446
          },
          {
            "metadata": {
              "doc_id": "269",
              "name": "Improper Privilege Management",
              "source": "sparse",
              "original_content": "The product does not properly assign, modify, track, or check privileges for an actor, creating an unintended sphere of control for that actor."
            },
            "similarity": 82.99902040160866
          },
          {
            "metadata": {
              "doc_id": "285",
              "name": "Improper Authorization",
              "source": "sparse",
              "original_content": "The product does not perform or incorrectly performs an authorization check when an actor attempts to access a resource or perform an action."
            },
            "similarity": 82.57674873664948
          },
          {
            "metadata": {
              "doc_id": "267",
              "name": "Privilege Defined With Unsafe Actions",
              "source": "sparse",
              "original_content": "A particular privilege, role, capability, or right can be used to perform unsafe actions that were not intended, even when it is assigned to the correct entity."
            },
            "similarity": 82.38211051441785
          },
          {
            "metadata": {
              "doc_id": "862",
              "name": "Missing Authorization",
              "source": "sparse",
              "original_content": "The product does not perform an authorization check when an actor attempts to access a resource or perform an action."
            },
            "similarity": 81.9819833047823
          }
        ]
      }
    },
    "keyphrase_mapping": {
      "732": [
        {
          "id": "rootcause:permission control vulnerability",
          "keyphrase": "permission control vulnerability",
          "type": "rootcause"
        },
        {
          "id": "rootcause:Improper permission control",
          "keyphrase": "Improper permission control",
          "type": "rootcause"
        },
        {
          "id": "impact:gain additional administrative permissions",
          "keyphrase": "gain additional administrative permissions",
          "type": "impact"
        },
        {
          "id": "attacker:attacker",
          "keyphrase": "attacker",
          "type": "attacker"
        },
        {
          "id": "product:OXARI ServiceDesk",
          "keyphrase": "OXARI ServiceDesk",
          "type": "product"
        },
        {
          "id": "version:before 2.0.324.0",
          "keyphrase": "before 2.0.324.0",
          "type": "version"
        }
      ],
      "862": [
        {
          "id": "rootcause:permission control vulnerability",
          "keyphrase": "permission control vulnerability",
          "type": "rootcause"
        },
        {
          "id": "rootcause:Improper permission control",
          "keyphrase": "Improper permission control",
          "type": "rootcause"
        },
        {
          "id": "impact:gain additional administrative permissions",
          "keyphrase": "gain additional administrative permissions",
          "type": "impact"
        },
        {
          "id": "attacker:attacker",
          "keyphrase": "attacker",
          "type": "attacker"
        },
        {
          "id": "version:before 2.0.324.0",
          "keyphrase": "before 2.0.324.0",
          "type": "version"
        }
      ],
      "285": [
        {
          "id": "rootcause:permission control vulnerability",
          "keyphrase": "permission control vulnerability",
          "type": "rootcause"
        },
        {
          "id": "rootcause:Improper permission control",
          "keyphrase": "Improper permission control",
          "type": "rootcause"
        },
        {
          "id": "impact:gain additional administrative permissions",
          "keyphrase": "gain additional administrative permissions",
          "type": "impact"
        },
        {
          "id": "attacker:attacker",
          "keyphrase": "attacker",
          "type": "attacker"
        },
        {
          "id": "product:OXARI ServiceDesk",
          "keyphrase": "OXARI ServiceDesk",
          "type": "product"
        },
        {
          "id": "version:before 2.0.324.0",
          "keyphrase": "before 2.0.324.0",
          "type": "version"
        }
      ],
      "269": [
        {
          "id": "rootcause:permission control vulnerability",
          "keyphrase": "permission control vulnerability",
          "type": "rootcause"
        },
        {
          "id": "rootcause:Improper permission control",
          "keyphrase": "Improper permission control",
          "type": "rootcause"
        },
        {
          "id": "impact:gain additional administrative permissions",
          "keyphrase": "gain additional administrative permissions",
          "type": "impact"
        },
        {
          "id": "attacker:attacker",
          "keyphrase": "attacker",
          "type": "attacker"
        },
        {
          "id": "product:OXARI ServiceDesk",
          "keyphrase": "OXARI ServiceDesk",
          "type": "product"
        },
        {
          "id": "version:before 2.0.324.0",
          "keyphrase": "before 2.0.324.0",
          "type": "version"
        }
      ],
      "863": [
        {
          "id": "rootcause:permission control vulnerability",
          "keyphrase": "permission control vulnerability",
          "type": "rootcause"
        },
        {
          "id": "rootcause:Improper permission control",
          "keyphrase": "Improper permission control",
          "type": "rootcause"
        }
      ],
      "267": [
        {
          "id": "impact:gain additional administrative permissions",
          "keyphrase": "gain additional administrative permissions",
          "type": "impact"
        },
        {
          "id": "product:OXARI ServiceDesk",
          "keyphrase": "OXARI ServiceDesk",
          "type": "product"
        },
        {
          "id": "version:before 2.0.324.0",
          "keyphrase": "before 2.0.324.0",
          "type": "version"
        }
      ],
      "306": [
        {
          "id": "attacker:attacker",
          "keyphrase": "attacker",
          "type": "attacker"
        },
        {
          "id": "product:OXARI ServiceDesk",
          "keyphrase": "OXARI ServiceDesk",
          "type": "product"
        }
      ]
    },
    "relevant_cwes": [
      {
        "metadata": {
          "doc_id": "732",
          "name": "Incorrect Permission Assignment for Critical Resource",
          "source": "sparse",
          "original_content": "The product specifies permissions for a security-critical resource in a way that allows that resource to be read or modified by unintended actors.",
          "keyphrase_sources": [
            {
              "id": "rootcause:permission control vulnerability",
              "keyphrase": "permission control vulnerability",
              "type": "rootcause"
            },
            {
              "id": "rootcause:Improper permission control",
              "keyphrase": "Improper permission control",
              "type": "rootcause"
            },
            {
              "id": "impact:gain additional administrative permissions",
              "keyphrase": "gain additional administrative permissions",
              "type": "impact"
            },
            {
              "id": "attacker:attacker",
              "keyphrase": "attacker",
              "type": "attacker"
            },
            {
              "id": "product:OXARI ServiceDesk",
              "keyphrase": "OXARI ServiceDesk",
              "type": "product"
            },
            {
              "id": "version:before 2.0.324.0",
              "keyphrase": "before 2.0.324.0",
              "type": "version"
            }
          ]
        },
        "similarity": 271.0147874084002
      },
      {
        "metadata": {
          "doc_id": "862",
          "name": "Missing Authorization",
          "source": "sparse",
          "original_content": "The product does not perform an authorization check when an actor attempts to access a resource or perform an action.",
          "keyphrase_sources": [
            {
              "id": "rootcause:permission control vulnerability",
              "keyphrase": "permission control vulnerability",
              "type": "rootcause"
            },
            {
              "id": "rootcause:Improper permission control",
              "keyphrase": "Improper permission control",
              "type": "rootcause"
            },
            {
              "id": "impact:gain additional administrative permissions",
              "keyphrase": "gain additional administrative permissions",
              "type": "impact"
            },
            {
              "id": "attacker:attacker",
              "keyphrase": "attacker",
              "type": "attacker"
            },
            {
              "id": "version:before 2.0.324.0",
              "keyphrase": "before 2.0.324.0",
              "type": "version"
            }
          ]
        },
        "similarity": 265.4726913453909
      },
      {
        "metadata": {
          "doc_id": "285",
          "name": "Improper Authorization",
          "source": "sparse",
          "original_content": "The product does not perform or incorrectly performs an authorization check when an actor attempts to access a resource or perform an action.",
          "keyphrase_sources": [
            {
              "id": "rootcause:permission control vulnerability",
              "keyphrase": "permission control vulnerability",
              "type": "rootcause"
            },
            {
              "id": "rootcause:Improper permission control",
              "keyphrase": "Improper permission control",
              "type": "rootcause"
            },
            {
              "id": "impact:gain additional administrative permissions",
              "keyphrase": "gain additional administrative permissions",
              "type": "impact"
            },
            {
              "id": "attacker:attacker",
              "keyphrase": "attacker",
              "type": "attacker"
            },
            {
              "id": "product:OXARI ServiceDesk",
              "keyphrase": "OXARI ServiceDesk",
              "type": "product"
            },
            {
              "id": "version:before 2.0.324.0",
              "keyphrase": "before 2.0.324.0",
              "type": "version"
            }
          ]
        },
        "similarity": 261.25874639544224
      },
      {
        "metadata": {
          "doc_id": "269",
          "name": "Improper Privilege Management",
          "source": "sparse",
          "original_content": "The product does not properly assign, modify, track, or check privileges for an actor, creating an unintended sphere of control for that actor.",
          "keyphrase_sources": [
            {
              "id": "rootcause:permission control vulnerability",
              "keyphrase": "permission control vulnerability",
              "type": "rootcause"
            },
            {
              "id": "rootcause:Improper permission control",
              "keyphrase": "Improper permission control",
              "type": "rootcause"
            },
            {
              "id": "impact:gain additional administrative permissions",
              "keyphrase": "gain additional administrative permissions",
              "type": "impact"
            },
            {
              "id": "attacker:attacker",
              "keyphrase": "attacker",
              "type": "attacker"
            },
            {
              "id": "product:OXARI ServiceDesk",
              "keyphrase": "OXARI ServiceDesk",
              "type": "product"
            },
            {
              "id": "version:before 2.0.324.0",
              "keyphrase": "before 2.0.324.0",
              "type": "version"
            }
          ]
        },
        "similarity": 257.6747561630914
      },
      {
        "metadata": {
          "doc_id": "863",
          "name": "Incorrect Authorization",
          "source": "sparse",
          "original_content": "The product performs an authorization check when an actor attempts to access a resource or perform an action, but it does not correctly perform the check.",
          "keyphrase_sources": [
            {
              "id": "rootcause:permission control vulnerability",
              "keyphrase": "permission control vulnerability",
              "type": "rootcause"
            },
            {
              "id": "rootcause:Improper permission control",
              "keyphrase": "Improper permission control",
              "type": "rootcause"
            }
          ]
        },
        "similarity": 255.1136171920417
      },
      {
        "metadata": {
          "doc_id": "267",
          "name": "Privilege Defined With Unsafe Actions",
          "source": "sparse",
          "original_content": "A particular privilege, role, capability, or right can be used to perform unsafe actions that were not intended, even when it is assigned to the correct entity.",
          "keyphrase_sources": [
            {
              "id": "impact:gain additional administrative permissions",
              "keyphrase": "gain additional administrative permissions",
              "type": "impact"
            },
            {
              "id": "product:OXARI ServiceDesk",
              "keyphrase": "OXARI ServiceDesk",
              "type": "product"
            },
            {
              "id": "version:before 2.0.324.0",
              "keyphrase": "before 2.0.324.0",
              "type": "version"
            }
          ]
        },
        "similarity": 89.33397154312156
      },
      {
        "metadata": {
          "doc_id": "306",
          "name": "Missing Authentication for Critical Function",
          "source": "sparse",
          "original_content": "The product does not perform any authentication for functionality that requires a provable user identity or consumes a significant amount of resources.",
          "keyphrase_sources": [
            {
              "id": "attacker:attacker",
              "keyphrase": "attacker",
              "type": "attacker"
            },
            {
              "id": "product:OXARI ServiceDesk",
              "keyphrase": "OXARI ServiceDesk",
              "type": "product"
            }
          ]
        },
        "similarity": 79.60159246630775
      }
    ],
    "enhanced_query": "# Vulnerability Description\n\n    Improper **permission control vulnerability** in the OXARI ServiceDesk application could allow an attacker using a guest access or an unprivileged account to gain additional administrative permissions in the application.This issue affects OXARI ServiceDesk in versions before 2.0.324.0.\n\n    # Keyphrase-Specific CWE Analysis\n    This vulnerability contains multiple keyphrases that may map to different CWEs. \n    Please analyze each keyphrase separately and determine the most appropriate CWE(s) for each.\n\n    ## ROOTCAUSE: 'permission control vulnerability'\n\nRelevant CWEs for this ROOTCAUSE:\n\n### 1. CWE-732: Incorrect Permission Assignment for Critical Resource (Score: 271.01)\n\nThe product specifies permissions for a security-critical resource in a way that allows that resource to be read or modified by unintended actors....\n\n### 2. CWE-862: Missing Authorization (Score: 265.47)\n\nThe product does not perform an authorization check when an actor attempts to access a resource or perform an action....\n\n### 3. CWE-285: Improper Authorization (Score: 261.26)\n\nThe product does not perform or incorrectly performs an authorization check when an actor attempts to access a resource or perform an action....\n\n### 4. CWE-269: Improper Privilege Management (Score: 257.67)\n\nThe product does not properly assign, modify, track, or check privileges for an actor, creating an unintended sphere of control for that actor....\n\n### 5. CWE-863: Incorrect Authorization (Score: 255.11)\n\nThe product performs an authorization check when an actor attempts to access a resource or perform an action, but it does not correctly perform the check....\n\n## ROOTCAUSE: 'Improper permission control'\n\nRelevant CWEs for this ROOTCAUSE:\n\n### 1. CWE-732: Incorrect Permission Assignment for Critical Resource (Score: 271.01)\n\nThe product specifies permissions for a security-critical resource in a way that allows that resource to be read or modified by unintended actors....\n\n### 2. CWE-862: Missing Authorization (Score: 265.47)\n\nThe product does not perform an authorization check when an actor attempts to access a resource or perform an action....\n\n### 3. CWE-285: Improper Authorization (Score: 261.26)\n\nThe product does not perform or incorrectly performs an authorization check when an actor attempts to access a resource or perform an action....\n\n### 4. CWE-269: Improper Privilege Management (Score: 257.67)\n\nThe product does not properly assign, modify, track, or check privileges for an actor, creating an unintended sphere of control for that actor....\n\n### 5. CWE-863: Incorrect Authorization (Score: 255.11)\n\nThe product performs an authorization check when an actor attempts to access a resource or perform an action, but it does not correctly perform the check....\n\n## IMPACT: 'gain additional administrative permissions'\n\nRelevant CWEs for this IMPACT:\n\n### 1. CWE-732: Incorrect Permission Assignment for Critical Resource (Score: 271.01)\n\nThe product specifies permissions for a security-critical resource in a way that allows that resource to be read or modified by unintended actors....\n\n### 2. CWE-862: Missing Authorization (Score: 265.47)\n\nThe product does not perform an authorization check when an actor attempts to access a resource or perform an action....\n\n### 3. CWE-285: Improper Authorization (Score: 261.26)\n\nThe product does not perform or incorrectly performs an authorization check when an actor attempts to access a resource or perform an action....\n\n### 4. CWE-269: Improper Privilege Management (Score: 257.67)\n\nThe product does not properly assign, modify, track, or check privileges for an actor, creating an unintended sphere of control for that actor....\n\n### 5. CWE-267: Privilege Defined With Unsafe Actions (Score: 89.33)\n\nA particular privilege, role, capability, or right can be used to perform unsafe actions that were not intended, even when it is assigned to the correct entity....\n\n## ATTACKER: 'attacker'\n\nRelevant CWEs for this ATTACKER:\n\n### 1. CWE-732: Incorrect Permission Assignment for Critical Resource (Score: 271.01)\n\nThe product specifies permissions for a security-critical resource in a way that allows that resource to be read or modified by unintended actors....\n\n### 2. CWE-862: Missing Authorization (Score: 265.47)\n\nThe product does not perform an authorization check when an actor attempts to access a resource or perform an action....\n\n### 3. CWE-285: Improper Authorization (Score: 261.26)\n\nThe product does not perform or incorrectly performs an authorization check when an actor attempts to access a resource or perform an action....\n\n### 4. CWE-269: Improper Privilege Management (Score: 257.67)\n\nThe product does not properly assign, modify, track, or check privileges for an actor, creating an unintended sphere of control for that actor....\n\n### 5. CWE-306: Missing Authentication for Critical Function (Score: 79.60)\n\nThe product does not perform any authentication for functionality that requires a provable user identity or consumes a significant amount of resources....\n\n## PRODUCT: 'OXARI ServiceDesk'\n\nRelevant CWEs for this PRODUCT:\n\n### 1. CWE-732: Incorrect Permission Assignment for Critical Resource (Score: 271.01)\n\nThe product specifies permissions for a security-critical resource in a way that allows that resource to be read or modified by unintended actors....\n\n### 2. CWE-285: Improper Authorization (Score: 261.26)\n\nThe product does not perform or incorrectly performs an authorization check when an actor attempts to access a resource or perform an action....\n\n### 3. CWE-269: Improper Privilege Management (Score: 257.67)\n\nThe product does not properly assign, modify, track, or check privileges for an actor, creating an unintended sphere of control for that actor....\n\n### 4. CWE-267: Privilege Defined With Unsafe Actions (Score: 89.33)\n\nA particular privilege, role, capability, or right can be used to perform unsafe actions that were not intended, even when it is assigned to the correct entity....\n\n### 5. CWE-306: Missing Authentication for Critical Function (Score: 79.60)\n\nThe product does not perform any authentication for functionality that requires a provable user identity or consumes a significant amount of resources....\n\n## VERSION: 'before 2.0.324.0'\n\nRelevant CWEs for this VERSION:\n\n### 1. CWE-732: Incorrect Permission Assignment for Critical Resource (Score: 271.01)\n\nThe product specifies permissions for a security-critical resource in a way that allows that resource to be read or modified by unintended actors....\n\n### 2. CWE-862: Missing Authorization (Score: 265.47)\n\nThe product does not perform an authorization check when an actor attempts to access a resource or perform an action....\n\n### 3. CWE-285: Improper Authorization (Score: 261.26)\n\nThe product does not perform or incorrectly performs an authorization check when an actor attempts to access a resource or perform an action....\n\n### 4. CWE-269: Improper Privilege Management (Score: 257.67)\n\nThe product does not properly assign, modify, track, or check privileges for an actor, creating an unintended sphere of control for that actor....\n\n### 5. CWE-267: Privilege Defined With Unsafe Actions (Score: 89.33)\n\nA particular privilege, role, capability, or right can be used to perform unsafe actions that were not intended, even when it is assigned to the correct entity....\n\n\n    # Analysis Instructions\n    1. For each keyphrase, identify the most appropriate CWE(s) that represent the weakness.\n    2. Consider how the different keyphrases might relate to each other in the vulnerability chain.\n    3. Provide a final determination of primary CWE(s) and any secondary CWEs.\n    4. Format your response using the standard analysis template.\n\n    Please analyze how these different weaknesses interact and provide a comprehensive CWE classification.\n    "
  },
  "retrieval_time": 1.1147370338439941
}