{
  "vulnerability_info": "VulnerabilityInfo(cve_id='CVE-2024-8073', description='**Improper Input Validation** vulnerability in Hillstone Networks Hillstone Networks Web Application Firewall on 5.5R6 allows Command Injection.This issue affects Hillstone Networks Web Application Firewall from 5.5R6-2.6.7 through 5.5R6-2.8.13.', key_phrases={'rootcause': ['Improper Input Validation', 'Input Validation vulnerability'], 'weakness': 'command injection', 'impact': '', 'vector': '', 'attacker': '', 'product': 'Hillstone Networks Hillstone Networks Web Application Firewall', 'version': '5.5R6-2.6.7 through 5.5R6-2.8.13', 'component': ''}, reference_content=\"The provided content describes a command injection vulnerability in Hillstone Networks Web Application Firewall (WAF).\\n\\n**Root Cause of Vulnerability:**\\nThe vulnerability exists in the WAF's verification code page.\\n\\n**Weaknesses/Vulnerabilities:**\\n- Command Injection: The WAF's verification code page allows for command injection.\\n\\n**Impact of Exploitation:**\\n- Arbitrary Code Execution: Attackers can execute arbitrary code on the server by crafting malicious requests.\\n- Server Control: Successful exploitation can lead to complete control of the server.\\n\\n**Attack Vectors:**\\n- Malicious HTTP Requests: Attackers can inject commands into HTTP requests to the WAF's verification code page.\\n\\n**Required Attacker Capabilities/Position:**\\n- The attacker needs to be able to send crafted HTTP requests to the WAF's vulnerable verification code page.\\n- No specific position within the network is specified.\", similar_info={'cwe_distribution': {}, 'cwe_consensus': '', 'similarity_stats': {'thresholds': [], 'total_samples_by_threshold': {}, 'top_cwes_by_threshold': {}}}, similarity_summary=SimilarityInsight(consensus_cwe='', top_cwes=[], confidence_levels={}, total_samples=0), analysis='', analysis_with_relationships='', criticism='', resolution='', relevant_cwes=[{'metadata': {'doc_id': '20', 'name': 'Improper Input Validation', 'source': 'sparse', 'original_content': 'The product receives input or data, but it does\\n        not validate or incorrectly validates that the input has the\\n        properties that are required to process the data safely and\\n        correctly.', 'keyphrase_sources': [{'id': 'rootcause:Improper Input Validation', 'keyphrase': 'Improper Input Validation', 'type': 'rootcause'}, {'id': 'rootcause:Input Validation vulnerability', 'keyphrase': 'Input Validation vulnerability', 'type': 'rootcause'}, {'id': 'weakness:command injection', 'keyphrase': 'command injection', 'type': 'weakness'}, {'id': 'product:Hillstone Networks Hillstone Networks Web Application Firewall', 'keyphrase': 'Hillstone Networks Hillstone Networks Web Application Firewall', 'type': 'product'}]}, 'similarity': np.float64(206.5731349012634)}, {'metadata': {'doc_id': '1286', 'name': 'Improper Validation of Syntactic Correctness of Input', 'source': 'sparse', 'original_content': 'The product receives input that is expected to be well-formed - i.e., to comply with a certain syntax - but it does not validate or incorrectly validates that the input complies with the syntax.', 'keyphrase_sources': [{'id': 'rootcause:Improper Input Validation', 'keyphrase': 'Improper Input Validation', 'type': 'rootcause'}, {'id': 'rootcause:Input Validation vulnerability', 'keyphrase': 'Input Validation vulnerability', 'type': 'rootcause'}, {'id': 'product:Hillstone Networks Hillstone Networks Web Application Firewall', 'keyphrase': 'Hillstone Networks Hillstone Networks Web Application Firewall', 'type': 'product'}, {'id': 'version:5.5R6-2.6.7 through 5.5R6-2.8.13', 'keyphrase': '5.5R6-2.6.7 through 5.5R6-2.8.13', 'type': 'version'}]}, 'similarity': np.float64(200.80804005317242)}, {'metadata': {'doc_id': '113', 'name': \"Improper Neutralization of CRLF Sequences in HTTP Headers ('HTTP Request/Response Splitting')\", 'source': 'sparse', 'original_content': 'The product receives data from an HTTP agent/component (e.g., web server, proxy, browser, etc.), but it does not neutralize or incorrectly neutralizes CR and LF characters before the data is included in outgoing HTTP headers.', 'keyphrase_sources': [{'id': 'rootcause:Improper Input Validation', 'keyphrase': 'Improper Input Validation', 'type': 'rootcause'}, {'id': 'rootcause:Input Validation vulnerability', 'keyphrase': 'Input Validation vulnerability', 'type': 'rootcause'}, {'id': 'product:Hillstone Networks Hillstone Networks Web Application Firewall', 'keyphrase': 'Hillstone Networks Hillstone Networks Web Application Firewall', 'type': 'product'}, {'id': 'version:5.5R6-2.6.7 through 5.5R6-2.8.13', 'keyphrase': '5.5R6-2.6.7 through 5.5R6-2.8.13', 'type': 'version'}]}, 'similarity': np.float64(191.30476243186396)}, {'metadata': {'doc_id': '77', 'name': \"Improper Neutralization of Special Elements used in a Command ('Command Injection')\", 'source': 'sparse', 'original_content': 'The product constructs all or part of a command using externally-influenced input from an upstream component, but it does not neutralize or incorrectly neutralizes special elements that could modify the intended command when it is sent to a downstream component.', 'keyphrase_sources': [{'id': 'weakness:command injection', 'keyphrase': 'command injection', 'type': 'weakness'}]}, 'similarity': np.float64(189.01165220860432)}, {'metadata': {'doc_id': '138', 'name': 'Improper Neutralization of Special Elements', 'source': 'sparse', 'original_content': 'The product receives input from an upstream component, but it does not neutralize or incorrectly neutralizes special elements that could be interpreted as control elements or syntactic markers when they are sent to a downstream component.', 'keyphrase_sources': [{'id': 'rootcause:Improper Input Validation', 'keyphrase': 'Improper Input Validation', 'type': 'rootcause'}, {'id': 'rootcause:Input Validation vulnerability', 'keyphrase': 'Input Validation vulnerability', 'type': 'rootcause'}, {'id': 'weakness:command injection', 'keyphrase': 'command injection', 'type': 'weakness'}]}, 'similarity': np.float64(183.53247865643618)}, {'metadata': {'doc_id': '1285', 'name': 'Improper Validation of Specified Index, Position, or Offset in Input', 'source': 'sparse', 'original_content': 'The product receives input that is expected to specify an index, position, or offset into an indexable resource such as a buffer or file, but it does not validate or incorrectly validates that the specified index/position/offset has the required properties.', 'keyphrase_sources': [{'id': 'rootcause:Improper Input Validation', 'keyphrase': 'Improper Input Validation', 'type': 'rootcause'}]}, 'similarity': np.float64(183.3155526456191)}, {'metadata': {'doc_id': '78', 'name': \"Improper Neutralization of Special Elements used in an OS Command ('OS Command Injection')\", 'source': 'sparse', 'original_content': 'The product constructs all or part of an OS command using externally-influenced input from an upstream component, but it does not neutralize or incorrectly neutralizes special elements that could modify the intended OS command when it is sent to a downstream component.', 'keyphrase_sources': [{'id': 'rootcause:Input Validation vulnerability', 'keyphrase': 'Input Validation vulnerability', 'type': 'rootcause'}, {'id': 'weakness:command injection', 'keyphrase': 'command injection', 'type': 'weakness'}, {'id': 'version:5.5R6-2.6.7 through 5.5R6-2.8.13', 'keyphrase': '5.5R6-2.6.7 through 5.5R6-2.8.13', 'type': 'version'}]}, 'similarity': np.float64(181.12285547448866)}, {'metadata': {'doc_id': '790', 'name': 'Improper Filtering of Special Elements', 'source': 'sparse', 'original_content': 'The product receives data from an upstream component, but does not filter or incorrectly filters special elements before sending it to a downstream component.', 'keyphrase_sources': [{'id': 'weakness:command injection', 'keyphrase': 'command injection', 'type': 'weakness'}]}, 'similarity': np.float64(176.89350438568056)}, {'metadata': {'doc_id': '400', 'name': 'Uncontrolled Resource Consumption', 'source': 'sparse', 'original_content': 'The product does not properly control the allocation and maintenance of a limited resource, thereby enabling an actor to influence the amount of resources consumed, eventually leading to the exhaustion of available resources.', 'keyphrase_sources': [{'id': 'product:Hillstone Networks Hillstone Networks Web Application Firewall', 'keyphrase': 'Hillstone Networks Hillstone Networks Web Application Firewall', 'type': 'product'}, {'id': 'version:5.5R6-2.6.7 through 5.5R6-2.8.13', 'keyphrase': '5.5R6-2.6.7 through 5.5R6-2.8.13', 'type': 'version'}]}, 'similarity': np.float64(72.0857780767714)}, {'metadata': {'doc_id': '269', 'name': 'Improper Privilege Management', 'source': 'sparse', 'original_content': 'The product does not properly assign, modify, track, or check privileges for an actor, creating an unintended sphere of control for that actor.', 'keyphrase_sources': [{'id': 'product:Hillstone Networks Hillstone Networks Web Application Firewall', 'keyphrase': 'Hillstone Networks Hillstone Networks Web Application Firewall', 'type': 'product'}, {'id': 'version:5.5R6-2.6.7 through 5.5R6-2.8.13', 'keyphrase': '5.5R6-2.6.7 through 5.5R6-2.8.13', 'type': 'version'}]}, 'similarity': np.float64(70.18312971301314)}], identified_cwes={'analyzer': [], 'critic_additional': []})",
  "retrieval_results": {
    "has_multiple_keyphrases": true,
    "keyphrase_cwe_sets": {
      "rootcause:Improper Input Validation": {
        "keyphrase": "Improper Input Validation",
        "type": "rootcause",
        "cwes": [
          {
            "metadata": {
              "doc_id": "20",
              "name": "Improper Input Validation",
              "source": "sparse",
              "original_content": "The product receives input or data, but it does\n        not validate or incorrectly validates that the input has the\n        properties that are required to process the data safely and\n        correctly.",
              "keyphrase_sources": [
                {
                  "id": "rootcause:Improper Input Validation",
                  "keyphrase": "Improper Input Validation",
                  "type": "rootcause"
                },
                {
                  "id": "rootcause:Input Validation vulnerability",
                  "keyphrase": "Input Validation vulnerability",
                  "type": "rootcause"
                },
                {
                  "id": "weakness:command injection",
                  "keyphrase": "command injection",
                  "type": "weakness"
                },
                {
                  "id": "product:Hillstone Networks Hillstone Networks Web Application Firewall",
                  "keyphrase": "Hillstone Networks Hillstone Networks Web Application Firewall",
                  "type": "product"
                }
              ]
            },
            "similarity": 206.5731349012634
          },
          {
            "metadata": {
              "doc_id": "1286",
              "name": "Improper Validation of Syntactic Correctness of Input",
              "source": "sparse",
              "original_content": "The product receives input that is expected to be well-formed - i.e., to comply with a certain syntax - but it does not validate or incorrectly validates that the input complies with the syntax.",
              "keyphrase_sources": [
                {
                  "id": "rootcause:Improper Input Validation",
                  "keyphrase": "Improper Input Validation",
                  "type": "rootcause"
                },
                {
                  "id": "rootcause:Input Validation vulnerability",
                  "keyphrase": "Input Validation vulnerability",
                  "type": "rootcause"
                },
                {
                  "id": "product:Hillstone Networks Hillstone Networks Web Application Firewall",
                  "keyphrase": "Hillstone Networks Hillstone Networks Web Application Firewall",
                  "type": "product"
                },
                {
                  "id": "version:5.5R6-2.6.7 through 5.5R6-2.8.13",
                  "keyphrase": "5.5R6-2.6.7 through 5.5R6-2.8.13",
                  "type": "version"
                }
              ]
            },
            "similarity": 200.80804005317242
          },
          {
            "metadata": {
              "doc_id": "113",
              "name": "Improper Neutralization of CRLF Sequences in HTTP Headers ('HTTP Request/Response Splitting')",
              "source": "sparse",
              "original_content": "The product receives data from an HTTP agent/component (e.g., web server, proxy, browser, etc.), but it does not neutralize or incorrectly neutralizes CR and LF characters before the data is included in outgoing HTTP headers.",
              "keyphrase_sources": [
                {
                  "id": "rootcause:Improper Input Validation",
                  "keyphrase": "Improper Input Validation",
                  "type": "rootcause"
                },
                {
                  "id": "rootcause:Input Validation vulnerability",
                  "keyphrase": "Input Validation vulnerability",
                  "type": "rootcause"
                },
                {
                  "id": "product:Hillstone Networks Hillstone Networks Web Application Firewall",
                  "keyphrase": "Hillstone Networks Hillstone Networks Web Application Firewall",
                  "type": "product"
                },
                {
                  "id": "version:5.5R6-2.6.7 through 5.5R6-2.8.13",
                  "keyphrase": "5.5R6-2.6.7 through 5.5R6-2.8.13",
                  "type": "version"
                }
              ]
            },
            "similarity": 191.30476243186396
          },
          {
            "metadata": {
              "doc_id": "138",
              "name": "Improper Neutralization of Special Elements",
              "source": "sparse",
              "original_content": "The product receives input from an upstream component, but it does not neutralize or incorrectly neutralizes special elements that could be interpreted as control elements or syntactic markers when they are sent to a downstream component.",
              "keyphrase_sources": [
                {
                  "id": "rootcause:Improper Input Validation",
                  "keyphrase": "Improper Input Validation",
                  "type": "rootcause"
                },
                {
                  "id": "rootcause:Input Validation vulnerability",
                  "keyphrase": "Input Validation vulnerability",
                  "type": "rootcause"
                },
                {
                  "id": "weakness:command injection",
                  "keyphrase": "command injection",
                  "type": "weakness"
                }
              ]
            },
            "similarity": 183.53247865643618
          },
          {
            "metadata": {
              "doc_id": "1285",
              "name": "Improper Validation of Specified Index, Position, or Offset in Input",
              "source": "sparse",
              "original_content": "The product receives input that is expected to specify an index, position, or offset into an indexable resource such as a buffer or file, but it does not validate or incorrectly validates that the specified index/position/offset has the required properties.",
              "keyphrase_sources": [
                {
                  "id": "rootcause:Improper Input Validation",
                  "keyphrase": "Improper Input Validation",
                  "type": "rootcause"
                }
              ]
            },
            "similarity": 183.3155526456191
          }
        ]
      },
      "rootcause:Input Validation vulnerability": {
        "keyphrase": "Input Validation vulnerability",
        "type": "rootcause",
        "cwes": [
          {
            "metadata": {
              "doc_id": "20",
              "name": "Improper Input Validation",
              "source": "sparse",
              "original_content": "The product receives input or data, but it does\n        not validate or incorrectly validates that the input has the\n        properties that are required to process the data safely and\n        correctly."
            },
            "similarity": 201.82015638382896
          },
          {
            "metadata": {
              "doc_id": "1286",
              "name": "Improper Validation of Syntactic Correctness of Input",
              "source": "sparse",
              "original_content": "The product receives input that is expected to be well-formed - i.e., to comply with a certain syntax - but it does not validate or incorrectly validates that the input complies with the syntax."
            },
            "similarity": 196.70123038479505
          },
          {
            "metadata": {
              "doc_id": "113",
              "name": "Improper Neutralization of CRLF Sequences in HTTP Headers ('HTTP Request/Response Splitting')",
              "source": "sparse",
              "original_content": "The product receives data from an HTTP agent/component (e.g., web server, proxy, browser, etc.), but it does not neutralize or incorrectly neutralizes CR and LF characters before the data is included in outgoing HTTP headers."
            },
            "similarity": 188.78879898295477
          },
          {
            "metadata": {
              "doc_id": "78",
              "name": "Improper Neutralization of Special Elements used in an OS Command ('OS Command Injection')",
              "source": "sparse",
              "original_content": "The product constructs all or part of an OS command using externally-influenced input from an upstream component, but it does not neutralize or incorrectly neutralizes special elements that could modify the intended OS command when it is sent to a downstream component.",
              "keyphrase_sources": [
                {
                  "id": "rootcause:Input Validation vulnerability",
                  "keyphrase": "Input Validation vulnerability",
                  "type": "rootcause"
                },
                {
                  "id": "weakness:command injection",
                  "keyphrase": "command injection",
                  "type": "weakness"
                },
                {
                  "id": "version:5.5R6-2.6.7 through 5.5R6-2.8.13",
                  "keyphrase": "5.5R6-2.6.7 through 5.5R6-2.8.13",
                  "type": "version"
                }
              ]
            },
            "similarity": 181.12285547448866
          },
          {
            "metadata": {
              "doc_id": "138",
              "name": "Improper Neutralization of Special Elements",
              "source": "sparse",
              "original_content": "The product receives input from an upstream component, but it does not neutralize or incorrectly neutralizes special elements that could be interpreted as control elements or syntactic markers when they are sent to a downstream component."
            },
            "similarity": 179.07535569642872
          }
        ]
      },
      "weakness:command injection": {
        "keyphrase": "command injection",
        "type": "weakness",
        "cwes": [
          {
            "metadata": {
              "doc_id": "78",
              "name": "Improper Neutralization of Special Elements used in an OS Command ('OS Command Injection')",
              "source": "sparse",
              "original_content": "The product constructs all or part of an OS command using externally-influenced input from an upstream component, but it does not neutralize or incorrectly neutralizes special elements that could modify the intended OS command when it is sent to a downstream component."
            },
            "similarity": 197.18046054845138
          },
          {
            "metadata": {
              "doc_id": "77",
              "name": "Improper Neutralization of Special Elements used in a Command ('Command Injection')",
              "source": "sparse",
              "original_content": "The product constructs all or part of a command using externally-influenced input from an upstream component, but it does not neutralize or incorrectly neutralizes special elements that could modify the intended command when it is sent to a downstream component.",
              "keyphrase_sources": [
                {
                  "id": "weakness:command injection",
                  "keyphrase": "command injection",
                  "type": "weakness"
                }
              ]
            },
            "similarity": 189.01165220860432
          },
          {
            "metadata": {
              "doc_id": "138",
              "name": "Improper Neutralization of Special Elements",
              "source": "sparse",
              "original_content": "The product receives input from an upstream component, but it does not neutralize or incorrectly neutralizes special elements that could be interpreted as control elements or syntactic markers when they are sent to a downstream component."
            },
            "similarity": 187.74783222272026
          },
          {
            "metadata": {
              "doc_id": "20",
              "name": "Improper Input Validation",
              "source": "sparse",
              "original_content": "The product receives input or data, but it does\n        not validate or incorrectly validates that the input has the\n        properties that are required to process the data safely and\n        correctly."
            },
            "similarity": 182.85366278268998
          },
          {
            "metadata": {
              "doc_id": "790",
              "name": "Improper Filtering of Special Elements",
              "source": "sparse",
              "original_content": "The product receives data from an upstream component, but does not filter or incorrectly filters special elements before sending it to a downstream component.",
              "keyphrase_sources": [
                {
                  "id": "weakness:command injection",
                  "keyphrase": "command injection",
                  "type": "weakness"
                }
              ]
            },
            "similarity": 176.89350438568056
          }
        ]
      },
      "product:Hillstone Networks Hillstone Networks Web Application Firewall": {
        "keyphrase": "Hillstone Networks Hillstone Networks Web Application Firewall",
        "type": "product",
        "cwes": [
          {
            "metadata": {
              "doc_id": "113",
              "name": "Improper Neutralization of CRLF Sequences in HTTP Headers ('HTTP Request/Response Splitting')",
              "source": "sparse",
              "original_content": "The product receives data from an HTTP agent/component (e.g., web server, proxy, browser, etc.), but it does not neutralize or incorrectly neutralizes CR and LF characters before the data is included in outgoing HTTP headers."
            },
            "similarity": 80.06047029997399
          },
          {
            "metadata": {
              "doc_id": "1286",
              "name": "Improper Validation of Syntactic Correctness of Input",
              "source": "sparse",
              "original_content": "The product receives input that is expected to be well-formed - i.e., to comply with a certain syntax - but it does not validate or incorrectly validates that the input complies with the syntax."
            },
            "similarity": 75.2645568363772
          },
          {
            "metadata": {
              "doc_id": "400",
              "name": "Uncontrolled Resource Consumption",
              "source": "sparse",
              "original_content": "The product does not properly control the allocation and maintenance of a limited resource, thereby enabling an actor to influence the amount of resources consumed, eventually leading to the exhaustion of available resources.",
              "keyphrase_sources": [
                {
                  "id": "product:Hillstone Networks Hillstone Networks Web Application Firewall",
                  "keyphrase": "Hillstone Networks Hillstone Networks Web Application Firewall",
                  "type": "product"
                },
                {
                  "id": "version:5.5R6-2.6.7 through 5.5R6-2.8.13",
                  "keyphrase": "5.5R6-2.6.7 through 5.5R6-2.8.13",
                  "type": "version"
                }
              ]
            },
            "similarity": 72.0857780767714
          },
          {
            "metadata": {
              "doc_id": "20",
              "name": "Improper Input Validation",
              "source": "sparse",
              "original_content": "The product receives input or data, but it does\n        not validate or incorrectly validates that the input has the\n        properties that are required to process the data safely and\n        correctly."
            },
            "similarity": 71.49600433679863
          },
          {
            "metadata": {
              "doc_id": "269",
              "name": "Improper Privilege Management",
              "source": "sparse",
              "original_content": "The product does not properly assign, modify, track, or check privileges for an actor, creating an unintended sphere of control for that actor.",
              "keyphrase_sources": [
                {
                  "id": "product:Hillstone Networks Hillstone Networks Web Application Firewall",
                  "keyphrase": "Hillstone Networks Hillstone Networks Web Application Firewall",
                  "type": "product"
                },
                {
                  "id": "version:5.5R6-2.6.7 through 5.5R6-2.8.13",
                  "keyphrase": "5.5R6-2.6.7 through 5.5R6-2.8.13",
                  "type": "version"
                }
              ]
            },
            "similarity": 70.18312971301314
          }
        ]
      },
      "version:5.5R6-2.6.7 through 5.5R6-2.8.13": {
        "keyphrase": "5.5R6-2.6.7 through 5.5R6-2.8.13",
        "type": "version",
        "cwes": [
          {
            "metadata": {
              "doc_id": "1286",
              "name": "Improper Validation of Syntactic Correctness of Input",
              "source": "sparse",
              "original_content": "The product receives input that is expected to be well-formed - i.e., to comply with a certain syntax - but it does not validate or incorrectly validates that the input complies with the syntax."
            },
            "similarity": 85.12652361635645
          },
          {
            "metadata": {
              "doc_id": "113",
              "name": "Improper Neutralization of CRLF Sequences in HTTP Headers ('HTTP Request/Response Splitting')",
              "source": "sparse",
              "original_content": "The product receives data from an HTTP agent/component (e.g., web server, proxy, browser, etc.), but it does not neutralize or incorrectly neutralizes CR and LF characters before the data is included in outgoing HTTP headers."
            },
            "similarity": 84.42861020546977
          },
          {
            "metadata": {
              "doc_id": "78",
              "name": "Improper Neutralization of Special Elements used in an OS Command ('OS Command Injection')",
              "source": "sparse",
              "original_content": "The product constructs all or part of an OS command using externally-influenced input from an upstream component, but it does not neutralize or incorrectly neutralizes special elements that could modify the intended OS command when it is sent to a downstream component."
            },
            "similarity": 83.07641216821938
          },
          {
            "metadata": {
              "doc_id": "400",
              "name": "Uncontrolled Resource Consumption",
              "source": "sparse",
              "original_content": "The product does not properly control the allocation and maintenance of a limited resource, thereby enabling an actor to influence the amount of resources consumed, eventually leading to the exhaustion of available resources."
            },
            "similarity": 82.08505047000585
          },
          {
            "metadata": {
              "doc_id": "269",
              "name": "Improper Privilege Management",
              "source": "sparse",
              "original_content": "The product does not properly assign, modify, track, or check privileges for an actor, creating an unintended sphere of control for that actor."
            },
            "similarity": 81.48381824909146
          }
        ]
      }
    },
    "keyphrase_mapping": {
      "20": [
        {
          "id": "rootcause:Improper Input Validation",
          "keyphrase": "Improper Input Validation",
          "type": "rootcause"
        },
        {
          "id": "rootcause:Input Validation vulnerability",
          "keyphrase": "Input Validation vulnerability",
          "type": "rootcause"
        },
        {
          "id": "weakness:command injection",
          "keyphrase": "command injection",
          "type": "weakness"
        },
        {
          "id": "product:Hillstone Networks Hillstone Networks Web Application Firewall",
          "keyphrase": "Hillstone Networks Hillstone Networks Web Application Firewall",
          "type": "product"
        }
      ],
      "1286": [
        {
          "id": "rootcause:Improper Input Validation",
          "keyphrase": "Improper Input Validation",
          "type": "rootcause"
        },
        {
          "id": "rootcause:Input Validation vulnerability",
          "keyphrase": "Input Validation vulnerability",
          "type": "rootcause"
        },
        {
          "id": "product:Hillstone Networks Hillstone Networks Web Application Firewall",
          "keyphrase": "Hillstone Networks Hillstone Networks Web Application Firewall",
          "type": "product"
        },
        {
          "id": "version:5.5R6-2.6.7 through 5.5R6-2.8.13",
          "keyphrase": "5.5R6-2.6.7 through 5.5R6-2.8.13",
          "type": "version"
        }
      ],
      "113": [
        {
          "id": "rootcause:Improper Input Validation",
          "keyphrase": "Improper Input Validation",
          "type": "rootcause"
        },
        {
          "id": "rootcause:Input Validation vulnerability",
          "keyphrase": "Input Validation vulnerability",
          "type": "rootcause"
        },
        {
          "id": "product:Hillstone Networks Hillstone Networks Web Application Firewall",
          "keyphrase": "Hillstone Networks Hillstone Networks Web Application Firewall",
          "type": "product"
        },
        {
          "id": "version:5.5R6-2.6.7 through 5.5R6-2.8.13",
          "keyphrase": "5.5R6-2.6.7 through 5.5R6-2.8.13",
          "type": "version"
        }
      ],
      "138": [
        {
          "id": "rootcause:Improper Input Validation",
          "keyphrase": "Improper Input Validation",
          "type": "rootcause"
        },
        {
          "id": "rootcause:Input Validation vulnerability",
          "keyphrase": "Input Validation vulnerability",
          "type": "rootcause"
        },
        {
          "id": "weakness:command injection",
          "keyphrase": "command injection",
          "type": "weakness"
        }
      ],
      "1285": [
        {
          "id": "rootcause:Improper Input Validation",
          "keyphrase": "Improper Input Validation",
          "type": "rootcause"
        }
      ],
      "78": [
        {
          "id": "rootcause:Input Validation vulnerability",
          "keyphrase": "Input Validation vulnerability",
          "type": "rootcause"
        },
        {
          "id": "weakness:command injection",
          "keyphrase": "command injection",
          "type": "weakness"
        },
        {
          "id": "version:5.5R6-2.6.7 through 5.5R6-2.8.13",
          "keyphrase": "5.5R6-2.6.7 through 5.5R6-2.8.13",
          "type": "version"
        }
      ],
      "77": [
        {
          "id": "weakness:command injection",
          "keyphrase": "command injection",
          "type": "weakness"
        }
      ],
      "790": [
        {
          "id": "weakness:command injection",
          "keyphrase": "command injection",
          "type": "weakness"
        }
      ],
      "400": [
        {
          "id": "product:Hillstone Networks Hillstone Networks Web Application Firewall",
          "keyphrase": "Hillstone Networks Hillstone Networks Web Application Firewall",
          "type": "product"
        },
        {
          "id": "version:5.5R6-2.6.7 through 5.5R6-2.8.13",
          "keyphrase": "5.5R6-2.6.7 through 5.5R6-2.8.13",
          "type": "version"
        }
      ],
      "269": [
        {
          "id": "product:Hillstone Networks Hillstone Networks Web Application Firewall",
          "keyphrase": "Hillstone Networks Hillstone Networks Web Application Firewall",
          "type": "product"
        },
        {
          "id": "version:5.5R6-2.6.7 through 5.5R6-2.8.13",
          "keyphrase": "5.5R6-2.6.7 through 5.5R6-2.8.13",
          "type": "version"
        }
      ]
    },
    "relevant_cwes": [
      {
        "metadata": {
          "doc_id": "20",
          "name": "Improper Input Validation",
          "source": "sparse",
          "original_content": "The product receives input or data, but it does\n        not validate or incorrectly validates that the input has the\n        properties that are required to process the data safely and\n        correctly.",
          "keyphrase_sources": [
            {
              "id": "rootcause:Improper Input Validation",
              "keyphrase": "Improper Input Validation",
              "type": "rootcause"
            },
            {
              "id": "rootcause:Input Validation vulnerability",
              "keyphrase": "Input Validation vulnerability",
              "type": "rootcause"
            },
            {
              "id": "weakness:command injection",
              "keyphrase": "command injection",
              "type": "weakness"
            },
            {
              "id": "product:Hillstone Networks Hillstone Networks Web Application Firewall",
              "keyphrase": "Hillstone Networks Hillstone Networks Web Application Firewall",
              "type": "product"
            }
          ]
        },
        "similarity": 206.5731349012634
      },
      {
        "metadata": {
          "doc_id": "1286",
          "name": "Improper Validation of Syntactic Correctness of Input",
          "source": "sparse",
          "original_content": "The product receives input that is expected to be well-formed - i.e., to comply with a certain syntax - but it does not validate or incorrectly validates that the input complies with the syntax.",
          "keyphrase_sources": [
            {
              "id": "rootcause:Improper Input Validation",
              "keyphrase": "Improper Input Validation",
              "type": "rootcause"
            },
            {
              "id": "rootcause:Input Validation vulnerability",
              "keyphrase": "Input Validation vulnerability",
              "type": "rootcause"
            },
            {
              "id": "product:Hillstone Networks Hillstone Networks Web Application Firewall",
              "keyphrase": "Hillstone Networks Hillstone Networks Web Application Firewall",
              "type": "product"
            },
            {
              "id": "version:5.5R6-2.6.7 through 5.5R6-2.8.13",
              "keyphrase": "5.5R6-2.6.7 through 5.5R6-2.8.13",
              "type": "version"
            }
          ]
        },
        "similarity": 200.80804005317242
      },
      {
        "metadata": {
          "doc_id": "113",
          "name": "Improper Neutralization of CRLF Sequences in HTTP Headers ('HTTP Request/Response Splitting')",
          "source": "sparse",
          "original_content": "The product receives data from an HTTP agent/component (e.g., web server, proxy, browser, etc.), but it does not neutralize or incorrectly neutralizes CR and LF characters before the data is included in outgoing HTTP headers.",
          "keyphrase_sources": [
            {
              "id": "rootcause:Improper Input Validation",
              "keyphrase": "Improper Input Validation",
              "type": "rootcause"
            },
            {
              "id": "rootcause:Input Validation vulnerability",
              "keyphrase": "Input Validation vulnerability",
              "type": "rootcause"
            },
            {
              "id": "product:Hillstone Networks Hillstone Networks Web Application Firewall",
              "keyphrase": "Hillstone Networks Hillstone Networks Web Application Firewall",
              "type": "product"
            },
            {
              "id": "version:5.5R6-2.6.7 through 5.5R6-2.8.13",
              "keyphrase": "5.5R6-2.6.7 through 5.5R6-2.8.13",
              "type": "version"
            }
          ]
        },
        "similarity": 191.30476243186396
      },
      {
        "metadata": {
          "doc_id": "77",
          "name": "Improper Neutralization of Special Elements used in a Command ('Command Injection')",
          "source": "sparse",
          "original_content": "The product constructs all or part of a command using externally-influenced input from an upstream component, but it does not neutralize or incorrectly neutralizes special elements that could modify the intended command when it is sent to a downstream component.",
          "keyphrase_sources": [
            {
              "id": "weakness:command injection",
              "keyphrase": "command injection",
              "type": "weakness"
            }
          ]
        },
        "similarity": 189.01165220860432
      },
      {
        "metadata": {
          "doc_id": "138",
          "name": "Improper Neutralization of Special Elements",
          "source": "sparse",
          "original_content": "The product receives input from an upstream component, but it does not neutralize or incorrectly neutralizes special elements that could be interpreted as control elements or syntactic markers when they are sent to a downstream component.",
          "keyphrase_sources": [
            {
              "id": "rootcause:Improper Input Validation",
              "keyphrase": "Improper Input Validation",
              "type": "rootcause"
            },
            {
              "id": "rootcause:Input Validation vulnerability",
              "keyphrase": "Input Validation vulnerability",
              "type": "rootcause"
            },
            {
              "id": "weakness:command injection",
              "keyphrase": "command injection",
              "type": "weakness"
            }
          ]
        },
        "similarity": 183.53247865643618
      },
      {
        "metadata": {
          "doc_id": "1285",
          "name": "Improper Validation of Specified Index, Position, or Offset in Input",
          "source": "sparse",
          "original_content": "The product receives input that is expected to specify an index, position, or offset into an indexable resource such as a buffer or file, but it does not validate or incorrectly validates that the specified index/position/offset has the required properties.",
          "keyphrase_sources": [
            {
              "id": "rootcause:Improper Input Validation",
              "keyphrase": "Improper Input Validation",
              "type": "rootcause"
            }
          ]
        },
        "similarity": 183.3155526456191
      },
      {
        "metadata": {
          "doc_id": "78",
          "name": "Improper Neutralization of Special Elements used in an OS Command ('OS Command Injection')",
          "source": "sparse",
          "original_content": "The product constructs all or part of an OS command using externally-influenced input from an upstream component, but it does not neutralize or incorrectly neutralizes special elements that could modify the intended OS command when it is sent to a downstream component.",
          "keyphrase_sources": [
            {
              "id": "rootcause:Input Validation vulnerability",
              "keyphrase": "Input Validation vulnerability",
              "type": "rootcause"
            },
            {
              "id": "weakness:command injection",
              "keyphrase": "command injection",
              "type": "weakness"
            },
            {
              "id": "version:5.5R6-2.6.7 through 5.5R6-2.8.13",
              "keyphrase": "5.5R6-2.6.7 through 5.5R6-2.8.13",
              "type": "version"
            }
          ]
        },
        "similarity": 181.12285547448866
      },
      {
        "metadata": {
          "doc_id": "790",
          "name": "Improper Filtering of Special Elements",
          "source": "sparse",
          "original_content": "The product receives data from an upstream component, but does not filter or incorrectly filters special elements before sending it to a downstream component.",
          "keyphrase_sources": [
            {
              "id": "weakness:command injection",
              "keyphrase": "command injection",
              "type": "weakness"
            }
          ]
        },
        "similarity": 176.89350438568056
      },
      {
        "metadata": {
          "doc_id": "400",
          "name": "Uncontrolled Resource Consumption",
          "source": "sparse",
          "original_content": "The product does not properly control the allocation and maintenance of a limited resource, thereby enabling an actor to influence the amount of resources consumed, eventually leading to the exhaustion of available resources.",
          "keyphrase_sources": [
            {
              "id": "product:Hillstone Networks Hillstone Networks Web Application Firewall",
              "keyphrase": "Hillstone Networks Hillstone Networks Web Application Firewall",
              "type": "product"
            },
            {
              "id": "version:5.5R6-2.6.7 through 5.5R6-2.8.13",
              "keyphrase": "5.5R6-2.6.7 through 5.5R6-2.8.13",
              "type": "version"
            }
          ]
        },
        "similarity": 72.0857780767714
      },
      {
        "metadata": {
          "doc_id": "269",
          "name": "Improper Privilege Management",
          "source": "sparse",
          "original_content": "The product does not properly assign, modify, track, or check privileges for an actor, creating an unintended sphere of control for that actor.",
          "keyphrase_sources": [
            {
              "id": "product:Hillstone Networks Hillstone Networks Web Application Firewall",
              "keyphrase": "Hillstone Networks Hillstone Networks Web Application Firewall",
              "type": "product"
            },
            {
              "id": "version:5.5R6-2.6.7 through 5.5R6-2.8.13",
              "keyphrase": "5.5R6-2.6.7 through 5.5R6-2.8.13",
              "type": "version"
            }
          ]
        },
        "similarity": 70.18312971301314
      }
    ],
    "enhanced_query": "# Vulnerability Description\n\n    **Improper Input Validation** vulnerability in Hillstone Networks Hillstone Networks Web Application Firewall on 5.5R6 allows Command Injection.This issue affects Hillstone Networks Web Application Firewall from 5.5R6-2.6.7 through 5.5R6-2.8.13.\n\n    # Keyphrase-Specific CWE Analysis\n    This vulnerability contains multiple keyphrases that may map to different CWEs. \n    Please analyze each keyphrase separately and determine the most appropriate CWE(s) for each.\n\n    ## ROOTCAUSE: 'Improper Input Validation'\n\nRelevant CWEs for this ROOTCAUSE:\n\n### 1. CWE-20: Improper Input Validation (Score: 206.57)\n\nThe product receives input or data, but it does\n        not validate or incorrectly validates that the input has the\n        properties that are required to process the data safely and\n        correctly....\n\n### 2. CWE-1286: Improper Validation of Syntactic Correctness of Input (Score: 200.81)\n\nThe product receives input that is expected to be well-formed - i.e., to comply with a certain syntax - but it does not validate or incorrectly validates that the input complies with the syntax....\n\n### 3. CWE-113: Improper Neutralization of CRLF Sequences in HTTP Headers ('HTTP Request/Response Splitting') (Score: 191.30)\n\nThe product receives data from an HTTP agent/component (e.g., web server, proxy, browser, etc.), but it does not neutralize or incorrectly neutralizes CR and LF characters before the data is included in outgoing HTTP headers....\n\n### 4. CWE-138: Improper Neutralization of Special Elements (Score: 183.53)\n\nThe product receives input from an upstream component, but it does not neutralize or incorrectly neutralizes special elements that could be interpreted as control elements or syntactic markers when they are sent to a downstream component....\n\n### 5. CWE-1285: Improper Validation of Specified Index, Position, or Offset in Input (Score: 183.32)\n\nThe product receives input that is expected to specify an index, position, or offset into an indexable resource such as a buffer or file, but it does not validate or incorrectly validates that the specified index/position/offset has the required properties....\n\n## ROOTCAUSE: 'Input Validation vulnerability'\n\nRelevant CWEs for this ROOTCAUSE:\n\n### 1. CWE-20: Improper Input Validation (Score: 206.57)\n\nThe product receives input or data, but it does\n        not validate or incorrectly validates that the input has the\n        properties that are required to process the data safely and\n        correctly....\n\n### 2. CWE-1286: Improper Validation of Syntactic Correctness of Input (Score: 200.81)\n\nThe product receives input that is expected to be well-formed - i.e., to comply with a certain syntax - but it does not validate or incorrectly validates that the input complies with the syntax....\n\n### 3. CWE-113: Improper Neutralization of CRLF Sequences in HTTP Headers ('HTTP Request/Response Splitting') (Score: 191.30)\n\nThe product receives data from an HTTP agent/component (e.g., web server, proxy, browser, etc.), but it does not neutralize or incorrectly neutralizes CR and LF characters before the data is included in outgoing HTTP headers....\n\n### 4. CWE-138: Improper Neutralization of Special Elements (Score: 183.53)\n\nThe product receives input from an upstream component, but it does not neutralize or incorrectly neutralizes special elements that could be interpreted as control elements or syntactic markers when they are sent to a downstream component....\n\n### 5. CWE-78: Improper Neutralization of Special Elements used in an OS Command ('OS Command Injection') (Score: 181.12)\n\nThe product constructs all or part of an OS command using externally-influenced input from an upstream component, but it does not neutralize or incorrectly neutralizes special elements that could modify the intended OS command when it is sent to a downstream component....\n\n## WEAKNESS: 'command injection'\n\nRelevant CWEs for this WEAKNESS:\n\n### 1. CWE-20: Improper Input Validation (Score: 206.57)\n\nThe product receives input or data, but it does\n        not validate or incorrectly validates that the input has the\n        properties that are required to process the data safely and\n        correctly....\n\n### 2. CWE-77: Improper Neutralization of Special Elements used in a Command ('Command Injection') (Score: 189.01)\n\nThe product constructs all or part of a command using externally-influenced input from an upstream component, but it does not neutralize or incorrectly neutralizes special elements that could modify the intended command when it is sent to a downstream component....\n\n### 3. CWE-138: Improper Neutralization of Special Elements (Score: 183.53)\n\nThe product receives input from an upstream component, but it does not neutralize or incorrectly neutralizes special elements that could be interpreted as control elements or syntactic markers when they are sent to a downstream component....\n\n### 4. CWE-78: Improper Neutralization of Special Elements used in an OS Command ('OS Command Injection') (Score: 181.12)\n\nThe product constructs all or part of an OS command using externally-influenced input from an upstream component, but it does not neutralize or incorrectly neutralizes special elements that could modify the intended OS command when it is sent to a downstream component....\n\n### 5. CWE-790: Improper Filtering of Special Elements (Score: 176.89)\n\nThe product receives data from an upstream component, but does not filter or incorrectly filters special elements before sending it to a downstream component....\n\n## PRODUCT: 'Hillstone Networks Hillstone Networks Web Application Firewall'\n\nRelevant CWEs for this PRODUCT:\n\n### 1. CWE-20: Improper Input Validation (Score: 206.57)\n\nThe product receives input or data, but it does\n        not validate or incorrectly validates that the input has the\n        properties that are required to process the data safely and\n        correctly....\n\n### 2. CWE-1286: Improper Validation of Syntactic Correctness of Input (Score: 200.81)\n\nThe product receives input that is expected to be well-formed - i.e., to comply with a certain syntax - but it does not validate or incorrectly validates that the input complies with the syntax....\n\n### 3. CWE-113: Improper Neutralization of CRLF Sequences in HTTP Headers ('HTTP Request/Response Splitting') (Score: 191.30)\n\nThe product receives data from an HTTP agent/component (e.g., web server, proxy, browser, etc.), but it does not neutralize or incorrectly neutralizes CR and LF characters before the data is included in outgoing HTTP headers....\n\n### 4. CWE-400: Uncontrolled Resource Consumption (Score: 72.09)\n\nThe product does not properly control the allocation and maintenance of a limited resource, thereby enabling an actor to influence the amount of resources consumed, eventually leading to the exhaustion of available resources....\n\n### 5. CWE-269: Improper Privilege Management (Score: 70.18)\n\nThe product does not properly assign, modify, track, or check privileges for an actor, creating an unintended sphere of control for that actor....\n\n## VERSION: '5.5R6-2.6.7 through 5.5R6-2.8.13'\n\nRelevant CWEs for this VERSION:\n\n### 1. CWE-1286: Improper Validation of Syntactic Correctness of Input (Score: 200.81)\n\nThe product receives input that is expected to be well-formed - i.e., to comply with a certain syntax - but it does not validate or incorrectly validates that the input complies with the syntax....\n\n### 2. CWE-113: Improper Neutralization of CRLF Sequences in HTTP Headers ('HTTP Request/Response Splitting') (Score: 191.30)\n\nThe product receives data from an HTTP agent/component (e.g., web server, proxy, browser, etc.), but it does not neutralize or incorrectly neutralizes CR and LF characters before the data is included in outgoing HTTP headers....\n\n### 3. CWE-78: Improper Neutralization of Special Elements used in an OS Command ('OS Command Injection') (Score: 181.12)\n\nThe product constructs all or part of an OS command using externally-influenced input from an upstream component, but it does not neutralize or incorrectly neutralizes special elements that could modify the intended OS command when it is sent to a downstream component....\n\n### 4. CWE-400: Uncontrolled Resource Consumption (Score: 72.09)\n\nThe product does not properly control the allocation and maintenance of a limited resource, thereby enabling an actor to influence the amount of resources consumed, eventually leading to the exhaustion of available resources....\n\n### 5. CWE-269: Improper Privilege Management (Score: 70.18)\n\nThe product does not properly assign, modify, track, or check privileges for an actor, creating an unintended sphere of control for that actor....\n\n\n    # Analysis Instructions\n    1. For each keyphrase, identify the most appropriate CWE(s) that represent the weakness.\n    2. Consider how the different keyphrases might relate to each other in the vulnerability chain.\n    3. Provide a final determination of primary CWE(s) and any secondary CWEs.\n    4. Format your response using the standard analysis template.\n\n    Please analyze how these different weaknesses interact and provide a comprehensive CWE classification.\n    "
  },
  "retrieval_time": 1.0785291194915771
}