{
  "vulnerability_info": "VulnerabilityInfo(cve_id='CVE-2024-38483', description='Dell BIOS contains an **Improper Input Validation** vulnerability in an externally developed component. A high privileged attacker with local access could potentially exploit this vulnerability, leading to Code execution.', key_phrases={'rootcause': ['Improper Input Validation', 'Input Validation vulnerability'], 'weakness': '', 'impact': 'Code execution', 'vector': '', 'attacker': 'high privileged attacker with local access', 'product': 'Dell BIOS', 'version': '', 'component': 'externally developed component'}, reference_content=\"Based on the provided document, here's the breakdown of the vulnerability:\\n\\n**Root cause of vulnerability:**\\n- Improper Input Validation in an externally developed component of Dell BIOS.\\n\\n**Weaknesses/vulnerabilities present:**\\n- The primary weakness is the lack of proper input validation, allowing for potential exploitation.\\n\\n**Impact of exploitation:**\\n- Successful exploitation can lead to code execution on the affected system.\\n\\n**Attack vectors:**\\n- The attack vector is local access.\\n\\n**Required attacker capabilities/position:**\\n- The attacker requires high privileges and local access to the system. User interaction is also required, so this is not an entirely automated attack.\\n\\n**Summary:**\\nThe vulnerability is due to improper input validation within the Dell BIOS, which can be exploited by a local, high-privileged attacker to achieve code execution on the system. The CVSS score of 5.8 reflects a medium severity due to the requirement of local access and high privileges, also user interaction is needed. Dell has released BIOS updates for the affected products to address this issue.\", similar_info={'cwe_distribution': {95: {'cwe_counts': defaultdict(<class 'int'>, {'CWE-NVD-noinfo': 3}), 'total_samples': 3, 'distribution': [{'cwes': ['CWE-NVD-noinfo'], 'frequency': 3, 'proportion': 1.0}]}, 90: {'cwe_counts': defaultdict(<class 'int'>, {'CWE-NVD-noinfo': 4, 'CWE-20': 1}), 'total_samples': 5, 'distribution': [{'cwes': ['CWE-NVD-noinfo'], 'frequency': 4, 'proportion': 0.8}, {'cwes': ['CWE-20'], 'frequency': 1, 'proportion': 0.2}]}, 85: {'cwe_counts': defaultdict(<class 'int'>, {'CWE-NVD-noinfo': 4, 'CWE-20': 1}), 'total_samples': 5, 'distribution': [{'cwes': ['CWE-NVD-noinfo'], 'frequency': 4, 'proportion': 0.8}, {'cwes': ['CWE-20'], 'frequency': 1, 'proportion': 0.2}]}, 80: {'cwe_counts': defaultdict(<class 'int'>, {'CWE-NVD-noinfo': 4, 'CWE-20': 1}), 'total_samples': 6, 'distribution': [{'cwes': ['CWE-NVD-noinfo'], 'frequency': 4, 'proportion': 0.667}, {'cwes': ['CWE-20'], 'frequency': 1, 'proportion': 0.167}, {'cwes': [], 'frequency': 1, 'proportion': 0.167}]}, 75: {'cwe_counts': defaultdict(<class 'int'>, {'CWE-NVD-noinfo': 4, 'CWE-20': 1}), 'total_samples': 6, 'distribution': [{'cwes': ['CWE-NVD-noinfo'], 'frequency': 4, 'proportion': 0.667}, {'cwes': ['CWE-20'], 'frequency': 1, 'proportion': 0.167}, {'cwes': [], 'frequency': 1, 'proportion': 0.167}]}, 70: {'cwe_counts': defaultdict(<class 'int'>, {'CWE-NVD-noinfo': 3, 'CWE-20': 2, 'CWE-NVD-Other': 1}), 'total_samples': 6, 'distribution': [{'cwes': ['CWE-NVD-noinfo'], 'frequency': 3, 'proportion': 0.5}, {'cwes': ['CWE-20'], 'frequency': 2, 'proportion': 0.333}, {'cwes': ['CWE-NVD-Other'], 'frequency': 1, 'proportion': 0.167}]}}, 'cwe_consensus': 'CWE-NVD-noinfo', 'similarity_stats': {'thresholds': [95, 90, 85, 80, 75, 70], 'total_samples_by_threshold': {95: 3, 90: 5, 85: 5, 80: 6, 75: 6, 70: 6}, 'top_cwes_by_threshold': {95: [('CWE-NVD-noinfo', 3)], 90: [('CWE-NVD-noinfo', 4), ('CWE-20', 1)], 85: [('CWE-NVD-noinfo', 4), ('CWE-20', 1)], 80: [('CWE-NVD-noinfo', 4), ('CWE-20', 1)], 75: [('CWE-NVD-noinfo', 4), ('CWE-20', 1)], 70: [('CWE-NVD-noinfo', 3), ('CWE-20', 2), ('CWE-NVD-Other', 1)]}}, 'raw_matches': [{'similarity': 95, 'cwes': ['NVD-noinfo'], 'total': 3, 'frequency': 3, 'proportion': 1.0}, {'similarity': 90, 'cwes': ['NVD-noinfo'], 'total': 5, 'frequency': 4, 'proportion': 0.8}, {'similarity': 90, 'cwes': ['20'], 'total': 5, 'frequency': 1, 'proportion': 0.2}, {'similarity': 85, 'cwes': ['NVD-noinfo'], 'total': 5, 'frequency': 4, 'proportion': 0.8}, {'similarity': 85, 'cwes': ['20'], 'total': 5, 'frequency': 1, 'proportion': 0.2}, {'similarity': 80, 'cwes': ['NVD-noinfo'], 'total': 6, 'frequency': 4, 'proportion': 0.667}, {'similarity': 80, 'cwes': ['20'], 'total': 6, 'frequency': 1, 'proportion': 0.167}, {'similarity': 80, 'cwes': [], 'total': 6, 'frequency': 1, 'proportion': 0.167}, {'similarity': 75, 'cwes': ['NVD-noinfo'], 'total': 6, 'frequency': 4, 'proportion': 0.667}, {'similarity': 75, 'cwes': ['20'], 'total': 6, 'frequency': 1, 'proportion': 0.167}, {'similarity': 75, 'cwes': [], 'total': 6, 'frequency': 1, 'proportion': 0.167}, {'similarity': 70, 'cwes': ['NVD-noinfo'], 'total': 6, 'frequency': 3, 'proportion': 0.5}, {'similarity': 70, 'cwes': ['20'], 'total': 6, 'frequency': 2, 'proportion': 0.333}, {'similarity': 70, 'cwes': ['NVD-Other'], 'total': 6, 'frequency': 1, 'proportion': 0.167}]}, similarity_summary=SimilarityInsight(consensus_cwe='CWE-NVD-noinfo', top_cwes=[('CWE-NVD-noinfo', 22), ('CWE-20', 6), ('CWE-NVD-Other', 1)], confidence_levels={'high': [], 'medium': [], 'low': []}, total_samples=31), analysis='', analysis_with_relationships='', criticism='', resolution='', relevant_cwes=[{'metadata': {'doc_id': '20', 'name': 'Improper Input Validation', 'source': 'sparse', 'original_content': 'The product receives input or data, but it does\\n        not validate or incorrectly validates that the input has the\\n        properties that are required to process the data safely and\\n        correctly.', 'keyphrase_sources': [{'id': 'rootcause:Improper Input Validation', 'keyphrase': 'Improper Input Validation', 'type': 'rootcause'}, {'id': 'rootcause:Input Validation vulnerability', 'keyphrase': 'Input Validation vulnerability', 'type': 'rootcause'}, {'id': 'impact:Code execution', 'keyphrase': 'Code execution', 'type': 'impact'}, {'id': 'attacker:high privileged attacker with local access', 'keyphrase': 'high privileged attacker with local access', 'type': 'attacker'}, {'id': 'product:Dell BIOS', 'keyphrase': 'Dell BIOS', 'type': 'product'}, {'id': 'component:externally developed component', 'keyphrase': 'externally developed component', 'type': 'component'}]}, 'similarity': np.float64(210.91834378929786)}, {'metadata': {'doc_id': '119', 'name': 'Improper Restriction of Operations within the Bounds of a Memory Buffer', 'source': 'sparse', 'original_content': \"The product performs operations on a memory buffer, but it reads from or writes to a memory location outside the buffer's intended boundary. This may result in read or write operations on unexpected memory locations that could be linked to other variables, data structures, or internal program data.\", 'keyphrase_sources': [{'id': 'rootcause:Improper Input Validation', 'keyphrase': 'Improper Input Validation', 'type': 'rootcause'}, {'id': 'rootcause:Input Validation vulnerability', 'keyphrase': 'Input Validation vulnerability', 'type': 'rootcause'}, {'id': 'impact:Code execution', 'keyphrase': 'Code execution', 'type': 'impact'}, {'id': 'attacker:high privileged attacker with local access', 'keyphrase': 'high privileged attacker with local access', 'type': 'attacker'}, {'id': 'product:Dell BIOS', 'keyphrase': 'Dell BIOS', 'type': 'product'}, {'id': 'component:externally developed component', 'keyphrase': 'externally developed component', 'type': 'component'}]}, 'similarity': np.float64(198.2129846091297)}, {'metadata': {'doc_id': '1285', 'name': 'Improper Validation of Specified Index, Position, or Offset in Input', 'source': 'sparse', 'original_content': 'The product receives input that is expected to specify an index, position, or offset into an indexable resource such as a buffer or file, but it does not validate or incorrectly validates that the specified index/position/offset has the required properties.', 'keyphrase_sources': [{'id': 'rootcause:Improper Input Validation', 'keyphrase': 'Improper Input Validation', 'type': 'rootcause'}, {'id': 'rootcause:Input Validation vulnerability', 'keyphrase': 'Input Validation vulnerability', 'type': 'rootcause'}]}, 'similarity': np.float64(183.90574611449907)}, {'metadata': {'doc_id': '665', 'name': 'Improper Initialization', 'source': 'sparse', 'original_content': 'The product does not initialize or incorrectly initializes a resource, which might leave the resource in an unexpected state when it is accessed or used.', 'keyphrase_sources': [{'id': 'rootcause:Improper Input Validation', 'keyphrase': 'Improper Input Validation', 'type': 'rootcause'}, {'id': 'rootcause:Input Validation vulnerability', 'keyphrase': 'Input Validation vulnerability', 'type': 'rootcause'}, {'id': 'impact:Code execution', 'keyphrase': 'Code execution', 'type': 'impact'}]}, 'similarity': np.float64(181.33972305066118)}, {'metadata': {'doc_id': '287', 'name': 'Improper Authentication', 'source': 'sparse', 'original_content': 'When an actor claims to have a given identity, the product does not prove or insufficiently proves that the claim is correct.', 'keyphrase_sources': [{'id': 'rootcause:Improper Input Validation', 'keyphrase': 'Improper Input Validation', 'type': 'rootcause'}, {'id': 'rootcause:Input Validation vulnerability', 'keyphrase': 'Input Validation vulnerability', 'type': 'rootcause'}, {'id': 'impact:Code execution', 'keyphrase': 'Code execution', 'type': 'impact'}, {'id': 'product:Dell BIOS', 'keyphrase': 'Dell BIOS', 'type': 'product'}]}, 'similarity': np.float64(178.41939396649317)}, {'metadata': {'doc_id': '732', 'name': 'Incorrect Permission Assignment for Critical Resource', 'source': 'sparse', 'original_content': 'The product specifies permissions for a security-critical resource in a way that allows that resource to be read or modified by unintended actors.', 'keyphrase_sources': [{'id': 'attacker:high privileged attacker with local access', 'keyphrase': 'high privileged attacker with local access', 'type': 'attacker'}, {'id': 'component:externally developed component', 'keyphrase': 'externally developed component', 'type': 'component'}]}, 'similarity': np.float64(84.01111392748903)}, {'metadata': {'doc_id': '250', 'name': 'Execution with Unnecessary Privileges', 'source': 'sparse', 'original_content': 'The product performs an operation at a privilege level that is higher than the minimum level required, which creates new weaknesses or amplifies the consequences of other weaknesses.', 'keyphrase_sources': [{'id': 'attacker:high privileged attacker with local access', 'keyphrase': 'high privileged attacker with local access', 'type': 'attacker'}]}, 'similarity': np.float64(82.16111522865071)}, {'metadata': {'doc_id': '269', 'name': 'Improper Privilege Management', 'source': 'sparse', 'original_content': 'The product does not properly assign, modify, track, or check privileges for an actor, creating an unintended sphere of control for that actor.', 'keyphrase_sources': [{'id': 'attacker:high privileged attacker with local access', 'keyphrase': 'high privileged attacker with local access', 'type': 'attacker'}]}, 'similarity': np.float64(81.84036787309269)}, {'metadata': {'doc_id': '457', 'name': 'Use of Uninitialized Variable', 'source': 'sparse', 'original_content': 'The code uses a variable that has not been initialized, leading to unpredictable or unintended results.', 'keyphrase_sources': [{'id': 'product:Dell BIOS', 'keyphrase': 'Dell BIOS', 'type': 'product'}]}, 'similarity': np.float64(59.55590184647966)}, {'metadata': {'doc_id': '823', 'name': 'Use of Out-of-range Pointer Offset', 'source': 'sparse', 'original_content': 'The product performs pointer arithmetic on a valid pointer, but it uses an offset that can point outside of the intended range of valid memory locations for the resulting pointer.', 'keyphrase_sources': [{'id': 'component:externally developed component', 'keyphrase': 'externally developed component', 'type': 'component'}]}, 'similarity': np.float64(58.77006656733565)}, {'metadata': {'doc_id': '125', 'name': 'Out-of-bounds Read', 'source': 'sparse', 'original_content': 'The product reads data past the end, or before the beginning, of the intended buffer.', 'keyphrase_sources': [{'id': 'impact:Code execution', 'keyphrase': 'Code execution', 'type': 'impact'}, {'id': 'product:Dell BIOS', 'keyphrase': 'Dell BIOS', 'type': 'product'}, {'id': 'component:externally developed component', 'keyphrase': 'externally developed component', 'type': 'component'}]}, 'similarity': np.float64(56.35289899754115)}], identified_cwes={'analyzer': [], 'critic_additional': []})",
  "retrieval_results": {
    "has_multiple_keyphrases": true,
    "keyphrase_cwe_sets": {
      "rootcause:Improper Input Validation": {
        "keyphrase": "Improper Input Validation",
        "type": "rootcause",
        "cwes": [
          {
            "metadata": {
              "doc_id": "20",
              "name": "Improper Input Validation",
              "source": "sparse",
              "original_content": "The product receives input or data, but it does\n        not validate or incorrectly validates that the input has the\n        properties that are required to process the data safely and\n        correctly.",
              "keyphrase_sources": [
                {
                  "id": "rootcause:Improper Input Validation",
                  "keyphrase": "Improper Input Validation",
                  "type": "rootcause"
                },
                {
                  "id": "rootcause:Input Validation vulnerability",
                  "keyphrase": "Input Validation vulnerability",
                  "type": "rootcause"
                },
                {
                  "id": "impact:Code execution",
                  "keyphrase": "Code execution",
                  "type": "impact"
                },
                {
                  "id": "attacker:high privileged attacker with local access",
                  "keyphrase": "high privileged attacker with local access",
                  "type": "attacker"
                },
                {
                  "id": "product:Dell BIOS",
                  "keyphrase": "Dell BIOS",
                  "type": "product"
                },
                {
                  "id": "component:externally developed component",
                  "keyphrase": "externally developed component",
                  "type": "component"
                }
              ]
            },
            "similarity": 210.91834378929786
          },
          {
            "metadata": {
              "doc_id": "119",
              "name": "Improper Restriction of Operations within the Bounds of a Memory Buffer",
              "source": "sparse",
              "original_content": "The product performs operations on a memory buffer, but it reads from or writes to a memory location outside the buffer's intended boundary. This may result in read or write operations on unexpected memory locations that could be linked to other variables, data structures, or internal program data.",
              "keyphrase_sources": [
                {
                  "id": "rootcause:Improper Input Validation",
                  "keyphrase": "Improper Input Validation",
                  "type": "rootcause"
                },
                {
                  "id": "rootcause:Input Validation vulnerability",
                  "keyphrase": "Input Validation vulnerability",
                  "type": "rootcause"
                },
                {
                  "id": "impact:Code execution",
                  "keyphrase": "Code execution",
                  "type": "impact"
                },
                {
                  "id": "attacker:high privileged attacker with local access",
                  "keyphrase": "high privileged attacker with local access",
                  "type": "attacker"
                },
                {
                  "id": "product:Dell BIOS",
                  "keyphrase": "Dell BIOS",
                  "type": "product"
                },
                {
                  "id": "component:externally developed component",
                  "keyphrase": "externally developed component",
                  "type": "component"
                }
              ]
            },
            "similarity": 198.2129846091297
          },
          {
            "metadata": {
              "doc_id": "1285",
              "name": "Improper Validation of Specified Index, Position, or Offset in Input",
              "source": "sparse",
              "original_content": "The product receives input that is expected to specify an index, position, or offset into an indexable resource such as a buffer or file, but it does not validate or incorrectly validates that the specified index/position/offset has the required properties.",
              "keyphrase_sources": [
                {
                  "id": "rootcause:Improper Input Validation",
                  "keyphrase": "Improper Input Validation",
                  "type": "rootcause"
                },
                {
                  "id": "rootcause:Input Validation vulnerability",
                  "keyphrase": "Input Validation vulnerability",
                  "type": "rootcause"
                }
              ]
            },
            "similarity": 183.90574611449907
          },
          {
            "metadata": {
              "doc_id": "665",
              "name": "Improper Initialization",
              "source": "sparse",
              "original_content": "The product does not initialize or incorrectly initializes a resource, which might leave the resource in an unexpected state when it is accessed or used.",
              "keyphrase_sources": [
                {
                  "id": "rootcause:Improper Input Validation",
                  "keyphrase": "Improper Input Validation",
                  "type": "rootcause"
                },
                {
                  "id": "rootcause:Input Validation vulnerability",
                  "keyphrase": "Input Validation vulnerability",
                  "type": "rootcause"
                },
                {
                  "id": "impact:Code execution",
                  "keyphrase": "Code execution",
                  "type": "impact"
                }
              ]
            },
            "similarity": 181.33972305066118
          },
          {
            "metadata": {
              "doc_id": "287",
              "name": "Improper Authentication",
              "source": "sparse",
              "original_content": "When an actor claims to have a given identity, the product does not prove or insufficiently proves that the claim is correct.",
              "keyphrase_sources": [
                {
                  "id": "rootcause:Improper Input Validation",
                  "keyphrase": "Improper Input Validation",
                  "type": "rootcause"
                },
                {
                  "id": "rootcause:Input Validation vulnerability",
                  "keyphrase": "Input Validation vulnerability",
                  "type": "rootcause"
                },
                {
                  "id": "impact:Code execution",
                  "keyphrase": "Code execution",
                  "type": "impact"
                },
                {
                  "id": "product:Dell BIOS",
                  "keyphrase": "Dell BIOS",
                  "type": "product"
                }
              ]
            },
            "similarity": 178.41939396649317
          }
        ]
      },
      "rootcause:Input Validation vulnerability": {
        "keyphrase": "Input Validation vulnerability",
        "type": "rootcause",
        "cwes": [
          {
            "metadata": {
              "doc_id": "20",
              "name": "Improper Input Validation",
              "source": "sparse",
              "original_content": "The product receives input or data, but it does\n        not validate or incorrectly validates that the input has the\n        properties that are required to process the data safely and\n        correctly."
            },
            "similarity": 206.16536527186344
          },
          {
            "metadata": {
              "doc_id": "119",
              "name": "Improper Restriction of Operations within the Bounds of a Memory Buffer",
              "source": "sparse",
              "original_content": "The product performs operations on a memory buffer, but it reads from or writes to a memory location outside the buffer's intended boundary. This may result in read or write operations on unexpected memory locations that could be linked to other variables, data structures, or internal program data."
            },
            "similarity": 193.7484332752636
          },
          {
            "metadata": {
              "doc_id": "1285",
              "name": "Improper Validation of Specified Index, Position, or Offset in Input",
              "source": "sparse",
              "original_content": "The product receives input that is expected to specify an index, position, or offset into an indexable resource such as a buffer or file, but it does not validate or incorrectly validates that the specified index/position/offset has the required properties."
            },
            "similarity": 179.5966163550948
          },
          {
            "metadata": {
              "doc_id": "665",
              "name": "Improper Initialization",
              "source": "sparse",
              "original_content": "The product does not initialize or incorrectly initializes a resource, which might leave the resource in an unexpected state when it is accessed or used."
            },
            "similarity": 176.74532875470413
          },
          {
            "metadata": {
              "doc_id": "287",
              "name": "Improper Authentication",
              "source": "sparse",
              "original_content": "When an actor claims to have a given identity, the product does not prove or insufficiently proves that the claim is correct."
            },
            "similarity": 173.75032030557105
          }
        ]
      },
      "impact:Code execution": {
        "keyphrase": "Code execution",
        "type": "impact",
        "cwes": [
          {
            "metadata": {
              "doc_id": "119",
              "name": "Improper Restriction of Operations within the Bounds of a Memory Buffer",
              "source": "sparse",
              "original_content": "The product performs operations on a memory buffer, but it reads from or writes to a memory location outside the buffer's intended boundary. This may result in read or write operations on unexpected memory locations that could be linked to other variables, data structures, or internal program data."
            },
            "similarity": 66.38498006776017
          },
          {
            "metadata": {
              "doc_id": "20",
              "name": "Improper Input Validation",
              "source": "sparse",
              "original_content": "The product receives input or data, but it does\n        not validate or incorrectly validates that the input has the\n        properties that are required to process the data safely and\n        correctly."
            },
            "similarity": 61.422063869039455
          },
          {
            "metadata": {
              "doc_id": "125",
              "name": "Out-of-bounds Read",
              "source": "sparse",
              "original_content": "The product reads data past the end, or before the beginning, of the intended buffer.",
              "keyphrase_sources": [
                {
                  "id": "impact:Code execution",
                  "keyphrase": "Code execution",
                  "type": "impact"
                },
                {
                  "id": "product:Dell BIOS",
                  "keyphrase": "Dell BIOS",
                  "type": "product"
                },
                {
                  "id": "component:externally developed component",
                  "keyphrase": "externally developed component",
                  "type": "component"
                }
              ]
            },
            "similarity": 56.35289899754115
          },
          {
            "metadata": {
              "doc_id": "665",
              "name": "Improper Initialization",
              "source": "sparse",
              "original_content": "The product does not initialize or incorrectly initializes a resource, which might leave the resource in an unexpected state when it is accessed or used."
            },
            "similarity": 56.18639622383903
          },
          {
            "metadata": {
              "doc_id": "287",
              "name": "Improper Authentication",
              "source": "sparse",
              "original_content": "When an actor claims to have a given identity, the product does not prove or insufficiently proves that the claim is correct."
            },
            "similarity": 54.83489084219559
          }
        ]
      },
      "attacker:high privileged attacker with local access": {
        "keyphrase": "high privileged attacker with local access",
        "type": "attacker",
        "cwes": [
          {
            "metadata": {
              "doc_id": "119",
              "name": "Improper Restriction of Operations within the Bounds of a Memory Buffer",
              "source": "sparse",
              "original_content": "The product performs operations on a memory buffer, but it reads from or writes to a memory location outside the buffer's intended boundary. This may result in read or write operations on unexpected memory locations that could be linked to other variables, data structures, or internal program data."
            },
            "similarity": 95.47946784781102
          },
          {
            "metadata": {
              "doc_id": "732",
              "name": "Incorrect Permission Assignment for Critical Resource",
              "source": "sparse",
              "original_content": "The product specifies permissions for a security-critical resource in a way that allows that resource to be read or modified by unintended actors.",
              "keyphrase_sources": [
                {
                  "id": "attacker:high privileged attacker with local access",
                  "keyphrase": "high privileged attacker with local access",
                  "type": "attacker"
                },
                {
                  "id": "component:externally developed component",
                  "keyphrase": "externally developed component",
                  "type": "component"
                }
              ]
            },
            "similarity": 84.01111392748903
          },
          {
            "metadata": {
              "doc_id": "20",
              "name": "Improper Input Validation",
              "source": "sparse",
              "original_content": "The product receives input or data, but it does\n        not validate or incorrectly validates that the input has the\n        properties that are required to process the data safely and\n        correctly."
            },
            "similarity": 83.96502448268106
          },
          {
            "metadata": {
              "doc_id": "250",
              "name": "Execution with Unnecessary Privileges",
              "source": "sparse",
              "original_content": "The product performs an operation at a privilege level that is higher than the minimum level required, which creates new weaknesses or amplifies the consequences of other weaknesses.",
              "keyphrase_sources": [
                {
                  "id": "attacker:high privileged attacker with local access",
                  "keyphrase": "high privileged attacker with local access",
                  "type": "attacker"
                }
              ]
            },
            "similarity": 82.16111522865071
          },
          {
            "metadata": {
              "doc_id": "269",
              "name": "Improper Privilege Management",
              "source": "sparse",
              "original_content": "The product does not properly assign, modify, track, or check privileges for an actor, creating an unintended sphere of control for that actor.",
              "keyphrase_sources": [
                {
                  "id": "attacker:high privileged attacker with local access",
                  "keyphrase": "high privileged attacker with local access",
                  "type": "attacker"
                }
              ]
            },
            "similarity": 81.84036787309269
          }
        ]
      },
      "product:Dell BIOS": {
        "keyphrase": "Dell BIOS",
        "type": "product",
        "cwes": [
          {
            "metadata": {
              "doc_id": "119",
              "name": "Improper Restriction of Operations within the Bounds of a Memory Buffer",
              "source": "sparse",
              "original_content": "The product performs operations on a memory buffer, but it reads from or writes to a memory location outside the buffer's intended boundary. This may result in read or write operations on unexpected memory locations that could be linked to other variables, data structures, or internal program data."
            },
            "similarity": 84.02872489335014
          },
          {
            "metadata": {
              "doc_id": "20",
              "name": "Improper Input Validation",
              "source": "sparse",
              "original_content": "The product receives input or data, but it does\n        not validate or incorrectly validates that the input has the\n        properties that are required to process the data safely and\n        correctly."
            },
            "similarity": 65.7185746504202
          },
          {
            "metadata": {
              "doc_id": "287",
              "name": "Improper Authentication",
              "source": "sparse",
              "original_content": "When an actor claims to have a given identity, the product does not prove or insufficiently proves that the claim is correct."
            },
            "similarity": 61.204728441573906
          },
          {
            "metadata": {
              "doc_id": "125",
              "name": "Out-of-bounds Read",
              "source": "sparse",
              "original_content": "The product reads data past the end, or before the beginning, of the intended buffer."
            },
            "similarity": 60.190533230001726
          },
          {
            "metadata": {
              "doc_id": "457",
              "name": "Use of Uninitialized Variable",
              "source": "sparse",
              "original_content": "The code uses a variable that has not been initialized, leading to unpredictable or unintended results.",
              "keyphrase_sources": [
                {
                  "id": "product:Dell BIOS",
                  "keyphrase": "Dell BIOS",
                  "type": "product"
                }
              ]
            },
            "similarity": 59.55590184647966
          }
        ]
      },
      "component:externally developed component": {
        "keyphrase": "externally developed component",
        "type": "component",
        "cwes": [
          {
            "metadata": {
              "doc_id": "119",
              "name": "Improper Restriction of Operations within the Bounds of a Memory Buffer",
              "source": "sparse",
              "original_content": "The product performs operations on a memory buffer, but it reads from or writes to a memory location outside the buffer's intended boundary. This may result in read or write operations on unexpected memory locations that could be linked to other variables, data structures, or internal program data."
            },
            "similarity": 62.32091911943972
          },
          {
            "metadata": {
              "doc_id": "823",
              "name": "Use of Out-of-range Pointer Offset",
              "source": "sparse",
              "original_content": "The product performs pointer arithmetic on a valid pointer, but it uses an offset that can point outside of the intended range of valid memory locations for the resulting pointer.",
              "keyphrase_sources": [
                {
                  "id": "component:externally developed component",
                  "keyphrase": "externally developed component",
                  "type": "component"
                }
              ]
            },
            "similarity": 58.77006656733565
          },
          {
            "metadata": {
              "doc_id": "20",
              "name": "Improper Input Validation",
              "source": "sparse",
              "original_content": "The product receives input or data, but it does\n        not validate or incorrectly validates that the input has the\n        properties that are required to process the data safely and\n        correctly."
            },
            "similarity": 58.63871723986848
          },
          {
            "metadata": {
              "doc_id": "125",
              "name": "Out-of-bounds Read",
              "source": "sparse",
              "original_content": "The product reads data past the end, or before the beginning, of the intended buffer."
            },
            "similarity": 56.32913758248042
          },
          {
            "metadata": {
              "doc_id": "732",
              "name": "Incorrect Permission Assignment for Critical Resource",
              "source": "sparse",
              "original_content": "The product specifies permissions for a security-critical resource in a way that allows that resource to be read or modified by unintended actors."
            },
            "similarity": 55.45324827988823
          }
        ]
      }
    },
    "keyphrase_mapping": {
      "20": [
        {
          "id": "rootcause:Improper Input Validation",
          "keyphrase": "Improper Input Validation",
          "type": "rootcause"
        },
        {
          "id": "rootcause:Input Validation vulnerability",
          "keyphrase": "Input Validation vulnerability",
          "type": "rootcause"
        },
        {
          "id": "impact:Code execution",
          "keyphrase": "Code execution",
          "type": "impact"
        },
        {
          "id": "attacker:high privileged attacker with local access",
          "keyphrase": "high privileged attacker with local access",
          "type": "attacker"
        },
        {
          "id": "product:Dell BIOS",
          "keyphrase": "Dell BIOS",
          "type": "product"
        },
        {
          "id": "component:externally developed component",
          "keyphrase": "externally developed component",
          "type": "component"
        }
      ],
      "119": [
        {
          "id": "rootcause:Improper Input Validation",
          "keyphrase": "Improper Input Validation",
          "type": "rootcause"
        },
        {
          "id": "rootcause:Input Validation vulnerability",
          "keyphrase": "Input Validation vulnerability",
          "type": "rootcause"
        },
        {
          "id": "impact:Code execution",
          "keyphrase": "Code execution",
          "type": "impact"
        },
        {
          "id": "attacker:high privileged attacker with local access",
          "keyphrase": "high privileged attacker with local access",
          "type": "attacker"
        },
        {
          "id": "product:Dell BIOS",
          "keyphrase": "Dell BIOS",
          "type": "product"
        },
        {
          "id": "component:externally developed component",
          "keyphrase": "externally developed component",
          "type": "component"
        }
      ],
      "1285": [
        {
          "id": "rootcause:Improper Input Validation",
          "keyphrase": "Improper Input Validation",
          "type": "rootcause"
        },
        {
          "id": "rootcause:Input Validation vulnerability",
          "keyphrase": "Input Validation vulnerability",
          "type": "rootcause"
        }
      ],
      "665": [
        {
          "id": "rootcause:Improper Input Validation",
          "keyphrase": "Improper Input Validation",
          "type": "rootcause"
        },
        {
          "id": "rootcause:Input Validation vulnerability",
          "keyphrase": "Input Validation vulnerability",
          "type": "rootcause"
        },
        {
          "id": "impact:Code execution",
          "keyphrase": "Code execution",
          "type": "impact"
        }
      ],
      "287": [
        {
          "id": "rootcause:Improper Input Validation",
          "keyphrase": "Improper Input Validation",
          "type": "rootcause"
        },
        {
          "id": "rootcause:Input Validation vulnerability",
          "keyphrase": "Input Validation vulnerability",
          "type": "rootcause"
        },
        {
          "id": "impact:Code execution",
          "keyphrase": "Code execution",
          "type": "impact"
        },
        {
          "id": "product:Dell BIOS",
          "keyphrase": "Dell BIOS",
          "type": "product"
        }
      ],
      "125": [
        {
          "id": "impact:Code execution",
          "keyphrase": "Code execution",
          "type": "impact"
        },
        {
          "id": "product:Dell BIOS",
          "keyphrase": "Dell BIOS",
          "type": "product"
        },
        {
          "id": "component:externally developed component",
          "keyphrase": "externally developed component",
          "type": "component"
        }
      ],
      "732": [
        {
          "id": "attacker:high privileged attacker with local access",
          "keyphrase": "high privileged attacker with local access",
          "type": "attacker"
        },
        {
          "id": "component:externally developed component",
          "keyphrase": "externally developed component",
          "type": "component"
        }
      ],
      "250": [
        {
          "id": "attacker:high privileged attacker with local access",
          "keyphrase": "high privileged attacker with local access",
          "type": "attacker"
        }
      ],
      "269": [
        {
          "id": "attacker:high privileged attacker with local access",
          "keyphrase": "high privileged attacker with local access",
          "type": "attacker"
        }
      ],
      "457": [
        {
          "id": "product:Dell BIOS",
          "keyphrase": "Dell BIOS",
          "type": "product"
        }
      ],
      "823": [
        {
          "id": "component:externally developed component",
          "keyphrase": "externally developed component",
          "type": "component"
        }
      ]
    },
    "relevant_cwes": [
      {
        "metadata": {
          "doc_id": "20",
          "name": "Improper Input Validation",
          "source": "sparse",
          "original_content": "The product receives input or data, but it does\n        not validate or incorrectly validates that the input has the\n        properties that are required to process the data safely and\n        correctly.",
          "keyphrase_sources": [
            {
              "id": "rootcause:Improper Input Validation",
              "keyphrase": "Improper Input Validation",
              "type": "rootcause"
            },
            {
              "id": "rootcause:Input Validation vulnerability",
              "keyphrase": "Input Validation vulnerability",
              "type": "rootcause"
            },
            {
              "id": "impact:Code execution",
              "keyphrase": "Code execution",
              "type": "impact"
            },
            {
              "id": "attacker:high privileged attacker with local access",
              "keyphrase": "high privileged attacker with local access",
              "type": "attacker"
            },
            {
              "id": "product:Dell BIOS",
              "keyphrase": "Dell BIOS",
              "type": "product"
            },
            {
              "id": "component:externally developed component",
              "keyphrase": "externally developed component",
              "type": "component"
            }
          ]
        },
        "similarity": 210.91834378929786
      },
      {
        "metadata": {
          "doc_id": "119",
          "name": "Improper Restriction of Operations within the Bounds of a Memory Buffer",
          "source": "sparse",
          "original_content": "The product performs operations on a memory buffer, but it reads from or writes to a memory location outside the buffer's intended boundary. This may result in read or write operations on unexpected memory locations that could be linked to other variables, data structures, or internal program data.",
          "keyphrase_sources": [
            {
              "id": "rootcause:Improper Input Validation",
              "keyphrase": "Improper Input Validation",
              "type": "rootcause"
            },
            {
              "id": "rootcause:Input Validation vulnerability",
              "keyphrase": "Input Validation vulnerability",
              "type": "rootcause"
            },
            {
              "id": "impact:Code execution",
              "keyphrase": "Code execution",
              "type": "impact"
            },
            {
              "id": "attacker:high privileged attacker with local access",
              "keyphrase": "high privileged attacker with local access",
              "type": "attacker"
            },
            {
              "id": "product:Dell BIOS",
              "keyphrase": "Dell BIOS",
              "type": "product"
            },
            {
              "id": "component:externally developed component",
              "keyphrase": "externally developed component",
              "type": "component"
            }
          ]
        },
        "similarity": 198.2129846091297
      },
      {
        "metadata": {
          "doc_id": "1285",
          "name": "Improper Validation of Specified Index, Position, or Offset in Input",
          "source": "sparse",
          "original_content": "The product receives input that is expected to specify an index, position, or offset into an indexable resource such as a buffer or file, but it does not validate or incorrectly validates that the specified index/position/offset has the required properties.",
          "keyphrase_sources": [
            {
              "id": "rootcause:Improper Input Validation",
              "keyphrase": "Improper Input Validation",
              "type": "rootcause"
            },
            {
              "id": "rootcause:Input Validation vulnerability",
              "keyphrase": "Input Validation vulnerability",
              "type": "rootcause"
            }
          ]
        },
        "similarity": 183.90574611449907
      },
      {
        "metadata": {
          "doc_id": "665",
          "name": "Improper Initialization",
          "source": "sparse",
          "original_content": "The product does not initialize or incorrectly initializes a resource, which might leave the resource in an unexpected state when it is accessed or used.",
          "keyphrase_sources": [
            {
              "id": "rootcause:Improper Input Validation",
              "keyphrase": "Improper Input Validation",
              "type": "rootcause"
            },
            {
              "id": "rootcause:Input Validation vulnerability",
              "keyphrase": "Input Validation vulnerability",
              "type": "rootcause"
            },
            {
              "id": "impact:Code execution",
              "keyphrase": "Code execution",
              "type": "impact"
            }
          ]
        },
        "similarity": 181.33972305066118
      },
      {
        "metadata": {
          "doc_id": "287",
          "name": "Improper Authentication",
          "source": "sparse",
          "original_content": "When an actor claims to have a given identity, the product does not prove or insufficiently proves that the claim is correct.",
          "keyphrase_sources": [
            {
              "id": "rootcause:Improper Input Validation",
              "keyphrase": "Improper Input Validation",
              "type": "rootcause"
            },
            {
              "id": "rootcause:Input Validation vulnerability",
              "keyphrase": "Input Validation vulnerability",
              "type": "rootcause"
            },
            {
              "id": "impact:Code execution",
              "keyphrase": "Code execution",
              "type": "impact"
            },
            {
              "id": "product:Dell BIOS",
              "keyphrase": "Dell BIOS",
              "type": "product"
            }
          ]
        },
        "similarity": 178.41939396649317
      },
      {
        "metadata": {
          "doc_id": "732",
          "name": "Incorrect Permission Assignment for Critical Resource",
          "source": "sparse",
          "original_content": "The product specifies permissions for a security-critical resource in a way that allows that resource to be read or modified by unintended actors.",
          "keyphrase_sources": [
            {
              "id": "attacker:high privileged attacker with local access",
              "keyphrase": "high privileged attacker with local access",
              "type": "attacker"
            },
            {
              "id": "component:externally developed component",
              "keyphrase": "externally developed component",
              "type": "component"
            }
          ]
        },
        "similarity": 84.01111392748903
      },
      {
        "metadata": {
          "doc_id": "250",
          "name": "Execution with Unnecessary Privileges",
          "source": "sparse",
          "original_content": "The product performs an operation at a privilege level that is higher than the minimum level required, which creates new weaknesses or amplifies the consequences of other weaknesses.",
          "keyphrase_sources": [
            {
              "id": "attacker:high privileged attacker with local access",
              "keyphrase": "high privileged attacker with local access",
              "type": "attacker"
            }
          ]
        },
        "similarity": 82.16111522865071
      },
      {
        "metadata": {
          "doc_id": "269",
          "name": "Improper Privilege Management",
          "source": "sparse",
          "original_content": "The product does not properly assign, modify, track, or check privileges for an actor, creating an unintended sphere of control for that actor.",
          "keyphrase_sources": [
            {
              "id": "attacker:high privileged attacker with local access",
              "keyphrase": "high privileged attacker with local access",
              "type": "attacker"
            }
          ]
        },
        "similarity": 81.84036787309269
      },
      {
        "metadata": {
          "doc_id": "457",
          "name": "Use of Uninitialized Variable",
          "source": "sparse",
          "original_content": "The code uses a variable that has not been initialized, leading to unpredictable or unintended results.",
          "keyphrase_sources": [
            {
              "id": "product:Dell BIOS",
              "keyphrase": "Dell BIOS",
              "type": "product"
            }
          ]
        },
        "similarity": 59.55590184647966
      },
      {
        "metadata": {
          "doc_id": "823",
          "name": "Use of Out-of-range Pointer Offset",
          "source": "sparse",
          "original_content": "The product performs pointer arithmetic on a valid pointer, but it uses an offset that can point outside of the intended range of valid memory locations for the resulting pointer.",
          "keyphrase_sources": [
            {
              "id": "component:externally developed component",
              "keyphrase": "externally developed component",
              "type": "component"
            }
          ]
        },
        "similarity": 58.77006656733565
      },
      {
        "metadata": {
          "doc_id": "125",
          "name": "Out-of-bounds Read",
          "source": "sparse",
          "original_content": "The product reads data past the end, or before the beginning, of the intended buffer.",
          "keyphrase_sources": [
            {
              "id": "impact:Code execution",
              "keyphrase": "Code execution",
              "type": "impact"
            },
            {
              "id": "product:Dell BIOS",
              "keyphrase": "Dell BIOS",
              "type": "product"
            },
            {
              "id": "component:externally developed component",
              "keyphrase": "externally developed component",
              "type": "component"
            }
          ]
        },
        "similarity": 56.35289899754115
      }
    ],
    "enhanced_query": "# Vulnerability Description\n\n    Dell BIOS contains an **Improper Input Validation** vulnerability in an externally developed component. A high privileged attacker with local access could potentially exploit this vulnerability, leading to Code execution.\n\n    # Keyphrase-Specific CWE Analysis\n    This vulnerability contains multiple keyphrases that may map to different CWEs. \n    Please analyze each keyphrase separately and determine the most appropriate CWE(s) for each.\n\n    ## ROOTCAUSE: 'Improper Input Validation'\n\nRelevant CWEs for this ROOTCAUSE:\n\n### 1. CWE-20: Improper Input Validation (Score: 210.92)\n\nThe product receives input or data, but it does\n        not validate or incorrectly validates that the input has the\n        properties that are required to process the data safely and\n        correctly....\n\n### 2. CWE-119: Improper Restriction of Operations within the Bounds of a Memory Buffer (Score: 198.21)\n\nThe product performs operations on a memory buffer, but it reads from or writes to a memory location outside the buffer's intended boundary. This may result in read or write operations on unexpected memory locations that could be linked to other variables, data structures, or internal program data....\n\n### 3. CWE-1285: Improper Validation of Specified Index, Position, or Offset in Input (Score: 183.91)\n\nThe product receives input that is expected to specify an index, position, or offset into an indexable resource such as a buffer or file, but it does not validate or incorrectly validates that the specified index/position/offset has the required properties....\n\n### 4. CWE-665: Improper Initialization (Score: 181.34)\n\nThe product does not initialize or incorrectly initializes a resource, which might leave the resource in an unexpected state when it is accessed or used....\n\n### 5. CWE-287: Improper Authentication (Score: 178.42)\n\nWhen an actor claims to have a given identity, the product does not prove or insufficiently proves that the claim is correct....\n\n## ROOTCAUSE: 'Input Validation vulnerability'\n\nRelevant CWEs for this ROOTCAUSE:\n\n### 1. CWE-20: Improper Input Validation (Score: 210.92)\n\nThe product receives input or data, but it does\n        not validate or incorrectly validates that the input has the\n        properties that are required to process the data safely and\n        correctly....\n\n### 2. CWE-119: Improper Restriction of Operations within the Bounds of a Memory Buffer (Score: 198.21)\n\nThe product performs operations on a memory buffer, but it reads from or writes to a memory location outside the buffer's intended boundary. This may result in read or write operations on unexpected memory locations that could be linked to other variables, data structures, or internal program data....\n\n### 3. CWE-1285: Improper Validation of Specified Index, Position, or Offset in Input (Score: 183.91)\n\nThe product receives input that is expected to specify an index, position, or offset into an indexable resource such as a buffer or file, but it does not validate or incorrectly validates that the specified index/position/offset has the required properties....\n\n### 4. CWE-665: Improper Initialization (Score: 181.34)\n\nThe product does not initialize or incorrectly initializes a resource, which might leave the resource in an unexpected state when it is accessed or used....\n\n### 5. CWE-287: Improper Authentication (Score: 178.42)\n\nWhen an actor claims to have a given identity, the product does not prove or insufficiently proves that the claim is correct....\n\n## IMPACT: 'Code execution'\n\nRelevant CWEs for this IMPACT:\n\n### 1. CWE-20: Improper Input Validation (Score: 210.92)\n\nThe product receives input or data, but it does\n        not validate or incorrectly validates that the input has the\n        properties that are required to process the data safely and\n        correctly....\n\n### 2. CWE-119: Improper Restriction of Operations within the Bounds of a Memory Buffer (Score: 198.21)\n\nThe product performs operations on a memory buffer, but it reads from or writes to a memory location outside the buffer's intended boundary. This may result in read or write operations on unexpected memory locations that could be linked to other variables, data structures, or internal program data....\n\n### 3. CWE-665: Improper Initialization (Score: 181.34)\n\nThe product does not initialize or incorrectly initializes a resource, which might leave the resource in an unexpected state when it is accessed or used....\n\n### 4. CWE-287: Improper Authentication (Score: 178.42)\n\nWhen an actor claims to have a given identity, the product does not prove or insufficiently proves that the claim is correct....\n\n### 5. CWE-125: Out-of-bounds Read (Score: 56.35)\n\nThe product reads data past the end, or before the beginning, of the intended buffer....\n\n## ATTACKER: 'high privileged attacker with local access'\n\nRelevant CWEs for this ATTACKER:\n\n### 1. CWE-20: Improper Input Validation (Score: 210.92)\n\nThe product receives input or data, but it does\n        not validate or incorrectly validates that the input has the\n        properties that are required to process the data safely and\n        correctly....\n\n### 2. CWE-119: Improper Restriction of Operations within the Bounds of a Memory Buffer (Score: 198.21)\n\nThe product performs operations on a memory buffer, but it reads from or writes to a memory location outside the buffer's intended boundary. This may result in read or write operations on unexpected memory locations that could be linked to other variables, data structures, or internal program data....\n\n### 3. CWE-732: Incorrect Permission Assignment for Critical Resource (Score: 84.01)\n\nThe product specifies permissions for a security-critical resource in a way that allows that resource to be read or modified by unintended actors....\n\n### 4. CWE-250: Execution with Unnecessary Privileges (Score: 82.16)\n\nThe product performs an operation at a privilege level that is higher than the minimum level required, which creates new weaknesses or amplifies the consequences of other weaknesses....\n\n### 5. CWE-269: Improper Privilege Management (Score: 81.84)\n\nThe product does not properly assign, modify, track, or check privileges for an actor, creating an unintended sphere of control for that actor....\n\n## PRODUCT: 'Dell BIOS'\n\nRelevant CWEs for this PRODUCT:\n\n### 1. CWE-20: Improper Input Validation (Score: 210.92)\n\nThe product receives input or data, but it does\n        not validate or incorrectly validates that the input has the\n        properties that are required to process the data safely and\n        correctly....\n\n### 2. CWE-119: Improper Restriction of Operations within the Bounds of a Memory Buffer (Score: 198.21)\n\nThe product performs operations on a memory buffer, but it reads from or writes to a memory location outside the buffer's intended boundary. This may result in read or write operations on unexpected memory locations that could be linked to other variables, data structures, or internal program data....\n\n### 3. CWE-287: Improper Authentication (Score: 178.42)\n\nWhen an actor claims to have a given identity, the product does not prove or insufficiently proves that the claim is correct....\n\n### 4. CWE-457: Use of Uninitialized Variable (Score: 59.56)\n\nThe code uses a variable that has not been initialized, leading to unpredictable or unintended results....\n\n### 5. CWE-125: Out-of-bounds Read (Score: 56.35)\n\nThe product reads data past the end, or before the beginning, of the intended buffer....\n\n## COMPONENT: 'externally developed component'\n\nRelevant CWEs for this COMPONENT:\n\n### 1. CWE-20: Improper Input Validation (Score: 210.92)\n\nThe product receives input or data, but it does\n        not validate or incorrectly validates that the input has the\n        properties that are required to process the data safely and\n        correctly....\n\n### 2. CWE-119: Improper Restriction of Operations within the Bounds of a Memory Buffer (Score: 198.21)\n\nThe product performs operations on a memory buffer, but it reads from or writes to a memory location outside the buffer's intended boundary. This may result in read or write operations on unexpected memory locations that could be linked to other variables, data structures, or internal program data....\n\n### 3. CWE-732: Incorrect Permission Assignment for Critical Resource (Score: 84.01)\n\nThe product specifies permissions for a security-critical resource in a way that allows that resource to be read or modified by unintended actors....\n\n### 4. CWE-823: Use of Out-of-range Pointer Offset (Score: 58.77)\n\nThe product performs pointer arithmetic on a valid pointer, but it uses an offset that can point outside of the intended range of valid memory locations for the resulting pointer....\n\n### 5. CWE-125: Out-of-bounds Read (Score: 56.35)\n\nThe product reads data past the end, or before the beginning, of the intended buffer....\n\n\n    # Analysis Instructions\n    1. For each keyphrase, identify the most appropriate CWE(s) that represent the weakness.\n    2. Consider how the different keyphrases might relate to each other in the vulnerability chain.\n    3. Provide a final determination of primary CWE(s) and any secondary CWEs.\n    4. Format your response using the standard analysis template.\n\n    Please analyze how these different weaknesses interact and provide a comprehensive CWE classification.\n    "
  },
  "retrieval_time": 1.0513699054718018
}