{
  "vulnerability_info": "VulnerabilityInfo(cve_id='CVE-2024-42105', description='In the Linux kernel, the following vulnerability has been resolved nilfs2 fix inode number range checks Patch series nilfs2 fix potential issues related to reserved inodes. This series fixes one **use-after-free** issue reported by syzbot, caused by nilfs2s internal inode being exposed in the namespace on a corrupted filesystem, and a couple of flaws that cause problems if the starting number of non-reserved inodes written in the on-disk super block is intentionally (or corruptly) changed from its default value. This patch (of 3) In the current implementation of nilfs2, nilfs->ns_first_ino, which gives the first non-reserved inode number, is read from the superblock, but its lower limit is not checked. As a result, if a number that overlaps with the inode number range of reserved inodes such as the root directory or metadata files is set in the super block parameter, the inode number test macros (NILFS_MDT_INODE and NILFS_VALID_INODE) will not function properly. In addition, these test macros use left bit-shift calculations using with the inode number as the shift count via the BIT macro, but the result of a shift calculation that exceeds the bit width of an integer is undefined in the C specification, so if ns_first_ino is set to a large value other than the default value NILFS_USER_INO (=11), the macros may potentially malfunction depending on the environment. Fix these issues by checking the lower bound of nilfs->ns_first_ino and by preventing bit shift', key_phrases={'rootcause': '', 'weakness': ['use-after-free', 'improper input validation'], 'impact': 'information disclosure', 'vector': '', 'attacker': '', 'product': 'Linux kernel', 'version': '', 'component': 'nilfs2'}, reference_content=\"Based on the provided information, here's an analysis of the vulnerability:\\n\\n**Root Cause:**\\n\\nThe root cause is the lack of proper validation for the `ns_first_ino` value read from the superblock in the NILFS2 filesystem. Specifically, the code does not check if this value, which represents the first non-reserved inode number, is within a valid range.\\n\\n**Weaknesses/Vulnerabilities:**\\n\\n1.  **Insufficient Lower Bound Check:** The code does not ensure that `ns_first_ino` is greater than or equal to `NILFS_USER_INO`. This allows for the possibility of `ns_first_ino` overlapping with reserved inode numbers.\\n2.  **Incorrect Inode Number Tests:** The macros `NILFS_MDT_INODE` and `NILFS_VALID_INODE` rely on the `ns_first_ino` value for their calculations. If `ns_first_ino` is set to a value less than `NILFS_USER_INO`, these macros will not function correctly.\\n3.  **Undefined Bit Shift Behavior:** The `BIT` macro performs left bit-shift operations using the inode number as a shift count. When the shift count exceeds the bit width of an integer, the behavior is undefined in the C specification and may result in unexpected behavior. This can occur if `ns_first_ino` is set to a large value.\\n\\n**Impact of Exploitation:**\\n\\n*   **Incorrect Inode Number Handling:** If a crafted or corrupted filesystem sets `ns_first_ino` to a low value (overlapping with reserved inodes), the inode number test macros will misidentify inodes, potentially leading to file system corruption, data loss, and other undefined behavior.\\n*   **Potential Use-After-Free:**  The description mentions a use-after-free issue reported by syzbot. This is not directly addressed by the provided patch, but the root cause of the use-after-free is related to the incorrect inode handling.\\n*   **System Instability**: Malfunctioning inode tests can lead to a variety of unpredictable issues and potentially crash the kernel.\\n\\n**Attack Vectors:**\\n\\n*   **Corrupted Filesystem:**  An attacker can create a corrupted NILFS2 filesystem image that includes a malicious value for `s_first_ino` in the superblock.\\n*   **Malicious Filesystem Creation:** An attacker with sufficient privileges could create and mount a malicious NILFS2 filesystem with the intention of triggering a vulnerability.\\n\\n**Required Attacker Capabilities/Position:**\\n\\n*   **Filesystem Manipulation:** The attacker must be able to create or manipulate a NILFS2 filesystem image and have the ability to mount this filesystem.\\n*   **System Access:** To trigger the vulnerability, the attacker needs to mount the crafted filesystem on a vulnerable Linux system running the NILFS2 driver.\\n\\n**Fix:**\\n\\nThe provided patches address the issue by:\\n* Adding a check to ensure `nilfs->ns_first_ino` is not less than `NILFS_USER_INO`, returning an error (`-EINVAL`) if the check fails.\\n*  Modifying `NILFS_MDT_INODE` and `NILFS_VALID_INODE` macros to use `NILFS_USER_INO` as the lower bound rather than `NILFS_FIRST_INO(sb)` to prevent bitshifts equal or greater than `NILFS_USER_INO`.\\n* Changing the type of `ns_first_ino` from a signed integer to an unsigned integer, which eliminates the need for type casting.\\n\\nThis fix prevents the issues caused by invalid values for `ns_first_ino` loaded from the superblock.\", similar_info={'cwe_distribution': {}, 'cwe_consensus': '', 'similarity_stats': {'thresholds': [], 'total_samples_by_threshold': {}, 'top_cwes_by_threshold': {}}}, similarity_summary=SimilarityInsight(consensus_cwe='', top_cwes=[], confidence_levels={}, total_samples=0), analysis='', analysis_with_relationships='', criticism='', resolution='', relevant_cwes=[{'metadata': {'doc_id': '775', 'name': 'Missing Release of File Descriptor or Handle after Effective Lifetime', 'source': 'sparse', 'original_content': 'The product does not release a file descriptor or handle after its effective lifetime has ended, i.e., after the file descriptor/handle is no longer needed.', 'keyphrase_sources': [{'id': 'weakness:use-after-free', 'keyphrase': 'use-after-free', 'type': 'weakness'}, {'id': 'weakness:improper input validation', 'keyphrase': 'improper input validation', 'type': 'weakness'}, {'id': 'impact:information disclosure', 'keyphrase': 'information disclosure', 'type': 'impact'}, {'id': 'product:Linux kernel', 'keyphrase': 'Linux kernel', 'type': 'product'}, {'id': 'component:nilfs2', 'keyphrase': 'nilfs2', 'type': 'component'}]}, 'similarity': np.float64(1149.543804380823)}, {'metadata': {'doc_id': '190', 'name': 'Integer Overflow or Wraparound', 'source': 'sparse', 'original_content': 'The product performs a calculation that can\\n         produce an integer overflow or wraparound when the logic\\n         assumes that the resulting value will always be larger than\\n         the original value. This occurs when an integer value is\\n         incremented to a value that is too large to store in the\\n         associated representation. When this occurs, the value may\\n         become a very small or negative number.', 'keyphrase_sources': [{'id': 'weakness:use-after-free', 'keyphrase': 'use-after-free', 'type': 'weakness'}, {'id': 'weakness:improper input validation', 'keyphrase': 'improper input validation', 'type': 'weakness'}, {'id': 'impact:information disclosure', 'keyphrase': 'information disclosure', 'type': 'impact'}, {'id': 'product:Linux kernel', 'keyphrase': 'Linux kernel', 'type': 'product'}, {'id': 'component:nilfs2', 'keyphrase': 'nilfs2', 'type': 'component'}]}, 'similarity': np.float64(1148.3285074852868)}, {'metadata': {'doc_id': '1284', 'name': 'Improper Validation of Specified Quantity in Input', 'source': 'sparse', 'original_content': 'The product receives input that is expected to specify a quantity (such as size or length), but it does not validate or incorrectly validates that the quantity has the required properties.', 'keyphrase_sources': [{'id': 'weakness:use-after-free', 'keyphrase': 'use-after-free', 'type': 'weakness'}, {'id': 'weakness:improper input validation', 'keyphrase': 'improper input validation', 'type': 'weakness'}, {'id': 'impact:information disclosure', 'keyphrase': 'information disclosure', 'type': 'impact'}, {'id': 'product:Linux kernel', 'keyphrase': 'Linux kernel', 'type': 'product'}, {'id': 'component:nilfs2', 'keyphrase': 'nilfs2', 'type': 'component'}]}, 'similarity': np.float64(1133.9563652255301)}, {'metadata': {'doc_id': '125', 'name': 'Out-of-bounds Read', 'source': 'sparse', 'original_content': 'The product reads data past the end, or before the beginning, of the intended buffer.', 'keyphrase_sources': [{'id': 'weakness:use-after-free', 'keyphrase': 'use-after-free', 'type': 'weakness'}, {'id': 'weakness:improper input validation', 'keyphrase': 'improper input validation', 'type': 'weakness'}, {'id': 'impact:information disclosure', 'keyphrase': 'information disclosure', 'type': 'impact'}, {'id': 'product:Linux kernel', 'keyphrase': 'Linux kernel', 'type': 'product'}, {'id': 'component:nilfs2', 'keyphrase': 'nilfs2', 'type': 'component'}]}, 'similarity': np.float64(1116.6469655852022)}, {'metadata': {'doc_id': '1335', 'name': 'Incorrect Bitwise Shift of Integer', 'source': 'sparse', 'original_content': 'An integer value is specified to be shifted by a negative amount or an amount greater than or equal to the number of bits contained in the value causing an unexpected or indeterminate result.', 'keyphrase_sources': [{'id': 'weakness:use-after-free', 'keyphrase': 'use-after-free', 'type': 'weakness'}, {'id': 'weakness:improper input validation', 'keyphrase': 'improper input validation', 'type': 'weakness'}, {'id': 'impact:information disclosure', 'keyphrase': 'information disclosure', 'type': 'impact'}, {'id': 'product:Linux kernel', 'keyphrase': 'Linux kernel', 'type': 'product'}, {'id': 'component:nilfs2', 'keyphrase': 'nilfs2', 'type': 'component'}]}, 'similarity': np.float64(1087.6527599990764)}], identified_cwes={'analyzer': [], 'critic_additional': []})",
  "retrieval_results": {
    "has_multiple_keyphrases": true,
    "keyphrase_cwe_sets": {
      "weakness:use-after-free": {
        "keyphrase": "use-after-free",
        "type": "weakness",
        "cwes": [
          {
            "metadata": {
              "doc_id": "775",
              "name": "Missing Release of File Descriptor or Handle after Effective Lifetime",
              "source": "sparse",
              "original_content": "The product does not release a file descriptor or handle after its effective lifetime has ended, i.e., after the file descriptor/handle is no longer needed.",
              "keyphrase_sources": [
                {
                  "id": "weakness:use-after-free",
                  "keyphrase": "use-after-free",
                  "type": "weakness"
                },
                {
                  "id": "weakness:improper input validation",
                  "keyphrase": "improper input validation",
                  "type": "weakness"
                },
                {
                  "id": "impact:information disclosure",
                  "keyphrase": "information disclosure",
                  "type": "impact"
                },
                {
                  "id": "product:Linux kernel",
                  "keyphrase": "Linux kernel",
                  "type": "product"
                },
                {
                  "id": "component:nilfs2",
                  "keyphrase": "nilfs2",
                  "type": "component"
                }
              ]
            },
            "similarity": 1149.543804380823
          },
          {
            "metadata": {
              "doc_id": "190",
              "name": "Integer Overflow or Wraparound",
              "source": "sparse",
              "original_content": "The product performs a calculation that can\n         produce an integer overflow or wraparound when the logic\n         assumes that the resulting value will always be larger than\n         the original value. This occurs when an integer value is\n         incremented to a value that is too large to store in the\n         associated representation. When this occurs, the value may\n         become a very small or negative number.",
              "keyphrase_sources": [
                {
                  "id": "weakness:use-after-free",
                  "keyphrase": "use-after-free",
                  "type": "weakness"
                },
                {
                  "id": "weakness:improper input validation",
                  "keyphrase": "improper input validation",
                  "type": "weakness"
                },
                {
                  "id": "impact:information disclosure",
                  "keyphrase": "information disclosure",
                  "type": "impact"
                },
                {
                  "id": "product:Linux kernel",
                  "keyphrase": "Linux kernel",
                  "type": "product"
                },
                {
                  "id": "component:nilfs2",
                  "keyphrase": "nilfs2",
                  "type": "component"
                }
              ]
            },
            "similarity": 1148.3285074852868
          },
          {
            "metadata": {
              "doc_id": "1284",
              "name": "Improper Validation of Specified Quantity in Input",
              "source": "sparse",
              "original_content": "The product receives input that is expected to specify a quantity (such as size or length), but it does not validate or incorrectly validates that the quantity has the required properties.",
              "keyphrase_sources": [
                {
                  "id": "weakness:use-after-free",
                  "keyphrase": "use-after-free",
                  "type": "weakness"
                },
                {
                  "id": "weakness:improper input validation",
                  "keyphrase": "improper input validation",
                  "type": "weakness"
                },
                {
                  "id": "impact:information disclosure",
                  "keyphrase": "information disclosure",
                  "type": "impact"
                },
                {
                  "id": "product:Linux kernel",
                  "keyphrase": "Linux kernel",
                  "type": "product"
                },
                {
                  "id": "component:nilfs2",
                  "keyphrase": "nilfs2",
                  "type": "component"
                }
              ]
            },
            "similarity": 1133.9563652255301
          },
          {
            "metadata": {
              "doc_id": "125",
              "name": "Out-of-bounds Read",
              "source": "sparse",
              "original_content": "The product reads data past the end, or before the beginning, of the intended buffer.",
              "keyphrase_sources": [
                {
                  "id": "weakness:use-after-free",
                  "keyphrase": "use-after-free",
                  "type": "weakness"
                },
                {
                  "id": "weakness:improper input validation",
                  "keyphrase": "improper input validation",
                  "type": "weakness"
                },
                {
                  "id": "impact:information disclosure",
                  "keyphrase": "information disclosure",
                  "type": "impact"
                },
                {
                  "id": "product:Linux kernel",
                  "keyphrase": "Linux kernel",
                  "type": "product"
                },
                {
                  "id": "component:nilfs2",
                  "keyphrase": "nilfs2",
                  "type": "component"
                }
              ]
            },
            "similarity": 1116.6469655852022
          },
          {
            "metadata": {
              "doc_id": "1335",
              "name": "Incorrect Bitwise Shift of Integer",
              "source": "sparse",
              "original_content": "An integer value is specified to be shifted by a negative amount or an amount greater than or equal to the number of bits contained in the value causing an unexpected or indeterminate result.",
              "keyphrase_sources": [
                {
                  "id": "weakness:use-after-free",
                  "keyphrase": "use-after-free",
                  "type": "weakness"
                },
                {
                  "id": "weakness:improper input validation",
                  "keyphrase": "improper input validation",
                  "type": "weakness"
                },
                {
                  "id": "impact:information disclosure",
                  "keyphrase": "information disclosure",
                  "type": "impact"
                },
                {
                  "id": "product:Linux kernel",
                  "keyphrase": "Linux kernel",
                  "type": "product"
                },
                {
                  "id": "component:nilfs2",
                  "keyphrase": "nilfs2",
                  "type": "component"
                }
              ]
            },
            "similarity": 1087.6527599990764
          }
        ]
      },
      "weakness:improper input validation": {
        "keyphrase": "improper input validation",
        "type": "weakness",
        "cwes": [
          {
            "metadata": {
              "doc_id": "1284",
              "name": "Improper Validation of Specified Quantity in Input",
              "source": "sparse",
              "original_content": "The product receives input that is expected to specify a quantity (such as size or length), but it does not validate or incorrectly validates that the quantity has the required properties."
            },
            "similarity": 1160.295467181363
          },
          {
            "metadata": {
              "doc_id": "190",
              "name": "Integer Overflow or Wraparound",
              "source": "sparse",
              "original_content": "The product performs a calculation that can\n         produce an integer overflow or wraparound when the logic\n         assumes that the resulting value will always be larger than\n         the original value. This occurs when an integer value is\n         incremented to a value that is too large to store in the\n         associated representation. When this occurs, the value may\n         become a very small or negative number."
            },
            "similarity": 1151.334762375842
          },
          {
            "metadata": {
              "doc_id": "775",
              "name": "Missing Release of File Descriptor or Handle after Effective Lifetime",
              "source": "sparse",
              "original_content": "The product does not release a file descriptor or handle after its effective lifetime has ended, i.e., after the file descriptor/handle is no longer needed."
            },
            "similarity": 1130.2141275986687
          },
          {
            "metadata": {
              "doc_id": "125",
              "name": "Out-of-bounds Read",
              "source": "sparse",
              "original_content": "The product reads data past the end, or before the beginning, of the intended buffer."
            },
            "similarity": 1126.075164523737
          },
          {
            "metadata": {
              "doc_id": "1335",
              "name": "Incorrect Bitwise Shift of Integer",
              "source": "sparse",
              "original_content": "An integer value is specified to be shifted by a negative amount or an amount greater than or equal to the number of bits contained in the value causing an unexpected or indeterminate result."
            },
            "similarity": 1087.6527599990764
          }
        ]
      },
      "impact:information disclosure": {
        "keyphrase": "information disclosure",
        "type": "impact",
        "cwes": [
          {
            "metadata": {
              "doc_id": "190",
              "name": "Integer Overflow or Wraparound",
              "source": "sparse",
              "original_content": "The product performs a calculation that can\n         produce an integer overflow or wraparound when the logic\n         assumes that the resulting value will always be larger than\n         the original value. This occurs when an integer value is\n         incremented to a value that is too large to store in the\n         associated representation. When this occurs, the value may\n         become a very small or negative number."
            },
            "similarity": 409.5583865580316
          },
          {
            "metadata": {
              "doc_id": "1284",
              "name": "Improper Validation of Specified Quantity in Input",
              "source": "sparse",
              "original_content": "The product receives input that is expected to specify a quantity (such as size or length), but it does not validate or incorrectly validates that the quantity has the required properties."
            },
            "similarity": 406.919601406385
          },
          {
            "metadata": {
              "doc_id": "775",
              "name": "Missing Release of File Descriptor or Handle after Effective Lifetime",
              "source": "sparse",
              "original_content": "The product does not release a file descriptor or handle after its effective lifetime has ended, i.e., after the file descriptor/handle is no longer needed."
            },
            "similarity": 403.64790271381025
          },
          {
            "metadata": {
              "doc_id": "125",
              "name": "Out-of-bounds Read",
              "source": "sparse",
              "original_content": "The product reads data past the end, or before the beginning, of the intended buffer."
            },
            "similarity": 403.57682605350476
          },
          {
            "metadata": {
              "doc_id": "1335",
              "name": "Incorrect Bitwise Shift of Integer",
              "source": "sparse",
              "original_content": "An integer value is specified to be shifted by a negative amount or an amount greater than or equal to the number of bits contained in the value causing an unexpected or indeterminate result."
            },
            "similarity": 388.4474142853844
          }
        ]
      },
      "product:Linux kernel": {
        "keyphrase": "Linux kernel",
        "type": "product",
        "cwes": [
          {
            "metadata": {
              "doc_id": "1284",
              "name": "Improper Validation of Specified Quantity in Input",
              "source": "sparse",
              "original_content": "The product receives input that is expected to specify a quantity (such as size or length), but it does not validate or incorrectly validates that the quantity has the required properties."
            },
            "similarity": 411.0249418235169
          },
          {
            "metadata": {
              "doc_id": "190",
              "name": "Integer Overflow or Wraparound",
              "source": "sparse",
              "original_content": "The product performs a calculation that can\n         produce an integer overflow or wraparound when the logic\n         assumes that the resulting value will always be larger than\n         the original value. This occurs when an integer value is\n         incremented to a value that is too large to store in the\n         associated representation. When this occurs, the value may\n         become a very small or negative number."
            },
            "similarity": 410.8249350030905
          },
          {
            "metadata": {
              "doc_id": "775",
              "name": "Missing Release of File Descriptor or Handle after Effective Lifetime",
              "source": "sparse",
              "original_content": "The product does not release a file descriptor or handle after its effective lifetime has ended, i.e., after the file descriptor/handle is no longer needed."
            },
            "similarity": 408.6348890923018
          },
          {
            "metadata": {
              "doc_id": "125",
              "name": "Out-of-bounds Read",
              "source": "sparse",
              "original_content": "The product reads data past the end, or before the beginning, of the intended buffer."
            },
            "similarity": 404.5532914822194
          },
          {
            "metadata": {
              "doc_id": "1335",
              "name": "Incorrect Bitwise Shift of Integer",
              "source": "sparse",
              "original_content": "An integer value is specified to be shifted by a negative amount or an amount greater than or equal to the number of bits contained in the value causing an unexpected or indeterminate result."
            },
            "similarity": 394.57513944309153
          }
        ]
      },
      "component:nilfs2": {
        "keyphrase": "nilfs2",
        "type": "component",
        "cwes": [
          {
            "metadata": {
              "doc_id": "190",
              "name": "Integer Overflow or Wraparound",
              "source": "sparse",
              "original_content": "The product performs a calculation that can\n         produce an integer overflow or wraparound when the logic\n         assumes that the resulting value will always be larger than\n         the original value. This occurs when an integer value is\n         incremented to a value that is too large to store in the\n         associated representation. When this occurs, the value may\n         become a very small or negative number."
            },
            "similarity": 404.25832022965034
          },
          {
            "metadata": {
              "doc_id": "775",
              "name": "Missing Release of File Descriptor or Handle after Effective Lifetime",
              "source": "sparse",
              "original_content": "The product does not release a file descriptor or handle after its effective lifetime has ended, i.e., after the file descriptor/handle is no longer needed."
            },
            "similarity": 403.64790271381025
          },
          {
            "metadata": {
              "doc_id": "1284",
              "name": "Improper Validation of Specified Quantity in Input",
              "source": "sparse",
              "original_content": "The product receives input that is expected to specify a quantity (such as size or length), but it does not validate or incorrectly validates that the quantity has the required properties."
            },
            "similarity": 402.3947372478609
          },
          {
            "metadata": {
              "doc_id": "125",
              "name": "Out-of-bounds Read",
              "source": "sparse",
              "original_content": "The product reads data past the end, or before the beginning, of the intended buffer."
            },
            "similarity": 396.31885307190464
          },
          {
            "metadata": {
              "doc_id": "1335",
              "name": "Incorrect Bitwise Shift of Integer",
              "source": "sparse",
              "original_content": "An integer value is specified to be shifted by a negative amount or an amount greater than or equal to the number of bits contained in the value causing an unexpected or indeterminate result."
            },
            "similarity": 388.4474142853844
          }
        ]
      }
    },
    "keyphrase_mapping": {
      "775": [
        {
          "id": "weakness:use-after-free",
          "keyphrase": "use-after-free",
          "type": "weakness"
        },
        {
          "id": "weakness:improper input validation",
          "keyphrase": "improper input validation",
          "type": "weakness"
        },
        {
          "id": "impact:information disclosure",
          "keyphrase": "information disclosure",
          "type": "impact"
        },
        {
          "id": "product:Linux kernel",
          "keyphrase": "Linux kernel",
          "type": "product"
        },
        {
          "id": "component:nilfs2",
          "keyphrase": "nilfs2",
          "type": "component"
        }
      ],
      "190": [
        {
          "id": "weakness:use-after-free",
          "keyphrase": "use-after-free",
          "type": "weakness"
        },
        {
          "id": "weakness:improper input validation",
          "keyphrase": "improper input validation",
          "type": "weakness"
        },
        {
          "id": "impact:information disclosure",
          "keyphrase": "information disclosure",
          "type": "impact"
        },
        {
          "id": "product:Linux kernel",
          "keyphrase": "Linux kernel",
          "type": "product"
        },
        {
          "id": "component:nilfs2",
          "keyphrase": "nilfs2",
          "type": "component"
        }
      ],
      "1284": [
        {
          "id": "weakness:use-after-free",
          "keyphrase": "use-after-free",
          "type": "weakness"
        },
        {
          "id": "weakness:improper input validation",
          "keyphrase": "improper input validation",
          "type": "weakness"
        },
        {
          "id": "impact:information disclosure",
          "keyphrase": "information disclosure",
          "type": "impact"
        },
        {
          "id": "product:Linux kernel",
          "keyphrase": "Linux kernel",
          "type": "product"
        },
        {
          "id": "component:nilfs2",
          "keyphrase": "nilfs2",
          "type": "component"
        }
      ],
      "125": [
        {
          "id": "weakness:use-after-free",
          "keyphrase": "use-after-free",
          "type": "weakness"
        },
        {
          "id": "weakness:improper input validation",
          "keyphrase": "improper input validation",
          "type": "weakness"
        },
        {
          "id": "impact:information disclosure",
          "keyphrase": "information disclosure",
          "type": "impact"
        },
        {
          "id": "product:Linux kernel",
          "keyphrase": "Linux kernel",
          "type": "product"
        },
        {
          "id": "component:nilfs2",
          "keyphrase": "nilfs2",
          "type": "component"
        }
      ],
      "1335": [
        {
          "id": "weakness:use-after-free",
          "keyphrase": "use-after-free",
          "type": "weakness"
        },
        {
          "id": "weakness:improper input validation",
          "keyphrase": "improper input validation",
          "type": "weakness"
        },
        {
          "id": "impact:information disclosure",
          "keyphrase": "information disclosure",
          "type": "impact"
        },
        {
          "id": "product:Linux kernel",
          "keyphrase": "Linux kernel",
          "type": "product"
        },
        {
          "id": "component:nilfs2",
          "keyphrase": "nilfs2",
          "type": "component"
        }
      ]
    },
    "relevant_cwes": [
      {
        "metadata": {
          "doc_id": "775",
          "name": "Missing Release of File Descriptor or Handle after Effective Lifetime",
          "source": "sparse",
          "original_content": "The product does not release a file descriptor or handle after its effective lifetime has ended, i.e., after the file descriptor/handle is no longer needed.",
          "keyphrase_sources": [
            {
              "id": "weakness:use-after-free",
              "keyphrase": "use-after-free",
              "type": "weakness"
            },
            {
              "id": "weakness:improper input validation",
              "keyphrase": "improper input validation",
              "type": "weakness"
            },
            {
              "id": "impact:information disclosure",
              "keyphrase": "information disclosure",
              "type": "impact"
            },
            {
              "id": "product:Linux kernel",
              "keyphrase": "Linux kernel",
              "type": "product"
            },
            {
              "id": "component:nilfs2",
              "keyphrase": "nilfs2",
              "type": "component"
            }
          ]
        },
        "similarity": 1149.543804380823
      },
      {
        "metadata": {
          "doc_id": "190",
          "name": "Integer Overflow or Wraparound",
          "source": "sparse",
          "original_content": "The product performs a calculation that can\n         produce an integer overflow or wraparound when the logic\n         assumes that the resulting value will always be larger than\n         the original value. This occurs when an integer value is\n         incremented to a value that is too large to store in the\n         associated representation. When this occurs, the value may\n         become a very small or negative number.",
          "keyphrase_sources": [
            {
              "id": "weakness:use-after-free",
              "keyphrase": "use-after-free",
              "type": "weakness"
            },
            {
              "id": "weakness:improper input validation",
              "keyphrase": "improper input validation",
              "type": "weakness"
            },
            {
              "id": "impact:information disclosure",
              "keyphrase": "information disclosure",
              "type": "impact"
            },
            {
              "id": "product:Linux kernel",
              "keyphrase": "Linux kernel",
              "type": "product"
            },
            {
              "id": "component:nilfs2",
              "keyphrase": "nilfs2",
              "type": "component"
            }
          ]
        },
        "similarity": 1148.3285074852868
      },
      {
        "metadata": {
          "doc_id": "1284",
          "name": "Improper Validation of Specified Quantity in Input",
          "source": "sparse",
          "original_content": "The product receives input that is expected to specify a quantity (such as size or length), but it does not validate or incorrectly validates that the quantity has the required properties.",
          "keyphrase_sources": [
            {
              "id": "weakness:use-after-free",
              "keyphrase": "use-after-free",
              "type": "weakness"
            },
            {
              "id": "weakness:improper input validation",
              "keyphrase": "improper input validation",
              "type": "weakness"
            },
            {
              "id": "impact:information disclosure",
              "keyphrase": "information disclosure",
              "type": "impact"
            },
            {
              "id": "product:Linux kernel",
              "keyphrase": "Linux kernel",
              "type": "product"
            },
            {
              "id": "component:nilfs2",
              "keyphrase": "nilfs2",
              "type": "component"
            }
          ]
        },
        "similarity": 1133.9563652255301
      },
      {
        "metadata": {
          "doc_id": "125",
          "name": "Out-of-bounds Read",
          "source": "sparse",
          "original_content": "The product reads data past the end, or before the beginning, of the intended buffer.",
          "keyphrase_sources": [
            {
              "id": "weakness:use-after-free",
              "keyphrase": "use-after-free",
              "type": "weakness"
            },
            {
              "id": "weakness:improper input validation",
              "keyphrase": "improper input validation",
              "type": "weakness"
            },
            {
              "id": "impact:information disclosure",
              "keyphrase": "information disclosure",
              "type": "impact"
            },
            {
              "id": "product:Linux kernel",
              "keyphrase": "Linux kernel",
              "type": "product"
            },
            {
              "id": "component:nilfs2",
              "keyphrase": "nilfs2",
              "type": "component"
            }
          ]
        },
        "similarity": 1116.6469655852022
      },
      {
        "metadata": {
          "doc_id": "1335",
          "name": "Incorrect Bitwise Shift of Integer",
          "source": "sparse",
          "original_content": "An integer value is specified to be shifted by a negative amount or an amount greater than or equal to the number of bits contained in the value causing an unexpected or indeterminate result.",
          "keyphrase_sources": [
            {
              "id": "weakness:use-after-free",
              "keyphrase": "use-after-free",
              "type": "weakness"
            },
            {
              "id": "weakness:improper input validation",
              "keyphrase": "improper input validation",
              "type": "weakness"
            },
            {
              "id": "impact:information disclosure",
              "keyphrase": "information disclosure",
              "type": "impact"
            },
            {
              "id": "product:Linux kernel",
              "keyphrase": "Linux kernel",
              "type": "product"
            },
            {
              "id": "component:nilfs2",
              "keyphrase": "nilfs2",
              "type": "component"
            }
          ]
        },
        "similarity": 1087.6527599990764
      }
    ],
    "enhanced_query": "# Vulnerability Description\n\n    In the Linux kernel, the following vulnerability has been resolved nilfs2 fix inode number range checks Patch series nilfs2 fix potential issues related to reserved inodes. This series fixes one **use-after-free** issue reported by syzbot, caused by nilfs2s internal inode being exposed in the namespace on a corrupted filesystem, and a couple of flaws that cause problems if the starting number of non-reserved inodes written in the on-disk super block is intentionally (or corruptly) changed from its default value. This patch (of 3) In the current implementation of nilfs2, nilfs->ns_first_ino, which gives the first non-reserved inode number, is read from the superblock, but its lower limit is not checked. As a result, if a number that overlaps with the inode number range of reserved inodes such as the root directory or metadata files is set in the super block parameter, the inode number test macros (NILFS_MDT_INODE and NILFS_VALID_INODE) will not function properly. In addition, these test macros use left bit-shift calculations using with the inode number as the shift count via the BIT macro, but the result of a shift calculation that exceeds the bit width of an integer is undefined in the C specification, so if ns_first_ino is set to a large value other than the default value NILFS_USER_INO (=11), the macros may potentially malfunction depending on the environment. Fix these issues by checking the lower bound of nilfs->ns_first_ino and by preventing bit shift\n\n    # Keyphrase-Specific CWE Analysis\n    This vulnerability contains multiple keyphrases that may map to different CWEs. \n    Please analyze each keyphrase separately and determine the most appropriate CWE(s) for each.\n\n    ## WEAKNESS: 'use-after-free'\n\nRelevant CWEs for this WEAKNESS:\n\n### 1. CWE-775: Missing Release of File Descriptor or Handle after Effective Lifetime (Score: 1149.54)\n\nThe product does not release a file descriptor or handle after its effective lifetime has ended, i.e., after the file descriptor/handle is no longer needed....\n\n### 2. CWE-190: Integer Overflow or Wraparound (Score: 1148.33)\n\nThe product performs a calculation that can\n         produce an integer overflow or wraparound when the logic\n         assumes that the resulting value will always be larger than\n         the original value. This occurs when an integer value is\n         incremented to a value that is too large to st...\n\n### 3. CWE-1284: Improper Validation of Specified Quantity in Input (Score: 1133.96)\n\nThe product receives input that is expected to specify a quantity (such as size or length), but it does not validate or incorrectly validates that the quantity has the required properties....\n\n### 4. CWE-125: Out-of-bounds Read (Score: 1116.65)\n\nThe product reads data past the end, or before the beginning, of the intended buffer....\n\n### 5. CWE-1335: Incorrect Bitwise Shift of Integer (Score: 1087.65)\n\nAn integer value is specified to be shifted by a negative amount or an amount greater than or equal to the number of bits contained in the value causing an unexpected or indeterminate result....\n\n## WEAKNESS: 'improper input validation'\n\nRelevant CWEs for this WEAKNESS:\n\n### 1. CWE-775: Missing Release of File Descriptor or Handle after Effective Lifetime (Score: 1149.54)\n\nThe product does not release a file descriptor or handle after its effective lifetime has ended, i.e., after the file descriptor/handle is no longer needed....\n\n### 2. CWE-190: Integer Overflow or Wraparound (Score: 1148.33)\n\nThe product performs a calculation that can\n         produce an integer overflow or wraparound when the logic\n         assumes that the resulting value will always be larger than\n         the original value. This occurs when an integer value is\n         incremented to a value that is too large to st...\n\n### 3. CWE-1284: Improper Validation of Specified Quantity in Input (Score: 1133.96)\n\nThe product receives input that is expected to specify a quantity (such as size or length), but it does not validate or incorrectly validates that the quantity has the required properties....\n\n### 4. CWE-125: Out-of-bounds Read (Score: 1116.65)\n\nThe product reads data past the end, or before the beginning, of the intended buffer....\n\n### 5. CWE-1335: Incorrect Bitwise Shift of Integer (Score: 1087.65)\n\nAn integer value is specified to be shifted by a negative amount or an amount greater than or equal to the number of bits contained in the value causing an unexpected or indeterminate result....\n\n## IMPACT: 'information disclosure'\n\nRelevant CWEs for this IMPACT:\n\n### 1. CWE-775: Missing Release of File Descriptor or Handle after Effective Lifetime (Score: 1149.54)\n\nThe product does not release a file descriptor or handle after its effective lifetime has ended, i.e., after the file descriptor/handle is no longer needed....\n\n### 2. CWE-190: Integer Overflow or Wraparound (Score: 1148.33)\n\nThe product performs a calculation that can\n         produce an integer overflow or wraparound when the logic\n         assumes that the resulting value will always be larger than\n         the original value. This occurs when an integer value is\n         incremented to a value that is too large to st...\n\n### 3. CWE-1284: Improper Validation of Specified Quantity in Input (Score: 1133.96)\n\nThe product receives input that is expected to specify a quantity (such as size or length), but it does not validate or incorrectly validates that the quantity has the required properties....\n\n### 4. CWE-125: Out-of-bounds Read (Score: 1116.65)\n\nThe product reads data past the end, or before the beginning, of the intended buffer....\n\n### 5. CWE-1335: Incorrect Bitwise Shift of Integer (Score: 1087.65)\n\nAn integer value is specified to be shifted by a negative amount or an amount greater than or equal to the number of bits contained in the value causing an unexpected or indeterminate result....\n\n## PRODUCT: 'Linux kernel'\n\nRelevant CWEs for this PRODUCT:\n\n### 1. CWE-775: Missing Release of File Descriptor or Handle after Effective Lifetime (Score: 1149.54)\n\nThe product does not release a file descriptor or handle after its effective lifetime has ended, i.e., after the file descriptor/handle is no longer needed....\n\n### 2. CWE-190: Integer Overflow or Wraparound (Score: 1148.33)\n\nThe product performs a calculation that can\n         produce an integer overflow or wraparound when the logic\n         assumes that the resulting value will always be larger than\n         the original value. This occurs when an integer value is\n         incremented to a value that is too large to st...\n\n### 3. CWE-1284: Improper Validation of Specified Quantity in Input (Score: 1133.96)\n\nThe product receives input that is expected to specify a quantity (such as size or length), but it does not validate or incorrectly validates that the quantity has the required properties....\n\n### 4. CWE-125: Out-of-bounds Read (Score: 1116.65)\n\nThe product reads data past the end, or before the beginning, of the intended buffer....\n\n### 5. CWE-1335: Incorrect Bitwise Shift of Integer (Score: 1087.65)\n\nAn integer value is specified to be shifted by a negative amount or an amount greater than or equal to the number of bits contained in the value causing an unexpected or indeterminate result....\n\n## COMPONENT: 'nilfs2'\n\nRelevant CWEs for this COMPONENT:\n\n### 1. CWE-775: Missing Release of File Descriptor or Handle after Effective Lifetime (Score: 1149.54)\n\nThe product does not release a file descriptor or handle after its effective lifetime has ended, i.e., after the file descriptor/handle is no longer needed....\n\n### 2. CWE-190: Integer Overflow or Wraparound (Score: 1148.33)\n\nThe product performs a calculation that can\n         produce an integer overflow or wraparound when the logic\n         assumes that the resulting value will always be larger than\n         the original value. This occurs when an integer value is\n         incremented to a value that is too large to st...\n\n### 3. CWE-1284: Improper Validation of Specified Quantity in Input (Score: 1133.96)\n\nThe product receives input that is expected to specify a quantity (such as size or length), but it does not validate or incorrectly validates that the quantity has the required properties....\n\n### 4. CWE-125: Out-of-bounds Read (Score: 1116.65)\n\nThe product reads data past the end, or before the beginning, of the intended buffer....\n\n### 5. CWE-1335: Incorrect Bitwise Shift of Integer (Score: 1087.65)\n\nAn integer value is specified to be shifted by a negative amount or an amount greater than or equal to the number of bits contained in the value causing an unexpected or indeterminate result....\n\n\n    # Analysis Instructions\n    1. For each keyphrase, identify the most appropriate CWE(s) that represent the weakness.\n    2. Consider how the different keyphrases might relate to each other in the vulnerability chain.\n    3. Provide a final determination of primary CWE(s) and any secondary CWEs.\n    4. Format your response using the standard analysis template.\n\n    Please analyze how these different weaknesses interact and provide a comprehensive CWE classification.\n    "
  },
  "retrieval_time": 1.8651161193847656
}