{
  "cve_id": "CVE-2024-23356",
  "description": "**Memory corruption** during session sign renewal request calls in HLOS.",
  "key_phrases": {
    "rootcause": "",
    "weakness": "Memory corruption",
    "impact": "",
    "vector": "",
    "attacker": "",
    "product": "HLOS",
    "version": "",
    "component": ""
  },
  "reference_content": null,
  "similar_info": {
    "cwe_distribution": {},
    "cwe_consensus": "",
    "similarity_stats": {
      "thresholds": [],
      "total_samples_by_threshold": {},
      "top_cwes_by_threshold": {}
    }
  },
  "similarity_summary": {
    "consensus_cwe": "",
    "top_cwes": [],
    "confidence_levels": {},
    "total_samples": 0
  },
  "analysis": "# Summary\n| CWE ID  | CWE Name                       | Confidence | CWE Abstraction Level | CWE Vulnerability Mapping Label | CWE-Vulnerability Mapping Notes |\n|---------|--------------------------------|------------|-----------------------|---------------------------------|---------------------------------|\n| CWE-787 | Out-of-bounds Write            | 0.9        | Base                  | Primary                         | Allowed                         |\n\n## Evidence and Confidence\n\n*   **Confidence Score:** 0.9\n*   **Evidence Strength:** MEDIUM\n\n## Relationship Analysis\nThe primary relationship considered was the parent-child relationship, particularly how CWE-787 relates to higher-level categories like memory corruption. CWE-787 is a base-level CWE, offering a specific description of the **out-of-bounds write** condition, which aligns with the provided vulnerability description of **memory corruption**. Other CWEs were considered, particularly related to pointer arithmetic and resource management, but lacked the direct relationship to the core issue of writing outside allocated memory regions. The relationships between the other CWEs in the Retriever Results were also examined for chain relationships but did not appear applicable to this vulnerability.\n\n```mermaid\ngraph TD\n    cwe787[\"CWE-787: Out-of-bounds Write\"]\n    cwe119[\"CWE-119: Improper Restriction of Operations\"]\n    \n    cwe787 -->|CHILDOF| cwe119\n    \n    classDef primary fill:#f96,stroke:#333,stroke-width:2px\n    classDef secondary fill:#69f,stroke:#333\n    \n    class cwe787 primary\n    class cwe119 secondary\n```\n\n## Vulnerability Chain\nThe vulnerability chain starts with an unspecified flaw in the HLOS session sign renewal request call that leads to **memory corruption**. The **memory corruption** occurs because of an **out-of-bounds write** (CWE-787). The ultimate impact is potentially arbitrary code execution or denial of service.\n\n## Summary of Analysis\nThe initial analysis focused on the provided vulnerability description, which mentions **memory corruption** during session sign renewal request calls. The key phrase \"memory corruption\" strongly suggests a memory safety issue. The Retriever Results identified CWE-787 (Out-of-bounds Write) as the top candidate, with a score of 1.000.\n\nCWE-787 is a Base level CWE, which is preferred. The description of CWE-787, \"The product writes data past the end, or before the beginning, of the intended buffer,\" directly matches the concept of **memory corruption**.\n\nOther CWEs were considered, such as CWE-823 (Use of Out-of-range Pointer Offset), CWE-908 (Use of Uninitialized Resource), CWE-415 (Double Free), CWE-479 (Signal Handler Use of a Non-reentrant Function), CWE-416 (Use After Free), CWE-681 (Incorrect Conversion between Numeric Types), CWE-476 (NULL Pointer Dereference), CWE-384 (Session Fixation), and CWE-123 (Write-what-where Condition). However, these CWEs are either less directly related to the **memory corruption** issue or represent potential causes or consequences of an **out-of-bounds write**.\n\nThe decision to map to CWE-787 is based on the direct match between the vulnerability description and the CWE description, as well as the high score from the Retriever Results.\n\nRelevant CWE Information:\n\n# Enhanced Context (25 CWEs)\nThe following CWEs were identified as potentially relevant to this vulnerability:\n\n## CWE-131: Incorrect Calculation of Buffer Size\n**Abstraction Level**: Base\n**Similarity Score**: 0.66\n**Source**: dense\n\n**Description**:\nThe product does not correctly calculate the size to be used when allocating a buffer, which could lead to a buffer overflow.\n\n**Mapping Guidance**:\n- Usage: Allowed\n- Rationale: This CWE entry is at the Base level of abstraction, which is a preferred level of abstraction for mapping to the root causes of vulnerabilities.\n\n## CWE-613: Insufficient Session Expiration\n**Abstraction Level**: Base\n**Similarity Score**: 0.66\n**Source**: dense\n\n**Description**:\nAccording to WASC, \"Insufficient Session Expiration is when a web site permits an attacker to reuse old session credentials or session IDs for authorization.\"\n\n**Mapping Guidance**:\n- Usage: Allowed\n- Rationale: This CWE entry is at the Base level of abstraction, which is a preferred level of abstraction for mapping to the root causes of vulnerabilities.\n\n## CWE-823: Use of Out-of-range Pointer Offset\n**Abstraction Level**: Base\n**Similarity Score**: 0.66\n**Source**: dense\n\n**Description**:\nThe product performs pointer arithmetic on a valid pointer, but it uses an offset that can point outside of the intended range of valid memory locations for the resulting pointer.\n\n**Mapping Guidance**:\n- Usage: Allowed\n- Rationale: This CWE entry is at the Base level of abstraction, which is a preferred level of abstraction for mapping to the root causes of vulnerabilities.\n\n## CWE-193: Off-by-one Error\n**Abstraction Level**: Base\n**Similarity Score**: 0.66\n**Source**: dense\n\n**Description**:\nA product calculates or uses an incorrect maximum or minimum value that is 1 more, or 1 less, than the correct value.\n\n**Mapping Guidance**:\n- Usage: Allowed\n- Rationale: This CWE entry is at the Base level of abstraction, which is a preferred level of abstraction for mapping to the root causes of vulnerabilities.\n\n## CWE-824: Access of Uninitialized Pointer\n**Abstraction Level**: Base\n**Similarity Score**: 0.66\n**Source**: dense\n\n**Description**:\nThe product accesses or uses a pointer that has not been initialized.\n\n**Mapping Guidance**:\n- Usage: Allowed\n- Rationale: This CWE entry is at the Base level of abstraction, which is a preferred level of abstraction for mapping to the root causes of vulnerabilities.\n\n## CWE-908: Use of Uninitialized Resource\n**Abstraction Level**: Base\n**Similarity Score**: 0.65\n**Source**: dense\n\n**Description**:\nThe product uses or accesses a resource that has not been initialized.\n\n**Mapping Guidance**:\n- Usage: Allowed\n- Rationale: This CWE entry is at the Base level of abstraction, which is a preferred level of abstraction for mapping to the root causes of vulnerabilities.\n\n## CWE-384: Session Fixation\n**Abstraction Level**: Compound\n**Similarity Score**: 0.65\n**Source**: dense\n\n**Description**:\nAuthenticating a user, or otherwise establishing a new user session, without invalidating any existing session identifier gives an attacker the opportunity to steal authenticated sessions.\n\n**Mapping Guidance**:\n- Usage: Allowed\n- Rationale: This is a well-known Composite of multiple weaknesses that must all occur simultaneously, although it is attack-oriented in nature.\n\n## CWE-130: Improper Handling of Length Parameter Inconsistency\n**Abstraction Level**: Base\n**Similarity Score**: 0.65\n**Source**: dense\n\n**Description**:\nThe product parses a formatted message or structure, but it does not handle or incorrectly handles a length field that is inconsistent with the actual length of the associated data.\n\n**Mapping Guidance**:\n- Usage: Allowed\n- Rationale: This CWE entry is at the Base level of abstraction, which is a preferred level of abstraction for mapping to the root causes of vulnerabilities.\n\n## CWE-226: Sensitive Information in Resource Not Removed Before Reuse\n**Abstraction Level**: Base\n**Similarity Score**: 0.65\n**Source**: dense\n\n**Description**:\nThe product releases a resource such as memory or a file so that it can be made available for reuse, but it does not clear or \"zeroize\" the information contained in the resource before the product performs a critical state transition or makes the resource available for reuse by other entities.\n\n**Mapping Guidance**:\n- Usage: Allowed\n- Rationale: This CWE entry is at the Base level of abstraction, which is a preferred level of abstraction for mapping to the root causes of vulnerabilities.\n\n## CWE-704: Incorrect Type Conversion or Cast\n**Abstraction Level**: Class\n**Similarity Score**: 0.64\n**Source**: dense\n\n**Description**:\nThe product does not correctly convert an object, resource, or structure from one type to a different type.\n\n**Mapping Guidance**:\n- Usage: Allowed-with-Review\n- Rationale: This CWE entry is a Class and might have Base-level children that would be more appropriate\n\n## CWE-823: Use of Out-of-range Pointer Offset\n**Abstraction Level**: Base\n**Similarity Score**: 302.10\n**Source**: sparse\n\n**Description**:\nThe product performs pointer arithmetic on a valid pointer, but it uses an offset that can point outside of the intended range of valid memory locations for the resulting pointer.\n\n**Mapping Guidance**:\n- Usage: Allowed\n- Rationale: This CWE entry is at the Base level of abstraction, which is a preferred level of abstraction for mapping to the root causes of vulnerabilities.\n\n## CWE-415: Double Free\n**Abstraction Level**: Variant\n**Similarity Score**: 301.76\n**Source**: sparse\n\n**Description**:\nThe product calls free() twice on the same memory address, potentially leading to modification of unexpected memory locations",
  "analysis_with_relationships": "# Summary\n| CWE ID  | CWE Name                       | Confidence | CWE Abstraction Level | CWE Vulnerability Mapping Label | CWE-Vulnerability Mapping Notes |\n|---------|--------------------------------|------------|-----------------------|---------------------------------|---------------------------------|\n| CWE-787 | Out-of-bounds Write            | 0.9        | Base                  | Primary                         | Allowed                         |\n\n## Evidence and Confidence\n\n*   **Confidence Score:** 0.9\n*   **Evidence Strength:** MEDIUM\n\n## Relationship Analysis\nThe primary relationship considered was the parent-child relationship, particularly how CWE-787 relates to higher-level categories like memory corruption. CWE-787 is a base-level CWE, offering a specific description of the **out-of-bounds write** condition, which aligns with the provided vulnerability description of **memory corruption**. Other CWEs were considered, particularly related to pointer arithmetic and resource management, but lacked the direct relationship to the core issue of writing outside allocated memory regions. The relationships between the other CWEs in the Retriever Results were also examined for chain relationships but did not appear applicable to this vulnerability.\n\n```mermaid\ngraph TD\n    cwe787[\"CWE-787: Out-of-bounds Write\"]\n    cwe119[\"CWE-119: Improper Restriction of Operations\"]\n    \n    cwe787 -->|CHILDOF| cwe119\n    \n    classDef primary fill:#f96,stroke:#333,stroke-width:2px\n    classDef secondary fill:#69f,stroke:#333\n    \n    class cwe787 primary\n    class cwe119 secondary\n```\n\n## Vulnerability Chain\nThe vulnerability chain starts with an unspecified flaw in the HLOS session sign renewal request call that leads to **memory corruption**. The **memory corruption** occurs because of an **out-of-bounds write** (CWE-787). The ultimate impact is potentially arbitrary code execution or denial of service.\n\n## Summary of Analysis\nThe initial analysis focused on the provided vulnerability description, which mentions **memory corruption** during session sign renewal request calls. The key phrase \"memory corruption\" strongly suggests a memory safety issue. The Retriever Results identified CWE-787 (Out-of-bounds Write) as the top candidate, with a score of 1.000.\n\nCWE-787 is a Base level CWE, which is preferred. The description of CWE-787, \"The product writes data past the end, or before the beginning, of the intended buffer,\" directly matches the concept of **memory corruption**.\n\nOther CWEs were considered, such as CWE-823 (Use of Out-of-range Pointer Offset), CWE-908 (Use of Uninitialized Resource), CWE-415 (Double Free), CWE-479 (Signal Handler Use of a Non-reentrant Function), CWE-416 (Use After Free), CWE-681 (Incorrect Conversion between Numeric Types), CWE-476 (NULL Pointer Dereference), CWE-384 (Session Fixation), and CWE-123 (Write-what-where Condition). However, these CWEs are either less directly related to the **memory corruption** issue or represent potential causes or consequences of an **out-of-bounds write**.\n\nThe decision to map to CWE-787 is based on the direct match between the vulnerability description and the CWE description, as well as the high score from the Retriever Results.\n\nRelevant CWE Information:\n\n# Enhanced Context (25 CWEs)\nThe following CWEs were identified as potentially relevant to this vulnerability:\n\n## CWE-131: Incorrect Calculation of Buffer Size\n**Abstraction Level**: Base\n**Similarity Score**: 0.66\n**Source**: dense\n\n**Description**:\nThe product does not correctly calculate the size to be used when allocating a buffer, which could lead to a buffer overflow.\n\n**Mapping Guidance**:\n- Usage: Allowed\n- Rationale: This CWE entry is at the Base level of abstraction, which is a preferred level of abstraction for mapping to the root causes of vulnerabilities.\n\n## CWE-613: Insufficient Session Expiration\n**Abstraction Level**: Base\n**Similarity Score**: 0.66\n**Source**: dense\n\n**Description**:\nAccording to WASC, \"Insufficient Session Expiration is when a web site permits an attacker to reuse old session credentials or session IDs for authorization.\"\n\n**Mapping Guidance**:\n- Usage: Allowed\n- Rationale: This CWE entry is at the Base level of abstraction, which is a preferred level of abstraction for mapping to the root causes of vulnerabilities.\n\n## CWE-823: Use of Out-of-range Pointer Offset\n**Abstraction Level**: Base\n**Similarity Score**: 0.66\n**Source**: dense\n\n**Description**:\nThe product performs pointer arithmetic on a valid pointer, but it uses an offset that can point outside of the intended range of valid memory locations for the resulting pointer.\n\n**Mapping Guidance**:\n- Usage: Allowed\n- Rationale: This CWE entry is at the Base level of abstraction, which is a preferred level of abstraction for mapping to the root causes of vulnerabilities.\n\n## CWE-193: Off-by-one Error\n**Abstraction Level**: Base\n**Similarity Score**: 0.66\n**Source**: dense\n\n**Description**:\nA product calculates or uses an incorrect maximum or minimum value that is 1 more, or 1 less, than the correct value.\n\n**Mapping Guidance**:\n- Usage: Allowed\n- Rationale: This CWE entry is at the Base level of abstraction, which is a preferred level of abstraction for mapping to the root causes of vulnerabilities.\n\n## CWE-824: Access of Uninitialized Pointer\n**Abstraction Level**: Base\n**Similarity Score**: 0.66\n**Source**: dense\n\n**Description**:\nThe product accesses or uses a pointer that has not been initialized.\n\n**Mapping Guidance**:\n- Usage: Allowed\n- Rationale: This CWE entry is at the Base level of abstraction, which is a preferred level of abstraction for mapping to the root causes of vulnerabilities.\n\n## CWE-908: Use of Uninitialized Resource\n**Abstraction Level**: Base\n**Similarity Score**: 0.65\n**Source**: dense\n\n**Description**:\nThe product uses or accesses a resource that has not been initialized.\n\n**Mapping Guidance**:\n- Usage: Allowed\n- Rationale: This CWE entry is at the Base level of abstraction, which is a preferred level of abstraction for mapping to the root causes of vulnerabilities.\n\n## CWE-384: Session Fixation\n**Abstraction Level**: Compound\n**Similarity Score**: 0.65\n**Source**: dense\n\n**Description**:\nAuthenticating a user, or otherwise establishing a new user session, without invalidating any existing session identifier gives an attacker the opportunity to steal authenticated sessions.\n\n**Mapping Guidance**:\n- Usage: Allowed\n- Rationale: This is a well-known Composite of multiple weaknesses that must all occur simultaneously, although it is attack-oriented in nature.\n\n## CWE-130: Improper Handling of Length Parameter Inconsistency\n**Abstraction Level**: Base\n**Similarity Score**: 0.65\n**Source**: dense\n\n**Description**:\nThe product parses a formatted message or structure, but it does not handle or incorrectly handles a length field that is inconsistent with the actual length of the associated data.\n\n**Mapping Guidance**:\n- Usage: Allowed\n- Rationale: This CWE entry is at the Base level of abstraction, which is a preferred level of abstraction for mapping to the root causes of vulnerabilities.\n\n## CWE-226: Sensitive Information in Resource Not Removed Before Reuse\n**Abstraction Level**: Base\n**Similarity Score**: 0.65\n**Source**: dense\n\n**Description**:\nThe product releases a resource such as memory or a file so that it can be made available for reuse, but it does not clear or \"zeroize\" the information contained in the resource before the product performs a critical state transition or makes the resource available for reuse by other entities.\n\n**Mapping Guidance**:\n- Usage: Allowed\n- Rationale: This CWE entry is at the Base level of abstraction, which is a preferred level of abstraction for mapping to the root causes of vulnerabilities.\n\n## CWE-704: Incorrect Type Conversion or Cast\n**Abstraction Level**: Class\n**Similarity Score**: 0.64\n**Source**: dense\n\n**Description**:\nThe product does not correctly convert an object, resource, or structure from one type to a different type.\n\n**Mapping Guidance**:\n- Usage: Allowed-with-Review\n- Rationale: This CWE entry is a Class and might have Base-level children that would be more appropriate\n\n## CWE-823: Use of Out-of-range Pointer Offset\n**Abstraction Level**: Base\n**Similarity Score**: 302.10\n**Source**: sparse\n\n**Description**:\nThe product performs pointer arithmetic on a valid pointer, but it uses an offset that can point outside of the intended range of valid memory locations for the resulting pointer.\n\n**Mapping Guidance**:\n- Usage: Allowed\n- Rationale: This CWE entry is at the Base level of abstraction, which is a preferred level of abstraction for mapping to the root causes of vulnerabilities.\n\n## CWE-415: Double Free\n**Abstraction Level**: Variant\n**Similarity Score**: 301.76\n**Source**: sparse\n\n**Description**:\nThe product calls free() twice on the same memory address, potentially leading to modification of unexpected memory locations\n\n\n## CWE Relationship Analysis\n\nCurrent CWEs represent these abstraction levels: .\n\n\n### Vulnerability Chain Analysis\n\n**Chain starting from CWE-123:**\n- 123 (Write-what-where Condition) - ROOT\n\n\n**Chain starting from CWE-479:**\n- 479 (Signal Handler Use of a Non-reentrant Function) - ROOT\n\n\n\n### CWE Relationship Diagram\n\n```mermaid\ngraph TD\n    classDef primary fill:#f96,stroke:#333,stroke-width:2px\n    classDef secondary fill:#69f,stroke:#333\n    classDef tertiary fill:#9e9,stroke:#333\n```",
  "criticism": "",
  "resolution": "",
  "relevant_cwes": [
    {
      "metadata": {
        "doc_id": "787",
        "name": "Out-of-bounds Write",
        "source": "alternate_terms",
        "original_matched_text": "AlternateTerms: Memory Corruption",
        "match_reason": "exact_match_whole_phrase"
      },
      "similarity": 1000.0,
      "alternate_term_match": true
    },
    {
      "metadata": {
        "doc_id": "823",
        "name": "Use of Out-of-range Pointer Offset",
        "source": "sparse"
      },
      "similarity": 76.80614373585975
    },
    {
      "metadata": {
        "doc_id": "908",
        "name": "Use of Uninitialized Resource",
        "source": "sparse"
      },
      "similarity": 73.02252657793686
    },
    {
      "metadata": {
        "doc_id": "415",
        "name": "Double Free",
        "source": "sparse"
      },
      "similarity": 69.53653056571851
    },
    {
      "metadata": {
        "doc_id": "479",
        "name": "Signal Handler Use of a Non-reentrant Function",
        "source": "sparse"
      },
      "similarity": 66.04671416383675
    },
    {
      "metadata": {
        "doc_id": "416",
        "name": "Use After Free",
        "source": "sparse"
      },
      "similarity": 65.35477832625293
    },
    {
      "metadata": {
        "doc_id": "681",
        "name": "Incorrect Conversion between Numeric Types",
        "source": "sparse"
      },
      "similarity": 62.834198953910445
    },
    {
      "metadata": {
        "doc_id": "476",
        "name": "NULL Pointer Dereference",
        "source": "sparse"
      },
      "similarity": 62.54052146010703
    },
    {
      "metadata": {
        "doc_id": "384",
        "name": "Session Fixation",
        "type": "Compound",
        "original_content": "Authenticating a user, or otherwise establishing a new user session, without invalidating any existing session identifier gives an attacker the opportunity to steal authenticated sessions.",
        "keyphrase_source": "weakness:Memory corruption",
        "source": "dense",
        "mapping_notes": {
          "usage": "Allowed",
          "rationale": "This is a well-known Composite of multiple weaknesses that must all occur simultaneously, although it is attack-oriented in nature.",
          "comments": "While attack-oriented composites are supported in CWE, they have not been a focus of research. There is a chance that future research or CWE scope clarifications will change or deprecate them. Perform root-cause analysis to determine which weaknesses allow session fixation to occur, and map to those weaknesses. For example, predictable session identifiers might enable session fixation attacks to succeed; if this occurs, they might be better characterized as randomness/predictability weaknesses.",
          "reasons": [
            "Other"
          ]
        },
        "score_info": {
          "retrievers": [
            "dense"
          ],
          "retriever_count": 1,
          "normalized_scores": {
            "dense": 0.4840158915590457
          }
        }
      },
      "similarity": 0.4840158915590457
    },
    {
      "doc_id": "123",
      "text": "CWE-123: Write-what-where Condition",
      "score": 3.5671999999999997,
      "metadata": {
        "doc_id": "123",
        "name": "Write-what-where Condition",
        "type": "base",
        "original_content": "CWE-123: Write-what-where Condition",
        "relationships": [
          {
            "source_id": "123",
            "target_id": "590",
            "label": "CANFOLLOW",
            "properties": {
              "view_id": "1000"
            }
          },
          {
            "source_id": "123",
            "target_id": "479",
            "label": "CANFOLLOW",
            "properties": {
              "view_id": "1000"
            }
          },
          {
            "source_id": "123",
            "target_id": "416",
            "label": "CANFOLLOW",
            "properties": {
              "view_id": "1000"
            }
          },
          {
            "source_id": "123",
            "target_id": "364",
            "label": "CANFOLLOW",
            "properties": {
              "view_id": "1000"
            }
          },
          {
            "source_id": "123",
            "target_id": "134",
            "label": "CANFOLLOW",
            "properties": {
              "view_id": "1000"
            }
          },
          {
            "source_id": "123",
            "target_id": "120",
            "label": "CANFOLLOW",
            "properties": {
              "view_id": "1000"
            }
          },
          {
            "source_id": "123",
            "target_id": "119",
            "label": "CHILDOF",
            "properties": {
              "ordinal": "Primary",
              "view_id": "1340"
            }
          },
          {
            "source_id": "123",
            "target_id": "119",
            "label": "CHILDOF",
            "properties": {
              "ordinal": "Primary",
              "view_id": "1305"
            }
          },
          {
            "source_id": "123",
            "target_id": "787",
            "label": "CHILDOF",
            "properties": {
              "ordinal": "Primary",
              "view_id": "1000"
            }
          },
          {
            "source_id": "787",
            "target_id": "123",
            "label": "PARENTOF",
            "properties": {
              "ordinal": "Primary",
              "view_id": "1000"
            }
          },
          {
            "source_id": "590",
            "target_id": "123",
            "label": "CANPRECEDE",
            "properties": {
              "view_id": "1000"
            }
          },
          {
            "source_id": "479",
            "target_id": "123",
            "label": "CANPRECEDE",
            "properties": {
              "view_id": "1000"
            }
          },
          {
            "source_id": "416",
            "target_id": "123",
            "label": "CANPRECEDE",
            "properties": {
              "view_id": "1000"
            }
          },
          {
            "source_id": "415",
            "target_id": "123",
            "label": "PEEROF",
            "properties": {
              "view_id": "1000"
            }
          },
          {
            "source_id": "364",
            "target_id": "123",
            "label": "CANPRECEDE",
            "properties": {
              "view_id": "1000"
            }
          },
          {
            "source_id": "134",
            "target_id": "123",
            "label": "CANPRECEDE",
            "properties": {
              "view_id": "1000"
            }
          },
          {
            "source_id": "120",
            "target_id": "123",
            "label": "CANPRECEDE",
            "properties": {
              "view_id": "1000"
            }
          },
          {
            "source_id": "119",
            "target_id": "123",
            "label": "PARENTOF",
            "properties": {
              "ordinal": "Primary",
              "view_id": "1305"
            }
          }
        ],
        "score_components": {
          "relationship_chain": 1.0,
          "abstraction_path": 0.7200000000000001,
          "sequence_path": 1.0,
          "peer_group": 0.9
        },
        "abstraction_factor": 1.3,
        "graph_path_info": {
          "path_types": [
            "relationship_chain",
            "abstraction_path_down",
            "vulnerability_sequence_forward",
            "peer_relationship"
          ],
          "best_paths": {
            "relationship_chain": {
              "path": [
                [
                  "479",
                  "123",
                  "CANPRECEDE"
                ]
              ],
              "score": 1.0,
              "type": "relationship_chain",
              "source": "479"
            },
            "abstraction_path_down": {
              "path": [
                [
                  "787",
                  "123",
                  "PARENTOF"
                ]
              ],
              "score": 0.7200000000000001,
              "type": "abstraction_path_down",
              "source": "787"
            },
            "vulnerability_sequence_forward": {
              "path": [
                [
                  "479",
                  "123",
                  "CANPRECEDE"
                ]
              ],
              "score": 1.0,
              "type": "vulnerability_sequence_forward",
              "source": "479"
            },
            "peer_relationship": {
              "path": [
                [
                  "415",
                  "123",
                  "PEEROF"
                ]
              ],
              "score": 0.9,
              "type": "peer_relationship",
              "source": "415"
            }
          }
        },
        "abstraction_level": "base",
        "position": "after",
        "sources": [
          "graph"
        ],
        "source": "graph",
        "mapping_notes": {
          "usage": "Allowed",
          "rationale": "This CWE entry is at the Base level of abstraction, which is a preferred level of abstraction for mapping to the root causes of vulnerabilities.",
          "comments": "Carefully read both the name and description to ensure that this mapping is an appropriate fit. Do not try to 'force' a mapping to a lower-level Base/Variant simply to comply with this preferred level of abstraction.",
          "reasons": [
            "Acceptable-Use"
          ]
        },
        "score_info": {
          "retrievers": [
            "graph"
          ],
          "retriever_count": 1,
          "normalized_scores": {
            "graph": 3.5671999999999997
          }
        }
      },
      "similarity": 3.5671999999999997
    }
  ],
  "identified_cwes": {
    "analyzer": [
      "CWE-123",
      "CWE-479",
      "CWE-416",
      "CWE-823",
      "CWE-476",
      "CWE-681",
      "CWE-130",
      "CWE-226",
      "CWE-131",
      "CWE-787",
      "CWE-704",
      "CWE-613",
      "CWE-193",
      "CWE-824",
      "CWE-119",
      "CWE-384",
      "CWE-415",
      "CWE-908"
    ],
    "critic_additional": []
  },
  "keyphrase_cwe_mapping": {}
}