{
  "vulnerability_info": "VulnerabilityInfo(cve_id='CVE-2024-3636', description='The Pinpoint Booking System WordPress plugin before 2.9.9.4.8 **does not sanitise and escape some of its settings**, which could allow high privilege users such as admin to perform Stored Cross-Site Scripting attacks even when the unfiltered_html capability is disallowed (for example in multisite setup)', key_phrases={'rootcause': ['does not sanitise and escape some of its settings', 'lack of input sanitization and escaping'], 'weakness': 'cross-site scripting', 'impact': 'Stored Cross-Site Scripting attacks', 'vector': '', 'attacker': 'high privilege users', 'product': 'Pinpoint Booking System WordPress plugin', 'version': 'before 2.9.9.4.8', 'component': ''}, reference_content='```\\n{\\n  \"vulnerability_details\": {\\n    \"root_cause\": \"The plugin does not sanitize and escape some of its settings.\",\\n    \"weaknesses\": [\\n      \"Stored Cross-Site Scripting (XSS)\"\\n    ],\\n    \"impact\": \"Allows high privilege users such as admin to perform Stored Cross-Site Scripting attacks, even when the unfiltered_html capability is disallowed.\",\\n    \"attack_vectors\": [\\n      \"By adding a malicious script within the \\'Name\\' field of an email template in the plugin settings page, or within SMS Templates.\"\\n    ],\\n    \"attacker_capabilities\": \"An attacker requires administrative privileges within the WordPress instance to access the plugin settings page and inject the malicious script.\"\\n  },\\n  \"affected_versions\": {\\n    \"version\": \"< 2.9.9.4.8\",\\n    \"fixed_version\": \"2.9.9.4.8\"\\n  }\\n}\\n```', similar_info={'cwe_distribution': {95: {'cwe_counts': defaultdict(<class 'int'>, {'CWE-79': 1}), 'total_samples': 1, 'distribution': [{'cwes': ['CWE-79'], 'frequency': 1, 'proportion': 1.0}]}, 90: {'cwe_counts': defaultdict(<class 'int'>, {'CWE-79': 6}), 'total_samples': 15, 'distribution': [{'cwes': [], 'frequency': 9, 'proportion': 0.6}, {'cwes': ['CWE-79'], 'frequency': 6, 'proportion': 0.4}]}, 85: {'cwe_counts': defaultdict(<class 'int'>, {'CWE-79': 5}), 'total_samples': 19, 'distribution': [{'cwes': [], 'frequency': 14, 'proportion': 0.737}, {'cwes': ['CWE-79'], 'frequency': 5, 'proportion': 0.263}]}, 80: {'cwe_counts': defaultdict(<class 'int'>, {'CWE-79': 8}), 'total_samples': 27, 'distribution': [{'cwes': [], 'frequency': 19, 'proportion': 0.704}, {'cwes': ['CWE-79'], 'frequency': 8, 'proportion': 0.296}]}, 75: {'cwe_counts': defaultdict(<class 'int'>, {'CWE-79': 5}), 'total_samples': 12, 'distribution': [{'cwes': [], 'frequency': 7, 'proportion': 0.583}, {'cwes': ['CWE-79'], 'frequency': 5, 'proportion': 0.417}]}, 70: {'cwe_counts': defaultdict(<class 'int'>, {'CWE-79': 6}), 'total_samples': 15, 'distribution': [{'cwes': [], 'frequency': 9, 'proportion': 0.6}, {'cwes': ['CWE-79'], 'frequency': 6, 'proportion': 0.4}]}}, 'cwe_consensus': 'CWE-79', 'similarity_stats': {'thresholds': [95, 90, 85, 80, 75, 70], 'total_samples_by_threshold': {95: 1, 90: 15, 85: 19, 80: 27, 75: 12, 70: 15}, 'top_cwes_by_threshold': {95: [('CWE-79', 1)], 90: [('CWE-79', 6)], 85: [('CWE-79', 5)], 80: [('CWE-79', 8)], 75: [('CWE-79', 5)], 70: [('CWE-79', 6)]}}, 'raw_matches': [{'similarity': 95, 'cwes': ['79'], 'total': 1, 'frequency': 1, 'proportion': 1.0}, {'similarity': 90, 'cwes': [], 'total': 15, 'frequency': 9, 'proportion': 0.6}, {'similarity': 90, 'cwes': ['79'], 'total': 15, 'frequency': 6, 'proportion': 0.4}, {'similarity': 85, 'cwes': [], 'total': 19, 'frequency': 14, 'proportion': 0.737}, {'similarity': 85, 'cwes': ['79'], 'total': 19, 'frequency': 5, 'proportion': 0.263}, {'similarity': 80, 'cwes': [], 'total': 27, 'frequency': 19, 'proportion': 0.704}, {'similarity': 80, 'cwes': ['79'], 'total': 27, 'frequency': 8, 'proportion': 0.296}, {'similarity': 75, 'cwes': [], 'total': 12, 'frequency': 7, 'proportion': 0.583}, {'similarity': 75, 'cwes': ['79'], 'total': 12, 'frequency': 5, 'proportion': 0.417}, {'similarity': 70, 'cwes': [], 'total': 15, 'frequency': 9, 'proportion': 0.6}, {'similarity': 70, 'cwes': ['79'], 'total': 15, 'frequency': 6, 'proportion': 0.4}]}, similarity_summary=SimilarityInsight(consensus_cwe='CWE-79', top_cwes=[('CWE-79', 31)], confidence_levels={'high': [], 'medium': [], 'low': []}, total_samples=89), analysis='', analysis_with_relationships='', criticism='', resolution='', relevant_cwes=[{'metadata': {'doc_id': '352', 'name': 'Cross-Site Request Forgery (CSRF)', 'source': 'sparse', 'original_content': 'The web application does not, or can not, sufficiently verify whether a well-formed, valid, consistent request was intentionally provided by the user who submitted the request.', 'keyphrase_sources': [{'id': 'rootcause:does not sanitise and escape some of its settings', 'keyphrase': 'does not sanitise and escape some of its settings', 'type': 'rootcause'}, {'id': 'rootcause:lack of input sanitization and escaping', 'keyphrase': 'lack of input sanitization and escaping', 'type': 'rootcause'}, {'id': 'weakness:cross-site scripting', 'keyphrase': 'cross-site scripting', 'type': 'weakness'}, {'id': 'impact:Stored Cross-Site Scripting attacks', 'keyphrase': 'Stored Cross-Site Scripting attacks', 'type': 'impact'}, {'id': 'attacker:high privilege users', 'keyphrase': 'high privilege users', 'type': 'attacker'}, {'id': 'product:Pinpoint Booking System WordPress plugin', 'keyphrase': 'Pinpoint Booking System WordPress plugin', 'type': 'product'}, {'id': 'version:before 2.9.9.4.8', 'keyphrase': 'before 2.9.9.4.8', 'type': 'version'}]}, 'similarity': np.float64(576.7084206562257)}, {'metadata': {'doc_id': '116', 'name': 'Improper Encoding or Escaping of Output', 'source': 'sparse', 'original_content': 'The product prepares a structured message for communication with another component, but encoding or escaping of the data is either missing or done incorrectly. As a result, the intended structure of the message is not preserved.', 'keyphrase_sources': [{'id': 'rootcause:does not sanitise and escape some of its settings', 'keyphrase': 'does not sanitise and escape some of its settings', 'type': 'rootcause'}, {'id': 'rootcause:lack of input sanitization and escaping', 'keyphrase': 'lack of input sanitization and escaping', 'type': 'rootcause'}, {'id': 'weakness:cross-site scripting', 'keyphrase': 'cross-site scripting', 'type': 'weakness'}, {'id': 'impact:Stored Cross-Site Scripting attacks', 'keyphrase': 'Stored Cross-Site Scripting attacks', 'type': 'impact'}, {'id': 'attacker:high privilege users', 'keyphrase': 'high privilege users', 'type': 'attacker'}, {'id': 'product:Pinpoint Booking System WordPress plugin', 'keyphrase': 'Pinpoint Booking System WordPress plugin', 'type': 'product'}, {'id': 'version:before 2.9.9.4.8', 'keyphrase': 'before 2.9.9.4.8', 'type': 'version'}]}, 'similarity': np.float64(474.7287288048298)}, {'metadata': {'doc_id': '862', 'name': 'Missing Authorization', 'source': 'sparse', 'original_content': 'The product does not perform an authorization check when an actor attempts to access a resource or perform an action.', 'keyphrase_sources': [{'id': 'rootcause:does not sanitise and escape some of its settings', 'keyphrase': 'does not sanitise and escape some of its settings', 'type': 'rootcause'}, {'id': 'rootcause:lack of input sanitization and escaping', 'keyphrase': 'lack of input sanitization and escaping', 'type': 'rootcause'}, {'id': 'impact:Stored Cross-Site Scripting attacks', 'keyphrase': 'Stored Cross-Site Scripting attacks', 'type': 'impact'}, {'id': 'attacker:high privilege users', 'keyphrase': 'high privilege users', 'type': 'attacker'}, {'id': 'product:Pinpoint Booking System WordPress plugin', 'keyphrase': 'Pinpoint Booking System WordPress plugin', 'type': 'product'}, {'id': 'version:before 2.9.9.4.8', 'keyphrase': 'before 2.9.9.4.8', 'type': 'version'}]}, 'similarity': np.float64(416.36431471578516)}, {'metadata': {'doc_id': '89', 'name': \"Improper Neutralization of Special Elements used in an SQL Command ('SQL Injection')\", 'source': 'sparse', 'original_content': 'The product constructs all or part of an SQL command using externally-influenced input from an upstream component, but it does not neutralize or incorrectly neutralizes special elements that could modify the intended SQL command when it is sent to a downstream component. Without sufficient removal or quoting of SQL syntax in user-controllable inputs, the generated SQL query can cause those inputs to be interpreted as SQL instead of ordinary user data.', 'keyphrase_sources': [{'id': 'rootcause:does not sanitise and escape some of its settings', 'keyphrase': 'does not sanitise and escape some of its settings', 'type': 'rootcause'}, {'id': 'weakness:cross-site scripting', 'keyphrase': 'cross-site scripting', 'type': 'weakness'}, {'id': 'attacker:high privilege users', 'keyphrase': 'high privilege users', 'type': 'attacker'}, {'id': 'product:Pinpoint Booking System WordPress plugin', 'keyphrase': 'Pinpoint Booking System WordPress plugin', 'type': 'product'}]}, 'similarity': np.float64(399.1205267970783)}, {'metadata': {'doc_id': '138', 'name': 'Improper Neutralization of Special Elements', 'source': 'sparse', 'original_content': 'The product receives input from an upstream component, but it does not neutralize or incorrectly neutralizes special elements that could be interpreted as control elements or syntactic markers when they are sent to a downstream component.', 'keyphrase_sources': [{'id': 'rootcause:lack of input sanitization and escaping', 'keyphrase': 'lack of input sanitization and escaping', 'type': 'rootcause'}]}, 'similarity': np.float64(385.1134369156416)}, {'metadata': {'doc_id': '79', 'name': \"Improper Neutralization of Input During Web Page Generation ('Cross-site Scripting')\", 'source': 'sparse', 'original_content': 'The product does not neutralize or incorrectly neutralizes user-controllable input before it is placed in output that is used as a web page that is served to other users.', 'keyphrase_sources': [{'id': 'rootcause:does not sanitise and escape some of its settings', 'keyphrase': 'does not sanitise and escape some of its settings', 'type': 'rootcause'}, {'id': 'weakness:cross-site scripting', 'keyphrase': 'cross-site scripting', 'type': 'weakness'}, {'id': 'impact:Stored Cross-Site Scripting attacks', 'keyphrase': 'Stored Cross-Site Scripting attacks', 'type': 'impact'}, {'id': 'version:before 2.9.9.4.8', 'keyphrase': 'before 2.9.9.4.8', 'type': 'version'}]}, 'similarity': np.float64(373.947239539591)}, {'metadata': {'doc_id': '434', 'name': 'Unrestricted Upload of File with Dangerous Type', 'source': 'sparse', 'original_content': 'The product allows the upload or transfer of dangerous file types that are automatically processed within its environment.', 'keyphrase_sources': [{'id': 'rootcause:lack of input sanitization and escaping', 'keyphrase': 'lack of input sanitization and escaping', 'type': 'rootcause'}, {'id': 'weakness:cross-site scripting', 'keyphrase': 'cross-site scripting', 'type': 'weakness'}, {'id': 'impact:Stored Cross-Site Scripting attacks', 'keyphrase': 'Stored Cross-Site Scripting attacks', 'type': 'impact'}, {'id': 'attacker:high privilege users', 'keyphrase': 'high privilege users', 'type': 'attacker'}, {'id': 'product:Pinpoint Booking System WordPress plugin', 'keyphrase': 'Pinpoint Booking System WordPress plugin', 'type': 'product'}, {'id': 'version:before 2.9.9.4.8', 'keyphrase': 'before 2.9.9.4.8', 'type': 'version'}]}, 'similarity': np.float64(359.46013606603907)}], identified_cwes={'analyzer': [], 'critic_additional': []})",
  "retrieval_results": {
    "has_multiple_keyphrases": true,
    "keyphrase_cwe_sets": {
      "rootcause:does not sanitise and escape some of its settings": {
        "keyphrase": "does not sanitise and escape some of its settings",
        "type": "rootcause",
        "cwes": [
          {
            "metadata": {
              "doc_id": "352",
              "name": "Cross-Site Request Forgery (CSRF)",
              "source": "sparse",
              "original_content": "The web application does not, or can not, sufficiently verify whether a well-formed, valid, consistent request was intentionally provided by the user who submitted the request.",
              "keyphrase_sources": [
                {
                  "id": "rootcause:does not sanitise and escape some of its settings",
                  "keyphrase": "does not sanitise and escape some of its settings",
                  "type": "rootcause"
                },
                {
                  "id": "rootcause:lack of input sanitization and escaping",
                  "keyphrase": "lack of input sanitization and escaping",
                  "type": "rootcause"
                },
                {
                  "id": "weakness:cross-site scripting",
                  "keyphrase": "cross-site scripting",
                  "type": "weakness"
                },
                {
                  "id": "impact:Stored Cross-Site Scripting attacks",
                  "keyphrase": "Stored Cross-Site Scripting attacks",
                  "type": "impact"
                },
                {
                  "id": "attacker:high privilege users",
                  "keyphrase": "high privilege users",
                  "type": "attacker"
                },
                {
                  "id": "product:Pinpoint Booking System WordPress plugin",
                  "keyphrase": "Pinpoint Booking System WordPress plugin",
                  "type": "product"
                },
                {
                  "id": "version:before 2.9.9.4.8",
                  "keyphrase": "before 2.9.9.4.8",
                  "type": "version"
                }
              ]
            },
            "similarity": 576.7084206562257
          },
          {
            "metadata": {
              "doc_id": "116",
              "name": "Improper Encoding or Escaping of Output",
              "source": "sparse",
              "original_content": "The product prepares a structured message for communication with another component, but encoding or escaping of the data is either missing or done incorrectly. As a result, the intended structure of the message is not preserved.",
              "keyphrase_sources": [
                {
                  "id": "rootcause:does not sanitise and escape some of its settings",
                  "keyphrase": "does not sanitise and escape some of its settings",
                  "type": "rootcause"
                },
                {
                  "id": "rootcause:lack of input sanitization and escaping",
                  "keyphrase": "lack of input sanitization and escaping",
                  "type": "rootcause"
                },
                {
                  "id": "weakness:cross-site scripting",
                  "keyphrase": "cross-site scripting",
                  "type": "weakness"
                },
                {
                  "id": "impact:Stored Cross-Site Scripting attacks",
                  "keyphrase": "Stored Cross-Site Scripting attacks",
                  "type": "impact"
                },
                {
                  "id": "attacker:high privilege users",
                  "keyphrase": "high privilege users",
                  "type": "attacker"
                },
                {
                  "id": "product:Pinpoint Booking System WordPress plugin",
                  "keyphrase": "Pinpoint Booking System WordPress plugin",
                  "type": "product"
                },
                {
                  "id": "version:before 2.9.9.4.8",
                  "keyphrase": "before 2.9.9.4.8",
                  "type": "version"
                }
              ]
            },
            "similarity": 474.7287288048298
          },
          {
            "metadata": {
              "doc_id": "862",
              "name": "Missing Authorization",
              "source": "sparse",
              "original_content": "The product does not perform an authorization check when an actor attempts to access a resource or perform an action.",
              "keyphrase_sources": [
                {
                  "id": "rootcause:does not sanitise and escape some of its settings",
                  "keyphrase": "does not sanitise and escape some of its settings",
                  "type": "rootcause"
                },
                {
                  "id": "rootcause:lack of input sanitization and escaping",
                  "keyphrase": "lack of input sanitization and escaping",
                  "type": "rootcause"
                },
                {
                  "id": "impact:Stored Cross-Site Scripting attacks",
                  "keyphrase": "Stored Cross-Site Scripting attacks",
                  "type": "impact"
                },
                {
                  "id": "attacker:high privilege users",
                  "keyphrase": "high privilege users",
                  "type": "attacker"
                },
                {
                  "id": "product:Pinpoint Booking System WordPress plugin",
                  "keyphrase": "Pinpoint Booking System WordPress plugin",
                  "type": "product"
                },
                {
                  "id": "version:before 2.9.9.4.8",
                  "keyphrase": "before 2.9.9.4.8",
                  "type": "version"
                }
              ]
            },
            "similarity": 416.36431471578516
          },
          {
            "metadata": {
              "doc_id": "89",
              "name": "Improper Neutralization of Special Elements used in an SQL Command ('SQL Injection')",
              "source": "sparse",
              "original_content": "The product constructs all or part of an SQL command using externally-influenced input from an upstream component, but it does not neutralize or incorrectly neutralizes special elements that could modify the intended SQL command when it is sent to a downstream component. Without sufficient removal or quoting of SQL syntax in user-controllable inputs, the generated SQL query can cause those inputs to be interpreted as SQL instead of ordinary user data.",
              "keyphrase_sources": [
                {
                  "id": "rootcause:does not sanitise and escape some of its settings",
                  "keyphrase": "does not sanitise and escape some of its settings",
                  "type": "rootcause"
                },
                {
                  "id": "weakness:cross-site scripting",
                  "keyphrase": "cross-site scripting",
                  "type": "weakness"
                },
                {
                  "id": "attacker:high privilege users",
                  "keyphrase": "high privilege users",
                  "type": "attacker"
                },
                {
                  "id": "product:Pinpoint Booking System WordPress plugin",
                  "keyphrase": "Pinpoint Booking System WordPress plugin",
                  "type": "product"
                }
              ]
            },
            "similarity": 399.1205267970783
          },
          {
            "metadata": {
              "doc_id": "79",
              "name": "Improper Neutralization of Input During Web Page Generation ('Cross-site Scripting')",
              "source": "sparse",
              "original_content": "The product does not neutralize or incorrectly neutralizes user-controllable input before it is placed in output that is used as a web page that is served to other users.",
              "keyphrase_sources": [
                {
                  "id": "rootcause:does not sanitise and escape some of its settings",
                  "keyphrase": "does not sanitise and escape some of its settings",
                  "type": "rootcause"
                },
                {
                  "id": "weakness:cross-site scripting",
                  "keyphrase": "cross-site scripting",
                  "type": "weakness"
                },
                {
                  "id": "impact:Stored Cross-Site Scripting attacks",
                  "keyphrase": "Stored Cross-Site Scripting attacks",
                  "type": "impact"
                },
                {
                  "id": "version:before 2.9.9.4.8",
                  "keyphrase": "before 2.9.9.4.8",
                  "type": "version"
                }
              ]
            },
            "similarity": 373.947239539591
          }
        ]
      },
      "rootcause:lack of input sanitization and escaping": {
        "keyphrase": "lack of input sanitization and escaping",
        "type": "rootcause",
        "cwes": [
          {
            "metadata": {
              "doc_id": "352",
              "name": "Cross-Site Request Forgery (CSRF)",
              "source": "sparse",
              "original_content": "The web application does not, or can not, sufficiently verify whether a well-formed, valid, consistent request was intentionally provided by the user who submitted the request."
            },
            "similarity": 496.1896465666205
          },
          {
            "metadata": {
              "doc_id": "116",
              "name": "Improper Encoding or Escaping of Output",
              "source": "sparse",
              "original_content": "The product prepares a structured message for communication with another component, but encoding or escaping of the data is either missing or done incorrectly. As a result, the intended structure of the message is not preserved."
            },
            "similarity": 447.8250053585857
          },
          {
            "metadata": {
              "doc_id": "138",
              "name": "Improper Neutralization of Special Elements",
              "source": "sparse",
              "original_content": "The product receives input from an upstream component, but it does not neutralize or incorrectly neutralizes special elements that could be interpreted as control elements or syntactic markers when they are sent to a downstream component.",
              "keyphrase_sources": [
                {
                  "id": "rootcause:lack of input sanitization and escaping",
                  "keyphrase": "lack of input sanitization and escaping",
                  "type": "rootcause"
                }
              ]
            },
            "similarity": 385.1134369156416
          },
          {
            "metadata": {
              "doc_id": "434",
              "name": "Unrestricted Upload of File with Dangerous Type",
              "source": "sparse",
              "original_content": "The product allows the upload or transfer of dangerous file types that are automatically processed within its environment.",
              "keyphrase_sources": [
                {
                  "id": "rootcause:lack of input sanitization and escaping",
                  "keyphrase": "lack of input sanitization and escaping",
                  "type": "rootcause"
                },
                {
                  "id": "weakness:cross-site scripting",
                  "keyphrase": "cross-site scripting",
                  "type": "weakness"
                },
                {
                  "id": "impact:Stored Cross-Site Scripting attacks",
                  "keyphrase": "Stored Cross-Site Scripting attacks",
                  "type": "impact"
                },
                {
                  "id": "attacker:high privilege users",
                  "keyphrase": "high privilege users",
                  "type": "attacker"
                },
                {
                  "id": "product:Pinpoint Booking System WordPress plugin",
                  "keyphrase": "Pinpoint Booking System WordPress plugin",
                  "type": "product"
                },
                {
                  "id": "version:before 2.9.9.4.8",
                  "keyphrase": "before 2.9.9.4.8",
                  "type": "version"
                }
              ]
            },
            "similarity": 359.46013606603907
          },
          {
            "metadata": {
              "doc_id": "862",
              "name": "Missing Authorization",
              "source": "sparse",
              "original_content": "The product does not perform an authorization check when an actor attempts to access a resource or perform an action."
            },
            "similarity": 359.3287550423023
          }
        ]
      },
      "weakness:cross-site scripting": {
        "keyphrase": "cross-site scripting",
        "type": "weakness",
        "cwes": [
          {
            "metadata": {
              "doc_id": "352",
              "name": "Cross-Site Request Forgery (CSRF)",
              "source": "sparse",
              "original_content": "The web application does not, or can not, sufficiently verify whether a well-formed, valid, consistent request was intentionally provided by the user who submitted the request."
            },
            "similarity": 439.9652176797415
          },
          {
            "metadata": {
              "doc_id": "116",
              "name": "Improper Encoding or Escaping of Output",
              "source": "sparse",
              "original_content": "The product prepares a structured message for communication with another component, but encoding or escaping of the data is either missing or done incorrectly. As a result, the intended structure of the message is not preserved."
            },
            "similarity": 364.57211673838555
          },
          {
            "metadata": {
              "doc_id": "79",
              "name": "Improper Neutralization of Input During Web Page Generation ('Cross-site Scripting')",
              "source": "sparse",
              "original_content": "The product does not neutralize or incorrectly neutralizes user-controllable input before it is placed in output that is used as a web page that is served to other users."
            },
            "similarity": 349.88079948745116
          },
          {
            "metadata": {
              "doc_id": "434",
              "name": "Unrestricted Upload of File with Dangerous Type",
              "source": "sparse",
              "original_content": "The product allows the upload or transfer of dangerous file types that are automatically processed within its environment."
            },
            "similarity": 320.28573242610855
          },
          {
            "metadata": {
              "doc_id": "89",
              "name": "Improper Neutralization of Special Elements used in an SQL Command ('SQL Injection')",
              "source": "sparse",
              "original_content": "The product constructs all or part of an SQL command using externally-influenced input from an upstream component, but it does not neutralize or incorrectly neutralizes special elements that could modify the intended SQL command when it is sent to a downstream component. Without sufficient removal or quoting of SQL syntax in user-controllable inputs, the generated SQL query can cause those inputs to be interpreted as SQL instead of ordinary user data."
            },
            "similarity": 319.717980516048
          }
        ]
      },
      "impact:Stored Cross-Site Scripting attacks": {
        "keyphrase": "Stored Cross-Site Scripting attacks",
        "type": "impact",
        "cwes": [
          {
            "metadata": {
              "doc_id": "352",
              "name": "Cross-Site Request Forgery (CSRF)",
              "source": "sparse",
              "original_content": "The web application does not, or can not, sufficiently verify whether a well-formed, valid, consistent request was intentionally provided by the user who submitted the request."
            },
            "similarity": 169.33604404184496
          },
          {
            "metadata": {
              "doc_id": "116",
              "name": "Improper Encoding or Escaping of Output",
              "source": "sparse",
              "original_content": "The product prepares a structured message for communication with another component, but encoding or escaping of the data is either missing or done incorrectly. As a result, the intended structure of the message is not preserved."
            },
            "similarity": 138.3292998716049
          },
          {
            "metadata": {
              "doc_id": "79",
              "name": "Improper Neutralization of Input During Web Page Generation ('Cross-site Scripting')",
              "source": "sparse",
              "original_content": "The product does not neutralize or incorrectly neutralizes user-controllable input before it is placed in output that is used as a web page that is served to other users."
            },
            "similarity": 133.90701399158695
          },
          {
            "metadata": {
              "doc_id": "434",
              "name": "Unrestricted Upload of File with Dangerous Type",
              "source": "sparse",
              "original_content": "The product allows the upload or transfer of dangerous file types that are automatically processed within its environment."
            },
            "similarity": 123.03452589284204
          },
          {
            "metadata": {
              "doc_id": "862",
              "name": "Missing Authorization",
              "source": "sparse",
              "original_content": "The product does not perform an authorization check when an actor attempts to access a resource or perform an action."
            },
            "similarity": 118.2524043345906
          }
        ]
      },
      "attacker:high privilege users": {
        "keyphrase": "high privilege users",
        "type": "attacker",
        "cwes": [
          {
            "metadata": {
              "doc_id": "352",
              "name": "Cross-Site Request Forgery (CSRF)",
              "source": "sparse",
              "original_content": "The web application does not, or can not, sufficiently verify whether a well-formed, valid, consistent request was intentionally provided by the user who submitted the request."
            },
            "similarity": 128.29012916257273
          },
          {
            "metadata": {
              "doc_id": "116",
              "name": "Improper Encoding or Escaping of Output",
              "source": "sparse",
              "original_content": "The product prepares a structured message for communication with another component, but encoding or escaping of the data is either missing or done incorrectly. As a result, the intended structure of the message is not preserved."
            },
            "similarity": 107.59071479690266
          },
          {
            "metadata": {
              "doc_id": "862",
              "name": "Missing Authorization",
              "source": "sparse",
              "original_content": "The product does not perform an authorization check when an actor attempts to access a resource or perform an action."
            },
            "similarity": 104.75883077156003
          },
          {
            "metadata": {
              "doc_id": "434",
              "name": "Unrestricted Upload of File with Dangerous Type",
              "source": "sparse",
              "original_content": "The product allows the upload or transfer of dangerous file types that are automatically processed within its environment."
            },
            "similarity": 101.59638883502826
          },
          {
            "metadata": {
              "doc_id": "89",
              "name": "Improper Neutralization of Special Elements used in an SQL Command ('SQL Injection')",
              "source": "sparse",
              "original_content": "The product constructs all or part of an SQL command using externally-influenced input from an upstream component, but it does not neutralize or incorrectly neutralizes special elements that could modify the intended SQL command when it is sent to a downstream component. Without sufficient removal or quoting of SQL syntax in user-controllable inputs, the generated SQL query can cause those inputs to be interpreted as SQL instead of ordinary user data."
            },
            "similarity": 99.66115646634898
          }
        ]
      },
      "product:Pinpoint Booking System WordPress plugin": {
        "keyphrase": "Pinpoint Booking System WordPress plugin",
        "type": "product",
        "cwes": [
          {
            "metadata": {
              "doc_id": "352",
              "name": "Cross-Site Request Forgery (CSRF)",
              "source": "sparse",
              "original_content": "The web application does not, or can not, sufficiently verify whether a well-formed, valid, consistent request was intentionally provided by the user who submitted the request."
            },
            "similarity": 146.08436265965062
          },
          {
            "metadata": {
              "doc_id": "116",
              "name": "Improper Encoding or Escaping of Output",
              "source": "sparse",
              "original_content": "The product prepares a structured message for communication with another component, but encoding or escaping of the data is either missing or done incorrectly. As a result, the intended structure of the message is not preserved."
            },
            "similarity": 126.51099644562416
          },
          {
            "metadata": {
              "doc_id": "862",
              "name": "Missing Authorization",
              "source": "sparse",
              "original_content": "The product does not perform an authorization check when an actor attempts to access a resource or perform an action."
            },
            "similarity": 116.44615561638768
          },
          {
            "metadata": {
              "doc_id": "89",
              "name": "Improper Neutralization of Special Elements used in an SQL Command ('SQL Injection')",
              "source": "sparse",
              "original_content": "The product constructs all or part of an SQL command using externally-influenced input from an upstream component, but it does not neutralize or incorrectly neutralizes special elements that could modify the intended SQL command when it is sent to a downstream component. Without sufficient removal or quoting of SQL syntax in user-controllable inputs, the generated SQL query can cause those inputs to be interpreted as SQL instead of ordinary user data."
            },
            "similarity": 113.13301513199156
          },
          {
            "metadata": {
              "doc_id": "434",
              "name": "Unrestricted Upload of File with Dangerous Type",
              "source": "sparse",
              "original_content": "The product allows the upload or transfer of dangerous file types that are automatically processed within its environment."
            },
            "similarity": 112.22058431776462
          }
        ]
      },
      "version:before 2.9.9.4.8": {
        "keyphrase": "before 2.9.9.4.8",
        "type": "version",
        "cwes": [
          {
            "metadata": {
              "doc_id": "352",
              "name": "Cross-Site Request Forgery (CSRF)",
              "source": "sparse",
              "original_content": "The web application does not, or can not, sufficiently verify whether a well-formed, valid, consistent request was intentionally provided by the user who submitted the request."
            },
            "similarity": 139.0528043389462
          },
          {
            "metadata": {
              "doc_id": "116",
              "name": "Improper Encoding or Escaping of Output",
              "source": "sparse",
              "original_content": "The product prepares a structured message for communication with another component, but encoding or escaping of the data is either missing or done incorrectly. As a result, the intended structure of the message is not preserved."
            },
            "similarity": 122.78379180025954
          },
          {
            "metadata": {
              "doc_id": "434",
              "name": "Unrestricted Upload of File with Dangerous Type",
              "source": "sparse",
              "original_content": "The product allows the upload or transfer of dangerous file types that are automatically processed within its environment."
            },
            "similarity": 111.92835424958683
          },
          {
            "metadata": {
              "doc_id": "862",
              "name": "Missing Authorization",
              "source": "sparse",
              "original_content": "The product does not perform an authorization check when an actor attempts to access a resource or perform an action."
            },
            "similarity": 111.7259002149947
          },
          {
            "metadata": {
              "doc_id": "79",
              "name": "Improper Neutralization of Input During Web Page Generation ('Cross-site Scripting')",
              "source": "sparse",
              "original_content": "The product does not neutralize or incorrectly neutralizes user-controllable input before it is placed in output that is used as a web page that is served to other users."
            },
            "similarity": 108.90364824883453
          }
        ]
      }
    },
    "keyphrase_mapping": {
      "352": [
        {
          "id": "rootcause:does not sanitise and escape some of its settings",
          "keyphrase": "does not sanitise and escape some of its settings",
          "type": "rootcause"
        },
        {
          "id": "rootcause:lack of input sanitization and escaping",
          "keyphrase": "lack of input sanitization and escaping",
          "type": "rootcause"
        },
        {
          "id": "weakness:cross-site scripting",
          "keyphrase": "cross-site scripting",
          "type": "weakness"
        },
        {
          "id": "impact:Stored Cross-Site Scripting attacks",
          "keyphrase": "Stored Cross-Site Scripting attacks",
          "type": "impact"
        },
        {
          "id": "attacker:high privilege users",
          "keyphrase": "high privilege users",
          "type": "attacker"
        },
        {
          "id": "product:Pinpoint Booking System WordPress plugin",
          "keyphrase": "Pinpoint Booking System WordPress plugin",
          "type": "product"
        },
        {
          "id": "version:before 2.9.9.4.8",
          "keyphrase": "before 2.9.9.4.8",
          "type": "version"
        }
      ],
      "116": [
        {
          "id": "rootcause:does not sanitise and escape some of its settings",
          "keyphrase": "does not sanitise and escape some of its settings",
          "type": "rootcause"
        },
        {
          "id": "rootcause:lack of input sanitization and escaping",
          "keyphrase": "lack of input sanitization and escaping",
          "type": "rootcause"
        },
        {
          "id": "weakness:cross-site scripting",
          "keyphrase": "cross-site scripting",
          "type": "weakness"
        },
        {
          "id": "impact:Stored Cross-Site Scripting attacks",
          "keyphrase": "Stored Cross-Site Scripting attacks",
          "type": "impact"
        },
        {
          "id": "attacker:high privilege users",
          "keyphrase": "high privilege users",
          "type": "attacker"
        },
        {
          "id": "product:Pinpoint Booking System WordPress plugin",
          "keyphrase": "Pinpoint Booking System WordPress plugin",
          "type": "product"
        },
        {
          "id": "version:before 2.9.9.4.8",
          "keyphrase": "before 2.9.9.4.8",
          "type": "version"
        }
      ],
      "862": [
        {
          "id": "rootcause:does not sanitise and escape some of its settings",
          "keyphrase": "does not sanitise and escape some of its settings",
          "type": "rootcause"
        },
        {
          "id": "rootcause:lack of input sanitization and escaping",
          "keyphrase": "lack of input sanitization and escaping",
          "type": "rootcause"
        },
        {
          "id": "impact:Stored Cross-Site Scripting attacks",
          "keyphrase": "Stored Cross-Site Scripting attacks",
          "type": "impact"
        },
        {
          "id": "attacker:high privilege users",
          "keyphrase": "high privilege users",
          "type": "attacker"
        },
        {
          "id": "product:Pinpoint Booking System WordPress plugin",
          "keyphrase": "Pinpoint Booking System WordPress plugin",
          "type": "product"
        },
        {
          "id": "version:before 2.9.9.4.8",
          "keyphrase": "before 2.9.9.4.8",
          "type": "version"
        }
      ],
      "89": [
        {
          "id": "rootcause:does not sanitise and escape some of its settings",
          "keyphrase": "does not sanitise and escape some of its settings",
          "type": "rootcause"
        },
        {
          "id": "weakness:cross-site scripting",
          "keyphrase": "cross-site scripting",
          "type": "weakness"
        },
        {
          "id": "attacker:high privilege users",
          "keyphrase": "high privilege users",
          "type": "attacker"
        },
        {
          "id": "product:Pinpoint Booking System WordPress plugin",
          "keyphrase": "Pinpoint Booking System WordPress plugin",
          "type": "product"
        }
      ],
      "79": [
        {
          "id": "rootcause:does not sanitise and escape some of its settings",
          "keyphrase": "does not sanitise and escape some of its settings",
          "type": "rootcause"
        },
        {
          "id": "weakness:cross-site scripting",
          "keyphrase": "cross-site scripting",
          "type": "weakness"
        },
        {
          "id": "impact:Stored Cross-Site Scripting attacks",
          "keyphrase": "Stored Cross-Site Scripting attacks",
          "type": "impact"
        },
        {
          "id": "version:before 2.9.9.4.8",
          "keyphrase": "before 2.9.9.4.8",
          "type": "version"
        }
      ],
      "138": [
        {
          "id": "rootcause:lack of input sanitization and escaping",
          "keyphrase": "lack of input sanitization and escaping",
          "type": "rootcause"
        }
      ],
      "434": [
        {
          "id": "rootcause:lack of input sanitization and escaping",
          "keyphrase": "lack of input sanitization and escaping",
          "type": "rootcause"
        },
        {
          "id": "weakness:cross-site scripting",
          "keyphrase": "cross-site scripting",
          "type": "weakness"
        },
        {
          "id": "impact:Stored Cross-Site Scripting attacks",
          "keyphrase": "Stored Cross-Site Scripting attacks",
          "type": "impact"
        },
        {
          "id": "attacker:high privilege users",
          "keyphrase": "high privilege users",
          "type": "attacker"
        },
        {
          "id": "product:Pinpoint Booking System WordPress plugin",
          "keyphrase": "Pinpoint Booking System WordPress plugin",
          "type": "product"
        },
        {
          "id": "version:before 2.9.9.4.8",
          "keyphrase": "before 2.9.9.4.8",
          "type": "version"
        }
      ]
    },
    "relevant_cwes": [
      {
        "metadata": {
          "doc_id": "352",
          "name": "Cross-Site Request Forgery (CSRF)",
          "source": "sparse",
          "original_content": "The web application does not, or can not, sufficiently verify whether a well-formed, valid, consistent request was intentionally provided by the user who submitted the request.",
          "keyphrase_sources": [
            {
              "id": "rootcause:does not sanitise and escape some of its settings",
              "keyphrase": "does not sanitise and escape some of its settings",
              "type": "rootcause"
            },
            {
              "id": "rootcause:lack of input sanitization and escaping",
              "keyphrase": "lack of input sanitization and escaping",
              "type": "rootcause"
            },
            {
              "id": "weakness:cross-site scripting",
              "keyphrase": "cross-site scripting",
              "type": "weakness"
            },
            {
              "id": "impact:Stored Cross-Site Scripting attacks",
              "keyphrase": "Stored Cross-Site Scripting attacks",
              "type": "impact"
            },
            {
              "id": "attacker:high privilege users",
              "keyphrase": "high privilege users",
              "type": "attacker"
            },
            {
              "id": "product:Pinpoint Booking System WordPress plugin",
              "keyphrase": "Pinpoint Booking System WordPress plugin",
              "type": "product"
            },
            {
              "id": "version:before 2.9.9.4.8",
              "keyphrase": "before 2.9.9.4.8",
              "type": "version"
            }
          ]
        },
        "similarity": 576.7084206562257
      },
      {
        "metadata": {
          "doc_id": "116",
          "name": "Improper Encoding or Escaping of Output",
          "source": "sparse",
          "original_content": "The product prepares a structured message for communication with another component, but encoding or escaping of the data is either missing or done incorrectly. As a result, the intended structure of the message is not preserved.",
          "keyphrase_sources": [
            {
              "id": "rootcause:does not sanitise and escape some of its settings",
              "keyphrase": "does not sanitise and escape some of its settings",
              "type": "rootcause"
            },
            {
              "id": "rootcause:lack of input sanitization and escaping",
              "keyphrase": "lack of input sanitization and escaping",
              "type": "rootcause"
            },
            {
              "id": "weakness:cross-site scripting",
              "keyphrase": "cross-site scripting",
              "type": "weakness"
            },
            {
              "id": "impact:Stored Cross-Site Scripting attacks",
              "keyphrase": "Stored Cross-Site Scripting attacks",
              "type": "impact"
            },
            {
              "id": "attacker:high privilege users",
              "keyphrase": "high privilege users",
              "type": "attacker"
            },
            {
              "id": "product:Pinpoint Booking System WordPress plugin",
              "keyphrase": "Pinpoint Booking System WordPress plugin",
              "type": "product"
            },
            {
              "id": "version:before 2.9.9.4.8",
              "keyphrase": "before 2.9.9.4.8",
              "type": "version"
            }
          ]
        },
        "similarity": 474.7287288048298
      },
      {
        "metadata": {
          "doc_id": "862",
          "name": "Missing Authorization",
          "source": "sparse",
          "original_content": "The product does not perform an authorization check when an actor attempts to access a resource or perform an action.",
          "keyphrase_sources": [
            {
              "id": "rootcause:does not sanitise and escape some of its settings",
              "keyphrase": "does not sanitise and escape some of its settings",
              "type": "rootcause"
            },
            {
              "id": "rootcause:lack of input sanitization and escaping",
              "keyphrase": "lack of input sanitization and escaping",
              "type": "rootcause"
            },
            {
              "id": "impact:Stored Cross-Site Scripting attacks",
              "keyphrase": "Stored Cross-Site Scripting attacks",
              "type": "impact"
            },
            {
              "id": "attacker:high privilege users",
              "keyphrase": "high privilege users",
              "type": "attacker"
            },
            {
              "id": "product:Pinpoint Booking System WordPress plugin",
              "keyphrase": "Pinpoint Booking System WordPress plugin",
              "type": "product"
            },
            {
              "id": "version:before 2.9.9.4.8",
              "keyphrase": "before 2.9.9.4.8",
              "type": "version"
            }
          ]
        },
        "similarity": 416.36431471578516
      },
      {
        "metadata": {
          "doc_id": "89",
          "name": "Improper Neutralization of Special Elements used in an SQL Command ('SQL Injection')",
          "source": "sparse",
          "original_content": "The product constructs all or part of an SQL command using externally-influenced input from an upstream component, but it does not neutralize or incorrectly neutralizes special elements that could modify the intended SQL command when it is sent to a downstream component. Without sufficient removal or quoting of SQL syntax in user-controllable inputs, the generated SQL query can cause those inputs to be interpreted as SQL instead of ordinary user data.",
          "keyphrase_sources": [
            {
              "id": "rootcause:does not sanitise and escape some of its settings",
              "keyphrase": "does not sanitise and escape some of its settings",
              "type": "rootcause"
            },
            {
              "id": "weakness:cross-site scripting",
              "keyphrase": "cross-site scripting",
              "type": "weakness"
            },
            {
              "id": "attacker:high privilege users",
              "keyphrase": "high privilege users",
              "type": "attacker"
            },
            {
              "id": "product:Pinpoint Booking System WordPress plugin",
              "keyphrase": "Pinpoint Booking System WordPress plugin",
              "type": "product"
            }
          ]
        },
        "similarity": 399.1205267970783
      },
      {
        "metadata": {
          "doc_id": "138",
          "name": "Improper Neutralization of Special Elements",
          "source": "sparse",
          "original_content": "The product receives input from an upstream component, but it does not neutralize or incorrectly neutralizes special elements that could be interpreted as control elements or syntactic markers when they are sent to a downstream component.",
          "keyphrase_sources": [
            {
              "id": "rootcause:lack of input sanitization and escaping",
              "keyphrase": "lack of input sanitization and escaping",
              "type": "rootcause"
            }
          ]
        },
        "similarity": 385.1134369156416
      },
      {
        "metadata": {
          "doc_id": "79",
          "name": "Improper Neutralization of Input During Web Page Generation ('Cross-site Scripting')",
          "source": "sparse",
          "original_content": "The product does not neutralize or incorrectly neutralizes user-controllable input before it is placed in output that is used as a web page that is served to other users.",
          "keyphrase_sources": [
            {
              "id": "rootcause:does not sanitise and escape some of its settings",
              "keyphrase": "does not sanitise and escape some of its settings",
              "type": "rootcause"
            },
            {
              "id": "weakness:cross-site scripting",
              "keyphrase": "cross-site scripting",
              "type": "weakness"
            },
            {
              "id": "impact:Stored Cross-Site Scripting attacks",
              "keyphrase": "Stored Cross-Site Scripting attacks",
              "type": "impact"
            },
            {
              "id": "version:before 2.9.9.4.8",
              "keyphrase": "before 2.9.9.4.8",
              "type": "version"
            }
          ]
        },
        "similarity": 373.947239539591
      },
      {
        "metadata": {
          "doc_id": "434",
          "name": "Unrestricted Upload of File with Dangerous Type",
          "source": "sparse",
          "original_content": "The product allows the upload or transfer of dangerous file types that are automatically processed within its environment.",
          "keyphrase_sources": [
            {
              "id": "rootcause:lack of input sanitization and escaping",
              "keyphrase": "lack of input sanitization and escaping",
              "type": "rootcause"
            },
            {
              "id": "weakness:cross-site scripting",
              "keyphrase": "cross-site scripting",
              "type": "weakness"
            },
            {
              "id": "impact:Stored Cross-Site Scripting attacks",
              "keyphrase": "Stored Cross-Site Scripting attacks",
              "type": "impact"
            },
            {
              "id": "attacker:high privilege users",
              "keyphrase": "high privilege users",
              "type": "attacker"
            },
            {
              "id": "product:Pinpoint Booking System WordPress plugin",
              "keyphrase": "Pinpoint Booking System WordPress plugin",
              "type": "product"
            },
            {
              "id": "version:before 2.9.9.4.8",
              "keyphrase": "before 2.9.9.4.8",
              "type": "version"
            }
          ]
        },
        "similarity": 359.46013606603907
      }
    ],
    "enhanced_query": "# Vulnerability Description\n\n    The Pinpoint Booking System WordPress plugin before 2.9.9.4.8 **does not sanitise and escape some of its settings**, which could allow high privilege users such as admin to perform Stored Cross-Site Scripting attacks even when the unfiltered_html capability is disallowed (for example in multisite setup)\n\n    # Keyphrase-Specific CWE Analysis\n    This vulnerability contains multiple keyphrases that may map to different CWEs. \n    Please analyze each keyphrase separately and determine the most appropriate CWE(s) for each.\n\n    ## ROOTCAUSE: 'does not sanitise and escape some of its settings'\n\nRelevant CWEs for this ROOTCAUSE:\n\n### 1. CWE-352: Cross-Site Request Forgery (CSRF) (Score: 576.71)\n\nThe web application does not, or can not, sufficiently verify whether a well-formed, valid, consistent request was intentionally provided by the user who submitted the request....\n\n### 2. CWE-116: Improper Encoding or Escaping of Output (Score: 474.73)\n\nThe product prepares a structured message for communication with another component, but encoding or escaping of the data is either missing or done incorrectly. As a result, the intended structure of the message is not preserved....\n\n### 3. CWE-862: Missing Authorization (Score: 416.36)\n\nThe product does not perform an authorization check when an actor attempts to access a resource or perform an action....\n\n### 4. CWE-89: Improper Neutralization of Special Elements used in an SQL Command ('SQL Injection') (Score: 399.12)\n\nThe product constructs all or part of an SQL command using externally-influenced input from an upstream component, but it does not neutralize or incorrectly neutralizes special elements that could modify the intended SQL command when it is sent to a downstream component. Without sufficient removal o...\n\n### 5. CWE-79: Improper Neutralization of Input During Web Page Generation ('Cross-site Scripting') (Score: 373.95)\n\nThe product does not neutralize or incorrectly neutralizes user-controllable input before it is placed in output that is used as a web page that is served to other users....\n\n## ROOTCAUSE: 'lack of input sanitization and escaping'\n\nRelevant CWEs for this ROOTCAUSE:\n\n### 1. CWE-352: Cross-Site Request Forgery (CSRF) (Score: 576.71)\n\nThe web application does not, or can not, sufficiently verify whether a well-formed, valid, consistent request was intentionally provided by the user who submitted the request....\n\n### 2. CWE-116: Improper Encoding or Escaping of Output (Score: 474.73)\n\nThe product prepares a structured message for communication with another component, but encoding or escaping of the data is either missing or done incorrectly. As a result, the intended structure of the message is not preserved....\n\n### 3. CWE-862: Missing Authorization (Score: 416.36)\n\nThe product does not perform an authorization check when an actor attempts to access a resource or perform an action....\n\n### 4. CWE-138: Improper Neutralization of Special Elements (Score: 385.11)\n\nThe product receives input from an upstream component, but it does not neutralize or incorrectly neutralizes special elements that could be interpreted as control elements or syntactic markers when they are sent to a downstream component....\n\n### 5. CWE-434: Unrestricted Upload of File with Dangerous Type (Score: 359.46)\n\nThe product allows the upload or transfer of dangerous file types that are automatically processed within its environment....\n\n## WEAKNESS: 'cross-site scripting'\n\nRelevant CWEs for this WEAKNESS:\n\n### 1. CWE-352: Cross-Site Request Forgery (CSRF) (Score: 576.71)\n\nThe web application does not, or can not, sufficiently verify whether a well-formed, valid, consistent request was intentionally provided by the user who submitted the request....\n\n### 2. CWE-116: Improper Encoding or Escaping of Output (Score: 474.73)\n\nThe product prepares a structured message for communication with another component, but encoding or escaping of the data is either missing or done incorrectly. As a result, the intended structure of the message is not preserved....\n\n### 3. CWE-89: Improper Neutralization of Special Elements used in an SQL Command ('SQL Injection') (Score: 399.12)\n\nThe product constructs all or part of an SQL command using externally-influenced input from an upstream component, but it does not neutralize or incorrectly neutralizes special elements that could modify the intended SQL command when it is sent to a downstream component. Without sufficient removal o...\n\n### 4. CWE-79: Improper Neutralization of Input During Web Page Generation ('Cross-site Scripting') (Score: 373.95)\n\nThe product does not neutralize or incorrectly neutralizes user-controllable input before it is placed in output that is used as a web page that is served to other users....\n\n### 5. CWE-434: Unrestricted Upload of File with Dangerous Type (Score: 359.46)\n\nThe product allows the upload or transfer of dangerous file types that are automatically processed within its environment....\n\n## IMPACT: 'Stored Cross-Site Scripting attacks'\n\nRelevant CWEs for this IMPACT:\n\n### 1. CWE-352: Cross-Site Request Forgery (CSRF) (Score: 576.71)\n\nThe web application does not, or can not, sufficiently verify whether a well-formed, valid, consistent request was intentionally provided by the user who submitted the request....\n\n### 2. CWE-116: Improper Encoding or Escaping of Output (Score: 474.73)\n\nThe product prepares a structured message for communication with another component, but encoding or escaping of the data is either missing or done incorrectly. As a result, the intended structure of the message is not preserved....\n\n### 3. CWE-862: Missing Authorization (Score: 416.36)\n\nThe product does not perform an authorization check when an actor attempts to access a resource or perform an action....\n\n### 4. CWE-79: Improper Neutralization of Input During Web Page Generation ('Cross-site Scripting') (Score: 373.95)\n\nThe product does not neutralize or incorrectly neutralizes user-controllable input before it is placed in output that is used as a web page that is served to other users....\n\n### 5. CWE-434: Unrestricted Upload of File with Dangerous Type (Score: 359.46)\n\nThe product allows the upload or transfer of dangerous file types that are automatically processed within its environment....\n\n## ATTACKER: 'high privilege users'\n\nRelevant CWEs for this ATTACKER:\n\n### 1. CWE-352: Cross-Site Request Forgery (CSRF) (Score: 576.71)\n\nThe web application does not, or can not, sufficiently verify whether a well-formed, valid, consistent request was intentionally provided by the user who submitted the request....\n\n### 2. CWE-116: Improper Encoding or Escaping of Output (Score: 474.73)\n\nThe product prepares a structured message for communication with another component, but encoding or escaping of the data is either missing or done incorrectly. As a result, the intended structure of the message is not preserved....\n\n### 3. CWE-862: Missing Authorization (Score: 416.36)\n\nThe product does not perform an authorization check when an actor attempts to access a resource or perform an action....\n\n### 4. CWE-89: Improper Neutralization of Special Elements used in an SQL Command ('SQL Injection') (Score: 399.12)\n\nThe product constructs all or part of an SQL command using externally-influenced input from an upstream component, but it does not neutralize or incorrectly neutralizes special elements that could modify the intended SQL command when it is sent to a downstream component. Without sufficient removal o...\n\n### 5. CWE-434: Unrestricted Upload of File with Dangerous Type (Score: 359.46)\n\nThe product allows the upload or transfer of dangerous file types that are automatically processed within its environment....\n\n## PRODUCT: 'Pinpoint Booking System WordPress plugin'\n\nRelevant CWEs for this PRODUCT:\n\n### 1. CWE-352: Cross-Site Request Forgery (CSRF) (Score: 576.71)\n\nThe web application does not, or can not, sufficiently verify whether a well-formed, valid, consistent request was intentionally provided by the user who submitted the request....\n\n### 2. CWE-116: Improper Encoding or Escaping of Output (Score: 474.73)\n\nThe product prepares a structured message for communication with another component, but encoding or escaping of the data is either missing or done incorrectly. As a result, the intended structure of the message is not preserved....\n\n### 3. CWE-862: Missing Authorization (Score: 416.36)\n\nThe product does not perform an authorization check when an actor attempts to access a resource or perform an action....\n\n### 4. CWE-89: Improper Neutralization of Special Elements used in an SQL Command ('SQL Injection') (Score: 399.12)\n\nThe product constructs all or part of an SQL command using externally-influenced input from an upstream component, but it does not neutralize or incorrectly neutralizes special elements that could modify the intended SQL command when it is sent to a downstream component. Without sufficient removal o...\n\n### 5. CWE-434: Unrestricted Upload of File with Dangerous Type (Score: 359.46)\n\nThe product allows the upload or transfer of dangerous file types that are automatically processed within its environment....\n\n## VERSION: 'before 2.9.9.4.8'\n\nRelevant CWEs for this VERSION:\n\n### 1. CWE-352: Cross-Site Request Forgery (CSRF) (Score: 576.71)\n\nThe web application does not, or can not, sufficiently verify whether a well-formed, valid, consistent request was intentionally provided by the user who submitted the request....\n\n### 2. CWE-116: Improper Encoding or Escaping of Output (Score: 474.73)\n\nThe product prepares a structured message for communication with another component, but encoding or escaping of the data is either missing or done incorrectly. As a result, the intended structure of the message is not preserved....\n\n### 3. CWE-862: Missing Authorization (Score: 416.36)\n\nThe product does not perform an authorization check when an actor attempts to access a resource or perform an action....\n\n### 4. CWE-79: Improper Neutralization of Input During Web Page Generation ('Cross-site Scripting') (Score: 373.95)\n\nThe product does not neutralize or incorrectly neutralizes user-controllable input before it is placed in output that is used as a web page that is served to other users....\n\n### 5. CWE-434: Unrestricted Upload of File with Dangerous Type (Score: 359.46)\n\nThe product allows the upload or transfer of dangerous file types that are automatically processed within its environment....\n\n\n    # Analysis Instructions\n    1. For each keyphrase, identify the most appropriate CWE(s) that represent the weakness.\n    2. Consider how the different keyphrases might relate to each other in the vulnerability chain.\n    3. Provide a final determination of primary CWE(s) and any secondary CWEs.\n    4. Format your response using the standard analysis template.\n\n    Please analyze how these different weaknesses interact and provide a comprehensive CWE classification.\n    "
  },
  "retrieval_time": 1.3205242156982422
}