{
  "vulnerability_info": "VulnerabilityInfo(cve_id='CVE-2025-3837', description='An improper **input validation vulnerability** is identified in the End of Life (EOL) OVA based connect component which is deployed for installation purposes in the customer internal network. This EOL component was deprecated in September 2023 with end of support extended till January 2024. Under certain circumstances, an actor can manipulate a specific request parameter and inject code execution payload which could lead to a remote code execution on the infrastructure hosting this component.', key_phrases={'rootcause': ['input validation vulnerability', 'improper input validation'], 'weakness': '', 'impact': 'remote code execution', 'vector': 'manipulating specific request parameter', 'attacker': 'actor', 'product': 'End of Life (EOL) OVA based connect component', 'version': '', 'component': ''}, reference_content=\"Based on the provided content and without a CVE description, here's an analysis:\\n\\n**CVE-2025-3837: PLACEHOLDER - Implement CVE description retrieval**\\n\\nThe content is **RELATED** to security vulnerabilities and remediation, but does not directly map to a specific CVE without the CVE description. It details Saviynt's security practices, compliance certifications, and vulnerability reporting process.\\n\\nHere's a breakdown of the security-relevant information extracted from the content:\\n\\n*   **Root cause of vulnerability:** Not explicitly stated, but the document indicates a proactive approach to identifying and addressing vulnerabilities.\\n*   **Weaknesses/vulnerabilities present:** Not specifically detailed. The document focuses on Saviynt's security measures to *prevent* vulnerabilities.\\n*   **Impact of exploitation:** Not specified, but the document implies potential impacts to data security and system availability.\\n*   **Attack vectors:** Not detailed.\\n*   **Required attacker capabilities/position:** Not detailed.\\n*   **Mitigation or fix:** Saviynt addresses vulnerabilities through:\\n    *   Robust data security and DevSecOps program with regular penetration testing.\\n    *   Use of their own Enterprise Identity Cloud (EIC) platform and security tools.\\n    *   Secured and encrypted communications.\\n    *   Security Bulletins (S25-01 and S25-02 are referenced).\\n    *   A vulnerability reporting process (security@saviynt.com).\\n*   **Additional Details:**\\n    *   Saviynt is a CNA (CVE Numbering Authority) recognized by MITRE.\\n    *   The company signed the CISA Secure by Design pledge.\\n    *   They maintain several compliance certifications (ISO 27001:2013, ISO 27017:2015, SOC 1 and 2 Type II, PCI-DSS, FedRAMP Moderate).\\n    *   They have a responsible disclosure policy.\\n\\n**Note:** This content provides a general overview of Saviynt's security posture and vulnerability management practices. It does *not* detail a specific vulnerability that corresponds to CVE-2025-3837 without the official CVE description. It provides more detail than a typical CVE description would, focusing on preventative measures and compliance.\", similar_info={'cwe_distribution': {}, 'cwe_consensus': '', 'similarity_stats': {'thresholds': [], 'total_samples_by_threshold': {}, 'top_cwes_by_threshold': {}}}, similarity_summary=SimilarityInsight(consensus_cwe='', top_cwes=[], confidence_levels={}, total_samples=0), analysis='', analysis_with_relationships='', criticism='', resolution='', relevant_cwes=[{'metadata': {'doc_id': '295', 'name': 'Improper Certificate Validation', 'source': 'sparse', 'original_content': 'The product does not validate, or incorrectly validates, a certificate.', 'keyphrase_sources': [{'id': 'rootcause:input validation vulnerability', 'keyphrase': 'input validation vulnerability', 'type': 'rootcause'}, {'id': 'rootcause:improper input validation', 'keyphrase': 'improper input validation', 'type': 'rootcause'}, {'id': 'impact:remote code execution', 'keyphrase': 'remote code execution', 'type': 'impact'}, {'id': 'vector:manipulating specific request parameter', 'keyphrase': 'manipulating specific request parameter', 'type': 'vector'}, {'id': 'attacker:actor', 'keyphrase': 'actor', 'type': 'attacker'}, {'id': 'product:End of Life (EOL) OVA based connect component', 'keyphrase': 'End of Life (EOL) OVA based connect component', 'type': 'product'}]}, 'similarity': np.float64(409.03442452703405)}, {'metadata': {'doc_id': '20', 'name': 'Improper Input Validation', 'source': 'sparse', 'original_content': 'The product receives input or data, but it does\\n        not validate or incorrectly validates that the input has the\\n        properties that are required to process the data safely and\\n        correctly.', 'keyphrase_sources': [{'id': 'rootcause:input validation vulnerability', 'keyphrase': 'input validation vulnerability', 'type': 'rootcause'}, {'id': 'rootcause:improper input validation', 'keyphrase': 'improper input validation', 'type': 'rootcause'}, {'id': 'impact:remote code execution', 'keyphrase': 'remote code execution', 'type': 'impact'}, {'id': 'attacker:actor', 'keyphrase': 'actor', 'type': 'attacker'}, {'id': 'product:End of Life (EOL) OVA based connect component', 'keyphrase': 'End of Life (EOL) OVA based connect component', 'type': 'product'}]}, 'similarity': np.float64(407.2695068346683)}, {'metadata': {'doc_id': '94', 'name': \"Improper Control of Generation of Code ('Code Injection')\", 'source': 'sparse', 'original_content': 'The product constructs all or part of a code segment using externally-influenced input from an upstream component, but it does not neutralize or incorrectly neutralizes special elements that could modify the syntax or behavior of the intended code segment.', 'keyphrase_sources': [{'id': 'rootcause:input validation vulnerability', 'keyphrase': 'input validation vulnerability', 'type': 'rootcause'}, {'id': 'rootcause:improper input validation', 'keyphrase': 'improper input validation', 'type': 'rootcause'}, {'id': 'impact:remote code execution', 'keyphrase': 'remote code execution', 'type': 'impact'}, {'id': 'vector:manipulating specific request parameter', 'keyphrase': 'manipulating specific request parameter', 'type': 'vector'}, {'id': 'attacker:actor', 'keyphrase': 'actor', 'type': 'attacker'}, {'id': 'product:End of Life (EOL) OVA based connect component', 'keyphrase': 'End of Life (EOL) OVA based connect component', 'type': 'product'}]}, 'similarity': np.float64(406.55167461808946)}, {'metadata': {'doc_id': '1284', 'name': 'Improper Validation of Specified Quantity in Input', 'source': 'sparse', 'original_content': 'The product receives input that is expected to specify a quantity (such as size or length), but it does not validate or incorrectly validates that the quantity has the required properties.', 'keyphrase_sources': [{'id': 'rootcause:input validation vulnerability', 'keyphrase': 'input validation vulnerability', 'type': 'rootcause'}, {'id': 'rootcause:improper input validation', 'keyphrase': 'improper input validation', 'type': 'rootcause'}]}, 'similarity': np.float64(389.94279386476575)}, {'metadata': {'doc_id': '918', 'name': 'Server-Side Request Forgery (SSRF)', 'source': 'sparse', 'original_content': 'The web server receives a URL or similar request from an upstream component and retrieves the contents of this URL, but it does not sufficiently ensure that the request is being sent to the expected destination.', 'keyphrase_sources': [{'id': 'rootcause:input validation vulnerability', 'keyphrase': 'input validation vulnerability', 'type': 'rootcause'}, {'id': 'rootcause:improper input validation', 'keyphrase': 'improper input validation', 'type': 'rootcause'}, {'id': 'impact:remote code execution', 'keyphrase': 'remote code execution', 'type': 'impact'}, {'id': 'vector:manipulating specific request parameter', 'keyphrase': 'manipulating specific request parameter', 'type': 'vector'}, {'id': 'attacker:actor', 'keyphrase': 'actor', 'type': 'attacker'}, {'id': 'product:End of Life (EOL) OVA based connect component', 'keyphrase': 'End of Life (EOL) OVA based connect component', 'type': 'product'}]}, 'similarity': np.float64(386.90525736365623)}, {'metadata': {'doc_id': '434', 'name': 'Unrestricted Upload of File with Dangerous Type', 'source': 'sparse', 'original_content': 'The product allows the upload or transfer of dangerous file types that are automatically processed within its environment.', 'keyphrase_sources': [{'id': 'product:End of Life (EOL) OVA based connect component', 'keyphrase': 'End of Life (EOL) OVA based connect component', 'type': 'product'}]}, 'similarity': np.float64(140.25421135007403)}, {'metadata': {'doc_id': '502', 'name': 'Deserialization of Untrusted Data', 'source': 'sparse', 'original_content': 'The product deserializes untrusted data without sufficiently ensuring that the resulting data will be valid.', 'keyphrase_sources': [{'id': 'vector:manipulating specific request parameter', 'keyphrase': 'manipulating specific request parameter', 'type': 'vector'}]}, 'similarity': np.float64(135.04352421518468)}, {'metadata': {'doc_id': '78', 'name': \"Improper Neutralization of Special Elements used in an OS Command ('OS Command Injection')\", 'source': 'sparse', 'original_content': 'The product constructs all or part of an OS command using externally-influenced input from an upstream component, but it does not neutralize or incorrectly neutralizes special elements that could modify the intended OS command when it is sent to a downstream component.', 'keyphrase_sources': [{'id': 'impact:remote code execution', 'keyphrase': 'remote code execution', 'type': 'impact'}, {'id': 'vector:manipulating specific request parameter', 'keyphrase': 'manipulating specific request parameter', 'type': 'vector'}]}, 'similarity': np.float64(129.466922575373)}, {'metadata': {'doc_id': '74', 'name': \"Improper Neutralization of Special Elements in Output Used by a Downstream Component ('Injection')\", 'source': 'sparse', 'original_content': 'The product constructs all or part of a command, data structure, or record using externally-influenced input from an upstream component, but it does not neutralize or incorrectly neutralizes special elements that could modify how it is parsed or interpreted when it is sent to a downstream component.', 'keyphrase_sources': [{'id': 'attacker:actor', 'keyphrase': 'actor', 'type': 'attacker'}]}, 'similarity': np.float64(125.71998124845348)}], identified_cwes={'analyzer': [], 'critic_additional': []})",
  "retrieval_results": {
    "has_multiple_keyphrases": true,
    "keyphrase_cwe_sets": {
      "rootcause:input validation vulnerability": {
        "keyphrase": "input validation vulnerability",
        "type": "rootcause",
        "cwes": [
          {
            "metadata": {
              "doc_id": "295",
              "name": "Improper Certificate Validation",
              "source": "sparse",
              "original_content": "The product does not validate, or incorrectly validates, a certificate.",
              "keyphrase_sources": [
                {
                  "id": "rootcause:input validation vulnerability",
                  "keyphrase": "input validation vulnerability",
                  "type": "rootcause"
                },
                {
                  "id": "rootcause:improper input validation",
                  "keyphrase": "improper input validation",
                  "type": "rootcause"
                },
                {
                  "id": "impact:remote code execution",
                  "keyphrase": "remote code execution",
                  "type": "impact"
                },
                {
                  "id": "vector:manipulating specific request parameter",
                  "keyphrase": "manipulating specific request parameter",
                  "type": "vector"
                },
                {
                  "id": "attacker:actor",
                  "keyphrase": "actor",
                  "type": "attacker"
                },
                {
                  "id": "product:End of Life (EOL) OVA based connect component",
                  "keyphrase": "End of Life (EOL) OVA based connect component",
                  "type": "product"
                }
              ]
            },
            "similarity": 409.03442452703405
          },
          {
            "metadata": {
              "doc_id": "20",
              "name": "Improper Input Validation",
              "source": "sparse",
              "original_content": "The product receives input or data, but it does\n        not validate or incorrectly validates that the input has the\n        properties that are required to process the data safely and\n        correctly.",
              "keyphrase_sources": [
                {
                  "id": "rootcause:input validation vulnerability",
                  "keyphrase": "input validation vulnerability",
                  "type": "rootcause"
                },
                {
                  "id": "rootcause:improper input validation",
                  "keyphrase": "improper input validation",
                  "type": "rootcause"
                },
                {
                  "id": "impact:remote code execution",
                  "keyphrase": "remote code execution",
                  "type": "impact"
                },
                {
                  "id": "attacker:actor",
                  "keyphrase": "actor",
                  "type": "attacker"
                },
                {
                  "id": "product:End of Life (EOL) OVA based connect component",
                  "keyphrase": "End of Life (EOL) OVA based connect component",
                  "type": "product"
                }
              ]
            },
            "similarity": 407.2695068346683
          },
          {
            "metadata": {
              "doc_id": "94",
              "name": "Improper Control of Generation of Code ('Code Injection')",
              "source": "sparse",
              "original_content": "The product constructs all or part of a code segment using externally-influenced input from an upstream component, but it does not neutralize or incorrectly neutralizes special elements that could modify the syntax or behavior of the intended code segment.",
              "keyphrase_sources": [
                {
                  "id": "rootcause:input validation vulnerability",
                  "keyphrase": "input validation vulnerability",
                  "type": "rootcause"
                },
                {
                  "id": "rootcause:improper input validation",
                  "keyphrase": "improper input validation",
                  "type": "rootcause"
                },
                {
                  "id": "impact:remote code execution",
                  "keyphrase": "remote code execution",
                  "type": "impact"
                },
                {
                  "id": "vector:manipulating specific request parameter",
                  "keyphrase": "manipulating specific request parameter",
                  "type": "vector"
                },
                {
                  "id": "attacker:actor",
                  "keyphrase": "actor",
                  "type": "attacker"
                },
                {
                  "id": "product:End of Life (EOL) OVA based connect component",
                  "keyphrase": "End of Life (EOL) OVA based connect component",
                  "type": "product"
                }
              ]
            },
            "similarity": 406.55167461808946
          },
          {
            "metadata": {
              "doc_id": "1284",
              "name": "Improper Validation of Specified Quantity in Input",
              "source": "sparse",
              "original_content": "The product receives input that is expected to specify a quantity (such as size or length), but it does not validate or incorrectly validates that the quantity has the required properties.",
              "keyphrase_sources": [
                {
                  "id": "rootcause:input validation vulnerability",
                  "keyphrase": "input validation vulnerability",
                  "type": "rootcause"
                },
                {
                  "id": "rootcause:improper input validation",
                  "keyphrase": "improper input validation",
                  "type": "rootcause"
                }
              ]
            },
            "similarity": 389.94279386476575
          },
          {
            "metadata": {
              "doc_id": "918",
              "name": "Server-Side Request Forgery (SSRF)",
              "source": "sparse",
              "original_content": "The web server receives a URL or similar request from an upstream component and retrieves the contents of this URL, but it does not sufficiently ensure that the request is being sent to the expected destination.",
              "keyphrase_sources": [
                {
                  "id": "rootcause:input validation vulnerability",
                  "keyphrase": "input validation vulnerability",
                  "type": "rootcause"
                },
                {
                  "id": "rootcause:improper input validation",
                  "keyphrase": "improper input validation",
                  "type": "rootcause"
                },
                {
                  "id": "impact:remote code execution",
                  "keyphrase": "remote code execution",
                  "type": "impact"
                },
                {
                  "id": "vector:manipulating specific request parameter",
                  "keyphrase": "manipulating specific request parameter",
                  "type": "vector"
                },
                {
                  "id": "attacker:actor",
                  "keyphrase": "actor",
                  "type": "attacker"
                },
                {
                  "id": "product:End of Life (EOL) OVA based connect component",
                  "keyphrase": "End of Life (EOL) OVA based connect component",
                  "type": "product"
                }
              ]
            },
            "similarity": 386.90525736365623
          }
        ]
      },
      "rootcause:improper input validation": {
        "keyphrase": "improper input validation",
        "type": "rootcause",
        "cwes": [
          {
            "metadata": {
              "doc_id": "20",
              "name": "Improper Input Validation",
              "source": "sparse",
              "original_content": "The product receives input or data, but it does\n        not validate or incorrectly validates that the input has the\n        properties that are required to process the data safely and\n        correctly."
            },
            "similarity": 412.02248535210276
          },
          {
            "metadata": {
              "doc_id": "295",
              "name": "Improper Certificate Validation",
              "source": "sparse",
              "original_content": "The product does not validate, or incorrectly validates, a certificate."
            },
            "similarity": 411.5284293230982
          },
          {
            "metadata": {
              "doc_id": "94",
              "name": "Improper Control of Generation of Code ('Code Injection')",
              "source": "sparse",
              "original_content": "The product constructs all or part of a code segment using externally-influenced input from an upstream component, but it does not neutralize or incorrectly neutralizes special elements that could modify the syntax or behavior of the intended code segment."
            },
            "similarity": 407.1390476184704
          },
          {
            "metadata": {
              "doc_id": "1284",
              "name": "Improper Validation of Specified Quantity in Input",
              "source": "sparse",
              "original_content": "The product receives input that is expected to specify a quantity (such as size or length), but it does not validate or incorrectly validates that the quantity has the required properties."
            },
            "similarity": 392.9977037290355
          },
          {
            "metadata": {
              "doc_id": "918",
              "name": "Server-Side Request Forgery (SSRF)",
              "source": "sparse",
              "original_content": "The web server receives a URL or similar request from an upstream component and retrieves the contents of this URL, but it does not sufficiently ensure that the request is being sent to the expected destination."
            },
            "similarity": 386.2050865249661
          }
        ]
      },
      "impact:remote code execution": {
        "keyphrase": "remote code execution",
        "type": "impact",
        "cwes": [
          {
            "metadata": {
              "doc_id": "94",
              "name": "Improper Control of Generation of Code ('Code Injection')",
              "source": "sparse",
              "original_content": "The product constructs all or part of a code segment using externally-influenced input from an upstream component, but it does not neutralize or incorrectly neutralizes special elements that could modify the syntax or behavior of the intended code segment."
            },
            "similarity": 138.62969170613877
          },
          {
            "metadata": {
              "doc_id": "295",
              "name": "Improper Certificate Validation",
              "source": "sparse",
              "original_content": "The product does not validate, or incorrectly validates, a certificate."
            },
            "similarity": 134.515354903124
          },
          {
            "metadata": {
              "doc_id": "20",
              "name": "Improper Input Validation",
              "source": "sparse",
              "original_content": "The product receives input or data, but it does\n        not validate or incorrectly validates that the input has the\n        properties that are required to process the data safely and\n        correctly."
            },
            "similarity": 130.86680087443176
          },
          {
            "metadata": {
              "doc_id": "918",
              "name": "Server-Side Request Forgery (SSRF)",
              "source": "sparse",
              "original_content": "The web server receives a URL or similar request from an upstream component and retrieves the contents of this URL, but it does not sufficiently ensure that the request is being sent to the expected destination."
            },
            "similarity": 129.68251091384076
          },
          {
            "metadata": {
              "doc_id": "78",
              "name": "Improper Neutralization of Special Elements used in an OS Command ('OS Command Injection')",
              "source": "sparse",
              "original_content": "The product constructs all or part of an OS command using externally-influenced input from an upstream component, but it does not neutralize or incorrectly neutralizes special elements that could modify the intended OS command when it is sent to a downstream component.",
              "keyphrase_sources": [
                {
                  "id": "impact:remote code execution",
                  "keyphrase": "remote code execution",
                  "type": "impact"
                },
                {
                  "id": "vector:manipulating specific request parameter",
                  "keyphrase": "manipulating specific request parameter",
                  "type": "vector"
                }
              ]
            },
            "similarity": 129.466922575373
          }
        ]
      },
      "vector:manipulating specific request parameter": {
        "keyphrase": "manipulating specific request parameter",
        "type": "vector",
        "cwes": [
          {
            "metadata": {
              "doc_id": "918",
              "name": "Server-Side Request Forgery (SSRF)",
              "source": "sparse",
              "original_content": "The web server receives a URL or similar request from an upstream component and retrieves the contents of this URL, but it does not sufficiently ensure that the request is being sent to the expected destination."
            },
            "similarity": 141.40600318255653
          },
          {
            "metadata": {
              "doc_id": "94",
              "name": "Improper Control of Generation of Code ('Code Injection')",
              "source": "sparse",
              "original_content": "The product constructs all or part of a code segment using externally-influenced input from an upstream component, but it does not neutralize or incorrectly neutralizes special elements that could modify the syntax or behavior of the intended code segment."
            },
            "similarity": 140.1098406471574
          },
          {
            "metadata": {
              "doc_id": "78",
              "name": "Improper Neutralization of Special Elements used in an OS Command ('OS Command Injection')",
              "source": "sparse",
              "original_content": "The product constructs all or part of an OS command using externally-influenced input from an upstream component, but it does not neutralize or incorrectly neutralizes special elements that could modify the intended OS command when it is sent to a downstream component."
            },
            "similarity": 137.8314820701584
          },
          {
            "metadata": {
              "doc_id": "295",
              "name": "Improper Certificate Validation",
              "source": "sparse",
              "original_content": "The product does not validate, or incorrectly validates, a certificate."
            },
            "similarity": 136.03904947548577
          },
          {
            "metadata": {
              "doc_id": "502",
              "name": "Deserialization of Untrusted Data",
              "source": "sparse",
              "original_content": "The product deserializes untrusted data without sufficiently ensuring that the resulting data will be valid.",
              "keyphrase_sources": [
                {
                  "id": "vector:manipulating specific request parameter",
                  "keyphrase": "manipulating specific request parameter",
                  "type": "vector"
                }
              ]
            },
            "similarity": 135.04352421518468
          }
        ]
      },
      "attacker:actor": {
        "keyphrase": "actor",
        "type": "attacker",
        "cwes": [
          {
            "metadata": {
              "doc_id": "295",
              "name": "Improper Certificate Validation",
              "source": "sparse",
              "original_content": "The product does not validate, or incorrectly validates, a certificate."
            },
            "similarity": 134.36440218434208
          },
          {
            "metadata": {
              "doc_id": "94",
              "name": "Improper Control of Generation of Code ('Code Injection')",
              "source": "sparse",
              "original_content": "The product constructs all or part of a code segment using externally-influenced input from an upstream component, but it does not neutralize or incorrectly neutralizes special elements that could modify the syntax or behavior of the intended code segment."
            },
            "similarity": 131.17270490691078
          },
          {
            "metadata": {
              "doc_id": "918",
              "name": "Server-Side Request Forgery (SSRF)",
              "source": "sparse",
              "original_content": "The web server receives a URL or similar request from an upstream component and retrieves the contents of this URL, but it does not sufficiently ensure that the request is being sent to the expected destination."
            },
            "similarity": 130.03416239725186
          },
          {
            "metadata": {
              "doc_id": "74",
              "name": "Improper Neutralization of Special Elements in Output Used by a Downstream Component ('Injection')",
              "source": "sparse",
              "original_content": "The product constructs all or part of a command, data structure, or record using externally-influenced input from an upstream component, but it does not neutralize or incorrectly neutralizes special elements that could modify how it is parsed or interpreted when it is sent to a downstream component.",
              "keyphrase_sources": [
                {
                  "id": "attacker:actor",
                  "keyphrase": "actor",
                  "type": "attacker"
                }
              ]
            },
            "similarity": 125.71998124845348
          },
          {
            "metadata": {
              "doc_id": "20",
              "name": "Improper Input Validation",
              "source": "sparse",
              "original_content": "The product receives input or data, but it does\n        not validate or incorrectly validates that the input has the\n        properties that are required to process the data safely and\n        correctly."
            },
            "similarity": 124.15426448182924
          }
        ]
      },
      "product:End of Life (EOL) OVA based connect component": {
        "keyphrase": "End of Life (EOL) OVA based connect component",
        "type": "product",
        "cwes": [
          {
            "metadata": {
              "doc_id": "295",
              "name": "Improper Certificate Validation",
              "source": "sparse",
              "original_content": "The product does not validate, or incorrectly validates, a certificate."
            },
            "similarity": 159.35178959545564
          },
          {
            "metadata": {
              "doc_id": "94",
              "name": "Improper Control of Generation of Code ('Code Injection')",
              "source": "sparse",
              "original_content": "The product constructs all or part of a code segment using externally-influenced input from an upstream component, but it does not neutralize or incorrectly neutralizes special elements that could modify the syntax or behavior of the intended code segment."
            },
            "similarity": 157.90538461382312
          },
          {
            "metadata": {
              "doc_id": "918",
              "name": "Server-Side Request Forgery (SSRF)",
              "source": "sparse",
              "original_content": "The web server receives a URL or similar request from an upstream component and retrieves the contents of this URL, but it does not sufficiently ensure that the request is being sent to the expected destination."
            },
            "similarity": 147.34998367692305
          },
          {
            "metadata": {
              "doc_id": "20",
              "name": "Improper Input Validation",
              "source": "sparse",
              "original_content": "The product receives input or data, but it does\n        not validate or incorrectly validates that the input has the\n        properties that are required to process the data safely and\n        correctly."
            },
            "similarity": 141.8122942806842
          },
          {
            "metadata": {
              "doc_id": "434",
              "name": "Unrestricted Upload of File with Dangerous Type",
              "source": "sparse",
              "original_content": "The product allows the upload or transfer of dangerous file types that are automatically processed within its environment.",
              "keyphrase_sources": [
                {
                  "id": "product:End of Life (EOL) OVA based connect component",
                  "keyphrase": "End of Life (EOL) OVA based connect component",
                  "type": "product"
                }
              ]
            },
            "similarity": 140.25421135007403
          }
        ]
      }
    },
    "keyphrase_mapping": {
      "295": [
        {
          "id": "rootcause:input validation vulnerability",
          "keyphrase": "input validation vulnerability",
          "type": "rootcause"
        },
        {
          "id": "rootcause:improper input validation",
          "keyphrase": "improper input validation",
          "type": "rootcause"
        },
        {
          "id": "impact:remote code execution",
          "keyphrase": "remote code execution",
          "type": "impact"
        },
        {
          "id": "vector:manipulating specific request parameter",
          "keyphrase": "manipulating specific request parameter",
          "type": "vector"
        },
        {
          "id": "attacker:actor",
          "keyphrase": "actor",
          "type": "attacker"
        },
        {
          "id": "product:End of Life (EOL) OVA based connect component",
          "keyphrase": "End of Life (EOL) OVA based connect component",
          "type": "product"
        }
      ],
      "20": [
        {
          "id": "rootcause:input validation vulnerability",
          "keyphrase": "input validation vulnerability",
          "type": "rootcause"
        },
        {
          "id": "rootcause:improper input validation",
          "keyphrase": "improper input validation",
          "type": "rootcause"
        },
        {
          "id": "impact:remote code execution",
          "keyphrase": "remote code execution",
          "type": "impact"
        },
        {
          "id": "attacker:actor",
          "keyphrase": "actor",
          "type": "attacker"
        },
        {
          "id": "product:End of Life (EOL) OVA based connect component",
          "keyphrase": "End of Life (EOL) OVA based connect component",
          "type": "product"
        }
      ],
      "94": [
        {
          "id": "rootcause:input validation vulnerability",
          "keyphrase": "input validation vulnerability",
          "type": "rootcause"
        },
        {
          "id": "rootcause:improper input validation",
          "keyphrase": "improper input validation",
          "type": "rootcause"
        },
        {
          "id": "impact:remote code execution",
          "keyphrase": "remote code execution",
          "type": "impact"
        },
        {
          "id": "vector:manipulating specific request parameter",
          "keyphrase": "manipulating specific request parameter",
          "type": "vector"
        },
        {
          "id": "attacker:actor",
          "keyphrase": "actor",
          "type": "attacker"
        },
        {
          "id": "product:End of Life (EOL) OVA based connect component",
          "keyphrase": "End of Life (EOL) OVA based connect component",
          "type": "product"
        }
      ],
      "1284": [
        {
          "id": "rootcause:input validation vulnerability",
          "keyphrase": "input validation vulnerability",
          "type": "rootcause"
        },
        {
          "id": "rootcause:improper input validation",
          "keyphrase": "improper input validation",
          "type": "rootcause"
        }
      ],
      "918": [
        {
          "id": "rootcause:input validation vulnerability",
          "keyphrase": "input validation vulnerability",
          "type": "rootcause"
        },
        {
          "id": "rootcause:improper input validation",
          "keyphrase": "improper input validation",
          "type": "rootcause"
        },
        {
          "id": "impact:remote code execution",
          "keyphrase": "remote code execution",
          "type": "impact"
        },
        {
          "id": "vector:manipulating specific request parameter",
          "keyphrase": "manipulating specific request parameter",
          "type": "vector"
        },
        {
          "id": "attacker:actor",
          "keyphrase": "actor",
          "type": "attacker"
        },
        {
          "id": "product:End of Life (EOL) OVA based connect component",
          "keyphrase": "End of Life (EOL) OVA based connect component",
          "type": "product"
        }
      ],
      "78": [
        {
          "id": "impact:remote code execution",
          "keyphrase": "remote code execution",
          "type": "impact"
        },
        {
          "id": "vector:manipulating specific request parameter",
          "keyphrase": "manipulating specific request parameter",
          "type": "vector"
        }
      ],
      "502": [
        {
          "id": "vector:manipulating specific request parameter",
          "keyphrase": "manipulating specific request parameter",
          "type": "vector"
        }
      ],
      "74": [
        {
          "id": "attacker:actor",
          "keyphrase": "actor",
          "type": "attacker"
        }
      ],
      "434": [
        {
          "id": "product:End of Life (EOL) OVA based connect component",
          "keyphrase": "End of Life (EOL) OVA based connect component",
          "type": "product"
        }
      ]
    },
    "relevant_cwes": [
      {
        "metadata": {
          "doc_id": "295",
          "name": "Improper Certificate Validation",
          "source": "sparse",
          "original_content": "The product does not validate, or incorrectly validates, a certificate.",
          "keyphrase_sources": [
            {
              "id": "rootcause:input validation vulnerability",
              "keyphrase": "input validation vulnerability",
              "type": "rootcause"
            },
            {
              "id": "rootcause:improper input validation",
              "keyphrase": "improper input validation",
              "type": "rootcause"
            },
            {
              "id": "impact:remote code execution",
              "keyphrase": "remote code execution",
              "type": "impact"
            },
            {
              "id": "vector:manipulating specific request parameter",
              "keyphrase": "manipulating specific request parameter",
              "type": "vector"
            },
            {
              "id": "attacker:actor",
              "keyphrase": "actor",
              "type": "attacker"
            },
            {
              "id": "product:End of Life (EOL) OVA based connect component",
              "keyphrase": "End of Life (EOL) OVA based connect component",
              "type": "product"
            }
          ]
        },
        "similarity": 409.03442452703405
      },
      {
        "metadata": {
          "doc_id": "20",
          "name": "Improper Input Validation",
          "source": "sparse",
          "original_content": "The product receives input or data, but it does\n        not validate or incorrectly validates that the input has the\n        properties that are required to process the data safely and\n        correctly.",
          "keyphrase_sources": [
            {
              "id": "rootcause:input validation vulnerability",
              "keyphrase": "input validation vulnerability",
              "type": "rootcause"
            },
            {
              "id": "rootcause:improper input validation",
              "keyphrase": "improper input validation",
              "type": "rootcause"
            },
            {
              "id": "impact:remote code execution",
              "keyphrase": "remote code execution",
              "type": "impact"
            },
            {
              "id": "attacker:actor",
              "keyphrase": "actor",
              "type": "attacker"
            },
            {
              "id": "product:End of Life (EOL) OVA based connect component",
              "keyphrase": "End of Life (EOL) OVA based connect component",
              "type": "product"
            }
          ]
        },
        "similarity": 407.2695068346683
      },
      {
        "metadata": {
          "doc_id": "94",
          "name": "Improper Control of Generation of Code ('Code Injection')",
          "source": "sparse",
          "original_content": "The product constructs all or part of a code segment using externally-influenced input from an upstream component, but it does not neutralize or incorrectly neutralizes special elements that could modify the syntax or behavior of the intended code segment.",
          "keyphrase_sources": [
            {
              "id": "rootcause:input validation vulnerability",
              "keyphrase": "input validation vulnerability",
              "type": "rootcause"
            },
            {
              "id": "rootcause:improper input validation",
              "keyphrase": "improper input validation",
              "type": "rootcause"
            },
            {
              "id": "impact:remote code execution",
              "keyphrase": "remote code execution",
              "type": "impact"
            },
            {
              "id": "vector:manipulating specific request parameter",
              "keyphrase": "manipulating specific request parameter",
              "type": "vector"
            },
            {
              "id": "attacker:actor",
              "keyphrase": "actor",
              "type": "attacker"
            },
            {
              "id": "product:End of Life (EOL) OVA based connect component",
              "keyphrase": "End of Life (EOL) OVA based connect component",
              "type": "product"
            }
          ]
        },
        "similarity": 406.55167461808946
      },
      {
        "metadata": {
          "doc_id": "1284",
          "name": "Improper Validation of Specified Quantity in Input",
          "source": "sparse",
          "original_content": "The product receives input that is expected to specify a quantity (such as size or length), but it does not validate or incorrectly validates that the quantity has the required properties.",
          "keyphrase_sources": [
            {
              "id": "rootcause:input validation vulnerability",
              "keyphrase": "input validation vulnerability",
              "type": "rootcause"
            },
            {
              "id": "rootcause:improper input validation",
              "keyphrase": "improper input validation",
              "type": "rootcause"
            }
          ]
        },
        "similarity": 389.94279386476575
      },
      {
        "metadata": {
          "doc_id": "918",
          "name": "Server-Side Request Forgery (SSRF)",
          "source": "sparse",
          "original_content": "The web server receives a URL or similar request from an upstream component and retrieves the contents of this URL, but it does not sufficiently ensure that the request is being sent to the expected destination.",
          "keyphrase_sources": [
            {
              "id": "rootcause:input validation vulnerability",
              "keyphrase": "input validation vulnerability",
              "type": "rootcause"
            },
            {
              "id": "rootcause:improper input validation",
              "keyphrase": "improper input validation",
              "type": "rootcause"
            },
            {
              "id": "impact:remote code execution",
              "keyphrase": "remote code execution",
              "type": "impact"
            },
            {
              "id": "vector:manipulating specific request parameter",
              "keyphrase": "manipulating specific request parameter",
              "type": "vector"
            },
            {
              "id": "attacker:actor",
              "keyphrase": "actor",
              "type": "attacker"
            },
            {
              "id": "product:End of Life (EOL) OVA based connect component",
              "keyphrase": "End of Life (EOL) OVA based connect component",
              "type": "product"
            }
          ]
        },
        "similarity": 386.90525736365623
      },
      {
        "metadata": {
          "doc_id": "434",
          "name": "Unrestricted Upload of File with Dangerous Type",
          "source": "sparse",
          "original_content": "The product allows the upload or transfer of dangerous file types that are automatically processed within its environment.",
          "keyphrase_sources": [
            {
              "id": "product:End of Life (EOL) OVA based connect component",
              "keyphrase": "End of Life (EOL) OVA based connect component",
              "type": "product"
            }
          ]
        },
        "similarity": 140.25421135007403
      },
      {
        "metadata": {
          "doc_id": "502",
          "name": "Deserialization of Untrusted Data",
          "source": "sparse",
          "original_content": "The product deserializes untrusted data without sufficiently ensuring that the resulting data will be valid.",
          "keyphrase_sources": [
            {
              "id": "vector:manipulating specific request parameter",
              "keyphrase": "manipulating specific request parameter",
              "type": "vector"
            }
          ]
        },
        "similarity": 135.04352421518468
      },
      {
        "metadata": {
          "doc_id": "78",
          "name": "Improper Neutralization of Special Elements used in an OS Command ('OS Command Injection')",
          "source": "sparse",
          "original_content": "The product constructs all or part of an OS command using externally-influenced input from an upstream component, but it does not neutralize or incorrectly neutralizes special elements that could modify the intended OS command when it is sent to a downstream component.",
          "keyphrase_sources": [
            {
              "id": "impact:remote code execution",
              "keyphrase": "remote code execution",
              "type": "impact"
            },
            {
              "id": "vector:manipulating specific request parameter",
              "keyphrase": "manipulating specific request parameter",
              "type": "vector"
            }
          ]
        },
        "similarity": 129.466922575373
      },
      {
        "metadata": {
          "doc_id": "74",
          "name": "Improper Neutralization of Special Elements in Output Used by a Downstream Component ('Injection')",
          "source": "sparse",
          "original_content": "The product constructs all or part of a command, data structure, or record using externally-influenced input from an upstream component, but it does not neutralize or incorrectly neutralizes special elements that could modify how it is parsed or interpreted when it is sent to a downstream component.",
          "keyphrase_sources": [
            {
              "id": "attacker:actor",
              "keyphrase": "actor",
              "type": "attacker"
            }
          ]
        },
        "similarity": 125.71998124845348
      }
    ],
    "enhanced_query": "# Vulnerability Description\n\n    An improper **input validation vulnerability** is identified in the End of Life (EOL) OVA based connect component which is deployed for installation purposes in the customer internal network. This EOL component was deprecated in September 2023 with end of support extended till January 2024. Under certain circumstances, an actor can manipulate a specific request parameter and inject code execution payload which could lead to a remote code execution on the infrastructure hosting this component.\n\n    # Keyphrase-Specific CWE Analysis\n    This vulnerability contains multiple keyphrases that may map to different CWEs. \n    Please analyze each keyphrase separately and determine the most appropriate CWE(s) for each.\n\n    ## ROOTCAUSE: 'input validation vulnerability'\n\nRelevant CWEs for this ROOTCAUSE:\n\n### 1. CWE-295: Improper Certificate Validation (Score: 409.03)\n\nThe product does not validate, or incorrectly validates, a certificate....\n\n### 2. CWE-20: Improper Input Validation (Score: 407.27)\n\nThe product receives input or data, but it does\n        not validate or incorrectly validates that the input has the\n        properties that are required to process the data safely and\n        correctly....\n\n### 3. CWE-94: Improper Control of Generation of Code ('Code Injection') (Score: 406.55)\n\nThe product constructs all or part of a code segment using externally-influenced input from an upstream component, but it does not neutralize or incorrectly neutralizes special elements that could modify the syntax or behavior of the intended code segment....\n\n### 4. CWE-1284: Improper Validation of Specified Quantity in Input (Score: 389.94)\n\nThe product receives input that is expected to specify a quantity (such as size or length), but it does not validate or incorrectly validates that the quantity has the required properties....\n\n### 5. CWE-918: Server-Side Request Forgery (SSRF) (Score: 386.91)\n\nThe web server receives a URL or similar request from an upstream component and retrieves the contents of this URL, but it does not sufficiently ensure that the request is being sent to the expected destination....\n\n## ROOTCAUSE: 'improper input validation'\n\nRelevant CWEs for this ROOTCAUSE:\n\n### 1. CWE-295: Improper Certificate Validation (Score: 409.03)\n\nThe product does not validate, or incorrectly validates, a certificate....\n\n### 2. CWE-20: Improper Input Validation (Score: 407.27)\n\nThe product receives input or data, but it does\n        not validate or incorrectly validates that the input has the\n        properties that are required to process the data safely and\n        correctly....\n\n### 3. CWE-94: Improper Control of Generation of Code ('Code Injection') (Score: 406.55)\n\nThe product constructs all or part of a code segment using externally-influenced input from an upstream component, but it does not neutralize or incorrectly neutralizes special elements that could modify the syntax or behavior of the intended code segment....\n\n### 4. CWE-1284: Improper Validation of Specified Quantity in Input (Score: 389.94)\n\nThe product receives input that is expected to specify a quantity (such as size or length), but it does not validate or incorrectly validates that the quantity has the required properties....\n\n### 5. CWE-918: Server-Side Request Forgery (SSRF) (Score: 386.91)\n\nThe web server receives a URL or similar request from an upstream component and retrieves the contents of this URL, but it does not sufficiently ensure that the request is being sent to the expected destination....\n\n## IMPACT: 'remote code execution'\n\nRelevant CWEs for this IMPACT:\n\n### 1. CWE-295: Improper Certificate Validation (Score: 409.03)\n\nThe product does not validate, or incorrectly validates, a certificate....\n\n### 2. CWE-20: Improper Input Validation (Score: 407.27)\n\nThe product receives input or data, but it does\n        not validate or incorrectly validates that the input has the\n        properties that are required to process the data safely and\n        correctly....\n\n### 3. CWE-94: Improper Control of Generation of Code ('Code Injection') (Score: 406.55)\n\nThe product constructs all or part of a code segment using externally-influenced input from an upstream component, but it does not neutralize or incorrectly neutralizes special elements that could modify the syntax or behavior of the intended code segment....\n\n### 4. CWE-918: Server-Side Request Forgery (SSRF) (Score: 386.91)\n\nThe web server receives a URL or similar request from an upstream component and retrieves the contents of this URL, but it does not sufficiently ensure that the request is being sent to the expected destination....\n\n### 5. CWE-78: Improper Neutralization of Special Elements used in an OS Command ('OS Command Injection') (Score: 129.47)\n\nThe product constructs all or part of an OS command using externally-influenced input from an upstream component, but it does not neutralize or incorrectly neutralizes special elements that could modify the intended OS command when it is sent to a downstream component....\n\n## VECTOR: 'manipulating specific request parameter'\n\nRelevant CWEs for this VECTOR:\n\n### 1. CWE-295: Improper Certificate Validation (Score: 409.03)\n\nThe product does not validate, or incorrectly validates, a certificate....\n\n### 2. CWE-94: Improper Control of Generation of Code ('Code Injection') (Score: 406.55)\n\nThe product constructs all or part of a code segment using externally-influenced input from an upstream component, but it does not neutralize or incorrectly neutralizes special elements that could modify the syntax or behavior of the intended code segment....\n\n### 3. CWE-918: Server-Side Request Forgery (SSRF) (Score: 386.91)\n\nThe web server receives a URL or similar request from an upstream component and retrieves the contents of this URL, but it does not sufficiently ensure that the request is being sent to the expected destination....\n\n### 4. CWE-502: Deserialization of Untrusted Data (Score: 135.04)\n\nThe product deserializes untrusted data without sufficiently ensuring that the resulting data will be valid....\n\n### 5. CWE-78: Improper Neutralization of Special Elements used in an OS Command ('OS Command Injection') (Score: 129.47)\n\nThe product constructs all or part of an OS command using externally-influenced input from an upstream component, but it does not neutralize or incorrectly neutralizes special elements that could modify the intended OS command when it is sent to a downstream component....\n\n## ATTACKER: 'actor'\n\nRelevant CWEs for this ATTACKER:\n\n### 1. CWE-295: Improper Certificate Validation (Score: 409.03)\n\nThe product does not validate, or incorrectly validates, a certificate....\n\n### 2. CWE-20: Improper Input Validation (Score: 407.27)\n\nThe product receives input or data, but it does\n        not validate or incorrectly validates that the input has the\n        properties that are required to process the data safely and\n        correctly....\n\n### 3. CWE-94: Improper Control of Generation of Code ('Code Injection') (Score: 406.55)\n\nThe product constructs all or part of a code segment using externally-influenced input from an upstream component, but it does not neutralize or incorrectly neutralizes special elements that could modify the syntax or behavior of the intended code segment....\n\n### 4. CWE-918: Server-Side Request Forgery (SSRF) (Score: 386.91)\n\nThe web server receives a URL or similar request from an upstream component and retrieves the contents of this URL, but it does not sufficiently ensure that the request is being sent to the expected destination....\n\n### 5. CWE-74: Improper Neutralization of Special Elements in Output Used by a Downstream Component ('Injection') (Score: 125.72)\n\nThe product constructs all or part of a command, data structure, or record using externally-influenced input from an upstream component, but it does not neutralize or incorrectly neutralizes special elements that could modify how it is parsed or interpreted when it is sent to a downstream component....\n\n## PRODUCT: 'End of Life (EOL) OVA based connect component'\n\nRelevant CWEs for this PRODUCT:\n\n### 1. CWE-295: Improper Certificate Validation (Score: 409.03)\n\nThe product does not validate, or incorrectly validates, a certificate....\n\n### 2. CWE-20: Improper Input Validation (Score: 407.27)\n\nThe product receives input or data, but it does\n        not validate or incorrectly validates that the input has the\n        properties that are required to process the data safely and\n        correctly....\n\n### 3. CWE-94: Improper Control of Generation of Code ('Code Injection') (Score: 406.55)\n\nThe product constructs all or part of a code segment using externally-influenced input from an upstream component, but it does not neutralize or incorrectly neutralizes special elements that could modify the syntax or behavior of the intended code segment....\n\n### 4. CWE-918: Server-Side Request Forgery (SSRF) (Score: 386.91)\n\nThe web server receives a URL or similar request from an upstream component and retrieves the contents of this URL, but it does not sufficiently ensure that the request is being sent to the expected destination....\n\n### 5. CWE-434: Unrestricted Upload of File with Dangerous Type (Score: 140.25)\n\nThe product allows the upload or transfer of dangerous file types that are automatically processed within its environment....\n\n\n    # Analysis Instructions\n    1. For each keyphrase, identify the most appropriate CWE(s) that represent the weakness.\n    2. Consider how the different keyphrases might relate to each other in the vulnerability chain.\n    3. Provide a final determination of primary CWE(s) and any secondary CWEs.\n    4. Format your response using the standard analysis template.\n\n    Please analyze how these different weaknesses interact and provide a comprehensive CWE classification.\n    "
  },
  "retrieval_time": 1.3090057373046875
}