{
  "vulnerability_info": "VulnerabilityInfo(cve_id='CVE-2025-0514', description='Improper **Input Validation vulnerability** in The Document Foundation LibreOffice allows Windows Executable hyperlink targets to be executed unconditionally on activation.This issue affects LibreOffice from 24.8 before < 24.8.5.', key_phrases={'rootcause': ['Input Validation vulnerability', 'Improper Input Validation'], 'weakness': '', 'impact': 'Windows Executable hyperlink targets to be executed unconditionally on activation', 'vector': '', 'attacker': '', 'product': 'LibreOffice', 'version': '24.8 before < 24.8.5', 'component': ''}, reference_content=\"## Analysis of CVE-2025-0514 based on provided content:\\n\\n**1. Verification:**\\n\\nThe content directly addresses CVE-2025-0514, providing a detailed description of the vulnerability.\\n\\n**2. Extracted Information:**\\n\\n*   **Root cause of vulnerability:** LibreOffice has a feature to activate hyperlinks with CTRL+click, which uses the system's ShellExecute function under Windows. A mechanism to block paths to executable targets was bypassed.\\n*   **Weaknesses/vulnerabilities present:**  A bypass in the mechanism designed to prevent launching executables via hyperlinks. Specifically, non-file URLs could be interpreted as Windows file paths by ShellExecute.\\n*   **Impact of exploitation:**  Allows execution of arbitrary executables on the victim's system via a crafted hyperlink.\\n*   **Attack vectors:**  A malicious document containing a crafted hyperlink that, when activated (CTRL+click), triggers the execution of an executable file.\\n*   **Required attacker capabilities/position:** An attacker needs to create a malicious document with a specially crafted hyperlink and deliver it to a user.\\n*   **Mitigation or fix:** Upgrade to LibreOffice version 24.8.5 or later, which includes a fix to block the circumvention.\\n\\n**3. Detail compared to official CVE description:**\\n\\nThe provided content offers significantly more detail than a typical CVE description. It explains *how* the vulnerability works (the bypass of the blocking mechanism), the specific component involved (ShellExecute), and the context of the vulnerability (CTRL+click hyperlink activation). It also credits the researchers who found and fixed the issue.\\n\\n**4. Response:**\\n\\nThe content is directly relevant to CVE-2025-0514 and provides a comprehensive explanation of the vulnerability.\", similar_info={'cwe_distribution': {}, 'cwe_consensus': '', 'similarity_stats': {'thresholds': [], 'total_samples_by_threshold': {}, 'top_cwes_by_threshold': {}}}, similarity_summary=SimilarityInsight(consensus_cwe='', top_cwes=[], confidence_levels={}, total_samples=0), analysis='', analysis_with_relationships='', criticism='', resolution='', relevant_cwes=[{'metadata': {'doc_id': '1204', 'name': 'Generation of Weak Initialization Vector (IV)', 'source': 'sparse', 'original_content': 'The product uses a cryptographic primitive that uses an Initialization\\n\\t\\t\\tVector (IV), but the product does not generate IVs that are\\n\\t\\t\\tsufficiently unpredictable or unique according to the expected\\n\\t\\t\\tcryptographic requirements for that primitive.\\n\\t\\t\\t', 'keyphrase_sources': [{'id': 'rootcause:Input Validation vulnerability', 'keyphrase': 'Input Validation vulnerability', 'type': 'rootcause'}, {'id': 'rootcause:Improper Input Validation', 'keyphrase': 'Improper Input Validation', 'type': 'rootcause'}, {'id': 'impact:Windows Executable hyperlink targets to be executed unconditionally on activation', 'keyphrase': 'Windows Executable hyperlink targets to be executed unconditionally on activation', 'type': 'impact'}, {'id': 'product:LibreOffice', 'keyphrase': 'LibreOffice', 'type': 'product'}, {'id': 'version:24.8 before < 24.8.5', 'keyphrase': '24.8 before < 24.8.5', 'type': 'version'}]}, 'similarity': np.float64(188.4566085506798)}, {'metadata': {'doc_id': '116', 'name': 'Improper Encoding or Escaping of Output', 'source': 'sparse', 'original_content': 'The product prepares a structured message for communication with another component, but encoding or escaping of the data is either missing or done incorrectly. As a result, the intended structure of the message is not preserved.', 'keyphrase_sources': [{'id': 'rootcause:Input Validation vulnerability', 'keyphrase': 'Input Validation vulnerability', 'type': 'rootcause'}, {'id': 'rootcause:Improper Input Validation', 'keyphrase': 'Improper Input Validation', 'type': 'rootcause'}, {'id': 'product:LibreOffice', 'keyphrase': 'LibreOffice', 'type': 'product'}]}, 'similarity': np.float64(169.4371587591231)}, {'metadata': {'doc_id': '20', 'name': 'Improper Input Validation', 'source': 'sparse', 'original_content': 'The product receives input or data, but it does\\n        not validate or incorrectly validates that the input has the\\n        properties that are required to process the data safely and\\n        correctly.', 'keyphrase_sources': [{'id': 'rootcause:Input Validation vulnerability', 'keyphrase': 'Input Validation vulnerability', 'type': 'rootcause'}, {'id': 'rootcause:Improper Input Validation', 'keyphrase': 'Improper Input Validation', 'type': 'rootcause'}]}, 'similarity': np.float64(167.52864609113797)}, {'metadata': {'doc_id': '494', 'name': 'Download of Code Without Integrity Check', 'source': 'sparse', 'original_content': 'The product downloads source code or an executable from a remote location and executes the code without sufficiently verifying the origin and integrity of the code.', 'keyphrase_sources': [{'id': 'rootcause:Input Validation vulnerability', 'keyphrase': 'Input Validation vulnerability', 'type': 'rootcause'}, {'id': 'rootcause:Improper Input Validation', 'keyphrase': 'Improper Input Validation', 'type': 'rootcause'}, {'id': 'impact:Windows Executable hyperlink targets to be executed unconditionally on activation', 'keyphrase': 'Windows Executable hyperlink targets to be executed unconditionally on activation', 'type': 'impact'}, {'id': 'product:LibreOffice', 'keyphrase': 'LibreOffice', 'type': 'product'}]}, 'similarity': np.float64(159.2941013104757)}, {'metadata': {'doc_id': '1285', 'name': 'Improper Validation of Specified Index, Position, or Offset in Input', 'source': 'sparse', 'original_content': 'The product receives input that is expected to specify an index, position, or offset into an indexable resource such as a buffer or file, but it does not validate or incorrectly validates that the specified index/position/offset has the required properties.', 'keyphrase_sources': [{'id': 'rootcause:Input Validation vulnerability', 'keyphrase': 'Input Validation vulnerability', 'type': 'rootcause'}, {'id': 'rootcause:Improper Input Validation', 'keyphrase': 'Improper Input Validation', 'type': 'rootcause'}]}, 'similarity': np.float64(158.20437428762946)}, {'metadata': {'doc_id': '183', 'name': 'Permissive List of Allowed Inputs', 'source': 'sparse', 'original_content': 'The product implements a protection mechanism that relies on a list of inputs (or properties of inputs) that are explicitly allowed by policy because the inputs are assumed to be safe, but the list is too permissive - that is, it allows an input that is unsafe, leading to resultant weaknesses.', 'keyphrase_sources': [{'id': 'impact:Windows Executable hyperlink targets to be executed unconditionally on activation', 'keyphrase': 'Windows Executable hyperlink targets to be executed unconditionally on activation', 'type': 'impact'}]}, 'similarity': np.float64(78.80247405832327)}, {'metadata': {'doc_id': '732', 'name': 'Incorrect Permission Assignment for Critical Resource', 'source': 'sparse', 'original_content': 'The product specifies permissions for a security-critical resource in a way that allows that resource to be read or modified by unintended actors.', 'keyphrase_sources': [{'id': 'impact:Windows Executable hyperlink targets to be executed unconditionally on activation', 'keyphrase': 'Windows Executable hyperlink targets to be executed unconditionally on activation', 'type': 'impact'}]}, 'similarity': np.float64(78.72236214882524)}, {'metadata': {'doc_id': '426', 'name': 'Untrusted Search Path', 'source': 'sparse', 'original_content': \"The product searches for critical resources using an externally-supplied search path that can point to resources that are not under the product's direct control.\", 'keyphrase_sources': [{'id': 'impact:Windows Executable hyperlink targets to be executed unconditionally on activation', 'keyphrase': 'Windows Executable hyperlink targets to be executed unconditionally on activation', 'type': 'impact'}]}, 'similarity': np.float64(76.39374345201969)}, {'metadata': {'doc_id': '172', 'name': 'Encoding Error', 'source': 'sparse', 'original_content': 'The product does not properly encode or decode the data, resulting in unexpected values.', 'keyphrase_sources': [{'id': 'product:LibreOffice', 'keyphrase': 'LibreOffice', 'type': 'product'}]}, 'similarity': np.float64(73.34542643505479)}, {'metadata': {'doc_id': '73', 'name': 'External Control of File Name or Path', 'source': 'sparse', 'original_content': 'The product allows user input to control or influence paths or file names that are used in filesystem operations.', 'keyphrase_sources': [{'id': 'version:24.8 before < 24.8.5', 'keyphrase': '24.8 before < 24.8.5', 'type': 'version'}]}, 'similarity': np.float64(69.26160106596613)}, {'metadata': {'doc_id': '93', 'name': \"Improper Neutralization of CRLF Sequences ('CRLF Injection')\", 'source': 'sparse', 'original_content': 'The product uses CRLF (carriage return line feeds) as a special element, e.g. to separate lines or records, but it does not neutralize or incorrectly neutralizes CRLF sequences from inputs.', 'keyphrase_sources': [{'id': 'version:24.8 before < 24.8.5', 'keyphrase': '24.8 before < 24.8.5', 'type': 'version'}]}, 'similarity': np.float64(66.6650110741761)}, {'metadata': {'doc_id': '22', 'name': \"Improper Limitation of a Pathname to a Restricted Directory ('Path Traversal')\", 'source': 'sparse', 'original_content': 'The product uses external input to construct a pathname that is intended to identify a file or directory that is located underneath a restricted parent directory, but the product does not properly neutralize special elements within the pathname that can cause the pathname to resolve to a location that is outside of the restricted directory.', 'keyphrase_sources': [{'id': 'version:24.8 before < 24.8.5', 'keyphrase': '24.8 before < 24.8.5', 'type': 'version'}]}, 'similarity': np.float64(65.5068476387176)}, {'metadata': {'doc_id': '77', 'name': \"Improper Neutralization of Special Elements used in a Command ('Command Injection')\", 'source': 'sparse', 'original_content': 'The product constructs all or part of a command using externally-influenced input from an upstream component, but it does not neutralize or incorrectly neutralizes special elements that could modify the intended command when it is sent to a downstream component.', 'keyphrase_sources': [{'id': 'version:24.8 before < 24.8.5', 'keyphrase': '24.8 before < 24.8.5', 'type': 'version'}]}, 'similarity': np.float64(63.70329242853851)}, {'metadata': {'doc_id': '331', 'name': 'Insufficient Entropy', 'source': 'sparse', 'original_content': 'The product uses an algorithm or scheme that produces insufficient entropy, leaving patterns or clusters of values that are more likely to occur than others.', 'keyphrase_sources': [{'id': 'product:LibreOffice', 'keyphrase': 'LibreOffice', 'type': 'product'}]}, 'similarity': np.float64(57.176792480251706)}], identified_cwes={'analyzer': [], 'critic_additional': []})",
  "retrieval_results": {
    "has_multiple_keyphrases": true,
    "keyphrase_cwe_sets": {
      "rootcause:Input Validation vulnerability": {
        "keyphrase": "Input Validation vulnerability",
        "type": "rootcause",
        "cwes": [
          {
            "metadata": {
              "doc_id": "1204",
              "name": "Generation of Weak Initialization Vector (IV)",
              "source": "sparse",
              "original_content": "The product uses a cryptographic primitive that uses an Initialization\n\t\t\tVector (IV), but the product does not generate IVs that are\n\t\t\tsufficiently unpredictable or unique according to the expected\n\t\t\tcryptographic requirements for that primitive.\n\t\t\t",
              "keyphrase_sources": [
                {
                  "id": "rootcause:Input Validation vulnerability",
                  "keyphrase": "Input Validation vulnerability",
                  "type": "rootcause"
                },
                {
                  "id": "rootcause:Improper Input Validation",
                  "keyphrase": "Improper Input Validation",
                  "type": "rootcause"
                },
                {
                  "id": "impact:Windows Executable hyperlink targets to be executed unconditionally on activation",
                  "keyphrase": "Windows Executable hyperlink targets to be executed unconditionally on activation",
                  "type": "impact"
                },
                {
                  "id": "product:LibreOffice",
                  "keyphrase": "LibreOffice",
                  "type": "product"
                },
                {
                  "id": "version:24.8 before < 24.8.5",
                  "keyphrase": "24.8 before < 24.8.5",
                  "type": "version"
                }
              ]
            },
            "similarity": 188.4566085506798
          },
          {
            "metadata": {
              "doc_id": "116",
              "name": "Improper Encoding or Escaping of Output",
              "source": "sparse",
              "original_content": "The product prepares a structured message for communication with another component, but encoding or escaping of the data is either missing or done incorrectly. As a result, the intended structure of the message is not preserved.",
              "keyphrase_sources": [
                {
                  "id": "rootcause:Input Validation vulnerability",
                  "keyphrase": "Input Validation vulnerability",
                  "type": "rootcause"
                },
                {
                  "id": "rootcause:Improper Input Validation",
                  "keyphrase": "Improper Input Validation",
                  "type": "rootcause"
                },
                {
                  "id": "product:LibreOffice",
                  "keyphrase": "LibreOffice",
                  "type": "product"
                }
              ]
            },
            "similarity": 169.4371587591231
          },
          {
            "metadata": {
              "doc_id": "20",
              "name": "Improper Input Validation",
              "source": "sparse",
              "original_content": "The product receives input or data, but it does\n        not validate or incorrectly validates that the input has the\n        properties that are required to process the data safely and\n        correctly.",
              "keyphrase_sources": [
                {
                  "id": "rootcause:Input Validation vulnerability",
                  "keyphrase": "Input Validation vulnerability",
                  "type": "rootcause"
                },
                {
                  "id": "rootcause:Improper Input Validation",
                  "keyphrase": "Improper Input Validation",
                  "type": "rootcause"
                }
              ]
            },
            "similarity": 167.52864609113797
          },
          {
            "metadata": {
              "doc_id": "494",
              "name": "Download of Code Without Integrity Check",
              "source": "sparse",
              "original_content": "The product downloads source code or an executable from a remote location and executes the code without sufficiently verifying the origin and integrity of the code.",
              "keyphrase_sources": [
                {
                  "id": "rootcause:Input Validation vulnerability",
                  "keyphrase": "Input Validation vulnerability",
                  "type": "rootcause"
                },
                {
                  "id": "rootcause:Improper Input Validation",
                  "keyphrase": "Improper Input Validation",
                  "type": "rootcause"
                },
                {
                  "id": "impact:Windows Executable hyperlink targets to be executed unconditionally on activation",
                  "keyphrase": "Windows Executable hyperlink targets to be executed unconditionally on activation",
                  "type": "impact"
                },
                {
                  "id": "product:LibreOffice",
                  "keyphrase": "LibreOffice",
                  "type": "product"
                }
              ]
            },
            "similarity": 159.2941013104757
          },
          {
            "metadata": {
              "doc_id": "1285",
              "name": "Improper Validation of Specified Index, Position, or Offset in Input",
              "source": "sparse",
              "original_content": "The product receives input that is expected to specify an index, position, or offset into an indexable resource such as a buffer or file, but it does not validate or incorrectly validates that the specified index/position/offset has the required properties.",
              "keyphrase_sources": [
                {
                  "id": "rootcause:Input Validation vulnerability",
                  "keyphrase": "Input Validation vulnerability",
                  "type": "rootcause"
                },
                {
                  "id": "rootcause:Improper Input Validation",
                  "keyphrase": "Improper Input Validation",
                  "type": "rootcause"
                }
              ]
            },
            "similarity": 158.20437428762946
          }
        ]
      },
      "rootcause:Improper Input Validation": {
        "keyphrase": "Improper Input Validation",
        "type": "rootcause",
        "cwes": [
          {
            "metadata": {
              "doc_id": "1204",
              "name": "Generation of Weak Initialization Vector (IV)",
              "source": "sparse",
              "original_content": "The product uses a cryptographic primitive that uses an Initialization\n\t\t\tVector (IV), but the product does not generate IVs that are\n\t\t\tsufficiently unpredictable or unique according to the expected\n\t\t\tcryptographic requirements for that primitive.\n\t\t\t"
            },
            "similarity": 185.20148001707966
          },
          {
            "metadata": {
              "doc_id": "20",
              "name": "Improper Input Validation",
              "source": "sparse",
              "original_content": "The product receives input or data, but it does\n        not validate or incorrectly validates that the input has the\n        properties that are required to process the data safely and\n        correctly."
            },
            "similarity": 172.28162460857237
          },
          {
            "metadata": {
              "doc_id": "116",
              "name": "Improper Encoding or Escaping of Output",
              "source": "sparse",
              "original_content": "The product prepares a structured message for communication with another component, but encoding or escaping of the data is either missing or done incorrectly. As a result, the intended structure of the message is not preserved."
            },
            "similarity": 171.88349569085045
          },
          {
            "metadata": {
              "doc_id": "1285",
              "name": "Improper Validation of Specified Index, Position, or Offset in Input",
              "source": "sparse",
              "original_content": "The product receives input that is expected to specify an index, position, or offset into an indexable resource such as a buffer or file, but it does not validate or incorrectly validates that the specified index/position/offset has the required properties."
            },
            "similarity": 162.51350404703376
          },
          {
            "metadata": {
              "doc_id": "494",
              "name": "Download of Code Without Integrity Check",
              "source": "sparse",
              "original_content": "The product downloads source code or an executable from a remote location and executes the code without sufficiently verifying the origin and integrity of the code."
            },
            "similarity": 161.86078477319265
          }
        ]
      },
      "impact:Windows Executable hyperlink targets to be executed unconditionally on activation": {
        "keyphrase": "Windows Executable hyperlink targets to be executed unconditionally on activation",
        "type": "impact",
        "cwes": [
          {
            "metadata": {
              "doc_id": "494",
              "name": "Download of Code Without Integrity Check",
              "source": "sparse",
              "original_content": "The product downloads source code or an executable from a remote location and executes the code without sufficiently verifying the origin and integrity of the code."
            },
            "similarity": 83.76210838390362
          },
          {
            "metadata": {
              "doc_id": "1204",
              "name": "Generation of Weak Initialization Vector (IV)",
              "source": "sparse",
              "original_content": "The product uses a cryptographic primitive that uses an Initialization\n\t\t\tVector (IV), but the product does not generate IVs that are\n\t\t\tsufficiently unpredictable or unique according to the expected\n\t\t\tcryptographic requirements for that primitive.\n\t\t\t"
            },
            "similarity": 83.31604668937472
          },
          {
            "metadata": {
              "doc_id": "183",
              "name": "Permissive List of Allowed Inputs",
              "source": "sparse",
              "original_content": "The product implements a protection mechanism that relies on a list of inputs (or properties of inputs) that are explicitly allowed by policy because the inputs are assumed to be safe, but the list is too permissive - that is, it allows an input that is unsafe, leading to resultant weaknesses.",
              "keyphrase_sources": [
                {
                  "id": "impact:Windows Executable hyperlink targets to be executed unconditionally on activation",
                  "keyphrase": "Windows Executable hyperlink targets to be executed unconditionally on activation",
                  "type": "impact"
                }
              ]
            },
            "similarity": 78.80247405832327
          },
          {
            "metadata": {
              "doc_id": "732",
              "name": "Incorrect Permission Assignment for Critical Resource",
              "source": "sparse",
              "original_content": "The product specifies permissions for a security-critical resource in a way that allows that resource to be read or modified by unintended actors.",
              "keyphrase_sources": [
                {
                  "id": "impact:Windows Executable hyperlink targets to be executed unconditionally on activation",
                  "keyphrase": "Windows Executable hyperlink targets to be executed unconditionally on activation",
                  "type": "impact"
                }
              ]
            },
            "similarity": 78.72236214882524
          },
          {
            "metadata": {
              "doc_id": "426",
              "name": "Untrusted Search Path",
              "source": "sparse",
              "original_content": "The product searches for critical resources using an externally-supplied search path that can point to resources that are not under the product's direct control.",
              "keyphrase_sources": [
                {
                  "id": "impact:Windows Executable hyperlink targets to be executed unconditionally on activation",
                  "keyphrase": "Windows Executable hyperlink targets to be executed unconditionally on activation",
                  "type": "impact"
                }
              ]
            },
            "similarity": 76.39374345201969
          }
        ]
      },
      "product:LibreOffice": {
        "keyphrase": "LibreOffice",
        "type": "product",
        "cwes": [
          {
            "metadata": {
              "doc_id": "1204",
              "name": "Generation of Weak Initialization Vector (IV)",
              "source": "sparse",
              "original_content": "The product uses a cryptographic primitive that uses an Initialization\n\t\t\tVector (IV), but the product does not generate IVs that are\n\t\t\tsufficiently unpredictable or unique according to the expected\n\t\t\tcryptographic requirements for that primitive.\n\t\t\t"
            },
            "similarity": 80.58951529952665
          },
          {
            "metadata": {
              "doc_id": "172",
              "name": "Encoding Error",
              "source": "sparse",
              "original_content": "The product does not properly encode or decode the data, resulting in unexpected values.",
              "keyphrase_sources": [
                {
                  "id": "product:LibreOffice",
                  "keyphrase": "LibreOffice",
                  "type": "product"
                }
              ]
            },
            "similarity": 73.34542643505479
          },
          {
            "metadata": {
              "doc_id": "331",
              "name": "Insufficient Entropy",
              "source": "sparse",
              "original_content": "The product uses an algorithm or scheme that produces insufficient entropy, leaving patterns or clusters of values that are more likely to occur than others.",
              "keyphrase_sources": [
                {
                  "id": "product:LibreOffice",
                  "keyphrase": "LibreOffice",
                  "type": "product"
                }
              ]
            },
            "similarity": 57.176792480251706
          },
          {
            "metadata": {
              "doc_id": "116",
              "name": "Improper Encoding or Escaping of Output",
              "source": "sparse",
              "original_content": "The product prepares a structured message for communication with another component, but encoding or escaping of the data is either missing or done incorrectly. As a result, the intended structure of the message is not preserved."
            },
            "similarity": 46.916742865642675
          },
          {
            "metadata": {
              "doc_id": "494",
              "name": "Download of Code Without Integrity Check",
              "source": "sparse",
              "original_content": "The product downloads source code or an executable from a remote location and executes the code without sufficiently verifying the origin and integrity of the code."
            },
            "similarity": 44.39351676597687
          }
        ]
      },
      "version:24.8 before < 24.8.5": {
        "keyphrase": "24.8 before < 24.8.5",
        "type": "version",
        "cwes": [
          {
            "metadata": {
              "doc_id": "1204",
              "name": "Generation of Weak Initialization Vector (IV)",
              "source": "sparse",
              "original_content": "The product uses a cryptographic primitive that uses an Initialization\n\t\t\tVector (IV), but the product does not generate IVs that are\n\t\t\tsufficiently unpredictable or unique according to the expected\n\t\t\tcryptographic requirements for that primitive.\n\t\t\t"
            },
            "similarity": 82.42887543426372
          },
          {
            "metadata": {
              "doc_id": "73",
              "name": "External Control of File Name or Path",
              "source": "sparse",
              "original_content": "The product allows user input to control or influence paths or file names that are used in filesystem operations.",
              "keyphrase_sources": [
                {
                  "id": "version:24.8 before < 24.8.5",
                  "keyphrase": "24.8 before < 24.8.5",
                  "type": "version"
                }
              ]
            },
            "similarity": 69.26160106596613
          },
          {
            "metadata": {
              "doc_id": "93",
              "name": "Improper Neutralization of CRLF Sequences ('CRLF Injection')",
              "source": "sparse",
              "original_content": "The product uses CRLF (carriage return line feeds) as a special element, e.g. to separate lines or records, but it does not neutralize or incorrectly neutralizes CRLF sequences from inputs.",
              "keyphrase_sources": [
                {
                  "id": "version:24.8 before < 24.8.5",
                  "keyphrase": "24.8 before < 24.8.5",
                  "type": "version"
                }
              ]
            },
            "similarity": 66.6650110741761
          },
          {
            "metadata": {
              "doc_id": "22",
              "name": "Improper Limitation of a Pathname to a Restricted Directory ('Path Traversal')",
              "source": "sparse",
              "original_content": "The product uses external input to construct a pathname that is intended to identify a file or directory that is located underneath a restricted parent directory, but the product does not properly neutralize special elements within the pathname that can cause the pathname to resolve to a location that is outside of the restricted directory.",
              "keyphrase_sources": [
                {
                  "id": "version:24.8 before < 24.8.5",
                  "keyphrase": "24.8 before < 24.8.5",
                  "type": "version"
                }
              ]
            },
            "similarity": 65.5068476387176
          },
          {
            "metadata": {
              "doc_id": "77",
              "name": "Improper Neutralization of Special Elements used in a Command ('Command Injection')",
              "source": "sparse",
              "original_content": "The product constructs all or part of a command using externally-influenced input from an upstream component, but it does not neutralize or incorrectly neutralizes special elements that could modify the intended command when it is sent to a downstream component.",
              "keyphrase_sources": [
                {
                  "id": "version:24.8 before < 24.8.5",
                  "keyphrase": "24.8 before < 24.8.5",
                  "type": "version"
                }
              ]
            },
            "similarity": 63.70329242853851
          }
        ]
      }
    },
    "keyphrase_mapping": {
      "1204": [
        {
          "id": "rootcause:Input Validation vulnerability",
          "keyphrase": "Input Validation vulnerability",
          "type": "rootcause"
        },
        {
          "id": "rootcause:Improper Input Validation",
          "keyphrase": "Improper Input Validation",
          "type": "rootcause"
        },
        {
          "id": "impact:Windows Executable hyperlink targets to be executed unconditionally on activation",
          "keyphrase": "Windows Executable hyperlink targets to be executed unconditionally on activation",
          "type": "impact"
        },
        {
          "id": "product:LibreOffice",
          "keyphrase": "LibreOffice",
          "type": "product"
        },
        {
          "id": "version:24.8 before < 24.8.5",
          "keyphrase": "24.8 before < 24.8.5",
          "type": "version"
        }
      ],
      "116": [
        {
          "id": "rootcause:Input Validation vulnerability",
          "keyphrase": "Input Validation vulnerability",
          "type": "rootcause"
        },
        {
          "id": "rootcause:Improper Input Validation",
          "keyphrase": "Improper Input Validation",
          "type": "rootcause"
        },
        {
          "id": "product:LibreOffice",
          "keyphrase": "LibreOffice",
          "type": "product"
        }
      ],
      "20": [
        {
          "id": "rootcause:Input Validation vulnerability",
          "keyphrase": "Input Validation vulnerability",
          "type": "rootcause"
        },
        {
          "id": "rootcause:Improper Input Validation",
          "keyphrase": "Improper Input Validation",
          "type": "rootcause"
        }
      ],
      "494": [
        {
          "id": "rootcause:Input Validation vulnerability",
          "keyphrase": "Input Validation vulnerability",
          "type": "rootcause"
        },
        {
          "id": "rootcause:Improper Input Validation",
          "keyphrase": "Improper Input Validation",
          "type": "rootcause"
        },
        {
          "id": "impact:Windows Executable hyperlink targets to be executed unconditionally on activation",
          "keyphrase": "Windows Executable hyperlink targets to be executed unconditionally on activation",
          "type": "impact"
        },
        {
          "id": "product:LibreOffice",
          "keyphrase": "LibreOffice",
          "type": "product"
        }
      ],
      "1285": [
        {
          "id": "rootcause:Input Validation vulnerability",
          "keyphrase": "Input Validation vulnerability",
          "type": "rootcause"
        },
        {
          "id": "rootcause:Improper Input Validation",
          "keyphrase": "Improper Input Validation",
          "type": "rootcause"
        }
      ],
      "183": [
        {
          "id": "impact:Windows Executable hyperlink targets to be executed unconditionally on activation",
          "keyphrase": "Windows Executable hyperlink targets to be executed unconditionally on activation",
          "type": "impact"
        }
      ],
      "732": [
        {
          "id": "impact:Windows Executable hyperlink targets to be executed unconditionally on activation",
          "keyphrase": "Windows Executable hyperlink targets to be executed unconditionally on activation",
          "type": "impact"
        }
      ],
      "426": [
        {
          "id": "impact:Windows Executable hyperlink targets to be executed unconditionally on activation",
          "keyphrase": "Windows Executable hyperlink targets to be executed unconditionally on activation",
          "type": "impact"
        }
      ],
      "172": [
        {
          "id": "product:LibreOffice",
          "keyphrase": "LibreOffice",
          "type": "product"
        }
      ],
      "331": [
        {
          "id": "product:LibreOffice",
          "keyphrase": "LibreOffice",
          "type": "product"
        }
      ],
      "73": [
        {
          "id": "version:24.8 before < 24.8.5",
          "keyphrase": "24.8 before < 24.8.5",
          "type": "version"
        }
      ],
      "93": [
        {
          "id": "version:24.8 before < 24.8.5",
          "keyphrase": "24.8 before < 24.8.5",
          "type": "version"
        }
      ],
      "22": [
        {
          "id": "version:24.8 before < 24.8.5",
          "keyphrase": "24.8 before < 24.8.5",
          "type": "version"
        }
      ],
      "77": [
        {
          "id": "version:24.8 before < 24.8.5",
          "keyphrase": "24.8 before < 24.8.5",
          "type": "version"
        }
      ]
    },
    "relevant_cwes": [
      {
        "metadata": {
          "doc_id": "1204",
          "name": "Generation of Weak Initialization Vector (IV)",
          "source": "sparse",
          "original_content": "The product uses a cryptographic primitive that uses an Initialization\n\t\t\tVector (IV), but the product does not generate IVs that are\n\t\t\tsufficiently unpredictable or unique according to the expected\n\t\t\tcryptographic requirements for that primitive.\n\t\t\t",
          "keyphrase_sources": [
            {
              "id": "rootcause:Input Validation vulnerability",
              "keyphrase": "Input Validation vulnerability",
              "type": "rootcause"
            },
            {
              "id": "rootcause:Improper Input Validation",
              "keyphrase": "Improper Input Validation",
              "type": "rootcause"
            },
            {
              "id": "impact:Windows Executable hyperlink targets to be executed unconditionally on activation",
              "keyphrase": "Windows Executable hyperlink targets to be executed unconditionally on activation",
              "type": "impact"
            },
            {
              "id": "product:LibreOffice",
              "keyphrase": "LibreOffice",
              "type": "product"
            },
            {
              "id": "version:24.8 before < 24.8.5",
              "keyphrase": "24.8 before < 24.8.5",
              "type": "version"
            }
          ]
        },
        "similarity": 188.4566085506798
      },
      {
        "metadata": {
          "doc_id": "116",
          "name": "Improper Encoding or Escaping of Output",
          "source": "sparse",
          "original_content": "The product prepares a structured message for communication with another component, but encoding or escaping of the data is either missing or done incorrectly. As a result, the intended structure of the message is not preserved.",
          "keyphrase_sources": [
            {
              "id": "rootcause:Input Validation vulnerability",
              "keyphrase": "Input Validation vulnerability",
              "type": "rootcause"
            },
            {
              "id": "rootcause:Improper Input Validation",
              "keyphrase": "Improper Input Validation",
              "type": "rootcause"
            },
            {
              "id": "product:LibreOffice",
              "keyphrase": "LibreOffice",
              "type": "product"
            }
          ]
        },
        "similarity": 169.4371587591231
      },
      {
        "metadata": {
          "doc_id": "20",
          "name": "Improper Input Validation",
          "source": "sparse",
          "original_content": "The product receives input or data, but it does\n        not validate or incorrectly validates that the input has the\n        properties that are required to process the data safely and\n        correctly.",
          "keyphrase_sources": [
            {
              "id": "rootcause:Input Validation vulnerability",
              "keyphrase": "Input Validation vulnerability",
              "type": "rootcause"
            },
            {
              "id": "rootcause:Improper Input Validation",
              "keyphrase": "Improper Input Validation",
              "type": "rootcause"
            }
          ]
        },
        "similarity": 167.52864609113797
      },
      {
        "metadata": {
          "doc_id": "494",
          "name": "Download of Code Without Integrity Check",
          "source": "sparse",
          "original_content": "The product downloads source code or an executable from a remote location and executes the code without sufficiently verifying the origin and integrity of the code.",
          "keyphrase_sources": [
            {
              "id": "rootcause:Input Validation vulnerability",
              "keyphrase": "Input Validation vulnerability",
              "type": "rootcause"
            },
            {
              "id": "rootcause:Improper Input Validation",
              "keyphrase": "Improper Input Validation",
              "type": "rootcause"
            },
            {
              "id": "impact:Windows Executable hyperlink targets to be executed unconditionally on activation",
              "keyphrase": "Windows Executable hyperlink targets to be executed unconditionally on activation",
              "type": "impact"
            },
            {
              "id": "product:LibreOffice",
              "keyphrase": "LibreOffice",
              "type": "product"
            }
          ]
        },
        "similarity": 159.2941013104757
      },
      {
        "metadata": {
          "doc_id": "1285",
          "name": "Improper Validation of Specified Index, Position, or Offset in Input",
          "source": "sparse",
          "original_content": "The product receives input that is expected to specify an index, position, or offset into an indexable resource such as a buffer or file, but it does not validate or incorrectly validates that the specified index/position/offset has the required properties.",
          "keyphrase_sources": [
            {
              "id": "rootcause:Input Validation vulnerability",
              "keyphrase": "Input Validation vulnerability",
              "type": "rootcause"
            },
            {
              "id": "rootcause:Improper Input Validation",
              "keyphrase": "Improper Input Validation",
              "type": "rootcause"
            }
          ]
        },
        "similarity": 158.20437428762946
      },
      {
        "metadata": {
          "doc_id": "183",
          "name": "Permissive List of Allowed Inputs",
          "source": "sparse",
          "original_content": "The product implements a protection mechanism that relies on a list of inputs (or properties of inputs) that are explicitly allowed by policy because the inputs are assumed to be safe, but the list is too permissive - that is, it allows an input that is unsafe, leading to resultant weaknesses.",
          "keyphrase_sources": [
            {
              "id": "impact:Windows Executable hyperlink targets to be executed unconditionally on activation",
              "keyphrase": "Windows Executable hyperlink targets to be executed unconditionally on activation",
              "type": "impact"
            }
          ]
        },
        "similarity": 78.80247405832327
      },
      {
        "metadata": {
          "doc_id": "732",
          "name": "Incorrect Permission Assignment for Critical Resource",
          "source": "sparse",
          "original_content": "The product specifies permissions for a security-critical resource in a way that allows that resource to be read or modified by unintended actors.",
          "keyphrase_sources": [
            {
              "id": "impact:Windows Executable hyperlink targets to be executed unconditionally on activation",
              "keyphrase": "Windows Executable hyperlink targets to be executed unconditionally on activation",
              "type": "impact"
            }
          ]
        },
        "similarity": 78.72236214882524
      },
      {
        "metadata": {
          "doc_id": "426",
          "name": "Untrusted Search Path",
          "source": "sparse",
          "original_content": "The product searches for critical resources using an externally-supplied search path that can point to resources that are not under the product's direct control.",
          "keyphrase_sources": [
            {
              "id": "impact:Windows Executable hyperlink targets to be executed unconditionally on activation",
              "keyphrase": "Windows Executable hyperlink targets to be executed unconditionally on activation",
              "type": "impact"
            }
          ]
        },
        "similarity": 76.39374345201969
      },
      {
        "metadata": {
          "doc_id": "172",
          "name": "Encoding Error",
          "source": "sparse",
          "original_content": "The product does not properly encode or decode the data, resulting in unexpected values.",
          "keyphrase_sources": [
            {
              "id": "product:LibreOffice",
              "keyphrase": "LibreOffice",
              "type": "product"
            }
          ]
        },
        "similarity": 73.34542643505479
      },
      {
        "metadata": {
          "doc_id": "73",
          "name": "External Control of File Name or Path",
          "source": "sparse",
          "original_content": "The product allows user input to control or influence paths or file names that are used in filesystem operations.",
          "keyphrase_sources": [
            {
              "id": "version:24.8 before < 24.8.5",
              "keyphrase": "24.8 before < 24.8.5",
              "type": "version"
            }
          ]
        },
        "similarity": 69.26160106596613
      },
      {
        "metadata": {
          "doc_id": "93",
          "name": "Improper Neutralization of CRLF Sequences ('CRLF Injection')",
          "source": "sparse",
          "original_content": "The product uses CRLF (carriage return line feeds) as a special element, e.g. to separate lines or records, but it does not neutralize or incorrectly neutralizes CRLF sequences from inputs.",
          "keyphrase_sources": [
            {
              "id": "version:24.8 before < 24.8.5",
              "keyphrase": "24.8 before < 24.8.5",
              "type": "version"
            }
          ]
        },
        "similarity": 66.6650110741761
      },
      {
        "metadata": {
          "doc_id": "22",
          "name": "Improper Limitation of a Pathname to a Restricted Directory ('Path Traversal')",
          "source": "sparse",
          "original_content": "The product uses external input to construct a pathname that is intended to identify a file or directory that is located underneath a restricted parent directory, but the product does not properly neutralize special elements within the pathname that can cause the pathname to resolve to a location that is outside of the restricted directory.",
          "keyphrase_sources": [
            {
              "id": "version:24.8 before < 24.8.5",
              "keyphrase": "24.8 before < 24.8.5",
              "type": "version"
            }
          ]
        },
        "similarity": 65.5068476387176
      },
      {
        "metadata": {
          "doc_id": "77",
          "name": "Improper Neutralization of Special Elements used in a Command ('Command Injection')",
          "source": "sparse",
          "original_content": "The product constructs all or part of a command using externally-influenced input from an upstream component, but it does not neutralize or incorrectly neutralizes special elements that could modify the intended command when it is sent to a downstream component.",
          "keyphrase_sources": [
            {
              "id": "version:24.8 before < 24.8.5",
              "keyphrase": "24.8 before < 24.8.5",
              "type": "version"
            }
          ]
        },
        "similarity": 63.70329242853851
      },
      {
        "metadata": {
          "doc_id": "331",
          "name": "Insufficient Entropy",
          "source": "sparse",
          "original_content": "The product uses an algorithm or scheme that produces insufficient entropy, leaving patterns or clusters of values that are more likely to occur than others.",
          "keyphrase_sources": [
            {
              "id": "product:LibreOffice",
              "keyphrase": "LibreOffice",
              "type": "product"
            }
          ]
        },
        "similarity": 57.176792480251706
      }
    ],
    "enhanced_query": "# Vulnerability Description\n\n    Improper **Input Validation vulnerability** in The Document Foundation LibreOffice allows Windows Executable hyperlink targets to be executed unconditionally on activation.This issue affects LibreOffice from 24.8 before < 24.8.5.\n\n    # Keyphrase-Specific CWE Analysis\n    This vulnerability contains multiple keyphrases that may map to different CWEs. \n    Please analyze each keyphrase separately and determine the most appropriate CWE(s) for each.\n\n    ## ROOTCAUSE: 'Input Validation vulnerability'\n\nRelevant CWEs for this ROOTCAUSE:\n\n### 1. CWE-1204: Generation of Weak Initialization Vector (IV) (Score: 188.46)\n\nThe product uses a cryptographic primitive that uses an Initialization\n\t\t\tVector (IV), but the product does not generate IVs that are\n\t\t\tsufficiently unpredictable or unique according to the expected\n\t\t\tcryptographic requirements for that primitive.\n\t\t\t...\n\n### 2. CWE-116: Improper Encoding or Escaping of Output (Score: 169.44)\n\nThe product prepares a structured message for communication with another component, but encoding or escaping of the data is either missing or done incorrectly. As a result, the intended structure of the message is not preserved....\n\n### 3. CWE-20: Improper Input Validation (Score: 167.53)\n\nThe product receives input or data, but it does\n        not validate or incorrectly validates that the input has the\n        properties that are required to process the data safely and\n        correctly....\n\n### 4. CWE-494: Download of Code Without Integrity Check (Score: 159.29)\n\nThe product downloads source code or an executable from a remote location and executes the code without sufficiently verifying the origin and integrity of the code....\n\n### 5. CWE-1285: Improper Validation of Specified Index, Position, or Offset in Input (Score: 158.20)\n\nThe product receives input that is expected to specify an index, position, or offset into an indexable resource such as a buffer or file, but it does not validate or incorrectly validates that the specified index/position/offset has the required properties....\n\n## ROOTCAUSE: 'Improper Input Validation'\n\nRelevant CWEs for this ROOTCAUSE:\n\n### 1. CWE-1204: Generation of Weak Initialization Vector (IV) (Score: 188.46)\n\nThe product uses a cryptographic primitive that uses an Initialization\n\t\t\tVector (IV), but the product does not generate IVs that are\n\t\t\tsufficiently unpredictable or unique according to the expected\n\t\t\tcryptographic requirements for that primitive.\n\t\t\t...\n\n### 2. CWE-116: Improper Encoding or Escaping of Output (Score: 169.44)\n\nThe product prepares a structured message for communication with another component, but encoding or escaping of the data is either missing or done incorrectly. As a result, the intended structure of the message is not preserved....\n\n### 3. CWE-20: Improper Input Validation (Score: 167.53)\n\nThe product receives input or data, but it does\n        not validate or incorrectly validates that the input has the\n        properties that are required to process the data safely and\n        correctly....\n\n### 4. CWE-494: Download of Code Without Integrity Check (Score: 159.29)\n\nThe product downloads source code or an executable from a remote location and executes the code without sufficiently verifying the origin and integrity of the code....\n\n### 5. CWE-1285: Improper Validation of Specified Index, Position, or Offset in Input (Score: 158.20)\n\nThe product receives input that is expected to specify an index, position, or offset into an indexable resource such as a buffer or file, but it does not validate or incorrectly validates that the specified index/position/offset has the required properties....\n\n## IMPACT: 'Windows Executable hyperlink targets to be executed unconditionally on activation'\n\nRelevant CWEs for this IMPACT:\n\n### 1. CWE-1204: Generation of Weak Initialization Vector (IV) (Score: 188.46)\n\nThe product uses a cryptographic primitive that uses an Initialization\n\t\t\tVector (IV), but the product does not generate IVs that are\n\t\t\tsufficiently unpredictable or unique according to the expected\n\t\t\tcryptographic requirements for that primitive.\n\t\t\t...\n\n### 2. CWE-494: Download of Code Without Integrity Check (Score: 159.29)\n\nThe product downloads source code or an executable from a remote location and executes the code without sufficiently verifying the origin and integrity of the code....\n\n### 3. CWE-183: Permissive List of Allowed Inputs (Score: 78.80)\n\nThe product implements a protection mechanism that relies on a list of inputs (or properties of inputs) that are explicitly allowed by policy because the inputs are assumed to be safe, but the list is too permissive - that is, it allows an input that is unsafe, leading to resultant weaknesses....\n\n### 4. CWE-732: Incorrect Permission Assignment for Critical Resource (Score: 78.72)\n\nThe product specifies permissions for a security-critical resource in a way that allows that resource to be read or modified by unintended actors....\n\n### 5. CWE-426: Untrusted Search Path (Score: 76.39)\n\nThe product searches for critical resources using an externally-supplied search path that can point to resources that are not under the product's direct control....\n\n## PRODUCT: 'LibreOffice'\n\nRelevant CWEs for this PRODUCT:\n\n### 1. CWE-1204: Generation of Weak Initialization Vector (IV) (Score: 188.46)\n\nThe product uses a cryptographic primitive that uses an Initialization\n\t\t\tVector (IV), but the product does not generate IVs that are\n\t\t\tsufficiently unpredictable or unique according to the expected\n\t\t\tcryptographic requirements for that primitive.\n\t\t\t...\n\n### 2. CWE-116: Improper Encoding or Escaping of Output (Score: 169.44)\n\nThe product prepares a structured message for communication with another component, but encoding or escaping of the data is either missing or done incorrectly. As a result, the intended structure of the message is not preserved....\n\n### 3. CWE-494: Download of Code Without Integrity Check (Score: 159.29)\n\nThe product downloads source code or an executable from a remote location and executes the code without sufficiently verifying the origin and integrity of the code....\n\n### 4. CWE-172: Encoding Error (Score: 73.35)\n\nThe product does not properly encode or decode the data, resulting in unexpected values....\n\n### 5. CWE-331: Insufficient Entropy (Score: 57.18)\n\nThe product uses an algorithm or scheme that produces insufficient entropy, leaving patterns or clusters of values that are more likely to occur than others....\n\n## VERSION: '24.8 before < 24.8.5'\n\nRelevant CWEs for this VERSION:\n\n### 1. CWE-1204: Generation of Weak Initialization Vector (IV) (Score: 188.46)\n\nThe product uses a cryptographic primitive that uses an Initialization\n\t\t\tVector (IV), but the product does not generate IVs that are\n\t\t\tsufficiently unpredictable or unique according to the expected\n\t\t\tcryptographic requirements for that primitive.\n\t\t\t...\n\n### 2. CWE-73: External Control of File Name or Path (Score: 69.26)\n\nThe product allows user input to control or influence paths or file names that are used in filesystem operations....\n\n### 3. CWE-93: Improper Neutralization of CRLF Sequences ('CRLF Injection') (Score: 66.67)\n\nThe product uses CRLF (carriage return line feeds) as a special element, e.g. to separate lines or records, but it does not neutralize or incorrectly neutralizes CRLF sequences from inputs....\n\n### 4. CWE-22: Improper Limitation of a Pathname to a Restricted Directory ('Path Traversal') (Score: 65.51)\n\nThe product uses external input to construct a pathname that is intended to identify a file or directory that is located underneath a restricted parent directory, but the product does not properly neutralize special elements within the pathname that can cause the pathname to resolve to a location th...\n\n### 5. CWE-77: Improper Neutralization of Special Elements used in a Command ('Command Injection') (Score: 63.70)\n\nThe product constructs all or part of a command using externally-influenced input from an upstream component, but it does not neutralize or incorrectly neutralizes special elements that could modify the intended command when it is sent to a downstream component....\n\n\n    # Analysis Instructions\n    1. For each keyphrase, identify the most appropriate CWE(s) that represent the weakness.\n    2. Consider how the different keyphrases might relate to each other in the vulnerability chain.\n    3. Provide a final determination of primary CWE(s) and any secondary CWEs.\n    4. Format your response using the standard analysis template.\n\n    Please analyze how these different weaknesses interact and provide a comprehensive CWE classification.\n    "
  },
  "retrieval_time": 1.010650634765625
}