{
  "cve_id": "CVE-2025-21351",
  "description": "Windows Active Directory Domain Services API Denial of Service Vulnerability",
  "key_phrases": {
    "rootcause": "",
    "weakness": "",
    "impact": "Denial of Service",
    "vector": "",
    "attacker": "",
    "product": "Windows Active Directory Domain Services",
    "version": "",
    "component": "API"
  },
  "reference_content": "UNRELATED",
  "similar_info": {
    "cwe_distribution": {},
    "cwe_consensus": "",
    "similarity_stats": {
      "thresholds": [],
      "total_samples_by_threshold": {},
      "top_cwes_by_threshold": {}
    }
  },
  "similarity_summary": {
    "consensus_cwe": "",
    "top_cwes": [],
    "confidence_levels": {},
    "total_samples": 0
  },
  "analysis": "# Summary\n| CWE ID | CWE Name | Confidence | CWE Abstraction Level | CWE Vulnerability Mapping Label | CWE-Vulnerability Mapping Notes |\n|---|---|---|---|---|---|\n| CWE-400 | Uncontrolled Resource Consumption | 0.7 | Base | Primary | Allowed |\n\n## Evidence and Confidence\n\n*   **Confidence Score:** 0.7\n*   **Evidence Strength:** LOW\n\n## Relationship Analysis\nThe primary CWE selected is CWE-400, which focuses on resource consumption. While there are no explicit parent-child or chain relationships that directly influenced the decision due to the limited information, the abstraction level (Base) is appropriate for the available details.\n\n```mermaid\ngraph TD\n    cwe400[\"CWE-400: Uncontrolled Resource Consumption\"]\n    classDef primary fill:#f96,stroke:#333,stroke-width:2px\n    class cwe400 primary\n```\n\n## Vulnerability Chain\nThe vulnerability chain is:\n1.  The API in Windows Active Directory Domain Services is exploited in some way.\n2.  This leads to **Uncontrolled Resource Consumption** (CWE-400).\n3.  The **impact** is Denial of Service.\n\nThe provided information doesn't give a lot of information of how the API is being exploited, so the first part of the chain is unknown.\n\n## Summary of Analysis\nThe analysis is based on limited evidence, primarily the \"Denial of Service\" **impact** and the affected component (\"Windows Active Directory Domain Services API\"). The vulnerability description key phrases identifies the **impact** as a Denial of Service. Without more detail about the **root cause**, it is difficult to assign a more specific CWE.\n\nCWE-400 (Uncontrolled Resource Consumption) is the most appropriate choice because a denial-of-service **impact** often results from a service being overwhelmed by requests or consuming excessive resources, leading to it becoming unavailable.\n\nOther CWEs Considered:\n\n*   CWE-295 (Improper Certificate Validation), CWE-379 (Creation of Temporary File in Directory with Insecure Permissions), CWE-923 (Improper Restriction of Communication Channel to Intended Endpoints), CWE-328 (Use of Weak Hash), CWE-732 (Incorrect Permission Assignment for Critical Resource), CWE-290 (Authentication Bypass by Spoofing), CWE-250 (Execution with Unnecessary Privileges), CWE-284 (Improper Access Control), CWE-69 (Improper Handling of Windows ::DATA Alternate Data Stream), CWE-322 (Key Exchange without Entity Authentication): These CWEs are not selected because they don't directly relate to the provided information about the vulnerability. They focus on certificate validation, file permissions, communication channels, or other specific security issues, none of which are explicitly mentioned in the vulnerability description.\nRelevant CWE Information:\n\n# Enhanced Context (25 CWEs)\nThe following CWEs were identified as potentially relevant to this vulnerability:\n\n## CWE-303: Incorrect Implementation of Authentication Algorithm\n**Abstraction Level**: Base\n**Similarity Score**: 0.67\n**Source**: dense\n\n**Description**:\nThe requirements for the product dictate the use of an established authentication algorithm, but the implementation of the algorithm is **incorrect**.\n\n**Mapping Guidance**:\n- Usage: Allowed\n- Rationale: This CWE entry is at the Base level of abstraction, which is a preferred level of abstraction for mapping to the root causes of vulnerabilities.\n\n\n\n## CWE-288: Authentication Bypass Using an Alternate Path or Channel\n**Abstraction Level**: Base\n**Similarity Score**: 0.67\n**Source**: dense\n\n**Description**:\nThe product requires authentication, but the product has an alternate path or channel that does not require authentication.\n\n**Mapping Guidance**:\n- Usage: Allowed\n- Rationale: This CWE entry is at the Base level of abstraction, which is a preferred level of abstraction for mapping to the root causes of vulnerabilities.\n\n\n\n## CWE-59: Improper Link Resolution Before File Access ('Link Following')\n**Abstraction Level**: Base\n**Similarity Score**: 0.67\n**Source**: dense\n\n**Description**:\nThe product attempts to access a file based on the filename, but it does not properly prevent that filename from identifying a link or shortcut that resolves to an unintended resource.\n\n**Mapping Guidance**:\n- Usage: Allowed\n- Rationale: This CWE entry is at the Base level of abstraction, which is a preferred level of abstraction for mapping to the root causes of vulnerabilities.\n\n\n\n## CWE-178: Improper Handling of Case Sensitivity\n**Abstraction Level**: Base\n**Similarity Score**: 0.66\n**Source**: dense\n\n**Description**:\nThe product does not properly account for differences in case sensitivity when accessing or determining the properties of a resource, leading to inconsistent results.\n\n**Mapping Guidance**:\n- Usage: Allowed\n- Rationale: This CWE entry is at the Base level of abstraction, which is a preferred level of abstraction for mapping to the root causes of vulnerabilities.\n\n\n\n## CWE-204: Observable Response Discrepancy\n**Abstraction Level**: Base\n**Similarity Score**: 0.66\n**Source**: dense\n\n**Description**:\nThe product provides different responses to incoming requests in a way that reveals internal state information to an unauthorized actor outside of the intended control sphere.\n\n**Mapping Guidance**:\n- Usage: Allowed\n- Rationale: This CWE entry is at the Base level of abstraction, which is a preferred level of abstraction for mapping to the root causes of vulnerabilities.\n\n\n\n## CWE-274: Improper Handling of Insufficient Privileges\n**Abstraction Level**: Base\n**Similarity Score**: 0.66\n**Source**: dense\n\n**Description**:\nThe product does not handle or incorrectly handles when it has insufficient privileges to perform an operation, leading to resultant weaknesses.\n\n**Mapping Guidance**:\n- Usage: Discouraged\n- Rationale: This CWE entry could be deprecated in a future version of CWE.\n\n\n\n## CWE-1391: Use of Weak Credentials\n**Abstraction Level**: Class\n**Similarity Score**: 0.66\n**Source**: dense\n\n**Description**:\nThe product uses weak credentials (such as a default key or hard-coded password) that can be calculated, derived, reused, or guessed by an attacker.\n\n**Mapping Guidance**:\n- Usage: Allowed-with-Review\n- Rationale: This CWE entry is a Class and might have Base-level children that would be more appropriate\n\n\n\n## CWE-472: External Control of Assumed-Immutable Web Parameter\n**Abstraction Level**: Base\n**Similarity Score**: 0.66\n**Source**: dense\n\n**Description**:\nThe web application does not sufficiently verify inputs that are assumed to be immutable but are actually externally controllable, such as hidden form fields.\n\n**Mapping Guidance**:\n- Usage: Allowed\n- Rationale: This CWE entry is at the Base level of abstraction, which is a preferred level of abstraction for mapping to the root causes of vulnerabilities.\n\n\n\n## CWE-617: Reachable Assertion\n**Abstraction Level**: Base\n**Similarity Score**: 0.66\n**Source**: dense\n\n**Description**:\nThe product contains an assert() or similar statement that can be triggered by an attacker, which leads to an application exit or other behavior that is more severe than necessary.\n\n**Mapping Guidance**:\n- Usage: Allowed\n- Rationale: This CWE entry is at the Base level of abstraction, which is a preferred level of abstraction for mapping to the root causes of vulnerabilities.\n\n\n\n## CWE-552: Files or Directories Accessible to External Parties\n**Abstraction Level**: Base\n**Similarity Score**: 0.66\n**Source**: dense\n\n**Description**:\nThe product makes files or directories accessible to unauthorized actors, even though they should not be.\n\n**Mapping Guidance**:\n- Usage: Allowed\n- Rationale: This CWE entry is at the Base level of abstraction, which is a preferred level of abstraction for mapping to the root causes of vulnerabilities.\n\n\n\n## CWE-732: Incorrect Permission Assignment for Critical Resource\n**Abstraction Level**: Class\n**Similarity Score**: 311.56\n**Source**: sparse\n\n**Description**:\nThe product specifies permissions for a security-critical resource in a way that allows that resource to be read or modified by unintended actors.\n\n**Mapping Guidance**:\n- Usage: Allowed-with-Review\n- Rationale: While the name itself indicates an assignment of permissions for resources, this is often misused for vulnerabilities in which \"permissions\" are not checked, which is an \"authorization\" weakness (CWE-285 or descendants) within CWE's model [REF-1287].\n\n\n\n## CWE-295: Improper Certificate Validation\n**Abstraction Level**: Base\n**Similarity Score**: 300.99\n**Source**: sparse\n\n**Description**:\nThe product does not validate, or incorrectly validates, a certificate.\n\n**Mapping Guidance**:\n- Usage: Allowed\n- Rationale: This CWE entry is at the Base level of abstraction, which is a preferred level of abstraction for mapping to the root causes of vulnerabilities.\n\n\n\n## CWE-923: Improper Restriction of Communication Channel to Intended Endpoints\n**Abstraction Level**: Class\n**Similarity Score**: 293.72\n**Source**: sparse\n\n**Description**:\nThe product establishes a communication channel to (or from) an endpoint for privileged or protected operations, but it does not properly ensure that it is communicating with the correct endpoint.\n\n**Mapping Guidance**:\n- Usage: Allowed-with-Review\n- Rationale: This CWE",
  "analysis_with_relationships": "# Summary\n| CWE ID | CWE Name | Confidence | CWE Abstraction Level | CWE Vulnerability Mapping Label | CWE-Vulnerability Mapping Notes |\n|---|---|---|---|---|---|\n| CWE-400 | Uncontrolled Resource Consumption | 0.7 | Base | Primary | Allowed |\n\n## Evidence and Confidence\n\n*   **Confidence Score:** 0.7\n*   **Evidence Strength:** LOW\n\n## Relationship Analysis\nThe primary CWE selected is CWE-400, which focuses on resource consumption. While there are no explicit parent-child or chain relationships that directly influenced the decision due to the limited information, the abstraction level (Base) is appropriate for the available details.\n\n```mermaid\ngraph TD\n    cwe400[\"CWE-400: Uncontrolled Resource Consumption\"]\n    classDef primary fill:#f96,stroke:#333,stroke-width:2px\n    class cwe400 primary\n```\n\n## Vulnerability Chain\nThe vulnerability chain is:\n1.  The API in Windows Active Directory Domain Services is exploited in some way.\n2.  This leads to **Uncontrolled Resource Consumption** (CWE-400).\n3.  The **impact** is Denial of Service.\n\nThe provided information doesn't give a lot of information of how the API is being exploited, so the first part of the chain is unknown.\n\n## Summary of Analysis\nThe analysis is based on limited evidence, primarily the \"Denial of Service\" **impact** and the affected component (\"Windows Active Directory Domain Services API\"). The vulnerability description key phrases identifies the **impact** as a Denial of Service. Without more detail about the **root cause**, it is difficult to assign a more specific CWE.\n\nCWE-400 (Uncontrolled Resource Consumption) is the most appropriate choice because a denial-of-service **impact** often results from a service being overwhelmed by requests or consuming excessive resources, leading to it becoming unavailable.\n\nOther CWEs Considered:\n\n*   CWE-295 (Improper Certificate Validation), CWE-379 (Creation of Temporary File in Directory with Insecure Permissions), CWE-923 (Improper Restriction of Communication Channel to Intended Endpoints), CWE-328 (Use of Weak Hash), CWE-732 (Incorrect Permission Assignment for Critical Resource), CWE-290 (Authentication Bypass by Spoofing), CWE-250 (Execution with Unnecessary Privileges), CWE-284 (Improper Access Control), CWE-69 (Improper Handling of Windows ::DATA Alternate Data Stream), CWE-322 (Key Exchange without Entity Authentication): These CWEs are not selected because they don't directly relate to the provided information about the vulnerability. They focus on certificate validation, file permissions, communication channels, or other specific security issues, none of which are explicitly mentioned in the vulnerability description.\nRelevant CWE Information:\n\n# Enhanced Context (25 CWEs)\nThe following CWEs were identified as potentially relevant to this vulnerability:\n\n## CWE-303: Incorrect Implementation of Authentication Algorithm\n**Abstraction Level**: Base\n**Similarity Score**: 0.67\n**Source**: dense\n\n**Description**:\nThe requirements for the product dictate the use of an established authentication algorithm, but the implementation of the algorithm is **incorrect**.\n\n**Mapping Guidance**:\n- Usage: Allowed\n- Rationale: This CWE entry is at the Base level of abstraction, which is a preferred level of abstraction for mapping to the root causes of vulnerabilities.\n\n\n\n## CWE-288: Authentication Bypass Using an Alternate Path or Channel\n**Abstraction Level**: Base\n**Similarity Score**: 0.67\n**Source**: dense\n\n**Description**:\nThe product requires authentication, but the product has an alternate path or channel that does not require authentication.\n\n**Mapping Guidance**:\n- Usage: Allowed\n- Rationale: This CWE entry is at the Base level of abstraction, which is a preferred level of abstraction for mapping to the root causes of vulnerabilities.\n\n\n\n## CWE-59: Improper Link Resolution Before File Access ('Link Following')\n**Abstraction Level**: Base\n**Similarity Score**: 0.67\n**Source**: dense\n\n**Description**:\nThe product attempts to access a file based on the filename, but it does not properly prevent that filename from identifying a link or shortcut that resolves to an unintended resource.\n\n**Mapping Guidance**:\n- Usage: Allowed\n- Rationale: This CWE entry is at the Base level of abstraction, which is a preferred level of abstraction for mapping to the root causes of vulnerabilities.\n\n\n\n## CWE-178: Improper Handling of Case Sensitivity\n**Abstraction Level**: Base\n**Similarity Score**: 0.66\n**Source**: dense\n\n**Description**:\nThe product does not properly account for differences in case sensitivity when accessing or determining the properties of a resource, leading to inconsistent results.\n\n**Mapping Guidance**:\n- Usage: Allowed\n- Rationale: This CWE entry is at the Base level of abstraction, which is a preferred level of abstraction for mapping to the root causes of vulnerabilities.\n\n\n\n## CWE-204: Observable Response Discrepancy\n**Abstraction Level**: Base\n**Similarity Score**: 0.66\n**Source**: dense\n\n**Description**:\nThe product provides different responses to incoming requests in a way that reveals internal state information to an unauthorized actor outside of the intended control sphere.\n\n**Mapping Guidance**:\n- Usage: Allowed\n- Rationale: This CWE entry is at the Base level of abstraction, which is a preferred level of abstraction for mapping to the root causes of vulnerabilities.\n\n\n\n## CWE-274: Improper Handling of Insufficient Privileges\n**Abstraction Level**: Base\n**Similarity Score**: 0.66\n**Source**: dense\n\n**Description**:\nThe product does not handle or incorrectly handles when it has insufficient privileges to perform an operation, leading to resultant weaknesses.\n\n**Mapping Guidance**:\n- Usage: Discouraged\n- Rationale: This CWE entry could be deprecated in a future version of CWE.\n\n\n\n## CWE-1391: Use of Weak Credentials\n**Abstraction Level**: Class\n**Similarity Score**: 0.66\n**Source**: dense\n\n**Description**:\nThe product uses weak credentials (such as a default key or hard-coded password) that can be calculated, derived, reused, or guessed by an attacker.\n\n**Mapping Guidance**:\n- Usage: Allowed-with-Review\n- Rationale: This CWE entry is a Class and might have Base-level children that would be more appropriate\n\n\n\n## CWE-472: External Control of Assumed-Immutable Web Parameter\n**Abstraction Level**: Base\n**Similarity Score**: 0.66\n**Source**: dense\n\n**Description**:\nThe web application does not sufficiently verify inputs that are assumed to be immutable but are actually externally controllable, such as hidden form fields.\n\n**Mapping Guidance**:\n- Usage: Allowed\n- Rationale: This CWE entry is at the Base level of abstraction, which is a preferred level of abstraction for mapping to the root causes of vulnerabilities.\n\n\n\n## CWE-617: Reachable Assertion\n**Abstraction Level**: Base\n**Similarity Score**: 0.66\n**Source**: dense\n\n**Description**:\nThe product contains an assert() or similar statement that can be triggered by an attacker, which leads to an application exit or other behavior that is more severe than necessary.\n\n**Mapping Guidance**:\n- Usage: Allowed\n- Rationale: This CWE entry is at the Base level of abstraction, which is a preferred level of abstraction for mapping to the root causes of vulnerabilities.\n\n\n\n## CWE-552: Files or Directories Accessible to External Parties\n**Abstraction Level**: Base\n**Similarity Score**: 0.66\n**Source**: dense\n\n**Description**:\nThe product makes files or directories accessible to unauthorized actors, even though they should not be.\n\n**Mapping Guidance**:\n- Usage: Allowed\n- Rationale: This CWE entry is at the Base level of abstraction, which is a preferred level of abstraction for mapping to the root causes of vulnerabilities.\n\n\n\n## CWE-732: Incorrect Permission Assignment for Critical Resource\n**Abstraction Level**: Class\n**Similarity Score**: 311.56\n**Source**: sparse\n\n**Description**:\nThe product specifies permissions for a security-critical resource in a way that allows that resource to be read or modified by unintended actors.\n\n**Mapping Guidance**:\n- Usage: Allowed-with-Review\n- Rationale: While the name itself indicates an assignment of permissions for resources, this is often misused for vulnerabilities in which \"permissions\" are not checked, which is an \"authorization\" weakness (CWE-285 or descendants) within CWE's model [REF-1287].\n\n\n\n## CWE-295: Improper Certificate Validation\n**Abstraction Level**: Base\n**Similarity Score**: 300.99\n**Source**: sparse\n\n**Description**:\nThe product does not validate, or incorrectly validates, a certificate.\n\n**Mapping Guidance**:\n- Usage: Allowed\n- Rationale: This CWE entry is at the Base level of abstraction, which is a preferred level of abstraction for mapping to the root causes of vulnerabilities.\n\n\n\n## CWE-923: Improper Restriction of Communication Channel to Intended Endpoints\n**Abstraction Level**: Class\n**Similarity Score**: 293.72\n**Source**: sparse\n\n**Description**:\nThe product establishes a communication channel to (or from) an endpoint for privileged or protected operations, but it does not properly ensure that it is communicating with the correct endpoint.\n\n**Mapping Guidance**:\n- Usage: Allowed-with-Review\n- Rationale: This CWE\n\n\n## CWE Relationship Analysis\n\nCurrent CWEs represent these abstraction levels: .\n\n\n### Vulnerability Chain Analysis\n\n**Chain starting from CWE-274:**\n- 274 (Improper Handling of Insufficient Privileges) - ROOT\n\n\n**Chain starting from CWE-400:**\n- 400 (Uncontrolled Resource Consumption) - ROOT\n\n\n\n### CWE Relationship Diagram\n\n```mermaid\ngraph TD\n    classDef primary fill:#f96,stroke:#333,stroke-width:2px\n    classDef secondary fill:#69f,stroke:#333\n    classDef tertiary fill:#9e9,stroke:#333\n```",
  "criticism": "",
  "resolution": "",
  "relevant_cwes": [
    {
      "metadata": {
        "doc_id": "295",
        "name": "Improper Certificate Validation",
        "source": "sparse"
      },
      "similarity": 19.727027886508075
    },
    {
      "metadata": {
        "doc_id": "379",
        "name": "Creation of Temporary File in Directory with Insecure Permissions",
        "source": "sparse"
      },
      "similarity": 19.44009710191723
    },
    {
      "metadata": {
        "doc_id": "923",
        "name": "Improper Restriction of Communication Channel to Intended Endpoints",
        "source": "sparse"
      },
      "similarity": 17.23849943162619
    },
    {
      "metadata": {
        "doc_id": "328",
        "name": "Use of Weak Hash",
        "source": "sparse"
      },
      "similarity": 17.204385240682058
    },
    {
      "metadata": {
        "doc_id": "732",
        "name": "Incorrect Permission Assignment for Critical Resource",
        "source": "sparse"
      },
      "similarity": 17.106974527822032
    },
    {
      "metadata": {
        "doc_id": "290",
        "name": "Authentication Bypass by Spoofing",
        "source": "sparse"
      },
      "similarity": 16.589462095531786
    },
    {
      "metadata": {
        "doc_id": "250",
        "name": "Execution with Unnecessary Privileges",
        "source": "sparse"
      },
      "similarity": 15.951333636587297
    },
    {
      "metadata": {
        "doc_id": "284",
        "name": "Improper Access Control",
        "source": "sparse"
      },
      "similarity": 15.752467999844386
    },
    {
      "metadata": {
        "doc_id": "69",
        "name": "Improper Handling of Windows ::DATA Alternate Data Stream",
        "type": "Variant",
        "original_content": "The product does not properly prevent access to, or detect usage of, alternate data streams (ADS).",
        "source": "dense",
        "mapping_notes": {
          "usage": "Allowed",
          "rationale": "This CWE entry is at the Variant level of abstraction, which is a preferred level of abstraction for mapping to the root causes of vulnerabilities.",
          "comments": "Carefully read both the name and description to ensure that this mapping is an appropriate fit. Do not try to 'force' a mapping to a lower-level Base/Variant simply to comply with this preferred level of abstraction.",
          "reasons": [
            "Acceptable-Use"
          ]
        },
        "score_info": {
          "retrievers": [
            "dense"
          ],
          "retriever_count": 1,
          "normalized_scores": {
            "dense": 0.5116316249912584
          }
        }
      },
      "similarity": 0.5116316249912584
    },
    {
      "doc_id": "322",
      "text": "CWE-322: Key Exchange without Entity Authentication",
      "score": 3.4361600000000005,
      "metadata": {
        "doc_id": "322",
        "name": "Key Exchange without Entity Authentication",
        "type": "base",
        "original_content": "CWE-322: Key Exchange without Entity Authentication",
        "relationships": [
          {
            "source_id": "322",
            "target_id": "295",
            "label": "PEEROF",
            "properties": {
              "view_id": "1000"
            }
          },
          {
            "source_id": "322",
            "target_id": "923",
            "label": "CANPRECEDE",
            "properties": {
              "view_id": "1000"
            }
          },
          {
            "source_id": "322",
            "target_id": "306",
            "label": "CHILDOF",
            "properties": {
              "ordinal": "Primary",
              "view_id": "1000"
            }
          },
          {
            "source_id": "923",
            "target_id": "322",
            "label": "CANFOLLOW",
            "properties": {
              "view_id": "1000"
            }
          },
          {
            "source_id": "306",
            "target_id": "322",
            "label": "PARENTOF",
            "properties": {
              "ordinal": "Primary",
              "view_id": "1000"
            }
          },
          {
            "source_id": "295",
            "target_id": "322",
            "label": "PEEROF",
            "properties": {
              "view_id": "1000"
            }
          }
        ],
        "score_components": {
          "relationship_chain": 1.0,
          "abstraction_path": 0.5760000000000002,
          "sequence_path": 1.0,
          "peer_group": 0.9
        },
        "abstraction_factor": 1.3,
        "graph_path_info": {
          "path_types": [
            "relationship_chain",
            "abstraction_path_down",
            "vulnerability_sequence_forward",
            "vulnerability_sequence_backward",
            "peer_relationship"
          ],
          "best_paths": {
            "relationship_chain": {
              "path": [
                [
                  "923",
                  "322",
                  "CANFOLLOW"
                ]
              ],
              "score": 1.0,
              "type": "relationship_chain",
              "source": "923"
            },
            "abstraction_path_down": {
              "path": [
                [
                  "287",
                  "306",
                  "PARENTOF"
                ],
                [
                  "306",
                  "322",
                  "PARENTOF"
                ]
              ],
              "score": 0.5760000000000002,
              "type": "abstraction_path_down",
              "source": "287"
            },
            "vulnerability_sequence_forward": {
              "path": [
                [
                  "923",
                  "322",
                  "CANFOLLOW"
                ]
              ],
              "score": 0.9,
              "type": "vulnerability_sequence_forward",
              "source": "923"
            },
            "vulnerability_sequence_backward": {
              "path": [
                [
                  "322",
                  "923",
                  "CANPRECEDE"
                ]
              ],
              "score": 1.0,
              "type": "vulnerability_sequence_backward",
              "source": "923"
            },
            "peer_relationship": {
              "path": [
                [
                  "295",
                  "322",
                  "PEEROF"
                ]
              ],
              "score": 0.9,
              "type": "peer_relationship",
              "source": "295"
            }
          }
        },
        "abstraction_level": "base",
        "position": "before",
        "sources": [
          "graph"
        ],
        "source": "graph",
        "mapping_notes": {
          "usage": "Allowed",
          "rationale": "This CWE entry is at the Base level of abstraction, which is a preferred level of abstraction for mapping to the root causes of vulnerabilities.",
          "comments": "Carefully read both the name and description to ensure that this mapping is an appropriate fit. Do not try to 'force' a mapping to a lower-level Base/Variant simply to comply with this preferred level of abstraction.",
          "reasons": [
            "Acceptable-Use"
          ]
        },
        "score_info": {
          "retrievers": [
            "graph"
          ],
          "retriever_count": 1,
          "normalized_scores": {
            "graph": 3.4361600000000005
          }
        }
      },
      "similarity": 3.4361600000000005
    }
  ],
  "identified_cwes": {
    "analyzer": [
      "CWE-274",
      "CWE-400",
      "CWE-552",
      "CWE-285",
      "CWE-322",
      "CWE-379",
      "CWE-328",
      "CWE-204",
      "CWE-290",
      "CWE-288",
      "CWE-69",
      "CWE-59",
      "CWE-923",
      "CWE-178",
      "CWE-1391",
      "CWE-284",
      "CWE-617",
      "CWE-732",
      "CWE-472",
      "CWE-250",
      "CWE-303",
      "CWE-295"
    ],
    "critic_additional": []
  },
  "keyphrase_cwe_mapping": {}
}