{
  "vulnerability_info": "VulnerabilityInfo(cve_id='CVE-2024-53101', description='In the Linux kernel, the following vulnerability has been resolved fs Fix **uninitialized value issue** in from_kuid and from_kgid ocfs2_setattr() uses attr->ia_mode, attr->ia_uid and attr->ia_gid in a trace point even though ATTR_MODE, ATTR_UID and ATTR_GID arent set. Initialize all fields of newattrs to avoid **uninitialized variables**, by checking if ATTR_MODE, ATTR_UID, ATTR_GID are initialized, otherwise 0.', key_phrases={'rootcause': ['uninitialized value issue', 'uninitialized variables'], 'weakness': '', 'impact': '', 'vector': 'uninitialized variables', 'attacker': '', 'product': 'Linux kernel', 'version': '', 'component': 'ocfs2_setattr()'}, reference_content=\"Based on the provided content, here's an analysis of the vulnerability:\\n\\n**Root Cause:**\\nThe `ocfs2_setattr` function in the Linux kernel's OCFS2 file system driver was using potentially uninitialized values from the `attr` structure (specifically, `attr->ia_mode`, `attr->ia_uid`, and `attr->ia_gid`) in a tracepoint. These values are only valid if the corresponding `ATTR_MODE`, `ATTR_UID`, and `ATTR_GID` flags are set in `attr->ia_valid`. If these flags were not set, the tracepoint would output garbage data from uninitialized stack memory.\\n\\n**Weaknesses/Vulnerabilities Present:**\\n- **Uninitialized Variables:** The core issue is the use of uninitialized variables in a tracepoint. The `ocfs2_setattr` function did not check if the `ATTR_MODE`, `ATTR_UID`, and `ATTR_GID` flags were set in `attr->ia_valid` before using  `attr->ia_mode`, `attr->ia_uid`, and `attr->ia_gid`.\\n- **Information Leak:** While not directly exploitable for privilege escalation, this could leak kernel memory contents through the tracepoint, which is a form of information disclosure.\\n\\n**Impact of Exploitation:**\\n- The primary impact is an information leak from the kernel memory. \\n-  The leaked information might include sensitive data, potentially aiding in further exploitation.\\n- The tracepoint output would be inconsistent and contain unpredictable values, which could cause issues for monitoring and debugging tools.\\n\\n**Attack Vectors:**\\n- The attack vector is triggering the `ocfs2_setattr` function with an `iattr` structure where the `ATTR_MODE`, `ATTR_UID`, and/or `ATTR_GID` flags are not set.\\n- This can occur through any legitimate or malicious file system operation that involves modifying file attributes.\\n\\n**Required Attacker Capabilities/Position:**\\n- An attacker would need the ability to trigger a call to `ocfs2_setattr`, which requires write access to files on an OCFS2 filesystem.\\n- No special privilege is needed.\\n\\n**Additional Notes:**\\n- This vulnerability is related to an information leak and not a crash or privilege escalation.\\n- The fix is to add checks for `ATTR_MODE`, `ATTR_UID`, and `ATTR_GID` flags and, if not set, default to 0 values to avoid uninitialized memory access during the tracepoint.\\n- The syzkaller tool reported this bug.\", similar_info={'cwe_distribution': {}, 'cwe_consensus': '', 'similarity_stats': {'thresholds': [], 'total_samples_by_threshold': {}, 'top_cwes_by_threshold': {}}}, similarity_summary=SimilarityInsight(consensus_cwe='', top_cwes=[], confidence_levels={}, total_samples=0), analysis='', analysis_with_relationships='', criticism='', resolution='', relevant_cwes=[{'metadata': {'doc_id': '457', 'name': 'Use of Uninitialized Variable', 'source': 'sparse', 'original_content': 'The code uses a variable that has not been initialized, leading to unpredictable or unintended results.', 'keyphrase_sources': [{'id': 'rootcause:uninitialized value issue', 'keyphrase': 'uninitialized value issue', 'type': 'rootcause'}, {'id': 'rootcause:uninitialized variables', 'keyphrase': 'uninitialized variables', 'type': 'rootcause'}, {'id': 'vector:uninitialized variables', 'keyphrase': 'uninitialized variables', 'type': 'vector'}, {'id': 'product:Linux kernel', 'keyphrase': 'Linux kernel', 'type': 'product'}, {'id': 'component:ocfs2_setattr()', 'keyphrase': 'ocfs2_setattr()', 'type': 'component'}]}, 'similarity': np.float64(344.4255179491033)}, {'metadata': {'doc_id': '909', 'name': 'Missing Initialization of Resource', 'source': 'sparse', 'original_content': 'The product does not initialize a critical resource.', 'keyphrase_sources': [{'id': 'rootcause:uninitialized value issue', 'keyphrase': 'uninitialized value issue', 'type': 'rootcause'}, {'id': 'rootcause:uninitialized variables', 'keyphrase': 'uninitialized variables', 'type': 'rootcause'}, {'id': 'vector:uninitialized variables', 'keyphrase': 'uninitialized variables', 'type': 'vector'}, {'id': 'product:Linux kernel', 'keyphrase': 'Linux kernel', 'type': 'product'}, {'id': 'component:ocfs2_setattr()', 'keyphrase': 'ocfs2_setattr()', 'type': 'component'}]}, 'similarity': np.float64(332.93341396177476)}, {'metadata': {'doc_id': '456', 'name': 'Missing Initialization of a Variable', 'source': 'sparse', 'original_content': 'The product does not initialize critical variables, which causes the execution environment to use unexpected values.', 'keyphrase_sources': [{'id': 'rootcause:uninitialized variables', 'keyphrase': 'uninitialized variables', 'type': 'rootcause'}, {'id': 'vector:uninitialized variables', 'keyphrase': 'uninitialized variables', 'type': 'vector'}]}, 'similarity': np.float64(309.35252280513157)}, {'metadata': {'doc_id': '824', 'name': 'Access of Uninitialized Pointer', 'source': 'sparse', 'original_content': 'The product accesses or uses a pointer that has not been initialized.', 'keyphrase_sources': [{'id': 'rootcause:uninitialized value issue', 'keyphrase': 'uninitialized value issue', 'type': 'rootcause'}, {'id': 'rootcause:uninitialized variables', 'keyphrase': 'uninitialized variables', 'type': 'rootcause'}, {'id': 'vector:uninitialized variables', 'keyphrase': 'uninitialized variables', 'type': 'vector'}, {'id': 'component:ocfs2_setattr()', 'keyphrase': 'ocfs2_setattr()', 'type': 'component'}]}, 'similarity': np.float64(305.5582594979962)}, {'metadata': {'doc_id': '392', 'name': 'Missing Report of Error Condition', 'source': 'sparse', 'original_content': 'The product encounters an error but does not provide a status code or return value to indicate that an error has occurred.', 'keyphrase_sources': [{'id': 'rootcause:uninitialized value issue', 'keyphrase': 'uninitialized value issue', 'type': 'rootcause'}, {'id': 'product:Linux kernel', 'keyphrase': 'Linux kernel', 'type': 'product'}, {'id': 'component:ocfs2_setattr()', 'keyphrase': 'ocfs2_setattr()', 'type': 'component'}]}, 'similarity': np.float64(302.23784576289313)}, {'metadata': {'doc_id': '665', 'name': 'Improper Initialization', 'source': 'sparse', 'original_content': 'The product does not initialize or incorrectly initializes a resource, which might leave the resource in an unexpected state when it is accessed or used.', 'keyphrase_sources': [{'id': 'rootcause:uninitialized value issue', 'keyphrase': 'uninitialized value issue', 'type': 'rootcause'}, {'id': 'rootcause:uninitialized variables', 'keyphrase': 'uninitialized variables', 'type': 'rootcause'}, {'id': 'vector:uninitialized variables', 'keyphrase': 'uninitialized variables', 'type': 'vector'}, {'id': 'product:Linux kernel', 'keyphrase': 'Linux kernel', 'type': 'product'}, {'id': 'component:ocfs2_setattr()', 'keyphrase': 'ocfs2_setattr()', 'type': 'component'}]}, 'similarity': np.float64(298.3781648915996)}, {'metadata': {'doc_id': '908', 'name': 'Use of Uninitialized Resource', 'source': 'sparse', 'original_content': 'The product uses or accesses a resource that has not been initialized.', 'keyphrase_sources': [{'id': 'product:Linux kernel', 'keyphrase': 'Linux kernel', 'type': 'product'}]}, 'similarity': np.float64(85.97772314668859)}], identified_cwes={'analyzer': [], 'critic_additional': []})",
  "retrieval_results": {
    "has_multiple_keyphrases": true,
    "keyphrase_cwe_sets": {
      "rootcause:uninitialized value issue": {
        "keyphrase": "uninitialized value issue",
        "type": "rootcause",
        "cwes": [
          {
            "metadata": {
              "doc_id": "457",
              "name": "Use of Uninitialized Variable",
              "source": "sparse",
              "original_content": "The code uses a variable that has not been initialized, leading to unpredictable or unintended results.",
              "keyphrase_sources": [
                {
                  "id": "rootcause:uninitialized value issue",
                  "keyphrase": "uninitialized value issue",
                  "type": "rootcause"
                },
                {
                  "id": "rootcause:uninitialized variables",
                  "keyphrase": "uninitialized variables",
                  "type": "rootcause"
                },
                {
                  "id": "vector:uninitialized variables",
                  "keyphrase": "uninitialized variables",
                  "type": "vector"
                },
                {
                  "id": "product:Linux kernel",
                  "keyphrase": "Linux kernel",
                  "type": "product"
                },
                {
                  "id": "component:ocfs2_setattr()",
                  "keyphrase": "ocfs2_setattr()",
                  "type": "component"
                }
              ]
            },
            "similarity": 344.4255179491033
          },
          {
            "metadata": {
              "doc_id": "909",
              "name": "Missing Initialization of Resource",
              "source": "sparse",
              "original_content": "The product does not initialize a critical resource.",
              "keyphrase_sources": [
                {
                  "id": "rootcause:uninitialized value issue",
                  "keyphrase": "uninitialized value issue",
                  "type": "rootcause"
                },
                {
                  "id": "rootcause:uninitialized variables",
                  "keyphrase": "uninitialized variables",
                  "type": "rootcause"
                },
                {
                  "id": "vector:uninitialized variables",
                  "keyphrase": "uninitialized variables",
                  "type": "vector"
                },
                {
                  "id": "product:Linux kernel",
                  "keyphrase": "Linux kernel",
                  "type": "product"
                },
                {
                  "id": "component:ocfs2_setattr()",
                  "keyphrase": "ocfs2_setattr()",
                  "type": "component"
                }
              ]
            },
            "similarity": 332.93341396177476
          },
          {
            "metadata": {
              "doc_id": "824",
              "name": "Access of Uninitialized Pointer",
              "source": "sparse",
              "original_content": "The product accesses or uses a pointer that has not been initialized.",
              "keyphrase_sources": [
                {
                  "id": "rootcause:uninitialized value issue",
                  "keyphrase": "uninitialized value issue",
                  "type": "rootcause"
                },
                {
                  "id": "rootcause:uninitialized variables",
                  "keyphrase": "uninitialized variables",
                  "type": "rootcause"
                },
                {
                  "id": "vector:uninitialized variables",
                  "keyphrase": "uninitialized variables",
                  "type": "vector"
                },
                {
                  "id": "component:ocfs2_setattr()",
                  "keyphrase": "ocfs2_setattr()",
                  "type": "component"
                }
              ]
            },
            "similarity": 305.5582594979962
          },
          {
            "metadata": {
              "doc_id": "392",
              "name": "Missing Report of Error Condition",
              "source": "sparse",
              "original_content": "The product encounters an error but does not provide a status code or return value to indicate that an error has occurred.",
              "keyphrase_sources": [
                {
                  "id": "rootcause:uninitialized value issue",
                  "keyphrase": "uninitialized value issue",
                  "type": "rootcause"
                },
                {
                  "id": "product:Linux kernel",
                  "keyphrase": "Linux kernel",
                  "type": "product"
                },
                {
                  "id": "component:ocfs2_setattr()",
                  "keyphrase": "ocfs2_setattr()",
                  "type": "component"
                }
              ]
            },
            "similarity": 302.23784576289313
          },
          {
            "metadata": {
              "doc_id": "665",
              "name": "Improper Initialization",
              "source": "sparse",
              "original_content": "The product does not initialize or incorrectly initializes a resource, which might leave the resource in an unexpected state when it is accessed or used.",
              "keyphrase_sources": [
                {
                  "id": "rootcause:uninitialized value issue",
                  "keyphrase": "uninitialized value issue",
                  "type": "rootcause"
                },
                {
                  "id": "rootcause:uninitialized variables",
                  "keyphrase": "uninitialized variables",
                  "type": "rootcause"
                },
                {
                  "id": "vector:uninitialized variables",
                  "keyphrase": "uninitialized variables",
                  "type": "vector"
                },
                {
                  "id": "product:Linux kernel",
                  "keyphrase": "Linux kernel",
                  "type": "product"
                },
                {
                  "id": "component:ocfs2_setattr()",
                  "keyphrase": "ocfs2_setattr()",
                  "type": "component"
                }
              ]
            },
            "similarity": 298.3781648915996
          }
        ]
      },
      "rootcause:uninitialized variables": {
        "keyphrase": "uninitialized variables",
        "type": "rootcause",
        "cwes": [
          {
            "metadata": {
              "doc_id": "457",
              "name": "Use of Uninitialized Variable",
              "source": "sparse",
              "original_content": "The code uses a variable that has not been initialized, leading to unpredictable or unintended results."
            },
            "similarity": 343.91926979639356
          },
          {
            "metadata": {
              "doc_id": "909",
              "name": "Missing Initialization of Resource",
              "source": "sparse",
              "original_content": "The product does not initialize a critical resource."
            },
            "similarity": 322.64622373749035
          },
          {
            "metadata": {
              "doc_id": "456",
              "name": "Missing Initialization of a Variable",
              "source": "sparse",
              "original_content": "The product does not initialize critical variables, which causes the execution environment to use unexpected values.",
              "keyphrase_sources": [
                {
                  "id": "rootcause:uninitialized variables",
                  "keyphrase": "uninitialized variables",
                  "type": "rootcause"
                },
                {
                  "id": "vector:uninitialized variables",
                  "keyphrase": "uninitialized variables",
                  "type": "vector"
                }
              ]
            },
            "similarity": 309.35252280513157
          },
          {
            "metadata": {
              "doc_id": "665",
              "name": "Improper Initialization",
              "source": "sparse",
              "original_content": "The product does not initialize or incorrectly initializes a resource, which might leave the resource in an unexpected state when it is accessed or used."
            },
            "similarity": 300.0889827516423
          },
          {
            "metadata": {
              "doc_id": "824",
              "name": "Access of Uninitialized Pointer",
              "source": "sparse",
              "original_content": "The product accesses or uses a pointer that has not been initialized."
            },
            "similarity": 287.83359776473344
          }
        ]
      },
      "vector:uninitialized variables": {
        "keyphrase": "uninitialized variables",
        "type": "vector",
        "cwes": [
          {
            "metadata": {
              "doc_id": "457",
              "name": "Use of Uninitialized Variable",
              "source": "sparse",
              "original_content": "The code uses a variable that has not been initialized, leading to unpredictable or unintended results."
            },
            "similarity": 114.63975659879785
          },
          {
            "metadata": {
              "doc_id": "909",
              "name": "Missing Initialization of Resource",
              "source": "sparse",
              "original_content": "The product does not initialize a critical resource."
            },
            "similarity": 107.54874124583012
          },
          {
            "metadata": {
              "doc_id": "456",
              "name": "Missing Initialization of a Variable",
              "source": "sparse",
              "original_content": "The product does not initialize critical variables, which causes the execution environment to use unexpected values."
            },
            "similarity": 103.11750760171051
          },
          {
            "metadata": {
              "doc_id": "665",
              "name": "Improper Initialization",
              "source": "sparse",
              "original_content": "The product does not initialize or incorrectly initializes a resource, which might leave the resource in an unexpected state when it is accessed or used."
            },
            "similarity": 100.02966091721409
          },
          {
            "metadata": {
              "doc_id": "824",
              "name": "Access of Uninitialized Pointer",
              "source": "sparse",
              "original_content": "The product accesses or uses a pointer that has not been initialized."
            },
            "similarity": 95.94453258824448
          }
        ]
      },
      "product:Linux kernel": {
        "keyphrase": "Linux kernel",
        "type": "product",
        "cwes": [
          {
            "metadata": {
              "doc_id": "909",
              "name": "Missing Initialization of Resource",
              "source": "sparse",
              "original_content": "The product does not initialize a critical resource."
            },
            "similarity": 109.05458565708551
          },
          {
            "metadata": {
              "doc_id": "457",
              "name": "Use of Uninitialized Variable",
              "source": "sparse",
              "original_content": "The code uses a variable that has not been initialized, leading to unpredictable or unintended results."
            },
            "similarity": 104.22915890287868
          },
          {
            "metadata": {
              "doc_id": "392",
              "name": "Missing Report of Error Condition",
              "source": "sparse",
              "original_content": "The product encounters an error but does not provide a status code or return value to indicate that an error has occurred."
            },
            "similarity": 99.23049519467942
          },
          {
            "metadata": {
              "doc_id": "665",
              "name": "Improper Initialization",
              "source": "sparse",
              "original_content": "The product does not initialize or incorrectly initializes a resource, which might leave the resource in an unexpected state when it is accessed or used."
            },
            "similarity": 88.29598686899219
          },
          {
            "metadata": {
              "doc_id": "908",
              "name": "Use of Uninitialized Resource",
              "source": "sparse",
              "original_content": "The product uses or accesses a resource that has not been initialized.",
              "keyphrase_sources": [
                {
                  "id": "product:Linux kernel",
                  "keyphrase": "Linux kernel",
                  "type": "product"
                }
              ]
            },
            "similarity": 85.97772314668859
          }
        ]
      },
      "component:ocfs2_setattr()": {
        "keyphrase": "ocfs2_setattr()",
        "type": "component",
        "cwes": [
          {
            "metadata": {
              "doc_id": "457",
              "name": "Use of Uninitialized Variable",
              "source": "sparse",
              "original_content": "The code uses a variable that has not been initialized, leading to unpredictable or unintended results."
            },
            "similarity": 94.18387340936013
          },
          {
            "metadata": {
              "doc_id": "909",
              "name": "Missing Initialization of Resource",
              "source": "sparse",
              "original_content": "The product does not initialize a critical resource."
            },
            "similarity": 92.59383213060579
          },
          {
            "metadata": {
              "doc_id": "392",
              "name": "Missing Report of Error Condition",
              "source": "sparse",
              "original_content": "The product encounters an error but does not provide a status code or return value to indicate that an error has occurred."
            },
            "similarity": 83.36683405836696
          },
          {
            "metadata": {
              "doc_id": "665",
              "name": "Improper Initialization",
              "source": "sparse",
              "original_content": "The product does not initialize or incorrectly initializes a resource, which might leave the resource in an unexpected state when it is accessed or used."
            },
            "similarity": 80.75770793386077
          },
          {
            "metadata": {
              "doc_id": "824",
              "name": "Access of Uninitialized Pointer",
              "source": "sparse",
              "original_content": "The product accesses or uses a pointer that has not been initialized."
            },
            "similarity": 80.49871876992536
          }
        ]
      }
    },
    "keyphrase_mapping": {
      "457": [
        {
          "id": "rootcause:uninitialized value issue",
          "keyphrase": "uninitialized value issue",
          "type": "rootcause"
        },
        {
          "id": "rootcause:uninitialized variables",
          "keyphrase": "uninitialized variables",
          "type": "rootcause"
        },
        {
          "id": "vector:uninitialized variables",
          "keyphrase": "uninitialized variables",
          "type": "vector"
        },
        {
          "id": "product:Linux kernel",
          "keyphrase": "Linux kernel",
          "type": "product"
        },
        {
          "id": "component:ocfs2_setattr()",
          "keyphrase": "ocfs2_setattr()",
          "type": "component"
        }
      ],
      "909": [
        {
          "id": "rootcause:uninitialized value issue",
          "keyphrase": "uninitialized value issue",
          "type": "rootcause"
        },
        {
          "id": "rootcause:uninitialized variables",
          "keyphrase": "uninitialized variables",
          "type": "rootcause"
        },
        {
          "id": "vector:uninitialized variables",
          "keyphrase": "uninitialized variables",
          "type": "vector"
        },
        {
          "id": "product:Linux kernel",
          "keyphrase": "Linux kernel",
          "type": "product"
        },
        {
          "id": "component:ocfs2_setattr()",
          "keyphrase": "ocfs2_setattr()",
          "type": "component"
        }
      ],
      "824": [
        {
          "id": "rootcause:uninitialized value issue",
          "keyphrase": "uninitialized value issue",
          "type": "rootcause"
        },
        {
          "id": "rootcause:uninitialized variables",
          "keyphrase": "uninitialized variables",
          "type": "rootcause"
        },
        {
          "id": "vector:uninitialized variables",
          "keyphrase": "uninitialized variables",
          "type": "vector"
        },
        {
          "id": "component:ocfs2_setattr()",
          "keyphrase": "ocfs2_setattr()",
          "type": "component"
        }
      ],
      "392": [
        {
          "id": "rootcause:uninitialized value issue",
          "keyphrase": "uninitialized value issue",
          "type": "rootcause"
        },
        {
          "id": "product:Linux kernel",
          "keyphrase": "Linux kernel",
          "type": "product"
        },
        {
          "id": "component:ocfs2_setattr()",
          "keyphrase": "ocfs2_setattr()",
          "type": "component"
        }
      ],
      "665": [
        {
          "id": "rootcause:uninitialized value issue",
          "keyphrase": "uninitialized value issue",
          "type": "rootcause"
        },
        {
          "id": "rootcause:uninitialized variables",
          "keyphrase": "uninitialized variables",
          "type": "rootcause"
        },
        {
          "id": "vector:uninitialized variables",
          "keyphrase": "uninitialized variables",
          "type": "vector"
        },
        {
          "id": "product:Linux kernel",
          "keyphrase": "Linux kernel",
          "type": "product"
        },
        {
          "id": "component:ocfs2_setattr()",
          "keyphrase": "ocfs2_setattr()",
          "type": "component"
        }
      ],
      "456": [
        {
          "id": "rootcause:uninitialized variables",
          "keyphrase": "uninitialized variables",
          "type": "rootcause"
        },
        {
          "id": "vector:uninitialized variables",
          "keyphrase": "uninitialized variables",
          "type": "vector"
        }
      ],
      "908": [
        {
          "id": "product:Linux kernel",
          "keyphrase": "Linux kernel",
          "type": "product"
        }
      ]
    },
    "relevant_cwes": [
      {
        "metadata": {
          "doc_id": "457",
          "name": "Use of Uninitialized Variable",
          "source": "sparse",
          "original_content": "The code uses a variable that has not been initialized, leading to unpredictable or unintended results.",
          "keyphrase_sources": [
            {
              "id": "rootcause:uninitialized value issue",
              "keyphrase": "uninitialized value issue",
              "type": "rootcause"
            },
            {
              "id": "rootcause:uninitialized variables",
              "keyphrase": "uninitialized variables",
              "type": "rootcause"
            },
            {
              "id": "vector:uninitialized variables",
              "keyphrase": "uninitialized variables",
              "type": "vector"
            },
            {
              "id": "product:Linux kernel",
              "keyphrase": "Linux kernel",
              "type": "product"
            },
            {
              "id": "component:ocfs2_setattr()",
              "keyphrase": "ocfs2_setattr()",
              "type": "component"
            }
          ]
        },
        "similarity": 344.4255179491033
      },
      {
        "metadata": {
          "doc_id": "909",
          "name": "Missing Initialization of Resource",
          "source": "sparse",
          "original_content": "The product does not initialize a critical resource.",
          "keyphrase_sources": [
            {
              "id": "rootcause:uninitialized value issue",
              "keyphrase": "uninitialized value issue",
              "type": "rootcause"
            },
            {
              "id": "rootcause:uninitialized variables",
              "keyphrase": "uninitialized variables",
              "type": "rootcause"
            },
            {
              "id": "vector:uninitialized variables",
              "keyphrase": "uninitialized variables",
              "type": "vector"
            },
            {
              "id": "product:Linux kernel",
              "keyphrase": "Linux kernel",
              "type": "product"
            },
            {
              "id": "component:ocfs2_setattr()",
              "keyphrase": "ocfs2_setattr()",
              "type": "component"
            }
          ]
        },
        "similarity": 332.93341396177476
      },
      {
        "metadata": {
          "doc_id": "456",
          "name": "Missing Initialization of a Variable",
          "source": "sparse",
          "original_content": "The product does not initialize critical variables, which causes the execution environment to use unexpected values.",
          "keyphrase_sources": [
            {
              "id": "rootcause:uninitialized variables",
              "keyphrase": "uninitialized variables",
              "type": "rootcause"
            },
            {
              "id": "vector:uninitialized variables",
              "keyphrase": "uninitialized variables",
              "type": "vector"
            }
          ]
        },
        "similarity": 309.35252280513157
      },
      {
        "metadata": {
          "doc_id": "824",
          "name": "Access of Uninitialized Pointer",
          "source": "sparse",
          "original_content": "The product accesses or uses a pointer that has not been initialized.",
          "keyphrase_sources": [
            {
              "id": "rootcause:uninitialized value issue",
              "keyphrase": "uninitialized value issue",
              "type": "rootcause"
            },
            {
              "id": "rootcause:uninitialized variables",
              "keyphrase": "uninitialized variables",
              "type": "rootcause"
            },
            {
              "id": "vector:uninitialized variables",
              "keyphrase": "uninitialized variables",
              "type": "vector"
            },
            {
              "id": "component:ocfs2_setattr()",
              "keyphrase": "ocfs2_setattr()",
              "type": "component"
            }
          ]
        },
        "similarity": 305.5582594979962
      },
      {
        "metadata": {
          "doc_id": "392",
          "name": "Missing Report of Error Condition",
          "source": "sparse",
          "original_content": "The product encounters an error but does not provide a status code or return value to indicate that an error has occurred.",
          "keyphrase_sources": [
            {
              "id": "rootcause:uninitialized value issue",
              "keyphrase": "uninitialized value issue",
              "type": "rootcause"
            },
            {
              "id": "product:Linux kernel",
              "keyphrase": "Linux kernel",
              "type": "product"
            },
            {
              "id": "component:ocfs2_setattr()",
              "keyphrase": "ocfs2_setattr()",
              "type": "component"
            }
          ]
        },
        "similarity": 302.23784576289313
      },
      {
        "metadata": {
          "doc_id": "665",
          "name": "Improper Initialization",
          "source": "sparse",
          "original_content": "The product does not initialize or incorrectly initializes a resource, which might leave the resource in an unexpected state when it is accessed or used.",
          "keyphrase_sources": [
            {
              "id": "rootcause:uninitialized value issue",
              "keyphrase": "uninitialized value issue",
              "type": "rootcause"
            },
            {
              "id": "rootcause:uninitialized variables",
              "keyphrase": "uninitialized variables",
              "type": "rootcause"
            },
            {
              "id": "vector:uninitialized variables",
              "keyphrase": "uninitialized variables",
              "type": "vector"
            },
            {
              "id": "product:Linux kernel",
              "keyphrase": "Linux kernel",
              "type": "product"
            },
            {
              "id": "component:ocfs2_setattr()",
              "keyphrase": "ocfs2_setattr()",
              "type": "component"
            }
          ]
        },
        "similarity": 298.3781648915996
      },
      {
        "metadata": {
          "doc_id": "908",
          "name": "Use of Uninitialized Resource",
          "source": "sparse",
          "original_content": "The product uses or accesses a resource that has not been initialized.",
          "keyphrase_sources": [
            {
              "id": "product:Linux kernel",
              "keyphrase": "Linux kernel",
              "type": "product"
            }
          ]
        },
        "similarity": 85.97772314668859
      }
    ],
    "enhanced_query": "# Vulnerability Description\n\n    In the Linux kernel, the following vulnerability has been resolved fs Fix **uninitialized value issue** in from_kuid and from_kgid ocfs2_setattr() uses attr->ia_mode, attr->ia_uid and attr->ia_gid in a trace point even though ATTR_MODE, ATTR_UID and ATTR_GID arent set. Initialize all fields of newattrs to avoid **uninitialized variables**, by checking if ATTR_MODE, ATTR_UID, ATTR_GID are initialized, otherwise 0.\n\n    # Keyphrase-Specific CWE Analysis\n    This vulnerability contains multiple keyphrases that may map to different CWEs. \n    Please analyze each keyphrase separately and determine the most appropriate CWE(s) for each.\n\n    ## ROOTCAUSE: 'uninitialized value issue'\n\nRelevant CWEs for this ROOTCAUSE:\n\n### 1. CWE-457: Use of Uninitialized Variable (Score: 344.43)\n\nThe code uses a variable that has not been initialized, leading to unpredictable or unintended results....\n\n### 2. CWE-909: Missing Initialization of Resource (Score: 332.93)\n\nThe product does not initialize a critical resource....\n\n### 3. CWE-824: Access of Uninitialized Pointer (Score: 305.56)\n\nThe product accesses or uses a pointer that has not been initialized....\n\n### 4. CWE-392: Missing Report of Error Condition (Score: 302.24)\n\nThe product encounters an error but does not provide a status code or return value to indicate that an error has occurred....\n\n### 5. CWE-665: Improper Initialization (Score: 298.38)\n\nThe product does not initialize or incorrectly initializes a resource, which might leave the resource in an unexpected state when it is accessed or used....\n\n## ROOTCAUSE: 'uninitialized variables'\n\nRelevant CWEs for this ROOTCAUSE:\n\n### 1. CWE-457: Use of Uninitialized Variable (Score: 344.43)\n\nThe code uses a variable that has not been initialized, leading to unpredictable or unintended results....\n\n### 2. CWE-909: Missing Initialization of Resource (Score: 332.93)\n\nThe product does not initialize a critical resource....\n\n### 3. CWE-456: Missing Initialization of a Variable (Score: 309.35)\n\nThe product does not initialize critical variables, which causes the execution environment to use unexpected values....\n\n### 4. CWE-824: Access of Uninitialized Pointer (Score: 305.56)\n\nThe product accesses or uses a pointer that has not been initialized....\n\n### 5. CWE-665: Improper Initialization (Score: 298.38)\n\nThe product does not initialize or incorrectly initializes a resource, which might leave the resource in an unexpected state when it is accessed or used....\n\n## VECTOR: 'uninitialized variables'\n\nRelevant CWEs for this VECTOR:\n\n### 1. CWE-457: Use of Uninitialized Variable (Score: 344.43)\n\nThe code uses a variable that has not been initialized, leading to unpredictable or unintended results....\n\n### 2. CWE-909: Missing Initialization of Resource (Score: 332.93)\n\nThe product does not initialize a critical resource....\n\n### 3. CWE-456: Missing Initialization of a Variable (Score: 309.35)\n\nThe product does not initialize critical variables, which causes the execution environment to use unexpected values....\n\n### 4. CWE-824: Access of Uninitialized Pointer (Score: 305.56)\n\nThe product accesses or uses a pointer that has not been initialized....\n\n### 5. CWE-665: Improper Initialization (Score: 298.38)\n\nThe product does not initialize or incorrectly initializes a resource, which might leave the resource in an unexpected state when it is accessed or used....\n\n## PRODUCT: 'Linux kernel'\n\nRelevant CWEs for this PRODUCT:\n\n### 1. CWE-457: Use of Uninitialized Variable (Score: 344.43)\n\nThe code uses a variable that has not been initialized, leading to unpredictable or unintended results....\n\n### 2. CWE-909: Missing Initialization of Resource (Score: 332.93)\n\nThe product does not initialize a critical resource....\n\n### 3. CWE-392: Missing Report of Error Condition (Score: 302.24)\n\nThe product encounters an error but does not provide a status code or return value to indicate that an error has occurred....\n\n### 4. CWE-665: Improper Initialization (Score: 298.38)\n\nThe product does not initialize or incorrectly initializes a resource, which might leave the resource in an unexpected state when it is accessed or used....\n\n### 5. CWE-908: Use of Uninitialized Resource (Score: 85.98)\n\nThe product uses or accesses a resource that has not been initialized....\n\n## COMPONENT: 'ocfs2_setattr()'\n\nRelevant CWEs for this COMPONENT:\n\n### 1. CWE-457: Use of Uninitialized Variable (Score: 344.43)\n\nThe code uses a variable that has not been initialized, leading to unpredictable or unintended results....\n\n### 2. CWE-909: Missing Initialization of Resource (Score: 332.93)\n\nThe product does not initialize a critical resource....\n\n### 3. CWE-824: Access of Uninitialized Pointer (Score: 305.56)\n\nThe product accesses or uses a pointer that has not been initialized....\n\n### 4. CWE-392: Missing Report of Error Condition (Score: 302.24)\n\nThe product encounters an error but does not provide a status code or return value to indicate that an error has occurred....\n\n### 5. CWE-665: Improper Initialization (Score: 298.38)\n\nThe product does not initialize or incorrectly initializes a resource, which might leave the resource in an unexpected state when it is accessed or used....\n\n\n    # Analysis Instructions\n    1. For each keyphrase, identify the most appropriate CWE(s) that represent the weakness.\n    2. Consider how the different keyphrases might relate to each other in the vulnerability chain.\n    3. Provide a final determination of primary CWE(s) and any secondary CWEs.\n    4. Format your response using the standard analysis template.\n\n    Please analyze how these different weaknesses interact and provide a comprehensive CWE classification.\n    "
  },
  "retrieval_time": 1.0713098049163818
}