{
  "cve_id": "CVE-2025-25797",
  "description": "SeaCMS v13.3 was discovered to contain a remote code execution (RCE) vulnerability via the component admin_smtp.php.",
  "key_phrases": {
    "rootcause": "",
    "weakness": "",
    "impact": "remote code execution",
    "vector": "",
    "attacker": "",
    "product": "SeaCMS",
    "version": "v13.3",
    "component": "admin_smtp.php"
  },
  "reference_content": null,
  "similar_info": {
    "cwe_distribution": {},
    "cwe_consensus": "",
    "similarity_stats": {
      "thresholds": [],
      "total_samples_by_threshold": {},
      "top_cwes_by_threshold": {}
    }
  },
  "similarity_summary": {
    "consensus_cwe": "",
    "top_cwes": [],
    "confidence_levels": {},
    "total_samples": 0
  },
  "analysis": "# Summary\n| CWE ID | CWE Name | Confidence | CWE Abstraction Level | CWE Vulnerability Mapping Label | CWE-Vulnerability Mapping Notes |\n|---|---|---|---|---|---|\n| CWE-96 | Improper Neutralization of Directives in Statically Saved Code ('Static Code Injection') | 0.7 | Base | Primary | Allowed |\n\n## Evidence and Confidence\n\n*   **Confidence Score:** 0.7\n*   **Evidence Strength:** LOW\n\n## Relationship Analysis\nThe primary identified CWE is CWE-96, which deals with the improper neutralization of directives in statically saved code, leading to static code injection. While there are many potential related CWEs, without specific details on the injected code or the exact mechanism, it's difficult to form a comprehensive chain or consider alternative classifications. The selection is based on the limited information provided, favoring the base-level CWE-96.\n\n```mermaid\ngraph TD\n    cwe96[\"CWE-96: Improper Neutralization of Directives in Statically Saved Code ('Static Code Injection')\"]\n    \n    classDef primary fill:#f96,stroke:#333,stroke-width:2px\n    class cwe96 primary\n```\n\n## Vulnerability Chain\nThe vulnerability chain is relatively simple:\n1.  **Root Cause:** Improper neutralization of directives in statically saved code (CWE-96).\n2.  **Impact:** Remote code execution.\n\nThe provided information lacks detail to expand this chain further.\n\n## Summary of Analysis\nThe analysis is based on the limited information provided in the vulnerability description, which indicates a remote code execution (RCE) vulnerability in SeaCMS v13.3 via the admin_smtp.php component. The key phrase \"remote code execution\" suggests code injection, and the retriever results point towards CWE-96 (Improper Neutralization of Directives in Statically Saved Code) as a potential candidate.\n\nGiven the limited evidence, the selection of CWE-96 is based on the following:\n*   The vulnerability description specifies RCE, suggesting code injection.\n*   The retriever results identify CWE-96 as a relevant CWE with a base abstraction level, which is preferred.\n\nThe confidence score is moderate (0.7) due to the lack of detailed information. Additional analysis would be needed to confirm this assessment.\n\nRelevant CWE Information:\n\n# Enhanced Context (25 CWEs)\nThe following CWEs were identified as potentially relevant to this vulnerability:\n\n## CWE-96: Improper Neutralization of Directives in Statically Saved Code ('Static Code Injection')\n**Abstraction Level**: Base\n**Similarity Score**: 0.78\n**Source**: dense\n\n**Description**:\nThe product receives input from an upstream component, but it does not neutralize or incorrectly neutralizes code syntax before inserting the input into an executable resource, such as a library, configuration file, or template.\n\n**Mapping Guidance**:\n- Usage: Allowed\n- Rationale: This CWE entry is at the Base level of abstraction, which is a preferred level of abstraction for mapping to the root causes of vulnerabilities.\n\n### Other CWEs Considered But Not Used\n*   **CWE-434: Unrestricted Upload of File with Dangerous Type**: While file uploads can lead to RCE, there's no explicit mention of file uploads in the description.\n*   **CWE-95: Improper Neutralization of Directives in Dynamically Evaluated Code ('Eval Injection')**: This involves dynamic evaluation. The description doesn't provide enough information to distinguish between static and dynamic code injection, but CWE-96 seems slightly more applicable given that it involves a specific file.\n*   **CWE-78: Improper Neutralization of Special Elements used in an OS Command ('OS Command Injection')**: This is specific to OS commands, which isn't explicitly indicated.\n*   **CWE-89: Improper Neutralization of Special Elements used in an SQL Command ('SQL Injection')**: While SQL injection is a common vulnerability, the description does not suggest anything related to Databases or SQL.\n*   **CWE-73: External Control of File Name or Path**: This is related to path manipulation, which is not directly indicated in the description.\n*   **CWE-74: Improper Neutralization of Special Elements in Output Used by a Downstream Component ('Injection')**: This is a more general injection category and not as specific as CWE-96.\n*   **CWE-77: Improper Neutralization of Special Elements used in a Command ('Command Injection')**: This is a more general command injection category, and not as specific as CWE-96.\n*   **CWE-1336: Improper Neutralization of Special Elements Used in a Template Engine**: This requires the use of a template engine, which is not specified in the description.\n*   **CWE-1236: Improper Neutralization of Formula Elements in a CSV File**: This is specific to CSV files, which aren't mentioned in the description.\n*   **CWE-425: Direct Request ('Forced Browsing')**: This relates to authorization issues, not directly code injection.\n*   **CWE-184: Incomplete List of Disallowed Inputs and CWE-183: Permissive List of Allowed Inputs**: These relate to input validation, which is not the primary issue.\n*   **CWE-22: Improper Limitation of a Pathname to a Restricted Directory ('Path Traversal') and CWE-41: Improper Resolution of Path Equivalence**: These are related to path traversal, which is not directly indicated in the description.\n*   **CWE-116: Improper Encoding or Escaping of Output**: This relates to encoding, which is not the primary issue.\n*   **CWE-472: External Control of Assumed-Immutable Web Parameter**: This relates to web parameters, which is not directly code injection.\n*   **CWE-93: Improper Neutralization of CRLF Sequences ('CRLF Injection')**: This relates to CRLF injection which is not apparent.\n*   **CWE-178: Improper Handling of Case Sensitivity**: This relates to case sensitivity which is not apparent.\n*   **CWE-790: Improper Filtering of Special Elements**: This is too generic to be useful.\n*   **CWE-502: Deserialization of Untrusted Data**: This requires deserialization, which is not apparent.\n*   **CWE-138: Improper Neutralization of Special Elements**: This is too generic to be useful.\n*   **CWE-94: Improper Control of Generation of Code ('Code Injection')**: This is too generic to be useful.",
  "analysis_with_relationships": "# Summary\n| CWE ID | CWE Name | Confidence | CWE Abstraction Level | CWE Vulnerability Mapping Label | CWE-Vulnerability Mapping Notes |\n|---|---|---|---|---|---|\n| CWE-96 | Improper Neutralization of Directives in Statically Saved Code ('Static Code Injection') | 0.7 | Base | Primary | Allowed |\n\n## Evidence and Confidence\n\n*   **Confidence Score:** 0.7\n*   **Evidence Strength:** LOW\n\n## Relationship Analysis\nThe primary identified CWE is CWE-96, which deals with the improper neutralization of directives in statically saved code, leading to static code injection. While there are many potential related CWEs, without specific details on the injected code or the exact mechanism, it's difficult to form a comprehensive chain or consider alternative classifications. The selection is based on the limited information provided, favoring the base-level CWE-96.\n\n```mermaid\ngraph TD\n    cwe96[\"CWE-96: Improper Neutralization of Directives in Statically Saved Code ('Static Code Injection')\"]\n    \n    classDef primary fill:#f96,stroke:#333,stroke-width:2px\n    class cwe96 primary\n```\n\n## Vulnerability Chain\nThe vulnerability chain is relatively simple:\n1.  **Root Cause:** Improper neutralization of directives in statically saved code (CWE-96).\n2.  **Impact:** Remote code execution.\n\nThe provided information lacks detail to expand this chain further.\n\n## Summary of Analysis\nThe analysis is based on the limited information provided in the vulnerability description, which indicates a remote code execution (RCE) vulnerability in SeaCMS v13.3 via the admin_smtp.php component. The key phrase \"remote code execution\" suggests code injection, and the retriever results point towards CWE-96 (Improper Neutralization of Directives in Statically Saved Code) as a potential candidate.\n\nGiven the limited evidence, the selection of CWE-96 is based on the following:\n*   The vulnerability description specifies RCE, suggesting code injection.\n*   The retriever results identify CWE-96 as a relevant CWE with a base abstraction level, which is preferred.\n\nThe confidence score is moderate (0.7) due to the lack of detailed information. Additional analysis would be needed to confirm this assessment.\n\nRelevant CWE Information:\n\n# Enhanced Context (25 CWEs)\nThe following CWEs were identified as potentially relevant to this vulnerability:\n\n## CWE-96: Improper Neutralization of Directives in Statically Saved Code ('Static Code Injection')\n**Abstraction Level**: Base\n**Similarity Score**: 0.78\n**Source**: dense\n\n**Description**:\nThe product receives input from an upstream component, but it does not neutralize or incorrectly neutralizes code syntax before inserting the input into an executable resource, such as a library, configuration file, or template.\n\n**Mapping Guidance**:\n- Usage: Allowed\n- Rationale: This CWE entry is at the Base level of abstraction, which is a preferred level of abstraction for mapping to the root causes of vulnerabilities.\n\n### Other CWEs Considered But Not Used\n*   **CWE-434: Unrestricted Upload of File with Dangerous Type**: While file uploads can lead to RCE, there's no explicit mention of file uploads in the description.\n*   **CWE-95: Improper Neutralization of Directives in Dynamically Evaluated Code ('Eval Injection')**: This involves dynamic evaluation. The description doesn't provide enough information to distinguish between static and dynamic code injection, but CWE-96 seems slightly more applicable given that it involves a specific file.\n*   **CWE-78: Improper Neutralization of Special Elements used in an OS Command ('OS Command Injection')**: This is specific to OS commands, which isn't explicitly indicated.\n*   **CWE-89: Improper Neutralization of Special Elements used in an SQL Command ('SQL Injection')**: While SQL injection is a common vulnerability, the description does not suggest anything related to Databases or SQL.\n*   **CWE-73: External Control of File Name or Path**: This is related to path manipulation, which is not directly indicated in the description.\n*   **CWE-74: Improper Neutralization of Special Elements in Output Used by a Downstream Component ('Injection')**: This is a more general injection category and not as specific as CWE-96.\n*   **CWE-77: Improper Neutralization of Special Elements used in a Command ('Command Injection')**: This is a more general command injection category, and not as specific as CWE-96.\n*   **CWE-1336: Improper Neutralization of Special Elements Used in a Template Engine**: This requires the use of a template engine, which is not specified in the description.\n*   **CWE-1236: Improper Neutralization of Formula Elements in a CSV File**: This is specific to CSV files, which aren't mentioned in the description.\n*   **CWE-425: Direct Request ('Forced Browsing')**: This relates to authorization issues, not directly code injection.\n*   **CWE-184: Incomplete List of Disallowed Inputs and CWE-183: Permissive List of Allowed Inputs**: These relate to input validation, which is not the primary issue.\n*   **CWE-22: Improper Limitation of a Pathname to a Restricted Directory ('Path Traversal') and CWE-41: Improper Resolution of Path Equivalence**: These are related to path traversal, which is not directly indicated in the description.\n*   **CWE-116: Improper Encoding or Escaping of Output**: This relates to encoding, which is not the primary issue.\n*   **CWE-472: External Control of Assumed-Immutable Web Parameter**: This relates to web parameters, which is not directly code injection.\n*   **CWE-93: Improper Neutralization of CRLF Sequences ('CRLF Injection')**: This relates to CRLF injection which is not apparent.\n*   **CWE-178: Improper Handling of Case Sensitivity**: This relates to case sensitivity which is not apparent.\n*   **CWE-790: Improper Filtering of Special Elements**: This is too generic to be useful.\n*   **CWE-502: Deserialization of Untrusted Data**: This requires deserialization, which is not apparent.\n*   **CWE-138: Improper Neutralization of Special Elements**: This is too generic to be useful.\n*   **CWE-94: Improper Control of Generation of Code ('Code Injection')**: This is too generic to be useful.\n\n\n## CWE Relationship Analysis\n\nCurrent CWEs represent these abstraction levels: .\n\n\n### Vulnerability Chain Analysis\n\n**Chain starting from CWE-94:**\n- 94 (Improper Control of Generation of Code ('Code Injection')) - ROOT\n\n\n**Chain starting from CWE-93:**\n- 93 (Improper Neutralization of CRLF Sequences ('CRLF Injection')) - ROOT\n\n\n\n### CWE Relationship Diagram\n\n```mermaid\ngraph TD\n    classDef primary fill:#f96,stroke:#333,stroke-width:2px\n    classDef secondary fill:#69f,stroke:#333\n    classDef tertiary fill:#9e9,stroke:#333\n```",
  "criticism": "",
  "resolution": "",
  "relevant_cwes": [
    {
      "metadata": {
        "doc_id": "96",
        "name": "Improper Neutralization of Directives in Statically Saved Code ('Static Code Injection')",
        "source": "sparse"
      },
      "similarity": 47.1871988144239
    },
    {
      "metadata": {
        "doc_id": "790",
        "name": "Improper Filtering of Special Elements",
        "source": "sparse"
      },
      "similarity": 33.83406258639027
    },
    {
      "metadata": {
        "doc_id": "95",
        "name": "Improper Neutralization of Directives in Dynamically Evaluated Code ('Eval Injection')",
        "source": "sparse"
      },
      "similarity": 32.93288288303527
    },
    {
      "metadata": {
        "doc_id": "78",
        "name": "Improper Neutralization of Special Elements used in an OS Command ('OS Command Injection')",
        "source": "sparse"
      },
      "similarity": 32.52135770725598
    },
    {
      "metadata": {
        "doc_id": "434",
        "name": "Unrestricted Upload of File with Dangerous Type",
        "source": "sparse"
      },
      "similarity": 32.17317139644764
    },
    {
      "metadata": {
        "doc_id": "1336",
        "name": "Improper Neutralization of Special Elements Used in a Template Engine",
        "source": "sparse"
      },
      "similarity": 32.04324856390241
    },
    {
      "metadata": {
        "doc_id": "77",
        "name": "Improper Neutralization of Special Elements used in a Command ('Command Injection')",
        "source": "sparse"
      },
      "similarity": 31.62002114418649
    },
    {
      "metadata": {
        "doc_id": "502",
        "name": "Deserialization of Untrusted Data",
        "source": "sparse"
      },
      "similarity": 31.45480587941132
    },
    {
      "metadata": {
        "doc_id": "89",
        "name": "Improper Neutralization of Special Elements used in an SQL Command ('SQL Injection')",
        "type": "Base",
        "original_content": "The product constructs all or part of an SQL command using externally-influenced input from an upstream component, but it does not neutralize or incorrectly neutralizes special elements that could modify the intended SQL command when it is sent to a downstream component. Without sufficient removal or quoting of SQL syntax in user-controllable inputs, the generated SQL query can cause those inputs to be interpreted as SQL instead of ordinary user data.",
        "source": "dense",
        "mapping_notes": {
          "usage": "Allowed",
          "rationale": "This CWE entry is at the Base level of abstraction, which is a preferred level of abstraction for mapping to the root causes of vulnerabilities.",
          "comments": "Carefully read both the name and description to ensure that this mapping is an appropriate fit. Do not try to 'force' a mapping to a lower-level Base/Variant simply to comply with this preferred level of abstraction.",
          "reasons": [
            "Acceptable-Use"
          ]
        },
        "score_info": {
          "retrievers": [
            "dense",
            "graph"
          ],
          "retriever_count": 2,
          "normalized_scores": {
            "dense": 0.5808719756107832,
            "graph": 1.9250912866295433
          }
        }
      },
      "similarity": 0.5808719756107832
    },
    {
      "doc_id": "73",
      "text": "CWE-73: External Control of File Name or Path",
      "score": 2.2100000000000004,
      "metadata": {
        "doc_id": "73",
        "name": "External Control of File Name or Path",
        "type": "base",
        "original_content": "CWE-73: External Control of File Name or Path",
        "relationships": [
          {
            "source_id": "73",
            "target_id": "114",
            "label": "PARENTOF",
            "properties": {
              "ordinal": "Primary",
              "view_id": "1000"
            }
          },
          {
            "source_id": "73",
            "target_id": "59",
            "label": "CANPRECEDE",
            "properties": {
              "view_id": "1000"
            }
          },
          {
            "source_id": "73",
            "target_id": "434",
            "label": "CANPRECEDE",
            "properties": {
              "view_id": "1000"
            }
          },
          {
            "source_id": "73",
            "target_id": "98",
            "label": "CANPRECEDE",
            "properties": {
              "view_id": "1000"
            }
          },
          {
            "source_id": "73",
            "target_id": "41",
            "label": "CANPRECEDE",
            "properties": {
              "view_id": "1000"
            }
          },
          {
            "source_id": "73",
            "target_id": "22",
            "label": "CANPRECEDE",
            "properties": {
              "view_id": "1000"
            }
          },
          {
            "source_id": "73",
            "target_id": "20",
            "label": "CHILDOF",
            "properties": {
              "ordinal": "Primary",
              "view_id": "700"
            }
          },
          {
            "source_id": "73",
            "target_id": "610",
            "label": "CHILDOF",
            "properties": {
              "view_id": "1000"
            }
          },
          {
            "source_id": "73",
            "target_id": "642",
            "label": "CHILDOF",
            "properties": {
              "ordinal": "Primary",
              "view_id": "1000"
            }
          },
          {
            "source_id": "99",
            "target_id": "73",
            "label": "CANALSOBE",
            "properties": {
              "view_id": "1000"
            }
          },
          {
            "source_id": "98",
            "target_id": "73",
            "label": "CANFOLLOW",
            "properties": {
              "view_id": "1000"
            }
          },
          {
            "source_id": "642",
            "target_id": "73",
            "label": "PARENTOF",
            "properties": {
              "ordinal": "Primary",
              "view_id": "1000"
            }
          },
          {
            "source_id": "610",
            "target_id": "73",
            "label": "PARENTOF",
            "properties": {
              "view_id": "1000"
            }
          },
          {
            "source_id": "59",
            "target_id": "73",
            "label": "CANFOLLOW",
            "properties": {
              "view_id": "1000"
            }
          },
          {
            "source_id": "434",
            "target_id": "73",
            "label": "CANFOLLOW",
            "properties": {
              "view_id": "1000"
            }
          },
          {
            "source_id": "41",
            "target_id": "73",
            "label": "CANFOLLOW",
            "properties": {
              "view_id": "1000"
            }
          },
          {
            "source_id": "22",
            "target_id": "73",
            "label": "CANFOLLOW",
            "properties": {
              "view_id": "1000"
            }
          },
          {
            "source_id": "20",
            "target_id": "73",
            "label": "PARENTOF",
            "properties": {
              "ordinal": "Primary",
              "view_id": "700"
            }
          },
          {
            "source_id": "114",
            "target_id": "73",
            "label": "CHILDOF",
            "properties": {
              "ordinal": "Primary",
              "view_id": "1000"
            }
          }
        ],
        "score_components": {
          "relationship_chain": 1.0,
          "sequence_path": 1.0
        },
        "abstraction_factor": 1.3,
        "graph_path_info": {
          "path_types": [
            "relationship_chain",
            "vulnerability_sequence_forward",
            "vulnerability_sequence_backward"
          ],
          "best_paths": {
            "relationship_chain": {
              "path": [
                [
                  "434",
                  "73",
                  "CANFOLLOW"
                ]
              ],
              "score": 1.0,
              "type": "relationship_chain",
              "source": "434"
            },
            "vulnerability_sequence_forward": {
              "path": [
                [
                  "434",
                  "73",
                  "CANFOLLOW"
                ]
              ],
              "score": 0.9,
              "type": "vulnerability_sequence_forward",
              "source": "434"
            },
            "vulnerability_sequence_backward": {
              "path": [
                [
                  "73",
                  "434",
                  "CANPRECEDE"
                ]
              ],
              "score": 1.0,
              "type": "vulnerability_sequence_backward",
              "source": "434"
            }
          }
        },
        "position": "before",
        "sources": [
          "graph"
        ],
        "source": "graph",
        "mapping_notes": {
          "usage": "Allowed",
          "rationale": "This CWE entry is at the Base level of abstraction, which is a preferred level of abstraction for mapping to the root causes of vulnerabilities.",
          "comments": "Carefully read both the name and description to ensure that this mapping is an appropriate fit. Do not try to 'force' a mapping to a lower-level Base/Variant simply to comply with this preferred level of abstraction.",
          "reasons": [
            "Acceptable-Use"
          ]
        },
        "score_info": {
          "retrievers": [
            "graph"
          ],
          "retriever_count": 1,
          "normalized_scores": {
            "graph": 2.2100000000000004
          }
        }
      },
      "similarity": 2.2100000000000004
    }
  ],
  "identified_cwes": {
    "analyzer": [
      "CWE-94",
      "CWE-93",
      "CWE-1336",
      "CWE-95",
      "CWE-790",
      "CWE-74",
      "CWE-184",
      "CWE-183",
      "CWE-89",
      "CWE-77",
      "CWE-73",
      "CWE-1236",
      "CWE-425",
      "CWE-41",
      "CWE-434",
      "CWE-178",
      "CWE-78",
      "CWE-138",
      "CWE-96",
      "CWE-502",
      "CWE-116",
      "CWE-22",
      "CWE-472"
    ],
    "critic_additional": []
  },
  "keyphrase_cwe_mapping": {}
}