{
  "vulnerability_info": "VulnerabilityInfo(cve_id='CVE-2025-0813', description='CWE-287 **Improper Authentication vulnerability** exists that could cause an Authentication Bypass when an unauthorized user without permission rights has physical access to the EPAS-UI computer and is able to reboot the workstation and interrupt the normal boot process.', key_phrases={'rootcause': ['Improper Authentication vulnerability', 'authentication bypass'], 'weakness': '', 'impact': 'Authentication Bypass', 'vector': ['physical access to EPAS-UI computer', 'interrupt normal boot process', 'reboot workstation'], 'attacker': 'unauthorized user without permission rights', 'product': '', 'version': '', 'component': ''}, reference_content='## Analysis of CVE-2025-0813 Content\\n\\nThis content is **RELEVANT** to CVE-2025-0813 and provides more detail than the official CVE description.\\n\\n**Root cause of vulnerability:**\\n\\nImproper Authentication vulnerability exists.\\n\\n**Weaknesses/vulnerabilities present:**\\n\\n*   Authentication Bypass\\n*   CWE-287: Improper Authentication\\n\\n**Impact of exploitation:**\\n\\nAn attacker could take partial to full control of EPAS-UI.\\n\\n**Attack vectors:**\\n\\n*   Physical access to the EPAS-UI computer.\\n*   Ability to reboot the workstation and interrupt the normal boot process.\\n\\n**Required attacker capabilities/position:**\\n\\n*   Unauthorized user without permission rights.\\n*   Physical access to the EPAS-UI computer.\\n\\n**Mitigation or fix:**\\n\\n*   **Patch:** Upgrade to version 2.10 of EcoStruxure\u2122 Power Automation System User Interface (EPAS-UI).\\n*   **Workaround:**\\n    1.  Login with Admin privileges.\\n    2.  Go to the folder C:\\\\MCIS\\\\Bin\\n    3.  Rename the file \u2018MCIS.chm\u2019 to \u2018MCIS.old\u2019\\n    4.  Restart the machine.\\n\\n**CVSS Scores:**\\n\\n*   CVSS v3.1 Base Score: 6.8 (Medium) - CVSS:3.1/AV:P/AC:L/PR:N/UI:N/S:U/C:H/I:H/A:H\\n*   CVSS v4.0 Base Score: 7.0 (High) - CVSS:4.0/AV:P/AC:L/AT:N/PR:N/UI:N/VC:H/VI:H/VA:H/SC:N/SI:N/SA:N\\n\\n**Affected Products and Versions:**\\n\\n*   EcoStruxure\u2122 Power Automation System User Interface (EPAS-UI) - Secured Versions v2.1 up to and including v2.9', similar_info={'cwe_distribution': {}, 'cwe_consensus': '', 'similarity_stats': {'thresholds': [], 'total_samples_by_threshold': {}, 'top_cwes_by_threshold': {}}}, similarity_summary=SimilarityInsight(consensus_cwe='', top_cwes=[], confidence_levels={}, total_samples=0), analysis='', analysis_with_relationships='', criticism='', resolution='', relevant_cwes=[{'metadata': {'doc_id': '287', 'name': 'Improper Authentication', 'source': 'sparse', 'original_content': 'When an actor claims to have a given identity, the product does not prove or insufficiently proves that the claim is correct.', 'keyphrase_sources': [{'id': 'rootcause:Improper Authentication vulnerability', 'keyphrase': 'Improper Authentication vulnerability', 'type': 'rootcause'}, {'id': 'rootcause:authentication bypass', 'keyphrase': 'authentication bypass', 'type': 'rootcause'}, {'id': 'impact:Authentication Bypass', 'keyphrase': 'Authentication Bypass', 'type': 'impact'}, {'id': 'vector:physical access to EPAS-UI computer', 'keyphrase': 'physical access to EPAS-UI computer', 'type': 'vector'}, {'id': 'vector:interrupt normal boot process', 'keyphrase': 'interrupt normal boot process', 'type': 'vector'}, {'id': 'vector:reboot workstation', 'keyphrase': 'reboot workstation', 'type': 'vector'}, {'id': 'attacker:unauthorized user without permission rights', 'keyphrase': 'unauthorized user without permission rights', 'type': 'attacker'}]}, 'similarity': np.float64(256.14539544830797)}, {'metadata': {'doc_id': '306', 'name': 'Missing Authentication for Critical Function', 'source': 'sparse', 'original_content': 'The product does not perform any authentication for functionality that requires a provable user identity or consumes a significant amount of resources.', 'keyphrase_sources': [{'id': 'rootcause:Improper Authentication vulnerability', 'keyphrase': 'Improper Authentication vulnerability', 'type': 'rootcause'}, {'id': 'rootcause:authentication bypass', 'keyphrase': 'authentication bypass', 'type': 'rootcause'}, {'id': 'impact:Authentication Bypass', 'keyphrase': 'Authentication Bypass', 'type': 'impact'}, {'id': 'vector:physical access to EPAS-UI computer', 'keyphrase': 'physical access to EPAS-UI computer', 'type': 'vector'}, {'id': 'vector:reboot workstation', 'keyphrase': 'reboot workstation', 'type': 'vector'}, {'id': 'attacker:unauthorized user without permission rights', 'keyphrase': 'unauthorized user without permission rights', 'type': 'attacker'}]}, 'similarity': np.float64(242.1413887425714)}, {'metadata': {'doc_id': '798', 'name': 'Use of Hard-coded Credentials', 'source': 'sparse', 'original_content': 'The product contains hard-coded credentials, such as a password or cryptographic key.', 'keyphrase_sources': [{'id': 'rootcause:Improper Authentication vulnerability', 'keyphrase': 'Improper Authentication vulnerability', 'type': 'rootcause'}, {'id': 'rootcause:authentication bypass', 'keyphrase': 'authentication bypass', 'type': 'rootcause'}, {'id': 'impact:Authentication Bypass', 'keyphrase': 'Authentication Bypass', 'type': 'impact'}, {'id': 'vector:physical access to EPAS-UI computer', 'keyphrase': 'physical access to EPAS-UI computer', 'type': 'vector'}, {'id': 'vector:interrupt normal boot process', 'keyphrase': 'interrupt normal boot process', 'type': 'vector'}, {'id': 'vector:reboot workstation', 'keyphrase': 'reboot workstation', 'type': 'vector'}]}, 'similarity': np.float64(239.03730235496835)}, {'metadata': {'doc_id': '285', 'name': 'Improper Authorization', 'source': 'sparse', 'original_content': 'The product does not perform or incorrectly performs an authorization check when an actor attempts to access a resource or perform an action.', 'keyphrase_sources': [{'id': 'rootcause:Improper Authentication vulnerability', 'keyphrase': 'Improper Authentication vulnerability', 'type': 'rootcause'}, {'id': 'rootcause:authentication bypass', 'keyphrase': 'authentication bypass', 'type': 'rootcause'}, {'id': 'impact:Authentication Bypass', 'keyphrase': 'Authentication Bypass', 'type': 'impact'}, {'id': 'vector:interrupt normal boot process', 'keyphrase': 'interrupt normal boot process', 'type': 'vector'}, {'id': 'attacker:unauthorized user without permission rights', 'keyphrase': 'unauthorized user without permission rights', 'type': 'attacker'}]}, 'similarity': np.float64(236.99700656184106)}, {'metadata': {'doc_id': '1390', 'name': 'Weak Authentication', 'source': 'sparse', 'original_content': 'The product uses an authentication mechanism to restrict access to specific users or identities, but the mechanism does not sufficiently prove that the claimed identity is correct.', 'keyphrase_sources': [{'id': 'rootcause:Improper Authentication vulnerability', 'keyphrase': 'Improper Authentication vulnerability', 'type': 'rootcause'}, {'id': 'rootcause:authentication bypass', 'keyphrase': 'authentication bypass', 'type': 'rootcause'}, {'id': 'impact:Authentication Bypass', 'keyphrase': 'Authentication Bypass', 'type': 'impact'}, {'id': 'vector:physical access to EPAS-UI computer', 'keyphrase': 'physical access to EPAS-UI computer', 'type': 'vector'}]}, 'similarity': np.float64(235.21614042082484)}, {'metadata': {'doc_id': '1263', 'name': 'Improper Physical Access Control', 'source': 'sparse', 'original_content': 'The product is designed with access restricted to certain information, but it does not sufficiently protect against an unauthorized actor with physical access to these areas.', 'keyphrase_sources': [{'id': 'vector:physical access to EPAS-UI computer', 'keyphrase': 'physical access to EPAS-UI computer', 'type': 'vector'}, {'id': 'vector:interrupt normal boot process', 'keyphrase': 'interrupt normal boot process', 'type': 'vector'}]}, 'similarity': np.float64(103.0524100454857)}, {'metadata': {'doc_id': '269', 'name': 'Improper Privilege Management', 'source': 'sparse', 'original_content': 'The product does not properly assign, modify, track, or check privileges for an actor, creating an unintended sphere of control for that actor.', 'keyphrase_sources': [{'id': 'attacker:unauthorized user without permission rights', 'keyphrase': 'unauthorized user without permission rights', 'type': 'attacker'}]}, 'similarity': np.float64(90.18582540455914)}, {'metadata': {'doc_id': '828', 'name': 'Signal Handler with Functionality that is not Asynchronous-Safe', 'source': 'sparse', 'original_content': 'The product defines a signal handler that contains code sequences that are not asynchronous-safe, i.e., the functionality is not reentrant, or it can be interrupted.', 'keyphrase_sources': [{'id': 'vector:interrupt normal boot process', 'keyphrase': 'interrupt normal boot process', 'type': 'vector'}]}, 'similarity': np.float64(86.43973172589972)}, {'metadata': {'doc_id': '863', 'name': 'Incorrect Authorization', 'source': 'sparse', 'original_content': 'The product performs an authorization check when an actor attempts to access a resource or perform an action, but it does not correctly perform the check.', 'keyphrase_sources': [{'id': 'attacker:unauthorized user without permission rights', 'keyphrase': 'unauthorized user without permission rights', 'type': 'attacker'}]}, 'similarity': np.float64(85.29826593376363)}, {'metadata': {'doc_id': '1287', 'name': 'Improper Validation of Specified Type of Input', 'source': 'sparse', 'original_content': 'The product receives input that is expected to be of a certain type, but it does not validate or incorrectly validates that the input is actually of the expected type.', 'keyphrase_sources': [{'id': 'vector:reboot workstation', 'keyphrase': 'reboot workstation', 'type': 'vector'}]}, 'similarity': np.float64(75.50467292316954)}, {'metadata': {'doc_id': '256', 'name': 'Plaintext Storage of a Password', 'source': 'sparse', 'original_content': 'Storing a password in plaintext may result in a system compromise.', 'keyphrase_sources': [{'id': 'vector:reboot workstation', 'keyphrase': 'reboot workstation', 'type': 'vector'}]}, 'similarity': np.float64(74.22661679845207)}], identified_cwes={'analyzer': [], 'critic_additional': []})",
  "retrieval_results": {
    "has_multiple_keyphrases": true,
    "keyphrase_cwe_sets": {
      "rootcause:Improper Authentication vulnerability": {
        "keyphrase": "Improper Authentication vulnerability",
        "type": "rootcause",
        "cwes": [
          {
            "metadata": {
              "doc_id": "287",
              "name": "Improper Authentication",
              "source": "sparse",
              "original_content": "When an actor claims to have a given identity, the product does not prove or insufficiently proves that the claim is correct.",
              "keyphrase_sources": [
                {
                  "id": "rootcause:Improper Authentication vulnerability",
                  "keyphrase": "Improper Authentication vulnerability",
                  "type": "rootcause"
                },
                {
                  "id": "rootcause:authentication bypass",
                  "keyphrase": "authentication bypass",
                  "type": "rootcause"
                },
                {
                  "id": "impact:Authentication Bypass",
                  "keyphrase": "Authentication Bypass",
                  "type": "impact"
                },
                {
                  "id": "vector:physical access to EPAS-UI computer",
                  "keyphrase": "physical access to EPAS-UI computer",
                  "type": "vector"
                },
                {
                  "id": "vector:interrupt normal boot process",
                  "keyphrase": "interrupt normal boot process",
                  "type": "vector"
                },
                {
                  "id": "vector:reboot workstation",
                  "keyphrase": "reboot workstation",
                  "type": "vector"
                },
                {
                  "id": "attacker:unauthorized user without permission rights",
                  "keyphrase": "unauthorized user without permission rights",
                  "type": "attacker"
                }
              ]
            },
            "similarity": 256.14539544830797
          },
          {
            "metadata": {
              "doc_id": "306",
              "name": "Missing Authentication for Critical Function",
              "source": "sparse",
              "original_content": "The product does not perform any authentication for functionality that requires a provable user identity or consumes a significant amount of resources.",
              "keyphrase_sources": [
                {
                  "id": "rootcause:Improper Authentication vulnerability",
                  "keyphrase": "Improper Authentication vulnerability",
                  "type": "rootcause"
                },
                {
                  "id": "rootcause:authentication bypass",
                  "keyphrase": "authentication bypass",
                  "type": "rootcause"
                },
                {
                  "id": "impact:Authentication Bypass",
                  "keyphrase": "Authentication Bypass",
                  "type": "impact"
                },
                {
                  "id": "vector:physical access to EPAS-UI computer",
                  "keyphrase": "physical access to EPAS-UI computer",
                  "type": "vector"
                },
                {
                  "id": "vector:reboot workstation",
                  "keyphrase": "reboot workstation",
                  "type": "vector"
                },
                {
                  "id": "attacker:unauthorized user without permission rights",
                  "keyphrase": "unauthorized user without permission rights",
                  "type": "attacker"
                }
              ]
            },
            "similarity": 242.1413887425714
          },
          {
            "metadata": {
              "doc_id": "798",
              "name": "Use of Hard-coded Credentials",
              "source": "sparse",
              "original_content": "The product contains hard-coded credentials, such as a password or cryptographic key.",
              "keyphrase_sources": [
                {
                  "id": "rootcause:Improper Authentication vulnerability",
                  "keyphrase": "Improper Authentication vulnerability",
                  "type": "rootcause"
                },
                {
                  "id": "rootcause:authentication bypass",
                  "keyphrase": "authentication bypass",
                  "type": "rootcause"
                },
                {
                  "id": "impact:Authentication Bypass",
                  "keyphrase": "Authentication Bypass",
                  "type": "impact"
                },
                {
                  "id": "vector:physical access to EPAS-UI computer",
                  "keyphrase": "physical access to EPAS-UI computer",
                  "type": "vector"
                },
                {
                  "id": "vector:interrupt normal boot process",
                  "keyphrase": "interrupt normal boot process",
                  "type": "vector"
                },
                {
                  "id": "vector:reboot workstation",
                  "keyphrase": "reboot workstation",
                  "type": "vector"
                }
              ]
            },
            "similarity": 239.03730235496835
          },
          {
            "metadata": {
              "doc_id": "285",
              "name": "Improper Authorization",
              "source": "sparse",
              "original_content": "The product does not perform or incorrectly performs an authorization check when an actor attempts to access a resource or perform an action.",
              "keyphrase_sources": [
                {
                  "id": "rootcause:Improper Authentication vulnerability",
                  "keyphrase": "Improper Authentication vulnerability",
                  "type": "rootcause"
                },
                {
                  "id": "rootcause:authentication bypass",
                  "keyphrase": "authentication bypass",
                  "type": "rootcause"
                },
                {
                  "id": "impact:Authentication Bypass",
                  "keyphrase": "Authentication Bypass",
                  "type": "impact"
                },
                {
                  "id": "vector:interrupt normal boot process",
                  "keyphrase": "interrupt normal boot process",
                  "type": "vector"
                },
                {
                  "id": "attacker:unauthorized user without permission rights",
                  "keyphrase": "unauthorized user without permission rights",
                  "type": "attacker"
                }
              ]
            },
            "similarity": 236.99700656184106
          },
          {
            "metadata": {
              "doc_id": "1390",
              "name": "Weak Authentication",
              "source": "sparse",
              "original_content": "The product uses an authentication mechanism to restrict access to specific users or identities, but the mechanism does not sufficiently prove that the claimed identity is correct.",
              "keyphrase_sources": [
                {
                  "id": "rootcause:Improper Authentication vulnerability",
                  "keyphrase": "Improper Authentication vulnerability",
                  "type": "rootcause"
                },
                {
                  "id": "rootcause:authentication bypass",
                  "keyphrase": "authentication bypass",
                  "type": "rootcause"
                },
                {
                  "id": "impact:Authentication Bypass",
                  "keyphrase": "Authentication Bypass",
                  "type": "impact"
                },
                {
                  "id": "vector:physical access to EPAS-UI computer",
                  "keyphrase": "physical access to EPAS-UI computer",
                  "type": "vector"
                }
              ]
            },
            "similarity": 235.21614042082484
          }
        ]
      },
      "rootcause:authentication bypass": {
        "keyphrase": "authentication bypass",
        "type": "rootcause",
        "cwes": [
          {
            "metadata": {
              "doc_id": "287",
              "name": "Improper Authentication",
              "source": "sparse",
              "original_content": "When an actor claims to have a given identity, the product does not prove or insufficiently proves that the claim is correct."
            },
            "similarity": 255.51331675146827
          },
          {
            "metadata": {
              "doc_id": "306",
              "name": "Missing Authentication for Critical Function",
              "source": "sparse",
              "original_content": "The product does not perform any authentication for functionality that requires a provable user identity or consumes a significant amount of resources."
            },
            "similarity": 243.73735730066647
          },
          {
            "metadata": {
              "doc_id": "798",
              "name": "Use of Hard-coded Credentials",
              "source": "sparse",
              "original_content": "The product contains hard-coded credentials, such as a password or cryptographic key."
            },
            "similarity": 241.95936320366337
          },
          {
            "metadata": {
              "doc_id": "1390",
              "name": "Weak Authentication",
              "source": "sparse",
              "original_content": "The product uses an authentication mechanism to restrict access to specific users or identities, but the mechanism does not sufficiently prove that the claimed identity is correct."
            },
            "similarity": 237.78813394347804
          },
          {
            "metadata": {
              "doc_id": "285",
              "name": "Improper Authorization",
              "source": "sparse",
              "original_content": "The product does not perform or incorrectly performs an authorization check when an actor attempts to access a resource or perform an action."
            },
            "similarity": 234.6643482233036
          }
        ]
      },
      "impact:Authentication Bypass": {
        "keyphrase": "Authentication Bypass",
        "type": "impact",
        "cwes": [
          {
            "metadata": {
              "doc_id": "287",
              "name": "Improper Authentication",
              "source": "sparse",
              "original_content": "When an actor claims to have a given identity, the product does not prove or insufficiently proves that the claim is correct."
            },
            "similarity": 85.17110558382275
          },
          {
            "metadata": {
              "doc_id": "306",
              "name": "Missing Authentication for Critical Function",
              "source": "sparse",
              "original_content": "The product does not perform any authentication for functionality that requires a provable user identity or consumes a significant amount of resources."
            },
            "similarity": 81.24578576688883
          },
          {
            "metadata": {
              "doc_id": "798",
              "name": "Use of Hard-coded Credentials",
              "source": "sparse",
              "original_content": "The product contains hard-coded credentials, such as a password or cryptographic key."
            },
            "similarity": 80.6531210678878
          },
          {
            "metadata": {
              "doc_id": "1390",
              "name": "Weak Authentication",
              "source": "sparse",
              "original_content": "The product uses an authentication mechanism to restrict access to specific users or identities, but the mechanism does not sufficiently prove that the claimed identity is correct."
            },
            "similarity": 79.26271131449268
          },
          {
            "metadata": {
              "doc_id": "285",
              "name": "Improper Authorization",
              "source": "sparse",
              "original_content": "The product does not perform or incorrectly performs an authorization check when an actor attempts to access a resource or perform an action."
            },
            "similarity": 78.22144940776786
          }
        ]
      },
      "vector:physical access to EPAS-UI computer": {
        "keyphrase": "physical access to EPAS-UI computer",
        "type": "vector",
        "cwes": [
          {
            "metadata": {
              "doc_id": "1263",
              "name": "Improper Physical Access Control",
              "source": "sparse",
              "original_content": "The product is designed with access restricted to certain information, but it does not sufficiently protect against an unauthorized actor with physical access to these areas.",
              "keyphrase_sources": [
                {
                  "id": "vector:physical access to EPAS-UI computer",
                  "keyphrase": "physical access to EPAS-UI computer",
                  "type": "vector"
                },
                {
                  "id": "vector:interrupt normal boot process",
                  "keyphrase": "interrupt normal boot process",
                  "type": "vector"
                }
              ]
            },
            "similarity": 103.0524100454857
          },
          {
            "metadata": {
              "doc_id": "287",
              "name": "Improper Authentication",
              "source": "sparse",
              "original_content": "When an actor claims to have a given identity, the product does not prove or insufficiently proves that the claim is correct."
            },
            "similarity": 97.40746357488611
          },
          {
            "metadata": {
              "doc_id": "798",
              "name": "Use of Hard-coded Credentials",
              "source": "sparse",
              "original_content": "The product contains hard-coded credentials, such as a password or cryptographic key."
            },
            "similarity": 94.49755251441344
          },
          {
            "metadata": {
              "doc_id": "1390",
              "name": "Weak Authentication",
              "source": "sparse",
              "original_content": "The product uses an authentication mechanism to restrict access to specific users or identities, but the mechanism does not sufficiently prove that the claimed identity is correct."
            },
            "similarity": 92.35243870079344
          },
          {
            "metadata": {
              "doc_id": "306",
              "name": "Missing Authentication for Critical Function",
              "source": "sparse",
              "original_content": "The product does not perform any authentication for functionality that requires a provable user identity or consumes a significant amount of resources."
            },
            "similarity": 92.180494522579
          }
        ]
      },
      "vector:interrupt normal boot process": {
        "keyphrase": "interrupt normal boot process",
        "type": "vector",
        "cwes": [
          {
            "metadata": {
              "doc_id": "828",
              "name": "Signal Handler with Functionality that is not Asynchronous-Safe",
              "source": "sparse",
              "original_content": "The product defines a signal handler that contains code sequences that are not asynchronous-safe, i.e., the functionality is not reentrant, or it can be interrupted.",
              "keyphrase_sources": [
                {
                  "id": "vector:interrupt normal boot process",
                  "keyphrase": "interrupt normal boot process",
                  "type": "vector"
                }
              ]
            },
            "similarity": 86.43973172589972
          },
          {
            "metadata": {
              "doc_id": "287",
              "name": "Improper Authentication",
              "source": "sparse",
              "original_content": "When an actor claims to have a given identity, the product does not prove or insufficiently proves that the claim is correct."
            },
            "similarity": 86.11637988208697
          },
          {
            "metadata": {
              "doc_id": "1263",
              "name": "Improper Physical Access Control",
              "source": "sparse",
              "original_content": "The product is designed with access restricted to certain information, but it does not sufficiently protect against an unauthorized actor with physical access to these areas."
            },
            "similarity": 80.49282136645591
          },
          {
            "metadata": {
              "doc_id": "285",
              "name": "Improper Authorization",
              "source": "sparse",
              "original_content": "The product does not perform or incorrectly performs an authorization check when an actor attempts to access a resource or perform an action."
            },
            "similarity": 78.88005049517236
          },
          {
            "metadata": {
              "doc_id": "798",
              "name": "Use of Hard-coded Credentials",
              "source": "sparse",
              "original_content": "The product contains hard-coded credentials, such as a password or cryptographic key."
            },
            "similarity": 78.68447295978369
          }
        ]
      },
      "vector:reboot workstation": {
        "keyphrase": "reboot workstation",
        "type": "vector",
        "cwes": [
          {
            "metadata": {
              "doc_id": "798",
              "name": "Use of Hard-coded Credentials",
              "source": "sparse",
              "original_content": "The product contains hard-coded credentials, such as a password or cryptographic key."
            },
            "similarity": 78.98650855372004
          },
          {
            "metadata": {
              "doc_id": "306",
              "name": "Missing Authentication for Critical Function",
              "source": "sparse",
              "original_content": "The product does not perform any authentication for functionality that requires a provable user identity or consumes a significant amount of resources."
            },
            "similarity": 77.82623990272232
          },
          {
            "metadata": {
              "doc_id": "287",
              "name": "Improper Authentication",
              "source": "sparse",
              "original_content": "When an actor claims to have a given identity, the product does not prove or insufficiently proves that the claim is correct."
            },
            "similarity": 75.87655087269157
          },
          {
            "metadata": {
              "doc_id": "1287",
              "name": "Improper Validation of Specified Type of Input",
              "source": "sparse",
              "original_content": "The product receives input that is expected to be of a certain type, but it does not validate or incorrectly validates that the input is actually of the expected type.",
              "keyphrase_sources": [
                {
                  "id": "vector:reboot workstation",
                  "keyphrase": "reboot workstation",
                  "type": "vector"
                }
              ]
            },
            "similarity": 75.50467292316954
          },
          {
            "metadata": {
              "doc_id": "256",
              "name": "Plaintext Storage of a Password",
              "source": "sparse",
              "original_content": "Storing a password in plaintext may result in a system compromise.",
              "keyphrase_sources": [
                {
                  "id": "vector:reboot workstation",
                  "keyphrase": "reboot workstation",
                  "type": "vector"
                }
              ]
            },
            "similarity": 74.22661679845207
          }
        ]
      },
      "attacker:unauthorized user without permission rights": {
        "keyphrase": "unauthorized user without permission rights",
        "type": "attacker",
        "cwes": [
          {
            "metadata": {
              "doc_id": "285",
              "name": "Improper Authorization",
              "source": "sparse",
              "original_content": "The product does not perform or incorrectly performs an authorization check when an actor attempts to access a resource or perform an action."
            },
            "similarity": 90.26626822477814
          },
          {
            "metadata": {
              "doc_id": "269",
              "name": "Improper Privilege Management",
              "source": "sparse",
              "original_content": "The product does not properly assign, modify, track, or check privileges for an actor, creating an unintended sphere of control for that actor.",
              "keyphrase_sources": [
                {
                  "id": "attacker:unauthorized user without permission rights",
                  "keyphrase": "unauthorized user without permission rights",
                  "type": "attacker"
                }
              ]
            },
            "similarity": 90.18582540455914
          },
          {
            "metadata": {
              "doc_id": "306",
              "name": "Missing Authentication for Critical Function",
              "source": "sparse",
              "original_content": "The product does not perform any authentication for functionality that requires a provable user identity or consumes a significant amount of resources."
            },
            "similarity": 85.88434631050595
          },
          {
            "metadata": {
              "doc_id": "287",
              "name": "Improper Authentication",
              "source": "sparse",
              "original_content": "When an actor claims to have a given identity, the product does not prove or insufficiently proves that the claim is correct."
            },
            "similarity": 85.31071622098555
          },
          {
            "metadata": {
              "doc_id": "863",
              "name": "Incorrect Authorization",
              "source": "sparse",
              "original_content": "The product performs an authorization check when an actor attempts to access a resource or perform an action, but it does not correctly perform the check.",
              "keyphrase_sources": [
                {
                  "id": "attacker:unauthorized user without permission rights",
                  "keyphrase": "unauthorized user without permission rights",
                  "type": "attacker"
                }
              ]
            },
            "similarity": 85.29826593376363
          }
        ]
      }
    },
    "keyphrase_mapping": {
      "287": [
        {
          "id": "rootcause:Improper Authentication vulnerability",
          "keyphrase": "Improper Authentication vulnerability",
          "type": "rootcause"
        },
        {
          "id": "rootcause:authentication bypass",
          "keyphrase": "authentication bypass",
          "type": "rootcause"
        },
        {
          "id": "impact:Authentication Bypass",
          "keyphrase": "Authentication Bypass",
          "type": "impact"
        },
        {
          "id": "vector:physical access to EPAS-UI computer",
          "keyphrase": "physical access to EPAS-UI computer",
          "type": "vector"
        },
        {
          "id": "vector:interrupt normal boot process",
          "keyphrase": "interrupt normal boot process",
          "type": "vector"
        },
        {
          "id": "vector:reboot workstation",
          "keyphrase": "reboot workstation",
          "type": "vector"
        },
        {
          "id": "attacker:unauthorized user without permission rights",
          "keyphrase": "unauthorized user without permission rights",
          "type": "attacker"
        }
      ],
      "306": [
        {
          "id": "rootcause:Improper Authentication vulnerability",
          "keyphrase": "Improper Authentication vulnerability",
          "type": "rootcause"
        },
        {
          "id": "rootcause:authentication bypass",
          "keyphrase": "authentication bypass",
          "type": "rootcause"
        },
        {
          "id": "impact:Authentication Bypass",
          "keyphrase": "Authentication Bypass",
          "type": "impact"
        },
        {
          "id": "vector:physical access to EPAS-UI computer",
          "keyphrase": "physical access to EPAS-UI computer",
          "type": "vector"
        },
        {
          "id": "vector:reboot workstation",
          "keyphrase": "reboot workstation",
          "type": "vector"
        },
        {
          "id": "attacker:unauthorized user without permission rights",
          "keyphrase": "unauthorized user without permission rights",
          "type": "attacker"
        }
      ],
      "798": [
        {
          "id": "rootcause:Improper Authentication vulnerability",
          "keyphrase": "Improper Authentication vulnerability",
          "type": "rootcause"
        },
        {
          "id": "rootcause:authentication bypass",
          "keyphrase": "authentication bypass",
          "type": "rootcause"
        },
        {
          "id": "impact:Authentication Bypass",
          "keyphrase": "Authentication Bypass",
          "type": "impact"
        },
        {
          "id": "vector:physical access to EPAS-UI computer",
          "keyphrase": "physical access to EPAS-UI computer",
          "type": "vector"
        },
        {
          "id": "vector:interrupt normal boot process",
          "keyphrase": "interrupt normal boot process",
          "type": "vector"
        },
        {
          "id": "vector:reboot workstation",
          "keyphrase": "reboot workstation",
          "type": "vector"
        }
      ],
      "285": [
        {
          "id": "rootcause:Improper Authentication vulnerability",
          "keyphrase": "Improper Authentication vulnerability",
          "type": "rootcause"
        },
        {
          "id": "rootcause:authentication bypass",
          "keyphrase": "authentication bypass",
          "type": "rootcause"
        },
        {
          "id": "impact:Authentication Bypass",
          "keyphrase": "Authentication Bypass",
          "type": "impact"
        },
        {
          "id": "vector:interrupt normal boot process",
          "keyphrase": "interrupt normal boot process",
          "type": "vector"
        },
        {
          "id": "attacker:unauthorized user without permission rights",
          "keyphrase": "unauthorized user without permission rights",
          "type": "attacker"
        }
      ],
      "1390": [
        {
          "id": "rootcause:Improper Authentication vulnerability",
          "keyphrase": "Improper Authentication vulnerability",
          "type": "rootcause"
        },
        {
          "id": "rootcause:authentication bypass",
          "keyphrase": "authentication bypass",
          "type": "rootcause"
        },
        {
          "id": "impact:Authentication Bypass",
          "keyphrase": "Authentication Bypass",
          "type": "impact"
        },
        {
          "id": "vector:physical access to EPAS-UI computer",
          "keyphrase": "physical access to EPAS-UI computer",
          "type": "vector"
        }
      ],
      "1263": [
        {
          "id": "vector:physical access to EPAS-UI computer",
          "keyphrase": "physical access to EPAS-UI computer",
          "type": "vector"
        },
        {
          "id": "vector:interrupt normal boot process",
          "keyphrase": "interrupt normal boot process",
          "type": "vector"
        }
      ],
      "828": [
        {
          "id": "vector:interrupt normal boot process",
          "keyphrase": "interrupt normal boot process",
          "type": "vector"
        }
      ],
      "1287": [
        {
          "id": "vector:reboot workstation",
          "keyphrase": "reboot workstation",
          "type": "vector"
        }
      ],
      "256": [
        {
          "id": "vector:reboot workstation",
          "keyphrase": "reboot workstation",
          "type": "vector"
        }
      ],
      "269": [
        {
          "id": "attacker:unauthorized user without permission rights",
          "keyphrase": "unauthorized user without permission rights",
          "type": "attacker"
        }
      ],
      "863": [
        {
          "id": "attacker:unauthorized user without permission rights",
          "keyphrase": "unauthorized user without permission rights",
          "type": "attacker"
        }
      ]
    },
    "relevant_cwes": [
      {
        "metadata": {
          "doc_id": "287",
          "name": "Improper Authentication",
          "source": "sparse",
          "original_content": "When an actor claims to have a given identity, the product does not prove or insufficiently proves that the claim is correct.",
          "keyphrase_sources": [
            {
              "id": "rootcause:Improper Authentication vulnerability",
              "keyphrase": "Improper Authentication vulnerability",
              "type": "rootcause"
            },
            {
              "id": "rootcause:authentication bypass",
              "keyphrase": "authentication bypass",
              "type": "rootcause"
            },
            {
              "id": "impact:Authentication Bypass",
              "keyphrase": "Authentication Bypass",
              "type": "impact"
            },
            {
              "id": "vector:physical access to EPAS-UI computer",
              "keyphrase": "physical access to EPAS-UI computer",
              "type": "vector"
            },
            {
              "id": "vector:interrupt normal boot process",
              "keyphrase": "interrupt normal boot process",
              "type": "vector"
            },
            {
              "id": "vector:reboot workstation",
              "keyphrase": "reboot workstation",
              "type": "vector"
            },
            {
              "id": "attacker:unauthorized user without permission rights",
              "keyphrase": "unauthorized user without permission rights",
              "type": "attacker"
            }
          ]
        },
        "similarity": 256.14539544830797
      },
      {
        "metadata": {
          "doc_id": "306",
          "name": "Missing Authentication for Critical Function",
          "source": "sparse",
          "original_content": "The product does not perform any authentication for functionality that requires a provable user identity or consumes a significant amount of resources.",
          "keyphrase_sources": [
            {
              "id": "rootcause:Improper Authentication vulnerability",
              "keyphrase": "Improper Authentication vulnerability",
              "type": "rootcause"
            },
            {
              "id": "rootcause:authentication bypass",
              "keyphrase": "authentication bypass",
              "type": "rootcause"
            },
            {
              "id": "impact:Authentication Bypass",
              "keyphrase": "Authentication Bypass",
              "type": "impact"
            },
            {
              "id": "vector:physical access to EPAS-UI computer",
              "keyphrase": "physical access to EPAS-UI computer",
              "type": "vector"
            },
            {
              "id": "vector:reboot workstation",
              "keyphrase": "reboot workstation",
              "type": "vector"
            },
            {
              "id": "attacker:unauthorized user without permission rights",
              "keyphrase": "unauthorized user without permission rights",
              "type": "attacker"
            }
          ]
        },
        "similarity": 242.1413887425714
      },
      {
        "metadata": {
          "doc_id": "798",
          "name": "Use of Hard-coded Credentials",
          "source": "sparse",
          "original_content": "The product contains hard-coded credentials, such as a password or cryptographic key.",
          "keyphrase_sources": [
            {
              "id": "rootcause:Improper Authentication vulnerability",
              "keyphrase": "Improper Authentication vulnerability",
              "type": "rootcause"
            },
            {
              "id": "rootcause:authentication bypass",
              "keyphrase": "authentication bypass",
              "type": "rootcause"
            },
            {
              "id": "impact:Authentication Bypass",
              "keyphrase": "Authentication Bypass",
              "type": "impact"
            },
            {
              "id": "vector:physical access to EPAS-UI computer",
              "keyphrase": "physical access to EPAS-UI computer",
              "type": "vector"
            },
            {
              "id": "vector:interrupt normal boot process",
              "keyphrase": "interrupt normal boot process",
              "type": "vector"
            },
            {
              "id": "vector:reboot workstation",
              "keyphrase": "reboot workstation",
              "type": "vector"
            }
          ]
        },
        "similarity": 239.03730235496835
      },
      {
        "metadata": {
          "doc_id": "285",
          "name": "Improper Authorization",
          "source": "sparse",
          "original_content": "The product does not perform or incorrectly performs an authorization check when an actor attempts to access a resource or perform an action.",
          "keyphrase_sources": [
            {
              "id": "rootcause:Improper Authentication vulnerability",
              "keyphrase": "Improper Authentication vulnerability",
              "type": "rootcause"
            },
            {
              "id": "rootcause:authentication bypass",
              "keyphrase": "authentication bypass",
              "type": "rootcause"
            },
            {
              "id": "impact:Authentication Bypass",
              "keyphrase": "Authentication Bypass",
              "type": "impact"
            },
            {
              "id": "vector:interrupt normal boot process",
              "keyphrase": "interrupt normal boot process",
              "type": "vector"
            },
            {
              "id": "attacker:unauthorized user without permission rights",
              "keyphrase": "unauthorized user without permission rights",
              "type": "attacker"
            }
          ]
        },
        "similarity": 236.99700656184106
      },
      {
        "metadata": {
          "doc_id": "1390",
          "name": "Weak Authentication",
          "source": "sparse",
          "original_content": "The product uses an authentication mechanism to restrict access to specific users or identities, but the mechanism does not sufficiently prove that the claimed identity is correct.",
          "keyphrase_sources": [
            {
              "id": "rootcause:Improper Authentication vulnerability",
              "keyphrase": "Improper Authentication vulnerability",
              "type": "rootcause"
            },
            {
              "id": "rootcause:authentication bypass",
              "keyphrase": "authentication bypass",
              "type": "rootcause"
            },
            {
              "id": "impact:Authentication Bypass",
              "keyphrase": "Authentication Bypass",
              "type": "impact"
            },
            {
              "id": "vector:physical access to EPAS-UI computer",
              "keyphrase": "physical access to EPAS-UI computer",
              "type": "vector"
            }
          ]
        },
        "similarity": 235.21614042082484
      },
      {
        "metadata": {
          "doc_id": "1263",
          "name": "Improper Physical Access Control",
          "source": "sparse",
          "original_content": "The product is designed with access restricted to certain information, but it does not sufficiently protect against an unauthorized actor with physical access to these areas.",
          "keyphrase_sources": [
            {
              "id": "vector:physical access to EPAS-UI computer",
              "keyphrase": "physical access to EPAS-UI computer",
              "type": "vector"
            },
            {
              "id": "vector:interrupt normal boot process",
              "keyphrase": "interrupt normal boot process",
              "type": "vector"
            }
          ]
        },
        "similarity": 103.0524100454857
      },
      {
        "metadata": {
          "doc_id": "269",
          "name": "Improper Privilege Management",
          "source": "sparse",
          "original_content": "The product does not properly assign, modify, track, or check privileges for an actor, creating an unintended sphere of control for that actor.",
          "keyphrase_sources": [
            {
              "id": "attacker:unauthorized user without permission rights",
              "keyphrase": "unauthorized user without permission rights",
              "type": "attacker"
            }
          ]
        },
        "similarity": 90.18582540455914
      },
      {
        "metadata": {
          "doc_id": "828",
          "name": "Signal Handler with Functionality that is not Asynchronous-Safe",
          "source": "sparse",
          "original_content": "The product defines a signal handler that contains code sequences that are not asynchronous-safe, i.e., the functionality is not reentrant, or it can be interrupted.",
          "keyphrase_sources": [
            {
              "id": "vector:interrupt normal boot process",
              "keyphrase": "interrupt normal boot process",
              "type": "vector"
            }
          ]
        },
        "similarity": 86.43973172589972
      },
      {
        "metadata": {
          "doc_id": "863",
          "name": "Incorrect Authorization",
          "source": "sparse",
          "original_content": "The product performs an authorization check when an actor attempts to access a resource or perform an action, but it does not correctly perform the check.",
          "keyphrase_sources": [
            {
              "id": "attacker:unauthorized user without permission rights",
              "keyphrase": "unauthorized user without permission rights",
              "type": "attacker"
            }
          ]
        },
        "similarity": 85.29826593376363
      },
      {
        "metadata": {
          "doc_id": "1287",
          "name": "Improper Validation of Specified Type of Input",
          "source": "sparse",
          "original_content": "The product receives input that is expected to be of a certain type, but it does not validate or incorrectly validates that the input is actually of the expected type.",
          "keyphrase_sources": [
            {
              "id": "vector:reboot workstation",
              "keyphrase": "reboot workstation",
              "type": "vector"
            }
          ]
        },
        "similarity": 75.50467292316954
      },
      {
        "metadata": {
          "doc_id": "256",
          "name": "Plaintext Storage of a Password",
          "source": "sparse",
          "original_content": "Storing a password in plaintext may result in a system compromise.",
          "keyphrase_sources": [
            {
              "id": "vector:reboot workstation",
              "keyphrase": "reboot workstation",
              "type": "vector"
            }
          ]
        },
        "similarity": 74.22661679845207
      }
    ],
    "enhanced_query": "# Vulnerability Description\n\n    CWE-287 **Improper Authentication vulnerability** exists that could cause an Authentication Bypass when an unauthorized user without permission rights has physical access to the EPAS-UI computer and is able to reboot the workstation and interrupt the normal boot process.\n\n    # Keyphrase-Specific CWE Analysis\n    This vulnerability contains multiple keyphrases that may map to different CWEs. \n    Please analyze each keyphrase separately and determine the most appropriate CWE(s) for each.\n\n    ## ROOTCAUSE: 'Improper Authentication vulnerability'\n\nRelevant CWEs for this ROOTCAUSE:\n\n### 1. CWE-287: Improper Authentication (Score: 256.15)\n\nWhen an actor claims to have a given identity, the product does not prove or insufficiently proves that the claim is correct....\n\n### 2. CWE-306: Missing Authentication for Critical Function (Score: 242.14)\n\nThe product does not perform any authentication for functionality that requires a provable user identity or consumes a significant amount of resources....\n\n### 3. CWE-798: Use of Hard-coded Credentials (Score: 239.04)\n\nThe product contains hard-coded credentials, such as a password or cryptographic key....\n\n### 4. CWE-285: Improper Authorization (Score: 237.00)\n\nThe product does not perform or incorrectly performs an authorization check when an actor attempts to access a resource or perform an action....\n\n### 5. CWE-1390: Weak Authentication (Score: 235.22)\n\nThe product uses an authentication mechanism to restrict access to specific users or identities, but the mechanism does not sufficiently prove that the claimed identity is correct....\n\n## ROOTCAUSE: 'authentication bypass'\n\nRelevant CWEs for this ROOTCAUSE:\n\n### 1. CWE-287: Improper Authentication (Score: 256.15)\n\nWhen an actor claims to have a given identity, the product does not prove or insufficiently proves that the claim is correct....\n\n### 2. CWE-306: Missing Authentication for Critical Function (Score: 242.14)\n\nThe product does not perform any authentication for functionality that requires a provable user identity or consumes a significant amount of resources....\n\n### 3. CWE-798: Use of Hard-coded Credentials (Score: 239.04)\n\nThe product contains hard-coded credentials, such as a password or cryptographic key....\n\n### 4. CWE-285: Improper Authorization (Score: 237.00)\n\nThe product does not perform or incorrectly performs an authorization check when an actor attempts to access a resource or perform an action....\n\n### 5. CWE-1390: Weak Authentication (Score: 235.22)\n\nThe product uses an authentication mechanism to restrict access to specific users or identities, but the mechanism does not sufficiently prove that the claimed identity is correct....\n\n## IMPACT: 'Authentication Bypass'\n\nRelevant CWEs for this IMPACT:\n\n### 1. CWE-287: Improper Authentication (Score: 256.15)\n\nWhen an actor claims to have a given identity, the product does not prove or insufficiently proves that the claim is correct....\n\n### 2. CWE-306: Missing Authentication for Critical Function (Score: 242.14)\n\nThe product does not perform any authentication for functionality that requires a provable user identity or consumes a significant amount of resources....\n\n### 3. CWE-798: Use of Hard-coded Credentials (Score: 239.04)\n\nThe product contains hard-coded credentials, such as a password or cryptographic key....\n\n### 4. CWE-285: Improper Authorization (Score: 237.00)\n\nThe product does not perform or incorrectly performs an authorization check when an actor attempts to access a resource or perform an action....\n\n### 5. CWE-1390: Weak Authentication (Score: 235.22)\n\nThe product uses an authentication mechanism to restrict access to specific users or identities, but the mechanism does not sufficiently prove that the claimed identity is correct....\n\n## VECTOR: 'physical access to EPAS-UI computer'\n\nRelevant CWEs for this VECTOR:\n\n### 1. CWE-287: Improper Authentication (Score: 256.15)\n\nWhen an actor claims to have a given identity, the product does not prove or insufficiently proves that the claim is correct....\n\n### 2. CWE-306: Missing Authentication for Critical Function (Score: 242.14)\n\nThe product does not perform any authentication for functionality that requires a provable user identity or consumes a significant amount of resources....\n\n### 3. CWE-798: Use of Hard-coded Credentials (Score: 239.04)\n\nThe product contains hard-coded credentials, such as a password or cryptographic key....\n\n### 4. CWE-1390: Weak Authentication (Score: 235.22)\n\nThe product uses an authentication mechanism to restrict access to specific users or identities, but the mechanism does not sufficiently prove that the claimed identity is correct....\n\n### 5. CWE-1263: Improper Physical Access Control (Score: 103.05)\n\nThe product is designed with access restricted to certain information, but it does not sufficiently protect against an unauthorized actor with physical access to these areas....\n\n## VECTOR: 'interrupt normal boot process'\n\nRelevant CWEs for this VECTOR:\n\n### 1. CWE-287: Improper Authentication (Score: 256.15)\n\nWhen an actor claims to have a given identity, the product does not prove or insufficiently proves that the claim is correct....\n\n### 2. CWE-798: Use of Hard-coded Credentials (Score: 239.04)\n\nThe product contains hard-coded credentials, such as a password or cryptographic key....\n\n### 3. CWE-285: Improper Authorization (Score: 237.00)\n\nThe product does not perform or incorrectly performs an authorization check when an actor attempts to access a resource or perform an action....\n\n### 4. CWE-1263: Improper Physical Access Control (Score: 103.05)\n\nThe product is designed with access restricted to certain information, but it does not sufficiently protect against an unauthorized actor with physical access to these areas....\n\n### 5. CWE-828: Signal Handler with Functionality that is not Asynchronous-Safe (Score: 86.44)\n\nThe product defines a signal handler that contains code sequences that are not asynchronous-safe, i.e., the functionality is not reentrant, or it can be interrupted....\n\n## VECTOR: 'reboot workstation'\n\nRelevant CWEs for this VECTOR:\n\n### 1. CWE-287: Improper Authentication (Score: 256.15)\n\nWhen an actor claims to have a given identity, the product does not prove or insufficiently proves that the claim is correct....\n\n### 2. CWE-306: Missing Authentication for Critical Function (Score: 242.14)\n\nThe product does not perform any authentication for functionality that requires a provable user identity or consumes a significant amount of resources....\n\n### 3. CWE-798: Use of Hard-coded Credentials (Score: 239.04)\n\nThe product contains hard-coded credentials, such as a password or cryptographic key....\n\n### 4. CWE-1287: Improper Validation of Specified Type of Input (Score: 75.50)\n\nThe product receives input that is expected to be of a certain type, but it does not validate or incorrectly validates that the input is actually of the expected type....\n\n### 5. CWE-256: Plaintext Storage of a Password (Score: 74.23)\n\nStoring a password in plaintext may result in a system compromise....\n\n## ATTACKER: 'unauthorized user without permission rights'\n\nRelevant CWEs for this ATTACKER:\n\n### 1. CWE-287: Improper Authentication (Score: 256.15)\n\nWhen an actor claims to have a given identity, the product does not prove or insufficiently proves that the claim is correct....\n\n### 2. CWE-306: Missing Authentication for Critical Function (Score: 242.14)\n\nThe product does not perform any authentication for functionality that requires a provable user identity or consumes a significant amount of resources....\n\n### 3. CWE-285: Improper Authorization (Score: 237.00)\n\nThe product does not perform or incorrectly performs an authorization check when an actor attempts to access a resource or perform an action....\n\n### 4. CWE-269: Improper Privilege Management (Score: 90.19)\n\nThe product does not properly assign, modify, track, or check privileges for an actor, creating an unintended sphere of control for that actor....\n\n### 5. CWE-863: Incorrect Authorization (Score: 85.30)\n\nThe product performs an authorization check when an actor attempts to access a resource or perform an action, but it does not correctly perform the check....\n\n\n    # Analysis Instructions\n    1. For each keyphrase, identify the most appropriate CWE(s) that represent the weakness.\n    2. Consider how the different keyphrases might relate to each other in the vulnerability chain.\n    3. Provide a final determination of primary CWE(s) and any secondary CWEs.\n    4. Format your response using the standard analysis template.\n\n    Please analyze how these different weaknesses interact and provide a comprehensive CWE classification.\n    "
  },
  "retrieval_time": 1.1484348773956299
}