{
  "cve_id": "CVE-2024-11485",
  "description": "A vulnerability, which was classified as critical, has been found in Code4Berry Decoration Management System 1.0. Affected by this issue is some unknown functionality of the file /decoration/admin/userregister.php of the component User Handler. The manipulation leads to permission issues. The attack may be launched remotely. The exploit has been disclosed to the public and may be used. The vendor was contacted early about this disclosure but did not respond in any way.",
  "key_phrases": {
    "rootcause": "",
    "weakness": "",
    "impact": "permission issues",
    "vector": "",
    "attacker": "",
    "product": "Code4Berry Decoration Management System",
    "version": "1",
    "component": "/decoration/admin/userregister.php"
  },
  "reference_content": null,
  "similar_info": {
    "cwe_distribution": {},
    "cwe_consensus": "",
    "similarity_stats": {
      "thresholds": [],
      "total_samples_by_threshold": {},
      "top_cwes_by_threshold": {}
    }
  },
  "similarity_summary": {
    "consensus_cwe": "",
    "top_cwes": [],
    "confidence_levels": {},
    "total_samples": 0
  },
  "analysis": "# Summary\n\n| CWE ID  | CWE Name                                                                   | Confidence | CWE Abstraction Level | CWE Vulnerability Mapping Label | CWE-Vulnerability Mapping Notes |\n| :-------- | :------------------------------------------------------------------------- | :--------- | :---------------------- | :------------------------------ | :------------------------------ |\n| CWE-266   | Incorrect Privilege Assignment                                             | 0.85       | Base                    | Primary                         | Allowed                         |\n| CWE-285   | Improper Authorization                                                     | 0.60       | Class                     | Secondary                       | Discouraged                     |\n\n## Evidence and Confidence\n\n*   **Confidence Score:** 0.75\n*   **Evidence Strength:** MEDIUM\n\n## Relationship Analysis\n\nThe primary relationship that influenced the decision was the parent-child relationship between CWE-285 (Improper Authorization) and more specific CWEs related to privilege and permission issues. Given that the vulnerability description explicitly mentions \"permission issues\" as the impact and the guidance suggests that CWE-266 is appropriate for misassigned privileges, it was selected as the primary CWE. CWE-285, being a higher-level class, was considered as a secondary CWE due to its broader applicability to authorization failures.\n\n```mermaid\ngraph TD\n    cwe266[\"CWE-266: Incorrect Privilege Assignment\"]\n    cwe285[\"CWE-285: Improper Authorization\"]\n\n    cwe266 -->|CHILDOF| cwe285\n\n    classDef primary fill:#f96,stroke:#333,stroke-width:2px\n    classDef secondary fill:#69f,stroke:#333\n    class cwe266 primary\n    class cwe285 secondary\n```\n\n## Vulnerability Chain\n\nThe vulnerability chain starts with **incorrect privilege assignment** (CWE-266), leading to **permission issues**.\n\nCWE-266 (Root Cause) -> Permission Issues (Impact)\n\n## Summary of Analysis\n\nThe initial analysis focused on identifying the root cause of the vulnerability. The description explicitly mentions \"permission issues\" resulting from manipulation of the `/decoration/admin/userregister.php` file.\n\nThe CWE guidance provides clear distinctions between privileges and permissions, suggesting CWE-266 for cases where privileges are incorrectly assigned. This aligned with the vulnerability details, indicating that a user or actor might be granted inappropriate access rights.\n\nThe retriever results also suggested CWE-266 and related CWEs, which further supported the selection of CWE-266 as the primary weakness.\n\nThe final decision prioritized CWE-266 because it represents the root cause of the issue which led to the impact of permission issues.\n\nRelevant CWE Information:\n\n# Enhanced Context (25 CWEs)\nThe following CWEs were identified as potentially relevant to this vulnerability:\n\n## CWE-266: Incorrect Privilege Assignment\n**Abstraction Level**: Base\n**Similarity Score**: 0.79\n**Source**: dense\n\n**Description**:\nA product incorrectly assigns a privilege to a particular actor, creating an unintended sphere of control for that actor.\n\n**Mapping Guidance**:\n- Usage: Allowed\n- Rationale: This CWE entry is at the Base level of abstraction, which is a preferred level of abstraction for mapping to the root causes of vulnerabilities.\n\n## CWE-285: Improper Authorization\n**Abstraction Level**: Class\n**Similarity Score**: 1324.36\n**Source**: sparse\n\n**Description**:\nThe product does not perform or incorrectly performs an authorization check when an actor attempts to access a resource or perform an action.\n\n**Mapping Guidance**:\n- Usage: Discouraged\n- Rationale: CWE-285 is high-level and lower-level CWEs can frequently be used instead. It is a level-1 Class (i.e., a child of a Pillar).\n\n## Technical Explanation for Selected CWEs:\n\n*   **CWE-266: Incorrect Privilege Assignment**\n    *   **How it matches:** The vulnerability description indicates that the manipulation of `/decoration/admin/userregister.php` leads to \"permission issues.\" Based on the CWE Guidance, this aligns with **incorrectly assigning privileges** during user registration.\n    *   **Security Implications:** This could allow unauthorized users to gain elevated privileges, potentially leading to data breaches, system compromise, or denial of service.\n    *   **Relationship:** CWE-266 is a child of CWE-285 (Improper Authorization), making it a more specific representation of the authorization failure.\n    *   **Mapping Guidance Influence:** The CWE guidance explicitly suggests using CWE-266 when a user is assigned the wrong role/group, which supports this mapping.\n    *   **Primary Weakness:** This is considered the primary weakness because it represents the root cause of the permission issues.\n    *   **Confidence:** 0.85\n\n*   **CWE-285: Improper Authorization**\n    *   **How it matches:** The vulnerability results in \"permission issues\", indicating that the application is not correctly authorizing access to resources or functionalities.\n    *   **Security Implications:** Users might gain unauthorized access to sensitive data or functionality, leading to data breaches, system compromise, or privilege escalation.\n    *   **Relationship:** CWE-285 is a parent Class of more specific authorization-related CWEs, such as CWE-266.\n    *   **Mapping Guidance Influence:** While CWE-285 is discouraged for direct mapping, it serves as a broader categorization for the authorization failure. It acts as a high-level classification when a more specific CWE is unavailable.\n    *   **Secondary Weakness:** This is a secondary weakness because it is a more general categorization of the authorization issue.\n    *   **Confidence:** 0.60\n\n## CWEs Considered but Not Used:\n\n*   **CWE-416: Use After Free:** This CWE is not relevant because the description does not indicate any memory management issues or use-after-free conditions.\n*   **CWE-441: Unintended Proxy or Intermediary ('Confused Deputy'):** This CWE is not relevant as there is no mention of a confused deputy situation where a program unintentionally misuses its authority.\n*   **CWE-563: Assignment to Variable without Use:** This CWE is not applicable because the description doesn't suggest any instances of variables being assigned values but not subsequently used.\n*   **CWE-89: Improper Neutralization of Special Elements used in an SQL Command ('SQL Injection'):** SQL injection is not indicated in the description.\n*   **CWE-79: Improper Neutralization of Input During Web Page Generation ('Cross-site Scripting'):** Cross-site scripting is not indicated in the description.\n*   **CWE-434: Unrestricted Upload of File with Dangerous Type:** The description does not mention any file upload functionality or associated vulnerabilities.\n*   **CWE-1336: Improper Neutralization of Special Elements Used in a Template Engine:** The description doesn't suggest any template engine related issues.\n*   **CWE-352: Cross-Site Request Forgery (CSRF):** There is no indication of CSRF in the description.\n*   **CWE-472: External Control of Assumed-Immutable Web Parameter:** The description does not specify any issues related to external control of assumed-immutable parameters.\n*   **CWE-471: Modification of Assumed-Immutable Data (MAID):** This CWE is not relevant because the description does not indicate any modification of assumed-immutable data.\n*   **CWE-269: Improper Privilege Management:** The guidance discourages use of this.\n*   **CWE-863: Incorrect Authorization:** Although related, CWE-266 provides a more specific root cause.\n*   **CWE-425: Direct Request ('Forced Browsing'):** There is no indication of forced browsing in the description.\n*   **CWE-276: Incorrect Default Permissions:** This is similar to CWE-266 but focuses on installation permissions. Since the vulnerability is at the user registration level, this is not applicable.\n*   **CWE-807: Reliance on Untrusted Inputs in a Security Decision:** There is no indication of security decisions based on untrusted inputs.\n*   **CWE-668: Exposure of Resource to Wrong Sphere:** This is a high level class that is not as specific as CWE-266.\n*   **CWE-41: Improper Resolution of Path Equivalence:** The description does not indicate any path equivalence issues.\n*   **CWE-274: Improper Handling of Insufficient Privileges:** The description does not indicate issues related to insufficient privileges.\n*   **CWE-280: Improper Handling of Insufficient Permissions or Privileges:** The description does not indicate issues related to insufficient permissions or privileges.\n*   **CWE-267: Privilege Defined With Unsafe Actions:** This is not as directly relevant as CWE-266.\n*   **CWE-1275: Sensitive Cookie with Improper SameSite Attribute:** No cookie information is available.\n*   **CWE-1336: Improper Neutralization of Special Elements Used in a Template Engine:** No template engine information is available.\n*   **CWE-123: Write-what-where Condition:** No memory corruption information is available.",
  "analysis_with_relationships": "# Summary\n\n| CWE ID  | CWE Name                                                                   | Confidence | CWE Abstraction Level | CWE Vulnerability Mapping Label | CWE-Vulnerability Mapping Notes |\n| :-------- | :------------------------------------------------------------------------- | :--------- | :---------------------- | :------------------------------ | :------------------------------ |\n| CWE-266   | Incorrect Privilege Assignment                                             | 0.85       | Base                    | Primary                         | Allowed                         |\n| CWE-285   | Improper Authorization                                                     | 0.60       | Class                     | Secondary                       | Discouraged                     |\n\n## Evidence and Confidence\n\n*   **Confidence Score:** 0.75\n*   **Evidence Strength:** MEDIUM\n\n## Relationship Analysis\n\nThe primary relationship that influenced the decision was the parent-child relationship between CWE-285 (Improper Authorization) and more specific CWEs related to privilege and permission issues. Given that the vulnerability description explicitly mentions \"permission issues\" as the impact and the guidance suggests that CWE-266 is appropriate for misassigned privileges, it was selected as the primary CWE. CWE-285, being a higher-level class, was considered as a secondary CWE due to its broader applicability to authorization failures.\n\n```mermaid\ngraph TD\n    cwe266[\"CWE-266: Incorrect Privilege Assignment\"]\n    cwe285[\"CWE-285: Improper Authorization\"]\n\n    cwe266 -->|CHILDOF| cwe285\n\n    classDef primary fill:#f96,stroke:#333,stroke-width:2px\n    classDef secondary fill:#69f,stroke:#333\n    class cwe266 primary\n    class cwe285 secondary\n```\n\n## Vulnerability Chain\n\nThe vulnerability chain starts with **incorrect privilege assignment** (CWE-266), leading to **permission issues**.\n\nCWE-266 (Root Cause) -> Permission Issues (Impact)\n\n## Summary of Analysis\n\nThe initial analysis focused on identifying the root cause of the vulnerability. The description explicitly mentions \"permission issues\" resulting from manipulation of the `/decoration/admin/userregister.php` file.\n\nThe CWE guidance provides clear distinctions between privileges and permissions, suggesting CWE-266 for cases where privileges are incorrectly assigned. This aligned with the vulnerability details, indicating that a user or actor might be granted inappropriate access rights.\n\nThe retriever results also suggested CWE-266 and related CWEs, which further supported the selection of CWE-266 as the primary weakness.\n\nThe final decision prioritized CWE-266 because it represents the root cause of the issue which led to the impact of permission issues.\n\nRelevant CWE Information:\n\n# Enhanced Context (25 CWEs)\nThe following CWEs were identified as potentially relevant to this vulnerability:\n\n## CWE-266: Incorrect Privilege Assignment\n**Abstraction Level**: Base\n**Similarity Score**: 0.79\n**Source**: dense\n\n**Description**:\nA product incorrectly assigns a privilege to a particular actor, creating an unintended sphere of control for that actor.\n\n**Mapping Guidance**:\n- Usage: Allowed\n- Rationale: This CWE entry is at the Base level of abstraction, which is a preferred level of abstraction for mapping to the root causes of vulnerabilities.\n\n## CWE-285: Improper Authorization\n**Abstraction Level**: Class\n**Similarity Score**: 1324.36\n**Source**: sparse\n\n**Description**:\nThe product does not perform or incorrectly performs an authorization check when an actor attempts to access a resource or perform an action.\n\n**Mapping Guidance**:\n- Usage: Discouraged\n- Rationale: CWE-285 is high-level and lower-level CWEs can frequently be used instead. It is a level-1 Class (i.e., a child of a Pillar).\n\n## Technical Explanation for Selected CWEs:\n\n*   **CWE-266: Incorrect Privilege Assignment**\n    *   **How it matches:** The vulnerability description indicates that the manipulation of `/decoration/admin/userregister.php` leads to \"permission issues.\" Based on the CWE Guidance, this aligns with **incorrectly assigning privileges** during user registration.\n    *   **Security Implications:** This could allow unauthorized users to gain elevated privileges, potentially leading to data breaches, system compromise, or denial of service.\n    *   **Relationship:** CWE-266 is a child of CWE-285 (Improper Authorization), making it a more specific representation of the authorization failure.\n    *   **Mapping Guidance Influence:** The CWE guidance explicitly suggests using CWE-266 when a user is assigned the wrong role/group, which supports this mapping.\n    *   **Primary Weakness:** This is considered the primary weakness because it represents the root cause of the permission issues.\n    *   **Confidence:** 0.85\n\n*   **CWE-285: Improper Authorization**\n    *   **How it matches:** The vulnerability results in \"permission issues\", indicating that the application is not correctly authorizing access to resources or functionalities.\n    *   **Security Implications:** Users might gain unauthorized access to sensitive data or functionality, leading to data breaches, system compromise, or privilege escalation.\n    *   **Relationship:** CWE-285 is a parent Class of more specific authorization-related CWEs, such as CWE-266.\n    *   **Mapping Guidance Influence:** While CWE-285 is discouraged for direct mapping, it serves as a broader categorization for the authorization failure. It acts as a high-level classification when a more specific CWE is unavailable.\n    *   **Secondary Weakness:** This is a secondary weakness because it is a more general categorization of the authorization issue.\n    *   **Confidence:** 0.60\n\n## CWEs Considered but Not Used:\n\n*   **CWE-416: Use After Free:** This CWE is not relevant because the description does not indicate any memory management issues or use-after-free conditions.\n*   **CWE-441: Unintended Proxy or Intermediary ('Confused Deputy'):** This CWE is not relevant as there is no mention of a confused deputy situation where a program unintentionally misuses its authority.\n*   **CWE-563: Assignment to Variable without Use:** This CWE is not applicable because the description doesn't suggest any instances of variables being assigned values but not subsequently used.\n*   **CWE-89: Improper Neutralization of Special Elements used in an SQL Command ('SQL Injection'):** SQL injection is not indicated in the description.\n*   **CWE-79: Improper Neutralization of Input During Web Page Generation ('Cross-site Scripting'):** Cross-site scripting is not indicated in the description.\n*   **CWE-434: Unrestricted Upload of File with Dangerous Type:** The description does not mention any file upload functionality or associated vulnerabilities.\n*   **CWE-1336: Improper Neutralization of Special Elements Used in a Template Engine:** The description doesn't suggest any template engine related issues.\n*   **CWE-352: Cross-Site Request Forgery (CSRF):** There is no indication of CSRF in the description.\n*   **CWE-472: External Control of Assumed-Immutable Web Parameter:** The description does not specify any issues related to external control of assumed-immutable parameters.\n*   **CWE-471: Modification of Assumed-Immutable Data (MAID):** This CWE is not relevant because the description does not indicate any modification of assumed-immutable data.\n*   **CWE-269: Improper Privilege Management:** The guidance discourages use of this.\n*   **CWE-863: Incorrect Authorization:** Although related, CWE-266 provides a more specific root cause.\n*   **CWE-425: Direct Request ('Forced Browsing'):** There is no indication of forced browsing in the description.\n*   **CWE-276: Incorrect Default Permissions:** This is similar to CWE-266 but focuses on installation permissions. Since the vulnerability is at the user registration level, this is not applicable.\n*   **CWE-807: Reliance on Untrusted Inputs in a Security Decision:** There is no indication of security decisions based on untrusted inputs.\n*   **CWE-668: Exposure of Resource to Wrong Sphere:** This is a high level class that is not as specific as CWE-266.\n*   **CWE-41: Improper Resolution of Path Equivalence:** The description does not indicate any path equivalence issues.\n*   **CWE-274: Improper Handling of Insufficient Privileges:** The description does not indicate issues related to insufficient privileges.\n*   **CWE-280: Improper Handling of Insufficient Permissions or Privileges:** The description does not indicate issues related to insufficient permissions or privileges.\n*   **CWE-267: Privilege Defined With Unsafe Actions:** This is not as directly relevant as CWE-266.\n*   **CWE-1275: Sensitive Cookie with Improper SameSite Attribute:** No cookie information is available.\n*   **CWE-1336: Improper Neutralization of Special Elements Used in a Template Engine:** No template engine information is available.\n*   **CWE-123: Write-what-where Condition:** No memory corruption information is available.\n\n\n## CWE Relationship Analysis\n\nCurrent CWEs represent these abstraction levels: .\n\n\n### Vulnerability Chain Analysis\n\n**Chain starting from CWE-274:**\n- 274 (Improper Handling of Insufficient Privileges) - ROOT\n\n\n**Chain starting from CWE-471:**\n- 471 (Modification of Assumed-Immutable Data (MAID)) - ROOT\n\n\n\n### CWE Relationship Diagram\n\n```mermaid\ngraph TD\n    classDef primary fill:#f96,stroke:#333,stroke-width:2px\n    classDef secondary fill:#69f,stroke:#333\n    classDef tertiary fill:#9e9,stroke:#333\n```",
  "criticism": "",
  "resolution": "",
  "relevant_cwes": [
    {
      "metadata": {
        "doc_id": "416",
        "name": "Use After Free",
        "source": "alternate_terms",
        "original_matched_text": "AlternateTerms: Use-After-Free",
        "match_reason": "phrase_in_term_compound_part_3"
      },
      "similarity": 700.0,
      "alternate_term_match": true
    },
    {
      "metadata": {
        "doc_id": "441",
        "name": "Unintended Proxy or Intermediary ('Confused Deputy')",
        "source": "alternate_terms",
        "original_matched_text": "AlternateTerms: Confused Deputy",
        "match_reason": "phrase_in_term_compound_part_3"
      },
      "similarity": 700.0,
      "alternate_term_match": true
    },
    {
      "metadata": {
        "doc_id": "563",
        "name": "Assignment to Variable without Use",
        "source": "alternate_terms",
        "original_matched_text": "AlternateTerms: Unused Variable",
        "match_reason": "phrase_in_term_compound_part_3"
      },
      "similarity": 700.0,
      "alternate_term_match": true
    },
    {
      "metadata": {
        "doc_id": "89",
        "name": "Improper Neutralization of Special Elements used in an SQL Command ('SQL Injection')",
        "source": "sparse"
      },
      "similarity": 171.35226697322727
    },
    {
      "metadata": {
        "doc_id": "79",
        "name": "Improper Neutralization of Input During Web Page Generation ('Cross-site Scripting')",
        "source": "sparse"
      },
      "similarity": 168.07380758419458
    },
    {
      "metadata": {
        "doc_id": "434",
        "name": "Unrestricted Upload of File with Dangerous Type",
        "source": "sparse"
      },
      "similarity": 141.00543651610366
    },
    {
      "metadata": {
        "doc_id": "1336",
        "name": "Improper Neutralization of Special Elements Used in a Template Engine",
        "source": "sparse"
      },
      "similarity": 136.62181648658455
    },
    {
      "metadata": {
        "doc_id": "352",
        "name": "Cross-Site Request Forgery (CSRF)",
        "source": "sparse"
      },
      "similarity": 136.21202625495349
    },
    {
      "metadata": {
        "doc_id": "472",
        "name": "External Control of Assumed-Immutable Web Parameter",
        "type": "Base",
        "original_content": "The web application does not sufficiently verify inputs that are assumed to be immutable but are actually externally controllable, such as hidden form fields.",
        "source": "dense",
        "mapping_notes": {
          "usage": "Allowed",
          "rationale": "This CWE entry is at the Base level of abstraction, which is a preferred level of abstraction for mapping to the root causes of vulnerabilities.",
          "comments": "Carefully read both the name and description to ensure that this mapping is an appropriate fit. Do not try to 'force' a mapping to a lower-level Base/Variant simply to comply with this preferred level of abstraction.",
          "reasons": [
            "Acceptable-Use"
          ]
        },
        "score_info": {
          "retrievers": [
            "dense",
            "graph"
          ],
          "retriever_count": 2,
          "normalized_scores": {
            "dense": 0.5798129474841545,
            "graph": 2.0882018154136603
          }
        }
      },
      "similarity": 0.5798129474841545
    },
    {
      "doc_id": "471",
      "text": "CWE-471: Modification of Assumed-Immutable Data (MAID)",
      "score": 2.7196000000000002,
      "metadata": {
        "doc_id": "471",
        "name": "Modification of Assumed-Immutable Data (MAID)",
        "type": "base",
        "original_content": "CWE-471: Modification of Assumed-Immutable Data (MAID)",
        "relationships": [
          {
            "source_id": "471",
            "target_id": "621",
            "label": "CANFOLLOW",
            "properties": {
              "view_id": "1000"
            }
          },
          {
            "source_id": "471",
            "target_id": "607",
            "label": "PARENTOF",
            "properties": {
              "ordinal": "Primary",
              "view_id": "1000"
            }
          },
          {
            "source_id": "471",
            "target_id": "602",
            "label": "CANFOLLOW",
            "properties": {
              "view_id": "1000"
            }
          },
          {
            "source_id": "471",
            "target_id": "473",
            "label": "PARENTOF",
            "properties": {
              "ordinal": "Primary",
              "view_id": "1000"
            }
          },
          {
            "source_id": "471",
            "target_id": "472",
            "label": "PARENTOF",
            "properties": {
              "view_id": "1000"
            }
          },
          {
            "source_id": "471",
            "target_id": "425",
            "label": "CANFOLLOW",
            "properties": {
              "view_id": "1000"
            }
          },
          {
            "source_id": "471",
            "target_id": "291",
            "label": "PARENTOF",
            "properties": {
              "view_id": "1000"
            }
          },
          {
            "source_id": "471",
            "target_id": "1321",
            "label": "CANFOLLOW",
            "properties": {
              "ordinal": "Primary",
              "view_id": "1000"
            }
          },
          {
            "source_id": "471",
            "target_id": "1282",
            "label": "CANFOLLOW",
            "properties": {
              "view_id": "1000"
            }
          },
          {
            "source_id": "471",
            "target_id": "664",
            "label": "CHILDOF",
            "properties": {
              "ordinal": "Primary",
              "view_id": "1000"
            }
          },
          {
            "source_id": "664",
            "target_id": "471",
            "label": "PARENTOF",
            "properties": {
              "ordinal": "Primary",
              "view_id": "1000"
            }
          },
          {
            "source_id": "621",
            "target_id": "471",
            "label": "CANPRECEDE",
            "properties": {
              "view_id": "1000"
            }
          },
          {
            "source_id": "607",
            "target_id": "471",
            "label": "CHILDOF",
            "properties": {
              "ordinal": "Primary",
              "view_id": "1000"
            }
          },
          {
            "source_id": "602",
            "target_id": "471",
            "label": "CANPRECEDE",
            "properties": {
              "view_id": "1000"
            }
          },
          {
            "source_id": "473",
            "target_id": "471",
            "label": "CHILDOF",
            "properties": {
              "ordinal": "Primary",
              "view_id": "1000"
            }
          },
          {
            "source_id": "472",
            "target_id": "471",
            "label": "CHILDOF",
            "properties": {
              "view_id": "1000"
            }
          },
          {
            "source_id": "425",
            "target_id": "471",
            "label": "CANPRECEDE",
            "properties": {
              "view_id": "1000"
            }
          },
          {
            "source_id": "291",
            "target_id": "471",
            "label": "CHILDOF",
            "properties": {
              "view_id": "1000"
            }
          },
          {
            "source_id": "1321",
            "target_id": "471",
            "label": "CANPRECEDE",
            "properties": {
              "ordinal": "Primary",
              "view_id": "1000"
            }
          },
          {
            "source_id": "1282",
            "target_id": "471",
            "label": "CANPRECEDE",
            "properties": {
              "view_id": "1000"
            }
          }
        ],
        "score_components": {
          "relationship_chain": 1.0,
          "abstraction_path": 0.5599999999999999,
          "sequence_path": 1.0
        },
        "abstraction_factor": 1.3,
        "graph_path_info": {
          "path_types": [
            "relationship_chain",
            "abstraction_path_up",
            "vulnerability_sequence_forward"
          ],
          "best_paths": {
            "relationship_chain": {
              "path": [
                [
                  "425",
                  "471",
                  "CANPRECEDE"
                ]
              ],
              "score": 1.0,
              "type": "relationship_chain",
              "source": "425"
            },
            "abstraction_path_up": {
              "path": [
                [
                  "472",
                  "471",
                  "CHILDOF"
                ]
              ],
              "score": 0.5599999999999999,
              "type": "abstraction_path_up",
              "source": "472"
            },
            "vulnerability_sequence_forward": {
              "path": [
                [
                  "425",
                  "471",
                  "CANPRECEDE"
                ]
              ],
              "score": 1.0,
              "type": "vulnerability_sequence_forward",
              "source": "425"
            }
          }
        },
        "abstraction_level": "base",
        "position": "after",
        "sources": [
          "graph"
        ],
        "source": "graph",
        "mapping_notes": {
          "usage": "Allowed",
          "rationale": "This CWE entry is at the Base level of abstraction, which is a preferred level of abstraction for mapping to the root causes of vulnerabilities.",
          "comments": "Carefully read both the name and description to ensure that this mapping is an appropriate fit. Do not try to 'force' a mapping to a lower-level Base/Variant simply to comply with this preferred level of abstraction.",
          "reasons": [
            "Acceptable-Use"
          ]
        },
        "score_info": {
          "retrievers": [
            "graph"
          ],
          "retriever_count": 1,
          "normalized_scores": {
            "graph": 2.7196000000000002
          }
        }
      },
      "similarity": 2.7196000000000002
    }
  ],
  "identified_cwes": {
    "analyzer": [
      "CWE-274",
      "CWE-471",
      "CWE-416",
      "CWE-79",
      "CWE-1336",
      "CWE-269",
      "CWE-285",
      "CWE-807",
      "CWE-89",
      "CWE-123",
      "CWE-352",
      "CWE-267",
      "CWE-266",
      "CWE-276",
      "CWE-425",
      "CWE-41",
      "CWE-434",
      "CWE-863",
      "CWE-280",
      "CWE-441",
      "CWE-668",
      "CWE-472",
      "CWE-563",
      "CWE-1275"
    ],
    "critic_additional": []
  },
  "keyphrase_cwe_mapping": {}
}