{
  "vulnerability_info": "VulnerabilityInfo(cve_id='CVE-2025-1960', description='**CWE-1188 Initialization of a Resource with an Insecure Default vulnerability** exists that could cause an attacker to execute unauthorized commands when a systems **default password** credentials have not been changed on first use. The default username is not displayed correctly in the WebHMI interface.', key_phrases={'rootcause': ['CWE-1188 Initialization of a Resource with an Insecure Default vulnerability', 'default password'], 'weakness': '', 'impact': 'execute unauthorized commands', 'vector': '', 'attacker': 'attacker', 'product': '', 'version': '', 'component': 'WebHMI interface'}, reference_content='## Analysis of CVE-2025-1960 Content\\n\\nThis content is **RELEVANT** to CVE-2025-1960 and provides more detail than the official CVE description.\\n\\n**Root cause of vulnerability:**\\n\\nInitialization of a Resource with an Insecure Default vulnerability exists because the default username is not displayed correctly in the WebHMI interface, and default password credentials have not been changed on first use.\\n\\n**Weaknesses/vulnerabilities present:**\\n\\n*   CWE-1188: Initialization of a Resource with an Insecure Default\\n\\n**Impact of exploitation:**\\n\\nUnauthorized access to the underlying software application running WebHMI. The CVSS scores indicate a Critical severity:\\n*   CVSS v3.1 Base Score: 9.8 (Critical)\\n*   CVSS v4.0 Base Score: 9.2 (Critical)\\n    *   Confidentiality: High\\n    *   Integrity: High\\n    *   Availability: High\\n\\n**Attack vectors:**\\n\\nNetwork accessible (AV:N). Low attack complexity (AC:L). No prior privileges required (PR:N). No user interaction required (UI:N).\\n\\n**Required attacker capabilities/position:**\\n\\nNo specific capabilities or positioning are mentioned beyond network access.\\n\\n**Mitigation or fix:**\\n\\n*   Apply Hotfix WebHMI\\\\_Fix\\\\_users\\\\_for\\\\_Standard.V1 of WebHMI, available from Schneider Electric Customer Care Center.\\n*   Implement all hardening guidelines provided with the product.\\n*   Ensure WebHMI is not exposed to the internet.\\n*   Change default credentials.', similar_info={'cwe_distribution': {}, 'cwe_consensus': '', 'similarity_stats': {'thresholds': [], 'total_samples_by_threshold': {}, 'top_cwes_by_threshold': {}}}, similarity_summary=SimilarityInsight(consensus_cwe='', top_cwes=[], confidence_levels={}, total_samples=0), analysis='', analysis_with_relationships='', criticism='', resolution='', relevant_cwes=[{'metadata': {'doc_id': '1188', 'name': 'Initialization of a Resource with an Insecure Default', 'source': 'sparse', 'original_content': 'The product initializes or sets a resource with a default that is intended to be changed by the administrator, but the default is not secure.', 'keyphrase_sources': [{'id': 'rootcause:CWE-1188 Initialization of a Resource with an Insecure Default vulnerability', 'keyphrase': 'CWE-1188 Initialization of a Resource with an Insecure Default vulnerability', 'type': 'rootcause'}, {'id': 'rootcause:default password', 'keyphrase': 'default password', 'type': 'rootcause'}, {'id': 'impact:execute unauthorized commands', 'keyphrase': 'execute unauthorized commands', 'type': 'impact'}, {'id': 'attacker:attacker', 'keyphrase': 'attacker', 'type': 'attacker'}, {'id': 'component:WebHMI interface', 'keyphrase': 'WebHMI interface', 'type': 'component'}]}, 'similarity': np.float64(513.3910414993238)}, {'metadata': {'doc_id': '453', 'name': 'Insecure Default Variable Initialization', 'source': 'sparse', 'original_content': 'The product, by default, initializes an internal variable with an insecure or less secure value than is possible.', 'keyphrase_sources': [{'id': 'rootcause:CWE-1188 Initialization of a Resource with an Insecure Default vulnerability', 'keyphrase': 'CWE-1188 Initialization of a Resource with an Insecure Default vulnerability', 'type': 'rootcause'}]}, 'similarity': np.float64(458.84176203891457)}, {'metadata': {'doc_id': '1419', 'name': 'Incorrect Initialization of Resource', 'source': 'sparse', 'original_content': 'The product attempts to initialize a resource but does not correctly do so, which might leave the resource in an unexpected, incorrect, or insecure state when it is accessed.', 'keyphrase_sources': [{'id': 'rootcause:CWE-1188 Initialization of a Resource with an Insecure Default vulnerability', 'keyphrase': 'CWE-1188 Initialization of a Resource with an Insecure Default vulnerability', 'type': 'rootcause'}]}, 'similarity': np.float64(448.8447056841791)}, {'metadata': {'doc_id': '1391', 'name': 'Use of Weak Credentials', 'source': 'sparse', 'original_content': 'The product uses weak credentials (such as a default key or hard-coded password) that can be calculated, derived, reused, or guessed by an attacker.', 'keyphrase_sources': [{'id': 'rootcause:CWE-1188 Initialization of a Resource with an Insecure Default vulnerability', 'keyphrase': 'CWE-1188 Initialization of a Resource with an Insecure Default vulnerability', 'type': 'rootcause'}, {'id': 'rootcause:default password', 'keyphrase': 'default password', 'type': 'rootcause'}, {'id': 'impact:execute unauthorized commands', 'keyphrase': 'execute unauthorized commands', 'type': 'impact'}, {'id': 'attacker:attacker', 'keyphrase': 'attacker', 'type': 'attacker'}, {'id': 'component:WebHMI interface', 'keyphrase': 'WebHMI interface', 'type': 'component'}]}, 'similarity': np.float64(411.393426753206)}, {'metadata': {'doc_id': '276', 'name': 'Incorrect Default Permissions', 'source': 'sparse', 'original_content': 'During installation, installed file permissions are set to allow anyone to modify those files.', 'keyphrase_sources': [{'id': 'rootcause:CWE-1188 Initialization of a Resource with an Insecure Default vulnerability', 'keyphrase': 'CWE-1188 Initialization of a Resource with an Insecure Default vulnerability', 'type': 'rootcause'}, {'id': 'attacker:attacker', 'keyphrase': 'attacker', 'type': 'attacker'}]}, 'similarity': np.float64(411.28060278261665)}, {'metadata': {'doc_id': '798', 'name': 'Use of Hard-coded Credentials', 'source': 'sparse', 'original_content': 'The product contains hard-coded credentials, such as a password or cryptographic key.', 'keyphrase_sources': [{'id': 'rootcause:default password', 'keyphrase': 'default password', 'type': 'rootcause'}, {'id': 'impact:execute unauthorized commands', 'keyphrase': 'execute unauthorized commands', 'type': 'impact'}, {'id': 'attacker:attacker', 'keyphrase': 'attacker', 'type': 'attacker'}, {'id': 'component:WebHMI interface', 'keyphrase': 'WebHMI interface', 'type': 'component'}]}, 'similarity': np.float64(321.55664161251707)}, {'metadata': {'doc_id': '306', 'name': 'Missing Authentication for Critical Function', 'source': 'sparse', 'original_content': 'The product does not perform any authentication for functionality that requires a provable user identity or consumes a significant amount of resources.', 'keyphrase_sources': [{'id': 'rootcause:default password', 'keyphrase': 'default password', 'type': 'rootcause'}, {'id': 'impact:execute unauthorized commands', 'keyphrase': 'execute unauthorized commands', 'type': 'impact'}, {'id': 'attacker:attacker', 'keyphrase': 'attacker', 'type': 'attacker'}, {'id': 'component:WebHMI interface', 'keyphrase': 'WebHMI interface', 'type': 'component'}]}, 'similarity': np.float64(304.96377563315264)}, {'metadata': {'doc_id': '259', 'name': 'Use of Hard-coded Password', 'source': 'sparse', 'original_content': 'The product contains a hard-coded password, which it uses for its own inbound authentication or for outbound communication to external components.', 'keyphrase_sources': [{'id': 'rootcause:default password', 'keyphrase': 'default password', 'type': 'rootcause'}]}, 'similarity': np.float64(302.924644832142)}, {'metadata': {'doc_id': '305', 'name': 'Authentication Bypass by Primary Weakness', 'source': 'sparse', 'original_content': 'The authentication algorithm is sound, but the implemented mechanism can be bypassed as the result of a separate weakness that is primary to the authentication error.', 'keyphrase_sources': [{'id': 'component:WebHMI interface', 'keyphrase': 'WebHMI interface', 'type': 'component'}]}, 'similarity': np.float64(103.76552089015696)}, {'metadata': {'doc_id': '1299', 'name': 'Missing Protection Mechanism for Alternate Hardware Interface', 'source': 'sparse', 'original_content': 'The lack of protections on alternate paths to access\\n                control-protected assets (such as unprotected shadow registers\\n                and other external facing unguarded interfaces) allows an\\n                attacker to bypass existing protections to the asset that are\\n\\t\\tonly performed against the primary path.', 'keyphrase_sources': [{'id': 'impact:execute unauthorized commands', 'keyphrase': 'execute unauthorized commands', 'type': 'impact'}]}, 'similarity': np.float64(102.82254263658673)}], identified_cwes={'analyzer': [], 'critic_additional': []})",
  "retrieval_results": {
    "has_multiple_keyphrases": true,
    "keyphrase_cwe_sets": {
      "rootcause:CWE-1188 Initialization of a Resource with an Insecure Default vulnerability": {
        "keyphrase": "CWE-1188 Initialization of a Resource with an Insecure Default vulnerability",
        "type": "rootcause",
        "cwes": [
          {
            "metadata": {
              "doc_id": "1188",
              "name": "Initialization of a Resource with an Insecure Default",
              "source": "sparse",
              "original_content": "The product initializes or sets a resource with a default that is intended to be changed by the administrator, but the default is not secure.",
              "keyphrase_sources": [
                {
                  "id": "rootcause:CWE-1188 Initialization of a Resource with an Insecure Default vulnerability",
                  "keyphrase": "CWE-1188 Initialization of a Resource with an Insecure Default vulnerability",
                  "type": "rootcause"
                },
                {
                  "id": "rootcause:default password",
                  "keyphrase": "default password",
                  "type": "rootcause"
                },
                {
                  "id": "impact:execute unauthorized commands",
                  "keyphrase": "execute unauthorized commands",
                  "type": "impact"
                },
                {
                  "id": "attacker:attacker",
                  "keyphrase": "attacker",
                  "type": "attacker"
                },
                {
                  "id": "component:WebHMI interface",
                  "keyphrase": "WebHMI interface",
                  "type": "component"
                }
              ]
            },
            "similarity": 513.3910414993238
          },
          {
            "metadata": {
              "doc_id": "453",
              "name": "Insecure Default Variable Initialization",
              "source": "sparse",
              "original_content": "The product, by default, initializes an internal variable with an insecure or less secure value than is possible.",
              "keyphrase_sources": [
                {
                  "id": "rootcause:CWE-1188 Initialization of a Resource with an Insecure Default vulnerability",
                  "keyphrase": "CWE-1188 Initialization of a Resource with an Insecure Default vulnerability",
                  "type": "rootcause"
                }
              ]
            },
            "similarity": 458.84176203891457
          },
          {
            "metadata": {
              "doc_id": "1419",
              "name": "Incorrect Initialization of Resource",
              "source": "sparse",
              "original_content": "The product attempts to initialize a resource but does not correctly do so, which might leave the resource in an unexpected, incorrect, or insecure state when it is accessed.",
              "keyphrase_sources": [
                {
                  "id": "rootcause:CWE-1188 Initialization of a Resource with an Insecure Default vulnerability",
                  "keyphrase": "CWE-1188 Initialization of a Resource with an Insecure Default vulnerability",
                  "type": "rootcause"
                }
              ]
            },
            "similarity": 448.8447056841791
          },
          {
            "metadata": {
              "doc_id": "1391",
              "name": "Use of Weak Credentials",
              "source": "sparse",
              "original_content": "The product uses weak credentials (such as a default key or hard-coded password) that can be calculated, derived, reused, or guessed by an attacker.",
              "keyphrase_sources": [
                {
                  "id": "rootcause:CWE-1188 Initialization of a Resource with an Insecure Default vulnerability",
                  "keyphrase": "CWE-1188 Initialization of a Resource with an Insecure Default vulnerability",
                  "type": "rootcause"
                },
                {
                  "id": "rootcause:default password",
                  "keyphrase": "default password",
                  "type": "rootcause"
                },
                {
                  "id": "impact:execute unauthorized commands",
                  "keyphrase": "execute unauthorized commands",
                  "type": "impact"
                },
                {
                  "id": "attacker:attacker",
                  "keyphrase": "attacker",
                  "type": "attacker"
                },
                {
                  "id": "component:WebHMI interface",
                  "keyphrase": "WebHMI interface",
                  "type": "component"
                }
              ]
            },
            "similarity": 411.393426753206
          },
          {
            "metadata": {
              "doc_id": "276",
              "name": "Incorrect Default Permissions",
              "source": "sparse",
              "original_content": "During installation, installed file permissions are set to allow anyone to modify those files.",
              "keyphrase_sources": [
                {
                  "id": "rootcause:CWE-1188 Initialization of a Resource with an Insecure Default vulnerability",
                  "keyphrase": "CWE-1188 Initialization of a Resource with an Insecure Default vulnerability",
                  "type": "rootcause"
                },
                {
                  "id": "attacker:attacker",
                  "keyphrase": "attacker",
                  "type": "attacker"
                }
              ]
            },
            "similarity": 411.28060278261665
          }
        ]
      },
      "rootcause:default password": {
        "keyphrase": "default password",
        "type": "rootcause",
        "cwes": [
          {
            "metadata": {
              "doc_id": "1188",
              "name": "Initialization of a Resource with an Insecure Default",
              "source": "sparse",
              "original_content": "The product initializes or sets a resource with a default that is intended to be changed by the administrator, but the default is not secure."
            },
            "similarity": 340.3791190946379
          },
          {
            "metadata": {
              "doc_id": "1391",
              "name": "Use of Weak Credentials",
              "source": "sparse",
              "original_content": "The product uses weak credentials (such as a default key or hard-coded password) that can be calculated, derived, reused, or guessed by an attacker."
            },
            "similarity": 321.5950468754156
          },
          {
            "metadata": {
              "doc_id": "798",
              "name": "Use of Hard-coded Credentials",
              "source": "sparse",
              "original_content": "The product contains hard-coded credentials, such as a password or cryptographic key.",
              "keyphrase_sources": [
                {
                  "id": "rootcause:default password",
                  "keyphrase": "default password",
                  "type": "rootcause"
                },
                {
                  "id": "impact:execute unauthorized commands",
                  "keyphrase": "execute unauthorized commands",
                  "type": "impact"
                },
                {
                  "id": "attacker:attacker",
                  "keyphrase": "attacker",
                  "type": "attacker"
                },
                {
                  "id": "component:WebHMI interface",
                  "keyphrase": "WebHMI interface",
                  "type": "component"
                }
              ]
            },
            "similarity": 321.55664161251707
          },
          {
            "metadata": {
              "doc_id": "306",
              "name": "Missing Authentication for Critical Function",
              "source": "sparse",
              "original_content": "The product does not perform any authentication for functionality that requires a provable user identity or consumes a significant amount of resources.",
              "keyphrase_sources": [
                {
                  "id": "rootcause:default password",
                  "keyphrase": "default password",
                  "type": "rootcause"
                },
                {
                  "id": "impact:execute unauthorized commands",
                  "keyphrase": "execute unauthorized commands",
                  "type": "impact"
                },
                {
                  "id": "attacker:attacker",
                  "keyphrase": "attacker",
                  "type": "attacker"
                },
                {
                  "id": "component:WebHMI interface",
                  "keyphrase": "WebHMI interface",
                  "type": "component"
                }
              ]
            },
            "similarity": 304.96377563315264
          },
          {
            "metadata": {
              "doc_id": "259",
              "name": "Use of Hard-coded Password",
              "source": "sparse",
              "original_content": "The product contains a hard-coded password, which it uses for its own inbound authentication or for outbound communication to external components.",
              "keyphrase_sources": [
                {
                  "id": "rootcause:default password",
                  "keyphrase": "default password",
                  "type": "rootcause"
                }
              ]
            },
            "similarity": 302.924644832142
          }
        ]
      },
      "impact:execute unauthorized commands": {
        "keyphrase": "execute unauthorized commands",
        "type": "impact",
        "cwes": [
          {
            "metadata": {
              "doc_id": "306",
              "name": "Missing Authentication for Critical Function",
              "source": "sparse",
              "original_content": "The product does not perform any authentication for functionality that requires a provable user identity or consumes a significant amount of resources."
            },
            "similarity": 102.93121969271435
          },
          {
            "metadata": {
              "doc_id": "1299",
              "name": "Missing Protection Mechanism for Alternate Hardware Interface",
              "source": "sparse",
              "original_content": "The lack of protections on alternate paths to access\n                control-protected assets (such as unprotected shadow registers\n                and other external facing unguarded interfaces) allows an\n                attacker to bypass existing protections to the asset that are\n\t\tonly performed against the primary path.",
              "keyphrase_sources": [
                {
                  "id": "impact:execute unauthorized commands",
                  "keyphrase": "execute unauthorized commands",
                  "type": "impact"
                }
              ]
            },
            "similarity": 102.82254263658673
          },
          {
            "metadata": {
              "doc_id": "798",
              "name": "Use of Hard-coded Credentials",
              "source": "sparse",
              "original_content": "The product contains hard-coded credentials, such as a password or cryptographic key."
            },
            "similarity": 102.71242964521565
          },
          {
            "metadata": {
              "doc_id": "1188",
              "name": "Initialization of a Resource with an Insecure Default",
              "source": "sparse",
              "original_content": "The product initializes or sets a resource with a default that is intended to be changed by the administrator, but the default is not secure."
            },
            "similarity": 102.24673279780487
          },
          {
            "metadata": {
              "doc_id": "1391",
              "name": "Use of Weak Credentials",
              "source": "sparse",
              "original_content": "The product uses weak credentials (such as a default key or hard-coded password) that can be calculated, derived, reused, or guessed by an attacker."
            },
            "similarity": 99.59141263870845
          }
        ]
      },
      "attacker:attacker": {
        "keyphrase": "attacker",
        "type": "attacker",
        "cwes": [
          {
            "metadata": {
              "doc_id": "1188",
              "name": "Initialization of a Resource with an Insecure Default",
              "source": "sparse",
              "original_content": "The product initializes or sets a resource with a default that is intended to be changed by the administrator, but the default is not secure."
            },
            "similarity": 104.95510244504129
          },
          {
            "metadata": {
              "doc_id": "798",
              "name": "Use of Hard-coded Credentials",
              "source": "sparse",
              "original_content": "The product contains hard-coded credentials, such as a password or cryptographic key."
            },
            "similarity": 101.43385714047375
          },
          {
            "metadata": {
              "doc_id": "1391",
              "name": "Use of Weak Credentials",
              "source": "sparse",
              "original_content": "The product uses weak credentials (such as a default key or hard-coded password) that can be calculated, derived, reused, or guessed by an attacker."
            },
            "similarity": 99.25041156894304
          },
          {
            "metadata": {
              "doc_id": "306",
              "name": "Missing Authentication for Critical Function",
              "source": "sparse",
              "original_content": "The product does not perform any authentication for functionality that requires a provable user identity or consumes a significant amount of resources."
            },
            "similarity": 96.83951759975245
          },
          {
            "metadata": {
              "doc_id": "276",
              "name": "Incorrect Default Permissions",
              "source": "sparse",
              "original_content": "During installation, installed file permissions are set to allow anyone to modify those files."
            },
            "similarity": 94.46016797768134
          }
        ]
      },
      "component:WebHMI interface": {
        "keyphrase": "WebHMI interface",
        "type": "component",
        "cwes": [
          {
            "metadata": {
              "doc_id": "1188",
              "name": "Initialization of a Resource with an Insecure Default",
              "source": "sparse",
              "original_content": "The product initializes or sets a resource with a default that is intended to be changed by the administrator, but the default is not secure."
            },
            "similarity": 105.56714850579525
          },
          {
            "metadata": {
              "doc_id": "305",
              "name": "Authentication Bypass by Primary Weakness",
              "source": "sparse",
              "original_content": "The authentication algorithm is sound, but the implemented mechanism can be bypassed as the result of a separate weakness that is primary to the authentication error.",
              "keyphrase_sources": [
                {
                  "id": "component:WebHMI interface",
                  "keyphrase": "WebHMI interface",
                  "type": "component"
                }
              ]
            },
            "similarity": 103.76552089015696
          },
          {
            "metadata": {
              "doc_id": "798",
              "name": "Use of Hard-coded Credentials",
              "source": "sparse",
              "original_content": "The product contains hard-coded credentials, such as a password or cryptographic key."
            },
            "similarity": 100.25010328541461
          },
          {
            "metadata": {
              "doc_id": "1391",
              "name": "Use of Weak Credentials",
              "source": "sparse",
              "original_content": "The product uses weak credentials (such as a default key or hard-coded password) that can be calculated, derived, reused, or guessed by an attacker."
            },
            "similarity": 99.22758260129237
          },
          {
            "metadata": {
              "doc_id": "306",
              "name": "Missing Authentication for Critical Function",
              "source": "sparse",
              "original_content": "The product does not perform any authentication for functionality that requires a provable user identity or consumes a significant amount of resources."
            },
            "similarity": 95.3819915829984
          }
        ]
      }
    },
    "keyphrase_mapping": {
      "1188": [
        {
          "id": "rootcause:CWE-1188 Initialization of a Resource with an Insecure Default vulnerability",
          "keyphrase": "CWE-1188 Initialization of a Resource with an Insecure Default vulnerability",
          "type": "rootcause"
        },
        {
          "id": "rootcause:default password",
          "keyphrase": "default password",
          "type": "rootcause"
        },
        {
          "id": "impact:execute unauthorized commands",
          "keyphrase": "execute unauthorized commands",
          "type": "impact"
        },
        {
          "id": "attacker:attacker",
          "keyphrase": "attacker",
          "type": "attacker"
        },
        {
          "id": "component:WebHMI interface",
          "keyphrase": "WebHMI interface",
          "type": "component"
        }
      ],
      "453": [
        {
          "id": "rootcause:CWE-1188 Initialization of a Resource with an Insecure Default vulnerability",
          "keyphrase": "CWE-1188 Initialization of a Resource with an Insecure Default vulnerability",
          "type": "rootcause"
        }
      ],
      "1419": [
        {
          "id": "rootcause:CWE-1188 Initialization of a Resource with an Insecure Default vulnerability",
          "keyphrase": "CWE-1188 Initialization of a Resource with an Insecure Default vulnerability",
          "type": "rootcause"
        }
      ],
      "1391": [
        {
          "id": "rootcause:CWE-1188 Initialization of a Resource with an Insecure Default vulnerability",
          "keyphrase": "CWE-1188 Initialization of a Resource with an Insecure Default vulnerability",
          "type": "rootcause"
        },
        {
          "id": "rootcause:default password",
          "keyphrase": "default password",
          "type": "rootcause"
        },
        {
          "id": "impact:execute unauthorized commands",
          "keyphrase": "execute unauthorized commands",
          "type": "impact"
        },
        {
          "id": "attacker:attacker",
          "keyphrase": "attacker",
          "type": "attacker"
        },
        {
          "id": "component:WebHMI interface",
          "keyphrase": "WebHMI interface",
          "type": "component"
        }
      ],
      "276": [
        {
          "id": "rootcause:CWE-1188 Initialization of a Resource with an Insecure Default vulnerability",
          "keyphrase": "CWE-1188 Initialization of a Resource with an Insecure Default vulnerability",
          "type": "rootcause"
        },
        {
          "id": "attacker:attacker",
          "keyphrase": "attacker",
          "type": "attacker"
        }
      ],
      "798": [
        {
          "id": "rootcause:default password",
          "keyphrase": "default password",
          "type": "rootcause"
        },
        {
          "id": "impact:execute unauthorized commands",
          "keyphrase": "execute unauthorized commands",
          "type": "impact"
        },
        {
          "id": "attacker:attacker",
          "keyphrase": "attacker",
          "type": "attacker"
        },
        {
          "id": "component:WebHMI interface",
          "keyphrase": "WebHMI interface",
          "type": "component"
        }
      ],
      "306": [
        {
          "id": "rootcause:default password",
          "keyphrase": "default password",
          "type": "rootcause"
        },
        {
          "id": "impact:execute unauthorized commands",
          "keyphrase": "execute unauthorized commands",
          "type": "impact"
        },
        {
          "id": "attacker:attacker",
          "keyphrase": "attacker",
          "type": "attacker"
        },
        {
          "id": "component:WebHMI interface",
          "keyphrase": "WebHMI interface",
          "type": "component"
        }
      ],
      "259": [
        {
          "id": "rootcause:default password",
          "keyphrase": "default password",
          "type": "rootcause"
        }
      ],
      "1299": [
        {
          "id": "impact:execute unauthorized commands",
          "keyphrase": "execute unauthorized commands",
          "type": "impact"
        }
      ],
      "305": [
        {
          "id": "component:WebHMI interface",
          "keyphrase": "WebHMI interface",
          "type": "component"
        }
      ]
    },
    "relevant_cwes": [
      {
        "metadata": {
          "doc_id": "1188",
          "name": "Initialization of a Resource with an Insecure Default",
          "source": "sparse",
          "original_content": "The product initializes or sets a resource with a default that is intended to be changed by the administrator, but the default is not secure.",
          "keyphrase_sources": [
            {
              "id": "rootcause:CWE-1188 Initialization of a Resource with an Insecure Default vulnerability",
              "keyphrase": "CWE-1188 Initialization of a Resource with an Insecure Default vulnerability",
              "type": "rootcause"
            },
            {
              "id": "rootcause:default password",
              "keyphrase": "default password",
              "type": "rootcause"
            },
            {
              "id": "impact:execute unauthorized commands",
              "keyphrase": "execute unauthorized commands",
              "type": "impact"
            },
            {
              "id": "attacker:attacker",
              "keyphrase": "attacker",
              "type": "attacker"
            },
            {
              "id": "component:WebHMI interface",
              "keyphrase": "WebHMI interface",
              "type": "component"
            }
          ]
        },
        "similarity": 513.3910414993238
      },
      {
        "metadata": {
          "doc_id": "453",
          "name": "Insecure Default Variable Initialization",
          "source": "sparse",
          "original_content": "The product, by default, initializes an internal variable with an insecure or less secure value than is possible.",
          "keyphrase_sources": [
            {
              "id": "rootcause:CWE-1188 Initialization of a Resource with an Insecure Default vulnerability",
              "keyphrase": "CWE-1188 Initialization of a Resource with an Insecure Default vulnerability",
              "type": "rootcause"
            }
          ]
        },
        "similarity": 458.84176203891457
      },
      {
        "metadata": {
          "doc_id": "1419",
          "name": "Incorrect Initialization of Resource",
          "source": "sparse",
          "original_content": "The product attempts to initialize a resource but does not correctly do so, which might leave the resource in an unexpected, incorrect, or insecure state when it is accessed.",
          "keyphrase_sources": [
            {
              "id": "rootcause:CWE-1188 Initialization of a Resource with an Insecure Default vulnerability",
              "keyphrase": "CWE-1188 Initialization of a Resource with an Insecure Default vulnerability",
              "type": "rootcause"
            }
          ]
        },
        "similarity": 448.8447056841791
      },
      {
        "metadata": {
          "doc_id": "1391",
          "name": "Use of Weak Credentials",
          "source": "sparse",
          "original_content": "The product uses weak credentials (such as a default key or hard-coded password) that can be calculated, derived, reused, or guessed by an attacker.",
          "keyphrase_sources": [
            {
              "id": "rootcause:CWE-1188 Initialization of a Resource with an Insecure Default vulnerability",
              "keyphrase": "CWE-1188 Initialization of a Resource with an Insecure Default vulnerability",
              "type": "rootcause"
            },
            {
              "id": "rootcause:default password",
              "keyphrase": "default password",
              "type": "rootcause"
            },
            {
              "id": "impact:execute unauthorized commands",
              "keyphrase": "execute unauthorized commands",
              "type": "impact"
            },
            {
              "id": "attacker:attacker",
              "keyphrase": "attacker",
              "type": "attacker"
            },
            {
              "id": "component:WebHMI interface",
              "keyphrase": "WebHMI interface",
              "type": "component"
            }
          ]
        },
        "similarity": 411.393426753206
      },
      {
        "metadata": {
          "doc_id": "276",
          "name": "Incorrect Default Permissions",
          "source": "sparse",
          "original_content": "During installation, installed file permissions are set to allow anyone to modify those files.",
          "keyphrase_sources": [
            {
              "id": "rootcause:CWE-1188 Initialization of a Resource with an Insecure Default vulnerability",
              "keyphrase": "CWE-1188 Initialization of a Resource with an Insecure Default vulnerability",
              "type": "rootcause"
            },
            {
              "id": "attacker:attacker",
              "keyphrase": "attacker",
              "type": "attacker"
            }
          ]
        },
        "similarity": 411.28060278261665
      },
      {
        "metadata": {
          "doc_id": "798",
          "name": "Use of Hard-coded Credentials",
          "source": "sparse",
          "original_content": "The product contains hard-coded credentials, such as a password or cryptographic key.",
          "keyphrase_sources": [
            {
              "id": "rootcause:default password",
              "keyphrase": "default password",
              "type": "rootcause"
            },
            {
              "id": "impact:execute unauthorized commands",
              "keyphrase": "execute unauthorized commands",
              "type": "impact"
            },
            {
              "id": "attacker:attacker",
              "keyphrase": "attacker",
              "type": "attacker"
            },
            {
              "id": "component:WebHMI interface",
              "keyphrase": "WebHMI interface",
              "type": "component"
            }
          ]
        },
        "similarity": 321.55664161251707
      },
      {
        "metadata": {
          "doc_id": "306",
          "name": "Missing Authentication for Critical Function",
          "source": "sparse",
          "original_content": "The product does not perform any authentication for functionality that requires a provable user identity or consumes a significant amount of resources.",
          "keyphrase_sources": [
            {
              "id": "rootcause:default password",
              "keyphrase": "default password",
              "type": "rootcause"
            },
            {
              "id": "impact:execute unauthorized commands",
              "keyphrase": "execute unauthorized commands",
              "type": "impact"
            },
            {
              "id": "attacker:attacker",
              "keyphrase": "attacker",
              "type": "attacker"
            },
            {
              "id": "component:WebHMI interface",
              "keyphrase": "WebHMI interface",
              "type": "component"
            }
          ]
        },
        "similarity": 304.96377563315264
      },
      {
        "metadata": {
          "doc_id": "259",
          "name": "Use of Hard-coded Password",
          "source": "sparse",
          "original_content": "The product contains a hard-coded password, which it uses for its own inbound authentication or for outbound communication to external components.",
          "keyphrase_sources": [
            {
              "id": "rootcause:default password",
              "keyphrase": "default password",
              "type": "rootcause"
            }
          ]
        },
        "similarity": 302.924644832142
      },
      {
        "metadata": {
          "doc_id": "305",
          "name": "Authentication Bypass by Primary Weakness",
          "source": "sparse",
          "original_content": "The authentication algorithm is sound, but the implemented mechanism can be bypassed as the result of a separate weakness that is primary to the authentication error.",
          "keyphrase_sources": [
            {
              "id": "component:WebHMI interface",
              "keyphrase": "WebHMI interface",
              "type": "component"
            }
          ]
        },
        "similarity": 103.76552089015696
      },
      {
        "metadata": {
          "doc_id": "1299",
          "name": "Missing Protection Mechanism for Alternate Hardware Interface",
          "source": "sparse",
          "original_content": "The lack of protections on alternate paths to access\n                control-protected assets (such as unprotected shadow registers\n                and other external facing unguarded interfaces) allows an\n                attacker to bypass existing protections to the asset that are\n\t\tonly performed against the primary path.",
          "keyphrase_sources": [
            {
              "id": "impact:execute unauthorized commands",
              "keyphrase": "execute unauthorized commands",
              "type": "impact"
            }
          ]
        },
        "similarity": 102.82254263658673
      }
    ],
    "enhanced_query": "# Vulnerability Description\n\n    **CWE-1188 Initialization of a Resource with an Insecure Default vulnerability** exists that could cause an attacker to execute unauthorized commands when a systems **default password** credentials have not been changed on first use. The default username is not displayed correctly in the WebHMI interface.\n\n    # Keyphrase-Specific CWE Analysis\n    This vulnerability contains multiple keyphrases that may map to different CWEs. \n    Please analyze each keyphrase separately and determine the most appropriate CWE(s) for each.\n\n    ## ROOTCAUSE: 'CWE-1188 Initialization of a Resource with an Insecure Default vulnerability'\n\nRelevant CWEs for this ROOTCAUSE:\n\n### 1. CWE-1188: Initialization of a Resource with an Insecure Default (Score: 513.39)\n\nThe product initializes or sets a resource with a default that is intended to be changed by the administrator, but the default is not secure....\n\n### 2. CWE-453: Insecure Default Variable Initialization (Score: 458.84)\n\nThe product, by default, initializes an internal variable with an insecure or less secure value than is possible....\n\n### 3. CWE-1419: Incorrect Initialization of Resource (Score: 448.84)\n\nThe product attempts to initialize a resource but does not correctly do so, which might leave the resource in an unexpected, incorrect, or insecure state when it is accessed....\n\n### 4. CWE-1391: Use of Weak Credentials (Score: 411.39)\n\nThe product uses weak credentials (such as a default key or hard-coded password) that can be calculated, derived, reused, or guessed by an attacker....\n\n### 5. CWE-276: Incorrect Default Permissions (Score: 411.28)\n\nDuring installation, installed file permissions are set to allow anyone to modify those files....\n\n## ROOTCAUSE: 'default password'\n\nRelevant CWEs for this ROOTCAUSE:\n\n### 1. CWE-1188: Initialization of a Resource with an Insecure Default (Score: 513.39)\n\nThe product initializes or sets a resource with a default that is intended to be changed by the administrator, but the default is not secure....\n\n### 2. CWE-1391: Use of Weak Credentials (Score: 411.39)\n\nThe product uses weak credentials (such as a default key or hard-coded password) that can be calculated, derived, reused, or guessed by an attacker....\n\n### 3. CWE-798: Use of Hard-coded Credentials (Score: 321.56)\n\nThe product contains hard-coded credentials, such as a password or cryptographic key....\n\n### 4. CWE-306: Missing Authentication for Critical Function (Score: 304.96)\n\nThe product does not perform any authentication for functionality that requires a provable user identity or consumes a significant amount of resources....\n\n### 5. CWE-259: Use of Hard-coded Password (Score: 302.92)\n\nThe product contains a hard-coded password, which it uses for its own inbound authentication or for outbound communication to external components....\n\n## IMPACT: 'execute unauthorized commands'\n\nRelevant CWEs for this IMPACT:\n\n### 1. CWE-1188: Initialization of a Resource with an Insecure Default (Score: 513.39)\n\nThe product initializes or sets a resource with a default that is intended to be changed by the administrator, but the default is not secure....\n\n### 2. CWE-1391: Use of Weak Credentials (Score: 411.39)\n\nThe product uses weak credentials (such as a default key or hard-coded password) that can be calculated, derived, reused, or guessed by an attacker....\n\n### 3. CWE-798: Use of Hard-coded Credentials (Score: 321.56)\n\nThe product contains hard-coded credentials, such as a password or cryptographic key....\n\n### 4. CWE-306: Missing Authentication for Critical Function (Score: 304.96)\n\nThe product does not perform any authentication for functionality that requires a provable user identity or consumes a significant amount of resources....\n\n### 5. CWE-1299: Missing Protection Mechanism for Alternate Hardware Interface (Score: 102.82)\n\nThe lack of protections on alternate paths to access\n                control-protected assets (such as unprotected shadow registers\n                and other external facing unguarded interfaces) allows an\n                attacker to bypass existing protections to the asset that are\n\t\tonly performed...\n\n## ATTACKER: 'attacker'\n\nRelevant CWEs for this ATTACKER:\n\n### 1. CWE-1188: Initialization of a Resource with an Insecure Default (Score: 513.39)\n\nThe product initializes or sets a resource with a default that is intended to be changed by the administrator, but the default is not secure....\n\n### 2. CWE-1391: Use of Weak Credentials (Score: 411.39)\n\nThe product uses weak credentials (such as a default key or hard-coded password) that can be calculated, derived, reused, or guessed by an attacker....\n\n### 3. CWE-276: Incorrect Default Permissions (Score: 411.28)\n\nDuring installation, installed file permissions are set to allow anyone to modify those files....\n\n### 4. CWE-798: Use of Hard-coded Credentials (Score: 321.56)\n\nThe product contains hard-coded credentials, such as a password or cryptographic key....\n\n### 5. CWE-306: Missing Authentication for Critical Function (Score: 304.96)\n\nThe product does not perform any authentication for functionality that requires a provable user identity or consumes a significant amount of resources....\n\n## COMPONENT: 'WebHMI interface'\n\nRelevant CWEs for this COMPONENT:\n\n### 1. CWE-1188: Initialization of a Resource with an Insecure Default (Score: 513.39)\n\nThe product initializes or sets a resource with a default that is intended to be changed by the administrator, but the default is not secure....\n\n### 2. CWE-1391: Use of Weak Credentials (Score: 411.39)\n\nThe product uses weak credentials (such as a default key or hard-coded password) that can be calculated, derived, reused, or guessed by an attacker....\n\n### 3. CWE-798: Use of Hard-coded Credentials (Score: 321.56)\n\nThe product contains hard-coded credentials, such as a password or cryptographic key....\n\n### 4. CWE-306: Missing Authentication for Critical Function (Score: 304.96)\n\nThe product does not perform any authentication for functionality that requires a provable user identity or consumes a significant amount of resources....\n\n### 5. CWE-305: Authentication Bypass by Primary Weakness (Score: 103.77)\n\nThe authentication algorithm is sound, but the implemented mechanism can be bypassed as the result of a separate weakness that is primary to the authentication error....\n\n\n    # Analysis Instructions\n    1. For each keyphrase, identify the most appropriate CWE(s) that represent the weakness.\n    2. Consider how the different keyphrases might relate to each other in the vulnerability chain.\n    3. Provide a final determination of primary CWE(s) and any secondary CWEs.\n    4. Format your response using the standard analysis template.\n\n    Please analyze how these different weaknesses interact and provide a comprehensive CWE classification.\n    "
  },
  "retrieval_time": 1.201693058013916
}