{
  "vulnerability_info": "VulnerabilityInfo(cve_id='CVE-2024-6739', description='The session cookie in MailGates and MailAudit from Openfind **does not have the HttpOnly flag enabled**, allowing remote attackers to potentially steal the session cookie via **XSS**.', key_phrases={'rootcause': '', 'weakness': ['XSS', 'does not have the HttpOnly flag enabled'], 'impact': 'steal the session cookie', 'vector': 'XSS', 'attacker': 'remote attackers', 'product': 'MailGates and MailAudit', 'version': '', 'component': 'session cookie'}, reference_content='```json\\n{\\n  \"related\": true,\\n  \"summary\": \"Openfind has released a security advisory (OF-ISAC-24-007) detailing multiple vulnerabilities and fixes across their MailGates, MailAudit, and Mail2000 product lines.\",\\n  \"details\": [\\n    {\\n      \"product\": \"MailGates V6.0, MailAudit V6.0\",\\n      \"vulnerability\": \"Cookie security improvement\",\\n      \"root_cause\": \"Insecure cookie handling\",\\n      \"weaknesses\": [\\n        \"Cookies were accessible by client-side scripts (e.g., JavaScript)\"\\n      ],\\n      \"impact\": \"Potential for unauthorized access to cookie information, leading to account hijacking and data theft\",\\n      \"attack_vectors\": [\\n        \"Client-side scripting attacks (e.g., Cross-Site Scripting - XSS)\"\\n      ],\\n       \"required_capabilities\": \"Attacker needs to inject malicious JavaScript or have user execute malicious JavaScript\"\\n    },\\n    {\\n      \"product\": \"MailGates V6.0, MailAudit V6.0\",\\n      \"vulnerability\": \"Unspecified security vulnerability\",\\n       \"root_cause\": \"Unknown\",\\n      \"weaknesses\": [\\n       \"Unspecified security vulnerability\"\\n      ],\\n     \"impact\":\"Potential unspecified security impact\",\\n     \"attack_vectors\":\"Unknown\",\\n     \"required_capabilities\":\"Unknown\"\\n    },\\n    {\\n      \"product\": \"Mail2000 V7.0, Mail2000 V8.0\",\\n      \"vulnerability\": \"Stack overflow\",\\n      \"root_cause\": \"Specific operations during IMAP4 service authorization\",\\n      \"weaknesses\": [\\n        \"Stack overflow vulnerability triggered when using IMAP4 service under specific conditions\"\\n      ],\\n      \"impact\": \"Potential for denial of service or arbitrary code execution\",\\n      \"attack_vectors\": [\\n        \"Exploitation through IMAP4 service\"\\n      ],\\n       \"required_capabilities\":\"Attacker needs to be able to send malicious IMAP commands\"\\n    },\\n    {\\n      \"product\": \"Mail2000 V7.0, Mail2000 V8.0\",\\n      \"vulnerability\": \"Cross-site scripting (XSS)\",\\n       \"root_cause\": \"Web application vulnerability\",\\n      \"weaknesses\": [\\n        \"XSS vulnerability allows injection of malicious code into web pages\"\\n      ],\\n      \"impact\": \"Cookie theft, account hijacking, data theft\",\\n     \"attack_vectors\": [\\n        \"Injection of malicious code into web application\"\\n      ],\\n       \"required_capabilities\":\"Attacker needs to find a way to inject malicious code, likely through a web input\"\\n    },\\n     {\\n      \"product\": \"Mail2000 V7.0, Mail2000 V8.0\",\\n      \"vulnerability\": \"HttpOnly Cookie issue\",\\n       \"root_cause\": \"Client-side script issues related to HttpOnly cookie flag\",\\n      \"weaknesses\": [\\n        \"HttpOnly flag implementation caused client-side scripting issues\"\\n      ],\\n       \"impact\": \"Client-side script functionality may break\",\\n      \"attack_vectors\": [\\n        \"None\"\\n      ],\\n      \"required_capabilities\": \"None\"\\n    }\\n  ],\\n  \"remediation\": \"Apply security patches provided by Openfind. Specific patch versions are listed in the advisory.\",\\n   \"cve\": \"CVE-2024-6739\"\\n}\\n```', similar_info={'cwe_distribution': {}, 'cwe_consensus': '', 'similarity_stats': {'thresholds': [], 'total_samples_by_threshold': {}, 'top_cwes_by_threshold': {}}}, similarity_summary=SimilarityInsight(consensus_cwe='', top_cwes=[], confidence_levels={}, total_samples=0), analysis='', analysis_with_relationships='', criticism='', resolution='', relevant_cwes=[{'metadata': {'doc_id': '1004', 'name': \"Sensitive Cookie Without 'HttpOnly' Flag\", 'source': 'sparse', 'original_content': 'The product uses a cookie to store sensitive information, but the cookie is not marked with the HttpOnly flag.', 'keyphrase_sources': [{'id': 'weakness:XSS', 'keyphrase': 'XSS', 'type': 'weakness'}, {'id': 'weakness:does not have the HttpOnly flag enabled', 'keyphrase': 'does not have the HttpOnly flag enabled', 'type': 'weakness'}, {'id': 'impact:steal the session cookie', 'keyphrase': 'steal the session cookie', 'type': 'impact'}, {'id': 'vector:XSS', 'keyphrase': 'XSS', 'type': 'vector'}, {'id': 'attacker:remote attackers', 'keyphrase': 'remote attackers', 'type': 'attacker'}, {'id': 'product:MailGates and MailAudit', 'keyphrase': 'MailGates and MailAudit', 'type': 'product'}, {'id': 'component:session cookie', 'keyphrase': 'session cookie', 'type': 'component'}]}, 'similarity': np.float64(266.6386523120208)}, {'metadata': {'doc_id': '610', 'name': 'Externally Controlled Reference to a Resource in Another Sphere', 'source': 'sparse', 'original_content': 'The product uses an externally controlled name or reference that resolves to a resource that is outside of the intended control sphere.', 'keyphrase_sources': [{'id': 'weakness:does not have the HttpOnly flag enabled', 'keyphrase': 'does not have the HttpOnly flag enabled', 'type': 'weakness'}]}, 'similarity': np.float64(224.4693939326342)}, {'metadata': {'doc_id': '614', 'name': \"Sensitive Cookie in HTTPS Session Without 'Secure' Attribute\", 'source': 'sparse', 'original_content': 'The Secure attribute for sensitive cookies in HTTPS sessions is not set, which could cause the user agent to send those cookies in plaintext over an HTTP session.', 'keyphrase_sources': [{'id': 'weakness:XSS', 'keyphrase': 'XSS', 'type': 'weakness'}, {'id': 'weakness:does not have the HttpOnly flag enabled', 'keyphrase': 'does not have the HttpOnly flag enabled', 'type': 'weakness'}, {'id': 'impact:steal the session cookie', 'keyphrase': 'steal the session cookie', 'type': 'impact'}, {'id': 'vector:XSS', 'keyphrase': 'XSS', 'type': 'vector'}, {'id': 'attacker:remote attackers', 'keyphrase': 'remote attackers', 'type': 'attacker'}, {'id': 'product:MailGates and MailAudit', 'keyphrase': 'MailGates and MailAudit', 'type': 'product'}, {'id': 'component:session cookie', 'keyphrase': 'session cookie', 'type': 'component'}]}, 'similarity': np.float64(185.09864979291902)}, {'metadata': {'doc_id': '352', 'name': 'Cross-Site Request Forgery (CSRF)', 'source': 'sparse', 'original_content': 'The web application does not, or can not, sufficiently verify whether a well-formed, valid, consistent request was intentionally provided by the user who submitted the request.', 'keyphrase_sources': [{'id': 'weakness:XSS', 'keyphrase': 'XSS', 'type': 'weakness'}, {'id': 'weakness:does not have the HttpOnly flag enabled', 'keyphrase': 'does not have the HttpOnly flag enabled', 'type': 'weakness'}, {'id': 'impact:steal the session cookie', 'keyphrase': 'steal the session cookie', 'type': 'impact'}, {'id': 'vector:XSS', 'keyphrase': 'XSS', 'type': 'vector'}, {'id': 'attacker:remote attackers', 'keyphrase': 'remote attackers', 'type': 'attacker'}, {'id': 'product:MailGates and MailAudit', 'keyphrase': 'MailGates and MailAudit', 'type': 'product'}]}, 'similarity': np.float64(179.26463578397568)}, {'metadata': {'doc_id': '79', 'name': \"Improper Neutralization of Input During Web Page Generation ('Cross-site Scripting')\", 'source': 'sparse', 'original_content': 'The product does not neutralize or incorrectly neutralizes user-controllable input before it is placed in output that is used as a web page that is served to other users.', 'keyphrase_sources': [{'id': 'weakness:XSS', 'keyphrase': 'XSS', 'type': 'weakness'}, {'id': 'weakness:does not have the HttpOnly flag enabled', 'keyphrase': 'does not have the HttpOnly flag enabled', 'type': 'weakness'}, {'id': 'vector:XSS', 'keyphrase': 'XSS', 'type': 'vector'}]}, 'similarity': np.float64(177.01328094904747)}, {'metadata': {'doc_id': '312', 'name': 'Cleartext Storage of Sensitive Information', 'source': 'sparse', 'original_content': 'The product stores sensitive information in cleartext within a resource that might be accessible to another control sphere.', 'keyphrase_sources': [{'id': 'weakness:XSS', 'keyphrase': 'XSS', 'type': 'weakness'}, {'id': 'impact:steal the session cookie', 'keyphrase': 'steal the session cookie', 'type': 'impact'}, {'id': 'vector:XSS', 'keyphrase': 'XSS', 'type': 'vector'}, {'id': 'attacker:remote attackers', 'keyphrase': 'remote attackers', 'type': 'attacker'}, {'id': 'product:MailGates and MailAudit', 'keyphrase': 'MailGates and MailAudit', 'type': 'product'}, {'id': 'component:session cookie', 'keyphrase': 'session cookie', 'type': 'component'}]}, 'similarity': np.float64(161.87707136262372)}, {'metadata': {'doc_id': '784', 'name': 'Reliance on Cookies without Validation and Integrity Checking in a Security Decision', 'source': 'sparse', 'original_content': 'The product uses a protection mechanism that relies on the existence or values of a cookie, but it does not properly ensure that the cookie is valid for the associated user.', 'keyphrase_sources': [{'id': 'impact:steal the session cookie', 'keyphrase': 'steal the session cookie', 'type': 'impact'}, {'id': 'attacker:remote attackers', 'keyphrase': 'remote attackers', 'type': 'attacker'}, {'id': 'product:MailGates and MailAudit', 'keyphrase': 'MailGates and MailAudit', 'type': 'product'}, {'id': 'component:session cookie', 'keyphrase': 'session cookie', 'type': 'component'}]}, 'similarity': np.float64(77.85658106102574)}, {'metadata': {'doc_id': '1390', 'name': 'Weak Authentication', 'source': 'sparse', 'original_content': 'The product uses an authentication mechanism to restrict access to specific users or identities, but the mechanism does not sufficiently prove that the claimed identity is correct.', 'keyphrase_sources': [{'id': 'component:session cookie', 'keyphrase': 'session cookie', 'type': 'component'}]}, 'similarity': np.float64(64.6103223948501)}], identified_cwes={'analyzer': [], 'critic_additional': []})",
  "retrieval_results": {
    "has_multiple_keyphrases": true,
    "keyphrase_cwe_sets": {
      "weakness:XSS": {
        "keyphrase": "XSS",
        "type": "weakness",
        "cwes": [
          {
            "metadata": {
              "doc_id": "1004",
              "name": "Sensitive Cookie Without 'HttpOnly' Flag",
              "source": "sparse",
              "original_content": "The product uses a cookie to store sensitive information, but the cookie is not marked with the HttpOnly flag.",
              "keyphrase_sources": [
                {
                  "id": "weakness:XSS",
                  "keyphrase": "XSS",
                  "type": "weakness"
                },
                {
                  "id": "weakness:does not have the HttpOnly flag enabled",
                  "keyphrase": "does not have the HttpOnly flag enabled",
                  "type": "weakness"
                },
                {
                  "id": "impact:steal the session cookie",
                  "keyphrase": "steal the session cookie",
                  "type": "impact"
                },
                {
                  "id": "vector:XSS",
                  "keyphrase": "XSS",
                  "type": "vector"
                },
                {
                  "id": "attacker:remote attackers",
                  "keyphrase": "remote attackers",
                  "type": "attacker"
                },
                {
                  "id": "product:MailGates and MailAudit",
                  "keyphrase": "MailGates and MailAudit",
                  "type": "product"
                },
                {
                  "id": "component:session cookie",
                  "keyphrase": "session cookie",
                  "type": "component"
                }
              ]
            },
            "similarity": 266.6386523120208
          },
          {
            "metadata": {
              "doc_id": "614",
              "name": "Sensitive Cookie in HTTPS Session Without 'Secure' Attribute",
              "source": "sparse",
              "original_content": "The Secure attribute for sensitive cookies in HTTPS sessions is not set, which could cause the user agent to send those cookies in plaintext over an HTTP session.",
              "keyphrase_sources": [
                {
                  "id": "weakness:XSS",
                  "keyphrase": "XSS",
                  "type": "weakness"
                },
                {
                  "id": "weakness:does not have the HttpOnly flag enabled",
                  "keyphrase": "does not have the HttpOnly flag enabled",
                  "type": "weakness"
                },
                {
                  "id": "impact:steal the session cookie",
                  "keyphrase": "steal the session cookie",
                  "type": "impact"
                },
                {
                  "id": "vector:XSS",
                  "keyphrase": "XSS",
                  "type": "vector"
                },
                {
                  "id": "attacker:remote attackers",
                  "keyphrase": "remote attackers",
                  "type": "attacker"
                },
                {
                  "id": "product:MailGates and MailAudit",
                  "keyphrase": "MailGates and MailAudit",
                  "type": "product"
                },
                {
                  "id": "component:session cookie",
                  "keyphrase": "session cookie",
                  "type": "component"
                }
              ]
            },
            "similarity": 185.09864979291902
          },
          {
            "metadata": {
              "doc_id": "352",
              "name": "Cross-Site Request Forgery (CSRF)",
              "source": "sparse",
              "original_content": "The web application does not, or can not, sufficiently verify whether a well-formed, valid, consistent request was intentionally provided by the user who submitted the request.",
              "keyphrase_sources": [
                {
                  "id": "weakness:XSS",
                  "keyphrase": "XSS",
                  "type": "weakness"
                },
                {
                  "id": "weakness:does not have the HttpOnly flag enabled",
                  "keyphrase": "does not have the HttpOnly flag enabled",
                  "type": "weakness"
                },
                {
                  "id": "impact:steal the session cookie",
                  "keyphrase": "steal the session cookie",
                  "type": "impact"
                },
                {
                  "id": "vector:XSS",
                  "keyphrase": "XSS",
                  "type": "vector"
                },
                {
                  "id": "attacker:remote attackers",
                  "keyphrase": "remote attackers",
                  "type": "attacker"
                },
                {
                  "id": "product:MailGates and MailAudit",
                  "keyphrase": "MailGates and MailAudit",
                  "type": "product"
                }
              ]
            },
            "similarity": 179.26463578397568
          },
          {
            "metadata": {
              "doc_id": "79",
              "name": "Improper Neutralization of Input During Web Page Generation ('Cross-site Scripting')",
              "source": "sparse",
              "original_content": "The product does not neutralize or incorrectly neutralizes user-controllable input before it is placed in output that is used as a web page that is served to other users.",
              "keyphrase_sources": [
                {
                  "id": "weakness:XSS",
                  "keyphrase": "XSS",
                  "type": "weakness"
                },
                {
                  "id": "weakness:does not have the HttpOnly flag enabled",
                  "keyphrase": "does not have the HttpOnly flag enabled",
                  "type": "weakness"
                },
                {
                  "id": "vector:XSS",
                  "keyphrase": "XSS",
                  "type": "vector"
                }
              ]
            },
            "similarity": 177.01328094904747
          },
          {
            "metadata": {
              "doc_id": "312",
              "name": "Cleartext Storage of Sensitive Information",
              "source": "sparse",
              "original_content": "The product stores sensitive information in cleartext within a resource that might be accessible to another control sphere.",
              "keyphrase_sources": [
                {
                  "id": "weakness:XSS",
                  "keyphrase": "XSS",
                  "type": "weakness"
                },
                {
                  "id": "impact:steal the session cookie",
                  "keyphrase": "steal the session cookie",
                  "type": "impact"
                },
                {
                  "id": "vector:XSS",
                  "keyphrase": "XSS",
                  "type": "vector"
                },
                {
                  "id": "attacker:remote attackers",
                  "keyphrase": "remote attackers",
                  "type": "attacker"
                },
                {
                  "id": "product:MailGates and MailAudit",
                  "keyphrase": "MailGates and MailAudit",
                  "type": "product"
                },
                {
                  "id": "component:session cookie",
                  "keyphrase": "session cookie",
                  "type": "component"
                }
              ]
            },
            "similarity": 161.87707136262372
          }
        ]
      },
      "weakness:does not have the HttpOnly flag enabled": {
        "keyphrase": "does not have the HttpOnly flag enabled",
        "type": "weakness",
        "cwes": [
          {
            "metadata": {
              "doc_id": "1004",
              "name": "Sensitive Cookie Without 'HttpOnly' Flag",
              "source": "sparse",
              "original_content": "The product uses a cookie to store sensitive information, but the cookie is not marked with the HttpOnly flag."
            },
            "similarity": 406.14394144583355
          },
          {
            "metadata": {
              "doc_id": "614",
              "name": "Sensitive Cookie in HTTPS Session Without 'Secure' Attribute",
              "source": "sparse",
              "original_content": "The Secure attribute for sensitive cookies in HTTPS sessions is not set, which could cause the user agent to send those cookies in plaintext over an HTTP session."
            },
            "similarity": 304.6411922973966
          },
          {
            "metadata": {
              "doc_id": "352",
              "name": "Cross-Site Request Forgery (CSRF)",
              "source": "sparse",
              "original_content": "The web application does not, or can not, sufficiently verify whether a well-formed, valid, consistent request was intentionally provided by the user who submitted the request."
            },
            "similarity": 237.38378655346398
          },
          {
            "metadata": {
              "doc_id": "79",
              "name": "Improper Neutralization of Input During Web Page Generation ('Cross-site Scripting')",
              "source": "sparse",
              "original_content": "The product does not neutralize or incorrectly neutralizes user-controllable input before it is placed in output that is used as a web page that is served to other users."
            },
            "similarity": 227.74930452383026
          },
          {
            "metadata": {
              "doc_id": "610",
              "name": "Externally Controlled Reference to a Resource in Another Sphere",
              "source": "sparse",
              "original_content": "The product uses an externally controlled name or reference that resolves to a resource that is outside of the intended control sphere.",
              "keyphrase_sources": [
                {
                  "id": "weakness:does not have the HttpOnly flag enabled",
                  "keyphrase": "does not have the HttpOnly flag enabled",
                  "type": "weakness"
                }
              ]
            },
            "similarity": 224.4693939326342
          }
        ]
      },
      "impact:steal the session cookie": {
        "keyphrase": "steal the session cookie",
        "type": "impact",
        "cwes": [
          {
            "metadata": {
              "doc_id": "1004",
              "name": "Sensitive Cookie Without 'HttpOnly' Flag",
              "source": "sparse",
              "original_content": "The product uses a cookie to store sensitive information, but the cookie is not marked with the HttpOnly flag."
            },
            "similarity": 125.44119850437433
          },
          {
            "metadata": {
              "doc_id": "614",
              "name": "Sensitive Cookie in HTTPS Session Without 'Secure' Attribute",
              "source": "sparse",
              "original_content": "The Secure attribute for sensitive cookies in HTTPS sessions is not set, which could cause the user agent to send those cookies in plaintext over an HTTP session."
            },
            "similarity": 95.32741993410237
          },
          {
            "metadata": {
              "doc_id": "784",
              "name": "Reliance on Cookies without Validation and Integrity Checking in a Security Decision",
              "source": "sparse",
              "original_content": "The product uses a protection mechanism that relies on the existence or values of a cookie, but it does not properly ensure that the cookie is valid for the associated user.",
              "keyphrase_sources": [
                {
                  "id": "impact:steal the session cookie",
                  "keyphrase": "steal the session cookie",
                  "type": "impact"
                },
                {
                  "id": "attacker:remote attackers",
                  "keyphrase": "remote attackers",
                  "type": "attacker"
                },
                {
                  "id": "product:MailGates and MailAudit",
                  "keyphrase": "MailGates and MailAudit",
                  "type": "product"
                },
                {
                  "id": "component:session cookie",
                  "keyphrase": "session cookie",
                  "type": "component"
                }
              ]
            },
            "similarity": 77.85658106102574
          },
          {
            "metadata": {
              "doc_id": "312",
              "name": "Cleartext Storage of Sensitive Information",
              "source": "sparse",
              "original_content": "The product stores sensitive information in cleartext within a resource that might be accessible to another control sphere."
            },
            "similarity": 77.82184988426236
          },
          {
            "metadata": {
              "doc_id": "352",
              "name": "Cross-Site Request Forgery (CSRF)",
              "source": "sparse",
              "original_content": "The web application does not, or can not, sufficiently verify whether a well-formed, valid, consistent request was intentionally provided by the user who submitted the request."
            },
            "similarity": 74.06500111511319
          }
        ]
      },
      "vector:XSS": {
        "keyphrase": "XSS",
        "type": "vector",
        "cwes": [
          {
            "metadata": {
              "doc_id": "1004",
              "name": "Sensitive Cookie Without 'HttpOnly' Flag",
              "source": "sparse",
              "original_content": "The product uses a cookie to store sensitive information, but the cookie is not marked with the HttpOnly flag."
            },
            "similarity": 95.228090111436
          },
          {
            "metadata": {
              "doc_id": "614",
              "name": "Sensitive Cookie in HTTPS Session Without 'Secure' Attribute",
              "source": "sparse",
              "original_content": "The Secure attribute for sensitive cookies in HTTPS sessions is not set, which could cause the user agent to send those cookies in plaintext over an HTTP session."
            },
            "similarity": 66.10666064032823
          },
          {
            "metadata": {
              "doc_id": "352",
              "name": "Cross-Site Request Forgery (CSRF)",
              "source": "sparse",
              "original_content": "The web application does not, or can not, sufficiently verify whether a well-formed, valid, consistent request was intentionally provided by the user who submitted the request."
            },
            "similarity": 64.02308420856275
          },
          {
            "metadata": {
              "doc_id": "79",
              "name": "Improper Neutralization of Input During Web Page Generation ('Cross-site Scripting')",
              "source": "sparse",
              "original_content": "The product does not neutralize or incorrectly neutralizes user-controllable input before it is placed in output that is used as a web page that is served to other users."
            },
            "similarity": 63.2190289103741
          },
          {
            "metadata": {
              "doc_id": "312",
              "name": "Cleartext Storage of Sensitive Information",
              "source": "sparse",
              "original_content": "The product stores sensitive information in cleartext within a resource that might be accessible to another control sphere."
            },
            "similarity": 57.81323977236562
          }
        ]
      },
      "attacker:remote attackers": {
        "keyphrase": "remote attackers",
        "type": "attacker",
        "cwes": [
          {
            "metadata": {
              "doc_id": "1004",
              "name": "Sensitive Cookie Without 'HttpOnly' Flag",
              "source": "sparse",
              "original_content": "The product uses a cookie to store sensitive information, but the cookie is not marked with the HttpOnly flag."
            },
            "similarity": 90.00202014768756
          },
          {
            "metadata": {
              "doc_id": "614",
              "name": "Sensitive Cookie in HTTPS Session Without 'Secure' Attribute",
              "source": "sparse",
              "original_content": "The Secure attribute for sensitive cookies in HTTPS sessions is not set, which could cause the user agent to send those cookies in plaintext over an HTTP session."
            },
            "similarity": 70.04393542867892
          },
          {
            "metadata": {
              "doc_id": "352",
              "name": "Cross-Site Request Forgery (CSRF)",
              "source": "sparse",
              "original_content": "The web application does not, or can not, sufficiently verify whether a well-formed, valid, consistent request was intentionally provided by the user who submitted the request."
            },
            "similarity": 58.234088911490836
          },
          {
            "metadata": {
              "doc_id": "784",
              "name": "Reliance on Cookies without Validation and Integrity Checking in a Security Decision",
              "source": "sparse",
              "original_content": "The product uses a protection mechanism that relies on the existence or values of a cookie, but it does not properly ensure that the cookie is valid for the associated user."
            },
            "similarity": 56.684476758433014
          },
          {
            "metadata": {
              "doc_id": "312",
              "name": "Cleartext Storage of Sensitive Information",
              "source": "sparse",
              "original_content": "The product stores sensitive information in cleartext within a resource that might be accessible to another control sphere."
            },
            "similarity": 56.53706799047664
          }
        ]
      },
      "product:MailGates and MailAudit": {
        "keyphrase": "MailGates and MailAudit",
        "type": "product",
        "cwes": [
          {
            "metadata": {
              "doc_id": "1004",
              "name": "Sensitive Cookie Without 'HttpOnly' Flag",
              "source": "sparse",
              "original_content": "The product uses a cookie to store sensitive information, but the cookie is not marked with the HttpOnly flag."
            },
            "similarity": 93.01429348750646
          },
          {
            "metadata": {
              "doc_id": "614",
              "name": "Sensitive Cookie in HTTPS Session Without 'Secure' Attribute",
              "source": "sparse",
              "original_content": "The Secure attribute for sensitive cookies in HTTPS sessions is not set, which could cause the user agent to send those cookies in plaintext over an HTTP session."
            },
            "similarity": 72.8002610980913
          },
          {
            "metadata": {
              "doc_id": "352",
              "name": "Cross-Site Request Forgery (CSRF)",
              "source": "sparse",
              "original_content": "The web application does not, or can not, sufficiently verify whether a well-formed, valid, consistent request was intentionally provided by the user who submitted the request."
            },
            "similarity": 61.65056260560328
          },
          {
            "metadata": {
              "doc_id": "312",
              "name": "Cleartext Storage of Sensitive Information",
              "source": "sparse",
              "original_content": "The product stores sensitive information in cleartext within a resource that might be accessible to another control sphere."
            },
            "similarity": 59.9735209670326
          },
          {
            "metadata": {
              "doc_id": "784",
              "name": "Reliance on Cookies without Validation and Integrity Checking in a Security Decision",
              "source": "sparse",
              "original_content": "The product uses a protection mechanism that relies on the existence or values of a cookie, but it does not properly ensure that the cookie is valid for the associated user."
            },
            "similarity": 59.74256367473476
          }
        ]
      },
      "component:session cookie": {
        "keyphrase": "session cookie",
        "type": "component",
        "cwes": [
          {
            "metadata": {
              "doc_id": "1004",
              "name": "Sensitive Cookie Without 'HttpOnly' Flag",
              "source": "sparse",
              "original_content": "The product uses a cookie to store sensitive information, but the cookie is not marked with the HttpOnly flag."
            },
            "similarity": 108.13139995632697
          },
          {
            "metadata": {
              "doc_id": "614",
              "name": "Sensitive Cookie in HTTPS Session Without 'Secure' Attribute",
              "source": "sparse",
              "original_content": "The Secure attribute for sensitive cookies in HTTPS sessions is not set, which could cause the user agent to send those cookies in plaintext over an HTTP session."
            },
            "similarity": 88.08398839545715
          },
          {
            "metadata": {
              "doc_id": "312",
              "name": "Cleartext Storage of Sensitive Information",
              "source": "sparse",
              "original_content": "The product stores sensitive information in cleartext within a resource that might be accessible to another control sphere."
            },
            "similarity": 70.70938037140384
          },
          {
            "metadata": {
              "doc_id": "784",
              "name": "Reliance on Cookies without Validation and Integrity Checking in a Security Decision",
              "source": "sparse",
              "original_content": "The product uses a protection mechanism that relies on the existence or values of a cookie, but it does not properly ensure that the cookie is valid for the associated user."
            },
            "similarity": 70.67170274462478
          },
          {
            "metadata": {
              "doc_id": "1390",
              "name": "Weak Authentication",
              "source": "sparse",
              "original_content": "The product uses an authentication mechanism to restrict access to specific users or identities, but the mechanism does not sufficiently prove that the claimed identity is correct.",
              "keyphrase_sources": [
                {
                  "id": "component:session cookie",
                  "keyphrase": "session cookie",
                  "type": "component"
                }
              ]
            },
            "similarity": 64.6103223948501
          }
        ]
      }
    },
    "keyphrase_mapping": {
      "1004": [
        {
          "id": "weakness:XSS",
          "keyphrase": "XSS",
          "type": "weakness"
        },
        {
          "id": "weakness:does not have the HttpOnly flag enabled",
          "keyphrase": "does not have the HttpOnly flag enabled",
          "type": "weakness"
        },
        {
          "id": "impact:steal the session cookie",
          "keyphrase": "steal the session cookie",
          "type": "impact"
        },
        {
          "id": "vector:XSS",
          "keyphrase": "XSS",
          "type": "vector"
        },
        {
          "id": "attacker:remote attackers",
          "keyphrase": "remote attackers",
          "type": "attacker"
        },
        {
          "id": "product:MailGates and MailAudit",
          "keyphrase": "MailGates and MailAudit",
          "type": "product"
        },
        {
          "id": "component:session cookie",
          "keyphrase": "session cookie",
          "type": "component"
        }
      ],
      "614": [
        {
          "id": "weakness:XSS",
          "keyphrase": "XSS",
          "type": "weakness"
        },
        {
          "id": "weakness:does not have the HttpOnly flag enabled",
          "keyphrase": "does not have the HttpOnly flag enabled",
          "type": "weakness"
        },
        {
          "id": "impact:steal the session cookie",
          "keyphrase": "steal the session cookie",
          "type": "impact"
        },
        {
          "id": "vector:XSS",
          "keyphrase": "XSS",
          "type": "vector"
        },
        {
          "id": "attacker:remote attackers",
          "keyphrase": "remote attackers",
          "type": "attacker"
        },
        {
          "id": "product:MailGates and MailAudit",
          "keyphrase": "MailGates and MailAudit",
          "type": "product"
        },
        {
          "id": "component:session cookie",
          "keyphrase": "session cookie",
          "type": "component"
        }
      ],
      "352": [
        {
          "id": "weakness:XSS",
          "keyphrase": "XSS",
          "type": "weakness"
        },
        {
          "id": "weakness:does not have the HttpOnly flag enabled",
          "keyphrase": "does not have the HttpOnly flag enabled",
          "type": "weakness"
        },
        {
          "id": "impact:steal the session cookie",
          "keyphrase": "steal the session cookie",
          "type": "impact"
        },
        {
          "id": "vector:XSS",
          "keyphrase": "XSS",
          "type": "vector"
        },
        {
          "id": "attacker:remote attackers",
          "keyphrase": "remote attackers",
          "type": "attacker"
        },
        {
          "id": "product:MailGates and MailAudit",
          "keyphrase": "MailGates and MailAudit",
          "type": "product"
        }
      ],
      "79": [
        {
          "id": "weakness:XSS",
          "keyphrase": "XSS",
          "type": "weakness"
        },
        {
          "id": "weakness:does not have the HttpOnly flag enabled",
          "keyphrase": "does not have the HttpOnly flag enabled",
          "type": "weakness"
        },
        {
          "id": "vector:XSS",
          "keyphrase": "XSS",
          "type": "vector"
        }
      ],
      "312": [
        {
          "id": "weakness:XSS",
          "keyphrase": "XSS",
          "type": "weakness"
        },
        {
          "id": "impact:steal the session cookie",
          "keyphrase": "steal the session cookie",
          "type": "impact"
        },
        {
          "id": "vector:XSS",
          "keyphrase": "XSS",
          "type": "vector"
        },
        {
          "id": "attacker:remote attackers",
          "keyphrase": "remote attackers",
          "type": "attacker"
        },
        {
          "id": "product:MailGates and MailAudit",
          "keyphrase": "MailGates and MailAudit",
          "type": "product"
        },
        {
          "id": "component:session cookie",
          "keyphrase": "session cookie",
          "type": "component"
        }
      ],
      "610": [
        {
          "id": "weakness:does not have the HttpOnly flag enabled",
          "keyphrase": "does not have the HttpOnly flag enabled",
          "type": "weakness"
        }
      ],
      "784": [
        {
          "id": "impact:steal the session cookie",
          "keyphrase": "steal the session cookie",
          "type": "impact"
        },
        {
          "id": "attacker:remote attackers",
          "keyphrase": "remote attackers",
          "type": "attacker"
        },
        {
          "id": "product:MailGates and MailAudit",
          "keyphrase": "MailGates and MailAudit",
          "type": "product"
        },
        {
          "id": "component:session cookie",
          "keyphrase": "session cookie",
          "type": "component"
        }
      ],
      "1390": [
        {
          "id": "component:session cookie",
          "keyphrase": "session cookie",
          "type": "component"
        }
      ]
    },
    "relevant_cwes": [
      {
        "metadata": {
          "doc_id": "1004",
          "name": "Sensitive Cookie Without 'HttpOnly' Flag",
          "source": "sparse",
          "original_content": "The product uses a cookie to store sensitive information, but the cookie is not marked with the HttpOnly flag.",
          "keyphrase_sources": [
            {
              "id": "weakness:XSS",
              "keyphrase": "XSS",
              "type": "weakness"
            },
            {
              "id": "weakness:does not have the HttpOnly flag enabled",
              "keyphrase": "does not have the HttpOnly flag enabled",
              "type": "weakness"
            },
            {
              "id": "impact:steal the session cookie",
              "keyphrase": "steal the session cookie",
              "type": "impact"
            },
            {
              "id": "vector:XSS",
              "keyphrase": "XSS",
              "type": "vector"
            },
            {
              "id": "attacker:remote attackers",
              "keyphrase": "remote attackers",
              "type": "attacker"
            },
            {
              "id": "product:MailGates and MailAudit",
              "keyphrase": "MailGates and MailAudit",
              "type": "product"
            },
            {
              "id": "component:session cookie",
              "keyphrase": "session cookie",
              "type": "component"
            }
          ]
        },
        "similarity": 266.6386523120208
      },
      {
        "metadata": {
          "doc_id": "610",
          "name": "Externally Controlled Reference to a Resource in Another Sphere",
          "source": "sparse",
          "original_content": "The product uses an externally controlled name or reference that resolves to a resource that is outside of the intended control sphere.",
          "keyphrase_sources": [
            {
              "id": "weakness:does not have the HttpOnly flag enabled",
              "keyphrase": "does not have the HttpOnly flag enabled",
              "type": "weakness"
            }
          ]
        },
        "similarity": 224.4693939326342
      },
      {
        "metadata": {
          "doc_id": "614",
          "name": "Sensitive Cookie in HTTPS Session Without 'Secure' Attribute",
          "source": "sparse",
          "original_content": "The Secure attribute for sensitive cookies in HTTPS sessions is not set, which could cause the user agent to send those cookies in plaintext over an HTTP session.",
          "keyphrase_sources": [
            {
              "id": "weakness:XSS",
              "keyphrase": "XSS",
              "type": "weakness"
            },
            {
              "id": "weakness:does not have the HttpOnly flag enabled",
              "keyphrase": "does not have the HttpOnly flag enabled",
              "type": "weakness"
            },
            {
              "id": "impact:steal the session cookie",
              "keyphrase": "steal the session cookie",
              "type": "impact"
            },
            {
              "id": "vector:XSS",
              "keyphrase": "XSS",
              "type": "vector"
            },
            {
              "id": "attacker:remote attackers",
              "keyphrase": "remote attackers",
              "type": "attacker"
            },
            {
              "id": "product:MailGates and MailAudit",
              "keyphrase": "MailGates and MailAudit",
              "type": "product"
            },
            {
              "id": "component:session cookie",
              "keyphrase": "session cookie",
              "type": "component"
            }
          ]
        },
        "similarity": 185.09864979291902
      },
      {
        "metadata": {
          "doc_id": "352",
          "name": "Cross-Site Request Forgery (CSRF)",
          "source": "sparse",
          "original_content": "The web application does not, or can not, sufficiently verify whether a well-formed, valid, consistent request was intentionally provided by the user who submitted the request.",
          "keyphrase_sources": [
            {
              "id": "weakness:XSS",
              "keyphrase": "XSS",
              "type": "weakness"
            },
            {
              "id": "weakness:does not have the HttpOnly flag enabled",
              "keyphrase": "does not have the HttpOnly flag enabled",
              "type": "weakness"
            },
            {
              "id": "impact:steal the session cookie",
              "keyphrase": "steal the session cookie",
              "type": "impact"
            },
            {
              "id": "vector:XSS",
              "keyphrase": "XSS",
              "type": "vector"
            },
            {
              "id": "attacker:remote attackers",
              "keyphrase": "remote attackers",
              "type": "attacker"
            },
            {
              "id": "product:MailGates and MailAudit",
              "keyphrase": "MailGates and MailAudit",
              "type": "product"
            }
          ]
        },
        "similarity": 179.26463578397568
      },
      {
        "metadata": {
          "doc_id": "79",
          "name": "Improper Neutralization of Input During Web Page Generation ('Cross-site Scripting')",
          "source": "sparse",
          "original_content": "The product does not neutralize or incorrectly neutralizes user-controllable input before it is placed in output that is used as a web page that is served to other users.",
          "keyphrase_sources": [
            {
              "id": "weakness:XSS",
              "keyphrase": "XSS",
              "type": "weakness"
            },
            {
              "id": "weakness:does not have the HttpOnly flag enabled",
              "keyphrase": "does not have the HttpOnly flag enabled",
              "type": "weakness"
            },
            {
              "id": "vector:XSS",
              "keyphrase": "XSS",
              "type": "vector"
            }
          ]
        },
        "similarity": 177.01328094904747
      },
      {
        "metadata": {
          "doc_id": "312",
          "name": "Cleartext Storage of Sensitive Information",
          "source": "sparse",
          "original_content": "The product stores sensitive information in cleartext within a resource that might be accessible to another control sphere.",
          "keyphrase_sources": [
            {
              "id": "weakness:XSS",
              "keyphrase": "XSS",
              "type": "weakness"
            },
            {
              "id": "impact:steal the session cookie",
              "keyphrase": "steal the session cookie",
              "type": "impact"
            },
            {
              "id": "vector:XSS",
              "keyphrase": "XSS",
              "type": "vector"
            },
            {
              "id": "attacker:remote attackers",
              "keyphrase": "remote attackers",
              "type": "attacker"
            },
            {
              "id": "product:MailGates and MailAudit",
              "keyphrase": "MailGates and MailAudit",
              "type": "product"
            },
            {
              "id": "component:session cookie",
              "keyphrase": "session cookie",
              "type": "component"
            }
          ]
        },
        "similarity": 161.87707136262372
      },
      {
        "metadata": {
          "doc_id": "784",
          "name": "Reliance on Cookies without Validation and Integrity Checking in a Security Decision",
          "source": "sparse",
          "original_content": "The product uses a protection mechanism that relies on the existence or values of a cookie, but it does not properly ensure that the cookie is valid for the associated user.",
          "keyphrase_sources": [
            {
              "id": "impact:steal the session cookie",
              "keyphrase": "steal the session cookie",
              "type": "impact"
            },
            {
              "id": "attacker:remote attackers",
              "keyphrase": "remote attackers",
              "type": "attacker"
            },
            {
              "id": "product:MailGates and MailAudit",
              "keyphrase": "MailGates and MailAudit",
              "type": "product"
            },
            {
              "id": "component:session cookie",
              "keyphrase": "session cookie",
              "type": "component"
            }
          ]
        },
        "similarity": 77.85658106102574
      },
      {
        "metadata": {
          "doc_id": "1390",
          "name": "Weak Authentication",
          "source": "sparse",
          "original_content": "The product uses an authentication mechanism to restrict access to specific users or identities, but the mechanism does not sufficiently prove that the claimed identity is correct.",
          "keyphrase_sources": [
            {
              "id": "component:session cookie",
              "keyphrase": "session cookie",
              "type": "component"
            }
          ]
        },
        "similarity": 64.6103223948501
      }
    ],
    "enhanced_query": "# Vulnerability Description\n\n    The session cookie in MailGates and MailAudit from Openfind **does not have the HttpOnly flag enabled**, allowing remote attackers to potentially steal the session cookie via **XSS**.\n\n    # Keyphrase-Specific CWE Analysis\n    This vulnerability contains multiple keyphrases that may map to different CWEs. \n    Please analyze each keyphrase separately and determine the most appropriate CWE(s) for each.\n\n    ## WEAKNESS: 'XSS'\n\nRelevant CWEs for this WEAKNESS:\n\n### 1. CWE-1004: Sensitive Cookie Without 'HttpOnly' Flag (Score: 266.64)\n\nThe product uses a cookie to store sensitive information, but the cookie is not marked with the HttpOnly flag....\n\n### 2. CWE-614: Sensitive Cookie in HTTPS Session Without 'Secure' Attribute (Score: 185.10)\n\nThe Secure attribute for sensitive cookies in HTTPS sessions is not set, which could cause the user agent to send those cookies in plaintext over an HTTP session....\n\n### 3. CWE-352: Cross-Site Request Forgery (CSRF) (Score: 179.26)\n\nThe web application does not, or can not, sufficiently verify whether a well-formed, valid, consistent request was intentionally provided by the user who submitted the request....\n\n### 4. CWE-79: Improper Neutralization of Input During Web Page Generation ('Cross-site Scripting') (Score: 177.01)\n\nThe product does not neutralize or incorrectly neutralizes user-controllable input before it is placed in output that is used as a web page that is served to other users....\n\n### 5. CWE-312: Cleartext Storage of Sensitive Information (Score: 161.88)\n\nThe product stores sensitive information in cleartext within a resource that might be accessible to another control sphere....\n\n## WEAKNESS: 'does not have the HttpOnly flag enabled'\n\nRelevant CWEs for this WEAKNESS:\n\n### 1. CWE-1004: Sensitive Cookie Without 'HttpOnly' Flag (Score: 266.64)\n\nThe product uses a cookie to store sensitive information, but the cookie is not marked with the HttpOnly flag....\n\n### 2. CWE-610: Externally Controlled Reference to a Resource in Another Sphere (Score: 224.47)\n\nThe product uses an externally controlled name or reference that resolves to a resource that is outside of the intended control sphere....\n\n### 3. CWE-614: Sensitive Cookie in HTTPS Session Without 'Secure' Attribute (Score: 185.10)\n\nThe Secure attribute for sensitive cookies in HTTPS sessions is not set, which could cause the user agent to send those cookies in plaintext over an HTTP session....\n\n### 4. CWE-352: Cross-Site Request Forgery (CSRF) (Score: 179.26)\n\nThe web application does not, or can not, sufficiently verify whether a well-formed, valid, consistent request was intentionally provided by the user who submitted the request....\n\n### 5. CWE-79: Improper Neutralization of Input During Web Page Generation ('Cross-site Scripting') (Score: 177.01)\n\nThe product does not neutralize or incorrectly neutralizes user-controllable input before it is placed in output that is used as a web page that is served to other users....\n\n## IMPACT: 'steal the session cookie'\n\nRelevant CWEs for this IMPACT:\n\n### 1. CWE-1004: Sensitive Cookie Without 'HttpOnly' Flag (Score: 266.64)\n\nThe product uses a cookie to store sensitive information, but the cookie is not marked with the HttpOnly flag....\n\n### 2. CWE-614: Sensitive Cookie in HTTPS Session Without 'Secure' Attribute (Score: 185.10)\n\nThe Secure attribute for sensitive cookies in HTTPS sessions is not set, which could cause the user agent to send those cookies in plaintext over an HTTP session....\n\n### 3. CWE-352: Cross-Site Request Forgery (CSRF) (Score: 179.26)\n\nThe web application does not, or can not, sufficiently verify whether a well-formed, valid, consistent request was intentionally provided by the user who submitted the request....\n\n### 4. CWE-312: Cleartext Storage of Sensitive Information (Score: 161.88)\n\nThe product stores sensitive information in cleartext within a resource that might be accessible to another control sphere....\n\n### 5. CWE-784: Reliance on Cookies without Validation and Integrity Checking in a Security Decision (Score: 77.86)\n\nThe product uses a protection mechanism that relies on the existence or values of a cookie, but it does not properly ensure that the cookie is valid for the associated user....\n\n## VECTOR: 'XSS'\n\nRelevant CWEs for this VECTOR:\n\n### 1. CWE-1004: Sensitive Cookie Without 'HttpOnly' Flag (Score: 266.64)\n\nThe product uses a cookie to store sensitive information, but the cookie is not marked with the HttpOnly flag....\n\n### 2. CWE-614: Sensitive Cookie in HTTPS Session Without 'Secure' Attribute (Score: 185.10)\n\nThe Secure attribute for sensitive cookies in HTTPS sessions is not set, which could cause the user agent to send those cookies in plaintext over an HTTP session....\n\n### 3. CWE-352: Cross-Site Request Forgery (CSRF) (Score: 179.26)\n\nThe web application does not, or can not, sufficiently verify whether a well-formed, valid, consistent request was intentionally provided by the user who submitted the request....\n\n### 4. CWE-79: Improper Neutralization of Input During Web Page Generation ('Cross-site Scripting') (Score: 177.01)\n\nThe product does not neutralize or incorrectly neutralizes user-controllable input before it is placed in output that is used as a web page that is served to other users....\n\n### 5. CWE-312: Cleartext Storage of Sensitive Information (Score: 161.88)\n\nThe product stores sensitive information in cleartext within a resource that might be accessible to another control sphere....\n\n## ATTACKER: 'remote attackers'\n\nRelevant CWEs for this ATTACKER:\n\n### 1. CWE-1004: Sensitive Cookie Without 'HttpOnly' Flag (Score: 266.64)\n\nThe product uses a cookie to store sensitive information, but the cookie is not marked with the HttpOnly flag....\n\n### 2. CWE-614: Sensitive Cookie in HTTPS Session Without 'Secure' Attribute (Score: 185.10)\n\nThe Secure attribute for sensitive cookies in HTTPS sessions is not set, which could cause the user agent to send those cookies in plaintext over an HTTP session....\n\n### 3. CWE-352: Cross-Site Request Forgery (CSRF) (Score: 179.26)\n\nThe web application does not, or can not, sufficiently verify whether a well-formed, valid, consistent request was intentionally provided by the user who submitted the request....\n\n### 4. CWE-312: Cleartext Storage of Sensitive Information (Score: 161.88)\n\nThe product stores sensitive information in cleartext within a resource that might be accessible to another control sphere....\n\n### 5. CWE-784: Reliance on Cookies without Validation and Integrity Checking in a Security Decision (Score: 77.86)\n\nThe product uses a protection mechanism that relies on the existence or values of a cookie, but it does not properly ensure that the cookie is valid for the associated user....\n\n## PRODUCT: 'MailGates and MailAudit'\n\nRelevant CWEs for this PRODUCT:\n\n### 1. CWE-1004: Sensitive Cookie Without 'HttpOnly' Flag (Score: 266.64)\n\nThe product uses a cookie to store sensitive information, but the cookie is not marked with the HttpOnly flag....\n\n### 2. CWE-614: Sensitive Cookie in HTTPS Session Without 'Secure' Attribute (Score: 185.10)\n\nThe Secure attribute for sensitive cookies in HTTPS sessions is not set, which could cause the user agent to send those cookies in plaintext over an HTTP session....\n\n### 3. CWE-352: Cross-Site Request Forgery (CSRF) (Score: 179.26)\n\nThe web application does not, or can not, sufficiently verify whether a well-formed, valid, consistent request was intentionally provided by the user who submitted the request....\n\n### 4. CWE-312: Cleartext Storage of Sensitive Information (Score: 161.88)\n\nThe product stores sensitive information in cleartext within a resource that might be accessible to another control sphere....\n\n### 5. CWE-784: Reliance on Cookies without Validation and Integrity Checking in a Security Decision (Score: 77.86)\n\nThe product uses a protection mechanism that relies on the existence or values of a cookie, but it does not properly ensure that the cookie is valid for the associated user....\n\n## COMPONENT: 'session cookie'\n\nRelevant CWEs for this COMPONENT:\n\n### 1. CWE-1004: Sensitive Cookie Without 'HttpOnly' Flag (Score: 266.64)\n\nThe product uses a cookie to store sensitive information, but the cookie is not marked with the HttpOnly flag....\n\n### 2. CWE-614: Sensitive Cookie in HTTPS Session Without 'Secure' Attribute (Score: 185.10)\n\nThe Secure attribute for sensitive cookies in HTTPS sessions is not set, which could cause the user agent to send those cookies in plaintext over an HTTP session....\n\n### 3. CWE-312: Cleartext Storage of Sensitive Information (Score: 161.88)\n\nThe product stores sensitive information in cleartext within a resource that might be accessible to another control sphere....\n\n### 4. CWE-784: Reliance on Cookies without Validation and Integrity Checking in a Security Decision (Score: 77.86)\n\nThe product uses a protection mechanism that relies on the existence or values of a cookie, but it does not properly ensure that the cookie is valid for the associated user....\n\n### 5. CWE-1390: Weak Authentication (Score: 64.61)\n\nThe product uses an authentication mechanism to restrict access to specific users or identities, but the mechanism does not sufficiently prove that the claimed identity is correct....\n\n\n    # Analysis Instructions\n    1. For each keyphrase, identify the most appropriate CWE(s) that represent the weakness.\n    2. Consider how the different keyphrases might relate to each other in the vulnerability chain.\n    3. Provide a final determination of primary CWE(s) and any secondary CWEs.\n    4. Format your response using the standard analysis template.\n\n    Please analyze how these different weaknesses interact and provide a comprehensive CWE classification.\n    "
  },
  "retrieval_time": 1.3687922954559326
}