{
  "vulnerability_info": "VulnerabilityInfo(cve_id='CVE-2024-38874', description='An issue was discovered in the events2 (aka Events 2) extension before 8.3.8 and 9.x before 9.0.6 for TYPO3. **Missing access checks in the management plugin** lead to an **insecure direct object reference** (IDOR) vulnerability with the potential to activate or delete various events for unauthenticated users.', key_phrases={'rootcause': ['Missing access checks in the management plugin', 'insecure direct object reference'], 'weakness': '', 'impact': 'activate or delete various events for unauthenticated users', 'vector': '', 'attacker': '', 'product': 'TYPO3', 'version': 'events2 (aka Events 2) extension before 8.3.8 and 9.x before 9.0.6', 'component': ''}, reference_content='```\\n{\\n  \"vulnerability_details\": [\\n    {\\n      \"cve_id\": \"CVE-2024-38874\",\\n      \"root_cause\": \"The extension \\\\\"Events 2\\\\\" (events2) has multiple vulnerabilities due to incorrect cache configuration, missing access checks, and improper user input sanitization.\",\\n      \"weaknesses\": [\\n        \"Cache Poisoning: Wrong cache configuration leads to caching of sensitive event data, potentially exposing it to unauthorized users.\",\\n        \"Insecure Direct Object Reference (IDOR): Missing access checks allow unauthenticated users to activate or delete events.\",\\n        \"SQL wildcard injection: Improperly escaped user input in LIKE comparison can lead to SQL injection.\"\\n      ],\\n      \"impact\": \"An attacker can:\\\\n\\\\n*   Gain unauthorized access to sensitive event data through cache poisoning.\\\\n*   Activate or delete events without proper authentication, potentially disrupting services.\\\\n*   Perform SQL wildcard injection attacks.\",\\n      \"attack_vectors\": [\\n        \"Network access to the vulnerable web application.\",\\n         \"By sending crafted requests to the application, either as an unauthenticated user or as a user with limited privileges.\"\\n      ],\\n       \"required_capabilities\": \"The attacker needs to be able to access the web application with a vulnerable version of the extension installed. For the IDOR vulnerability they do not need to authenticate. For cache poisoning they can be an authenticated user, and for SQL injection they need to be able to provide user input.\"\\n    }\\n  ]\\n}\\n```', similar_info={'cwe_distribution': {}, 'cwe_consensus': '', 'similarity_stats': {'thresholds': [], 'total_samples_by_threshold': {}, 'top_cwes_by_threshold': {}}}, similarity_summary=SimilarityInsight(consensus_cwe='', top_cwes=[], confidence_levels={}, total_samples=0), analysis='', analysis_with_relationships='', criticism='', resolution='', relevant_cwes=[{'metadata': {'doc_id': '639', 'name': 'Authorization Bypass Through User-Controlled Key', 'source': 'sparse', 'original_content': \"The system's authorization functionality does not prevent one user from gaining access to another user's data or record by modifying the key value identifying the data.\", 'keyphrase_sources': [{'id': 'rootcause:Missing access checks in the management plugin', 'keyphrase': 'Missing access checks in the management plugin', 'type': 'rootcause'}, {'id': 'rootcause:insecure direct object reference', 'keyphrase': 'insecure direct object reference', 'type': 'rootcause'}, {'id': 'impact:activate or delete various events for unauthenticated users', 'keyphrase': 'activate or delete various events for unauthenticated users', 'type': 'impact'}, {'id': 'product:TYPO3', 'keyphrase': 'TYPO3', 'type': 'product'}, {'id': 'version:events2 (aka Events 2) extension before 8.3.8 and 9.x before 9.0.6', 'keyphrase': 'events2 (aka Events 2) extension before 8.3.8 and 9.x before 9.0.6', 'type': 'version'}]}, 'similarity': np.float64(483.61325828129486)}, {'metadata': {'doc_id': '862', 'name': 'Missing Authorization', 'source': 'sparse', 'original_content': 'The product does not perform an authorization check when an actor attempts to access a resource or perform an action.', 'keyphrase_sources': [{'id': 'rootcause:Missing access checks in the management plugin', 'keyphrase': 'Missing access checks in the management plugin', 'type': 'rootcause'}, {'id': 'impact:activate or delete various events for unauthenticated users', 'keyphrase': 'activate or delete various events for unauthenticated users', 'type': 'impact'}, {'id': 'product:TYPO3', 'keyphrase': 'TYPO3', 'type': 'product'}]}, 'similarity': np.float64(439.05230109944034)}, {'metadata': {'doc_id': '863', 'name': 'Incorrect Authorization', 'source': 'sparse', 'original_content': 'The product performs an authorization check when an actor attempts to access a resource or perform an action, but it does not correctly perform the check.', 'keyphrase_sources': [{'id': 'rootcause:Missing access checks in the management plugin', 'keyphrase': 'Missing access checks in the management plugin', 'type': 'rootcause'}, {'id': 'rootcause:insecure direct object reference', 'keyphrase': 'insecure direct object reference', 'type': 'rootcause'}, {'id': 'impact:activate or delete various events for unauthenticated users', 'keyphrase': 'activate or delete various events for unauthenticated users', 'type': 'impact'}, {'id': 'version:events2 (aka Events 2) extension before 8.3.8 and 9.x before 9.0.6', 'keyphrase': 'events2 (aka Events 2) extension before 8.3.8 and 9.x before 9.0.6', 'type': 'version'}]}, 'similarity': np.float64(406.8830090010189)}, {'metadata': {'doc_id': '285', 'name': 'Improper Authorization', 'source': 'sparse', 'original_content': 'The product does not perform or incorrectly performs an authorization check when an actor attempts to access a resource or perform an action.', 'keyphrase_sources': [{'id': 'rootcause:Missing access checks in the management plugin', 'keyphrase': 'Missing access checks in the management plugin', 'type': 'rootcause'}, {'id': 'rootcause:insecure direct object reference', 'keyphrase': 'insecure direct object reference', 'type': 'rootcause'}, {'id': 'impact:activate or delete various events for unauthenticated users', 'keyphrase': 'activate or delete various events for unauthenticated users', 'type': 'impact'}, {'id': 'product:TYPO3', 'keyphrase': 'TYPO3', 'type': 'product'}, {'id': 'version:events2 (aka Events 2) extension before 8.3.8 and 9.x before 9.0.6', 'keyphrase': 'events2 (aka Events 2) extension before 8.3.8 and 9.x before 9.0.6', 'type': 'version'}]}, 'similarity': np.float64(405.456353310484)}, {'metadata': {'doc_id': '352', 'name': 'Cross-Site Request Forgery (CSRF)', 'source': 'sparse', 'original_content': 'The web application does not, or can not, sufficiently verify whether a well-formed, valid, consistent request was intentionally provided by the user who submitted the request.', 'keyphrase_sources': [{'id': 'rootcause:Missing access checks in the management plugin', 'keyphrase': 'Missing access checks in the management plugin', 'type': 'rootcause'}]}, 'similarity': np.float64(405.1718673858604)}, {'metadata': {'doc_id': '99', 'name': \"Improper Control of Resource Identifiers ('Resource Injection')\", 'source': 'sparse', 'original_content': 'The product receives input from an upstream component, but it does not restrict or incorrectly restricts the input before it is used as an identifier for a resource that may be outside the intended sphere of control.', 'keyphrase_sources': [{'id': 'rootcause:insecure direct object reference', 'keyphrase': 'insecure direct object reference', 'type': 'rootcause'}]}, 'similarity': np.float64(338.6038659897248)}, {'metadata': {'doc_id': '425', 'name': \"Direct Request ('Forced Browsing')\", 'source': 'sparse', 'original_content': 'The web application does not adequately enforce appropriate authorization on all restricted URLs, scripts, or files.', 'keyphrase_sources': [{'id': 'rootcause:insecure direct object reference', 'keyphrase': 'insecure direct object reference', 'type': 'rootcause'}, {'id': 'impact:activate or delete various events for unauthenticated users', 'keyphrase': 'activate or delete various events for unauthenticated users', 'type': 'impact'}, {'id': 'product:TYPO3', 'keyphrase': 'TYPO3', 'type': 'product'}]}, 'similarity': np.float64(337.66716736942925)}, {'metadata': {'doc_id': '284', 'name': 'Improper Access Control', 'source': 'sparse', 'original_content': 'The product does not restrict or incorrectly restricts access to a resource from an unauthorized actor.', 'keyphrase_sources': [{'id': 'version:events2 (aka Events 2) extension before 8.3.8 and 9.x before 9.0.6', 'keyphrase': 'events2 (aka Events 2) extension before 8.3.8 and 9.x before 9.0.6', 'type': 'version'}]}, 'similarity': np.float64(137.8903770138766)}, {'metadata': {'doc_id': '201', 'name': 'Insertion of Sensitive Information Into Sent Data', 'source': 'sparse', 'original_content': 'The code transmits data to another actor, but a portion of the data includes sensitive information that should not be accessible to that actor.', 'keyphrase_sources': [{'id': 'version:events2 (aka Events 2) extension before 8.3.8 and 9.x before 9.0.6', 'keyphrase': 'events2 (aka Events 2) extension before 8.3.8 and 9.x before 9.0.6', 'type': 'version'}]}, 'similarity': np.float64(137.81723914550494)}, {'metadata': {'doc_id': '1390', 'name': 'Weak Authentication', 'source': 'sparse', 'original_content': 'The product uses an authentication mechanism to restrict access to specific users or identities, but the mechanism does not sufficiently prove that the claimed identity is correct.', 'keyphrase_sources': [{'id': 'product:TYPO3', 'keyphrase': 'TYPO3', 'type': 'product'}]}, 'similarity': np.float64(105.43960469495299)}], identified_cwes={'analyzer': [], 'critic_additional': []})",
  "retrieval_results": {
    "has_multiple_keyphrases": true,
    "keyphrase_cwe_sets": {
      "rootcause:Missing access checks in the management plugin": {
        "keyphrase": "Missing access checks in the management plugin",
        "type": "rootcause",
        "cwes": [
          {
            "metadata": {
              "doc_id": "639",
              "name": "Authorization Bypass Through User-Controlled Key",
              "source": "sparse",
              "original_content": "The system's authorization functionality does not prevent one user from gaining access to another user's data or record by modifying the key value identifying the data.",
              "keyphrase_sources": [
                {
                  "id": "rootcause:Missing access checks in the management plugin",
                  "keyphrase": "Missing access checks in the management plugin",
                  "type": "rootcause"
                },
                {
                  "id": "rootcause:insecure direct object reference",
                  "keyphrase": "insecure direct object reference",
                  "type": "rootcause"
                },
                {
                  "id": "impact:activate or delete various events for unauthenticated users",
                  "keyphrase": "activate or delete various events for unauthenticated users",
                  "type": "impact"
                },
                {
                  "id": "product:TYPO3",
                  "keyphrase": "TYPO3",
                  "type": "product"
                },
                {
                  "id": "version:events2 (aka Events 2) extension before 8.3.8 and 9.x before 9.0.6",
                  "keyphrase": "events2 (aka Events 2) extension before 8.3.8 and 9.x before 9.0.6",
                  "type": "version"
                }
              ]
            },
            "similarity": 483.61325828129486
          },
          {
            "metadata": {
              "doc_id": "862",
              "name": "Missing Authorization",
              "source": "sparse",
              "original_content": "The product does not perform an authorization check when an actor attempts to access a resource or perform an action.",
              "keyphrase_sources": [
                {
                  "id": "rootcause:Missing access checks in the management plugin",
                  "keyphrase": "Missing access checks in the management plugin",
                  "type": "rootcause"
                },
                {
                  "id": "impact:activate or delete various events for unauthenticated users",
                  "keyphrase": "activate or delete various events for unauthenticated users",
                  "type": "impact"
                },
                {
                  "id": "product:TYPO3",
                  "keyphrase": "TYPO3",
                  "type": "product"
                }
              ]
            },
            "similarity": 439.05230109944034
          },
          {
            "metadata": {
              "doc_id": "863",
              "name": "Incorrect Authorization",
              "source": "sparse",
              "original_content": "The product performs an authorization check when an actor attempts to access a resource or perform an action, but it does not correctly perform the check.",
              "keyphrase_sources": [
                {
                  "id": "rootcause:Missing access checks in the management plugin",
                  "keyphrase": "Missing access checks in the management plugin",
                  "type": "rootcause"
                },
                {
                  "id": "rootcause:insecure direct object reference",
                  "keyphrase": "insecure direct object reference",
                  "type": "rootcause"
                },
                {
                  "id": "impact:activate or delete various events for unauthenticated users",
                  "keyphrase": "activate or delete various events for unauthenticated users",
                  "type": "impact"
                },
                {
                  "id": "version:events2 (aka Events 2) extension before 8.3.8 and 9.x before 9.0.6",
                  "keyphrase": "events2 (aka Events 2) extension before 8.3.8 and 9.x before 9.0.6",
                  "type": "version"
                }
              ]
            },
            "similarity": 406.8830090010189
          },
          {
            "metadata": {
              "doc_id": "285",
              "name": "Improper Authorization",
              "source": "sparse",
              "original_content": "The product does not perform or incorrectly performs an authorization check when an actor attempts to access a resource or perform an action.",
              "keyphrase_sources": [
                {
                  "id": "rootcause:Missing access checks in the management plugin",
                  "keyphrase": "Missing access checks in the management plugin",
                  "type": "rootcause"
                },
                {
                  "id": "rootcause:insecure direct object reference",
                  "keyphrase": "insecure direct object reference",
                  "type": "rootcause"
                },
                {
                  "id": "impact:activate or delete various events for unauthenticated users",
                  "keyphrase": "activate or delete various events for unauthenticated users",
                  "type": "impact"
                },
                {
                  "id": "product:TYPO3",
                  "keyphrase": "TYPO3",
                  "type": "product"
                },
                {
                  "id": "version:events2 (aka Events 2) extension before 8.3.8 and 9.x before 9.0.6",
                  "keyphrase": "events2 (aka Events 2) extension before 8.3.8 and 9.x before 9.0.6",
                  "type": "version"
                }
              ]
            },
            "similarity": 405.456353310484
          },
          {
            "metadata": {
              "doc_id": "352",
              "name": "Cross-Site Request Forgery (CSRF)",
              "source": "sparse",
              "original_content": "The web application does not, or can not, sufficiently verify whether a well-formed, valid, consistent request was intentionally provided by the user who submitted the request.",
              "keyphrase_sources": [
                {
                  "id": "rootcause:Missing access checks in the management plugin",
                  "keyphrase": "Missing access checks in the management plugin",
                  "type": "rootcause"
                }
              ]
            },
            "similarity": 405.1718673858604
          }
        ]
      },
      "rootcause:insecure direct object reference": {
        "keyphrase": "insecure direct object reference",
        "type": "rootcause",
        "cwes": [
          {
            "metadata": {
              "doc_id": "639",
              "name": "Authorization Bypass Through User-Controlled Key",
              "source": "sparse",
              "original_content": "The system's authorization functionality does not prevent one user from gaining access to another user's data or record by modifying the key value identifying the data."
            },
            "similarity": 493.4928446290103
          },
          {
            "metadata": {
              "doc_id": "99",
              "name": "Improper Control of Resource Identifiers ('Resource Injection')",
              "source": "sparse",
              "original_content": "The product receives input from an upstream component, but it does not restrict or incorrectly restricts the input before it is used as an identifier for a resource that may be outside the intended sphere of control.",
              "keyphrase_sources": [
                {
                  "id": "rootcause:insecure direct object reference",
                  "keyphrase": "insecure direct object reference",
                  "type": "rootcause"
                }
              ]
            },
            "similarity": 338.6038659897248
          },
          {
            "metadata": {
              "doc_id": "425",
              "name": "Direct Request ('Forced Browsing')",
              "source": "sparse",
              "original_content": "The web application does not adequately enforce appropriate authorization on all restricted URLs, scripts, or files.",
              "keyphrase_sources": [
                {
                  "id": "rootcause:insecure direct object reference",
                  "keyphrase": "insecure direct object reference",
                  "type": "rootcause"
                },
                {
                  "id": "impact:activate or delete various events for unauthenticated users",
                  "keyphrase": "activate or delete various events for unauthenticated users",
                  "type": "impact"
                },
                {
                  "id": "product:TYPO3",
                  "keyphrase": "TYPO3",
                  "type": "product"
                }
              ]
            },
            "similarity": 337.66716736942925
          },
          {
            "metadata": {
              "doc_id": "285",
              "name": "Improper Authorization",
              "source": "sparse",
              "original_content": "The product does not perform or incorrectly performs an authorization check when an actor attempts to access a resource or perform an action."
            },
            "similarity": 308.251083451369
          },
          {
            "metadata": {
              "doc_id": "863",
              "name": "Incorrect Authorization",
              "source": "sparse",
              "original_content": "The product performs an authorization check when an actor attempts to access a resource or perform an action, but it does not correctly perform the check."
            },
            "similarity": 303.8432494742274
          }
        ]
      },
      "impact:activate or delete various events for unauthenticated users": {
        "keyphrase": "activate or delete various events for unauthenticated users",
        "type": "impact",
        "cwes": [
          {
            "metadata": {
              "doc_id": "639",
              "name": "Authorization Bypass Through User-Controlled Key",
              "source": "sparse",
              "original_content": "The system's authorization functionality does not prevent one user from gaining access to another user's data or record by modifying the key value identifying the data."
            },
            "similarity": 154.17803447316572
          },
          {
            "metadata": {
              "doc_id": "285",
              "name": "Improper Authorization",
              "source": "sparse",
              "original_content": "The product does not perform or incorrectly performs an authorization check when an actor attempts to access a resource or perform an action."
            },
            "similarity": 132.98308187972705
          },
          {
            "metadata": {
              "doc_id": "425",
              "name": "Direct Request ('Forced Browsing')",
              "source": "sparse",
              "original_content": "The web application does not adequately enforce appropriate authorization on all restricted URLs, scripts, or files."
            },
            "similarity": 131.51015563178132
          },
          {
            "metadata": {
              "doc_id": "863",
              "name": "Incorrect Authorization",
              "source": "sparse",
              "original_content": "The product performs an authorization check when an actor attempts to access a resource or perform an action, but it does not correctly perform the check."
            },
            "similarity": 129.1990408262479
          },
          {
            "metadata": {
              "doc_id": "862",
              "name": "Missing Authorization",
              "source": "sparse",
              "original_content": "The product does not perform an authorization check when an actor attempts to access a resource or perform an action."
            },
            "similarity": 128.28482578083324
          }
        ]
      },
      "product:TYPO3": {
        "keyphrase": "TYPO3",
        "type": "product",
        "cwes": [
          {
            "metadata": {
              "doc_id": "639",
              "name": "Authorization Bypass Through User-Controlled Key",
              "source": "sparse",
              "original_content": "The system's authorization functionality does not prevent one user from gaining access to another user's data or record by modifying the key value identifying the data."
            },
            "similarity": 124.63842966048831
          },
          {
            "metadata": {
              "doc_id": "1390",
              "name": "Weak Authentication",
              "source": "sparse",
              "original_content": "The product uses an authentication mechanism to restrict access to specific users or identities, but the mechanism does not sufficiently prove that the claimed identity is correct.",
              "keyphrase_sources": [
                {
                  "id": "product:TYPO3",
                  "keyphrase": "TYPO3",
                  "type": "product"
                }
              ]
            },
            "similarity": 105.43960469495299
          },
          {
            "metadata": {
              "doc_id": "285",
              "name": "Improper Authorization",
              "source": "sparse",
              "original_content": "The product does not perform or incorrectly performs an authorization check when an actor attempts to access a resource or perform an action."
            },
            "similarity": 97.45349645093904
          },
          {
            "metadata": {
              "doc_id": "862",
              "name": "Missing Authorization",
              "source": "sparse",
              "original_content": "The product does not perform an authorization check when an actor attempts to access a resource or perform an action."
            },
            "similarity": 97.34399284926525
          },
          {
            "metadata": {
              "doc_id": "425",
              "name": "Direct Request ('Forced Browsing')",
              "source": "sparse",
              "original_content": "The web application does not adequately enforce appropriate authorization on all restricted URLs, scripts, or files."
            },
            "similarity": 97.31891581264725
          }
        ]
      },
      "version:events2 (aka Events 2) extension before 8.3.8 and 9.x before 9.0.6": {
        "keyphrase": "events2 (aka Events 2) extension before 8.3.8 and 9.x before 9.0.6",
        "type": "version",
        "cwes": [
          {
            "metadata": {
              "doc_id": "639",
              "name": "Authorization Bypass Through User-Controlled Key",
              "source": "sparse",
              "original_content": "The system's authorization functionality does not prevent one user from gaining access to another user's data or record by modifying the key value identifying the data."
            },
            "similarity": 168.83400924142794
          },
          {
            "metadata": {
              "doc_id": "863",
              "name": "Incorrect Authorization",
              "source": "sparse",
              "original_content": "The product performs an authorization check when an actor attempts to access a resource or perform an action, but it does not correctly perform the check."
            },
            "similarity": 145.16497060634433
          },
          {
            "metadata": {
              "doc_id": "285",
              "name": "Improper Authorization",
              "source": "sparse",
              "original_content": "The product does not perform or incorrectly performs an authorization check when an actor attempts to access a resource or perform an action."
            },
            "similarity": 141.03269090739403
          },
          {
            "metadata": {
              "doc_id": "284",
              "name": "Improper Access Control",
              "source": "sparse",
              "original_content": "The product does not restrict or incorrectly restricts access to a resource from an unauthorized actor.",
              "keyphrase_sources": [
                {
                  "id": "version:events2 (aka Events 2) extension before 8.3.8 and 9.x before 9.0.6",
                  "keyphrase": "events2 (aka Events 2) extension before 8.3.8 and 9.x before 9.0.6",
                  "type": "version"
                }
              ]
            },
            "similarity": 137.8903770138766
          },
          {
            "metadata": {
              "doc_id": "201",
              "name": "Insertion of Sensitive Information Into Sent Data",
              "source": "sparse",
              "original_content": "The code transmits data to another actor, but a portion of the data includes sensitive information that should not be accessible to that actor.",
              "keyphrase_sources": [
                {
                  "id": "version:events2 (aka Events 2) extension before 8.3.8 and 9.x before 9.0.6",
                  "keyphrase": "events2 (aka Events 2) extension before 8.3.8 and 9.x before 9.0.6",
                  "type": "version"
                }
              ]
            },
            "similarity": 137.81723914550494
          }
        ]
      }
    },
    "keyphrase_mapping": {
      "639": [
        {
          "id": "rootcause:Missing access checks in the management plugin",
          "keyphrase": "Missing access checks in the management plugin",
          "type": "rootcause"
        },
        {
          "id": "rootcause:insecure direct object reference",
          "keyphrase": "insecure direct object reference",
          "type": "rootcause"
        },
        {
          "id": "impact:activate or delete various events for unauthenticated users",
          "keyphrase": "activate or delete various events for unauthenticated users",
          "type": "impact"
        },
        {
          "id": "product:TYPO3",
          "keyphrase": "TYPO3",
          "type": "product"
        },
        {
          "id": "version:events2 (aka Events 2) extension before 8.3.8 and 9.x before 9.0.6",
          "keyphrase": "events2 (aka Events 2) extension before 8.3.8 and 9.x before 9.0.6",
          "type": "version"
        }
      ],
      "862": [
        {
          "id": "rootcause:Missing access checks in the management plugin",
          "keyphrase": "Missing access checks in the management plugin",
          "type": "rootcause"
        },
        {
          "id": "impact:activate or delete various events for unauthenticated users",
          "keyphrase": "activate or delete various events for unauthenticated users",
          "type": "impact"
        },
        {
          "id": "product:TYPO3",
          "keyphrase": "TYPO3",
          "type": "product"
        }
      ],
      "863": [
        {
          "id": "rootcause:Missing access checks in the management plugin",
          "keyphrase": "Missing access checks in the management plugin",
          "type": "rootcause"
        },
        {
          "id": "rootcause:insecure direct object reference",
          "keyphrase": "insecure direct object reference",
          "type": "rootcause"
        },
        {
          "id": "impact:activate or delete various events for unauthenticated users",
          "keyphrase": "activate or delete various events for unauthenticated users",
          "type": "impact"
        },
        {
          "id": "version:events2 (aka Events 2) extension before 8.3.8 and 9.x before 9.0.6",
          "keyphrase": "events2 (aka Events 2) extension before 8.3.8 and 9.x before 9.0.6",
          "type": "version"
        }
      ],
      "285": [
        {
          "id": "rootcause:Missing access checks in the management plugin",
          "keyphrase": "Missing access checks in the management plugin",
          "type": "rootcause"
        },
        {
          "id": "rootcause:insecure direct object reference",
          "keyphrase": "insecure direct object reference",
          "type": "rootcause"
        },
        {
          "id": "impact:activate or delete various events for unauthenticated users",
          "keyphrase": "activate or delete various events for unauthenticated users",
          "type": "impact"
        },
        {
          "id": "product:TYPO3",
          "keyphrase": "TYPO3",
          "type": "product"
        },
        {
          "id": "version:events2 (aka Events 2) extension before 8.3.8 and 9.x before 9.0.6",
          "keyphrase": "events2 (aka Events 2) extension before 8.3.8 and 9.x before 9.0.6",
          "type": "version"
        }
      ],
      "352": [
        {
          "id": "rootcause:Missing access checks in the management plugin",
          "keyphrase": "Missing access checks in the management plugin",
          "type": "rootcause"
        }
      ],
      "99": [
        {
          "id": "rootcause:insecure direct object reference",
          "keyphrase": "insecure direct object reference",
          "type": "rootcause"
        }
      ],
      "425": [
        {
          "id": "rootcause:insecure direct object reference",
          "keyphrase": "insecure direct object reference",
          "type": "rootcause"
        },
        {
          "id": "impact:activate or delete various events for unauthenticated users",
          "keyphrase": "activate or delete various events for unauthenticated users",
          "type": "impact"
        },
        {
          "id": "product:TYPO3",
          "keyphrase": "TYPO3",
          "type": "product"
        }
      ],
      "1390": [
        {
          "id": "product:TYPO3",
          "keyphrase": "TYPO3",
          "type": "product"
        }
      ],
      "284": [
        {
          "id": "version:events2 (aka Events 2) extension before 8.3.8 and 9.x before 9.0.6",
          "keyphrase": "events2 (aka Events 2) extension before 8.3.8 and 9.x before 9.0.6",
          "type": "version"
        }
      ],
      "201": [
        {
          "id": "version:events2 (aka Events 2) extension before 8.3.8 and 9.x before 9.0.6",
          "keyphrase": "events2 (aka Events 2) extension before 8.3.8 and 9.x before 9.0.6",
          "type": "version"
        }
      ]
    },
    "relevant_cwes": [
      {
        "metadata": {
          "doc_id": "639",
          "name": "Authorization Bypass Through User-Controlled Key",
          "source": "sparse",
          "original_content": "The system's authorization functionality does not prevent one user from gaining access to another user's data or record by modifying the key value identifying the data.",
          "keyphrase_sources": [
            {
              "id": "rootcause:Missing access checks in the management plugin",
              "keyphrase": "Missing access checks in the management plugin",
              "type": "rootcause"
            },
            {
              "id": "rootcause:insecure direct object reference",
              "keyphrase": "insecure direct object reference",
              "type": "rootcause"
            },
            {
              "id": "impact:activate or delete various events for unauthenticated users",
              "keyphrase": "activate or delete various events for unauthenticated users",
              "type": "impact"
            },
            {
              "id": "product:TYPO3",
              "keyphrase": "TYPO3",
              "type": "product"
            },
            {
              "id": "version:events2 (aka Events 2) extension before 8.3.8 and 9.x before 9.0.6",
              "keyphrase": "events2 (aka Events 2) extension before 8.3.8 and 9.x before 9.0.6",
              "type": "version"
            }
          ]
        },
        "similarity": 483.61325828129486
      },
      {
        "metadata": {
          "doc_id": "862",
          "name": "Missing Authorization",
          "source": "sparse",
          "original_content": "The product does not perform an authorization check when an actor attempts to access a resource or perform an action.",
          "keyphrase_sources": [
            {
              "id": "rootcause:Missing access checks in the management plugin",
              "keyphrase": "Missing access checks in the management plugin",
              "type": "rootcause"
            },
            {
              "id": "impact:activate or delete various events for unauthenticated users",
              "keyphrase": "activate or delete various events for unauthenticated users",
              "type": "impact"
            },
            {
              "id": "product:TYPO3",
              "keyphrase": "TYPO3",
              "type": "product"
            }
          ]
        },
        "similarity": 439.05230109944034
      },
      {
        "metadata": {
          "doc_id": "863",
          "name": "Incorrect Authorization",
          "source": "sparse",
          "original_content": "The product performs an authorization check when an actor attempts to access a resource or perform an action, but it does not correctly perform the check.",
          "keyphrase_sources": [
            {
              "id": "rootcause:Missing access checks in the management plugin",
              "keyphrase": "Missing access checks in the management plugin",
              "type": "rootcause"
            },
            {
              "id": "rootcause:insecure direct object reference",
              "keyphrase": "insecure direct object reference",
              "type": "rootcause"
            },
            {
              "id": "impact:activate or delete various events for unauthenticated users",
              "keyphrase": "activate or delete various events for unauthenticated users",
              "type": "impact"
            },
            {
              "id": "version:events2 (aka Events 2) extension before 8.3.8 and 9.x before 9.0.6",
              "keyphrase": "events2 (aka Events 2) extension before 8.3.8 and 9.x before 9.0.6",
              "type": "version"
            }
          ]
        },
        "similarity": 406.8830090010189
      },
      {
        "metadata": {
          "doc_id": "285",
          "name": "Improper Authorization",
          "source": "sparse",
          "original_content": "The product does not perform or incorrectly performs an authorization check when an actor attempts to access a resource or perform an action.",
          "keyphrase_sources": [
            {
              "id": "rootcause:Missing access checks in the management plugin",
              "keyphrase": "Missing access checks in the management plugin",
              "type": "rootcause"
            },
            {
              "id": "rootcause:insecure direct object reference",
              "keyphrase": "insecure direct object reference",
              "type": "rootcause"
            },
            {
              "id": "impact:activate or delete various events for unauthenticated users",
              "keyphrase": "activate or delete various events for unauthenticated users",
              "type": "impact"
            },
            {
              "id": "product:TYPO3",
              "keyphrase": "TYPO3",
              "type": "product"
            },
            {
              "id": "version:events2 (aka Events 2) extension before 8.3.8 and 9.x before 9.0.6",
              "keyphrase": "events2 (aka Events 2) extension before 8.3.8 and 9.x before 9.0.6",
              "type": "version"
            }
          ]
        },
        "similarity": 405.456353310484
      },
      {
        "metadata": {
          "doc_id": "352",
          "name": "Cross-Site Request Forgery (CSRF)",
          "source": "sparse",
          "original_content": "The web application does not, or can not, sufficiently verify whether a well-formed, valid, consistent request was intentionally provided by the user who submitted the request.",
          "keyphrase_sources": [
            {
              "id": "rootcause:Missing access checks in the management plugin",
              "keyphrase": "Missing access checks in the management plugin",
              "type": "rootcause"
            }
          ]
        },
        "similarity": 405.1718673858604
      },
      {
        "metadata": {
          "doc_id": "99",
          "name": "Improper Control of Resource Identifiers ('Resource Injection')",
          "source": "sparse",
          "original_content": "The product receives input from an upstream component, but it does not restrict or incorrectly restricts the input before it is used as an identifier for a resource that may be outside the intended sphere of control.",
          "keyphrase_sources": [
            {
              "id": "rootcause:insecure direct object reference",
              "keyphrase": "insecure direct object reference",
              "type": "rootcause"
            }
          ]
        },
        "similarity": 338.6038659897248
      },
      {
        "metadata": {
          "doc_id": "425",
          "name": "Direct Request ('Forced Browsing')",
          "source": "sparse",
          "original_content": "The web application does not adequately enforce appropriate authorization on all restricted URLs, scripts, or files.",
          "keyphrase_sources": [
            {
              "id": "rootcause:insecure direct object reference",
              "keyphrase": "insecure direct object reference",
              "type": "rootcause"
            },
            {
              "id": "impact:activate or delete various events for unauthenticated users",
              "keyphrase": "activate or delete various events for unauthenticated users",
              "type": "impact"
            },
            {
              "id": "product:TYPO3",
              "keyphrase": "TYPO3",
              "type": "product"
            }
          ]
        },
        "similarity": 337.66716736942925
      },
      {
        "metadata": {
          "doc_id": "284",
          "name": "Improper Access Control",
          "source": "sparse",
          "original_content": "The product does not restrict or incorrectly restricts access to a resource from an unauthorized actor.",
          "keyphrase_sources": [
            {
              "id": "version:events2 (aka Events 2) extension before 8.3.8 and 9.x before 9.0.6",
              "keyphrase": "events2 (aka Events 2) extension before 8.3.8 and 9.x before 9.0.6",
              "type": "version"
            }
          ]
        },
        "similarity": 137.8903770138766
      },
      {
        "metadata": {
          "doc_id": "201",
          "name": "Insertion of Sensitive Information Into Sent Data",
          "source": "sparse",
          "original_content": "The code transmits data to another actor, but a portion of the data includes sensitive information that should not be accessible to that actor.",
          "keyphrase_sources": [
            {
              "id": "version:events2 (aka Events 2) extension before 8.3.8 and 9.x before 9.0.6",
              "keyphrase": "events2 (aka Events 2) extension before 8.3.8 and 9.x before 9.0.6",
              "type": "version"
            }
          ]
        },
        "similarity": 137.81723914550494
      },
      {
        "metadata": {
          "doc_id": "1390",
          "name": "Weak Authentication",
          "source": "sparse",
          "original_content": "The product uses an authentication mechanism to restrict access to specific users or identities, but the mechanism does not sufficiently prove that the claimed identity is correct.",
          "keyphrase_sources": [
            {
              "id": "product:TYPO3",
              "keyphrase": "TYPO3",
              "type": "product"
            }
          ]
        },
        "similarity": 105.43960469495299
      }
    ],
    "enhanced_query": "# Vulnerability Description\n\n    An issue was discovered in the events2 (aka Events 2) extension before 8.3.8 and 9.x before 9.0.6 for TYPO3. **Missing access checks in the management plugin** lead to an **insecure direct object reference** (IDOR) vulnerability with the potential to activate or delete various events for unauthenticated users.\n\n    # Keyphrase-Specific CWE Analysis\n    This vulnerability contains multiple keyphrases that may map to different CWEs. \n    Please analyze each keyphrase separately and determine the most appropriate CWE(s) for each.\n\n    ## ROOTCAUSE: 'Missing access checks in the management plugin'\n\nRelevant CWEs for this ROOTCAUSE:\n\n### 1. CWE-639: Authorization Bypass Through User-Controlled Key (Score: 483.61)\n\nThe system's authorization functionality does not prevent one user from gaining access to another user's data or record by modifying the key value identifying the data....\n\n### 2. CWE-862: Missing Authorization (Score: 439.05)\n\nThe product does not perform an authorization check when an actor attempts to access a resource or perform an action....\n\n### 3. CWE-863: Incorrect Authorization (Score: 406.88)\n\nThe product performs an authorization check when an actor attempts to access a resource or perform an action, but it does not correctly perform the check....\n\n### 4. CWE-285: Improper Authorization (Score: 405.46)\n\nThe product does not perform or incorrectly performs an authorization check when an actor attempts to access a resource or perform an action....\n\n### 5. CWE-352: Cross-Site Request Forgery (CSRF) (Score: 405.17)\n\nThe web application does not, or can not, sufficiently verify whether a well-formed, valid, consistent request was intentionally provided by the user who submitted the request....\n\n## ROOTCAUSE: 'insecure direct object reference'\n\nRelevant CWEs for this ROOTCAUSE:\n\n### 1. CWE-639: Authorization Bypass Through User-Controlled Key (Score: 483.61)\n\nThe system's authorization functionality does not prevent one user from gaining access to another user's data or record by modifying the key value identifying the data....\n\n### 2. CWE-863: Incorrect Authorization (Score: 406.88)\n\nThe product performs an authorization check when an actor attempts to access a resource or perform an action, but it does not correctly perform the check....\n\n### 3. CWE-285: Improper Authorization (Score: 405.46)\n\nThe product does not perform or incorrectly performs an authorization check when an actor attempts to access a resource or perform an action....\n\n### 4. CWE-99: Improper Control of Resource Identifiers ('Resource Injection') (Score: 338.60)\n\nThe product receives input from an upstream component, but it does not restrict or incorrectly restricts the input before it is used as an identifier for a resource that may be outside the intended sphere of control....\n\n### 5. CWE-425: Direct Request ('Forced Browsing') (Score: 337.67)\n\nThe web application does not adequately enforce appropriate authorization on all restricted URLs, scripts, or files....\n\n## IMPACT: 'activate or delete various events for unauthenticated users'\n\nRelevant CWEs for this IMPACT:\n\n### 1. CWE-639: Authorization Bypass Through User-Controlled Key (Score: 483.61)\n\nThe system's authorization functionality does not prevent one user from gaining access to another user's data or record by modifying the key value identifying the data....\n\n### 2. CWE-862: Missing Authorization (Score: 439.05)\n\nThe product does not perform an authorization check when an actor attempts to access a resource or perform an action....\n\n### 3. CWE-863: Incorrect Authorization (Score: 406.88)\n\nThe product performs an authorization check when an actor attempts to access a resource or perform an action, but it does not correctly perform the check....\n\n### 4. CWE-285: Improper Authorization (Score: 405.46)\n\nThe product does not perform or incorrectly performs an authorization check when an actor attempts to access a resource or perform an action....\n\n### 5. CWE-425: Direct Request ('Forced Browsing') (Score: 337.67)\n\nThe web application does not adequately enforce appropriate authorization on all restricted URLs, scripts, or files....\n\n## PRODUCT: 'TYPO3'\n\nRelevant CWEs for this PRODUCT:\n\n### 1. CWE-639: Authorization Bypass Through User-Controlled Key (Score: 483.61)\n\nThe system's authorization functionality does not prevent one user from gaining access to another user's data or record by modifying the key value identifying the data....\n\n### 2. CWE-862: Missing Authorization (Score: 439.05)\n\nThe product does not perform an authorization check when an actor attempts to access a resource or perform an action....\n\n### 3. CWE-285: Improper Authorization (Score: 405.46)\n\nThe product does not perform or incorrectly performs an authorization check when an actor attempts to access a resource or perform an action....\n\n### 4. CWE-425: Direct Request ('Forced Browsing') (Score: 337.67)\n\nThe web application does not adequately enforce appropriate authorization on all restricted URLs, scripts, or files....\n\n### 5. CWE-1390: Weak Authentication (Score: 105.44)\n\nThe product uses an authentication mechanism to restrict access to specific users or identities, but the mechanism does not sufficiently prove that the claimed identity is correct....\n\n## VERSION: 'events2 (aka Events 2) extension before 8.3.8 and 9.x before 9.0.6'\n\nRelevant CWEs for this VERSION:\n\n### 1. CWE-639: Authorization Bypass Through User-Controlled Key (Score: 483.61)\n\nThe system's authorization functionality does not prevent one user from gaining access to another user's data or record by modifying the key value identifying the data....\n\n### 2. CWE-863: Incorrect Authorization (Score: 406.88)\n\nThe product performs an authorization check when an actor attempts to access a resource or perform an action, but it does not correctly perform the check....\n\n### 3. CWE-285: Improper Authorization (Score: 405.46)\n\nThe product does not perform or incorrectly performs an authorization check when an actor attempts to access a resource or perform an action....\n\n### 4. CWE-284: Improper Access Control (Score: 137.89)\n\nThe product does not restrict or incorrectly restricts access to a resource from an unauthorized actor....\n\n### 5. CWE-201: Insertion of Sensitive Information Into Sent Data (Score: 137.82)\n\nThe code transmits data to another actor, but a portion of the data includes sensitive information that should not be accessible to that actor....\n\n\n    # Analysis Instructions\n    1. For each keyphrase, identify the most appropriate CWE(s) that represent the weakness.\n    2. Consider how the different keyphrases might relate to each other in the vulnerability chain.\n    3. Provide a final determination of primary CWE(s) and any secondary CWEs.\n    4. Format your response using the standard analysis template.\n\n    Please analyze how these different weaknesses interact and provide a comprehensive CWE classification.\n    "
  },
  "retrieval_time": 1.3616454601287842
}