{
  "vulnerability_info": "VulnerabilityInfo(cve_id='CVE-2024-49221', description='Cross-Site Request Forgery (CSRF) vulnerability in Julian Weinert // cs&m cSlider allows Stored **XSS**.This issue affects cSlider from n/a through 2.4.2.', key_phrases={'rootcause': 'lack of CSRF protection', 'weakness': ['XSS', 'cross-site scripting'], 'impact': '', 'vector': '', 'attacker': '', 'product': 'Julian Weinert // cs&m cSlider', 'version': 'n/a through 2.4.2', 'component': ''}, reference_content='```\\n{\\n  \"Root cause of vulnerability\": \"The cSlider WordPress plugin lacks proper CSRF protection.\",\\n  \"Weaknesses/vulnerabilities present\": \"Cross-Site Request Forgery (CSRF)\",\\n  \"Impact of exploitation\": \"A malicious actor can force higher privileged users to execute unwanted actions under their current authentication.\",\\n  \"Attack vectors\": \"The attacker could craft a malicious link or embed a form on a website. When a logged-in administrator clicks the link or visits the page containing the form, actions will be performed on the vulnerable WordPress site.\",\\n  \"Required attacker capabilities/position\": \"The attacker needs to trick a logged-in user with sufficient privileges to visit the malicious link or page.\"\\n}\\n```', similar_info={'cwe_distribution': {}, 'cwe_consensus': '', 'similarity_stats': {'thresholds': [], 'total_samples_by_threshold': {}, 'top_cwes_by_threshold': {}}}, similarity_summary=SimilarityInsight(consensus_cwe='', top_cwes=[], confidence_levels={}, total_samples=0), analysis='', analysis_with_relationships='', criticism='', resolution='', relevant_cwes=[{'metadata': {'doc_id': '352', 'name': 'Cross-Site Request Forgery (CSRF)', 'source': 'sparse', 'original_content': 'The web application does not, or can not, sufficiently verify whether a well-formed, valid, consistent request was intentionally provided by the user who submitted the request.', 'keyphrase_sources': [{'id': 'rootcause:lack of CSRF protection', 'keyphrase': 'lack of CSRF protection', 'type': 'rootcause'}, {'id': 'weakness:XSS', 'keyphrase': 'XSS', 'type': 'weakness'}, {'id': 'weakness:cross-site scripting', 'keyphrase': 'cross-site scripting', 'type': 'weakness'}, {'id': 'product:Julian Weinert // cs&m cSlider', 'keyphrase': 'Julian Weinert // cs&m cSlider', 'type': 'product'}, {'id': 'version:n/a through 2.4.2', 'keyphrase': 'n/a through 2.4.2', 'type': 'version'}]}, 'similarity': np.float64(273.54246680874985)}, {'metadata': {'doc_id': '434', 'name': 'Unrestricted Upload of File with Dangerous Type', 'source': 'sparse', 'original_content': 'The product allows the upload or transfer of dangerous file types that are automatically processed within its environment.', 'keyphrase_sources': [{'id': 'rootcause:lack of CSRF protection', 'keyphrase': 'lack of CSRF protection', 'type': 'rootcause'}, {'id': 'version:n/a through 2.4.2', 'keyphrase': 'n/a through 2.4.2', 'type': 'version'}]}, 'similarity': np.float64(202.19471575026046)}, {'metadata': {'doc_id': '79', 'name': \"Improper Neutralization of Input During Web Page Generation ('Cross-site Scripting')\", 'source': 'sparse', 'original_content': 'The product does not neutralize or incorrectly neutralizes user-controllable input before it is placed in output that is used as a web page that is served to other users.', 'keyphrase_sources': [{'id': 'rootcause:lack of CSRF protection', 'keyphrase': 'lack of CSRF protection', 'type': 'rootcause'}, {'id': 'weakness:XSS', 'keyphrase': 'XSS', 'type': 'weakness'}, {'id': 'weakness:cross-site scripting', 'keyphrase': 'cross-site scripting', 'type': 'weakness'}, {'id': 'product:Julian Weinert // cs&m cSlider', 'keyphrase': 'Julian Weinert // cs&m cSlider', 'type': 'product'}, {'id': 'version:n/a through 2.4.2', 'keyphrase': 'n/a through 2.4.2', 'type': 'version'}]}, 'similarity': np.float64(197.9994555901746)}, {'metadata': {'doc_id': '116', 'name': 'Improper Encoding or Escaping of Output', 'source': 'sparse', 'original_content': 'The product prepares a structured message for communication with another component, but encoding or escaping of the data is either missing or done incorrectly. As a result, the intended structure of the message is not preserved.', 'keyphrase_sources': [{'id': 'rootcause:lack of CSRF protection', 'keyphrase': 'lack of CSRF protection', 'type': 'rootcause'}, {'id': 'weakness:XSS', 'keyphrase': 'XSS', 'type': 'weakness'}, {'id': 'weakness:cross-site scripting', 'keyphrase': 'cross-site scripting', 'type': 'weakness'}]}, 'similarity': np.float64(194.61559497089291)}, {'metadata': {'doc_id': '1004', 'name': \"Sensitive Cookie Without 'HttpOnly' Flag\", 'source': 'sparse', 'original_content': 'The product uses a cookie to store sensitive information, but the cookie is not marked with the HttpOnly flag.', 'keyphrase_sources': [{'id': 'rootcause:lack of CSRF protection', 'keyphrase': 'lack of CSRF protection', 'type': 'rootcause'}, {'id': 'weakness:XSS', 'keyphrase': 'XSS', 'type': 'weakness'}, {'id': 'weakness:cross-site scripting', 'keyphrase': 'cross-site scripting', 'type': 'weakness'}, {'id': 'product:Julian Weinert // cs&m cSlider', 'keyphrase': 'Julian Weinert // cs&m cSlider', 'type': 'product'}]}, 'similarity': np.float64(180.86413440121214)}, {'metadata': {'doc_id': '80', 'name': 'Improper Neutralization of Script-Related HTML Tags in a Web Page (Basic XSS)', 'source': 'sparse', 'original_content': 'The product receives input from an upstream component, but it does not neutralize or incorrectly neutralizes special characters such as \"<\", \">\", and \"&\" that could be interpreted as web-scripting elements when they are sent to a downstream component that processes web pages.', 'keyphrase_sources': [{'id': 'weakness:XSS', 'keyphrase': 'XSS', 'type': 'weakness'}, {'id': 'weakness:cross-site scripting', 'keyphrase': 'cross-site scripting', 'type': 'weakness'}]}, 'similarity': np.float64(141.00406479971866)}, {'metadata': {'doc_id': '22', 'name': \"Improper Limitation of a Pathname to a Restricted Directory ('Path Traversal')\", 'source': 'sparse', 'original_content': 'The product uses external input to construct a pathname that is intended to identify a file or directory that is located underneath a restricted parent directory, but the product does not properly neutralize special elements within the pathname that can cause the pathname to resolve to a location that is outside of the restricted directory.', 'keyphrase_sources': [{'id': 'version:n/a through 2.4.2', 'keyphrase': 'n/a through 2.4.2', 'type': 'version'}]}, 'similarity': np.float64(62.87820094499571)}, {'metadata': {'doc_id': '89', 'name': \"Improper Neutralization of Special Elements used in an SQL Command ('SQL Injection')\", 'source': 'sparse', 'original_content': 'The product constructs all or part of an SQL command using externally-influenced input from an upstream component, but it does not neutralize or incorrectly neutralizes special elements that could modify the intended SQL command when it is sent to a downstream component. Without sufficient removal or quoting of SQL syntax in user-controllable inputs, the generated SQL query can cause those inputs to be interpreted as SQL instead of ordinary user data.', 'keyphrase_sources': [{'id': 'version:n/a through 2.4.2', 'keyphrase': 'n/a through 2.4.2', 'type': 'version'}]}, 'similarity': np.float64(60.73670531786052)}, {'metadata': {'doc_id': '665', 'name': 'Improper Initialization', 'source': 'sparse', 'original_content': 'The product does not initialize or incorrectly initializes a resource, which might leave the resource in an unexpected state when it is accessed or used.', 'keyphrase_sources': [{'id': 'product:Julian Weinert // cs&m cSlider', 'keyphrase': 'Julian Weinert // cs&m cSlider', 'type': 'product'}]}, 'similarity': np.float64(58.750202901555554)}, {'metadata': {'doc_id': '657', 'name': 'Violation of Secure Design Principles', 'source': 'sparse', 'original_content': 'The product violates well-established principles for secure design.', 'keyphrase_sources': [{'id': 'product:Julian Weinert // cs&m cSlider', 'keyphrase': 'Julian Weinert // cs&m cSlider', 'type': 'product'}]}, 'similarity': np.float64(44.804652723461736)}], identified_cwes={'analyzer': [], 'critic_additional': []})",
  "retrieval_results": {
    "has_multiple_keyphrases": true,
    "keyphrase_cwe_sets": {
      "rootcause:lack of CSRF protection": {
        "keyphrase": "lack of CSRF protection",
        "type": "rootcause",
        "cwes": [
          {
            "metadata": {
              "doc_id": "352",
              "name": "Cross-Site Request Forgery (CSRF)",
              "source": "sparse",
              "original_content": "The web application does not, or can not, sufficiently verify whether a well-formed, valid, consistent request was intentionally provided by the user who submitted the request.",
              "keyphrase_sources": [
                {
                  "id": "rootcause:lack of CSRF protection",
                  "keyphrase": "lack of CSRF protection",
                  "type": "rootcause"
                },
                {
                  "id": "weakness:XSS",
                  "keyphrase": "XSS",
                  "type": "weakness"
                },
                {
                  "id": "weakness:cross-site scripting",
                  "keyphrase": "cross-site scripting",
                  "type": "weakness"
                },
                {
                  "id": "product:Julian Weinert // cs&m cSlider",
                  "keyphrase": "Julian Weinert // cs&m cSlider",
                  "type": "product"
                },
                {
                  "id": "version:n/a through 2.4.2",
                  "keyphrase": "n/a through 2.4.2",
                  "type": "version"
                }
              ]
            },
            "similarity": 273.54246680874985
          },
          {
            "metadata": {
              "doc_id": "434",
              "name": "Unrestricted Upload of File with Dangerous Type",
              "source": "sparse",
              "original_content": "The product allows the upload or transfer of dangerous file types that are automatically processed within its environment.",
              "keyphrase_sources": [
                {
                  "id": "rootcause:lack of CSRF protection",
                  "keyphrase": "lack of CSRF protection",
                  "type": "rootcause"
                },
                {
                  "id": "version:n/a through 2.4.2",
                  "keyphrase": "n/a through 2.4.2",
                  "type": "version"
                }
              ]
            },
            "similarity": 202.19471575026046
          },
          {
            "metadata": {
              "doc_id": "79",
              "name": "Improper Neutralization of Input During Web Page Generation ('Cross-site Scripting')",
              "source": "sparse",
              "original_content": "The product does not neutralize or incorrectly neutralizes user-controllable input before it is placed in output that is used as a web page that is served to other users.",
              "keyphrase_sources": [
                {
                  "id": "rootcause:lack of CSRF protection",
                  "keyphrase": "lack of CSRF protection",
                  "type": "rootcause"
                },
                {
                  "id": "weakness:XSS",
                  "keyphrase": "XSS",
                  "type": "weakness"
                },
                {
                  "id": "weakness:cross-site scripting",
                  "keyphrase": "cross-site scripting",
                  "type": "weakness"
                },
                {
                  "id": "product:Julian Weinert // cs&m cSlider",
                  "keyphrase": "Julian Weinert // cs&m cSlider",
                  "type": "product"
                },
                {
                  "id": "version:n/a through 2.4.2",
                  "keyphrase": "n/a through 2.4.2",
                  "type": "version"
                }
              ]
            },
            "similarity": 197.9994555901746
          },
          {
            "metadata": {
              "doc_id": "116",
              "name": "Improper Encoding or Escaping of Output",
              "source": "sparse",
              "original_content": "The product prepares a structured message for communication with another component, but encoding or escaping of the data is either missing or done incorrectly. As a result, the intended structure of the message is not preserved.",
              "keyphrase_sources": [
                {
                  "id": "rootcause:lack of CSRF protection",
                  "keyphrase": "lack of CSRF protection",
                  "type": "rootcause"
                },
                {
                  "id": "weakness:XSS",
                  "keyphrase": "XSS",
                  "type": "weakness"
                },
                {
                  "id": "weakness:cross-site scripting",
                  "keyphrase": "cross-site scripting",
                  "type": "weakness"
                }
              ]
            },
            "similarity": 194.61559497089291
          },
          {
            "metadata": {
              "doc_id": "1004",
              "name": "Sensitive Cookie Without 'HttpOnly' Flag",
              "source": "sparse",
              "original_content": "The product uses a cookie to store sensitive information, but the cookie is not marked with the HttpOnly flag.",
              "keyphrase_sources": [
                {
                  "id": "rootcause:lack of CSRF protection",
                  "keyphrase": "lack of CSRF protection",
                  "type": "rootcause"
                },
                {
                  "id": "weakness:XSS",
                  "keyphrase": "XSS",
                  "type": "weakness"
                },
                {
                  "id": "weakness:cross-site scripting",
                  "keyphrase": "cross-site scripting",
                  "type": "weakness"
                },
                {
                  "id": "product:Julian Weinert // cs&m cSlider",
                  "keyphrase": "Julian Weinert // cs&m cSlider",
                  "type": "product"
                }
              ]
            },
            "similarity": 180.86413440121214
          }
        ]
      },
      "weakness:XSS": {
        "keyphrase": "XSS",
        "type": "weakness",
        "cwes": [
          {
            "metadata": {
              "doc_id": "352",
              "name": "Cross-Site Request Forgery (CSRF)",
              "source": "sparse",
              "original_content": "The web application does not, or can not, sufficiently verify whether a well-formed, valid, consistent request was intentionally provided by the user who submitted the request."
            },
            "similarity": 183.06474679745278
          },
          {
            "metadata": {
              "doc_id": "79",
              "name": "Improper Neutralization of Input During Web Page Generation ('Cross-site Scripting')",
              "source": "sparse",
              "original_content": "The product does not neutralize or incorrectly neutralizes user-controllable input before it is placed in output that is used as a web page that is served to other users."
            },
            "similarity": 166.56188321780425
          },
          {
            "metadata": {
              "doc_id": "1004",
              "name": "Sensitive Cookie Without 'HttpOnly' Flag",
              "source": "sparse",
              "original_content": "The product uses a cookie to store sensitive information, but the cookie is not marked with the HttpOnly flag."
            },
            "similarity": 147.70464472924925
          },
          {
            "metadata": {
              "doc_id": "116",
              "name": "Improper Encoding or Escaping of Output",
              "source": "sparse",
              "original_content": "The product prepares a structured message for communication with another component, but encoding or escaping of the data is either missing or done incorrectly. As a result, the intended structure of the message is not preserved."
            },
            "similarity": 141.07793638711422
          },
          {
            "metadata": {
              "doc_id": "80",
              "name": "Improper Neutralization of Script-Related HTML Tags in a Web Page (Basic XSS)",
              "source": "sparse",
              "original_content": "The product receives input from an upstream component, but it does not neutralize or incorrectly neutralizes special characters such as \"<\", \">\", and \"&\" that could be interpreted as web-scripting elements when they are sent to a downstream component that processes web pages.",
              "keyphrase_sources": [
                {
                  "id": "weakness:XSS",
                  "keyphrase": "XSS",
                  "type": "weakness"
                },
                {
                  "id": "weakness:cross-site scripting",
                  "keyphrase": "cross-site scripting",
                  "type": "weakness"
                }
              ]
            },
            "similarity": 141.00406479971866
          }
        ]
      },
      "weakness:cross-site scripting": {
        "keyphrase": "cross-site scripting",
        "type": "weakness",
        "cwes": [
          {
            "metadata": {
              "doc_id": "352",
              "name": "Cross-Site Request Forgery (CSRF)",
              "source": "sparse",
              "original_content": "The web application does not, or can not, sufficiently verify whether a well-formed, valid, consistent request was intentionally provided by the user who submitted the request."
            },
            "similarity": 251.08789207358873
          },
          {
            "metadata": {
              "doc_id": "79",
              "name": "Improper Neutralization of Input During Web Page Generation ('Cross-site Scripting')",
              "source": "sparse",
              "original_content": "The product does not neutralize or incorrectly neutralizes user-controllable input before it is placed in output that is used as a web page that is served to other users."
            },
            "similarity": 228.5266745746904
          },
          {
            "metadata": {
              "doc_id": "80",
              "name": "Improper Neutralization of Script-Related HTML Tags in a Web Page (Basic XSS)",
              "source": "sparse",
              "original_content": "The product receives input from an upstream component, but it does not neutralize or incorrectly neutralizes special characters such as \"<\", \">\", and \"&\" that could be interpreted as web-scripting elements when they are sent to a downstream component that processes web pages."
            },
            "similarity": 197.68256801819697
          },
          {
            "metadata": {
              "doc_id": "1004",
              "name": "Sensitive Cookie Without 'HttpOnly' Flag",
              "source": "sparse",
              "original_content": "The product uses a cookie to store sensitive information, but the cookie is not marked with the HttpOnly flag."
            },
            "similarity": 192.256421475394
          },
          {
            "metadata": {
              "doc_id": "116",
              "name": "Improper Encoding or Escaping of Output",
              "source": "sparse",
              "original_content": "The product prepares a structured message for communication with another component, but encoding or escaping of the data is either missing or done incorrectly. As a result, the intended structure of the message is not preserved."
            },
            "similarity": 188.24816427127467
          }
        ]
      },
      "product:Julian Weinert // cs&m cSlider": {
        "keyphrase": "Julian Weinert // cs&m cSlider",
        "type": "product",
        "cwes": [
          {
            "metadata": {
              "doc_id": "665",
              "name": "Improper Initialization",
              "source": "sparse",
              "original_content": "The product does not initialize or incorrectly initializes a resource, which might leave the resource in an unexpected state when it is accessed or used.",
              "keyphrase_sources": [
                {
                  "id": "product:Julian Weinert // cs&m cSlider",
                  "keyphrase": "Julian Weinert // cs&m cSlider",
                  "type": "product"
                }
              ]
            },
            "similarity": 58.750202901555554
          },
          {
            "metadata": {
              "doc_id": "352",
              "name": "Cross-Site Request Forgery (CSRF)",
              "source": "sparse",
              "original_content": "The web application does not, or can not, sufficiently verify whether a well-formed, valid, consistent request was intentionally provided by the user who submitted the request."
            },
            "similarity": 56.02296243255641
          },
          {
            "metadata": {
              "doc_id": "79",
              "name": "Improper Neutralization of Input During Web Page Generation ('Cross-site Scripting')",
              "source": "sparse",
              "original_content": "The product does not neutralize or incorrectly neutralizes user-controllable input before it is placed in output that is used as a web page that is served to other users."
            },
            "similarity": 53.19092790704285
          },
          {
            "metadata": {
              "doc_id": "657",
              "name": "Violation of Secure Design Principles",
              "source": "sparse",
              "original_content": "The product violates well-established principles for secure design.",
              "keyphrase_sources": [
                {
                  "id": "product:Julian Weinert // cs&m cSlider",
                  "keyphrase": "Julian Weinert // cs&m cSlider",
                  "type": "product"
                }
              ]
            },
            "similarity": 44.804652723461736
          },
          {
            "metadata": {
              "doc_id": "1004",
              "name": "Sensitive Cookie Without 'HttpOnly' Flag",
              "source": "sparse",
              "original_content": "The product uses a cookie to store sensitive information, but the cookie is not marked with the HttpOnly flag."
            },
            "similarity": 43.88619942164577
          }
        ]
      },
      "version:n/a through 2.4.2": {
        "keyphrase": "n/a through 2.4.2",
        "type": "version",
        "cwes": [
          {
            "metadata": {
              "doc_id": "352",
              "name": "Cross-Site Request Forgery (CSRF)",
              "source": "sparse",
              "original_content": "The web application does not, or can not, sufficiently verify whether a well-formed, valid, consistent request was intentionally provided by the user who submitted the request."
            },
            "similarity": 73.31445810600788
          },
          {
            "metadata": {
              "doc_id": "79",
              "name": "Improper Neutralization of Input During Web Page Generation ('Cross-site Scripting')",
              "source": "sparse",
              "original_content": "The product does not neutralize or incorrectly neutralizes user-controllable input before it is placed in output that is used as a web page that is served to other users."
            },
            "similarity": 65.67044467107539
          },
          {
            "metadata": {
              "doc_id": "434",
              "name": "Unrestricted Upload of File with Dangerous Type",
              "source": "sparse",
              "original_content": "The product allows the upload or transfer of dangerous file types that are automatically processed within its environment."
            },
            "similarity": 64.0983153220014
          },
          {
            "metadata": {
              "doc_id": "22",
              "name": "Improper Limitation of a Pathname to a Restricted Directory ('Path Traversal')",
              "source": "sparse",
              "original_content": "The product uses external input to construct a pathname that is intended to identify a file or directory that is located underneath a restricted parent directory, but the product does not properly neutralize special elements within the pathname that can cause the pathname to resolve to a location that is outside of the restricted directory.",
              "keyphrase_sources": [
                {
                  "id": "version:n/a through 2.4.2",
                  "keyphrase": "n/a through 2.4.2",
                  "type": "version"
                }
              ]
            },
            "similarity": 62.87820094499571
          },
          {
            "metadata": {
              "doc_id": "89",
              "name": "Improper Neutralization of Special Elements used in an SQL Command ('SQL Injection')",
              "source": "sparse",
              "original_content": "The product constructs all or part of an SQL command using externally-influenced input from an upstream component, but it does not neutralize or incorrectly neutralizes special elements that could modify the intended SQL command when it is sent to a downstream component. Without sufficient removal or quoting of SQL syntax in user-controllable inputs, the generated SQL query can cause those inputs to be interpreted as SQL instead of ordinary user data.",
              "keyphrase_sources": [
                {
                  "id": "version:n/a through 2.4.2",
                  "keyphrase": "n/a through 2.4.2",
                  "type": "version"
                }
              ]
            },
            "similarity": 60.73670531786052
          }
        ]
      }
    },
    "keyphrase_mapping": {
      "352": [
        {
          "id": "rootcause:lack of CSRF protection",
          "keyphrase": "lack of CSRF protection",
          "type": "rootcause"
        },
        {
          "id": "weakness:XSS",
          "keyphrase": "XSS",
          "type": "weakness"
        },
        {
          "id": "weakness:cross-site scripting",
          "keyphrase": "cross-site scripting",
          "type": "weakness"
        },
        {
          "id": "product:Julian Weinert // cs&m cSlider",
          "keyphrase": "Julian Weinert // cs&m cSlider",
          "type": "product"
        },
        {
          "id": "version:n/a through 2.4.2",
          "keyphrase": "n/a through 2.4.2",
          "type": "version"
        }
      ],
      "434": [
        {
          "id": "rootcause:lack of CSRF protection",
          "keyphrase": "lack of CSRF protection",
          "type": "rootcause"
        },
        {
          "id": "version:n/a through 2.4.2",
          "keyphrase": "n/a through 2.4.2",
          "type": "version"
        }
      ],
      "79": [
        {
          "id": "rootcause:lack of CSRF protection",
          "keyphrase": "lack of CSRF protection",
          "type": "rootcause"
        },
        {
          "id": "weakness:XSS",
          "keyphrase": "XSS",
          "type": "weakness"
        },
        {
          "id": "weakness:cross-site scripting",
          "keyphrase": "cross-site scripting",
          "type": "weakness"
        },
        {
          "id": "product:Julian Weinert // cs&m cSlider",
          "keyphrase": "Julian Weinert // cs&m cSlider",
          "type": "product"
        },
        {
          "id": "version:n/a through 2.4.2",
          "keyphrase": "n/a through 2.4.2",
          "type": "version"
        }
      ],
      "116": [
        {
          "id": "rootcause:lack of CSRF protection",
          "keyphrase": "lack of CSRF protection",
          "type": "rootcause"
        },
        {
          "id": "weakness:XSS",
          "keyphrase": "XSS",
          "type": "weakness"
        },
        {
          "id": "weakness:cross-site scripting",
          "keyphrase": "cross-site scripting",
          "type": "weakness"
        }
      ],
      "1004": [
        {
          "id": "rootcause:lack of CSRF protection",
          "keyphrase": "lack of CSRF protection",
          "type": "rootcause"
        },
        {
          "id": "weakness:XSS",
          "keyphrase": "XSS",
          "type": "weakness"
        },
        {
          "id": "weakness:cross-site scripting",
          "keyphrase": "cross-site scripting",
          "type": "weakness"
        },
        {
          "id": "product:Julian Weinert // cs&m cSlider",
          "keyphrase": "Julian Weinert // cs&m cSlider",
          "type": "product"
        }
      ],
      "80": [
        {
          "id": "weakness:XSS",
          "keyphrase": "XSS",
          "type": "weakness"
        },
        {
          "id": "weakness:cross-site scripting",
          "keyphrase": "cross-site scripting",
          "type": "weakness"
        }
      ],
      "665": [
        {
          "id": "product:Julian Weinert // cs&m cSlider",
          "keyphrase": "Julian Weinert // cs&m cSlider",
          "type": "product"
        }
      ],
      "657": [
        {
          "id": "product:Julian Weinert // cs&m cSlider",
          "keyphrase": "Julian Weinert // cs&m cSlider",
          "type": "product"
        }
      ],
      "22": [
        {
          "id": "version:n/a through 2.4.2",
          "keyphrase": "n/a through 2.4.2",
          "type": "version"
        }
      ],
      "89": [
        {
          "id": "version:n/a through 2.4.2",
          "keyphrase": "n/a through 2.4.2",
          "type": "version"
        }
      ]
    },
    "relevant_cwes": [
      {
        "metadata": {
          "doc_id": "352",
          "name": "Cross-Site Request Forgery (CSRF)",
          "source": "sparse",
          "original_content": "The web application does not, or can not, sufficiently verify whether a well-formed, valid, consistent request was intentionally provided by the user who submitted the request.",
          "keyphrase_sources": [
            {
              "id": "rootcause:lack of CSRF protection",
              "keyphrase": "lack of CSRF protection",
              "type": "rootcause"
            },
            {
              "id": "weakness:XSS",
              "keyphrase": "XSS",
              "type": "weakness"
            },
            {
              "id": "weakness:cross-site scripting",
              "keyphrase": "cross-site scripting",
              "type": "weakness"
            },
            {
              "id": "product:Julian Weinert // cs&m cSlider",
              "keyphrase": "Julian Weinert // cs&m cSlider",
              "type": "product"
            },
            {
              "id": "version:n/a through 2.4.2",
              "keyphrase": "n/a through 2.4.2",
              "type": "version"
            }
          ]
        },
        "similarity": 273.54246680874985
      },
      {
        "metadata": {
          "doc_id": "434",
          "name": "Unrestricted Upload of File with Dangerous Type",
          "source": "sparse",
          "original_content": "The product allows the upload or transfer of dangerous file types that are automatically processed within its environment.",
          "keyphrase_sources": [
            {
              "id": "rootcause:lack of CSRF protection",
              "keyphrase": "lack of CSRF protection",
              "type": "rootcause"
            },
            {
              "id": "version:n/a through 2.4.2",
              "keyphrase": "n/a through 2.4.2",
              "type": "version"
            }
          ]
        },
        "similarity": 202.19471575026046
      },
      {
        "metadata": {
          "doc_id": "79",
          "name": "Improper Neutralization of Input During Web Page Generation ('Cross-site Scripting')",
          "source": "sparse",
          "original_content": "The product does not neutralize or incorrectly neutralizes user-controllable input before it is placed in output that is used as a web page that is served to other users.",
          "keyphrase_sources": [
            {
              "id": "rootcause:lack of CSRF protection",
              "keyphrase": "lack of CSRF protection",
              "type": "rootcause"
            },
            {
              "id": "weakness:XSS",
              "keyphrase": "XSS",
              "type": "weakness"
            },
            {
              "id": "weakness:cross-site scripting",
              "keyphrase": "cross-site scripting",
              "type": "weakness"
            },
            {
              "id": "product:Julian Weinert // cs&m cSlider",
              "keyphrase": "Julian Weinert // cs&m cSlider",
              "type": "product"
            },
            {
              "id": "version:n/a through 2.4.2",
              "keyphrase": "n/a through 2.4.2",
              "type": "version"
            }
          ]
        },
        "similarity": 197.9994555901746
      },
      {
        "metadata": {
          "doc_id": "116",
          "name": "Improper Encoding or Escaping of Output",
          "source": "sparse",
          "original_content": "The product prepares a structured message for communication with another component, but encoding or escaping of the data is either missing or done incorrectly. As a result, the intended structure of the message is not preserved.",
          "keyphrase_sources": [
            {
              "id": "rootcause:lack of CSRF protection",
              "keyphrase": "lack of CSRF protection",
              "type": "rootcause"
            },
            {
              "id": "weakness:XSS",
              "keyphrase": "XSS",
              "type": "weakness"
            },
            {
              "id": "weakness:cross-site scripting",
              "keyphrase": "cross-site scripting",
              "type": "weakness"
            }
          ]
        },
        "similarity": 194.61559497089291
      },
      {
        "metadata": {
          "doc_id": "1004",
          "name": "Sensitive Cookie Without 'HttpOnly' Flag",
          "source": "sparse",
          "original_content": "The product uses a cookie to store sensitive information, but the cookie is not marked with the HttpOnly flag.",
          "keyphrase_sources": [
            {
              "id": "rootcause:lack of CSRF protection",
              "keyphrase": "lack of CSRF protection",
              "type": "rootcause"
            },
            {
              "id": "weakness:XSS",
              "keyphrase": "XSS",
              "type": "weakness"
            },
            {
              "id": "weakness:cross-site scripting",
              "keyphrase": "cross-site scripting",
              "type": "weakness"
            },
            {
              "id": "product:Julian Weinert // cs&m cSlider",
              "keyphrase": "Julian Weinert // cs&m cSlider",
              "type": "product"
            }
          ]
        },
        "similarity": 180.86413440121214
      },
      {
        "metadata": {
          "doc_id": "80",
          "name": "Improper Neutralization of Script-Related HTML Tags in a Web Page (Basic XSS)",
          "source": "sparse",
          "original_content": "The product receives input from an upstream component, but it does not neutralize or incorrectly neutralizes special characters such as \"<\", \">\", and \"&\" that could be interpreted as web-scripting elements when they are sent to a downstream component that processes web pages.",
          "keyphrase_sources": [
            {
              "id": "weakness:XSS",
              "keyphrase": "XSS",
              "type": "weakness"
            },
            {
              "id": "weakness:cross-site scripting",
              "keyphrase": "cross-site scripting",
              "type": "weakness"
            }
          ]
        },
        "similarity": 141.00406479971866
      },
      {
        "metadata": {
          "doc_id": "22",
          "name": "Improper Limitation of a Pathname to a Restricted Directory ('Path Traversal')",
          "source": "sparse",
          "original_content": "The product uses external input to construct a pathname that is intended to identify a file or directory that is located underneath a restricted parent directory, but the product does not properly neutralize special elements within the pathname that can cause the pathname to resolve to a location that is outside of the restricted directory.",
          "keyphrase_sources": [
            {
              "id": "version:n/a through 2.4.2",
              "keyphrase": "n/a through 2.4.2",
              "type": "version"
            }
          ]
        },
        "similarity": 62.87820094499571
      },
      {
        "metadata": {
          "doc_id": "89",
          "name": "Improper Neutralization of Special Elements used in an SQL Command ('SQL Injection')",
          "source": "sparse",
          "original_content": "The product constructs all or part of an SQL command using externally-influenced input from an upstream component, but it does not neutralize or incorrectly neutralizes special elements that could modify the intended SQL command when it is sent to a downstream component. Without sufficient removal or quoting of SQL syntax in user-controllable inputs, the generated SQL query can cause those inputs to be interpreted as SQL instead of ordinary user data.",
          "keyphrase_sources": [
            {
              "id": "version:n/a through 2.4.2",
              "keyphrase": "n/a through 2.4.2",
              "type": "version"
            }
          ]
        },
        "similarity": 60.73670531786052
      },
      {
        "metadata": {
          "doc_id": "665",
          "name": "Improper Initialization",
          "source": "sparse",
          "original_content": "The product does not initialize or incorrectly initializes a resource, which might leave the resource in an unexpected state when it is accessed or used.",
          "keyphrase_sources": [
            {
              "id": "product:Julian Weinert // cs&m cSlider",
              "keyphrase": "Julian Weinert // cs&m cSlider",
              "type": "product"
            }
          ]
        },
        "similarity": 58.750202901555554
      },
      {
        "metadata": {
          "doc_id": "657",
          "name": "Violation of Secure Design Principles",
          "source": "sparse",
          "original_content": "The product violates well-established principles for secure design.",
          "keyphrase_sources": [
            {
              "id": "product:Julian Weinert // cs&m cSlider",
              "keyphrase": "Julian Weinert // cs&m cSlider",
              "type": "product"
            }
          ]
        },
        "similarity": 44.804652723461736
      }
    ],
    "enhanced_query": "# Vulnerability Description\n\n    Cross-Site Request Forgery (CSRF) vulnerability in Julian Weinert // cs&m cSlider allows Stored **XSS**.This issue affects cSlider from n/a through 2.4.2.\n\n    # Keyphrase-Specific CWE Analysis\n    This vulnerability contains multiple keyphrases that may map to different CWEs. \n    Please analyze each keyphrase separately and determine the most appropriate CWE(s) for each.\n\n    ## ROOTCAUSE: 'lack of CSRF protection'\n\nRelevant CWEs for this ROOTCAUSE:\n\n### 1. CWE-352: Cross-Site Request Forgery (CSRF) (Score: 273.54)\n\nThe web application does not, or can not, sufficiently verify whether a well-formed, valid, consistent request was intentionally provided by the user who submitted the request....\n\n### 2. CWE-434: Unrestricted Upload of File with Dangerous Type (Score: 202.19)\n\nThe product allows the upload or transfer of dangerous file types that are automatically processed within its environment....\n\n### 3. CWE-79: Improper Neutralization of Input During Web Page Generation ('Cross-site Scripting') (Score: 198.00)\n\nThe product does not neutralize or incorrectly neutralizes user-controllable input before it is placed in output that is used as a web page that is served to other users....\n\n### 4. CWE-116: Improper Encoding or Escaping of Output (Score: 194.62)\n\nThe product prepares a structured message for communication with another component, but encoding or escaping of the data is either missing or done incorrectly. As a result, the intended structure of the message is not preserved....\n\n### 5. CWE-1004: Sensitive Cookie Without 'HttpOnly' Flag (Score: 180.86)\n\nThe product uses a cookie to store sensitive information, but the cookie is not marked with the HttpOnly flag....\n\n## WEAKNESS: 'XSS'\n\nRelevant CWEs for this WEAKNESS:\n\n### 1. CWE-352: Cross-Site Request Forgery (CSRF) (Score: 273.54)\n\nThe web application does not, or can not, sufficiently verify whether a well-formed, valid, consistent request was intentionally provided by the user who submitted the request....\n\n### 2. CWE-79: Improper Neutralization of Input During Web Page Generation ('Cross-site Scripting') (Score: 198.00)\n\nThe product does not neutralize or incorrectly neutralizes user-controllable input before it is placed in output that is used as a web page that is served to other users....\n\n### 3. CWE-116: Improper Encoding or Escaping of Output (Score: 194.62)\n\nThe product prepares a structured message for communication with another component, but encoding or escaping of the data is either missing or done incorrectly. As a result, the intended structure of the message is not preserved....\n\n### 4. CWE-1004: Sensitive Cookie Without 'HttpOnly' Flag (Score: 180.86)\n\nThe product uses a cookie to store sensitive information, but the cookie is not marked with the HttpOnly flag....\n\n### 5. CWE-80: Improper Neutralization of Script-Related HTML Tags in a Web Page (Basic XSS) (Score: 141.00)\n\nThe product receives input from an upstream component, but it does not neutralize or incorrectly neutralizes special characters such as \"<\", \">\", and \"&\" that could be interpreted as web-scripting elements when they are sent to a downstream component that processes web pages....\n\n## WEAKNESS: 'cross-site scripting'\n\nRelevant CWEs for this WEAKNESS:\n\n### 1. CWE-352: Cross-Site Request Forgery (CSRF) (Score: 273.54)\n\nThe web application does not, or can not, sufficiently verify whether a well-formed, valid, consistent request was intentionally provided by the user who submitted the request....\n\n### 2. CWE-79: Improper Neutralization of Input During Web Page Generation ('Cross-site Scripting') (Score: 198.00)\n\nThe product does not neutralize or incorrectly neutralizes user-controllable input before it is placed in output that is used as a web page that is served to other users....\n\n### 3. CWE-116: Improper Encoding or Escaping of Output (Score: 194.62)\n\nThe product prepares a structured message for communication with another component, but encoding or escaping of the data is either missing or done incorrectly. As a result, the intended structure of the message is not preserved....\n\n### 4. CWE-1004: Sensitive Cookie Without 'HttpOnly' Flag (Score: 180.86)\n\nThe product uses a cookie to store sensitive information, but the cookie is not marked with the HttpOnly flag....\n\n### 5. CWE-80: Improper Neutralization of Script-Related HTML Tags in a Web Page (Basic XSS) (Score: 141.00)\n\nThe product receives input from an upstream component, but it does not neutralize or incorrectly neutralizes special characters such as \"<\", \">\", and \"&\" that could be interpreted as web-scripting elements when they are sent to a downstream component that processes web pages....\n\n## PRODUCT: 'Julian Weinert // cs&m cSlider'\n\nRelevant CWEs for this PRODUCT:\n\n### 1. CWE-352: Cross-Site Request Forgery (CSRF) (Score: 273.54)\n\nThe web application does not, or can not, sufficiently verify whether a well-formed, valid, consistent request was intentionally provided by the user who submitted the request....\n\n### 2. CWE-79: Improper Neutralization of Input During Web Page Generation ('Cross-site Scripting') (Score: 198.00)\n\nThe product does not neutralize or incorrectly neutralizes user-controllable input before it is placed in output that is used as a web page that is served to other users....\n\n### 3. CWE-1004: Sensitive Cookie Without 'HttpOnly' Flag (Score: 180.86)\n\nThe product uses a cookie to store sensitive information, but the cookie is not marked with the HttpOnly flag....\n\n### 4. CWE-665: Improper Initialization (Score: 58.75)\n\nThe product does not initialize or incorrectly initializes a resource, which might leave the resource in an unexpected state when it is accessed or used....\n\n### 5. CWE-657: Violation of Secure Design Principles (Score: 44.80)\n\nThe product violates well-established principles for secure design....\n\n## VERSION: 'n/a through 2.4.2'\n\nRelevant CWEs for this VERSION:\n\n### 1. CWE-352: Cross-Site Request Forgery (CSRF) (Score: 273.54)\n\nThe web application does not, or can not, sufficiently verify whether a well-formed, valid, consistent request was intentionally provided by the user who submitted the request....\n\n### 2. CWE-434: Unrestricted Upload of File with Dangerous Type (Score: 202.19)\n\nThe product allows the upload or transfer of dangerous file types that are automatically processed within its environment....\n\n### 3. CWE-79: Improper Neutralization of Input During Web Page Generation ('Cross-site Scripting') (Score: 198.00)\n\nThe product does not neutralize or incorrectly neutralizes user-controllable input before it is placed in output that is used as a web page that is served to other users....\n\n### 4. CWE-22: Improper Limitation of a Pathname to a Restricted Directory ('Path Traversal') (Score: 62.88)\n\nThe product uses external input to construct a pathname that is intended to identify a file or directory that is located underneath a restricted parent directory, but the product does not properly neutralize special elements within the pathname that can cause the pathname to resolve to a location th...\n\n### 5. CWE-89: Improper Neutralization of Special Elements used in an SQL Command ('SQL Injection') (Score: 60.74)\n\nThe product constructs all or part of an SQL command using externally-influenced input from an upstream component, but it does not neutralize or incorrectly neutralizes special elements that could modify the intended SQL command when it is sent to a downstream component. Without sufficient removal o...\n\n\n    # Analysis Instructions\n    1. For each keyphrase, identify the most appropriate CWE(s) that represent the weakness.\n    2. Consider how the different keyphrases might relate to each other in the vulnerability chain.\n    3. Provide a final determination of primary CWE(s) and any secondary CWEs.\n    4. Format your response using the standard analysis template.\n\n    Please analyze how these different weaknesses interact and provide a comprehensive CWE classification.\n    "
  },
  "retrieval_time": 1.0377197265625
}