{
  "vulnerability_info": "VulnerabilityInfo(cve_id='CVE-2024-43357', description='ECMA-262 is the language specification for the scripting language ECMAScript. A problem in the ECMAScript (JavaScript) specification of async generators, introduced by a May 2021 spec refactor, may lead to mis-implementation in a way that could present as a security vulnerability, such as **type confusion** and pointer dereference. The internal async generator machinery calls regular promise resolver functions on IteratorResult (`{ done, value }`) objects that it creates, assuming that the IteratorResult objects will not be then-ables. Unfortunately, these IteratorResult objects inherit from `Object.prototype`, so these IteratorResult objects can be made then-able, triggering arbitrary behaviour, including re-entering the async generator machinery in a way that violates some internal invariants. The ECMAScript specification is a living standard and the issue has been addressed at the time of this advisorys public disclosure. JavaScript engine implementors should refer to the latest specification and update their implementations to comply with the `AsyncGenerator` section. ## References - https//github.com/tc39/ecma262/commit/1e24a286d0a327d08e1154926b3ee79820232727 - https//bugzilla.mozilla.org/show_bug.cgi?id=1901411 - https//github.com/boa-dev/boa/security/advisories/GHSA-f67q-wr6w-23jq - https//bugs.webkit.org/show_bug.cgi?id=275407 - https//issues.chromium.org/issues/346692561 - https//www.cve.org/CVERecord?id=CVE-2024-7652', key_phrases={'rootcause': ['mis-implementation of async generators', 'type confusion'], 'weakness': 'type confusion and pointer dereference', 'impact': 'arbitrary behaviour', 'vector': '', 'attacker': '', 'product': 'ECMAScript', 'version': '', 'component': ''}, reference_content='```json\\n{\\n  \"guidelines\": [\\n    \"1. First verify if the content relates to the CVE specified based on the official description\",\\n    \"2. If the content does not relate to this CVE, respond with \\\\\"UNRELATED\\\\\"\",\\n    \"3. If no useful vulnerability information is found, respond with \\\\\"NOINFO\\\\\"\",\\n    \"4. For relevant content, extract:\",\\n    \"   - Root cause of vulnerability\",\\n    \"   - Weaknesses/vulnerabilities present\",\\n    \"   - Impact of exploitation\",\\n    \"   - Attack vectors\",\\n    \"   - Required attacker capabilities/position\",\\n    \"\",\\n    \"Additional instructions:\",\\n    \"- Preserve original technical details and descriptions\",\\n    \"- Remove unrelated content\",\\n    \"- Translate non-English content to English\",\\n    \"- Note if the content provides more detail than the official CVE description\"\\n  ],\\n  \"vulnerability\": {\\n    \"root_cause\": \"A problem in the ECMAScript (JavaScript) specification of async generators, introduced by a May 2021 spec refactor may lead to mis-implementation. The internal async generator machinery calls regular promise resolver functions on IteratorResult objects that it creates, assuming that the IteratorResult objects will not be then-ables. Unfortunately, these IteratorResult objects inherit from `Object.prototype`, so these IteratorResult objects can be made then-able, triggering arbitrary behaviour, including re-entering the async generator machinery in a way that violates some internal invariants.\",\\n    \"weaknesses\": [\\n      \"CWE-248\",\\n      \"CWE-476\",\\n      \"CWE-843\"\\n    ],\\n    \"impact\": \"Type confusion, pointer dereference, and uncaught exception.\",\\n    \"attack_vectors\": \"A carefully constructed code could trigger a state transition from a getter method for the promise\\'s `then` property, which causes the engine to fail an assertion of this assumption, causing an uncaught exception.\",\\n    \"attacker_capabilities\": \"An attacker must be able to provide ECMAScript code.\"\\n  },\\n  \"CVE\": \"CVE-2024-43357\",\\n  \"type\": \"relevant\"\\n}\\n```', similar_info={'cwe_distribution': {}, 'cwe_consensus': '', 'similarity_stats': {'thresholds': [], 'total_samples_by_threshold': {}, 'top_cwes_by_threshold': {}}}, similarity_summary=SimilarityInsight(consensus_cwe='', top_cwes=[], confidence_levels={}, total_samples=0), analysis='', analysis_with_relationships='', criticism='', resolution='', relevant_cwes=[{'metadata': {'doc_id': '787', 'name': 'Out-of-bounds Write', 'source': 'sparse', 'original_content': 'The product writes data past the end, or before the beginning, of the intended buffer.', 'keyphrase_sources': [{'id': 'rootcause:mis-implementation of async generators', 'keyphrase': 'mis-implementation of async generators', 'type': 'rootcause'}, {'id': 'rootcause:type confusion', 'keyphrase': 'type confusion', 'type': 'rootcause'}, {'id': 'weakness:type confusion and pointer dereference', 'keyphrase': 'type confusion and pointer dereference', 'type': 'weakness'}, {'id': 'impact:arbitrary behaviour', 'keyphrase': 'arbitrary behaviour', 'type': 'impact'}, {'id': 'product:ECMAScript', 'keyphrase': 'ECMAScript', 'type': 'product'}]}, 'similarity': np.float64(836.410050343077)}, {'metadata': {'doc_id': '1333', 'name': 'Inefficient Regular Expression Complexity', 'source': 'sparse', 'original_content': 'The product uses a regular expression with an inefficient, possibly exponential worst-case computational complexity that consumes excessive CPU cycles.', 'keyphrase_sources': [{'id': 'rootcause:mis-implementation of async generators', 'keyphrase': 'mis-implementation of async generators', 'type': 'rootcause'}, {'id': 'rootcause:type confusion', 'keyphrase': 'type confusion', 'type': 'rootcause'}, {'id': 'weakness:type confusion and pointer dereference', 'keyphrase': 'type confusion and pointer dereference', 'type': 'weakness'}, {'id': 'impact:arbitrary behaviour', 'keyphrase': 'arbitrary behaviour', 'type': 'impact'}, {'id': 'product:ECMAScript', 'keyphrase': 'ECMAScript', 'type': 'product'}]}, 'similarity': np.float64(836.3840877104365)}, {'metadata': {'doc_id': '1284', 'name': 'Improper Validation of Specified Quantity in Input', 'source': 'sparse', 'original_content': 'The product receives input that is expected to specify a quantity (such as size or length), but it does not validate or incorrectly validates that the quantity has the required properties.', 'keyphrase_sources': [{'id': 'rootcause:mis-implementation of async generators', 'keyphrase': 'mis-implementation of async generators', 'type': 'rootcause'}, {'id': 'rootcause:type confusion', 'keyphrase': 'type confusion', 'type': 'rootcause'}, {'id': 'weakness:type confusion and pointer dereference', 'keyphrase': 'type confusion and pointer dereference', 'type': 'weakness'}, {'id': 'impact:arbitrary behaviour', 'keyphrase': 'arbitrary behaviour', 'type': 'impact'}, {'id': 'product:ECMAScript', 'keyphrase': 'ECMAScript', 'type': 'product'}]}, 'similarity': np.float64(834.8702245027873)}, {'metadata': {'doc_id': '335', 'name': 'Incorrect Usage of Seeds in Pseudo-Random Number Generator (PRNG)', 'source': 'sparse', 'original_content': 'The product uses a Pseudo-Random Number Generator (PRNG) but does not correctly manage seeds.', 'keyphrase_sources': [{'id': 'rootcause:mis-implementation of async generators', 'keyphrase': 'mis-implementation of async generators', 'type': 'rootcause'}, {'id': 'rootcause:type confusion', 'keyphrase': 'type confusion', 'type': 'rootcause'}, {'id': 'product:ECMAScript', 'keyphrase': 'ECMAScript', 'type': 'product'}]}, 'similarity': np.float64(828.6016465286084)}, {'metadata': {'doc_id': '1321', 'name': \"Improperly Controlled Modification of Object Prototype Attributes ('Prototype Pollution')\", 'source': 'sparse', 'original_content': 'The product receives input from an upstream component that specifies attributes that are to be initialized or updated in an object, but it does not properly control modifications of attributes of the object prototype.', 'keyphrase_sources': [{'id': 'rootcause:mis-implementation of async generators', 'keyphrase': 'mis-implementation of async generators', 'type': 'rootcause'}, {'id': 'impact:arbitrary behaviour', 'keyphrase': 'arbitrary behaviour', 'type': 'impact'}]}, 'similarity': np.float64(808.4968338500505)}, {'metadata': {'doc_id': '822', 'name': 'Untrusted Pointer Dereference', 'source': 'sparse', 'original_content': 'The product obtains a value from an untrusted source, converts this value to a pointer, and dereferences the resulting pointer.', 'keyphrase_sources': [{'id': 'weakness:type confusion and pointer dereference', 'keyphrase': 'type confusion and pointer dereference', 'type': 'weakness'}]}, 'similarity': np.float64(805.1223000171516)}, {'metadata': {'doc_id': '476', 'name': 'NULL Pointer Dereference', 'source': 'sparse', 'original_content': 'The product dereferences a pointer that it expects to be valid but is NULL.', 'keyphrase_sources': [{'id': 'weakness:type confusion and pointer dereference', 'keyphrase': 'type confusion and pointer dereference', 'type': 'weakness'}]}, 'similarity': np.float64(804.7464517378554)}, {'metadata': {'doc_id': '1188', 'name': 'Initialization of a Resource with an Insecure Default', 'source': 'sparse', 'original_content': 'The product initializes or sets a resource with a default that is intended to be changed by the administrator, but the default is not secure.', 'keyphrase_sources': [{'id': 'rootcause:type confusion', 'keyphrase': 'type confusion', 'type': 'rootcause'}, {'id': 'impact:arbitrary behaviour', 'keyphrase': 'arbitrary behaviour', 'type': 'impact'}, {'id': 'product:ECMAScript', 'keyphrase': 'ECMAScript', 'type': 'product'}]}, 'similarity': np.float64(787.1569825666694)}], identified_cwes={'analyzer': [], 'critic_additional': []})",
  "retrieval_results": {
    "has_multiple_keyphrases": true,
    "keyphrase_cwe_sets": {
      "rootcause:mis-implementation of async generators": {
        "keyphrase": "mis-implementation of async generators",
        "type": "rootcause",
        "cwes": [
          {
            "metadata": {
              "doc_id": "787",
              "name": "Out-of-bounds Write",
              "source": "sparse",
              "original_content": "The product writes data past the end, or before the beginning, of the intended buffer.",
              "keyphrase_sources": [
                {
                  "id": "rootcause:mis-implementation of async generators",
                  "keyphrase": "mis-implementation of async generators",
                  "type": "rootcause"
                },
                {
                  "id": "rootcause:type confusion",
                  "keyphrase": "type confusion",
                  "type": "rootcause"
                },
                {
                  "id": "weakness:type confusion and pointer dereference",
                  "keyphrase": "type confusion and pointer dereference",
                  "type": "weakness"
                },
                {
                  "id": "impact:arbitrary behaviour",
                  "keyphrase": "arbitrary behaviour",
                  "type": "impact"
                },
                {
                  "id": "product:ECMAScript",
                  "keyphrase": "ECMAScript",
                  "type": "product"
                }
              ]
            },
            "similarity": 836.410050343077
          },
          {
            "metadata": {
              "doc_id": "1333",
              "name": "Inefficient Regular Expression Complexity",
              "source": "sparse",
              "original_content": "The product uses a regular expression with an inefficient, possibly exponential worst-case computational complexity that consumes excessive CPU cycles.",
              "keyphrase_sources": [
                {
                  "id": "rootcause:mis-implementation of async generators",
                  "keyphrase": "mis-implementation of async generators",
                  "type": "rootcause"
                },
                {
                  "id": "rootcause:type confusion",
                  "keyphrase": "type confusion",
                  "type": "rootcause"
                },
                {
                  "id": "weakness:type confusion and pointer dereference",
                  "keyphrase": "type confusion and pointer dereference",
                  "type": "weakness"
                },
                {
                  "id": "impact:arbitrary behaviour",
                  "keyphrase": "arbitrary behaviour",
                  "type": "impact"
                },
                {
                  "id": "product:ECMAScript",
                  "keyphrase": "ECMAScript",
                  "type": "product"
                }
              ]
            },
            "similarity": 836.3840877104365
          },
          {
            "metadata": {
              "doc_id": "1284",
              "name": "Improper Validation of Specified Quantity in Input",
              "source": "sparse",
              "original_content": "The product receives input that is expected to specify a quantity (such as size or length), but it does not validate or incorrectly validates that the quantity has the required properties.",
              "keyphrase_sources": [
                {
                  "id": "rootcause:mis-implementation of async generators",
                  "keyphrase": "mis-implementation of async generators",
                  "type": "rootcause"
                },
                {
                  "id": "rootcause:type confusion",
                  "keyphrase": "type confusion",
                  "type": "rootcause"
                },
                {
                  "id": "weakness:type confusion and pointer dereference",
                  "keyphrase": "type confusion and pointer dereference",
                  "type": "weakness"
                },
                {
                  "id": "impact:arbitrary behaviour",
                  "keyphrase": "arbitrary behaviour",
                  "type": "impact"
                },
                {
                  "id": "product:ECMAScript",
                  "keyphrase": "ECMAScript",
                  "type": "product"
                }
              ]
            },
            "similarity": 834.8702245027873
          },
          {
            "metadata": {
              "doc_id": "335",
              "name": "Incorrect Usage of Seeds in Pseudo-Random Number Generator (PRNG)",
              "source": "sparse",
              "original_content": "The product uses a Pseudo-Random Number Generator (PRNG) but does not correctly manage seeds.",
              "keyphrase_sources": [
                {
                  "id": "rootcause:mis-implementation of async generators",
                  "keyphrase": "mis-implementation of async generators",
                  "type": "rootcause"
                },
                {
                  "id": "rootcause:type confusion",
                  "keyphrase": "type confusion",
                  "type": "rootcause"
                },
                {
                  "id": "product:ECMAScript",
                  "keyphrase": "ECMAScript",
                  "type": "product"
                }
              ]
            },
            "similarity": 828.6016465286084
          },
          {
            "metadata": {
              "doc_id": "1321",
              "name": "Improperly Controlled Modification of Object Prototype Attributes ('Prototype Pollution')",
              "source": "sparse",
              "original_content": "The product receives input from an upstream component that specifies attributes that are to be initialized or updated in an object, but it does not properly control modifications of attributes of the object prototype.",
              "keyphrase_sources": [
                {
                  "id": "rootcause:mis-implementation of async generators",
                  "keyphrase": "mis-implementation of async generators",
                  "type": "rootcause"
                },
                {
                  "id": "impact:arbitrary behaviour",
                  "keyphrase": "arbitrary behaviour",
                  "type": "impact"
                }
              ]
            },
            "similarity": 808.4968338500505
          }
        ]
      },
      "rootcause:type confusion": {
        "keyphrase": "type confusion",
        "type": "rootcause",
        "cwes": [
          {
            "metadata": {
              "doc_id": "1333",
              "name": "Inefficient Regular Expression Complexity",
              "source": "sparse",
              "original_content": "The product uses a regular expression with an inefficient, possibly exponential worst-case computational complexity that consumes excessive CPU cycles."
            },
            "similarity": 816.6465380373404
          },
          {
            "metadata": {
              "doc_id": "787",
              "name": "Out-of-bounds Write",
              "source": "sparse",
              "original_content": "The product writes data past the end, or before the beginning, of the intended buffer."
            },
            "similarity": 815.5541357444195
          },
          {
            "metadata": {
              "doc_id": "1284",
              "name": "Improper Validation of Specified Quantity in Input",
              "source": "sparse",
              "original_content": "The product receives input that is expected to specify a quantity (such as size or length), but it does not validate or incorrectly validates that the quantity has the required properties."
            },
            "similarity": 808.8638988004374
          },
          {
            "metadata": {
              "doc_id": "335",
              "name": "Incorrect Usage of Seeds in Pseudo-Random Number Generator (PRNG)",
              "source": "sparse",
              "original_content": "The product uses a Pseudo-Random Number Generator (PRNG) but does not correctly manage seeds."
            },
            "similarity": 802.5388558482582
          },
          {
            "metadata": {
              "doc_id": "1188",
              "name": "Initialization of a Resource with an Insecure Default",
              "source": "sparse",
              "original_content": "The product initializes or sets a resource with a default that is intended to be changed by the administrator, but the default is not secure.",
              "keyphrase_sources": [
                {
                  "id": "rootcause:type confusion",
                  "keyphrase": "type confusion",
                  "type": "rootcause"
                },
                {
                  "id": "impact:arbitrary behaviour",
                  "keyphrase": "arbitrary behaviour",
                  "type": "impact"
                },
                {
                  "id": "product:ECMAScript",
                  "keyphrase": "ECMAScript",
                  "type": "product"
                }
              ]
            },
            "similarity": 787.1569825666694
          }
        ]
      },
      "weakness:type confusion and pointer dereference": {
        "keyphrase": "type confusion and pointer dereference",
        "type": "weakness",
        "cwes": [
          {
            "metadata": {
              "doc_id": "787",
              "name": "Out-of-bounds Write",
              "source": "sparse",
              "original_content": "The product writes data past the end, or before the beginning, of the intended buffer."
            },
            "similarity": 811.7025127502652
          },
          {
            "metadata": {
              "doc_id": "822",
              "name": "Untrusted Pointer Dereference",
              "source": "sparse",
              "original_content": "The product obtains a value from an untrusted source, converts this value to a pointer, and dereferences the resulting pointer.",
              "keyphrase_sources": [
                {
                  "id": "weakness:type confusion and pointer dereference",
                  "keyphrase": "type confusion and pointer dereference",
                  "type": "weakness"
                }
              ]
            },
            "similarity": 805.1223000171516
          },
          {
            "metadata": {
              "doc_id": "476",
              "name": "NULL Pointer Dereference",
              "source": "sparse",
              "original_content": "The product dereferences a pointer that it expects to be valid but is NULL.",
              "keyphrase_sources": [
                {
                  "id": "weakness:type confusion and pointer dereference",
                  "keyphrase": "type confusion and pointer dereference",
                  "type": "weakness"
                }
              ]
            },
            "similarity": 804.7464517378554
          },
          {
            "metadata": {
              "doc_id": "1333",
              "name": "Inefficient Regular Expression Complexity",
              "source": "sparse",
              "original_content": "The product uses a regular expression with an inefficient, possibly exponential worst-case computational complexity that consumes excessive CPU cycles."
            },
            "similarity": 780.893995699843
          },
          {
            "metadata": {
              "doc_id": "1284",
              "name": "Improper Validation of Specified Quantity in Input",
              "source": "sparse",
              "original_content": "The product receives input that is expected to specify a quantity (such as size or length), but it does not validate or incorrectly validates that the quantity has the required properties."
            },
            "similarity": 780.2886873801006
          }
        ]
      },
      "impact:arbitrary behaviour": {
        "keyphrase": "arbitrary behaviour",
        "type": "impact",
        "cwes": [
          {
            "metadata": {
              "doc_id": "787",
              "name": "Out-of-bounds Write",
              "source": "sparse",
              "original_content": "The product writes data past the end, or before the beginning, of the intended buffer."
            },
            "similarity": 272.76447165193764
          },
          {
            "metadata": {
              "doc_id": "1333",
              "name": "Inefficient Regular Expression Complexity",
              "source": "sparse",
              "original_content": "The product uses a regular expression with an inefficient, possibly exponential worst-case computational complexity that consumes excessive CPU cycles."
            },
            "similarity": 271.2828368068828
          },
          {
            "metadata": {
              "doc_id": "1284",
              "name": "Improper Validation of Specified Quantity in Input",
              "source": "sparse",
              "original_content": "The product receives input that is expected to specify a quantity (such as size or length), but it does not validate or incorrectly validates that the quantity has the required properties."
            },
            "similarity": 268.96184505773476
          },
          {
            "metadata": {
              "doc_id": "1188",
              "name": "Initialization of a Resource with an Insecure Default",
              "source": "sparse",
              "original_content": "The product initializes or sets a resource with a default that is intended to be changed by the administrator, but the default is not secure."
            },
            "similarity": 267.7601902958629
          },
          {
            "metadata": {
              "doc_id": "1321",
              "name": "Improperly Controlled Modification of Object Prototype Attributes ('Prototype Pollution')",
              "source": "sparse",
              "original_content": "The product receives input from an upstream component that specifies attributes that are to be initialized or updated in an object, but it does not properly control modifications of attributes of the object prototype."
            },
            "similarity": 265.8396149774462
          }
        ]
      },
      "product:ECMAScript": {
        "keyphrase": "ECMAScript",
        "type": "product",
        "cwes": [
          {
            "metadata": {
              "doc_id": "787",
              "name": "Out-of-bounds Write",
              "source": "sparse",
              "original_content": "The product writes data past the end, or before the beginning, of the intended buffer."
            },
            "similarity": 269.0748690364448
          },
          {
            "metadata": {
              "doc_id": "1333",
              "name": "Inefficient Regular Expression Complexity",
              "source": "sparse",
              "original_content": "The product uses a regular expression with an inefficient, possibly exponential worst-case computational complexity that consumes excessive CPU cycles."
            },
            "similarity": 268.9093426758116
          },
          {
            "metadata": {
              "doc_id": "1284",
              "name": "Improper Validation of Specified Quantity in Input",
              "source": "sparse",
              "original_content": "The product receives input that is expected to specify a quantity (such as size or length), but it does not validate or incorrectly validates that the quantity has the required properties."
            },
            "similarity": 266.7134732608348
          },
          {
            "metadata": {
              "doc_id": "335",
              "name": "Incorrect Usage of Seeds in Pseudo-Random Number Generator (PRNG)",
              "source": "sparse",
              "original_content": "The product uses a Pseudo-Random Number Generator (PRNG) but does not correctly manage seeds."
            },
            "similarity": 264.5027926758462
          },
          {
            "metadata": {
              "doc_id": "1188",
              "name": "Initialization of a Resource with an Insecure Default",
              "source": "sparse",
              "original_content": "The product initializes or sets a resource with a default that is intended to be changed by the administrator, but the default is not secure."
            },
            "similarity": 259.6062328472483
          }
        ]
      }
    },
    "keyphrase_mapping": {
      "787": [
        {
          "id": "rootcause:mis-implementation of async generators",
          "keyphrase": "mis-implementation of async generators",
          "type": "rootcause"
        },
        {
          "id": "rootcause:type confusion",
          "keyphrase": "type confusion",
          "type": "rootcause"
        },
        {
          "id": "weakness:type confusion and pointer dereference",
          "keyphrase": "type confusion and pointer dereference",
          "type": "weakness"
        },
        {
          "id": "impact:arbitrary behaviour",
          "keyphrase": "arbitrary behaviour",
          "type": "impact"
        },
        {
          "id": "product:ECMAScript",
          "keyphrase": "ECMAScript",
          "type": "product"
        }
      ],
      "1333": [
        {
          "id": "rootcause:mis-implementation of async generators",
          "keyphrase": "mis-implementation of async generators",
          "type": "rootcause"
        },
        {
          "id": "rootcause:type confusion",
          "keyphrase": "type confusion",
          "type": "rootcause"
        },
        {
          "id": "weakness:type confusion and pointer dereference",
          "keyphrase": "type confusion and pointer dereference",
          "type": "weakness"
        },
        {
          "id": "impact:arbitrary behaviour",
          "keyphrase": "arbitrary behaviour",
          "type": "impact"
        },
        {
          "id": "product:ECMAScript",
          "keyphrase": "ECMAScript",
          "type": "product"
        }
      ],
      "1284": [
        {
          "id": "rootcause:mis-implementation of async generators",
          "keyphrase": "mis-implementation of async generators",
          "type": "rootcause"
        },
        {
          "id": "rootcause:type confusion",
          "keyphrase": "type confusion",
          "type": "rootcause"
        },
        {
          "id": "weakness:type confusion and pointer dereference",
          "keyphrase": "type confusion and pointer dereference",
          "type": "weakness"
        },
        {
          "id": "impact:arbitrary behaviour",
          "keyphrase": "arbitrary behaviour",
          "type": "impact"
        },
        {
          "id": "product:ECMAScript",
          "keyphrase": "ECMAScript",
          "type": "product"
        }
      ],
      "335": [
        {
          "id": "rootcause:mis-implementation of async generators",
          "keyphrase": "mis-implementation of async generators",
          "type": "rootcause"
        },
        {
          "id": "rootcause:type confusion",
          "keyphrase": "type confusion",
          "type": "rootcause"
        },
        {
          "id": "product:ECMAScript",
          "keyphrase": "ECMAScript",
          "type": "product"
        }
      ],
      "1321": [
        {
          "id": "rootcause:mis-implementation of async generators",
          "keyphrase": "mis-implementation of async generators",
          "type": "rootcause"
        },
        {
          "id": "impact:arbitrary behaviour",
          "keyphrase": "arbitrary behaviour",
          "type": "impact"
        }
      ],
      "1188": [
        {
          "id": "rootcause:type confusion",
          "keyphrase": "type confusion",
          "type": "rootcause"
        },
        {
          "id": "impact:arbitrary behaviour",
          "keyphrase": "arbitrary behaviour",
          "type": "impact"
        },
        {
          "id": "product:ECMAScript",
          "keyphrase": "ECMAScript",
          "type": "product"
        }
      ],
      "822": [
        {
          "id": "weakness:type confusion and pointer dereference",
          "keyphrase": "type confusion and pointer dereference",
          "type": "weakness"
        }
      ],
      "476": [
        {
          "id": "weakness:type confusion and pointer dereference",
          "keyphrase": "type confusion and pointer dereference",
          "type": "weakness"
        }
      ]
    },
    "relevant_cwes": [
      {
        "metadata": {
          "doc_id": "787",
          "name": "Out-of-bounds Write",
          "source": "sparse",
          "original_content": "The product writes data past the end, or before the beginning, of the intended buffer.",
          "keyphrase_sources": [
            {
              "id": "rootcause:mis-implementation of async generators",
              "keyphrase": "mis-implementation of async generators",
              "type": "rootcause"
            },
            {
              "id": "rootcause:type confusion",
              "keyphrase": "type confusion",
              "type": "rootcause"
            },
            {
              "id": "weakness:type confusion and pointer dereference",
              "keyphrase": "type confusion and pointer dereference",
              "type": "weakness"
            },
            {
              "id": "impact:arbitrary behaviour",
              "keyphrase": "arbitrary behaviour",
              "type": "impact"
            },
            {
              "id": "product:ECMAScript",
              "keyphrase": "ECMAScript",
              "type": "product"
            }
          ]
        },
        "similarity": 836.410050343077
      },
      {
        "metadata": {
          "doc_id": "1333",
          "name": "Inefficient Regular Expression Complexity",
          "source": "sparse",
          "original_content": "The product uses a regular expression with an inefficient, possibly exponential worst-case computational complexity that consumes excessive CPU cycles.",
          "keyphrase_sources": [
            {
              "id": "rootcause:mis-implementation of async generators",
              "keyphrase": "mis-implementation of async generators",
              "type": "rootcause"
            },
            {
              "id": "rootcause:type confusion",
              "keyphrase": "type confusion",
              "type": "rootcause"
            },
            {
              "id": "weakness:type confusion and pointer dereference",
              "keyphrase": "type confusion and pointer dereference",
              "type": "weakness"
            },
            {
              "id": "impact:arbitrary behaviour",
              "keyphrase": "arbitrary behaviour",
              "type": "impact"
            },
            {
              "id": "product:ECMAScript",
              "keyphrase": "ECMAScript",
              "type": "product"
            }
          ]
        },
        "similarity": 836.3840877104365
      },
      {
        "metadata": {
          "doc_id": "1284",
          "name": "Improper Validation of Specified Quantity in Input",
          "source": "sparse",
          "original_content": "The product receives input that is expected to specify a quantity (such as size or length), but it does not validate or incorrectly validates that the quantity has the required properties.",
          "keyphrase_sources": [
            {
              "id": "rootcause:mis-implementation of async generators",
              "keyphrase": "mis-implementation of async generators",
              "type": "rootcause"
            },
            {
              "id": "rootcause:type confusion",
              "keyphrase": "type confusion",
              "type": "rootcause"
            },
            {
              "id": "weakness:type confusion and pointer dereference",
              "keyphrase": "type confusion and pointer dereference",
              "type": "weakness"
            },
            {
              "id": "impact:arbitrary behaviour",
              "keyphrase": "arbitrary behaviour",
              "type": "impact"
            },
            {
              "id": "product:ECMAScript",
              "keyphrase": "ECMAScript",
              "type": "product"
            }
          ]
        },
        "similarity": 834.8702245027873
      },
      {
        "metadata": {
          "doc_id": "335",
          "name": "Incorrect Usage of Seeds in Pseudo-Random Number Generator (PRNG)",
          "source": "sparse",
          "original_content": "The product uses a Pseudo-Random Number Generator (PRNG) but does not correctly manage seeds.",
          "keyphrase_sources": [
            {
              "id": "rootcause:mis-implementation of async generators",
              "keyphrase": "mis-implementation of async generators",
              "type": "rootcause"
            },
            {
              "id": "rootcause:type confusion",
              "keyphrase": "type confusion",
              "type": "rootcause"
            },
            {
              "id": "product:ECMAScript",
              "keyphrase": "ECMAScript",
              "type": "product"
            }
          ]
        },
        "similarity": 828.6016465286084
      },
      {
        "metadata": {
          "doc_id": "1321",
          "name": "Improperly Controlled Modification of Object Prototype Attributes ('Prototype Pollution')",
          "source": "sparse",
          "original_content": "The product receives input from an upstream component that specifies attributes that are to be initialized or updated in an object, but it does not properly control modifications of attributes of the object prototype.",
          "keyphrase_sources": [
            {
              "id": "rootcause:mis-implementation of async generators",
              "keyphrase": "mis-implementation of async generators",
              "type": "rootcause"
            },
            {
              "id": "impact:arbitrary behaviour",
              "keyphrase": "arbitrary behaviour",
              "type": "impact"
            }
          ]
        },
        "similarity": 808.4968338500505
      },
      {
        "metadata": {
          "doc_id": "822",
          "name": "Untrusted Pointer Dereference",
          "source": "sparse",
          "original_content": "The product obtains a value from an untrusted source, converts this value to a pointer, and dereferences the resulting pointer.",
          "keyphrase_sources": [
            {
              "id": "weakness:type confusion and pointer dereference",
              "keyphrase": "type confusion and pointer dereference",
              "type": "weakness"
            }
          ]
        },
        "similarity": 805.1223000171516
      },
      {
        "metadata": {
          "doc_id": "476",
          "name": "NULL Pointer Dereference",
          "source": "sparse",
          "original_content": "The product dereferences a pointer that it expects to be valid but is NULL.",
          "keyphrase_sources": [
            {
              "id": "weakness:type confusion and pointer dereference",
              "keyphrase": "type confusion and pointer dereference",
              "type": "weakness"
            }
          ]
        },
        "similarity": 804.7464517378554
      },
      {
        "metadata": {
          "doc_id": "1188",
          "name": "Initialization of a Resource with an Insecure Default",
          "source": "sparse",
          "original_content": "The product initializes or sets a resource with a default that is intended to be changed by the administrator, but the default is not secure.",
          "keyphrase_sources": [
            {
              "id": "rootcause:type confusion",
              "keyphrase": "type confusion",
              "type": "rootcause"
            },
            {
              "id": "impact:arbitrary behaviour",
              "keyphrase": "arbitrary behaviour",
              "type": "impact"
            },
            {
              "id": "product:ECMAScript",
              "keyphrase": "ECMAScript",
              "type": "product"
            }
          ]
        },
        "similarity": 787.1569825666694
      }
    ],
    "enhanced_query": "# Vulnerability Description\n\n    ECMA-262 is the language specification for the scripting language ECMAScript. A problem in the ECMAScript (JavaScript) specification of async generators, introduced by a May 2021 spec refactor, may lead to mis-implementation in a way that could present as a security vulnerability, such as **type confusion** and pointer dereference. The internal async generator machinery calls regular promise resolver functions on IteratorResult (`{ done, value }`) objects that it creates, assuming that the IteratorResult objects will not be then-ables. Unfortunately, these IteratorResult objects inherit from `Object.prototype`, so these IteratorResult objects can be made then-able, triggering arbitrary behaviour, including re-entering the async generator machinery in a way that violates some internal invariants. The ECMAScript specification is a living standard and the issue has been addressed at the time of this advisorys public disclosure. JavaScript engine implementors should refer to the latest specification and update their implementations to comply with the `AsyncGenerator` section. ## References - https//github.com/tc39/ecma262/commit/1e24a286d0a327d08e1154926b3ee79820232727 - https//bugzilla.mozilla.org/show_bug.cgi?id=1901411 - https//github.com/boa-dev/boa/security/advisories/GHSA-f67q-wr6w-23jq - https//bugs.webkit.org/show_bug.cgi?id=275407 - https//issues.chromium.org/issues/346692561 - https//www.cve.org/CVERecord?id=CVE-2024-7652\n\n    # Keyphrase-Specific CWE Analysis\n    This vulnerability contains multiple keyphrases that may map to different CWEs. \n    Please analyze each keyphrase separately and determine the most appropriate CWE(s) for each.\n\n    ## ROOTCAUSE: 'mis-implementation of async generators'\n\nRelevant CWEs for this ROOTCAUSE:\n\n### 1. CWE-787: Out-of-bounds Write (Score: 836.41)\n\nThe product writes data past the end, or before the beginning, of the intended buffer....\n\n### 2. CWE-1333: Inefficient Regular Expression Complexity (Score: 836.38)\n\nThe product uses a regular expression with an inefficient, possibly exponential worst-case computational complexity that consumes excessive CPU cycles....\n\n### 3. CWE-1284: Improper Validation of Specified Quantity in Input (Score: 834.87)\n\nThe product receives input that is expected to specify a quantity (such as size or length), but it does not validate or incorrectly validates that the quantity has the required properties....\n\n### 4. CWE-335: Incorrect Usage of Seeds in Pseudo-Random Number Generator (PRNG) (Score: 828.60)\n\nThe product uses a Pseudo-Random Number Generator (PRNG) but does not correctly manage seeds....\n\n### 5. CWE-1321: Improperly Controlled Modification of Object Prototype Attributes ('Prototype Pollution') (Score: 808.50)\n\nThe product receives input from an upstream component that specifies attributes that are to be initialized or updated in an object, but it does not properly control modifications of attributes of the object prototype....\n\n## ROOTCAUSE: 'type confusion'\n\nRelevant CWEs for this ROOTCAUSE:\n\n### 1. CWE-787: Out-of-bounds Write (Score: 836.41)\n\nThe product writes data past the end, or before the beginning, of the intended buffer....\n\n### 2. CWE-1333: Inefficient Regular Expression Complexity (Score: 836.38)\n\nThe product uses a regular expression with an inefficient, possibly exponential worst-case computational complexity that consumes excessive CPU cycles....\n\n### 3. CWE-1284: Improper Validation of Specified Quantity in Input (Score: 834.87)\n\nThe product receives input that is expected to specify a quantity (such as size or length), but it does not validate or incorrectly validates that the quantity has the required properties....\n\n### 4. CWE-335: Incorrect Usage of Seeds in Pseudo-Random Number Generator (PRNG) (Score: 828.60)\n\nThe product uses a Pseudo-Random Number Generator (PRNG) but does not correctly manage seeds....\n\n### 5. CWE-1188: Initialization of a Resource with an Insecure Default (Score: 787.16)\n\nThe product initializes or sets a resource with a default that is intended to be changed by the administrator, but the default is not secure....\n\n## WEAKNESS: 'type confusion and pointer dereference'\n\nRelevant CWEs for this WEAKNESS:\n\n### 1. CWE-787: Out-of-bounds Write (Score: 836.41)\n\nThe product writes data past the end, or before the beginning, of the intended buffer....\n\n### 2. CWE-1333: Inefficient Regular Expression Complexity (Score: 836.38)\n\nThe product uses a regular expression with an inefficient, possibly exponential worst-case computational complexity that consumes excessive CPU cycles....\n\n### 3. CWE-1284: Improper Validation of Specified Quantity in Input (Score: 834.87)\n\nThe product receives input that is expected to specify a quantity (such as size or length), but it does not validate or incorrectly validates that the quantity has the required properties....\n\n### 4. CWE-822: Untrusted Pointer Dereference (Score: 805.12)\n\nThe product obtains a value from an untrusted source, converts this value to a pointer, and dereferences the resulting pointer....\n\n### 5. CWE-476: NULL Pointer Dereference (Score: 804.75)\n\nThe product dereferences a pointer that it expects to be valid but is NULL....\n\n## IMPACT: 'arbitrary behaviour'\n\nRelevant CWEs for this IMPACT:\n\n### 1. CWE-787: Out-of-bounds Write (Score: 836.41)\n\nThe product writes data past the end, or before the beginning, of the intended buffer....\n\n### 2. CWE-1333: Inefficient Regular Expression Complexity (Score: 836.38)\n\nThe product uses a regular expression with an inefficient, possibly exponential worst-case computational complexity that consumes excessive CPU cycles....\n\n### 3. CWE-1284: Improper Validation of Specified Quantity in Input (Score: 834.87)\n\nThe product receives input that is expected to specify a quantity (such as size or length), but it does not validate or incorrectly validates that the quantity has the required properties....\n\n### 4. CWE-1321: Improperly Controlled Modification of Object Prototype Attributes ('Prototype Pollution') (Score: 808.50)\n\nThe product receives input from an upstream component that specifies attributes that are to be initialized or updated in an object, but it does not properly control modifications of attributes of the object prototype....\n\n### 5. CWE-1188: Initialization of a Resource with an Insecure Default (Score: 787.16)\n\nThe product initializes or sets a resource with a default that is intended to be changed by the administrator, but the default is not secure....\n\n## PRODUCT: 'ECMAScript'\n\nRelevant CWEs for this PRODUCT:\n\n### 1. CWE-787: Out-of-bounds Write (Score: 836.41)\n\nThe product writes data past the end, or before the beginning, of the intended buffer....\n\n### 2. CWE-1333: Inefficient Regular Expression Complexity (Score: 836.38)\n\nThe product uses a regular expression with an inefficient, possibly exponential worst-case computational complexity that consumes excessive CPU cycles....\n\n### 3. CWE-1284: Improper Validation of Specified Quantity in Input (Score: 834.87)\n\nThe product receives input that is expected to specify a quantity (such as size or length), but it does not validate or incorrectly validates that the quantity has the required properties....\n\n### 4. CWE-335: Incorrect Usage of Seeds in Pseudo-Random Number Generator (PRNG) (Score: 828.60)\n\nThe product uses a Pseudo-Random Number Generator (PRNG) but does not correctly manage seeds....\n\n### 5. CWE-1188: Initialization of a Resource with an Insecure Default (Score: 787.16)\n\nThe product initializes or sets a resource with a default that is intended to be changed by the administrator, but the default is not secure....\n\n\n    # Analysis Instructions\n    1. For each keyphrase, identify the most appropriate CWE(s) that represent the weakness.\n    2. Consider how the different keyphrases might relate to each other in the vulnerability chain.\n    3. Provide a final determination of primary CWE(s) and any secondary CWEs.\n    4. Format your response using the standard analysis template.\n\n    Please analyze how these different weaknesses interact and provide a comprehensive CWE classification.\n    "
  },
  "retrieval_time": 1.6442186832427979
}