{
  "vulnerability_info": "VulnerabilityInfo(cve_id='CVE-2024-50533', description='Cross-Site Request Forgery (CSRF) vulnerability in David Garcia Domain Sharding allows Stored **XSS**.This issue affects Domain Sharding from n/a through 1.2.1.', key_phrases={'rootcause': 'improper input sanitization', 'weakness': ['XSS', 'cross-site request forgery'], 'impact': 'stored cross-site scripting', 'vector': '', 'attacker': '', 'product': 'David Garcia Domain Sharding', 'version': 'n/a through 1.2.1', 'component': ''}, reference_content='- **Root cause of vulnerability**: The WordPress Domain Sharding Plugin version 1.2.1 and below is vulnerable to Cross-Site Request Forgery (CSRF).\\n- **Weaknesses/vulnerabilities present**: CSRF vulnerability.\\n- **Impact of exploitation**: A malicious actor can force higher-privileged users to execute unwanted actions under their current authentication.\\n- **Attack vectors**: The attacker can craft a malicious request and trick a logged-in user into executing it.\\n- **Required attacker capabilities/position**: The attacker needs to be able to trick a logged-in user into submitting a crafted request. This can be achieved by various methods such as malicious links, images, or iframes. The attacker does not need to be authenticated but needs the victim to be authenticated.', similar_info={'cwe_distribution': {}, 'cwe_consensus': '', 'similarity_stats': {'thresholds': [], 'total_samples_by_threshold': {}, 'top_cwes_by_threshold': {}}}, similarity_summary=SimilarityInsight(consensus_cwe='', top_cwes=[], confidence_levels={}, total_samples=0), analysis='', analysis_with_relationships='', criticism='', resolution='', relevant_cwes=[{'metadata': {'doc_id': '89', 'name': \"Improper Neutralization of Special Elements used in an SQL Command ('SQL Injection')\", 'source': 'sparse', 'original_content': 'The product constructs all or part of an SQL command using externally-influenced input from an upstream component, but it does not neutralize or incorrectly neutralizes special elements that could modify the intended SQL command when it is sent to a downstream component. Without sufficient removal or quoting of SQL syntax in user-controllable inputs, the generated SQL query can cause those inputs to be interpreted as SQL instead of ordinary user data.', 'keyphrase_sources': [{'id': 'weakness:cross-site request forgery', 'keyphrase': 'cross-site request forgery', 'type': 'weakness'}]}, 'similarity': np.float64(228.99542639401656)}, {'metadata': {'doc_id': '918', 'name': 'Server-Side Request Forgery (SSRF)', 'source': 'sparse', 'original_content': 'The web server receives a URL or similar request from an upstream component and retrieves the contents of this URL, but it does not sufficiently ensure that the request is being sent to the expected destination.', 'keyphrase_sources': [{'id': 'weakness:cross-site request forgery', 'keyphrase': 'cross-site request forgery', 'type': 'weakness'}]}, 'similarity': np.float64(220.70850276664297)}, {'metadata': {'doc_id': '1275', 'name': 'Sensitive Cookie with Improper SameSite Attribute', 'source': 'sparse', 'original_content': 'The SameSite attribute for sensitive cookies is not set, or an insecure value is used.', 'keyphrase_sources': [{'id': 'weakness:cross-site request forgery', 'keyphrase': 'cross-site request forgery', 'type': 'weakness'}, {'id': 'product:David Garcia Domain Sharding', 'keyphrase': 'David Garcia Domain Sharding', 'type': 'product'}]}, 'similarity': np.float64(217.76717269629208)}, {'metadata': {'doc_id': '352', 'name': 'Cross-Site Request Forgery (CSRF)', 'source': 'sparse', 'original_content': 'The web application does not, or can not, sufficiently verify whether a well-formed, valid, consistent request was intentionally provided by the user who submitted the request.', 'keyphrase_sources': [{'id': 'rootcause:improper input sanitization', 'keyphrase': 'improper input sanitization', 'type': 'rootcause'}, {'id': 'weakness:XSS', 'keyphrase': 'XSS', 'type': 'weakness'}, {'id': 'weakness:cross-site request forgery', 'keyphrase': 'cross-site request forgery', 'type': 'weakness'}, {'id': 'impact:stored cross-site scripting', 'keyphrase': 'stored cross-site scripting', 'type': 'impact'}, {'id': 'product:David Garcia Domain Sharding', 'keyphrase': 'David Garcia Domain Sharding', 'type': 'product'}, {'id': 'version:n/a through 1.2.1', 'keyphrase': 'n/a through 1.2.1', 'type': 'version'}]}, 'similarity': np.float64(189.0303176436778)}, {'metadata': {'doc_id': '79', 'name': \"Improper Neutralization of Input During Web Page Generation ('Cross-site Scripting')\", 'source': 'sparse', 'original_content': 'The product does not neutralize or incorrectly neutralizes user-controllable input before it is placed in output that is used as a web page that is served to other users.', 'keyphrase_sources': [{'id': 'rootcause:improper input sanitization', 'keyphrase': 'improper input sanitization', 'type': 'rootcause'}, {'id': 'weakness:XSS', 'keyphrase': 'XSS', 'type': 'weakness'}, {'id': 'impact:stored cross-site scripting', 'keyphrase': 'stored cross-site scripting', 'type': 'impact'}, {'id': 'product:David Garcia Domain Sharding', 'keyphrase': 'David Garcia Domain Sharding', 'type': 'product'}, {'id': 'version:n/a through 1.2.1', 'keyphrase': 'n/a through 1.2.1', 'type': 'version'}]}, 'similarity': np.float64(174.21428063663652)}, {'metadata': {'doc_id': '138', 'name': 'Improper Neutralization of Special Elements', 'source': 'sparse', 'original_content': 'The product receives input from an upstream component, but it does not neutralize or incorrectly neutralizes special elements that could be interpreted as control elements or syntactic markers when they are sent to a downstream component.', 'keyphrase_sources': [{'id': 'rootcause:improper input sanitization', 'keyphrase': 'improper input sanitization', 'type': 'rootcause'}]}, 'similarity': np.float64(167.2889781426117)}, {'metadata': {'doc_id': '116', 'name': 'Improper Encoding or Escaping of Output', 'source': 'sparse', 'original_content': 'The product prepares a structured message for communication with another component, but encoding or escaping of the data is either missing or done incorrectly. As a result, the intended structure of the message is not preserved.', 'keyphrase_sources': [{'id': 'rootcause:improper input sanitization', 'keyphrase': 'improper input sanitization', 'type': 'rootcause'}, {'id': 'impact:stored cross-site scripting', 'keyphrase': 'stored cross-site scripting', 'type': 'impact'}]}, 'similarity': np.float64(163.55279604436845)}, {'metadata': {'doc_id': '601', 'name': \"URL Redirection to Untrusted Site ('Open Redirect')\", 'source': 'sparse', 'original_content': 'The web application accepts a user-controlled input that specifies a link to an external site, and uses that link in a redirect.', 'keyphrase_sources': [{'id': 'rootcause:improper input sanitization', 'keyphrase': 'improper input sanitization', 'type': 'rootcause'}, {'id': 'weakness:cross-site request forgery', 'keyphrase': 'cross-site request forgery', 'type': 'weakness'}, {'id': 'product:David Garcia Domain Sharding', 'keyphrase': 'David Garcia Domain Sharding', 'type': 'product'}, {'id': 'version:n/a through 1.2.1', 'keyphrase': 'n/a through 1.2.1', 'type': 'version'}]}, 'similarity': np.float64(158.55615127486024)}, {'metadata': {'doc_id': '1004', 'name': \"Sensitive Cookie Without 'HttpOnly' Flag\", 'source': 'sparse', 'original_content': 'The product uses a cookie to store sensitive information, but the cookie is not marked with the HttpOnly flag.', 'keyphrase_sources': [{'id': 'weakness:XSS', 'keyphrase': 'XSS', 'type': 'weakness'}]}, 'similarity': np.float64(145.41012780584032)}, {'metadata': {'doc_id': '942', 'name': 'Permissive Cross-domain Policy with Untrusted Domains', 'source': 'sparse', 'original_content': 'The product uses a cross-domain policy file that includes domains that should not be trusted.', 'keyphrase_sources': [{'id': 'weakness:XSS', 'keyphrase': 'XSS', 'type': 'weakness'}, {'id': 'impact:stored cross-site scripting', 'keyphrase': 'stored cross-site scripting', 'type': 'impact'}, {'id': 'product:David Garcia Domain Sharding', 'keyphrase': 'David Garcia Domain Sharding', 'type': 'product'}]}, 'similarity': np.float64(139.55563315239138)}, {'metadata': {'doc_id': '80', 'name': 'Improper Neutralization of Script-Related HTML Tags in a Web Page (Basic XSS)', 'source': 'sparse', 'original_content': 'The product receives input from an upstream component, but it does not neutralize or incorrectly neutralizes special characters such as \"<\", \">\", and \"&\" that could be interpreted as web-scripting elements when they are sent to a downstream component that processes web pages.', 'keyphrase_sources': [{'id': 'weakness:XSS', 'keyphrase': 'XSS', 'type': 'weakness'}, {'id': 'impact:stored cross-site scripting', 'keyphrase': 'stored cross-site scripting', 'type': 'impact'}]}, 'similarity': np.float64(138.99926066392837)}, {'metadata': {'doc_id': '434', 'name': 'Unrestricted Upload of File with Dangerous Type', 'source': 'sparse', 'original_content': 'The product allows the upload or transfer of dangerous file types that are automatically processed within its environment.', 'keyphrase_sources': [{'id': 'version:n/a through 1.2.1', 'keyphrase': 'n/a through 1.2.1', 'type': 'version'}]}, 'similarity': np.float64(62.145640287743426)}, {'metadata': {'doc_id': '22', 'name': \"Improper Limitation of a Pathname to a Restricted Directory ('Path Traversal')\", 'source': 'sparse', 'original_content': 'The product uses external input to construct a pathname that is intended to identify a file or directory that is located underneath a restricted parent directory, but the product does not properly neutralize special elements within the pathname that can cause the pathname to resolve to a location that is outside of the restricted directory.', 'keyphrase_sources': [{'id': 'version:n/a through 1.2.1', 'keyphrase': 'n/a through 1.2.1', 'type': 'version'}]}, 'similarity': np.float64(59.343400139467526)}], identified_cwes={'analyzer': [], 'critic_additional': []})",
  "retrieval_results": {
    "has_multiple_keyphrases": true,
    "keyphrase_cwe_sets": {
      "rootcause:improper input sanitization": {
        "keyphrase": "improper input sanitization",
        "type": "rootcause",
        "cwes": [
          {
            "metadata": {
              "doc_id": "352",
              "name": "Cross-Site Request Forgery (CSRF)",
              "source": "sparse",
              "original_content": "The web application does not, or can not, sufficiently verify whether a well-formed, valid, consistent request was intentionally provided by the user who submitted the request.",
              "keyphrase_sources": [
                {
                  "id": "rootcause:improper input sanitization",
                  "keyphrase": "improper input sanitization",
                  "type": "rootcause"
                },
                {
                  "id": "weakness:XSS",
                  "keyphrase": "XSS",
                  "type": "weakness"
                },
                {
                  "id": "weakness:cross-site request forgery",
                  "keyphrase": "cross-site request forgery",
                  "type": "weakness"
                },
                {
                  "id": "impact:stored cross-site scripting",
                  "keyphrase": "stored cross-site scripting",
                  "type": "impact"
                },
                {
                  "id": "product:David Garcia Domain Sharding",
                  "keyphrase": "David Garcia Domain Sharding",
                  "type": "product"
                },
                {
                  "id": "version:n/a through 1.2.1",
                  "keyphrase": "n/a through 1.2.1",
                  "type": "version"
                }
              ]
            },
            "similarity": 189.0303176436778
          },
          {
            "metadata": {
              "doc_id": "79",
              "name": "Improper Neutralization of Input During Web Page Generation ('Cross-site Scripting')",
              "source": "sparse",
              "original_content": "The product does not neutralize or incorrectly neutralizes user-controllable input before it is placed in output that is used as a web page that is served to other users.",
              "keyphrase_sources": [
                {
                  "id": "rootcause:improper input sanitization",
                  "keyphrase": "improper input sanitization",
                  "type": "rootcause"
                },
                {
                  "id": "weakness:XSS",
                  "keyphrase": "XSS",
                  "type": "weakness"
                },
                {
                  "id": "impact:stored cross-site scripting",
                  "keyphrase": "stored cross-site scripting",
                  "type": "impact"
                },
                {
                  "id": "product:David Garcia Domain Sharding",
                  "keyphrase": "David Garcia Domain Sharding",
                  "type": "product"
                },
                {
                  "id": "version:n/a through 1.2.1",
                  "keyphrase": "n/a through 1.2.1",
                  "type": "version"
                }
              ]
            },
            "similarity": 174.21428063663652
          },
          {
            "metadata": {
              "doc_id": "138",
              "name": "Improper Neutralization of Special Elements",
              "source": "sparse",
              "original_content": "The product receives input from an upstream component, but it does not neutralize or incorrectly neutralizes special elements that could be interpreted as control elements or syntactic markers when they are sent to a downstream component.",
              "keyphrase_sources": [
                {
                  "id": "rootcause:improper input sanitization",
                  "keyphrase": "improper input sanitization",
                  "type": "rootcause"
                }
              ]
            },
            "similarity": 167.2889781426117
          },
          {
            "metadata": {
              "doc_id": "116",
              "name": "Improper Encoding or Escaping of Output",
              "source": "sparse",
              "original_content": "The product prepares a structured message for communication with another component, but encoding or escaping of the data is either missing or done incorrectly. As a result, the intended structure of the message is not preserved.",
              "keyphrase_sources": [
                {
                  "id": "rootcause:improper input sanitization",
                  "keyphrase": "improper input sanitization",
                  "type": "rootcause"
                },
                {
                  "id": "impact:stored cross-site scripting",
                  "keyphrase": "stored cross-site scripting",
                  "type": "impact"
                }
              ]
            },
            "similarity": 163.55279604436845
          },
          {
            "metadata": {
              "doc_id": "601",
              "name": "URL Redirection to Untrusted Site ('Open Redirect')",
              "source": "sparse",
              "original_content": "The web application accepts a user-controlled input that specifies a link to an external site, and uses that link in a redirect.",
              "keyphrase_sources": [
                {
                  "id": "rootcause:improper input sanitization",
                  "keyphrase": "improper input sanitization",
                  "type": "rootcause"
                },
                {
                  "id": "weakness:cross-site request forgery",
                  "keyphrase": "cross-site request forgery",
                  "type": "weakness"
                },
                {
                  "id": "product:David Garcia Domain Sharding",
                  "keyphrase": "David Garcia Domain Sharding",
                  "type": "product"
                },
                {
                  "id": "version:n/a through 1.2.1",
                  "keyphrase": "n/a through 1.2.1",
                  "type": "version"
                }
              ]
            },
            "similarity": 158.55615127486024
          }
        ]
      },
      "weakness:XSS": {
        "keyphrase": "XSS",
        "type": "weakness",
        "cwes": [
          {
            "metadata": {
              "doc_id": "352",
              "name": "Cross-Site Request Forgery (CSRF)",
              "source": "sparse",
              "original_content": "The web application does not, or can not, sufficiently verify whether a well-formed, valid, consistent request was intentionally provided by the user who submitted the request."
            },
            "similarity": 189.0173255255257
          },
          {
            "metadata": {
              "doc_id": "79",
              "name": "Improper Neutralization of Input During Web Page Generation ('Cross-site Scripting')",
              "source": "sparse",
              "original_content": "The product does not neutralize or incorrectly neutralizes user-controllable input before it is placed in output that is used as a web page that is served to other users."
            },
            "similarity": 167.20607340069716
          },
          {
            "metadata": {
              "doc_id": "1004",
              "name": "Sensitive Cookie Without 'HttpOnly' Flag",
              "source": "sparse",
              "original_content": "The product uses a cookie to store sensitive information, but the cookie is not marked with the HttpOnly flag.",
              "keyphrase_sources": [
                {
                  "id": "weakness:XSS",
                  "keyphrase": "XSS",
                  "type": "weakness"
                }
              ]
            },
            "similarity": 145.41012780584032
          },
          {
            "metadata": {
              "doc_id": "942",
              "name": "Permissive Cross-domain Policy with Untrusted Domains",
              "source": "sparse",
              "original_content": "The product uses a cross-domain policy file that includes domains that should not be trusted.",
              "keyphrase_sources": [
                {
                  "id": "weakness:XSS",
                  "keyphrase": "XSS",
                  "type": "weakness"
                },
                {
                  "id": "impact:stored cross-site scripting",
                  "keyphrase": "stored cross-site scripting",
                  "type": "impact"
                },
                {
                  "id": "product:David Garcia Domain Sharding",
                  "keyphrase": "David Garcia Domain Sharding",
                  "type": "product"
                }
              ]
            },
            "similarity": 139.55563315239138
          },
          {
            "metadata": {
              "doc_id": "80",
              "name": "Improper Neutralization of Script-Related HTML Tags in a Web Page (Basic XSS)",
              "source": "sparse",
              "original_content": "The product receives input from an upstream component, but it does not neutralize or incorrectly neutralizes special characters such as \"<\", \">\", and \"&\" that could be interpreted as web-scripting elements when they are sent to a downstream component that processes web pages.",
              "keyphrase_sources": [
                {
                  "id": "weakness:XSS",
                  "keyphrase": "XSS",
                  "type": "weakness"
                },
                {
                  "id": "impact:stored cross-site scripting",
                  "keyphrase": "stored cross-site scripting",
                  "type": "impact"
                }
              ]
            },
            "similarity": 138.99926066392837
          }
        ]
      },
      "weakness:cross-site request forgery": {
        "keyphrase": "cross-site request forgery",
        "type": "weakness",
        "cwes": [
          {
            "metadata": {
              "doc_id": "352",
              "name": "Cross-Site Request Forgery (CSRF)",
              "source": "sparse",
              "original_content": "The web application does not, or can not, sufficiently verify whether a well-formed, valid, consistent request was intentionally provided by the user who submitted the request."
            },
            "similarity": 275.19707513884356
          },
          {
            "metadata": {
              "doc_id": "601",
              "name": "URL Redirection to Untrusted Site ('Open Redirect')",
              "source": "sparse",
              "original_content": "The web application accepts a user-controlled input that specifies a link to an external site, and uses that link in a redirect."
            },
            "similarity": 238.75310097707643
          },
          {
            "metadata": {
              "doc_id": "89",
              "name": "Improper Neutralization of Special Elements used in an SQL Command ('SQL Injection')",
              "source": "sparse",
              "original_content": "The product constructs all or part of an SQL command using externally-influenced input from an upstream component, but it does not neutralize or incorrectly neutralizes special elements that could modify the intended SQL command when it is sent to a downstream component. Without sufficient removal or quoting of SQL syntax in user-controllable inputs, the generated SQL query can cause those inputs to be interpreted as SQL instead of ordinary user data.",
              "keyphrase_sources": [
                {
                  "id": "weakness:cross-site request forgery",
                  "keyphrase": "cross-site request forgery",
                  "type": "weakness"
                }
              ]
            },
            "similarity": 228.99542639401656
          },
          {
            "metadata": {
              "doc_id": "918",
              "name": "Server-Side Request Forgery (SSRF)",
              "source": "sparse",
              "original_content": "The web server receives a URL or similar request from an upstream component and retrieves the contents of this URL, but it does not sufficiently ensure that the request is being sent to the expected destination.",
              "keyphrase_sources": [
                {
                  "id": "weakness:cross-site request forgery",
                  "keyphrase": "cross-site request forgery",
                  "type": "weakness"
                }
              ]
            },
            "similarity": 220.70850276664297
          },
          {
            "metadata": {
              "doc_id": "1275",
              "name": "Sensitive Cookie with Improper SameSite Attribute",
              "source": "sparse",
              "original_content": "The SameSite attribute for sensitive cookies is not set, or an insecure value is used.",
              "keyphrase_sources": [
                {
                  "id": "weakness:cross-site request forgery",
                  "keyphrase": "cross-site request forgery",
                  "type": "weakness"
                },
                {
                  "id": "product:David Garcia Domain Sharding",
                  "keyphrase": "David Garcia Domain Sharding",
                  "type": "product"
                }
              ]
            },
            "similarity": 217.76717269629208
          }
        ]
      },
      "impact:stored cross-site scripting": {
        "keyphrase": "stored cross-site scripting",
        "type": "impact",
        "cwes": [
          {
            "metadata": {
              "doc_id": "352",
              "name": "Cross-Site Request Forgery (CSRF)",
              "source": "sparse",
              "original_content": "The web application does not, or can not, sufficiently verify whether a well-formed, valid, consistent request was intentionally provided by the user who submitted the request."
            },
            "similarity": 99.92342701020424
          },
          {
            "metadata": {
              "doc_id": "79",
              "name": "Improper Neutralization of Input During Web Page Generation ('Cross-site Scripting')",
              "source": "sparse",
              "original_content": "The product does not neutralize or incorrectly neutralizes user-controllable input before it is placed in output that is used as a web page that is served to other users."
            },
            "similarity": 87.85520992172859
          },
          {
            "metadata": {
              "doc_id": "80",
              "name": "Improper Neutralization of Script-Related HTML Tags in a Web Page (Basic XSS)",
              "source": "sparse",
              "original_content": "The product receives input from an upstream component, but it does not neutralize or incorrectly neutralizes special characters such as \"<\", \">\", and \"&\" that could be interpreted as web-scripting elements when they are sent to a downstream component that processes web pages."
            },
            "similarity": 75.80930145179799
          },
          {
            "metadata": {
              "doc_id": "942",
              "name": "Permissive Cross-domain Policy with Untrusted Domains",
              "source": "sparse",
              "original_content": "The product uses a cross-domain policy file that includes domains that should not be trusted."
            },
            "similarity": 74.48063517204835
          },
          {
            "metadata": {
              "doc_id": "116",
              "name": "Improper Encoding or Escaping of Output",
              "source": "sparse",
              "original_content": "The product prepares a structured message for communication with another component, but encoding or escaping of the data is either missing or done incorrectly. As a result, the intended structure of the message is not preserved."
            },
            "similarity": 73.07185806739228
          }
        ]
      },
      "product:David Garcia Domain Sharding": {
        "keyphrase": "David Garcia Domain Sharding",
        "type": "product",
        "cwes": [
          {
            "metadata": {
              "doc_id": "352",
              "name": "Cross-Site Request Forgery (CSRF)",
              "source": "sparse",
              "original_content": "The web application does not, or can not, sufficiently verify whether a well-formed, valid, consistent request was intentionally provided by the user who submitted the request."
            },
            "similarity": 63.986429682551076
          },
          {
            "metadata": {
              "doc_id": "601",
              "name": "URL Redirection to Untrusted Site ('Open Redirect')",
              "source": "sparse",
              "original_content": "The web application accepts a user-controlled input that specifies a link to an external site, and uses that link in a redirect."
            },
            "similarity": 59.09797277411606
          },
          {
            "metadata": {
              "doc_id": "942",
              "name": "Permissive Cross-domain Policy with Untrusted Domains",
              "source": "sparse",
              "original_content": "The product uses a cross-domain policy file that includes domains that should not be trusted."
            },
            "similarity": 55.906745270332024
          },
          {
            "metadata": {
              "doc_id": "1275",
              "name": "Sensitive Cookie with Improper SameSite Attribute",
              "source": "sparse",
              "original_content": "The SameSite attribute for sensitive cookies is not set, or an insecure value is used."
            },
            "similarity": 53.1501958825734
          },
          {
            "metadata": {
              "doc_id": "79",
              "name": "Improper Neutralization of Input During Web Page Generation ('Cross-site Scripting')",
              "source": "sparse",
              "original_content": "The product does not neutralize or incorrectly neutralizes user-controllable input before it is placed in output that is used as a web page that is served to other users."
            },
            "similarity": 52.53680416306577
          }
        ]
      },
      "version:n/a through 1.2.1": {
        "keyphrase": "n/a through 1.2.1",
        "type": "version",
        "cwes": [
          {
            "metadata": {
              "doc_id": "352",
              "name": "Cross-Site Request Forgery (CSRF)",
              "source": "sparse",
              "original_content": "The web application does not, or can not, sufficiently verify whether a well-formed, valid, consistent request was intentionally provided by the user who submitted the request."
            },
            "similarity": 73.85467475326023
          },
          {
            "metadata": {
              "doc_id": "79",
              "name": "Improper Neutralization of Input During Web Page Generation ('Cross-site Scripting')",
              "source": "sparse",
              "original_content": "The product does not neutralize or incorrectly neutralizes user-controllable input before it is placed in output that is used as a web page that is served to other users."
            },
            "similarity": 63.8581223389788
          },
          {
            "metadata": {
              "doc_id": "434",
              "name": "Unrestricted Upload of File with Dangerous Type",
              "source": "sparse",
              "original_content": "The product allows the upload or transfer of dangerous file types that are automatically processed within its environment.",
              "keyphrase_sources": [
                {
                  "id": "version:n/a through 1.2.1",
                  "keyphrase": "n/a through 1.2.1",
                  "type": "version"
                }
              ]
            },
            "similarity": 62.145640287743426
          },
          {
            "metadata": {
              "doc_id": "601",
              "name": "URL Redirection to Untrusted Site ('Open Redirect')",
              "source": "sparse",
              "original_content": "The web application accepts a user-controlled input that specifies a link to an external site, and uses that link in a redirect."
            },
            "similarity": 60.84501828688236
          },
          {
            "metadata": {
              "doc_id": "22",
              "name": "Improper Limitation of a Pathname to a Restricted Directory ('Path Traversal')",
              "source": "sparse",
              "original_content": "The product uses external input to construct a pathname that is intended to identify a file or directory that is located underneath a restricted parent directory, but the product does not properly neutralize special elements within the pathname that can cause the pathname to resolve to a location that is outside of the restricted directory.",
              "keyphrase_sources": [
                {
                  "id": "version:n/a through 1.2.1",
                  "keyphrase": "n/a through 1.2.1",
                  "type": "version"
                }
              ]
            },
            "similarity": 59.343400139467526
          }
        ]
      }
    },
    "keyphrase_mapping": {
      "352": [
        {
          "id": "rootcause:improper input sanitization",
          "keyphrase": "improper input sanitization",
          "type": "rootcause"
        },
        {
          "id": "weakness:XSS",
          "keyphrase": "XSS",
          "type": "weakness"
        },
        {
          "id": "weakness:cross-site request forgery",
          "keyphrase": "cross-site request forgery",
          "type": "weakness"
        },
        {
          "id": "impact:stored cross-site scripting",
          "keyphrase": "stored cross-site scripting",
          "type": "impact"
        },
        {
          "id": "product:David Garcia Domain Sharding",
          "keyphrase": "David Garcia Domain Sharding",
          "type": "product"
        },
        {
          "id": "version:n/a through 1.2.1",
          "keyphrase": "n/a through 1.2.1",
          "type": "version"
        }
      ],
      "79": [
        {
          "id": "rootcause:improper input sanitization",
          "keyphrase": "improper input sanitization",
          "type": "rootcause"
        },
        {
          "id": "weakness:XSS",
          "keyphrase": "XSS",
          "type": "weakness"
        },
        {
          "id": "impact:stored cross-site scripting",
          "keyphrase": "stored cross-site scripting",
          "type": "impact"
        },
        {
          "id": "product:David Garcia Domain Sharding",
          "keyphrase": "David Garcia Domain Sharding",
          "type": "product"
        },
        {
          "id": "version:n/a through 1.2.1",
          "keyphrase": "n/a through 1.2.1",
          "type": "version"
        }
      ],
      "138": [
        {
          "id": "rootcause:improper input sanitization",
          "keyphrase": "improper input sanitization",
          "type": "rootcause"
        }
      ],
      "116": [
        {
          "id": "rootcause:improper input sanitization",
          "keyphrase": "improper input sanitization",
          "type": "rootcause"
        },
        {
          "id": "impact:stored cross-site scripting",
          "keyphrase": "stored cross-site scripting",
          "type": "impact"
        }
      ],
      "601": [
        {
          "id": "rootcause:improper input sanitization",
          "keyphrase": "improper input sanitization",
          "type": "rootcause"
        },
        {
          "id": "weakness:cross-site request forgery",
          "keyphrase": "cross-site request forgery",
          "type": "weakness"
        },
        {
          "id": "product:David Garcia Domain Sharding",
          "keyphrase": "David Garcia Domain Sharding",
          "type": "product"
        },
        {
          "id": "version:n/a through 1.2.1",
          "keyphrase": "n/a through 1.2.1",
          "type": "version"
        }
      ],
      "1004": [
        {
          "id": "weakness:XSS",
          "keyphrase": "XSS",
          "type": "weakness"
        }
      ],
      "942": [
        {
          "id": "weakness:XSS",
          "keyphrase": "XSS",
          "type": "weakness"
        },
        {
          "id": "impact:stored cross-site scripting",
          "keyphrase": "stored cross-site scripting",
          "type": "impact"
        },
        {
          "id": "product:David Garcia Domain Sharding",
          "keyphrase": "David Garcia Domain Sharding",
          "type": "product"
        }
      ],
      "80": [
        {
          "id": "weakness:XSS",
          "keyphrase": "XSS",
          "type": "weakness"
        },
        {
          "id": "impact:stored cross-site scripting",
          "keyphrase": "stored cross-site scripting",
          "type": "impact"
        }
      ],
      "89": [
        {
          "id": "weakness:cross-site request forgery",
          "keyphrase": "cross-site request forgery",
          "type": "weakness"
        }
      ],
      "918": [
        {
          "id": "weakness:cross-site request forgery",
          "keyphrase": "cross-site request forgery",
          "type": "weakness"
        }
      ],
      "1275": [
        {
          "id": "weakness:cross-site request forgery",
          "keyphrase": "cross-site request forgery",
          "type": "weakness"
        },
        {
          "id": "product:David Garcia Domain Sharding",
          "keyphrase": "David Garcia Domain Sharding",
          "type": "product"
        }
      ],
      "434": [
        {
          "id": "version:n/a through 1.2.1",
          "keyphrase": "n/a through 1.2.1",
          "type": "version"
        }
      ],
      "22": [
        {
          "id": "version:n/a through 1.2.1",
          "keyphrase": "n/a through 1.2.1",
          "type": "version"
        }
      ]
    },
    "relevant_cwes": [
      {
        "metadata": {
          "doc_id": "89",
          "name": "Improper Neutralization of Special Elements used in an SQL Command ('SQL Injection')",
          "source": "sparse",
          "original_content": "The product constructs all or part of an SQL command using externally-influenced input from an upstream component, but it does not neutralize or incorrectly neutralizes special elements that could modify the intended SQL command when it is sent to a downstream component. Without sufficient removal or quoting of SQL syntax in user-controllable inputs, the generated SQL query can cause those inputs to be interpreted as SQL instead of ordinary user data.",
          "keyphrase_sources": [
            {
              "id": "weakness:cross-site request forgery",
              "keyphrase": "cross-site request forgery",
              "type": "weakness"
            }
          ]
        },
        "similarity": 228.99542639401656
      },
      {
        "metadata": {
          "doc_id": "918",
          "name": "Server-Side Request Forgery (SSRF)",
          "source": "sparse",
          "original_content": "The web server receives a URL or similar request from an upstream component and retrieves the contents of this URL, but it does not sufficiently ensure that the request is being sent to the expected destination.",
          "keyphrase_sources": [
            {
              "id": "weakness:cross-site request forgery",
              "keyphrase": "cross-site request forgery",
              "type": "weakness"
            }
          ]
        },
        "similarity": 220.70850276664297
      },
      {
        "metadata": {
          "doc_id": "1275",
          "name": "Sensitive Cookie with Improper SameSite Attribute",
          "source": "sparse",
          "original_content": "The SameSite attribute for sensitive cookies is not set, or an insecure value is used.",
          "keyphrase_sources": [
            {
              "id": "weakness:cross-site request forgery",
              "keyphrase": "cross-site request forgery",
              "type": "weakness"
            },
            {
              "id": "product:David Garcia Domain Sharding",
              "keyphrase": "David Garcia Domain Sharding",
              "type": "product"
            }
          ]
        },
        "similarity": 217.76717269629208
      },
      {
        "metadata": {
          "doc_id": "352",
          "name": "Cross-Site Request Forgery (CSRF)",
          "source": "sparse",
          "original_content": "The web application does not, or can not, sufficiently verify whether a well-formed, valid, consistent request was intentionally provided by the user who submitted the request.",
          "keyphrase_sources": [
            {
              "id": "rootcause:improper input sanitization",
              "keyphrase": "improper input sanitization",
              "type": "rootcause"
            },
            {
              "id": "weakness:XSS",
              "keyphrase": "XSS",
              "type": "weakness"
            },
            {
              "id": "weakness:cross-site request forgery",
              "keyphrase": "cross-site request forgery",
              "type": "weakness"
            },
            {
              "id": "impact:stored cross-site scripting",
              "keyphrase": "stored cross-site scripting",
              "type": "impact"
            },
            {
              "id": "product:David Garcia Domain Sharding",
              "keyphrase": "David Garcia Domain Sharding",
              "type": "product"
            },
            {
              "id": "version:n/a through 1.2.1",
              "keyphrase": "n/a through 1.2.1",
              "type": "version"
            }
          ]
        },
        "similarity": 189.0303176436778
      },
      {
        "metadata": {
          "doc_id": "79",
          "name": "Improper Neutralization of Input During Web Page Generation ('Cross-site Scripting')",
          "source": "sparse",
          "original_content": "The product does not neutralize or incorrectly neutralizes user-controllable input before it is placed in output that is used as a web page that is served to other users.",
          "keyphrase_sources": [
            {
              "id": "rootcause:improper input sanitization",
              "keyphrase": "improper input sanitization",
              "type": "rootcause"
            },
            {
              "id": "weakness:XSS",
              "keyphrase": "XSS",
              "type": "weakness"
            },
            {
              "id": "impact:stored cross-site scripting",
              "keyphrase": "stored cross-site scripting",
              "type": "impact"
            },
            {
              "id": "product:David Garcia Domain Sharding",
              "keyphrase": "David Garcia Domain Sharding",
              "type": "product"
            },
            {
              "id": "version:n/a through 1.2.1",
              "keyphrase": "n/a through 1.2.1",
              "type": "version"
            }
          ]
        },
        "similarity": 174.21428063663652
      },
      {
        "metadata": {
          "doc_id": "138",
          "name": "Improper Neutralization of Special Elements",
          "source": "sparse",
          "original_content": "The product receives input from an upstream component, but it does not neutralize or incorrectly neutralizes special elements that could be interpreted as control elements or syntactic markers when they are sent to a downstream component.",
          "keyphrase_sources": [
            {
              "id": "rootcause:improper input sanitization",
              "keyphrase": "improper input sanitization",
              "type": "rootcause"
            }
          ]
        },
        "similarity": 167.2889781426117
      },
      {
        "metadata": {
          "doc_id": "116",
          "name": "Improper Encoding or Escaping of Output",
          "source": "sparse",
          "original_content": "The product prepares a structured message for communication with another component, but encoding or escaping of the data is either missing or done incorrectly. As a result, the intended structure of the message is not preserved.",
          "keyphrase_sources": [
            {
              "id": "rootcause:improper input sanitization",
              "keyphrase": "improper input sanitization",
              "type": "rootcause"
            },
            {
              "id": "impact:stored cross-site scripting",
              "keyphrase": "stored cross-site scripting",
              "type": "impact"
            }
          ]
        },
        "similarity": 163.55279604436845
      },
      {
        "metadata": {
          "doc_id": "601",
          "name": "URL Redirection to Untrusted Site ('Open Redirect')",
          "source": "sparse",
          "original_content": "The web application accepts a user-controlled input that specifies a link to an external site, and uses that link in a redirect.",
          "keyphrase_sources": [
            {
              "id": "rootcause:improper input sanitization",
              "keyphrase": "improper input sanitization",
              "type": "rootcause"
            },
            {
              "id": "weakness:cross-site request forgery",
              "keyphrase": "cross-site request forgery",
              "type": "weakness"
            },
            {
              "id": "product:David Garcia Domain Sharding",
              "keyphrase": "David Garcia Domain Sharding",
              "type": "product"
            },
            {
              "id": "version:n/a through 1.2.1",
              "keyphrase": "n/a through 1.2.1",
              "type": "version"
            }
          ]
        },
        "similarity": 158.55615127486024
      },
      {
        "metadata": {
          "doc_id": "1004",
          "name": "Sensitive Cookie Without 'HttpOnly' Flag",
          "source": "sparse",
          "original_content": "The product uses a cookie to store sensitive information, but the cookie is not marked with the HttpOnly flag.",
          "keyphrase_sources": [
            {
              "id": "weakness:XSS",
              "keyphrase": "XSS",
              "type": "weakness"
            }
          ]
        },
        "similarity": 145.41012780584032
      },
      {
        "metadata": {
          "doc_id": "942",
          "name": "Permissive Cross-domain Policy with Untrusted Domains",
          "source": "sparse",
          "original_content": "The product uses a cross-domain policy file that includes domains that should not be trusted.",
          "keyphrase_sources": [
            {
              "id": "weakness:XSS",
              "keyphrase": "XSS",
              "type": "weakness"
            },
            {
              "id": "impact:stored cross-site scripting",
              "keyphrase": "stored cross-site scripting",
              "type": "impact"
            },
            {
              "id": "product:David Garcia Domain Sharding",
              "keyphrase": "David Garcia Domain Sharding",
              "type": "product"
            }
          ]
        },
        "similarity": 139.55563315239138
      },
      {
        "metadata": {
          "doc_id": "80",
          "name": "Improper Neutralization of Script-Related HTML Tags in a Web Page (Basic XSS)",
          "source": "sparse",
          "original_content": "The product receives input from an upstream component, but it does not neutralize or incorrectly neutralizes special characters such as \"<\", \">\", and \"&\" that could be interpreted as web-scripting elements when they are sent to a downstream component that processes web pages.",
          "keyphrase_sources": [
            {
              "id": "weakness:XSS",
              "keyphrase": "XSS",
              "type": "weakness"
            },
            {
              "id": "impact:stored cross-site scripting",
              "keyphrase": "stored cross-site scripting",
              "type": "impact"
            }
          ]
        },
        "similarity": 138.99926066392837
      },
      {
        "metadata": {
          "doc_id": "434",
          "name": "Unrestricted Upload of File with Dangerous Type",
          "source": "sparse",
          "original_content": "The product allows the upload or transfer of dangerous file types that are automatically processed within its environment.",
          "keyphrase_sources": [
            {
              "id": "version:n/a through 1.2.1",
              "keyphrase": "n/a through 1.2.1",
              "type": "version"
            }
          ]
        },
        "similarity": 62.145640287743426
      },
      {
        "metadata": {
          "doc_id": "22",
          "name": "Improper Limitation of a Pathname to a Restricted Directory ('Path Traversal')",
          "source": "sparse",
          "original_content": "The product uses external input to construct a pathname that is intended to identify a file or directory that is located underneath a restricted parent directory, but the product does not properly neutralize special elements within the pathname that can cause the pathname to resolve to a location that is outside of the restricted directory.",
          "keyphrase_sources": [
            {
              "id": "version:n/a through 1.2.1",
              "keyphrase": "n/a through 1.2.1",
              "type": "version"
            }
          ]
        },
        "similarity": 59.343400139467526
      }
    ],
    "enhanced_query": "# Vulnerability Description\n\n    Cross-Site Request Forgery (CSRF) vulnerability in David Garcia Domain Sharding allows Stored **XSS**.This issue affects Domain Sharding from n/a through 1.2.1.\n\n    # Keyphrase-Specific CWE Analysis\n    This vulnerability contains multiple keyphrases that may map to different CWEs. \n    Please analyze each keyphrase separately and determine the most appropriate CWE(s) for each.\n\n    ## WEAKNESS: 'cross-site request forgery'\n\nRelevant CWEs for this WEAKNESS:\n\n### 1. CWE-89: Improper Neutralization of Special Elements used in an SQL Command ('SQL Injection') (Score: 229.00)\n\nThe product constructs all or part of an SQL command using externally-influenced input from an upstream component, but it does not neutralize or incorrectly neutralizes special elements that could modify the intended SQL command when it is sent to a downstream component. Without sufficient removal o...\n\n### 2. CWE-918: Server-Side Request Forgery (SSRF) (Score: 220.71)\n\nThe web server receives a URL or similar request from an upstream component and retrieves the contents of this URL, but it does not sufficiently ensure that the request is being sent to the expected destination....\n\n### 3. CWE-1275: Sensitive Cookie with Improper SameSite Attribute (Score: 217.77)\n\nThe SameSite attribute for sensitive cookies is not set, or an insecure value is used....\n\n### 4. CWE-352: Cross-Site Request Forgery (CSRF) (Score: 189.03)\n\nThe web application does not, or can not, sufficiently verify whether a well-formed, valid, consistent request was intentionally provided by the user who submitted the request....\n\n### 5. CWE-601: URL Redirection to Untrusted Site ('Open Redirect') (Score: 158.56)\n\nThe web application accepts a user-controlled input that specifies a link to an external site, and uses that link in a redirect....\n\n## PRODUCT: 'David Garcia Domain Sharding'\n\nRelevant CWEs for this PRODUCT:\n\n### 1. CWE-1275: Sensitive Cookie with Improper SameSite Attribute (Score: 217.77)\n\nThe SameSite attribute for sensitive cookies is not set, or an insecure value is used....\n\n### 2. CWE-352: Cross-Site Request Forgery (CSRF) (Score: 189.03)\n\nThe web application does not, or can not, sufficiently verify whether a well-formed, valid, consistent request was intentionally provided by the user who submitted the request....\n\n### 3. CWE-79: Improper Neutralization of Input During Web Page Generation ('Cross-site Scripting') (Score: 174.21)\n\nThe product does not neutralize or incorrectly neutralizes user-controllable input before it is placed in output that is used as a web page that is served to other users....\n\n### 4. CWE-601: URL Redirection to Untrusted Site ('Open Redirect') (Score: 158.56)\n\nThe web application accepts a user-controlled input that specifies a link to an external site, and uses that link in a redirect....\n\n### 5. CWE-942: Permissive Cross-domain Policy with Untrusted Domains (Score: 139.56)\n\nThe product uses a cross-domain policy file that includes domains that should not be trusted....\n\n## ROOTCAUSE: 'improper input sanitization'\n\nRelevant CWEs for this ROOTCAUSE:\n\n### 1. CWE-352: Cross-Site Request Forgery (CSRF) (Score: 189.03)\n\nThe web application does not, or can not, sufficiently verify whether a well-formed, valid, consistent request was intentionally provided by the user who submitted the request....\n\n### 2. CWE-79: Improper Neutralization of Input During Web Page Generation ('Cross-site Scripting') (Score: 174.21)\n\nThe product does not neutralize or incorrectly neutralizes user-controllable input before it is placed in output that is used as a web page that is served to other users....\n\n### 3. CWE-138: Improper Neutralization of Special Elements (Score: 167.29)\n\nThe product receives input from an upstream component, but it does not neutralize or incorrectly neutralizes special elements that could be interpreted as control elements or syntactic markers when they are sent to a downstream component....\n\n### 4. CWE-116: Improper Encoding or Escaping of Output (Score: 163.55)\n\nThe product prepares a structured message for communication with another component, but encoding or escaping of the data is either missing or done incorrectly. As a result, the intended structure of the message is not preserved....\n\n### 5. CWE-601: URL Redirection to Untrusted Site ('Open Redirect') (Score: 158.56)\n\nThe web application accepts a user-controlled input that specifies a link to an external site, and uses that link in a redirect....\n\n## WEAKNESS: 'XSS'\n\nRelevant CWEs for this WEAKNESS:\n\n### 1. CWE-352: Cross-Site Request Forgery (CSRF) (Score: 189.03)\n\nThe web application does not, or can not, sufficiently verify whether a well-formed, valid, consistent request was intentionally provided by the user who submitted the request....\n\n### 2. CWE-79: Improper Neutralization of Input During Web Page Generation ('Cross-site Scripting') (Score: 174.21)\n\nThe product does not neutralize or incorrectly neutralizes user-controllable input before it is placed in output that is used as a web page that is served to other users....\n\n### 3. CWE-1004: Sensitive Cookie Without 'HttpOnly' Flag (Score: 145.41)\n\nThe product uses a cookie to store sensitive information, but the cookie is not marked with the HttpOnly flag....\n\n### 4. CWE-942: Permissive Cross-domain Policy with Untrusted Domains (Score: 139.56)\n\nThe product uses a cross-domain policy file that includes domains that should not be trusted....\n\n### 5. CWE-80: Improper Neutralization of Script-Related HTML Tags in a Web Page (Basic XSS) (Score: 139.00)\n\nThe product receives input from an upstream component, but it does not neutralize or incorrectly neutralizes special characters such as \"<\", \">\", and \"&\" that could be interpreted as web-scripting elements when they are sent to a downstream component that processes web pages....\n\n## IMPACT: 'stored cross-site scripting'\n\nRelevant CWEs for this IMPACT:\n\n### 1. CWE-352: Cross-Site Request Forgery (CSRF) (Score: 189.03)\n\nThe web application does not, or can not, sufficiently verify whether a well-formed, valid, consistent request was intentionally provided by the user who submitted the request....\n\n### 2. CWE-79: Improper Neutralization of Input During Web Page Generation ('Cross-site Scripting') (Score: 174.21)\n\nThe product does not neutralize or incorrectly neutralizes user-controllable input before it is placed in output that is used as a web page that is served to other users....\n\n### 3. CWE-116: Improper Encoding or Escaping of Output (Score: 163.55)\n\nThe product prepares a structured message for communication with another component, but encoding or escaping of the data is either missing or done incorrectly. As a result, the intended structure of the message is not preserved....\n\n### 4. CWE-942: Permissive Cross-domain Policy with Untrusted Domains (Score: 139.56)\n\nThe product uses a cross-domain policy file that includes domains that should not be trusted....\n\n### 5. CWE-80: Improper Neutralization of Script-Related HTML Tags in a Web Page (Basic XSS) (Score: 139.00)\n\nThe product receives input from an upstream component, but it does not neutralize or incorrectly neutralizes special characters such as \"<\", \">\", and \"&\" that could be interpreted as web-scripting elements when they are sent to a downstream component that processes web pages....\n\n## VERSION: 'n/a through 1.2.1'\n\nRelevant CWEs for this VERSION:\n\n### 1. CWE-352: Cross-Site Request Forgery (CSRF) (Score: 189.03)\n\nThe web application does not, or can not, sufficiently verify whether a well-formed, valid, consistent request was intentionally provided by the user who submitted the request....\n\n### 2. CWE-79: Improper Neutralization of Input During Web Page Generation ('Cross-site Scripting') (Score: 174.21)\n\nThe product does not neutralize or incorrectly neutralizes user-controllable input before it is placed in output that is used as a web page that is served to other users....\n\n### 3. CWE-601: URL Redirection to Untrusted Site ('Open Redirect') (Score: 158.56)\n\nThe web application accepts a user-controlled input that specifies a link to an external site, and uses that link in a redirect....\n\n### 4. CWE-434: Unrestricted Upload of File with Dangerous Type (Score: 62.15)\n\nThe product allows the upload or transfer of dangerous file types that are automatically processed within its environment....\n\n### 5. CWE-22: Improper Limitation of a Pathname to a Restricted Directory ('Path Traversal') (Score: 59.34)\n\nThe product uses external input to construct a pathname that is intended to identify a file or directory that is located underneath a restricted parent directory, but the product does not properly neutralize special elements within the pathname that can cause the pathname to resolve to a location th...\n\n\n    # Analysis Instructions\n    1. For each keyphrase, identify the most appropriate CWE(s) that represent the weakness.\n    2. Consider how the different keyphrases might relate to each other in the vulnerability chain.\n    3. Provide a final determination of primary CWE(s) and any secondary CWEs.\n    4. Format your response using the standard analysis template.\n\n    Please analyze how these different weaknesses interact and provide a comprehensive CWE classification.\n    "
  },
  "retrieval_time": 1.0192241668701172
}