{
  "vulnerability_info": "VulnerabilityInfo(cve_id='CVE-2024-53724', description='Cross-Site Request Forgery (CSRF) vulnerability in Ronny L. Bull IceStats allows Stored **XSS**.This issue affects IceStats from n/a through 1.3.', key_phrases={'rootcause': 'lack of CSRF protection', 'weakness': ['XSS', 'cross-site scripting'], 'impact': '', 'vector': '', 'attacker': '', 'product': 'Ronny L. Bull IceStats', 'version': 'n/a through 1.3', 'component': ''}, reference_content='```\\n{\\n  \"Root cause of vulnerability\": \"The WordPress IceStats plugin <= 1.3 is vulnerable to Cross-Site Request Forgery (CSRF).\",\\n  \"Weaknesses/vulnerabilities present\": \"Cross-Site Request Forgery (CSRF)\",\\n  \"Impact of exploitation\": \"A malicious actor could force higher privileged users to execute unwanted actions under their current authentication.\",\\n  \"Attack vectors\": \"The vulnerability is exploited through a CSRF attack where a malicious actor tricks an authenticated user into performing actions they did not intend.\",\\n  \"Required attacker capabilities/position\": \"The attacker needs to trick a higher-privileged user to interact with a malicious link or website while logged into the vulnerable plugin.\"\\n}\\n```', similar_info={'cwe_distribution': {}, 'cwe_consensus': '', 'similarity_stats': {'thresholds': [], 'total_samples_by_threshold': {}, 'top_cwes_by_threshold': {}}}, similarity_summary=SimilarityInsight(consensus_cwe='', top_cwes=[], confidence_levels={}, total_samples=0), analysis='', analysis_with_relationships='', criticism='', resolution='', relevant_cwes=[{'metadata': {'doc_id': '352', 'name': 'Cross-Site Request Forgery (CSRF)', 'source': 'sparse', 'original_content': 'The web application does not, or can not, sufficiently verify whether a well-formed, valid, consistent request was intentionally provided by the user who submitted the request.', 'keyphrase_sources': [{'id': 'rootcause:lack of CSRF protection', 'keyphrase': 'lack of CSRF protection', 'type': 'rootcause'}, {'id': 'weakness:XSS', 'keyphrase': 'XSS', 'type': 'weakness'}, {'id': 'weakness:cross-site scripting', 'keyphrase': 'cross-site scripting', 'type': 'weakness'}, {'id': 'product:Ronny L. Bull IceStats', 'keyphrase': 'Ronny L. Bull IceStats', 'type': 'product'}, {'id': 'version:n/a through 1.3', 'keyphrase': 'n/a through 1.3', 'type': 'version'}]}, 'similarity': np.float64(269.6954048494395)}, {'metadata': {'doc_id': '434', 'name': 'Unrestricted Upload of File with Dangerous Type', 'source': 'sparse', 'original_content': 'The product allows the upload or transfer of dangerous file types that are automatically processed within its environment.', 'keyphrase_sources': [{'id': 'rootcause:lack of CSRF protection', 'keyphrase': 'lack of CSRF protection', 'type': 'rootcause'}, {'id': 'version:n/a through 1.3', 'keyphrase': 'n/a through 1.3', 'type': 'version'}]}, 'similarity': np.float64(198.55552441013666)}, {'metadata': {'doc_id': '116', 'name': 'Improper Encoding or Escaping of Output', 'source': 'sparse', 'original_content': 'The product prepares a structured message for communication with another component, but encoding or escaping of the data is either missing or done incorrectly. As a result, the intended structure of the message is not preserved.', 'keyphrase_sources': [{'id': 'rootcause:lack of CSRF protection', 'keyphrase': 'lack of CSRF protection', 'type': 'rootcause'}, {'id': 'weakness:XSS', 'keyphrase': 'XSS', 'type': 'weakness'}, {'id': 'weakness:cross-site scripting', 'keyphrase': 'cross-site scripting', 'type': 'weakness'}]}, 'similarity': np.float64(190.85721412577982)}, {'metadata': {'doc_id': '80', 'name': 'Improper Neutralization of Script-Related HTML Tags in a Web Page (Basic XSS)', 'source': 'sparse', 'original_content': 'The product receives input from an upstream component, but it does not neutralize or incorrectly neutralizes special characters such as \"<\", \">\", and \"&\" that could be interpreted as web-scripting elements when they are sent to a downstream component that processes web pages.', 'keyphrase_sources': [{'id': 'weakness:cross-site scripting', 'keyphrase': 'cross-site scripting', 'type': 'weakness'}]}, 'similarity': np.float64(190.7090344076184)}, {'metadata': {'doc_id': '79', 'name': \"Improper Neutralization of Input During Web Page Generation ('Cross-site Scripting')\", 'source': 'sparse', 'original_content': 'The product does not neutralize or incorrectly neutralizes user-controllable input before it is placed in output that is used as a web page that is served to other users.', 'keyphrase_sources': [{'id': 'rootcause:lack of CSRF protection', 'keyphrase': 'lack of CSRF protection', 'type': 'rootcause'}, {'id': 'weakness:XSS', 'keyphrase': 'XSS', 'type': 'weakness'}, {'id': 'weakness:cross-site scripting', 'keyphrase': 'cross-site scripting', 'type': 'weakness'}, {'id': 'product:Ronny L. Bull IceStats', 'keyphrase': 'Ronny L. Bull IceStats', 'type': 'product'}, {'id': 'version:n/a through 1.3', 'keyphrase': 'n/a through 1.3', 'type': 'version'}]}, 'similarity': np.float64(187.0583031699984)}, {'metadata': {'doc_id': '1004', 'name': \"Sensitive Cookie Without 'HttpOnly' Flag\", 'source': 'sparse', 'original_content': 'The product uses a cookie to store sensitive information, but the cookie is not marked with the HttpOnly flag.', 'keyphrase_sources': [{'id': 'rootcause:lack of CSRF protection', 'keyphrase': 'lack of CSRF protection', 'type': 'rootcause'}, {'id': 'weakness:XSS', 'keyphrase': 'XSS', 'type': 'weakness'}, {'id': 'weakness:cross-site scripting', 'keyphrase': 'cross-site scripting', 'type': 'weakness'}]}, 'similarity': np.float64(176.82537553364966)}, {'metadata': {'doc_id': '918', 'name': 'Server-Side Request Forgery (SSRF)', 'source': 'sparse', 'original_content': 'The web server receives a URL or similar request from an upstream component and retrieves the contents of this URL, but it does not sufficiently ensure that the request is being sent to the expected destination.', 'keyphrase_sources': [{'id': 'weakness:XSS', 'keyphrase': 'XSS', 'type': 'weakness'}]}, 'similarity': np.float64(136.18060110226702)}, {'metadata': {'doc_id': '22', 'name': \"Improper Limitation of a Pathname to a Restricted Directory ('Path Traversal')\", 'source': 'sparse', 'original_content': 'The product uses external input to construct a pathname that is intended to identify a file or directory that is located underneath a restricted parent directory, but the product does not properly neutralize special elements within the pathname that can cause the pathname to resolve to a location that is outside of the restricted directory.', 'keyphrase_sources': [{'id': 'version:n/a through 1.3', 'keyphrase': 'n/a through 1.3', 'type': 'version'}]}, 'similarity': np.float64(61.2177042001252)}, {'metadata': {'doc_id': '611', 'name': 'Improper Restriction of XML External Entity Reference', 'source': 'sparse', 'original_content': 'The product processes an XML document that can contain XML entities with URIs that resolve to documents outside of the intended sphere of control, causing the product to embed incorrect documents into its output.', 'keyphrase_sources': [{'id': 'product:Ronny L. Bull IceStats', 'keyphrase': 'Ronny L. Bull IceStats', 'type': 'product'}, {'id': 'version:n/a through 1.3', 'keyphrase': 'n/a through 1.3', 'type': 'version'}]}, 'similarity': np.float64(45.10253700245566)}, {'metadata': {'doc_id': '444', 'name': \"Inconsistent Interpretation of HTTP Requests ('HTTP Request/Response Smuggling')\", 'source': 'sparse', 'original_content': 'The product acts as an intermediary HTTP agent\\n         (such as a proxy or firewall) in the data flow between two\\n         entities such as a client and server, but it does not\\n         interpret malformed HTTP requests or responses in ways that\\n         are consistent with how the messages will be processed by\\n         those entities that are at the ultimate destination.', 'keyphrase_sources': [{'id': 'product:Ronny L. Bull IceStats', 'keyphrase': 'Ronny L. Bull IceStats', 'type': 'product'}]}, 'similarity': np.float64(43.22782203986487)}, {'metadata': {'doc_id': '89', 'name': \"Improper Neutralization of Special Elements used in an SQL Command ('SQL Injection')\", 'source': 'sparse', 'original_content': 'The product constructs all or part of an SQL command using externally-influenced input from an upstream component, but it does not neutralize or incorrectly neutralizes special elements that could modify the intended SQL command when it is sent to a downstream component. Without sufficient removal or quoting of SQL syntax in user-controllable inputs, the generated SQL query can cause those inputs to be interpreted as SQL instead of ordinary user data.', 'keyphrase_sources': [{'id': 'product:Ronny L. Bull IceStats', 'keyphrase': 'Ronny L. Bull IceStats', 'type': 'product'}]}, 'similarity': np.float64(42.54698413248697)}], identified_cwes={'analyzer': [], 'critic_additional': []})",
  "retrieval_results": {
    "has_multiple_keyphrases": true,
    "keyphrase_cwe_sets": {
      "rootcause:lack of CSRF protection": {
        "keyphrase": "lack of CSRF protection",
        "type": "rootcause",
        "cwes": [
          {
            "metadata": {
              "doc_id": "352",
              "name": "Cross-Site Request Forgery (CSRF)",
              "source": "sparse",
              "original_content": "The web application does not, or can not, sufficiently verify whether a well-formed, valid, consistent request was intentionally provided by the user who submitted the request.",
              "keyphrase_sources": [
                {
                  "id": "rootcause:lack of CSRF protection",
                  "keyphrase": "lack of CSRF protection",
                  "type": "rootcause"
                },
                {
                  "id": "weakness:XSS",
                  "keyphrase": "XSS",
                  "type": "weakness"
                },
                {
                  "id": "weakness:cross-site scripting",
                  "keyphrase": "cross-site scripting",
                  "type": "weakness"
                },
                {
                  "id": "product:Ronny L. Bull IceStats",
                  "keyphrase": "Ronny L. Bull IceStats",
                  "type": "product"
                },
                {
                  "id": "version:n/a through 1.3",
                  "keyphrase": "n/a through 1.3",
                  "type": "version"
                }
              ]
            },
            "similarity": 269.6954048494395
          },
          {
            "metadata": {
              "doc_id": "434",
              "name": "Unrestricted Upload of File with Dangerous Type",
              "source": "sparse",
              "original_content": "The product allows the upload or transfer of dangerous file types that are automatically processed within its environment.",
              "keyphrase_sources": [
                {
                  "id": "rootcause:lack of CSRF protection",
                  "keyphrase": "lack of CSRF protection",
                  "type": "rootcause"
                },
                {
                  "id": "version:n/a through 1.3",
                  "keyphrase": "n/a through 1.3",
                  "type": "version"
                }
              ]
            },
            "similarity": 198.55552441013666
          },
          {
            "metadata": {
              "doc_id": "116",
              "name": "Improper Encoding or Escaping of Output",
              "source": "sparse",
              "original_content": "The product prepares a structured message for communication with another component, but encoding or escaping of the data is either missing or done incorrectly. As a result, the intended structure of the message is not preserved.",
              "keyphrase_sources": [
                {
                  "id": "rootcause:lack of CSRF protection",
                  "keyphrase": "lack of CSRF protection",
                  "type": "rootcause"
                },
                {
                  "id": "weakness:XSS",
                  "keyphrase": "XSS",
                  "type": "weakness"
                },
                {
                  "id": "weakness:cross-site scripting",
                  "keyphrase": "cross-site scripting",
                  "type": "weakness"
                }
              ]
            },
            "similarity": 190.85721412577982
          },
          {
            "metadata": {
              "doc_id": "79",
              "name": "Improper Neutralization of Input During Web Page Generation ('Cross-site Scripting')",
              "source": "sparse",
              "original_content": "The product does not neutralize or incorrectly neutralizes user-controllable input before it is placed in output that is used as a web page that is served to other users.",
              "keyphrase_sources": [
                {
                  "id": "rootcause:lack of CSRF protection",
                  "keyphrase": "lack of CSRF protection",
                  "type": "rootcause"
                },
                {
                  "id": "weakness:XSS",
                  "keyphrase": "XSS",
                  "type": "weakness"
                },
                {
                  "id": "weakness:cross-site scripting",
                  "keyphrase": "cross-site scripting",
                  "type": "weakness"
                },
                {
                  "id": "product:Ronny L. Bull IceStats",
                  "keyphrase": "Ronny L. Bull IceStats",
                  "type": "product"
                },
                {
                  "id": "version:n/a through 1.3",
                  "keyphrase": "n/a through 1.3",
                  "type": "version"
                }
              ]
            },
            "similarity": 187.0583031699984
          },
          {
            "metadata": {
              "doc_id": "1004",
              "name": "Sensitive Cookie Without 'HttpOnly' Flag",
              "source": "sparse",
              "original_content": "The product uses a cookie to store sensitive information, but the cookie is not marked with the HttpOnly flag.",
              "keyphrase_sources": [
                {
                  "id": "rootcause:lack of CSRF protection",
                  "keyphrase": "lack of CSRF protection",
                  "type": "rootcause"
                },
                {
                  "id": "weakness:XSS",
                  "keyphrase": "XSS",
                  "type": "weakness"
                },
                {
                  "id": "weakness:cross-site scripting",
                  "keyphrase": "cross-site scripting",
                  "type": "weakness"
                }
              ]
            },
            "similarity": 176.82537553364966
          }
        ]
      },
      "weakness:XSS": {
        "keyphrase": "XSS",
        "type": "weakness",
        "cwes": [
          {
            "metadata": {
              "doc_id": "352",
              "name": "Cross-Site Request Forgery (CSRF)",
              "source": "sparse",
              "original_content": "The web application does not, or can not, sufficiently verify whether a well-formed, valid, consistent request was intentionally provided by the user who submitted the request."
            },
            "similarity": 179.47415563542984
          },
          {
            "metadata": {
              "doc_id": "79",
              "name": "Improper Neutralization of Input During Web Page Generation ('Cross-site Scripting')",
              "source": "sparse",
              "original_content": "The product does not neutralize or incorrectly neutralizes user-controllable input before it is placed in output that is used as a web page that is served to other users."
            },
            "similarity": 156.35014095897316
          },
          {
            "metadata": {
              "doc_id": "1004",
              "name": "Sensitive Cookie Without 'HttpOnly' Flag",
              "source": "sparse",
              "original_content": "The product uses a cookie to store sensitive information, but the cookie is not marked with the HttpOnly flag."
            },
            "similarity": 143.9351364528576
          },
          {
            "metadata": {
              "doc_id": "116",
              "name": "Improper Encoding or Escaping of Output",
              "source": "sparse",
              "original_content": "The product prepares a structured message for communication with another component, but encoding or escaping of the data is either missing or done incorrectly. As a result, the intended structure of the message is not preserved."
            },
            "similarity": 137.57011426500867
          },
          {
            "metadata": {
              "doc_id": "918",
              "name": "Server-Side Request Forgery (SSRF)",
              "source": "sparse",
              "original_content": "The web server receives a URL or similar request from an upstream component and retrieves the contents of this URL, but it does not sufficiently ensure that the request is being sent to the expected destination.",
              "keyphrase_sources": [
                {
                  "id": "weakness:XSS",
                  "keyphrase": "XSS",
                  "type": "weakness"
                }
              ]
            },
            "similarity": 136.18060110226702
          }
        ]
      },
      "weakness:cross-site scripting": {
        "keyphrase": "cross-site scripting",
        "type": "weakness",
        "cwes": [
          {
            "metadata": {
              "doc_id": "352",
              "name": "Cross-Site Request Forgery (CSRF)",
              "source": "sparse",
              "original_content": "The web application does not, or can not, sufficiently verify whether a well-formed, valid, consistent request was intentionally provided by the user who submitted the request."
            },
            "similarity": 247.49730091156573
          },
          {
            "metadata": {
              "doc_id": "79",
              "name": "Improper Neutralization of Input During Web Page Generation ('Cross-site Scripting')",
              "source": "sparse",
              "original_content": "The product does not neutralize or incorrectly neutralizes user-controllable input before it is placed in output that is used as a web page that is served to other users."
            },
            "similarity": 218.3149323158593
          },
          {
            "metadata": {
              "doc_id": "80",
              "name": "Improper Neutralization of Script-Related HTML Tags in a Web Page (Basic XSS)",
              "source": "sparse",
              "original_content": "The product receives input from an upstream component, but it does not neutralize or incorrectly neutralizes special characters such as \"<\", \">\", and \"&\" that could be interpreted as web-scripting elements when they are sent to a downstream component that processes web pages.",
              "keyphrase_sources": [
                {
                  "id": "weakness:cross-site scripting",
                  "keyphrase": "cross-site scripting",
                  "type": "weakness"
                }
              ]
            },
            "similarity": 190.7090344076184
          },
          {
            "metadata": {
              "doc_id": "1004",
              "name": "Sensitive Cookie Without 'HttpOnly' Flag",
              "source": "sparse",
              "original_content": "The product uses a cookie to store sensitive information, but the cookie is not marked with the HttpOnly flag."
            },
            "similarity": 188.48691319900237
          },
          {
            "metadata": {
              "doc_id": "116",
              "name": "Improper Encoding or Escaping of Output",
              "source": "sparse",
              "original_content": "The product prepares a structured message for communication with another component, but encoding or escaping of the data is either missing or done incorrectly. As a result, the intended structure of the message is not preserved."
            },
            "similarity": 184.74034214916915
          }
        ]
      },
      "product:Ronny L. Bull IceStats": {
        "keyphrase": "Ronny L. Bull IceStats",
        "type": "product",
        "cwes": [
          {
            "metadata": {
              "doc_id": "352",
              "name": "Cross-Site Request Forgery (CSRF)",
              "source": "sparse",
              "original_content": "The web application does not, or can not, sufficiently verify whether a well-formed, valid, consistent request was intentionally provided by the user who submitted the request."
            },
            "similarity": 54.74060844611963
          },
          {
            "metadata": {
              "doc_id": "79",
              "name": "Improper Neutralization of Input During Web Page Generation ('Cross-site Scripting')",
              "source": "sparse",
              "original_content": "The product does not neutralize or incorrectly neutralizes user-controllable input before it is placed in output that is used as a web page that is served to other users."
            },
            "similarity": 45.27296766795793
          },
          {
            "metadata": {
              "doc_id": "611",
              "name": "Improper Restriction of XML External Entity Reference",
              "source": "sparse",
              "original_content": "The product processes an XML document that can contain XML entities with URIs that resolve to documents outside of the intended sphere of control, causing the product to embed incorrect documents into its output.",
              "keyphrase_sources": [
                {
                  "id": "product:Ronny L. Bull IceStats",
                  "keyphrase": "Ronny L. Bull IceStats",
                  "type": "product"
                },
                {
                  "id": "version:n/a through 1.3",
                  "keyphrase": "n/a through 1.3",
                  "type": "version"
                }
              ]
            },
            "similarity": 45.10253700245566
          },
          {
            "metadata": {
              "doc_id": "444",
              "name": "Inconsistent Interpretation of HTTP Requests ('HTTP Request/Response Smuggling')",
              "source": "sparse",
              "original_content": "The product acts as an intermediary HTTP agent\n         (such as a proxy or firewall) in the data flow between two\n         entities such as a client and server, but it does not\n         interpret malformed HTTP requests or responses in ways that\n         are consistent with how the messages will be processed by\n         those entities that are at the ultimate destination.",
              "keyphrase_sources": [
                {
                  "id": "product:Ronny L. Bull IceStats",
                  "keyphrase": "Ronny L. Bull IceStats",
                  "type": "product"
                }
              ]
            },
            "similarity": 43.22782203986487
          },
          {
            "metadata": {
              "doc_id": "89",
              "name": "Improper Neutralization of Special Elements used in an SQL Command ('SQL Injection')",
              "source": "sparse",
              "original_content": "The product constructs all or part of an SQL command using externally-influenced input from an upstream component, but it does not neutralize or incorrectly neutralizes special elements that could modify the intended SQL command when it is sent to a downstream component. Without sufficient removal or quoting of SQL syntax in user-controllable inputs, the generated SQL query can cause those inputs to be interpreted as SQL instead of ordinary user data.",
              "keyphrase_sources": [
                {
                  "id": "product:Ronny L. Bull IceStats",
                  "keyphrase": "Ronny L. Bull IceStats",
                  "type": "product"
                }
              ]
            },
            "similarity": 42.54698413248697
          }
        ]
      },
      "version:n/a through 1.3": {
        "keyphrase": "n/a through 1.3",
        "type": "version",
        "cwes": [
          {
            "metadata": {
              "doc_id": "352",
              "name": "Cross-Site Request Forgery (CSRF)",
              "source": "sparse",
              "original_content": "The web application does not, or can not, sufficiently verify whether a well-formed, valid, consistent request was intentionally provided by the user who submitted the request."
            },
            "similarity": 69.46739614669755
          },
          {
            "metadata": {
              "doc_id": "22",
              "name": "Improper Limitation of a Pathname to a Restricted Directory ('Path Traversal')",
              "source": "sparse",
              "original_content": "The product uses external input to construct a pathname that is intended to identify a file or directory that is located underneath a restricted parent directory, but the product does not properly neutralize special elements within the pathname that can cause the pathname to resolve to a location that is outside of the restricted directory.",
              "keyphrase_sources": [
                {
                  "id": "version:n/a through 1.3",
                  "keyphrase": "n/a through 1.3",
                  "type": "version"
                }
              ]
            },
            "similarity": 61.2177042001252
          },
          {
            "metadata": {
              "doc_id": "611",
              "name": "Improper Restriction of XML External Entity Reference",
              "source": "sparse",
              "original_content": "The product processes an XML document that can contain XML entities with URIs that resolve to documents outside of the intended sphere of control, causing the product to embed incorrect documents into its output."
            },
            "similarity": 60.679212497808024
          },
          {
            "metadata": {
              "doc_id": "434",
              "name": "Unrestricted Upload of File with Dangerous Type",
              "source": "sparse",
              "original_content": "The product allows the upload or transfer of dangerous file types that are automatically processed within its environment."
            },
            "similarity": 60.459123981877575
          },
          {
            "metadata": {
              "doc_id": "79",
              "name": "Improper Neutralization of Input During Web Page Generation ('Cross-site Scripting')",
              "source": "sparse",
              "original_content": "The product does not neutralize or incorrectly neutralizes user-controllable input before it is placed in output that is used as a web page that is served to other users."
            },
            "similarity": 59.00020168325874
          }
        ]
      }
    },
    "keyphrase_mapping": {
      "352": [
        {
          "id": "rootcause:lack of CSRF protection",
          "keyphrase": "lack of CSRF protection",
          "type": "rootcause"
        },
        {
          "id": "weakness:XSS",
          "keyphrase": "XSS",
          "type": "weakness"
        },
        {
          "id": "weakness:cross-site scripting",
          "keyphrase": "cross-site scripting",
          "type": "weakness"
        },
        {
          "id": "product:Ronny L. Bull IceStats",
          "keyphrase": "Ronny L. Bull IceStats",
          "type": "product"
        },
        {
          "id": "version:n/a through 1.3",
          "keyphrase": "n/a through 1.3",
          "type": "version"
        }
      ],
      "434": [
        {
          "id": "rootcause:lack of CSRF protection",
          "keyphrase": "lack of CSRF protection",
          "type": "rootcause"
        },
        {
          "id": "version:n/a through 1.3",
          "keyphrase": "n/a through 1.3",
          "type": "version"
        }
      ],
      "116": [
        {
          "id": "rootcause:lack of CSRF protection",
          "keyphrase": "lack of CSRF protection",
          "type": "rootcause"
        },
        {
          "id": "weakness:XSS",
          "keyphrase": "XSS",
          "type": "weakness"
        },
        {
          "id": "weakness:cross-site scripting",
          "keyphrase": "cross-site scripting",
          "type": "weakness"
        }
      ],
      "79": [
        {
          "id": "rootcause:lack of CSRF protection",
          "keyphrase": "lack of CSRF protection",
          "type": "rootcause"
        },
        {
          "id": "weakness:XSS",
          "keyphrase": "XSS",
          "type": "weakness"
        },
        {
          "id": "weakness:cross-site scripting",
          "keyphrase": "cross-site scripting",
          "type": "weakness"
        },
        {
          "id": "product:Ronny L. Bull IceStats",
          "keyphrase": "Ronny L. Bull IceStats",
          "type": "product"
        },
        {
          "id": "version:n/a through 1.3",
          "keyphrase": "n/a through 1.3",
          "type": "version"
        }
      ],
      "1004": [
        {
          "id": "rootcause:lack of CSRF protection",
          "keyphrase": "lack of CSRF protection",
          "type": "rootcause"
        },
        {
          "id": "weakness:XSS",
          "keyphrase": "XSS",
          "type": "weakness"
        },
        {
          "id": "weakness:cross-site scripting",
          "keyphrase": "cross-site scripting",
          "type": "weakness"
        }
      ],
      "918": [
        {
          "id": "weakness:XSS",
          "keyphrase": "XSS",
          "type": "weakness"
        }
      ],
      "80": [
        {
          "id": "weakness:cross-site scripting",
          "keyphrase": "cross-site scripting",
          "type": "weakness"
        }
      ],
      "611": [
        {
          "id": "product:Ronny L. Bull IceStats",
          "keyphrase": "Ronny L. Bull IceStats",
          "type": "product"
        },
        {
          "id": "version:n/a through 1.3",
          "keyphrase": "n/a through 1.3",
          "type": "version"
        }
      ],
      "444": [
        {
          "id": "product:Ronny L. Bull IceStats",
          "keyphrase": "Ronny L. Bull IceStats",
          "type": "product"
        }
      ],
      "89": [
        {
          "id": "product:Ronny L. Bull IceStats",
          "keyphrase": "Ronny L. Bull IceStats",
          "type": "product"
        }
      ],
      "22": [
        {
          "id": "version:n/a through 1.3",
          "keyphrase": "n/a through 1.3",
          "type": "version"
        }
      ]
    },
    "relevant_cwes": [
      {
        "metadata": {
          "doc_id": "352",
          "name": "Cross-Site Request Forgery (CSRF)",
          "source": "sparse",
          "original_content": "The web application does not, or can not, sufficiently verify whether a well-formed, valid, consistent request was intentionally provided by the user who submitted the request.",
          "keyphrase_sources": [
            {
              "id": "rootcause:lack of CSRF protection",
              "keyphrase": "lack of CSRF protection",
              "type": "rootcause"
            },
            {
              "id": "weakness:XSS",
              "keyphrase": "XSS",
              "type": "weakness"
            },
            {
              "id": "weakness:cross-site scripting",
              "keyphrase": "cross-site scripting",
              "type": "weakness"
            },
            {
              "id": "product:Ronny L. Bull IceStats",
              "keyphrase": "Ronny L. Bull IceStats",
              "type": "product"
            },
            {
              "id": "version:n/a through 1.3",
              "keyphrase": "n/a through 1.3",
              "type": "version"
            }
          ]
        },
        "similarity": 269.6954048494395
      },
      {
        "metadata": {
          "doc_id": "434",
          "name": "Unrestricted Upload of File with Dangerous Type",
          "source": "sparse",
          "original_content": "The product allows the upload or transfer of dangerous file types that are automatically processed within its environment.",
          "keyphrase_sources": [
            {
              "id": "rootcause:lack of CSRF protection",
              "keyphrase": "lack of CSRF protection",
              "type": "rootcause"
            },
            {
              "id": "version:n/a through 1.3",
              "keyphrase": "n/a through 1.3",
              "type": "version"
            }
          ]
        },
        "similarity": 198.55552441013666
      },
      {
        "metadata": {
          "doc_id": "116",
          "name": "Improper Encoding or Escaping of Output",
          "source": "sparse",
          "original_content": "The product prepares a structured message for communication with another component, but encoding or escaping of the data is either missing or done incorrectly. As a result, the intended structure of the message is not preserved.",
          "keyphrase_sources": [
            {
              "id": "rootcause:lack of CSRF protection",
              "keyphrase": "lack of CSRF protection",
              "type": "rootcause"
            },
            {
              "id": "weakness:XSS",
              "keyphrase": "XSS",
              "type": "weakness"
            },
            {
              "id": "weakness:cross-site scripting",
              "keyphrase": "cross-site scripting",
              "type": "weakness"
            }
          ]
        },
        "similarity": 190.85721412577982
      },
      {
        "metadata": {
          "doc_id": "80",
          "name": "Improper Neutralization of Script-Related HTML Tags in a Web Page (Basic XSS)",
          "source": "sparse",
          "original_content": "The product receives input from an upstream component, but it does not neutralize or incorrectly neutralizes special characters such as \"<\", \">\", and \"&\" that could be interpreted as web-scripting elements when they are sent to a downstream component that processes web pages.",
          "keyphrase_sources": [
            {
              "id": "weakness:cross-site scripting",
              "keyphrase": "cross-site scripting",
              "type": "weakness"
            }
          ]
        },
        "similarity": 190.7090344076184
      },
      {
        "metadata": {
          "doc_id": "79",
          "name": "Improper Neutralization of Input During Web Page Generation ('Cross-site Scripting')",
          "source": "sparse",
          "original_content": "The product does not neutralize or incorrectly neutralizes user-controllable input before it is placed in output that is used as a web page that is served to other users.",
          "keyphrase_sources": [
            {
              "id": "rootcause:lack of CSRF protection",
              "keyphrase": "lack of CSRF protection",
              "type": "rootcause"
            },
            {
              "id": "weakness:XSS",
              "keyphrase": "XSS",
              "type": "weakness"
            },
            {
              "id": "weakness:cross-site scripting",
              "keyphrase": "cross-site scripting",
              "type": "weakness"
            },
            {
              "id": "product:Ronny L. Bull IceStats",
              "keyphrase": "Ronny L. Bull IceStats",
              "type": "product"
            },
            {
              "id": "version:n/a through 1.3",
              "keyphrase": "n/a through 1.3",
              "type": "version"
            }
          ]
        },
        "similarity": 187.0583031699984
      },
      {
        "metadata": {
          "doc_id": "1004",
          "name": "Sensitive Cookie Without 'HttpOnly' Flag",
          "source": "sparse",
          "original_content": "The product uses a cookie to store sensitive information, but the cookie is not marked with the HttpOnly flag.",
          "keyphrase_sources": [
            {
              "id": "rootcause:lack of CSRF protection",
              "keyphrase": "lack of CSRF protection",
              "type": "rootcause"
            },
            {
              "id": "weakness:XSS",
              "keyphrase": "XSS",
              "type": "weakness"
            },
            {
              "id": "weakness:cross-site scripting",
              "keyphrase": "cross-site scripting",
              "type": "weakness"
            }
          ]
        },
        "similarity": 176.82537553364966
      },
      {
        "metadata": {
          "doc_id": "918",
          "name": "Server-Side Request Forgery (SSRF)",
          "source": "sparse",
          "original_content": "The web server receives a URL or similar request from an upstream component and retrieves the contents of this URL, but it does not sufficiently ensure that the request is being sent to the expected destination.",
          "keyphrase_sources": [
            {
              "id": "weakness:XSS",
              "keyphrase": "XSS",
              "type": "weakness"
            }
          ]
        },
        "similarity": 136.18060110226702
      },
      {
        "metadata": {
          "doc_id": "22",
          "name": "Improper Limitation of a Pathname to a Restricted Directory ('Path Traversal')",
          "source": "sparse",
          "original_content": "The product uses external input to construct a pathname that is intended to identify a file or directory that is located underneath a restricted parent directory, but the product does not properly neutralize special elements within the pathname that can cause the pathname to resolve to a location that is outside of the restricted directory.",
          "keyphrase_sources": [
            {
              "id": "version:n/a through 1.3",
              "keyphrase": "n/a through 1.3",
              "type": "version"
            }
          ]
        },
        "similarity": 61.2177042001252
      },
      {
        "metadata": {
          "doc_id": "611",
          "name": "Improper Restriction of XML External Entity Reference",
          "source": "sparse",
          "original_content": "The product processes an XML document that can contain XML entities with URIs that resolve to documents outside of the intended sphere of control, causing the product to embed incorrect documents into its output.",
          "keyphrase_sources": [
            {
              "id": "product:Ronny L. Bull IceStats",
              "keyphrase": "Ronny L. Bull IceStats",
              "type": "product"
            },
            {
              "id": "version:n/a through 1.3",
              "keyphrase": "n/a through 1.3",
              "type": "version"
            }
          ]
        },
        "similarity": 45.10253700245566
      },
      {
        "metadata": {
          "doc_id": "444",
          "name": "Inconsistent Interpretation of HTTP Requests ('HTTP Request/Response Smuggling')",
          "source": "sparse",
          "original_content": "The product acts as an intermediary HTTP agent\n         (such as a proxy or firewall) in the data flow between two\n         entities such as a client and server, but it does not\n         interpret malformed HTTP requests or responses in ways that\n         are consistent with how the messages will be processed by\n         those entities that are at the ultimate destination.",
          "keyphrase_sources": [
            {
              "id": "product:Ronny L. Bull IceStats",
              "keyphrase": "Ronny L. Bull IceStats",
              "type": "product"
            }
          ]
        },
        "similarity": 43.22782203986487
      },
      {
        "metadata": {
          "doc_id": "89",
          "name": "Improper Neutralization of Special Elements used in an SQL Command ('SQL Injection')",
          "source": "sparse",
          "original_content": "The product constructs all or part of an SQL command using externally-influenced input from an upstream component, but it does not neutralize or incorrectly neutralizes special elements that could modify the intended SQL command when it is sent to a downstream component. Without sufficient removal or quoting of SQL syntax in user-controllable inputs, the generated SQL query can cause those inputs to be interpreted as SQL instead of ordinary user data.",
          "keyphrase_sources": [
            {
              "id": "product:Ronny L. Bull IceStats",
              "keyphrase": "Ronny L. Bull IceStats",
              "type": "product"
            }
          ]
        },
        "similarity": 42.54698413248697
      }
    ],
    "enhanced_query": "# Vulnerability Description\n\n    Cross-Site Request Forgery (CSRF) vulnerability in Ronny L. Bull IceStats allows Stored **XSS**.This issue affects IceStats from n/a through 1.3.\n\n    # Keyphrase-Specific CWE Analysis\n    This vulnerability contains multiple keyphrases that may map to different CWEs. \n    Please analyze each keyphrase separately and determine the most appropriate CWE(s) for each.\n\n    ## ROOTCAUSE: 'lack of CSRF protection'\n\nRelevant CWEs for this ROOTCAUSE:\n\n### 1. CWE-352: Cross-Site Request Forgery (CSRF) (Score: 269.70)\n\nThe web application does not, or can not, sufficiently verify whether a well-formed, valid, consistent request was intentionally provided by the user who submitted the request....\n\n### 2. CWE-434: Unrestricted Upload of File with Dangerous Type (Score: 198.56)\n\nThe product allows the upload or transfer of dangerous file types that are automatically processed within its environment....\n\n### 3. CWE-116: Improper Encoding or Escaping of Output (Score: 190.86)\n\nThe product prepares a structured message for communication with another component, but encoding or escaping of the data is either missing or done incorrectly. As a result, the intended structure of the message is not preserved....\n\n### 4. CWE-79: Improper Neutralization of Input During Web Page Generation ('Cross-site Scripting') (Score: 187.06)\n\nThe product does not neutralize or incorrectly neutralizes user-controllable input before it is placed in output that is used as a web page that is served to other users....\n\n### 5. CWE-1004: Sensitive Cookie Without 'HttpOnly' Flag (Score: 176.83)\n\nThe product uses a cookie to store sensitive information, but the cookie is not marked with the HttpOnly flag....\n\n## WEAKNESS: 'XSS'\n\nRelevant CWEs for this WEAKNESS:\n\n### 1. CWE-352: Cross-Site Request Forgery (CSRF) (Score: 269.70)\n\nThe web application does not, or can not, sufficiently verify whether a well-formed, valid, consistent request was intentionally provided by the user who submitted the request....\n\n### 2. CWE-116: Improper Encoding or Escaping of Output (Score: 190.86)\n\nThe product prepares a structured message for communication with another component, but encoding or escaping of the data is either missing or done incorrectly. As a result, the intended structure of the message is not preserved....\n\n### 3. CWE-79: Improper Neutralization of Input During Web Page Generation ('Cross-site Scripting') (Score: 187.06)\n\nThe product does not neutralize or incorrectly neutralizes user-controllable input before it is placed in output that is used as a web page that is served to other users....\n\n### 4. CWE-1004: Sensitive Cookie Without 'HttpOnly' Flag (Score: 176.83)\n\nThe product uses a cookie to store sensitive information, but the cookie is not marked with the HttpOnly flag....\n\n### 5. CWE-918: Server-Side Request Forgery (SSRF) (Score: 136.18)\n\nThe web server receives a URL or similar request from an upstream component and retrieves the contents of this URL, but it does not sufficiently ensure that the request is being sent to the expected destination....\n\n## WEAKNESS: 'cross-site scripting'\n\nRelevant CWEs for this WEAKNESS:\n\n### 1. CWE-352: Cross-Site Request Forgery (CSRF) (Score: 269.70)\n\nThe web application does not, or can not, sufficiently verify whether a well-formed, valid, consistent request was intentionally provided by the user who submitted the request....\n\n### 2. CWE-116: Improper Encoding or Escaping of Output (Score: 190.86)\n\nThe product prepares a structured message for communication with another component, but encoding or escaping of the data is either missing or done incorrectly. As a result, the intended structure of the message is not preserved....\n\n### 3. CWE-80: Improper Neutralization of Script-Related HTML Tags in a Web Page (Basic XSS) (Score: 190.71)\n\nThe product receives input from an upstream component, but it does not neutralize or incorrectly neutralizes special characters such as \"<\", \">\", and \"&\" that could be interpreted as web-scripting elements when they are sent to a downstream component that processes web pages....\n\n### 4. CWE-79: Improper Neutralization of Input During Web Page Generation ('Cross-site Scripting') (Score: 187.06)\n\nThe product does not neutralize or incorrectly neutralizes user-controllable input before it is placed in output that is used as a web page that is served to other users....\n\n### 5. CWE-1004: Sensitive Cookie Without 'HttpOnly' Flag (Score: 176.83)\n\nThe product uses a cookie to store sensitive information, but the cookie is not marked with the HttpOnly flag....\n\n## PRODUCT: 'Ronny L. Bull IceStats'\n\nRelevant CWEs for this PRODUCT:\n\n### 1. CWE-352: Cross-Site Request Forgery (CSRF) (Score: 269.70)\n\nThe web application does not, or can not, sufficiently verify whether a well-formed, valid, consistent request was intentionally provided by the user who submitted the request....\n\n### 2. CWE-79: Improper Neutralization of Input During Web Page Generation ('Cross-site Scripting') (Score: 187.06)\n\nThe product does not neutralize or incorrectly neutralizes user-controllable input before it is placed in output that is used as a web page that is served to other users....\n\n### 3. CWE-611: Improper Restriction of XML External Entity Reference (Score: 45.10)\n\nThe product processes an XML document that can contain XML entities with URIs that resolve to documents outside of the intended sphere of control, causing the product to embed incorrect documents into its output....\n\n### 4. CWE-444: Inconsistent Interpretation of HTTP Requests ('HTTP Request/Response Smuggling') (Score: 43.23)\n\nThe product acts as an intermediary HTTP agent\n         (such as a proxy or firewall) in the data flow between two\n         entities such as a client and server, but it does not\n         interpret malformed HTTP requests or responses in ways that\n         are consistent with how the messages will be...\n\n### 5. CWE-89: Improper Neutralization of Special Elements used in an SQL Command ('SQL Injection') (Score: 42.55)\n\nThe product constructs all or part of an SQL command using externally-influenced input from an upstream component, but it does not neutralize or incorrectly neutralizes special elements that could modify the intended SQL command when it is sent to a downstream component. Without sufficient removal o...\n\n## VERSION: 'n/a through 1.3'\n\nRelevant CWEs for this VERSION:\n\n### 1. CWE-352: Cross-Site Request Forgery (CSRF) (Score: 269.70)\n\nThe web application does not, or can not, sufficiently verify whether a well-formed, valid, consistent request was intentionally provided by the user who submitted the request....\n\n### 2. CWE-434: Unrestricted Upload of File with Dangerous Type (Score: 198.56)\n\nThe product allows the upload or transfer of dangerous file types that are automatically processed within its environment....\n\n### 3. CWE-79: Improper Neutralization of Input During Web Page Generation ('Cross-site Scripting') (Score: 187.06)\n\nThe product does not neutralize or incorrectly neutralizes user-controllable input before it is placed in output that is used as a web page that is served to other users....\n\n### 4. CWE-22: Improper Limitation of a Pathname to a Restricted Directory ('Path Traversal') (Score: 61.22)\n\nThe product uses external input to construct a pathname that is intended to identify a file or directory that is located underneath a restricted parent directory, but the product does not properly neutralize special elements within the pathname that can cause the pathname to resolve to a location th...\n\n### 5. CWE-611: Improper Restriction of XML External Entity Reference (Score: 45.10)\n\nThe product processes an XML document that can contain XML entities with URIs that resolve to documents outside of the intended sphere of control, causing the product to embed incorrect documents into its output....\n\n\n    # Analysis Instructions\n    1. For each keyphrase, identify the most appropriate CWE(s) that represent the weakness.\n    2. Consider how the different keyphrases might relate to each other in the vulnerability chain.\n    3. Provide a final determination of primary CWE(s) and any secondary CWEs.\n    4. Format your response using the standard analysis template.\n\n    Please analyze how these different weaknesses interact and provide a comprehensive CWE classification.\n    "
  },
  "retrieval_time": 1.2293860912322998
}