{
  "vulnerability_info": "VulnerabilityInfo(cve_id='CVE-2024-7015', description='**Improper Authentication**, **Missing Authentication for Critical Function**, Improper Authorization vulnerability in Profelis Informatics and Consulting PassBox allows Authentication Abuse.This issue affects PassBox before v1.2.', key_phrases={'rootcause': ['Improper Authentication', 'Missing Authentication for Critical Function'], 'weakness': '', 'impact': 'Authentication Abuse', 'vector': '', 'attacker': '', 'product': 'Profelis Informatics and Consulting PassBox', 'version': 'before v1.2', 'component': ''}, reference_content='UNRELATED', similar_info={'cwe_distribution': {}, 'cwe_consensus': '', 'similarity_stats': {'thresholds': [], 'total_samples_by_threshold': {}, 'top_cwes_by_threshold': {}}}, similarity_summary=SimilarityInsight(consensus_cwe='', top_cwes=[], confidence_levels={}, total_samples=0), analysis='', analysis_with_relationships='', criticism='', resolution='', relevant_cwes=[{'metadata': {'doc_id': '89', 'name': \"Improper Neutralization of Special Elements used in an SQL Command ('SQL Injection')\", 'source': 'sparse', 'original_content': 'The product constructs all or part of an SQL command using externally-influenced input from an upstream component, but it does not neutralize or incorrectly neutralizes special elements that could modify the intended SQL command when it is sent to a downstream component. Without sufficient removal or quoting of SQL syntax in user-controllable inputs, the generated SQL query can cause those inputs to be interpreted as SQL instead of ordinary user data.', 'keyphrase_sources': [{'id': 'rootcause:Missing Authentication for Critical Function', 'keyphrase': 'Missing Authentication for Critical Function', 'type': 'rootcause'}]}, 'similarity': np.float64(160.2795406698442)}, {'metadata': {'doc_id': '306', 'name': 'Missing Authentication for Critical Function', 'source': 'sparse', 'original_content': 'The product does not perform any authentication for functionality that requires a provable user identity or consumes a significant amount of resources.', 'keyphrase_sources': [{'id': 'rootcause:Improper Authentication', 'keyphrase': 'Improper Authentication', 'type': 'rootcause'}, {'id': 'rootcause:Missing Authentication for Critical Function', 'keyphrase': 'Missing Authentication for Critical Function', 'type': 'rootcause'}, {'id': 'impact:Authentication Abuse', 'keyphrase': 'Authentication Abuse', 'type': 'impact'}, {'id': 'product:Profelis Informatics and Consulting PassBox', 'keyphrase': 'Profelis Informatics and Consulting PassBox', 'type': 'product'}, {'id': 'version:before v1.2', 'keyphrase': 'before v1.2', 'type': 'version'}]}, 'similarity': np.float64(142.3097209563171)}, {'metadata': {'doc_id': '287', 'name': 'Improper Authentication', 'source': 'sparse', 'original_content': 'When an actor claims to have a given identity, the product does not prove or insufficiently proves that the claim is correct.', 'keyphrase_sources': [{'id': 'rootcause:Improper Authentication', 'keyphrase': 'Improper Authentication', 'type': 'rootcause'}, {'id': 'rootcause:Missing Authentication for Critical Function', 'keyphrase': 'Missing Authentication for Critical Function', 'type': 'rootcause'}, {'id': 'impact:Authentication Abuse', 'keyphrase': 'Authentication Abuse', 'type': 'impact'}, {'id': 'product:Profelis Informatics and Consulting PassBox', 'keyphrase': 'Profelis Informatics and Consulting PassBox', 'type': 'product'}, {'id': 'version:before v1.2', 'keyphrase': 'before v1.2', 'type': 'version'}]}, 'similarity': np.float64(137.31179942951502)}, {'metadata': {'doc_id': '285', 'name': 'Improper Authorization', 'source': 'sparse', 'original_content': 'The product does not perform or incorrectly performs an authorization check when an actor attempts to access a resource or perform an action.', 'keyphrase_sources': [{'id': 'rootcause:Improper Authentication', 'keyphrase': 'Improper Authentication', 'type': 'rootcause'}, {'id': 'rootcause:Missing Authentication for Critical Function', 'keyphrase': 'Missing Authentication for Critical Function', 'type': 'rootcause'}, {'id': 'impact:Authentication Abuse', 'keyphrase': 'Authentication Abuse', 'type': 'impact'}, {'id': 'product:Profelis Informatics and Consulting PassBox', 'keyphrase': 'Profelis Informatics and Consulting PassBox', 'type': 'product'}, {'id': 'version:before v1.2', 'keyphrase': 'before v1.2', 'type': 'version'}]}, 'similarity': np.float64(130.61843197055404)}, {'metadata': {'doc_id': '472', 'name': 'External Control of Assumed-Immutable Web Parameter', 'source': 'sparse', 'original_content': 'The web application does not sufficiently verify inputs that are assumed to be immutable but are actually externally controllable, such as hidden form fields.', 'keyphrase_sources': [{'id': 'rootcause:Improper Authentication', 'keyphrase': 'Improper Authentication', 'type': 'rootcause'}, {'id': 'rootcause:Missing Authentication for Critical Function', 'keyphrase': 'Missing Authentication for Critical Function', 'type': 'rootcause'}, {'id': 'product:Profelis Informatics and Consulting PassBox', 'keyphrase': 'Profelis Informatics and Consulting PassBox', 'type': 'product'}, {'id': 'version:before v1.2', 'keyphrase': 'before v1.2', 'type': 'version'}]}, 'similarity': np.float64(127.94773316346398)}, {'metadata': {'doc_id': '425', 'name': \"Direct Request ('Forced Browsing')\", 'source': 'sparse', 'original_content': 'The web application does not adequately enforce appropriate authorization on all restricted URLs, scripts, or files.', 'keyphrase_sources': [{'id': 'rootcause:Improper Authentication', 'keyphrase': 'Improper Authentication', 'type': 'rootcause'}, {'id': 'version:before v1.2', 'keyphrase': 'before v1.2', 'type': 'version'}]}, 'similarity': np.float64(126.04971098409038)}, {'metadata': {'doc_id': '80', 'name': 'Improper Neutralization of Script-Related HTML Tags in a Web Page (Basic XSS)', 'source': 'sparse', 'original_content': 'The product receives input from an upstream component, but it does not neutralize or incorrectly neutralizes special characters such as \"<\", \">\", and \"&\" that could be interpreted as web-scripting elements when they are sent to a downstream component that processes web pages.', 'keyphrase_sources': [{'id': 'product:Profelis Informatics and Consulting PassBox', 'keyphrase': 'Profelis Informatics and Consulting PassBox', 'type': 'product'}]}, 'similarity': np.float64(55.77433830598242)}, {'metadata': {'doc_id': '798', 'name': 'Use of Hard-coded Credentials', 'source': 'sparse', 'original_content': 'The product contains hard-coded credentials, such as a password or cryptographic key.', 'keyphrase_sources': [{'id': 'impact:Authentication Abuse', 'keyphrase': 'Authentication Abuse', 'type': 'impact'}]}, 'similarity': np.float64(43.09935064213471)}, {'metadata': {'doc_id': '1390', 'name': 'Weak Authentication', 'source': 'sparse', 'original_content': 'The product uses an authentication mechanism to restrict access to specific users or identities, but the mechanism does not sufficiently prove that the claimed identity is correct.', 'keyphrase_sources': [{'id': 'impact:Authentication Abuse', 'keyphrase': 'Authentication Abuse', 'type': 'impact'}]}, 'similarity': np.float64(42.26311194908533)}], identified_cwes={'analyzer': [], 'critic_additional': []})",
  "retrieval_results": {
    "has_multiple_keyphrases": true,
    "keyphrase_cwe_sets": {
      "rootcause:Improper Authentication": {
        "keyphrase": "Improper Authentication",
        "type": "rootcause",
        "cwes": [
          {
            "metadata": {
              "doc_id": "306",
              "name": "Missing Authentication for Critical Function",
              "source": "sparse",
              "original_content": "The product does not perform any authentication for functionality that requires a provable user identity or consumes a significant amount of resources.",
              "keyphrase_sources": [
                {
                  "id": "rootcause:Improper Authentication",
                  "keyphrase": "Improper Authentication",
                  "type": "rootcause"
                },
                {
                  "id": "rootcause:Missing Authentication for Critical Function",
                  "keyphrase": "Missing Authentication for Critical Function",
                  "type": "rootcause"
                },
                {
                  "id": "impact:Authentication Abuse",
                  "keyphrase": "Authentication Abuse",
                  "type": "impact"
                },
                {
                  "id": "product:Profelis Informatics and Consulting PassBox",
                  "keyphrase": "Profelis Informatics and Consulting PassBox",
                  "type": "product"
                },
                {
                  "id": "version:before v1.2",
                  "keyphrase": "before v1.2",
                  "type": "version"
                }
              ]
            },
            "similarity": 142.3097209563171
          },
          {
            "metadata": {
              "doc_id": "287",
              "name": "Improper Authentication",
              "source": "sparse",
              "original_content": "When an actor claims to have a given identity, the product does not prove or insufficiently proves that the claim is correct.",
              "keyphrase_sources": [
                {
                  "id": "rootcause:Improper Authentication",
                  "keyphrase": "Improper Authentication",
                  "type": "rootcause"
                },
                {
                  "id": "rootcause:Missing Authentication for Critical Function",
                  "keyphrase": "Missing Authentication for Critical Function",
                  "type": "rootcause"
                },
                {
                  "id": "impact:Authentication Abuse",
                  "keyphrase": "Authentication Abuse",
                  "type": "impact"
                },
                {
                  "id": "product:Profelis Informatics and Consulting PassBox",
                  "keyphrase": "Profelis Informatics and Consulting PassBox",
                  "type": "product"
                },
                {
                  "id": "version:before v1.2",
                  "keyphrase": "before v1.2",
                  "type": "version"
                }
              ]
            },
            "similarity": 137.31179942951502
          },
          {
            "metadata": {
              "doc_id": "285",
              "name": "Improper Authorization",
              "source": "sparse",
              "original_content": "The product does not perform or incorrectly performs an authorization check when an actor attempts to access a resource or perform an action.",
              "keyphrase_sources": [
                {
                  "id": "rootcause:Improper Authentication",
                  "keyphrase": "Improper Authentication",
                  "type": "rootcause"
                },
                {
                  "id": "rootcause:Missing Authentication for Critical Function",
                  "keyphrase": "Missing Authentication for Critical Function",
                  "type": "rootcause"
                },
                {
                  "id": "impact:Authentication Abuse",
                  "keyphrase": "Authentication Abuse",
                  "type": "impact"
                },
                {
                  "id": "product:Profelis Informatics and Consulting PassBox",
                  "keyphrase": "Profelis Informatics and Consulting PassBox",
                  "type": "product"
                },
                {
                  "id": "version:before v1.2",
                  "keyphrase": "before v1.2",
                  "type": "version"
                }
              ]
            },
            "similarity": 130.61843197055404
          },
          {
            "metadata": {
              "doc_id": "472",
              "name": "External Control of Assumed-Immutable Web Parameter",
              "source": "sparse",
              "original_content": "The web application does not sufficiently verify inputs that are assumed to be immutable but are actually externally controllable, such as hidden form fields.",
              "keyphrase_sources": [
                {
                  "id": "rootcause:Improper Authentication",
                  "keyphrase": "Improper Authentication",
                  "type": "rootcause"
                },
                {
                  "id": "rootcause:Missing Authentication for Critical Function",
                  "keyphrase": "Missing Authentication for Critical Function",
                  "type": "rootcause"
                },
                {
                  "id": "product:Profelis Informatics and Consulting PassBox",
                  "keyphrase": "Profelis Informatics and Consulting PassBox",
                  "type": "product"
                },
                {
                  "id": "version:before v1.2",
                  "keyphrase": "before v1.2",
                  "type": "version"
                }
              ]
            },
            "similarity": 127.94773316346398
          },
          {
            "metadata": {
              "doc_id": "425",
              "name": "Direct Request ('Forced Browsing')",
              "source": "sparse",
              "original_content": "The web application does not adequately enforce appropriate authorization on all restricted URLs, scripts, or files.",
              "keyphrase_sources": [
                {
                  "id": "rootcause:Improper Authentication",
                  "keyphrase": "Improper Authentication",
                  "type": "rootcause"
                },
                {
                  "id": "version:before v1.2",
                  "keyphrase": "before v1.2",
                  "type": "version"
                }
              ]
            },
            "similarity": 126.04971098409038
          }
        ]
      },
      "rootcause:Missing Authentication for Critical Function": {
        "keyphrase": "Missing Authentication for Critical Function",
        "type": "rootcause",
        "cwes": [
          {
            "metadata": {
              "doc_id": "306",
              "name": "Missing Authentication for Critical Function",
              "source": "sparse",
              "original_content": "The product does not perform any authentication for functionality that requires a provable user identity or consumes a significant amount of resources."
            },
            "similarity": 191.8631881767032
          },
          {
            "metadata": {
              "doc_id": "287",
              "name": "Improper Authentication",
              "source": "sparse",
              "original_content": "When an actor claims to have a given identity, the product does not prove or insufficiently proves that the claim is correct."
            },
            "similarity": 166.64746916634297
          },
          {
            "metadata": {
              "doc_id": "89",
              "name": "Improper Neutralization of Special Elements used in an SQL Command ('SQL Injection')",
              "source": "sparse",
              "original_content": "The product constructs all or part of an SQL command using externally-influenced input from an upstream component, but it does not neutralize or incorrectly neutralizes special elements that could modify the intended SQL command when it is sent to a downstream component. Without sufficient removal or quoting of SQL syntax in user-controllable inputs, the generated SQL query can cause those inputs to be interpreted as SQL instead of ordinary user data.",
              "keyphrase_sources": [
                {
                  "id": "rootcause:Missing Authentication for Critical Function",
                  "keyphrase": "Missing Authentication for Critical Function",
                  "type": "rootcause"
                }
              ]
            },
            "similarity": 160.2795406698442
          },
          {
            "metadata": {
              "doc_id": "285",
              "name": "Improper Authorization",
              "source": "sparse",
              "original_content": "The product does not perform or incorrectly performs an authorization check when an actor attempts to access a resource or perform an action."
            },
            "similarity": 158.94184385348433
          },
          {
            "metadata": {
              "doc_id": "472",
              "name": "External Control of Assumed-Immutable Web Parameter",
              "source": "sparse",
              "original_content": "The web application does not sufficiently verify inputs that are assumed to be immutable but are actually externally controllable, such as hidden form fields."
            },
            "similarity": 156.02506698264318
          }
        ]
      },
      "impact:Authentication Abuse": {
        "keyphrase": "Authentication Abuse",
        "type": "impact",
        "cwes": [
          {
            "metadata": {
              "doc_id": "306",
              "name": "Missing Authentication for Critical Function",
              "source": "sparse",
              "original_content": "The product does not perform any authentication for functionality that requires a provable user identity or consumes a significant amount of resources."
            },
            "similarity": 50.10221858420071
          },
          {
            "metadata": {
              "doc_id": "798",
              "name": "Use of Hard-coded Credentials",
              "source": "sparse",
              "original_content": "The product contains hard-coded credentials, such as a password or cryptographic key.",
              "keyphrase_sources": [
                {
                  "id": "impact:Authentication Abuse",
                  "keyphrase": "Authentication Abuse",
                  "type": "impact"
                }
              ]
            },
            "similarity": 43.09935064213471
          },
          {
            "metadata": {
              "doc_id": "287",
              "name": "Improper Authentication",
              "source": "sparse",
              "original_content": "When an actor claims to have a given identity, the product does not prove or insufficiently proves that the claim is correct."
            },
            "similarity": 43.08012464026647
          },
          {
            "metadata": {
              "doc_id": "1390",
              "name": "Weak Authentication",
              "source": "sparse",
              "original_content": "The product uses an authentication mechanism to restrict access to specific users or identities, but the mechanism does not sufficiently prove that the claimed identity is correct.",
              "keyphrase_sources": [
                {
                  "id": "impact:Authentication Abuse",
                  "keyphrase": "Authentication Abuse",
                  "type": "impact"
                }
              ]
            },
            "similarity": 42.26311194908533
          },
          {
            "metadata": {
              "doc_id": "285",
              "name": "Improper Authorization",
              "source": "sparse",
              "original_content": "The product does not perform or incorrectly performs an authorization check when an actor attempts to access a resource or perform an action."
            },
            "similarity": 40.77025996222423
          }
        ]
      },
      "product:Profelis Informatics and Consulting PassBox": {
        "keyphrase": "Profelis Informatics and Consulting PassBox",
        "type": "product",
        "cwes": [
          {
            "metadata": {
              "doc_id": "80",
              "name": "Improper Neutralization of Script-Related HTML Tags in a Web Page (Basic XSS)",
              "source": "sparse",
              "original_content": "The product receives input from an upstream component, but it does not neutralize or incorrectly neutralizes special characters such as \"<\", \">\", and \"&\" that could be interpreted as web-scripting elements when they are sent to a downstream component that processes web pages.",
              "keyphrase_sources": [
                {
                  "id": "product:Profelis Informatics and Consulting PassBox",
                  "keyphrase": "Profelis Informatics and Consulting PassBox",
                  "type": "product"
                }
              ]
            },
            "similarity": 55.77433830598242
          },
          {
            "metadata": {
              "doc_id": "306",
              "name": "Missing Authentication for Critical Function",
              "source": "sparse",
              "original_content": "The product does not perform any authentication for functionality that requires a provable user identity or consumes a significant amount of resources."
            },
            "similarity": 47.421988660286814
          },
          {
            "metadata": {
              "doc_id": "287",
              "name": "Improper Authentication",
              "source": "sparse",
              "original_content": "When an actor claims to have a given identity, the product does not prove or insufficiently proves that the claim is correct."
            },
            "similarity": 44.29918150342443
          },
          {
            "metadata": {
              "doc_id": "285",
              "name": "Improper Authorization",
              "source": "sparse",
              "original_content": "The product does not perform or incorrectly performs an authorization check when an actor attempts to access a resource or perform an action."
            },
            "similarity": 43.92739318540413
          },
          {
            "metadata": {
              "doc_id": "472",
              "name": "External Control of Assumed-Immutable Web Parameter",
              "source": "sparse",
              "original_content": "The web application does not sufficiently verify inputs that are assumed to be immutable but are actually externally controllable, such as hidden form fields."
            },
            "similarity": 42.73277358668963
          }
        ]
      },
      "version:before v1.2": {
        "keyphrase": "before v1.2",
        "type": "version",
        "cwes": [
          {
            "metadata": {
              "doc_id": "306",
              "name": "Missing Authentication for Critical Function",
              "source": "sparse",
              "original_content": "The product does not perform any authentication for functionality that requires a provable user identity or consumes a significant amount of resources."
            },
            "similarity": 47.95894685425394
          },
          {
            "metadata": {
              "doc_id": "287",
              "name": "Improper Authentication",
              "source": "sparse",
              "original_content": "When an actor claims to have a given identity, the product does not prove or insufficiently proves that the claim is correct."
            },
            "similarity": 46.79558247539722
          },
          {
            "metadata": {
              "doc_id": "472",
              "name": "External Control of Assumed-Immutable Web Parameter",
              "source": "sparse",
              "original_content": "The web application does not sufficiently verify inputs that are assumed to be immutable but are actually externally controllable, such as hidden form fields."
            },
            "similarity": 46.26788627723518
          },
          {
            "metadata": {
              "doc_id": "425",
              "name": "Direct Request ('Forced Browsing')",
              "source": "sparse",
              "original_content": "The web application does not adequately enforce appropriate authorization on all restricted URLs, scripts, or files."
            },
            "similarity": 45.728361407725075
          },
          {
            "metadata": {
              "doc_id": "285",
              "name": "Improper Authorization",
              "source": "sparse",
              "original_content": "The product does not perform or incorrectly performs an authorization check when an actor attempts to access a resource or perform an action."
            },
            "similarity": 44.76736997943267
          }
        ]
      }
    },
    "keyphrase_mapping": {
      "306": [
        {
          "id": "rootcause:Improper Authentication",
          "keyphrase": "Improper Authentication",
          "type": "rootcause"
        },
        {
          "id": "rootcause:Missing Authentication for Critical Function",
          "keyphrase": "Missing Authentication for Critical Function",
          "type": "rootcause"
        },
        {
          "id": "impact:Authentication Abuse",
          "keyphrase": "Authentication Abuse",
          "type": "impact"
        },
        {
          "id": "product:Profelis Informatics and Consulting PassBox",
          "keyphrase": "Profelis Informatics and Consulting PassBox",
          "type": "product"
        },
        {
          "id": "version:before v1.2",
          "keyphrase": "before v1.2",
          "type": "version"
        }
      ],
      "287": [
        {
          "id": "rootcause:Improper Authentication",
          "keyphrase": "Improper Authentication",
          "type": "rootcause"
        },
        {
          "id": "rootcause:Missing Authentication for Critical Function",
          "keyphrase": "Missing Authentication for Critical Function",
          "type": "rootcause"
        },
        {
          "id": "impact:Authentication Abuse",
          "keyphrase": "Authentication Abuse",
          "type": "impact"
        },
        {
          "id": "product:Profelis Informatics and Consulting PassBox",
          "keyphrase": "Profelis Informatics and Consulting PassBox",
          "type": "product"
        },
        {
          "id": "version:before v1.2",
          "keyphrase": "before v1.2",
          "type": "version"
        }
      ],
      "285": [
        {
          "id": "rootcause:Improper Authentication",
          "keyphrase": "Improper Authentication",
          "type": "rootcause"
        },
        {
          "id": "rootcause:Missing Authentication for Critical Function",
          "keyphrase": "Missing Authentication for Critical Function",
          "type": "rootcause"
        },
        {
          "id": "impact:Authentication Abuse",
          "keyphrase": "Authentication Abuse",
          "type": "impact"
        },
        {
          "id": "product:Profelis Informatics and Consulting PassBox",
          "keyphrase": "Profelis Informatics and Consulting PassBox",
          "type": "product"
        },
        {
          "id": "version:before v1.2",
          "keyphrase": "before v1.2",
          "type": "version"
        }
      ],
      "472": [
        {
          "id": "rootcause:Improper Authentication",
          "keyphrase": "Improper Authentication",
          "type": "rootcause"
        },
        {
          "id": "rootcause:Missing Authentication for Critical Function",
          "keyphrase": "Missing Authentication for Critical Function",
          "type": "rootcause"
        },
        {
          "id": "product:Profelis Informatics and Consulting PassBox",
          "keyphrase": "Profelis Informatics and Consulting PassBox",
          "type": "product"
        },
        {
          "id": "version:before v1.2",
          "keyphrase": "before v1.2",
          "type": "version"
        }
      ],
      "425": [
        {
          "id": "rootcause:Improper Authentication",
          "keyphrase": "Improper Authentication",
          "type": "rootcause"
        },
        {
          "id": "version:before v1.2",
          "keyphrase": "before v1.2",
          "type": "version"
        }
      ],
      "89": [
        {
          "id": "rootcause:Missing Authentication for Critical Function",
          "keyphrase": "Missing Authentication for Critical Function",
          "type": "rootcause"
        }
      ],
      "798": [
        {
          "id": "impact:Authentication Abuse",
          "keyphrase": "Authentication Abuse",
          "type": "impact"
        }
      ],
      "1390": [
        {
          "id": "impact:Authentication Abuse",
          "keyphrase": "Authentication Abuse",
          "type": "impact"
        }
      ],
      "80": [
        {
          "id": "product:Profelis Informatics and Consulting PassBox",
          "keyphrase": "Profelis Informatics and Consulting PassBox",
          "type": "product"
        }
      ]
    },
    "relevant_cwes": [
      {
        "metadata": {
          "doc_id": "89",
          "name": "Improper Neutralization of Special Elements used in an SQL Command ('SQL Injection')",
          "source": "sparse",
          "original_content": "The product constructs all or part of an SQL command using externally-influenced input from an upstream component, but it does not neutralize or incorrectly neutralizes special elements that could modify the intended SQL command when it is sent to a downstream component. Without sufficient removal or quoting of SQL syntax in user-controllable inputs, the generated SQL query can cause those inputs to be interpreted as SQL instead of ordinary user data.",
          "keyphrase_sources": [
            {
              "id": "rootcause:Missing Authentication for Critical Function",
              "keyphrase": "Missing Authentication for Critical Function",
              "type": "rootcause"
            }
          ]
        },
        "similarity": 160.2795406698442
      },
      {
        "metadata": {
          "doc_id": "306",
          "name": "Missing Authentication for Critical Function",
          "source": "sparse",
          "original_content": "The product does not perform any authentication for functionality that requires a provable user identity or consumes a significant amount of resources.",
          "keyphrase_sources": [
            {
              "id": "rootcause:Improper Authentication",
              "keyphrase": "Improper Authentication",
              "type": "rootcause"
            },
            {
              "id": "rootcause:Missing Authentication for Critical Function",
              "keyphrase": "Missing Authentication for Critical Function",
              "type": "rootcause"
            },
            {
              "id": "impact:Authentication Abuse",
              "keyphrase": "Authentication Abuse",
              "type": "impact"
            },
            {
              "id": "product:Profelis Informatics and Consulting PassBox",
              "keyphrase": "Profelis Informatics and Consulting PassBox",
              "type": "product"
            },
            {
              "id": "version:before v1.2",
              "keyphrase": "before v1.2",
              "type": "version"
            }
          ]
        },
        "similarity": 142.3097209563171
      },
      {
        "metadata": {
          "doc_id": "287",
          "name": "Improper Authentication",
          "source": "sparse",
          "original_content": "When an actor claims to have a given identity, the product does not prove or insufficiently proves that the claim is correct.",
          "keyphrase_sources": [
            {
              "id": "rootcause:Improper Authentication",
              "keyphrase": "Improper Authentication",
              "type": "rootcause"
            },
            {
              "id": "rootcause:Missing Authentication for Critical Function",
              "keyphrase": "Missing Authentication for Critical Function",
              "type": "rootcause"
            },
            {
              "id": "impact:Authentication Abuse",
              "keyphrase": "Authentication Abuse",
              "type": "impact"
            },
            {
              "id": "product:Profelis Informatics and Consulting PassBox",
              "keyphrase": "Profelis Informatics and Consulting PassBox",
              "type": "product"
            },
            {
              "id": "version:before v1.2",
              "keyphrase": "before v1.2",
              "type": "version"
            }
          ]
        },
        "similarity": 137.31179942951502
      },
      {
        "metadata": {
          "doc_id": "285",
          "name": "Improper Authorization",
          "source": "sparse",
          "original_content": "The product does not perform or incorrectly performs an authorization check when an actor attempts to access a resource or perform an action.",
          "keyphrase_sources": [
            {
              "id": "rootcause:Improper Authentication",
              "keyphrase": "Improper Authentication",
              "type": "rootcause"
            },
            {
              "id": "rootcause:Missing Authentication for Critical Function",
              "keyphrase": "Missing Authentication for Critical Function",
              "type": "rootcause"
            },
            {
              "id": "impact:Authentication Abuse",
              "keyphrase": "Authentication Abuse",
              "type": "impact"
            },
            {
              "id": "product:Profelis Informatics and Consulting PassBox",
              "keyphrase": "Profelis Informatics and Consulting PassBox",
              "type": "product"
            },
            {
              "id": "version:before v1.2",
              "keyphrase": "before v1.2",
              "type": "version"
            }
          ]
        },
        "similarity": 130.61843197055404
      },
      {
        "metadata": {
          "doc_id": "472",
          "name": "External Control of Assumed-Immutable Web Parameter",
          "source": "sparse",
          "original_content": "The web application does not sufficiently verify inputs that are assumed to be immutable but are actually externally controllable, such as hidden form fields.",
          "keyphrase_sources": [
            {
              "id": "rootcause:Improper Authentication",
              "keyphrase": "Improper Authentication",
              "type": "rootcause"
            },
            {
              "id": "rootcause:Missing Authentication for Critical Function",
              "keyphrase": "Missing Authentication for Critical Function",
              "type": "rootcause"
            },
            {
              "id": "product:Profelis Informatics and Consulting PassBox",
              "keyphrase": "Profelis Informatics and Consulting PassBox",
              "type": "product"
            },
            {
              "id": "version:before v1.2",
              "keyphrase": "before v1.2",
              "type": "version"
            }
          ]
        },
        "similarity": 127.94773316346398
      },
      {
        "metadata": {
          "doc_id": "425",
          "name": "Direct Request ('Forced Browsing')",
          "source": "sparse",
          "original_content": "The web application does not adequately enforce appropriate authorization on all restricted URLs, scripts, or files.",
          "keyphrase_sources": [
            {
              "id": "rootcause:Improper Authentication",
              "keyphrase": "Improper Authentication",
              "type": "rootcause"
            },
            {
              "id": "version:before v1.2",
              "keyphrase": "before v1.2",
              "type": "version"
            }
          ]
        },
        "similarity": 126.04971098409038
      },
      {
        "metadata": {
          "doc_id": "80",
          "name": "Improper Neutralization of Script-Related HTML Tags in a Web Page (Basic XSS)",
          "source": "sparse",
          "original_content": "The product receives input from an upstream component, but it does not neutralize or incorrectly neutralizes special characters such as \"<\", \">\", and \"&\" that could be interpreted as web-scripting elements when they are sent to a downstream component that processes web pages.",
          "keyphrase_sources": [
            {
              "id": "product:Profelis Informatics and Consulting PassBox",
              "keyphrase": "Profelis Informatics and Consulting PassBox",
              "type": "product"
            }
          ]
        },
        "similarity": 55.77433830598242
      },
      {
        "metadata": {
          "doc_id": "798",
          "name": "Use of Hard-coded Credentials",
          "source": "sparse",
          "original_content": "The product contains hard-coded credentials, such as a password or cryptographic key.",
          "keyphrase_sources": [
            {
              "id": "impact:Authentication Abuse",
              "keyphrase": "Authentication Abuse",
              "type": "impact"
            }
          ]
        },
        "similarity": 43.09935064213471
      },
      {
        "metadata": {
          "doc_id": "1390",
          "name": "Weak Authentication",
          "source": "sparse",
          "original_content": "The product uses an authentication mechanism to restrict access to specific users or identities, but the mechanism does not sufficiently prove that the claimed identity is correct.",
          "keyphrase_sources": [
            {
              "id": "impact:Authentication Abuse",
              "keyphrase": "Authentication Abuse",
              "type": "impact"
            }
          ]
        },
        "similarity": 42.26311194908533
      }
    ],
    "enhanced_query": "# Vulnerability Description\n\n    **Improper Authentication**, **Missing Authentication for Critical Function**, Improper Authorization vulnerability in Profelis Informatics and Consulting PassBox allows Authentication Abuse.This issue affects PassBox before v1.2.\n\n    # Keyphrase-Specific CWE Analysis\n    This vulnerability contains multiple keyphrases that may map to different CWEs. \n    Please analyze each keyphrase separately and determine the most appropriate CWE(s) for each.\n\n    ## ROOTCAUSE: 'Missing Authentication for Critical Function'\n\nRelevant CWEs for this ROOTCAUSE:\n\n### 1. CWE-89: Improper Neutralization of Special Elements used in an SQL Command ('SQL Injection') (Score: 160.28)\n\nThe product constructs all or part of an SQL command using externally-influenced input from an upstream component, but it does not neutralize or incorrectly neutralizes special elements that could modify the intended SQL command when it is sent to a downstream component. Without sufficient removal o...\n\n### 2. CWE-306: Missing Authentication for Critical Function (Score: 142.31)\n\nThe product does not perform any authentication for functionality that requires a provable user identity or consumes a significant amount of resources....\n\n### 3. CWE-287: Improper Authentication (Score: 137.31)\n\nWhen an actor claims to have a given identity, the product does not prove or insufficiently proves that the claim is correct....\n\n### 4. CWE-285: Improper Authorization (Score: 130.62)\n\nThe product does not perform or incorrectly performs an authorization check when an actor attempts to access a resource or perform an action....\n\n### 5. CWE-472: External Control of Assumed-Immutable Web Parameter (Score: 127.95)\n\nThe web application does not sufficiently verify inputs that are assumed to be immutable but are actually externally controllable, such as hidden form fields....\n\n## ROOTCAUSE: 'Improper Authentication'\n\nRelevant CWEs for this ROOTCAUSE:\n\n### 1. CWE-306: Missing Authentication for Critical Function (Score: 142.31)\n\nThe product does not perform any authentication for functionality that requires a provable user identity or consumes a significant amount of resources....\n\n### 2. CWE-287: Improper Authentication (Score: 137.31)\n\nWhen an actor claims to have a given identity, the product does not prove or insufficiently proves that the claim is correct....\n\n### 3. CWE-285: Improper Authorization (Score: 130.62)\n\nThe product does not perform or incorrectly performs an authorization check when an actor attempts to access a resource or perform an action....\n\n### 4. CWE-472: External Control of Assumed-Immutable Web Parameter (Score: 127.95)\n\nThe web application does not sufficiently verify inputs that are assumed to be immutable but are actually externally controllable, such as hidden form fields....\n\n### 5. CWE-425: Direct Request ('Forced Browsing') (Score: 126.05)\n\nThe web application does not adequately enforce appropriate authorization on all restricted URLs, scripts, or files....\n\n## IMPACT: 'Authentication Abuse'\n\nRelevant CWEs for this IMPACT:\n\n### 1. CWE-306: Missing Authentication for Critical Function (Score: 142.31)\n\nThe product does not perform any authentication for functionality that requires a provable user identity or consumes a significant amount of resources....\n\n### 2. CWE-287: Improper Authentication (Score: 137.31)\n\nWhen an actor claims to have a given identity, the product does not prove or insufficiently proves that the claim is correct....\n\n### 3. CWE-285: Improper Authorization (Score: 130.62)\n\nThe product does not perform or incorrectly performs an authorization check when an actor attempts to access a resource or perform an action....\n\n### 4. CWE-798: Use of Hard-coded Credentials (Score: 43.10)\n\nThe product contains hard-coded credentials, such as a password or cryptographic key....\n\n### 5. CWE-1390: Weak Authentication (Score: 42.26)\n\nThe product uses an authentication mechanism to restrict access to specific users or identities, but the mechanism does not sufficiently prove that the claimed identity is correct....\n\n## PRODUCT: 'Profelis Informatics and Consulting PassBox'\n\nRelevant CWEs for this PRODUCT:\n\n### 1. CWE-306: Missing Authentication for Critical Function (Score: 142.31)\n\nThe product does not perform any authentication for functionality that requires a provable user identity or consumes a significant amount of resources....\n\n### 2. CWE-287: Improper Authentication (Score: 137.31)\n\nWhen an actor claims to have a given identity, the product does not prove or insufficiently proves that the claim is correct....\n\n### 3. CWE-285: Improper Authorization (Score: 130.62)\n\nThe product does not perform or incorrectly performs an authorization check when an actor attempts to access a resource or perform an action....\n\n### 4. CWE-472: External Control of Assumed-Immutable Web Parameter (Score: 127.95)\n\nThe web application does not sufficiently verify inputs that are assumed to be immutable but are actually externally controllable, such as hidden form fields....\n\n### 5. CWE-80: Improper Neutralization of Script-Related HTML Tags in a Web Page (Basic XSS) (Score: 55.77)\n\nThe product receives input from an upstream component, but it does not neutralize or incorrectly neutralizes special characters such as \"<\", \">\", and \"&\" that could be interpreted as web-scripting elements when they are sent to a downstream component that processes web pages....\n\n## VERSION: 'before v1.2'\n\nRelevant CWEs for this VERSION:\n\n### 1. CWE-306: Missing Authentication for Critical Function (Score: 142.31)\n\nThe product does not perform any authentication for functionality that requires a provable user identity or consumes a significant amount of resources....\n\n### 2. CWE-287: Improper Authentication (Score: 137.31)\n\nWhen an actor claims to have a given identity, the product does not prove or insufficiently proves that the claim is correct....\n\n### 3. CWE-285: Improper Authorization (Score: 130.62)\n\nThe product does not perform or incorrectly performs an authorization check when an actor attempts to access a resource or perform an action....\n\n### 4. CWE-472: External Control of Assumed-Immutable Web Parameter (Score: 127.95)\n\nThe web application does not sufficiently verify inputs that are assumed to be immutable but are actually externally controllable, such as hidden form fields....\n\n### 5. CWE-425: Direct Request ('Forced Browsing') (Score: 126.05)\n\nThe web application does not adequately enforce appropriate authorization on all restricted URLs, scripts, or files....\n\n\n    # Analysis Instructions\n    1. For each keyphrase, identify the most appropriate CWE(s) that represent the weakness.\n    2. Consider how the different keyphrases might relate to each other in the vulnerability chain.\n    3. Provide a final determination of primary CWE(s) and any secondary CWEs.\n    4. Format your response using the standard analysis template.\n\n    Please analyze how these different weaknesses interact and provide a comprehensive CWE classification.\n    "
  },
  "retrieval_time": 1.0102229118347168
}