{
  "cve_id": "CVE-2024-53101",
  "description": "In the Linux kernel, the following vulnerability has been resolved fs Fix **uninitialized value issue** in from_kuid and from_kgid ocfs2_setattr() uses attr->ia_mode, attr->ia_uid and attr->ia_gid in a trace point even though ATTR_MODE, ATTR_UID and ATTR_GID arent set. Initialize all fields of newattrs to avoid **uninitialized variables**, by checking if ATTR_MODE, ATTR_UID, ATTR_GID are initialized, otherwise 0.",
  "key_phrases": {
    "rootcause": [
      "uninitialized value issue",
      "uninitialized variables"
    ],
    "weakness": "",
    "impact": "",
    "vector": "uninitialized variables",
    "attacker": "",
    "product": "Linux kernel",
    "version": "",
    "component": "ocfs2_setattr()"
  },
  "reference_content": "Based on the provided content, here's an analysis of the vulnerability:\n\n**Root Cause:**\nThe `ocfs2_setattr` function in the Linux kernel's OCFS2 file system driver was using potentially uninitialized values from the `attr` structure (specifically, `attr->ia_mode`, `attr->ia_uid`, and `attr->ia_gid`) in a tracepoint. These values are only valid if the corresponding `ATTR_MODE`, `ATTR_UID`, and `ATTR_GID` flags are set in `attr->ia_valid`. If these flags were not set, the tracepoint would output garbage data from uninitialized stack memory.\n\n**Weaknesses/Vulnerabilities Present:**\n- **Uninitialized Variables:** The core issue is the use of uninitialized variables in a tracepoint. The `ocfs2_setattr` function did not check if the `ATTR_MODE`, `ATTR_UID`, and `ATTR_GID` flags were set in `attr->ia_valid` before using  `attr->ia_mode`, `attr->ia_uid`, and `attr->ia_gid`.\n- **Information Leak:** While not directly exploitable for privilege escalation, this could leak kernel memory contents through the tracepoint, which is a form of information disclosure.\n\n**Impact of Exploitation:**\n- The primary impact is an information leak from the kernel memory. \n-  The leaked information might include sensitive data, potentially aiding in further exploitation.\n- The tracepoint output would be inconsistent and contain unpredictable values, which could cause issues for monitoring and debugging tools.\n\n**Attack Vectors:**\n- The attack vector is triggering the `ocfs2_setattr` function with an `iattr` structure where the `ATTR_MODE`, `ATTR_UID`, and/or `ATTR_GID` flags are not set.\n- This can occur through any legitimate or malicious file system operation that involves modifying file attributes.\n\n**Required Attacker Capabilities/Position:**\n- An attacker would need the ability to trigger a call to `ocfs2_setattr`, which requires write access to files on an OCFS2 filesystem.\n- No special privilege is needed.\n\n**Additional Notes:**\n- This vulnerability is related to an information leak and not a crash or privilege escalation.\n- The fix is to add checks for `ATTR_MODE`, `ATTR_UID`, and `ATTR_GID` flags and, if not set, default to 0 values to avoid uninitialized memory access during the tracepoint.\n- The syzkaller tool reported this bug.",
  "similar_info": {
    "cwe_distribution": {},
    "cwe_consensus": "",
    "similarity_stats": {
      "thresholds": [],
      "total_samples_by_threshold": {},
      "top_cwes_by_threshold": {}
    }
  },
  "similarity_summary": {
    "consensus_cwe": "",
    "top_cwes": [],
    "confidence_levels": {},
    "total_samples": 0
  },
  "analysis": "# Summary\n| CWE ID | CWE Name | Confidence | CWE Abstraction Level | CWE Vulnerability Mapping Label | CWE-Vulnerability Mapping Notes |\n|---|---|---|---|---|---|\n| CWE-457 | Use of Uninitialized Variable | 0.9 | Variant | Primary | Allowed |\n| CWE-908 | Use of Uninitialized Resource | 0.7 | Base | Secondary | Allowed |\n\n## Evidence and Confidence\n\n*   **Confidence Score:** 0.9\n*   **Evidence Strength:** HIGH\n\n## Relationship Analysis\nThe primary relationship that influenced the decision was the hierarchical relationship where CWE-457 is a child of CWE-908, and both are related to improper initialization. CWE-457 is a more specific case of using an uninitialized variable, which directly aligns with the vulnerability description.\n\n```mermaid\ngraph TD\n    cwe457[\"CWE-457: Use of Uninitialized Variable\"]\n    cwe908[\"CWE-908: Use of Uninitialized Resource\"]\n    cwe665[\"CWE-665: Improper Initialization\"]\n    \n    cwe457 -->|CHILDOF| cwe908\n    cwe908 -->|CHILDOF| cwe665\n    \n    classDef primary fill:#f96,stroke:#333,stroke-width:2px\n    classDef secondary fill:#69f,stroke:#333\n    classDef tertiary fill:#9e9,stroke:#333\n    class cwe457 primary\n    class cwe908 secondary\n    class cwe665 tertiary\n```\n\n## Vulnerability Chain\nThe vulnerability chain starts with the **missing initialization** of variables, leading to the **use of uninitialized values**. The final impact is the potential for unpredictable or incorrect behavior in the `ocfs2_setattr()` function within the Linux kernel.\n\n## Summary of Analysis\nThe initial analysis identified several candidate CWEs, primarily focusing on initialization issues. The critical evidence lies in the vulnerability description, which explicitly mentions \"**uninitialized value issue**\" and \"**uninitialized variables**\".\n\nThe graph relationships helped to narrow down the selection to the most specific and relevant CWEs. Given the explicit mention of using uninitialized variables, CWE-457 was chosen as the primary CWE due to its direct alignment with the described weakness.\n\nCWE-908 was considered as a potential parent, but CWE-457 offers more specific details of the **use of uninitialized variables**, making it a better fit.\n\nThe selected CWEs are at the optimal level of specificity, providing a clear and accurate representation of the vulnerability. The decision is based on direct evidence from the vulnerability description and supported by the provided relationship data.\n\nRelevant CWE Information:\n\n# Enhanced Context (25 CWEs)\nThe following CWEs were identified as potentially relevant to this vulnerability:\n\n## CWE-457: Use of Uninitialized Variable\n**Abstraction Level**: Variant\n**Similarity Score**: 0.74\n**Source**: dense\n\n**Description**:\nThe code uses a variable that has not been initialized, leading to unpredictable or unintended results.\n\n**Mapping Guidance**:\n- Usage: Allowed\n- Rationale: This CWE entry is at the Variant level of abstraction, which is a preferred level of abstraction for mapping to the root causes of vulnerabilities.\n\n\n\n## CWE-665: Improper Initialization\n**Abstraction Level**: Class\n**Similarity Score**: 0.73\n**Source**: dense\n\n**Description**:\nThe product does not initialize or incorrectly initializes a resource, which might leave the resource in an unexpected state when it is accessed or used.\n\n**Mapping Guidance**:\n- Usage: Discouraged\n- Rationale: This CWE entry is a level-1 Class (i.e., a child of a Pillar). It might have lower-level children that would be more appropriate\n\n\n\n## CWE-456: Missing Initialization of a Variable\n**Abstraction Level**: Variant\n**Similarity Score**: 0.73\n**Source**: dense\n\n**Description**:\nThe product does not initialize critical variables, which causes the execution environment to use unexpected values.\n\n**Mapping Guidance**:\n- Usage: Allowed\n- Rationale: This CWE entry is at the Variant level of abstraction, which is a preferred level of abstraction for mapping to the root causes of vulnerabilities.\n\n\n\n## CWE-824: Access of Uninitialized Pointer\n**Abstraction Level**: Base\n**Similarity Score**: 0.72\n**Source**: dense\n\n**Description**:\nThe product accesses or uses a pointer that has not been initialized.\n\n**Mapping Guidance**:\n- Usage: Allowed\n- Rationale: This CWE entry is at the Base level of abstraction, which is a preferred level of abstraction for mapping to the root causes of vulnerabilities.\n\n\n\n## CWE-909: Missing Initialization of Resource\n**Abstraction Level**: Class\n**Similarity Score**: 0.72\n**Source**: dense\n\n**Description**:\nThe product does not initialize a critical resource.\n\n**Mapping Guidance**:\n- Usage: Allowed-with-Review\n- Rationale: This CWE entry is a Class and might have Base-level children that would be more appropriate\n\n\n\n## CWE-1419: Incorrect Initialization of Resource\n**Abstraction Level**: Class\n**Similarity Score**: 0.71\n**Source**: dense\n\n**Description**:\nThe product attempts to initialize a resource but does not correctly do so, which might leave the resource in an unexpected, incorrect, or insecure state when it is accessed.\n\n**Mapping Guidance**:\n- Usage: Allowed-with-Review\n- Rationale: This CWE entry is a Class and might have Base-level children that would be more appropriate\n\n\n\n## CWE-908: Use of Uninitialized Resource\n**Abstraction Level**: Base\n**Similarity Score**: 0.70\n**Source**: dense\n\n**Description**:\nThe product uses or accesses a resource that has not been initialized.\n\n**Mapping Guidance**:\n- Usage: Allowed\n- Rationale: This CWE entry is at the Base level of abstraction, which is a preferred level of abstraction for mapping to the root causes of vulnerabilities.\n\n\n\n## CWE-252: Unchecked Return Value\n**Abstraction Level**: Base\n**Similarity Score**: 0.70\n**Source**: dense\n\n**Description**:\nThe product does not check the return value from a method or function, which can prevent it from detecting unexpected states and conditions.\n\n**Mapping Guidance**:\n- Usage: Allowed\n- Rationale: This CWE entry is at the Base level of abstraction, which is a preferred level of abstraction for mapping to the root causes of vulnerabilities.\n\n\n\n## CWE-667: Improper Locking\n**Abstraction Level**: Class\n**Similarity Score**: 0.69\n**Source**: dense\n\n**Description**:\nThe product does not properly acquire or release a lock on a resource, leading to unexpected resource state changes and behaviors.\n\n**Mapping Guidance**:\n- Usage: Allowed-with-Review\n- Rationale: This CWE entry is a Class and might have Base-level children that would be more appropriate\n\n\n\n## CWE-754: Improper Check for Unusual or Exceptional Conditions\n**Abstraction Level**: Class\n**Similarity Score**: 0.69\n**Source**: dense\n\n**Description**:\nThe product does not check or incorrectly checks for unusual or exceptional conditions that are not expected to occur frequently during day to day operation of the product.\n\n**Mapping Guidance**:\n- Usage: Allowed-with-Review\n- Rationale: This CWE entry is a Class and might have Base-level children that would be more appropriate\n\n\n\n## CWE-909: Missing Initialization of Resource\n**Abstraction Level**: Class\n**Similarity Score**: 1846.05\n**Source**: sparse\n\n**Description**:\nThe product does not initialize a critical resource.\n\n**Mapping Guidance**:\n- Usage: Allowed-with-Review\n- Rationale: This CWE entry is a Class and might have Base-level children that would be more appropriate\n\n\n\n## CWE-456: Missing Initialization of a Variable\n**Abstraction Level**: Variant\n**Similarity Score**: 1780.53\n**Source**: sparse\n\n**Description**:\nThe product does not initialize critical variables, which causes the execution environment to use unexpected values.\n\n**Mapping Guidance**:\n- Usage: Allowed\n- Rationale: This CWE entry is at the Variant level of abstraction, which is a preferred level of abstraction for mapping to the root causes of vulnerabilities.\n\n\n\n## CWE-665: Improper Initialization\n**Abstraction Level**: Class\n**Similarity Score**: 1756.84\n**Source**: sparse\n\n**Description**:\nThe product does not initialize or incorrectly initializes a resource, which might leave the resource in an unexpected state when it is accessed or used.\n\n**Mapping Guidance**:\n- Usage: Discouraged\n- Rationale: This CWE entry is a level-1 Class (i.e., a child of a Pillar). It might have lower-level children that would be more appropriate\n\n\n\n## CWE-1419: Incorrect Initialization of Resource\n**Abstraction Level**: Class\n**Similarity Score**: 1686.36\n**Source**: sparse\n\n**Description**:\nThe product attempts to initialize a resource but does not correctly do so, which might leave the resource in an unexpected, incorrect, or insecure state when it is accessed.\n\n**Mapping Guidance**:\n- Usage: Allowed-with-Review\n- Rationale: This CWE entry is a Class and might have Base-level children that would be more appropriate\n\n\n\n## CWE",
  "analysis_with_relationships": "# Summary\n| CWE ID | CWE Name | Confidence | CWE Abstraction Level | CWE Vulnerability Mapping Label | CWE-Vulnerability Mapping Notes |\n|---|---|---|---|---|---|\n| CWE-457 | Use of Uninitialized Variable | 0.9 | Variant | Primary | Allowed |\n| CWE-908 | Use of Uninitialized Resource | 0.7 | Base | Secondary | Allowed |\n\n## Evidence and Confidence\n\n*   **Confidence Score:** 0.9\n*   **Evidence Strength:** HIGH\n\n## Relationship Analysis\nThe primary relationship that influenced the decision was the hierarchical relationship where CWE-457 is a child of CWE-908, and both are related to improper initialization. CWE-457 is a more specific case of using an uninitialized variable, which directly aligns with the vulnerability description.\n\n```mermaid\ngraph TD\n    cwe457[\"CWE-457: Use of Uninitialized Variable\"]\n    cwe908[\"CWE-908: Use of Uninitialized Resource\"]\n    cwe665[\"CWE-665: Improper Initialization\"]\n    \n    cwe457 -->|CHILDOF| cwe908\n    cwe908 -->|CHILDOF| cwe665\n    \n    classDef primary fill:#f96,stroke:#333,stroke-width:2px\n    classDef secondary fill:#69f,stroke:#333\n    classDef tertiary fill:#9e9,stroke:#333\n    class cwe457 primary\n    class cwe908 secondary\n    class cwe665 tertiary\n```\n\n## Vulnerability Chain\nThe vulnerability chain starts with the **missing initialization** of variables, leading to the **use of uninitialized values**. The final impact is the potential for unpredictable or incorrect behavior in the `ocfs2_setattr()` function within the Linux kernel.\n\n## Summary of Analysis\nThe initial analysis identified several candidate CWEs, primarily focusing on initialization issues. The critical evidence lies in the vulnerability description, which explicitly mentions \"**uninitialized value issue**\" and \"**uninitialized variables**\".\n\nThe graph relationships helped to narrow down the selection to the most specific and relevant CWEs. Given the explicit mention of using uninitialized variables, CWE-457 was chosen as the primary CWE due to its direct alignment with the described weakness.\n\nCWE-908 was considered as a potential parent, but CWE-457 offers more specific details of the **use of uninitialized variables**, making it a better fit.\n\nThe selected CWEs are at the optimal level of specificity, providing a clear and accurate representation of the vulnerability. The decision is based on direct evidence from the vulnerability description and supported by the provided relationship data.\n\nRelevant CWE Information:\n\n# Enhanced Context (25 CWEs)\nThe following CWEs were identified as potentially relevant to this vulnerability:\n\n## CWE-457: Use of Uninitialized Variable\n**Abstraction Level**: Variant\n**Similarity Score**: 0.74\n**Source**: dense\n\n**Description**:\nThe code uses a variable that has not been initialized, leading to unpredictable or unintended results.\n\n**Mapping Guidance**:\n- Usage: Allowed\n- Rationale: This CWE entry is at the Variant level of abstraction, which is a preferred level of abstraction for mapping to the root causes of vulnerabilities.\n\n\n\n## CWE-665: Improper Initialization\n**Abstraction Level**: Class\n**Similarity Score**: 0.73\n**Source**: dense\n\n**Description**:\nThe product does not initialize or incorrectly initializes a resource, which might leave the resource in an unexpected state when it is accessed or used.\n\n**Mapping Guidance**:\n- Usage: Discouraged\n- Rationale: This CWE entry is a level-1 Class (i.e., a child of a Pillar). It might have lower-level children that would be more appropriate\n\n\n\n## CWE-456: Missing Initialization of a Variable\n**Abstraction Level**: Variant\n**Similarity Score**: 0.73\n**Source**: dense\n\n**Description**:\nThe product does not initialize critical variables, which causes the execution environment to use unexpected values.\n\n**Mapping Guidance**:\n- Usage: Allowed\n- Rationale: This CWE entry is at the Variant level of abstraction, which is a preferred level of abstraction for mapping to the root causes of vulnerabilities.\n\n\n\n## CWE-824: Access of Uninitialized Pointer\n**Abstraction Level**: Base\n**Similarity Score**: 0.72\n**Source**: dense\n\n**Description**:\nThe product accesses or uses a pointer that has not been initialized.\n\n**Mapping Guidance**:\n- Usage: Allowed\n- Rationale: This CWE entry is at the Base level of abstraction, which is a preferred level of abstraction for mapping to the root causes of vulnerabilities.\n\n\n\n## CWE-909: Missing Initialization of Resource\n**Abstraction Level**: Class\n**Similarity Score**: 0.72\n**Source**: dense\n\n**Description**:\nThe product does not initialize a critical resource.\n\n**Mapping Guidance**:\n- Usage: Allowed-with-Review\n- Rationale: This CWE entry is a Class and might have Base-level children that would be more appropriate\n\n\n\n## CWE-1419: Incorrect Initialization of Resource\n**Abstraction Level**: Class\n**Similarity Score**: 0.71\n**Source**: dense\n\n**Description**:\nThe product attempts to initialize a resource but does not correctly do so, which might leave the resource in an unexpected, incorrect, or insecure state when it is accessed.\n\n**Mapping Guidance**:\n- Usage: Allowed-with-Review\n- Rationale: This CWE entry is a Class and might have Base-level children that would be more appropriate\n\n\n\n## CWE-908: Use of Uninitialized Resource\n**Abstraction Level**: Base\n**Similarity Score**: 0.70\n**Source**: dense\n\n**Description**:\nThe product uses or accesses a resource that has not been initialized.\n\n**Mapping Guidance**:\n- Usage: Allowed\n- Rationale: This CWE entry is at the Base level of abstraction, which is a preferred level of abstraction for mapping to the root causes of vulnerabilities.\n\n\n\n## CWE-252: Unchecked Return Value\n**Abstraction Level**: Base\n**Similarity Score**: 0.70\n**Source**: dense\n\n**Description**:\nThe product does not check the return value from a method or function, which can prevent it from detecting unexpected states and conditions.\n\n**Mapping Guidance**:\n- Usage: Allowed\n- Rationale: This CWE entry is at the Base level of abstraction, which is a preferred level of abstraction for mapping to the root causes of vulnerabilities.\n\n\n\n## CWE-667: Improper Locking\n**Abstraction Level**: Class\n**Similarity Score**: 0.69\n**Source**: dense\n\n**Description**:\nThe product does not properly acquire or release a lock on a resource, leading to unexpected resource state changes and behaviors.\n\n**Mapping Guidance**:\n- Usage: Allowed-with-Review\n- Rationale: This CWE entry is a Class and might have Base-level children that would be more appropriate\n\n\n\n## CWE-754: Improper Check for Unusual or Exceptional Conditions\n**Abstraction Level**: Class\n**Similarity Score**: 0.69\n**Source**: dense\n\n**Description**:\nThe product does not check or incorrectly checks for unusual or exceptional conditions that are not expected to occur frequently during day to day operation of the product.\n\n**Mapping Guidance**:\n- Usage: Allowed-with-Review\n- Rationale: This CWE entry is a Class and might have Base-level children that would be more appropriate\n\n\n\n## CWE-909: Missing Initialization of Resource\n**Abstraction Level**: Class\n**Similarity Score**: 1846.05\n**Source**: sparse\n\n**Description**:\nThe product does not initialize a critical resource.\n\n**Mapping Guidance**:\n- Usage: Allowed-with-Review\n- Rationale: This CWE entry is a Class and might have Base-level children that would be more appropriate\n\n\n\n## CWE-456: Missing Initialization of a Variable\n**Abstraction Level**: Variant\n**Similarity Score**: 1780.53\n**Source**: sparse\n\n**Description**:\nThe product does not initialize critical variables, which causes the execution environment to use unexpected values.\n\n**Mapping Guidance**:\n- Usage: Allowed\n- Rationale: This CWE entry is at the Variant level of abstraction, which is a preferred level of abstraction for mapping to the root causes of vulnerabilities.\n\n\n\n## CWE-665: Improper Initialization\n**Abstraction Level**: Class\n**Similarity Score**: 1756.84\n**Source**: sparse\n\n**Description**:\nThe product does not initialize or incorrectly initializes a resource, which might leave the resource in an unexpected state when it is accessed or used.\n\n**Mapping Guidance**:\n- Usage: Discouraged\n- Rationale: This CWE entry is a level-1 Class (i.e., a child of a Pillar). It might have lower-level children that would be more appropriate\n\n\n\n## CWE-1419: Incorrect Initialization of Resource\n**Abstraction Level**: Class\n**Similarity Score**: 1686.36\n**Source**: sparse\n\n**Description**:\nThe product attempts to initialize a resource but does not correctly do so, which might leave the resource in an unexpected, incorrect, or insecure state when it is accessed.\n\n**Mapping Guidance**:\n- Usage: Allowed-with-Review\n- Rationale: This CWE entry is a Class and might have Base-level children that would be more appropriate\n\n\n\n## CWE\n\n\n## CWE Relationship Analysis\n\nCurrent CWEs represent these abstraction levels: .\n\n\n### Vulnerability Chain Analysis\n\n**Chain starting from CWE-665:**\n- 665 (Improper Initialization) - ROOT\n\n\n**Chain starting from CWE-1419:**\n- 1419 (Incorrect Initialization of Resource) - ROOT\n\n\n\n### CWE Relationship Diagram\n\n```mermaid\ngraph TD\n    classDef primary fill:#f96,stroke:#333,stroke-width:2px\n    classDef secondary fill:#69f,stroke:#333\n    classDef tertiary fill:#9e9,stroke:#333\n```",
  "criticism": "",
  "resolution": "",
  "relevant_cwes": [
    {
      "metadata": {
        "doc_id": "457",
        "name": "Use of Uninitialized Variable",
        "source": "sparse",
        "original_content": "The code uses a variable that has not been initialized, leading to unpredictable or unintended results.",
        "keyphrase_sources": [
          {
            "id": "rootcause:uninitialized value issue",
            "keyphrase": "uninitialized value issue",
            "type": "rootcause"
          },
          {
            "id": "rootcause:uninitialized variables",
            "keyphrase": "uninitialized variables",
            "type": "rootcause"
          },
          {
            "id": "vector:uninitialized variables",
            "keyphrase": "uninitialized variables",
            "type": "vector"
          },
          {
            "id": "product:Linux kernel",
            "keyphrase": "Linux kernel",
            "type": "product"
          },
          {
            "id": "component:ocfs2_setattr()",
            "keyphrase": "ocfs2_setattr()",
            "type": "component"
          }
        ]
      },
      "similarity": 344.4255179491033
    },
    {
      "metadata": {
        "doc_id": "909",
        "name": "Missing Initialization of Resource",
        "source": "sparse",
        "original_content": "The product does not initialize a critical resource.",
        "keyphrase_sources": [
          {
            "id": "rootcause:uninitialized value issue",
            "keyphrase": "uninitialized value issue",
            "type": "rootcause"
          },
          {
            "id": "rootcause:uninitialized variables",
            "keyphrase": "uninitialized variables",
            "type": "rootcause"
          },
          {
            "id": "vector:uninitialized variables",
            "keyphrase": "uninitialized variables",
            "type": "vector"
          },
          {
            "id": "product:Linux kernel",
            "keyphrase": "Linux kernel",
            "type": "product"
          },
          {
            "id": "component:ocfs2_setattr()",
            "keyphrase": "ocfs2_setattr()",
            "type": "component"
          }
        ]
      },
      "similarity": 332.93341396177476
    },
    {
      "metadata": {
        "doc_id": "456",
        "name": "Missing Initialization of a Variable",
        "source": "sparse",
        "original_content": "The product does not initialize critical variables, which causes the execution environment to use unexpected values.",
        "keyphrase_sources": [
          {
            "id": "rootcause:uninitialized variables",
            "keyphrase": "uninitialized variables",
            "type": "rootcause"
          },
          {
            "id": "vector:uninitialized variables",
            "keyphrase": "uninitialized variables",
            "type": "vector"
          }
        ]
      },
      "similarity": 309.35252280513157
    },
    {
      "metadata": {
        "doc_id": "824",
        "name": "Access of Uninitialized Pointer",
        "source": "sparse",
        "original_content": "The product accesses or uses a pointer that has not been initialized.",
        "keyphrase_sources": [
          {
            "id": "rootcause:uninitialized value issue",
            "keyphrase": "uninitialized value issue",
            "type": "rootcause"
          },
          {
            "id": "rootcause:uninitialized variables",
            "keyphrase": "uninitialized variables",
            "type": "rootcause"
          },
          {
            "id": "vector:uninitialized variables",
            "keyphrase": "uninitialized variables",
            "type": "vector"
          },
          {
            "id": "component:ocfs2_setattr()",
            "keyphrase": "ocfs2_setattr()",
            "type": "component"
          }
        ]
      },
      "similarity": 305.5582594979962
    },
    {
      "metadata": {
        "doc_id": "392",
        "name": "Missing Report of Error Condition",
        "source": "sparse",
        "original_content": "The product encounters an error but does not provide a status code or return value to indicate that an error has occurred.",
        "keyphrase_sources": [
          {
            "id": "rootcause:uninitialized value issue",
            "keyphrase": "uninitialized value issue",
            "type": "rootcause"
          },
          {
            "id": "product:Linux kernel",
            "keyphrase": "Linux kernel",
            "type": "product"
          },
          {
            "id": "component:ocfs2_setattr()",
            "keyphrase": "ocfs2_setattr()",
            "type": "component"
          }
        ]
      },
      "similarity": 302.23784576289313
    },
    {
      "metadata": {
        "doc_id": "665",
        "name": "Improper Initialization",
        "source": "sparse",
        "original_content": "The product does not initialize or incorrectly initializes a resource, which might leave the resource in an unexpected state when it is accessed or used.",
        "keyphrase_sources": [
          {
            "id": "rootcause:uninitialized value issue",
            "keyphrase": "uninitialized value issue",
            "type": "rootcause"
          },
          {
            "id": "rootcause:uninitialized variables",
            "keyphrase": "uninitialized variables",
            "type": "rootcause"
          },
          {
            "id": "vector:uninitialized variables",
            "keyphrase": "uninitialized variables",
            "type": "vector"
          },
          {
            "id": "product:Linux kernel",
            "keyphrase": "Linux kernel",
            "type": "product"
          },
          {
            "id": "component:ocfs2_setattr()",
            "keyphrase": "ocfs2_setattr()",
            "type": "component"
          }
        ]
      },
      "similarity": 298.3781648915996
    },
    {
      "metadata": {
        "doc_id": "908",
        "name": "Use of Uninitialized Resource",
        "source": "sparse",
        "original_content": "The product uses or accesses a resource that has not been initialized.",
        "keyphrase_sources": [
          {
            "id": "product:Linux kernel",
            "keyphrase": "Linux kernel",
            "type": "product"
          }
        ]
      },
      "similarity": 85.97772314668859
    }
  ],
  "identified_cwes": {
    "analyzer": [
      "CWE-665",
      "CWE-1419",
      "CWE-457",
      "CWE-667",
      "CWE-909",
      "CWE-824",
      "CWE-252",
      "CWE-754",
      "CWE-908",
      "CWE-456"
    ],
    "critic_additional": []
  },
  "keyphrase_cwe_mapping": {
    "457": [
      {
        "id": "rootcause:uninitialized value issue",
        "keyphrase": "uninitialized value issue",
        "type": "rootcause"
      },
      {
        "id": "rootcause:uninitialized variables",
        "keyphrase": "uninitialized variables",
        "type": "rootcause"
      },
      {
        "id": "vector:uninitialized variables",
        "keyphrase": "uninitialized variables",
        "type": "vector"
      },
      {
        "id": "product:Linux kernel",
        "keyphrase": "Linux kernel",
        "type": "product"
      },
      {
        "id": "component:ocfs2_setattr()",
        "keyphrase": "ocfs2_setattr()",
        "type": "component"
      }
    ],
    "909": [
      {
        "id": "rootcause:uninitialized value issue",
        "keyphrase": "uninitialized value issue",
        "type": "rootcause"
      },
      {
        "id": "rootcause:uninitialized variables",
        "keyphrase": "uninitialized variables",
        "type": "rootcause"
      },
      {
        "id": "vector:uninitialized variables",
        "keyphrase": "uninitialized variables",
        "type": "vector"
      },
      {
        "id": "product:Linux kernel",
        "keyphrase": "Linux kernel",
        "type": "product"
      },
      {
        "id": "component:ocfs2_setattr()",
        "keyphrase": "ocfs2_setattr()",
        "type": "component"
      }
    ],
    "824": [
      {
        "id": "rootcause:uninitialized value issue",
        "keyphrase": "uninitialized value issue",
        "type": "rootcause"
      },
      {
        "id": "rootcause:uninitialized variables",
        "keyphrase": "uninitialized variables",
        "type": "rootcause"
      },
      {
        "id": "vector:uninitialized variables",
        "keyphrase": "uninitialized variables",
        "type": "vector"
      },
      {
        "id": "component:ocfs2_setattr()",
        "keyphrase": "ocfs2_setattr()",
        "type": "component"
      }
    ],
    "392": [
      {
        "id": "rootcause:uninitialized value issue",
        "keyphrase": "uninitialized value issue",
        "type": "rootcause"
      },
      {
        "id": "product:Linux kernel",
        "keyphrase": "Linux kernel",
        "type": "product"
      },
      {
        "id": "component:ocfs2_setattr()",
        "keyphrase": "ocfs2_setattr()",
        "type": "component"
      }
    ],
    "665": [
      {
        "id": "rootcause:uninitialized value issue",
        "keyphrase": "uninitialized value issue",
        "type": "rootcause"
      },
      {
        "id": "rootcause:uninitialized variables",
        "keyphrase": "uninitialized variables",
        "type": "rootcause"
      },
      {
        "id": "vector:uninitialized variables",
        "keyphrase": "uninitialized variables",
        "type": "vector"
      },
      {
        "id": "product:Linux kernel",
        "keyphrase": "Linux kernel",
        "type": "product"
      },
      {
        "id": "component:ocfs2_setattr()",
        "keyphrase": "ocfs2_setattr()",
        "type": "component"
      }
    ],
    "456": [
      {
        "id": "rootcause:uninitialized variables",
        "keyphrase": "uninitialized variables",
        "type": "rootcause"
      },
      {
        "id": "vector:uninitialized variables",
        "keyphrase": "uninitialized variables",
        "type": "vector"
      }
    ],
    "908": [
      {
        "id": "product:Linux kernel",
        "keyphrase": "Linux kernel",
        "type": "product"
      }
    ]
  }
}