{
  "vulnerability_info": "VulnerabilityInfo(cve_id='CVE-2025-30588', description='Cross-Site Request Forgery (CSRF) vulnerability in ryan_xantoo Map Contact allows Stored **XSS**. This issue affects Map Contact from n/a through 3.0.4.', key_phrases={'rootcause': 'cross-site request forgery', 'weakness': ['cross-site scripting', 'XSS'], 'impact': '', 'vector': '', 'attacker': '', 'product': 'Map Contact', 'version': 'n/a through 3.0.4', 'component': ''}, reference_content='## Analysis of CVE-2025-30588 Content\\n\\nThe provided content **relates** to CVE-2025-30588 as indicated by the CVE ID listed within the document. It provides details about a Cross-Site Request Forgery (CSRF) vulnerability in the WordPress Map Contact Plugin.\\n\\nHere\\'s an extraction of the relevant information:\\n\\n*   **Root cause of vulnerability:** The vulnerability is a Cross-Site Request Forgery (CSRF).\\n*   **Weaknesses/vulnerabilities present:** CSRF vulnerability allows a malicious actor to force higher privileged users to execute unwanted actions.\\n*   **Impact of exploitation:** Allows a malicious actor to force higher privileged users to execute unwanted actions under their current authentication.\\n*   **Attack vectors:**  The content does not specify the exact attack vector, but CSRF generally involves tricking a logged-in user into submitting a malicious request.\\n*   **Required attacker capabilities/position:** Unauthenticated attacker.\\n*   **Mitigation or fix:** No official fix is available as of March 24, 2025. Patchstack offers \"vPatching\" as a mitigation.\\n*   **Affected versions:** <= 3.0.4\\n*   **CVSS Score:** 7.1 (Low severity)\\n*   **OWASP Top 10:** A1: Broken Access Control\\n\\n**Note:** This content provides more detail than the placeholder CVE description, specifically detailing the vulnerability type (CSRF), impact, and affected versions. It also mentions the availability of a virtual patch.', similar_info={'cwe_distribution': {}, 'cwe_consensus': '', 'similarity_stats': {'thresholds': [], 'total_samples_by_threshold': {}, 'top_cwes_by_threshold': {}}}, similarity_summary=SimilarityInsight(consensus_cwe='', top_cwes=[], confidence_levels={}, total_samples=0), analysis='', analysis_with_relationships='', criticism='', resolution='', relevant_cwes=[{'metadata': {'doc_id': '352', 'name': 'Cross-Site Request Forgery (CSRF)', 'source': 'sparse', 'original_content': 'The web application does not, or can not, sufficiently verify whether a well-formed, valid, consistent request was intentionally provided by the user who submitted the request.', 'keyphrase_sources': [{'id': 'rootcause:cross-site request forgery', 'keyphrase': 'cross-site request forgery', 'type': 'rootcause'}, {'id': 'weakness:cross-site scripting', 'keyphrase': 'cross-site scripting', 'type': 'weakness'}, {'id': 'weakness:XSS', 'keyphrase': 'XSS', 'type': 'weakness'}, {'id': 'product:Map Contact', 'keyphrase': 'Map Contact', 'type': 'product'}, {'id': 'version:n/a through 3.0.4', 'keyphrase': 'n/a through 3.0.4', 'type': 'version'}]}, 'similarity': np.float64(317.6211582551045)}, {'metadata': {'doc_id': '89', 'name': \"Improper Neutralization of Special Elements used in an SQL Command ('SQL Injection')\", 'source': 'sparse', 'original_content': 'The product constructs all or part of an SQL command using externally-influenced input from an upstream component, but it does not neutralize or incorrectly neutralizes special elements that could modify the intended SQL command when it is sent to a downstream component. Without sufficient removal or quoting of SQL syntax in user-controllable inputs, the generated SQL query can cause those inputs to be interpreted as SQL instead of ordinary user data.', 'keyphrase_sources': [{'id': 'rootcause:cross-site request forgery', 'keyphrase': 'cross-site request forgery', 'type': 'rootcause'}, {'id': 'weakness:cross-site scripting', 'keyphrase': 'cross-site scripting', 'type': 'weakness'}, {'id': 'product:Map Contact', 'keyphrase': 'Map Contact', 'type': 'product'}, {'id': 'version:n/a through 3.0.4', 'keyphrase': 'n/a through 3.0.4', 'type': 'version'}]}, 'similarity': np.float64(253.2801140345664)}, {'metadata': {'doc_id': '918', 'name': 'Server-Side Request Forgery (SSRF)', 'source': 'sparse', 'original_content': 'The web server receives a URL or similar request from an upstream component and retrieves the contents of this URL, but it does not sufficiently ensure that the request is being sent to the expected destination.', 'keyphrase_sources': [{'id': 'rootcause:cross-site request forgery', 'keyphrase': 'cross-site request forgery', 'type': 'rootcause'}, {'id': 'weakness:XSS', 'keyphrase': 'XSS', 'type': 'weakness'}]}, 'similarity': np.float64(239.05490010258808)}, {'metadata': {'doc_id': '79', 'name': \"Improper Neutralization of Input During Web Page Generation ('Cross-site Scripting')\", 'source': 'sparse', 'original_content': 'The product does not neutralize or incorrectly neutralizes user-controllable input before it is placed in output that is used as a web page that is served to other users.', 'keyphrase_sources': [{'id': 'rootcause:cross-site request forgery', 'keyphrase': 'cross-site request forgery', 'type': 'rootcause'}, {'id': 'weakness:cross-site scripting', 'keyphrase': 'cross-site scripting', 'type': 'weakness'}, {'id': 'weakness:XSS', 'keyphrase': 'XSS', 'type': 'weakness'}, {'id': 'product:Map Contact', 'keyphrase': 'Map Contact', 'type': 'product'}, {'id': 'version:n/a through 3.0.4', 'keyphrase': 'n/a through 3.0.4', 'type': 'version'}]}, 'similarity': np.float64(231.0725553953488)}, {'metadata': {'doc_id': '601', 'name': \"URL Redirection to Untrusted Site ('Open Redirect')\", 'source': 'sparse', 'original_content': 'The web application accepts a user-controlled input that specifies a link to an external site, and uses that link in a redirect.', 'keyphrase_sources': [{'id': 'rootcause:cross-site request forgery', 'keyphrase': 'cross-site request forgery', 'type': 'rootcause'}]}, 'similarity': np.float64(220.33731053434383)}, {'metadata': {'doc_id': '80', 'name': 'Improper Neutralization of Script-Related HTML Tags in a Web Page (Basic XSS)', 'source': 'sparse', 'original_content': 'The product receives input from an upstream component, but it does not neutralize or incorrectly neutralizes special characters such as \"<\", \">\", and \"&\" that could be interpreted as web-scripting elements when they are sent to a downstream component that processes web pages.', 'keyphrase_sources': [{'id': 'weakness:cross-site scripting', 'keyphrase': 'cross-site scripting', 'type': 'weakness'}]}, 'similarity': np.float64(193.9789020290669)}, {'metadata': {'doc_id': '1004', 'name': \"Sensitive Cookie Without 'HttpOnly' Flag\", 'source': 'sparse', 'original_content': 'The product uses a cookie to store sensitive information, but the cookie is not marked with the HttpOnly flag.', 'keyphrase_sources': [{'id': 'weakness:cross-site scripting', 'keyphrase': 'cross-site scripting', 'type': 'weakness'}, {'id': 'weakness:XSS', 'keyphrase': 'XSS', 'type': 'weakness'}]}, 'similarity': np.float64(192.34246738590068)}, {'metadata': {'doc_id': '116', 'name': 'Improper Encoding or Escaping of Output', 'source': 'sparse', 'original_content': 'The product prepares a structured message for communication with another component, but encoding or escaping of the data is either missing or done incorrectly. As a result, the intended structure of the message is not preserved.', 'keyphrase_sources': [{'id': 'weakness:XSS', 'keyphrase': 'XSS', 'type': 'weakness'}]}, 'similarity': np.float64(141.81252067161222)}, {'metadata': {'doc_id': '434', 'name': 'Unrestricted Upload of File with Dangerous Type', 'source': 'sparse', 'original_content': 'The product allows the upload or transfer of dangerous file types that are automatically processed within its environment.', 'keyphrase_sources': [{'id': 'version:n/a through 3.0.4', 'keyphrase': 'n/a through 3.0.4', 'type': 'version'}]}, 'similarity': np.float64(64.15773764279174)}, {'metadata': {'doc_id': '22', 'name': \"Improper Limitation of a Pathname to a Restricted Directory ('Path Traversal')\", 'source': 'sparse', 'original_content': 'The product uses external input to construct a pathname that is intended to identify a file or directory that is located underneath a restricted parent directory, but the product does not properly neutralize special elements within the pathname that can cause the pathname to resolve to a location that is outside of the restricted directory.', 'keyphrase_sources': [{'id': 'product:Map Contact', 'keyphrase': 'Map Contact', 'type': 'product'}, {'id': 'version:n/a through 3.0.4', 'keyphrase': 'n/a through 3.0.4', 'type': 'version'}]}, 'similarity': np.float64(48.71302217972777)}, {'metadata': {'doc_id': '696', 'name': 'Incorrect Behavior Order', 'source': 'sparse', 'original_content': 'The product performs multiple related behaviors, but the behaviors are performed in the wrong order in ways which may produce resultant weaknesses.', 'keyphrase_sources': [{'id': 'product:Map Contact', 'keyphrase': 'Map Contact', 'type': 'product'}]}, 'similarity': np.float64(48.60667622092646)}], identified_cwes={'analyzer': [], 'critic_additional': []})",
  "retrieval_results": {
    "has_multiple_keyphrases": true,
    "keyphrase_cwe_sets": {
      "rootcause:cross-site request forgery": {
        "keyphrase": "cross-site request forgery",
        "type": "rootcause",
        "cwes": [
          {
            "metadata": {
              "doc_id": "352",
              "name": "Cross-Site Request Forgery (CSRF)",
              "source": "sparse",
              "original_content": "The web application does not, or can not, sufficiently verify whether a well-formed, valid, consistent request was intentionally provided by the user who submitted the request.",
              "keyphrase_sources": [
                {
                  "id": "rootcause:cross-site request forgery",
                  "keyphrase": "cross-site request forgery",
                  "type": "rootcause"
                },
                {
                  "id": "weakness:cross-site scripting",
                  "keyphrase": "cross-site scripting",
                  "type": "weakness"
                },
                {
                  "id": "weakness:XSS",
                  "keyphrase": "XSS",
                  "type": "weakness"
                },
                {
                  "id": "product:Map Contact",
                  "keyphrase": "Map Contact",
                  "type": "product"
                },
                {
                  "id": "version:n/a through 3.0.4",
                  "keyphrase": "n/a through 3.0.4",
                  "type": "version"
                }
              ]
            },
            "similarity": 317.6211582551045
          },
          {
            "metadata": {
              "doc_id": "89",
              "name": "Improper Neutralization of Special Elements used in an SQL Command ('SQL Injection')",
              "source": "sparse",
              "original_content": "The product constructs all or part of an SQL command using externally-influenced input from an upstream component, but it does not neutralize or incorrectly neutralizes special elements that could modify the intended SQL command when it is sent to a downstream component. Without sufficient removal or quoting of SQL syntax in user-controllable inputs, the generated SQL query can cause those inputs to be interpreted as SQL instead of ordinary user data.",
              "keyphrase_sources": [
                {
                  "id": "rootcause:cross-site request forgery",
                  "keyphrase": "cross-site request forgery",
                  "type": "rootcause"
                },
                {
                  "id": "weakness:cross-site scripting",
                  "keyphrase": "cross-site scripting",
                  "type": "weakness"
                },
                {
                  "id": "product:Map Contact",
                  "keyphrase": "Map Contact",
                  "type": "product"
                },
                {
                  "id": "version:n/a through 3.0.4",
                  "keyphrase": "n/a through 3.0.4",
                  "type": "version"
                }
              ]
            },
            "similarity": 253.2801140345664
          },
          {
            "metadata": {
              "doc_id": "918",
              "name": "Server-Side Request Forgery (SSRF)",
              "source": "sparse",
              "original_content": "The web server receives a URL or similar request from an upstream component and retrieves the contents of this URL, but it does not sufficiently ensure that the request is being sent to the expected destination.",
              "keyphrase_sources": [
                {
                  "id": "rootcause:cross-site request forgery",
                  "keyphrase": "cross-site request forgery",
                  "type": "rootcause"
                },
                {
                  "id": "weakness:XSS",
                  "keyphrase": "XSS",
                  "type": "weakness"
                }
              ]
            },
            "similarity": 239.05490010258808
          },
          {
            "metadata": {
              "doc_id": "79",
              "name": "Improper Neutralization of Input During Web Page Generation ('Cross-site Scripting')",
              "source": "sparse",
              "original_content": "The product does not neutralize or incorrectly neutralizes user-controllable input before it is placed in output that is used as a web page that is served to other users.",
              "keyphrase_sources": [
                {
                  "id": "rootcause:cross-site request forgery",
                  "keyphrase": "cross-site request forgery",
                  "type": "rootcause"
                },
                {
                  "id": "weakness:cross-site scripting",
                  "keyphrase": "cross-site scripting",
                  "type": "weakness"
                },
                {
                  "id": "weakness:XSS",
                  "keyphrase": "XSS",
                  "type": "weakness"
                },
                {
                  "id": "product:Map Contact",
                  "keyphrase": "Map Contact",
                  "type": "product"
                },
                {
                  "id": "version:n/a through 3.0.4",
                  "keyphrase": "n/a through 3.0.4",
                  "type": "version"
                }
              ]
            },
            "similarity": 231.0725553953488
          },
          {
            "metadata": {
              "doc_id": "601",
              "name": "URL Redirection to Untrusted Site ('Open Redirect')",
              "source": "sparse",
              "original_content": "The web application accepts a user-controlled input that specifies a link to an external site, and uses that link in a redirect.",
              "keyphrase_sources": [
                {
                  "id": "rootcause:cross-site request forgery",
                  "keyphrase": "cross-site request forgery",
                  "type": "rootcause"
                }
              ]
            },
            "similarity": 220.33731053434383
          }
        ]
      },
      "weakness:cross-site scripting": {
        "keyphrase": "cross-site scripting",
        "type": "weakness",
        "cwes": [
          {
            "metadata": {
              "doc_id": "352",
              "name": "Cross-Site Request Forgery (CSRF)",
              "source": "sparse",
              "original_content": "The web application does not, or can not, sufficiently verify whether a well-formed, valid, consistent request was intentionally provided by the user who submitted the request."
            },
            "similarity": 278.28981003424894
          },
          {
            "metadata": {
              "doc_id": "79",
              "name": "Improper Neutralization of Input During Web Page Generation ('Cross-site Scripting')",
              "source": "sparse",
              "original_content": "The product does not neutralize or incorrectly neutralizes user-controllable input before it is placed in output that is used as a web page that is served to other users."
            },
            "similarity": 234.83212774587065
          },
          {
            "metadata": {
              "doc_id": "80",
              "name": "Improper Neutralization of Script-Related HTML Tags in a Web Page (Basic XSS)",
              "source": "sparse",
              "original_content": "The product receives input from an upstream component, but it does not neutralize or incorrectly neutralizes special characters such as \"<\", \">\", and \"&\" that could be interpreted as web-scripting elements when they are sent to a downstream component that processes web pages.",
              "keyphrase_sources": [
                {
                  "id": "weakness:cross-site scripting",
                  "keyphrase": "cross-site scripting",
                  "type": "weakness"
                }
              ]
            },
            "similarity": 193.9789020290669
          },
          {
            "metadata": {
              "doc_id": "1004",
              "name": "Sensitive Cookie Without 'HttpOnly' Flag",
              "source": "sparse",
              "original_content": "The product uses a cookie to store sensitive information, but the cookie is not marked with the HttpOnly flag.",
              "keyphrase_sources": [
                {
                  "id": "weakness:cross-site scripting",
                  "keyphrase": "cross-site scripting",
                  "type": "weakness"
                },
                {
                  "id": "weakness:XSS",
                  "keyphrase": "XSS",
                  "type": "weakness"
                }
              ]
            },
            "similarity": 192.34246738590068
          },
          {
            "metadata": {
              "doc_id": "89",
              "name": "Improper Neutralization of Special Elements used in an SQL Command ('SQL Injection')",
              "source": "sparse",
              "original_content": "The product constructs all or part of an SQL command using externally-influenced input from an upstream component, but it does not neutralize or incorrectly neutralizes special elements that could modify the intended SQL command when it is sent to a downstream component. Without sufficient removal or quoting of SQL syntax in user-controllable inputs, the generated SQL query can cause those inputs to be interpreted as SQL instead of ordinary user data."
            },
            "similarity": 191.42690391271938
          }
        ]
      },
      "weakness:XSS": {
        "keyphrase": "XSS",
        "type": "weakness",
        "cwes": [
          {
            "metadata": {
              "doc_id": "352",
              "name": "Cross-Site Request Forgery (CSRF)",
              "source": "sparse",
              "original_content": "The web application does not, or can not, sufficiently verify whether a well-formed, valid, consistent request was intentionally provided by the user who submitted the request."
            },
            "similarity": 210.26666475811302
          },
          {
            "metadata": {
              "doc_id": "79",
              "name": "Improper Neutralization of Input During Web Page Generation ('Cross-site Scripting')",
              "source": "sparse",
              "original_content": "The product does not neutralize or incorrectly neutralizes user-controllable input before it is placed in output that is used as a web page that is served to other users."
            },
            "similarity": 172.8673363889845
          },
          {
            "metadata": {
              "doc_id": "1004",
              "name": "Sensitive Cookie Without 'HttpOnly' Flag",
              "source": "sparse",
              "original_content": "The product uses a cookie to store sensitive information, but the cookie is not marked with the HttpOnly flag."
            },
            "similarity": 147.7906906397559
          },
          {
            "metadata": {
              "doc_id": "116",
              "name": "Improper Encoding or Escaping of Output",
              "source": "sparse",
              "original_content": "The product prepares a structured message for communication with another component, but encoding or escaping of the data is either missing or done incorrectly. As a result, the intended structure of the message is not preserved.",
              "keyphrase_sources": [
                {
                  "id": "weakness:XSS",
                  "keyphrase": "XSS",
                  "type": "weakness"
                }
              ]
            },
            "similarity": 141.81252067161222
          },
          {
            "metadata": {
              "doc_id": "918",
              "name": "Server-Side Request Forgery (SSRF)",
              "source": "sparse",
              "original_content": "The web server receives a URL or similar request from an upstream component and retrieves the contents of this URL, but it does not sufficiently ensure that the request is being sent to the expected destination."
            },
            "similarity": 139.91540075660112
          }
        ]
      },
      "product:Map Contact": {
        "keyphrase": "Map Contact",
        "type": "product",
        "cwes": [
          {
            "metadata": {
              "doc_id": "352",
              "name": "Cross-Site Request Forgery (CSRF)",
              "source": "sparse",
              "original_content": "The web application does not, or can not, sufficiently verify whether a well-formed, valid, consistent request was intentionally provided by the user who submitted the request."
            },
            "similarity": 75.38145820062765
          },
          {
            "metadata": {
              "doc_id": "79",
              "name": "Improper Neutralization of Input During Web Page Generation ('Cross-site Scripting')",
              "source": "sparse",
              "original_content": "The product does not neutralize or incorrectly neutralizes user-controllable input before it is placed in output that is used as a web page that is served to other users."
            },
            "similarity": 55.50575273835358
          },
          {
            "metadata": {
              "doc_id": "22",
              "name": "Improper Limitation of a Pathname to a Restricted Directory ('Path Traversal')",
              "source": "sparse",
              "original_content": "The product uses external input to construct a pathname that is intended to identify a file or directory that is located underneath a restricted parent directory, but the product does not properly neutralize special elements within the pathname that can cause the pathname to resolve to a location that is outside of the restricted directory.",
              "keyphrase_sources": [
                {
                  "id": "product:Map Contact",
                  "keyphrase": "Map Contact",
                  "type": "product"
                },
                {
                  "id": "version:n/a through 3.0.4",
                  "keyphrase": "n/a through 3.0.4",
                  "type": "version"
                }
              ]
            },
            "similarity": 48.71302217972777
          },
          {
            "metadata": {
              "doc_id": "696",
              "name": "Incorrect Behavior Order",
              "source": "sparse",
              "original_content": "The product performs multiple related behaviors, but the behaviors are performed in the wrong order in ways which may produce resultant weaknesses.",
              "keyphrase_sources": [
                {
                  "id": "product:Map Contact",
                  "keyphrase": "Map Contact",
                  "type": "product"
                }
              ]
            },
            "similarity": 48.60667622092646
          },
          {
            "metadata": {
              "doc_id": "89",
              "name": "Improper Neutralization of Special Elements used in an SQL Command ('SQL Injection')",
              "source": "sparse",
              "original_content": "The product constructs all or part of an SQL command using externally-influenced input from an upstream component, but it does not neutralize or incorrectly neutralizes special elements that could modify the intended SQL command when it is sent to a downstream component. Without sufficient removal or quoting of SQL syntax in user-controllable inputs, the generated SQL query can cause those inputs to be interpreted as SQL instead of ordinary user data."
            },
            "similarity": 47.819705233846015
          }
        ]
      },
      "version:n/a through 3.0.4": {
        "keyphrase": "n/a through 3.0.4",
        "type": "version",
        "cwes": [
          {
            "metadata": {
              "doc_id": "352",
              "name": "Cross-Site Request Forgery (CSRF)",
              "source": "sparse",
              "original_content": "The web application does not, or can not, sufficiently verify whether a well-formed, valid, consistent request was intentionally provided by the user who submitted the request."
            },
            "similarity": 83.17232007104444
          },
          {
            "metadata": {
              "doc_id": "22",
              "name": "Improper Limitation of a Pathname to a Restricted Directory ('Path Traversal')",
              "source": "sparse",
              "original_content": "The product uses external input to construct a pathname that is intended to identify a file or directory that is located underneath a restricted parent directory, but the product does not properly neutralize special elements within the pathname that can cause the pathname to resolve to a location that is outside of the restricted directory."
            },
            "similarity": 69.92338448937936
          },
          {
            "metadata": {
              "doc_id": "79",
              "name": "Improper Neutralization of Input During Web Page Generation ('Cross-site Scripting')",
              "source": "sparse",
              "original_content": "The product does not neutralize or incorrectly neutralizes user-controllable input before it is placed in output that is used as a web page that is served to other users."
            },
            "similarity": 68.02962338177342
          },
          {
            "metadata": {
              "doc_id": "434",
              "name": "Unrestricted Upload of File with Dangerous Type",
              "source": "sparse",
              "original_content": "The product allows the upload or transfer of dangerous file types that are automatically processed within its environment.",
              "keyphrase_sources": [
                {
                  "id": "version:n/a through 3.0.4",
                  "keyphrase": "n/a through 3.0.4",
                  "type": "version"
                }
              ]
            },
            "similarity": 64.15773764279174
          },
          {
            "metadata": {
              "doc_id": "89",
              "name": "Improper Neutralization of Special Elements used in an SQL Command ('SQL Injection')",
              "source": "sparse",
              "original_content": "The product constructs all or part of an SQL command using externally-influenced input from an upstream component, but it does not neutralize or incorrectly neutralizes special elements that could modify the intended SQL command when it is sent to a downstream component. Without sufficient removal or quoting of SQL syntax in user-controllable inputs, the generated SQL query can cause those inputs to be interpreted as SQL instead of ordinary user data."
            },
            "similarity": 62.38536842704993
          }
        ]
      }
    },
    "keyphrase_mapping": {
      "352": [
        {
          "id": "rootcause:cross-site request forgery",
          "keyphrase": "cross-site request forgery",
          "type": "rootcause"
        },
        {
          "id": "weakness:cross-site scripting",
          "keyphrase": "cross-site scripting",
          "type": "weakness"
        },
        {
          "id": "weakness:XSS",
          "keyphrase": "XSS",
          "type": "weakness"
        },
        {
          "id": "product:Map Contact",
          "keyphrase": "Map Contact",
          "type": "product"
        },
        {
          "id": "version:n/a through 3.0.4",
          "keyphrase": "n/a through 3.0.4",
          "type": "version"
        }
      ],
      "89": [
        {
          "id": "rootcause:cross-site request forgery",
          "keyphrase": "cross-site request forgery",
          "type": "rootcause"
        },
        {
          "id": "weakness:cross-site scripting",
          "keyphrase": "cross-site scripting",
          "type": "weakness"
        },
        {
          "id": "product:Map Contact",
          "keyphrase": "Map Contact",
          "type": "product"
        },
        {
          "id": "version:n/a through 3.0.4",
          "keyphrase": "n/a through 3.0.4",
          "type": "version"
        }
      ],
      "918": [
        {
          "id": "rootcause:cross-site request forgery",
          "keyphrase": "cross-site request forgery",
          "type": "rootcause"
        },
        {
          "id": "weakness:XSS",
          "keyphrase": "XSS",
          "type": "weakness"
        }
      ],
      "79": [
        {
          "id": "rootcause:cross-site request forgery",
          "keyphrase": "cross-site request forgery",
          "type": "rootcause"
        },
        {
          "id": "weakness:cross-site scripting",
          "keyphrase": "cross-site scripting",
          "type": "weakness"
        },
        {
          "id": "weakness:XSS",
          "keyphrase": "XSS",
          "type": "weakness"
        },
        {
          "id": "product:Map Contact",
          "keyphrase": "Map Contact",
          "type": "product"
        },
        {
          "id": "version:n/a through 3.0.4",
          "keyphrase": "n/a through 3.0.4",
          "type": "version"
        }
      ],
      "601": [
        {
          "id": "rootcause:cross-site request forgery",
          "keyphrase": "cross-site request forgery",
          "type": "rootcause"
        }
      ],
      "80": [
        {
          "id": "weakness:cross-site scripting",
          "keyphrase": "cross-site scripting",
          "type": "weakness"
        }
      ],
      "1004": [
        {
          "id": "weakness:cross-site scripting",
          "keyphrase": "cross-site scripting",
          "type": "weakness"
        },
        {
          "id": "weakness:XSS",
          "keyphrase": "XSS",
          "type": "weakness"
        }
      ],
      "116": [
        {
          "id": "weakness:XSS",
          "keyphrase": "XSS",
          "type": "weakness"
        }
      ],
      "22": [
        {
          "id": "product:Map Contact",
          "keyphrase": "Map Contact",
          "type": "product"
        },
        {
          "id": "version:n/a through 3.0.4",
          "keyphrase": "n/a through 3.0.4",
          "type": "version"
        }
      ],
      "696": [
        {
          "id": "product:Map Contact",
          "keyphrase": "Map Contact",
          "type": "product"
        }
      ],
      "434": [
        {
          "id": "version:n/a through 3.0.4",
          "keyphrase": "n/a through 3.0.4",
          "type": "version"
        }
      ]
    },
    "relevant_cwes": [
      {
        "metadata": {
          "doc_id": "352",
          "name": "Cross-Site Request Forgery (CSRF)",
          "source": "sparse",
          "original_content": "The web application does not, or can not, sufficiently verify whether a well-formed, valid, consistent request was intentionally provided by the user who submitted the request.",
          "keyphrase_sources": [
            {
              "id": "rootcause:cross-site request forgery",
              "keyphrase": "cross-site request forgery",
              "type": "rootcause"
            },
            {
              "id": "weakness:cross-site scripting",
              "keyphrase": "cross-site scripting",
              "type": "weakness"
            },
            {
              "id": "weakness:XSS",
              "keyphrase": "XSS",
              "type": "weakness"
            },
            {
              "id": "product:Map Contact",
              "keyphrase": "Map Contact",
              "type": "product"
            },
            {
              "id": "version:n/a through 3.0.4",
              "keyphrase": "n/a through 3.0.4",
              "type": "version"
            }
          ]
        },
        "similarity": 317.6211582551045
      },
      {
        "metadata": {
          "doc_id": "89",
          "name": "Improper Neutralization of Special Elements used in an SQL Command ('SQL Injection')",
          "source": "sparse",
          "original_content": "The product constructs all or part of an SQL command using externally-influenced input from an upstream component, but it does not neutralize or incorrectly neutralizes special elements that could modify the intended SQL command when it is sent to a downstream component. Without sufficient removal or quoting of SQL syntax in user-controllable inputs, the generated SQL query can cause those inputs to be interpreted as SQL instead of ordinary user data.",
          "keyphrase_sources": [
            {
              "id": "rootcause:cross-site request forgery",
              "keyphrase": "cross-site request forgery",
              "type": "rootcause"
            },
            {
              "id": "weakness:cross-site scripting",
              "keyphrase": "cross-site scripting",
              "type": "weakness"
            },
            {
              "id": "product:Map Contact",
              "keyphrase": "Map Contact",
              "type": "product"
            },
            {
              "id": "version:n/a through 3.0.4",
              "keyphrase": "n/a through 3.0.4",
              "type": "version"
            }
          ]
        },
        "similarity": 253.2801140345664
      },
      {
        "metadata": {
          "doc_id": "918",
          "name": "Server-Side Request Forgery (SSRF)",
          "source": "sparse",
          "original_content": "The web server receives a URL or similar request from an upstream component and retrieves the contents of this URL, but it does not sufficiently ensure that the request is being sent to the expected destination.",
          "keyphrase_sources": [
            {
              "id": "rootcause:cross-site request forgery",
              "keyphrase": "cross-site request forgery",
              "type": "rootcause"
            },
            {
              "id": "weakness:XSS",
              "keyphrase": "XSS",
              "type": "weakness"
            }
          ]
        },
        "similarity": 239.05490010258808
      },
      {
        "metadata": {
          "doc_id": "79",
          "name": "Improper Neutralization of Input During Web Page Generation ('Cross-site Scripting')",
          "source": "sparse",
          "original_content": "The product does not neutralize or incorrectly neutralizes user-controllable input before it is placed in output that is used as a web page that is served to other users.",
          "keyphrase_sources": [
            {
              "id": "rootcause:cross-site request forgery",
              "keyphrase": "cross-site request forgery",
              "type": "rootcause"
            },
            {
              "id": "weakness:cross-site scripting",
              "keyphrase": "cross-site scripting",
              "type": "weakness"
            },
            {
              "id": "weakness:XSS",
              "keyphrase": "XSS",
              "type": "weakness"
            },
            {
              "id": "product:Map Contact",
              "keyphrase": "Map Contact",
              "type": "product"
            },
            {
              "id": "version:n/a through 3.0.4",
              "keyphrase": "n/a through 3.0.4",
              "type": "version"
            }
          ]
        },
        "similarity": 231.0725553953488
      },
      {
        "metadata": {
          "doc_id": "601",
          "name": "URL Redirection to Untrusted Site ('Open Redirect')",
          "source": "sparse",
          "original_content": "The web application accepts a user-controlled input that specifies a link to an external site, and uses that link in a redirect.",
          "keyphrase_sources": [
            {
              "id": "rootcause:cross-site request forgery",
              "keyphrase": "cross-site request forgery",
              "type": "rootcause"
            }
          ]
        },
        "similarity": 220.33731053434383
      },
      {
        "metadata": {
          "doc_id": "80",
          "name": "Improper Neutralization of Script-Related HTML Tags in a Web Page (Basic XSS)",
          "source": "sparse",
          "original_content": "The product receives input from an upstream component, but it does not neutralize or incorrectly neutralizes special characters such as \"<\", \">\", and \"&\" that could be interpreted as web-scripting elements when they are sent to a downstream component that processes web pages.",
          "keyphrase_sources": [
            {
              "id": "weakness:cross-site scripting",
              "keyphrase": "cross-site scripting",
              "type": "weakness"
            }
          ]
        },
        "similarity": 193.9789020290669
      },
      {
        "metadata": {
          "doc_id": "1004",
          "name": "Sensitive Cookie Without 'HttpOnly' Flag",
          "source": "sparse",
          "original_content": "The product uses a cookie to store sensitive information, but the cookie is not marked with the HttpOnly flag.",
          "keyphrase_sources": [
            {
              "id": "weakness:cross-site scripting",
              "keyphrase": "cross-site scripting",
              "type": "weakness"
            },
            {
              "id": "weakness:XSS",
              "keyphrase": "XSS",
              "type": "weakness"
            }
          ]
        },
        "similarity": 192.34246738590068
      },
      {
        "metadata": {
          "doc_id": "116",
          "name": "Improper Encoding or Escaping of Output",
          "source": "sparse",
          "original_content": "The product prepares a structured message for communication with another component, but encoding or escaping of the data is either missing or done incorrectly. As a result, the intended structure of the message is not preserved.",
          "keyphrase_sources": [
            {
              "id": "weakness:XSS",
              "keyphrase": "XSS",
              "type": "weakness"
            }
          ]
        },
        "similarity": 141.81252067161222
      },
      {
        "metadata": {
          "doc_id": "434",
          "name": "Unrestricted Upload of File with Dangerous Type",
          "source": "sparse",
          "original_content": "The product allows the upload or transfer of dangerous file types that are automatically processed within its environment.",
          "keyphrase_sources": [
            {
              "id": "version:n/a through 3.0.4",
              "keyphrase": "n/a through 3.0.4",
              "type": "version"
            }
          ]
        },
        "similarity": 64.15773764279174
      },
      {
        "metadata": {
          "doc_id": "22",
          "name": "Improper Limitation of a Pathname to a Restricted Directory ('Path Traversal')",
          "source": "sparse",
          "original_content": "The product uses external input to construct a pathname that is intended to identify a file or directory that is located underneath a restricted parent directory, but the product does not properly neutralize special elements within the pathname that can cause the pathname to resolve to a location that is outside of the restricted directory.",
          "keyphrase_sources": [
            {
              "id": "product:Map Contact",
              "keyphrase": "Map Contact",
              "type": "product"
            },
            {
              "id": "version:n/a through 3.0.4",
              "keyphrase": "n/a through 3.0.4",
              "type": "version"
            }
          ]
        },
        "similarity": 48.71302217972777
      },
      {
        "metadata": {
          "doc_id": "696",
          "name": "Incorrect Behavior Order",
          "source": "sparse",
          "original_content": "The product performs multiple related behaviors, but the behaviors are performed in the wrong order in ways which may produce resultant weaknesses.",
          "keyphrase_sources": [
            {
              "id": "product:Map Contact",
              "keyphrase": "Map Contact",
              "type": "product"
            }
          ]
        },
        "similarity": 48.60667622092646
      }
    ],
    "enhanced_query": "# Vulnerability Description\n\n    Cross-Site Request Forgery (CSRF) vulnerability in ryan_xantoo Map Contact allows Stored **XSS**. This issue affects Map Contact from n/a through 3.0.4.\n\n    # Keyphrase-Specific CWE Analysis\n    This vulnerability contains multiple keyphrases that may map to different CWEs. \n    Please analyze each keyphrase separately and determine the most appropriate CWE(s) for each.\n\n    ## ROOTCAUSE: 'cross-site request forgery'\n\nRelevant CWEs for this ROOTCAUSE:\n\n### 1. CWE-352: Cross-Site Request Forgery (CSRF) (Score: 317.62)\n\nThe web application does not, or can not, sufficiently verify whether a well-formed, valid, consistent request was intentionally provided by the user who submitted the request....\n\n### 2. CWE-89: Improper Neutralization of Special Elements used in an SQL Command ('SQL Injection') (Score: 253.28)\n\nThe product constructs all or part of an SQL command using externally-influenced input from an upstream component, but it does not neutralize or incorrectly neutralizes special elements that could modify the intended SQL command when it is sent to a downstream component. Without sufficient removal o...\n\n### 3. CWE-918: Server-Side Request Forgery (SSRF) (Score: 239.05)\n\nThe web server receives a URL or similar request from an upstream component and retrieves the contents of this URL, but it does not sufficiently ensure that the request is being sent to the expected destination....\n\n### 4. CWE-79: Improper Neutralization of Input During Web Page Generation ('Cross-site Scripting') (Score: 231.07)\n\nThe product does not neutralize or incorrectly neutralizes user-controllable input before it is placed in output that is used as a web page that is served to other users....\n\n### 5. CWE-601: URL Redirection to Untrusted Site ('Open Redirect') (Score: 220.34)\n\nThe web application accepts a user-controlled input that specifies a link to an external site, and uses that link in a redirect....\n\n## WEAKNESS: 'cross-site scripting'\n\nRelevant CWEs for this WEAKNESS:\n\n### 1. CWE-352: Cross-Site Request Forgery (CSRF) (Score: 317.62)\n\nThe web application does not, or can not, sufficiently verify whether a well-formed, valid, consistent request was intentionally provided by the user who submitted the request....\n\n### 2. CWE-89: Improper Neutralization of Special Elements used in an SQL Command ('SQL Injection') (Score: 253.28)\n\nThe product constructs all or part of an SQL command using externally-influenced input from an upstream component, but it does not neutralize or incorrectly neutralizes special elements that could modify the intended SQL command when it is sent to a downstream component. Without sufficient removal o...\n\n### 3. CWE-79: Improper Neutralization of Input During Web Page Generation ('Cross-site Scripting') (Score: 231.07)\n\nThe product does not neutralize or incorrectly neutralizes user-controllable input before it is placed in output that is used as a web page that is served to other users....\n\n### 4. CWE-80: Improper Neutralization of Script-Related HTML Tags in a Web Page (Basic XSS) (Score: 193.98)\n\nThe product receives input from an upstream component, but it does not neutralize or incorrectly neutralizes special characters such as \"<\", \">\", and \"&\" that could be interpreted as web-scripting elements when they are sent to a downstream component that processes web pages....\n\n### 5. CWE-1004: Sensitive Cookie Without 'HttpOnly' Flag (Score: 192.34)\n\nThe product uses a cookie to store sensitive information, but the cookie is not marked with the HttpOnly flag....\n\n## WEAKNESS: 'XSS'\n\nRelevant CWEs for this WEAKNESS:\n\n### 1. CWE-352: Cross-Site Request Forgery (CSRF) (Score: 317.62)\n\nThe web application does not, or can not, sufficiently verify whether a well-formed, valid, consistent request was intentionally provided by the user who submitted the request....\n\n### 2. CWE-918: Server-Side Request Forgery (SSRF) (Score: 239.05)\n\nThe web server receives a URL or similar request from an upstream component and retrieves the contents of this URL, but it does not sufficiently ensure that the request is being sent to the expected destination....\n\n### 3. CWE-79: Improper Neutralization of Input During Web Page Generation ('Cross-site Scripting') (Score: 231.07)\n\nThe product does not neutralize or incorrectly neutralizes user-controllable input before it is placed in output that is used as a web page that is served to other users....\n\n### 4. CWE-1004: Sensitive Cookie Without 'HttpOnly' Flag (Score: 192.34)\n\nThe product uses a cookie to store sensitive information, but the cookie is not marked with the HttpOnly flag....\n\n### 5. CWE-116: Improper Encoding or Escaping of Output (Score: 141.81)\n\nThe product prepares a structured message for communication with another component, but encoding or escaping of the data is either missing or done incorrectly. As a result, the intended structure of the message is not preserved....\n\n## PRODUCT: 'Map Contact'\n\nRelevant CWEs for this PRODUCT:\n\n### 1. CWE-352: Cross-Site Request Forgery (CSRF) (Score: 317.62)\n\nThe web application does not, or can not, sufficiently verify whether a well-formed, valid, consistent request was intentionally provided by the user who submitted the request....\n\n### 2. CWE-89: Improper Neutralization of Special Elements used in an SQL Command ('SQL Injection') (Score: 253.28)\n\nThe product constructs all or part of an SQL command using externally-influenced input from an upstream component, but it does not neutralize or incorrectly neutralizes special elements that could modify the intended SQL command when it is sent to a downstream component. Without sufficient removal o...\n\n### 3. CWE-79: Improper Neutralization of Input During Web Page Generation ('Cross-site Scripting') (Score: 231.07)\n\nThe product does not neutralize or incorrectly neutralizes user-controllable input before it is placed in output that is used as a web page that is served to other users....\n\n### 4. CWE-22: Improper Limitation of a Pathname to a Restricted Directory ('Path Traversal') (Score: 48.71)\n\nThe product uses external input to construct a pathname that is intended to identify a file or directory that is located underneath a restricted parent directory, but the product does not properly neutralize special elements within the pathname that can cause the pathname to resolve to a location th...\n\n### 5. CWE-696: Incorrect Behavior Order (Score: 48.61)\n\nThe product performs multiple related behaviors, but the behaviors are performed in the wrong order in ways which may produce resultant weaknesses....\n\n## VERSION: 'n/a through 3.0.4'\n\nRelevant CWEs for this VERSION:\n\n### 1. CWE-352: Cross-Site Request Forgery (CSRF) (Score: 317.62)\n\nThe web application does not, or can not, sufficiently verify whether a well-formed, valid, consistent request was intentionally provided by the user who submitted the request....\n\n### 2. CWE-89: Improper Neutralization of Special Elements used in an SQL Command ('SQL Injection') (Score: 253.28)\n\nThe product constructs all or part of an SQL command using externally-influenced input from an upstream component, but it does not neutralize or incorrectly neutralizes special elements that could modify the intended SQL command when it is sent to a downstream component. Without sufficient removal o...\n\n### 3. CWE-79: Improper Neutralization of Input During Web Page Generation ('Cross-site Scripting') (Score: 231.07)\n\nThe product does not neutralize or incorrectly neutralizes user-controllable input before it is placed in output that is used as a web page that is served to other users....\n\n### 4. CWE-434: Unrestricted Upload of File with Dangerous Type (Score: 64.16)\n\nThe product allows the upload or transfer of dangerous file types that are automatically processed within its environment....\n\n### 5. CWE-22: Improper Limitation of a Pathname to a Restricted Directory ('Path Traversal') (Score: 48.71)\n\nThe product uses external input to construct a pathname that is intended to identify a file or directory that is located underneath a restricted parent directory, but the product does not properly neutralize special elements within the pathname that can cause the pathname to resolve to a location th...\n\n\n    # Analysis Instructions\n    1. For each keyphrase, identify the most appropriate CWE(s) that represent the weakness.\n    2. Consider how the different keyphrases might relate to each other in the vulnerability chain.\n    3. Provide a final determination of primary CWE(s) and any secondary CWEs.\n    4. Format your response using the standard analysis template.\n\n    Please analyze how these different weaknesses interact and provide a comprehensive CWE classification.\n    "
  },
  "retrieval_time": 1.3731472492218018
}