{
  "vulnerability_info": "VulnerabilityInfo(cve_id='CVE-2025-31569', description='Cross-Site Request Forgery (CSRF) vulnerability in wp-buy wordpress related Posts with thumbnails allows Stored **XSS**. This issue affects wordpress related Posts with thumbnails from n/a through 3.0.0.1.', key_phrases={'rootcause': '', 'weakness': ['cross-site request forgery', 'XSS'], 'impact': 'stored cross-site scripting', 'vector': '', 'attacker': '', 'product': 'wp-buy wordpress related Posts with thumbnails', 'version': 'n/a through 3.0.0.1', 'component': ''}, reference_content='## Analysis of CVE-2025-31569 Content\\n\\nThe provided content **relates** to CVE-2025-31569. It provides details about a Cross-Site Request Forgery (CSRF) vulnerability in the \"wordpress related Posts with thumbnails\" plugin.\\n\\nHere\\'s an extraction of the relevant information:\\n\\n**Root cause of vulnerability:**\\nThe vulnerability is a Cross-Site Request Forgery (CSRF).\\n\\n**Weaknesses/vulnerabilities present:**\\nCross-Site Request Forgery (CSRF) - allows a malicious actor to force higher privileged users to execute unwanted actions.\\n\\n**Impact of exploitation:**\\nA malicious actor can force higher privileged users to execute unwanted actions under their current authentication. The impact varies case by case.\\n\\n**Attack vectors:**\\nThe vulnerability is exploitable via Cross-Site Request Forgery attacks.\\n\\n**Required attacker capabilities/position:**\\nUnauthenticated attacker.\\n\\n**Mitigation or fix:**\\n*   Remove and replace the software, as it is likely abandoned and won\\'t receive updates.\\n*   Deactivating the software does not remove the threat unless a vPatch is deployed.\\n\\n**Additional Details:**\\n\\n*   **Affected Software:** wordpress related Posts with thumbnails Plugin\\n*   **Vulnerable Versions:** <= 3.0.0.1\\n*   **Fixed Version:** N/A (No official fix available)\\n*   **CVSS Score:** 7.1 (Low severity)\\n*   **OWASP Top 10:** A1: Broken Access Control\\n*   **PSID:** 8b2fff2aff8f\\n*   **Researcher:** Abdi Pranata\\n*   **Reported Date:** 23 Jan 2025\\n*   **Published Date:** 31 Mar 2025\\n\\nThe content provides more detail than the official CVE description would likely contain, specifically regarding the plugin name, vulnerable versions, and the researcher who reported the vulnerability. It also highlights the plugin\\'s abandoned status.', similar_info={'cwe_distribution': {}, 'cwe_consensus': '', 'similarity_stats': {'thresholds': [], 'total_samples_by_threshold': {}, 'top_cwes_by_threshold': {}}}, similarity_summary=SimilarityInsight(consensus_cwe='', top_cwes=[], confidence_levels={}, total_samples=0), analysis='', analysis_with_relationships='', criticism='', resolution='', relevant_cwes=[{'metadata': {'doc_id': '352', 'name': 'Cross-Site Request Forgery (CSRF)', 'source': 'sparse', 'original_content': 'The web application does not, or can not, sufficiently verify whether a well-formed, valid, consistent request was intentionally provided by the user who submitted the request.', 'keyphrase_sources': [{'id': 'weakness:cross-site request forgery', 'keyphrase': 'cross-site request forgery', 'type': 'weakness'}, {'id': 'weakness:XSS', 'keyphrase': 'XSS', 'type': 'weakness'}, {'id': 'impact:stored cross-site scripting', 'keyphrase': 'stored cross-site scripting', 'type': 'impact'}, {'id': 'product:wp-buy wordpress related Posts with thumbnails', 'keyphrase': 'wp-buy wordpress related Posts with thumbnails', 'type': 'product'}, {'id': 'version:n/a through 3.0.0.1', 'keyphrase': 'n/a through 3.0.0.1', 'type': 'version'}]}, 'similarity': np.float64(352.7992829751004)}, {'metadata': {'doc_id': '89', 'name': \"Improper Neutralization of Special Elements used in an SQL Command ('SQL Injection')\", 'source': 'sparse', 'original_content': 'The product constructs all or part of an SQL command using externally-influenced input from an upstream component, but it does not neutralize or incorrectly neutralizes special elements that could modify the intended SQL command when it is sent to a downstream component. Without sufficient removal or quoting of SQL syntax in user-controllable inputs, the generated SQL query can cause those inputs to be interpreted as SQL instead of ordinary user data.', 'keyphrase_sources': [{'id': 'weakness:cross-site request forgery', 'keyphrase': 'cross-site request forgery', 'type': 'weakness'}]}, 'similarity': np.float64(274.8385870694747)}, {'metadata': {'doc_id': '918', 'name': 'Server-Side Request Forgery (SSRF)', 'source': 'sparse', 'original_content': 'The web server receives a URL or similar request from an upstream component and retrieves the contents of this URL, but it does not sufficiently ensure that the request is being sent to the expected destination.', 'keyphrase_sources': [{'id': 'weakness:cross-site request forgery', 'keyphrase': 'cross-site request forgery', 'type': 'weakness'}]}, 'similarity': np.float64(249.14371205204378)}, {'metadata': {'doc_id': '79', 'name': \"Improper Neutralization of Input During Web Page Generation ('Cross-site Scripting')\", 'source': 'sparse', 'original_content': 'The product does not neutralize or incorrectly neutralizes user-controllable input before it is placed in output that is used as a web page that is served to other users.', 'keyphrase_sources': [{'id': 'weakness:cross-site request forgery', 'keyphrase': 'cross-site request forgery', 'type': 'weakness'}, {'id': 'weakness:XSS', 'keyphrase': 'XSS', 'type': 'weakness'}, {'id': 'impact:stored cross-site scripting', 'keyphrase': 'stored cross-site scripting', 'type': 'impact'}, {'id': 'version:n/a through 3.0.0.1', 'keyphrase': 'n/a through 3.0.0.1', 'type': 'version'}]}, 'similarity': np.float64(243.93159367606975)}, {'metadata': {'doc_id': '601', 'name': \"URL Redirection to Untrusted Site ('Open Redirect')\", 'source': 'sparse', 'original_content': 'The web application accepts a user-controlled input that specifies a link to an external site, and uses that link in a redirect.', 'keyphrase_sources': [{'id': 'weakness:cross-site request forgery', 'keyphrase': 'cross-site request forgery', 'type': 'weakness'}]}, 'similarity': np.float64(234.43154055816748)}, {'metadata': {'doc_id': '434', 'name': 'Unrestricted Upload of File with Dangerous Type', 'source': 'sparse', 'original_content': 'The product allows the upload or transfer of dangerous file types that are automatically processed within its environment.', 'keyphrase_sources': [{'id': 'weakness:XSS', 'keyphrase': 'XSS', 'type': 'weakness'}, {'id': 'impact:stored cross-site scripting', 'keyphrase': 'stored cross-site scripting', 'type': 'impact'}, {'id': 'product:wp-buy wordpress related Posts with thumbnails', 'keyphrase': 'wp-buy wordpress related Posts with thumbnails', 'type': 'product'}, {'id': 'version:n/a through 3.0.0.1', 'keyphrase': 'n/a through 3.0.0.1', 'type': 'version'}]}, 'similarity': np.float64(206.82594145480675)}, {'metadata': {'doc_id': '116', 'name': 'Improper Encoding or Escaping of Output', 'source': 'sparse', 'original_content': 'The product prepares a structured message for communication with another component, but encoding or escaping of the data is either missing or done incorrectly. As a result, the intended structure of the message is not preserved.', 'keyphrase_sources': [{'id': 'weakness:XSS', 'keyphrase': 'XSS', 'type': 'weakness'}, {'id': 'impact:stored cross-site scripting', 'keyphrase': 'stored cross-site scripting', 'type': 'impact'}, {'id': 'version:n/a through 3.0.0.1', 'keyphrase': 'n/a through 3.0.0.1', 'type': 'version'}]}, 'similarity': np.float64(194.588517330421)}, {'metadata': {'doc_id': '862', 'name': 'Missing Authorization', 'source': 'sparse', 'original_content': 'The product does not perform an authorization check when an actor attempts to access a resource or perform an action.', 'keyphrase_sources': [{'id': 'weakness:XSS', 'keyphrase': 'XSS', 'type': 'weakness'}, {'id': 'product:wp-buy wordpress related Posts with thumbnails', 'keyphrase': 'wp-buy wordpress related Posts with thumbnails', 'type': 'product'}, {'id': 'version:n/a through 3.0.0.1', 'keyphrase': 'n/a through 3.0.0.1', 'type': 'version'}]}, 'similarity': np.float64(173.70611673378502)}, {'metadata': {'doc_id': '266', 'name': 'Incorrect Privilege Assignment', 'source': 'sparse', 'original_content': 'A product incorrectly assigns a privilege to a particular actor, creating an unintended sphere of control for that actor.', 'keyphrase_sources': [{'id': 'product:wp-buy wordpress related Posts with thumbnails', 'keyphrase': 'wp-buy wordpress related Posts with thumbnails', 'type': 'product'}]}, 'similarity': np.float64(88.04186871009664)}, {'metadata': {'doc_id': '80', 'name': 'Improper Neutralization of Script-Related HTML Tags in a Web Page (Basic XSS)', 'source': 'sparse', 'original_content': 'The product receives input from an upstream component, but it does not neutralize or incorrectly neutralizes special characters such as \"<\", \">\", and \"&\" that could be interpreted as web-scripting elements when they are sent to a downstream component that processes web pages.', 'keyphrase_sources': [{'id': 'impact:stored cross-site scripting', 'keyphrase': 'stored cross-site scripting', 'type': 'impact'}]}, 'similarity': np.float64(84.56623185109716)}, {'metadata': {'doc_id': '863', 'name': 'Incorrect Authorization', 'source': 'sparse', 'original_content': 'The product performs an authorization check when an actor attempts to access a resource or perform an action, but it does not correctly perform the check.', 'keyphrase_sources': [{'id': 'product:wp-buy wordpress related Posts with thumbnails', 'keyphrase': 'wp-buy wordpress related Posts with thumbnails', 'type': 'product'}]}, 'similarity': np.float64(82.21902330204124)}], identified_cwes={'analyzer': [], 'critic_additional': []})",
  "retrieval_results": {
    "has_multiple_keyphrases": true,
    "keyphrase_cwe_sets": {
      "weakness:cross-site request forgery": {
        "keyphrase": "cross-site request forgery",
        "type": "weakness",
        "cwes": [
          {
            "metadata": {
              "doc_id": "352",
              "name": "Cross-Site Request Forgery (CSRF)",
              "source": "sparse",
              "original_content": "The web application does not, or can not, sufficiently verify whether a well-formed, valid, consistent request was intentionally provided by the user who submitted the request.",
              "keyphrase_sources": [
                {
                  "id": "weakness:cross-site request forgery",
                  "keyphrase": "cross-site request forgery",
                  "type": "weakness"
                },
                {
                  "id": "weakness:XSS",
                  "keyphrase": "XSS",
                  "type": "weakness"
                },
                {
                  "id": "impact:stored cross-site scripting",
                  "keyphrase": "stored cross-site scripting",
                  "type": "impact"
                },
                {
                  "id": "product:wp-buy wordpress related Posts with thumbnails",
                  "keyphrase": "wp-buy wordpress related Posts with thumbnails",
                  "type": "product"
                },
                {
                  "id": "version:n/a through 3.0.0.1",
                  "keyphrase": "n/a through 3.0.0.1",
                  "type": "version"
                }
              ]
            },
            "similarity": 352.7992829751004
          },
          {
            "metadata": {
              "doc_id": "89",
              "name": "Improper Neutralization of Special Elements used in an SQL Command ('SQL Injection')",
              "source": "sparse",
              "original_content": "The product constructs all or part of an SQL command using externally-influenced input from an upstream component, but it does not neutralize or incorrectly neutralizes special elements that could modify the intended SQL command when it is sent to a downstream component. Without sufficient removal or quoting of SQL syntax in user-controllable inputs, the generated SQL query can cause those inputs to be interpreted as SQL instead of ordinary user data.",
              "keyphrase_sources": [
                {
                  "id": "weakness:cross-site request forgery",
                  "keyphrase": "cross-site request forgery",
                  "type": "weakness"
                }
              ]
            },
            "similarity": 274.8385870694747
          },
          {
            "metadata": {
              "doc_id": "918",
              "name": "Server-Side Request Forgery (SSRF)",
              "source": "sparse",
              "original_content": "The web server receives a URL or similar request from an upstream component and retrieves the contents of this URL, but it does not sufficiently ensure that the request is being sent to the expected destination.",
              "keyphrase_sources": [
                {
                  "id": "weakness:cross-site request forgery",
                  "keyphrase": "cross-site request forgery",
                  "type": "weakness"
                }
              ]
            },
            "similarity": 249.14371205204378
          },
          {
            "metadata": {
              "doc_id": "79",
              "name": "Improper Neutralization of Input During Web Page Generation ('Cross-site Scripting')",
              "source": "sparse",
              "original_content": "The product does not neutralize or incorrectly neutralizes user-controllable input before it is placed in output that is used as a web page that is served to other users.",
              "keyphrase_sources": [
                {
                  "id": "weakness:cross-site request forgery",
                  "keyphrase": "cross-site request forgery",
                  "type": "weakness"
                },
                {
                  "id": "weakness:XSS",
                  "keyphrase": "XSS",
                  "type": "weakness"
                },
                {
                  "id": "impact:stored cross-site scripting",
                  "keyphrase": "stored cross-site scripting",
                  "type": "impact"
                },
                {
                  "id": "version:n/a through 3.0.0.1",
                  "keyphrase": "n/a through 3.0.0.1",
                  "type": "version"
                }
              ]
            },
            "similarity": 243.93159367606975
          },
          {
            "metadata": {
              "doc_id": "601",
              "name": "URL Redirection to Untrusted Site ('Open Redirect')",
              "source": "sparse",
              "original_content": "The web application accepts a user-controlled input that specifies a link to an external site, and uses that link in a redirect.",
              "keyphrase_sources": [
                {
                  "id": "weakness:cross-site request forgery",
                  "keyphrase": "cross-site request forgery",
                  "type": "weakness"
                }
              ]
            },
            "similarity": 234.43154055816748
          }
        ]
      },
      "weakness:XSS": {
        "keyphrase": "XSS",
        "type": "weakness",
        "cwes": [
          {
            "metadata": {
              "doc_id": "352",
              "name": "Cross-Site Request Forgery (CSRF)",
              "source": "sparse",
              "original_content": "The web application does not, or can not, sufficiently verify whether a well-formed, valid, consistent request was intentionally provided by the user who submitted the request."
            },
            "similarity": 266.6195333617826
          },
          {
            "metadata": {
              "doc_id": "434",
              "name": "Unrestricted Upload of File with Dangerous Type",
              "source": "sparse",
              "original_content": "The product allows the upload or transfer of dangerous file types that are automatically processed within its environment.",
              "keyphrase_sources": [
                {
                  "id": "weakness:XSS",
                  "keyphrase": "XSS",
                  "type": "weakness"
                },
                {
                  "id": "impact:stored cross-site scripting",
                  "keyphrase": "stored cross-site scripting",
                  "type": "impact"
                },
                {
                  "id": "product:wp-buy wordpress related Posts with thumbnails",
                  "keyphrase": "wp-buy wordpress related Posts with thumbnails",
                  "type": "product"
                },
                {
                  "id": "version:n/a through 3.0.0.1",
                  "keyphrase": "n/a through 3.0.0.1",
                  "type": "version"
                }
              ]
            },
            "similarity": 206.82594145480675
          },
          {
            "metadata": {
              "doc_id": "79",
              "name": "Improper Neutralization of Input During Web Page Generation ('Cross-site Scripting')",
              "source": "sparse",
              "original_content": "The product does not neutralize or incorrectly neutralizes user-controllable input before it is placed in output that is used as a web page that is served to other users."
            },
            "similarity": 201.13121169606205
          },
          {
            "metadata": {
              "doc_id": "116",
              "name": "Improper Encoding or Escaping of Output",
              "source": "sparse",
              "original_content": "The product prepares a structured message for communication with another component, but encoding or escaping of the data is either missing or done incorrectly. As a result, the intended structure of the message is not preserved.",
              "keyphrase_sources": [
                {
                  "id": "weakness:XSS",
                  "keyphrase": "XSS",
                  "type": "weakness"
                },
                {
                  "id": "impact:stored cross-site scripting",
                  "keyphrase": "stored cross-site scripting",
                  "type": "impact"
                },
                {
                  "id": "version:n/a through 3.0.0.1",
                  "keyphrase": "n/a through 3.0.0.1",
                  "type": "version"
                }
              ]
            },
            "similarity": 194.588517330421
          },
          {
            "metadata": {
              "doc_id": "862",
              "name": "Missing Authorization",
              "source": "sparse",
              "original_content": "The product does not perform an authorization check when an actor attempts to access a resource or perform an action.",
              "keyphrase_sources": [
                {
                  "id": "weakness:XSS",
                  "keyphrase": "XSS",
                  "type": "weakness"
                },
                {
                  "id": "product:wp-buy wordpress related Posts with thumbnails",
                  "keyphrase": "wp-buy wordpress related Posts with thumbnails",
                  "type": "product"
                },
                {
                  "id": "version:n/a through 3.0.0.1",
                  "keyphrase": "n/a through 3.0.0.1",
                  "type": "version"
                }
              ]
            },
            "similarity": 173.70611673378502
          }
        ]
      },
      "impact:stored cross-site scripting": {
        "keyphrase": "stored cross-site scripting",
        "type": "impact",
        "cwes": [
          {
            "metadata": {
              "doc_id": "352",
              "name": "Cross-Site Request Forgery (CSRF)",
              "source": "sparse",
              "original_content": "The web application does not, or can not, sufficiently verify whether a well-formed, valid, consistent request was intentionally provided by the user who submitted the request."
            },
            "similarity": 127.63850123743885
          },
          {
            "metadata": {
              "doc_id": "79",
              "name": "Improper Neutralization of Input During Web Page Generation ('Cross-site Scripting')",
              "source": "sparse",
              "original_content": "The product does not neutralize or incorrectly neutralizes user-controllable input before it is placed in output that is used as a web page that is served to other users."
            },
            "similarity": 99.97133074150176
          },
          {
            "metadata": {
              "doc_id": "434",
              "name": "Unrestricted Upload of File with Dangerous Type",
              "source": "sparse",
              "original_content": "The product allows the upload or transfer of dangerous file types that are automatically processed within its environment."
            },
            "similarity": 93.65636037257232
          },
          {
            "metadata": {
              "doc_id": "116",
              "name": "Improper Encoding or Escaping of Output",
              "source": "sparse",
              "original_content": "The product prepares a structured message for communication with another component, but encoding or escaping of the data is either missing or done incorrectly. As a result, the intended structure of the message is not preserved."
            },
            "similarity": 93.01213646849949
          },
          {
            "metadata": {
              "doc_id": "80",
              "name": "Improper Neutralization of Script-Related HTML Tags in a Web Page (Basic XSS)",
              "source": "sparse",
              "original_content": "The product receives input from an upstream component, but it does not neutralize or incorrectly neutralizes special characters such as \"<\", \">\", and \"&\" that could be interpreted as web-scripting elements when they are sent to a downstream component that processes web pages.",
              "keyphrase_sources": [
                {
                  "id": "impact:stored cross-site scripting",
                  "keyphrase": "stored cross-site scripting",
                  "type": "impact"
                }
              ]
            },
            "similarity": 84.56623185109716
          }
        ]
      },
      "product:wp-buy wordpress related Posts with thumbnails": {
        "keyphrase": "wp-buy wordpress related Posts with thumbnails",
        "type": "product",
        "cwes": [
          {
            "metadata": {
              "doc_id": "352",
              "name": "Cross-Site Request Forgery (CSRF)",
              "source": "sparse",
              "original_content": "The web application does not, or can not, sufficiently verify whether a well-formed, valid, consistent request was intentionally provided by the user who submitted the request."
            },
            "similarity": 120.73601323359028
          },
          {
            "metadata": {
              "doc_id": "434",
              "name": "Unrestricted Upload of File with Dangerous Type",
              "source": "sparse",
              "original_content": "The product allows the upload or transfer of dangerous file types that are automatically processed within its environment."
            },
            "similarity": 95.47176619867625
          },
          {
            "metadata": {
              "doc_id": "862",
              "name": "Missing Authorization",
              "source": "sparse",
              "original_content": "The product does not perform an authorization check when an actor attempts to access a resource or perform an action."
            },
            "similarity": 89.23000073362277
          },
          {
            "metadata": {
              "doc_id": "266",
              "name": "Incorrect Privilege Assignment",
              "source": "sparse",
              "original_content": "A product incorrectly assigns a privilege to a particular actor, creating an unintended sphere of control for that actor.",
              "keyphrase_sources": [
                {
                  "id": "product:wp-buy wordpress related Posts with thumbnails",
                  "keyphrase": "wp-buy wordpress related Posts with thumbnails",
                  "type": "product"
                }
              ]
            },
            "similarity": 88.04186871009664
          },
          {
            "metadata": {
              "doc_id": "863",
              "name": "Incorrect Authorization",
              "source": "sparse",
              "original_content": "The product performs an authorization check when an actor attempts to access a resource or perform an action, but it does not correctly perform the check.",
              "keyphrase_sources": [
                {
                  "id": "product:wp-buy wordpress related Posts with thumbnails",
                  "keyphrase": "wp-buy wordpress related Posts with thumbnails",
                  "type": "product"
                }
              ]
            },
            "similarity": 82.21902330204124
          }
        ]
      },
      "version:n/a through 3.0.0.1": {
        "keyphrase": "n/a through 3.0.0.1",
        "type": "version",
        "cwes": [
          {
            "metadata": {
              "doc_id": "352",
              "name": "Cross-Site Request Forgery (CSRF)",
              "source": "sparse",
              "original_content": "The web application does not, or can not, sufficiently verify whether a well-formed, valid, consistent request was intentionally provided by the user who submitted the request."
            },
            "similarity": 103.67459207760535
          },
          {
            "metadata": {
              "doc_id": "434",
              "name": "Unrestricted Upload of File with Dangerous Type",
              "source": "sparse",
              "original_content": "The product allows the upload or transfer of dangerous file types that are automatically processed within its environment."
            },
            "similarity": 89.0459864428368
          },
          {
            "metadata": {
              "doc_id": "862",
              "name": "Missing Authorization",
              "source": "sparse",
              "original_content": "The product does not perform an authorization check when an actor attempts to access a resource or perform an action."
            },
            "similarity": 80.27103303745223
          },
          {
            "metadata": {
              "doc_id": "79",
              "name": "Improper Neutralization of Input During Web Page Generation ('Cross-site Scripting')",
              "source": "sparse",
              "original_content": "The product does not neutralize or incorrectly neutralizes user-controllable input before it is placed in output that is used as a web page that is served to other users."
            },
            "similarity": 78.28923537852805
          },
          {
            "metadata": {
              "doc_id": "116",
              "name": "Improper Encoding or Escaping of Output",
              "source": "sparse",
              "original_content": "The product prepares a structured message for communication with another component, but encoding or escaping of the data is either missing or done incorrectly. As a result, the intended structure of the message is not preserved."
            },
            "similarity": 76.91984911609951
          }
        ]
      }
    },
    "keyphrase_mapping": {
      "352": [
        {
          "id": "weakness:cross-site request forgery",
          "keyphrase": "cross-site request forgery",
          "type": "weakness"
        },
        {
          "id": "weakness:XSS",
          "keyphrase": "XSS",
          "type": "weakness"
        },
        {
          "id": "impact:stored cross-site scripting",
          "keyphrase": "stored cross-site scripting",
          "type": "impact"
        },
        {
          "id": "product:wp-buy wordpress related Posts with thumbnails",
          "keyphrase": "wp-buy wordpress related Posts with thumbnails",
          "type": "product"
        },
        {
          "id": "version:n/a through 3.0.0.1",
          "keyphrase": "n/a through 3.0.0.1",
          "type": "version"
        }
      ],
      "89": [
        {
          "id": "weakness:cross-site request forgery",
          "keyphrase": "cross-site request forgery",
          "type": "weakness"
        }
      ],
      "918": [
        {
          "id": "weakness:cross-site request forgery",
          "keyphrase": "cross-site request forgery",
          "type": "weakness"
        }
      ],
      "79": [
        {
          "id": "weakness:cross-site request forgery",
          "keyphrase": "cross-site request forgery",
          "type": "weakness"
        },
        {
          "id": "weakness:XSS",
          "keyphrase": "XSS",
          "type": "weakness"
        },
        {
          "id": "impact:stored cross-site scripting",
          "keyphrase": "stored cross-site scripting",
          "type": "impact"
        },
        {
          "id": "version:n/a through 3.0.0.1",
          "keyphrase": "n/a through 3.0.0.1",
          "type": "version"
        }
      ],
      "601": [
        {
          "id": "weakness:cross-site request forgery",
          "keyphrase": "cross-site request forgery",
          "type": "weakness"
        }
      ],
      "434": [
        {
          "id": "weakness:XSS",
          "keyphrase": "XSS",
          "type": "weakness"
        },
        {
          "id": "impact:stored cross-site scripting",
          "keyphrase": "stored cross-site scripting",
          "type": "impact"
        },
        {
          "id": "product:wp-buy wordpress related Posts with thumbnails",
          "keyphrase": "wp-buy wordpress related Posts with thumbnails",
          "type": "product"
        },
        {
          "id": "version:n/a through 3.0.0.1",
          "keyphrase": "n/a through 3.0.0.1",
          "type": "version"
        }
      ],
      "116": [
        {
          "id": "weakness:XSS",
          "keyphrase": "XSS",
          "type": "weakness"
        },
        {
          "id": "impact:stored cross-site scripting",
          "keyphrase": "stored cross-site scripting",
          "type": "impact"
        },
        {
          "id": "version:n/a through 3.0.0.1",
          "keyphrase": "n/a through 3.0.0.1",
          "type": "version"
        }
      ],
      "862": [
        {
          "id": "weakness:XSS",
          "keyphrase": "XSS",
          "type": "weakness"
        },
        {
          "id": "product:wp-buy wordpress related Posts with thumbnails",
          "keyphrase": "wp-buy wordpress related Posts with thumbnails",
          "type": "product"
        },
        {
          "id": "version:n/a through 3.0.0.1",
          "keyphrase": "n/a through 3.0.0.1",
          "type": "version"
        }
      ],
      "80": [
        {
          "id": "impact:stored cross-site scripting",
          "keyphrase": "stored cross-site scripting",
          "type": "impact"
        }
      ],
      "266": [
        {
          "id": "product:wp-buy wordpress related Posts with thumbnails",
          "keyphrase": "wp-buy wordpress related Posts with thumbnails",
          "type": "product"
        }
      ],
      "863": [
        {
          "id": "product:wp-buy wordpress related Posts with thumbnails",
          "keyphrase": "wp-buy wordpress related Posts with thumbnails",
          "type": "product"
        }
      ]
    },
    "relevant_cwes": [
      {
        "metadata": {
          "doc_id": "352",
          "name": "Cross-Site Request Forgery (CSRF)",
          "source": "sparse",
          "original_content": "The web application does not, or can not, sufficiently verify whether a well-formed, valid, consistent request was intentionally provided by the user who submitted the request.",
          "keyphrase_sources": [
            {
              "id": "weakness:cross-site request forgery",
              "keyphrase": "cross-site request forgery",
              "type": "weakness"
            },
            {
              "id": "weakness:XSS",
              "keyphrase": "XSS",
              "type": "weakness"
            },
            {
              "id": "impact:stored cross-site scripting",
              "keyphrase": "stored cross-site scripting",
              "type": "impact"
            },
            {
              "id": "product:wp-buy wordpress related Posts with thumbnails",
              "keyphrase": "wp-buy wordpress related Posts with thumbnails",
              "type": "product"
            },
            {
              "id": "version:n/a through 3.0.0.1",
              "keyphrase": "n/a through 3.0.0.1",
              "type": "version"
            }
          ]
        },
        "similarity": 352.7992829751004
      },
      {
        "metadata": {
          "doc_id": "89",
          "name": "Improper Neutralization of Special Elements used in an SQL Command ('SQL Injection')",
          "source": "sparse",
          "original_content": "The product constructs all or part of an SQL command using externally-influenced input from an upstream component, but it does not neutralize or incorrectly neutralizes special elements that could modify the intended SQL command when it is sent to a downstream component. Without sufficient removal or quoting of SQL syntax in user-controllable inputs, the generated SQL query can cause those inputs to be interpreted as SQL instead of ordinary user data.",
          "keyphrase_sources": [
            {
              "id": "weakness:cross-site request forgery",
              "keyphrase": "cross-site request forgery",
              "type": "weakness"
            }
          ]
        },
        "similarity": 274.8385870694747
      },
      {
        "metadata": {
          "doc_id": "918",
          "name": "Server-Side Request Forgery (SSRF)",
          "source": "sparse",
          "original_content": "The web server receives a URL or similar request from an upstream component and retrieves the contents of this URL, but it does not sufficiently ensure that the request is being sent to the expected destination.",
          "keyphrase_sources": [
            {
              "id": "weakness:cross-site request forgery",
              "keyphrase": "cross-site request forgery",
              "type": "weakness"
            }
          ]
        },
        "similarity": 249.14371205204378
      },
      {
        "metadata": {
          "doc_id": "79",
          "name": "Improper Neutralization of Input During Web Page Generation ('Cross-site Scripting')",
          "source": "sparse",
          "original_content": "The product does not neutralize or incorrectly neutralizes user-controllable input before it is placed in output that is used as a web page that is served to other users.",
          "keyphrase_sources": [
            {
              "id": "weakness:cross-site request forgery",
              "keyphrase": "cross-site request forgery",
              "type": "weakness"
            },
            {
              "id": "weakness:XSS",
              "keyphrase": "XSS",
              "type": "weakness"
            },
            {
              "id": "impact:stored cross-site scripting",
              "keyphrase": "stored cross-site scripting",
              "type": "impact"
            },
            {
              "id": "version:n/a through 3.0.0.1",
              "keyphrase": "n/a through 3.0.0.1",
              "type": "version"
            }
          ]
        },
        "similarity": 243.93159367606975
      },
      {
        "metadata": {
          "doc_id": "601",
          "name": "URL Redirection to Untrusted Site ('Open Redirect')",
          "source": "sparse",
          "original_content": "The web application accepts a user-controlled input that specifies a link to an external site, and uses that link in a redirect.",
          "keyphrase_sources": [
            {
              "id": "weakness:cross-site request forgery",
              "keyphrase": "cross-site request forgery",
              "type": "weakness"
            }
          ]
        },
        "similarity": 234.43154055816748
      },
      {
        "metadata": {
          "doc_id": "434",
          "name": "Unrestricted Upload of File with Dangerous Type",
          "source": "sparse",
          "original_content": "The product allows the upload or transfer of dangerous file types that are automatically processed within its environment.",
          "keyphrase_sources": [
            {
              "id": "weakness:XSS",
              "keyphrase": "XSS",
              "type": "weakness"
            },
            {
              "id": "impact:stored cross-site scripting",
              "keyphrase": "stored cross-site scripting",
              "type": "impact"
            },
            {
              "id": "product:wp-buy wordpress related Posts with thumbnails",
              "keyphrase": "wp-buy wordpress related Posts with thumbnails",
              "type": "product"
            },
            {
              "id": "version:n/a through 3.0.0.1",
              "keyphrase": "n/a through 3.0.0.1",
              "type": "version"
            }
          ]
        },
        "similarity": 206.82594145480675
      },
      {
        "metadata": {
          "doc_id": "116",
          "name": "Improper Encoding or Escaping of Output",
          "source": "sparse",
          "original_content": "The product prepares a structured message for communication with another component, but encoding or escaping of the data is either missing or done incorrectly. As a result, the intended structure of the message is not preserved.",
          "keyphrase_sources": [
            {
              "id": "weakness:XSS",
              "keyphrase": "XSS",
              "type": "weakness"
            },
            {
              "id": "impact:stored cross-site scripting",
              "keyphrase": "stored cross-site scripting",
              "type": "impact"
            },
            {
              "id": "version:n/a through 3.0.0.1",
              "keyphrase": "n/a through 3.0.0.1",
              "type": "version"
            }
          ]
        },
        "similarity": 194.588517330421
      },
      {
        "metadata": {
          "doc_id": "862",
          "name": "Missing Authorization",
          "source": "sparse",
          "original_content": "The product does not perform an authorization check when an actor attempts to access a resource or perform an action.",
          "keyphrase_sources": [
            {
              "id": "weakness:XSS",
              "keyphrase": "XSS",
              "type": "weakness"
            },
            {
              "id": "product:wp-buy wordpress related Posts with thumbnails",
              "keyphrase": "wp-buy wordpress related Posts with thumbnails",
              "type": "product"
            },
            {
              "id": "version:n/a through 3.0.0.1",
              "keyphrase": "n/a through 3.0.0.1",
              "type": "version"
            }
          ]
        },
        "similarity": 173.70611673378502
      },
      {
        "metadata": {
          "doc_id": "266",
          "name": "Incorrect Privilege Assignment",
          "source": "sparse",
          "original_content": "A product incorrectly assigns a privilege to a particular actor, creating an unintended sphere of control for that actor.",
          "keyphrase_sources": [
            {
              "id": "product:wp-buy wordpress related Posts with thumbnails",
              "keyphrase": "wp-buy wordpress related Posts with thumbnails",
              "type": "product"
            }
          ]
        },
        "similarity": 88.04186871009664
      },
      {
        "metadata": {
          "doc_id": "80",
          "name": "Improper Neutralization of Script-Related HTML Tags in a Web Page (Basic XSS)",
          "source": "sparse",
          "original_content": "The product receives input from an upstream component, but it does not neutralize or incorrectly neutralizes special characters such as \"<\", \">\", and \"&\" that could be interpreted as web-scripting elements when they are sent to a downstream component that processes web pages.",
          "keyphrase_sources": [
            {
              "id": "impact:stored cross-site scripting",
              "keyphrase": "stored cross-site scripting",
              "type": "impact"
            }
          ]
        },
        "similarity": 84.56623185109716
      },
      {
        "metadata": {
          "doc_id": "863",
          "name": "Incorrect Authorization",
          "source": "sparse",
          "original_content": "The product performs an authorization check when an actor attempts to access a resource or perform an action, but it does not correctly perform the check.",
          "keyphrase_sources": [
            {
              "id": "product:wp-buy wordpress related Posts with thumbnails",
              "keyphrase": "wp-buy wordpress related Posts with thumbnails",
              "type": "product"
            }
          ]
        },
        "similarity": 82.21902330204124
      }
    ],
    "enhanced_query": "# Vulnerability Description\n\n    Cross-Site Request Forgery (CSRF) vulnerability in wp-buy wordpress related Posts with thumbnails allows Stored **XSS**. This issue affects wordpress related Posts with thumbnails from n/a through 3.0.0.1.\n\n    # Keyphrase-Specific CWE Analysis\n    This vulnerability contains multiple keyphrases that may map to different CWEs. \n    Please analyze each keyphrase separately and determine the most appropriate CWE(s) for each.\n\n    ## WEAKNESS: 'cross-site request forgery'\n\nRelevant CWEs for this WEAKNESS:\n\n### 1. CWE-352: Cross-Site Request Forgery (CSRF) (Score: 352.80)\n\nThe web application does not, or can not, sufficiently verify whether a well-formed, valid, consistent request was intentionally provided by the user who submitted the request....\n\n### 2. CWE-89: Improper Neutralization of Special Elements used in an SQL Command ('SQL Injection') (Score: 274.84)\n\nThe product constructs all or part of an SQL command using externally-influenced input from an upstream component, but it does not neutralize or incorrectly neutralizes special elements that could modify the intended SQL command when it is sent to a downstream component. Without sufficient removal o...\n\n### 3. CWE-918: Server-Side Request Forgery (SSRF) (Score: 249.14)\n\nThe web server receives a URL or similar request from an upstream component and retrieves the contents of this URL, but it does not sufficiently ensure that the request is being sent to the expected destination....\n\n### 4. CWE-79: Improper Neutralization of Input During Web Page Generation ('Cross-site Scripting') (Score: 243.93)\n\nThe product does not neutralize or incorrectly neutralizes user-controllable input before it is placed in output that is used as a web page that is served to other users....\n\n### 5. CWE-601: URL Redirection to Untrusted Site ('Open Redirect') (Score: 234.43)\n\nThe web application accepts a user-controlled input that specifies a link to an external site, and uses that link in a redirect....\n\n## WEAKNESS: 'XSS'\n\nRelevant CWEs for this WEAKNESS:\n\n### 1. CWE-352: Cross-Site Request Forgery (CSRF) (Score: 352.80)\n\nThe web application does not, or can not, sufficiently verify whether a well-formed, valid, consistent request was intentionally provided by the user who submitted the request....\n\n### 2. CWE-79: Improper Neutralization of Input During Web Page Generation ('Cross-site Scripting') (Score: 243.93)\n\nThe product does not neutralize or incorrectly neutralizes user-controllable input before it is placed in output that is used as a web page that is served to other users....\n\n### 3. CWE-434: Unrestricted Upload of File with Dangerous Type (Score: 206.83)\n\nThe product allows the upload or transfer of dangerous file types that are automatically processed within its environment....\n\n### 4. CWE-116: Improper Encoding or Escaping of Output (Score: 194.59)\n\nThe product prepares a structured message for communication with another component, but encoding or escaping of the data is either missing or done incorrectly. As a result, the intended structure of the message is not preserved....\n\n### 5. CWE-862: Missing Authorization (Score: 173.71)\n\nThe product does not perform an authorization check when an actor attempts to access a resource or perform an action....\n\n## IMPACT: 'stored cross-site scripting'\n\nRelevant CWEs for this IMPACT:\n\n### 1. CWE-352: Cross-Site Request Forgery (CSRF) (Score: 352.80)\n\nThe web application does not, or can not, sufficiently verify whether a well-formed, valid, consistent request was intentionally provided by the user who submitted the request....\n\n### 2. CWE-79: Improper Neutralization of Input During Web Page Generation ('Cross-site Scripting') (Score: 243.93)\n\nThe product does not neutralize or incorrectly neutralizes user-controllable input before it is placed in output that is used as a web page that is served to other users....\n\n### 3. CWE-434: Unrestricted Upload of File with Dangerous Type (Score: 206.83)\n\nThe product allows the upload or transfer of dangerous file types that are automatically processed within its environment....\n\n### 4. CWE-116: Improper Encoding or Escaping of Output (Score: 194.59)\n\nThe product prepares a structured message for communication with another component, but encoding or escaping of the data is either missing or done incorrectly. As a result, the intended structure of the message is not preserved....\n\n### 5. CWE-80: Improper Neutralization of Script-Related HTML Tags in a Web Page (Basic XSS) (Score: 84.57)\n\nThe product receives input from an upstream component, but it does not neutralize or incorrectly neutralizes special characters such as \"<\", \">\", and \"&\" that could be interpreted as web-scripting elements when they are sent to a downstream component that processes web pages....\n\n## PRODUCT: 'wp-buy wordpress related Posts with thumbnails'\n\nRelevant CWEs for this PRODUCT:\n\n### 1. CWE-352: Cross-Site Request Forgery (CSRF) (Score: 352.80)\n\nThe web application does not, or can not, sufficiently verify whether a well-formed, valid, consistent request was intentionally provided by the user who submitted the request....\n\n### 2. CWE-434: Unrestricted Upload of File with Dangerous Type (Score: 206.83)\n\nThe product allows the upload or transfer of dangerous file types that are automatically processed within its environment....\n\n### 3. CWE-862: Missing Authorization (Score: 173.71)\n\nThe product does not perform an authorization check when an actor attempts to access a resource or perform an action....\n\n### 4. CWE-266: Incorrect Privilege Assignment (Score: 88.04)\n\nA product incorrectly assigns a privilege to a particular actor, creating an unintended sphere of control for that actor....\n\n### 5. CWE-863: Incorrect Authorization (Score: 82.22)\n\nThe product performs an authorization check when an actor attempts to access a resource or perform an action, but it does not correctly perform the check....\n\n## VERSION: 'n/a through 3.0.0.1'\n\nRelevant CWEs for this VERSION:\n\n### 1. CWE-352: Cross-Site Request Forgery (CSRF) (Score: 352.80)\n\nThe web application does not, or can not, sufficiently verify whether a well-formed, valid, consistent request was intentionally provided by the user who submitted the request....\n\n### 2. CWE-79: Improper Neutralization of Input During Web Page Generation ('Cross-site Scripting') (Score: 243.93)\n\nThe product does not neutralize or incorrectly neutralizes user-controllable input before it is placed in output that is used as a web page that is served to other users....\n\n### 3. CWE-434: Unrestricted Upload of File with Dangerous Type (Score: 206.83)\n\nThe product allows the upload or transfer of dangerous file types that are automatically processed within its environment....\n\n### 4. CWE-116: Improper Encoding or Escaping of Output (Score: 194.59)\n\nThe product prepares a structured message for communication with another component, but encoding or escaping of the data is either missing or done incorrectly. As a result, the intended structure of the message is not preserved....\n\n### 5. CWE-862: Missing Authorization (Score: 173.71)\n\nThe product does not perform an authorization check when an actor attempts to access a resource or perform an action....\n\n\n    # Analysis Instructions\n    1. For each keyphrase, identify the most appropriate CWE(s) that represent the weakness.\n    2. Consider how the different keyphrases might relate to each other in the vulnerability chain.\n    3. Provide a final determination of primary CWE(s) and any secondary CWEs.\n    4. Format your response using the standard analysis template.\n\n    Please analyze how these different weaknesses interact and provide a comprehensive CWE classification.\n    "
  },
  "retrieval_time": 1.0495216846466064
}