{
  "vulnerability_info": "VulnerabilityInfo(cve_id='CVE-2024-40239', description='An incorrect **access control issue** in Life Personal Diary, Journal android app 17.5.0 allows a physically proximate attacker to escalate privileges via the fingerprint authentication function.', key_phrases={'rootcause': ['access control issue', 'incorrect access control'], 'weakness': '', 'impact': 'escalate privileges', 'vector': 'fingerprint authentication function', 'attacker': 'physically proximate attacker', 'product': ['Life Personal Diary', 'Journal android app'], 'version': '17.5.0', 'component': ''}, reference_content='Based on the provided information, here\\'s an analysis of the vulnerability:\\n\\n**CVE ID:** CVE-2024-40239 (Based on the content provided in the second source)\\n\\n**Root Cause of Vulnerability:**\\nThe root cause lies in the insecure implementation of the fingerprint authentication mechanism within the \"Life : Personal Diary, Journal\" application. Specifically:\\n1.  **Failure to invalidate existing authentication keys on new fingerprint enrollment:** The application does not disable fingerprint authentication or force re-authentication when a new fingerprint is added to the device.\\n2. **Lack of user identity verification when disabling fingerprint authentication:**  The app allows the fingerprint lock feature to be disabled without any form of identity verification.\\n\\n**Weaknesses/Vulnerabilities Present:**\\n1. **Bypass of fingerprint authentication:** An attacker can bypass the fingerprint lock by adding a new fingerprint to the device, effectively granting unauthorized access to the app\\'s contents.\\n2.  **Compromised fingerprint protection integrity:** An attacker can disable the fingerprint lock feature without proper authentication, rendering the fingerprint protection mechanism useless.\\n\\n**Impact of Exploitation:**\\n- **Unauthorized Access:** Attackers can gain access to the diary app and its contents, including personal journal entries, notes, photos, and other stored data.\\n- **Data Breach:** Sensitive and private user information is exposed to unauthorized individuals.\\n- **Compromise of user privacy and security:** The vulnerability directly impacts the privacy and security of the user, as they believe their personal diary data is protected via fingerprint.\\n\\n**Attack Vectors:**\\n- **Physical Access:** An attacker needs physical access to the device where the app is installed.\\n- **Fingerprint Enrollment:** The attacker needs the ability to add a new fingerprint to the device\\'s biometric settings.\\n- **App Manipulation:** The attacker needs to open the application and may need to modify settings to disable the fingerprint lock\\n\\n**Required Attacker Capabilities/Position:**\\n- The attacker needs physical access to the device and the ability to manipulate the device settings and enroll a new fingerprint.\\n\\n**Additional Details:**\\n- The affected app version is 17.5.0.\\n- The second document provides a more detailed explanation of the vulnerability than the official CVE description, which is a placeholder.\\n- It also proposes specific remedies for the issues that are found.\\n- This vulnerability is categorized as \"Incorrect Access Control\".', similar_info={'cwe_distribution': {}, 'cwe_consensus': '', 'similarity_stats': {'thresholds': [], 'total_samples_by_threshold': {}, 'top_cwes_by_threshold': {}}}, similarity_summary=SimilarityInsight(consensus_cwe='', top_cwes=[], confidence_levels={}, total_samples=0), analysis='', analysis_with_relationships='', criticism='', resolution='', relevant_cwes=[{'metadata': {'doc_id': '284', 'name': 'Improper Access Control', 'source': 'sparse', 'original_content': 'The product does not restrict or incorrectly restricts access to a resource from an unauthorized actor.', 'keyphrase_sources': [{'id': 'rootcause:access control issue', 'keyphrase': 'access control issue', 'type': 'rootcause'}, {'id': 'rootcause:incorrect access control', 'keyphrase': 'incorrect access control', 'type': 'rootcause'}, {'id': 'vector:fingerprint authentication function', 'keyphrase': 'fingerprint authentication function', 'type': 'vector'}]}, 'similarity': np.float64(172.2173899387957)}, {'metadata': {'doc_id': '732', 'name': 'Incorrect Permission Assignment for Critical Resource', 'source': 'sparse', 'original_content': 'The product specifies permissions for a security-critical resource in a way that allows that resource to be read or modified by unintended actors.', 'keyphrase_sources': [{'id': 'rootcause:access control issue', 'keyphrase': 'access control issue', 'type': 'rootcause'}, {'id': 'rootcause:incorrect access control', 'keyphrase': 'incorrect access control', 'type': 'rootcause'}, {'id': 'impact:escalate privileges', 'keyphrase': 'escalate privileges', 'type': 'impact'}, {'id': 'version:17.5.0', 'keyphrase': '17.5.0', 'type': 'version'}]}, 'similarity': np.float64(167.73558126572647)}, {'metadata': {'doc_id': '639', 'name': 'Authorization Bypass Through User-Controlled Key', 'source': 'sparse', 'original_content': \"The system's authorization functionality does not prevent one user from gaining access to another user's data or record by modifying the key value identifying the data.\", 'keyphrase_sources': [{'id': 'rootcause:incorrect access control', 'keyphrase': 'incorrect access control', 'type': 'rootcause'}, {'id': 'product:Life Personal Diary', 'keyphrase': 'Life Personal Diary', 'type': 'product'}]}, 'similarity': np.float64(167.49379801034394)}, {'metadata': {'doc_id': '362', 'name': \"Concurrent Execution using Shared Resource with Improper Synchronization ('Race Condition')\", 'source': 'sparse', 'original_content': 'The product contains a concurrent code sequence that requires temporary, exclusive access to a shared resource, but a timing window exists in which the shared resource can be modified by another code sequence operating concurrently.', 'keyphrase_sources': [{'id': 'rootcause:access control issue', 'keyphrase': 'access control issue', 'type': 'rootcause'}, {'id': 'impact:escalate privileges', 'keyphrase': 'escalate privileges', 'type': 'impact'}, {'id': 'vector:fingerprint authentication function', 'keyphrase': 'fingerprint authentication function', 'type': 'vector'}, {'id': 'product:Journal android app', 'keyphrase': 'Journal android app', 'type': 'product'}, {'id': 'version:17.5.0', 'keyphrase': '17.5.0', 'type': 'version'}]}, 'similarity': np.float64(166.2543708092814)}, {'metadata': {'doc_id': '863', 'name': 'Incorrect Authorization', 'source': 'sparse', 'original_content': 'The product performs an authorization check when an actor attempts to access a resource or perform an action, but it does not correctly perform the check.', 'keyphrase_sources': [{'id': 'rootcause:access control issue', 'keyphrase': 'access control issue', 'type': 'rootcause'}, {'id': 'rootcause:incorrect access control', 'keyphrase': 'incorrect access control', 'type': 'rootcause'}, {'id': 'vector:fingerprint authentication function', 'keyphrase': 'fingerprint authentication function', 'type': 'vector'}, {'id': 'version:17.5.0', 'keyphrase': '17.5.0', 'type': 'version'}]}, 'similarity': np.float64(165.679788286065)}, {'metadata': {'doc_id': '287', 'name': 'Improper Authentication', 'source': 'sparse', 'original_content': 'When an actor claims to have a given identity, the product does not prove or insufficiently proves that the claim is correct.', 'keyphrase_sources': [{'id': 'rootcause:access control issue', 'keyphrase': 'access control issue', 'type': 'rootcause'}, {'id': 'rootcause:incorrect access control', 'keyphrase': 'incorrect access control', 'type': 'rootcause'}, {'id': 'vector:fingerprint authentication function', 'keyphrase': 'fingerprint authentication function', 'type': 'vector'}]}, 'similarity': np.float64(162.85660517150808)}, {'metadata': {'doc_id': '1263', 'name': 'Improper Physical Access Control', 'source': 'sparse', 'original_content': 'The product is designed with access restricted to certain information, but it does not sufficiently protect against an unauthorized actor with physical access to these areas.', 'keyphrase_sources': [{'id': 'attacker:physically proximate attacker', 'keyphrase': 'physically proximate attacker', 'type': 'attacker'}]}, 'similarity': np.float64(69.94007413041977)}, {'metadata': {'doc_id': '311', 'name': 'Missing Encryption of Sensitive Data', 'source': 'sparse', 'original_content': 'The product does not encrypt sensitive or critical information before storage or transmission.', 'keyphrase_sources': [{'id': 'attacker:physically proximate attacker', 'keyphrase': 'physically proximate attacker', 'type': 'attacker'}]}, 'similarity': np.float64(69.27621059661277)}, {'metadata': {'doc_id': '1247', 'name': 'Improper Protection Against Voltage and Clock Glitches', 'source': 'sparse', 'original_content': 'The device does not contain or contains incorrectly implemented circuitry or sensors to detect and mitigate voltage and clock glitches and protect sensitive information or software contained on the device.', 'keyphrase_sources': [{'id': 'attacker:physically proximate attacker', 'keyphrase': 'physically proximate attacker', 'type': 'attacker'}]}, 'similarity': np.float64(68.68879918544867)}, {'metadata': {'doc_id': '549', 'name': 'Missing Password Field Masking', 'source': 'sparse', 'original_content': 'The product does not mask passwords during entry, increasing the potential for attackers to observe and capture passwords.', 'keyphrase_sources': [{'id': 'attacker:physically proximate attacker', 'keyphrase': 'physically proximate attacker', 'type': 'attacker'}]}, 'similarity': np.float64(65.45978828624635)}, {'metadata': {'doc_id': '707', 'name': 'Improper Neutralization', 'source': 'sparse', 'original_content': 'The product does not ensure or incorrectly ensures that structured messages or data are well-formed and that certain security properties are met before being read from an upstream component or sent to a downstream component.', 'keyphrase_sources': [{'id': 'attacker:physically proximate attacker', 'keyphrase': 'physically proximate attacker', 'type': 'attacker'}]}, 'similarity': np.float64(64.22319545640896)}, {'metadata': {'doc_id': '250', 'name': 'Execution with Unnecessary Privileges', 'source': 'sparse', 'original_content': 'The product performs an operation at a privilege level that is higher than the minimum level required, which creates new weaknesses or amplifies the consequences of other weaknesses.', 'keyphrase_sources': [{'id': 'impact:escalate privileges', 'keyphrase': 'escalate privileges', 'type': 'impact'}, {'id': 'version:17.5.0', 'keyphrase': '17.5.0', 'type': 'version'}]}, 'similarity': np.float64(59.53259947425671)}, {'metadata': {'doc_id': '939', 'name': 'Improper Authorization in Handler for Custom URL Scheme', 'source': 'sparse', 'original_content': 'The product uses a handler for a custom URL scheme, but it does not properly restrict which actors can invoke the handler using the scheme.', 'keyphrase_sources': [{'id': 'product:Journal android app', 'keyphrase': 'Journal android app', 'type': 'product'}]}, 'similarity': np.float64(58.96396885053941)}, {'metadata': {'doc_id': '302', 'name': 'Authentication Bypass by Assumed-Immutable Data', 'source': 'sparse', 'original_content': 'The authentication scheme or implementation uses key data elements that are assumed to be immutable, but can be controlled or modified by the attacker.', 'keyphrase_sources': [{'id': 'product:Journal android app', 'keyphrase': 'Journal android app', 'type': 'product'}]}, 'similarity': np.float64(56.34176790660478)}, {'metadata': {'doc_id': '862', 'name': 'Missing Authorization', 'source': 'sparse', 'original_content': 'The product does not perform an authorization check when an actor attempts to access a resource or perform an action.', 'keyphrase_sources': [{'id': 'product:Journal android app', 'keyphrase': 'Journal android app', 'type': 'product'}]}, 'similarity': np.float64(55.99727892189006)}, {'metadata': {'doc_id': '755', 'name': 'Improper Handling of Exceptional Conditions', 'source': 'sparse', 'original_content': 'The product does not handle or incorrectly handles an exceptional condition.', 'keyphrase_sources': [{'id': 'version:17.5.0', 'keyphrase': '17.5.0', 'type': 'version'}]}, 'similarity': np.float64(55.28692842668624)}, {'metadata': {'doc_id': '269', 'name': 'Improper Privilege Management', 'source': 'sparse', 'original_content': 'The product does not properly assign, modify, track, or check privileges for an actor, creating an unintended sphere of control for that actor.', 'keyphrase_sources': [{'id': 'impact:escalate privileges', 'keyphrase': 'escalate privileges', 'type': 'impact'}]}, 'similarity': np.float64(53.641442542531735)}, {'metadata': {'doc_id': '266', 'name': 'Incorrect Privilege Assignment', 'source': 'sparse', 'original_content': 'A product incorrectly assigns a privilege to a particular actor, creating an unintended sphere of control for that actor.', 'keyphrase_sources': [{'id': 'impact:escalate privileges', 'keyphrase': 'escalate privileges', 'type': 'impact'}]}, 'similarity': np.float64(52.67195197064708)}, {'metadata': {'doc_id': '359', 'name': 'Exposure of Private Personal Information to an Unauthorized Actor', 'source': 'sparse', 'original_content': \"The product does not properly prevent a person's private, personal information from being accessed by actors who either (1) are not explicitly authorized to access the information or (2) do not have the implicit consent of the person about whom the information is collected.\", 'keyphrase_sources': [{'id': 'product:Life Personal Diary', 'keyphrase': 'Life Personal Diary', 'type': 'product'}]}, 'similarity': np.float64(52.665840417780586)}, {'metadata': {'doc_id': '295', 'name': 'Improper Certificate Validation', 'source': 'sparse', 'original_content': 'The product does not validate, or incorrectly validates, a certificate.', 'keyphrase_sources': [{'id': 'product:Life Personal Diary', 'keyphrase': 'Life Personal Diary', 'type': 'product'}, {'id': 'product:Journal android app', 'keyphrase': 'Journal android app', 'type': 'product'}]}, 'similarity': np.float64(52.4705479981469)}, {'metadata': {'doc_id': '1390', 'name': 'Weak Authentication', 'source': 'sparse', 'original_content': 'The product uses an authentication mechanism to restrict access to specific users or identities, but the mechanism does not sufficiently prove that the claimed identity is correct.', 'keyphrase_sources': [{'id': 'vector:fingerprint authentication function', 'keyphrase': 'fingerprint authentication function', 'type': 'vector'}, {'id': 'product:Life Personal Diary', 'keyphrase': 'Life Personal Diary', 'type': 'product'}]}, 'similarity': np.float64(51.48067754510954)}, {'metadata': {'doc_id': '532', 'name': 'Insertion of Sensitive Information into Log File', 'source': 'sparse', 'original_content': 'The product writes sensitive information to a log file.', 'keyphrase_sources': [{'id': 'product:Life Personal Diary', 'keyphrase': 'Life Personal Diary', 'type': 'product'}]}, 'similarity': np.float64(47.34011517510793)}], identified_cwes={'analyzer': [], 'critic_additional': []})",
  "retrieval_results": {
    "has_multiple_keyphrases": true,
    "keyphrase_cwe_sets": {
      "rootcause:access control issue": {
        "keyphrase": "access control issue",
        "type": "rootcause",
        "cwes": [
          {
            "metadata": {
              "doc_id": "284",
              "name": "Improper Access Control",
              "source": "sparse",
              "original_content": "The product does not restrict or incorrectly restricts access to a resource from an unauthorized actor.",
              "keyphrase_sources": [
                {
                  "id": "rootcause:access control issue",
                  "keyphrase": "access control issue",
                  "type": "rootcause"
                },
                {
                  "id": "rootcause:incorrect access control",
                  "keyphrase": "incorrect access control",
                  "type": "rootcause"
                },
                {
                  "id": "vector:fingerprint authentication function",
                  "keyphrase": "fingerprint authentication function",
                  "type": "vector"
                }
              ]
            },
            "similarity": 172.2173899387957
          },
          {
            "metadata": {
              "doc_id": "732",
              "name": "Incorrect Permission Assignment for Critical Resource",
              "source": "sparse",
              "original_content": "The product specifies permissions for a security-critical resource in a way that allows that resource to be read or modified by unintended actors.",
              "keyphrase_sources": [
                {
                  "id": "rootcause:access control issue",
                  "keyphrase": "access control issue",
                  "type": "rootcause"
                },
                {
                  "id": "rootcause:incorrect access control",
                  "keyphrase": "incorrect access control",
                  "type": "rootcause"
                },
                {
                  "id": "impact:escalate privileges",
                  "keyphrase": "escalate privileges",
                  "type": "impact"
                },
                {
                  "id": "version:17.5.0",
                  "keyphrase": "17.5.0",
                  "type": "version"
                }
              ]
            },
            "similarity": 167.73558126572647
          },
          {
            "metadata": {
              "doc_id": "362",
              "name": "Concurrent Execution using Shared Resource with Improper Synchronization ('Race Condition')",
              "source": "sparse",
              "original_content": "The product contains a concurrent code sequence that requires temporary, exclusive access to a shared resource, but a timing window exists in which the shared resource can be modified by another code sequence operating concurrently.",
              "keyphrase_sources": [
                {
                  "id": "rootcause:access control issue",
                  "keyphrase": "access control issue",
                  "type": "rootcause"
                },
                {
                  "id": "impact:escalate privileges",
                  "keyphrase": "escalate privileges",
                  "type": "impact"
                },
                {
                  "id": "vector:fingerprint authentication function",
                  "keyphrase": "fingerprint authentication function",
                  "type": "vector"
                },
                {
                  "id": "product:Journal android app",
                  "keyphrase": "Journal android app",
                  "type": "product"
                },
                {
                  "id": "version:17.5.0",
                  "keyphrase": "17.5.0",
                  "type": "version"
                }
              ]
            },
            "similarity": 166.2543708092814
          },
          {
            "metadata": {
              "doc_id": "863",
              "name": "Incorrect Authorization",
              "source": "sparse",
              "original_content": "The product performs an authorization check when an actor attempts to access a resource or perform an action, but it does not correctly perform the check.",
              "keyphrase_sources": [
                {
                  "id": "rootcause:access control issue",
                  "keyphrase": "access control issue",
                  "type": "rootcause"
                },
                {
                  "id": "rootcause:incorrect access control",
                  "keyphrase": "incorrect access control",
                  "type": "rootcause"
                },
                {
                  "id": "vector:fingerprint authentication function",
                  "keyphrase": "fingerprint authentication function",
                  "type": "vector"
                },
                {
                  "id": "version:17.5.0",
                  "keyphrase": "17.5.0",
                  "type": "version"
                }
              ]
            },
            "similarity": 165.679788286065
          },
          {
            "metadata": {
              "doc_id": "287",
              "name": "Improper Authentication",
              "source": "sparse",
              "original_content": "When an actor claims to have a given identity, the product does not prove or insufficiently proves that the claim is correct.",
              "keyphrase_sources": [
                {
                  "id": "rootcause:access control issue",
                  "keyphrase": "access control issue",
                  "type": "rootcause"
                },
                {
                  "id": "rootcause:incorrect access control",
                  "keyphrase": "incorrect access control",
                  "type": "rootcause"
                },
                {
                  "id": "vector:fingerprint authentication function",
                  "keyphrase": "fingerprint authentication function",
                  "type": "vector"
                }
              ]
            },
            "similarity": 162.85660517150808
          }
        ]
      },
      "rootcause:incorrect access control": {
        "keyphrase": "incorrect access control",
        "type": "rootcause",
        "cwes": [
          {
            "metadata": {
              "doc_id": "284",
              "name": "Improper Access Control",
              "source": "sparse",
              "original_content": "The product does not restrict or incorrectly restricts access to a resource from an unauthorized actor."
            },
            "similarity": 179.39340796975495
          },
          {
            "metadata": {
              "doc_id": "732",
              "name": "Incorrect Permission Assignment for Critical Resource",
              "source": "sparse",
              "original_content": "The product specifies permissions for a security-critical resource in a way that allows that resource to be read or modified by unintended actors."
            },
            "similarity": 177.91346635955293
          },
          {
            "metadata": {
              "doc_id": "863",
              "name": "Incorrect Authorization",
              "source": "sparse",
              "original_content": "The product performs an authorization check when an actor attempts to access a resource or perform an action, but it does not correctly perform the check."
            },
            "similarity": 173.83686096540168
          },
          {
            "metadata": {
              "doc_id": "639",
              "name": "Authorization Bypass Through User-Controlled Key",
              "source": "sparse",
              "original_content": "The system's authorization functionality does not prevent one user from gaining access to another user's data or record by modifying the key value identifying the data.",
              "keyphrase_sources": [
                {
                  "id": "rootcause:incorrect access control",
                  "keyphrase": "incorrect access control",
                  "type": "rootcause"
                },
                {
                  "id": "product:Life Personal Diary",
                  "keyphrase": "Life Personal Diary",
                  "type": "product"
                }
              ]
            },
            "similarity": 167.49379801034394
          },
          {
            "metadata": {
              "doc_id": "287",
              "name": "Improper Authentication",
              "source": "sparse",
              "original_content": "When an actor claims to have a given identity, the product does not prove or insufficiently proves that the claim is correct."
            },
            "similarity": 167.33994354224134
          }
        ]
      },
      "impact:escalate privileges": {
        "keyphrase": "escalate privileges",
        "type": "impact",
        "cwes": [
          {
            "metadata": {
              "doc_id": "250",
              "name": "Execution with Unnecessary Privileges",
              "source": "sparse",
              "original_content": "The product performs an operation at a privilege level that is higher than the minimum level required, which creates new weaknesses or amplifies the consequences of other weaknesses.",
              "keyphrase_sources": [
                {
                  "id": "impact:escalate privileges",
                  "keyphrase": "escalate privileges",
                  "type": "impact"
                },
                {
                  "id": "version:17.5.0",
                  "keyphrase": "17.5.0",
                  "type": "version"
                }
              ]
            },
            "similarity": 59.53259947425671
          },
          {
            "metadata": {
              "doc_id": "732",
              "name": "Incorrect Permission Assignment for Critical Resource",
              "source": "sparse",
              "original_content": "The product specifies permissions for a security-critical resource in a way that allows that resource to be read or modified by unintended actors."
            },
            "similarity": 58.690886121353806
          },
          {
            "metadata": {
              "doc_id": "362",
              "name": "Concurrent Execution using Shared Resource with Improper Synchronization ('Race Condition')",
              "source": "sparse",
              "original_content": "The product contains a concurrent code sequence that requires temporary, exclusive access to a shared resource, but a timing window exists in which the shared resource can be modified by another code sequence operating concurrently."
            },
            "similarity": 55.359380763070526
          },
          {
            "metadata": {
              "doc_id": "269",
              "name": "Improper Privilege Management",
              "source": "sparse",
              "original_content": "The product does not properly assign, modify, track, or check privileges for an actor, creating an unintended sphere of control for that actor.",
              "keyphrase_sources": [
                {
                  "id": "impact:escalate privileges",
                  "keyphrase": "escalate privileges",
                  "type": "impact"
                }
              ]
            },
            "similarity": 53.641442542531735
          },
          {
            "metadata": {
              "doc_id": "266",
              "name": "Incorrect Privilege Assignment",
              "source": "sparse",
              "original_content": "A product incorrectly assigns a privilege to a particular actor, creating an unintended sphere of control for that actor.",
              "keyphrase_sources": [
                {
                  "id": "impact:escalate privileges",
                  "keyphrase": "escalate privileges",
                  "type": "impact"
                }
              ]
            },
            "similarity": 52.67195197064708
          }
        ]
      },
      "vector:fingerprint authentication function": {
        "keyphrase": "fingerprint authentication function",
        "type": "vector",
        "cwes": [
          {
            "metadata": {
              "doc_id": "287",
              "name": "Improper Authentication",
              "source": "sparse",
              "original_content": "When an actor claims to have a given identity, the product does not prove or insufficiently proves that the claim is correct."
            },
            "similarity": 52.431389780010605
          },
          {
            "metadata": {
              "doc_id": "1390",
              "name": "Weak Authentication",
              "source": "sparse",
              "original_content": "The product uses an authentication mechanism to restrict access to specific users or identities, but the mechanism does not sufficiently prove that the claimed identity is correct.",
              "keyphrase_sources": [
                {
                  "id": "vector:fingerprint authentication function",
                  "keyphrase": "fingerprint authentication function",
                  "type": "vector"
                },
                {
                  "id": "product:Life Personal Diary",
                  "keyphrase": "Life Personal Diary",
                  "type": "product"
                }
              ]
            },
            "similarity": 51.48067754510954
          },
          {
            "metadata": {
              "doc_id": "362",
              "name": "Concurrent Execution using Shared Resource with Improper Synchronization ('Race Condition')",
              "source": "sparse",
              "original_content": "The product contains a concurrent code sequence that requires temporary, exclusive access to a shared resource, but a timing window exists in which the shared resource can be modified by another code sequence operating concurrently."
            },
            "similarity": 50.386373808048624
          },
          {
            "metadata": {
              "doc_id": "863",
              "name": "Incorrect Authorization",
              "source": "sparse",
              "original_content": "The product performs an authorization check when an actor attempts to access a resource or perform an action, but it does not correctly perform the check."
            },
            "similarity": 49.98988443368321
          },
          {
            "metadata": {
              "doc_id": "284",
              "name": "Improper Access Control",
              "source": "sparse",
              "original_content": "The product does not restrict or incorrectly restricts access to a resource from an unauthorized actor."
            },
            "similarity": 49.86827935478489
          }
        ]
      },
      "attacker:physically proximate attacker": {
        "keyphrase": "physically proximate attacker",
        "type": "attacker",
        "cwes": [
          {
            "metadata": {
              "doc_id": "1263",
              "name": "Improper Physical Access Control",
              "source": "sparse",
              "original_content": "The product is designed with access restricted to certain information, but it does not sufficiently protect against an unauthorized actor with physical access to these areas.",
              "keyphrase_sources": [
                {
                  "id": "attacker:physically proximate attacker",
                  "keyphrase": "physically proximate attacker",
                  "type": "attacker"
                }
              ]
            },
            "similarity": 69.94007413041977
          },
          {
            "metadata": {
              "doc_id": "311",
              "name": "Missing Encryption of Sensitive Data",
              "source": "sparse",
              "original_content": "The product does not encrypt sensitive or critical information before storage or transmission.",
              "keyphrase_sources": [
                {
                  "id": "attacker:physically proximate attacker",
                  "keyphrase": "physically proximate attacker",
                  "type": "attacker"
                }
              ]
            },
            "similarity": 69.27621059661277
          },
          {
            "metadata": {
              "doc_id": "1247",
              "name": "Improper Protection Against Voltage and Clock Glitches",
              "source": "sparse",
              "original_content": "The device does not contain or contains incorrectly implemented circuitry or sensors to detect and mitigate voltage and clock glitches and protect sensitive information or software contained on the device.",
              "keyphrase_sources": [
                {
                  "id": "attacker:physically proximate attacker",
                  "keyphrase": "physically proximate attacker",
                  "type": "attacker"
                }
              ]
            },
            "similarity": 68.68879918544867
          },
          {
            "metadata": {
              "doc_id": "549",
              "name": "Missing Password Field Masking",
              "source": "sparse",
              "original_content": "The product does not mask passwords during entry, increasing the potential for attackers to observe and capture passwords.",
              "keyphrase_sources": [
                {
                  "id": "attacker:physically proximate attacker",
                  "keyphrase": "physically proximate attacker",
                  "type": "attacker"
                }
              ]
            },
            "similarity": 65.45978828624635
          },
          {
            "metadata": {
              "doc_id": "707",
              "name": "Improper Neutralization",
              "source": "sparse",
              "original_content": "The product does not ensure or incorrectly ensures that structured messages or data are well-formed and that certain security properties are met before being read from an upstream component or sent to a downstream component.",
              "keyphrase_sources": [
                {
                  "id": "attacker:physically proximate attacker",
                  "keyphrase": "physically proximate attacker",
                  "type": "attacker"
                }
              ]
            },
            "similarity": 64.22319545640896
          }
        ]
      },
      "product:Life Personal Diary": {
        "keyphrase": "Life Personal Diary",
        "type": "product",
        "cwes": [
          {
            "metadata": {
              "doc_id": "359",
              "name": "Exposure of Private Personal Information to an Unauthorized Actor",
              "source": "sparse",
              "original_content": "The product does not properly prevent a person's private, personal information from being accessed by actors who either (1) are not explicitly authorized to access the information or (2) do not have the implicit consent of the person about whom the information is collected.",
              "keyphrase_sources": [
                {
                  "id": "product:Life Personal Diary",
                  "keyphrase": "Life Personal Diary",
                  "type": "product"
                }
              ]
            },
            "similarity": 52.665840417780586
          },
          {
            "metadata": {
              "doc_id": "295",
              "name": "Improper Certificate Validation",
              "source": "sparse",
              "original_content": "The product does not validate, or incorrectly validates, a certificate.",
              "keyphrase_sources": [
                {
                  "id": "product:Life Personal Diary",
                  "keyphrase": "Life Personal Diary",
                  "type": "product"
                },
                {
                  "id": "product:Journal android app",
                  "keyphrase": "Journal android app",
                  "type": "product"
                }
              ]
            },
            "similarity": 52.4705479981469
          },
          {
            "metadata": {
              "doc_id": "639",
              "name": "Authorization Bypass Through User-Controlled Key",
              "source": "sparse",
              "original_content": "The system's authorization functionality does not prevent one user from gaining access to another user's data or record by modifying the key value identifying the data."
            },
            "similarity": 49.60409900018814
          },
          {
            "metadata": {
              "doc_id": "1390",
              "name": "Weak Authentication",
              "source": "sparse",
              "original_content": "The product uses an authentication mechanism to restrict access to specific users or identities, but the mechanism does not sufficiently prove that the claimed identity is correct."
            },
            "similarity": 49.32388897054226
          },
          {
            "metadata": {
              "doc_id": "532",
              "name": "Insertion of Sensitive Information into Log File",
              "source": "sparse",
              "original_content": "The product writes sensitive information to a log file.",
              "keyphrase_sources": [
                {
                  "id": "product:Life Personal Diary",
                  "keyphrase": "Life Personal Diary",
                  "type": "product"
                }
              ]
            },
            "similarity": 47.34011517510793
          }
        ]
      },
      "product:Journal android app": {
        "keyphrase": "Journal android app",
        "type": "product",
        "cwes": [
          {
            "metadata": {
              "doc_id": "939",
              "name": "Improper Authorization in Handler for Custom URL Scheme",
              "source": "sparse",
              "original_content": "The product uses a handler for a custom URL scheme, but it does not properly restrict which actors can invoke the handler using the scheme.",
              "keyphrase_sources": [
                {
                  "id": "product:Journal android app",
                  "keyphrase": "Journal android app",
                  "type": "product"
                }
              ]
            },
            "similarity": 58.96396885053941
          },
          {
            "metadata": {
              "doc_id": "302",
              "name": "Authentication Bypass by Assumed-Immutable Data",
              "source": "sparse",
              "original_content": "The authentication scheme or implementation uses key data elements that are assumed to be immutable, but can be controlled or modified by the attacker.",
              "keyphrase_sources": [
                {
                  "id": "product:Journal android app",
                  "keyphrase": "Journal android app",
                  "type": "product"
                }
              ]
            },
            "similarity": 56.34176790660478
          },
          {
            "metadata": {
              "doc_id": "295",
              "name": "Improper Certificate Validation",
              "source": "sparse",
              "original_content": "The product does not validate, or incorrectly validates, a certificate."
            },
            "similarity": 56.27142912957382
          },
          {
            "metadata": {
              "doc_id": "862",
              "name": "Missing Authorization",
              "source": "sparse",
              "original_content": "The product does not perform an authorization check when an actor attempts to access a resource or perform an action.",
              "keyphrase_sources": [
                {
                  "id": "product:Journal android app",
                  "keyphrase": "Journal android app",
                  "type": "product"
                }
              ]
            },
            "similarity": 55.99727892189006
          },
          {
            "metadata": {
              "doc_id": "362",
              "name": "Concurrent Execution using Shared Resource with Improper Synchronization ('Race Condition')",
              "source": "sparse",
              "original_content": "The product contains a concurrent code sequence that requires temporary, exclusive access to a shared resource, but a timing window exists in which the shared resource can be modified by another code sequence operating concurrently."
            },
            "similarity": 55.43370479709315
          }
        ]
      },
      "version:17.5.0": {
        "keyphrase": "17.5.0",
        "type": "version",
        "cwes": [
          {
            "metadata": {
              "doc_id": "362",
              "name": "Concurrent Execution using Shared Resource with Improper Synchronization ('Race Condition')",
              "source": "sparse",
              "original_content": "The product contains a concurrent code sequence that requires temporary, exclusive access to a shared resource, but a timing window exists in which the shared resource can be modified by another code sequence operating concurrently."
            },
            "similarity": 58.443028108746425
          },
          {
            "metadata": {
              "doc_id": "250",
              "name": "Execution with Unnecessary Privileges",
              "source": "sparse",
              "original_content": "The product performs an operation at a privilege level that is higher than the minimum level required, which creates new weaknesses or amplifies the consequences of other weaknesses."
            },
            "similarity": 57.90940260276254
          },
          {
            "metadata": {
              "doc_id": "755",
              "name": "Improper Handling of Exceptional Conditions",
              "source": "sparse",
              "original_content": "The product does not handle or incorrectly handles an exceptional condition.",
              "keyphrase_sources": [
                {
                  "id": "version:17.5.0",
                  "keyphrase": "17.5.0",
                  "type": "version"
                }
              ]
            },
            "similarity": 55.28692842668624
          },
          {
            "metadata": {
              "doc_id": "732",
              "name": "Incorrect Permission Assignment for Critical Resource",
              "source": "sparse",
              "original_content": "The product specifies permissions for a security-critical resource in a way that allows that resource to be read or modified by unintended actors."
            },
            "similarity": 54.62115765807388
          },
          {
            "metadata": {
              "doc_id": "863",
              "name": "Incorrect Authorization",
              "source": "sparse",
              "original_content": "The product performs an authorization check when an actor attempts to access a resource or perform an action, but it does not correctly perform the check."
            },
            "similarity": 51.75270761110138
          }
        ]
      }
    },
    "keyphrase_mapping": {
      "284": [
        {
          "id": "rootcause:access control issue",
          "keyphrase": "access control issue",
          "type": "rootcause"
        },
        {
          "id": "rootcause:incorrect access control",
          "keyphrase": "incorrect access control",
          "type": "rootcause"
        },
        {
          "id": "vector:fingerprint authentication function",
          "keyphrase": "fingerprint authentication function",
          "type": "vector"
        }
      ],
      "732": [
        {
          "id": "rootcause:access control issue",
          "keyphrase": "access control issue",
          "type": "rootcause"
        },
        {
          "id": "rootcause:incorrect access control",
          "keyphrase": "incorrect access control",
          "type": "rootcause"
        },
        {
          "id": "impact:escalate privileges",
          "keyphrase": "escalate privileges",
          "type": "impact"
        },
        {
          "id": "version:17.5.0",
          "keyphrase": "17.5.0",
          "type": "version"
        }
      ],
      "362": [
        {
          "id": "rootcause:access control issue",
          "keyphrase": "access control issue",
          "type": "rootcause"
        },
        {
          "id": "impact:escalate privileges",
          "keyphrase": "escalate privileges",
          "type": "impact"
        },
        {
          "id": "vector:fingerprint authentication function",
          "keyphrase": "fingerprint authentication function",
          "type": "vector"
        },
        {
          "id": "product:Journal android app",
          "keyphrase": "Journal android app",
          "type": "product"
        },
        {
          "id": "version:17.5.0",
          "keyphrase": "17.5.0",
          "type": "version"
        }
      ],
      "863": [
        {
          "id": "rootcause:access control issue",
          "keyphrase": "access control issue",
          "type": "rootcause"
        },
        {
          "id": "rootcause:incorrect access control",
          "keyphrase": "incorrect access control",
          "type": "rootcause"
        },
        {
          "id": "vector:fingerprint authentication function",
          "keyphrase": "fingerprint authentication function",
          "type": "vector"
        },
        {
          "id": "version:17.5.0",
          "keyphrase": "17.5.0",
          "type": "version"
        }
      ],
      "287": [
        {
          "id": "rootcause:access control issue",
          "keyphrase": "access control issue",
          "type": "rootcause"
        },
        {
          "id": "rootcause:incorrect access control",
          "keyphrase": "incorrect access control",
          "type": "rootcause"
        },
        {
          "id": "vector:fingerprint authentication function",
          "keyphrase": "fingerprint authentication function",
          "type": "vector"
        }
      ],
      "639": [
        {
          "id": "rootcause:incorrect access control",
          "keyphrase": "incorrect access control",
          "type": "rootcause"
        },
        {
          "id": "product:Life Personal Diary",
          "keyphrase": "Life Personal Diary",
          "type": "product"
        }
      ],
      "250": [
        {
          "id": "impact:escalate privileges",
          "keyphrase": "escalate privileges",
          "type": "impact"
        },
        {
          "id": "version:17.5.0",
          "keyphrase": "17.5.0",
          "type": "version"
        }
      ],
      "269": [
        {
          "id": "impact:escalate privileges",
          "keyphrase": "escalate privileges",
          "type": "impact"
        }
      ],
      "266": [
        {
          "id": "impact:escalate privileges",
          "keyphrase": "escalate privileges",
          "type": "impact"
        }
      ],
      "1390": [
        {
          "id": "vector:fingerprint authentication function",
          "keyphrase": "fingerprint authentication function",
          "type": "vector"
        },
        {
          "id": "product:Life Personal Diary",
          "keyphrase": "Life Personal Diary",
          "type": "product"
        }
      ],
      "1263": [
        {
          "id": "attacker:physically proximate attacker",
          "keyphrase": "physically proximate attacker",
          "type": "attacker"
        }
      ],
      "311": [
        {
          "id": "attacker:physically proximate attacker",
          "keyphrase": "physically proximate attacker",
          "type": "attacker"
        }
      ],
      "1247": [
        {
          "id": "attacker:physically proximate attacker",
          "keyphrase": "physically proximate attacker",
          "type": "attacker"
        }
      ],
      "549": [
        {
          "id": "attacker:physically proximate attacker",
          "keyphrase": "physically proximate attacker",
          "type": "attacker"
        }
      ],
      "707": [
        {
          "id": "attacker:physically proximate attacker",
          "keyphrase": "physically proximate attacker",
          "type": "attacker"
        }
      ],
      "359": [
        {
          "id": "product:Life Personal Diary",
          "keyphrase": "Life Personal Diary",
          "type": "product"
        }
      ],
      "295": [
        {
          "id": "product:Life Personal Diary",
          "keyphrase": "Life Personal Diary",
          "type": "product"
        },
        {
          "id": "product:Journal android app",
          "keyphrase": "Journal android app",
          "type": "product"
        }
      ],
      "532": [
        {
          "id": "product:Life Personal Diary",
          "keyphrase": "Life Personal Diary",
          "type": "product"
        }
      ],
      "939": [
        {
          "id": "product:Journal android app",
          "keyphrase": "Journal android app",
          "type": "product"
        }
      ],
      "302": [
        {
          "id": "product:Journal android app",
          "keyphrase": "Journal android app",
          "type": "product"
        }
      ],
      "862": [
        {
          "id": "product:Journal android app",
          "keyphrase": "Journal android app",
          "type": "product"
        }
      ],
      "755": [
        {
          "id": "version:17.5.0",
          "keyphrase": "17.5.0",
          "type": "version"
        }
      ]
    },
    "relevant_cwes": [
      {
        "metadata": {
          "doc_id": "284",
          "name": "Improper Access Control",
          "source": "sparse",
          "original_content": "The product does not restrict or incorrectly restricts access to a resource from an unauthorized actor.",
          "keyphrase_sources": [
            {
              "id": "rootcause:access control issue",
              "keyphrase": "access control issue",
              "type": "rootcause"
            },
            {
              "id": "rootcause:incorrect access control",
              "keyphrase": "incorrect access control",
              "type": "rootcause"
            },
            {
              "id": "vector:fingerprint authentication function",
              "keyphrase": "fingerprint authentication function",
              "type": "vector"
            }
          ]
        },
        "similarity": 172.2173899387957
      },
      {
        "metadata": {
          "doc_id": "732",
          "name": "Incorrect Permission Assignment for Critical Resource",
          "source": "sparse",
          "original_content": "The product specifies permissions for a security-critical resource in a way that allows that resource to be read or modified by unintended actors.",
          "keyphrase_sources": [
            {
              "id": "rootcause:access control issue",
              "keyphrase": "access control issue",
              "type": "rootcause"
            },
            {
              "id": "rootcause:incorrect access control",
              "keyphrase": "incorrect access control",
              "type": "rootcause"
            },
            {
              "id": "impact:escalate privileges",
              "keyphrase": "escalate privileges",
              "type": "impact"
            },
            {
              "id": "version:17.5.0",
              "keyphrase": "17.5.0",
              "type": "version"
            }
          ]
        },
        "similarity": 167.73558126572647
      },
      {
        "metadata": {
          "doc_id": "639",
          "name": "Authorization Bypass Through User-Controlled Key",
          "source": "sparse",
          "original_content": "The system's authorization functionality does not prevent one user from gaining access to another user's data or record by modifying the key value identifying the data.",
          "keyphrase_sources": [
            {
              "id": "rootcause:incorrect access control",
              "keyphrase": "incorrect access control",
              "type": "rootcause"
            },
            {
              "id": "product:Life Personal Diary",
              "keyphrase": "Life Personal Diary",
              "type": "product"
            }
          ]
        },
        "similarity": 167.49379801034394
      },
      {
        "metadata": {
          "doc_id": "362",
          "name": "Concurrent Execution using Shared Resource with Improper Synchronization ('Race Condition')",
          "source": "sparse",
          "original_content": "The product contains a concurrent code sequence that requires temporary, exclusive access to a shared resource, but a timing window exists in which the shared resource can be modified by another code sequence operating concurrently.",
          "keyphrase_sources": [
            {
              "id": "rootcause:access control issue",
              "keyphrase": "access control issue",
              "type": "rootcause"
            },
            {
              "id": "impact:escalate privileges",
              "keyphrase": "escalate privileges",
              "type": "impact"
            },
            {
              "id": "vector:fingerprint authentication function",
              "keyphrase": "fingerprint authentication function",
              "type": "vector"
            },
            {
              "id": "product:Journal android app",
              "keyphrase": "Journal android app",
              "type": "product"
            },
            {
              "id": "version:17.5.0",
              "keyphrase": "17.5.0",
              "type": "version"
            }
          ]
        },
        "similarity": 166.2543708092814
      },
      {
        "metadata": {
          "doc_id": "863",
          "name": "Incorrect Authorization",
          "source": "sparse",
          "original_content": "The product performs an authorization check when an actor attempts to access a resource or perform an action, but it does not correctly perform the check.",
          "keyphrase_sources": [
            {
              "id": "rootcause:access control issue",
              "keyphrase": "access control issue",
              "type": "rootcause"
            },
            {
              "id": "rootcause:incorrect access control",
              "keyphrase": "incorrect access control",
              "type": "rootcause"
            },
            {
              "id": "vector:fingerprint authentication function",
              "keyphrase": "fingerprint authentication function",
              "type": "vector"
            },
            {
              "id": "version:17.5.0",
              "keyphrase": "17.5.0",
              "type": "version"
            }
          ]
        },
        "similarity": 165.679788286065
      },
      {
        "metadata": {
          "doc_id": "287",
          "name": "Improper Authentication",
          "source": "sparse",
          "original_content": "When an actor claims to have a given identity, the product does not prove or insufficiently proves that the claim is correct.",
          "keyphrase_sources": [
            {
              "id": "rootcause:access control issue",
              "keyphrase": "access control issue",
              "type": "rootcause"
            },
            {
              "id": "rootcause:incorrect access control",
              "keyphrase": "incorrect access control",
              "type": "rootcause"
            },
            {
              "id": "vector:fingerprint authentication function",
              "keyphrase": "fingerprint authentication function",
              "type": "vector"
            }
          ]
        },
        "similarity": 162.85660517150808
      },
      {
        "metadata": {
          "doc_id": "1263",
          "name": "Improper Physical Access Control",
          "source": "sparse",
          "original_content": "The product is designed with access restricted to certain information, but it does not sufficiently protect against an unauthorized actor with physical access to these areas.",
          "keyphrase_sources": [
            {
              "id": "attacker:physically proximate attacker",
              "keyphrase": "physically proximate attacker",
              "type": "attacker"
            }
          ]
        },
        "similarity": 69.94007413041977
      },
      {
        "metadata": {
          "doc_id": "311",
          "name": "Missing Encryption of Sensitive Data",
          "source": "sparse",
          "original_content": "The product does not encrypt sensitive or critical information before storage or transmission.",
          "keyphrase_sources": [
            {
              "id": "attacker:physically proximate attacker",
              "keyphrase": "physically proximate attacker",
              "type": "attacker"
            }
          ]
        },
        "similarity": 69.27621059661277
      },
      {
        "metadata": {
          "doc_id": "1247",
          "name": "Improper Protection Against Voltage and Clock Glitches",
          "source": "sparse",
          "original_content": "The device does not contain or contains incorrectly implemented circuitry or sensors to detect and mitigate voltage and clock glitches and protect sensitive information or software contained on the device.",
          "keyphrase_sources": [
            {
              "id": "attacker:physically proximate attacker",
              "keyphrase": "physically proximate attacker",
              "type": "attacker"
            }
          ]
        },
        "similarity": 68.68879918544867
      },
      {
        "metadata": {
          "doc_id": "549",
          "name": "Missing Password Field Masking",
          "source": "sparse",
          "original_content": "The product does not mask passwords during entry, increasing the potential for attackers to observe and capture passwords.",
          "keyphrase_sources": [
            {
              "id": "attacker:physically proximate attacker",
              "keyphrase": "physically proximate attacker",
              "type": "attacker"
            }
          ]
        },
        "similarity": 65.45978828624635
      },
      {
        "metadata": {
          "doc_id": "707",
          "name": "Improper Neutralization",
          "source": "sparse",
          "original_content": "The product does not ensure or incorrectly ensures that structured messages or data are well-formed and that certain security properties are met before being read from an upstream component or sent to a downstream component.",
          "keyphrase_sources": [
            {
              "id": "attacker:physically proximate attacker",
              "keyphrase": "physically proximate attacker",
              "type": "attacker"
            }
          ]
        },
        "similarity": 64.22319545640896
      },
      {
        "metadata": {
          "doc_id": "250",
          "name": "Execution with Unnecessary Privileges",
          "source": "sparse",
          "original_content": "The product performs an operation at a privilege level that is higher than the minimum level required, which creates new weaknesses or amplifies the consequences of other weaknesses.",
          "keyphrase_sources": [
            {
              "id": "impact:escalate privileges",
              "keyphrase": "escalate privileges",
              "type": "impact"
            },
            {
              "id": "version:17.5.0",
              "keyphrase": "17.5.0",
              "type": "version"
            }
          ]
        },
        "similarity": 59.53259947425671
      },
      {
        "metadata": {
          "doc_id": "939",
          "name": "Improper Authorization in Handler for Custom URL Scheme",
          "source": "sparse",
          "original_content": "The product uses a handler for a custom URL scheme, but it does not properly restrict which actors can invoke the handler using the scheme.",
          "keyphrase_sources": [
            {
              "id": "product:Journal android app",
              "keyphrase": "Journal android app",
              "type": "product"
            }
          ]
        },
        "similarity": 58.96396885053941
      },
      {
        "metadata": {
          "doc_id": "302",
          "name": "Authentication Bypass by Assumed-Immutable Data",
          "source": "sparse",
          "original_content": "The authentication scheme or implementation uses key data elements that are assumed to be immutable, but can be controlled or modified by the attacker.",
          "keyphrase_sources": [
            {
              "id": "product:Journal android app",
              "keyphrase": "Journal android app",
              "type": "product"
            }
          ]
        },
        "similarity": 56.34176790660478
      },
      {
        "metadata": {
          "doc_id": "862",
          "name": "Missing Authorization",
          "source": "sparse",
          "original_content": "The product does not perform an authorization check when an actor attempts to access a resource or perform an action.",
          "keyphrase_sources": [
            {
              "id": "product:Journal android app",
              "keyphrase": "Journal android app",
              "type": "product"
            }
          ]
        },
        "similarity": 55.99727892189006
      },
      {
        "metadata": {
          "doc_id": "755",
          "name": "Improper Handling of Exceptional Conditions",
          "source": "sparse",
          "original_content": "The product does not handle or incorrectly handles an exceptional condition.",
          "keyphrase_sources": [
            {
              "id": "version:17.5.0",
              "keyphrase": "17.5.0",
              "type": "version"
            }
          ]
        },
        "similarity": 55.28692842668624
      },
      {
        "metadata": {
          "doc_id": "269",
          "name": "Improper Privilege Management",
          "source": "sparse",
          "original_content": "The product does not properly assign, modify, track, or check privileges for an actor, creating an unintended sphere of control for that actor.",
          "keyphrase_sources": [
            {
              "id": "impact:escalate privileges",
              "keyphrase": "escalate privileges",
              "type": "impact"
            }
          ]
        },
        "similarity": 53.641442542531735
      },
      {
        "metadata": {
          "doc_id": "266",
          "name": "Incorrect Privilege Assignment",
          "source": "sparse",
          "original_content": "A product incorrectly assigns a privilege to a particular actor, creating an unintended sphere of control for that actor.",
          "keyphrase_sources": [
            {
              "id": "impact:escalate privileges",
              "keyphrase": "escalate privileges",
              "type": "impact"
            }
          ]
        },
        "similarity": 52.67195197064708
      },
      {
        "metadata": {
          "doc_id": "359",
          "name": "Exposure of Private Personal Information to an Unauthorized Actor",
          "source": "sparse",
          "original_content": "The product does not properly prevent a person's private, personal information from being accessed by actors who either (1) are not explicitly authorized to access the information or (2) do not have the implicit consent of the person about whom the information is collected.",
          "keyphrase_sources": [
            {
              "id": "product:Life Personal Diary",
              "keyphrase": "Life Personal Diary",
              "type": "product"
            }
          ]
        },
        "similarity": 52.665840417780586
      },
      {
        "metadata": {
          "doc_id": "295",
          "name": "Improper Certificate Validation",
          "source": "sparse",
          "original_content": "The product does not validate, or incorrectly validates, a certificate.",
          "keyphrase_sources": [
            {
              "id": "product:Life Personal Diary",
              "keyphrase": "Life Personal Diary",
              "type": "product"
            },
            {
              "id": "product:Journal android app",
              "keyphrase": "Journal android app",
              "type": "product"
            }
          ]
        },
        "similarity": 52.4705479981469
      },
      {
        "metadata": {
          "doc_id": "1390",
          "name": "Weak Authentication",
          "source": "sparse",
          "original_content": "The product uses an authentication mechanism to restrict access to specific users or identities, but the mechanism does not sufficiently prove that the claimed identity is correct.",
          "keyphrase_sources": [
            {
              "id": "vector:fingerprint authentication function",
              "keyphrase": "fingerprint authentication function",
              "type": "vector"
            },
            {
              "id": "product:Life Personal Diary",
              "keyphrase": "Life Personal Diary",
              "type": "product"
            }
          ]
        },
        "similarity": 51.48067754510954
      },
      {
        "metadata": {
          "doc_id": "532",
          "name": "Insertion of Sensitive Information into Log File",
          "source": "sparse",
          "original_content": "The product writes sensitive information to a log file.",
          "keyphrase_sources": [
            {
              "id": "product:Life Personal Diary",
              "keyphrase": "Life Personal Diary",
              "type": "product"
            }
          ]
        },
        "similarity": 47.34011517510793
      }
    ],
    "enhanced_query": "# Vulnerability Description\n\n    An incorrect **access control issue** in Life Personal Diary, Journal android app 17.5.0 allows a physically proximate attacker to escalate privileges via the fingerprint authentication function.\n\n    # Keyphrase-Specific CWE Analysis\n    This vulnerability contains multiple keyphrases that may map to different CWEs. \n    Please analyze each keyphrase separately and determine the most appropriate CWE(s) for each.\n\n    ## ROOTCAUSE: 'access control issue'\n\nRelevant CWEs for this ROOTCAUSE:\n\n### 1. CWE-284: Improper Access Control (Score: 172.22)\n\nThe product does not restrict or incorrectly restricts access to a resource from an unauthorized actor....\n\n### 2. CWE-732: Incorrect Permission Assignment for Critical Resource (Score: 167.74)\n\nThe product specifies permissions for a security-critical resource in a way that allows that resource to be read or modified by unintended actors....\n\n### 3. CWE-362: Concurrent Execution using Shared Resource with Improper Synchronization ('Race Condition') (Score: 166.25)\n\nThe product contains a concurrent code sequence that requires temporary, exclusive access to a shared resource, but a timing window exists in which the shared resource can be modified by another code sequence operating concurrently....\n\n### 4. CWE-863: Incorrect Authorization (Score: 165.68)\n\nThe product performs an authorization check when an actor attempts to access a resource or perform an action, but it does not correctly perform the check....\n\n### 5. CWE-287: Improper Authentication (Score: 162.86)\n\nWhen an actor claims to have a given identity, the product does not prove or insufficiently proves that the claim is correct....\n\n## ROOTCAUSE: 'incorrect access control'\n\nRelevant CWEs for this ROOTCAUSE:\n\n### 1. CWE-284: Improper Access Control (Score: 172.22)\n\nThe product does not restrict or incorrectly restricts access to a resource from an unauthorized actor....\n\n### 2. CWE-732: Incorrect Permission Assignment for Critical Resource (Score: 167.74)\n\nThe product specifies permissions for a security-critical resource in a way that allows that resource to be read or modified by unintended actors....\n\n### 3. CWE-639: Authorization Bypass Through User-Controlled Key (Score: 167.49)\n\nThe system's authorization functionality does not prevent one user from gaining access to another user's data or record by modifying the key value identifying the data....\n\n### 4. CWE-863: Incorrect Authorization (Score: 165.68)\n\nThe product performs an authorization check when an actor attempts to access a resource or perform an action, but it does not correctly perform the check....\n\n### 5. CWE-287: Improper Authentication (Score: 162.86)\n\nWhen an actor claims to have a given identity, the product does not prove or insufficiently proves that the claim is correct....\n\n## VECTOR: 'fingerprint authentication function'\n\nRelevant CWEs for this VECTOR:\n\n### 1. CWE-284: Improper Access Control (Score: 172.22)\n\nThe product does not restrict or incorrectly restricts access to a resource from an unauthorized actor....\n\n### 2. CWE-362: Concurrent Execution using Shared Resource with Improper Synchronization ('Race Condition') (Score: 166.25)\n\nThe product contains a concurrent code sequence that requires temporary, exclusive access to a shared resource, but a timing window exists in which the shared resource can be modified by another code sequence operating concurrently....\n\n### 3. CWE-863: Incorrect Authorization (Score: 165.68)\n\nThe product performs an authorization check when an actor attempts to access a resource or perform an action, but it does not correctly perform the check....\n\n### 4. CWE-287: Improper Authentication (Score: 162.86)\n\nWhen an actor claims to have a given identity, the product does not prove or insufficiently proves that the claim is correct....\n\n### 5. CWE-1390: Weak Authentication (Score: 51.48)\n\nThe product uses an authentication mechanism to restrict access to specific users or identities, but the mechanism does not sufficiently prove that the claimed identity is correct....\n\n## IMPACT: 'escalate privileges'\n\nRelevant CWEs for this IMPACT:\n\n### 1. CWE-732: Incorrect Permission Assignment for Critical Resource (Score: 167.74)\n\nThe product specifies permissions for a security-critical resource in a way that allows that resource to be read or modified by unintended actors....\n\n### 2. CWE-362: Concurrent Execution using Shared Resource with Improper Synchronization ('Race Condition') (Score: 166.25)\n\nThe product contains a concurrent code sequence that requires temporary, exclusive access to a shared resource, but a timing window exists in which the shared resource can be modified by another code sequence operating concurrently....\n\n### 3. CWE-250: Execution with Unnecessary Privileges (Score: 59.53)\n\nThe product performs an operation at a privilege level that is higher than the minimum level required, which creates new weaknesses or amplifies the consequences of other weaknesses....\n\n### 4. CWE-269: Improper Privilege Management (Score: 53.64)\n\nThe product does not properly assign, modify, track, or check privileges for an actor, creating an unintended sphere of control for that actor....\n\n### 5. CWE-266: Incorrect Privilege Assignment (Score: 52.67)\n\nA product incorrectly assigns a privilege to a particular actor, creating an unintended sphere of control for that actor....\n\n## VERSION: '17.5.0'\n\nRelevant CWEs for this VERSION:\n\n### 1. CWE-732: Incorrect Permission Assignment for Critical Resource (Score: 167.74)\n\nThe product specifies permissions for a security-critical resource in a way that allows that resource to be read or modified by unintended actors....\n\n### 2. CWE-362: Concurrent Execution using Shared Resource with Improper Synchronization ('Race Condition') (Score: 166.25)\n\nThe product contains a concurrent code sequence that requires temporary, exclusive access to a shared resource, but a timing window exists in which the shared resource can be modified by another code sequence operating concurrently....\n\n### 3. CWE-863: Incorrect Authorization (Score: 165.68)\n\nThe product performs an authorization check when an actor attempts to access a resource or perform an action, but it does not correctly perform the check....\n\n### 4. CWE-250: Execution with Unnecessary Privileges (Score: 59.53)\n\nThe product performs an operation at a privilege level that is higher than the minimum level required, which creates new weaknesses or amplifies the consequences of other weaknesses....\n\n### 5. CWE-755: Improper Handling of Exceptional Conditions (Score: 55.29)\n\nThe product does not handle or incorrectly handles an exceptional condition....\n\n## PRODUCT: 'Life Personal Diary'\n\nRelevant CWEs for this PRODUCT:\n\n### 1. CWE-639: Authorization Bypass Through User-Controlled Key (Score: 167.49)\n\nThe system's authorization functionality does not prevent one user from gaining access to another user's data or record by modifying the key value identifying the data....\n\n### 2. CWE-359: Exposure of Private Personal Information to an Unauthorized Actor (Score: 52.67)\n\nThe product does not properly prevent a person's private, personal information from being accessed by actors who either (1) are not explicitly authorized to access the information or (2) do not have the implicit consent of the person about whom the information is collected....\n\n### 3. CWE-295: Improper Certificate Validation (Score: 52.47)\n\nThe product does not validate, or incorrectly validates, a certificate....\n\n### 4. CWE-1390: Weak Authentication (Score: 51.48)\n\nThe product uses an authentication mechanism to restrict access to specific users or identities, but the mechanism does not sufficiently prove that the claimed identity is correct....\n\n### 5. CWE-532: Insertion of Sensitive Information into Log File (Score: 47.34)\n\nThe product writes sensitive information to a log file....\n\n## PRODUCT: 'Journal android app'\n\nRelevant CWEs for this PRODUCT:\n\n### 1. CWE-362: Concurrent Execution using Shared Resource with Improper Synchronization ('Race Condition') (Score: 166.25)\n\nThe product contains a concurrent code sequence that requires temporary, exclusive access to a shared resource, but a timing window exists in which the shared resource can be modified by another code sequence operating concurrently....\n\n### 2. CWE-939: Improper Authorization in Handler for Custom URL Scheme (Score: 58.96)\n\nThe product uses a handler for a custom URL scheme, but it does not properly restrict which actors can invoke the handler using the scheme....\n\n### 3. CWE-302: Authentication Bypass by Assumed-Immutable Data (Score: 56.34)\n\nThe authentication scheme or implementation uses key data elements that are assumed to be immutable, but can be controlled or modified by the attacker....\n\n### 4. CWE-862: Missing Authorization (Score: 56.00)\n\nThe product does not perform an authorization check when an actor attempts to access a resource or perform an action....\n\n### 5. CWE-295: Improper Certificate Validation (Score: 52.47)\n\nThe product does not validate, or incorrectly validates, a certificate....\n\n## ATTACKER: 'physically proximate attacker'\n\nRelevant CWEs for this ATTACKER:\n\n### 1. CWE-1263: Improper Physical Access Control (Score: 69.94)\n\nThe product is designed with access restricted to certain information, but it does not sufficiently protect against an unauthorized actor with physical access to these areas....\n\n### 2. CWE-311: Missing Encryption of Sensitive Data (Score: 69.28)\n\nThe product does not encrypt sensitive or critical information before storage or transmission....\n\n### 3. CWE-1247: Improper Protection Against Voltage and Clock Glitches (Score: 68.69)\n\nThe device does not contain or contains incorrectly implemented circuitry or sensors to detect and mitigate voltage and clock glitches and protect sensitive information or software contained on the device....\n\n### 4. CWE-549: Missing Password Field Masking (Score: 65.46)\n\nThe product does not mask passwords during entry, increasing the potential for attackers to observe and capture passwords....\n\n### 5. CWE-707: Improper Neutralization (Score: 64.22)\n\nThe product does not ensure or incorrectly ensures that structured messages or data are well-formed and that certain security properties are met before being read from an upstream component or sent to a downstream component....\n\n\n    # Analysis Instructions\n    1. For each keyphrase, identify the most appropriate CWE(s) that represent the weakness.\n    2. Consider how the different keyphrases might relate to each other in the vulnerability chain.\n    3. Provide a final determination of primary CWE(s) and any secondary CWEs.\n    4. Format your response using the standard analysis template.\n\n    Please analyze how these different weaknesses interact and provide a comprehensive CWE classification.\n    "
  },
  "retrieval_time": 1.1237452030181885
}