{
  "vulnerability_info": "VulnerabilityInfo(cve_id='CVE-2025-22477', description='Dell Storage Center - Dell Storage Manager, version(s) 20.1.20, contain(s) an **Improper Authentication vulnerability**. An unauthenticated attacker with adjacent network access could potentially exploit this vulnerability, leading to Elevation of privileges.', key_phrases={'rootcause': ['Improper Authentication vulnerability', 'authentication bypass'], 'weakness': 'authentication bypass', 'impact': ['Elevation of privileges', 'privilege escalation'], 'vector': '', 'attacker': 'unauthenticated attacker', 'product': 'Dell Storage Center - Dell Storage Manager', 'version': '20.1.20', 'component': ''}, reference_content=\"CVE-2025-22477 is related to the content. Here's the extracted information:\\n\\n* **Root cause of vulnerability:** Improper Authentication\\n* **Weaknesses/vulnerabilities present:** Improper Authentication\\n* **Impact of exploitation:** Elevation of privileges\\n* **Attack vectors:** Adjacent network access, unauthenticated attacker\\n* **Required attacker capabilities/position:** Unauthenticated attacker with adjacent network access\\n* **Mitigation or fix:**  The document does not provide a specific fix, but references affected products and remediated versions: Dell Storage Manager version(s) 20.1.20, remediated in versions prior to 2020 R1.21, version 2020 R1.21 or later.\\n* **CVSS:** 8.3, CVSS:3.1/AV:A/AC:L/PR:N/UI:N/S:U/C:H/I:H/A:L\\n\\nThe content provides more detail than the official CVE description, specifically detailing the CVSS score and vector string.\", similar_info={'cwe_distribution': {}, 'cwe_consensus': '', 'similarity_stats': {'thresholds': [], 'total_samples_by_threshold': {}, 'top_cwes_by_threshold': {}}}, similarity_summary=SimilarityInsight(consensus_cwe='', top_cwes=[], confidence_levels={}, total_samples=0), analysis='', analysis_with_relationships='', criticism='', resolution='', relevant_cwes=[{'metadata': {'doc_id': '256', 'name': 'Plaintext Storage of a Password', 'source': 'sparse', 'original_content': 'Storing a password in plaintext may result in a system compromise.', 'keyphrase_sources': [{'id': 'rootcause:Improper Authentication vulnerability', 'keyphrase': 'Improper Authentication vulnerability', 'type': 'rootcause'}, {'id': 'rootcause:authentication bypass', 'keyphrase': 'authentication bypass', 'type': 'rootcause'}, {'id': 'weakness:authentication bypass', 'keyphrase': 'authentication bypass', 'type': 'weakness'}, {'id': 'impact:Elevation of privileges', 'keyphrase': 'Elevation of privileges', 'type': 'impact'}, {'id': 'attacker:unauthenticated attacker', 'keyphrase': 'unauthenticated attacker', 'type': 'attacker'}, {'id': 'product:Dell Storage Center - Dell Storage Manager', 'keyphrase': 'Dell Storage Center - Dell Storage Manager', 'type': 'product'}, {'id': 'version:20.1.20', 'keyphrase': '20.1.20', 'type': 'version'}]}, 'similarity': np.float64(214.19765246858208)}, {'metadata': {'doc_id': '321', 'name': 'Use of Hard-coded Cryptographic Key', 'source': 'sparse', 'original_content': 'The use of a hard-coded cryptographic key significantly increases the possibility that encrypted data may be recovered.', 'keyphrase_sources': [{'id': 'rootcause:Improper Authentication vulnerability', 'keyphrase': 'Improper Authentication vulnerability', 'type': 'rootcause'}, {'id': 'rootcause:authentication bypass', 'keyphrase': 'authentication bypass', 'type': 'rootcause'}, {'id': 'weakness:authentication bypass', 'keyphrase': 'authentication bypass', 'type': 'weakness'}, {'id': 'impact:Elevation of privileges', 'keyphrase': 'Elevation of privileges', 'type': 'impact'}, {'id': 'attacker:unauthenticated attacker', 'keyphrase': 'unauthenticated attacker', 'type': 'attacker'}, {'id': 'product:Dell Storage Center - Dell Storage Manager', 'keyphrase': 'Dell Storage Center - Dell Storage Manager', 'type': 'product'}, {'id': 'version:20.1.20', 'keyphrase': '20.1.20', 'type': 'version'}]}, 'similarity': np.float64(213.69278013269277)}, {'metadata': {'doc_id': '287', 'name': 'Improper Authentication', 'source': 'sparse', 'original_content': 'When an actor claims to have a given identity, the product does not prove or insufficiently proves that the claim is correct.', 'keyphrase_sources': [{'id': 'rootcause:Improper Authentication vulnerability', 'keyphrase': 'Improper Authentication vulnerability', 'type': 'rootcause'}, {'id': 'rootcause:authentication bypass', 'keyphrase': 'authentication bypass', 'type': 'rootcause'}, {'id': 'weakness:authentication bypass', 'keyphrase': 'authentication bypass', 'type': 'weakness'}]}, 'similarity': np.float64(209.05452787100927)}, {'metadata': {'doc_id': '119', 'name': 'Improper Restriction of Operations within the Bounds of a Memory Buffer', 'source': 'sparse', 'original_content': \"The product performs operations on a memory buffer, but it reads from or writes to a memory location outside the buffer's intended boundary. This may result in read or write operations on unexpected memory locations that could be linked to other variables, data structures, or internal program data.\", 'keyphrase_sources': [{'id': 'rootcause:Improper Authentication vulnerability', 'keyphrase': 'Improper Authentication vulnerability', 'type': 'rootcause'}, {'id': 'impact:Elevation of privileges', 'keyphrase': 'Elevation of privileges', 'type': 'impact'}, {'id': 'impact:privilege escalation', 'keyphrase': 'privilege escalation', 'type': 'impact'}, {'id': 'attacker:unauthenticated attacker', 'keyphrase': 'unauthenticated attacker', 'type': 'attacker'}, {'id': 'product:Dell Storage Center - Dell Storage Manager', 'keyphrase': 'Dell Storage Center - Dell Storage Manager', 'type': 'product'}, {'id': 'version:20.1.20', 'keyphrase': '20.1.20', 'type': 'version'}]}, 'similarity': np.float64(204.85718233914574)}, {'metadata': {'doc_id': '284', 'name': 'Improper Access Control', 'source': 'sparse', 'original_content': 'The product does not restrict or incorrectly restricts access to a resource from an unauthorized actor.', 'keyphrase_sources': [{'id': 'rootcause:Improper Authentication vulnerability', 'keyphrase': 'Improper Authentication vulnerability', 'type': 'rootcause'}, {'id': 'rootcause:authentication bypass', 'keyphrase': 'authentication bypass', 'type': 'rootcause'}, {'id': 'weakness:authentication bypass', 'keyphrase': 'authentication bypass', 'type': 'weakness'}, {'id': 'impact:privilege escalation', 'keyphrase': 'privilege escalation', 'type': 'impact'}, {'id': 'attacker:unauthenticated attacker', 'keyphrase': 'unauthenticated attacker', 'type': 'attacker'}]}, 'similarity': np.float64(203.81258753635092)}, {'metadata': {'doc_id': '288', 'name': 'Authentication Bypass Using an Alternate Path or Channel', 'source': 'sparse', 'original_content': 'The product requires authentication, but the product has an alternate path or channel that does not require authentication.', 'keyphrase_sources': [{'id': 'rootcause:authentication bypass', 'keyphrase': 'authentication bypass', 'type': 'rootcause'}, {'id': 'weakness:authentication bypass', 'keyphrase': 'authentication bypass', 'type': 'weakness'}]}, 'similarity': np.float64(200.12100701092766)}, {'metadata': {'doc_id': '331', 'name': 'Insufficient Entropy', 'source': 'sparse', 'original_content': 'The product uses an algorithm or scheme that produces insufficient entropy, leaving patterns or clusters of values that are more likely to occur than others.', 'keyphrase_sources': [{'id': 'product:Dell Storage Center - Dell Storage Manager', 'keyphrase': 'Dell Storage Center - Dell Storage Manager', 'type': 'product'}]}, 'similarity': np.float64(82.84931047678359)}, {'metadata': {'doc_id': '59', 'name': \"Improper Link Resolution Before File Access ('Link Following')\", 'source': 'sparse', 'original_content': 'The product attempts to access a file based on the filename, but it does not properly prevent that filename from identifying a link or shortcut that resolves to an unintended resource.', 'keyphrase_sources': [{'id': 'impact:Elevation of privileges', 'keyphrase': 'Elevation of privileges', 'type': 'impact'}]}, 'similarity': np.float64(75.9710262677018)}, {'metadata': {'doc_id': '266', 'name': 'Incorrect Privilege Assignment', 'source': 'sparse', 'original_content': 'A product incorrectly assigns a privilege to a particular actor, creating an unintended sphere of control for that actor.', 'keyphrase_sources': [{'id': 'impact:Elevation of privileges', 'keyphrase': 'Elevation of privileges', 'type': 'impact'}]}, 'similarity': np.float64(74.22338503443324)}, {'metadata': {'doc_id': '532', 'name': 'Insertion of Sensitive Information into Log File', 'source': 'sparse', 'original_content': 'The product writes sensitive information to a log file.', 'keyphrase_sources': [{'id': 'attacker:unauthenticated attacker', 'keyphrase': 'unauthenticated attacker', 'type': 'attacker'}, {'id': 'product:Dell Storage Center - Dell Storage Manager', 'keyphrase': 'Dell Storage Center - Dell Storage Manager', 'type': 'product'}]}, 'similarity': np.float64(73.35811319920899)}, {'metadata': {'doc_id': '912', 'name': 'Hidden Functionality', 'source': 'sparse', 'original_content': \"The product contains functionality that is not documented, not part of the specification, and not accessible through an interface or command sequence that is obvious to the product's users or administrators.\", 'keyphrase_sources': [{'id': 'version:20.1.20', 'keyphrase': '20.1.20', 'type': 'version'}]}, 'similarity': np.float64(72.61473033942954)}, {'metadata': {'doc_id': '20', 'name': 'Improper Input Validation', 'source': 'sparse', 'original_content': 'The product receives input or data, but it does\\n        not validate or incorrectly validates that the input has the\\n        properties that are required to process the data safely and\\n        correctly.', 'keyphrase_sources': [{'id': 'impact:privilege escalation', 'keyphrase': 'privilege escalation', 'type': 'impact'}, {'id': 'version:20.1.20', 'keyphrase': '20.1.20', 'type': 'version'}]}, 'similarity': np.float64(70.39469781712732)}, {'metadata': {'doc_id': '269', 'name': 'Improper Privilege Management', 'source': 'sparse', 'original_content': 'The product does not properly assign, modify, track, or check privileges for an actor, creating an unintended sphere of control for that actor.', 'keyphrase_sources': [{'id': 'impact:privilege escalation', 'keyphrase': 'privilege escalation', 'type': 'impact'}]}, 'similarity': np.float64(69.72688897429535)}, {'metadata': {'doc_id': '732', 'name': 'Incorrect Permission Assignment for Critical Resource', 'source': 'sparse', 'original_content': 'The product specifies permissions for a security-critical resource in a way that allows that resource to be read or modified by unintended actors.', 'keyphrase_sources': [{'id': 'impact:privilege escalation', 'keyphrase': 'privilege escalation', 'type': 'impact'}]}, 'similarity': np.float64(69.10483162567914)}], identified_cwes={'analyzer': [], 'critic_additional': []})",
  "retrieval_results": {
    "has_multiple_keyphrases": true,
    "keyphrase_cwe_sets": {
      "rootcause:Improper Authentication vulnerability": {
        "keyphrase": "Improper Authentication vulnerability",
        "type": "rootcause",
        "cwes": [
          {
            "metadata": {
              "doc_id": "256",
              "name": "Plaintext Storage of a Password",
              "source": "sparse",
              "original_content": "Storing a password in plaintext may result in a system compromise.",
              "keyphrase_sources": [
                {
                  "id": "rootcause:Improper Authentication vulnerability",
                  "keyphrase": "Improper Authentication vulnerability",
                  "type": "rootcause"
                },
                {
                  "id": "rootcause:authentication bypass",
                  "keyphrase": "authentication bypass",
                  "type": "rootcause"
                },
                {
                  "id": "weakness:authentication bypass",
                  "keyphrase": "authentication bypass",
                  "type": "weakness"
                },
                {
                  "id": "impact:Elevation of privileges",
                  "keyphrase": "Elevation of privileges",
                  "type": "impact"
                },
                {
                  "id": "attacker:unauthenticated attacker",
                  "keyphrase": "unauthenticated attacker",
                  "type": "attacker"
                },
                {
                  "id": "product:Dell Storage Center - Dell Storage Manager",
                  "keyphrase": "Dell Storage Center - Dell Storage Manager",
                  "type": "product"
                },
                {
                  "id": "version:20.1.20",
                  "keyphrase": "20.1.20",
                  "type": "version"
                }
              ]
            },
            "similarity": 214.19765246858208
          },
          {
            "metadata": {
              "doc_id": "321",
              "name": "Use of Hard-coded Cryptographic Key",
              "source": "sparse",
              "original_content": "The use of a hard-coded cryptographic key significantly increases the possibility that encrypted data may be recovered.",
              "keyphrase_sources": [
                {
                  "id": "rootcause:Improper Authentication vulnerability",
                  "keyphrase": "Improper Authentication vulnerability",
                  "type": "rootcause"
                },
                {
                  "id": "rootcause:authentication bypass",
                  "keyphrase": "authentication bypass",
                  "type": "rootcause"
                },
                {
                  "id": "weakness:authentication bypass",
                  "keyphrase": "authentication bypass",
                  "type": "weakness"
                },
                {
                  "id": "impact:Elevation of privileges",
                  "keyphrase": "Elevation of privileges",
                  "type": "impact"
                },
                {
                  "id": "attacker:unauthenticated attacker",
                  "keyphrase": "unauthenticated attacker",
                  "type": "attacker"
                },
                {
                  "id": "product:Dell Storage Center - Dell Storage Manager",
                  "keyphrase": "Dell Storage Center - Dell Storage Manager",
                  "type": "product"
                },
                {
                  "id": "version:20.1.20",
                  "keyphrase": "20.1.20",
                  "type": "version"
                }
              ]
            },
            "similarity": 213.69278013269277
          },
          {
            "metadata": {
              "doc_id": "287",
              "name": "Improper Authentication",
              "source": "sparse",
              "original_content": "When an actor claims to have a given identity, the product does not prove or insufficiently proves that the claim is correct.",
              "keyphrase_sources": [
                {
                  "id": "rootcause:Improper Authentication vulnerability",
                  "keyphrase": "Improper Authentication vulnerability",
                  "type": "rootcause"
                },
                {
                  "id": "rootcause:authentication bypass",
                  "keyphrase": "authentication bypass",
                  "type": "rootcause"
                },
                {
                  "id": "weakness:authentication bypass",
                  "keyphrase": "authentication bypass",
                  "type": "weakness"
                }
              ]
            },
            "similarity": 209.05452787100927
          },
          {
            "metadata": {
              "doc_id": "119",
              "name": "Improper Restriction of Operations within the Bounds of a Memory Buffer",
              "source": "sparse",
              "original_content": "The product performs operations on a memory buffer, but it reads from or writes to a memory location outside the buffer's intended boundary. This may result in read or write operations on unexpected memory locations that could be linked to other variables, data structures, or internal program data.",
              "keyphrase_sources": [
                {
                  "id": "rootcause:Improper Authentication vulnerability",
                  "keyphrase": "Improper Authentication vulnerability",
                  "type": "rootcause"
                },
                {
                  "id": "impact:Elevation of privileges",
                  "keyphrase": "Elevation of privileges",
                  "type": "impact"
                },
                {
                  "id": "impact:privilege escalation",
                  "keyphrase": "privilege escalation",
                  "type": "impact"
                },
                {
                  "id": "attacker:unauthenticated attacker",
                  "keyphrase": "unauthenticated attacker",
                  "type": "attacker"
                },
                {
                  "id": "product:Dell Storage Center - Dell Storage Manager",
                  "keyphrase": "Dell Storage Center - Dell Storage Manager",
                  "type": "product"
                },
                {
                  "id": "version:20.1.20",
                  "keyphrase": "20.1.20",
                  "type": "version"
                }
              ]
            },
            "similarity": 204.85718233914574
          },
          {
            "metadata": {
              "doc_id": "284",
              "name": "Improper Access Control",
              "source": "sparse",
              "original_content": "The product does not restrict or incorrectly restricts access to a resource from an unauthorized actor.",
              "keyphrase_sources": [
                {
                  "id": "rootcause:Improper Authentication vulnerability",
                  "keyphrase": "Improper Authentication vulnerability",
                  "type": "rootcause"
                },
                {
                  "id": "rootcause:authentication bypass",
                  "keyphrase": "authentication bypass",
                  "type": "rootcause"
                },
                {
                  "id": "weakness:authentication bypass",
                  "keyphrase": "authentication bypass",
                  "type": "weakness"
                },
                {
                  "id": "impact:privilege escalation",
                  "keyphrase": "privilege escalation",
                  "type": "impact"
                },
                {
                  "id": "attacker:unauthenticated attacker",
                  "keyphrase": "unauthenticated attacker",
                  "type": "attacker"
                }
              ]
            },
            "similarity": 203.81258753635092
          }
        ]
      },
      "rootcause:authentication bypass": {
        "keyphrase": "authentication bypass",
        "type": "rootcause",
        "cwes": [
          {
            "metadata": {
              "doc_id": "321",
              "name": "Use of Hard-coded Cryptographic Key",
              "source": "sparse",
              "original_content": "The use of a hard-coded cryptographic key significantly increases the possibility that encrypted data may be recovered."
            },
            "similarity": 211.00292918385173
          },
          {
            "metadata": {
              "doc_id": "256",
              "name": "Plaintext Storage of a Password",
              "source": "sparse",
              "original_content": "Storing a password in plaintext may result in a system compromise."
            },
            "similarity": 210.89905058488583
          },
          {
            "metadata": {
              "doc_id": "287",
              "name": "Improper Authentication",
              "source": "sparse",
              "original_content": "When an actor claims to have a given identity, the product does not prove or insufficiently proves that the claim is correct."
            },
            "similarity": 208.42244917416951
          },
          {
            "metadata": {
              "doc_id": "284",
              "name": "Improper Access Control",
              "source": "sparse",
              "original_content": "The product does not restrict or incorrectly restricts access to a resource from an unauthorized actor."
            },
            "similarity": 200.63880248653408
          },
          {
            "metadata": {
              "doc_id": "288",
              "name": "Authentication Bypass Using an Alternate Path or Channel",
              "source": "sparse",
              "original_content": "The product requires authentication, but the product has an alternate path or channel that does not require authentication.",
              "keyphrase_sources": [
                {
                  "id": "rootcause:authentication bypass",
                  "keyphrase": "authentication bypass",
                  "type": "rootcause"
                },
                {
                  "id": "weakness:authentication bypass",
                  "keyphrase": "authentication bypass",
                  "type": "weakness"
                }
              ]
            },
            "similarity": 200.12100701092766
          }
        ]
      },
      "weakness:authentication bypass": {
        "keyphrase": "authentication bypass",
        "type": "weakness",
        "cwes": [
          {
            "metadata": {
              "doc_id": "321",
              "name": "Use of Hard-coded Cryptographic Key",
              "source": "sparse",
              "original_content": "The use of a hard-coded cryptographic key significantly increases the possibility that encrypted data may be recovered."
            },
            "similarity": 196.93606723826161
          },
          {
            "metadata": {
              "doc_id": "256",
              "name": "Plaintext Storage of a Password",
              "source": "sparse",
              "original_content": "Storing a password in plaintext may result in a system compromise."
            },
            "similarity": 196.83911387922677
          },
          {
            "metadata": {
              "doc_id": "287",
              "name": "Improper Authentication",
              "source": "sparse",
              "original_content": "When an actor claims to have a given identity, the product does not prove or insufficiently proves that the claim is correct."
            },
            "similarity": 194.52761922922488
          },
          {
            "metadata": {
              "doc_id": "284",
              "name": "Improper Access Control",
              "source": "sparse",
              "original_content": "The product does not restrict or incorrectly restricts access to a resource from an unauthorized actor."
            },
            "similarity": 187.2628823207651
          },
          {
            "metadata": {
              "doc_id": "288",
              "name": "Authentication Bypass Using an Alternate Path or Channel",
              "source": "sparse",
              "original_content": "The product requires authentication, but the product has an alternate path or channel that does not require authentication."
            },
            "similarity": 186.77960654353248
          }
        ]
      },
      "impact:Elevation of privileges": {
        "keyphrase": "Elevation of privileges",
        "type": "impact",
        "cwes": [
          {
            "metadata": {
              "doc_id": "119",
              "name": "Improper Restriction of Operations within the Bounds of a Memory Buffer",
              "source": "sparse",
              "original_content": "The product performs operations on a memory buffer, but it reads from or writes to a memory location outside the buffer's intended boundary. This may result in read or write operations on unexpected memory locations that could be linked to other variables, data structures, or internal program data."
            },
            "similarity": 78.66848568691107
          },
          {
            "metadata": {
              "doc_id": "256",
              "name": "Plaintext Storage of a Password",
              "source": "sparse",
              "original_content": "Storing a password in plaintext may result in a system compromise."
            },
            "similarity": 78.51201693555464
          },
          {
            "metadata": {
              "doc_id": "59",
              "name": "Improper Link Resolution Before File Access ('Link Following')",
              "source": "sparse",
              "original_content": "The product attempts to access a file based on the filename, but it does not properly prevent that filename from identifying a link or shortcut that resolves to an unintended resource.",
              "keyphrase_sources": [
                {
                  "id": "impact:Elevation of privileges",
                  "keyphrase": "Elevation of privileges",
                  "type": "impact"
                }
              ]
            },
            "similarity": 75.9710262677018
          },
          {
            "metadata": {
              "doc_id": "321",
              "name": "Use of Hard-coded Cryptographic Key",
              "source": "sparse",
              "original_content": "The use of a hard-coded cryptographic key significantly increases the possibility that encrypted data may be recovered."
            },
            "similarity": 75.56272638061365
          },
          {
            "metadata": {
              "doc_id": "266",
              "name": "Incorrect Privilege Assignment",
              "source": "sparse",
              "original_content": "A product incorrectly assigns a privilege to a particular actor, creating an unintended sphere of control for that actor.",
              "keyphrase_sources": [
                {
                  "id": "impact:Elevation of privileges",
                  "keyphrase": "Elevation of privileges",
                  "type": "impact"
                }
              ]
            },
            "similarity": 74.22338503443324
          }
        ]
      },
      "impact:privilege escalation": {
        "keyphrase": "privilege escalation",
        "type": "impact",
        "cwes": [
          {
            "metadata": {
              "doc_id": "119",
              "name": "Improper Restriction of Operations within the Bounds of a Memory Buffer",
              "source": "sparse",
              "original_content": "The product performs operations on a memory buffer, but it reads from or writes to a memory location outside the buffer's intended boundary. This may result in read or write operations on unexpected memory locations that could be linked to other variables, data structures, or internal program data."
            },
            "similarity": 73.02217289266937
          },
          {
            "metadata": {
              "doc_id": "284",
              "name": "Improper Access Control",
              "source": "sparse",
              "original_content": "The product does not restrict or incorrectly restricts access to a resource from an unauthorized actor."
            },
            "similarity": 71.57420092481102
          },
          {
            "metadata": {
              "doc_id": "20",
              "name": "Improper Input Validation",
              "source": "sparse",
              "original_content": "The product receives input or data, but it does\n        not validate or incorrectly validates that the input has the\n        properties that are required to process the data safely and\n        correctly.",
              "keyphrase_sources": [
                {
                  "id": "impact:privilege escalation",
                  "keyphrase": "privilege escalation",
                  "type": "impact"
                },
                {
                  "id": "version:20.1.20",
                  "keyphrase": "20.1.20",
                  "type": "version"
                }
              ]
            },
            "similarity": 70.39469781712732
          },
          {
            "metadata": {
              "doc_id": "269",
              "name": "Improper Privilege Management",
              "source": "sparse",
              "original_content": "The product does not properly assign, modify, track, or check privileges for an actor, creating an unintended sphere of control for that actor.",
              "keyphrase_sources": [
                {
                  "id": "impact:privilege escalation",
                  "keyphrase": "privilege escalation",
                  "type": "impact"
                }
              ]
            },
            "similarity": 69.72688897429535
          },
          {
            "metadata": {
              "doc_id": "732",
              "name": "Incorrect Permission Assignment for Critical Resource",
              "source": "sparse",
              "original_content": "The product specifies permissions for a security-critical resource in a way that allows that resource to be read or modified by unintended actors.",
              "keyphrase_sources": [
                {
                  "id": "impact:privilege escalation",
                  "keyphrase": "privilege escalation",
                  "type": "impact"
                }
              ]
            },
            "similarity": 69.10483162567914
          }
        ]
      },
      "attacker:unauthenticated attacker": {
        "keyphrase": "unauthenticated attacker",
        "type": "attacker",
        "cwes": [
          {
            "metadata": {
              "doc_id": "321",
              "name": "Use of Hard-coded Cryptographic Key",
              "source": "sparse",
              "original_content": "The use of a hard-coded cryptographic key significantly increases the possibility that encrypted data may be recovered."
            },
            "similarity": 76.83855151332456
          },
          {
            "metadata": {
              "doc_id": "256",
              "name": "Plaintext Storage of a Password",
              "source": "sparse",
              "original_content": "Storing a password in plaintext may result in a system compromise."
            },
            "similarity": 75.34067775461534
          },
          {
            "metadata": {
              "doc_id": "532",
              "name": "Insertion of Sensitive Information into Log File",
              "source": "sparse",
              "original_content": "The product writes sensitive information to a log file.",
              "keyphrase_sources": [
                {
                  "id": "attacker:unauthenticated attacker",
                  "keyphrase": "unauthenticated attacker",
                  "type": "attacker"
                },
                {
                  "id": "product:Dell Storage Center - Dell Storage Manager",
                  "keyphrase": "Dell Storage Center - Dell Storage Manager",
                  "type": "product"
                }
              ]
            },
            "similarity": 73.35811319920899
          },
          {
            "metadata": {
              "doc_id": "119",
              "name": "Improper Restriction of Operations within the Bounds of a Memory Buffer",
              "source": "sparse",
              "original_content": "The product performs operations on a memory buffer, but it reads from or writes to a memory location outside the buffer's intended boundary. This may result in read or write operations on unexpected memory locations that could be linked to other variables, data structures, or internal program data."
            },
            "similarity": 72.81909153995207
          },
          {
            "metadata": {
              "doc_id": "284",
              "name": "Improper Access Control",
              "source": "sparse",
              "original_content": "The product does not restrict or incorrectly restricts access to a resource from an unauthorized actor."
            },
            "similarity": 72.29961758077103
          }
        ]
      },
      "product:Dell Storage Center - Dell Storage Manager": {
        "keyphrase": "Dell Storage Center - Dell Storage Manager",
        "type": "product",
        "cwes": [
          {
            "metadata": {
              "doc_id": "256",
              "name": "Plaintext Storage of a Password",
              "source": "sparse",
              "original_content": "Storing a password in plaintext may result in a system compromise."
            },
            "similarity": 112.76075796252547
          },
          {
            "metadata": {
              "doc_id": "532",
              "name": "Insertion of Sensitive Information into Log File",
              "source": "sparse",
              "original_content": "The product writes sensitive information to a log file."
            },
            "similarity": 99.85220043702626
          },
          {
            "metadata": {
              "doc_id": "321",
              "name": "Use of Hard-coded Cryptographic Key",
              "source": "sparse",
              "original_content": "The use of a hard-coded cryptographic key significantly increases the possibility that encrypted data may be recovered."
            },
            "similarity": 88.20723379426907
          },
          {
            "metadata": {
              "doc_id": "119",
              "name": "Improper Restriction of Operations within the Bounds of a Memory Buffer",
              "source": "sparse",
              "original_content": "The product performs operations on a memory buffer, but it reads from or writes to a memory location outside the buffer's intended boundary. This may result in read or write operations on unexpected memory locations that could be linked to other variables, data structures, or internal program data."
            },
            "similarity": 84.2879350357228
          },
          {
            "metadata": {
              "doc_id": "331",
              "name": "Insufficient Entropy",
              "source": "sparse",
              "original_content": "The product uses an algorithm or scheme that produces insufficient entropy, leaving patterns or clusters of values that are more likely to occur than others.",
              "keyphrase_sources": [
                {
                  "id": "product:Dell Storage Center - Dell Storage Manager",
                  "keyphrase": "Dell Storage Center - Dell Storage Manager",
                  "type": "product"
                }
              ]
            },
            "similarity": 82.84931047678359
          }
        ]
      },
      "version:20.1.20": {
        "keyphrase": "20.1.20",
        "type": "version",
        "cwes": [
          {
            "metadata": {
              "doc_id": "321",
              "name": "Use of Hard-coded Cryptographic Key",
              "source": "sparse",
              "original_content": "The use of a hard-coded cryptographic key significantly increases the possibility that encrypted data may be recovered."
            },
            "similarity": 75.77930444564406
          },
          {
            "metadata": {
              "doc_id": "912",
              "name": "Hidden Functionality",
              "source": "sparse",
              "original_content": "The product contains functionality that is not documented, not part of the specification, and not accessible through an interface or command sequence that is obvious to the product's users or administrators.",
              "keyphrase_sources": [
                {
                  "id": "version:20.1.20",
                  "keyphrase": "20.1.20",
                  "type": "version"
                }
              ]
            },
            "similarity": 72.61473033942954
          },
          {
            "metadata": {
              "doc_id": "256",
              "name": "Plaintext Storage of a Password",
              "source": "sparse",
              "original_content": "Storing a password in plaintext may result in a system compromise."
            },
            "similarity": 72.56258228336219
          },
          {
            "metadata": {
              "doc_id": "119",
              "name": "Improper Restriction of Operations within the Bounds of a Memory Buffer",
              "source": "sparse",
              "original_content": "The product performs operations on a memory buffer, but it reads from or writes to a memory location outside the buffer's intended boundary. This may result in read or write operations on unexpected memory locations that could be linked to other variables, data structures, or internal program data."
            },
            "similarity": 72.36653507220736
          },
          {
            "metadata": {
              "doc_id": "20",
              "name": "Improper Input Validation",
              "source": "sparse",
              "original_content": "The product receives input or data, but it does\n        not validate or incorrectly validates that the input has the\n        properties that are required to process the data safely and\n        correctly."
            },
            "similarity": 72.01109206756412
          }
        ]
      }
    },
    "keyphrase_mapping": {
      "256": [
        {
          "id": "rootcause:Improper Authentication vulnerability",
          "keyphrase": "Improper Authentication vulnerability",
          "type": "rootcause"
        },
        {
          "id": "rootcause:authentication bypass",
          "keyphrase": "authentication bypass",
          "type": "rootcause"
        },
        {
          "id": "weakness:authentication bypass",
          "keyphrase": "authentication bypass",
          "type": "weakness"
        },
        {
          "id": "impact:Elevation of privileges",
          "keyphrase": "Elevation of privileges",
          "type": "impact"
        },
        {
          "id": "attacker:unauthenticated attacker",
          "keyphrase": "unauthenticated attacker",
          "type": "attacker"
        },
        {
          "id": "product:Dell Storage Center - Dell Storage Manager",
          "keyphrase": "Dell Storage Center - Dell Storage Manager",
          "type": "product"
        },
        {
          "id": "version:20.1.20",
          "keyphrase": "20.1.20",
          "type": "version"
        }
      ],
      "321": [
        {
          "id": "rootcause:Improper Authentication vulnerability",
          "keyphrase": "Improper Authentication vulnerability",
          "type": "rootcause"
        },
        {
          "id": "rootcause:authentication bypass",
          "keyphrase": "authentication bypass",
          "type": "rootcause"
        },
        {
          "id": "weakness:authentication bypass",
          "keyphrase": "authentication bypass",
          "type": "weakness"
        },
        {
          "id": "impact:Elevation of privileges",
          "keyphrase": "Elevation of privileges",
          "type": "impact"
        },
        {
          "id": "attacker:unauthenticated attacker",
          "keyphrase": "unauthenticated attacker",
          "type": "attacker"
        },
        {
          "id": "product:Dell Storage Center - Dell Storage Manager",
          "keyphrase": "Dell Storage Center - Dell Storage Manager",
          "type": "product"
        },
        {
          "id": "version:20.1.20",
          "keyphrase": "20.1.20",
          "type": "version"
        }
      ],
      "287": [
        {
          "id": "rootcause:Improper Authentication vulnerability",
          "keyphrase": "Improper Authentication vulnerability",
          "type": "rootcause"
        },
        {
          "id": "rootcause:authentication bypass",
          "keyphrase": "authentication bypass",
          "type": "rootcause"
        },
        {
          "id": "weakness:authentication bypass",
          "keyphrase": "authentication bypass",
          "type": "weakness"
        }
      ],
      "119": [
        {
          "id": "rootcause:Improper Authentication vulnerability",
          "keyphrase": "Improper Authentication vulnerability",
          "type": "rootcause"
        },
        {
          "id": "impact:Elevation of privileges",
          "keyphrase": "Elevation of privileges",
          "type": "impact"
        },
        {
          "id": "impact:privilege escalation",
          "keyphrase": "privilege escalation",
          "type": "impact"
        },
        {
          "id": "attacker:unauthenticated attacker",
          "keyphrase": "unauthenticated attacker",
          "type": "attacker"
        },
        {
          "id": "product:Dell Storage Center - Dell Storage Manager",
          "keyphrase": "Dell Storage Center - Dell Storage Manager",
          "type": "product"
        },
        {
          "id": "version:20.1.20",
          "keyphrase": "20.1.20",
          "type": "version"
        }
      ],
      "284": [
        {
          "id": "rootcause:Improper Authentication vulnerability",
          "keyphrase": "Improper Authentication vulnerability",
          "type": "rootcause"
        },
        {
          "id": "rootcause:authentication bypass",
          "keyphrase": "authentication bypass",
          "type": "rootcause"
        },
        {
          "id": "weakness:authentication bypass",
          "keyphrase": "authentication bypass",
          "type": "weakness"
        },
        {
          "id": "impact:privilege escalation",
          "keyphrase": "privilege escalation",
          "type": "impact"
        },
        {
          "id": "attacker:unauthenticated attacker",
          "keyphrase": "unauthenticated attacker",
          "type": "attacker"
        }
      ],
      "288": [
        {
          "id": "rootcause:authentication bypass",
          "keyphrase": "authentication bypass",
          "type": "rootcause"
        },
        {
          "id": "weakness:authentication bypass",
          "keyphrase": "authentication bypass",
          "type": "weakness"
        }
      ],
      "59": [
        {
          "id": "impact:Elevation of privileges",
          "keyphrase": "Elevation of privileges",
          "type": "impact"
        }
      ],
      "266": [
        {
          "id": "impact:Elevation of privileges",
          "keyphrase": "Elevation of privileges",
          "type": "impact"
        }
      ],
      "20": [
        {
          "id": "impact:privilege escalation",
          "keyphrase": "privilege escalation",
          "type": "impact"
        },
        {
          "id": "version:20.1.20",
          "keyphrase": "20.1.20",
          "type": "version"
        }
      ],
      "269": [
        {
          "id": "impact:privilege escalation",
          "keyphrase": "privilege escalation",
          "type": "impact"
        }
      ],
      "732": [
        {
          "id": "impact:privilege escalation",
          "keyphrase": "privilege escalation",
          "type": "impact"
        }
      ],
      "532": [
        {
          "id": "attacker:unauthenticated attacker",
          "keyphrase": "unauthenticated attacker",
          "type": "attacker"
        },
        {
          "id": "product:Dell Storage Center - Dell Storage Manager",
          "keyphrase": "Dell Storage Center - Dell Storage Manager",
          "type": "product"
        }
      ],
      "331": [
        {
          "id": "product:Dell Storage Center - Dell Storage Manager",
          "keyphrase": "Dell Storage Center - Dell Storage Manager",
          "type": "product"
        }
      ],
      "912": [
        {
          "id": "version:20.1.20",
          "keyphrase": "20.1.20",
          "type": "version"
        }
      ]
    },
    "relevant_cwes": [
      {
        "metadata": {
          "doc_id": "256",
          "name": "Plaintext Storage of a Password",
          "source": "sparse",
          "original_content": "Storing a password in plaintext may result in a system compromise.",
          "keyphrase_sources": [
            {
              "id": "rootcause:Improper Authentication vulnerability",
              "keyphrase": "Improper Authentication vulnerability",
              "type": "rootcause"
            },
            {
              "id": "rootcause:authentication bypass",
              "keyphrase": "authentication bypass",
              "type": "rootcause"
            },
            {
              "id": "weakness:authentication bypass",
              "keyphrase": "authentication bypass",
              "type": "weakness"
            },
            {
              "id": "impact:Elevation of privileges",
              "keyphrase": "Elevation of privileges",
              "type": "impact"
            },
            {
              "id": "attacker:unauthenticated attacker",
              "keyphrase": "unauthenticated attacker",
              "type": "attacker"
            },
            {
              "id": "product:Dell Storage Center - Dell Storage Manager",
              "keyphrase": "Dell Storage Center - Dell Storage Manager",
              "type": "product"
            },
            {
              "id": "version:20.1.20",
              "keyphrase": "20.1.20",
              "type": "version"
            }
          ]
        },
        "similarity": 214.19765246858208
      },
      {
        "metadata": {
          "doc_id": "321",
          "name": "Use of Hard-coded Cryptographic Key",
          "source": "sparse",
          "original_content": "The use of a hard-coded cryptographic key significantly increases the possibility that encrypted data may be recovered.",
          "keyphrase_sources": [
            {
              "id": "rootcause:Improper Authentication vulnerability",
              "keyphrase": "Improper Authentication vulnerability",
              "type": "rootcause"
            },
            {
              "id": "rootcause:authentication bypass",
              "keyphrase": "authentication bypass",
              "type": "rootcause"
            },
            {
              "id": "weakness:authentication bypass",
              "keyphrase": "authentication bypass",
              "type": "weakness"
            },
            {
              "id": "impact:Elevation of privileges",
              "keyphrase": "Elevation of privileges",
              "type": "impact"
            },
            {
              "id": "attacker:unauthenticated attacker",
              "keyphrase": "unauthenticated attacker",
              "type": "attacker"
            },
            {
              "id": "product:Dell Storage Center - Dell Storage Manager",
              "keyphrase": "Dell Storage Center - Dell Storage Manager",
              "type": "product"
            },
            {
              "id": "version:20.1.20",
              "keyphrase": "20.1.20",
              "type": "version"
            }
          ]
        },
        "similarity": 213.69278013269277
      },
      {
        "metadata": {
          "doc_id": "287",
          "name": "Improper Authentication",
          "source": "sparse",
          "original_content": "When an actor claims to have a given identity, the product does not prove or insufficiently proves that the claim is correct.",
          "keyphrase_sources": [
            {
              "id": "rootcause:Improper Authentication vulnerability",
              "keyphrase": "Improper Authentication vulnerability",
              "type": "rootcause"
            },
            {
              "id": "rootcause:authentication bypass",
              "keyphrase": "authentication bypass",
              "type": "rootcause"
            },
            {
              "id": "weakness:authentication bypass",
              "keyphrase": "authentication bypass",
              "type": "weakness"
            }
          ]
        },
        "similarity": 209.05452787100927
      },
      {
        "metadata": {
          "doc_id": "119",
          "name": "Improper Restriction of Operations within the Bounds of a Memory Buffer",
          "source": "sparse",
          "original_content": "The product performs operations on a memory buffer, but it reads from or writes to a memory location outside the buffer's intended boundary. This may result in read or write operations on unexpected memory locations that could be linked to other variables, data structures, or internal program data.",
          "keyphrase_sources": [
            {
              "id": "rootcause:Improper Authentication vulnerability",
              "keyphrase": "Improper Authentication vulnerability",
              "type": "rootcause"
            },
            {
              "id": "impact:Elevation of privileges",
              "keyphrase": "Elevation of privileges",
              "type": "impact"
            },
            {
              "id": "impact:privilege escalation",
              "keyphrase": "privilege escalation",
              "type": "impact"
            },
            {
              "id": "attacker:unauthenticated attacker",
              "keyphrase": "unauthenticated attacker",
              "type": "attacker"
            },
            {
              "id": "product:Dell Storage Center - Dell Storage Manager",
              "keyphrase": "Dell Storage Center - Dell Storage Manager",
              "type": "product"
            },
            {
              "id": "version:20.1.20",
              "keyphrase": "20.1.20",
              "type": "version"
            }
          ]
        },
        "similarity": 204.85718233914574
      },
      {
        "metadata": {
          "doc_id": "284",
          "name": "Improper Access Control",
          "source": "sparse",
          "original_content": "The product does not restrict or incorrectly restricts access to a resource from an unauthorized actor.",
          "keyphrase_sources": [
            {
              "id": "rootcause:Improper Authentication vulnerability",
              "keyphrase": "Improper Authentication vulnerability",
              "type": "rootcause"
            },
            {
              "id": "rootcause:authentication bypass",
              "keyphrase": "authentication bypass",
              "type": "rootcause"
            },
            {
              "id": "weakness:authentication bypass",
              "keyphrase": "authentication bypass",
              "type": "weakness"
            },
            {
              "id": "impact:privilege escalation",
              "keyphrase": "privilege escalation",
              "type": "impact"
            },
            {
              "id": "attacker:unauthenticated attacker",
              "keyphrase": "unauthenticated attacker",
              "type": "attacker"
            }
          ]
        },
        "similarity": 203.81258753635092
      },
      {
        "metadata": {
          "doc_id": "288",
          "name": "Authentication Bypass Using an Alternate Path or Channel",
          "source": "sparse",
          "original_content": "The product requires authentication, but the product has an alternate path or channel that does not require authentication.",
          "keyphrase_sources": [
            {
              "id": "rootcause:authentication bypass",
              "keyphrase": "authentication bypass",
              "type": "rootcause"
            },
            {
              "id": "weakness:authentication bypass",
              "keyphrase": "authentication bypass",
              "type": "weakness"
            }
          ]
        },
        "similarity": 200.12100701092766
      },
      {
        "metadata": {
          "doc_id": "331",
          "name": "Insufficient Entropy",
          "source": "sparse",
          "original_content": "The product uses an algorithm or scheme that produces insufficient entropy, leaving patterns or clusters of values that are more likely to occur than others.",
          "keyphrase_sources": [
            {
              "id": "product:Dell Storage Center - Dell Storage Manager",
              "keyphrase": "Dell Storage Center - Dell Storage Manager",
              "type": "product"
            }
          ]
        },
        "similarity": 82.84931047678359
      },
      {
        "metadata": {
          "doc_id": "59",
          "name": "Improper Link Resolution Before File Access ('Link Following')",
          "source": "sparse",
          "original_content": "The product attempts to access a file based on the filename, but it does not properly prevent that filename from identifying a link or shortcut that resolves to an unintended resource.",
          "keyphrase_sources": [
            {
              "id": "impact:Elevation of privileges",
              "keyphrase": "Elevation of privileges",
              "type": "impact"
            }
          ]
        },
        "similarity": 75.9710262677018
      },
      {
        "metadata": {
          "doc_id": "266",
          "name": "Incorrect Privilege Assignment",
          "source": "sparse",
          "original_content": "A product incorrectly assigns a privilege to a particular actor, creating an unintended sphere of control for that actor.",
          "keyphrase_sources": [
            {
              "id": "impact:Elevation of privileges",
              "keyphrase": "Elevation of privileges",
              "type": "impact"
            }
          ]
        },
        "similarity": 74.22338503443324
      },
      {
        "metadata": {
          "doc_id": "532",
          "name": "Insertion of Sensitive Information into Log File",
          "source": "sparse",
          "original_content": "The product writes sensitive information to a log file.",
          "keyphrase_sources": [
            {
              "id": "attacker:unauthenticated attacker",
              "keyphrase": "unauthenticated attacker",
              "type": "attacker"
            },
            {
              "id": "product:Dell Storage Center - Dell Storage Manager",
              "keyphrase": "Dell Storage Center - Dell Storage Manager",
              "type": "product"
            }
          ]
        },
        "similarity": 73.35811319920899
      },
      {
        "metadata": {
          "doc_id": "912",
          "name": "Hidden Functionality",
          "source": "sparse",
          "original_content": "The product contains functionality that is not documented, not part of the specification, and not accessible through an interface or command sequence that is obvious to the product's users or administrators.",
          "keyphrase_sources": [
            {
              "id": "version:20.1.20",
              "keyphrase": "20.1.20",
              "type": "version"
            }
          ]
        },
        "similarity": 72.61473033942954
      },
      {
        "metadata": {
          "doc_id": "20",
          "name": "Improper Input Validation",
          "source": "sparse",
          "original_content": "The product receives input or data, but it does\n        not validate or incorrectly validates that the input has the\n        properties that are required to process the data safely and\n        correctly.",
          "keyphrase_sources": [
            {
              "id": "impact:privilege escalation",
              "keyphrase": "privilege escalation",
              "type": "impact"
            },
            {
              "id": "version:20.1.20",
              "keyphrase": "20.1.20",
              "type": "version"
            }
          ]
        },
        "similarity": 70.39469781712732
      },
      {
        "metadata": {
          "doc_id": "269",
          "name": "Improper Privilege Management",
          "source": "sparse",
          "original_content": "The product does not properly assign, modify, track, or check privileges for an actor, creating an unintended sphere of control for that actor.",
          "keyphrase_sources": [
            {
              "id": "impact:privilege escalation",
              "keyphrase": "privilege escalation",
              "type": "impact"
            }
          ]
        },
        "similarity": 69.72688897429535
      },
      {
        "metadata": {
          "doc_id": "732",
          "name": "Incorrect Permission Assignment for Critical Resource",
          "source": "sparse",
          "original_content": "The product specifies permissions for a security-critical resource in a way that allows that resource to be read or modified by unintended actors.",
          "keyphrase_sources": [
            {
              "id": "impact:privilege escalation",
              "keyphrase": "privilege escalation",
              "type": "impact"
            }
          ]
        },
        "similarity": 69.10483162567914
      }
    ],
    "enhanced_query": "# Vulnerability Description\n\n    Dell Storage Center - Dell Storage Manager, version(s) 20.1.20, contain(s) an **Improper Authentication vulnerability**. An unauthenticated attacker with adjacent network access could potentially exploit this vulnerability, leading to Elevation of privileges.\n\n    # Keyphrase-Specific CWE Analysis\n    This vulnerability contains multiple keyphrases that may map to different CWEs. \n    Please analyze each keyphrase separately and determine the most appropriate CWE(s) for each.\n\n    ## ROOTCAUSE: 'Improper Authentication vulnerability'\n\nRelevant CWEs for this ROOTCAUSE:\n\n### 1. CWE-256: Plaintext Storage of a Password (Score: 214.20)\n\nStoring a password in plaintext may result in a system compromise....\n\n### 2. CWE-321: Use of Hard-coded Cryptographic Key (Score: 213.69)\n\nThe use of a hard-coded cryptographic key significantly increases the possibility that encrypted data may be recovered....\n\n### 3. CWE-287: Improper Authentication (Score: 209.05)\n\nWhen an actor claims to have a given identity, the product does not prove or insufficiently proves that the claim is correct....\n\n### 4. CWE-119: Improper Restriction of Operations within the Bounds of a Memory Buffer (Score: 204.86)\n\nThe product performs operations on a memory buffer, but it reads from or writes to a memory location outside the buffer's intended boundary. This may result in read or write operations on unexpected memory locations that could be linked to other variables, data structures, or internal program data....\n\n### 5. CWE-284: Improper Access Control (Score: 203.81)\n\nThe product does not restrict or incorrectly restricts access to a resource from an unauthorized actor....\n\n## ROOTCAUSE: 'authentication bypass'\n\nRelevant CWEs for this ROOTCAUSE:\n\n### 1. CWE-256: Plaintext Storage of a Password (Score: 214.20)\n\nStoring a password in plaintext may result in a system compromise....\n\n### 2. CWE-321: Use of Hard-coded Cryptographic Key (Score: 213.69)\n\nThe use of a hard-coded cryptographic key significantly increases the possibility that encrypted data may be recovered....\n\n### 3. CWE-287: Improper Authentication (Score: 209.05)\n\nWhen an actor claims to have a given identity, the product does not prove or insufficiently proves that the claim is correct....\n\n### 4. CWE-284: Improper Access Control (Score: 203.81)\n\nThe product does not restrict or incorrectly restricts access to a resource from an unauthorized actor....\n\n### 5. CWE-288: Authentication Bypass Using an Alternate Path or Channel (Score: 200.12)\n\nThe product requires authentication, but the product has an alternate path or channel that does not require authentication....\n\n## WEAKNESS: 'authentication bypass'\n\nRelevant CWEs for this WEAKNESS:\n\n### 1. CWE-256: Plaintext Storage of a Password (Score: 214.20)\n\nStoring a password in plaintext may result in a system compromise....\n\n### 2. CWE-321: Use of Hard-coded Cryptographic Key (Score: 213.69)\n\nThe use of a hard-coded cryptographic key significantly increases the possibility that encrypted data may be recovered....\n\n### 3. CWE-287: Improper Authentication (Score: 209.05)\n\nWhen an actor claims to have a given identity, the product does not prove or insufficiently proves that the claim is correct....\n\n### 4. CWE-284: Improper Access Control (Score: 203.81)\n\nThe product does not restrict or incorrectly restricts access to a resource from an unauthorized actor....\n\n### 5. CWE-288: Authentication Bypass Using an Alternate Path or Channel (Score: 200.12)\n\nThe product requires authentication, but the product has an alternate path or channel that does not require authentication....\n\n## IMPACT: 'Elevation of privileges'\n\nRelevant CWEs for this IMPACT:\n\n### 1. CWE-256: Plaintext Storage of a Password (Score: 214.20)\n\nStoring a password in plaintext may result in a system compromise....\n\n### 2. CWE-321: Use of Hard-coded Cryptographic Key (Score: 213.69)\n\nThe use of a hard-coded cryptographic key significantly increases the possibility that encrypted data may be recovered....\n\n### 3. CWE-119: Improper Restriction of Operations within the Bounds of a Memory Buffer (Score: 204.86)\n\nThe product performs operations on a memory buffer, but it reads from or writes to a memory location outside the buffer's intended boundary. This may result in read or write operations on unexpected memory locations that could be linked to other variables, data structures, or internal program data....\n\n### 4. CWE-59: Improper Link Resolution Before File Access ('Link Following') (Score: 75.97)\n\nThe product attempts to access a file based on the filename, but it does not properly prevent that filename from identifying a link or shortcut that resolves to an unintended resource....\n\n### 5. CWE-266: Incorrect Privilege Assignment (Score: 74.22)\n\nA product incorrectly assigns a privilege to a particular actor, creating an unintended sphere of control for that actor....\n\n## ATTACKER: 'unauthenticated attacker'\n\nRelevant CWEs for this ATTACKER:\n\n### 1. CWE-256: Plaintext Storage of a Password (Score: 214.20)\n\nStoring a password in plaintext may result in a system compromise....\n\n### 2. CWE-321: Use of Hard-coded Cryptographic Key (Score: 213.69)\n\nThe use of a hard-coded cryptographic key significantly increases the possibility that encrypted data may be recovered....\n\n### 3. CWE-119: Improper Restriction of Operations within the Bounds of a Memory Buffer (Score: 204.86)\n\nThe product performs operations on a memory buffer, but it reads from or writes to a memory location outside the buffer's intended boundary. This may result in read or write operations on unexpected memory locations that could be linked to other variables, data structures, or internal program data....\n\n### 4. CWE-284: Improper Access Control (Score: 203.81)\n\nThe product does not restrict or incorrectly restricts access to a resource from an unauthorized actor....\n\n### 5. CWE-532: Insertion of Sensitive Information into Log File (Score: 73.36)\n\nThe product writes sensitive information to a log file....\n\n## PRODUCT: 'Dell Storage Center - Dell Storage Manager'\n\nRelevant CWEs for this PRODUCT:\n\n### 1. CWE-256: Plaintext Storage of a Password (Score: 214.20)\n\nStoring a password in plaintext may result in a system compromise....\n\n### 2. CWE-321: Use of Hard-coded Cryptographic Key (Score: 213.69)\n\nThe use of a hard-coded cryptographic key significantly increases the possibility that encrypted data may be recovered....\n\n### 3. CWE-119: Improper Restriction of Operations within the Bounds of a Memory Buffer (Score: 204.86)\n\nThe product performs operations on a memory buffer, but it reads from or writes to a memory location outside the buffer's intended boundary. This may result in read or write operations on unexpected memory locations that could be linked to other variables, data structures, or internal program data....\n\n### 4. CWE-331: Insufficient Entropy (Score: 82.85)\n\nThe product uses an algorithm or scheme that produces insufficient entropy, leaving patterns or clusters of values that are more likely to occur than others....\n\n### 5. CWE-532: Insertion of Sensitive Information into Log File (Score: 73.36)\n\nThe product writes sensitive information to a log file....\n\n## VERSION: '20.1.20'\n\nRelevant CWEs for this VERSION:\n\n### 1. CWE-256: Plaintext Storage of a Password (Score: 214.20)\n\nStoring a password in plaintext may result in a system compromise....\n\n### 2. CWE-321: Use of Hard-coded Cryptographic Key (Score: 213.69)\n\nThe use of a hard-coded cryptographic key significantly increases the possibility that encrypted data may be recovered....\n\n### 3. CWE-119: Improper Restriction of Operations within the Bounds of a Memory Buffer (Score: 204.86)\n\nThe product performs operations on a memory buffer, but it reads from or writes to a memory location outside the buffer's intended boundary. This may result in read or write operations on unexpected memory locations that could be linked to other variables, data structures, or internal program data....\n\n### 4. CWE-912: Hidden Functionality (Score: 72.61)\n\nThe product contains functionality that is not documented, not part of the specification, and not accessible through an interface or command sequence that is obvious to the product's users or administrators....\n\n### 5. CWE-20: Improper Input Validation (Score: 70.39)\n\nThe product receives input or data, but it does\n        not validate or incorrectly validates that the input has the\n        properties that are required to process the data safely and\n        correctly....\n\n## IMPACT: 'privilege escalation'\n\nRelevant CWEs for this IMPACT:\n\n### 1. CWE-119: Improper Restriction of Operations within the Bounds of a Memory Buffer (Score: 204.86)\n\nThe product performs operations on a memory buffer, but it reads from or writes to a memory location outside the buffer's intended boundary. This may result in read or write operations on unexpected memory locations that could be linked to other variables, data structures, or internal program data....\n\n### 2. CWE-284: Improper Access Control (Score: 203.81)\n\nThe product does not restrict or incorrectly restricts access to a resource from an unauthorized actor....\n\n### 3. CWE-20: Improper Input Validation (Score: 70.39)\n\nThe product receives input or data, but it does\n        not validate or incorrectly validates that the input has the\n        properties that are required to process the data safely and\n        correctly....\n\n### 4. CWE-269: Improper Privilege Management (Score: 69.73)\n\nThe product does not properly assign, modify, track, or check privileges for an actor, creating an unintended sphere of control for that actor....\n\n### 5. CWE-732: Incorrect Permission Assignment for Critical Resource (Score: 69.10)\n\nThe product specifies permissions for a security-critical resource in a way that allows that resource to be read or modified by unintended actors....\n\n\n    # Analysis Instructions\n    1. For each keyphrase, identify the most appropriate CWE(s) that represent the weakness.\n    2. Consider how the different keyphrases might relate to each other in the vulnerability chain.\n    3. Provide a final determination of primary CWE(s) and any secondary CWEs.\n    4. Format your response using the standard analysis template.\n\n    Please analyze how these different weaknesses interact and provide a comprehensive CWE classification.\n    "
  },
  "retrieval_time": 1.259716510772705
}