{
  "cve_id": "CVE-2024-6844",
  "description": "A vulnerability in corydolphin/flask-cors version 4.0.1 allows for **inconsistent CORS matching** due to the handling of the + character in URL paths. The request.path is passed through the unquote_plus function, which converts the + character to a space . This behavior leads to incorrect path normalization, causing potential mismatches in CORS configuration. As a result, endpoints may not be matched correctly to their CORS settings, leading to unexpected CORS policy application. This can cause unauthorized cross-origin access or block valid requests, creating security vulnerabilities and usability issues.",
  "key_phrases": {
    "component": "",
    "rootcause": "",
    "vector": "+ character in URL paths",
    "weakness": "inconsistent CORS matching",
    "product": "corydolphin/flask-cors",
    "impact": "improper CORS matching, unauthorized cross-origin access",
    "attacker": "",
    "version": "4.0.1"
  },
  "reference_content": null,
  "similar_info": {
    "cwe_distribution": {},
    "cwe_consensus": "",
    "similarity_stats": {
      "thresholds": [],
      "total_samples_by_threshold": {},
      "top_cwes_by_threshold": {}
    }
  },
  "similarity_summary": {
    "consensus_cwe": "",
    "top_cwes": [],
    "confidence_levels": {},
    "total_samples": 0
  },
  "analysis": "# Summary\n| CWE ID | CWE Name | Confidence | CWE Abstraction Level | CWE Vulnerability Mapping Label | CWE-Vulnerability Mapping Notes |\n|---|---|---|---|---|---|\n| CWE-346 | Origin Validation Error | 0.7 | Class | Primary | Allowed-with-Review |\n| CWE-1385 | Missing Origin Validation in WebSockets | 0.6 | Variant | Secondary | Allowed |\n\n## Evidence and Confidence\n\n*   **Confidence Score:** 0.7\n*   **Evidence Strength:** MEDIUM\n\n## Relationship Analysis\nThe primary relationship influencing the decision is the ChildOf relationship between CWE-1385 (Missing Origin Validation in WebSockets) and CWE-346 (Origin Validation Error). Since the vulnerability description mentions CORS and specifically points to origin validation issues due to the handling of '+' character in URL paths, CWE-346 serves as a broader classification. The more specific CWE-1385 is also applicable because the context involves web-based communication and origin validation. CWE-346 is a Class, so it is better to choose a child that is a Base or Variant. CWE-1385 fits that description.\n\n```mermaid\ngraph TD\n    cwe346[\"CWE-346: Origin Validation Error\"]\n    cwe1385[\"CWE-1385: Missing Origin Validation in WebSockets\"]\n    \n    cwe1385 -->|CHILDOF| cwe346\n    \n    classDef primary fill:#f96,stroke:#333,stroke-width:2px\n    classDef secondary fill:#69f,stroke:#333\n    class cwe346 primary\n    class cwe1385 secondary\n```\n\n## Vulnerability Chain\nThe vulnerability chain starts with the **improper handling of the + character in URL paths**, leading to **inconsistent CORS matching**, which results in **unauthorized cross-origin access** or blocked valid requests. The root cause is the **missing or improper origin validation**.\n\n## Summary of Analysis\nThe initial assessment identified that the vulnerability stemmed from **inconsistent CORS matching** due to the handling of the + character. The vulnerability description states that \"The request.path is passed through the unquote_plus function, which converts the + character to a space. This behavior leads to incorrect path normalization, causing potential mismatches in CORS configuration.\" This issue is primarily related to origin validation, making CWE-346 (Origin Validation Error) a relevant candidate. Furthermore, the mention of CORS and the context of web requests suggests that CWE-1385 (Missing Origin Validation in WebSockets) is also applicable, providing a more specific classification within the broader scope of origin validation errors.\n\nThe evidence suggests that the application **does not properly verify the origin** due to the way it processes URL paths, leading to potential security vulnerabilities. This aligns well with the description of CWE-346. The connection to web requests and CORS makes the more specific CWE-1385 also relevant.\n\nThe selection is based on the evidence provided in the vulnerability description and the relationships between the CWEs. The chosen CWEs are at an appropriate level of specificity, addressing both the general issue of origin validation and the specific context of web-based communication.\n\nRelevant CWE Information:\n\n# Enhanced Context (25 CWEs)\nThe following CWEs were identified as potentially relevant to this vulnerability:\n\n## CWE-346: Origin Validation Error\n**Abstraction Level**: Class\n**Similarity Score**: 0.74\n**Source**: dense\n\n**Description**:\nThe product does not properly verify that the source of data or communication is valid.\n\n**Mapping Guidance**:\n- Usage: Allowed-with-Review\n- Rationale: This CWE entry is a Class and might have Base-level children that would be more appropriate\n\n## CWE-1385: Missing Origin Validation in WebSockets\n**Abstraction Level**: Variant\n**Similarity Score**: 0.435\n**Source**: sparse\n\n**Description**:\nThe product uses a WebSocket, but it does not properly verify that the source of data or communication is valid.\n\n**Mapping Guidance**:\n- Usage: Allowed\n- Rationale: This CWE entry is at the Variant level of abstraction, which is a preferred level of abstraction for mapping to the root causes of vulnerabilities.\n\n**Relationships**:\n- CHILDOF -> CWE-346\n- PARENTOF -> CWE-1385\n\n## CWE-942: Permissive Cross-domain Policy with Untrusted Domains\n**Abstraction Level**: Variant\n**Similarity Score**: 0.502\n**Source**: sparse\n\n**Description**:\nThe product uses a cross-domain policy file that includes domains that should not be trusted.\n\n**Mapping Guidance**:\n- Usage: Allowed\n- Rationale: This CWE entry is at the Variant level of abstraction, which is a preferred level of abstraction for mapping to the root causes of vulnerabilities.\n\n## CWE-93: Improper Neutralization of CRLF Sequences ('CRLF Injection')\n**Abstraction Level**: Base\n**Similarity Score**: 0.482\n**Source**: sparse\n\n**Description**:\nThe product uses CRLF (carriage return line feeds) as a special element, e.g. to separate lines or records, but it does not neutralize or incorrectly neutralizes CRLF sequences from inputs.\n\n**Mapping Guidance**:\n- Usage: Allowed\n- Rationale: This CWE entry is at the Base level of abstraction, which is a preferred level of abstraction for mapping to the root causes of vulnerabilities.\n\n## CWE-923: Improper Restriction of Communication Channel to Intended Endpoints\n**Abstraction Level**: Class\n**Similarity Score**: 0.475\n**Source**: sparse\n\n**Description**:\nThe product establishes a communication channel to (or from) an endpoint for privileged or protected operations, but it does not properly ensure that it is communicating with the correct endpoint.\n\n**Mapping Guidance**:\n- Usage: Allowed-with-Review\n- Rationale: This CWE entry is a Class and might have Base-level children that would be more appropriate\n\n## CWE-113: Improper Neutralization of CRLF Sequences in HTTP Headers ('HTTP Request/Response Splitting')\n**Abstraction Level**: Variant\n**Similarity Score**: 0.454\n**Source**: sparse\n\n**Description**:\nThe product receives data from an HTTP agent/component (e.g., web server, proxy, browser, etc.), but it does not neutralize or incorrectly neutralizes CR and LF characters before the data is included in outgoing HTTP headers.\n\n**Mapping Guidance**:\n- Usage: Allowed\n- Rationale: This CWE entry is at the Variant level of abstraction, which is a preferred level of abstraction for mapping to the root causes of vulnerabilities.\n\n## CWE-696: Incorrect Behavior Order\n**Abstraction Level**: Class\n**Similarity Score**: 0.441\n**Source**: sparse\n\n**Description**:\nThe product performs operations in an order that causes an unexpected or undesirable behavior.\n\n**Mapping Guidance**:\n- Usage: Allowed-with-Review\n- Rationale: This CWE entry is a Class and might have Base-level children that would be more appropriate\n\n## CWE-863: Incorrect Authorization\n**Abstraction Level**: Class\n**Similarity Score**: 0.415\n**Source**: sparse\n\n**Description**:\nThe application does not perform proper authorization checks when a user attempts to access a resource or perform an action.\n\n**Mapping Guidance**:\n- Usage: Allowed-with-Review\n- Rationale: This CWE entry is a Class and might have Base-level children that would be more appropriate\n\n## CWE-204: Observable Response Discrepancy\n**Abstraction Level**: Base\n**Similarity Score**: 0.410\n**Source**: sparse\n\n**Description**:\nThe product provides different responses to incoming requests in a way that reveals internal state information to an unauthorized actor outside of the intended control sphere.\n\n**Mapping Guidance**:\n- Usage: Allowed\n- Rationale: This CWE entry is at the Base level of abstraction, which is a preferred level of abstraction for mapping to the root causes of vulnerabilities.\n\n## CWE-36: Absolute Path Traversal\n**Abstraction Level**: Base\n**Similarity Score**: 0.529\n**Source**: dense\n\n**Description**:\nThe product uses external input to construct a pathname that should be within a restricted directory, but it does not properly neutralize special elements within the pathname that can cause the resulting pathname to resolve to a location that is outside of the restricted directory.\n\n**Mapping Guidance**:\n- Usage: Allowed\n- Rationale: This CWE entry is at the Base level of abstraction, which is a preferred level of abstraction for mapping to the root causes of vulnerabilities.\n\n## CWE-1275: Sensitive Cookie with Improper SameSite Attribute\n**Abstraction Level**: variant\n**Similarity Score**: 0.002\n**Source**: graph\n\n**Description**:\nCWE-1275: Sensitive Cookie with Improper SameSite Attribute\n\n**Mapping Guidance**:\n- Usage: Allowed\n- Rationale: This CWE entry is at the Variant level of abstraction, which is a preferred level of abstraction for mapping to the root causes of vulnerabilities.\n\nCWEs considered but not used:\n\n*   CWE-942 (Permissive Cross-domain Policy with Untrusted Domains), CWE-93 (Improper Neutralization of CRLF Sequences ('CRLF Injection')), CWE-923 (Improper Restriction of Communication Channel to Intended Endpoints), and CWE-113 (Improper Neutralization of CRLF",
  "analysis_with_relationships": "# Summary\n| CWE ID | CWE Name | Confidence | CWE Abstraction Level | CWE Vulnerability Mapping Label | CWE-Vulnerability Mapping Notes |\n|---|---|---|---|---|---|\n| CWE-346 | Origin Validation Error | 0.7 | Class | Primary | Allowed-with-Review |\n| CWE-1385 | Missing Origin Validation in WebSockets | 0.6 | Variant | Secondary | Allowed |\n\n## Evidence and Confidence\n\n*   **Confidence Score:** 0.7\n*   **Evidence Strength:** MEDIUM\n\n## Relationship Analysis\nThe primary relationship influencing the decision is the ChildOf relationship between CWE-1385 (Missing Origin Validation in WebSockets) and CWE-346 (Origin Validation Error). Since the vulnerability description mentions CORS and specifically points to origin validation issues due to the handling of '+' character in URL paths, CWE-346 serves as a broader classification. The more specific CWE-1385 is also applicable because the context involves web-based communication and origin validation. CWE-346 is a Class, so it is better to choose a child that is a Base or Variant. CWE-1385 fits that description.\n\n```mermaid\ngraph TD\n    cwe346[\"CWE-346: Origin Validation Error\"]\n    cwe1385[\"CWE-1385: Missing Origin Validation in WebSockets\"]\n    \n    cwe1385 -->|CHILDOF| cwe346\n    \n    classDef primary fill:#f96,stroke:#333,stroke-width:2px\n    classDef secondary fill:#69f,stroke:#333\n    class cwe346 primary\n    class cwe1385 secondary\n```\n\n## Vulnerability Chain\nThe vulnerability chain starts with the **improper handling of the + character in URL paths**, leading to **inconsistent CORS matching**, which results in **unauthorized cross-origin access** or blocked valid requests. The root cause is the **missing or improper origin validation**.\n\n## Summary of Analysis\nThe initial assessment identified that the vulnerability stemmed from **inconsistent CORS matching** due to the handling of the + character. The vulnerability description states that \"The request.path is passed through the unquote_plus function, which converts the + character to a space. This behavior leads to incorrect path normalization, causing potential mismatches in CORS configuration.\" This issue is primarily related to origin validation, making CWE-346 (Origin Validation Error) a relevant candidate. Furthermore, the mention of CORS and the context of web requests suggests that CWE-1385 (Missing Origin Validation in WebSockets) is also applicable, providing a more specific classification within the broader scope of origin validation errors.\n\nThe evidence suggests that the application **does not properly verify the origin** due to the way it processes URL paths, leading to potential security vulnerabilities. This aligns well with the description of CWE-346. The connection to web requests and CORS makes the more specific CWE-1385 also relevant.\n\nThe selection is based on the evidence provided in the vulnerability description and the relationships between the CWEs. The chosen CWEs are at an appropriate level of specificity, addressing both the general issue of origin validation and the specific context of web-based communication.\n\nRelevant CWE Information:\n\n# Enhanced Context (25 CWEs)\nThe following CWEs were identified as potentially relevant to this vulnerability:\n\n## CWE-346: Origin Validation Error\n**Abstraction Level**: Class\n**Similarity Score**: 0.74\n**Source**: dense\n\n**Description**:\nThe product does not properly verify that the source of data or communication is valid.\n\n**Mapping Guidance**:\n- Usage: Allowed-with-Review\n- Rationale: This CWE entry is a Class and might have Base-level children that would be more appropriate\n\n## CWE-1385: Missing Origin Validation in WebSockets\n**Abstraction Level**: Variant\n**Similarity Score**: 0.435\n**Source**: sparse\n\n**Description**:\nThe product uses a WebSocket, but it does not properly verify that the source of data or communication is valid.\n\n**Mapping Guidance**:\n- Usage: Allowed\n- Rationale: This CWE entry is at the Variant level of abstraction, which is a preferred level of abstraction for mapping to the root causes of vulnerabilities.\n\n**Relationships**:\n- CHILDOF -> CWE-346\n- PARENTOF -> CWE-1385\n\n## CWE-942: Permissive Cross-domain Policy with Untrusted Domains\n**Abstraction Level**: Variant\n**Similarity Score**: 0.502\n**Source**: sparse\n\n**Description**:\nThe product uses a cross-domain policy file that includes domains that should not be trusted.\n\n**Mapping Guidance**:\n- Usage: Allowed\n- Rationale: This CWE entry is at the Variant level of abstraction, which is a preferred level of abstraction for mapping to the root causes of vulnerabilities.\n\n## CWE-93: Improper Neutralization of CRLF Sequences ('CRLF Injection')\n**Abstraction Level**: Base\n**Similarity Score**: 0.482\n**Source**: sparse\n\n**Description**:\nThe product uses CRLF (carriage return line feeds) as a special element, e.g. to separate lines or records, but it does not neutralize or incorrectly neutralizes CRLF sequences from inputs.\n\n**Mapping Guidance**:\n- Usage: Allowed\n- Rationale: This CWE entry is at the Base level of abstraction, which is a preferred level of abstraction for mapping to the root causes of vulnerabilities.\n\n## CWE-923: Improper Restriction of Communication Channel to Intended Endpoints\n**Abstraction Level**: Class\n**Similarity Score**: 0.475\n**Source**: sparse\n\n**Description**:\nThe product establishes a communication channel to (or from) an endpoint for privileged or protected operations, but it does not properly ensure that it is communicating with the correct endpoint.\n\n**Mapping Guidance**:\n- Usage: Allowed-with-Review\n- Rationale: This CWE entry is a Class and might have Base-level children that would be more appropriate\n\n## CWE-113: Improper Neutralization of CRLF Sequences in HTTP Headers ('HTTP Request/Response Splitting')\n**Abstraction Level**: Variant\n**Similarity Score**: 0.454\n**Source**: sparse\n\n**Description**:\nThe product receives data from an HTTP agent/component (e.g., web server, proxy, browser, etc.), but it does not neutralize or incorrectly neutralizes CR and LF characters before the data is included in outgoing HTTP headers.\n\n**Mapping Guidance**:\n- Usage: Allowed\n- Rationale: This CWE entry is at the Variant level of abstraction, which is a preferred level of abstraction for mapping to the root causes of vulnerabilities.\n\n## CWE-696: Incorrect Behavior Order\n**Abstraction Level**: Class\n**Similarity Score**: 0.441\n**Source**: sparse\n\n**Description**:\nThe product performs operations in an order that causes an unexpected or undesirable behavior.\n\n**Mapping Guidance**:\n- Usage: Allowed-with-Review\n- Rationale: This CWE entry is a Class and might have Base-level children that would be more appropriate\n\n## CWE-863: Incorrect Authorization\n**Abstraction Level**: Class\n**Similarity Score**: 0.415\n**Source**: sparse\n\n**Description**:\nThe application does not perform proper authorization checks when a user attempts to access a resource or perform an action.\n\n**Mapping Guidance**:\n- Usage: Allowed-with-Review\n- Rationale: This CWE entry is a Class and might have Base-level children that would be more appropriate\n\n## CWE-204: Observable Response Discrepancy\n**Abstraction Level**: Base\n**Similarity Score**: 0.410\n**Source**: sparse\n\n**Description**:\nThe product provides different responses to incoming requests in a way that reveals internal state information to an unauthorized actor outside of the intended control sphere.\n\n**Mapping Guidance**:\n- Usage: Allowed\n- Rationale: This CWE entry is at the Base level of abstraction, which is a preferred level of abstraction for mapping to the root causes of vulnerabilities.\n\n## CWE-36: Absolute Path Traversal\n**Abstraction Level**: Base\n**Similarity Score**: 0.529\n**Source**: dense\n\n**Description**:\nThe product uses external input to construct a pathname that should be within a restricted directory, but it does not properly neutralize special elements within the pathname that can cause the resulting pathname to resolve to a location that is outside of the restricted directory.\n\n**Mapping Guidance**:\n- Usage: Allowed\n- Rationale: This CWE entry is at the Base level of abstraction, which is a preferred level of abstraction for mapping to the root causes of vulnerabilities.\n\n## CWE-1275: Sensitive Cookie with Improper SameSite Attribute\n**Abstraction Level**: variant\n**Similarity Score**: 0.002\n**Source**: graph\n\n**Description**:\nCWE-1275: Sensitive Cookie with Improper SameSite Attribute\n\n**Mapping Guidance**:\n- Usage: Allowed\n- Rationale: This CWE entry is at the Variant level of abstraction, which is a preferred level of abstraction for mapping to the root causes of vulnerabilities.\n\nCWEs considered but not used:\n\n*   CWE-942 (Permissive Cross-domain Policy with Untrusted Domains), CWE-93 (Improper Neutralization of CRLF Sequences ('CRLF Injection')), CWE-923 (Improper Restriction of Communication Channel to Intended Endpoints), and CWE-113 (Improper Neutralization of CRLF\n\n\n## CWE Relationship Analysis\n\nCurrent CWEs represent these abstraction levels: .\n\n\n### Vulnerability Chain Analysis\n\n**Chain starting from CWE-863:**\n- 863 (Incorrect Authorization) - ROOT\n\n\n**Chain starting from CWE-93:**\n- 93 (Improper Neutralization of CRLF Sequences ('CRLF Injection')) - ROOT\n\n\n\n### CWE Relationship Diagram\n\n```mermaid\ngraph TD\n    classDef primary fill:#f96,stroke:#333,stroke-width:2px\n    classDef secondary fill:#69f,stroke:#333\n    classDef tertiary fill:#9e9,stroke:#333\n```",
  "criticism": "",
  "resolution": "",
  "relevant_cwes": [
    {
      "metadata": {
        "doc_id": "942",
        "name": "Permissive Cross-domain Policy with Untrusted Domains",
        "source": "sparse"
      },
      "similarity": 501.6538366031895
    },
    {
      "metadata": {
        "doc_id": "93",
        "name": "Improper Neutralization of CRLF Sequences ('CRLF Injection')",
        "source": "sparse"
      },
      "similarity": 482.29746354629356
    },
    {
      "metadata": {
        "doc_id": "923",
        "name": "Improper Restriction of Communication Channel to Intended Endpoints",
        "source": "sparse"
      },
      "similarity": 475.29193566365956
    },
    {
      "metadata": {
        "doc_id": "113",
        "name": "Improper Neutralization of CRLF Sequences in HTTP Headers ('HTTP Request/Response Splitting')",
        "source": "sparse"
      },
      "similarity": 453.9942620108846
    },
    {
      "metadata": {
        "doc_id": "696",
        "name": "Incorrect Behavior Order",
        "source": "sparse"
      },
      "similarity": 441.1376562325387
    },
    {
      "metadata": {
        "doc_id": "1385",
        "name": "Missing Origin Validation in WebSockets",
        "source": "sparse"
      },
      "similarity": 434.9987804567337
    },
    {
      "metadata": {
        "doc_id": "863",
        "name": "Incorrect Authorization",
        "source": "sparse"
      },
      "similarity": 414.6092792660816
    },
    {
      "metadata": {
        "doc_id": "204",
        "name": "Observable Response Discrepancy",
        "source": "sparse"
      },
      "similarity": 409.64851214061304
    },
    {
      "metadata": {
        "doc_id": "36",
        "name": "Absolute Path Traversal",
        "type": "Base",
        "original_content": "The product uses external input to construct a pathname that should be within a restricted directory, but it does not properly neutralize absolute path sequences such as \"/abs/path\" that can resolve to a location that is outside of that directory.",
        "keyphrase_source": "weakness:inconsistent CORS matching",
        "source": "dense",
        "mapping_notes": {
          "usage": "Allowed",
          "rationale": "This CWE entry is at the Base level of abstraction, which is a preferred level of abstraction for mapping to the root causes of vulnerabilities.",
          "comments": "Carefully read both the name and description to ensure that this mapping is an appropriate fit. Do not try to 'force' a mapping to a lower-level Base/Variant simply to comply with this preferred level of abstraction.",
          "reasons": [
            "Acceptable-Use"
          ]
        },
        "score_info": {
          "retrievers": [
            "dense",
            "graph"
          ],
          "retriever_count": 2,
          "normalized_scores": {
            "dense": 0.5293355391434462,
            "graph": 1.6307579971794275
          }
        }
      },
      "similarity": 0.5293355391434462
    },
    {
      "doc_id": "1275",
      "text": "CWE-1275: Sensitive Cookie with Improper SameSite Attribute",
      "score": 2.2704,
      "metadata": {
        "doc_id": "1275",
        "name": "Sensitive Cookie with Improper SameSite Attribute",
        "type": "variant",
        "original_content": "CWE-1275: Sensitive Cookie with Improper SameSite Attribute",
        "relationships": [
          {
            "source_id": "1275",
            "target_id": "352",
            "label": "CANPRECEDE",
            "properties": {
              "view_id": "1000"
            }
          },
          {
            "source_id": "1275",
            "target_id": "923",
            "label": "CHILDOF",
            "properties": {
              "ordinal": "Primary",
              "view_id": "1000"
            }
          },
          {
            "source_id": "923",
            "target_id": "1275",
            "label": "PARENTOF",
            "properties": {
              "ordinal": "Primary",
              "view_id": "1000"
            }
          },
          {
            "source_id": "352",
            "target_id": "1275",
            "label": "CANFOLLOW",
            "properties": {
              "view_id": "1000"
            }
          }
        ],
        "score_components": {
          "relationship_chain": 0.8,
          "abstraction_path": 0.76,
          "sequence_path": 0.8
        },
        "abstraction_factor": 1.2,
        "graph_path_info": {
          "path_types": [
            "relationship_chain",
            "abstraction_path_down",
            "vulnerability_sequence_forward",
            "vulnerability_sequence_backward"
          ],
          "best_paths": {
            "relationship_chain": {
              "path": [
                [
                  "346",
                  "352",
                  "REQUIREDBY"
                ],
                [
                  "352",
                  "1275",
                  "CANFOLLOW"
                ]
              ],
              "score": 0.8,
              "type": "relationship_chain",
              "source": "346"
            },
            "abstraction_path_down": {
              "path": [
                [
                  "923",
                  "1275",
                  "PARENTOF"
                ]
              ],
              "score": 0.76,
              "type": "abstraction_path_down",
              "source": "923"
            },
            "vulnerability_sequence_forward": {
              "path": [
                [
                  "346",
                  "352",
                  "REQUIREDBY"
                ],
                [
                  "352",
                  "1275",
                  "CANFOLLOW"
                ]
              ],
              "score": 0.7200000000000001,
              "type": "vulnerability_sequence_forward",
              "source": "346"
            },
            "vulnerability_sequence_backward": {
              "path": [
                [
                  "352",
                  "346",
                  "REQUIRES"
                ],
                [
                  "1275",
                  "352",
                  "CANPRECEDE"
                ]
              ],
              "score": 0.8,
              "type": "vulnerability_sequence_backward",
              "source": "346"
            }
          }
        },
        "abstraction_level": "variant",
        "position": "before",
        "sources": [
          "graph"
        ],
        "source": "graph",
        "mapping_notes": {
          "usage": "Allowed",
          "rationale": "This CWE entry is at the Variant level of abstraction, which is a preferred level of abstraction for mapping to the root causes of vulnerabilities.",
          "comments": "Carefully read both the name and description to ensure that this mapping is an appropriate fit. Do not try to 'force' a mapping to a lower-level Base/Variant simply to comply with this preferred level of abstraction.",
          "reasons": [
            "Acceptable-Use"
          ]
        },
        "score_info": {
          "retrievers": [
            "graph"
          ],
          "retriever_count": 1,
          "normalized_scores": {
            "graph": 2.2704
          }
        }
      },
      "similarity": 2.2704
    }
  ],
  "identified_cwes": {
    "analyzer": [
      "CWE-863",
      "CWE-93",
      "CWE-346",
      "CWE-113",
      "CWE-923",
      "CWE-696",
      "CWE-1385",
      "CWE-36",
      "CWE-942",
      "CWE-204",
      "CWE-1275"
    ],
    "critic_additional": []
  },
  "keyphrase_cwe_mapping": {}
}