{
  "vulnerability_info": "VulnerabilityInfo(cve_id='CVE-2024-40087', description='Vilo 5 Mesh WiFi System <= 5.16.1.33 is vulnerable to **Insecure Permissions**. **Lack of authentication** in the custom TCP service on port 5432 allows remote, unauthenticated attackers to gain administrative access over the router.', key_phrases={'rootcause': ['Insecure Permissions', 'Lack of authentication'], 'weakness': '', 'impact': 'gain administrative access over the router', 'vector': '', 'attacker': 'remote unauthenticated attackers', 'product': 'Vilo 5 Mesh WiFi System', 'version': '<= 5.16.1.33', 'component': 'custom TCP service on port 5432'}, reference_content='```\\n{\\n  \"Root cause of vulnerability\": \"The local service running on port 5432 uses a custom TCP protocol that does not require authentication.\",\\n  \"Weaknesses/vulnerabilities present\": [\\n    \"Lack of authentication for a custom TCP service.\",\\n    \"Custom protocol is easily reverse engineered.\",\\n     \"Service uses XXTEA encryption but does not require authentication before use\"\\n  ],\\n  \"Impact of exploitation\": \"An attacker on the LAN can change and see sensitive router settings including the SSID and WiFi password, PPPoE username and password, reboot the router, and any other functionality the Vilo app has access to.\",\\n  \"Attack vectors\": \"An attacker connected to the router\\'s LAN can interact with the local service on port 5432.\",\\n  \"Required attacker capabilities/position\": \"The attacker must be on the same LAN as the Vilo 5 Mesh WiFi System.\"\\n}\\n```', similar_info={'cwe_distribution': {}, 'cwe_consensus': '', 'similarity_stats': {'thresholds': [], 'total_samples_by_threshold': {}, 'top_cwes_by_threshold': {}}}, similarity_summary=SimilarityInsight(consensus_cwe='', top_cwes=[], confidence_levels={}, total_samples=0), analysis='', analysis_with_relationships='', criticism='', resolution='', relevant_cwes=[{'metadata': {'doc_id': '287', 'name': 'Improper Authentication', 'source': 'sparse', 'original_content': 'When an actor claims to have a given identity, the product does not prove or insufficiently proves that the claim is correct.', 'keyphrase_sources': [{'id': 'rootcause:Lack of authentication', 'keyphrase': 'Lack of authentication', 'type': 'rootcause'}, {'id': 'impact:gain administrative access over the router', 'keyphrase': 'gain administrative access over the router', 'type': 'impact'}, {'id': 'attacker:remote unauthenticated attackers', 'keyphrase': 'remote unauthenticated attackers', 'type': 'attacker'}]}, 'similarity': np.float64(228.52419818297386)}, {'metadata': {'doc_id': '798', 'name': 'Use of Hard-coded Credentials', 'source': 'sparse', 'original_content': 'The product contains hard-coded credentials, such as a password or cryptographic key.', 'keyphrase_sources': [{'id': 'rootcause:Lack of authentication', 'keyphrase': 'Lack of authentication', 'type': 'rootcause'}, {'id': 'impact:gain administrative access over the router', 'keyphrase': 'gain administrative access over the router', 'type': 'impact'}, {'id': 'attacker:remote unauthenticated attackers', 'keyphrase': 'remote unauthenticated attackers', 'type': 'attacker'}, {'id': 'product:Vilo 5 Mesh WiFi System', 'keyphrase': 'Vilo 5 Mesh WiFi System', 'type': 'product'}, {'id': 'version:<= 5.16.1.33', 'keyphrase': '<= 5.16.1.33', 'type': 'version'}, {'id': 'component:custom TCP service on port 5432', 'keyphrase': 'custom TCP service on port 5432', 'type': 'component'}]}, 'similarity': np.float64(228.51529623797234)}, {'metadata': {'doc_id': '732', 'name': 'Incorrect Permission Assignment for Critical Resource', 'source': 'sparse', 'original_content': 'The product specifies permissions for a security-critical resource in a way that allows that resource to be read or modified by unintended actors.', 'keyphrase_sources': [{'id': 'rootcause:Insecure Permissions', 'keyphrase': 'Insecure Permissions', 'type': 'rootcause'}]}, 'similarity': np.float64(222.76077153596373)}, {'metadata': {'doc_id': '284', 'name': 'Improper Access Control', 'source': 'sparse', 'original_content': 'The product does not restrict or incorrectly restricts access to a resource from an unauthorized actor.', 'keyphrase_sources': [{'id': 'rootcause:Lack of authentication', 'keyphrase': 'Lack of authentication', 'type': 'rootcause'}, {'id': 'attacker:remote unauthenticated attackers', 'keyphrase': 'remote unauthenticated attackers', 'type': 'attacker'}]}, 'similarity': np.float64(222.04741017041695)}, {'metadata': {'doc_id': '379', 'name': 'Creation of Temporary File in Directory with Insecure Permissions', 'source': 'sparse', 'original_content': \"The product creates a temporary file in a directory whose permissions allow unintended actors to determine the file's existence or otherwise access that file.\", 'keyphrase_sources': [{'id': 'rootcause:Insecure Permissions', 'keyphrase': 'Insecure Permissions', 'type': 'rootcause'}]}, 'similarity': np.float64(221.18554349543035)}, {'metadata': {'doc_id': '306', 'name': 'Missing Authentication for Critical Function', 'source': 'sparse', 'original_content': 'The product does not perform any authentication for functionality that requires a provable user identity or consumes a significant amount of resources.', 'keyphrase_sources': [{'id': 'rootcause:Insecure Permissions', 'keyphrase': 'Insecure Permissions', 'type': 'rootcause'}, {'id': 'rootcause:Lack of authentication', 'keyphrase': 'Lack of authentication', 'type': 'rootcause'}, {'id': 'impact:gain administrative access over the router', 'keyphrase': 'gain administrative access over the router', 'type': 'impact'}, {'id': 'attacker:remote unauthenticated attackers', 'keyphrase': 'remote unauthenticated attackers', 'type': 'attacker'}, {'id': 'product:Vilo 5 Mesh WiFi System', 'keyphrase': 'Vilo 5 Mesh WiFi System', 'type': 'product'}, {'id': 'version:<= 5.16.1.33', 'keyphrase': '<= 5.16.1.33', 'type': 'version'}, {'id': 'component:custom TCP service on port 5432', 'keyphrase': 'custom TCP service on port 5432', 'type': 'component'}]}, 'similarity': np.float64(221.0832046350735)}, {'metadata': {'doc_id': '425', 'name': \"Direct Request ('Forced Browsing')\", 'source': 'sparse', 'original_content': 'The web application does not adequately enforce appropriate authorization on all restricted URLs, scripts, or files.', 'keyphrase_sources': [{'id': 'rootcause:Insecure Permissions', 'keyphrase': 'Insecure Permissions', 'type': 'rootcause'}, {'id': 'attacker:remote unauthenticated attackers', 'keyphrase': 'remote unauthenticated attackers', 'type': 'attacker'}, {'id': 'product:Vilo 5 Mesh WiFi System', 'keyphrase': 'Vilo 5 Mesh WiFi System', 'type': 'product'}]}, 'similarity': np.float64(218.29908171081388)}, {'metadata': {'doc_id': '330', 'name': 'Use of Insufficiently Random Values', 'source': 'sparse', 'original_content': 'The product uses insufficiently random numbers or values in a security context that depends on unpredictable numbers.', 'keyphrase_sources': [{'id': 'rootcause:Insecure Permissions', 'keyphrase': 'Insecure Permissions', 'type': 'rootcause'}, {'id': 'rootcause:Lack of authentication', 'keyphrase': 'Lack of authentication', 'type': 'rootcause'}, {'id': 'version:<= 5.16.1.33', 'keyphrase': '<= 5.16.1.33', 'type': 'version'}, {'id': 'component:custom TCP service on port 5432', 'keyphrase': 'custom TCP service on port 5432', 'type': 'component'}]}, 'similarity': np.float64(216.38807539992666)}, {'metadata': {'doc_id': '1188', 'name': 'Initialization of a Resource with an Insecure Default', 'source': 'sparse', 'original_content': 'The product initializes or sets a resource with a default that is intended to be changed by the administrator, but the default is not secure.', 'keyphrase_sources': [{'id': 'impact:gain administrative access over the router', 'keyphrase': 'gain administrative access over the router', 'type': 'impact'}]}, 'similarity': np.float64(91.15327922710681)}, {'metadata': {'doc_id': '259', 'name': 'Use of Hard-coded Password', 'source': 'sparse', 'original_content': 'The product contains a hard-coded password, which it uses for its own inbound authentication or for outbound communication to external components.', 'keyphrase_sources': [{'id': 'impact:gain administrative access over the router', 'keyphrase': 'gain administrative access over the router', 'type': 'impact'}, {'id': 'product:Vilo 5 Mesh WiFi System', 'keyphrase': 'Vilo 5 Mesh WiFi System', 'type': 'product'}]}, 'similarity': np.float64(88.15616926179989)}, {'metadata': {'doc_id': '290', 'name': 'Authentication Bypass by Spoofing', 'source': 'sparse', 'original_content': 'This attack-focused weakness is caused by incorrectly implemented authentication schemes that are subject to spoofing attacks.', 'keyphrase_sources': [{'id': 'product:Vilo 5 Mesh WiFi System', 'keyphrase': 'Vilo 5 Mesh WiFi System', 'type': 'product'}, {'id': 'component:custom TCP service on port 5432', 'keyphrase': 'custom TCP service on port 5432', 'type': 'component'}]}, 'similarity': np.float64(72.91306603469506)}, {'metadata': {'doc_id': '400', 'name': 'Uncontrolled Resource Consumption', 'source': 'sparse', 'original_content': 'The product does not properly control the allocation and maintenance of a limited resource, thereby enabling an actor to influence the amount of resources consumed, eventually leading to the exhaustion of available resources.', 'keyphrase_sources': [{'id': 'version:<= 5.16.1.33', 'keyphrase': '<= 5.16.1.33', 'type': 'version'}, {'id': 'component:custom TCP service on port 5432', 'keyphrase': 'custom TCP service on port 5432', 'type': 'component'}]}, 'similarity': np.float64(72.78759380939292)}, {'metadata': {'doc_id': '337', 'name': 'Predictable Seed in Pseudo-Random Number Generator (PRNG)', 'source': 'sparse', 'original_content': 'A Pseudo-Random Number Generator (PRNG) is initialized from a predictable seed, such as the process ID or system time.', 'keyphrase_sources': [{'id': 'version:<= 5.16.1.33', 'keyphrase': '<= 5.16.1.33', 'type': 'version'}]}, 'similarity': np.float64(72.23430394114447)}], identified_cwes={'analyzer': [], 'critic_additional': []})",
  "retrieval_results": {
    "has_multiple_keyphrases": true,
    "keyphrase_cwe_sets": {
      "rootcause:Insecure Permissions": {
        "keyphrase": "Insecure Permissions",
        "type": "rootcause",
        "cwes": [
          {
            "metadata": {
              "doc_id": "732",
              "name": "Incorrect Permission Assignment for Critical Resource",
              "source": "sparse",
              "original_content": "The product specifies permissions for a security-critical resource in a way that allows that resource to be read or modified by unintended actors.",
              "keyphrase_sources": [
                {
                  "id": "rootcause:Insecure Permissions",
                  "keyphrase": "Insecure Permissions",
                  "type": "rootcause"
                }
              ]
            },
            "similarity": 222.76077153596373
          },
          {
            "metadata": {
              "doc_id": "379",
              "name": "Creation of Temporary File in Directory with Insecure Permissions",
              "source": "sparse",
              "original_content": "The product creates a temporary file in a directory whose permissions allow unintended actors to determine the file's existence or otherwise access that file.",
              "keyphrase_sources": [
                {
                  "id": "rootcause:Insecure Permissions",
                  "keyphrase": "Insecure Permissions",
                  "type": "rootcause"
                }
              ]
            },
            "similarity": 221.18554349543035
          },
          {
            "metadata": {
              "doc_id": "306",
              "name": "Missing Authentication for Critical Function",
              "source": "sparse",
              "original_content": "The product does not perform any authentication for functionality that requires a provable user identity or consumes a significant amount of resources.",
              "keyphrase_sources": [
                {
                  "id": "rootcause:Insecure Permissions",
                  "keyphrase": "Insecure Permissions",
                  "type": "rootcause"
                },
                {
                  "id": "rootcause:Lack of authentication",
                  "keyphrase": "Lack of authentication",
                  "type": "rootcause"
                },
                {
                  "id": "impact:gain administrative access over the router",
                  "keyphrase": "gain administrative access over the router",
                  "type": "impact"
                },
                {
                  "id": "attacker:remote unauthenticated attackers",
                  "keyphrase": "remote unauthenticated attackers",
                  "type": "attacker"
                },
                {
                  "id": "product:Vilo 5 Mesh WiFi System",
                  "keyphrase": "Vilo 5 Mesh WiFi System",
                  "type": "product"
                },
                {
                  "id": "version:<= 5.16.1.33",
                  "keyphrase": "<= 5.16.1.33",
                  "type": "version"
                },
                {
                  "id": "component:custom TCP service on port 5432",
                  "keyphrase": "custom TCP service on port 5432",
                  "type": "component"
                }
              ]
            },
            "similarity": 221.0832046350735
          },
          {
            "metadata": {
              "doc_id": "425",
              "name": "Direct Request ('Forced Browsing')",
              "source": "sparse",
              "original_content": "The web application does not adequately enforce appropriate authorization on all restricted URLs, scripts, or files.",
              "keyphrase_sources": [
                {
                  "id": "rootcause:Insecure Permissions",
                  "keyphrase": "Insecure Permissions",
                  "type": "rootcause"
                },
                {
                  "id": "attacker:remote unauthenticated attackers",
                  "keyphrase": "remote unauthenticated attackers",
                  "type": "attacker"
                },
                {
                  "id": "product:Vilo 5 Mesh WiFi System",
                  "keyphrase": "Vilo 5 Mesh WiFi System",
                  "type": "product"
                }
              ]
            },
            "similarity": 218.29908171081388
          },
          {
            "metadata": {
              "doc_id": "330",
              "name": "Use of Insufficiently Random Values",
              "source": "sparse",
              "original_content": "The product uses insufficiently random numbers or values in a security context that depends on unpredictable numbers.",
              "keyphrase_sources": [
                {
                  "id": "rootcause:Insecure Permissions",
                  "keyphrase": "Insecure Permissions",
                  "type": "rootcause"
                },
                {
                  "id": "rootcause:Lack of authentication",
                  "keyphrase": "Lack of authentication",
                  "type": "rootcause"
                },
                {
                  "id": "version:<= 5.16.1.33",
                  "keyphrase": "<= 5.16.1.33",
                  "type": "version"
                },
                {
                  "id": "component:custom TCP service on port 5432",
                  "keyphrase": "custom TCP service on port 5432",
                  "type": "component"
                }
              ]
            },
            "similarity": 216.38807539992666
          }
        ]
      },
      "rootcause:Lack of authentication": {
        "keyphrase": "Lack of authentication",
        "type": "rootcause",
        "cwes": [
          {
            "metadata": {
              "doc_id": "306",
              "name": "Missing Authentication for Critical Function",
              "source": "sparse",
              "original_content": "The product does not perform any authentication for functionality that requires a provable user identity or consumes a significant amount of resources."
            },
            "similarity": 251.09935066726953
          },
          {
            "metadata": {
              "doc_id": "287",
              "name": "Improper Authentication",
              "source": "sparse",
              "original_content": "When an actor claims to have a given identity, the product does not prove or insufficiently proves that the claim is correct.",
              "keyphrase_sources": [
                {
                  "id": "rootcause:Lack of authentication",
                  "keyphrase": "Lack of authentication",
                  "type": "rootcause"
                },
                {
                  "id": "impact:gain administrative access over the router",
                  "keyphrase": "gain administrative access over the router",
                  "type": "impact"
                },
                {
                  "id": "attacker:remote unauthenticated attackers",
                  "keyphrase": "remote unauthenticated attackers",
                  "type": "attacker"
                }
              ]
            },
            "similarity": 228.52419818297386
          },
          {
            "metadata": {
              "doc_id": "798",
              "name": "Use of Hard-coded Credentials",
              "source": "sparse",
              "original_content": "The product contains hard-coded credentials, such as a password or cryptographic key.",
              "keyphrase_sources": [
                {
                  "id": "rootcause:Lack of authentication",
                  "keyphrase": "Lack of authentication",
                  "type": "rootcause"
                },
                {
                  "id": "impact:gain administrative access over the router",
                  "keyphrase": "gain administrative access over the router",
                  "type": "impact"
                },
                {
                  "id": "attacker:remote unauthenticated attackers",
                  "keyphrase": "remote unauthenticated attackers",
                  "type": "attacker"
                },
                {
                  "id": "product:Vilo 5 Mesh WiFi System",
                  "keyphrase": "Vilo 5 Mesh WiFi System",
                  "type": "product"
                },
                {
                  "id": "version:<= 5.16.1.33",
                  "keyphrase": "<= 5.16.1.33",
                  "type": "version"
                },
                {
                  "id": "component:custom TCP service on port 5432",
                  "keyphrase": "custom TCP service on port 5432",
                  "type": "component"
                }
              ]
            },
            "similarity": 228.51529623797234
          },
          {
            "metadata": {
              "doc_id": "330",
              "name": "Use of Insufficiently Random Values",
              "source": "sparse",
              "original_content": "The product uses insufficiently random numbers or values in a security context that depends on unpredictable numbers."
            },
            "similarity": 225.68268885926784
          },
          {
            "metadata": {
              "doc_id": "284",
              "name": "Improper Access Control",
              "source": "sparse",
              "original_content": "The product does not restrict or incorrectly restricts access to a resource from an unauthorized actor.",
              "keyphrase_sources": [
                {
                  "id": "rootcause:Lack of authentication",
                  "keyphrase": "Lack of authentication",
                  "type": "rootcause"
                },
                {
                  "id": "attacker:remote unauthenticated attackers",
                  "keyphrase": "remote unauthenticated attackers",
                  "type": "attacker"
                }
              ]
            },
            "similarity": 222.04741017041695
          }
        ]
      },
      "impact:gain administrative access over the router": {
        "keyphrase": "gain administrative access over the router",
        "type": "impact",
        "cwes": [
          {
            "metadata": {
              "doc_id": "306",
              "name": "Missing Authentication for Critical Function",
              "source": "sparse",
              "original_content": "The product does not perform any authentication for functionality that requires a provable user identity or consumes a significant amount of resources."
            },
            "similarity": 99.12726892261026
          },
          {
            "metadata": {
              "doc_id": "798",
              "name": "Use of Hard-coded Credentials",
              "source": "sparse",
              "original_content": "The product contains hard-coded credentials, such as a password or cryptographic key."
            },
            "similarity": 99.0358518956006
          },
          {
            "metadata": {
              "doc_id": "1188",
              "name": "Initialization of a Resource with an Insecure Default",
              "source": "sparse",
              "original_content": "The product initializes or sets a resource with a default that is intended to be changed by the administrator, but the default is not secure.",
              "keyphrase_sources": [
                {
                  "id": "impact:gain administrative access over the router",
                  "keyphrase": "gain administrative access over the router",
                  "type": "impact"
                }
              ]
            },
            "similarity": 91.15327922710681
          },
          {
            "metadata": {
              "doc_id": "287",
              "name": "Improper Authentication",
              "source": "sparse",
              "original_content": "When an actor claims to have a given identity, the product does not prove or insufficiently proves that the claim is correct."
            },
            "similarity": 88.60138861448857
          },
          {
            "metadata": {
              "doc_id": "259",
              "name": "Use of Hard-coded Password",
              "source": "sparse",
              "original_content": "The product contains a hard-coded password, which it uses for its own inbound authentication or for outbound communication to external components.",
              "keyphrase_sources": [
                {
                  "id": "impact:gain administrative access over the router",
                  "keyphrase": "gain administrative access over the router",
                  "type": "impact"
                },
                {
                  "id": "product:Vilo 5 Mesh WiFi System",
                  "keyphrase": "Vilo 5 Mesh WiFi System",
                  "type": "product"
                }
              ]
            },
            "similarity": 88.15616926179989
          }
        ]
      },
      "attacker:remote unauthenticated attackers": {
        "keyphrase": "remote unauthenticated attackers",
        "type": "attacker",
        "cwes": [
          {
            "metadata": {
              "doc_id": "306",
              "name": "Missing Authentication for Critical Function",
              "source": "sparse",
              "original_content": "The product does not perform any authentication for functionality that requires a provable user identity or consumes a significant amount of resources."
            },
            "similarity": 78.61082332656957
          },
          {
            "metadata": {
              "doc_id": "798",
              "name": "Use of Hard-coded Credentials",
              "source": "sparse",
              "original_content": "The product contains hard-coded credentials, such as a password or cryptographic key."
            },
            "similarity": 72.71171846879493
          },
          {
            "metadata": {
              "doc_id": "425",
              "name": "Direct Request ('Forced Browsing')",
              "source": "sparse",
              "original_content": "The web application does not adequately enforce appropriate authorization on all restricted URLs, scripts, or files."
            },
            "similarity": 72.11834217552472
          },
          {
            "metadata": {
              "doc_id": "287",
              "name": "Improper Authentication",
              "source": "sparse",
              "original_content": "When an actor claims to have a given identity, the product does not prove or insufficiently proves that the claim is correct."
            },
            "similarity": 70.72225966039717
          },
          {
            "metadata": {
              "doc_id": "284",
              "name": "Improper Access Control",
              "source": "sparse",
              "original_content": "The product does not restrict or incorrectly restricts access to a resource from an unauthorized actor."
            },
            "similarity": 69.00589194768804
          }
        ]
      },
      "product:Vilo 5 Mesh WiFi System": {
        "keyphrase": "Vilo 5 Mesh WiFi System",
        "type": "product",
        "cwes": [
          {
            "metadata": {
              "doc_id": "306",
              "name": "Missing Authentication for Critical Function",
              "source": "sparse",
              "original_content": "The product does not perform any authentication for functionality that requires a provable user identity or consumes a significant amount of resources."
            },
            "similarity": 77.94597748463283
          },
          {
            "metadata": {
              "doc_id": "425",
              "name": "Direct Request ('Forced Browsing')",
              "source": "sparse",
              "original_content": "The web application does not adequately enforce appropriate authorization on all restricted URLs, scripts, or files."
            },
            "similarity": 76.66043991870411
          },
          {
            "metadata": {
              "doc_id": "798",
              "name": "Use of Hard-coded Credentials",
              "source": "sparse",
              "original_content": "The product contains hard-coded credentials, such as a password or cryptographic key."
            },
            "similarity": 73.28276762252746
          },
          {
            "metadata": {
              "doc_id": "259",
              "name": "Use of Hard-coded Password",
              "source": "sparse",
              "original_content": "The product contains a hard-coded password, which it uses for its own inbound authentication or for outbound communication to external components."
            },
            "similarity": 73.00798092744742
          },
          {
            "metadata": {
              "doc_id": "290",
              "name": "Authentication Bypass by Spoofing",
              "source": "sparse",
              "original_content": "This attack-focused weakness is caused by incorrectly implemented authentication schemes that are subject to spoofing attacks.",
              "keyphrase_sources": [
                {
                  "id": "product:Vilo 5 Mesh WiFi System",
                  "keyphrase": "Vilo 5 Mesh WiFi System",
                  "type": "product"
                },
                {
                  "id": "component:custom TCP service on port 5432",
                  "keyphrase": "custom TCP service on port 5432",
                  "type": "component"
                }
              ]
            },
            "similarity": 72.91306603469506
          }
        ]
      },
      "version:<= 5.16.1.33": {
        "keyphrase": "<= 5.16.1.33",
        "type": "version",
        "cwes": [
          {
            "metadata": {
              "doc_id": "306",
              "name": "Missing Authentication for Critical Function",
              "source": "sparse",
              "original_content": "The product does not perform any authentication for functionality that requires a provable user identity or consumes a significant amount of resources."
            },
            "similarity": 77.6921455073188
          },
          {
            "metadata": {
              "doc_id": "798",
              "name": "Use of Hard-coded Credentials",
              "source": "sparse",
              "original_content": "The product contains hard-coded credentials, such as a password or cryptographic key."
            },
            "similarity": 73.58775921837416
          },
          {
            "metadata": {
              "doc_id": "400",
              "name": "Uncontrolled Resource Consumption",
              "source": "sparse",
              "original_content": "The product does not properly control the allocation and maintenance of a limited resource, thereby enabling an actor to influence the amount of resources consumed, eventually leading to the exhaustion of available resources.",
              "keyphrase_sources": [
                {
                  "id": "version:<= 5.16.1.33",
                  "keyphrase": "<= 5.16.1.33",
                  "type": "version"
                },
                {
                  "id": "component:custom TCP service on port 5432",
                  "keyphrase": "custom TCP service on port 5432",
                  "type": "component"
                }
              ]
            },
            "similarity": 72.78759380939292
          },
          {
            "metadata": {
              "doc_id": "330",
              "name": "Use of Insufficiently Random Values",
              "source": "sparse",
              "original_content": "The product uses insufficiently random numbers or values in a security context that depends on unpredictable numbers."
            },
            "similarity": 72.75010351088783
          },
          {
            "metadata": {
              "doc_id": "337",
              "name": "Predictable Seed in Pseudo-Random Number Generator (PRNG)",
              "source": "sparse",
              "original_content": "A Pseudo-Random Number Generator (PRNG) is initialized from a predictable seed, such as the process ID or system time.",
              "keyphrase_sources": [
                {
                  "id": "version:<= 5.16.1.33",
                  "keyphrase": "<= 5.16.1.33",
                  "type": "version"
                }
              ]
            },
            "similarity": 72.23430394114447
          }
        ]
      },
      "component:custom TCP service on port 5432": {
        "keyphrase": "custom TCP service on port 5432",
        "type": "component",
        "cwes": [
          {
            "metadata": {
              "doc_id": "306",
              "name": "Missing Authentication for Critical Function",
              "source": "sparse",
              "original_content": "The product does not perform any authentication for functionality that requires a provable user identity or consumes a significant amount of resources."
            },
            "similarity": 90.86655982560856
          },
          {
            "metadata": {
              "doc_id": "330",
              "name": "Use of Insufficiently Random Values",
              "source": "sparse",
              "original_content": "The product uses insufficiently random numbers or values in a security context that depends on unpredictable numbers."
            },
            "similarity": 88.0345602618684
          },
          {
            "metadata": {
              "doc_id": "400",
              "name": "Uncontrolled Resource Consumption",
              "source": "sparse",
              "original_content": "The product does not properly control the allocation and maintenance of a limited resource, thereby enabling an actor to influence the amount of resources consumed, eventually leading to the exhaustion of available resources."
            },
            "similarity": 84.37627668916888
          },
          {
            "metadata": {
              "doc_id": "798",
              "name": "Use of Hard-coded Credentials",
              "source": "sparse",
              "original_content": "The product contains hard-coded credentials, such as a password or cryptographic key."
            },
            "similarity": 79.41009484078627
          },
          {
            "metadata": {
              "doc_id": "290",
              "name": "Authentication Bypass by Spoofing",
              "source": "sparse",
              "original_content": "This attack-focused weakness is caused by incorrectly implemented authentication schemes that are subject to spoofing attacks."
            },
            "similarity": 79.01646048360527
          }
        ]
      }
    },
    "keyphrase_mapping": {
      "732": [
        {
          "id": "rootcause:Insecure Permissions",
          "keyphrase": "Insecure Permissions",
          "type": "rootcause"
        }
      ],
      "379": [
        {
          "id": "rootcause:Insecure Permissions",
          "keyphrase": "Insecure Permissions",
          "type": "rootcause"
        }
      ],
      "306": [
        {
          "id": "rootcause:Insecure Permissions",
          "keyphrase": "Insecure Permissions",
          "type": "rootcause"
        },
        {
          "id": "rootcause:Lack of authentication",
          "keyphrase": "Lack of authentication",
          "type": "rootcause"
        },
        {
          "id": "impact:gain administrative access over the router",
          "keyphrase": "gain administrative access over the router",
          "type": "impact"
        },
        {
          "id": "attacker:remote unauthenticated attackers",
          "keyphrase": "remote unauthenticated attackers",
          "type": "attacker"
        },
        {
          "id": "product:Vilo 5 Mesh WiFi System",
          "keyphrase": "Vilo 5 Mesh WiFi System",
          "type": "product"
        },
        {
          "id": "version:<= 5.16.1.33",
          "keyphrase": "<= 5.16.1.33",
          "type": "version"
        },
        {
          "id": "component:custom TCP service on port 5432",
          "keyphrase": "custom TCP service on port 5432",
          "type": "component"
        }
      ],
      "425": [
        {
          "id": "rootcause:Insecure Permissions",
          "keyphrase": "Insecure Permissions",
          "type": "rootcause"
        },
        {
          "id": "attacker:remote unauthenticated attackers",
          "keyphrase": "remote unauthenticated attackers",
          "type": "attacker"
        },
        {
          "id": "product:Vilo 5 Mesh WiFi System",
          "keyphrase": "Vilo 5 Mesh WiFi System",
          "type": "product"
        }
      ],
      "330": [
        {
          "id": "rootcause:Insecure Permissions",
          "keyphrase": "Insecure Permissions",
          "type": "rootcause"
        },
        {
          "id": "rootcause:Lack of authentication",
          "keyphrase": "Lack of authentication",
          "type": "rootcause"
        },
        {
          "id": "version:<= 5.16.1.33",
          "keyphrase": "<= 5.16.1.33",
          "type": "version"
        },
        {
          "id": "component:custom TCP service on port 5432",
          "keyphrase": "custom TCP service on port 5432",
          "type": "component"
        }
      ],
      "287": [
        {
          "id": "rootcause:Lack of authentication",
          "keyphrase": "Lack of authentication",
          "type": "rootcause"
        },
        {
          "id": "impact:gain administrative access over the router",
          "keyphrase": "gain administrative access over the router",
          "type": "impact"
        },
        {
          "id": "attacker:remote unauthenticated attackers",
          "keyphrase": "remote unauthenticated attackers",
          "type": "attacker"
        }
      ],
      "798": [
        {
          "id": "rootcause:Lack of authentication",
          "keyphrase": "Lack of authentication",
          "type": "rootcause"
        },
        {
          "id": "impact:gain administrative access over the router",
          "keyphrase": "gain administrative access over the router",
          "type": "impact"
        },
        {
          "id": "attacker:remote unauthenticated attackers",
          "keyphrase": "remote unauthenticated attackers",
          "type": "attacker"
        },
        {
          "id": "product:Vilo 5 Mesh WiFi System",
          "keyphrase": "Vilo 5 Mesh WiFi System",
          "type": "product"
        },
        {
          "id": "version:<= 5.16.1.33",
          "keyphrase": "<= 5.16.1.33",
          "type": "version"
        },
        {
          "id": "component:custom TCP service on port 5432",
          "keyphrase": "custom TCP service on port 5432",
          "type": "component"
        }
      ],
      "284": [
        {
          "id": "rootcause:Lack of authentication",
          "keyphrase": "Lack of authentication",
          "type": "rootcause"
        },
        {
          "id": "attacker:remote unauthenticated attackers",
          "keyphrase": "remote unauthenticated attackers",
          "type": "attacker"
        }
      ],
      "1188": [
        {
          "id": "impact:gain administrative access over the router",
          "keyphrase": "gain administrative access over the router",
          "type": "impact"
        }
      ],
      "259": [
        {
          "id": "impact:gain administrative access over the router",
          "keyphrase": "gain administrative access over the router",
          "type": "impact"
        },
        {
          "id": "product:Vilo 5 Mesh WiFi System",
          "keyphrase": "Vilo 5 Mesh WiFi System",
          "type": "product"
        }
      ],
      "290": [
        {
          "id": "product:Vilo 5 Mesh WiFi System",
          "keyphrase": "Vilo 5 Mesh WiFi System",
          "type": "product"
        },
        {
          "id": "component:custom TCP service on port 5432",
          "keyphrase": "custom TCP service on port 5432",
          "type": "component"
        }
      ],
      "400": [
        {
          "id": "version:<= 5.16.1.33",
          "keyphrase": "<= 5.16.1.33",
          "type": "version"
        },
        {
          "id": "component:custom TCP service on port 5432",
          "keyphrase": "custom TCP service on port 5432",
          "type": "component"
        }
      ],
      "337": [
        {
          "id": "version:<= 5.16.1.33",
          "keyphrase": "<= 5.16.1.33",
          "type": "version"
        }
      ]
    },
    "relevant_cwes": [
      {
        "metadata": {
          "doc_id": "287",
          "name": "Improper Authentication",
          "source": "sparse",
          "original_content": "When an actor claims to have a given identity, the product does not prove or insufficiently proves that the claim is correct.",
          "keyphrase_sources": [
            {
              "id": "rootcause:Lack of authentication",
              "keyphrase": "Lack of authentication",
              "type": "rootcause"
            },
            {
              "id": "impact:gain administrative access over the router",
              "keyphrase": "gain administrative access over the router",
              "type": "impact"
            },
            {
              "id": "attacker:remote unauthenticated attackers",
              "keyphrase": "remote unauthenticated attackers",
              "type": "attacker"
            }
          ]
        },
        "similarity": 228.52419818297386
      },
      {
        "metadata": {
          "doc_id": "798",
          "name": "Use of Hard-coded Credentials",
          "source": "sparse",
          "original_content": "The product contains hard-coded credentials, such as a password or cryptographic key.",
          "keyphrase_sources": [
            {
              "id": "rootcause:Lack of authentication",
              "keyphrase": "Lack of authentication",
              "type": "rootcause"
            },
            {
              "id": "impact:gain administrative access over the router",
              "keyphrase": "gain administrative access over the router",
              "type": "impact"
            },
            {
              "id": "attacker:remote unauthenticated attackers",
              "keyphrase": "remote unauthenticated attackers",
              "type": "attacker"
            },
            {
              "id": "product:Vilo 5 Mesh WiFi System",
              "keyphrase": "Vilo 5 Mesh WiFi System",
              "type": "product"
            },
            {
              "id": "version:<= 5.16.1.33",
              "keyphrase": "<= 5.16.1.33",
              "type": "version"
            },
            {
              "id": "component:custom TCP service on port 5432",
              "keyphrase": "custom TCP service on port 5432",
              "type": "component"
            }
          ]
        },
        "similarity": 228.51529623797234
      },
      {
        "metadata": {
          "doc_id": "732",
          "name": "Incorrect Permission Assignment for Critical Resource",
          "source": "sparse",
          "original_content": "The product specifies permissions for a security-critical resource in a way that allows that resource to be read or modified by unintended actors.",
          "keyphrase_sources": [
            {
              "id": "rootcause:Insecure Permissions",
              "keyphrase": "Insecure Permissions",
              "type": "rootcause"
            }
          ]
        },
        "similarity": 222.76077153596373
      },
      {
        "metadata": {
          "doc_id": "284",
          "name": "Improper Access Control",
          "source": "sparse",
          "original_content": "The product does not restrict or incorrectly restricts access to a resource from an unauthorized actor.",
          "keyphrase_sources": [
            {
              "id": "rootcause:Lack of authentication",
              "keyphrase": "Lack of authentication",
              "type": "rootcause"
            },
            {
              "id": "attacker:remote unauthenticated attackers",
              "keyphrase": "remote unauthenticated attackers",
              "type": "attacker"
            }
          ]
        },
        "similarity": 222.04741017041695
      },
      {
        "metadata": {
          "doc_id": "379",
          "name": "Creation of Temporary File in Directory with Insecure Permissions",
          "source": "sparse",
          "original_content": "The product creates a temporary file in a directory whose permissions allow unintended actors to determine the file's existence or otherwise access that file.",
          "keyphrase_sources": [
            {
              "id": "rootcause:Insecure Permissions",
              "keyphrase": "Insecure Permissions",
              "type": "rootcause"
            }
          ]
        },
        "similarity": 221.18554349543035
      },
      {
        "metadata": {
          "doc_id": "306",
          "name": "Missing Authentication for Critical Function",
          "source": "sparse",
          "original_content": "The product does not perform any authentication for functionality that requires a provable user identity or consumes a significant amount of resources.",
          "keyphrase_sources": [
            {
              "id": "rootcause:Insecure Permissions",
              "keyphrase": "Insecure Permissions",
              "type": "rootcause"
            },
            {
              "id": "rootcause:Lack of authentication",
              "keyphrase": "Lack of authentication",
              "type": "rootcause"
            },
            {
              "id": "impact:gain administrative access over the router",
              "keyphrase": "gain administrative access over the router",
              "type": "impact"
            },
            {
              "id": "attacker:remote unauthenticated attackers",
              "keyphrase": "remote unauthenticated attackers",
              "type": "attacker"
            },
            {
              "id": "product:Vilo 5 Mesh WiFi System",
              "keyphrase": "Vilo 5 Mesh WiFi System",
              "type": "product"
            },
            {
              "id": "version:<= 5.16.1.33",
              "keyphrase": "<= 5.16.1.33",
              "type": "version"
            },
            {
              "id": "component:custom TCP service on port 5432",
              "keyphrase": "custom TCP service on port 5432",
              "type": "component"
            }
          ]
        },
        "similarity": 221.0832046350735
      },
      {
        "metadata": {
          "doc_id": "425",
          "name": "Direct Request ('Forced Browsing')",
          "source": "sparse",
          "original_content": "The web application does not adequately enforce appropriate authorization on all restricted URLs, scripts, or files.",
          "keyphrase_sources": [
            {
              "id": "rootcause:Insecure Permissions",
              "keyphrase": "Insecure Permissions",
              "type": "rootcause"
            },
            {
              "id": "attacker:remote unauthenticated attackers",
              "keyphrase": "remote unauthenticated attackers",
              "type": "attacker"
            },
            {
              "id": "product:Vilo 5 Mesh WiFi System",
              "keyphrase": "Vilo 5 Mesh WiFi System",
              "type": "product"
            }
          ]
        },
        "similarity": 218.29908171081388
      },
      {
        "metadata": {
          "doc_id": "330",
          "name": "Use of Insufficiently Random Values",
          "source": "sparse",
          "original_content": "The product uses insufficiently random numbers or values in a security context that depends on unpredictable numbers.",
          "keyphrase_sources": [
            {
              "id": "rootcause:Insecure Permissions",
              "keyphrase": "Insecure Permissions",
              "type": "rootcause"
            },
            {
              "id": "rootcause:Lack of authentication",
              "keyphrase": "Lack of authentication",
              "type": "rootcause"
            },
            {
              "id": "version:<= 5.16.1.33",
              "keyphrase": "<= 5.16.1.33",
              "type": "version"
            },
            {
              "id": "component:custom TCP service on port 5432",
              "keyphrase": "custom TCP service on port 5432",
              "type": "component"
            }
          ]
        },
        "similarity": 216.38807539992666
      },
      {
        "metadata": {
          "doc_id": "1188",
          "name": "Initialization of a Resource with an Insecure Default",
          "source": "sparse",
          "original_content": "The product initializes or sets a resource with a default that is intended to be changed by the administrator, but the default is not secure.",
          "keyphrase_sources": [
            {
              "id": "impact:gain administrative access over the router",
              "keyphrase": "gain administrative access over the router",
              "type": "impact"
            }
          ]
        },
        "similarity": 91.15327922710681
      },
      {
        "metadata": {
          "doc_id": "259",
          "name": "Use of Hard-coded Password",
          "source": "sparse",
          "original_content": "The product contains a hard-coded password, which it uses for its own inbound authentication or for outbound communication to external components.",
          "keyphrase_sources": [
            {
              "id": "impact:gain administrative access over the router",
              "keyphrase": "gain administrative access over the router",
              "type": "impact"
            },
            {
              "id": "product:Vilo 5 Mesh WiFi System",
              "keyphrase": "Vilo 5 Mesh WiFi System",
              "type": "product"
            }
          ]
        },
        "similarity": 88.15616926179989
      },
      {
        "metadata": {
          "doc_id": "290",
          "name": "Authentication Bypass by Spoofing",
          "source": "sparse",
          "original_content": "This attack-focused weakness is caused by incorrectly implemented authentication schemes that are subject to spoofing attacks.",
          "keyphrase_sources": [
            {
              "id": "product:Vilo 5 Mesh WiFi System",
              "keyphrase": "Vilo 5 Mesh WiFi System",
              "type": "product"
            },
            {
              "id": "component:custom TCP service on port 5432",
              "keyphrase": "custom TCP service on port 5432",
              "type": "component"
            }
          ]
        },
        "similarity": 72.91306603469506
      },
      {
        "metadata": {
          "doc_id": "400",
          "name": "Uncontrolled Resource Consumption",
          "source": "sparse",
          "original_content": "The product does not properly control the allocation and maintenance of a limited resource, thereby enabling an actor to influence the amount of resources consumed, eventually leading to the exhaustion of available resources.",
          "keyphrase_sources": [
            {
              "id": "version:<= 5.16.1.33",
              "keyphrase": "<= 5.16.1.33",
              "type": "version"
            },
            {
              "id": "component:custom TCP service on port 5432",
              "keyphrase": "custom TCP service on port 5432",
              "type": "component"
            }
          ]
        },
        "similarity": 72.78759380939292
      },
      {
        "metadata": {
          "doc_id": "337",
          "name": "Predictable Seed in Pseudo-Random Number Generator (PRNG)",
          "source": "sparse",
          "original_content": "A Pseudo-Random Number Generator (PRNG) is initialized from a predictable seed, such as the process ID or system time.",
          "keyphrase_sources": [
            {
              "id": "version:<= 5.16.1.33",
              "keyphrase": "<= 5.16.1.33",
              "type": "version"
            }
          ]
        },
        "similarity": 72.23430394114447
      }
    ],
    "enhanced_query": "# Vulnerability Description\n\n    Vilo 5 Mesh WiFi System <= 5.16.1.33 is vulnerable to **Insecure Permissions**. **Lack of authentication** in the custom TCP service on port 5432 allows remote, unauthenticated attackers to gain administrative access over the router.\n\n    # Keyphrase-Specific CWE Analysis\n    This vulnerability contains multiple keyphrases that may map to different CWEs. \n    Please analyze each keyphrase separately and determine the most appropriate CWE(s) for each.\n\n    ## ROOTCAUSE: 'Lack of authentication'\n\nRelevant CWEs for this ROOTCAUSE:\n\n### 1. CWE-287: Improper Authentication (Score: 228.52)\n\nWhen an actor claims to have a given identity, the product does not prove or insufficiently proves that the claim is correct....\n\n### 2. CWE-798: Use of Hard-coded Credentials (Score: 228.52)\n\nThe product contains hard-coded credentials, such as a password or cryptographic key....\n\n### 3. CWE-284: Improper Access Control (Score: 222.05)\n\nThe product does not restrict or incorrectly restricts access to a resource from an unauthorized actor....\n\n### 4. CWE-306: Missing Authentication for Critical Function (Score: 221.08)\n\nThe product does not perform any authentication for functionality that requires a provable user identity or consumes a significant amount of resources....\n\n### 5. CWE-330: Use of Insufficiently Random Values (Score: 216.39)\n\nThe product uses insufficiently random numbers or values in a security context that depends on unpredictable numbers....\n\n## IMPACT: 'gain administrative access over the router'\n\nRelevant CWEs for this IMPACT:\n\n### 1. CWE-287: Improper Authentication (Score: 228.52)\n\nWhen an actor claims to have a given identity, the product does not prove or insufficiently proves that the claim is correct....\n\n### 2. CWE-798: Use of Hard-coded Credentials (Score: 228.52)\n\nThe product contains hard-coded credentials, such as a password or cryptographic key....\n\n### 3. CWE-306: Missing Authentication for Critical Function (Score: 221.08)\n\nThe product does not perform any authentication for functionality that requires a provable user identity or consumes a significant amount of resources....\n\n### 4. CWE-1188: Initialization of a Resource with an Insecure Default (Score: 91.15)\n\nThe product initializes or sets a resource with a default that is intended to be changed by the administrator, but the default is not secure....\n\n### 5. CWE-259: Use of Hard-coded Password (Score: 88.16)\n\nThe product contains a hard-coded password, which it uses for its own inbound authentication or for outbound communication to external components....\n\n## ATTACKER: 'remote unauthenticated attackers'\n\nRelevant CWEs for this ATTACKER:\n\n### 1. CWE-287: Improper Authentication (Score: 228.52)\n\nWhen an actor claims to have a given identity, the product does not prove or insufficiently proves that the claim is correct....\n\n### 2. CWE-798: Use of Hard-coded Credentials (Score: 228.52)\n\nThe product contains hard-coded credentials, such as a password or cryptographic key....\n\n### 3. CWE-284: Improper Access Control (Score: 222.05)\n\nThe product does not restrict or incorrectly restricts access to a resource from an unauthorized actor....\n\n### 4. CWE-306: Missing Authentication for Critical Function (Score: 221.08)\n\nThe product does not perform any authentication for functionality that requires a provable user identity or consumes a significant amount of resources....\n\n### 5. CWE-425: Direct Request ('Forced Browsing') (Score: 218.30)\n\nThe web application does not adequately enforce appropriate authorization on all restricted URLs, scripts, or files....\n\n## PRODUCT: 'Vilo 5 Mesh WiFi System'\n\nRelevant CWEs for this PRODUCT:\n\n### 1. CWE-798: Use of Hard-coded Credentials (Score: 228.52)\n\nThe product contains hard-coded credentials, such as a password or cryptographic key....\n\n### 2. CWE-306: Missing Authentication for Critical Function (Score: 221.08)\n\nThe product does not perform any authentication for functionality that requires a provable user identity or consumes a significant amount of resources....\n\n### 3. CWE-425: Direct Request ('Forced Browsing') (Score: 218.30)\n\nThe web application does not adequately enforce appropriate authorization on all restricted URLs, scripts, or files....\n\n### 4. CWE-259: Use of Hard-coded Password (Score: 88.16)\n\nThe product contains a hard-coded password, which it uses for its own inbound authentication or for outbound communication to external components....\n\n### 5. CWE-290: Authentication Bypass by Spoofing (Score: 72.91)\n\nThis attack-focused weakness is caused by incorrectly implemented authentication schemes that are subject to spoofing attacks....\n\n## VERSION: '<= 5.16.1.33'\n\nRelevant CWEs for this VERSION:\n\n### 1. CWE-798: Use of Hard-coded Credentials (Score: 228.52)\n\nThe product contains hard-coded credentials, such as a password or cryptographic key....\n\n### 2. CWE-306: Missing Authentication for Critical Function (Score: 221.08)\n\nThe product does not perform any authentication for functionality that requires a provable user identity or consumes a significant amount of resources....\n\n### 3. CWE-330: Use of Insufficiently Random Values (Score: 216.39)\n\nThe product uses insufficiently random numbers or values in a security context that depends on unpredictable numbers....\n\n### 4. CWE-400: Uncontrolled Resource Consumption (Score: 72.79)\n\nThe product does not properly control the allocation and maintenance of a limited resource, thereby enabling an actor to influence the amount of resources consumed, eventually leading to the exhaustion of available resources....\n\n### 5. CWE-337: Predictable Seed in Pseudo-Random Number Generator (PRNG) (Score: 72.23)\n\nA Pseudo-Random Number Generator (PRNG) is initialized from a predictable seed, such as the process ID or system time....\n\n## COMPONENT: 'custom TCP service on port 5432'\n\nRelevant CWEs for this COMPONENT:\n\n### 1. CWE-798: Use of Hard-coded Credentials (Score: 228.52)\n\nThe product contains hard-coded credentials, such as a password or cryptographic key....\n\n### 2. CWE-306: Missing Authentication for Critical Function (Score: 221.08)\n\nThe product does not perform any authentication for functionality that requires a provable user identity or consumes a significant amount of resources....\n\n### 3. CWE-330: Use of Insufficiently Random Values (Score: 216.39)\n\nThe product uses insufficiently random numbers or values in a security context that depends on unpredictable numbers....\n\n### 4. CWE-290: Authentication Bypass by Spoofing (Score: 72.91)\n\nThis attack-focused weakness is caused by incorrectly implemented authentication schemes that are subject to spoofing attacks....\n\n### 5. CWE-400: Uncontrolled Resource Consumption (Score: 72.79)\n\nThe product does not properly control the allocation and maintenance of a limited resource, thereby enabling an actor to influence the amount of resources consumed, eventually leading to the exhaustion of available resources....\n\n## ROOTCAUSE: 'Insecure Permissions'\n\nRelevant CWEs for this ROOTCAUSE:\n\n### 1. CWE-732: Incorrect Permission Assignment for Critical Resource (Score: 222.76)\n\nThe product specifies permissions for a security-critical resource in a way that allows that resource to be read or modified by unintended actors....\n\n### 2. CWE-379: Creation of Temporary File in Directory with Insecure Permissions (Score: 221.19)\n\nThe product creates a temporary file in a directory whose permissions allow unintended actors to determine the file's existence or otherwise access that file....\n\n### 3. CWE-306: Missing Authentication for Critical Function (Score: 221.08)\n\nThe product does not perform any authentication for functionality that requires a provable user identity or consumes a significant amount of resources....\n\n### 4. CWE-425: Direct Request ('Forced Browsing') (Score: 218.30)\n\nThe web application does not adequately enforce appropriate authorization on all restricted URLs, scripts, or files....\n\n### 5. CWE-330: Use of Insufficiently Random Values (Score: 216.39)\n\nThe product uses insufficiently random numbers or values in a security context that depends on unpredictable numbers....\n\n\n    # Analysis Instructions\n    1. For each keyphrase, identify the most appropriate CWE(s) that represent the weakness.\n    2. Consider how the different keyphrases might relate to each other in the vulnerability chain.\n    3. Provide a final determination of primary CWE(s) and any secondary CWEs.\n    4. Format your response using the standard analysis template.\n\n    Please analyze how these different weaknesses interact and provide a comprehensive CWE classification.\n    "
  },
  "retrieval_time": 1.0820612907409668
}