{
  "vulnerability_info": "VulnerabilityInfo(cve_id='CVE-2024-41084', description='In the Linux kernel, the following vulnerability has been resolved cxl/region Avoid **null pointer dereference** in region lookup cxl_dpa_to_region() looks up a region based on a memdev and DPA. It wrongly assumes an endpoint found mapping the DPA is also of a fully assembled region. When not true it leads to a **null pointer dereference** looking up the region name. This appears during testing of region lookup after a failure to assemble a BIOS defined region or if the lookup raced with the assembly of the BIOS defined region. Failure to clean up BIOS defined regions that fail assembly is an issue in itself and a fix to that problem will alleviate some of the impact. It will not alleviate the **race condition** so lets harden this path. The behavior change is that the kernel oops due to a **null pointer dereference** is replaced with a dev_dbg() message noting that an endpoint was mapped. Additional comments are added so that future users of this function can more clearly understand what it provides.', key_phrases={'rootcause': ['race condition', 'wrong assumption that an endpoint is a fully assembled region'], 'weakness': 'null pointer dereference', 'impact': 'kernel oops', 'vector': '', 'attacker': '', 'product': 'Linux kernel', 'version': '', 'component': 'cxl/region'}, reference_content='Based on the provided information, here\\'s an analysis of the vulnerability:\\n\\n**Root Cause:**\\n\\nThe vulnerability lies in the `cxl_dpa_to_region()` function within the Linux kernel\\'s CXL (Compute Express Link) subsystem. This function is responsible for looking up a memory region based on a Device-Private Address (DPA) and a memory device. The root cause is that the function incorrectly assumes that any endpoint mapping a DPA also belongs to a fully assembled region. When this assumption is false, the code attempts to access the region name via a null pointer, causing a kernel panic.\\n\\n**Weaknesses/Vulnerabilities:**\\n\\n- **Null Pointer Dereference:** The primary vulnerability is a null pointer dereference. The code accesses `cxled->cxld.region->dev` without verifying if `cxled->cxld.region` is valid. In cases where the region is not fully assembled (e.g., due to a failed assembly, or race conditions during assembly) `cxled->cxld.region` can be null.\\n\\n**Impact of Exploitation:**\\n\\n- **Kernel Panic/Crash:** The impact of this vulnerability is a kernel panic (oops) due to the null pointer dereference. This can lead to a denial-of-service (DoS) scenario where the system crashes.\\n\\n**Attack Vectors:**\\n\\n- **Triggering a Region Lookup on a Partially Assembled Region:** The vulnerability can be triggered during region lookup attempts after a failure to assemble a BIOS-defined region, or if the lookup raced with the assembly of the BIOS defined region.\\n\\n**Required Attacker Capabilities/Position:**\\n\\n- To exploit this vulnerability, an attacker needs a way to trigger a region lookup under the conditions described in the \"Attack Vectors\" section. The attacker would need some level of interaction with the CXL subsystem, which could involve specific hardware configurations or interactions with the driver interface.\\n\\n**Additional Notes:**\\n\\n- The provided code diffs show the fix for the vulnerability. Instead of causing a kernel panic, the code now logs a debug message if the region is not fully assembled and the `cxlr` pointer is null.\\n- The fix also introduces additional comments to improve code clarity.\\n- The vulnerability exists due to a logical flaw in the assumption that an endpoint mapping a DPA always implies a fully assembled region.\\n- The fix hardens the code by explicitly checking if the `cxlr` is null before attempting to dereference it.\\n\\n**Summary of the Fix:**\\nThe fix addresses the null pointer dereference by:\\n1.  Adding a check to see if `cxlr = cxled->cxld.region` is null or not.\\n2.  If it is not null, it will proceed with printing the debug message with the region\\'s device name.\\n3. If it is null, it prints a debug message indicating the dpa was mapped to an endpoint rather than a region.\\n4.  The code now also sets `ctx->cxlr = cxlr` where cxlr can be a null value.', similar_info={'cwe_distribution': {}, 'cwe_consensus': '', 'similarity_stats': {'thresholds': [], 'total_samples_by_threshold': {}, 'top_cwes_by_threshold': {}}}, similarity_summary=SimilarityInsight(consensus_cwe='', top_cwes=[], confidence_levels={}, total_samples=0), analysis='', analysis_with_relationships='', criticism='', resolution='', relevant_cwes=[{'metadata': {'doc_id': '252', 'name': 'Unchecked Return Value', 'source': 'sparse', 'original_content': 'The product does not check the return value from a method or function, which can prevent it from detecting unexpected states and conditions.', 'keyphrase_sources': [{'id': 'rootcause:wrong assumption that an endpoint is a fully assembled region', 'keyphrase': 'wrong assumption that an endpoint is a fully assembled region', 'type': 'rootcause'}, {'id': 'weakness:null pointer dereference', 'keyphrase': 'null pointer dereference', 'type': 'weakness'}, {'id': 'impact:kernel oops', 'keyphrase': 'kernel oops', 'type': 'impact'}, {'id': 'product:Linux kernel', 'keyphrase': 'Linux kernel', 'type': 'product'}, {'id': 'component:cxl/region', 'keyphrase': 'cxl/region', 'type': 'component'}]}, 'similarity': np.float64(979.3707259233393)}, {'metadata': {'doc_id': '362', 'name': \"Concurrent Execution using Shared Resource with Improper Synchronization ('Race Condition')\", 'source': 'sparse', 'original_content': 'The product contains a concurrent code sequence that requires temporary, exclusive access to a shared resource, but a timing window exists in which the shared resource can be modified by another code sequence operating concurrently.', 'keyphrase_sources': [{'id': 'rootcause:race condition', 'keyphrase': 'race condition', 'type': 'rootcause'}, {'id': 'rootcause:wrong assumption that an endpoint is a fully assembled region', 'keyphrase': 'wrong assumption that an endpoint is a fully assembled region', 'type': 'rootcause'}, {'id': 'weakness:null pointer dereference', 'keyphrase': 'null pointer dereference', 'type': 'weakness'}, {'id': 'impact:kernel oops', 'keyphrase': 'kernel oops', 'type': 'impact'}, {'id': 'product:Linux kernel', 'keyphrase': 'Linux kernel', 'type': 'product'}, {'id': 'component:cxl/region', 'keyphrase': 'cxl/region', 'type': 'component'}]}, 'similarity': np.float64(972.5998177273964)}, {'metadata': {'doc_id': '476', 'name': 'NULL Pointer Dereference', 'source': 'sparse', 'original_content': 'The product dereferences a pointer that it expects to be valid but is NULL.', 'keyphrase_sources': [{'id': 'rootcause:race condition', 'keyphrase': 'race condition', 'type': 'rootcause'}, {'id': 'rootcause:wrong assumption that an endpoint is a fully assembled region', 'keyphrase': 'wrong assumption that an endpoint is a fully assembled region', 'type': 'rootcause'}, {'id': 'weakness:null pointer dereference', 'keyphrase': 'null pointer dereference', 'type': 'weakness'}, {'id': 'impact:kernel oops', 'keyphrase': 'kernel oops', 'type': 'impact'}, {'id': 'product:Linux kernel', 'keyphrase': 'Linux kernel', 'type': 'product'}, {'id': 'component:cxl/region', 'keyphrase': 'cxl/region', 'type': 'component'}]}, 'similarity': np.float64(969.6225996477124)}, {'metadata': {'doc_id': '367', 'name': 'Time-of-check Time-of-use (TOCTOU) Race Condition', 'source': 'sparse', 'original_content': \"The product checks the state of a resource before using that resource, but the resource's state can change between the check and the use in a way that invalidates the results of the check. This can cause the product to perform invalid actions when the resource is in an unexpected state.\", 'keyphrase_sources': [{'id': 'rootcause:race condition', 'keyphrase': 'race condition', 'type': 'rootcause'}]}, 'similarity': np.float64(938.6352242776663)}, {'metadata': {'doc_id': '667', 'name': 'Improper Locking', 'source': 'sparse', 'original_content': 'The product does not properly acquire or release a lock on a resource, leading to unexpected resource state changes and behaviors.', 'keyphrase_sources': [{'id': 'rootcause:race condition', 'keyphrase': 'race condition', 'type': 'rootcause'}, {'id': 'rootcause:wrong assumption that an endpoint is a fully assembled region', 'keyphrase': 'wrong assumption that an endpoint is a fully assembled region', 'type': 'rootcause'}, {'id': 'impact:kernel oops', 'keyphrase': 'kernel oops', 'type': 'impact'}, {'id': 'product:Linux kernel', 'keyphrase': 'Linux kernel', 'type': 'product'}, {'id': 'component:cxl/region', 'keyphrase': 'cxl/region', 'type': 'component'}]}, 'similarity': np.float64(937.9063851602962)}, {'metadata': {'doc_id': '1257', 'name': 'Improper Access Control Applied to Mirrored or Aliased Memory Regions', 'source': 'sparse', 'original_content': 'Aliased or mirrored memory regions in hardware designs may have inconsistent read/write permissions enforced by the hardware. A possible result is that an untrusted agent is blocked from accessing a memory region but is not blocked from accessing the corresponding aliased memory region.\\n\\t\\t\\t', 'keyphrase_sources': [{'id': 'rootcause:race condition', 'keyphrase': 'race condition', 'type': 'rootcause'}, {'id': 'rootcause:wrong assumption that an endpoint is a fully assembled region', 'keyphrase': 'wrong assumption that an endpoint is a fully assembled region', 'type': 'rootcause'}, {'id': 'impact:kernel oops', 'keyphrase': 'kernel oops', 'type': 'impact'}, {'id': 'product:Linux kernel', 'keyphrase': 'Linux kernel', 'type': 'product'}, {'id': 'component:cxl/region', 'keyphrase': 'cxl/region', 'type': 'component'}]}, 'similarity': np.float64(914.2980751741234)}, {'metadata': {'doc_id': '665', 'name': 'Improper Initialization', 'source': 'sparse', 'original_content': 'The product does not initialize or incorrectly initializes a resource, which might leave the resource in an unexpected state when it is accessed or used.', 'keyphrase_sources': [{'id': 'weakness:null pointer dereference', 'keyphrase': 'null pointer dereference', 'type': 'weakness'}]}, 'similarity': np.float64(882.6053589369687)}, {'metadata': {'doc_id': '822', 'name': 'Untrusted Pointer Dereference', 'source': 'sparse', 'original_content': 'The product obtains a value from an untrusted source, converts this value to a pointer, and dereferences the resulting pointer.', 'keyphrase_sources': [{'id': 'weakness:null pointer dereference', 'keyphrase': 'null pointer dereference', 'type': 'weakness'}]}, 'similarity': np.float64(873.6390352804843)}], identified_cwes={'analyzer': [], 'critic_additional': []})",
  "retrieval_results": {
    "has_multiple_keyphrases": true,
    "keyphrase_cwe_sets": {
      "rootcause:race condition": {
        "keyphrase": "race condition",
        "type": "rootcause",
        "cwes": [
          {
            "metadata": {
              "doc_id": "362",
              "name": "Concurrent Execution using Shared Resource with Improper Synchronization ('Race Condition')",
              "source": "sparse",
              "original_content": "The product contains a concurrent code sequence that requires temporary, exclusive access to a shared resource, but a timing window exists in which the shared resource can be modified by another code sequence operating concurrently.",
              "keyphrase_sources": [
                {
                  "id": "rootcause:race condition",
                  "keyphrase": "race condition",
                  "type": "rootcause"
                },
                {
                  "id": "rootcause:wrong assumption that an endpoint is a fully assembled region",
                  "keyphrase": "wrong assumption that an endpoint is a fully assembled region",
                  "type": "rootcause"
                },
                {
                  "id": "weakness:null pointer dereference",
                  "keyphrase": "null pointer dereference",
                  "type": "weakness"
                },
                {
                  "id": "impact:kernel oops",
                  "keyphrase": "kernel oops",
                  "type": "impact"
                },
                {
                  "id": "product:Linux kernel",
                  "keyphrase": "Linux kernel",
                  "type": "product"
                },
                {
                  "id": "component:cxl/region",
                  "keyphrase": "cxl/region",
                  "type": "component"
                }
              ]
            },
            "similarity": 972.5998177273964
          },
          {
            "metadata": {
              "doc_id": "476",
              "name": "NULL Pointer Dereference",
              "source": "sparse",
              "original_content": "The product dereferences a pointer that it expects to be valid but is NULL.",
              "keyphrase_sources": [
                {
                  "id": "rootcause:race condition",
                  "keyphrase": "race condition",
                  "type": "rootcause"
                },
                {
                  "id": "rootcause:wrong assumption that an endpoint is a fully assembled region",
                  "keyphrase": "wrong assumption that an endpoint is a fully assembled region",
                  "type": "rootcause"
                },
                {
                  "id": "weakness:null pointer dereference",
                  "keyphrase": "null pointer dereference",
                  "type": "weakness"
                },
                {
                  "id": "impact:kernel oops",
                  "keyphrase": "kernel oops",
                  "type": "impact"
                },
                {
                  "id": "product:Linux kernel",
                  "keyphrase": "Linux kernel",
                  "type": "product"
                },
                {
                  "id": "component:cxl/region",
                  "keyphrase": "cxl/region",
                  "type": "component"
                }
              ]
            },
            "similarity": 969.6225996477124
          },
          {
            "metadata": {
              "doc_id": "367",
              "name": "Time-of-check Time-of-use (TOCTOU) Race Condition",
              "source": "sparse",
              "original_content": "The product checks the state of a resource before using that resource, but the resource's state can change between the check and the use in a way that invalidates the results of the check. This can cause the product to perform invalid actions when the resource is in an unexpected state.",
              "keyphrase_sources": [
                {
                  "id": "rootcause:race condition",
                  "keyphrase": "race condition",
                  "type": "rootcause"
                }
              ]
            },
            "similarity": 938.6352242776663
          },
          {
            "metadata": {
              "doc_id": "667",
              "name": "Improper Locking",
              "source": "sparse",
              "original_content": "The product does not properly acquire or release a lock on a resource, leading to unexpected resource state changes and behaviors.",
              "keyphrase_sources": [
                {
                  "id": "rootcause:race condition",
                  "keyphrase": "race condition",
                  "type": "rootcause"
                },
                {
                  "id": "rootcause:wrong assumption that an endpoint is a fully assembled region",
                  "keyphrase": "wrong assumption that an endpoint is a fully assembled region",
                  "type": "rootcause"
                },
                {
                  "id": "impact:kernel oops",
                  "keyphrase": "kernel oops",
                  "type": "impact"
                },
                {
                  "id": "product:Linux kernel",
                  "keyphrase": "Linux kernel",
                  "type": "product"
                },
                {
                  "id": "component:cxl/region",
                  "keyphrase": "cxl/region",
                  "type": "component"
                }
              ]
            },
            "similarity": 937.9063851602962
          },
          {
            "metadata": {
              "doc_id": "1257",
              "name": "Improper Access Control Applied to Mirrored or Aliased Memory Regions",
              "source": "sparse",
              "original_content": "Aliased or mirrored memory regions in hardware designs may have inconsistent read/write permissions enforced by the hardware. A possible result is that an untrusted agent is blocked from accessing a memory region but is not blocked from accessing the corresponding aliased memory region.\n\t\t\t",
              "keyphrase_sources": [
                {
                  "id": "rootcause:race condition",
                  "keyphrase": "race condition",
                  "type": "rootcause"
                },
                {
                  "id": "rootcause:wrong assumption that an endpoint is a fully assembled region",
                  "keyphrase": "wrong assumption that an endpoint is a fully assembled region",
                  "type": "rootcause"
                },
                {
                  "id": "impact:kernel oops",
                  "keyphrase": "kernel oops",
                  "type": "impact"
                },
                {
                  "id": "product:Linux kernel",
                  "keyphrase": "Linux kernel",
                  "type": "product"
                },
                {
                  "id": "component:cxl/region",
                  "keyphrase": "cxl/region",
                  "type": "component"
                }
              ]
            },
            "similarity": 914.2980751741234
          }
        ]
      },
      "rootcause:wrong assumption that an endpoint is a fully assembled region": {
        "keyphrase": "wrong assumption that an endpoint is a fully assembled region",
        "type": "rootcause",
        "cwes": [
          {
            "metadata": {
              "doc_id": "1257",
              "name": "Improper Access Control Applied to Mirrored or Aliased Memory Regions",
              "source": "sparse",
              "original_content": "Aliased or mirrored memory regions in hardware designs may have inconsistent read/write permissions enforced by the hardware. A possible result is that an untrusted agent is blocked from accessing a memory region but is not blocked from accessing the corresponding aliased memory region.\n\t\t\t"
            },
            "similarity": 1046.548261490154
          },
          {
            "metadata": {
              "doc_id": "476",
              "name": "NULL Pointer Dereference",
              "source": "sparse",
              "original_content": "The product dereferences a pointer that it expects to be valid but is NULL."
            },
            "similarity": 1043.3822992372445
          },
          {
            "metadata": {
              "doc_id": "362",
              "name": "Concurrent Execution using Shared Resource with Improper Synchronization ('Race Condition')",
              "source": "sparse",
              "original_content": "The product contains a concurrent code sequence that requires temporary, exclusive access to a shared resource, but a timing window exists in which the shared resource can be modified by another code sequence operating concurrently."
            },
            "similarity": 992.9928169641563
          },
          {
            "metadata": {
              "doc_id": "252",
              "name": "Unchecked Return Value",
              "source": "sparse",
              "original_content": "The product does not check the return value from a method or function, which can prevent it from detecting unexpected states and conditions.",
              "keyphrase_sources": [
                {
                  "id": "rootcause:wrong assumption that an endpoint is a fully assembled region",
                  "keyphrase": "wrong assumption that an endpoint is a fully assembled region",
                  "type": "rootcause"
                },
                {
                  "id": "weakness:null pointer dereference",
                  "keyphrase": "null pointer dereference",
                  "type": "weakness"
                },
                {
                  "id": "impact:kernel oops",
                  "keyphrase": "kernel oops",
                  "type": "impact"
                },
                {
                  "id": "product:Linux kernel",
                  "keyphrase": "Linux kernel",
                  "type": "product"
                },
                {
                  "id": "component:cxl/region",
                  "keyphrase": "cxl/region",
                  "type": "component"
                }
              ]
            },
            "similarity": 979.3707259233393
          },
          {
            "metadata": {
              "doc_id": "667",
              "name": "Improper Locking",
              "source": "sparse",
              "original_content": "The product does not properly acquire or release a lock on a resource, leading to unexpected resource state changes and behaviors."
            },
            "similarity": 974.8199569878798
          }
        ]
      },
      "weakness:null pointer dereference": {
        "keyphrase": "null pointer dereference",
        "type": "weakness",
        "cwes": [
          {
            "metadata": {
              "doc_id": "476",
              "name": "NULL Pointer Dereference",
              "source": "sparse",
              "original_content": "The product dereferences a pointer that it expects to be valid but is NULL."
            },
            "similarity": 985.4896123246888
          },
          {
            "metadata": {
              "doc_id": "252",
              "name": "Unchecked Return Value",
              "source": "sparse",
              "original_content": "The product does not check the return value from a method or function, which can prevent it from detecting unexpected states and conditions."
            },
            "similarity": 933.2876139293091
          },
          {
            "metadata": {
              "doc_id": "665",
              "name": "Improper Initialization",
              "source": "sparse",
              "original_content": "The product does not initialize or incorrectly initializes a resource, which might leave the resource in an unexpected state when it is accessed or used.",
              "keyphrase_sources": [
                {
                  "id": "weakness:null pointer dereference",
                  "keyphrase": "null pointer dereference",
                  "type": "weakness"
                }
              ]
            },
            "similarity": 882.6053589369687
          },
          {
            "metadata": {
              "doc_id": "362",
              "name": "Concurrent Execution using Shared Resource with Improper Synchronization ('Race Condition')",
              "source": "sparse",
              "original_content": "The product contains a concurrent code sequence that requires temporary, exclusive access to a shared resource, but a timing window exists in which the shared resource can be modified by another code sequence operating concurrently."
            },
            "similarity": 880.5408801864512
          },
          {
            "metadata": {
              "doc_id": "822",
              "name": "Untrusted Pointer Dereference",
              "source": "sparse",
              "original_content": "The product obtains a value from an untrusted source, converts this value to a pointer, and dereferences the resulting pointer.",
              "keyphrase_sources": [
                {
                  "id": "weakness:null pointer dereference",
                  "keyphrase": "null pointer dereference",
                  "type": "weakness"
                }
              ]
            },
            "similarity": 873.6390352804843
          }
        ]
      },
      "impact:kernel oops": {
        "keyphrase": "kernel oops",
        "type": "impact",
        "cwes": [
          {
            "metadata": {
              "doc_id": "476",
              "name": "NULL Pointer Dereference",
              "source": "sparse",
              "original_content": "The product dereferences a pointer that it expects to be valid but is NULL."
            },
            "similarity": 317.8658875268953
          },
          {
            "metadata": {
              "doc_id": "362",
              "name": "Concurrent Execution using Shared Resource with Improper Synchronization ('Race Condition')",
              "source": "sparse",
              "original_content": "The product contains a concurrent code sequence that requires temporary, exclusive access to a shared resource, but a timing window exists in which the shared resource can be modified by another code sequence operating concurrently."
            },
            "similarity": 311.09941572494347
          },
          {
            "metadata": {
              "doc_id": "667",
              "name": "Improper Locking",
              "source": "sparse",
              "original_content": "The product does not properly acquire or release a lock on a resource, leading to unexpected resource state changes and behaviors."
            },
            "similarity": 304.9737644352494
          },
          {
            "metadata": {
              "doc_id": "1257",
              "name": "Improper Access Control Applied to Mirrored or Aliased Memory Regions",
              "source": "sparse",
              "original_content": "Aliased or mirrored memory regions in hardware designs may have inconsistent read/write permissions enforced by the hardware. A possible result is that an untrusted agent is blocked from accessing a memory region but is not blocked from accessing the corresponding aliased memory region.\n\t\t\t"
            },
            "similarity": 304.7660250580411
          },
          {
            "metadata": {
              "doc_id": "252",
              "name": "Unchecked Return Value",
              "source": "sparse",
              "original_content": "The product does not check the return value from a method or function, which can prevent it from detecting unexpected states and conditions."
            },
            "similarity": 300.8652106997876
          }
        ]
      },
      "product:Linux kernel": {
        "keyphrase": "Linux kernel",
        "type": "product",
        "cwes": [
          {
            "metadata": {
              "doc_id": "476",
              "name": "NULL Pointer Dereference",
              "source": "sparse",
              "original_content": "The product dereferences a pointer that it expects to be valid but is NULL."
            },
            "similarity": 322.34101421436714
          },
          {
            "metadata": {
              "doc_id": "362",
              "name": "Concurrent Execution using Shared Resource with Improper Synchronization ('Race Condition')",
              "source": "sparse",
              "original_content": "The product contains a concurrent code sequence that requires temporary, exclusive access to a shared resource, but a timing window exists in which the shared resource can be modified by another code sequence operating concurrently."
            },
            "similarity": 318.5318537674747
          },
          {
            "metadata": {
              "doc_id": "667",
              "name": "Improper Locking",
              "source": "sparse",
              "original_content": "The product does not properly acquire or release a lock on a resource, leading to unexpected resource state changes and behaviors."
            },
            "similarity": 310.2436674171865
          },
          {
            "metadata": {
              "doc_id": "252",
              "name": "Unchecked Return Value",
              "source": "sparse",
              "original_content": "The product does not check the return value from a method or function, which can prevent it from detecting unexpected states and conditions."
            },
            "similarity": 306.048911148523
          },
          {
            "metadata": {
              "doc_id": "1257",
              "name": "Improper Access Control Applied to Mirrored or Aliased Memory Regions",
              "source": "sparse",
              "original_content": "Aliased or mirrored memory regions in hardware designs may have inconsistent read/write permissions enforced by the hardware. A possible result is that an untrusted agent is blocked from accessing a memory region but is not blocked from accessing the corresponding aliased memory region.\n\t\t\t"
            },
            "similarity": 304.7660250580411
          }
        ]
      },
      "component:cxl/region": {
        "keyphrase": "cxl/region",
        "type": "component",
        "cwes": [
          {
            "metadata": {
              "doc_id": "1257",
              "name": "Improper Access Control Applied to Mirrored or Aliased Memory Regions",
              "source": "sparse",
              "original_content": "Aliased or mirrored memory regions in hardware designs may have inconsistent read/write permissions enforced by the hardware. A possible result is that an untrusted agent is blocked from accessing a memory region but is not blocked from accessing the corresponding aliased memory region.\n\t\t\t"
            },
            "similarity": 322.34295122605204
          },
          {
            "metadata": {
              "doc_id": "476",
              "name": "NULL Pointer Dereference",
              "source": "sparse",
              "original_content": "The product dereferences a pointer that it expects to be valid but is NULL."
            },
            "similarity": 312.42235907554397
          },
          {
            "metadata": {
              "doc_id": "362",
              "name": "Concurrent Execution using Shared Resource with Improper Synchronization ('Race Condition')",
              "source": "sparse",
              "original_content": "The product contains a concurrent code sequence that requires temporary, exclusive access to a shared resource, but a timing window exists in which the shared resource can be modified by another code sequence operating concurrently."
            },
            "similarity": 303.5847165427342
          },
          {
            "metadata": {
              "doc_id": "252",
              "name": "Unchecked Return Value",
              "source": "sparse",
              "original_content": "The product does not check the return value from a method or function, which can prevent it from detecting unexpected states and conditions."
            },
            "similarity": 300.8652106997876
          },
          {
            "metadata": {
              "doc_id": "667",
              "name": "Improper Locking",
              "source": "sparse",
              "original_content": "The product does not properly acquire or release a lock on a resource, leading to unexpected resource state changes and behaviors."
            },
            "similarity": 295.92297127446324
          }
        ]
      }
    },
    "keyphrase_mapping": {
      "362": [
        {
          "id": "rootcause:race condition",
          "keyphrase": "race condition",
          "type": "rootcause"
        },
        {
          "id": "rootcause:wrong assumption that an endpoint is a fully assembled region",
          "keyphrase": "wrong assumption that an endpoint is a fully assembled region",
          "type": "rootcause"
        },
        {
          "id": "weakness:null pointer dereference",
          "keyphrase": "null pointer dereference",
          "type": "weakness"
        },
        {
          "id": "impact:kernel oops",
          "keyphrase": "kernel oops",
          "type": "impact"
        },
        {
          "id": "product:Linux kernel",
          "keyphrase": "Linux kernel",
          "type": "product"
        },
        {
          "id": "component:cxl/region",
          "keyphrase": "cxl/region",
          "type": "component"
        }
      ],
      "476": [
        {
          "id": "rootcause:race condition",
          "keyphrase": "race condition",
          "type": "rootcause"
        },
        {
          "id": "rootcause:wrong assumption that an endpoint is a fully assembled region",
          "keyphrase": "wrong assumption that an endpoint is a fully assembled region",
          "type": "rootcause"
        },
        {
          "id": "weakness:null pointer dereference",
          "keyphrase": "null pointer dereference",
          "type": "weakness"
        },
        {
          "id": "impact:kernel oops",
          "keyphrase": "kernel oops",
          "type": "impact"
        },
        {
          "id": "product:Linux kernel",
          "keyphrase": "Linux kernel",
          "type": "product"
        },
        {
          "id": "component:cxl/region",
          "keyphrase": "cxl/region",
          "type": "component"
        }
      ],
      "367": [
        {
          "id": "rootcause:race condition",
          "keyphrase": "race condition",
          "type": "rootcause"
        }
      ],
      "667": [
        {
          "id": "rootcause:race condition",
          "keyphrase": "race condition",
          "type": "rootcause"
        },
        {
          "id": "rootcause:wrong assumption that an endpoint is a fully assembled region",
          "keyphrase": "wrong assumption that an endpoint is a fully assembled region",
          "type": "rootcause"
        },
        {
          "id": "impact:kernel oops",
          "keyphrase": "kernel oops",
          "type": "impact"
        },
        {
          "id": "product:Linux kernel",
          "keyphrase": "Linux kernel",
          "type": "product"
        },
        {
          "id": "component:cxl/region",
          "keyphrase": "cxl/region",
          "type": "component"
        }
      ],
      "1257": [
        {
          "id": "rootcause:race condition",
          "keyphrase": "race condition",
          "type": "rootcause"
        },
        {
          "id": "rootcause:wrong assumption that an endpoint is a fully assembled region",
          "keyphrase": "wrong assumption that an endpoint is a fully assembled region",
          "type": "rootcause"
        },
        {
          "id": "impact:kernel oops",
          "keyphrase": "kernel oops",
          "type": "impact"
        },
        {
          "id": "product:Linux kernel",
          "keyphrase": "Linux kernel",
          "type": "product"
        },
        {
          "id": "component:cxl/region",
          "keyphrase": "cxl/region",
          "type": "component"
        }
      ],
      "252": [
        {
          "id": "rootcause:wrong assumption that an endpoint is a fully assembled region",
          "keyphrase": "wrong assumption that an endpoint is a fully assembled region",
          "type": "rootcause"
        },
        {
          "id": "weakness:null pointer dereference",
          "keyphrase": "null pointer dereference",
          "type": "weakness"
        },
        {
          "id": "impact:kernel oops",
          "keyphrase": "kernel oops",
          "type": "impact"
        },
        {
          "id": "product:Linux kernel",
          "keyphrase": "Linux kernel",
          "type": "product"
        },
        {
          "id": "component:cxl/region",
          "keyphrase": "cxl/region",
          "type": "component"
        }
      ],
      "665": [
        {
          "id": "weakness:null pointer dereference",
          "keyphrase": "null pointer dereference",
          "type": "weakness"
        }
      ],
      "822": [
        {
          "id": "weakness:null pointer dereference",
          "keyphrase": "null pointer dereference",
          "type": "weakness"
        }
      ]
    },
    "relevant_cwes": [
      {
        "metadata": {
          "doc_id": "252",
          "name": "Unchecked Return Value",
          "source": "sparse",
          "original_content": "The product does not check the return value from a method or function, which can prevent it from detecting unexpected states and conditions.",
          "keyphrase_sources": [
            {
              "id": "rootcause:wrong assumption that an endpoint is a fully assembled region",
              "keyphrase": "wrong assumption that an endpoint is a fully assembled region",
              "type": "rootcause"
            },
            {
              "id": "weakness:null pointer dereference",
              "keyphrase": "null pointer dereference",
              "type": "weakness"
            },
            {
              "id": "impact:kernel oops",
              "keyphrase": "kernel oops",
              "type": "impact"
            },
            {
              "id": "product:Linux kernel",
              "keyphrase": "Linux kernel",
              "type": "product"
            },
            {
              "id": "component:cxl/region",
              "keyphrase": "cxl/region",
              "type": "component"
            }
          ]
        },
        "similarity": 979.3707259233393
      },
      {
        "metadata": {
          "doc_id": "362",
          "name": "Concurrent Execution using Shared Resource with Improper Synchronization ('Race Condition')",
          "source": "sparse",
          "original_content": "The product contains a concurrent code sequence that requires temporary, exclusive access to a shared resource, but a timing window exists in which the shared resource can be modified by another code sequence operating concurrently.",
          "keyphrase_sources": [
            {
              "id": "rootcause:race condition",
              "keyphrase": "race condition",
              "type": "rootcause"
            },
            {
              "id": "rootcause:wrong assumption that an endpoint is a fully assembled region",
              "keyphrase": "wrong assumption that an endpoint is a fully assembled region",
              "type": "rootcause"
            },
            {
              "id": "weakness:null pointer dereference",
              "keyphrase": "null pointer dereference",
              "type": "weakness"
            },
            {
              "id": "impact:kernel oops",
              "keyphrase": "kernel oops",
              "type": "impact"
            },
            {
              "id": "product:Linux kernel",
              "keyphrase": "Linux kernel",
              "type": "product"
            },
            {
              "id": "component:cxl/region",
              "keyphrase": "cxl/region",
              "type": "component"
            }
          ]
        },
        "similarity": 972.5998177273964
      },
      {
        "metadata": {
          "doc_id": "476",
          "name": "NULL Pointer Dereference",
          "source": "sparse",
          "original_content": "The product dereferences a pointer that it expects to be valid but is NULL.",
          "keyphrase_sources": [
            {
              "id": "rootcause:race condition",
              "keyphrase": "race condition",
              "type": "rootcause"
            },
            {
              "id": "rootcause:wrong assumption that an endpoint is a fully assembled region",
              "keyphrase": "wrong assumption that an endpoint is a fully assembled region",
              "type": "rootcause"
            },
            {
              "id": "weakness:null pointer dereference",
              "keyphrase": "null pointer dereference",
              "type": "weakness"
            },
            {
              "id": "impact:kernel oops",
              "keyphrase": "kernel oops",
              "type": "impact"
            },
            {
              "id": "product:Linux kernel",
              "keyphrase": "Linux kernel",
              "type": "product"
            },
            {
              "id": "component:cxl/region",
              "keyphrase": "cxl/region",
              "type": "component"
            }
          ]
        },
        "similarity": 969.6225996477124
      },
      {
        "metadata": {
          "doc_id": "367",
          "name": "Time-of-check Time-of-use (TOCTOU) Race Condition",
          "source": "sparse",
          "original_content": "The product checks the state of a resource before using that resource, but the resource's state can change between the check and the use in a way that invalidates the results of the check. This can cause the product to perform invalid actions when the resource is in an unexpected state.",
          "keyphrase_sources": [
            {
              "id": "rootcause:race condition",
              "keyphrase": "race condition",
              "type": "rootcause"
            }
          ]
        },
        "similarity": 938.6352242776663
      },
      {
        "metadata": {
          "doc_id": "667",
          "name": "Improper Locking",
          "source": "sparse",
          "original_content": "The product does not properly acquire or release a lock on a resource, leading to unexpected resource state changes and behaviors.",
          "keyphrase_sources": [
            {
              "id": "rootcause:race condition",
              "keyphrase": "race condition",
              "type": "rootcause"
            },
            {
              "id": "rootcause:wrong assumption that an endpoint is a fully assembled region",
              "keyphrase": "wrong assumption that an endpoint is a fully assembled region",
              "type": "rootcause"
            },
            {
              "id": "impact:kernel oops",
              "keyphrase": "kernel oops",
              "type": "impact"
            },
            {
              "id": "product:Linux kernel",
              "keyphrase": "Linux kernel",
              "type": "product"
            },
            {
              "id": "component:cxl/region",
              "keyphrase": "cxl/region",
              "type": "component"
            }
          ]
        },
        "similarity": 937.9063851602962
      },
      {
        "metadata": {
          "doc_id": "1257",
          "name": "Improper Access Control Applied to Mirrored or Aliased Memory Regions",
          "source": "sparse",
          "original_content": "Aliased or mirrored memory regions in hardware designs may have inconsistent read/write permissions enforced by the hardware. A possible result is that an untrusted agent is blocked from accessing a memory region but is not blocked from accessing the corresponding aliased memory region.\n\t\t\t",
          "keyphrase_sources": [
            {
              "id": "rootcause:race condition",
              "keyphrase": "race condition",
              "type": "rootcause"
            },
            {
              "id": "rootcause:wrong assumption that an endpoint is a fully assembled region",
              "keyphrase": "wrong assumption that an endpoint is a fully assembled region",
              "type": "rootcause"
            },
            {
              "id": "impact:kernel oops",
              "keyphrase": "kernel oops",
              "type": "impact"
            },
            {
              "id": "product:Linux kernel",
              "keyphrase": "Linux kernel",
              "type": "product"
            },
            {
              "id": "component:cxl/region",
              "keyphrase": "cxl/region",
              "type": "component"
            }
          ]
        },
        "similarity": 914.2980751741234
      },
      {
        "metadata": {
          "doc_id": "665",
          "name": "Improper Initialization",
          "source": "sparse",
          "original_content": "The product does not initialize or incorrectly initializes a resource, which might leave the resource in an unexpected state when it is accessed or used.",
          "keyphrase_sources": [
            {
              "id": "weakness:null pointer dereference",
              "keyphrase": "null pointer dereference",
              "type": "weakness"
            }
          ]
        },
        "similarity": 882.6053589369687
      },
      {
        "metadata": {
          "doc_id": "822",
          "name": "Untrusted Pointer Dereference",
          "source": "sparse",
          "original_content": "The product obtains a value from an untrusted source, converts this value to a pointer, and dereferences the resulting pointer.",
          "keyphrase_sources": [
            {
              "id": "weakness:null pointer dereference",
              "keyphrase": "null pointer dereference",
              "type": "weakness"
            }
          ]
        },
        "similarity": 873.6390352804843
      }
    ],
    "enhanced_query": "# Vulnerability Description\n\n    In the Linux kernel, the following vulnerability has been resolved cxl/region Avoid **null pointer dereference** in region lookup cxl_dpa_to_region() looks up a region based on a memdev and DPA. It wrongly assumes an endpoint found mapping the DPA is also of a fully assembled region. When not true it leads to a **null pointer dereference** looking up the region name. This appears during testing of region lookup after a failure to assemble a BIOS defined region or if the lookup raced with the assembly of the BIOS defined region. Failure to clean up BIOS defined regions that fail assembly is an issue in itself and a fix to that problem will alleviate some of the impact. It will not alleviate the **race condition** so lets harden this path. The behavior change is that the kernel oops due to a **null pointer dereference** is replaced with a dev_dbg() message noting that an endpoint was mapped. Additional comments are added so that future users of this function can more clearly understand what it provides.\n\n    # Keyphrase-Specific CWE Analysis\n    This vulnerability contains multiple keyphrases that may map to different CWEs. \n    Please analyze each keyphrase separately and determine the most appropriate CWE(s) for each.\n\n    ## ROOTCAUSE: 'wrong assumption that an endpoint is a fully assembled region'\n\nRelevant CWEs for this ROOTCAUSE:\n\n### 1. CWE-252: Unchecked Return Value (Score: 979.37)\n\nThe product does not check the return value from a method or function, which can prevent it from detecting unexpected states and conditions....\n\n### 2. CWE-362: Concurrent Execution using Shared Resource with Improper Synchronization ('Race Condition') (Score: 972.60)\n\nThe product contains a concurrent code sequence that requires temporary, exclusive access to a shared resource, but a timing window exists in which the shared resource can be modified by another code sequence operating concurrently....\n\n### 3. CWE-476: NULL Pointer Dereference (Score: 969.62)\n\nThe product dereferences a pointer that it expects to be valid but is NULL....\n\n### 4. CWE-667: Improper Locking (Score: 937.91)\n\nThe product does not properly acquire or release a lock on a resource, leading to unexpected resource state changes and behaviors....\n\n### 5. CWE-1257: Improper Access Control Applied to Mirrored or Aliased Memory Regions (Score: 914.30)\n\nAliased or mirrored memory regions in hardware designs may have inconsistent read/write permissions enforced by the hardware. A possible result is that an untrusted agent is blocked from accessing a memory region but is not blocked from accessing the corresponding aliased memory region.\n\t\t\t...\n\n## WEAKNESS: 'null pointer dereference'\n\nRelevant CWEs for this WEAKNESS:\n\n### 1. CWE-252: Unchecked Return Value (Score: 979.37)\n\nThe product does not check the return value from a method or function, which can prevent it from detecting unexpected states and conditions....\n\n### 2. CWE-362: Concurrent Execution using Shared Resource with Improper Synchronization ('Race Condition') (Score: 972.60)\n\nThe product contains a concurrent code sequence that requires temporary, exclusive access to a shared resource, but a timing window exists in which the shared resource can be modified by another code sequence operating concurrently....\n\n### 3. CWE-476: NULL Pointer Dereference (Score: 969.62)\n\nThe product dereferences a pointer that it expects to be valid but is NULL....\n\n### 4. CWE-665: Improper Initialization (Score: 882.61)\n\nThe product does not initialize or incorrectly initializes a resource, which might leave the resource in an unexpected state when it is accessed or used....\n\n### 5. CWE-822: Untrusted Pointer Dereference (Score: 873.64)\n\nThe product obtains a value from an untrusted source, converts this value to a pointer, and dereferences the resulting pointer....\n\n## IMPACT: 'kernel oops'\n\nRelevant CWEs for this IMPACT:\n\n### 1. CWE-252: Unchecked Return Value (Score: 979.37)\n\nThe product does not check the return value from a method or function, which can prevent it from detecting unexpected states and conditions....\n\n### 2. CWE-362: Concurrent Execution using Shared Resource with Improper Synchronization ('Race Condition') (Score: 972.60)\n\nThe product contains a concurrent code sequence that requires temporary, exclusive access to a shared resource, but a timing window exists in which the shared resource can be modified by another code sequence operating concurrently....\n\n### 3. CWE-476: NULL Pointer Dereference (Score: 969.62)\n\nThe product dereferences a pointer that it expects to be valid but is NULL....\n\n### 4. CWE-667: Improper Locking (Score: 937.91)\n\nThe product does not properly acquire or release a lock on a resource, leading to unexpected resource state changes and behaviors....\n\n### 5. CWE-1257: Improper Access Control Applied to Mirrored or Aliased Memory Regions (Score: 914.30)\n\nAliased or mirrored memory regions in hardware designs may have inconsistent read/write permissions enforced by the hardware. A possible result is that an untrusted agent is blocked from accessing a memory region but is not blocked from accessing the corresponding aliased memory region.\n\t\t\t...\n\n## PRODUCT: 'Linux kernel'\n\nRelevant CWEs for this PRODUCT:\n\n### 1. CWE-252: Unchecked Return Value (Score: 979.37)\n\nThe product does not check the return value from a method or function, which can prevent it from detecting unexpected states and conditions....\n\n### 2. CWE-362: Concurrent Execution using Shared Resource with Improper Synchronization ('Race Condition') (Score: 972.60)\n\nThe product contains a concurrent code sequence that requires temporary, exclusive access to a shared resource, but a timing window exists in which the shared resource can be modified by another code sequence operating concurrently....\n\n### 3. CWE-476: NULL Pointer Dereference (Score: 969.62)\n\nThe product dereferences a pointer that it expects to be valid but is NULL....\n\n### 4. CWE-667: Improper Locking (Score: 937.91)\n\nThe product does not properly acquire or release a lock on a resource, leading to unexpected resource state changes and behaviors....\n\n### 5. CWE-1257: Improper Access Control Applied to Mirrored or Aliased Memory Regions (Score: 914.30)\n\nAliased or mirrored memory regions in hardware designs may have inconsistent read/write permissions enforced by the hardware. A possible result is that an untrusted agent is blocked from accessing a memory region but is not blocked from accessing the corresponding aliased memory region.\n\t\t\t...\n\n## COMPONENT: 'cxl/region'\n\nRelevant CWEs for this COMPONENT:\n\n### 1. CWE-252: Unchecked Return Value (Score: 979.37)\n\nThe product does not check the return value from a method or function, which can prevent it from detecting unexpected states and conditions....\n\n### 2. CWE-362: Concurrent Execution using Shared Resource with Improper Synchronization ('Race Condition') (Score: 972.60)\n\nThe product contains a concurrent code sequence that requires temporary, exclusive access to a shared resource, but a timing window exists in which the shared resource can be modified by another code sequence operating concurrently....\n\n### 3. CWE-476: NULL Pointer Dereference (Score: 969.62)\n\nThe product dereferences a pointer that it expects to be valid but is NULL....\n\n### 4. CWE-667: Improper Locking (Score: 937.91)\n\nThe product does not properly acquire or release a lock on a resource, leading to unexpected resource state changes and behaviors....\n\n### 5. CWE-1257: Improper Access Control Applied to Mirrored or Aliased Memory Regions (Score: 914.30)\n\nAliased or mirrored memory regions in hardware designs may have inconsistent read/write permissions enforced by the hardware. A possible result is that an untrusted agent is blocked from accessing a memory region but is not blocked from accessing the corresponding aliased memory region.\n\t\t\t...\n\n## ROOTCAUSE: 'race condition'\n\nRelevant CWEs for this ROOTCAUSE:\n\n### 1. CWE-362: Concurrent Execution using Shared Resource with Improper Synchronization ('Race Condition') (Score: 972.60)\n\nThe product contains a concurrent code sequence that requires temporary, exclusive access to a shared resource, but a timing window exists in which the shared resource can be modified by another code sequence operating concurrently....\n\n### 2. CWE-476: NULL Pointer Dereference (Score: 969.62)\n\nThe product dereferences a pointer that it expects to be valid but is NULL....\n\n### 3. CWE-367: Time-of-check Time-of-use (TOCTOU) Race Condition (Score: 938.64)\n\nThe product checks the state of a resource before using that resource, but the resource's state can change between the check and the use in a way that invalidates the results of the check. This can cause the product to perform invalid actions when the resource is in an unexpected state....\n\n### 4. CWE-667: Improper Locking (Score: 937.91)\n\nThe product does not properly acquire or release a lock on a resource, leading to unexpected resource state changes and behaviors....\n\n### 5. CWE-1257: Improper Access Control Applied to Mirrored or Aliased Memory Regions (Score: 914.30)\n\nAliased or mirrored memory regions in hardware designs may have inconsistent read/write permissions enforced by the hardware. A possible result is that an untrusted agent is blocked from accessing a memory region but is not blocked from accessing the corresponding aliased memory region.\n\t\t\t...\n\n\n    # Analysis Instructions\n    1. For each keyphrase, identify the most appropriate CWE(s) that represent the weakness.\n    2. Consider how the different keyphrases might relate to each other in the vulnerability chain.\n    3. Provide a final determination of primary CWE(s) and any secondary CWEs.\n    4. Format your response using the standard analysis template.\n\n    Please analyze how these different weaknesses interact and provide a comprehensive CWE classification.\n    "
  },
  "retrieval_time": 1.7335243225097656
}