{
  "cve_id": "CVE-2024-40462",
  "description": "An issue in Ocuco Innovation v.2.10.24.51 allows a local attacker to escalate privileges via the SETTINGSVATIGATOR.EXE component",
  "key_phrases": {
    "rootcause": "",
    "weakness": "",
    "impact": "escalate privileges",
    "vector": "",
    "attacker": "local attacker",
    "product": "Ocuco Innovation",
    "version": "v.2.10.24.51",
    "component": "SETTINGSVATIGATOR.EXE component"
  },
  "reference_content": "CVE-2024-40462 relates to Ocuco Innovation software. The provided content details multiple vulnerabilities across various executables within the Ocuco Innovation suite. The first entry specifically addresses CVE-2024-40462. Here's the extracted information:\n\n**Root cause of vulnerability:**\nThe vulnerability lies in the lack of proper authentication checks when intercepting and modifying TCP packets.\n\n**Weaknesses/vulnerabilities present:**\n*   Privilege escalation to Administrator.\n*   Insufficient authentication.\n*   TCP packet manipulation vulnerability.\n\n**Impact of exploitation:**\n*   Unauthorized users can gain administrative access.\n*   Compromised security and integrity of the system.\n*   Data integrity issues (alteration, deletion, manipulation).\n*   Operational risks (downtime, data loss).\n*   Regulatory compliance violations.\n*   Reputation damage.\n\n**Attack vectors:**\n*   Intercepting and modifying TCP packets during the login process.\n*   Manipulating bytes within the TCP packet (specifically to whitespace \"20\" in hex).\n\n**Required attacker capabilities/position:**\n*   Ability to intercept and modify network traffic (TCP packets).\n*   Understanding of the software's network communication.\n\n**Mitigation or fix:**\n*   Patch the vulnerability (zero-day, so a patch is needed).\n*   Restrict network access to authorized users only.\n*   Enhance authentication mechanisms.\n*   Use encrypted communication channels (packet encryption).\n*   Regular security audits.\n*   User training on security practices.\n*   Strict access controls.\n*   Incident response plan.\n\n**Proof-of-Concept (PoC):**\n\n1.  Requires the \"Settings Navigator\" (SETTINGSVATIGATOR.EXE) software.\n2.  Intercept TCP packets.\n3.  Modify the intercepted TCP packet by changing bytes to whitespace (\"20\" in hex).\n4.  An access violation error occurs (VCRUNTIME140.dll).\n5.  The software allows login without privileged accounts.\n6.  Create a new administrative user (e.g., \"PENTESTPE\").\n7.  Successfully log in with the new user, gaining administrator privileges.\n\n**Additional Notes:**\n\nThe document details *nine* additional CVEs (CVE-2024-40458, CVE-2024-40459, CVE-2024-40460, CVE-2024-40461, CVE-2024-41195, CVE-2024-41196, CVE-2024-41197, CVE-2024-41198, CVE-2024-41199) all exhibiting similar vulnerabilities within different Ocuco Innovation executables. They all involve intercepting and modifying TCP packets to bypass authentication and gain administrative access. The PoC steps are largely consistent across these CVEs, involving packet manipulation and resulting in access violations followed by unauthorized administrative access.\n\nThe content provides significantly more detail than a typical CVE description, including a detailed PoC.",
  "similar_info": {
    "cwe_distribution": {},
    "cwe_consensus": "",
    "similarity_stats": {
      "thresholds": [],
      "total_samples_by_threshold": {},
      "top_cwes_by_threshold": {}
    }
  },
  "similarity_summary": {
    "consensus_cwe": "",
    "top_cwes": [],
    "confidence_levels": {},
    "total_samples": 0
  },
  "analysis": "# Summary\n| CWE ID | CWE Name | Confidence | CWE Abstraction Level | CWE Vulnerability Mapping Label | CWE-Vulnerability Mapping Notes |\n|---|---|---|---|---|---|\n| CWE-306 | Missing Authentication for Critical Function | 0.9 | Base | Allowed | Primary CWE |\n| CWE-863 | Incorrect Authorization | 0.7 | Class | Allowed-with-Review | Secondary Candidate |\n| CWE-266 | Incorrect Privilege Assignment | 0.6 | Base | Allowed | Secondary Candidate |\n\n## Evidence and Confidence\n\n*   **Confidence Score:** 0.8\n*   **Evidence Strength:** HIGH\n\n## Relationship Analysis\nThe primary CWE is CWE-306 (Missing Authentication for Critical Function), which is a base-level CWE. CWE-306 is a child of CWE-287 (Improper Authentication) at the class level. CWE-863 (Incorrect Authorization) and CWE-266 (Incorrect Privilege Assignment) are considered as secondary candidates because the vulnerability also involves incorrect authorization/privilege assignment due to the missing authentication. CWE-863 is a class-level CWE, and CWE-266 is a base-level CWE.\n\n```mermaid\ngraph TD\n    cwe306[\"CWE-306: Missing Authentication for Critical Function\"]\n    cwe287[\"CWE-287: Improper Authentication\"]\n    cwe863[\"CWE-863: Incorrect Authorization\"]\n    cwe266[\"CWE-266: Incorrect Privilege Assignment\"]\n\n    cwe306 -->|CHILDOF| cwe287\n    cwe863 -->|PEEROF| cwe306\n    cwe266 -->|PEEROF| cwe306\n\n    classDef primary fill:#f96,stroke:#333,stroke-width:2px\n    classDef secondary fill:#69f,stroke:#333\n    classDef tertiary fill:#9e9,stroke:#333\n    class cwe306 primary\n    class cwe863,cwe266 secondary\n    class cwe287 tertiary\n```\n\n## Vulnerability Chain\nThe vulnerability chain starts with **missing authentication (CWE-306)**, leading to **incorrect authorization (CWE-863)**, and ultimately resulting in **privilege escalation (CWE-266)**. The **lack of proper authentication** allows attackers to bypass security checks and gain administrative privileges.\n  - **CWE-306**: Missing Authentication for Critical Function (Root Cause)\n  - **CWE-863**: Incorrect Authorization (Intermediate Weakness)\n  - **CWE-266**: Incorrect Privilege Assignment (Impact)\n\n## Summary of Analysis\nThe initial assessment focused on privilege escalation as the primary impact. However, after analyzing the CVE reference and considering the retriever results, it became clear that the root cause is the **lack of proper authentication**. The vulnerability allows attackers to bypass authentication checks by manipulating TCP packets, leading to unauthorized administrative access.\nThe selection of CWE-306 is based on the evidence of **insufficient authentication** checks when intercepting and modifying TCP packets. This aligns with the CWE description of \"Missing Authentication for Critical Function.\" The retriever results also listed CWE-306, supporting this selection.\nCWE-863 (Incorrect Authorization) and CWE-266 (Incorrect Privilege Assignment) were considered as secondary candidates because the ultimate impact is privilege escalation. However, they are consequences of the **missing authentication** and not the primary cause.\nThe selected CWEs are at the optimal level of specificity. CWE-306 is a base-level CWE that accurately represents the **missing authentication** vulnerability. CWE-863 and CWE-266 are also at appropriate levels, representing the related authorization and privilege assignment issues. The \"Privileges vs Permissions Guidance\" section also indicates that escalation is a result of a misconfigured role, permission not dropped, or role-check bypass.\n\nRelevant CWE Information:\n- Vulnerability Description: \"An issue in Ocuco Innovation v.2.10.24.51 allows a local attacker to escalate privileges via the SETTINGSVATIGATOR.EXE component\"\n- CVE Reference Links Content Summary: \"The vulnerability lies in the **lack of proper authentication** checks when intercepting and modifying TCP packets.\"\n\n---\nHere's the breakdown of why each CWE was chosen or not:\n\n*   **CWE-306: Missing Authentication for Critical Function** - **Chosen as Primary CWE**. The root cause of the vulnerability is the **lack of proper authentication** checks when intercepting and modifying TCP packets. This allows attackers to bypass security and gain administrative privileges. The evidence is: \"The vulnerability lies in the **lack of proper authentication** checks when intercepting and modifying TCP packets.\"\n*   **CWE-863: Incorrect Authorization** - **Chosen as Secondary Candidate**. Due to the missing authentication, authorization checks are bypassed or incorrectly performed. The system does not properly verify the identity of the user before granting access to resources, leading to **incorrect authorization**.\n*   **CWE-266: Incorrect Privilege Assignment** - **Chosen as Secondary Candidate**. The ultimate impact of the vulnerability is privilege escalation. The missing authentication leads to the assignment of administrative privileges to unauthorized users. This aligns with the CWE description of **incorrectly assigning a privilege** to a particular actor.\n*   **CWE-732: Incorrect Permission Assignment for Critical Resource** - **Not Chosen**. While the vulnerability results in unauthorized access, the root cause is not primarily related to incorrect permission assignments. The issue is the lack of authentication, which allows attackers to bypass permission checks.\n*   **CWE-276: Incorrect Default Permissions** - **Not Chosen**. This CWE relates to incorrect default permissions being set during installation. The vulnerability is not related to default permissions.\n*   **CWE-65: Windows Hard Link** - **Not Chosen**. This CWE is specific to Windows hard links, which are not relevant to the vulnerability.\n*   **CWE-248: Uncaught Exception** - **Not Chosen**. While the PoC mentions an access violation error, this is a symptom of the vulnerability and not the root cause. The root cause is the **lack of authentication**.\n*   **CWE-250: Execution with Unnecessary Privileges** - **Not Chosen**. The vulnerability is not directly related to a process or component running with unnecessary privileges. It is about gaining unauthorized privileges through a **lack of authentication**.\n*   **CWE-427: Uncontrolled Search Path Element** - **Not Chosen**. This CWE is not relevant to the vulnerability.\n*   **CWE-269: Improper Privilege Management** - **Not Chosen**. While privilege escalation is the impact, the root cause is the **missing authentication**, not improper management of existing privileges.\n*   **CWE-912: Hidden Functionality** - **Not Chosen**. This CWE is not relevant to the vulnerability.\n*   **CWE-782: Exposed IOCTL with Insufficient Access Control** - **Not Chosen**. This CWE is very specific to IOCTLs and is not relevant to the vulnerability.\n*   **CWE-781: Improper Address Validation in IOCTL with METHOD_NEITHER I/O Control Code** - **Not Chosen**. This CWE is even more specific to IOCTLs and is not relevant to the vulnerability.",
  "analysis_with_relationships": "# Summary\n| CWE ID | CWE Name | Confidence | CWE Abstraction Level | CWE Vulnerability Mapping Label | CWE-Vulnerability Mapping Notes |\n|---|---|---|---|---|---|\n| CWE-306 | Missing Authentication for Critical Function | 0.9 | Base | Allowed | Primary CWE |\n| CWE-863 | Incorrect Authorization | 0.7 | Class | Allowed-with-Review | Secondary Candidate |\n| CWE-266 | Incorrect Privilege Assignment | 0.6 | Base | Allowed | Secondary Candidate |\n\n## Evidence and Confidence\n\n*   **Confidence Score:** 0.8\n*   **Evidence Strength:** HIGH\n\n## Relationship Analysis\nThe primary CWE is CWE-306 (Missing Authentication for Critical Function), which is a base-level CWE. CWE-306 is a child of CWE-287 (Improper Authentication) at the class level. CWE-863 (Incorrect Authorization) and CWE-266 (Incorrect Privilege Assignment) are considered as secondary candidates because the vulnerability also involves incorrect authorization/privilege assignment due to the missing authentication. CWE-863 is a class-level CWE, and CWE-266 is a base-level CWE.\n\n```mermaid\ngraph TD\n    cwe306[\"CWE-306: Missing Authentication for Critical Function\"]\n    cwe287[\"CWE-287: Improper Authentication\"]\n    cwe863[\"CWE-863: Incorrect Authorization\"]\n    cwe266[\"CWE-266: Incorrect Privilege Assignment\"]\n\n    cwe306 -->|CHILDOF| cwe287\n    cwe863 -->|PEEROF| cwe306\n    cwe266 -->|PEEROF| cwe306\n\n    classDef primary fill:#f96,stroke:#333,stroke-width:2px\n    classDef secondary fill:#69f,stroke:#333\n    classDef tertiary fill:#9e9,stroke:#333\n    class cwe306 primary\n    class cwe863,cwe266 secondary\n    class cwe287 tertiary\n```\n\n## Vulnerability Chain\nThe vulnerability chain starts with **missing authentication (CWE-306)**, leading to **incorrect authorization (CWE-863)**, and ultimately resulting in **privilege escalation (CWE-266)**. The **lack of proper authentication** allows attackers to bypass security checks and gain administrative privileges.\n  - **CWE-306**: Missing Authentication for Critical Function (Root Cause)\n  - **CWE-863**: Incorrect Authorization (Intermediate Weakness)\n  - **CWE-266**: Incorrect Privilege Assignment (Impact)\n\n## Summary of Analysis\nThe initial assessment focused on privilege escalation as the primary impact. However, after analyzing the CVE reference and considering the retriever results, it became clear that the root cause is the **lack of proper authentication**. The vulnerability allows attackers to bypass authentication checks by manipulating TCP packets, leading to unauthorized administrative access.\nThe selection of CWE-306 is based on the evidence of **insufficient authentication** checks when intercepting and modifying TCP packets. This aligns with the CWE description of \"Missing Authentication for Critical Function.\" The retriever results also listed CWE-306, supporting this selection.\nCWE-863 (Incorrect Authorization) and CWE-266 (Incorrect Privilege Assignment) were considered as secondary candidates because the ultimate impact is privilege escalation. However, they are consequences of the **missing authentication** and not the primary cause.\nThe selected CWEs are at the optimal level of specificity. CWE-306 is a base-level CWE that accurately represents the **missing authentication** vulnerability. CWE-863 and CWE-266 are also at appropriate levels, representing the related authorization and privilege assignment issues. The \"Privileges vs Permissions Guidance\" section also indicates that escalation is a result of a misconfigured role, permission not dropped, or role-check bypass.\n\nRelevant CWE Information:\n- Vulnerability Description: \"An issue in Ocuco Innovation v.2.10.24.51 allows a local attacker to escalate privileges via the SETTINGSVATIGATOR.EXE component\"\n- CVE Reference Links Content Summary: \"The vulnerability lies in the **lack of proper authentication** checks when intercepting and modifying TCP packets.\"\n\n---\nHere's the breakdown of why each CWE was chosen or not:\n\n*   **CWE-306: Missing Authentication for Critical Function** - **Chosen as Primary CWE**. The root cause of the vulnerability is the **lack of proper authentication** checks when intercepting and modifying TCP packets. This allows attackers to bypass security and gain administrative privileges. The evidence is: \"The vulnerability lies in the **lack of proper authentication** checks when intercepting and modifying TCP packets.\"\n*   **CWE-863: Incorrect Authorization** - **Chosen as Secondary Candidate**. Due to the missing authentication, authorization checks are bypassed or incorrectly performed. The system does not properly verify the identity of the user before granting access to resources, leading to **incorrect authorization**.\n*   **CWE-266: Incorrect Privilege Assignment** - **Chosen as Secondary Candidate**. The ultimate impact of the vulnerability is privilege escalation. The missing authentication leads to the assignment of administrative privileges to unauthorized users. This aligns with the CWE description of **incorrectly assigning a privilege** to a particular actor.\n*   **CWE-732: Incorrect Permission Assignment for Critical Resource** - **Not Chosen**. While the vulnerability results in unauthorized access, the root cause is not primarily related to incorrect permission assignments. The issue is the lack of authentication, which allows attackers to bypass permission checks.\n*   **CWE-276: Incorrect Default Permissions** - **Not Chosen**. This CWE relates to incorrect default permissions being set during installation. The vulnerability is not related to default permissions.\n*   **CWE-65: Windows Hard Link** - **Not Chosen**. This CWE is specific to Windows hard links, which are not relevant to the vulnerability.\n*   **CWE-248: Uncaught Exception** - **Not Chosen**. While the PoC mentions an access violation error, this is a symptom of the vulnerability and not the root cause. The root cause is the **lack of authentication**.\n*   **CWE-250: Execution with Unnecessary Privileges** - **Not Chosen**. The vulnerability is not directly related to a process or component running with unnecessary privileges. It is about gaining unauthorized privileges through a **lack of authentication**.\n*   **CWE-427: Uncontrolled Search Path Element** - **Not Chosen**. This CWE is not relevant to the vulnerability.\n*   **CWE-269: Improper Privilege Management** - **Not Chosen**. While privilege escalation is the impact, the root cause is the **missing authentication**, not improper management of existing privileges.\n*   **CWE-912: Hidden Functionality** - **Not Chosen**. This CWE is not relevant to the vulnerability.\n*   **CWE-782: Exposed IOCTL with Insufficient Access Control** - **Not Chosen**. This CWE is very specific to IOCTLs and is not relevant to the vulnerability.\n*   **CWE-781: Improper Address Validation in IOCTL with METHOD_NEITHER I/O Control Code** - **Not Chosen**. This CWE is even more specific to IOCTLs and is not relevant to the vulnerability.\n\n\n## CWE Relationship Analysis\n\nCurrent CWEs represent these abstraction levels: .\n\n\n### Vulnerability Chain Analysis\n\n**Chain starting from CWE-863:**\n- 863 (Incorrect Authorization) - ROOT\n\n\n**Chain starting from CWE-427:**\n- 427 (Uncontrolled Search Path Element) - ROOT\n\n\n\n### CWE Relationship Diagram\n\n```mermaid\ngraph TD\n    classDef primary fill:#f96,stroke:#333,stroke-width:2px\n    classDef secondary fill:#69f,stroke:#333\n    classDef tertiary fill:#9e9,stroke:#333\n```",
  "criticism": "",
  "resolution": "",
  "relevant_cwes": [
    {
      "metadata": {
        "doc_id": "732",
        "name": "Incorrect Permission Assignment for Critical Resource",
        "source": "sparse"
      },
      "similarity": 40.51021114057964
    },
    {
      "metadata": {
        "doc_id": "276",
        "name": "Incorrect Default Permissions",
        "source": "sparse"
      },
      "similarity": 39.21280582886661
    },
    {
      "metadata": {
        "doc_id": "65",
        "name": "Windows Hard Link",
        "source": "sparse"
      },
      "similarity": 38.94029857939341
    },
    {
      "metadata": {
        "doc_id": "248",
        "name": "Uncaught Exception",
        "source": "sparse"
      },
      "similarity": 38.77703892062025
    },
    {
      "metadata": {
        "doc_id": "250",
        "name": "Execution with Unnecessary Privileges",
        "source": "sparse"
      },
      "similarity": 37.60479122585019
    },
    {
      "metadata": {
        "doc_id": "427",
        "name": "Uncontrolled Search Path Element",
        "source": "sparse"
      },
      "similarity": 37.17225535872945
    },
    {
      "metadata": {
        "doc_id": "269",
        "name": "Improper Privilege Management",
        "source": "sparse"
      },
      "similarity": 35.67007500005058
    },
    {
      "metadata": {
        "doc_id": "912",
        "name": "Hidden Functionality",
        "source": "sparse"
      },
      "similarity": 35.62394736768532
    },
    {
      "metadata": {
        "doc_id": "782",
        "name": "Exposed IOCTL with Insufficient Access Control",
        "type": "Variant",
        "original_content": "The product implements an IOCTL with functionality that should be restricted, but it does not properly enforce access control for the IOCTL.",
        "source": "dense",
        "mapping_notes": {
          "usage": "Allowed",
          "rationale": "This CWE entry is at the Variant level of abstraction, which is a preferred level of abstraction for mapping to the root causes of vulnerabilities.",
          "comments": "Carefully read both the name and description to ensure that this mapping is an appropriate fit. Do not try to 'force' a mapping to a lower-level Base/Variant simply to comply with this preferred level of abstraction.",
          "reasons": [
            "Acceptable-Use"
          ]
        },
        "score_info": {
          "retrievers": [
            "dense"
          ],
          "retriever_count": 1,
          "normalized_scores": {
            "dense": 0.5668516035197407
          }
        }
      },
      "similarity": 0.5668516035197407
    },
    {
      "doc_id": "781",
      "text": "CWE-781: Improper Address Validation in IOCTL with METHOD_NEITHER I/O Control Code",
      "score": 2.04,
      "metadata": {
        "doc_id": "781",
        "name": "Improper Address Validation in IOCTL with METHOD_NEITHER I/O Control Code",
        "type": "variant",
        "original_content": "CWE-781: Improper Address Validation in IOCTL with METHOD_NEITHER I/O Control Code",
        "relationships": [
          {
            "source_id": "781",
            "target_id": "782",
            "label": "CANFOLLOW",
            "properties": {
              "view_id": "1000"
            }
          },
          {
            "source_id": "781",
            "target_id": "822",
            "label": "CANPRECEDE",
            "properties": {
              "view_id": "1000"
            }
          },
          {
            "source_id": "781",
            "target_id": "1285",
            "label": "CHILDOF",
            "properties": {
              "ordinal": "Primary",
              "view_id": "1000"
            }
          },
          {
            "source_id": "822",
            "target_id": "781",
            "label": "CANFOLLOW",
            "properties": {
              "view_id": "1000"
            }
          },
          {
            "source_id": "782",
            "target_id": "781",
            "label": "CANPRECEDE",
            "properties": {
              "view_id": "1000"
            }
          },
          {
            "source_id": "1285",
            "target_id": "781",
            "label": "PARENTOF",
            "properties": {
              "ordinal": "Primary",
              "view_id": "1000"
            }
          }
        ],
        "score_components": {
          "relationship_chain": 1.0,
          "sequence_path": 1.0
        },
        "abstraction_factor": 1.2,
        "graph_path_info": {
          "path_types": [
            "relationship_chain",
            "vulnerability_sequence_forward"
          ],
          "best_paths": {
            "relationship_chain": {
              "path": [
                [
                  "782",
                  "781",
                  "CANPRECEDE"
                ]
              ],
              "score": 1.0,
              "type": "relationship_chain",
              "source": "782"
            },
            "vulnerability_sequence_forward": {
              "path": [
                [
                  "782",
                  "781",
                  "CANPRECEDE"
                ]
              ],
              "score": 1.0,
              "type": "vulnerability_sequence_forward",
              "source": "782"
            }
          }
        },
        "position": "after",
        "sources": [
          "graph"
        ],
        "source": "graph",
        "mapping_notes": {
          "usage": "Allowed",
          "rationale": "This CWE entry is at the Variant level of abstraction, which is a preferred level of abstraction for mapping to the root causes of vulnerabilities.",
          "comments": "Carefully read both the name and description to ensure that this mapping is an appropriate fit. Do not try to 'force' a mapping to a lower-level Base/Variant simply to comply with this preferred level of abstraction.",
          "reasons": [
            "Acceptable-Use"
          ]
        },
        "score_info": {
          "retrievers": [
            "graph"
          ],
          "retriever_count": 1,
          "normalized_scores": {
            "graph": 2.04
          }
        }
      },
      "similarity": 2.04
    }
  ],
  "identified_cwes": {
    "analyzer": [
      "CWE-863",
      "CWE-427",
      "CWE-732",
      "CWE-306",
      "CWE-248",
      "CWE-65",
      "CWE-782",
      "CWE-269",
      "CWE-250",
      "CWE-781",
      "CWE-266",
      "CWE-276",
      "CWE-287",
      "CWE-912"
    ],
    "critic_additional": []
  },
  "keyphrase_cwe_mapping": {}
}