{
  "cve_id": "CVE-2024-22219",
  "description": "XML External Entity (XXE) vulnerability in Terminalfour 8.0.0001 through 8.3.18 and XML JDBC versions up to 1.0.4 allows authenticated users to submit malicious XML via unspecified features which could lead to various actions such as accessing the underlying server, remote code execution (RCE), or performing **Server-Side Request Forgery** (SSRF) attacks.",
  "key_phrases": {
    "rootcause": "XML External Entity expansion",
    "weakness": "Server-Side Request Forgery",
    "impact": "remote code execution",
    "vector": "malicious XML",
    "attacker": "authenticated users",
    "product": [
      "['Terminalfour'",
      "'XML JDBC']"
    ],
    "version": [
      "['8.0.0001 through 8.3.18'",
      "'up to 1.0.4']"
    ],
    "component": [
      "['unspecified features'",
      "'multiple components']"
    ]
  },
  "reference_content": "Based on the provided content, here's an analysis of CVE-2024-22219:\n\n**Root Cause of Vulnerability:**\n- The vulnerability stems from the improper handling of XML External Entities (XXE) within the Terminalfour application. Specifically, the application processes XML input without adequate sanitization, allowing for the inclusion of malicious external entities.\n\n**Weaknesses/Vulnerabilities Present:**\n- **XML External Entity (XXE) Injection:** The core weakness is the susceptibility to XXE injection. This occurs because the application parses untrusted XML data, which can include references to external entities.\n\n**Impact of Exploitation:**\n- Successful exploitation of this vulnerability can lead to several critical impacts:\n    - **Accessing the Underlying Server:** Attackers can potentially gain access to the server's file system or other sensitive resources.\n   - **Remote Code Execution (RCE):** By leveraging XXE, attackers might be able to execute arbitrary code on the server.\n    - **Server-Side Request Forgery (SSRF):** Attackers could use the server to make requests to other internal or external systems, potentially gaining access to those resources or disrupting services.\n\n**Attack Vectors:**\n- The primary attack vector is through the submission of maliciously crafted XML input via Terminalfour features. The specific features aren't specified in the provided content, only that authenticated users can submit XML data.\n\n**Required Attacker Capabilities/Position:**\n- **Authenticated User:** An attacker needs to be an authenticated Terminalfour user to exploit this vulnerability. This implies that they must have valid credentials to access the application.\n- **Ability to Submit XML Data:** The attacker must be able to utilize Terminalfour features that allow the submission of XML data.\n\n**Affected Versions:**\n- Terminalfour versions 8.0.0001 to 8.3.18 are vulnerable.\n- Terminalfour XML JDBC versions up to 1.0.4 are vulnerable.\n\n**Mitigation:**\n- Upgrade to Terminalfour version 8.3.19 or later, or Terminalfour XML JDBC 1.0.5 or later, which contain fixes for this vulnerability.\n\n**Additional Notes:**\n- The content explicitly states that there is currently no evidence of active exploitation of these vulnerabilities.\n- The vulnerability is present in a range of versions indicating a widespread exposure of this vulnerability for systems running earlier versions.",
  "similar_info": {
    "cwe_distribution": {
      "95": {
        "cwe_counts": {},
        "total_samples": 1,
        "distribution": [
          {
            "cwes": [],
            "frequency": 1,
            "proportion": 1.0
          }
        ]
      },
      "90": {
        "cwe_counts": {},
        "total_samples": 1,
        "distribution": [
          {
            "cwes": [],
            "frequency": 1,
            "proportion": 1.0
          }
        ]
      },
      "85": {
        "cwe_counts": {},
        "total_samples": 1,
        "distribution": [
          {
            "cwes": [],
            "frequency": 1,
            "proportion": 1.0
          }
        ]
      },
      "80": {
        "cwe_counts": {},
        "total_samples": 1,
        "distribution": [
          {
            "cwes": [],
            "frequency": 1,
            "proportion": 1.0
          }
        ]
      },
      "75": {
        "cwe_counts": {},
        "total_samples": 1,
        "distribution": [
          {
            "cwes": [],
            "frequency": 1,
            "proportion": 1.0
          }
        ]
      },
      "70": {
        "cwe_counts": {},
        "total_samples": 1,
        "distribution": [
          {
            "cwes": [],
            "frequency": 1,
            "proportion": 1.0
          }
        ]
      }
    },
    "cwe_consensus": "",
    "similarity_stats": {
      "thresholds": [
        95,
        90,
        85,
        80,
        75,
        70
      ],
      "total_samples_by_threshold": {
        "95": 1,
        "90": 1,
        "85": 1,
        "80": 1,
        "75": 1,
        "70": 1
      },
      "top_cwes_by_threshold": {
        "95": [],
        "90": [],
        "85": [],
        "80": [],
        "75": [],
        "70": []
      }
    },
    "raw_matches": [
      {
        "similarity": 95,
        "cwes": [],
        "total": 1,
        "frequency": 1,
        "proportion": 1.0
      },
      {
        "similarity": 90,
        "cwes": [],
        "total": 1,
        "frequency": 1,
        "proportion": 1.0
      },
      {
        "similarity": 85,
        "cwes": [],
        "total": 1,
        "frequency": 1,
        "proportion": 1.0
      },
      {
        "similarity": 80,
        "cwes": [],
        "total": 1,
        "frequency": 1,
        "proportion": 1.0
      },
      {
        "similarity": 75,
        "cwes": [],
        "total": 1,
        "frequency": 1,
        "proportion": 1.0
      },
      {
        "similarity": 70,
        "cwes": [],
        "total": 1,
        "frequency": 1,
        "proportion": 1.0
      }
    ]
  },
  "similarity_summary": {
    "consensus_cwe": "",
    "top_cwes": [],
    "confidence_levels": {
      "high": [],
      "medium": [],
      "low": []
    },
    "total_samples": 6
  },
  "analysis": "# Summary\n| CWE ID | CWE Name | Confidence | CWE Abstraction Level | CWE Vulnerability Mapping Label | CWE-Vulnerability Mapping Notes |\n|---|---|---|---|---|---|\n| CWE-611 | Improper Restriction of XML External Entity Reference | 1.0 | Base | Primary | Allowed |\n| CWE-918 | Server-Side Request Forgery (SSRF) | 0.7 | Base | Secondary | Allowed |\n\n## Evidence and Confidence\n\n*   **Confidence Score:** 0.85\n*   **Evidence Strength:** HIGH\n\n## Relationship Analysis\nThe primary CWE is CWE-611, which directly reflects the **XML External Entity expansion** root cause. CWE-918 is a potential impact, as successful XXE exploitation can lead to SSRF. There is no direct hierarchical relationship between CWE-611 and CWE-918, but the vulnerability description and CVE details explicitly mention SSRF as a possible outcome of XXE. The abstraction levels are both Base, which is appropriate for direct mapping.\n\n```mermaid\ngraph TD\n    cwe611[\"CWE-611: Improper Restriction of XML External Entity Reference\"]\n    cwe918[\"CWE-918: Server-Side Request Forgery (SSRF)\"]\n    \n    cwe611 -->|CAN_LEAD_TO| cwe918\n    \n    classDef primary fill:#f96,stroke:#333,stroke-width:2px\n    classDef secondary fill:#69f,stroke:#333\n    class cwe611 primary\n    class cwe918 secondary\n```\n\n## Vulnerability Chain\nThe vulnerability chain starts with the **improper handling of XML External Entities** (CWE-611), which allows an attacker to inject malicious XML. This can then lead to several impacts, including **Server-Side Request Forgery** (CWE-918) and potentially Remote Code Execution (RCE). The chain is XXE -> SSRF/RCE.\n\n## Summary of Analysis\nThe primary weakness is clearly the improper handling of XML External Entities, making CWE-611 the most appropriate primary CWE. The description and CVE summary explicitly mention SSRF as a potential consequence, thus warranting its inclusion as a secondary CWE. The retriever results support this selection, with CWE-611 being the top match and CWE-918 also appearing in the top results. The analysis is strongly based on the provided evidence, especially the CVE Reference Links Content Summary.\n\nThe vulnerability description states: \"XML External Entity (XXE) vulnerability...allows authenticated users to submit malicious XML...which could lead to various actions such as accessing the underlying server, remote code execution (RCE), or performing **Server-Side Request Forgery** (SSRF) attacks.\" The CVE Reference Links Content Summary further confirms this: \"The vulnerability stems from the **improper handling of XML External Entities** (XXE)...Attackers could use the server to make requests to other internal or external systems, potentially gaining access to those resources or disrupting services.\"\n\nCWE-611 is at the optimal level of specificity, as it directly addresses the root cause. CWE-918 is added as a secondary CWE to reflect the potential impact of SSRF.\n\n**CWEs Considered but Not Used:**\n\n*   **CWE-776: Improper Restriction of Recursive Entity References in DTDs ('XML Entity Expansion')**: While related to XML vulnerabilities, this CWE focuses specifically on recursive entity references, which is not explicitly mentioned in the vulnerability description. CWE-611 is a more general and applicable CWE for XXE vulnerabilities.\n*   **CWE-502: Deserialization of Untrusted Data**: This CWE is not applicable because the vulnerability is related to XML External Entities, not deserialization of untrusted data.\n*   **CWE-79: Improper Neutralization of Input During Web Page Generation ('Cross-site Scripting')**: This is not relevant as the vulnerability is not related to XSS.\n*   **CWE-74: Improper Neutralization of Special Elements in Output Used by a Downstream Component ('Injection')**: While XXE is a type of injection, CWE-611 is more specific to the type of injection.\n*   **CWE-91: XML Injection (aka Blind XPath Injection)** and **CWE-643: Improper Neutralization of Data within XPath Expressions ('XPath Injection')**: These are related to XML injection but focus on XPath expressions, which is not the primary issue in this vulnerability. CWE-611 better represents the core weakness of XXE.\n*   **CWE-138: Improper Neutralization of Special Elements**: This is too general; CWE-611 is more specific.\n*   **CWE-346: Origin Validation Error**: This is not relevant.\n*   **CWE-917: Improper Neutralization of Special Elements used in an Expression Language Statement ('Expression Language Injection')**: This is not relevant.\n*   **CWE-23: Relative Path Traversal**: This is not relevant.\n*   **CWE-532: Insertion of Sensitive Information into Log File**: This is not relevant.\n*   **CWE-613: Insufficient Session Expiration**: This is not relevant.\n*   **CWE-1275: Sensitive Cookie with Improper SameSite Attribute**: This is not relevant.\n*   **CWE-827: Improper Control of Document Type Definition**: This is not specific enough.\n*   **CWE-352: Cross-Site Request Forgery (CSRF)**: This is not relevant.\n*   **CWE-941: Incorrectly Specified Destination in a Communication Channel**: This is not the primary issue.\n\n# Enhanced Context (25 CWEs)\nThe following CWEs were identified as potentially relevant to this vulnerability:\n\n## CWE-611: Improper Restriction of XML External Entity Reference\n**Abstraction Level**: Base\n**Similarity Score**: 0.85\n**Source**: dense\n\n**Description**:\nThe product processes an XML document that can contain XML entities with URIs that resolve to documents outside of the intended sphere of control, causing the product to embed incorrect documents into its output.\n\n**Mapping Guidance**:\n- Usage: Allowed\n- Rationale: This CWE entry is at the Base level of abstraction, which is a preferred level of abstraction for mapping to the root causes of vulnerabilities.\n\n\n\n## CWE-776: Improper Restriction of Recursive Entity References in DTDs ('XML Entity Expansion')\n**Abstraction Level**: Base\n**Similarity Score**: 0.77\n**Source**: dense\n\n**Description**:\nThe product uses XML documents and allows their structure to be defined with a Document Type Definition (DTD), but it does not properly control the number of recursive definitions of entities.\n\n**Mapping Guidance**:\n- Usage: Allowed\n- Rationale: This CWE entry is at the Base level of abstraction, which is a preferred level of abstraction for mapping to the root causes of vulnerabilities.\n\n\n\n## CWE-80: Improper Neutralization of Script-Related HTML Tags in a Web Page (Basic XSS)\n**Abstraction Level**: Variant\n**Similarity Score**: 0.76\n**Source**: dense\n\n**Description**:\nThe product receives input from an upstream component, but it does not neutralize or incorrectly neutralizes special characters such as \"<\", \">\", and \"&\" that could be interpreted as web-scripting elements when they are sent to a downstream component that processes web pages.\n\n**Mapping Guidance**:\n- Usage: Allowed\n- Rationale: This CWE entry is at the Variant level of abstraction, which is a preferred level of abstraction for mapping to the root causes of vulnerabilities.\n\n\n\n## CWE-116: Improper Encoding or Escaping of Output\n**Abstraction Level**: Class\n**Similarity Score**: 0.76\n**Source**: dense\n\n**Description**:\nThe product prepares a structured message for communication with another component, but encoding or escaping of the data is either missing or done incorrectly. As a result, the intended structure of the message is not preserved.\n\n**Mapping Guidance**:\n- Usage: Allowed-with-Review\n- Rationale: This CWE entry is a Class and might have Base-level children that would be more appropriate\n\n\n\n## CWE-918: Server-Side Request Forgery (SSRF)\n**Abstraction Level**: Base\n**Similarity Score**: 0.75\n**Source**: dense\n\n**Description**:\nThe web server receives a URL or similar request from an upstream component and retrieves the contents of this URL, but it does not sufficiently ensure that the request is being sent to the expected destination.\n\n**Mapping Guidance**:\n- Usage: Allowed\n- Rationale: This CWE entry is at the Base level of abstraction, which is a preferred level of abstraction for mapping to the root causes of vulnerabilities.\n\n\n\n## CWE-74: Improper Neutralization of Special Elements in Output Used by a Downstream Component ('Injection')\n**Abstraction Level**: Class\n**Similarity Score**: 0.74\n**Source**: dense\n\n**Description**:\nThe product constructs all or part of a command, data structure, or record using externally-influenced input from an upstream component, but it does not neutralize or incorrectly neutralizes special elements that could modify how it is parsed or interpreted when it is sent to a downstream component.\n\n**Mapping Guidance**:\n- Usage: Discouraged\n- Rationale: CWE-74 is high-level and often misused when lower-level weaknesses are more appropriate.\n\n\n\n##",
  "analysis_with_relationships": "# Summary\n| CWE ID | CWE Name | Confidence | CWE Abstraction Level | CWE Vulnerability Mapping Label | CWE-Vulnerability Mapping Notes |\n|---|---|---|---|---|---|\n| CWE-611 | Improper Restriction of XML External Entity Reference | 1.0 | Base | Primary | Allowed |\n| CWE-918 | Server-Side Request Forgery (SSRF) | 0.7 | Base | Secondary | Allowed |\n\n## Evidence and Confidence\n\n*   **Confidence Score:** 0.85\n*   **Evidence Strength:** HIGH\n\n## Relationship Analysis\nThe primary CWE is CWE-611, which directly reflects the **XML External Entity expansion** root cause. CWE-918 is a potential impact, as successful XXE exploitation can lead to SSRF. There is no direct hierarchical relationship between CWE-611 and CWE-918, but the vulnerability description and CVE details explicitly mention SSRF as a possible outcome of XXE. The abstraction levels are both Base, which is appropriate for direct mapping.\n\n```mermaid\ngraph TD\n    cwe611[\"CWE-611: Improper Restriction of XML External Entity Reference\"]\n    cwe918[\"CWE-918: Server-Side Request Forgery (SSRF)\"]\n    \n    cwe611 -->|CAN_LEAD_TO| cwe918\n    \n    classDef primary fill:#f96,stroke:#333,stroke-width:2px\n    classDef secondary fill:#69f,stroke:#333\n    class cwe611 primary\n    class cwe918 secondary\n```\n\n## Vulnerability Chain\nThe vulnerability chain starts with the **improper handling of XML External Entities** (CWE-611), which allows an attacker to inject malicious XML. This can then lead to several impacts, including **Server-Side Request Forgery** (CWE-918) and potentially Remote Code Execution (RCE). The chain is XXE -> SSRF/RCE.\n\n## Summary of Analysis\nThe primary weakness is clearly the improper handling of XML External Entities, making CWE-611 the most appropriate primary CWE. The description and CVE summary explicitly mention SSRF as a potential consequence, thus warranting its inclusion as a secondary CWE. The retriever results support this selection, with CWE-611 being the top match and CWE-918 also appearing in the top results. The analysis is strongly based on the provided evidence, especially the CVE Reference Links Content Summary.\n\nThe vulnerability description states: \"XML External Entity (XXE) vulnerability...allows authenticated users to submit malicious XML...which could lead to various actions such as accessing the underlying server, remote code execution (RCE), or performing **Server-Side Request Forgery** (SSRF) attacks.\" The CVE Reference Links Content Summary further confirms this: \"The vulnerability stems from the **improper handling of XML External Entities** (XXE)...Attackers could use the server to make requests to other internal or external systems, potentially gaining access to those resources or disrupting services.\"\n\nCWE-611 is at the optimal level of specificity, as it directly addresses the root cause. CWE-918 is added as a secondary CWE to reflect the potential impact of SSRF.\n\n**CWEs Considered but Not Used:**\n\n*   **CWE-776: Improper Restriction of Recursive Entity References in DTDs ('XML Entity Expansion')**: While related to XML vulnerabilities, this CWE focuses specifically on recursive entity references, which is not explicitly mentioned in the vulnerability description. CWE-611 is a more general and applicable CWE for XXE vulnerabilities.\n*   **CWE-502: Deserialization of Untrusted Data**: This CWE is not applicable because the vulnerability is related to XML External Entities, not deserialization of untrusted data.\n*   **CWE-79: Improper Neutralization of Input During Web Page Generation ('Cross-site Scripting')**: This is not relevant as the vulnerability is not related to XSS.\n*   **CWE-74: Improper Neutralization of Special Elements in Output Used by a Downstream Component ('Injection')**: While XXE is a type of injection, CWE-611 is more specific to the type of injection.\n*   **CWE-91: XML Injection (aka Blind XPath Injection)** and **CWE-643: Improper Neutralization of Data within XPath Expressions ('XPath Injection')**: These are related to XML injection but focus on XPath expressions, which is not the primary issue in this vulnerability. CWE-611 better represents the core weakness of XXE.\n*   **CWE-138: Improper Neutralization of Special Elements**: This is too general; CWE-611 is more specific.\n*   **CWE-346: Origin Validation Error**: This is not relevant.\n*   **CWE-917: Improper Neutralization of Special Elements used in an Expression Language Statement ('Expression Language Injection')**: This is not relevant.\n*   **CWE-23: Relative Path Traversal**: This is not relevant.\n*   **CWE-532: Insertion of Sensitive Information into Log File**: This is not relevant.\n*   **CWE-613: Insufficient Session Expiration**: This is not relevant.\n*   **CWE-1275: Sensitive Cookie with Improper SameSite Attribute**: This is not relevant.\n*   **CWE-827: Improper Control of Document Type Definition**: This is not specific enough.\n*   **CWE-352: Cross-Site Request Forgery (CSRF)**: This is not relevant.\n*   **CWE-941: Incorrectly Specified Destination in a Communication Channel**: This is not the primary issue.\n\n# Enhanced Context (25 CWEs)\nThe following CWEs were identified as potentially relevant to this vulnerability:\n\n## CWE-611: Improper Restriction of XML External Entity Reference\n**Abstraction Level**: Base\n**Similarity Score**: 0.85\n**Source**: dense\n\n**Description**:\nThe product processes an XML document that can contain XML entities with URIs that resolve to documents outside of the intended sphere of control, causing the product to embed incorrect documents into its output.\n\n**Mapping Guidance**:\n- Usage: Allowed\n- Rationale: This CWE entry is at the Base level of abstraction, which is a preferred level of abstraction for mapping to the root causes of vulnerabilities.\n\n\n\n## CWE-776: Improper Restriction of Recursive Entity References in DTDs ('XML Entity Expansion')\n**Abstraction Level**: Base\n**Similarity Score**: 0.77\n**Source**: dense\n\n**Description**:\nThe product uses XML documents and allows their structure to be defined with a Document Type Definition (DTD), but it does not properly control the number of recursive definitions of entities.\n\n**Mapping Guidance**:\n- Usage: Allowed\n- Rationale: This CWE entry is at the Base level of abstraction, which is a preferred level of abstraction for mapping to the root causes of vulnerabilities.\n\n\n\n## CWE-80: Improper Neutralization of Script-Related HTML Tags in a Web Page (Basic XSS)\n**Abstraction Level**: Variant\n**Similarity Score**: 0.76\n**Source**: dense\n\n**Description**:\nThe product receives input from an upstream component, but it does not neutralize or incorrectly neutralizes special characters such as \"<\", \">\", and \"&\" that could be interpreted as web-scripting elements when they are sent to a downstream component that processes web pages.\n\n**Mapping Guidance**:\n- Usage: Allowed\n- Rationale: This CWE entry is at the Variant level of abstraction, which is a preferred level of abstraction for mapping to the root causes of vulnerabilities.\n\n\n\n## CWE-116: Improper Encoding or Escaping of Output\n**Abstraction Level**: Class\n**Similarity Score**: 0.76\n**Source**: dense\n\n**Description**:\nThe product prepares a structured message for communication with another component, but encoding or escaping of the data is either missing or done incorrectly. As a result, the intended structure of the message is not preserved.\n\n**Mapping Guidance**:\n- Usage: Allowed-with-Review\n- Rationale: This CWE entry is a Class and might have Base-level children that would be more appropriate\n\n\n\n## CWE-918: Server-Side Request Forgery (SSRF)\n**Abstraction Level**: Base\n**Similarity Score**: 0.75\n**Source**: dense\n\n**Description**:\nThe web server receives a URL or similar request from an upstream component and retrieves the contents of this URL, but it does not sufficiently ensure that the request is being sent to the expected destination.\n\n**Mapping Guidance**:\n- Usage: Allowed\n- Rationale: This CWE entry is at the Base level of abstraction, which is a preferred level of abstraction for mapping to the root causes of vulnerabilities.\n\n\n\n## CWE-74: Improper Neutralization of Special Elements in Output Used by a Downstream Component ('Injection')\n**Abstraction Level**: Class\n**Similarity Score**: 0.74\n**Source**: dense\n\n**Description**:\nThe product constructs all or part of a command, data structure, or record using externally-influenced input from an upstream component, but it does not neutralize or incorrectly neutralizes special elements that could modify how it is parsed or interpreted when it is sent to a downstream component.\n\n**Mapping Guidance**:\n- Usage: Discouraged\n- Rationale: CWE-74 is high-level and often misused when lower-level weaknesses are more appropriate.\n\n\n\n##\n\n\n## CWE Relationship Analysis\n\nCurrent CWEs represent these abstraction levels: .\n\n\n### Vulnerability Chain Analysis\n\n**Chain starting from CWE-91:**\n- 91 (XML Injection (aka Blind XPath Injection)) - ROOT\n\n\n**Chain starting from CWE-611:**\n- 611 (Improper Restriction of XML External Entity Reference) - ROOT\n\n\n\n### CWE Relationship Diagram\n\n```mermaid\ngraph TD\n    classDef primary fill:#f96,stroke:#333,stroke-width:2px\n    classDef secondary fill:#69f,stroke:#333\n    classDef tertiary fill:#9e9,stroke:#333\n```",
  "criticism": "",
  "resolution": "",
  "relevant_cwes": [
    {
      "metadata": {
        "doc_id": "611",
        "name": "Improper Restriction of XML External Entity Reference",
        "source": "sparse"
      },
      "similarity": 432.27706779337893
    },
    {
      "metadata": {
        "doc_id": "776",
        "name": "Improper Restriction of Recursive Entity References in DTDs ('XML Entity Expansion')",
        "source": "sparse"
      },
      "similarity": 286.88635401274826
    },
    {
      "metadata": {
        "doc_id": "918",
        "name": "Server-Side Request Forgery (SSRF)",
        "source": "sparse"
      },
      "similarity": 274.74209628100516
    },
    {
      "metadata": {
        "doc_id": "502",
        "name": "Deserialization of Untrusted Data",
        "source": "sparse"
      },
      "similarity": 257.03080836865746
    },
    {
      "metadata": {
        "doc_id": "138",
        "name": "Improper Neutralization of Special Elements",
        "source": "sparse"
      },
      "similarity": 253.70519640229048
    },
    {
      "metadata": {
        "doc_id": "352",
        "name": "Cross-Site Request Forgery (CSRF)",
        "source": "sparse"
      },
      "similarity": 252.676577352131
    },
    {
      "metadata": {
        "doc_id": "941",
        "name": "Incorrectly Specified Destination in a Communication Channel",
        "source": "sparse"
      },
      "similarity": 245.68852598430473
    },
    {
      "metadata": {
        "doc_id": "532",
        "name": "Insertion of Sensitive Information into Log File",
        "source": "sparse"
      },
      "similarity": 242.11928642126975
    },
    {
      "metadata": {
        "doc_id": "91",
        "name": "XML Injection (aka Blind XPath Injection)",
        "type": "Base",
        "original_content": "The product does not properly neutralize special elements that are used in XML, allowing attackers to modify the syntax, content, or commands of the XML before it is processed by an end system.",
        "keyphrase_source": "weakness:Server-Side Request Forgery",
        "source": "dense",
        "mapping_notes": {
          "usage": "Allowed",
          "rationale": "This CWE entry is at the Base level of abstraction, which is a preferred level of abstraction for mapping to the root causes of vulnerabilities.",
          "comments": "Carefully read both the name and description to ensure that this mapping is an appropriate fit. Do not try to 'force' a mapping to a lower-level Base/Variant simply to comply with this preferred level of abstraction.",
          "reasons": [
            "Acceptable-Use"
          ]
        },
        "score_info": {
          "retrievers": [
            "dense",
            "graph"
          ],
          "retriever_count": 2,
          "normalized_scores": {
            "dense": 0.6009470708912995,
            "graph": 1.7375548504628981
          }
        }
      },
      "similarity": 0.6009470708912995
    },
    {
      "doc_id": "643",
      "text": "The product uses external input to dynamically construct an XPath expression used to retrieve data from an XML database, but it does not neutralize or incorrectly neutralizes that input. This allows an attacker to control the structure of the query.",
      "score": 0.6177239463015477,
      "metadata": {
        "doc_id": "643",
        "name": "Improper Neutralization of Data within XPath Expressions ('XPath Injection')",
        "type": "Base",
        "extended_description": "The net effect is that the attacker will have control over the information selected from the XML database and may use that ability to control application flow, modify logic, retrieve unauthorized data, or bypass important checks (e.g. authentication).",
        "alternate_terms": [],
        "original_content": "The product uses external input to dynamically construct an XPath expression used to retrieve data from an XML database, but it does not neutralize or incorrectly neutralizes that input. This allows an attacker to control the structure of the query.",
        "relationships": [
          {
            "source_id": "643",
            "target_id": "91",
            "label": "CHILDOF",
            "properties": {
              "view_id": "1000"
            }
          },
          {
            "source_id": "643",
            "target_id": "943",
            "label": "CHILDOF",
            "properties": {
              "ordinal": "Primary",
              "view_id": "1000"
            }
          },
          {
            "source_id": "943",
            "target_id": "643",
            "label": "PARENTOF",
            "properties": {
              "ordinal": "Primary",
              "view_id": "1000"
            }
          },
          {
            "source_id": "91",
            "target_id": "643",
            "label": "PARENTOF",
            "properties": {
              "view_id": "1000"
            }
          }
        ],
        "source": "graph",
        "sources": [
          "vector",
          "graph"
        ],
        "vector_score": 0.6177239463015477,
        "graph_score": 2.4699999999999998,
        "score_components": {
          "relationship_chain": 0.3,
          "explicit_mention": 1.0,
          "abstraction_path": 0.9
        },
        "abstraction_factor": 1.3,
        "graph_path_info": {
          "path_types": [
            "relationship_chain",
            "abstraction_path_down"
          ],
          "best_paths": {
            "relationship_chain": {
              "path": [
                [
                  "91",
                  "643",
                  "PARENTOF"
                ]
              ],
              "score": 0.3,
              "type": "relationship_chain",
              "source": "91"
            },
            "abstraction_path_down": {
              "path": [
                [
                  "91",
                  "643",
                  "PARENTOF"
                ]
              ],
              "score": 0.7200000000000001,
              "type": "abstraction_path_down",
              "source": "91"
            }
          }
        },
        "is_explicit": true,
        "abstraction_level": "base",
        "mapping_notes": {
          "usage": "Allowed",
          "rationale": "This CWE entry is at the Base level of abstraction, which is a preferred level of abstraction for mapping to the root causes of vulnerabilities.",
          "comments": "Carefully read both the name and description to ensure that this mapping is an appropriate fit. Do not try to 'force' a mapping to a lower-level Base/Variant simply to comply with this preferred level of abstraction.",
          "reasons": [
            "Acceptable-Use"
          ]
        },
        "score_info": {
          "retrievers": [
            "dense",
            "graph"
          ],
          "retriever_count": 2,
          "normalized_scores": {
            "dense": 0.5898262963191074,
            "graph": 1.7290895785206188
          }
        }
      },
      "similarity": 1.7290895785206188
    }
  ],
  "identified_cwes": {
    "analyzer": [
      "CWE-91",
      "CWE-611",
      "CWE-80",
      "CWE-79",
      "CWE-74",
      "CWE-346",
      "CWE-917",
      "CWE-827",
      "CWE-613",
      "CWE-352",
      "CWE-918",
      "CWE-23",
      "CWE-532",
      "CWE-776",
      "CWE-643",
      "CWE-138",
      "CWE-941",
      "CWE-502",
      "CWE-116",
      "CWE-1275"
    ],
    "critic_additional": []
  },
  "keyphrase_cwe_mapping": {}
}