{
  "vulnerability_info": "VulnerabilityInfo(cve_id='CVE-2024-3036', description='**Improper Input Validation** vulnerability in ABB 800xA Base. An attacker who successfully exploited this vulnerability could cause services to crash by sending specifically crafted messages. This issue affects 800xA Base from 6.0.0 through 6.1.1-2.', key_phrases={'rootcause': ['Improper Input Validation', 'Input Validation vulnerability'], 'weakness': '', 'impact': 'cause services to crash', 'vector': 'specifically crafted messages', 'attacker': 'attacker', 'product': 'ABB 800xA Base', 'version': '6.0.0 through 6.1.1-2', 'component': ''}, reference_content=None, similar_info={'cwe_distribution': {}, 'cwe_consensus': '', 'similarity_stats': {'thresholds': [], 'total_samples_by_threshold': {}, 'top_cwes_by_threshold': {}}}, similarity_summary=SimilarityInsight(consensus_cwe='', top_cwes=[], confidence_levels={}, total_samples=0), analysis='', analysis_with_relationships='', criticism='', resolution='', relevant_cwes=[{'metadata': {'doc_id': '20', 'name': 'Improper Input Validation', 'source': 'sparse', 'original_content': 'The product receives input or data, but it does\\n        not validate or incorrectly validates that the input has the\\n        properties that are required to process the data safely and\\n        correctly.', 'keyphrase_sources': [{'id': 'rootcause:Improper Input Validation', 'keyphrase': 'Improper Input Validation', 'type': 'rootcause'}, {'id': 'rootcause:Input Validation vulnerability', 'keyphrase': 'Input Validation vulnerability', 'type': 'rootcause'}, {'id': 'impact:cause services to crash', 'keyphrase': 'cause services to crash', 'type': 'impact'}, {'id': 'vector:specifically crafted messages', 'keyphrase': 'specifically crafted messages', 'type': 'vector'}, {'id': 'attacker:attacker', 'keyphrase': 'attacker', 'type': 'attacker'}, {'id': 'product:ABB 800xA Base', 'keyphrase': 'ABB 800xA Base', 'type': 'product'}, {'id': 'version:6.0.0 through 6.1.1-2', 'keyphrase': '6.0.0 through 6.1.1-2', 'type': 'version'}]}, 'similarity': np.float64(221.18223963257884)}, {'metadata': {'doc_id': '1284', 'name': 'Improper Validation of Specified Quantity in Input', 'source': 'sparse', 'original_content': 'The product receives input that is expected to specify a quantity (such as size or length), but it does not validate or incorrectly validates that the quantity has the required properties.', 'keyphrase_sources': [{'id': 'rootcause:Improper Input Validation', 'keyphrase': 'Improper Input Validation', 'type': 'rootcause'}, {'id': 'rootcause:Input Validation vulnerability', 'keyphrase': 'Input Validation vulnerability', 'type': 'rootcause'}, {'id': 'attacker:attacker', 'keyphrase': 'attacker', 'type': 'attacker'}]}, 'similarity': np.float64(204.6485853858864)}, {'metadata': {'doc_id': '1285', 'name': 'Improper Validation of Specified Index, Position, or Offset in Input', 'source': 'sparse', 'original_content': 'The product receives input that is expected to specify an index, position, or offset into an indexable resource such as a buffer or file, but it does not validate or incorrectly validates that the specified index/position/offset has the required properties.', 'keyphrase_sources': [{'id': 'rootcause:Improper Input Validation', 'keyphrase': 'Improper Input Validation', 'type': 'rootcause'}]}, 'similarity': np.float64(196.67543141620962)}, {'metadata': {'doc_id': '1333', 'name': 'Inefficient Regular Expression Complexity', 'source': 'sparse', 'original_content': 'The product uses a regular expression with an inefficient, possibly exponential worst-case computational complexity that consumes excessive CPU cycles.', 'keyphrase_sources': [{'id': 'rootcause:Improper Input Validation', 'keyphrase': 'Improper Input Validation', 'type': 'rootcause'}, {'id': 'rootcause:Input Validation vulnerability', 'keyphrase': 'Input Validation vulnerability', 'type': 'rootcause'}, {'id': 'vector:specifically crafted messages', 'keyphrase': 'specifically crafted messages', 'type': 'vector'}, {'id': 'attacker:attacker', 'keyphrase': 'attacker', 'type': 'attacker'}, {'id': 'version:6.0.0 through 6.1.1-2', 'keyphrase': '6.0.0 through 6.1.1-2', 'type': 'version'}]}, 'similarity': np.float64(195.76286336253656)}, {'metadata': {'doc_id': '1286', 'name': 'Improper Validation of Syntactic Correctness of Input', 'source': 'sparse', 'original_content': 'The product receives input that is expected to be well-formed - i.e., to comply with a certain syntax - but it does not validate or incorrectly validates that the input complies with the syntax.', 'keyphrase_sources': [{'id': 'rootcause:Improper Input Validation', 'keyphrase': 'Improper Input Validation', 'type': 'rootcause'}]}, 'similarity': np.float64(195.3853427597707)}, {'metadata': {'doc_id': '787', 'name': 'Out-of-bounds Write', 'source': 'sparse', 'original_content': 'The product writes data past the end, or before the beginning, of the intended buffer.', 'keyphrase_sources': [{'id': 'rootcause:Input Validation vulnerability', 'keyphrase': 'Input Validation vulnerability', 'type': 'rootcause'}, {'id': 'impact:cause services to crash', 'keyphrase': 'cause services to crash', 'type': 'impact'}, {'id': 'attacker:attacker', 'keyphrase': 'attacker', 'type': 'attacker'}, {'id': 'product:ABB 800xA Base', 'keyphrase': 'ABB 800xA Base', 'type': 'product'}, {'id': 'version:6.0.0 through 6.1.1-2', 'keyphrase': '6.0.0 through 6.1.1-2', 'type': 'version'}]}, 'similarity': np.float64(192.82736872456024)}, {'metadata': {'doc_id': '502', 'name': 'Deserialization of Untrusted Data', 'source': 'sparse', 'original_content': 'The product deserializes untrusted data without sufficiently ensuring that the resulting data will be valid.', 'keyphrase_sources': [{'id': 'rootcause:Input Validation vulnerability', 'keyphrase': 'Input Validation vulnerability', 'type': 'rootcause'}, {'id': 'impact:cause services to crash', 'keyphrase': 'cause services to crash', 'type': 'impact'}, {'id': 'vector:specifically crafted messages', 'keyphrase': 'specifically crafted messages', 'type': 'vector'}, {'id': 'attacker:attacker', 'keyphrase': 'attacker', 'type': 'attacker'}, {'id': 'product:ABB 800xA Base', 'keyphrase': 'ABB 800xA Base', 'type': 'product'}, {'id': 'version:6.0.0 through 6.1.1-2', 'keyphrase': '6.0.0 through 6.1.1-2', 'type': 'version'}]}, 'similarity': np.float64(192.5358540458027)}, {'metadata': {'doc_id': '248', 'name': 'Uncaught Exception', 'source': 'sparse', 'original_content': 'An exception is thrown from a function, but it is not caught.', 'keyphrase_sources': [{'id': 'impact:cause services to crash', 'keyphrase': 'cause services to crash', 'type': 'impact'}]}, 'similarity': np.float64(75.19903075528174)}, {'metadata': {'doc_id': '113', 'name': \"Improper Neutralization of CRLF Sequences in HTTP Headers ('HTTP Request/Response Splitting')\", 'source': 'sparse', 'original_content': 'The product receives data from an HTTP agent/component (e.g., web server, proxy, browser, etc.), but it does not neutralize or incorrectly neutralizes CR and LF characters before the data is included in outgoing HTTP headers.', 'keyphrase_sources': [{'id': 'version:6.0.0 through 6.1.1-2', 'keyphrase': '6.0.0 through 6.1.1-2', 'type': 'version'}]}, 'similarity': np.float64(74.51157984983467)}, {'metadata': {'doc_id': '789', 'name': 'Memory Allocation with Excessive Size Value', 'source': 'sparse', 'original_content': 'The product allocates memory based on an untrusted, large size value, but it does not ensure that the size is within expected limits, allowing arbitrary amounts of memory to be allocated.', 'keyphrase_sources': [{'id': 'impact:cause services to crash', 'keyphrase': 'cause services to crash', 'type': 'impact'}]}, 'similarity': np.float64(74.39220095697203)}, {'metadata': {'doc_id': '257', 'name': 'Storing Passwords in a Recoverable Format', 'source': 'sparse', 'original_content': 'The storage of passwords in a recoverable format makes them subject to password reuse attacks by malicious users. In fact, it should be noted that recoverable encrypted passwords provide no significant benefit over plaintext passwords since they are subject not only to reuse by malicious attackers but also by malicious insiders. If a system administrator can recover a password directly, or use a brute force search on the available information, the administrator can use the password on other accounts.', 'keyphrase_sources': [{'id': 'product:ABB 800xA Base', 'keyphrase': 'ABB 800xA Base', 'type': 'product'}]}, 'similarity': np.float64(70.24637060138835)}, {'metadata': {'doc_id': '312', 'name': 'Cleartext Storage of Sensitive Information', 'source': 'sparse', 'original_content': 'The product stores sensitive information in cleartext within a resource that might be accessible to another control sphere.', 'keyphrase_sources': [{'id': 'product:ABB 800xA Base', 'keyphrase': 'ABB 800xA Base', 'type': 'product'}]}, 'similarity': np.float64(67.64444291431546)}, {'metadata': {'doc_id': '93', 'name': \"Improper Neutralization of CRLF Sequences ('CRLF Injection')\", 'source': 'sparse', 'original_content': 'The product uses CRLF (carriage return line feeds) as a special element, e.g. to separate lines or records, but it does not neutralize or incorrectly neutralizes CRLF sequences from inputs.', 'keyphrase_sources': [{'id': 'vector:specifically crafted messages', 'keyphrase': 'specifically crafted messages', 'type': 'vector'}]}, 'similarity': np.float64(64.50548499638585)}, {'metadata': {'doc_id': '835', 'name': \"Loop with Unreachable Exit Condition ('Infinite Loop')\", 'source': 'sparse', 'original_content': 'The product contains an iteration or loop with an exit condition that cannot be reached, i.e., an infinite loop.', 'keyphrase_sources': [{'id': 'vector:specifically crafted messages', 'keyphrase': 'specifically crafted messages', 'type': 'vector'}]}, 'similarity': np.float64(64.33495832483477)}], identified_cwes={'analyzer': [], 'critic_additional': []})",
  "retrieval_results": {
    "has_multiple_keyphrases": true,
    "keyphrase_cwe_sets": {
      "rootcause:Improper Input Validation": {
        "keyphrase": "Improper Input Validation",
        "type": "rootcause",
        "cwes": [
          {
            "metadata": {
              "doc_id": "20",
              "name": "Improper Input Validation",
              "source": "sparse",
              "original_content": "The product receives input or data, but it does\n        not validate or incorrectly validates that the input has the\n        properties that are required to process the data safely and\n        correctly.",
              "keyphrase_sources": [
                {
                  "id": "rootcause:Improper Input Validation",
                  "keyphrase": "Improper Input Validation",
                  "type": "rootcause"
                },
                {
                  "id": "rootcause:Input Validation vulnerability",
                  "keyphrase": "Input Validation vulnerability",
                  "type": "rootcause"
                },
                {
                  "id": "impact:cause services to crash",
                  "keyphrase": "cause services to crash",
                  "type": "impact"
                },
                {
                  "id": "vector:specifically crafted messages",
                  "keyphrase": "specifically crafted messages",
                  "type": "vector"
                },
                {
                  "id": "attacker:attacker",
                  "keyphrase": "attacker",
                  "type": "attacker"
                },
                {
                  "id": "product:ABB 800xA Base",
                  "keyphrase": "ABB 800xA Base",
                  "type": "product"
                },
                {
                  "id": "version:6.0.0 through 6.1.1-2",
                  "keyphrase": "6.0.0 through 6.1.1-2",
                  "type": "version"
                }
              ]
            },
            "similarity": 221.18223963257884
          },
          {
            "metadata": {
              "doc_id": "1284",
              "name": "Improper Validation of Specified Quantity in Input",
              "source": "sparse",
              "original_content": "The product receives input that is expected to specify a quantity (such as size or length), but it does not validate or incorrectly validates that the quantity has the required properties.",
              "keyphrase_sources": [
                {
                  "id": "rootcause:Improper Input Validation",
                  "keyphrase": "Improper Input Validation",
                  "type": "rootcause"
                },
                {
                  "id": "rootcause:Input Validation vulnerability",
                  "keyphrase": "Input Validation vulnerability",
                  "type": "rootcause"
                },
                {
                  "id": "attacker:attacker",
                  "keyphrase": "attacker",
                  "type": "attacker"
                }
              ]
            },
            "similarity": 204.6485853858864
          },
          {
            "metadata": {
              "doc_id": "1285",
              "name": "Improper Validation of Specified Index, Position, or Offset in Input",
              "source": "sparse",
              "original_content": "The product receives input that is expected to specify an index, position, or offset into an indexable resource such as a buffer or file, but it does not validate or incorrectly validates that the specified index/position/offset has the required properties.",
              "keyphrase_sources": [
                {
                  "id": "rootcause:Improper Input Validation",
                  "keyphrase": "Improper Input Validation",
                  "type": "rootcause"
                }
              ]
            },
            "similarity": 196.67543141620962
          },
          {
            "metadata": {
              "doc_id": "1333",
              "name": "Inefficient Regular Expression Complexity",
              "source": "sparse",
              "original_content": "The product uses a regular expression with an inefficient, possibly exponential worst-case computational complexity that consumes excessive CPU cycles.",
              "keyphrase_sources": [
                {
                  "id": "rootcause:Improper Input Validation",
                  "keyphrase": "Improper Input Validation",
                  "type": "rootcause"
                },
                {
                  "id": "rootcause:Input Validation vulnerability",
                  "keyphrase": "Input Validation vulnerability",
                  "type": "rootcause"
                },
                {
                  "id": "vector:specifically crafted messages",
                  "keyphrase": "specifically crafted messages",
                  "type": "vector"
                },
                {
                  "id": "attacker:attacker",
                  "keyphrase": "attacker",
                  "type": "attacker"
                },
                {
                  "id": "version:6.0.0 through 6.1.1-2",
                  "keyphrase": "6.0.0 through 6.1.1-2",
                  "type": "version"
                }
              ]
            },
            "similarity": 195.76286336253656
          },
          {
            "metadata": {
              "doc_id": "1286",
              "name": "Improper Validation of Syntactic Correctness of Input",
              "source": "sparse",
              "original_content": "The product receives input that is expected to be well-formed - i.e., to comply with a certain syntax - but it does not validate or incorrectly validates that the input complies with the syntax.",
              "keyphrase_sources": [
                {
                  "id": "rootcause:Improper Input Validation",
                  "keyphrase": "Improper Input Validation",
                  "type": "rootcause"
                }
              ]
            },
            "similarity": 195.3853427597707
          }
        ]
      },
      "rootcause:Input Validation vulnerability": {
        "keyphrase": "Input Validation vulnerability",
        "type": "rootcause",
        "cwes": [
          {
            "metadata": {
              "doc_id": "20",
              "name": "Improper Input Validation",
              "source": "sparse",
              "original_content": "The product receives input or data, but it does\n        not validate or incorrectly validates that the input has the\n        properties that are required to process the data safely and\n        correctly."
            },
            "similarity": 216.4292611151444
          },
          {
            "metadata": {
              "doc_id": "1284",
              "name": "Improper Validation of Specified Quantity in Input",
              "source": "sparse",
              "original_content": "The product receives input that is expected to specify a quantity (such as size or length), but it does not validate or incorrectly validates that the quantity has the required properties."
            },
            "similarity": 201.5936755216166
          },
          {
            "metadata": {
              "doc_id": "1333",
              "name": "Inefficient Regular Expression Complexity",
              "source": "sparse",
              "original_content": "The product uses a regular expression with an inefficient, possibly exponential worst-case computational complexity that consumes excessive CPU cycles."
            },
            "similarity": 198.11389900408253
          },
          {
            "metadata": {
              "doc_id": "787",
              "name": "Out-of-bounds Write",
              "source": "sparse",
              "original_content": "The product writes data past the end, or before the beginning, of the intended buffer.",
              "keyphrase_sources": [
                {
                  "id": "rootcause:Input Validation vulnerability",
                  "keyphrase": "Input Validation vulnerability",
                  "type": "rootcause"
                },
                {
                  "id": "impact:cause services to crash",
                  "keyphrase": "cause services to crash",
                  "type": "impact"
                },
                {
                  "id": "attacker:attacker",
                  "keyphrase": "attacker",
                  "type": "attacker"
                },
                {
                  "id": "product:ABB 800xA Base",
                  "keyphrase": "ABB 800xA Base",
                  "type": "product"
                },
                {
                  "id": "version:6.0.0 through 6.1.1-2",
                  "keyphrase": "6.0.0 through 6.1.1-2",
                  "type": "version"
                }
              ]
            },
            "similarity": 192.82736872456024
          },
          {
            "metadata": {
              "doc_id": "502",
              "name": "Deserialization of Untrusted Data",
              "source": "sparse",
              "original_content": "The product deserializes untrusted data without sufficiently ensuring that the resulting data will be valid.",
              "keyphrase_sources": [
                {
                  "id": "rootcause:Input Validation vulnerability",
                  "keyphrase": "Input Validation vulnerability",
                  "type": "rootcause"
                },
                {
                  "id": "impact:cause services to crash",
                  "keyphrase": "cause services to crash",
                  "type": "impact"
                },
                {
                  "id": "vector:specifically crafted messages",
                  "keyphrase": "specifically crafted messages",
                  "type": "vector"
                },
                {
                  "id": "attacker:attacker",
                  "keyphrase": "attacker",
                  "type": "attacker"
                },
                {
                  "id": "product:ABB 800xA Base",
                  "keyphrase": "ABB 800xA Base",
                  "type": "product"
                },
                {
                  "id": "version:6.0.0 through 6.1.1-2",
                  "keyphrase": "6.0.0 through 6.1.1-2",
                  "type": "version"
                }
              ]
            },
            "similarity": 192.5358540458027
          }
        ]
      },
      "impact:cause services to crash": {
        "keyphrase": "cause services to crash",
        "type": "impact",
        "cwes": [
          {
            "metadata": {
              "doc_id": "502",
              "name": "Deserialization of Untrusted Data",
              "source": "sparse",
              "original_content": "The product deserializes untrusted data without sufficiently ensuring that the resulting data will be valid."
            },
            "similarity": 77.85233161221002
          },
          {
            "metadata": {
              "doc_id": "20",
              "name": "Improper Input Validation",
              "source": "sparse",
              "original_content": "The product receives input or data, but it does\n        not validate or incorrectly validates that the input has the\n        properties that are required to process the data safely and\n        correctly."
            },
            "similarity": 77.51407082052073
          },
          {
            "metadata": {
              "doc_id": "248",
              "name": "Uncaught Exception",
              "source": "sparse",
              "original_content": "An exception is thrown from a function, but it is not caught.",
              "keyphrase_sources": [
                {
                  "id": "impact:cause services to crash",
                  "keyphrase": "cause services to crash",
                  "type": "impact"
                }
              ]
            },
            "similarity": 75.19903075528174
          },
          {
            "metadata": {
              "doc_id": "787",
              "name": "Out-of-bounds Write",
              "source": "sparse",
              "original_content": "The product writes data past the end, or before the beginning, of the intended buffer."
            },
            "similarity": 75.02948209674348
          },
          {
            "metadata": {
              "doc_id": "789",
              "name": "Memory Allocation with Excessive Size Value",
              "source": "sparse",
              "original_content": "The product allocates memory based on an untrusted, large size value, but it does not ensure that the size is within expected limits, allowing arbitrary amounts of memory to be allocated.",
              "keyphrase_sources": [
                {
                  "id": "impact:cause services to crash",
                  "keyphrase": "cause services to crash",
                  "type": "impact"
                }
              ]
            },
            "similarity": 74.39220095697203
          }
        ]
      },
      "vector:specifically crafted messages": {
        "keyphrase": "specifically crafted messages",
        "type": "vector",
        "cwes": [
          {
            "metadata": {
              "doc_id": "1333",
              "name": "Inefficient Regular Expression Complexity",
              "source": "sparse",
              "original_content": "The product uses a regular expression with an inefficient, possibly exponential worst-case computational complexity that consumes excessive CPU cycles."
            },
            "similarity": 68.95717832457133
          },
          {
            "metadata": {
              "doc_id": "20",
              "name": "Improper Input Validation",
              "source": "sparse",
              "original_content": "The product receives input or data, but it does\n        not validate or incorrectly validates that the input has the\n        properties that are required to process the data safely and\n        correctly."
            },
            "similarity": 67.04848286288438
          },
          {
            "metadata": {
              "doc_id": "502",
              "name": "Deserialization of Untrusted Data",
              "source": "sparse",
              "original_content": "The product deserializes untrusted data without sufficiently ensuring that the resulting data will be valid."
            },
            "similarity": 65.61002367948802
          },
          {
            "metadata": {
              "doc_id": "93",
              "name": "Improper Neutralization of CRLF Sequences ('CRLF Injection')",
              "source": "sparse",
              "original_content": "The product uses CRLF (carriage return line feeds) as a special element, e.g. to separate lines or records, but it does not neutralize or incorrectly neutralizes CRLF sequences from inputs.",
              "keyphrase_sources": [
                {
                  "id": "vector:specifically crafted messages",
                  "keyphrase": "specifically crafted messages",
                  "type": "vector"
                }
              ]
            },
            "similarity": 64.50548499638585
          },
          {
            "metadata": {
              "doc_id": "835",
              "name": "Loop with Unreachable Exit Condition ('Infinite Loop')",
              "source": "sparse",
              "original_content": "The product contains an iteration or loop with an exit condition that cannot be reached, i.e., an infinite loop.",
              "keyphrase_sources": [
                {
                  "id": "vector:specifically crafted messages",
                  "keyphrase": "specifically crafted messages",
                  "type": "vector"
                }
              ]
            },
            "similarity": 64.33495832483477
          }
        ]
      },
      "attacker:attacker": {
        "keyphrase": "attacker",
        "type": "attacker",
        "cwes": [
          {
            "metadata": {
              "doc_id": "20",
              "name": "Improper Input Validation",
              "source": "sparse",
              "original_content": "The product receives input or data, but it does\n        not validate or incorrectly validates that the input has the\n        properties that are required to process the data safely and\n        correctly."
            },
            "similarity": 66.8483595639624
          },
          {
            "metadata": {
              "doc_id": "502",
              "name": "Deserialization of Untrusted Data",
              "source": "sparse",
              "original_content": "The product deserializes untrusted data without sufficiently ensuring that the resulting data will be valid."
            },
            "similarity": 66.22572379412296
          },
          {
            "metadata": {
              "doc_id": "787",
              "name": "Out-of-bounds Write",
              "source": "sparse",
              "original_content": "The product writes data past the end, or before the beginning, of the intended buffer."
            },
            "similarity": 64.34752807576578
          },
          {
            "metadata": {
              "doc_id": "1284",
              "name": "Improper Validation of Specified Quantity in Input",
              "source": "sparse",
              "original_content": "The product receives input that is expected to specify a quantity (such as size or length), but it does not validate or incorrectly validates that the quantity has the required properties."
            },
            "similarity": 62.50158073782637
          },
          {
            "metadata": {
              "doc_id": "1333",
              "name": "Inefficient Regular Expression Complexity",
              "source": "sparse",
              "original_content": "The product uses a regular expression with an inefficient, possibly exponential worst-case computational complexity that consumes excessive CPU cycles."
            },
            "similarity": 62.21698950892026
          }
        ]
      },
      "product:ABB 800xA Base": {
        "keyphrase": "ABB 800xA Base",
        "type": "product",
        "cwes": [
          {
            "metadata": {
              "doc_id": "257",
              "name": "Storing Passwords in a Recoverable Format",
              "source": "sparse",
              "original_content": "The storage of passwords in a recoverable format makes them subject to password reuse attacks by malicious users. In fact, it should be noted that recoverable encrypted passwords provide no significant benefit over plaintext passwords since they are subject not only to reuse by malicious attackers but also by malicious insiders. If a system administrator can recover a password directly, or use a brute force search on the available information, the administrator can use the password on other accounts.",
              "keyphrase_sources": [
                {
                  "id": "product:ABB 800xA Base",
                  "keyphrase": "ABB 800xA Base",
                  "type": "product"
                }
              ]
            },
            "similarity": 70.24637060138835
          },
          {
            "metadata": {
              "doc_id": "312",
              "name": "Cleartext Storage of Sensitive Information",
              "source": "sparse",
              "original_content": "The product stores sensitive information in cleartext within a resource that might be accessible to another control sphere.",
              "keyphrase_sources": [
                {
                  "id": "product:ABB 800xA Base",
                  "keyphrase": "ABB 800xA Base",
                  "type": "product"
                }
              ]
            },
            "similarity": 67.64444291431546
          },
          {
            "metadata": {
              "doc_id": "20",
              "name": "Improper Input Validation",
              "source": "sparse",
              "original_content": "The product receives input or data, but it does\n        not validate or incorrectly validates that the input has the\n        properties that are required to process the data safely and\n        correctly."
            },
            "similarity": 64.36330426815219
          },
          {
            "metadata": {
              "doc_id": "502",
              "name": "Deserialization of Untrusted Data",
              "source": "sparse",
              "original_content": "The product deserializes untrusted data without sufficiently ensuring that the resulting data will be valid."
            },
            "similarity": 61.97363910106918
          },
          {
            "metadata": {
              "doc_id": "787",
              "name": "Out-of-bounds Write",
              "source": "sparse",
              "original_content": "The product writes data past the end, or before the beginning, of the intended buffer."
            },
            "similarity": 58.804944211834986
          }
        ]
      },
      "version:6.0.0 through 6.1.1-2": {
        "keyphrase": "6.0.0 through 6.1.1-2",
        "type": "version",
        "cwes": [
          {
            "metadata": {
              "doc_id": "502",
              "name": "Deserialization of Untrusted Data",
              "source": "sparse",
              "original_content": "The product deserializes untrusted data without sufficiently ensuring that the resulting data will be valid."
            },
            "similarity": 78.60366654267881
          },
          {
            "metadata": {
              "doc_id": "20",
              "name": "Improper Input Validation",
              "source": "sparse",
              "original_content": "The product receives input or data, but it does\n        not validate or incorrectly validates that the input has the\n        properties that are required to process the data safely and\n        correctly."
            },
            "similarity": 76.47429608024139
          },
          {
            "metadata": {
              "doc_id": "787",
              "name": "Out-of-bounds Write",
              "source": "sparse",
              "original_content": "The product writes data past the end, or before the beginning, of the intended buffer."
            },
            "similarity": 75.59421632824896
          },
          {
            "metadata": {
              "doc_id": "1333",
              "name": "Inefficient Regular Expression Complexity",
              "source": "sparse",
              "original_content": "The product uses a regular expression with an inefficient, possibly exponential worst-case computational complexity that consumes excessive CPU cycles."
            },
            "similarity": 74.67204101043814
          },
          {
            "metadata": {
              "doc_id": "113",
              "name": "Improper Neutralization of CRLF Sequences in HTTP Headers ('HTTP Request/Response Splitting')",
              "source": "sparse",
              "original_content": "The product receives data from an HTTP agent/component (e.g., web server, proxy, browser, etc.), but it does not neutralize or incorrectly neutralizes CR and LF characters before the data is included in outgoing HTTP headers.",
              "keyphrase_sources": [
                {
                  "id": "version:6.0.0 through 6.1.1-2",
                  "keyphrase": "6.0.0 through 6.1.1-2",
                  "type": "version"
                }
              ]
            },
            "similarity": 74.51157984983467
          }
        ]
      }
    },
    "keyphrase_mapping": {
      "20": [
        {
          "id": "rootcause:Improper Input Validation",
          "keyphrase": "Improper Input Validation",
          "type": "rootcause"
        },
        {
          "id": "rootcause:Input Validation vulnerability",
          "keyphrase": "Input Validation vulnerability",
          "type": "rootcause"
        },
        {
          "id": "impact:cause services to crash",
          "keyphrase": "cause services to crash",
          "type": "impact"
        },
        {
          "id": "vector:specifically crafted messages",
          "keyphrase": "specifically crafted messages",
          "type": "vector"
        },
        {
          "id": "attacker:attacker",
          "keyphrase": "attacker",
          "type": "attacker"
        },
        {
          "id": "product:ABB 800xA Base",
          "keyphrase": "ABB 800xA Base",
          "type": "product"
        },
        {
          "id": "version:6.0.0 through 6.1.1-2",
          "keyphrase": "6.0.0 through 6.1.1-2",
          "type": "version"
        }
      ],
      "1284": [
        {
          "id": "rootcause:Improper Input Validation",
          "keyphrase": "Improper Input Validation",
          "type": "rootcause"
        },
        {
          "id": "rootcause:Input Validation vulnerability",
          "keyphrase": "Input Validation vulnerability",
          "type": "rootcause"
        },
        {
          "id": "attacker:attacker",
          "keyphrase": "attacker",
          "type": "attacker"
        }
      ],
      "1285": [
        {
          "id": "rootcause:Improper Input Validation",
          "keyphrase": "Improper Input Validation",
          "type": "rootcause"
        }
      ],
      "1333": [
        {
          "id": "rootcause:Improper Input Validation",
          "keyphrase": "Improper Input Validation",
          "type": "rootcause"
        },
        {
          "id": "rootcause:Input Validation vulnerability",
          "keyphrase": "Input Validation vulnerability",
          "type": "rootcause"
        },
        {
          "id": "vector:specifically crafted messages",
          "keyphrase": "specifically crafted messages",
          "type": "vector"
        },
        {
          "id": "attacker:attacker",
          "keyphrase": "attacker",
          "type": "attacker"
        },
        {
          "id": "version:6.0.0 through 6.1.1-2",
          "keyphrase": "6.0.0 through 6.1.1-2",
          "type": "version"
        }
      ],
      "1286": [
        {
          "id": "rootcause:Improper Input Validation",
          "keyphrase": "Improper Input Validation",
          "type": "rootcause"
        }
      ],
      "787": [
        {
          "id": "rootcause:Input Validation vulnerability",
          "keyphrase": "Input Validation vulnerability",
          "type": "rootcause"
        },
        {
          "id": "impact:cause services to crash",
          "keyphrase": "cause services to crash",
          "type": "impact"
        },
        {
          "id": "attacker:attacker",
          "keyphrase": "attacker",
          "type": "attacker"
        },
        {
          "id": "product:ABB 800xA Base",
          "keyphrase": "ABB 800xA Base",
          "type": "product"
        },
        {
          "id": "version:6.0.0 through 6.1.1-2",
          "keyphrase": "6.0.0 through 6.1.1-2",
          "type": "version"
        }
      ],
      "502": [
        {
          "id": "rootcause:Input Validation vulnerability",
          "keyphrase": "Input Validation vulnerability",
          "type": "rootcause"
        },
        {
          "id": "impact:cause services to crash",
          "keyphrase": "cause services to crash",
          "type": "impact"
        },
        {
          "id": "vector:specifically crafted messages",
          "keyphrase": "specifically crafted messages",
          "type": "vector"
        },
        {
          "id": "attacker:attacker",
          "keyphrase": "attacker",
          "type": "attacker"
        },
        {
          "id": "product:ABB 800xA Base",
          "keyphrase": "ABB 800xA Base",
          "type": "product"
        },
        {
          "id": "version:6.0.0 through 6.1.1-2",
          "keyphrase": "6.0.0 through 6.1.1-2",
          "type": "version"
        }
      ],
      "248": [
        {
          "id": "impact:cause services to crash",
          "keyphrase": "cause services to crash",
          "type": "impact"
        }
      ],
      "789": [
        {
          "id": "impact:cause services to crash",
          "keyphrase": "cause services to crash",
          "type": "impact"
        }
      ],
      "93": [
        {
          "id": "vector:specifically crafted messages",
          "keyphrase": "specifically crafted messages",
          "type": "vector"
        }
      ],
      "835": [
        {
          "id": "vector:specifically crafted messages",
          "keyphrase": "specifically crafted messages",
          "type": "vector"
        }
      ],
      "257": [
        {
          "id": "product:ABB 800xA Base",
          "keyphrase": "ABB 800xA Base",
          "type": "product"
        }
      ],
      "312": [
        {
          "id": "product:ABB 800xA Base",
          "keyphrase": "ABB 800xA Base",
          "type": "product"
        }
      ],
      "113": [
        {
          "id": "version:6.0.0 through 6.1.1-2",
          "keyphrase": "6.0.0 through 6.1.1-2",
          "type": "version"
        }
      ]
    },
    "relevant_cwes": [
      {
        "metadata": {
          "doc_id": "20",
          "name": "Improper Input Validation",
          "source": "sparse",
          "original_content": "The product receives input or data, but it does\n        not validate or incorrectly validates that the input has the\n        properties that are required to process the data safely and\n        correctly.",
          "keyphrase_sources": [
            {
              "id": "rootcause:Improper Input Validation",
              "keyphrase": "Improper Input Validation",
              "type": "rootcause"
            },
            {
              "id": "rootcause:Input Validation vulnerability",
              "keyphrase": "Input Validation vulnerability",
              "type": "rootcause"
            },
            {
              "id": "impact:cause services to crash",
              "keyphrase": "cause services to crash",
              "type": "impact"
            },
            {
              "id": "vector:specifically crafted messages",
              "keyphrase": "specifically crafted messages",
              "type": "vector"
            },
            {
              "id": "attacker:attacker",
              "keyphrase": "attacker",
              "type": "attacker"
            },
            {
              "id": "product:ABB 800xA Base",
              "keyphrase": "ABB 800xA Base",
              "type": "product"
            },
            {
              "id": "version:6.0.0 through 6.1.1-2",
              "keyphrase": "6.0.0 through 6.1.1-2",
              "type": "version"
            }
          ]
        },
        "similarity": 221.18223963257884
      },
      {
        "metadata": {
          "doc_id": "1284",
          "name": "Improper Validation of Specified Quantity in Input",
          "source": "sparse",
          "original_content": "The product receives input that is expected to specify a quantity (such as size or length), but it does not validate or incorrectly validates that the quantity has the required properties.",
          "keyphrase_sources": [
            {
              "id": "rootcause:Improper Input Validation",
              "keyphrase": "Improper Input Validation",
              "type": "rootcause"
            },
            {
              "id": "rootcause:Input Validation vulnerability",
              "keyphrase": "Input Validation vulnerability",
              "type": "rootcause"
            },
            {
              "id": "attacker:attacker",
              "keyphrase": "attacker",
              "type": "attacker"
            }
          ]
        },
        "similarity": 204.6485853858864
      },
      {
        "metadata": {
          "doc_id": "1285",
          "name": "Improper Validation of Specified Index, Position, or Offset in Input",
          "source": "sparse",
          "original_content": "The product receives input that is expected to specify an index, position, or offset into an indexable resource such as a buffer or file, but it does not validate or incorrectly validates that the specified index/position/offset has the required properties.",
          "keyphrase_sources": [
            {
              "id": "rootcause:Improper Input Validation",
              "keyphrase": "Improper Input Validation",
              "type": "rootcause"
            }
          ]
        },
        "similarity": 196.67543141620962
      },
      {
        "metadata": {
          "doc_id": "1333",
          "name": "Inefficient Regular Expression Complexity",
          "source": "sparse",
          "original_content": "The product uses a regular expression with an inefficient, possibly exponential worst-case computational complexity that consumes excessive CPU cycles.",
          "keyphrase_sources": [
            {
              "id": "rootcause:Improper Input Validation",
              "keyphrase": "Improper Input Validation",
              "type": "rootcause"
            },
            {
              "id": "rootcause:Input Validation vulnerability",
              "keyphrase": "Input Validation vulnerability",
              "type": "rootcause"
            },
            {
              "id": "vector:specifically crafted messages",
              "keyphrase": "specifically crafted messages",
              "type": "vector"
            },
            {
              "id": "attacker:attacker",
              "keyphrase": "attacker",
              "type": "attacker"
            },
            {
              "id": "version:6.0.0 through 6.1.1-2",
              "keyphrase": "6.0.0 through 6.1.1-2",
              "type": "version"
            }
          ]
        },
        "similarity": 195.76286336253656
      },
      {
        "metadata": {
          "doc_id": "1286",
          "name": "Improper Validation of Syntactic Correctness of Input",
          "source": "sparse",
          "original_content": "The product receives input that is expected to be well-formed - i.e., to comply with a certain syntax - but it does not validate or incorrectly validates that the input complies with the syntax.",
          "keyphrase_sources": [
            {
              "id": "rootcause:Improper Input Validation",
              "keyphrase": "Improper Input Validation",
              "type": "rootcause"
            }
          ]
        },
        "similarity": 195.3853427597707
      },
      {
        "metadata": {
          "doc_id": "787",
          "name": "Out-of-bounds Write",
          "source": "sparse",
          "original_content": "The product writes data past the end, or before the beginning, of the intended buffer.",
          "keyphrase_sources": [
            {
              "id": "rootcause:Input Validation vulnerability",
              "keyphrase": "Input Validation vulnerability",
              "type": "rootcause"
            },
            {
              "id": "impact:cause services to crash",
              "keyphrase": "cause services to crash",
              "type": "impact"
            },
            {
              "id": "attacker:attacker",
              "keyphrase": "attacker",
              "type": "attacker"
            },
            {
              "id": "product:ABB 800xA Base",
              "keyphrase": "ABB 800xA Base",
              "type": "product"
            },
            {
              "id": "version:6.0.0 through 6.1.1-2",
              "keyphrase": "6.0.0 through 6.1.1-2",
              "type": "version"
            }
          ]
        },
        "similarity": 192.82736872456024
      },
      {
        "metadata": {
          "doc_id": "502",
          "name": "Deserialization of Untrusted Data",
          "source": "sparse",
          "original_content": "The product deserializes untrusted data without sufficiently ensuring that the resulting data will be valid.",
          "keyphrase_sources": [
            {
              "id": "rootcause:Input Validation vulnerability",
              "keyphrase": "Input Validation vulnerability",
              "type": "rootcause"
            },
            {
              "id": "impact:cause services to crash",
              "keyphrase": "cause services to crash",
              "type": "impact"
            },
            {
              "id": "vector:specifically crafted messages",
              "keyphrase": "specifically crafted messages",
              "type": "vector"
            },
            {
              "id": "attacker:attacker",
              "keyphrase": "attacker",
              "type": "attacker"
            },
            {
              "id": "product:ABB 800xA Base",
              "keyphrase": "ABB 800xA Base",
              "type": "product"
            },
            {
              "id": "version:6.0.0 through 6.1.1-2",
              "keyphrase": "6.0.0 through 6.1.1-2",
              "type": "version"
            }
          ]
        },
        "similarity": 192.5358540458027
      },
      {
        "metadata": {
          "doc_id": "248",
          "name": "Uncaught Exception",
          "source": "sparse",
          "original_content": "An exception is thrown from a function, but it is not caught.",
          "keyphrase_sources": [
            {
              "id": "impact:cause services to crash",
              "keyphrase": "cause services to crash",
              "type": "impact"
            }
          ]
        },
        "similarity": 75.19903075528174
      },
      {
        "metadata": {
          "doc_id": "113",
          "name": "Improper Neutralization of CRLF Sequences in HTTP Headers ('HTTP Request/Response Splitting')",
          "source": "sparse",
          "original_content": "The product receives data from an HTTP agent/component (e.g., web server, proxy, browser, etc.), but it does not neutralize or incorrectly neutralizes CR and LF characters before the data is included in outgoing HTTP headers.",
          "keyphrase_sources": [
            {
              "id": "version:6.0.0 through 6.1.1-2",
              "keyphrase": "6.0.0 through 6.1.1-2",
              "type": "version"
            }
          ]
        },
        "similarity": 74.51157984983467
      },
      {
        "metadata": {
          "doc_id": "789",
          "name": "Memory Allocation with Excessive Size Value",
          "source": "sparse",
          "original_content": "The product allocates memory based on an untrusted, large size value, but it does not ensure that the size is within expected limits, allowing arbitrary amounts of memory to be allocated.",
          "keyphrase_sources": [
            {
              "id": "impact:cause services to crash",
              "keyphrase": "cause services to crash",
              "type": "impact"
            }
          ]
        },
        "similarity": 74.39220095697203
      },
      {
        "metadata": {
          "doc_id": "257",
          "name": "Storing Passwords in a Recoverable Format",
          "source": "sparse",
          "original_content": "The storage of passwords in a recoverable format makes them subject to password reuse attacks by malicious users. In fact, it should be noted that recoverable encrypted passwords provide no significant benefit over plaintext passwords since they are subject not only to reuse by malicious attackers but also by malicious insiders. If a system administrator can recover a password directly, or use a brute force search on the available information, the administrator can use the password on other accounts.",
          "keyphrase_sources": [
            {
              "id": "product:ABB 800xA Base",
              "keyphrase": "ABB 800xA Base",
              "type": "product"
            }
          ]
        },
        "similarity": 70.24637060138835
      },
      {
        "metadata": {
          "doc_id": "312",
          "name": "Cleartext Storage of Sensitive Information",
          "source": "sparse",
          "original_content": "The product stores sensitive information in cleartext within a resource that might be accessible to another control sphere.",
          "keyphrase_sources": [
            {
              "id": "product:ABB 800xA Base",
              "keyphrase": "ABB 800xA Base",
              "type": "product"
            }
          ]
        },
        "similarity": 67.64444291431546
      },
      {
        "metadata": {
          "doc_id": "93",
          "name": "Improper Neutralization of CRLF Sequences ('CRLF Injection')",
          "source": "sparse",
          "original_content": "The product uses CRLF (carriage return line feeds) as a special element, e.g. to separate lines or records, but it does not neutralize or incorrectly neutralizes CRLF sequences from inputs.",
          "keyphrase_sources": [
            {
              "id": "vector:specifically crafted messages",
              "keyphrase": "specifically crafted messages",
              "type": "vector"
            }
          ]
        },
        "similarity": 64.50548499638585
      },
      {
        "metadata": {
          "doc_id": "835",
          "name": "Loop with Unreachable Exit Condition ('Infinite Loop')",
          "source": "sparse",
          "original_content": "The product contains an iteration or loop with an exit condition that cannot be reached, i.e., an infinite loop.",
          "keyphrase_sources": [
            {
              "id": "vector:specifically crafted messages",
              "keyphrase": "specifically crafted messages",
              "type": "vector"
            }
          ]
        },
        "similarity": 64.33495832483477
      }
    ],
    "enhanced_query": "# Vulnerability Description\n\n    **Improper Input Validation** vulnerability in ABB 800xA Base. An attacker who successfully exploited this vulnerability could cause services to crash by sending specifically crafted messages. This issue affects 800xA Base from 6.0.0 through 6.1.1-2.\n\n    # Keyphrase-Specific CWE Analysis\n    This vulnerability contains multiple keyphrases that may map to different CWEs. \n    Please analyze each keyphrase separately and determine the most appropriate CWE(s) for each.\n\n    ## ROOTCAUSE: 'Improper Input Validation'\n\nRelevant CWEs for this ROOTCAUSE:\n\n### 1. CWE-20: Improper Input Validation (Score: 221.18)\n\nThe product receives input or data, but it does\n        not validate or incorrectly validates that the input has the\n        properties that are required to process the data safely and\n        correctly....\n\n### 2. CWE-1284: Improper Validation of Specified Quantity in Input (Score: 204.65)\n\nThe product receives input that is expected to specify a quantity (such as size or length), but it does not validate or incorrectly validates that the quantity has the required properties....\n\n### 3. CWE-1285: Improper Validation of Specified Index, Position, or Offset in Input (Score: 196.68)\n\nThe product receives input that is expected to specify an index, position, or offset into an indexable resource such as a buffer or file, but it does not validate or incorrectly validates that the specified index/position/offset has the required properties....\n\n### 4. CWE-1333: Inefficient Regular Expression Complexity (Score: 195.76)\n\nThe product uses a regular expression with an inefficient, possibly exponential worst-case computational complexity that consumes excessive CPU cycles....\n\n### 5. CWE-1286: Improper Validation of Syntactic Correctness of Input (Score: 195.39)\n\nThe product receives input that is expected to be well-formed - i.e., to comply with a certain syntax - but it does not validate or incorrectly validates that the input complies with the syntax....\n\n## ROOTCAUSE: 'Input Validation vulnerability'\n\nRelevant CWEs for this ROOTCAUSE:\n\n### 1. CWE-20: Improper Input Validation (Score: 221.18)\n\nThe product receives input or data, but it does\n        not validate or incorrectly validates that the input has the\n        properties that are required to process the data safely and\n        correctly....\n\n### 2. CWE-1284: Improper Validation of Specified Quantity in Input (Score: 204.65)\n\nThe product receives input that is expected to specify a quantity (such as size or length), but it does not validate or incorrectly validates that the quantity has the required properties....\n\n### 3. CWE-1333: Inefficient Regular Expression Complexity (Score: 195.76)\n\nThe product uses a regular expression with an inefficient, possibly exponential worst-case computational complexity that consumes excessive CPU cycles....\n\n### 4. CWE-787: Out-of-bounds Write (Score: 192.83)\n\nThe product writes data past the end, or before the beginning, of the intended buffer....\n\n### 5. CWE-502: Deserialization of Untrusted Data (Score: 192.54)\n\nThe product deserializes untrusted data without sufficiently ensuring that the resulting data will be valid....\n\n## IMPACT: 'cause services to crash'\n\nRelevant CWEs for this IMPACT:\n\n### 1. CWE-20: Improper Input Validation (Score: 221.18)\n\nThe product receives input or data, but it does\n        not validate or incorrectly validates that the input has the\n        properties that are required to process the data safely and\n        correctly....\n\n### 2. CWE-787: Out-of-bounds Write (Score: 192.83)\n\nThe product writes data past the end, or before the beginning, of the intended buffer....\n\n### 3. CWE-502: Deserialization of Untrusted Data (Score: 192.54)\n\nThe product deserializes untrusted data without sufficiently ensuring that the resulting data will be valid....\n\n### 4. CWE-248: Uncaught Exception (Score: 75.20)\n\nAn exception is thrown from a function, but it is not caught....\n\n### 5. CWE-789: Memory Allocation with Excessive Size Value (Score: 74.39)\n\nThe product allocates memory based on an untrusted, large size value, but it does not ensure that the size is within expected limits, allowing arbitrary amounts of memory to be allocated....\n\n## VECTOR: 'specifically crafted messages'\n\nRelevant CWEs for this VECTOR:\n\n### 1. CWE-20: Improper Input Validation (Score: 221.18)\n\nThe product receives input or data, but it does\n        not validate or incorrectly validates that the input has the\n        properties that are required to process the data safely and\n        correctly....\n\n### 2. CWE-1333: Inefficient Regular Expression Complexity (Score: 195.76)\n\nThe product uses a regular expression with an inefficient, possibly exponential worst-case computational complexity that consumes excessive CPU cycles....\n\n### 3. CWE-502: Deserialization of Untrusted Data (Score: 192.54)\n\nThe product deserializes untrusted data without sufficiently ensuring that the resulting data will be valid....\n\n### 4. CWE-93: Improper Neutralization of CRLF Sequences ('CRLF Injection') (Score: 64.51)\n\nThe product uses CRLF (carriage return line feeds) as a special element, e.g. to separate lines or records, but it does not neutralize or incorrectly neutralizes CRLF sequences from inputs....\n\n### 5. CWE-835: Loop with Unreachable Exit Condition ('Infinite Loop') (Score: 64.33)\n\nThe product contains an iteration or loop with an exit condition that cannot be reached, i.e., an infinite loop....\n\n## ATTACKER: 'attacker'\n\nRelevant CWEs for this ATTACKER:\n\n### 1. CWE-20: Improper Input Validation (Score: 221.18)\n\nThe product receives input or data, but it does\n        not validate or incorrectly validates that the input has the\n        properties that are required to process the data safely and\n        correctly....\n\n### 2. CWE-1284: Improper Validation of Specified Quantity in Input (Score: 204.65)\n\nThe product receives input that is expected to specify a quantity (such as size or length), but it does not validate or incorrectly validates that the quantity has the required properties....\n\n### 3. CWE-1333: Inefficient Regular Expression Complexity (Score: 195.76)\n\nThe product uses a regular expression with an inefficient, possibly exponential worst-case computational complexity that consumes excessive CPU cycles....\n\n### 4. CWE-787: Out-of-bounds Write (Score: 192.83)\n\nThe product writes data past the end, or before the beginning, of the intended buffer....\n\n### 5. CWE-502: Deserialization of Untrusted Data (Score: 192.54)\n\nThe product deserializes untrusted data without sufficiently ensuring that the resulting data will be valid....\n\n## PRODUCT: 'ABB 800xA Base'\n\nRelevant CWEs for this PRODUCT:\n\n### 1. CWE-20: Improper Input Validation (Score: 221.18)\n\nThe product receives input or data, but it does\n        not validate or incorrectly validates that the input has the\n        properties that are required to process the data safely and\n        correctly....\n\n### 2. CWE-787: Out-of-bounds Write (Score: 192.83)\n\nThe product writes data past the end, or before the beginning, of the intended buffer....\n\n### 3. CWE-502: Deserialization of Untrusted Data (Score: 192.54)\n\nThe product deserializes untrusted data without sufficiently ensuring that the resulting data will be valid....\n\n### 4. CWE-257: Storing Passwords in a Recoverable Format (Score: 70.25)\n\nThe storage of passwords in a recoverable format makes them subject to password reuse attacks by malicious users. In fact, it should be noted that recoverable encrypted passwords provide no significant benefit over plaintext passwords since they are subject not only to reuse by malicious attackers b...\n\n### 5. CWE-312: Cleartext Storage of Sensitive Information (Score: 67.64)\n\nThe product stores sensitive information in cleartext within a resource that might be accessible to another control sphere....\n\n## VERSION: '6.0.0 through 6.1.1-2'\n\nRelevant CWEs for this VERSION:\n\n### 1. CWE-20: Improper Input Validation (Score: 221.18)\n\nThe product receives input or data, but it does\n        not validate or incorrectly validates that the input has the\n        properties that are required to process the data safely and\n        correctly....\n\n### 2. CWE-1333: Inefficient Regular Expression Complexity (Score: 195.76)\n\nThe product uses a regular expression with an inefficient, possibly exponential worst-case computational complexity that consumes excessive CPU cycles....\n\n### 3. CWE-787: Out-of-bounds Write (Score: 192.83)\n\nThe product writes data past the end, or before the beginning, of the intended buffer....\n\n### 4. CWE-502: Deserialization of Untrusted Data (Score: 192.54)\n\nThe product deserializes untrusted data without sufficiently ensuring that the resulting data will be valid....\n\n### 5. CWE-113: Improper Neutralization of CRLF Sequences in HTTP Headers ('HTTP Request/Response Splitting') (Score: 74.51)\n\nThe product receives data from an HTTP agent/component (e.g., web server, proxy, browser, etc.), but it does not neutralize or incorrectly neutralizes CR and LF characters before the data is included in outgoing HTTP headers....\n\n\n    # Analysis Instructions\n    1. For each keyphrase, identify the most appropriate CWE(s) that represent the weakness.\n    2. Consider how the different keyphrases might relate to each other in the vulnerability chain.\n    3. Provide a final determination of primary CWE(s) and any secondary CWEs.\n    4. Format your response using the standard analysis template.\n\n    Please analyze how these different weaknesses interact and provide a comprehensive CWE classification.\n    "
  },
  "retrieval_time": 2.3899307250976562
}