{
  "vulnerability_info": "VulnerabilityInfo(cve_id='CVE-2024-46953', description='An issue was discovered in base/gsdevice.c in Artifex Ghostscript before 10.04.0. An **integer overflow** when parsing the filename format string (for the output filename) results in **path truncation**, and possible **path traversal** and code execution.', key_phrases={'rootcause': '', 'weakness': ['integer overflow', 'path traversal', 'path truncation'], 'impact': 'path traversal and code execution', 'vector': '', 'attacker': '', 'product': 'Artifex Ghostscript', 'version': 'before 10.04.0', 'component': 'base/gsdevice.c'}, reference_content=\"Based on the provided content, here's a breakdown of the vulnerability information related to CVE-2024-46953:\\n\\n**Root Cause of Vulnerability:**\\n- An integer overflow occurs when parsing the filename format string for the output filename in the `base/gsdevice.c` file of Artifex Ghostscript.\\n\\n**Weaknesses/Vulnerabilities Present:**\\n- Integer overflow leading to path truncation.\\n- Potential for path traversal due to the truncation.\\n- Possible arbitrary code execution due to path traversal and control over file output.\\n\\n**Impact of Exploitation:**\\n- Arbitrary code execution is possible.\\n- Path traversal can lead to writing to arbitrary files.\\n- Truncated file paths could lead to information leaks or unintended file overwrites.\\n\\n**Attack Vectors:**\\n- The attack vector is local, meaning the attacker would need to have access to the system to trigger the vulnerability.\\n- The vulnerability is triggered via a specifically crafted filename format string.\\n- User interaction is required to trigger this vulnerability by processing a malicious file.\\n\\n**Required Attacker Capabilities/Position:**\\n- Local access to the system is required.\\n- An ability to supply a malicious file that triggers the vulnerable code is needed.\\n- No special privileges are needed, only a user that can execute the vulnerable ghostscript.\\n\\n**Additional Notes:**\\n- The vulnerability exists in Artifex Ghostscript versions prior to 10.04.0.\\n- SUSE has provided patches to fix this vulnerability for several products.\\n- The CVSS v3 score assigned is 7.8, indicating a high severity.\\n\\nThis information is consistent with the official CVE description.\", similar_info={'cwe_distribution': {}, 'cwe_consensus': '', 'similarity_stats': {'thresholds': [], 'total_samples_by_threshold': {}, 'top_cwes_by_threshold': {}}}, similarity_summary=SimilarityInsight(consensus_cwe='', top_cwes=[], confidence_levels={}, total_samples=0), analysis='', analysis_with_relationships='', criticism='', resolution='', relevant_cwes=[{'metadata': {'doc_id': '190', 'name': 'Integer Overflow or Wraparound', 'source': 'sparse', 'original_content': 'The product performs a calculation that can\\n         produce an integer overflow or wraparound when the logic\\n         assumes that the resulting value will always be larger than\\n         the original value. This occurs when an integer value is\\n         incremented to a value that is too large to store in the\\n         associated representation. When this occurs, the value may\\n         become a very small or negative number.', 'keyphrase_sources': [{'id': 'weakness:integer overflow', 'keyphrase': 'integer overflow', 'type': 'weakness'}, {'id': 'product:Artifex Ghostscript', 'keyphrase': 'Artifex Ghostscript', 'type': 'product'}]}, 'similarity': np.float64(262.2315697047687)}, {'metadata': {'doc_id': '22', 'name': \"Improper Limitation of a Pathname to a Restricted Directory ('Path Traversal')\", 'source': 'sparse', 'original_content': 'The product uses external input to construct a pathname that is intended to identify a file or directory that is located underneath a restricted parent directory, but the product does not properly neutralize special elements within the pathname that can cause the pathname to resolve to a location that is outside of the restricted directory.', 'keyphrase_sources': [{'id': 'weakness:path traversal', 'keyphrase': 'path traversal', 'type': 'weakness'}, {'id': 'weakness:path truncation', 'keyphrase': 'path truncation', 'type': 'weakness'}, {'id': 'impact:path traversal and code execution', 'keyphrase': 'path traversal and code execution', 'type': 'impact'}, {'id': 'product:Artifex Ghostscript', 'keyphrase': 'Artifex Ghostscript', 'type': 'product'}, {'id': 'version:before 10.04.0', 'keyphrase': 'before 10.04.0', 'type': 'version'}, {'id': 'component:base/gsdevice.c', 'keyphrase': 'base/gsdevice.c', 'type': 'component'}]}, 'similarity': np.float64(251.33072239401835)}, {'metadata': {'doc_id': '681', 'name': 'Incorrect Conversion between Numeric Types', 'source': 'sparse', 'original_content': 'When converting from one data type to another, such as long to integer, data can be omitted or translated in a way that produces unexpected values. If the resulting values are used in a sensitive context, then dangerous behaviors may occur.', 'keyphrase_sources': [{'id': 'weakness:integer overflow', 'keyphrase': 'integer overflow', 'type': 'weakness'}, {'id': 'weakness:path truncation', 'keyphrase': 'path truncation', 'type': 'weakness'}]}, 'similarity': np.float64(249.8426639760831)}, {'metadata': {'doc_id': '197', 'name': 'Numeric Truncation Error', 'source': 'sparse', 'original_content': 'Truncation errors occur when a primitive is cast to a primitive of a smaller size and data is lost in the conversion.', 'keyphrase_sources': [{'id': 'weakness:integer overflow', 'keyphrase': 'integer overflow', 'type': 'weakness'}, {'id': 'weakness:path truncation', 'keyphrase': 'path truncation', 'type': 'weakness'}, {'id': 'component:base/gsdevice.c', 'keyphrase': 'base/gsdevice.c', 'type': 'component'}]}, 'similarity': np.float64(248.5339692470851)}, {'metadata': {'doc_id': '36', 'name': 'Absolute Path Traversal', 'source': 'sparse', 'original_content': 'The product uses external input to construct a pathname that should be within a restricted directory, but it does not properly neutralize absolute path sequences such as \"/abs/path\" that can resolve to a location that is outside of that directory.', 'keyphrase_sources': [{'id': 'weakness:path traversal', 'keyphrase': 'path traversal', 'type': 'weakness'}, {'id': 'weakness:path truncation', 'keyphrase': 'path truncation', 'type': 'weakness'}, {'id': 'impact:path traversal and code execution', 'keyphrase': 'path traversal and code execution', 'type': 'impact'}, {'id': 'version:before 10.04.0', 'keyphrase': 'before 10.04.0', 'type': 'version'}]}, 'similarity': np.float64(241.9890285908022)}, {'metadata': {'doc_id': '122', 'name': 'Heap-based Buffer Overflow', 'source': 'sparse', 'original_content': 'A heap overflow condition is a buffer overflow, where the buffer that can be overwritten is allocated in the heap portion of memory, generally meaning that the buffer was allocated using a routine such as malloc().', 'keyphrase_sources': [{'id': 'weakness:integer overflow', 'keyphrase': 'integer overflow', 'type': 'weakness'}, {'id': 'product:Artifex Ghostscript', 'keyphrase': 'Artifex Ghostscript', 'type': 'product'}, {'id': 'version:before 10.04.0', 'keyphrase': 'before 10.04.0', 'type': 'version'}, {'id': 'component:base/gsdevice.c', 'keyphrase': 'base/gsdevice.c', 'type': 'component'}]}, 'similarity': np.float64(238.55219119154216)}, {'metadata': {'doc_id': '191', 'name': 'Integer Underflow (Wrap or Wraparound)', 'source': 'sparse', 'original_content': 'The product subtracts one value from another, such that the result is less than the minimum allowable integer value, which produces a value that is not equal to the correct result.', 'keyphrase_sources': [{'id': 'weakness:integer overflow', 'keyphrase': 'integer overflow', 'type': 'weakness'}]}, 'similarity': np.float64(238.22083986186033)}, {'metadata': {'doc_id': '23', 'name': 'Relative Path Traversal', 'source': 'sparse', 'original_content': 'The product uses external input to construct a pathname that should be within a restricted directory, but it does not properly neutralize sequences such as \"..\" that can resolve to a location that is outside of that directory.', 'keyphrase_sources': [{'id': 'weakness:path traversal', 'keyphrase': 'path traversal', 'type': 'weakness'}, {'id': 'impact:path traversal and code execution', 'keyphrase': 'path traversal and code execution', 'type': 'impact'}]}, 'similarity': np.float64(232.76078498373502)}, {'metadata': {'doc_id': '41', 'name': 'Improper Resolution of Path Equivalence', 'source': 'sparse', 'original_content': 'The product is vulnerable to file system contents disclosure through path equivalence. Path equivalence involves the use of special characters in file and directory names. The associated manipulations are intended to generate multiple names for the same object.', 'keyphrase_sources': [{'id': 'weakness:path traversal', 'keyphrase': 'path traversal', 'type': 'weakness'}, {'id': 'impact:path traversal and code execution', 'keyphrase': 'path traversal and code execution', 'type': 'impact'}]}, 'similarity': np.float64(232.50647104144323)}, {'metadata': {'doc_id': '451', 'name': 'User Interface (UI) Misrepresentation of Critical Information', 'source': 'sparse', 'original_content': 'The user interface (UI) does not properly represent critical information to the user, allowing the information - or its source - to be obscured or spoofed. This is often a component in phishing attacks.', 'keyphrase_sources': [{'id': 'weakness:path truncation', 'keyphrase': 'path truncation', 'type': 'weakness'}]}, 'similarity': np.float64(225.38167763653573)}, {'metadata': {'doc_id': '98', 'name': \"Improper Control of Filename for Include/Require Statement in PHP Program ('PHP Remote File Inclusion')\", 'source': 'sparse', 'original_content': 'The PHP application receives input from an upstream component, but it does not restrict or incorrectly restricts the input before its usage in \"require,\" \"include,\" or similar functions.', 'keyphrase_sources': [{'id': 'weakness:path traversal', 'keyphrase': 'path traversal', 'type': 'weakness'}]}, 'similarity': np.float64(224.4166850493815)}, {'metadata': {'doc_id': '59', 'name': \"Improper Link Resolution Before File Access ('Link Following')\", 'source': 'sparse', 'original_content': 'The product attempts to access a file based on the filename, but it does not properly prevent that filename from identifying a link or shortcut that resolves to an unintended resource.', 'keyphrase_sources': [{'id': 'impact:path traversal and code execution', 'keyphrase': 'path traversal and code execution', 'type': 'impact'}]}, 'similarity': np.float64(88.56578848603326)}, {'metadata': {'doc_id': '20', 'name': 'Improper Input Validation', 'source': 'sparse', 'original_content': 'The product receives input or data, but it does\\n        not validate or incorrectly validates that the input has the\\n        properties that are required to process the data safely and\\n        correctly.', 'keyphrase_sources': [{'id': 'version:before 10.04.0', 'keyphrase': 'before 10.04.0', 'type': 'version'}]}, 'similarity': np.float64(76.95593616649785)}, {'metadata': {'doc_id': '170', 'name': 'Improper Null Termination', 'source': 'sparse', 'original_content': 'The product does not terminate or incorrectly terminates a string or array with a null character or equivalent terminator.', 'keyphrase_sources': [{'id': 'component:base/gsdevice.c', 'keyphrase': 'base/gsdevice.c', 'type': 'component'}]}, 'similarity': np.float64(76.12611985367057)}, {'metadata': {'doc_id': '125', 'name': 'Out-of-bounds Read', 'source': 'sparse', 'original_content': 'The product reads data past the end, or before the beginning, of the intended buffer.', 'keyphrase_sources': [{'id': 'product:Artifex Ghostscript', 'keyphrase': 'Artifex Ghostscript', 'type': 'product'}, {'id': 'version:before 10.04.0', 'keyphrase': 'before 10.04.0', 'type': 'version'}, {'id': 'component:base/gsdevice.c', 'keyphrase': 'base/gsdevice.c', 'type': 'component'}]}, 'similarity': np.float64(69.6530637850112)}, {'metadata': {'doc_id': '787', 'name': 'Out-of-bounds Write', 'source': 'sparse', 'original_content': 'The product writes data past the end, or before the beginning, of the intended buffer.', 'keyphrase_sources': [{'id': 'product:Artifex Ghostscript', 'keyphrase': 'Artifex Ghostscript', 'type': 'product'}]}, 'similarity': np.float64(68.54538912425798)}], identified_cwes={'analyzer': [], 'critic_additional': []})",
  "retrieval_results": {
    "has_multiple_keyphrases": true,
    "keyphrase_cwe_sets": {
      "weakness:integer overflow": {
        "keyphrase": "integer overflow",
        "type": "weakness",
        "cwes": [
          {
            "metadata": {
              "doc_id": "190",
              "name": "Integer Overflow or Wraparound",
              "source": "sparse",
              "original_content": "The product performs a calculation that can\n         produce an integer overflow or wraparound when the logic\n         assumes that the resulting value will always be larger than\n         the original value. This occurs when an integer value is\n         incremented to a value that is too large to store in the\n         associated representation. When this occurs, the value may\n         become a very small or negative number.",
              "keyphrase_sources": [
                {
                  "id": "weakness:integer overflow",
                  "keyphrase": "integer overflow",
                  "type": "weakness"
                },
                {
                  "id": "product:Artifex Ghostscript",
                  "keyphrase": "Artifex Ghostscript",
                  "type": "product"
                }
              ]
            },
            "similarity": 262.2315697047687
          },
          {
            "metadata": {
              "doc_id": "681",
              "name": "Incorrect Conversion between Numeric Types",
              "source": "sparse",
              "original_content": "When converting from one data type to another, such as long to integer, data can be omitted or translated in a way that produces unexpected values. If the resulting values are used in a sensitive context, then dangerous behaviors may occur.",
              "keyphrase_sources": [
                {
                  "id": "weakness:integer overflow",
                  "keyphrase": "integer overflow",
                  "type": "weakness"
                },
                {
                  "id": "weakness:path truncation",
                  "keyphrase": "path truncation",
                  "type": "weakness"
                }
              ]
            },
            "similarity": 249.8426639760831
          },
          {
            "metadata": {
              "doc_id": "197",
              "name": "Numeric Truncation Error",
              "source": "sparse",
              "original_content": "Truncation errors occur when a primitive is cast to a primitive of a smaller size and data is lost in the conversion.",
              "keyphrase_sources": [
                {
                  "id": "weakness:integer overflow",
                  "keyphrase": "integer overflow",
                  "type": "weakness"
                },
                {
                  "id": "weakness:path truncation",
                  "keyphrase": "path truncation",
                  "type": "weakness"
                },
                {
                  "id": "component:base/gsdevice.c",
                  "keyphrase": "base/gsdevice.c",
                  "type": "component"
                }
              ]
            },
            "similarity": 248.5339692470851
          },
          {
            "metadata": {
              "doc_id": "122",
              "name": "Heap-based Buffer Overflow",
              "source": "sparse",
              "original_content": "A heap overflow condition is a buffer overflow, where the buffer that can be overwritten is allocated in the heap portion of memory, generally meaning that the buffer was allocated using a routine such as malloc().",
              "keyphrase_sources": [
                {
                  "id": "weakness:integer overflow",
                  "keyphrase": "integer overflow",
                  "type": "weakness"
                },
                {
                  "id": "product:Artifex Ghostscript",
                  "keyphrase": "Artifex Ghostscript",
                  "type": "product"
                },
                {
                  "id": "version:before 10.04.0",
                  "keyphrase": "before 10.04.0",
                  "type": "version"
                },
                {
                  "id": "component:base/gsdevice.c",
                  "keyphrase": "base/gsdevice.c",
                  "type": "component"
                }
              ]
            },
            "similarity": 238.55219119154216
          },
          {
            "metadata": {
              "doc_id": "191",
              "name": "Integer Underflow (Wrap or Wraparound)",
              "source": "sparse",
              "original_content": "The product subtracts one value from another, such that the result is less than the minimum allowable integer value, which produces a value that is not equal to the correct result.",
              "keyphrase_sources": [
                {
                  "id": "weakness:integer overflow",
                  "keyphrase": "integer overflow",
                  "type": "weakness"
                }
              ]
            },
            "similarity": 238.22083986186033
          }
        ]
      },
      "weakness:path traversal": {
        "keyphrase": "path traversal",
        "type": "weakness",
        "cwes": [
          {
            "metadata": {
              "doc_id": "22",
              "name": "Improper Limitation of a Pathname to a Restricted Directory ('Path Traversal')",
              "source": "sparse",
              "original_content": "The product uses external input to construct a pathname that is intended to identify a file or directory that is located underneath a restricted parent directory, but the product does not properly neutralize special elements within the pathname that can cause the pathname to resolve to a location that is outside of the restricted directory.",
              "keyphrase_sources": [
                {
                  "id": "weakness:path traversal",
                  "keyphrase": "path traversal",
                  "type": "weakness"
                },
                {
                  "id": "weakness:path truncation",
                  "keyphrase": "path truncation",
                  "type": "weakness"
                },
                {
                  "id": "impact:path traversal and code execution",
                  "keyphrase": "path traversal and code execution",
                  "type": "impact"
                },
                {
                  "id": "product:Artifex Ghostscript",
                  "keyphrase": "Artifex Ghostscript",
                  "type": "product"
                },
                {
                  "id": "version:before 10.04.0",
                  "keyphrase": "before 10.04.0",
                  "type": "version"
                },
                {
                  "id": "component:base/gsdevice.c",
                  "keyphrase": "base/gsdevice.c",
                  "type": "component"
                }
              ]
            },
            "similarity": 251.33072239401835
          },
          {
            "metadata": {
              "doc_id": "36",
              "name": "Absolute Path Traversal",
              "source": "sparse",
              "original_content": "The product uses external input to construct a pathname that should be within a restricted directory, but it does not properly neutralize absolute path sequences such as \"/abs/path\" that can resolve to a location that is outside of that directory.",
              "keyphrase_sources": [
                {
                  "id": "weakness:path traversal",
                  "keyphrase": "path traversal",
                  "type": "weakness"
                },
                {
                  "id": "weakness:path truncation",
                  "keyphrase": "path truncation",
                  "type": "weakness"
                },
                {
                  "id": "impact:path traversal and code execution",
                  "keyphrase": "path traversal and code execution",
                  "type": "impact"
                },
                {
                  "id": "version:before 10.04.0",
                  "keyphrase": "before 10.04.0",
                  "type": "version"
                }
              ]
            },
            "similarity": 241.9890285908022
          },
          {
            "metadata": {
              "doc_id": "23",
              "name": "Relative Path Traversal",
              "source": "sparse",
              "original_content": "The product uses external input to construct a pathname that should be within a restricted directory, but it does not properly neutralize sequences such as \"..\" that can resolve to a location that is outside of that directory.",
              "keyphrase_sources": [
                {
                  "id": "weakness:path traversal",
                  "keyphrase": "path traversal",
                  "type": "weakness"
                },
                {
                  "id": "impact:path traversal and code execution",
                  "keyphrase": "path traversal and code execution",
                  "type": "impact"
                }
              ]
            },
            "similarity": 232.76078498373502
          },
          {
            "metadata": {
              "doc_id": "41",
              "name": "Improper Resolution of Path Equivalence",
              "source": "sparse",
              "original_content": "The product is vulnerable to file system contents disclosure through path equivalence. Path equivalence involves the use of special characters in file and directory names. The associated manipulations are intended to generate multiple names for the same object.",
              "keyphrase_sources": [
                {
                  "id": "weakness:path traversal",
                  "keyphrase": "path traversal",
                  "type": "weakness"
                },
                {
                  "id": "impact:path traversal and code execution",
                  "keyphrase": "path traversal and code execution",
                  "type": "impact"
                }
              ]
            },
            "similarity": 232.50647104144323
          },
          {
            "metadata": {
              "doc_id": "98",
              "name": "Improper Control of Filename for Include/Require Statement in PHP Program ('PHP Remote File Inclusion')",
              "source": "sparse",
              "original_content": "The PHP application receives input from an upstream component, but it does not restrict or incorrectly restricts the input before its usage in \"require,\" \"include,\" or similar functions.",
              "keyphrase_sources": [
                {
                  "id": "weakness:path traversal",
                  "keyphrase": "path traversal",
                  "type": "weakness"
                }
              ]
            },
            "similarity": 224.4166850493815
          }
        ]
      },
      "weakness:path truncation": {
        "keyphrase": "path truncation",
        "type": "weakness",
        "cwes": [
          {
            "metadata": {
              "doc_id": "197",
              "name": "Numeric Truncation Error",
              "source": "sparse",
              "original_content": "Truncation errors occur when a primitive is cast to a primitive of a smaller size and data is lost in the conversion."
            },
            "similarity": 246.38860023029483
          },
          {
            "metadata": {
              "doc_id": "451",
              "name": "User Interface (UI) Misrepresentation of Critical Information",
              "source": "sparse",
              "original_content": "The user interface (UI) does not properly represent critical information to the user, allowing the information - or its source - to be obscured or spoofed. This is often a component in phishing attacks.",
              "keyphrase_sources": [
                {
                  "id": "weakness:path truncation",
                  "keyphrase": "path truncation",
                  "type": "weakness"
                }
              ]
            },
            "similarity": 225.38167763653573
          },
          {
            "metadata": {
              "doc_id": "681",
              "name": "Incorrect Conversion between Numeric Types",
              "source": "sparse",
              "original_content": "When converting from one data type to another, such as long to integer, data can be omitted or translated in a way that produces unexpected values. If the resulting values are used in a sensitive context, then dangerous behaviors may occur."
            },
            "similarity": 223.6508552722686
          },
          {
            "metadata": {
              "doc_id": "22",
              "name": "Improper Limitation of a Pathname to a Restricted Directory ('Path Traversal')",
              "source": "sparse",
              "original_content": "The product uses external input to construct a pathname that is intended to identify a file or directory that is located underneath a restricted parent directory, but the product does not properly neutralize special elements within the pathname that can cause the pathname to resolve to a location that is outside of the restricted directory."
            },
            "similarity": 219.36851055486068
          },
          {
            "metadata": {
              "doc_id": "36",
              "name": "Absolute Path Traversal",
              "source": "sparse",
              "original_content": "The product uses external input to construct a pathname that should be within a restricted directory, but it does not properly neutralize absolute path sequences such as \"/abs/path\" that can resolve to a location that is outside of that directory."
            },
            "similarity": 208.47173958385474
          }
        ]
      },
      "impact:path traversal and code execution": {
        "keyphrase": "path traversal and code execution",
        "type": "impact",
        "cwes": [
          {
            "metadata": {
              "doc_id": "22",
              "name": "Improper Limitation of a Pathname to a Restricted Directory ('Path Traversal')",
              "source": "sparse",
              "original_content": "The product uses external input to construct a pathname that is intended to identify a file or directory that is located underneath a restricted parent directory, but the product does not properly neutralize special elements within the pathname that can cause the pathname to resolve to a location that is outside of the restricted directory."
            },
            "similarity": 100.39970576622288
          },
          {
            "metadata": {
              "doc_id": "36",
              "name": "Absolute Path Traversal",
              "source": "sparse",
              "original_content": "The product uses external input to construct a pathname that should be within a restricted directory, but it does not properly neutralize absolute path sequences such as \"/abs/path\" that can resolve to a location that is outside of that directory."
            },
            "similarity": 94.63312313107868
          },
          {
            "metadata": {
              "doc_id": "23",
              "name": "Relative Path Traversal",
              "source": "sparse",
              "original_content": "The product uses external input to construct a pathname that should be within a restricted directory, but it does not properly neutralize sequences such as \"..\" that can resolve to a location that is outside of that directory."
            },
            "similarity": 93.38634499620088
          },
          {
            "metadata": {
              "doc_id": "41",
              "name": "Improper Resolution of Path Equivalence",
              "source": "sparse",
              "original_content": "The product is vulnerable to file system contents disclosure through path equivalence. Path equivalence involves the use of special characters in file and directory names. The associated manipulations are intended to generate multiple names for the same object."
            },
            "similarity": 92.57513311957054
          },
          {
            "metadata": {
              "doc_id": "59",
              "name": "Improper Link Resolution Before File Access ('Link Following')",
              "source": "sparse",
              "original_content": "The product attempts to access a file based on the filename, but it does not properly prevent that filename from identifying a link or shortcut that resolves to an unintended resource.",
              "keyphrase_sources": [
                {
                  "id": "impact:path traversal and code execution",
                  "keyphrase": "path traversal and code execution",
                  "type": "impact"
                }
              ]
            },
            "similarity": 88.56578848603326
          }
        ]
      },
      "product:Artifex Ghostscript": {
        "keyphrase": "Artifex Ghostscript",
        "type": "product",
        "cwes": [
          {
            "metadata": {
              "doc_id": "122",
              "name": "Heap-based Buffer Overflow",
              "source": "sparse",
              "original_content": "A heap overflow condition is a buffer overflow, where the buffer that can be overwritten is allocated in the heap portion of memory, generally meaning that the buffer was allocated using a routine such as malloc()."
            },
            "similarity": 72.55270689495904
          },
          {
            "metadata": {
              "doc_id": "22",
              "name": "Improper Limitation of a Pathname to a Restricted Directory ('Path Traversal')",
              "source": "sparse",
              "original_content": "The product uses external input to construct a pathname that is intended to identify a file or directory that is located underneath a restricted parent directory, but the product does not properly neutralize special elements within the pathname that can cause the pathname to resolve to a location that is outside of the restricted directory."
            },
            "similarity": 71.1629607434777
          },
          {
            "metadata": {
              "doc_id": "125",
              "name": "Out-of-bounds Read",
              "source": "sparse",
              "original_content": "The product reads data past the end, or before the beginning, of the intended buffer.",
              "keyphrase_sources": [
                {
                  "id": "product:Artifex Ghostscript",
                  "keyphrase": "Artifex Ghostscript",
                  "type": "product"
                },
                {
                  "id": "version:before 10.04.0",
                  "keyphrase": "before 10.04.0",
                  "type": "version"
                },
                {
                  "id": "component:base/gsdevice.c",
                  "keyphrase": "base/gsdevice.c",
                  "type": "component"
                }
              ]
            },
            "similarity": 69.6530637850112
          },
          {
            "metadata": {
              "doc_id": "190",
              "name": "Integer Overflow or Wraparound",
              "source": "sparse",
              "original_content": "The product performs a calculation that can\n         produce an integer overflow or wraparound when the logic\n         assumes that the resulting value will always be larger than\n         the original value. This occurs when an integer value is\n         incremented to a value that is too large to store in the\n         associated representation. When this occurs, the value may\n         become a very small or negative number."
            },
            "similarity": 69.08696710984788
          },
          {
            "metadata": {
              "doc_id": "787",
              "name": "Out-of-bounds Write",
              "source": "sparse",
              "original_content": "The product writes data past the end, or before the beginning, of the intended buffer.",
              "keyphrase_sources": [
                {
                  "id": "product:Artifex Ghostscript",
                  "keyphrase": "Artifex Ghostscript",
                  "type": "product"
                }
              ]
            },
            "similarity": 68.54538912425798
          }
        ]
      },
      "version:before 10.04.0": {
        "keyphrase": "before 10.04.0",
        "type": "version",
        "cwes": [
          {
            "metadata": {
              "doc_id": "36",
              "name": "Absolute Path Traversal",
              "source": "sparse",
              "original_content": "The product uses external input to construct a pathname that should be within a restricted directory, but it does not properly neutralize absolute path sequences such as \"/abs/path\" that can resolve to a location that is outside of that directory."
            },
            "similarity": 84.96397708450782
          },
          {
            "metadata": {
              "doc_id": "122",
              "name": "Heap-based Buffer Overflow",
              "source": "sparse",
              "original_content": "A heap overflow condition is a buffer overflow, where the buffer that can be overwritten is allocated in the heap portion of memory, generally meaning that the buffer was allocated using a routine such as malloc()."
            },
            "similarity": 79.74951138638593
          },
          {
            "metadata": {
              "doc_id": "22",
              "name": "Improper Limitation of a Pathname to a Restricted Directory ('Path Traversal')",
              "source": "sparse",
              "original_content": "The product uses external input to construct a pathname that is intended to identify a file or directory that is located underneath a restricted parent directory, but the product does not properly neutralize special elements within the pathname that can cause the pathname to resolve to a location that is outside of the restricted directory."
            },
            "similarity": 79.51404406747685
          },
          {
            "metadata": {
              "doc_id": "125",
              "name": "Out-of-bounds Read",
              "source": "sparse",
              "original_content": "The product reads data past the end, or before the beginning, of the intended buffer."
            },
            "similarity": 76.96817689129645
          },
          {
            "metadata": {
              "doc_id": "20",
              "name": "Improper Input Validation",
              "source": "sparse",
              "original_content": "The product receives input or data, but it does\n        not validate or incorrectly validates that the input has the\n        properties that are required to process the data safely and\n        correctly.",
              "keyphrase_sources": [
                {
                  "id": "version:before 10.04.0",
                  "keyphrase": "before 10.04.0",
                  "type": "version"
                }
              ]
            },
            "similarity": 76.95593616649785
          }
        ]
      },
      "component:base/gsdevice.c": {
        "keyphrase": "base/gsdevice.c",
        "type": "component",
        "cwes": [
          {
            "metadata": {
              "doc_id": "122",
              "name": "Heap-based Buffer Overflow",
              "source": "sparse",
              "original_content": "A heap overflow condition is a buffer overflow, where the buffer that can be overwritten is allocated in the heap portion of memory, generally meaning that the buffer was allocated using a routine such as malloc()."
            },
            "similarity": 78.22421122469439
          },
          {
            "metadata": {
              "doc_id": "125",
              "name": "Out-of-bounds Read",
              "source": "sparse",
              "original_content": "The product reads data past the end, or before the beginning, of the intended buffer."
            },
            "similarity": 77.77466110884552
          },
          {
            "metadata": {
              "doc_id": "197",
              "name": "Numeric Truncation Error",
              "source": "sparse",
              "original_content": "Truncation errors occur when a primitive is cast to a primitive of a smaller size and data is lost in the conversion."
            },
            "similarity": 76.73766422611475
          },
          {
            "metadata": {
              "doc_id": "170",
              "name": "Improper Null Termination",
              "source": "sparse",
              "original_content": "The product does not terminate or incorrectly terminates a string or array with a null character or equivalent terminator.",
              "keyphrase_sources": [
                {
                  "id": "component:base/gsdevice.c",
                  "keyphrase": "base/gsdevice.c",
                  "type": "component"
                }
              ]
            },
            "similarity": 76.12611985367057
          },
          {
            "metadata": {
              "doc_id": "22",
              "name": "Improper Limitation of a Pathname to a Restricted Directory ('Path Traversal')",
              "source": "sparse",
              "original_content": "The product uses external input to construct a pathname that is intended to identify a file or directory that is located underneath a restricted parent directory, but the product does not properly neutralize special elements within the pathname that can cause the pathname to resolve to a location that is outside of the restricted directory."
            },
            "similarity": 76.08974256063195
          }
        ]
      }
    },
    "keyphrase_mapping": {
      "190": [
        {
          "id": "weakness:integer overflow",
          "keyphrase": "integer overflow",
          "type": "weakness"
        },
        {
          "id": "product:Artifex Ghostscript",
          "keyphrase": "Artifex Ghostscript",
          "type": "product"
        }
      ],
      "681": [
        {
          "id": "weakness:integer overflow",
          "keyphrase": "integer overflow",
          "type": "weakness"
        },
        {
          "id": "weakness:path truncation",
          "keyphrase": "path truncation",
          "type": "weakness"
        }
      ],
      "197": [
        {
          "id": "weakness:integer overflow",
          "keyphrase": "integer overflow",
          "type": "weakness"
        },
        {
          "id": "weakness:path truncation",
          "keyphrase": "path truncation",
          "type": "weakness"
        },
        {
          "id": "component:base/gsdevice.c",
          "keyphrase": "base/gsdevice.c",
          "type": "component"
        }
      ],
      "122": [
        {
          "id": "weakness:integer overflow",
          "keyphrase": "integer overflow",
          "type": "weakness"
        },
        {
          "id": "product:Artifex Ghostscript",
          "keyphrase": "Artifex Ghostscript",
          "type": "product"
        },
        {
          "id": "version:before 10.04.0",
          "keyphrase": "before 10.04.0",
          "type": "version"
        },
        {
          "id": "component:base/gsdevice.c",
          "keyphrase": "base/gsdevice.c",
          "type": "component"
        }
      ],
      "191": [
        {
          "id": "weakness:integer overflow",
          "keyphrase": "integer overflow",
          "type": "weakness"
        }
      ],
      "22": [
        {
          "id": "weakness:path traversal",
          "keyphrase": "path traversal",
          "type": "weakness"
        },
        {
          "id": "weakness:path truncation",
          "keyphrase": "path truncation",
          "type": "weakness"
        },
        {
          "id": "impact:path traversal and code execution",
          "keyphrase": "path traversal and code execution",
          "type": "impact"
        },
        {
          "id": "product:Artifex Ghostscript",
          "keyphrase": "Artifex Ghostscript",
          "type": "product"
        },
        {
          "id": "version:before 10.04.0",
          "keyphrase": "before 10.04.0",
          "type": "version"
        },
        {
          "id": "component:base/gsdevice.c",
          "keyphrase": "base/gsdevice.c",
          "type": "component"
        }
      ],
      "36": [
        {
          "id": "weakness:path traversal",
          "keyphrase": "path traversal",
          "type": "weakness"
        },
        {
          "id": "weakness:path truncation",
          "keyphrase": "path truncation",
          "type": "weakness"
        },
        {
          "id": "impact:path traversal and code execution",
          "keyphrase": "path traversal and code execution",
          "type": "impact"
        },
        {
          "id": "version:before 10.04.0",
          "keyphrase": "before 10.04.0",
          "type": "version"
        }
      ],
      "23": [
        {
          "id": "weakness:path traversal",
          "keyphrase": "path traversal",
          "type": "weakness"
        },
        {
          "id": "impact:path traversal and code execution",
          "keyphrase": "path traversal and code execution",
          "type": "impact"
        }
      ],
      "41": [
        {
          "id": "weakness:path traversal",
          "keyphrase": "path traversal",
          "type": "weakness"
        },
        {
          "id": "impact:path traversal and code execution",
          "keyphrase": "path traversal and code execution",
          "type": "impact"
        }
      ],
      "98": [
        {
          "id": "weakness:path traversal",
          "keyphrase": "path traversal",
          "type": "weakness"
        }
      ],
      "451": [
        {
          "id": "weakness:path truncation",
          "keyphrase": "path truncation",
          "type": "weakness"
        }
      ],
      "59": [
        {
          "id": "impact:path traversal and code execution",
          "keyphrase": "path traversal and code execution",
          "type": "impact"
        }
      ],
      "125": [
        {
          "id": "product:Artifex Ghostscript",
          "keyphrase": "Artifex Ghostscript",
          "type": "product"
        },
        {
          "id": "version:before 10.04.0",
          "keyphrase": "before 10.04.0",
          "type": "version"
        },
        {
          "id": "component:base/gsdevice.c",
          "keyphrase": "base/gsdevice.c",
          "type": "component"
        }
      ],
      "787": [
        {
          "id": "product:Artifex Ghostscript",
          "keyphrase": "Artifex Ghostscript",
          "type": "product"
        }
      ],
      "20": [
        {
          "id": "version:before 10.04.0",
          "keyphrase": "before 10.04.0",
          "type": "version"
        }
      ],
      "170": [
        {
          "id": "component:base/gsdevice.c",
          "keyphrase": "base/gsdevice.c",
          "type": "component"
        }
      ]
    },
    "relevant_cwes": [
      {
        "metadata": {
          "doc_id": "190",
          "name": "Integer Overflow or Wraparound",
          "source": "sparse",
          "original_content": "The product performs a calculation that can\n         produce an integer overflow or wraparound when the logic\n         assumes that the resulting value will always be larger than\n         the original value. This occurs when an integer value is\n         incremented to a value that is too large to store in the\n         associated representation. When this occurs, the value may\n         become a very small or negative number.",
          "keyphrase_sources": [
            {
              "id": "weakness:integer overflow",
              "keyphrase": "integer overflow",
              "type": "weakness"
            },
            {
              "id": "product:Artifex Ghostscript",
              "keyphrase": "Artifex Ghostscript",
              "type": "product"
            }
          ]
        },
        "similarity": 262.2315697047687
      },
      {
        "metadata": {
          "doc_id": "22",
          "name": "Improper Limitation of a Pathname to a Restricted Directory ('Path Traversal')",
          "source": "sparse",
          "original_content": "The product uses external input to construct a pathname that is intended to identify a file or directory that is located underneath a restricted parent directory, but the product does not properly neutralize special elements within the pathname that can cause the pathname to resolve to a location that is outside of the restricted directory.",
          "keyphrase_sources": [
            {
              "id": "weakness:path traversal",
              "keyphrase": "path traversal",
              "type": "weakness"
            },
            {
              "id": "weakness:path truncation",
              "keyphrase": "path truncation",
              "type": "weakness"
            },
            {
              "id": "impact:path traversal and code execution",
              "keyphrase": "path traversal and code execution",
              "type": "impact"
            },
            {
              "id": "product:Artifex Ghostscript",
              "keyphrase": "Artifex Ghostscript",
              "type": "product"
            },
            {
              "id": "version:before 10.04.0",
              "keyphrase": "before 10.04.0",
              "type": "version"
            },
            {
              "id": "component:base/gsdevice.c",
              "keyphrase": "base/gsdevice.c",
              "type": "component"
            }
          ]
        },
        "similarity": 251.33072239401835
      },
      {
        "metadata": {
          "doc_id": "681",
          "name": "Incorrect Conversion between Numeric Types",
          "source": "sparse",
          "original_content": "When converting from one data type to another, such as long to integer, data can be omitted or translated in a way that produces unexpected values. If the resulting values are used in a sensitive context, then dangerous behaviors may occur.",
          "keyphrase_sources": [
            {
              "id": "weakness:integer overflow",
              "keyphrase": "integer overflow",
              "type": "weakness"
            },
            {
              "id": "weakness:path truncation",
              "keyphrase": "path truncation",
              "type": "weakness"
            }
          ]
        },
        "similarity": 249.8426639760831
      },
      {
        "metadata": {
          "doc_id": "197",
          "name": "Numeric Truncation Error",
          "source": "sparse",
          "original_content": "Truncation errors occur when a primitive is cast to a primitive of a smaller size and data is lost in the conversion.",
          "keyphrase_sources": [
            {
              "id": "weakness:integer overflow",
              "keyphrase": "integer overflow",
              "type": "weakness"
            },
            {
              "id": "weakness:path truncation",
              "keyphrase": "path truncation",
              "type": "weakness"
            },
            {
              "id": "component:base/gsdevice.c",
              "keyphrase": "base/gsdevice.c",
              "type": "component"
            }
          ]
        },
        "similarity": 248.5339692470851
      },
      {
        "metadata": {
          "doc_id": "36",
          "name": "Absolute Path Traversal",
          "source": "sparse",
          "original_content": "The product uses external input to construct a pathname that should be within a restricted directory, but it does not properly neutralize absolute path sequences such as \"/abs/path\" that can resolve to a location that is outside of that directory.",
          "keyphrase_sources": [
            {
              "id": "weakness:path traversal",
              "keyphrase": "path traversal",
              "type": "weakness"
            },
            {
              "id": "weakness:path truncation",
              "keyphrase": "path truncation",
              "type": "weakness"
            },
            {
              "id": "impact:path traversal and code execution",
              "keyphrase": "path traversal and code execution",
              "type": "impact"
            },
            {
              "id": "version:before 10.04.0",
              "keyphrase": "before 10.04.0",
              "type": "version"
            }
          ]
        },
        "similarity": 241.9890285908022
      },
      {
        "metadata": {
          "doc_id": "122",
          "name": "Heap-based Buffer Overflow",
          "source": "sparse",
          "original_content": "A heap overflow condition is a buffer overflow, where the buffer that can be overwritten is allocated in the heap portion of memory, generally meaning that the buffer was allocated using a routine such as malloc().",
          "keyphrase_sources": [
            {
              "id": "weakness:integer overflow",
              "keyphrase": "integer overflow",
              "type": "weakness"
            },
            {
              "id": "product:Artifex Ghostscript",
              "keyphrase": "Artifex Ghostscript",
              "type": "product"
            },
            {
              "id": "version:before 10.04.0",
              "keyphrase": "before 10.04.0",
              "type": "version"
            },
            {
              "id": "component:base/gsdevice.c",
              "keyphrase": "base/gsdevice.c",
              "type": "component"
            }
          ]
        },
        "similarity": 238.55219119154216
      },
      {
        "metadata": {
          "doc_id": "191",
          "name": "Integer Underflow (Wrap or Wraparound)",
          "source": "sparse",
          "original_content": "The product subtracts one value from another, such that the result is less than the minimum allowable integer value, which produces a value that is not equal to the correct result.",
          "keyphrase_sources": [
            {
              "id": "weakness:integer overflow",
              "keyphrase": "integer overflow",
              "type": "weakness"
            }
          ]
        },
        "similarity": 238.22083986186033
      },
      {
        "metadata": {
          "doc_id": "23",
          "name": "Relative Path Traversal",
          "source": "sparse",
          "original_content": "The product uses external input to construct a pathname that should be within a restricted directory, but it does not properly neutralize sequences such as \"..\" that can resolve to a location that is outside of that directory.",
          "keyphrase_sources": [
            {
              "id": "weakness:path traversal",
              "keyphrase": "path traversal",
              "type": "weakness"
            },
            {
              "id": "impact:path traversal and code execution",
              "keyphrase": "path traversal and code execution",
              "type": "impact"
            }
          ]
        },
        "similarity": 232.76078498373502
      },
      {
        "metadata": {
          "doc_id": "41",
          "name": "Improper Resolution of Path Equivalence",
          "source": "sparse",
          "original_content": "The product is vulnerable to file system contents disclosure through path equivalence. Path equivalence involves the use of special characters in file and directory names. The associated manipulations are intended to generate multiple names for the same object.",
          "keyphrase_sources": [
            {
              "id": "weakness:path traversal",
              "keyphrase": "path traversal",
              "type": "weakness"
            },
            {
              "id": "impact:path traversal and code execution",
              "keyphrase": "path traversal and code execution",
              "type": "impact"
            }
          ]
        },
        "similarity": 232.50647104144323
      },
      {
        "metadata": {
          "doc_id": "451",
          "name": "User Interface (UI) Misrepresentation of Critical Information",
          "source": "sparse",
          "original_content": "The user interface (UI) does not properly represent critical information to the user, allowing the information - or its source - to be obscured or spoofed. This is often a component in phishing attacks.",
          "keyphrase_sources": [
            {
              "id": "weakness:path truncation",
              "keyphrase": "path truncation",
              "type": "weakness"
            }
          ]
        },
        "similarity": 225.38167763653573
      },
      {
        "metadata": {
          "doc_id": "98",
          "name": "Improper Control of Filename for Include/Require Statement in PHP Program ('PHP Remote File Inclusion')",
          "source": "sparse",
          "original_content": "The PHP application receives input from an upstream component, but it does not restrict or incorrectly restricts the input before its usage in \"require,\" \"include,\" or similar functions.",
          "keyphrase_sources": [
            {
              "id": "weakness:path traversal",
              "keyphrase": "path traversal",
              "type": "weakness"
            }
          ]
        },
        "similarity": 224.4166850493815
      },
      {
        "metadata": {
          "doc_id": "59",
          "name": "Improper Link Resolution Before File Access ('Link Following')",
          "source": "sparse",
          "original_content": "The product attempts to access a file based on the filename, but it does not properly prevent that filename from identifying a link or shortcut that resolves to an unintended resource.",
          "keyphrase_sources": [
            {
              "id": "impact:path traversal and code execution",
              "keyphrase": "path traversal and code execution",
              "type": "impact"
            }
          ]
        },
        "similarity": 88.56578848603326
      },
      {
        "metadata": {
          "doc_id": "20",
          "name": "Improper Input Validation",
          "source": "sparse",
          "original_content": "The product receives input or data, but it does\n        not validate or incorrectly validates that the input has the\n        properties that are required to process the data safely and\n        correctly.",
          "keyphrase_sources": [
            {
              "id": "version:before 10.04.0",
              "keyphrase": "before 10.04.0",
              "type": "version"
            }
          ]
        },
        "similarity": 76.95593616649785
      },
      {
        "metadata": {
          "doc_id": "170",
          "name": "Improper Null Termination",
          "source": "sparse",
          "original_content": "The product does not terminate or incorrectly terminates a string or array with a null character or equivalent terminator.",
          "keyphrase_sources": [
            {
              "id": "component:base/gsdevice.c",
              "keyphrase": "base/gsdevice.c",
              "type": "component"
            }
          ]
        },
        "similarity": 76.12611985367057
      },
      {
        "metadata": {
          "doc_id": "125",
          "name": "Out-of-bounds Read",
          "source": "sparse",
          "original_content": "The product reads data past the end, or before the beginning, of the intended buffer.",
          "keyphrase_sources": [
            {
              "id": "product:Artifex Ghostscript",
              "keyphrase": "Artifex Ghostscript",
              "type": "product"
            },
            {
              "id": "version:before 10.04.0",
              "keyphrase": "before 10.04.0",
              "type": "version"
            },
            {
              "id": "component:base/gsdevice.c",
              "keyphrase": "base/gsdevice.c",
              "type": "component"
            }
          ]
        },
        "similarity": 69.6530637850112
      },
      {
        "metadata": {
          "doc_id": "787",
          "name": "Out-of-bounds Write",
          "source": "sparse",
          "original_content": "The product writes data past the end, or before the beginning, of the intended buffer.",
          "keyphrase_sources": [
            {
              "id": "product:Artifex Ghostscript",
              "keyphrase": "Artifex Ghostscript",
              "type": "product"
            }
          ]
        },
        "similarity": 68.54538912425798
      }
    ],
    "enhanced_query": "# Vulnerability Description\n\n    An issue was discovered in base/gsdevice.c in Artifex Ghostscript before 10.04.0. An **integer overflow** when parsing the filename format string (for the output filename) results in **path truncation**, and possible **path traversal** and code execution.\n\n    # Keyphrase-Specific CWE Analysis\n    This vulnerability contains multiple keyphrases that may map to different CWEs. \n    Please analyze each keyphrase separately and determine the most appropriate CWE(s) for each.\n\n    ## WEAKNESS: 'integer overflow'\n\nRelevant CWEs for this WEAKNESS:\n\n### 1. CWE-190: Integer Overflow or Wraparound (Score: 262.23)\n\nThe product performs a calculation that can\n         produce an integer overflow or wraparound when the logic\n         assumes that the resulting value will always be larger than\n         the original value. This occurs when an integer value is\n         incremented to a value that is too large to st...\n\n### 2. CWE-681: Incorrect Conversion between Numeric Types (Score: 249.84)\n\nWhen converting from one data type to another, such as long to integer, data can be omitted or translated in a way that produces unexpected values. If the resulting values are used in a sensitive context, then dangerous behaviors may occur....\n\n### 3. CWE-197: Numeric Truncation Error (Score: 248.53)\n\nTruncation errors occur when a primitive is cast to a primitive of a smaller size and data is lost in the conversion....\n\n### 4. CWE-122: Heap-based Buffer Overflow (Score: 238.55)\n\nA heap overflow condition is a buffer overflow, where the buffer that can be overwritten is allocated in the heap portion of memory, generally meaning that the buffer was allocated using a routine such as malloc()....\n\n### 5. CWE-191: Integer Underflow (Wrap or Wraparound) (Score: 238.22)\n\nThe product subtracts one value from another, such that the result is less than the minimum allowable integer value, which produces a value that is not equal to the correct result....\n\n## PRODUCT: 'Artifex Ghostscript'\n\nRelevant CWEs for this PRODUCT:\n\n### 1. CWE-190: Integer Overflow or Wraparound (Score: 262.23)\n\nThe product performs a calculation that can\n         produce an integer overflow or wraparound when the logic\n         assumes that the resulting value will always be larger than\n         the original value. This occurs when an integer value is\n         incremented to a value that is too large to st...\n\n### 2. CWE-22: Improper Limitation of a Pathname to a Restricted Directory ('Path Traversal') (Score: 251.33)\n\nThe product uses external input to construct a pathname that is intended to identify a file or directory that is located underneath a restricted parent directory, but the product does not properly neutralize special elements within the pathname that can cause the pathname to resolve to a location th...\n\n### 3. CWE-122: Heap-based Buffer Overflow (Score: 238.55)\n\nA heap overflow condition is a buffer overflow, where the buffer that can be overwritten is allocated in the heap portion of memory, generally meaning that the buffer was allocated using a routine such as malloc()....\n\n### 4. CWE-125: Out-of-bounds Read (Score: 69.65)\n\nThe product reads data past the end, or before the beginning, of the intended buffer....\n\n### 5. CWE-787: Out-of-bounds Write (Score: 68.55)\n\nThe product writes data past the end, or before the beginning, of the intended buffer....\n\n## WEAKNESS: 'path traversal'\n\nRelevant CWEs for this WEAKNESS:\n\n### 1. CWE-22: Improper Limitation of a Pathname to a Restricted Directory ('Path Traversal') (Score: 251.33)\n\nThe product uses external input to construct a pathname that is intended to identify a file or directory that is located underneath a restricted parent directory, but the product does not properly neutralize special elements within the pathname that can cause the pathname to resolve to a location th...\n\n### 2. CWE-36: Absolute Path Traversal (Score: 241.99)\n\nThe product uses external input to construct a pathname that should be within a restricted directory, but it does not properly neutralize absolute path sequences such as \"/abs/path\" that can resolve to a location that is outside of that directory....\n\n### 3. CWE-23: Relative Path Traversal (Score: 232.76)\n\nThe product uses external input to construct a pathname that should be within a restricted directory, but it does not properly neutralize sequences such as \"..\" that can resolve to a location that is outside of that directory....\n\n### 4. CWE-41: Improper Resolution of Path Equivalence (Score: 232.51)\n\nThe product is vulnerable to file system contents disclosure through path equivalence. Path equivalence involves the use of special characters in file and directory names. The associated manipulations are intended to generate multiple names for the same object....\n\n### 5. CWE-98: Improper Control of Filename for Include/Require Statement in PHP Program ('PHP Remote File Inclusion') (Score: 224.42)\n\nThe PHP application receives input from an upstream component, but it does not restrict or incorrectly restricts the input before its usage in \"require,\" \"include,\" or similar functions....\n\n## WEAKNESS: 'path truncation'\n\nRelevant CWEs for this WEAKNESS:\n\n### 1. CWE-22: Improper Limitation of a Pathname to a Restricted Directory ('Path Traversal') (Score: 251.33)\n\nThe product uses external input to construct a pathname that is intended to identify a file or directory that is located underneath a restricted parent directory, but the product does not properly neutralize special elements within the pathname that can cause the pathname to resolve to a location th...\n\n### 2. CWE-681: Incorrect Conversion between Numeric Types (Score: 249.84)\n\nWhen converting from one data type to another, such as long to integer, data can be omitted or translated in a way that produces unexpected values. If the resulting values are used in a sensitive context, then dangerous behaviors may occur....\n\n### 3. CWE-197: Numeric Truncation Error (Score: 248.53)\n\nTruncation errors occur when a primitive is cast to a primitive of a smaller size and data is lost in the conversion....\n\n### 4. CWE-36: Absolute Path Traversal (Score: 241.99)\n\nThe product uses external input to construct a pathname that should be within a restricted directory, but it does not properly neutralize absolute path sequences such as \"/abs/path\" that can resolve to a location that is outside of that directory....\n\n### 5. CWE-451: User Interface (UI) Misrepresentation of Critical Information (Score: 225.38)\n\nThe user interface (UI) does not properly represent critical information to the user, allowing the information - or its source - to be obscured or spoofed. This is often a component in phishing attacks....\n\n## IMPACT: 'path traversal and code execution'\n\nRelevant CWEs for this IMPACT:\n\n### 1. CWE-22: Improper Limitation of a Pathname to a Restricted Directory ('Path Traversal') (Score: 251.33)\n\nThe product uses external input to construct a pathname that is intended to identify a file or directory that is located underneath a restricted parent directory, but the product does not properly neutralize special elements within the pathname that can cause the pathname to resolve to a location th...\n\n### 2. CWE-36: Absolute Path Traversal (Score: 241.99)\n\nThe product uses external input to construct a pathname that should be within a restricted directory, but it does not properly neutralize absolute path sequences such as \"/abs/path\" that can resolve to a location that is outside of that directory....\n\n### 3. CWE-23: Relative Path Traversal (Score: 232.76)\n\nThe product uses external input to construct a pathname that should be within a restricted directory, but it does not properly neutralize sequences such as \"..\" that can resolve to a location that is outside of that directory....\n\n### 4. CWE-41: Improper Resolution of Path Equivalence (Score: 232.51)\n\nThe product is vulnerable to file system contents disclosure through path equivalence. Path equivalence involves the use of special characters in file and directory names. The associated manipulations are intended to generate multiple names for the same object....\n\n### 5. CWE-59: Improper Link Resolution Before File Access ('Link Following') (Score: 88.57)\n\nThe product attempts to access a file based on the filename, but it does not properly prevent that filename from identifying a link or shortcut that resolves to an unintended resource....\n\n## VERSION: 'before 10.04.0'\n\nRelevant CWEs for this VERSION:\n\n### 1. CWE-22: Improper Limitation of a Pathname to a Restricted Directory ('Path Traversal') (Score: 251.33)\n\nThe product uses external input to construct a pathname that is intended to identify a file or directory that is located underneath a restricted parent directory, but the product does not properly neutralize special elements within the pathname that can cause the pathname to resolve to a location th...\n\n### 2. CWE-36: Absolute Path Traversal (Score: 241.99)\n\nThe product uses external input to construct a pathname that should be within a restricted directory, but it does not properly neutralize absolute path sequences such as \"/abs/path\" that can resolve to a location that is outside of that directory....\n\n### 3. CWE-122: Heap-based Buffer Overflow (Score: 238.55)\n\nA heap overflow condition is a buffer overflow, where the buffer that can be overwritten is allocated in the heap portion of memory, generally meaning that the buffer was allocated using a routine such as malloc()....\n\n### 4. CWE-20: Improper Input Validation (Score: 76.96)\n\nThe product receives input or data, but it does\n        not validate or incorrectly validates that the input has the\n        properties that are required to process the data safely and\n        correctly....\n\n### 5. CWE-125: Out-of-bounds Read (Score: 69.65)\n\nThe product reads data past the end, or before the beginning, of the intended buffer....\n\n## COMPONENT: 'base/gsdevice.c'\n\nRelevant CWEs for this COMPONENT:\n\n### 1. CWE-22: Improper Limitation of a Pathname to a Restricted Directory ('Path Traversal') (Score: 251.33)\n\nThe product uses external input to construct a pathname that is intended to identify a file or directory that is located underneath a restricted parent directory, but the product does not properly neutralize special elements within the pathname that can cause the pathname to resolve to a location th...\n\n### 2. CWE-197: Numeric Truncation Error (Score: 248.53)\n\nTruncation errors occur when a primitive is cast to a primitive of a smaller size and data is lost in the conversion....\n\n### 3. CWE-122: Heap-based Buffer Overflow (Score: 238.55)\n\nA heap overflow condition is a buffer overflow, where the buffer that can be overwritten is allocated in the heap portion of memory, generally meaning that the buffer was allocated using a routine such as malloc()....\n\n### 4. CWE-170: Improper Null Termination (Score: 76.13)\n\nThe product does not terminate or incorrectly terminates a string or array with a null character or equivalent terminator....\n\n### 5. CWE-125: Out-of-bounds Read (Score: 69.65)\n\nThe product reads data past the end, or before the beginning, of the intended buffer....\n\n\n    # Analysis Instructions\n    1. For each keyphrase, identify the most appropriate CWE(s) that represent the weakness.\n    2. Consider how the different keyphrases might relate to each other in the vulnerability chain.\n    3. Provide a final determination of primary CWE(s) and any secondary CWEs.\n    4. Format your response using the standard analysis template.\n\n    Please analyze how these different weaknesses interact and provide a comprehensive CWE classification.\n    "
  },
  "retrieval_time": 1.1804802417755127
}