{
  "vulnerability_info": "VulnerabilityInfo(cve_id='CVE-2024-7604', description='Logsign Unified SecOps Platform **Incorrect Authorization** Authentication Bypass Vulnerability. This vulnerability allows local attackers to bypass authentication on affected installations of Logsign Unified SecOps Platform. Authentication is required to exploit this vulnerability. The specific flaw exists within the HTTP API service, which listens on TCP port 443 by default. The issue results from the **lack of proper validation of the users license expiration date**. An attacker can leverage this vulnerability to bypass authentication on the system. Was ZDI-CAN-25029.', key_phrases={'rootcause': ['Incorrect Authorization', 'lack of proper validation of the users license expiration date'], 'weakness': '', 'impact': 'authentication bypass', 'vector': '', 'attacker': 'local attackers', 'product': 'Logsign Unified SecOps Platform', 'version': '', 'component': 'HTTP API service'}, reference_content='```\\n{\\n  \"Root cause of vulnerability\": \"The vulnerability results from the lack of proper validation of the user\\'s license expiration date within the HTTP API service.\",\\n  \"Weaknesses/vulnerabilities present\": \"Incorrect authorization, authentication bypass due to improper license validation.\",\\n  \"Impact of exploitation\": \"Local attackers can bypass authentication on the Logsign Unified SecOps Platform.\",\\n  \"Attack vectors\": \"Local access to the system, exploiting the HTTP API service.\",\\n  \"Required attacker capabilities/position\": \"Local access to the system. No prior authentication is required since the vulnerability allows bypassing authentication.\"\\n}\\n```', similar_info={'cwe_distribution': {}, 'cwe_consensus': '', 'similarity_stats': {'thresholds': [], 'total_samples_by_threshold': {}, 'top_cwes_by_threshold': {}}}, similarity_summary=SimilarityInsight(consensus_cwe='', top_cwes=[], confidence_levels={}, total_samples=0), analysis='', analysis_with_relationships='', criticism='', resolution='', relevant_cwes=[{'metadata': {'doc_id': '20', 'name': 'Improper Input Validation', 'source': 'sparse', 'original_content': 'The product receives input or data, but it does\\n        not validate or incorrectly validates that the input has the\\n        properties that are required to process the data safely and\\n        correctly.', 'keyphrase_sources': [{'id': 'rootcause:lack of proper validation of the users license expiration date', 'keyphrase': 'lack of proper validation of the users license expiration date', 'type': 'rootcause'}, {'id': 'product:Logsign Unified SecOps Platform', 'keyphrase': 'Logsign Unified SecOps Platform', 'type': 'product'}]}, 'similarity': np.float64(556.4010002359846)}, {'metadata': {'doc_id': '287', 'name': 'Improper Authentication', 'source': 'sparse', 'original_content': 'When an actor claims to have a given identity, the product does not prove or insufficiently proves that the claim is correct.', 'keyphrase_sources': [{'id': 'rootcause:lack of proper validation of the users license expiration date', 'keyphrase': 'lack of proper validation of the users license expiration date', 'type': 'rootcause'}, {'id': 'impact:authentication bypass', 'keyphrase': 'authentication bypass', 'type': 'impact'}, {'id': 'component:HTTP API service', 'keyphrase': 'HTTP API service', 'type': 'component'}]}, 'similarity': np.float64(544.3420694692978)}, {'metadata': {'doc_id': '697', 'name': 'Incorrect Comparison', 'source': 'sparse', 'original_content': 'The product compares two entities in a security-relevant context, but the comparison is incorrect, which may lead to resultant weaknesses.', 'keyphrase_sources': [{'id': 'rootcause:Incorrect Authorization', 'keyphrase': 'Incorrect Authorization', 'type': 'rootcause'}, {'id': 'impact:authentication bypass', 'keyphrase': 'authentication bypass', 'type': 'impact'}, {'id': 'attacker:local attackers', 'keyphrase': 'local attackers', 'type': 'attacker'}, {'id': 'product:Logsign Unified SecOps Platform', 'keyphrase': 'Logsign Unified SecOps Platform', 'type': 'product'}, {'id': 'component:HTTP API service', 'keyphrase': 'HTTP API service', 'type': 'component'}]}, 'similarity': np.float64(503.66998484383845)}, {'metadata': {'doc_id': '306', 'name': 'Missing Authentication for Critical Function', 'source': 'sparse', 'original_content': 'The product does not perform any authentication for functionality that requires a provable user identity or consumes a significant amount of resources.', 'keyphrase_sources': [{'id': 'rootcause:Incorrect Authorization', 'keyphrase': 'Incorrect Authorization', 'type': 'rootcause'}, {'id': 'rootcause:lack of proper validation of the users license expiration date', 'keyphrase': 'lack of proper validation of the users license expiration date', 'type': 'rootcause'}, {'id': 'impact:authentication bypass', 'keyphrase': 'authentication bypass', 'type': 'impact'}, {'id': 'attacker:local attackers', 'keyphrase': 'local attackers', 'type': 'attacker'}, {'id': 'product:Logsign Unified SecOps Platform', 'keyphrase': 'Logsign Unified SecOps Platform', 'type': 'product'}, {'id': 'component:HTTP API service', 'keyphrase': 'HTTP API service', 'type': 'component'}]}, 'similarity': np.float64(491.6750999649038)}, {'metadata': {'doc_id': '285', 'name': 'Improper Authorization', 'source': 'sparse', 'original_content': 'The product does not perform or incorrectly performs an authorization check when an actor attempts to access a resource or perform an action.', 'keyphrase_sources': [{'id': 'rootcause:Incorrect Authorization', 'keyphrase': 'Incorrect Authorization', 'type': 'rootcause'}, {'id': 'rootcause:lack of proper validation of the users license expiration date', 'keyphrase': 'lack of proper validation of the users license expiration date', 'type': 'rootcause'}, {'id': 'impact:authentication bypass', 'keyphrase': 'authentication bypass', 'type': 'impact'}, {'id': 'attacker:local attackers', 'keyphrase': 'local attackers', 'type': 'attacker'}, {'id': 'product:Logsign Unified SecOps Platform', 'keyphrase': 'Logsign Unified SecOps Platform', 'type': 'product'}, {'id': 'component:HTTP API service', 'keyphrase': 'HTTP API service', 'type': 'component'}]}, 'similarity': np.float64(476.7149680820336)}, {'metadata': {'doc_id': '863', 'name': 'Incorrect Authorization', 'source': 'sparse', 'original_content': 'The product performs an authorization check when an actor attempts to access a resource or perform an action, but it does not correctly perform the check.', 'keyphrase_sources': [{'id': 'rootcause:Incorrect Authorization', 'keyphrase': 'Incorrect Authorization', 'type': 'rootcause'}]}, 'similarity': np.float64(468.1876825143777)}, {'metadata': {'doc_id': '620', 'name': 'Unverified Password Change', 'source': 'sparse', 'original_content': 'When setting a new password for a user, the product does not require knowledge of the original password, or using another form of authentication.', 'keyphrase_sources': [{'id': 'rootcause:Incorrect Authorization', 'keyphrase': 'Incorrect Authorization', 'type': 'rootcause'}, {'id': 'rootcause:lack of proper validation of the users license expiration date', 'keyphrase': 'lack of proper validation of the users license expiration date', 'type': 'rootcause'}, {'id': 'impact:authentication bypass', 'keyphrase': 'authentication bypass', 'type': 'impact'}, {'id': 'attacker:local attackers', 'keyphrase': 'local attackers', 'type': 'attacker'}, {'id': 'component:HTTP API service', 'keyphrase': 'HTTP API service', 'type': 'component'}]}, 'similarity': np.float64(461.0609327987769)}, {'metadata': {'doc_id': '321', 'name': 'Use of Hard-coded Cryptographic Key', 'source': 'sparse', 'original_content': 'The use of a hard-coded cryptographic key significantly increases the possibility that encrypted data may be recovered.', 'keyphrase_sources': [{'id': 'attacker:local attackers', 'keyphrase': 'local attackers', 'type': 'attacker'}, {'id': 'product:Logsign Unified SecOps Platform', 'keyphrase': 'Logsign Unified SecOps Platform', 'type': 'product'}]}, 'similarity': np.float64(152.45990666531884)}], identified_cwes={'analyzer': [], 'critic_additional': []})",
  "retrieval_results": {
    "has_multiple_keyphrases": true,
    "keyphrase_cwe_sets": {
      "rootcause:Incorrect Authorization": {
        "keyphrase": "Incorrect Authorization",
        "type": "rootcause",
        "cwes": [
          {
            "metadata": {
              "doc_id": "697",
              "name": "Incorrect Comparison",
              "source": "sparse",
              "original_content": "The product compares two entities in a security-relevant context, but the comparison is incorrect, which may lead to resultant weaknesses.",
              "keyphrase_sources": [
                {
                  "id": "rootcause:Incorrect Authorization",
                  "keyphrase": "Incorrect Authorization",
                  "type": "rootcause"
                },
                {
                  "id": "impact:authentication bypass",
                  "keyphrase": "authentication bypass",
                  "type": "impact"
                },
                {
                  "id": "attacker:local attackers",
                  "keyphrase": "local attackers",
                  "type": "attacker"
                },
                {
                  "id": "product:Logsign Unified SecOps Platform",
                  "keyphrase": "Logsign Unified SecOps Platform",
                  "type": "product"
                },
                {
                  "id": "component:HTTP API service",
                  "keyphrase": "HTTP API service",
                  "type": "component"
                }
              ]
            },
            "similarity": 503.66998484383845
          },
          {
            "metadata": {
              "doc_id": "306",
              "name": "Missing Authentication for Critical Function",
              "source": "sparse",
              "original_content": "The product does not perform any authentication for functionality that requires a provable user identity or consumes a significant amount of resources.",
              "keyphrase_sources": [
                {
                  "id": "rootcause:Incorrect Authorization",
                  "keyphrase": "Incorrect Authorization",
                  "type": "rootcause"
                },
                {
                  "id": "rootcause:lack of proper validation of the users license expiration date",
                  "keyphrase": "lack of proper validation of the users license expiration date",
                  "type": "rootcause"
                },
                {
                  "id": "impact:authentication bypass",
                  "keyphrase": "authentication bypass",
                  "type": "impact"
                },
                {
                  "id": "attacker:local attackers",
                  "keyphrase": "local attackers",
                  "type": "attacker"
                },
                {
                  "id": "product:Logsign Unified SecOps Platform",
                  "keyphrase": "Logsign Unified SecOps Platform",
                  "type": "product"
                },
                {
                  "id": "component:HTTP API service",
                  "keyphrase": "HTTP API service",
                  "type": "component"
                }
              ]
            },
            "similarity": 491.6750999649038
          },
          {
            "metadata": {
              "doc_id": "285",
              "name": "Improper Authorization",
              "source": "sparse",
              "original_content": "The product does not perform or incorrectly performs an authorization check when an actor attempts to access a resource or perform an action.",
              "keyphrase_sources": [
                {
                  "id": "rootcause:Incorrect Authorization",
                  "keyphrase": "Incorrect Authorization",
                  "type": "rootcause"
                },
                {
                  "id": "rootcause:lack of proper validation of the users license expiration date",
                  "keyphrase": "lack of proper validation of the users license expiration date",
                  "type": "rootcause"
                },
                {
                  "id": "impact:authentication bypass",
                  "keyphrase": "authentication bypass",
                  "type": "impact"
                },
                {
                  "id": "attacker:local attackers",
                  "keyphrase": "local attackers",
                  "type": "attacker"
                },
                {
                  "id": "product:Logsign Unified SecOps Platform",
                  "keyphrase": "Logsign Unified SecOps Platform",
                  "type": "product"
                },
                {
                  "id": "component:HTTP API service",
                  "keyphrase": "HTTP API service",
                  "type": "component"
                }
              ]
            },
            "similarity": 476.7149680820336
          },
          {
            "metadata": {
              "doc_id": "863",
              "name": "Incorrect Authorization",
              "source": "sparse",
              "original_content": "The product performs an authorization check when an actor attempts to access a resource or perform an action, but it does not correctly perform the check.",
              "keyphrase_sources": [
                {
                  "id": "rootcause:Incorrect Authorization",
                  "keyphrase": "Incorrect Authorization",
                  "type": "rootcause"
                }
              ]
            },
            "similarity": 468.1876825143777
          },
          {
            "metadata": {
              "doc_id": "620",
              "name": "Unverified Password Change",
              "source": "sparse",
              "original_content": "When setting a new password for a user, the product does not require knowledge of the original password, or using another form of authentication.",
              "keyphrase_sources": [
                {
                  "id": "rootcause:Incorrect Authorization",
                  "keyphrase": "Incorrect Authorization",
                  "type": "rootcause"
                },
                {
                  "id": "rootcause:lack of proper validation of the users license expiration date",
                  "keyphrase": "lack of proper validation of the users license expiration date",
                  "type": "rootcause"
                },
                {
                  "id": "impact:authentication bypass",
                  "keyphrase": "authentication bypass",
                  "type": "impact"
                },
                {
                  "id": "attacker:local attackers",
                  "keyphrase": "local attackers",
                  "type": "attacker"
                },
                {
                  "id": "component:HTTP API service",
                  "keyphrase": "HTTP API service",
                  "type": "component"
                }
              ]
            },
            "similarity": 461.0609327987769
          }
        ]
      },
      "rootcause:lack of proper validation of the users license expiration date": {
        "keyphrase": "lack of proper validation of the users license expiration date",
        "type": "rootcause",
        "cwes": [
          {
            "metadata": {
              "doc_id": "306",
              "name": "Missing Authentication for Critical Function",
              "source": "sparse",
              "original_content": "The product does not perform any authentication for functionality that requires a provable user identity or consumes a significant amount of resources."
            },
            "similarity": 566.2792005249856
          },
          {
            "metadata": {
              "doc_id": "620",
              "name": "Unverified Password Change",
              "source": "sparse",
              "original_content": "When setting a new password for a user, the product does not require knowledge of the original password, or using another form of authentication."
            },
            "similarity": 563.0597309239231
          },
          {
            "metadata": {
              "doc_id": "20",
              "name": "Improper Input Validation",
              "source": "sparse",
              "original_content": "The product receives input or data, but it does\n        not validate or incorrectly validates that the input has the\n        properties that are required to process the data safely and\n        correctly.",
              "keyphrase_sources": [
                {
                  "id": "rootcause:lack of proper validation of the users license expiration date",
                  "keyphrase": "lack of proper validation of the users license expiration date",
                  "type": "rootcause"
                },
                {
                  "id": "product:Logsign Unified SecOps Platform",
                  "keyphrase": "Logsign Unified SecOps Platform",
                  "type": "product"
                }
              ]
            },
            "similarity": 556.4010002359846
          },
          {
            "metadata": {
              "doc_id": "287",
              "name": "Improper Authentication",
              "source": "sparse",
              "original_content": "When an actor claims to have a given identity, the product does not prove or insufficiently proves that the claim is correct.",
              "keyphrase_sources": [
                {
                  "id": "rootcause:lack of proper validation of the users license expiration date",
                  "keyphrase": "lack of proper validation of the users license expiration date",
                  "type": "rootcause"
                },
                {
                  "id": "impact:authentication bypass",
                  "keyphrase": "authentication bypass",
                  "type": "impact"
                },
                {
                  "id": "component:HTTP API service",
                  "keyphrase": "HTTP API service",
                  "type": "component"
                }
              ]
            },
            "similarity": 544.3420694692978
          },
          {
            "metadata": {
              "doc_id": "285",
              "name": "Improper Authorization",
              "source": "sparse",
              "original_content": "The product does not perform or incorrectly performs an authorization check when an actor attempts to access a resource or perform an action."
            },
            "similarity": 542.4713808737815
          }
        ]
      },
      "impact:authentication bypass": {
        "keyphrase": "authentication bypass",
        "type": "impact",
        "cwes": [
          {
            "metadata": {
              "doc_id": "306",
              "name": "Missing Authentication for Critical Function",
              "source": "sparse",
              "original_content": "The product does not perform any authentication for functionality that requires a provable user identity or consumes a significant amount of resources."
            },
            "similarity": 163.60720762146465
          },
          {
            "metadata": {
              "doc_id": "697",
              "name": "Incorrect Comparison",
              "source": "sparse",
              "original_content": "The product compares two entities in a security-relevant context, but the comparison is incorrect, which may lead to resultant weaknesses."
            },
            "similarity": 162.70376502026392
          },
          {
            "metadata": {
              "doc_id": "287",
              "name": "Improper Authentication",
              "source": "sparse",
              "original_content": "When an actor claims to have a given identity, the product does not prove or insufficiently proves that the claim is correct."
            },
            "similarity": 155.03851337020714
          },
          {
            "metadata": {
              "doc_id": "620",
              "name": "Unverified Password Change",
              "source": "sparse",
              "original_content": "When setting a new password for a user, the product does not require knowledge of the original password, or using another form of authentication."
            },
            "similarity": 154.0910829404986
          },
          {
            "metadata": {
              "doc_id": "285",
              "name": "Improper Authorization",
              "source": "sparse",
              "original_content": "The product does not perform or incorrectly performs an authorization check when an actor attempts to access a resource or perform an action."
            },
            "similarity": 152.9151073221886
          }
        ]
      },
      "attacker:local attackers": {
        "keyphrase": "local attackers",
        "type": "attacker",
        "cwes": [
          {
            "metadata": {
              "doc_id": "306",
              "name": "Missing Authentication for Critical Function",
              "source": "sparse",
              "original_content": "The product does not perform any authentication for functionality that requires a provable user identity or consumes a significant amount of resources."
            },
            "similarity": 159.55660968316076
          },
          {
            "metadata": {
              "doc_id": "697",
              "name": "Incorrect Comparison",
              "source": "sparse",
              "original_content": "The product compares two entities in a security-relevant context, but the comparison is incorrect, which may lead to resultant weaknesses."
            },
            "similarity": 156.10956967831737
          },
          {
            "metadata": {
              "doc_id": "321",
              "name": "Use of Hard-coded Cryptographic Key",
              "source": "sparse",
              "original_content": "The use of a hard-coded cryptographic key significantly increases the possibility that encrypted data may be recovered.",
              "keyphrase_sources": [
                {
                  "id": "attacker:local attackers",
                  "keyphrase": "local attackers",
                  "type": "attacker"
                },
                {
                  "id": "product:Logsign Unified SecOps Platform",
                  "keyphrase": "Logsign Unified SecOps Platform",
                  "type": "product"
                }
              ]
            },
            "similarity": 152.45990666531884
          },
          {
            "metadata": {
              "doc_id": "285",
              "name": "Improper Authorization",
              "source": "sparse",
              "original_content": "The product does not perform or incorrectly performs an authorization check when an actor attempts to access a resource or perform an action."
            },
            "similarity": 150.60844745538577
          },
          {
            "metadata": {
              "doc_id": "620",
              "name": "Unverified Password Change",
              "source": "sparse",
              "original_content": "When setting a new password for a user, the product does not require knowledge of the original password, or using another form of authentication."
            },
            "similarity": 150.53406446912675
          }
        ]
      },
      "product:Logsign Unified SecOps Platform": {
        "keyphrase": "Logsign Unified SecOps Platform",
        "type": "product",
        "cwes": [
          {
            "metadata": {
              "doc_id": "306",
              "name": "Missing Authentication for Critical Function",
              "source": "sparse",
              "original_content": "The product does not perform any authentication for functionality that requires a provable user identity or consumes a significant amount of resources."
            },
            "similarity": 159.11215978487948
          },
          {
            "metadata": {
              "doc_id": "321",
              "name": "Use of Hard-coded Cryptographic Key",
              "source": "sparse",
              "original_content": "The use of a hard-coded cryptographic key significantly increases the possibility that encrypted data may be recovered."
            },
            "similarity": 158.6304773444357
          },
          {
            "metadata": {
              "doc_id": "697",
              "name": "Incorrect Comparison",
              "source": "sparse",
              "original_content": "The product compares two entities in a security-relevant context, but the comparison is incorrect, which may lead to resultant weaknesses."
            },
            "similarity": 154.59027959911828
          },
          {
            "metadata": {
              "doc_id": "20",
              "name": "Improper Input Validation",
              "source": "sparse",
              "original_content": "The product receives input or data, but it does\n        not validate or incorrectly validates that the input has the\n        properties that are required to process the data safely and\n        correctly."
            },
            "similarity": 153.16937017229563
          },
          {
            "metadata": {
              "doc_id": "285",
              "name": "Improper Authorization",
              "source": "sparse",
              "original_content": "The product does not perform or incorrectly performs an authorization check when an actor attempts to access a resource or perform an action."
            },
            "similarity": 149.0081077472106
          }
        ]
      },
      "component:HTTP API service": {
        "keyphrase": "HTTP API service",
        "type": "component",
        "cwes": [
          {
            "metadata": {
              "doc_id": "306",
              "name": "Missing Authentication for Critical Function",
              "source": "sparse",
              "original_content": "The product does not perform any authentication for functionality that requires a provable user identity or consumes a significant amount of resources."
            },
            "similarity": 167.53221456463243
          },
          {
            "metadata": {
              "doc_id": "697",
              "name": "Incorrect Comparison",
              "source": "sparse",
              "original_content": "The product compares two entities in a security-relevant context, but the comparison is incorrect, which may lead to resultant weaknesses."
            },
            "similarity": 160.3767593217583
          },
          {
            "metadata": {
              "doc_id": "285",
              "name": "Improper Authorization",
              "source": "sparse",
              "original_content": "The product does not perform or incorrectly performs an authorization check when an actor attempts to access a resource or perform an action."
            },
            "similarity": 156.8990189763981
          },
          {
            "metadata": {
              "doc_id": "287",
              "name": "Improper Authentication",
              "source": "sparse",
              "original_content": "When an actor claims to have a given identity, the product does not prove or insufficiently proves that the claim is correct."
            },
            "similarity": 155.61902971928768
          },
          {
            "metadata": {
              "doc_id": "620",
              "name": "Unverified Password Change",
              "source": "sparse",
              "original_content": "When setting a new password for a user, the product does not require knowledge of the original password, or using another form of authentication."
            },
            "similarity": 155.49523783796394
          }
        ]
      }
    },
    "keyphrase_mapping": {
      "697": [
        {
          "id": "rootcause:Incorrect Authorization",
          "keyphrase": "Incorrect Authorization",
          "type": "rootcause"
        },
        {
          "id": "impact:authentication bypass",
          "keyphrase": "authentication bypass",
          "type": "impact"
        },
        {
          "id": "attacker:local attackers",
          "keyphrase": "local attackers",
          "type": "attacker"
        },
        {
          "id": "product:Logsign Unified SecOps Platform",
          "keyphrase": "Logsign Unified SecOps Platform",
          "type": "product"
        },
        {
          "id": "component:HTTP API service",
          "keyphrase": "HTTP API service",
          "type": "component"
        }
      ],
      "306": [
        {
          "id": "rootcause:Incorrect Authorization",
          "keyphrase": "Incorrect Authorization",
          "type": "rootcause"
        },
        {
          "id": "rootcause:lack of proper validation of the users license expiration date",
          "keyphrase": "lack of proper validation of the users license expiration date",
          "type": "rootcause"
        },
        {
          "id": "impact:authentication bypass",
          "keyphrase": "authentication bypass",
          "type": "impact"
        },
        {
          "id": "attacker:local attackers",
          "keyphrase": "local attackers",
          "type": "attacker"
        },
        {
          "id": "product:Logsign Unified SecOps Platform",
          "keyphrase": "Logsign Unified SecOps Platform",
          "type": "product"
        },
        {
          "id": "component:HTTP API service",
          "keyphrase": "HTTP API service",
          "type": "component"
        }
      ],
      "285": [
        {
          "id": "rootcause:Incorrect Authorization",
          "keyphrase": "Incorrect Authorization",
          "type": "rootcause"
        },
        {
          "id": "rootcause:lack of proper validation of the users license expiration date",
          "keyphrase": "lack of proper validation of the users license expiration date",
          "type": "rootcause"
        },
        {
          "id": "impact:authentication bypass",
          "keyphrase": "authentication bypass",
          "type": "impact"
        },
        {
          "id": "attacker:local attackers",
          "keyphrase": "local attackers",
          "type": "attacker"
        },
        {
          "id": "product:Logsign Unified SecOps Platform",
          "keyphrase": "Logsign Unified SecOps Platform",
          "type": "product"
        },
        {
          "id": "component:HTTP API service",
          "keyphrase": "HTTP API service",
          "type": "component"
        }
      ],
      "863": [
        {
          "id": "rootcause:Incorrect Authorization",
          "keyphrase": "Incorrect Authorization",
          "type": "rootcause"
        }
      ],
      "620": [
        {
          "id": "rootcause:Incorrect Authorization",
          "keyphrase": "Incorrect Authorization",
          "type": "rootcause"
        },
        {
          "id": "rootcause:lack of proper validation of the users license expiration date",
          "keyphrase": "lack of proper validation of the users license expiration date",
          "type": "rootcause"
        },
        {
          "id": "impact:authentication bypass",
          "keyphrase": "authentication bypass",
          "type": "impact"
        },
        {
          "id": "attacker:local attackers",
          "keyphrase": "local attackers",
          "type": "attacker"
        },
        {
          "id": "component:HTTP API service",
          "keyphrase": "HTTP API service",
          "type": "component"
        }
      ],
      "20": [
        {
          "id": "rootcause:lack of proper validation of the users license expiration date",
          "keyphrase": "lack of proper validation of the users license expiration date",
          "type": "rootcause"
        },
        {
          "id": "product:Logsign Unified SecOps Platform",
          "keyphrase": "Logsign Unified SecOps Platform",
          "type": "product"
        }
      ],
      "287": [
        {
          "id": "rootcause:lack of proper validation of the users license expiration date",
          "keyphrase": "lack of proper validation of the users license expiration date",
          "type": "rootcause"
        },
        {
          "id": "impact:authentication bypass",
          "keyphrase": "authentication bypass",
          "type": "impact"
        },
        {
          "id": "component:HTTP API service",
          "keyphrase": "HTTP API service",
          "type": "component"
        }
      ],
      "321": [
        {
          "id": "attacker:local attackers",
          "keyphrase": "local attackers",
          "type": "attacker"
        },
        {
          "id": "product:Logsign Unified SecOps Platform",
          "keyphrase": "Logsign Unified SecOps Platform",
          "type": "product"
        }
      ]
    },
    "relevant_cwes": [
      {
        "metadata": {
          "doc_id": "20",
          "name": "Improper Input Validation",
          "source": "sparse",
          "original_content": "The product receives input or data, but it does\n        not validate or incorrectly validates that the input has the\n        properties that are required to process the data safely and\n        correctly.",
          "keyphrase_sources": [
            {
              "id": "rootcause:lack of proper validation of the users license expiration date",
              "keyphrase": "lack of proper validation of the users license expiration date",
              "type": "rootcause"
            },
            {
              "id": "product:Logsign Unified SecOps Platform",
              "keyphrase": "Logsign Unified SecOps Platform",
              "type": "product"
            }
          ]
        },
        "similarity": 556.4010002359846
      },
      {
        "metadata": {
          "doc_id": "287",
          "name": "Improper Authentication",
          "source": "sparse",
          "original_content": "When an actor claims to have a given identity, the product does not prove or insufficiently proves that the claim is correct.",
          "keyphrase_sources": [
            {
              "id": "rootcause:lack of proper validation of the users license expiration date",
              "keyphrase": "lack of proper validation of the users license expiration date",
              "type": "rootcause"
            },
            {
              "id": "impact:authentication bypass",
              "keyphrase": "authentication bypass",
              "type": "impact"
            },
            {
              "id": "component:HTTP API service",
              "keyphrase": "HTTP API service",
              "type": "component"
            }
          ]
        },
        "similarity": 544.3420694692978
      },
      {
        "metadata": {
          "doc_id": "697",
          "name": "Incorrect Comparison",
          "source": "sparse",
          "original_content": "The product compares two entities in a security-relevant context, but the comparison is incorrect, which may lead to resultant weaknesses.",
          "keyphrase_sources": [
            {
              "id": "rootcause:Incorrect Authorization",
              "keyphrase": "Incorrect Authorization",
              "type": "rootcause"
            },
            {
              "id": "impact:authentication bypass",
              "keyphrase": "authentication bypass",
              "type": "impact"
            },
            {
              "id": "attacker:local attackers",
              "keyphrase": "local attackers",
              "type": "attacker"
            },
            {
              "id": "product:Logsign Unified SecOps Platform",
              "keyphrase": "Logsign Unified SecOps Platform",
              "type": "product"
            },
            {
              "id": "component:HTTP API service",
              "keyphrase": "HTTP API service",
              "type": "component"
            }
          ]
        },
        "similarity": 503.66998484383845
      },
      {
        "metadata": {
          "doc_id": "306",
          "name": "Missing Authentication for Critical Function",
          "source": "sparse",
          "original_content": "The product does not perform any authentication for functionality that requires a provable user identity or consumes a significant amount of resources.",
          "keyphrase_sources": [
            {
              "id": "rootcause:Incorrect Authorization",
              "keyphrase": "Incorrect Authorization",
              "type": "rootcause"
            },
            {
              "id": "rootcause:lack of proper validation of the users license expiration date",
              "keyphrase": "lack of proper validation of the users license expiration date",
              "type": "rootcause"
            },
            {
              "id": "impact:authentication bypass",
              "keyphrase": "authentication bypass",
              "type": "impact"
            },
            {
              "id": "attacker:local attackers",
              "keyphrase": "local attackers",
              "type": "attacker"
            },
            {
              "id": "product:Logsign Unified SecOps Platform",
              "keyphrase": "Logsign Unified SecOps Platform",
              "type": "product"
            },
            {
              "id": "component:HTTP API service",
              "keyphrase": "HTTP API service",
              "type": "component"
            }
          ]
        },
        "similarity": 491.6750999649038
      },
      {
        "metadata": {
          "doc_id": "285",
          "name": "Improper Authorization",
          "source": "sparse",
          "original_content": "The product does not perform or incorrectly performs an authorization check when an actor attempts to access a resource or perform an action.",
          "keyphrase_sources": [
            {
              "id": "rootcause:Incorrect Authorization",
              "keyphrase": "Incorrect Authorization",
              "type": "rootcause"
            },
            {
              "id": "rootcause:lack of proper validation of the users license expiration date",
              "keyphrase": "lack of proper validation of the users license expiration date",
              "type": "rootcause"
            },
            {
              "id": "impact:authentication bypass",
              "keyphrase": "authentication bypass",
              "type": "impact"
            },
            {
              "id": "attacker:local attackers",
              "keyphrase": "local attackers",
              "type": "attacker"
            },
            {
              "id": "product:Logsign Unified SecOps Platform",
              "keyphrase": "Logsign Unified SecOps Platform",
              "type": "product"
            },
            {
              "id": "component:HTTP API service",
              "keyphrase": "HTTP API service",
              "type": "component"
            }
          ]
        },
        "similarity": 476.7149680820336
      },
      {
        "metadata": {
          "doc_id": "863",
          "name": "Incorrect Authorization",
          "source": "sparse",
          "original_content": "The product performs an authorization check when an actor attempts to access a resource or perform an action, but it does not correctly perform the check.",
          "keyphrase_sources": [
            {
              "id": "rootcause:Incorrect Authorization",
              "keyphrase": "Incorrect Authorization",
              "type": "rootcause"
            }
          ]
        },
        "similarity": 468.1876825143777
      },
      {
        "metadata": {
          "doc_id": "620",
          "name": "Unverified Password Change",
          "source": "sparse",
          "original_content": "When setting a new password for a user, the product does not require knowledge of the original password, or using another form of authentication.",
          "keyphrase_sources": [
            {
              "id": "rootcause:Incorrect Authorization",
              "keyphrase": "Incorrect Authorization",
              "type": "rootcause"
            },
            {
              "id": "rootcause:lack of proper validation of the users license expiration date",
              "keyphrase": "lack of proper validation of the users license expiration date",
              "type": "rootcause"
            },
            {
              "id": "impact:authentication bypass",
              "keyphrase": "authentication bypass",
              "type": "impact"
            },
            {
              "id": "attacker:local attackers",
              "keyphrase": "local attackers",
              "type": "attacker"
            },
            {
              "id": "component:HTTP API service",
              "keyphrase": "HTTP API service",
              "type": "component"
            }
          ]
        },
        "similarity": 461.0609327987769
      },
      {
        "metadata": {
          "doc_id": "321",
          "name": "Use of Hard-coded Cryptographic Key",
          "source": "sparse",
          "original_content": "The use of a hard-coded cryptographic key significantly increases the possibility that encrypted data may be recovered.",
          "keyphrase_sources": [
            {
              "id": "attacker:local attackers",
              "keyphrase": "local attackers",
              "type": "attacker"
            },
            {
              "id": "product:Logsign Unified SecOps Platform",
              "keyphrase": "Logsign Unified SecOps Platform",
              "type": "product"
            }
          ]
        },
        "similarity": 152.45990666531884
      }
    ],
    "enhanced_query": "# Vulnerability Description\n\n    Logsign Unified SecOps Platform **Incorrect Authorization** Authentication Bypass Vulnerability. This vulnerability allows local attackers to bypass authentication on affected installations of Logsign Unified SecOps Platform. Authentication is required to exploit this vulnerability. The specific flaw exists within the HTTP API service, which listens on TCP port 443 by default. The issue results from the **lack of proper validation of the users license expiration date**. An attacker can leverage this vulnerability to bypass authentication on the system. Was ZDI-CAN-25029.\n\n    # Keyphrase-Specific CWE Analysis\n    This vulnerability contains multiple keyphrases that may map to different CWEs. \n    Please analyze each keyphrase separately and determine the most appropriate CWE(s) for each.\n\n    ## ROOTCAUSE: 'lack of proper validation of the users license expiration date'\n\nRelevant CWEs for this ROOTCAUSE:\n\n### 1. CWE-20: Improper Input Validation (Score: 556.40)\n\nThe product receives input or data, but it does\n        not validate or incorrectly validates that the input has the\n        properties that are required to process the data safely and\n        correctly....\n\n### 2. CWE-287: Improper Authentication (Score: 544.34)\n\nWhen an actor claims to have a given identity, the product does not prove or insufficiently proves that the claim is correct....\n\n### 3. CWE-306: Missing Authentication for Critical Function (Score: 491.68)\n\nThe product does not perform any authentication for functionality that requires a provable user identity or consumes a significant amount of resources....\n\n### 4. CWE-285: Improper Authorization (Score: 476.71)\n\nThe product does not perform or incorrectly performs an authorization check when an actor attempts to access a resource or perform an action....\n\n### 5. CWE-620: Unverified Password Change (Score: 461.06)\n\nWhen setting a new password for a user, the product does not require knowledge of the original password, or using another form of authentication....\n\n## PRODUCT: 'Logsign Unified SecOps Platform'\n\nRelevant CWEs for this PRODUCT:\n\n### 1. CWE-20: Improper Input Validation (Score: 556.40)\n\nThe product receives input or data, but it does\n        not validate or incorrectly validates that the input has the\n        properties that are required to process the data safely and\n        correctly....\n\n### 2. CWE-697: Incorrect Comparison (Score: 503.67)\n\nThe product compares two entities in a security-relevant context, but the comparison is incorrect, which may lead to resultant weaknesses....\n\n### 3. CWE-306: Missing Authentication for Critical Function (Score: 491.68)\n\nThe product does not perform any authentication for functionality that requires a provable user identity or consumes a significant amount of resources....\n\n### 4. CWE-285: Improper Authorization (Score: 476.71)\n\nThe product does not perform or incorrectly performs an authorization check when an actor attempts to access a resource or perform an action....\n\n### 5. CWE-321: Use of Hard-coded Cryptographic Key (Score: 152.46)\n\nThe use of a hard-coded cryptographic key significantly increases the possibility that encrypted data may be recovered....\n\n## IMPACT: 'authentication bypass'\n\nRelevant CWEs for this IMPACT:\n\n### 1. CWE-287: Improper Authentication (Score: 544.34)\n\nWhen an actor claims to have a given identity, the product does not prove or insufficiently proves that the claim is correct....\n\n### 2. CWE-697: Incorrect Comparison (Score: 503.67)\n\nThe product compares two entities in a security-relevant context, but the comparison is incorrect, which may lead to resultant weaknesses....\n\n### 3. CWE-306: Missing Authentication for Critical Function (Score: 491.68)\n\nThe product does not perform any authentication for functionality that requires a provable user identity or consumes a significant amount of resources....\n\n### 4. CWE-285: Improper Authorization (Score: 476.71)\n\nThe product does not perform or incorrectly performs an authorization check when an actor attempts to access a resource or perform an action....\n\n### 5. CWE-620: Unverified Password Change (Score: 461.06)\n\nWhen setting a new password for a user, the product does not require knowledge of the original password, or using another form of authentication....\n\n## COMPONENT: 'HTTP API service'\n\nRelevant CWEs for this COMPONENT:\n\n### 1. CWE-287: Improper Authentication (Score: 544.34)\n\nWhen an actor claims to have a given identity, the product does not prove or insufficiently proves that the claim is correct....\n\n### 2. CWE-697: Incorrect Comparison (Score: 503.67)\n\nThe product compares two entities in a security-relevant context, but the comparison is incorrect, which may lead to resultant weaknesses....\n\n### 3. CWE-306: Missing Authentication for Critical Function (Score: 491.68)\n\nThe product does not perform any authentication for functionality that requires a provable user identity or consumes a significant amount of resources....\n\n### 4. CWE-285: Improper Authorization (Score: 476.71)\n\nThe product does not perform or incorrectly performs an authorization check when an actor attempts to access a resource or perform an action....\n\n### 5. CWE-620: Unverified Password Change (Score: 461.06)\n\nWhen setting a new password for a user, the product does not require knowledge of the original password, or using another form of authentication....\n\n## ROOTCAUSE: 'Incorrect Authorization'\n\nRelevant CWEs for this ROOTCAUSE:\n\n### 1. CWE-697: Incorrect Comparison (Score: 503.67)\n\nThe product compares two entities in a security-relevant context, but the comparison is incorrect, which may lead to resultant weaknesses....\n\n### 2. CWE-306: Missing Authentication for Critical Function (Score: 491.68)\n\nThe product does not perform any authentication for functionality that requires a provable user identity or consumes a significant amount of resources....\n\n### 3. CWE-285: Improper Authorization (Score: 476.71)\n\nThe product does not perform or incorrectly performs an authorization check when an actor attempts to access a resource or perform an action....\n\n### 4. CWE-863: Incorrect Authorization (Score: 468.19)\n\nThe product performs an authorization check when an actor attempts to access a resource or perform an action, but it does not correctly perform the check....\n\n### 5. CWE-620: Unverified Password Change (Score: 461.06)\n\nWhen setting a new password for a user, the product does not require knowledge of the original password, or using another form of authentication....\n\n## ATTACKER: 'local attackers'\n\nRelevant CWEs for this ATTACKER:\n\n### 1. CWE-697: Incorrect Comparison (Score: 503.67)\n\nThe product compares two entities in a security-relevant context, but the comparison is incorrect, which may lead to resultant weaknesses....\n\n### 2. CWE-306: Missing Authentication for Critical Function (Score: 491.68)\n\nThe product does not perform any authentication for functionality that requires a provable user identity or consumes a significant amount of resources....\n\n### 3. CWE-285: Improper Authorization (Score: 476.71)\n\nThe product does not perform or incorrectly performs an authorization check when an actor attempts to access a resource or perform an action....\n\n### 4. CWE-620: Unverified Password Change (Score: 461.06)\n\nWhen setting a new password for a user, the product does not require knowledge of the original password, or using another form of authentication....\n\n### 5. CWE-321: Use of Hard-coded Cryptographic Key (Score: 152.46)\n\nThe use of a hard-coded cryptographic key significantly increases the possibility that encrypted data may be recovered....\n\n\n    # Analysis Instructions\n    1. For each keyphrase, identify the most appropriate CWE(s) that represent the weakness.\n    2. Consider how the different keyphrases might relate to each other in the vulnerability chain.\n    3. Provide a final determination of primary CWE(s) and any secondary CWEs.\n    4. Format your response using the standard analysis template.\n\n    Please analyze how these different weaknesses interact and provide a comprehensive CWE classification.\n    "
  },
  "retrieval_time": 1.3418827056884766
}