{
  "cve_id": "CVE-2024-47747",
  "description": "In the Linux kernel, the following vulnerability has been resolved net seeq Fix **use after free** vulnerability in ether3 Driver Due to Race Condition In the ether3_probe function, a timer is initialized with a callback function ether3_ledoff, bound to &prev(dev)->timer. Once the timer is started, there is a risk of a **race condition** if the module or device is removed, triggering the ether3_remove function to perform cleanup. The sequence of operations that may lead to a UAF bug is as follows CPU0 CPU1 | ether3_ledoff ether3_remove | free_netdev(dev) | put_devic | kfree(dev) | | ether3_outw(priv(dev)->regs.config2 |= CFG2_CTRLO, REG_CONFIG2) | // use dev Fix it by ensuring that the timer is canceled before proceeding with the cleanup in ether3_remove.",
  "key_phrases": {
    "rootcause": [
      "race condition",
      "use after free"
    ],
    "weakness": "",
    "impact": "",
    "vector": "",
    "attacker": "",
    "product": "Linux kernel",
    "version": "",
    "component": "ether3 driver"
  },
  "reference_content": "Based on the provided content, here's an analysis of the vulnerability:\n\n**CVE ID:** CVE-2024-47747 (based on the content provided)\n\n**Root cause of vulnerability:**\nThe root cause is a race condition in the `ether3` driver related to timer management. A timer is initialized in `ether3_probe` with callback `ether3_ledoff`, which is bound to `&prev(dev)->timer`. If the module or device is removed, triggering the `ether3_remove` function, a race condition can occur if the timer callback executes after the device has been freed, but before `ether3_remove` has completed its cleanup tasks, leading to a use-after-free (UAF).\n\n**Weaknesses/vulnerabilities present:**\n- **Use-after-free (UAF):** The core vulnerability is a UAF. The `ether3_ledoff` timer callback can attempt to access the `dev` structure after it has been freed by `free_netdev(dev)` during the module removal process.\n- **Race Condition:** The vulnerability is triggered by a race condition between the timer callback and the device removal process.\n\n**Impact of exploitation:**\n- **Crash/Denial of Service:** A successful exploitation would result in a kernel crash due to the UAF, causing a denial of service.\n- **Potential for arbitrary code execution:** Although not explicitly mentioned, UAF vulnerabilities can sometimes be exploited to achieve arbitrary code execution within the kernel context.\n\n**Attack vectors:**\n- **Module/Device Removal:** The attack vector involves removing the network device/module while the timer callback is pending. This can happen through system administration or by triggering an event that causes the device to be removed.\n\n**Required attacker capabilities/position:**\n- **Local Access:** The attacker would likely need local access to the system to remove the device/module.\n- **Timing:** The attacker would need to trigger the device removal such that it races with the timer callback.\n\n**Technical Details:**\n\nThe vulnerable code sequence is described as:\n\n```\nCPU0                  CPU1\n---------------------------------\nether3_ledoff\nether3_remove       |\nfree_netdev(dev);   |\nput_devic           |\nkfree(dev);         |\n                    | ether3_outw(priv(dev)->regs.config2 |= CFG2_CTRLO, REG_CONFIG2);\n                    | // use dev\n```\nThe fix involves adding `del_timer_sync(&priv(dev)->timer)` in `ether3_remove` before `free_netdev(dev)` to ensure the timer is canceled before freeing the associated data.\n```diff\n--- a/drivers/net/ethernet/seeq/ether3.c\n+++ b/drivers/net/ethernet/seeq/ether3.c\n@@ -847,9 +847,11 @@\n static void ether3_remove(struct expansion_card *ec)\n {\n        struct net_device *dev = ecard_get_drvdata(ec);\n+       ether3_outw(priv(dev)->regs.config2 |= CFG2_CTRLO, REG_CONFIG2);\n        ecard_set_drvdata(ec, NULL);\n        unregister_netdev(dev);\n+       del_timer_sync(&priv(dev)->timer);\n        free_netdev(dev);\n        ecard_release_resources(ec);\n }\n```\nThe provided diffstat shows that the fix adds 2 lines of code and removes 0.",
  "similar_info": {
    "cwe_distribution": {},
    "cwe_consensus": "",
    "similarity_stats": {
      "thresholds": [],
      "total_samples_by_threshold": {},
      "top_cwes_by_threshold": {}
    }
  },
  "similarity_summary": {
    "consensus_cwe": "",
    "top_cwes": [],
    "confidence_levels": {},
    "total_samples": 0
  },
  "analysis": "# Summary\n| CWE ID | CWE Name | Confidence | CWE Abstraction Level | CWE Vulnerability Mapping Label | CWE-Vulnerability Mapping Notes |\n|---|---|---|---|---|---|\n| CWE-362 | Concurrent Execution using Shared Resource with Improper Synchronization ('Race Condition') | 1.0 | Class | Allowed-with-Review | Primary CWE |\n| CWE-416 | Use After Free | 1.0 | Variant | Allowed | Secondary Candidate |\n\n## Evidence and Confidence\n\n*   **Confidence Score:** 1.0\n*   **Evidence Strength:** HIGH\n\n## Relationship Analysis\nThe primary weakness is a race condition (CWE-362) that leads to a use-after-free vulnerability (CWE-416). CWE-362 is a class-level CWE, while CWE-416 is a variant. The relationship is that the race condition can precede the use-after-free. I selected CWE-362 as primary because it is the root cause.\n\n```mermaid\ngraph TD\n    cwe362[\"CWE-362: Concurrent Execution using Shared Resource with Improper Synchronization ('Race Condition')\"]\n    cwe416[\"CWE-416: Use After Free\"]\n    \n    cwe362 -->|CANPRECEDE| cwe416\n    \n    classDef primary fill:#f96,stroke:#333,stroke-width:2px\n    classDef secondary fill:#69f,stroke:#333\n    class cwe362 primary\n    class cwe416 secondary\n```\n\n## Vulnerability Chain\nThe vulnerability chain starts with a **race condition** (CWE-362) in the `ether3_probe` and `ether3_remove` functions of the Linux kernel's ether3 driver. The race condition occurs when the `ether3_ledoff` timer callback function, which is bound to `&prev(dev)->timer`, attempts to use the `dev` resource after it has been freed by the `ether3_remove` function, leading to a **use after free** (CWE-416). The fix involves ensuring that the timer is canceled before proceeding with cleanup in `ether3_remove`, preventing the callback from accessing the freed resource.\n\n## Summary of Analysis\nBased on the provided information, the primary root cause is the **race condition** (CWE-362) between the timer callback and the device removal function. This leads to a **use after free** vulnerability (CWE-416). The evidence for this is strong, as the vulnerability description explicitly mentions both \"race condition\" and \"use after free.\" The suggested fix of canceling the timer before cleanup further supports this analysis.\n\nThe retriever results strongly suggest CWE-362 due to the **race condition**. Other CWEs like CWE-667 (Improper Locking), CWE-367 (Time-of-check Time-of-use), CWE-415 (Double Free), CWE-909 (Missing Initialization of Resource), and CWE-476 (NULL Pointer Dereference) were considered but deemed less relevant as they do not directly address the root cause of the race condition leading to the use-after-free.\n\nI selected CWE-362 as the primary CWE because it is the root cause of the vulnerability. The use-after-free (CWE-416) is a consequence of the race condition. The level of specificity is appropriate as CWE-362 accurately describes the concurrent execution issue, and CWE-416 accurately describes the resulting memory access issue.\n\nRelevant CWE Information:\n# Enhanced Context (25 CWEs)\nThe following CWEs were identified as potentially relevant to this vulnerability:\n\n## CWE-667: Improper Locking\n**Abstraction Level**: Class\n**Similarity Score**: 0.75\n**Source**: dense\n\n**Description**:\nThe product does not properly acquire or release a lock on a resource, leading to unexpected resource state changes and behaviors.\n\n**Mapping Guidance**:\n- Usage: Allowed-with-Review\n- Rationale: This CWE entry is a Class and might have Base-level children that would be more appropriate\n\n## CWE-366: Race Condition within a Thread\n**Abstraction Level**: Base\n**Similarity Score**: 0.74\n**Source**: dense\n\n**Description**:\nIf two threads of execution use a resource simultaneously, there exists the possibility that resources may be used while invalid, in turn making the state of execution undefined.\n\n**Mapping Guidance**:\n- Usage: Allowed\n- Rationale: This CWE entry is at the Base level of abstraction, which is a preferred level of abstraction for mapping to the root causes of vulnerabilities.\n\n## CWE-362: Concurrent Execution using Shared Resource with Improper Synchronization ('Race Condition')\n**Abstraction Level**: Class\n**Similarity Score**: 0.73\n**Source**: dense\n\n**Description**:\nThe product contains a concurrent code sequence that requires temporary, exclusive access to a shared resource, but a timing window exists in which the shared resource can be modified by another code sequence operating concurrently.\n\n**Mapping Guidance**:\n- Usage: Allowed-with-Review\n- Rationale: This CWE entry is a Class and might have Base-level children that would be more appropriate\n\n## CWE-824: Access of Uninitialized Pointer\n**Abstraction Level**: Base\n**Similarity Score**: 0.73\n**Source**: dense\n\n**Description**:\nThe product accesses or uses a pointer that has not been initialized.\n\n**Mapping Guidance**:\n- Usage: Allowed\n- Rationale: This CWE entry is at the Base level of abstraction, which is a preferred level of abstraction for mapping to the root causes of vulnerabilities.\n\n## CWE-367: Time-of-check Time-of-use (TOCTOU) Race Condition\n**Abstraction Level**: Base\n**Similarity Score**: 0.72\n**Source**: dense\n\n**Description**:\nThe product checks the state of a resource before using that resource, but the resource's state can change between the check and the use in a way that invalidates the results of the check. This can cause the product to perform invalid actions when the resource is in an unexpected state.\n\n**Mapping Guidance**:\n- Usage: Allowed\n- Rationale: This CWE entry is at the Base level of abstraction, which is a preferred level of abstraction for mapping to the root causes of vulnerabilities.\n\n## CWE-703: Improper Check or Handling of Exceptional Conditions\n**Abstraction Level**: Pillar\n**Similarity Score**: 0.72\n**Source**: dense\n\n**Description**:\nThe product does not properly anticipate or handle exceptional conditions that rarely occur during normal operation of the product.\n\n**Mapping Guidance**:\n- Usage: Discouraged\n- Rationale: This CWE entry is extremely high-level, a Pillar.\n\n## CWE-665: Improper Initialization\n**Abstraction Level**: Class\n**Similarity Score**: 0.72\n**Source**: dense\n\n**Description**:\nThe product does not initialize or incorrectly initializes a resource, which might leave the resource in an unexpected state when it is accessed or used.\n\n**Mapping Guidance**:\n- Usage: Discouraged\n- Rationale: This CWE entry is a level-1 Class (i.e., a child of a Pillar). It might have lower-level children that would be more appropriate\n\n## CWE-909: Missing Initialization of Resource\n**Abstraction Level**: Class\n**Similarity Score**: 0.71\n**Source**: dense\n\n**Description**:\nThe product does not initialize a critical resource.\n\n**Mapping Guidance**:\n- Usage: Allowed-with-Review\n- Rationale: This CWE entry is a Class and might have Base-level children that would be more appropriate\n\n## CWE-696: Incorrect Behavior Order\n**Abstraction Level**: Class\n**Similarity Score**: 0.71\n**Source**: dense\n\n**Description**:\nThe product performs multiple related behaviors, but the behaviors are performed in the wrong order in ways which may produce resultant weaknesses.\n\n**Mapping Guidance**:\n- Usage: Allowed-with-Review\n- Rationale: This CWE entry is a Class and might have Base-level children that would be more appropriate\n\n## CWE-754: Improper Check for Unusual or Exceptional Conditions\n**Abstraction Level**: Class\n**Similarity Score**: 0.71\n**Source**: dense\n\n**Description**:\nThe product does not check or incorrectly checks for unusual or exceptional conditions that are not expected to occur frequently during day to day operation of the product.\n\n**Mapping Guidance**:\n- Usage: Allowed-with-Review\n- Rationale: This CWE entry is a Class and might have Base-level children that would be more appropriate\n\n## CWE-667: Improper Locking\n**Abstraction Level**: Class\n**Similarity Score**: 2059.56\n**Source**: sparse\n\n**Description**:\nThe product does not properly acquire or release a lock on a resource, leading to unexpected resource state changes and behaviors.\n\n**Mapping Guidance**:\n- Usage: Allowed-with-Review\n- Rationale: This CWE entry is a Class and might have Base-level children that would be more appropriate\n\n## CWE-362: Concurrent Execution using Shared Resource with Improper Synchronization ('Race Condition')\n**Abstraction Level**: Class\n**Similarity Score**: 2046.07\n**Source**: sparse\n\n**Description**:\nThe product contains a concurrent code sequence that requires temporary, exclusive access to a shared resource, but a timing window exists in which the shared resource can",
  "analysis_with_relationships": "# Summary\n| CWE ID | CWE Name | Confidence | CWE Abstraction Level | CWE Vulnerability Mapping Label | CWE-Vulnerability Mapping Notes |\n|---|---|---|---|---|---|\n| CWE-362 | Concurrent Execution using Shared Resource with Improper Synchronization ('Race Condition') | 1.0 | Class | Allowed-with-Review | Primary CWE |\n| CWE-416 | Use After Free | 1.0 | Variant | Allowed | Secondary Candidate |\n\n## Evidence and Confidence\n\n*   **Confidence Score:** 1.0\n*   **Evidence Strength:** HIGH\n\n## Relationship Analysis\nThe primary weakness is a race condition (CWE-362) that leads to a use-after-free vulnerability (CWE-416). CWE-362 is a class-level CWE, while CWE-416 is a variant. The relationship is that the race condition can precede the use-after-free. I selected CWE-362 as primary because it is the root cause.\n\n```mermaid\ngraph TD\n    cwe362[\"CWE-362: Concurrent Execution using Shared Resource with Improper Synchronization ('Race Condition')\"]\n    cwe416[\"CWE-416: Use After Free\"]\n    \n    cwe362 -->|CANPRECEDE| cwe416\n    \n    classDef primary fill:#f96,stroke:#333,stroke-width:2px\n    classDef secondary fill:#69f,stroke:#333\n    class cwe362 primary\n    class cwe416 secondary\n```\n\n## Vulnerability Chain\nThe vulnerability chain starts with a **race condition** (CWE-362) in the `ether3_probe` and `ether3_remove` functions of the Linux kernel's ether3 driver. The race condition occurs when the `ether3_ledoff` timer callback function, which is bound to `&prev(dev)->timer`, attempts to use the `dev` resource after it has been freed by the `ether3_remove` function, leading to a **use after free** (CWE-416). The fix involves ensuring that the timer is canceled before proceeding with cleanup in `ether3_remove`, preventing the callback from accessing the freed resource.\n\n## Summary of Analysis\nBased on the provided information, the primary root cause is the **race condition** (CWE-362) between the timer callback and the device removal function. This leads to a **use after free** vulnerability (CWE-416). The evidence for this is strong, as the vulnerability description explicitly mentions both \"race condition\" and \"use after free.\" The suggested fix of canceling the timer before cleanup further supports this analysis.\n\nThe retriever results strongly suggest CWE-362 due to the **race condition**. Other CWEs like CWE-667 (Improper Locking), CWE-367 (Time-of-check Time-of-use), CWE-415 (Double Free), CWE-909 (Missing Initialization of Resource), and CWE-476 (NULL Pointer Dereference) were considered but deemed less relevant as they do not directly address the root cause of the race condition leading to the use-after-free.\n\nI selected CWE-362 as the primary CWE because it is the root cause of the vulnerability. The use-after-free (CWE-416) is a consequence of the race condition. The level of specificity is appropriate as CWE-362 accurately describes the concurrent execution issue, and CWE-416 accurately describes the resulting memory access issue.\n\nRelevant CWE Information:\n# Enhanced Context (25 CWEs)\nThe following CWEs were identified as potentially relevant to this vulnerability:\n\n## CWE-667: Improper Locking\n**Abstraction Level**: Class\n**Similarity Score**: 0.75\n**Source**: dense\n\n**Description**:\nThe product does not properly acquire or release a lock on a resource, leading to unexpected resource state changes and behaviors.\n\n**Mapping Guidance**:\n- Usage: Allowed-with-Review\n- Rationale: This CWE entry is a Class and might have Base-level children that would be more appropriate\n\n## CWE-366: Race Condition within a Thread\n**Abstraction Level**: Base\n**Similarity Score**: 0.74\n**Source**: dense\n\n**Description**:\nIf two threads of execution use a resource simultaneously, there exists the possibility that resources may be used while invalid, in turn making the state of execution undefined.\n\n**Mapping Guidance**:\n- Usage: Allowed\n- Rationale: This CWE entry is at the Base level of abstraction, which is a preferred level of abstraction for mapping to the root causes of vulnerabilities.\n\n## CWE-362: Concurrent Execution using Shared Resource with Improper Synchronization ('Race Condition')\n**Abstraction Level**: Class\n**Similarity Score**: 0.73\n**Source**: dense\n\n**Description**:\nThe product contains a concurrent code sequence that requires temporary, exclusive access to a shared resource, but a timing window exists in which the shared resource can be modified by another code sequence operating concurrently.\n\n**Mapping Guidance**:\n- Usage: Allowed-with-Review\n- Rationale: This CWE entry is a Class and might have Base-level children that would be more appropriate\n\n## CWE-824: Access of Uninitialized Pointer\n**Abstraction Level**: Base\n**Similarity Score**: 0.73\n**Source**: dense\n\n**Description**:\nThe product accesses or uses a pointer that has not been initialized.\n\n**Mapping Guidance**:\n- Usage: Allowed\n- Rationale: This CWE entry is at the Base level of abstraction, which is a preferred level of abstraction for mapping to the root causes of vulnerabilities.\n\n## CWE-367: Time-of-check Time-of-use (TOCTOU) Race Condition\n**Abstraction Level**: Base\n**Similarity Score**: 0.72\n**Source**: dense\n\n**Description**:\nThe product checks the state of a resource before using that resource, but the resource's state can change between the check and the use in a way that invalidates the results of the check. This can cause the product to perform invalid actions when the resource is in an unexpected state.\n\n**Mapping Guidance**:\n- Usage: Allowed\n- Rationale: This CWE entry is at the Base level of abstraction, which is a preferred level of abstraction for mapping to the root causes of vulnerabilities.\n\n## CWE-703: Improper Check or Handling of Exceptional Conditions\n**Abstraction Level**: Pillar\n**Similarity Score**: 0.72\n**Source**: dense\n\n**Description**:\nThe product does not properly anticipate or handle exceptional conditions that rarely occur during normal operation of the product.\n\n**Mapping Guidance**:\n- Usage: Discouraged\n- Rationale: This CWE entry is extremely high-level, a Pillar.\n\n## CWE-665: Improper Initialization\n**Abstraction Level**: Class\n**Similarity Score**: 0.72\n**Source**: dense\n\n**Description**:\nThe product does not initialize or incorrectly initializes a resource, which might leave the resource in an unexpected state when it is accessed or used.\n\n**Mapping Guidance**:\n- Usage: Discouraged\n- Rationale: This CWE entry is a level-1 Class (i.e., a child of a Pillar). It might have lower-level children that would be more appropriate\n\n## CWE-909: Missing Initialization of Resource\n**Abstraction Level**: Class\n**Similarity Score**: 0.71\n**Source**: dense\n\n**Description**:\nThe product does not initialize a critical resource.\n\n**Mapping Guidance**:\n- Usage: Allowed-with-Review\n- Rationale: This CWE entry is a Class and might have Base-level children that would be more appropriate\n\n## CWE-696: Incorrect Behavior Order\n**Abstraction Level**: Class\n**Similarity Score**: 0.71\n**Source**: dense\n\n**Description**:\nThe product performs multiple related behaviors, but the behaviors are performed in the wrong order in ways which may produce resultant weaknesses.\n\n**Mapping Guidance**:\n- Usage: Allowed-with-Review\n- Rationale: This CWE entry is a Class and might have Base-level children that would be more appropriate\n\n## CWE-754: Improper Check for Unusual or Exceptional Conditions\n**Abstraction Level**: Class\n**Similarity Score**: 0.71\n**Source**: dense\n\n**Description**:\nThe product does not check or incorrectly checks for unusual or exceptional conditions that are not expected to occur frequently during day to day operation of the product.\n\n**Mapping Guidance**:\n- Usage: Allowed-with-Review\n- Rationale: This CWE entry is a Class and might have Base-level children that would be more appropriate\n\n## CWE-667: Improper Locking\n**Abstraction Level**: Class\n**Similarity Score**: 2059.56\n**Source**: sparse\n\n**Description**:\nThe product does not properly acquire or release a lock on a resource, leading to unexpected resource state changes and behaviors.\n\n**Mapping Guidance**:\n- Usage: Allowed-with-Review\n- Rationale: This CWE entry is a Class and might have Base-level children that would be more appropriate\n\n## CWE-362: Concurrent Execution using Shared Resource with Improper Synchronization ('Race Condition')\n**Abstraction Level**: Class\n**Similarity Score**: 2046.07\n**Source**: sparse\n\n**Description**:\nThe product contains a concurrent code sequence that requires temporary, exclusive access to a shared resource, but a timing window exists in which the shared resource can\n\n\n## CWE Relationship Analysis\n\nCurrent CWEs represent these abstraction levels: .\n\n\n### Vulnerability Chain Analysis\n\n**Chain starting from CWE-665:**\n- 665 (Improper Initialization) - ROOT\n\n\n**Chain starting from CWE-416:**\n- 416 (Use After Free) - ROOT\n\n\n\n### CWE Relationship Diagram\n\n```mermaid\ngraph TD\n    classDef primary fill:#f96,stroke:#333,stroke-width:2px\n    classDef secondary fill:#69f,stroke:#333\n    classDef tertiary fill:#9e9,stroke:#333\n```",
  "criticism": "",
  "resolution": "",
  "relevant_cwes": [
    {
      "metadata": {
        "doc_id": "362",
        "name": "Concurrent Execution using Shared Resource with Improper Synchronization ('Race Condition')",
        "source": "sparse",
        "original_content": "The product contains a concurrent code sequence that requires temporary, exclusive access to a shared resource, but a timing window exists in which the shared resource can be modified by another code sequence operating concurrently.",
        "keyphrase_sources": [
          {
            "id": "rootcause:race condition",
            "keyphrase": "race condition",
            "type": "rootcause"
          },
          {
            "id": "rootcause:use after free",
            "keyphrase": "use after free",
            "type": "rootcause"
          },
          {
            "id": "product:Linux kernel",
            "keyphrase": "Linux kernel",
            "type": "product"
          },
          {
            "id": "component:ether3 driver",
            "keyphrase": "ether3 driver",
            "type": "component"
          }
        ]
      },
      "similarity": 694.3408943448521
    },
    {
      "metadata": {
        "doc_id": "667",
        "name": "Improper Locking",
        "source": "sparse",
        "original_content": "The product does not properly acquire or release a lock on a resource, leading to unexpected resource state changes and behaviors.",
        "keyphrase_sources": [
          {
            "id": "rootcause:race condition",
            "keyphrase": "race condition",
            "type": "rootcause"
          },
          {
            "id": "rootcause:use after free",
            "keyphrase": "use after free",
            "type": "rootcause"
          },
          {
            "id": "product:Linux kernel",
            "keyphrase": "Linux kernel",
            "type": "product"
          },
          {
            "id": "component:ether3 driver",
            "keyphrase": "ether3 driver",
            "type": "component"
          }
        ]
      },
      "similarity": 638.7984736360377
    },
    {
      "metadata": {
        "doc_id": "367",
        "name": "Time-of-check Time-of-use (TOCTOU) Race Condition",
        "source": "sparse",
        "original_content": "The product checks the state of a resource before using that resource, but the resource's state can change between the check and the use in a way that invalidates the results of the check. This can cause the product to perform invalid actions when the resource is in an unexpected state.",
        "keyphrase_sources": [
          {
            "id": "rootcause:race condition",
            "keyphrase": "race condition",
            "type": "rootcause"
          },
          {
            "id": "rootcause:use after free",
            "keyphrase": "use after free",
            "type": "rootcause"
          },
          {
            "id": "product:Linux kernel",
            "keyphrase": "Linux kernel",
            "type": "product"
          },
          {
            "id": "component:ether3 driver",
            "keyphrase": "ether3 driver",
            "type": "component"
          }
        ]
      },
      "similarity": 635.7289210121293
    },
    {
      "metadata": {
        "doc_id": "415",
        "name": "Double Free",
        "source": "sparse",
        "original_content": "The product calls free() twice on the same memory address, potentially leading to modification of unexpected memory locations.",
        "keyphrase_sources": [
          {
            "id": "rootcause:race condition",
            "keyphrase": "race condition",
            "type": "rootcause"
          },
          {
            "id": "rootcause:use after free",
            "keyphrase": "use after free",
            "type": "rootcause"
          },
          {
            "id": "product:Linux kernel",
            "keyphrase": "Linux kernel",
            "type": "product"
          },
          {
            "id": "component:ether3 driver",
            "keyphrase": "ether3 driver",
            "type": "component"
          }
        ]
      },
      "similarity": 604.607473703536
    },
    {
      "metadata": {
        "doc_id": "909",
        "name": "Missing Initialization of Resource",
        "source": "sparse",
        "original_content": "The product does not initialize a critical resource.",
        "keyphrase_sources": [
          {
            "id": "rootcause:use after free",
            "keyphrase": "use after free",
            "type": "rootcause"
          },
          {
            "id": "product:Linux kernel",
            "keyphrase": "Linux kernel",
            "type": "product"
          },
          {
            "id": "component:ether3 driver",
            "keyphrase": "ether3 driver",
            "type": "component"
          }
        ]
      },
      "similarity": 594.0376191365991
    },
    {
      "metadata": {
        "doc_id": "476",
        "name": "NULL Pointer Dereference",
        "source": "sparse",
        "original_content": "The product dereferences a pointer that it expects to be valid but is NULL.",
        "keyphrase_sources": [
          {
            "id": "rootcause:race condition",
            "keyphrase": "race condition",
            "type": "rootcause"
          }
        ]
      },
      "similarity": 592.4810494223244
    }
  ],
  "identified_cwes": {
    "analyzer": [
      "CWE-665",
      "CWE-416",
      "CWE-476",
      "CWE-754",
      "CWE-667",
      "CWE-909",
      "CWE-696",
      "CWE-362",
      "CWE-824",
      "CWE-366",
      "CWE-367",
      "CWE-415",
      "CWE-703"
    ],
    "critic_additional": []
  },
  "keyphrase_cwe_mapping": {
    "362": [
      {
        "id": "rootcause:race condition",
        "keyphrase": "race condition",
        "type": "rootcause"
      },
      {
        "id": "rootcause:use after free",
        "keyphrase": "use after free",
        "type": "rootcause"
      },
      {
        "id": "product:Linux kernel",
        "keyphrase": "Linux kernel",
        "type": "product"
      },
      {
        "id": "component:ether3 driver",
        "keyphrase": "ether3 driver",
        "type": "component"
      }
    ],
    "667": [
      {
        "id": "rootcause:race condition",
        "keyphrase": "race condition",
        "type": "rootcause"
      },
      {
        "id": "rootcause:use after free",
        "keyphrase": "use after free",
        "type": "rootcause"
      },
      {
        "id": "product:Linux kernel",
        "keyphrase": "Linux kernel",
        "type": "product"
      },
      {
        "id": "component:ether3 driver",
        "keyphrase": "ether3 driver",
        "type": "component"
      }
    ],
    "367": [
      {
        "id": "rootcause:race condition",
        "keyphrase": "race condition",
        "type": "rootcause"
      },
      {
        "id": "rootcause:use after free",
        "keyphrase": "use after free",
        "type": "rootcause"
      },
      {
        "id": "product:Linux kernel",
        "keyphrase": "Linux kernel",
        "type": "product"
      },
      {
        "id": "component:ether3 driver",
        "keyphrase": "ether3 driver",
        "type": "component"
      }
    ],
    "415": [
      {
        "id": "rootcause:race condition",
        "keyphrase": "race condition",
        "type": "rootcause"
      },
      {
        "id": "rootcause:use after free",
        "keyphrase": "use after free",
        "type": "rootcause"
      },
      {
        "id": "product:Linux kernel",
        "keyphrase": "Linux kernel",
        "type": "product"
      },
      {
        "id": "component:ether3 driver",
        "keyphrase": "ether3 driver",
        "type": "component"
      }
    ],
    "476": [
      {
        "id": "rootcause:race condition",
        "keyphrase": "race condition",
        "type": "rootcause"
      }
    ],
    "909": [
      {
        "id": "rootcause:use after free",
        "keyphrase": "use after free",
        "type": "rootcause"
      },
      {
        "id": "product:Linux kernel",
        "keyphrase": "Linux kernel",
        "type": "product"
      },
      {
        "id": "component:ether3 driver",
        "keyphrase": "ether3 driver",
        "type": "component"
      }
    ]
  }
}