{
  "vulnerability_info": "VulnerabilityInfo(cve_id='CVE-2024-21455', description='**Memory corruption** when a compat IOCTL call is followed by another IOCTL call from userspace to a driver.', key_phrases={'rootcause': '', 'weakness': ['Memory corruption', 'race condition'], 'impact': 'memory corruption', 'vector': '', 'attacker': '', 'product': '', 'version': '', 'component': ''}, reference_content=None, similar_info={'cwe_distribution': {}, 'cwe_consensus': '', 'similarity_stats': {'thresholds': [], 'total_samples_by_threshold': {}, 'top_cwes_by_threshold': {}}}, similarity_summary=SimilarityInsight(consensus_cwe='', top_cwes=[], confidence_levels={}, total_samples=0), analysis='', analysis_with_relationships='', criticism='', resolution='', relevant_cwes=[{'metadata': {'doc_id': '782', 'name': 'Exposed IOCTL with Insufficient Access Control', 'source': 'sparse', 'original_content': 'The product implements an IOCTL with functionality that should be restricted, but it does not properly enforce access control for the IOCTL.', 'keyphrase_sources': [{'id': 'weakness:Memory corruption', 'keyphrase': 'Memory corruption', 'type': 'weakness'}, {'id': 'weakness:race condition', 'keyphrase': 'race condition', 'type': 'weakness'}, {'id': 'impact:memory corruption', 'keyphrase': 'memory corruption', 'type': 'impact'}]}, 'similarity': np.float64(165.40358660714335)}, {'metadata': {'doc_id': '362', 'name': \"Concurrent Execution using Shared Resource with Improper Synchronization ('Race Condition')\", 'source': 'sparse', 'original_content': 'The product contains a concurrent code sequence that requires temporary, exclusive access to a shared resource, but a timing window exists in which the shared resource can be modified by another code sequence operating concurrently.', 'keyphrase_sources': [{'id': 'weakness:race condition', 'keyphrase': 'race condition', 'type': 'weakness'}]}, 'similarity': np.float64(156.52771146948848)}, {'metadata': {'doc_id': '667', 'name': 'Improper Locking', 'source': 'sparse', 'original_content': 'The product does not properly acquire or release a lock on a resource, leading to unexpected resource state changes and behaviors.', 'keyphrase_sources': [{'id': 'weakness:Memory corruption', 'keyphrase': 'Memory corruption', 'type': 'weakness'}, {'id': 'weakness:race condition', 'keyphrase': 'race condition', 'type': 'weakness'}, {'id': 'impact:memory corruption', 'keyphrase': 'memory corruption', 'type': 'impact'}]}, 'similarity': np.float64(155.64406200808196)}, {'metadata': {'doc_id': '787', 'name': 'Out-of-bounds Write', 'source': 'sparse', 'original_content': 'The product writes data past the end, or before the beginning, of the intended buffer.', 'keyphrase_sources': [{'id': 'weakness:Memory corruption', 'keyphrase': 'Memory corruption', 'type': 'weakness'}, {'id': 'impact:memory corruption', 'keyphrase': 'memory corruption', 'type': 'impact'}]}, 'similarity': np.float64(154.66086653982364)}, {'metadata': {'doc_id': '394', 'name': 'Unexpected Status Code or Return Value', 'source': 'sparse', 'original_content': 'The product does not properly check when a function or operation returns a value that is legitimate for the function, but is not expected by the product.', 'keyphrase_sources': [{'id': 'weakness:Memory corruption', 'keyphrase': 'Memory corruption', 'type': 'weakness'}, {'id': 'impact:memory corruption', 'keyphrase': 'memory corruption', 'type': 'impact'}]}, 'similarity': np.float64(151.88594953011827)}, {'metadata': {'doc_id': '131', 'name': 'Incorrect Calculation of Buffer Size', 'source': 'sparse', 'original_content': 'The product does not correctly calculate the size to be used when allocating a buffer, which could lead to a buffer overflow.', 'keyphrase_sources': [{'id': 'weakness:Memory corruption', 'keyphrase': 'Memory corruption', 'type': 'weakness'}, {'id': 'impact:memory corruption', 'keyphrase': 'memory corruption', 'type': 'impact'}]}, 'similarity': np.float64(146.8863724827199)}, {'metadata': {'doc_id': '367', 'name': 'Time-of-check Time-of-use (TOCTOU) Race Condition', 'source': 'sparse', 'original_content': \"The product checks the state of a resource before using that resource, but the resource's state can change between the check and the use in a way that invalidates the results of the check. This can cause the product to perform invalid actions when the resource is in an unexpected state.\", 'keyphrase_sources': [{'id': 'weakness:race condition', 'keyphrase': 'race condition', 'type': 'weakness'}]}, 'similarity': np.float64(143.29447218758898)}, {'metadata': {'doc_id': '364', 'name': 'Signal Handler Race Condition', 'source': 'sparse', 'original_content': 'The product uses a signal handler that introduces a race condition.', 'keyphrase_sources': [{'id': 'weakness:race condition', 'keyphrase': 'race condition', 'type': 'weakness'}]}, 'similarity': np.float64(137.4390077065814)}], identified_cwes={'analyzer': [], 'critic_additional': []})",
  "retrieval_results": {
    "has_multiple_keyphrases": true,
    "keyphrase_cwe_sets": {
      "weakness:Memory corruption": {
        "keyphrase": "Memory corruption",
        "type": "weakness",
        "cwes": [
          {
            "metadata": {
              "doc_id": "782",
              "name": "Exposed IOCTL with Insufficient Access Control",
              "source": "sparse",
              "original_content": "The product implements an IOCTL with functionality that should be restricted, but it does not properly enforce access control for the IOCTL.",
              "keyphrase_sources": [
                {
                  "id": "weakness:Memory corruption",
                  "keyphrase": "Memory corruption",
                  "type": "weakness"
                },
                {
                  "id": "weakness:race condition",
                  "keyphrase": "race condition",
                  "type": "weakness"
                },
                {
                  "id": "impact:memory corruption",
                  "keyphrase": "memory corruption",
                  "type": "impact"
                }
              ]
            },
            "similarity": 165.40358660714335
          },
          {
            "metadata": {
              "doc_id": "667",
              "name": "Improper Locking",
              "source": "sparse",
              "original_content": "The product does not properly acquire or release a lock on a resource, leading to unexpected resource state changes and behaviors.",
              "keyphrase_sources": [
                {
                  "id": "weakness:Memory corruption",
                  "keyphrase": "Memory corruption",
                  "type": "weakness"
                },
                {
                  "id": "weakness:race condition",
                  "keyphrase": "race condition",
                  "type": "weakness"
                },
                {
                  "id": "impact:memory corruption",
                  "keyphrase": "memory corruption",
                  "type": "impact"
                }
              ]
            },
            "similarity": 155.64406200808196
          },
          {
            "metadata": {
              "doc_id": "787",
              "name": "Out-of-bounds Write",
              "source": "sparse",
              "original_content": "The product writes data past the end, or before the beginning, of the intended buffer.",
              "keyphrase_sources": [
                {
                  "id": "weakness:Memory corruption",
                  "keyphrase": "Memory corruption",
                  "type": "weakness"
                },
                {
                  "id": "impact:memory corruption",
                  "keyphrase": "memory corruption",
                  "type": "impact"
                }
              ]
            },
            "similarity": 154.66086653982364
          },
          {
            "metadata": {
              "doc_id": "394",
              "name": "Unexpected Status Code or Return Value",
              "source": "sparse",
              "original_content": "The product does not properly check when a function or operation returns a value that is legitimate for the function, but is not expected by the product.",
              "keyphrase_sources": [
                {
                  "id": "weakness:Memory corruption",
                  "keyphrase": "Memory corruption",
                  "type": "weakness"
                },
                {
                  "id": "impact:memory corruption",
                  "keyphrase": "memory corruption",
                  "type": "impact"
                }
              ]
            },
            "similarity": 151.88594953011827
          },
          {
            "metadata": {
              "doc_id": "131",
              "name": "Incorrect Calculation of Buffer Size",
              "source": "sparse",
              "original_content": "The product does not correctly calculate the size to be used when allocating a buffer, which could lead to a buffer overflow.",
              "keyphrase_sources": [
                {
                  "id": "weakness:Memory corruption",
                  "keyphrase": "Memory corruption",
                  "type": "weakness"
                },
                {
                  "id": "impact:memory corruption",
                  "keyphrase": "memory corruption",
                  "type": "impact"
                }
              ]
            },
            "similarity": 146.8863724827199
          }
        ]
      },
      "weakness:race condition": {
        "keyphrase": "race condition",
        "type": "weakness",
        "cwes": [
          {
            "metadata": {
              "doc_id": "667",
              "name": "Improper Locking",
              "source": "sparse",
              "original_content": "The product does not properly acquire or release a lock on a resource, leading to unexpected resource state changes and behaviors."
            },
            "similarity": 162.80150987705431
          },
          {
            "metadata": {
              "doc_id": "362",
              "name": "Concurrent Execution using Shared Resource with Improper Synchronization ('Race Condition')",
              "source": "sparse",
              "original_content": "The product contains a concurrent code sequence that requires temporary, exclusive access to a shared resource, but a timing window exists in which the shared resource can be modified by another code sequence operating concurrently.",
              "keyphrase_sources": [
                {
                  "id": "weakness:race condition",
                  "keyphrase": "race condition",
                  "type": "weakness"
                }
              ]
            },
            "similarity": 156.52771146948848
          },
          {
            "metadata": {
              "doc_id": "782",
              "name": "Exposed IOCTL with Insufficient Access Control",
              "source": "sparse",
              "original_content": "The product implements an IOCTL with functionality that should be restricted, but it does not properly enforce access control for the IOCTL."
            },
            "similarity": 150.37943623055628
          },
          {
            "metadata": {
              "doc_id": "367",
              "name": "Time-of-check Time-of-use (TOCTOU) Race Condition",
              "source": "sparse",
              "original_content": "The product checks the state of a resource before using that resource, but the resource's state can change between the check and the use in a way that invalidates the results of the check. This can cause the product to perform invalid actions when the resource is in an unexpected state.",
              "keyphrase_sources": [
                {
                  "id": "weakness:race condition",
                  "keyphrase": "race condition",
                  "type": "weakness"
                }
              ]
            },
            "similarity": 143.29447218758898
          },
          {
            "metadata": {
              "doc_id": "364",
              "name": "Signal Handler Race Condition",
              "source": "sparse",
              "original_content": "The product uses a signal handler that introduces a race condition.",
              "keyphrase_sources": [
                {
                  "id": "weakness:race condition",
                  "keyphrase": "race condition",
                  "type": "weakness"
                }
              ]
            },
            "similarity": 137.4390077065814
          }
        ]
      },
      "impact:memory corruption": {
        "keyphrase": "memory corruption",
        "type": "impact",
        "cwes": [
          {
            "metadata": {
              "doc_id": "782",
              "name": "Exposed IOCTL with Insufficient Access Control",
              "source": "sparse",
              "original_content": "The product implements an IOCTL with functionality that should be restricted, but it does not properly enforce access control for the IOCTL."
            },
            "similarity": 59.0727095025512
          },
          {
            "metadata": {
              "doc_id": "667",
              "name": "Improper Locking",
              "source": "sparse",
              "original_content": "The product does not properly acquire or release a lock on a resource, leading to unexpected resource state changes and behaviors."
            },
            "similarity": 55.587165002886415
          },
          {
            "metadata": {
              "doc_id": "787",
              "name": "Out-of-bounds Write",
              "source": "sparse",
              "original_content": "The product writes data past the end, or before the beginning, of the intended buffer."
            },
            "similarity": 55.23602376422273
          },
          {
            "metadata": {
              "doc_id": "394",
              "name": "Unexpected Status Code or Return Value",
              "source": "sparse",
              "original_content": "The product does not properly check when a function or operation returns a value that is legitimate for the function, but is not expected by the product."
            },
            "similarity": 54.24498197504224
          },
          {
            "metadata": {
              "doc_id": "131",
              "name": "Incorrect Calculation of Buffer Size",
              "source": "sparse",
              "original_content": "The product does not correctly calculate the size to be used when allocating a buffer, which could lead to a buffer overflow."
            },
            "similarity": 52.45941874382854
          }
        ]
      }
    },
    "keyphrase_mapping": {
      "782": [
        {
          "id": "weakness:Memory corruption",
          "keyphrase": "Memory corruption",
          "type": "weakness"
        },
        {
          "id": "weakness:race condition",
          "keyphrase": "race condition",
          "type": "weakness"
        },
        {
          "id": "impact:memory corruption",
          "keyphrase": "memory corruption",
          "type": "impact"
        }
      ],
      "667": [
        {
          "id": "weakness:Memory corruption",
          "keyphrase": "Memory corruption",
          "type": "weakness"
        },
        {
          "id": "weakness:race condition",
          "keyphrase": "race condition",
          "type": "weakness"
        },
        {
          "id": "impact:memory corruption",
          "keyphrase": "memory corruption",
          "type": "impact"
        }
      ],
      "787": [
        {
          "id": "weakness:Memory corruption",
          "keyphrase": "Memory corruption",
          "type": "weakness"
        },
        {
          "id": "impact:memory corruption",
          "keyphrase": "memory corruption",
          "type": "impact"
        }
      ],
      "394": [
        {
          "id": "weakness:Memory corruption",
          "keyphrase": "Memory corruption",
          "type": "weakness"
        },
        {
          "id": "impact:memory corruption",
          "keyphrase": "memory corruption",
          "type": "impact"
        }
      ],
      "131": [
        {
          "id": "weakness:Memory corruption",
          "keyphrase": "Memory corruption",
          "type": "weakness"
        },
        {
          "id": "impact:memory corruption",
          "keyphrase": "memory corruption",
          "type": "impact"
        }
      ],
      "362": [
        {
          "id": "weakness:race condition",
          "keyphrase": "race condition",
          "type": "weakness"
        }
      ],
      "367": [
        {
          "id": "weakness:race condition",
          "keyphrase": "race condition",
          "type": "weakness"
        }
      ],
      "364": [
        {
          "id": "weakness:race condition",
          "keyphrase": "race condition",
          "type": "weakness"
        }
      ]
    },
    "relevant_cwes": [
      {
        "metadata": {
          "doc_id": "782",
          "name": "Exposed IOCTL with Insufficient Access Control",
          "source": "sparse",
          "original_content": "The product implements an IOCTL with functionality that should be restricted, but it does not properly enforce access control for the IOCTL.",
          "keyphrase_sources": [
            {
              "id": "weakness:Memory corruption",
              "keyphrase": "Memory corruption",
              "type": "weakness"
            },
            {
              "id": "weakness:race condition",
              "keyphrase": "race condition",
              "type": "weakness"
            },
            {
              "id": "impact:memory corruption",
              "keyphrase": "memory corruption",
              "type": "impact"
            }
          ]
        },
        "similarity": 165.40358660714335
      },
      {
        "metadata": {
          "doc_id": "362",
          "name": "Concurrent Execution using Shared Resource with Improper Synchronization ('Race Condition')",
          "source": "sparse",
          "original_content": "The product contains a concurrent code sequence that requires temporary, exclusive access to a shared resource, but a timing window exists in which the shared resource can be modified by another code sequence operating concurrently.",
          "keyphrase_sources": [
            {
              "id": "weakness:race condition",
              "keyphrase": "race condition",
              "type": "weakness"
            }
          ]
        },
        "similarity": 156.52771146948848
      },
      {
        "metadata": {
          "doc_id": "667",
          "name": "Improper Locking",
          "source": "sparse",
          "original_content": "The product does not properly acquire or release a lock on a resource, leading to unexpected resource state changes and behaviors.",
          "keyphrase_sources": [
            {
              "id": "weakness:Memory corruption",
              "keyphrase": "Memory corruption",
              "type": "weakness"
            },
            {
              "id": "weakness:race condition",
              "keyphrase": "race condition",
              "type": "weakness"
            },
            {
              "id": "impact:memory corruption",
              "keyphrase": "memory corruption",
              "type": "impact"
            }
          ]
        },
        "similarity": 155.64406200808196
      },
      {
        "metadata": {
          "doc_id": "787",
          "name": "Out-of-bounds Write",
          "source": "sparse",
          "original_content": "The product writes data past the end, or before the beginning, of the intended buffer.",
          "keyphrase_sources": [
            {
              "id": "weakness:Memory corruption",
              "keyphrase": "Memory corruption",
              "type": "weakness"
            },
            {
              "id": "impact:memory corruption",
              "keyphrase": "memory corruption",
              "type": "impact"
            }
          ]
        },
        "similarity": 154.66086653982364
      },
      {
        "metadata": {
          "doc_id": "394",
          "name": "Unexpected Status Code or Return Value",
          "source": "sparse",
          "original_content": "The product does not properly check when a function or operation returns a value that is legitimate for the function, but is not expected by the product.",
          "keyphrase_sources": [
            {
              "id": "weakness:Memory corruption",
              "keyphrase": "Memory corruption",
              "type": "weakness"
            },
            {
              "id": "impact:memory corruption",
              "keyphrase": "memory corruption",
              "type": "impact"
            }
          ]
        },
        "similarity": 151.88594953011827
      },
      {
        "metadata": {
          "doc_id": "131",
          "name": "Incorrect Calculation of Buffer Size",
          "source": "sparse",
          "original_content": "The product does not correctly calculate the size to be used when allocating a buffer, which could lead to a buffer overflow.",
          "keyphrase_sources": [
            {
              "id": "weakness:Memory corruption",
              "keyphrase": "Memory corruption",
              "type": "weakness"
            },
            {
              "id": "impact:memory corruption",
              "keyphrase": "memory corruption",
              "type": "impact"
            }
          ]
        },
        "similarity": 146.8863724827199
      },
      {
        "metadata": {
          "doc_id": "367",
          "name": "Time-of-check Time-of-use (TOCTOU) Race Condition",
          "source": "sparse",
          "original_content": "The product checks the state of a resource before using that resource, but the resource's state can change between the check and the use in a way that invalidates the results of the check. This can cause the product to perform invalid actions when the resource is in an unexpected state.",
          "keyphrase_sources": [
            {
              "id": "weakness:race condition",
              "keyphrase": "race condition",
              "type": "weakness"
            }
          ]
        },
        "similarity": 143.29447218758898
      },
      {
        "metadata": {
          "doc_id": "364",
          "name": "Signal Handler Race Condition",
          "source": "sparse",
          "original_content": "The product uses a signal handler that introduces a race condition.",
          "keyphrase_sources": [
            {
              "id": "weakness:race condition",
              "keyphrase": "race condition",
              "type": "weakness"
            }
          ]
        },
        "similarity": 137.4390077065814
      }
    ],
    "enhanced_query": "# Vulnerability Description\n\n    **Memory corruption** when a compat IOCTL call is followed by another IOCTL call from userspace to a driver.\n\n    # Keyphrase-Specific CWE Analysis\n    This vulnerability contains multiple keyphrases that may map to different CWEs. \n    Please analyze each keyphrase separately and determine the most appropriate CWE(s) for each.\n\n    ## WEAKNESS: 'Memory corruption'\n\nRelevant CWEs for this WEAKNESS:\n\n### 1. CWE-782: Exposed IOCTL with Insufficient Access Control (Score: 165.40)\n\nThe product implements an IOCTL with functionality that should be restricted, but it does not properly enforce access control for the IOCTL....\n\n### 2. CWE-667: Improper Locking (Score: 155.64)\n\nThe product does not properly acquire or release a lock on a resource, leading to unexpected resource state changes and behaviors....\n\n### 3. CWE-787: Out-of-bounds Write (Score: 154.66)\n\nThe product writes data past the end, or before the beginning, of the intended buffer....\n\n### 4. CWE-394: Unexpected Status Code or Return Value (Score: 151.89)\n\nThe product does not properly check when a function or operation returns a value that is legitimate for the function, but is not expected by the product....\n\n### 5. CWE-131: Incorrect Calculation of Buffer Size (Score: 146.89)\n\nThe product does not correctly calculate the size to be used when allocating a buffer, which could lead to a buffer overflow....\n\n## WEAKNESS: 'race condition'\n\nRelevant CWEs for this WEAKNESS:\n\n### 1. CWE-782: Exposed IOCTL with Insufficient Access Control (Score: 165.40)\n\nThe product implements an IOCTL with functionality that should be restricted, but it does not properly enforce access control for the IOCTL....\n\n### 2. CWE-362: Concurrent Execution using Shared Resource with Improper Synchronization ('Race Condition') (Score: 156.53)\n\nThe product contains a concurrent code sequence that requires temporary, exclusive access to a shared resource, but a timing window exists in which the shared resource can be modified by another code sequence operating concurrently....\n\n### 3. CWE-667: Improper Locking (Score: 155.64)\n\nThe product does not properly acquire or release a lock on a resource, leading to unexpected resource state changes and behaviors....\n\n### 4. CWE-367: Time-of-check Time-of-use (TOCTOU) Race Condition (Score: 143.29)\n\nThe product checks the state of a resource before using that resource, but the resource's state can change between the check and the use in a way that invalidates the results of the check. This can cause the product to perform invalid actions when the resource is in an unexpected state....\n\n### 5. CWE-364: Signal Handler Race Condition (Score: 137.44)\n\nThe product uses a signal handler that introduces a race condition....\n\n## IMPACT: 'memory corruption'\n\nRelevant CWEs for this IMPACT:\n\n### 1. CWE-782: Exposed IOCTL with Insufficient Access Control (Score: 165.40)\n\nThe product implements an IOCTL with functionality that should be restricted, but it does not properly enforce access control for the IOCTL....\n\n### 2. CWE-667: Improper Locking (Score: 155.64)\n\nThe product does not properly acquire or release a lock on a resource, leading to unexpected resource state changes and behaviors....\n\n### 3. CWE-787: Out-of-bounds Write (Score: 154.66)\n\nThe product writes data past the end, or before the beginning, of the intended buffer....\n\n### 4. CWE-394: Unexpected Status Code or Return Value (Score: 151.89)\n\nThe product does not properly check when a function or operation returns a value that is legitimate for the function, but is not expected by the product....\n\n### 5. CWE-131: Incorrect Calculation of Buffer Size (Score: 146.89)\n\nThe product does not correctly calculate the size to be used when allocating a buffer, which could lead to a buffer overflow....\n\n\n    # Analysis Instructions\n    1. For each keyphrase, identify the most appropriate CWE(s) that represent the weakness.\n    2. Consider how the different keyphrases might relate to each other in the vulnerability chain.\n    3. Provide a final determination of primary CWE(s) and any secondary CWEs.\n    4. Format your response using the standard analysis template.\n\n    Please analyze how these different weaknesses interact and provide a comprehensive CWE classification.\n    "
  },
  "retrieval_time": 1.192777395248413
}