{
  "vulnerability_info": "VulnerabilityInfo(cve_id='CVE-2024-51649', description='Cross-Site Request Forgery (CSRF) vulnerability in Patrick Lumumba Mobilize allows Stored **XSS**.This issue affects Mobilize from n/a through 3.0.7.', key_phrases={'rootcause': 'improper input sanitization', 'weakness': ['XSS', 'cross-site request forgery'], 'impact': 'stored cross-site scripting', 'vector': '', 'attacker': '', 'product': 'Patrick Lumumba Mobilize', 'version': 'n/a through 3.0.7', 'component': ''}, reference_content=\"Based on the provided content, here's a breakdown of the vulnerability:\\n\\n**Root Cause:** The Mobilize WordPress plugin (versions 3.0.7 and earlier) lacks sufficient Cross-Site Request Forgery (CSRF) protection.\\n\\n**Weaknesses/Vulnerabilities:**\\n*   **CSRF Vulnerability:** The plugin is susceptible to CSRF attacks.\\n\\n**Impact of Exploitation:**\\n*   A malicious actor can force higher-privileged users (e.g., administrators) to perform unwanted actions on the WordPress site while they are authenticated. This could lead to various malicious outcomes such as unauthorized modifications, data manipulation, or complete site compromise.\\n\\n**Attack Vectors:**\\n*   The attack is performed through a malicious link or webpage crafted by the attacker. If a logged-in user with sufficient privileges clicks the link or loads the page, their browser automatically sends a forged request to the vulnerable WordPress site, leading to the execution of the attacker's desired action.\\n\\n**Required Attacker Capabilities/Position:**\\n*   The attacker needs to craft a malicious request targeting a vulnerable action in the Mobilize plugin.\\n*   The attacker needs to trick a logged-in, higher-privileged user into executing the forged request. This is usually done by social engineering, such as sending malicious links or injecting malicious code into visited pages.\\n*   The attacker does not need to be authenticated to initiate the attack, they only need to target an authenticated user.\", similar_info={'cwe_distribution': {}, 'cwe_consensus': '', 'similarity_stats': {'thresholds': [], 'total_samples_by_threshold': {}, 'top_cwes_by_threshold': {}}}, similarity_summary=SimilarityInsight(consensus_cwe='', top_cwes=[], confidence_levels={}, total_samples=0), analysis='', analysis_with_relationships='', criticism='', resolution='', relevant_cwes=[{'metadata': {'doc_id': '601', 'name': \"URL Redirection to Untrusted Site ('Open Redirect')\", 'source': 'sparse', 'original_content': 'The web application accepts a user-controlled input that specifies a link to an external site, and uses that link in a redirect.', 'keyphrase_sources': [{'id': 'weakness:cross-site request forgery', 'keyphrase': 'cross-site request forgery', 'type': 'weakness'}]}, 'similarity': np.float64(209.47767485894113)}, {'metadata': {'doc_id': '352', 'name': 'Cross-Site Request Forgery (CSRF)', 'source': 'sparse', 'original_content': 'The web application does not, or can not, sufficiently verify whether a well-formed, valid, consistent request was intentionally provided by the user who submitted the request.', 'keyphrase_sources': [{'id': 'rootcause:improper input sanitization', 'keyphrase': 'improper input sanitization', 'type': 'rootcause'}, {'id': 'weakness:XSS', 'keyphrase': 'XSS', 'type': 'weakness'}, {'id': 'weakness:cross-site request forgery', 'keyphrase': 'cross-site request forgery', 'type': 'weakness'}, {'id': 'impact:stored cross-site scripting', 'keyphrase': 'stored cross-site scripting', 'type': 'impact'}, {'id': 'product:Patrick Lumumba Mobilize', 'keyphrase': 'Patrick Lumumba Mobilize', 'type': 'product'}, {'id': 'version:n/a through 3.0.7', 'keyphrase': 'n/a through 3.0.7', 'type': 'version'}]}, 'similarity': np.float64(184.04703593866327)}, {'metadata': {'doc_id': '138', 'name': 'Improper Neutralization of Special Elements', 'source': 'sparse', 'original_content': 'The product receives input from an upstream component, but it does not neutralize or incorrectly neutralizes special elements that could be interpreted as control elements or syntactic markers when they are sent to a downstream component.', 'keyphrase_sources': [{'id': 'rootcause:improper input sanitization', 'keyphrase': 'improper input sanitization', 'type': 'rootcause'}]}, 'similarity': np.float64(169.66827037044516)}, {'metadata': {'doc_id': '79', 'name': \"Improper Neutralization of Input During Web Page Generation ('Cross-site Scripting')\", 'source': 'sparse', 'original_content': 'The product does not neutralize or incorrectly neutralizes user-controllable input before it is placed in output that is used as a web page that is served to other users.', 'keyphrase_sources': [{'id': 'rootcause:improper input sanitization', 'keyphrase': 'improper input sanitization', 'type': 'rootcause'}, {'id': 'weakness:XSS', 'keyphrase': 'XSS', 'type': 'weakness'}, {'id': 'weakness:cross-site request forgery', 'keyphrase': 'cross-site request forgery', 'type': 'weakness'}, {'id': 'impact:stored cross-site scripting', 'keyphrase': 'stored cross-site scripting', 'type': 'impact'}, {'id': 'product:Patrick Lumumba Mobilize', 'keyphrase': 'Patrick Lumumba Mobilize', 'type': 'product'}, {'id': 'version:n/a through 3.0.7', 'keyphrase': 'n/a through 3.0.7', 'type': 'version'}]}, 'similarity': np.float64(169.0106182975224)}, {'metadata': {'doc_id': '116', 'name': 'Improper Encoding or Escaping of Output', 'source': 'sparse', 'original_content': 'The product prepares a structured message for communication with another component, but encoding or escaping of the data is either missing or done incorrectly. As a result, the intended structure of the message is not preserved.', 'keyphrase_sources': [{'id': 'rootcause:improper input sanitization', 'keyphrase': 'improper input sanitization', 'type': 'rootcause'}, {'id': 'weakness:XSS', 'keyphrase': 'XSS', 'type': 'weakness'}, {'id': 'impact:stored cross-site scripting', 'keyphrase': 'stored cross-site scripting', 'type': 'impact'}]}, 'similarity': np.float64(168.03016383997823)}, {'metadata': {'doc_id': '89', 'name': \"Improper Neutralization of Special Elements used in an SQL Command ('SQL Injection')\", 'source': 'sparse', 'original_content': 'The product constructs all or part of an SQL command using externally-influenced input from an upstream component, but it does not neutralize or incorrectly neutralizes special elements that could modify the intended SQL command when it is sent to a downstream component. Without sufficient removal or quoting of SQL syntax in user-controllable inputs, the generated SQL query can cause those inputs to be interpreted as SQL instead of ordinary user data.', 'keyphrase_sources': [{'id': 'rootcause:improper input sanitization', 'keyphrase': 'improper input sanitization', 'type': 'rootcause'}, {'id': 'weakness:cross-site request forgery', 'keyphrase': 'cross-site request forgery', 'type': 'weakness'}, {'id': 'product:Patrick Lumumba Mobilize', 'keyphrase': 'Patrick Lumumba Mobilize', 'type': 'product'}]}, 'similarity': np.float64(152.4881673030608)}, {'metadata': {'doc_id': '1004', 'name': \"Sensitive Cookie Without 'HttpOnly' Flag\", 'source': 'sparse', 'original_content': 'The product uses a cookie to store sensitive information, but the cookie is not marked with the HttpOnly flag.', 'keyphrase_sources': [{'id': 'weakness:XSS', 'keyphrase': 'XSS', 'type': 'weakness'}, {'id': 'impact:stored cross-site scripting', 'keyphrase': 'stored cross-site scripting', 'type': 'impact'}, {'id': 'product:Patrick Lumumba Mobilize', 'keyphrase': 'Patrick Lumumba Mobilize', 'type': 'product'}]}, 'similarity': np.float64(150.73063829399385)}, {'metadata': {'doc_id': '918', 'name': 'Server-Side Request Forgery (SSRF)', 'source': 'sparse', 'original_content': 'The web server receives a URL or similar request from an upstream component and retrieves the contents of this URL, but it does not sufficiently ensure that the request is being sent to the expected destination.', 'keyphrase_sources': [{'id': 'weakness:XSS', 'keyphrase': 'XSS', 'type': 'weakness'}, {'id': 'weakness:cross-site request forgery', 'keyphrase': 'cross-site request forgery', 'type': 'weakness'}, {'id': 'product:Patrick Lumumba Mobilize', 'keyphrase': 'Patrick Lumumba Mobilize', 'type': 'product'}]}, 'similarity': np.float64(142.10450664248572)}, {'metadata': {'doc_id': '80', 'name': 'Improper Neutralization of Script-Related HTML Tags in a Web Page (Basic XSS)', 'source': 'sparse', 'original_content': 'The product receives input from an upstream component, but it does not neutralize or incorrectly neutralizes special characters such as \"<\", \">\", and \"&\" that could be interpreted as web-scripting elements when they are sent to a downstream component that processes web pages.', 'keyphrase_sources': [{'id': 'impact:stored cross-site scripting', 'keyphrase': 'stored cross-site scripting', 'type': 'impact'}]}, 'similarity': np.float64(73.96055075256646)}, {'metadata': {'doc_id': '434', 'name': 'Unrestricted Upload of File with Dangerous Type', 'source': 'sparse', 'original_content': 'The product allows the upload or transfer of dangerous file types that are automatically processed within its environment.', 'keyphrase_sources': [{'id': 'version:n/a through 3.0.7', 'keyphrase': 'n/a through 3.0.7', 'type': 'version'}]}, 'similarity': np.float64(66.17699272220102)}, {'metadata': {'doc_id': '22', 'name': \"Improper Limitation of a Pathname to a Restricted Directory ('Path Traversal')\", 'source': 'sparse', 'original_content': 'The product uses external input to construct a pathname that is intended to identify a file or directory that is located underneath a restricted parent directory, but the product does not properly neutralize special elements within the pathname that can cause the pathname to resolve to a location that is outside of the restricted directory.', 'keyphrase_sources': [{'id': 'version:n/a through 3.0.7', 'keyphrase': 'n/a through 3.0.7', 'type': 'version'}]}, 'similarity': np.float64(64.69378629264577)}, {'metadata': {'doc_id': '611', 'name': 'Improper Restriction of XML External Entity Reference', 'source': 'sparse', 'original_content': 'The product processes an XML document that can contain XML entities with URIs that resolve to documents outside of the intended sphere of control, causing the product to embed incorrect documents into its output.', 'keyphrase_sources': [{'id': 'version:n/a through 3.0.7', 'keyphrase': 'n/a through 3.0.7', 'type': 'version'}]}, 'similarity': np.float64(63.225922087714565)}], identified_cwes={'analyzer': [], 'critic_additional': []})",
  "retrieval_results": {
    "has_multiple_keyphrases": true,
    "keyphrase_cwe_sets": {
      "rootcause:improper input sanitization": {
        "keyphrase": "improper input sanitization",
        "type": "rootcause",
        "cwes": [
          {
            "metadata": {
              "doc_id": "352",
              "name": "Cross-Site Request Forgery (CSRF)",
              "source": "sparse",
              "original_content": "The web application does not, or can not, sufficiently verify whether a well-formed, valid, consistent request was intentionally provided by the user who submitted the request.",
              "keyphrase_sources": [
                {
                  "id": "rootcause:improper input sanitization",
                  "keyphrase": "improper input sanitization",
                  "type": "rootcause"
                },
                {
                  "id": "weakness:XSS",
                  "keyphrase": "XSS",
                  "type": "weakness"
                },
                {
                  "id": "weakness:cross-site request forgery",
                  "keyphrase": "cross-site request forgery",
                  "type": "weakness"
                },
                {
                  "id": "impact:stored cross-site scripting",
                  "keyphrase": "stored cross-site scripting",
                  "type": "impact"
                },
                {
                  "id": "product:Patrick Lumumba Mobilize",
                  "keyphrase": "Patrick Lumumba Mobilize",
                  "type": "product"
                },
                {
                  "id": "version:n/a through 3.0.7",
                  "keyphrase": "n/a through 3.0.7",
                  "type": "version"
                }
              ]
            },
            "similarity": 184.04703593866327
          },
          {
            "metadata": {
              "doc_id": "138",
              "name": "Improper Neutralization of Special Elements",
              "source": "sparse",
              "original_content": "The product receives input from an upstream component, but it does not neutralize or incorrectly neutralizes special elements that could be interpreted as control elements or syntactic markers when they are sent to a downstream component.",
              "keyphrase_sources": [
                {
                  "id": "rootcause:improper input sanitization",
                  "keyphrase": "improper input sanitization",
                  "type": "rootcause"
                }
              ]
            },
            "similarity": 169.66827037044516
          },
          {
            "metadata": {
              "doc_id": "79",
              "name": "Improper Neutralization of Input During Web Page Generation ('Cross-site Scripting')",
              "source": "sparse",
              "original_content": "The product does not neutralize or incorrectly neutralizes user-controllable input before it is placed in output that is used as a web page that is served to other users.",
              "keyphrase_sources": [
                {
                  "id": "rootcause:improper input sanitization",
                  "keyphrase": "improper input sanitization",
                  "type": "rootcause"
                },
                {
                  "id": "weakness:XSS",
                  "keyphrase": "XSS",
                  "type": "weakness"
                },
                {
                  "id": "weakness:cross-site request forgery",
                  "keyphrase": "cross-site request forgery",
                  "type": "weakness"
                },
                {
                  "id": "impact:stored cross-site scripting",
                  "keyphrase": "stored cross-site scripting",
                  "type": "impact"
                },
                {
                  "id": "product:Patrick Lumumba Mobilize",
                  "keyphrase": "Patrick Lumumba Mobilize",
                  "type": "product"
                },
                {
                  "id": "version:n/a through 3.0.7",
                  "keyphrase": "n/a through 3.0.7",
                  "type": "version"
                }
              ]
            },
            "similarity": 169.0106182975224
          },
          {
            "metadata": {
              "doc_id": "116",
              "name": "Improper Encoding or Escaping of Output",
              "source": "sparse",
              "original_content": "The product prepares a structured message for communication with another component, but encoding or escaping of the data is either missing or done incorrectly. As a result, the intended structure of the message is not preserved.",
              "keyphrase_sources": [
                {
                  "id": "rootcause:improper input sanitization",
                  "keyphrase": "improper input sanitization",
                  "type": "rootcause"
                },
                {
                  "id": "weakness:XSS",
                  "keyphrase": "XSS",
                  "type": "weakness"
                },
                {
                  "id": "impact:stored cross-site scripting",
                  "keyphrase": "stored cross-site scripting",
                  "type": "impact"
                }
              ]
            },
            "similarity": 168.03016383997823
          },
          {
            "metadata": {
              "doc_id": "89",
              "name": "Improper Neutralization of Special Elements used in an SQL Command ('SQL Injection')",
              "source": "sparse",
              "original_content": "The product constructs all or part of an SQL command using externally-influenced input from an upstream component, but it does not neutralize or incorrectly neutralizes special elements that could modify the intended SQL command when it is sent to a downstream component. Without sufficient removal or quoting of SQL syntax in user-controllable inputs, the generated SQL query can cause those inputs to be interpreted as SQL instead of ordinary user data.",
              "keyphrase_sources": [
                {
                  "id": "rootcause:improper input sanitization",
                  "keyphrase": "improper input sanitization",
                  "type": "rootcause"
                },
                {
                  "id": "weakness:cross-site request forgery",
                  "keyphrase": "cross-site request forgery",
                  "type": "weakness"
                },
                {
                  "id": "product:Patrick Lumumba Mobilize",
                  "keyphrase": "Patrick Lumumba Mobilize",
                  "type": "product"
                }
              ]
            },
            "similarity": 152.4881673030608
          }
        ]
      },
      "weakness:XSS": {
        "keyphrase": "XSS",
        "type": "weakness",
        "cwes": [
          {
            "metadata": {
              "doc_id": "352",
              "name": "Cross-Site Request Forgery (CSRF)",
              "source": "sparse",
              "original_content": "The web application does not, or can not, sufficiently verify whether a well-formed, valid, consistent request was intentionally provided by the user who submitted the request."
            },
            "similarity": 184.36626260084552
          },
          {
            "metadata": {
              "doc_id": "79",
              "name": "Improper Neutralization of Input During Web Page Generation ('Cross-site Scripting')",
              "source": "sparse",
              "original_content": "The product does not neutralize or incorrectly neutralizes user-controllable input before it is placed in output that is used as a web page that is served to other users."
            },
            "similarity": 162.34932188419066
          },
          {
            "metadata": {
              "doc_id": "1004",
              "name": "Sensitive Cookie Without 'HttpOnly' Flag",
              "source": "sparse",
              "original_content": "The product uses a cookie to store sensitive information, but the cookie is not marked with the HttpOnly flag.",
              "keyphrase_sources": [
                {
                  "id": "weakness:XSS",
                  "keyphrase": "XSS",
                  "type": "weakness"
                },
                {
                  "id": "impact:stored cross-site scripting",
                  "keyphrase": "stored cross-site scripting",
                  "type": "impact"
                },
                {
                  "id": "product:Patrick Lumumba Mobilize",
                  "keyphrase": "Patrick Lumumba Mobilize",
                  "type": "product"
                }
              ]
            },
            "similarity": 150.73063829399385
          },
          {
            "metadata": {
              "doc_id": "116",
              "name": "Improper Encoding or Escaping of Output",
              "source": "sparse",
              "original_content": "The product prepares a structured message for communication with another component, but encoding or escaping of the data is either missing or done incorrectly. As a result, the intended structure of the message is not preserved."
            },
            "similarity": 142.9346144165567
          },
          {
            "metadata": {
              "doc_id": "918",
              "name": "Server-Side Request Forgery (SSRF)",
              "source": "sparse",
              "original_content": "The web server receives a URL or similar request from an upstream component and retrieves the contents of this URL, but it does not sufficiently ensure that the request is being sent to the expected destination.",
              "keyphrase_sources": [
                {
                  "id": "weakness:XSS",
                  "keyphrase": "XSS",
                  "type": "weakness"
                },
                {
                  "id": "weakness:cross-site request forgery",
                  "keyphrase": "cross-site request forgery",
                  "type": "weakness"
                },
                {
                  "id": "product:Patrick Lumumba Mobilize",
                  "keyphrase": "Patrick Lumumba Mobilize",
                  "type": "product"
                }
              ]
            },
            "similarity": 142.10450664248572
          }
        ]
      },
      "weakness:cross-site request forgery": {
        "keyphrase": "cross-site request forgery",
        "type": "weakness",
        "cwes": [
          {
            "metadata": {
              "doc_id": "352",
              "name": "Cross-Site Request Forgery (CSRF)",
              "source": "sparse",
              "original_content": "The web application does not, or can not, sufficiently verify whether a well-formed, valid, consistent request was intentionally provided by the user who submitted the request."
            },
            "similarity": 270.54601221416334
          },
          {
            "metadata": {
              "doc_id": "89",
              "name": "Improper Neutralization of Special Elements used in an SQL Command ('SQL Injection')",
              "source": "sparse",
              "original_content": "The product constructs all or part of an SQL command using externally-influenced input from an upstream component, but it does not neutralize or incorrectly neutralizes special elements that could modify the intended SQL command when it is sent to a downstream component. Without sufficient removal or quoting of SQL syntax in user-controllable inputs, the generated SQL query can cause those inputs to be interpreted as SQL instead of ordinary user data."
            },
            "similarity": 232.1588188711377
          },
          {
            "metadata": {
              "doc_id": "918",
              "name": "Server-Side Request Forgery (SSRF)",
              "source": "sparse",
              "original_content": "The web server receives a URL or similar request from an upstream component and retrieves the contents of this URL, but it does not sufficiently ensure that the request is being sent to the expected destination."
            },
            "similarity": 225.3070126483001
          },
          {
            "metadata": {
              "doc_id": "601",
              "name": "URL Redirection to Untrusted Site ('Open Redirect')",
              "source": "sparse",
              "original_content": "The web application accepts a user-controlled input that specifies a link to an external site, and uses that link in a redirect.",
              "keyphrase_sources": [
                {
                  "id": "weakness:cross-site request forgery",
                  "keyphrase": "cross-site request forgery",
                  "type": "weakness"
                }
              ]
            },
            "similarity": 209.47767485894113
          },
          {
            "metadata": {
              "doc_id": "79",
              "name": "Improper Neutralization of Input During Web Page Generation ('Cross-site Scripting')",
              "source": "sparse",
              "original_content": "The product does not neutralize or incorrectly neutralizes user-controllable input before it is placed in output that is used as a web page that is served to other users."
            },
            "similarity": 205.14970386419833
          }
        ]
      },
      "impact:stored cross-site scripting": {
        "keyphrase": "stored cross-site scripting",
        "type": "impact",
        "cwes": [
          {
            "metadata": {
              "doc_id": "352",
              "name": "Cross-Site Request Forgery (CSRF)",
              "source": "sparse",
              "original_content": "The web application does not, or can not, sufficiently verify whether a well-formed, valid, consistent request was intentionally provided by the user who submitted the request."
            },
            "similarity": 98.26233310853274
          },
          {
            "metadata": {
              "doc_id": "79",
              "name": "Improper Neutralization of Input During Web Page Generation ('Cross-site Scripting')",
              "source": "sparse",
              "original_content": "The product does not neutralize or incorrectly neutralizes user-controllable input before it is placed in output that is used as a web page that is served to other users."
            },
            "similarity": 86.12065580869056
          },
          {
            "metadata": {
              "doc_id": "116",
              "name": "Improper Encoding or Escaping of Output",
              "source": "sparse",
              "original_content": "The product prepares a structured message for communication with another component, but encoding or escaping of the data is either missing or done incorrectly. As a result, the intended structure of the message is not preserved."
            },
            "similarity": 74.56431399926223
          },
          {
            "metadata": {
              "doc_id": "80",
              "name": "Improper Neutralization of Script-Related HTML Tags in a Web Page (Basic XSS)",
              "source": "sparse",
              "original_content": "The product receives input from an upstream component, but it does not neutralize or incorrectly neutralizes special characters such as \"<\", \">\", and \"&\" that could be interpreted as web-scripting elements when they are sent to a downstream component that processes web pages.",
              "keyphrase_sources": [
                {
                  "id": "impact:stored cross-site scripting",
                  "keyphrase": "stored cross-site scripting",
                  "type": "impact"
                }
              ]
            },
            "similarity": 73.96055075256646
          },
          {
            "metadata": {
              "doc_id": "1004",
              "name": "Sensitive Cookie Without 'HttpOnly' Flag",
              "source": "sparse",
              "original_content": "The product uses a cookie to store sensitive information, but the cookie is not marked with the HttpOnly flag."
            },
            "similarity": 73.13894492920531
          }
        ]
      },
      "product:Patrick Lumumba Mobilize": {
        "keyphrase": "Patrick Lumumba Mobilize",
        "type": "product",
        "cwes": [
          {
            "metadata": {
              "doc_id": "352",
              "name": "Cross-Site Request Forgery (CSRF)",
              "source": "sparse",
              "original_content": "The web application does not, or can not, sufficiently verify whether a well-formed, valid, consistent request was intentionally provided by the user who submitted the request."
            },
            "similarity": 56.487789505196666
          },
          {
            "metadata": {
              "doc_id": "79",
              "name": "Improper Neutralization of Input During Web Page Generation ('Cross-site Scripting')",
              "source": "sparse",
              "original_content": "The product does not neutralize or incorrectly neutralizes user-controllable input before it is placed in output that is used as a web page that is served to other users."
            },
            "similarity": 47.41553228410704
          },
          {
            "metadata": {
              "doc_id": "1004",
              "name": "Sensitive Cookie Without 'HttpOnly' Flag",
              "source": "sparse",
              "original_content": "The product uses a cookie to store sensitive information, but the cookie is not marked with the HttpOnly flag."
            },
            "similarity": 44.96691140905456
          },
          {
            "metadata": {
              "doc_id": "89",
              "name": "Improper Neutralization of Special Elements used in an SQL Command ('SQL Injection')",
              "source": "sparse",
              "original_content": "The product constructs all or part of an SQL command using externally-influenced input from an upstream component, but it does not neutralize or incorrectly neutralizes special elements that could modify the intended SQL command when it is sent to a downstream component. Without sufficient removal or quoting of SQL syntax in user-controllable inputs, the generated SQL query can cause those inputs to be interpreted as SQL instead of ordinary user data."
            },
            "similarity": 44.27506934920301
          },
          {
            "metadata": {
              "doc_id": "918",
              "name": "Server-Side Request Forgery (SSRF)",
              "source": "sparse",
              "original_content": "The web server receives a URL or similar request from an upstream component and retrieves the contents of this URL, but it does not sufficiently ensure that the request is being sent to the expected destination."
            },
            "similarity": 43.49988395816527
          }
        ]
      },
      "version:n/a through 3.0.7": {
        "keyphrase": "n/a through 3.0.7",
        "type": "version",
        "cwes": [
          {
            "metadata": {
              "doc_id": "352",
              "name": "Cross-Site Request Forgery (CSRF)",
              "source": "sparse",
              "original_content": "The web application does not, or can not, sufficiently verify whether a well-formed, valid, consistent request was intentionally provided by the user who submitted the request."
            },
            "similarity": 74.70893932392866
          },
          {
            "metadata": {
              "doc_id": "434",
              "name": "Unrestricted Upload of File with Dangerous Type",
              "source": "sparse",
              "original_content": "The product allows the upload or transfer of dangerous file types that are automatically processed within its environment.",
              "keyphrase_sources": [
                {
                  "id": "version:n/a through 3.0.7",
                  "keyphrase": "n/a through 3.0.7",
                  "type": "version"
                }
              ]
            },
            "similarity": 66.17699272220102
          },
          {
            "metadata": {
              "doc_id": "79",
              "name": "Improper Neutralization of Input During Web Page Generation ('Cross-site Scripting')",
              "source": "sparse",
              "original_content": "The product does not neutralize or incorrectly neutralizes user-controllable input before it is placed in output that is used as a web page that is served to other users."
            },
            "similarity": 65.42789553170607
          },
          {
            "metadata": {
              "doc_id": "22",
              "name": "Improper Limitation of a Pathname to a Restricted Directory ('Path Traversal')",
              "source": "sparse",
              "original_content": "The product uses external input to construct a pathname that is intended to identify a file or directory that is located underneath a restricted parent directory, but the product does not properly neutralize special elements within the pathname that can cause the pathname to resolve to a location that is outside of the restricted directory.",
              "keyphrase_sources": [
                {
                  "id": "version:n/a through 3.0.7",
                  "keyphrase": "n/a through 3.0.7",
                  "type": "version"
                }
              ]
            },
            "similarity": 64.69378629264577
          },
          {
            "metadata": {
              "doc_id": "611",
              "name": "Improper Restriction of XML External Entity Reference",
              "source": "sparse",
              "original_content": "The product processes an XML document that can contain XML entities with URIs that resolve to documents outside of the intended sphere of control, causing the product to embed incorrect documents into its output.",
              "keyphrase_sources": [
                {
                  "id": "version:n/a through 3.0.7",
                  "keyphrase": "n/a through 3.0.7",
                  "type": "version"
                }
              ]
            },
            "similarity": 63.225922087714565
          }
        ]
      }
    },
    "keyphrase_mapping": {
      "352": [
        {
          "id": "rootcause:improper input sanitization",
          "keyphrase": "improper input sanitization",
          "type": "rootcause"
        },
        {
          "id": "weakness:XSS",
          "keyphrase": "XSS",
          "type": "weakness"
        },
        {
          "id": "weakness:cross-site request forgery",
          "keyphrase": "cross-site request forgery",
          "type": "weakness"
        },
        {
          "id": "impact:stored cross-site scripting",
          "keyphrase": "stored cross-site scripting",
          "type": "impact"
        },
        {
          "id": "product:Patrick Lumumba Mobilize",
          "keyphrase": "Patrick Lumumba Mobilize",
          "type": "product"
        },
        {
          "id": "version:n/a through 3.0.7",
          "keyphrase": "n/a through 3.0.7",
          "type": "version"
        }
      ],
      "138": [
        {
          "id": "rootcause:improper input sanitization",
          "keyphrase": "improper input sanitization",
          "type": "rootcause"
        }
      ],
      "79": [
        {
          "id": "rootcause:improper input sanitization",
          "keyphrase": "improper input sanitization",
          "type": "rootcause"
        },
        {
          "id": "weakness:XSS",
          "keyphrase": "XSS",
          "type": "weakness"
        },
        {
          "id": "weakness:cross-site request forgery",
          "keyphrase": "cross-site request forgery",
          "type": "weakness"
        },
        {
          "id": "impact:stored cross-site scripting",
          "keyphrase": "stored cross-site scripting",
          "type": "impact"
        },
        {
          "id": "product:Patrick Lumumba Mobilize",
          "keyphrase": "Patrick Lumumba Mobilize",
          "type": "product"
        },
        {
          "id": "version:n/a through 3.0.7",
          "keyphrase": "n/a through 3.0.7",
          "type": "version"
        }
      ],
      "116": [
        {
          "id": "rootcause:improper input sanitization",
          "keyphrase": "improper input sanitization",
          "type": "rootcause"
        },
        {
          "id": "weakness:XSS",
          "keyphrase": "XSS",
          "type": "weakness"
        },
        {
          "id": "impact:stored cross-site scripting",
          "keyphrase": "stored cross-site scripting",
          "type": "impact"
        }
      ],
      "89": [
        {
          "id": "rootcause:improper input sanitization",
          "keyphrase": "improper input sanitization",
          "type": "rootcause"
        },
        {
          "id": "weakness:cross-site request forgery",
          "keyphrase": "cross-site request forgery",
          "type": "weakness"
        },
        {
          "id": "product:Patrick Lumumba Mobilize",
          "keyphrase": "Patrick Lumumba Mobilize",
          "type": "product"
        }
      ],
      "1004": [
        {
          "id": "weakness:XSS",
          "keyphrase": "XSS",
          "type": "weakness"
        },
        {
          "id": "impact:stored cross-site scripting",
          "keyphrase": "stored cross-site scripting",
          "type": "impact"
        },
        {
          "id": "product:Patrick Lumumba Mobilize",
          "keyphrase": "Patrick Lumumba Mobilize",
          "type": "product"
        }
      ],
      "918": [
        {
          "id": "weakness:XSS",
          "keyphrase": "XSS",
          "type": "weakness"
        },
        {
          "id": "weakness:cross-site request forgery",
          "keyphrase": "cross-site request forgery",
          "type": "weakness"
        },
        {
          "id": "product:Patrick Lumumba Mobilize",
          "keyphrase": "Patrick Lumumba Mobilize",
          "type": "product"
        }
      ],
      "601": [
        {
          "id": "weakness:cross-site request forgery",
          "keyphrase": "cross-site request forgery",
          "type": "weakness"
        }
      ],
      "80": [
        {
          "id": "impact:stored cross-site scripting",
          "keyphrase": "stored cross-site scripting",
          "type": "impact"
        }
      ],
      "434": [
        {
          "id": "version:n/a through 3.0.7",
          "keyphrase": "n/a through 3.0.7",
          "type": "version"
        }
      ],
      "22": [
        {
          "id": "version:n/a through 3.0.7",
          "keyphrase": "n/a through 3.0.7",
          "type": "version"
        }
      ],
      "611": [
        {
          "id": "version:n/a through 3.0.7",
          "keyphrase": "n/a through 3.0.7",
          "type": "version"
        }
      ]
    },
    "relevant_cwes": [
      {
        "metadata": {
          "doc_id": "601",
          "name": "URL Redirection to Untrusted Site ('Open Redirect')",
          "source": "sparse",
          "original_content": "The web application accepts a user-controlled input that specifies a link to an external site, and uses that link in a redirect.",
          "keyphrase_sources": [
            {
              "id": "weakness:cross-site request forgery",
              "keyphrase": "cross-site request forgery",
              "type": "weakness"
            }
          ]
        },
        "similarity": 209.47767485894113
      },
      {
        "metadata": {
          "doc_id": "352",
          "name": "Cross-Site Request Forgery (CSRF)",
          "source": "sparse",
          "original_content": "The web application does not, or can not, sufficiently verify whether a well-formed, valid, consistent request was intentionally provided by the user who submitted the request.",
          "keyphrase_sources": [
            {
              "id": "rootcause:improper input sanitization",
              "keyphrase": "improper input sanitization",
              "type": "rootcause"
            },
            {
              "id": "weakness:XSS",
              "keyphrase": "XSS",
              "type": "weakness"
            },
            {
              "id": "weakness:cross-site request forgery",
              "keyphrase": "cross-site request forgery",
              "type": "weakness"
            },
            {
              "id": "impact:stored cross-site scripting",
              "keyphrase": "stored cross-site scripting",
              "type": "impact"
            },
            {
              "id": "product:Patrick Lumumba Mobilize",
              "keyphrase": "Patrick Lumumba Mobilize",
              "type": "product"
            },
            {
              "id": "version:n/a through 3.0.7",
              "keyphrase": "n/a through 3.0.7",
              "type": "version"
            }
          ]
        },
        "similarity": 184.04703593866327
      },
      {
        "metadata": {
          "doc_id": "138",
          "name": "Improper Neutralization of Special Elements",
          "source": "sparse",
          "original_content": "The product receives input from an upstream component, but it does not neutralize or incorrectly neutralizes special elements that could be interpreted as control elements or syntactic markers when they are sent to a downstream component.",
          "keyphrase_sources": [
            {
              "id": "rootcause:improper input sanitization",
              "keyphrase": "improper input sanitization",
              "type": "rootcause"
            }
          ]
        },
        "similarity": 169.66827037044516
      },
      {
        "metadata": {
          "doc_id": "79",
          "name": "Improper Neutralization of Input During Web Page Generation ('Cross-site Scripting')",
          "source": "sparse",
          "original_content": "The product does not neutralize or incorrectly neutralizes user-controllable input before it is placed in output that is used as a web page that is served to other users.",
          "keyphrase_sources": [
            {
              "id": "rootcause:improper input sanitization",
              "keyphrase": "improper input sanitization",
              "type": "rootcause"
            },
            {
              "id": "weakness:XSS",
              "keyphrase": "XSS",
              "type": "weakness"
            },
            {
              "id": "weakness:cross-site request forgery",
              "keyphrase": "cross-site request forgery",
              "type": "weakness"
            },
            {
              "id": "impact:stored cross-site scripting",
              "keyphrase": "stored cross-site scripting",
              "type": "impact"
            },
            {
              "id": "product:Patrick Lumumba Mobilize",
              "keyphrase": "Patrick Lumumba Mobilize",
              "type": "product"
            },
            {
              "id": "version:n/a through 3.0.7",
              "keyphrase": "n/a through 3.0.7",
              "type": "version"
            }
          ]
        },
        "similarity": 169.0106182975224
      },
      {
        "metadata": {
          "doc_id": "116",
          "name": "Improper Encoding or Escaping of Output",
          "source": "sparse",
          "original_content": "The product prepares a structured message for communication with another component, but encoding or escaping of the data is either missing or done incorrectly. As a result, the intended structure of the message is not preserved.",
          "keyphrase_sources": [
            {
              "id": "rootcause:improper input sanitization",
              "keyphrase": "improper input sanitization",
              "type": "rootcause"
            },
            {
              "id": "weakness:XSS",
              "keyphrase": "XSS",
              "type": "weakness"
            },
            {
              "id": "impact:stored cross-site scripting",
              "keyphrase": "stored cross-site scripting",
              "type": "impact"
            }
          ]
        },
        "similarity": 168.03016383997823
      },
      {
        "metadata": {
          "doc_id": "89",
          "name": "Improper Neutralization of Special Elements used in an SQL Command ('SQL Injection')",
          "source": "sparse",
          "original_content": "The product constructs all or part of an SQL command using externally-influenced input from an upstream component, but it does not neutralize or incorrectly neutralizes special elements that could modify the intended SQL command when it is sent to a downstream component. Without sufficient removal or quoting of SQL syntax in user-controllable inputs, the generated SQL query can cause those inputs to be interpreted as SQL instead of ordinary user data.",
          "keyphrase_sources": [
            {
              "id": "rootcause:improper input sanitization",
              "keyphrase": "improper input sanitization",
              "type": "rootcause"
            },
            {
              "id": "weakness:cross-site request forgery",
              "keyphrase": "cross-site request forgery",
              "type": "weakness"
            },
            {
              "id": "product:Patrick Lumumba Mobilize",
              "keyphrase": "Patrick Lumumba Mobilize",
              "type": "product"
            }
          ]
        },
        "similarity": 152.4881673030608
      },
      {
        "metadata": {
          "doc_id": "1004",
          "name": "Sensitive Cookie Without 'HttpOnly' Flag",
          "source": "sparse",
          "original_content": "The product uses a cookie to store sensitive information, but the cookie is not marked with the HttpOnly flag.",
          "keyphrase_sources": [
            {
              "id": "weakness:XSS",
              "keyphrase": "XSS",
              "type": "weakness"
            },
            {
              "id": "impact:stored cross-site scripting",
              "keyphrase": "stored cross-site scripting",
              "type": "impact"
            },
            {
              "id": "product:Patrick Lumumba Mobilize",
              "keyphrase": "Patrick Lumumba Mobilize",
              "type": "product"
            }
          ]
        },
        "similarity": 150.73063829399385
      },
      {
        "metadata": {
          "doc_id": "918",
          "name": "Server-Side Request Forgery (SSRF)",
          "source": "sparse",
          "original_content": "The web server receives a URL or similar request from an upstream component and retrieves the contents of this URL, but it does not sufficiently ensure that the request is being sent to the expected destination.",
          "keyphrase_sources": [
            {
              "id": "weakness:XSS",
              "keyphrase": "XSS",
              "type": "weakness"
            },
            {
              "id": "weakness:cross-site request forgery",
              "keyphrase": "cross-site request forgery",
              "type": "weakness"
            },
            {
              "id": "product:Patrick Lumumba Mobilize",
              "keyphrase": "Patrick Lumumba Mobilize",
              "type": "product"
            }
          ]
        },
        "similarity": 142.10450664248572
      },
      {
        "metadata": {
          "doc_id": "80",
          "name": "Improper Neutralization of Script-Related HTML Tags in a Web Page (Basic XSS)",
          "source": "sparse",
          "original_content": "The product receives input from an upstream component, but it does not neutralize or incorrectly neutralizes special characters such as \"<\", \">\", and \"&\" that could be interpreted as web-scripting elements when they are sent to a downstream component that processes web pages.",
          "keyphrase_sources": [
            {
              "id": "impact:stored cross-site scripting",
              "keyphrase": "stored cross-site scripting",
              "type": "impact"
            }
          ]
        },
        "similarity": 73.96055075256646
      },
      {
        "metadata": {
          "doc_id": "434",
          "name": "Unrestricted Upload of File with Dangerous Type",
          "source": "sparse",
          "original_content": "The product allows the upload or transfer of dangerous file types that are automatically processed within its environment.",
          "keyphrase_sources": [
            {
              "id": "version:n/a through 3.0.7",
              "keyphrase": "n/a through 3.0.7",
              "type": "version"
            }
          ]
        },
        "similarity": 66.17699272220102
      },
      {
        "metadata": {
          "doc_id": "22",
          "name": "Improper Limitation of a Pathname to a Restricted Directory ('Path Traversal')",
          "source": "sparse",
          "original_content": "The product uses external input to construct a pathname that is intended to identify a file or directory that is located underneath a restricted parent directory, but the product does not properly neutralize special elements within the pathname that can cause the pathname to resolve to a location that is outside of the restricted directory.",
          "keyphrase_sources": [
            {
              "id": "version:n/a through 3.0.7",
              "keyphrase": "n/a through 3.0.7",
              "type": "version"
            }
          ]
        },
        "similarity": 64.69378629264577
      },
      {
        "metadata": {
          "doc_id": "611",
          "name": "Improper Restriction of XML External Entity Reference",
          "source": "sparse",
          "original_content": "The product processes an XML document that can contain XML entities with URIs that resolve to documents outside of the intended sphere of control, causing the product to embed incorrect documents into its output.",
          "keyphrase_sources": [
            {
              "id": "version:n/a through 3.0.7",
              "keyphrase": "n/a through 3.0.7",
              "type": "version"
            }
          ]
        },
        "similarity": 63.225922087714565
      }
    ],
    "enhanced_query": "# Vulnerability Description\n\n    Cross-Site Request Forgery (CSRF) vulnerability in Patrick Lumumba Mobilize allows Stored **XSS**.This issue affects Mobilize from n/a through 3.0.7.\n\n    # Keyphrase-Specific CWE Analysis\n    This vulnerability contains multiple keyphrases that may map to different CWEs. \n    Please analyze each keyphrase separately and determine the most appropriate CWE(s) for each.\n\n    ## WEAKNESS: 'cross-site request forgery'\n\nRelevant CWEs for this WEAKNESS:\n\n### 1. CWE-601: URL Redirection to Untrusted Site ('Open Redirect') (Score: 209.48)\n\nThe web application accepts a user-controlled input that specifies a link to an external site, and uses that link in a redirect....\n\n### 2. CWE-352: Cross-Site Request Forgery (CSRF) (Score: 184.05)\n\nThe web application does not, or can not, sufficiently verify whether a well-formed, valid, consistent request was intentionally provided by the user who submitted the request....\n\n### 3. CWE-79: Improper Neutralization of Input During Web Page Generation ('Cross-site Scripting') (Score: 169.01)\n\nThe product does not neutralize or incorrectly neutralizes user-controllable input before it is placed in output that is used as a web page that is served to other users....\n\n### 4. CWE-89: Improper Neutralization of Special Elements used in an SQL Command ('SQL Injection') (Score: 152.49)\n\nThe product constructs all or part of an SQL command using externally-influenced input from an upstream component, but it does not neutralize or incorrectly neutralizes special elements that could modify the intended SQL command when it is sent to a downstream component. Without sufficient removal o...\n\n### 5. CWE-918: Server-Side Request Forgery (SSRF) (Score: 142.10)\n\nThe web server receives a URL or similar request from an upstream component and retrieves the contents of this URL, but it does not sufficiently ensure that the request is being sent to the expected destination....\n\n## ROOTCAUSE: 'improper input sanitization'\n\nRelevant CWEs for this ROOTCAUSE:\n\n### 1. CWE-352: Cross-Site Request Forgery (CSRF) (Score: 184.05)\n\nThe web application does not, or can not, sufficiently verify whether a well-formed, valid, consistent request was intentionally provided by the user who submitted the request....\n\n### 2. CWE-138: Improper Neutralization of Special Elements (Score: 169.67)\n\nThe product receives input from an upstream component, but it does not neutralize or incorrectly neutralizes special elements that could be interpreted as control elements or syntactic markers when they are sent to a downstream component....\n\n### 3. CWE-79: Improper Neutralization of Input During Web Page Generation ('Cross-site Scripting') (Score: 169.01)\n\nThe product does not neutralize or incorrectly neutralizes user-controllable input before it is placed in output that is used as a web page that is served to other users....\n\n### 4. CWE-116: Improper Encoding or Escaping of Output (Score: 168.03)\n\nThe product prepares a structured message for communication with another component, but encoding or escaping of the data is either missing or done incorrectly. As a result, the intended structure of the message is not preserved....\n\n### 5. CWE-89: Improper Neutralization of Special Elements used in an SQL Command ('SQL Injection') (Score: 152.49)\n\nThe product constructs all or part of an SQL command using externally-influenced input from an upstream component, but it does not neutralize or incorrectly neutralizes special elements that could modify the intended SQL command when it is sent to a downstream component. Without sufficient removal o...\n\n## WEAKNESS: 'XSS'\n\nRelevant CWEs for this WEAKNESS:\n\n### 1. CWE-352: Cross-Site Request Forgery (CSRF) (Score: 184.05)\n\nThe web application does not, or can not, sufficiently verify whether a well-formed, valid, consistent request was intentionally provided by the user who submitted the request....\n\n### 2. CWE-79: Improper Neutralization of Input During Web Page Generation ('Cross-site Scripting') (Score: 169.01)\n\nThe product does not neutralize or incorrectly neutralizes user-controllable input before it is placed in output that is used as a web page that is served to other users....\n\n### 3. CWE-116: Improper Encoding or Escaping of Output (Score: 168.03)\n\nThe product prepares a structured message for communication with another component, but encoding or escaping of the data is either missing or done incorrectly. As a result, the intended structure of the message is not preserved....\n\n### 4. CWE-1004: Sensitive Cookie Without 'HttpOnly' Flag (Score: 150.73)\n\nThe product uses a cookie to store sensitive information, but the cookie is not marked with the HttpOnly flag....\n\n### 5. CWE-918: Server-Side Request Forgery (SSRF) (Score: 142.10)\n\nThe web server receives a URL or similar request from an upstream component and retrieves the contents of this URL, but it does not sufficiently ensure that the request is being sent to the expected destination....\n\n## IMPACT: 'stored cross-site scripting'\n\nRelevant CWEs for this IMPACT:\n\n### 1. CWE-352: Cross-Site Request Forgery (CSRF) (Score: 184.05)\n\nThe web application does not, or can not, sufficiently verify whether a well-formed, valid, consistent request was intentionally provided by the user who submitted the request....\n\n### 2. CWE-79: Improper Neutralization of Input During Web Page Generation ('Cross-site Scripting') (Score: 169.01)\n\nThe product does not neutralize or incorrectly neutralizes user-controllable input before it is placed in output that is used as a web page that is served to other users....\n\n### 3. CWE-116: Improper Encoding or Escaping of Output (Score: 168.03)\n\nThe product prepares a structured message for communication with another component, but encoding or escaping of the data is either missing or done incorrectly. As a result, the intended structure of the message is not preserved....\n\n### 4. CWE-1004: Sensitive Cookie Without 'HttpOnly' Flag (Score: 150.73)\n\nThe product uses a cookie to store sensitive information, but the cookie is not marked with the HttpOnly flag....\n\n### 5. CWE-80: Improper Neutralization of Script-Related HTML Tags in a Web Page (Basic XSS) (Score: 73.96)\n\nThe product receives input from an upstream component, but it does not neutralize or incorrectly neutralizes special characters such as \"<\", \">\", and \"&\" that could be interpreted as web-scripting elements when they are sent to a downstream component that processes web pages....\n\n## PRODUCT: 'Patrick Lumumba Mobilize'\n\nRelevant CWEs for this PRODUCT:\n\n### 1. CWE-352: Cross-Site Request Forgery (CSRF) (Score: 184.05)\n\nThe web application does not, or can not, sufficiently verify whether a well-formed, valid, consistent request was intentionally provided by the user who submitted the request....\n\n### 2. CWE-79: Improper Neutralization of Input During Web Page Generation ('Cross-site Scripting') (Score: 169.01)\n\nThe product does not neutralize or incorrectly neutralizes user-controllable input before it is placed in output that is used as a web page that is served to other users....\n\n### 3. CWE-89: Improper Neutralization of Special Elements used in an SQL Command ('SQL Injection') (Score: 152.49)\n\nThe product constructs all or part of an SQL command using externally-influenced input from an upstream component, but it does not neutralize or incorrectly neutralizes special elements that could modify the intended SQL command when it is sent to a downstream component. Without sufficient removal o...\n\n### 4. CWE-1004: Sensitive Cookie Without 'HttpOnly' Flag (Score: 150.73)\n\nThe product uses a cookie to store sensitive information, but the cookie is not marked with the HttpOnly flag....\n\n### 5. CWE-918: Server-Side Request Forgery (SSRF) (Score: 142.10)\n\nThe web server receives a URL or similar request from an upstream component and retrieves the contents of this URL, but it does not sufficiently ensure that the request is being sent to the expected destination....\n\n## VERSION: 'n/a through 3.0.7'\n\nRelevant CWEs for this VERSION:\n\n### 1. CWE-352: Cross-Site Request Forgery (CSRF) (Score: 184.05)\n\nThe web application does not, or can not, sufficiently verify whether a well-formed, valid, consistent request was intentionally provided by the user who submitted the request....\n\n### 2. CWE-79: Improper Neutralization of Input During Web Page Generation ('Cross-site Scripting') (Score: 169.01)\n\nThe product does not neutralize or incorrectly neutralizes user-controllable input before it is placed in output that is used as a web page that is served to other users....\n\n### 3. CWE-434: Unrestricted Upload of File with Dangerous Type (Score: 66.18)\n\nThe product allows the upload or transfer of dangerous file types that are automatically processed within its environment....\n\n### 4. CWE-22: Improper Limitation of a Pathname to a Restricted Directory ('Path Traversal') (Score: 64.69)\n\nThe product uses external input to construct a pathname that is intended to identify a file or directory that is located underneath a restricted parent directory, but the product does not properly neutralize special elements within the pathname that can cause the pathname to resolve to a location th...\n\n### 5. CWE-611: Improper Restriction of XML External Entity Reference (Score: 63.23)\n\nThe product processes an XML document that can contain XML entities with URIs that resolve to documents outside of the intended sphere of control, causing the product to embed incorrect documents into its output....\n\n\n    # Analysis Instructions\n    1. For each keyphrase, identify the most appropriate CWE(s) that represent the weakness.\n    2. Consider how the different keyphrases might relate to each other in the vulnerability chain.\n    3. Provide a final determination of primary CWE(s) and any secondary CWEs.\n    4. Format your response using the standard analysis template.\n\n    Please analyze how these different weaknesses interact and provide a comprehensive CWE classification.\n    "
  },
  "retrieval_time": 0.993114709854126
}