{
  "cve_id": "CVE-2024-10498",
  "description": "****CWE-119** Improper Restriction of Operations within the Bounds of a Memory Buffer** vulnerability exists that could allow an unauthorized attacker to modify configuration values outside of the normal range when the attacker sends specific Modbus write packets to the device which could result in invalid data or loss of web interface functionality.",
  "key_phrases": {
    "rootcause": "CWE-119 Improper Restriction of Operations within the Bounds of a Memory Buffer",
    "weakness": "CWE-119",
    "impact": "modify configuration values outside of the normal range",
    "vector": "specific Modbus write packets",
    "attacker": "unauthorized attacker",
    "product": "",
    "version": "",
    "component": ""
  },
  "reference_content": "## Analysis of CVE-2024-10498 Content\n\nThis content is **RELEVANT** to CVE-2024-10498. Here's an extraction of the relevant information:\n\n**Root cause of vulnerability:**\n\n*   Improper Restriction of Operations within the Bounds of a Memory Buffer (CWE-119).\n\n**Weaknesses/vulnerabilities present:**\n\n*   An unauthorized attacker can modify configuration values outside of the normal range when sending specific Modbus write packets to the device. This can result in invalid data or loss of web interface functionality.\n\n**Impact of exploitation:**\n\n*   Invalid data\n*   Loss of web interface functionality\n\n**Attack vectors:**\n\n*   Sending specific Modbus write packets to the device.\n\n**Required attacker capabilities/position:**\n\n*   Unauthorized attacker\n*   Network access to the device.\n\n**Mitigation or fix:**\n\n*   **Remediation:** Upgrade to version v0.62.11 or newer of HDPM6000.\n*   **Mitigation (if patching is delayed):** Ensure the device is not accessible via the Modbus protocol outside the local network segment by applying appropriate firewall configuration and controls, and that access to the network segment is protected and controlled.\n\n**Additional Details (more than official CVE description):**\n\n*   **CVSS Scores:**\n    *   v3.1 Base Score: 6.5 (Medium) - CVSS:3.1/AV:N/AC:L/PR:N/UI:N/S:U/C:N/I:L/A:L\n    *   v4.0 Base Score: 6.9 (Medium) - CVSS:4.0/AV:N/AC:L/AT:N/PR:N/UI:N/VC:N/VI:L/VA:L/SC:N/SI:N/SA:N\n*   Affected Product: PowerLogic\u2122 HDPM6000, versions v0.62.7 and prior.\n*   The document also provides general security recommendations like network segmentation and physical access controls.\n*   Links to firmware downloads and cybersecurity resources are provided.",
  "similar_info": {
    "cwe_distribution": {},
    "cwe_consensus": "",
    "similarity_stats": {
      "thresholds": [],
      "total_samples_by_threshold": {},
      "top_cwes_by_threshold": {}
    }
  },
  "similarity_summary": {
    "consensus_cwe": "",
    "top_cwes": [],
    "confidence_levels": {},
    "total_samples": 0
  },
  "analysis": "# Summary\n| CWE ID | CWE Name | Confidence | CWE Abstraction Level | CWE Vulnerability Mapping Label | CWE-Vulnerability Mapping Notes |\n|---|---|---|---|---|---|\n| CWE-119 | Improper Restriction of Operations within the Bounds of a Memory Buffer | 1.0 | Class | Allowed | Primary CWE. Matches the description and is the root cause. |\n\n## Evidence and Confidence\n\n*   **Confidence Score:** 1.0\n*   **Evidence Strength:** HIGH\n\n## Relationship Analysis\nThe primary CWE is CWE-119, which is a Class-level CWE. While more specific CWEs exist that are children of CWE-119 such as CWE-122 (Heap-based Buffer Overflow) and CWE-787 (Out-of-bounds Write), there isn't enough information provided to determine that the buffer is heap-based or that a write occurred. Therefore, the Class level is more appropriate.\n\n```mermaid\ngraph TD\n    cwe119[\"CWE-119: Improper Restriction of Operations within the Bounds of a Memory Buffer\"]\n    \n    classDef primary fill:#f96,stroke:#333,stroke-width:2px\n    \n    class cwe119 primary\n```\n\n## Vulnerability Chain\nThe vulnerability chain starts with **CWE-119 Improper Restriction of Operations within the Bounds of a Memory Buffer**. This leads to the attacker's ability to modify configuration values outside of the normal range, resulting in invalid data or loss of web interface functionality.\n\n## Summary of Analysis\nThe analysis is based on the provided evidence, which explicitly states the **root cause** as **CWE-119 Improper Restriction of Operations within the Bounds of a Memory Buffer**. The description indicates that the vulnerability allows an attacker to modify configuration values outside of the normal range by sending specific Modbus write packets. This aligns with the definition of CWE-119, which describes operations on a memory buffer outside its intended boundary.\n\nThe retriever results also list CWE-119 as the top candidate, supporting its selection. While other CWEs such as CWE-787 (Out-of-bounds Write) and CWE-125 (Out-of-bounds Read) are related to buffer operations, there's no specific information provided that confirms a write or read operation occurred outside the bounds of the buffer. The description focuses on the **improper restriction** which allows for modification of configuration values, making CWE-119 the most accurate and specific choice based on the available information.\n\nThe selection of CWE-119 is at the optimal level of specificity, as it captures the essence of the vulnerability without over-specifying the type of buffer operation.\n\nRelevant CWE Information:\n\n# Enhanced Context (25 CWEs)\nThe following CWEs were identified as potentially relevant to this vulnerability:\n\n## CWE-119: Improper Restriction of Operations within the Bounds of a Memory Buffer\n**Abstraction Level**: Class\n**Similarity Score**: 0.77\n**Source**: dense\n\n**Description**:\nThe product performs operations on a memory buffer, but it reads from or writes to a memory location outside the buffer's intended boundary. This may result in read or write operations on unexpected memory locations that could be linked to other variables, data structures, or internal program data.\n\n**Mapping Guidance**:\n- Usage: Discouraged\n- Rationale: CWE-119 is commonly misused in low-information vulnerability reports when lower-level CWEs could be used instead, or when more details about the vulnerability are available.\n\n**Justification for not selecting other CWEs:**\n\n*   CWE-125 (Out-of-bounds Read), CWE-787 (Out-of-bounds Write): These are more specific types of buffer errors. The current description doesn't specify whether the operation is a read or a write.\n*   CWE-823 (Use of Out-of-range Pointer Offset): This could be related but there is no mention of pointers.\n*   CWE-190 (Integer Overflow or Wraparound), CWE-193 (Off-by-one Error): These are integer-related errors and there is no evidence of these.\n*   CWE-122 (Heap-based Buffer Overflow): It is more specific than CWE-119, and the provided information does not specify that the buffer is heap-based.\n*   CWE-824: (Access of Uninitialized Pointer): There's no mention of uninitialized pointers.\n*   CWE-1260: Improper Handling of Overlap Between Protected Memory Ranges: There's no information about overlaps.\n*   CWE-128: Wrap-around Error and CWE-1339: Insufficient Precision or Accuracy of a Real Number: Not relevant to the vulnerability description.\n*   CWE-755: Improper Handling of Exceptional Conditions, CWE-345: Insufficient Verification of Data Authenticity, CWE-798: Use of Hard-coded Credentials, CWE-1285: Improper Validation of Specified Index, Position, or Offset in Input, CWE-280: Improper Handling of Insufficient Permissions or Privileges , CWE-294: Authentication Bypass by Capture-replay, CWE-912: Hidden Functionality, CWE-130: Improper Handling of Length Parameter Inconsistency: These do not seem relevant based on the vulnerability description.",
  "analysis_with_relationships": "# Summary\n| CWE ID | CWE Name | Confidence | CWE Abstraction Level | CWE Vulnerability Mapping Label | CWE-Vulnerability Mapping Notes |\n|---|---|---|---|---|---|\n| CWE-119 | Improper Restriction of Operations within the Bounds of a Memory Buffer | 1.0 | Class | Allowed | Primary CWE. Matches the description and is the root cause. |\n\n## Evidence and Confidence\n\n*   **Confidence Score:** 1.0\n*   **Evidence Strength:** HIGH\n\n## Relationship Analysis\nThe primary CWE is CWE-119, which is a Class-level CWE. While more specific CWEs exist that are children of CWE-119 such as CWE-122 (Heap-based Buffer Overflow) and CWE-787 (Out-of-bounds Write), there isn't enough information provided to determine that the buffer is heap-based or that a write occurred. Therefore, the Class level is more appropriate.\n\n```mermaid\ngraph TD\n    cwe119[\"CWE-119: Improper Restriction of Operations within the Bounds of a Memory Buffer\"]\n    \n    classDef primary fill:#f96,stroke:#333,stroke-width:2px\n    \n    class cwe119 primary\n```\n\n## Vulnerability Chain\nThe vulnerability chain starts with **CWE-119 Improper Restriction of Operations within the Bounds of a Memory Buffer**. This leads to the attacker's ability to modify configuration values outside of the normal range, resulting in invalid data or loss of web interface functionality.\n\n## Summary of Analysis\nThe analysis is based on the provided evidence, which explicitly states the **root cause** as **CWE-119 Improper Restriction of Operations within the Bounds of a Memory Buffer**. The description indicates that the vulnerability allows an attacker to modify configuration values outside of the normal range by sending specific Modbus write packets. This aligns with the definition of CWE-119, which describes operations on a memory buffer outside its intended boundary.\n\nThe retriever results also list CWE-119 as the top candidate, supporting its selection. While other CWEs such as CWE-787 (Out-of-bounds Write) and CWE-125 (Out-of-bounds Read) are related to buffer operations, there's no specific information provided that confirms a write or read operation occurred outside the bounds of the buffer. The description focuses on the **improper restriction** which allows for modification of configuration values, making CWE-119 the most accurate and specific choice based on the available information.\n\nThe selection of CWE-119 is at the optimal level of specificity, as it captures the essence of the vulnerability without over-specifying the type of buffer operation.\n\nRelevant CWE Information:\n\n# Enhanced Context (25 CWEs)\nThe following CWEs were identified as potentially relevant to this vulnerability:\n\n## CWE-119: Improper Restriction of Operations within the Bounds of a Memory Buffer\n**Abstraction Level**: Class\n**Similarity Score**: 0.77\n**Source**: dense\n\n**Description**:\nThe product performs operations on a memory buffer, but it reads from or writes to a memory location outside the buffer's intended boundary. This may result in read or write operations on unexpected memory locations that could be linked to other variables, data structures, or internal program data.\n\n**Mapping Guidance**:\n- Usage: Discouraged\n- Rationale: CWE-119 is commonly misused in low-information vulnerability reports when lower-level CWEs could be used instead, or when more details about the vulnerability are available.\n\n**Justification for not selecting other CWEs:**\n\n*   CWE-125 (Out-of-bounds Read), CWE-787 (Out-of-bounds Write): These are more specific types of buffer errors. The current description doesn't specify whether the operation is a read or a write.\n*   CWE-823 (Use of Out-of-range Pointer Offset): This could be related but there is no mention of pointers.\n*   CWE-190 (Integer Overflow or Wraparound), CWE-193 (Off-by-one Error): These are integer-related errors and there is no evidence of these.\n*   CWE-122 (Heap-based Buffer Overflow): It is more specific than CWE-119, and the provided information does not specify that the buffer is heap-based.\n*   CWE-824: (Access of Uninitialized Pointer): There's no mention of uninitialized pointers.\n*   CWE-1260: Improper Handling of Overlap Between Protected Memory Ranges: There's no information about overlaps.\n*   CWE-128: Wrap-around Error and CWE-1339: Insufficient Precision or Accuracy of a Real Number: Not relevant to the vulnerability description.\n*   CWE-755: Improper Handling of Exceptional Conditions, CWE-345: Insufficient Verification of Data Authenticity, CWE-798: Use of Hard-coded Credentials, CWE-1285: Improper Validation of Specified Index, Position, or Offset in Input, CWE-280: Improper Handling of Insufficient Permissions or Privileges , CWE-294: Authentication Bypass by Capture-replay, CWE-912: Hidden Functionality, CWE-130: Improper Handling of Length Parameter Inconsistency: These do not seem relevant based on the vulnerability description.\n\n\n## CWE Relationship Analysis\n\nCurrent CWEs represent these abstraction levels: .\n\n\n### Vulnerability Chain Analysis\n\n**Chain starting from CWE-130:**\n- 130 (Improper Handling of Length Parameter Inconsistency) - ROOT\n\n\n**Chain starting from CWE-345:**\n- 345 (Insufficient Verification of Data Authenticity) - ROOT\n\n\n\n### CWE Relationship Diagram\n\n```mermaid\ngraph TD\n    classDef primary fill:#f96,stroke:#333,stroke-width:2px\n    classDef secondary fill:#69f,stroke:#333\n    classDef tertiary fill:#9e9,stroke:#333\n```",
  "criticism": "",
  "resolution": "",
  "relevant_cwes": [
    {
      "metadata": {
        "doc_id": "119",
        "name": "Improper Restriction of Operations within the Bounds of a Memory Buffer",
        "source": "sparse"
      },
      "similarity": 512.3839180835481
    },
    {
      "metadata": {
        "doc_id": "125",
        "name": "Out-of-bounds Read",
        "source": "sparse"
      },
      "similarity": 436.0192176588504
    },
    {
      "metadata": {
        "doc_id": "823",
        "name": "Use of Out-of-range Pointer Offset",
        "source": "sparse"
      },
      "similarity": 426.0547434876273
    },
    {
      "metadata": {
        "doc_id": "190",
        "name": "Integer Overflow or Wraparound",
        "source": "sparse"
      },
      "similarity": 416.67829622252987
    },
    {
      "metadata": {
        "doc_id": "824",
        "name": "Access of Uninitialized Pointer",
        "source": "sparse"
      },
      "similarity": 409.0843483916258
    },
    {
      "metadata": {
        "doc_id": "787",
        "name": "Out-of-bounds Write",
        "source": "sparse"
      },
      "similarity": 407.47082388470244
    },
    {
      "metadata": {
        "doc_id": "122",
        "name": "Heap-based Buffer Overflow",
        "source": "sparse"
      },
      "similarity": 391.2672210392451
    },
    {
      "metadata": {
        "doc_id": "193",
        "name": "Off-by-one Error",
        "source": "sparse"
      },
      "similarity": 386.6215675205988
    },
    {
      "metadata": {
        "doc_id": "1260",
        "name": "Improper Handling of Overlap Between Protected Memory Ranges",
        "type": "Base",
        "original_content": "The product allows address regions to overlap, which can result in the bypassing of intended memory protection.",
        "source": "dense",
        "mapping_notes": {
          "usage": "Allowed",
          "rationale": "This CWE entry is at the Base level of abstraction, which is a preferred level of abstraction for mapping to the root causes of vulnerabilities.",
          "comments": "Carefully read both the name and description to ensure that this mapping is an appropriate fit. Do not try to 'force' a mapping to a lower-level Base/Variant simply to comply with this preferred level of abstraction.",
          "reasons": [
            "Acceptable-Use"
          ]
        },
        "score_info": {
          "retrievers": [
            "dense",
            "graph"
          ],
          "retriever_count": 2,
          "normalized_scores": {
            "dense": 0.6964519047595912,
            "graph": 2.871698048298095
          }
        }
      },
      "similarity": 0.6964519047595912
    },
    {
      "doc_id": "128",
      "text": "CWE-128: Wrap-around Error",
      "score": 2.9120000000000004,
      "metadata": {
        "doc_id": "128",
        "name": "Wrap-around Error",
        "type": "base",
        "original_content": "CWE-128: Wrap-around Error",
        "relationships": [
          {
            "source_id": "128",
            "target_id": "190",
            "label": "PEEROF",
            "properties": {
              "view_id": "1000"
            }
          },
          {
            "source_id": "128",
            "target_id": "119",
            "label": "CANPRECEDE",
            "properties": {
              "view_id": "1000"
            }
          },
          {
            "source_id": "128",
            "target_id": "682",
            "label": "CHILDOF",
            "properties": {
              "ordinal": "Primary",
              "view_id": "1000"
            }
          },
          {
            "source_id": "682",
            "target_id": "128",
            "label": "PARENTOF",
            "properties": {
              "ordinal": "Primary",
              "view_id": "1000"
            }
          },
          {
            "source_id": "119",
            "target_id": "128",
            "label": "CANFOLLOW",
            "properties": {
              "view_id": "1000"
            }
          }
        ],
        "score_components": {
          "relationship_chain": 1.0,
          "sequence_path": 1.0,
          "peer_group": 0.9
        },
        "abstraction_factor": 1.3,
        "graph_path_info": {
          "path_types": [
            "relationship_chain",
            "vulnerability_sequence_forward",
            "vulnerability_sequence_backward",
            "peer_relationship"
          ],
          "best_paths": {
            "relationship_chain": {
              "path": [
                [
                  "119",
                  "128",
                  "CANFOLLOW"
                ]
              ],
              "score": 1.0,
              "type": "relationship_chain",
              "source": "119"
            },
            "vulnerability_sequence_forward": {
              "path": [
                [
                  "119",
                  "128",
                  "CANFOLLOW"
                ]
              ],
              "score": 0.9,
              "type": "vulnerability_sequence_forward",
              "source": "119"
            },
            "vulnerability_sequence_backward": {
              "path": [
                [
                  "128",
                  "119",
                  "CANPRECEDE"
                ]
              ],
              "score": 1.0,
              "type": "vulnerability_sequence_backward",
              "source": "119"
            },
            "peer_relationship": {
              "path": [
                [
                  "128",
                  "190",
                  "PEEROF"
                ]
              ],
              "score": 0.9,
              "type": "peer_relationship",
              "source": "190"
            }
          }
        },
        "position": "after",
        "sources": [
          "graph"
        ],
        "source": "graph",
        "mapping_notes": {
          "usage": "Allowed",
          "rationale": "This CWE entry is at the Base level of abstraction, which is a preferred level of abstraction for mapping to the root causes of vulnerabilities.",
          "comments": "Carefully read both the name and description to ensure that this mapping is an appropriate fit. Do not try to 'force' a mapping to a lower-level Base/Variant simply to comply with this preferred level of abstraction.",
          "reasons": [
            "Acceptable-Use"
          ]
        },
        "score_info": {
          "retrievers": [
            "graph"
          ],
          "retriever_count": 1,
          "normalized_scores": {
            "graph": 2.9120000000000004
          }
        }
      },
      "similarity": 2.9120000000000004
    }
  ],
  "identified_cwes": {
    "analyzer": [
      "CWE-130",
      "CWE-345",
      "CWE-125",
      "CWE-787",
      "CWE-193",
      "CWE-1339",
      "CWE-1260",
      "CWE-912",
      "CWE-128",
      "CWE-280",
      "CWE-823",
      "CWE-1285",
      "CWE-294",
      "CWE-122",
      "CWE-755",
      "CWE-798",
      "CWE-824",
      "CWE-190",
      "CWE-119"
    ],
    "critic_additional": []
  },
  "keyphrase_cwe_mapping": {}
}