{
  "cve_id": "CVE-2024-36446",
  "description": "The provisioning manager component of Mitel MiVoice MX-ONE through 7.6 SP1 could allow an authenticated attacker to conduct an authentication bypass attack due to **improper access control**. A successful exploit could allow an attacker to bypass the authorization schema.",
  "key_phrases": {
    "rootcause": "improper access control",
    "weakness": "",
    "impact": "bypass the authorization schema",
    "vector": "",
    "attacker": "authenticated attacker",
    "product": "Mitel MiVoice MX-ONE",
    "version": "through 7.6 SP1",
    "component": "provisioning manager component"
  },
  "reference_content": "- **Root cause of vulnerability**: An authentication bypass vulnerability exists in the Provisioning Manager component of Mitel MiVoice MX-ONE.\n- **Weaknesses/vulnerabilities present**: Authentication bypass.\n- **Impact of exploitation**: Successful exploitation allows a malicious actor to bypass the authorization schema.\n- **Attack vectors**: The vulnerability is located in the Provisioning Manager component of Mitel MiVoice MX-ONE. The method of exploitation is not detailed beyond that it's a bypass of the authorization schema.\n- **Required attacker capabilities/position**: The attacker must be able to interact with the vulnerable Provisioning Manager component in MiVoice MX-ONE to bypass authentication.\n\nThis content provides more specific details than the CVE description placeholder.",
  "similar_info": {
    "cwe_distribution": {},
    "cwe_consensus": "",
    "similarity_stats": {
      "thresholds": [],
      "total_samples_by_threshold": {},
      "top_cwes_by_threshold": {}
    }
  },
  "similarity_summary": {
    "consensus_cwe": "",
    "top_cwes": [],
    "confidence_levels": {},
    "total_samples": 0
  },
  "analysis": "# Summary\n| CWE ID | CWE Name | Confidence | CWE Abstraction Level | CWE Vulnerability Mapping Label | CWE-Vulnerability Mapping Notes |\n|---|---|---|---|---|---|\n| CWE-284 | Improper Access Control | 0.8 | Pillar | Primary | Allowed |\n| CWE-288 | Authentication Bypass Using an Alternate Path or Channel | 0.6 | Base | Secondary Candidate | Allowed |\n\n## Evidence and Confidence\n\n*   **Confidence Score:** 0.8\n*   **Evidence Strength:** HIGH\n\n## Relationship Analysis\nThe primary selection is CWE-284, which is a high-level category. CWE-288 is a more specific type of authentication bypass. Since the vulnerability involves **improper access control** that leads to an authentication bypass, CWE-284 is selected as the primary weakness, with CWE-288 as a secondary weakness representing the authentication bypass achieved through **improper access control**.\n\n```mermaid\ngraph TD\n    cwe284[\"CWE-284: Improper Access Control\"]\n    cwe288[\"CWE-288: Authentication Bypass Using an Alternate Path or Channel\"]\n    \n    cwe288 -->|CHILDOF| cwe284\n    \n    classDef primary fill:#f96,stroke:#333,stroke-width:2px\n    classDef secondary fill:#69f,stroke:#333\n    class cwe284 primary\n    class cwe288 secondary\n```\n\n## Vulnerability Chain\nThe vulnerability chain starts with **improper access control** (CWE-284), which leads to an authentication bypass (CWE-288), ultimately resulting in the ability to bypass the authorization schema and gain unauthorized access.\n  - **Root Cause:** CWE-284 Improper Access Control\n  - **Weakness:** CWE-288 Authentication Bypass Using an Alternate Path or Channel\n  - **Impact:** Bypass of authorization schema\n\n## Summary of Analysis\nThe initial assessment considered the retriever results, which suggested CWE-284, CWE-285, CWE-287, and CWE-306. The vulnerability description explicitly mentions \"**improper access control**\", pointing to CWE-284. The reference links content summary confirms an authentication bypass vulnerability. Based on the evidence, CWE-284 is the primary root cause, and CWE-288 describes the specific authentication bypass. The abstraction levels are appropriate, with CWE-284 as a high-level category and CWE-288 as a more specific base-level weakness.\n\nThe selection of CWE-284 and CWE-288 is primarily based on the following evidence:\n- Vulnerability Description Key Phrases: \"**improper access control**\"\n- CVE Reference Links Content Summary: \"An authentication bypass vulnerability exists...Successful exploitation allows a malicious actor to bypass the authorization schema.\"\n\nThe graph relationships influenced the selection by showing that CWE-288 is a child of CWE-284.\n\n# Enhanced Context (25 CWEs)\nThe following CWEs were identified as potentially relevant to this vulnerability:\n\n## CWE-284: Improper Access Control\n**Abstraction Level**: Pillar\n**Similarity Score**: 0.265\n**Source**: sparse\n\n**Description**:\nThe software does not restrict access to resources (data, files, actions, etc.) to only the intended privileged actors (users, processes, etc.).\n\n**Mapping Guidance**:\n- Usage: Allowed\n- Rationale: There are times when it is not possible to determine the specific type of access control problem, such as during initial triage. This is a very broad CWE that covers many types of access control problems. It should only be used when a more specific CWE is not available.\n\n**Relationships**:\n- PARENTOF -> CWE-264\n- PARENTOF -> CWE-269\n- PARENTOF -> CWE-272\n- PARENTOF -> CWE-273\n- PARENTOF -> CWE-275\n- PARENTOF -> CWE-276\n- PARENTOF -> CWE-279\n- PARENTOF -> CWE-280\n- PARENTOF -> CWE-281\n- PARENTOF -> CWE-282\n- PARENTOF -> CWE-283\n- PARENTOF -> CWE-285\n- PARENTOF -> CWE-288\n- PARENTOF -> CWE-290\n- PARENTOF -> CWE-291\n- PARENTOF -> CWE-292\n- PARENTOF -> CWE-293\n- PARENTOF -> CWE-294\n- PARENTOF -> CWE-296\n- PARENTOF -> CWE-297\n- PARENTOF -> CWE-298\n- PARENTOF -> CWE-299\n- PARENTOF -> CWE-300\n- PARENTOF -> CWE-301\n- PARENTOF -> CWE-302\n- PARENTOF -> CWE-303\n- PARENTOF -> CWE-304\n- PARENTOF -> CWE-305\n- PARENTOF -> CWE-306\n- PARENTOF -> CWE-307\n- PARENTOF -> CWE-308\n- PARENTOF -> CWE-309\n- PARENTOF -> CWE-310\n- PARENTOF -> CWE-311\n- PARENTOF -> CWE-312\n- PARENTOF -> CWE-313\n- PARENTOF -> CWE-314\n- PARENTOF -> CWE-315\n- PARENTOF -> CWE-316\n- PARENTOF -> CWE-317\n- PARENTOF -> CWE-318\n- PARENTOF -> CWE-319\n- PARENTOF -> CWE-320\n- PARENTOF -> CWE-323\n- PARENTOF -> CWE-324\n- PARENTOF -> CWE-325\n- PARENTOF -> CWE-326\n- PARENTOF -> CWE-327\n- PARENTOF -> CWE-328\n- PARENTOF -> CWE-329\n- PARENTOF -> CWE-330\n- PARENTOF -> CWE-331\n- PARENTOF -> CWE-332\n- PARENTOF -> CWE-333\n- PARENTOF -> CWE-334\n- PARENTOF -> CWE-335\n- PARENTOF -> CWE-336\n- PARENTOF -> CWE-337\n- PARENTOF -> CWE-338\n- PARENTOF -> CWE-339\n- PARENTOF -> CWE-340\n- PARENTOF -> CWE-341\n- PARENTOF -> CWE-342\n- PARENTOF -> CWE-343\n- PARENTOF -> CWE-344\n- PARENTOF -> CWE-345\n- PARENTOF -> CWE-346\n- PARENTOF -> CWE-347\n- PARENTOF -> CWE-348\n- PARENTOF -> CWE-349\n- PARENTOF -> CWE-350\n- PARENTOF -> CWE-351\n- PARENTOF -> CWE-352\n- PARENTOF -> CWE-353\n- PARENTOF -> CWE-354\n- PARENTOF -> CWE-355\n- PARENTOF -> CWE-356\n- PARENTOF -> CWE-357\n- PARENTOF -> CWE-358\n- PARENTOF -> CWE-359\n- PARENTOF -> CWE-360\n- PARENTOF -> CWE-361\n- PARENTOF -> CWE-362\n- PARENTOF -> CWE-363\n- PARENTOF -> CWE-364\n- PARENTOF -> CWE-365\n- PARENTOF -> CWE-366\n- PARENTOF -> CWE-367\n- PARENTOF -> CWE-368\n- PARENTOF -> CWE-369\n- PARENTOF -> CWE-370\n- PARENTOF -> CWE-371\n- PARENTOF -> CWE-372\n- PARENTOF -> CWE-373\n- PARENTOF -> CWE-374\n- PARENTOF -> CWE-375\n- PARENTOF -> CWE-376\n- PARENTOF -> CWE-377\n- PARENTOF -> CWE-378\n- PARENTOF -> CWE-379\n- PARENTOF -> CWE-380\n- PARENTOF -> CWE-381\n- PARENTOF -> CWE-382\n- PARENTOF -> CWE-383\n- PARENTOF -> CWE-384\n- PARENTOF -> CWE-385\n- PARENTOF -> CWE-386\n- PARENTOF -> CWE-387\n- PARENTOF -> CWE-388\n- PARENTOF -> CWE-389\n- PARENTOF -> CWE-390\n- PARENTOF -> CWE-3",
  "analysis_with_relationships": "# Summary\n| CWE ID | CWE Name | Confidence | CWE Abstraction Level | CWE Vulnerability Mapping Label | CWE-Vulnerability Mapping Notes |\n|---|---|---|---|---|---|\n| CWE-284 | Improper Access Control | 0.8 | Pillar | Primary | Allowed |\n| CWE-288 | Authentication Bypass Using an Alternate Path or Channel | 0.6 | Base | Secondary Candidate | Allowed |\n\n## Evidence and Confidence\n\n*   **Confidence Score:** 0.8\n*   **Evidence Strength:** HIGH\n\n## Relationship Analysis\nThe primary selection is CWE-284, which is a high-level category. CWE-288 is a more specific type of authentication bypass. Since the vulnerability involves **improper access control** that leads to an authentication bypass, CWE-284 is selected as the primary weakness, with CWE-288 as a secondary weakness representing the authentication bypass achieved through **improper access control**.\n\n```mermaid\ngraph TD\n    cwe284[\"CWE-284: Improper Access Control\"]\n    cwe288[\"CWE-288: Authentication Bypass Using an Alternate Path or Channel\"]\n    \n    cwe288 -->|CHILDOF| cwe284\n    \n    classDef primary fill:#f96,stroke:#333,stroke-width:2px\n    classDef secondary fill:#69f,stroke:#333\n    class cwe284 primary\n    class cwe288 secondary\n```\n\n## Vulnerability Chain\nThe vulnerability chain starts with **improper access control** (CWE-284), which leads to an authentication bypass (CWE-288), ultimately resulting in the ability to bypass the authorization schema and gain unauthorized access.\n  - **Root Cause:** CWE-284 Improper Access Control\n  - **Weakness:** CWE-288 Authentication Bypass Using an Alternate Path or Channel\n  - **Impact:** Bypass of authorization schema\n\n## Summary of Analysis\nThe initial assessment considered the retriever results, which suggested CWE-284, CWE-285, CWE-287, and CWE-306. The vulnerability description explicitly mentions \"**improper access control**\", pointing to CWE-284. The reference links content summary confirms an authentication bypass vulnerability. Based on the evidence, CWE-284 is the primary root cause, and CWE-288 describes the specific authentication bypass. The abstraction levels are appropriate, with CWE-284 as a high-level category and CWE-288 as a more specific base-level weakness.\n\nThe selection of CWE-284 and CWE-288 is primarily based on the following evidence:\n- Vulnerability Description Key Phrases: \"**improper access control**\"\n- CVE Reference Links Content Summary: \"An authentication bypass vulnerability exists...Successful exploitation allows a malicious actor to bypass the authorization schema.\"\n\nThe graph relationships influenced the selection by showing that CWE-288 is a child of CWE-284.\n\n# Enhanced Context (25 CWEs)\nThe following CWEs were identified as potentially relevant to this vulnerability:\n\n## CWE-284: Improper Access Control\n**Abstraction Level**: Pillar\n**Similarity Score**: 0.265\n**Source**: sparse\n\n**Description**:\nThe software does not restrict access to resources (data, files, actions, etc.) to only the intended privileged actors (users, processes, etc.).\n\n**Mapping Guidance**:\n- Usage: Allowed\n- Rationale: There are times when it is not possible to determine the specific type of access control problem, such as during initial triage. This is a very broad CWE that covers many types of access control problems. It should only be used when a more specific CWE is not available.\n\n**Relationships**:\n- PARENTOF -> CWE-264\n- PARENTOF -> CWE-269\n- PARENTOF -> CWE-272\n- PARENTOF -> CWE-273\n- PARENTOF -> CWE-275\n- PARENTOF -> CWE-276\n- PARENTOF -> CWE-279\n- PARENTOF -> CWE-280\n- PARENTOF -> CWE-281\n- PARENTOF -> CWE-282\n- PARENTOF -> CWE-283\n- PARENTOF -> CWE-285\n- PARENTOF -> CWE-288\n- PARENTOF -> CWE-290\n- PARENTOF -> CWE-291\n- PARENTOF -> CWE-292\n- PARENTOF -> CWE-293\n- PARENTOF -> CWE-294\n- PARENTOF -> CWE-296\n- PARENTOF -> CWE-297\n- PARENTOF -> CWE-298\n- PARENTOF -> CWE-299\n- PARENTOF -> CWE-300\n- PARENTOF -> CWE-301\n- PARENTOF -> CWE-302\n- PARENTOF -> CWE-303\n- PARENTOF -> CWE-304\n- PARENTOF -> CWE-305\n- PARENTOF -> CWE-306\n- PARENTOF -> CWE-307\n- PARENTOF -> CWE-308\n- PARENTOF -> CWE-309\n- PARENTOF -> CWE-310\n- PARENTOF -> CWE-311\n- PARENTOF -> CWE-312\n- PARENTOF -> CWE-313\n- PARENTOF -> CWE-314\n- PARENTOF -> CWE-315\n- PARENTOF -> CWE-316\n- PARENTOF -> CWE-317\n- PARENTOF -> CWE-318\n- PARENTOF -> CWE-319\n- PARENTOF -> CWE-320\n- PARENTOF -> CWE-323\n- PARENTOF -> CWE-324\n- PARENTOF -> CWE-325\n- PARENTOF -> CWE-326\n- PARENTOF -> CWE-327\n- PARENTOF -> CWE-328\n- PARENTOF -> CWE-329\n- PARENTOF -> CWE-330\n- PARENTOF -> CWE-331\n- PARENTOF -> CWE-332\n- PARENTOF -> CWE-333\n- PARENTOF -> CWE-334\n- PARENTOF -> CWE-335\n- PARENTOF -> CWE-336\n- PARENTOF -> CWE-337\n- PARENTOF -> CWE-338\n- PARENTOF -> CWE-339\n- PARENTOF -> CWE-340\n- PARENTOF -> CWE-341\n- PARENTOF -> CWE-342\n- PARENTOF -> CWE-343\n- PARENTOF -> CWE-344\n- PARENTOF -> CWE-345\n- PARENTOF -> CWE-346\n- PARENTOF -> CWE-347\n- PARENTOF -> CWE-348\n- PARENTOF -> CWE-349\n- PARENTOF -> CWE-350\n- PARENTOF -> CWE-351\n- PARENTOF -> CWE-352\n- PARENTOF -> CWE-353\n- PARENTOF -> CWE-354\n- PARENTOF -> CWE-355\n- PARENTOF -> CWE-356\n- PARENTOF -> CWE-357\n- PARENTOF -> CWE-358\n- PARENTOF -> CWE-359\n- PARENTOF -> CWE-360\n- PARENTOF -> CWE-361\n- PARENTOF -> CWE-362\n- PARENTOF -> CWE-363\n- PARENTOF -> CWE-364\n- PARENTOF -> CWE-365\n- PARENTOF -> CWE-366\n- PARENTOF -> CWE-367\n- PARENTOF -> CWE-368\n- PARENTOF -> CWE-369\n- PARENTOF -> CWE-370\n- PARENTOF -> CWE-371\n- PARENTOF -> CWE-372\n- PARENTOF -> CWE-373\n- PARENTOF -> CWE-374\n- PARENTOF -> CWE-375\n- PARENTOF -> CWE-376\n- PARENTOF -> CWE-377\n- PARENTOF -> CWE-378\n- PARENTOF -> CWE-379\n- PARENTOF -> CWE-380\n- PARENTOF -> CWE-381\n- PARENTOF -> CWE-382\n- PARENTOF -> CWE-383\n- PARENTOF -> CWE-384\n- PARENTOF -> CWE-385\n- PARENTOF -> CWE-386\n- PARENTOF -> CWE-387\n- PARENTOF -> CWE-388\n- PARENTOF -> CWE-389\n- PARENTOF -> CWE-390\n- PARENTOF -> CWE-3\n\n\n## CWE Relationship Analysis\n\nCurrent CWEs represent these abstraction levels: .\n\n\n### Vulnerability Chain Analysis\n\n**Chain starting from CWE-390:**\n- 390 (Detection of Error Condition Without Action) - ROOT\n\n\n**Chain starting from CWE-358:**\n- 358 (Improperly Implemented Security Check for Standard) - ROOT\n\n\n\n### CWE Relationship Diagram\n\n```mermaid\ngraph TD\n    classDef primary fill:#f96,stroke:#333,stroke-width:2px\n    classDef secondary fill:#69f,stroke:#333\n    classDef tertiary fill:#9e9,stroke:#333\n```",
  "criticism": "",
  "resolution": "",
  "relevant_cwes": [
    {
      "metadata": {
        "doc_id": "284",
        "name": "Improper Access Control",
        "source": "sparse"
      },
      "similarity": 264.6747412511842
    },
    {
      "metadata": {
        "doc_id": "285",
        "name": "Improper Authorization",
        "source": "sparse"
      },
      "similarity": 261.58164204452333
    },
    {
      "metadata": {
        "doc_id": "287",
        "name": "Improper Authentication",
        "source": "sparse"
      },
      "similarity": 254.13574164546804
    },
    {
      "metadata": {
        "doc_id": "306",
        "name": "Missing Authentication for Critical Function",
        "source": "sparse"
      },
      "similarity": 247.99512559821738
    },
    {
      "metadata": {
        "doc_id": "22",
        "name": "Improper Limitation of a Pathname to a Restricted Directory ('Path Traversal')",
        "source": "sparse"
      },
      "similarity": 241.15610584839212
    },
    {
      "metadata": {
        "doc_id": "863",
        "name": "Incorrect Authorization",
        "source": "sparse"
      },
      "similarity": 238.03589156507041
    },
    {
      "metadata": {
        "doc_id": "639",
        "name": "Authorization Bypass Through User-Controlled Key",
        "source": "sparse"
      },
      "similarity": 237.15186509894164
    },
    {
      "metadata": {
        "doc_id": "522",
        "name": "Insufficiently Protected Credentials",
        "source": "sparse"
      },
      "similarity": 236.70446383670406
    },
    {
      "metadata": {
        "doc_id": "288",
        "name": "Authentication Bypass Using an Alternate Path or Channel",
        "type": "Base",
        "original_content": "The product requires authentication, but the product has an alternate path or channel that does not require authentication.",
        "keyphrase_source": "rootcause:improper access control",
        "source": "dense",
        "mapping_notes": {
          "usage": "Allowed",
          "rationale": "This CWE entry is at the Base level of abstraction, which is a preferred level of abstraction for mapping to the root causes of vulnerabilities.",
          "comments": "Carefully read both the name and description to ensure that this mapping is an appropriate fit. Do not try to 'force' a mapping to a lower-level Base/Variant simply to comply with this preferred level of abstraction.",
          "reasons": [
            "Acceptable-Use"
          ]
        },
        "score_info": {
          "retrievers": [
            "dense",
            "graph"
          ],
          "retriever_count": 2,
          "normalized_scores": {
            "dense": 0.5300385100709122,
            "graph": 1.721987099039788
          }
        }
      },
      "similarity": 0.5300385100709122
    },
    {
      "doc_id": "73",
      "text": "CWE-73: External Control of File Name or Path",
      "score": 2.2100000000000004,
      "metadata": {
        "doc_id": "73",
        "name": "External Control of File Name or Path",
        "type": "base",
        "original_content": "CWE-73: External Control of File Name or Path",
        "relationships": [
          {
            "source_id": "73",
            "target_id": "114",
            "label": "PARENTOF",
            "properties": {
              "ordinal": "Primary",
              "view_id": "1000"
            }
          },
          {
            "source_id": "73",
            "target_id": "59",
            "label": "CANPRECEDE",
            "properties": {
              "view_id": "1000"
            }
          },
          {
            "source_id": "73",
            "target_id": "434",
            "label": "CANPRECEDE",
            "properties": {
              "view_id": "1000"
            }
          },
          {
            "source_id": "73",
            "target_id": "98",
            "label": "CANPRECEDE",
            "properties": {
              "view_id": "1000"
            }
          },
          {
            "source_id": "73",
            "target_id": "41",
            "label": "CANPRECEDE",
            "properties": {
              "view_id": "1000"
            }
          },
          {
            "source_id": "73",
            "target_id": "22",
            "label": "CANPRECEDE",
            "properties": {
              "view_id": "1000"
            }
          },
          {
            "source_id": "73",
            "target_id": "20",
            "label": "CHILDOF",
            "properties": {
              "ordinal": "Primary",
              "view_id": "700"
            }
          },
          {
            "source_id": "73",
            "target_id": "610",
            "label": "CHILDOF",
            "properties": {
              "view_id": "1000"
            }
          },
          {
            "source_id": "73",
            "target_id": "642",
            "label": "CHILDOF",
            "properties": {
              "ordinal": "Primary",
              "view_id": "1000"
            }
          },
          {
            "source_id": "99",
            "target_id": "73",
            "label": "CANALSOBE",
            "properties": {
              "view_id": "1000"
            }
          },
          {
            "source_id": "98",
            "target_id": "73",
            "label": "CANFOLLOW",
            "properties": {
              "view_id": "1000"
            }
          },
          {
            "source_id": "642",
            "target_id": "73",
            "label": "PARENTOF",
            "properties": {
              "ordinal": "Primary",
              "view_id": "1000"
            }
          },
          {
            "source_id": "610",
            "target_id": "73",
            "label": "PARENTOF",
            "properties": {
              "view_id": "1000"
            }
          },
          {
            "source_id": "59",
            "target_id": "73",
            "label": "CANFOLLOW",
            "properties": {
              "view_id": "1000"
            }
          },
          {
            "source_id": "434",
            "target_id": "73",
            "label": "CANFOLLOW",
            "properties": {
              "view_id": "1000"
            }
          },
          {
            "source_id": "41",
            "target_id": "73",
            "label": "CANFOLLOW",
            "properties": {
              "view_id": "1000"
            }
          },
          {
            "source_id": "22",
            "target_id": "73",
            "label": "CANFOLLOW",
            "properties": {
              "view_id": "1000"
            }
          },
          {
            "source_id": "20",
            "target_id": "73",
            "label": "PARENTOF",
            "properties": {
              "ordinal": "Primary",
              "view_id": "700"
            }
          },
          {
            "source_id": "114",
            "target_id": "73",
            "label": "CHILDOF",
            "properties": {
              "ordinal": "Primary",
              "view_id": "1000"
            }
          }
        ],
        "score_components": {
          "relationship_chain": 1.0,
          "sequence_path": 1.0
        },
        "abstraction_factor": 1.3,
        "graph_path_info": {
          "path_types": [
            "relationship_chain",
            "vulnerability_sequence_forward",
            "vulnerability_sequence_backward"
          ],
          "best_paths": {
            "relationship_chain": {
              "path": [
                [
                  "22",
                  "73",
                  "CANFOLLOW"
                ]
              ],
              "score": 1.0,
              "type": "relationship_chain",
              "source": "22"
            },
            "vulnerability_sequence_forward": {
              "path": [
                [
                  "22",
                  "73",
                  "CANFOLLOW"
                ]
              ],
              "score": 0.9,
              "type": "vulnerability_sequence_forward",
              "source": "22"
            },
            "vulnerability_sequence_backward": {
              "path": [
                [
                  "73",
                  "22",
                  "CANPRECEDE"
                ]
              ],
              "score": 1.0,
              "type": "vulnerability_sequence_backward",
              "source": "22"
            }
          }
        },
        "position": "before",
        "sources": [
          "graph"
        ],
        "source": "graph",
        "mapping_notes": {
          "usage": "Allowed",
          "rationale": "This CWE entry is at the Base level of abstraction, which is a preferred level of abstraction for mapping to the root causes of vulnerabilities.",
          "comments": "Carefully read both the name and description to ensure that this mapping is an appropriate fit. Do not try to 'force' a mapping to a lower-level Base/Variant simply to comply with this preferred level of abstraction.",
          "reasons": [
            "Acceptable-Use"
          ]
        },
        "score_info": {
          "retrievers": [
            "graph"
          ],
          "retriever_count": 1,
          "normalized_scores": {
            "graph": 2.2100000000000004
          }
        }
      },
      "similarity": 2.2100000000000004
    }
  ],
  "identified_cwes": {
    "analyzer": [
      "CWE-390",
      "CWE-3",
      "CWE-358",
      "CWE-316",
      "CWE-363",
      "CWE-314",
      "CWE-269",
      "CWE-285",
      "CWE-364",
      "CWE-365",
      "CWE-380",
      "CWE-290",
      "CWE-306",
      "CWE-326",
      "CWE-347",
      "CWE-292",
      "CWE-330",
      "CWE-361",
      "CWE-294",
      "CWE-327",
      "CWE-344",
      "CWE-310",
      "CWE-362",
      "CWE-308",
      "CWE-355",
      "CWE-382",
      "CWE-329",
      "CWE-379",
      "CWE-378",
      "CWE-320",
      "CWE-386",
      "CWE-337",
      "CWE-313",
      "CWE-276",
      "CWE-384",
      "CWE-351",
      "CWE-288",
      "CWE-280",
      "CWE-389",
      "CWE-291",
      "CWE-356",
      "CWE-273",
      "CWE-360",
      "CWE-284",
      "CWE-304",
      "CWE-359",
      "CWE-317",
      "CWE-297",
      "CWE-349",
      "CWE-323",
      "CWE-311",
      "CWE-309",
      "CWE-367",
      "CWE-264",
      "CWE-332",
      "CWE-345",
      "CWE-350",
      "CWE-301",
      "CWE-331",
      "CWE-312",
      "CWE-385",
      "CWE-328",
      "CWE-325",
      "CWE-293",
      "CWE-388",
      "CWE-346",
      "CWE-368",
      "CWE-357",
      "CWE-319",
      "CWE-318",
      "CWE-352",
      "CWE-336",
      "CWE-338",
      "CWE-369",
      "CWE-370",
      "CWE-372",
      "CWE-374",
      "CWE-334",
      "CWE-383",
      "CWE-348",
      "CWE-303",
      "CWE-366",
      "CWE-307",
      "CWE-381",
      "CWE-296",
      "CWE-339",
      "CWE-302",
      "CWE-298",
      "CWE-324",
      "CWE-315",
      "CWE-340",
      "CWE-305",
      "CWE-376",
      "CWE-377",
      "CWE-282",
      "CWE-375",
      "CWE-354",
      "CWE-333",
      "CWE-335",
      "CWE-283",
      "CWE-272",
      "CWE-373",
      "CWE-279",
      "CWE-287",
      "CWE-275",
      "CWE-371",
      "CWE-341",
      "CWE-387",
      "CWE-299",
      "CWE-353",
      "CWE-343",
      "CWE-300",
      "CWE-342",
      "CWE-281"
    ],
    "critic_additional": []
  },
  "keyphrase_cwe_mapping": {}
}