{
  "vulnerability_info": "VulnerabilityInfo(cve_id='CVE-2024-29510', description='Artifex Ghostscript before 10.03.1 allows **memory corruption**, and SAFER **sandbox bypass**, via ****format string injection**** with a uniprint device.', key_phrases={'rootcause': 'format string injection', 'weakness': ['format string injection', 'memory corruption', 'sandbox bypass'], 'impact': 'SAFER sandbox bypass', 'vector': '', 'attacker': '', 'product': 'Artifex Ghostscript', 'version': 'before 10.03.1', 'component': 'uniprint device'}, reference_content=\"Based on the provided information, here's a breakdown of the vulnerability associated with CVE-2024-29510:\\n\\n**Root Cause:**\\n\\n*   The `uniprint` device in Ghostscript allows users to specify string fragments as device options. Two specific parameters, `upWriteComponentCommands` and `upYMoveCommand`, are treated as format strings during output generation, specifically when using the Pcl output format. The format string is used with `gs_snprintf`.\\n*   There is no validation or sanitization of these format strings, allowing an attacker to inject arbitrary format specifiers.\\n\\n**Weaknesses/Vulnerabilities:**\\n\\n*   **Format String Vulnerability:** The primary vulnerability is the uncontrolled use of user-supplied strings as format specifiers in `gs_snprintf`, allowing for format string injection. The format string parsing logic is not hardened by compiler measures like `D_FORTIFY_SOURCE`, while it still supports the `%n` modifier.\\n*   Lack of input validation: The application does not validate the contents of the `upWriteComponentCommands` and `upYMoveCommand` parameters.\\n*   **Information Leakage:** Attackers can use format string specifiers like `%x` and `%s` to read arbitrary data from the stack.\\n*   **Memory Corruption:** Using the `%n` format specifier, attackers can write to memory addresses on the stack, allowing for memory corruption.\\n*  **SAFER sandbox bypass:** By corrupting a specific memory location, the `path_control_active` flag can be set to zero, bypassing the `-dSAFER` sandbox.\\n\\n**Impact of Exploitation:**\\n\\n*   **Arbitrary Code Execution:** By combining the information leak and memory corruption capabilities, an attacker can disable the `-dSAFER` sandbox and execute arbitrary shell commands.\\n*   **Information Disclosure:** The attacker can leak sensitive information from the stack, such as environment variables, pointers, and stack cookies.\\n*   **Control Flow Hijacking:** The arbitrary write primitive could be used to hijack the control flow of the application, leading to arbitrary code execution.\\n*   **Bypass of security measures:** The `-dSAFER` sandbox is designed to limit access and prevent system commands. This vulnerability allows bypassing this mechanism.\\n\\n**Attack Vectors:**\\n\\n*   **Specially crafted PostScript files:** An attacker can create a specially crafted PostScript file that uses `setpagedevice` to configure the `uniprint` device and set the vulnerable format string parameters.\\n*   **File Upload:** This exploit can be used when a user uploads a document, like an EPS file, to a web service which uses Ghostscript (directly or indirectly) for file conversion or preview.\\n*   **Embedded files:** The exploit can also be embedded in files like LibreOffice documents which internally use Ghostscript for rendering (e.g. embedded EPS).\\n\\n**Required Attacker Capabilities/Position:**\\n\\n*   **Ability to supply a Postscript file to Ghostscript:** The attacker needs to be able to provide a malicious PostScript file as input to a vulnerable Ghostscript process.\\n*   **Ability to read the output:** The attacker needs read access to the device output (e.g. by setting it to a temporary file path).\\n*   **Understanding of format string vulnerabilities:** The attacker needs knowledge of how format string vulnerabilities can be exploited.\\n\\n**Additional Notes:**\\n\\n* The vulnerability is present in Ghostscript versions <= 10.03.0 (but >= 9.50).\\n* The vulnerability was fixed in Ghostscript version 10.03.1.\\n* The fix involves preventing PostScript code from altering the `upWriteComponentCommands` and `upYMoveCommand` parameters when `-dSAFER` is enabled. These parameters can only be set from the command line when `-dSAFER` is active.\\n* The vulnerability is exploitable because the parameters `upWriteComponentCommands` and `upYMoveCommand` can be set via the `setpagedevice` operator, which is available in the SAFER sandbox, and there is no mechanism to prevent the user from supplying format string specifiers.\\n* The `gs_snprintf` function used for string formatting does not implement protections against format string vulnerabilities (such as `FORTIFY_SOURCE`).\\n* The vulnerability can be used to bypass the `-dSAFER` sandbox via a memory corruption exploit, ultimately leading to arbitrary command execution.\", similar_info={'cwe_distribution': {}, 'cwe_consensus': '', 'similarity_stats': {'thresholds': [], 'total_samples_by_threshold': {}, 'top_cwes_by_threshold': {}}}, similarity_summary=SimilarityInsight(consensus_cwe='', top_cwes=[], confidence_levels={}, total_samples=0), analysis='', analysis_with_relationships='', criticism='', resolution='', relevant_cwes=[{'metadata': {'doc_id': '134', 'name': 'Use of Externally-Controlled Format String', 'source': 'sparse', 'original_content': 'The product uses a function that accepts a format string as an argument, but the format string originates from an external source.', 'keyphrase_sources': [{'id': 'rootcause:format string injection', 'keyphrase': 'format string injection', 'type': 'rootcause'}, {'id': 'weakness:format string injection', 'keyphrase': 'format string injection', 'type': 'weakness'}, {'id': 'weakness:memory corruption', 'keyphrase': 'memory corruption', 'type': 'weakness'}, {'id': 'product:Artifex Ghostscript', 'keyphrase': 'Artifex Ghostscript', 'type': 'product'}, {'id': 'component:uniprint device', 'keyphrase': 'uniprint device', 'type': 'component'}]}, 'similarity': np.float64(191.83597583697062)}, {'metadata': {'doc_id': '95', 'name': \"Improper Neutralization of Directives in Dynamically Evaluated Code ('Eval Injection')\", 'source': 'sparse', 'original_content': 'The product receives input from an upstream component, but it does not neutralize or incorrectly neutralizes code syntax before using the input in a dynamic evaluation call (e.g. \"eval\").', 'keyphrase_sources': [{'id': 'rootcause:format string injection', 'keyphrase': 'format string injection', 'type': 'rootcause'}, {'id': 'weakness:format string injection', 'keyphrase': 'format string injection', 'type': 'weakness'}, {'id': 'product:Artifex Ghostscript', 'keyphrase': 'Artifex Ghostscript', 'type': 'product'}, {'id': 'version:before 10.03.1', 'keyphrase': 'before 10.03.1', 'type': 'version'}, {'id': 'component:uniprint device', 'keyphrase': 'uniprint device', 'type': 'component'}]}, 'similarity': np.float64(145.7093165591434)}, {'metadata': {'doc_id': '115', 'name': 'Misinterpretation of Input', 'source': 'sparse', 'original_content': 'The product misinterprets an input, whether from an attacker or another product, in a security-relevant fashion.', 'keyphrase_sources': [{'id': 'rootcause:format string injection', 'keyphrase': 'format string injection', 'type': 'rootcause'}, {'id': 'weakness:format string injection', 'keyphrase': 'format string injection', 'type': 'weakness'}]}, 'similarity': np.float64(145.01288591427547)}, {'metadata': {'doc_id': '1286', 'name': 'Improper Validation of Syntactic Correctness of Input', 'source': 'sparse', 'original_content': 'The product receives input that is expected to be well-formed - i.e., to comply with a certain syntax - but it does not validate or incorrectly validates that the input complies with the syntax.', 'keyphrase_sources': [{'id': 'rootcause:format string injection', 'keyphrase': 'format string injection', 'type': 'rootcause'}, {'id': 'weakness:format string injection', 'keyphrase': 'format string injection', 'type': 'weakness'}]}, 'similarity': np.float64(128.17401990085366)}, {'metadata': {'doc_id': '787', 'name': 'Out-of-bounds Write', 'source': 'sparse', 'original_content': 'The product writes data past the end, or before the beginning, of the intended buffer.', 'keyphrase_sources': [{'id': 'weakness:memory corruption', 'keyphrase': 'memory corruption', 'type': 'weakness'}, {'id': 'product:Artifex Ghostscript', 'keyphrase': 'Artifex Ghostscript', 'type': 'product'}]}, 'similarity': np.float64(126.82948395197059)}, {'metadata': {'doc_id': '122', 'name': 'Heap-based Buffer Overflow', 'source': 'sparse', 'original_content': 'A heap overflow condition is a buffer overflow, where the buffer that can be overwritten is allocated in the heap portion of memory, generally meaning that the buffer was allocated using a routine such as malloc().', 'keyphrase_sources': [{'id': 'weakness:memory corruption', 'keyphrase': 'memory corruption', 'type': 'weakness'}, {'id': 'weakness:sandbox bypass', 'keyphrase': 'sandbox bypass', 'type': 'weakness'}, {'id': 'impact:SAFER sandbox bypass', 'keyphrase': 'SAFER sandbox bypass', 'type': 'impact'}, {'id': 'product:Artifex Ghostscript', 'keyphrase': 'Artifex Ghostscript', 'type': 'product'}]}, 'similarity': np.float64(121.00667522426139)}, {'metadata': {'doc_id': '843', 'name': \"Access of Resource Using Incompatible Type ('Type Confusion')\", 'source': 'sparse', 'original_content': 'The product allocates or initializes a resource such as a pointer, object, or variable using one type, but it later accesses that resource using a type that is incompatible with the original type.', 'keyphrase_sources': [{'id': 'weakness:memory corruption', 'keyphrase': 'memory corruption', 'type': 'weakness'}]}, 'similarity': np.float64(118.98596262872219)}, {'metadata': {'doc_id': '367', 'name': 'Time-of-check Time-of-use (TOCTOU) Race Condition', 'source': 'sparse', 'original_content': \"The product checks the state of a resource before using that resource, but the resource's state can change between the check and the use in a way that invalidates the results of the check. This can cause the product to perform invalid actions when the resource is in an unexpected state.\", 'keyphrase_sources': [{'id': 'weakness:memory corruption', 'keyphrase': 'memory corruption', 'type': 'weakness'}, {'id': 'weakness:sandbox bypass', 'keyphrase': 'sandbox bypass', 'type': 'weakness'}, {'id': 'impact:SAFER sandbox bypass', 'keyphrase': 'SAFER sandbox bypass', 'type': 'impact'}, {'id': 'product:Artifex Ghostscript', 'keyphrase': 'Artifex Ghostscript', 'type': 'product'}, {'id': 'component:uniprint device', 'keyphrase': 'uniprint device', 'type': 'component'}]}, 'similarity': np.float64(117.36899578073275)}, {'metadata': {'doc_id': '78', 'name': \"Improper Neutralization of Special Elements used in an OS Command ('OS Command Injection')\", 'source': 'sparse', 'original_content': 'The product constructs all or part of an OS command using externally-influenced input from an upstream component, but it does not neutralize or incorrectly neutralizes special elements that could modify the intended OS command when it is sent to a downstream component.', 'keyphrase_sources': [{'id': 'rootcause:format string injection', 'keyphrase': 'format string injection', 'type': 'rootcause'}, {'id': 'weakness:format string injection', 'keyphrase': 'format string injection', 'type': 'weakness'}, {'id': 'version:before 10.03.1', 'keyphrase': 'before 10.03.1', 'type': 'version'}]}, 'similarity': np.float64(116.70976179141692)}, {'metadata': {'doc_id': '183', 'name': 'Permissive List of Allowed Inputs', 'source': 'sparse', 'original_content': 'The product implements a protection mechanism that relies on a list of inputs (or properties of inputs) that are explicitly allowed by policy because the inputs are assumed to be safe, but the list is too permissive - that is, it allows an input that is unsafe, leading to resultant weaknesses.', 'keyphrase_sources': [{'id': 'weakness:sandbox bypass', 'keyphrase': 'sandbox bypass', 'type': 'weakness'}, {'id': 'impact:SAFER sandbox bypass', 'keyphrase': 'SAFER sandbox bypass', 'type': 'impact'}]}, 'similarity': np.float64(104.58715860715738)}, {'metadata': {'doc_id': '653', 'name': 'Improper Isolation or Compartmentalization', 'source': 'sparse', 'original_content': 'The product does not properly compartmentalize or isolate functionality, processes, or resources that require different privilege levels, rights, or permissions.', 'keyphrase_sources': [{'id': 'weakness:sandbox bypass', 'keyphrase': 'sandbox bypass', 'type': 'weakness'}, {'id': 'impact:SAFER sandbox bypass', 'keyphrase': 'SAFER sandbox bypass', 'type': 'impact'}]}, 'similarity': np.float64(98.32211556906523)}, {'metadata': {'doc_id': '470', 'name': \"Use of Externally-Controlled Input to Select Classes or Code ('Unsafe Reflection')\", 'source': 'sparse', 'original_content': 'The product uses external input with reflection to select which classes or code to use, but it does not sufficiently prevent the input from selecting improper classes or code.', 'keyphrase_sources': [{'id': 'weakness:sandbox bypass', 'keyphrase': 'sandbox bypass', 'type': 'weakness'}, {'id': 'impact:SAFER sandbox bypass', 'keyphrase': 'SAFER sandbox bypass', 'type': 'impact'}]}, 'similarity': np.float64(95.49953041487198)}, {'metadata': {'doc_id': '121', 'name': 'Stack-based Buffer Overflow', 'source': 'sparse', 'original_content': 'A stack-based buffer overflow condition is a condition where the buffer being overwritten is allocated on the stack (i.e., is a local variable or, rarely, a parameter to a function).', 'keyphrase_sources': [{'id': 'version:before 10.03.1', 'keyphrase': 'before 10.03.1', 'type': 'version'}]}, 'similarity': np.float64(44.156970992300835)}, {'metadata': {'doc_id': '36', 'name': 'Absolute Path Traversal', 'source': 'sparse', 'original_content': 'The product uses external input to construct a pathname that should be within a restricted directory, but it does not properly neutralize absolute path sequences such as \"/abs/path\" that can resolve to a location that is outside of that directory.', 'keyphrase_sources': [{'id': 'version:before 10.03.1', 'keyphrase': 'before 10.03.1', 'type': 'version'}]}, 'similarity': np.float64(39.1910043611661)}, {'metadata': {'doc_id': '284', 'name': 'Improper Access Control', 'source': 'sparse', 'original_content': 'The product does not restrict or incorrectly restricts access to a resource from an unauthorized actor.', 'keyphrase_sources': [{'id': 'version:before 10.03.1', 'keyphrase': 'before 10.03.1', 'type': 'version'}]}, 'similarity': np.float64(39.10140411158265)}, {'metadata': {'doc_id': '20', 'name': 'Improper Input Validation', 'source': 'sparse', 'original_content': 'The product receives input or data, but it does\\n        not validate or incorrectly validates that the input has the\\n        properties that are required to process the data safely and\\n        correctly.', 'keyphrase_sources': [{'id': 'component:uniprint device', 'keyphrase': 'uniprint device', 'type': 'component'}]}, 'similarity': np.float64(32.24482522381193)}, {'metadata': {'doc_id': '457', 'name': 'Use of Uninitialized Variable', 'source': 'sparse', 'original_content': 'The code uses a variable that has not been initialized, leading to unpredictable or unintended results.', 'keyphrase_sources': [{'id': 'component:uniprint device', 'keyphrase': 'uniprint device', 'type': 'component'}]}, 'similarity': np.float64(31.56410300905893)}], identified_cwes={'analyzer': [], 'critic_additional': []})",
  "retrieval_results": {
    "has_multiple_keyphrases": true,
    "keyphrase_cwe_sets": {
      "rootcause:format string injection": {
        "keyphrase": "format string injection",
        "type": "rootcause",
        "cwes": [
          {
            "metadata": {
              "doc_id": "134",
              "name": "Use of Externally-Controlled Format String",
              "source": "sparse",
              "original_content": "The product uses a function that accepts a format string as an argument, but the format string originates from an external source.",
              "keyphrase_sources": [
                {
                  "id": "rootcause:format string injection",
                  "keyphrase": "format string injection",
                  "type": "rootcause"
                },
                {
                  "id": "weakness:format string injection",
                  "keyphrase": "format string injection",
                  "type": "weakness"
                },
                {
                  "id": "weakness:memory corruption",
                  "keyphrase": "memory corruption",
                  "type": "weakness"
                },
                {
                  "id": "product:Artifex Ghostscript",
                  "keyphrase": "Artifex Ghostscript",
                  "type": "product"
                },
                {
                  "id": "component:uniprint device",
                  "keyphrase": "uniprint device",
                  "type": "component"
                }
              ]
            },
            "similarity": 191.83597583697062
          },
          {
            "metadata": {
              "doc_id": "95",
              "name": "Improper Neutralization of Directives in Dynamically Evaluated Code ('Eval Injection')",
              "source": "sparse",
              "original_content": "The product receives input from an upstream component, but it does not neutralize or incorrectly neutralizes code syntax before using the input in a dynamic evaluation call (e.g. \"eval\").",
              "keyphrase_sources": [
                {
                  "id": "rootcause:format string injection",
                  "keyphrase": "format string injection",
                  "type": "rootcause"
                },
                {
                  "id": "weakness:format string injection",
                  "keyphrase": "format string injection",
                  "type": "weakness"
                },
                {
                  "id": "product:Artifex Ghostscript",
                  "keyphrase": "Artifex Ghostscript",
                  "type": "product"
                },
                {
                  "id": "version:before 10.03.1",
                  "keyphrase": "before 10.03.1",
                  "type": "version"
                },
                {
                  "id": "component:uniprint device",
                  "keyphrase": "uniprint device",
                  "type": "component"
                }
              ]
            },
            "similarity": 145.7093165591434
          },
          {
            "metadata": {
              "doc_id": "115",
              "name": "Misinterpretation of Input",
              "source": "sparse",
              "original_content": "The product misinterprets an input, whether from an attacker or another product, in a security-relevant fashion.",
              "keyphrase_sources": [
                {
                  "id": "rootcause:format string injection",
                  "keyphrase": "format string injection",
                  "type": "rootcause"
                },
                {
                  "id": "weakness:format string injection",
                  "keyphrase": "format string injection",
                  "type": "weakness"
                }
              ]
            },
            "similarity": 145.01288591427547
          },
          {
            "metadata": {
              "doc_id": "1286",
              "name": "Improper Validation of Syntactic Correctness of Input",
              "source": "sparse",
              "original_content": "The product receives input that is expected to be well-formed - i.e., to comply with a certain syntax - but it does not validate or incorrectly validates that the input complies with the syntax.",
              "keyphrase_sources": [
                {
                  "id": "rootcause:format string injection",
                  "keyphrase": "format string injection",
                  "type": "rootcause"
                },
                {
                  "id": "weakness:format string injection",
                  "keyphrase": "format string injection",
                  "type": "weakness"
                }
              ]
            },
            "similarity": 128.17401990085366
          },
          {
            "metadata": {
              "doc_id": "78",
              "name": "Improper Neutralization of Special Elements used in an OS Command ('OS Command Injection')",
              "source": "sparse",
              "original_content": "The product constructs all or part of an OS command using externally-influenced input from an upstream component, but it does not neutralize or incorrectly neutralizes special elements that could modify the intended OS command when it is sent to a downstream component.",
              "keyphrase_sources": [
                {
                  "id": "rootcause:format string injection",
                  "keyphrase": "format string injection",
                  "type": "rootcause"
                },
                {
                  "id": "weakness:format string injection",
                  "keyphrase": "format string injection",
                  "type": "weakness"
                },
                {
                  "id": "version:before 10.03.1",
                  "keyphrase": "before 10.03.1",
                  "type": "version"
                }
              ]
            },
            "similarity": 116.70976179141692
          }
        ]
      },
      "weakness:format string injection": {
        "keyphrase": "format string injection",
        "type": "weakness",
        "cwes": [
          {
            "metadata": {
              "doc_id": "134",
              "name": "Use of Externally-Controlled Format String",
              "source": "sparse",
              "original_content": "The product uses a function that accepts a format string as an argument, but the format string originates from an external source."
            },
            "similarity": 179.04691078117256
          },
          {
            "metadata": {
              "doc_id": "95",
              "name": "Improper Neutralization of Directives in Dynamically Evaluated Code ('Eval Injection')",
              "source": "sparse",
              "original_content": "The product receives input from an upstream component, but it does not neutralize or incorrectly neutralizes code syntax before using the input in a dynamic evaluation call (e.g. \"eval\")."
            },
            "similarity": 135.99536212186715
          },
          {
            "metadata": {
              "doc_id": "115",
              "name": "Misinterpretation of Input",
              "source": "sparse",
              "original_content": "The product misinterprets an input, whether from an attacker or another product, in a security-relevant fashion."
            },
            "similarity": 135.3453601866571
          },
          {
            "metadata": {
              "doc_id": "1286",
              "name": "Improper Validation of Syntactic Correctness of Input",
              "source": "sparse",
              "original_content": "The product receives input that is expected to be well-formed - i.e., to comply with a certain syntax - but it does not validate or incorrectly validates that the input complies with the syntax."
            },
            "similarity": 119.62908524079675
          },
          {
            "metadata": {
              "doc_id": "78",
              "name": "Improper Neutralization of Special Elements used in an OS Command ('OS Command Injection')",
              "source": "sparse",
              "original_content": "The product constructs all or part of an OS command using externally-influenced input from an upstream component, but it does not neutralize or incorrectly neutralizes special elements that could modify the intended OS command when it is sent to a downstream component."
            },
            "similarity": 108.92911100532247
          }
        ]
      },
      "weakness:memory corruption": {
        "keyphrase": "memory corruption",
        "type": "weakness",
        "cwes": [
          {
            "metadata": {
              "doc_id": "134",
              "name": "Use of Externally-Controlled Format String",
              "source": "sparse",
              "original_content": "The product uses a function that accepts a format string as an argument, but the format string originates from an external source."
            },
            "similarity": 136.6022025241501
          },
          {
            "metadata": {
              "doc_id": "787",
              "name": "Out-of-bounds Write",
              "source": "sparse",
              "original_content": "The product writes data past the end, or before the beginning, of the intended buffer.",
              "keyphrase_sources": [
                {
                  "id": "weakness:memory corruption",
                  "keyphrase": "memory corruption",
                  "type": "weakness"
                },
                {
                  "id": "product:Artifex Ghostscript",
                  "keyphrase": "Artifex Ghostscript",
                  "type": "product"
                }
              ]
            },
            "similarity": 126.82948395197059
          },
          {
            "metadata": {
              "doc_id": "122",
              "name": "Heap-based Buffer Overflow",
              "source": "sparse",
              "original_content": "A heap overflow condition is a buffer overflow, where the buffer that can be overwritten is allocated in the heap portion of memory, generally meaning that the buffer was allocated using a routine such as malloc().",
              "keyphrase_sources": [
                {
                  "id": "weakness:memory corruption",
                  "keyphrase": "memory corruption",
                  "type": "weakness"
                },
                {
                  "id": "weakness:sandbox bypass",
                  "keyphrase": "sandbox bypass",
                  "type": "weakness"
                },
                {
                  "id": "impact:SAFER sandbox bypass",
                  "keyphrase": "SAFER sandbox bypass",
                  "type": "impact"
                },
                {
                  "id": "product:Artifex Ghostscript",
                  "keyphrase": "Artifex Ghostscript",
                  "type": "product"
                }
              ]
            },
            "similarity": 121.00667522426139
          },
          {
            "metadata": {
              "doc_id": "843",
              "name": "Access of Resource Using Incompatible Type ('Type Confusion')",
              "source": "sparse",
              "original_content": "The product allocates or initializes a resource such as a pointer, object, or variable using one type, but it later accesses that resource using a type that is incompatible with the original type.",
              "keyphrase_sources": [
                {
                  "id": "weakness:memory corruption",
                  "keyphrase": "memory corruption",
                  "type": "weakness"
                }
              ]
            },
            "similarity": 118.98596262872219
          },
          {
            "metadata": {
              "doc_id": "367",
              "name": "Time-of-check Time-of-use (TOCTOU) Race Condition",
              "source": "sparse",
              "original_content": "The product checks the state of a resource before using that resource, but the resource's state can change between the check and the use in a way that invalidates the results of the check. This can cause the product to perform invalid actions when the resource is in an unexpected state.",
              "keyphrase_sources": [
                {
                  "id": "weakness:memory corruption",
                  "keyphrase": "memory corruption",
                  "type": "weakness"
                },
                {
                  "id": "weakness:sandbox bypass",
                  "keyphrase": "sandbox bypass",
                  "type": "weakness"
                },
                {
                  "id": "impact:SAFER sandbox bypass",
                  "keyphrase": "SAFER sandbox bypass",
                  "type": "impact"
                },
                {
                  "id": "product:Artifex Ghostscript",
                  "keyphrase": "Artifex Ghostscript",
                  "type": "product"
                },
                {
                  "id": "component:uniprint device",
                  "keyphrase": "uniprint device",
                  "type": "component"
                }
              ]
            },
            "similarity": 117.36899578073275
          }
        ]
      },
      "weakness:sandbox bypass": {
        "keyphrase": "sandbox bypass",
        "type": "weakness",
        "cwes": [
          {
            "metadata": {
              "doc_id": "183",
              "name": "Permissive List of Allowed Inputs",
              "source": "sparse",
              "original_content": "The product implements a protection mechanism that relies on a list of inputs (or properties of inputs) that are explicitly allowed by policy because the inputs are assumed to be safe, but the list is too permissive - that is, it allows an input that is unsafe, leading to resultant weaknesses.",
              "keyphrase_sources": [
                {
                  "id": "weakness:sandbox bypass",
                  "keyphrase": "sandbox bypass",
                  "type": "weakness"
                },
                {
                  "id": "impact:SAFER sandbox bypass",
                  "keyphrase": "SAFER sandbox bypass",
                  "type": "impact"
                }
              ]
            },
            "similarity": 104.58715860715738
          },
          {
            "metadata": {
              "doc_id": "367",
              "name": "Time-of-check Time-of-use (TOCTOU) Race Condition",
              "source": "sparse",
              "original_content": "The product checks the state of a resource before using that resource, but the resource's state can change between the check and the use in a way that invalidates the results of the check. This can cause the product to perform invalid actions when the resource is in an unexpected state."
            },
            "similarity": 102.03449282844241
          },
          {
            "metadata": {
              "doc_id": "653",
              "name": "Improper Isolation or Compartmentalization",
              "source": "sparse",
              "original_content": "The product does not properly compartmentalize or isolate functionality, processes, or resources that require different privilege levels, rights, or permissions.",
              "keyphrase_sources": [
                {
                  "id": "weakness:sandbox bypass",
                  "keyphrase": "sandbox bypass",
                  "type": "weakness"
                },
                {
                  "id": "impact:SAFER sandbox bypass",
                  "keyphrase": "SAFER sandbox bypass",
                  "type": "impact"
                }
              ]
            },
            "similarity": 98.32211556906523
          },
          {
            "metadata": {
              "doc_id": "122",
              "name": "Heap-based Buffer Overflow",
              "source": "sparse",
              "original_content": "A heap overflow condition is a buffer overflow, where the buffer that can be overwritten is allocated in the heap portion of memory, generally meaning that the buffer was allocated using a routine such as malloc()."
            },
            "similarity": 95.6203434736219
          },
          {
            "metadata": {
              "doc_id": "470",
              "name": "Use of Externally-Controlled Input to Select Classes or Code ('Unsafe Reflection')",
              "source": "sparse",
              "original_content": "The product uses external input with reflection to select which classes or code to use, but it does not sufficiently prevent the input from selecting improper classes or code.",
              "keyphrase_sources": [
                {
                  "id": "weakness:sandbox bypass",
                  "keyphrase": "sandbox bypass",
                  "type": "weakness"
                },
                {
                  "id": "impact:SAFER sandbox bypass",
                  "keyphrase": "SAFER sandbox bypass",
                  "type": "impact"
                }
              ]
            },
            "similarity": 95.49953041487198
          }
        ]
      },
      "impact:SAFER sandbox bypass": {
        "keyphrase": "SAFER sandbox bypass",
        "type": "impact",
        "cwes": [
          {
            "metadata": {
              "doc_id": "367",
              "name": "Time-of-check Time-of-use (TOCTOU) Race Condition",
              "source": "sparse",
              "original_content": "The product checks the state of a resource before using that resource, but the resource's state can change between the check and the use in a way that invalidates the results of the check. This can cause the product to perform invalid actions when the resource is in an unexpected state."
            },
            "similarity": 40.73703463905636
          },
          {
            "metadata": {
              "doc_id": "183",
              "name": "Permissive List of Allowed Inputs",
              "source": "sparse",
              "original_content": "The product implements a protection mechanism that relies on a list of inputs (or properties of inputs) that are explicitly allowed by policy because the inputs are assumed to be safe, but the list is too permissive - that is, it allows an input that is unsafe, leading to resultant weaknesses."
            },
            "similarity": 37.35255664541335
          },
          {
            "metadata": {
              "doc_id": "653",
              "name": "Improper Isolation or Compartmentalization",
              "source": "sparse",
              "original_content": "The product does not properly compartmentalize or isolate functionality, processes, or resources that require different privilege levels, rights, or permissions."
            },
            "similarity": 35.115041274666154
          },
          {
            "metadata": {
              "doc_id": "122",
              "name": "Heap-based Buffer Overflow",
              "source": "sparse",
              "original_content": "A heap overflow condition is a buffer overflow, where the buffer that can be overwritten is allocated in the heap portion of memory, generally meaning that the buffer was allocated using a routine such as malloc()."
            },
            "similarity": 34.15012266915068
          },
          {
            "metadata": {
              "doc_id": "470",
              "name": "Use of Externally-Controlled Input to Select Classes or Code ('Unsafe Reflection')",
              "source": "sparse",
              "original_content": "The product uses external input with reflection to select which classes or code to use, but it does not sufficiently prevent the input from selecting improper classes or code."
            },
            "similarity": 34.106975148168566
          }
        ]
      },
      "product:Artifex Ghostscript": {
        "keyphrase": "Artifex Ghostscript",
        "type": "product",
        "cwes": [
          {
            "metadata": {
              "doc_id": "134",
              "name": "Use of Externally-Controlled Format String",
              "source": "sparse",
              "original_content": "The product uses a function that accepts a format string as an argument, but the format string originates from an external source."
            },
            "similarity": 33.00663362504009
          },
          {
            "metadata": {
              "doc_id": "122",
              "name": "Heap-based Buffer Overflow",
              "source": "sparse",
              "original_content": "A heap overflow condition is a buffer overflow, where the buffer that can be overwritten is allocated in the heap portion of memory, generally meaning that the buffer was allocated using a routine such as malloc()."
            },
            "similarity": 31.4341478632288
          },
          {
            "metadata": {
              "doc_id": "787",
              "name": "Out-of-bounds Write",
              "source": "sparse",
              "original_content": "The product writes data past the end, or before the beginning, of the intended buffer."
            },
            "similarity": 30.54539005731199
          },
          {
            "metadata": {
              "doc_id": "95",
              "name": "Improper Neutralization of Directives in Dynamically Evaluated Code ('Eval Injection')",
              "source": "sparse",
              "original_content": "The product receives input from an upstream component, but it does not neutralize or incorrectly neutralizes code syntax before using the input in a dynamic evaluation call (e.g. \"eval\")."
            },
            "similarity": 30.389416706364013
          },
          {
            "metadata": {
              "doc_id": "367",
              "name": "Time-of-check Time-of-use (TOCTOU) Race Condition",
              "source": "sparse",
              "original_content": "The product checks the state of a resource before using that resource, but the resource's state can change between the check and the use in a way that invalidates the results of the check. This can cause the product to perform invalid actions when the resource is in an unexpected state."
            },
            "similarity": 29.512204153334455
          }
        ]
      },
      "version:before 10.03.1": {
        "keyphrase": "before 10.03.1",
        "type": "version",
        "cwes": [
          {
            "metadata": {
              "doc_id": "95",
              "name": "Improper Neutralization of Directives in Dynamically Evaluated Code ('Eval Injection')",
              "source": "sparse",
              "original_content": "The product receives input from an upstream component, but it does not neutralize or incorrectly neutralizes code syntax before using the input in a dynamic evaluation call (e.g. \"eval\")."
            },
            "similarity": 48.486120486154356
          },
          {
            "metadata": {
              "doc_id": "121",
              "name": "Stack-based Buffer Overflow",
              "source": "sparse",
              "original_content": "A stack-based buffer overflow condition is a condition where the buffer being overwritten is allocated on the stack (i.e., is a local variable or, rarely, a parameter to a function).",
              "keyphrase_sources": [
                {
                  "id": "version:before 10.03.1",
                  "keyphrase": "before 10.03.1",
                  "type": "version"
                }
              ]
            },
            "similarity": 44.156970992300835
          },
          {
            "metadata": {
              "doc_id": "78",
              "name": "Improper Neutralization of Special Elements used in an OS Command ('OS Command Injection')",
              "source": "sparse",
              "original_content": "The product constructs all or part of an OS command using externally-influenced input from an upstream component, but it does not neutralize or incorrectly neutralizes special elements that could modify the intended OS command when it is sent to a downstream component."
            },
            "similarity": 41.28671864120835
          },
          {
            "metadata": {
              "doc_id": "36",
              "name": "Absolute Path Traversal",
              "source": "sparse",
              "original_content": "The product uses external input to construct a pathname that should be within a restricted directory, but it does not properly neutralize absolute path sequences such as \"/abs/path\" that can resolve to a location that is outside of that directory.",
              "keyphrase_sources": [
                {
                  "id": "version:before 10.03.1",
                  "keyphrase": "before 10.03.1",
                  "type": "version"
                }
              ]
            },
            "similarity": 39.1910043611661
          },
          {
            "metadata": {
              "doc_id": "284",
              "name": "Improper Access Control",
              "source": "sparse",
              "original_content": "The product does not restrict or incorrectly restricts access to a resource from an unauthorized actor.",
              "keyphrase_sources": [
                {
                  "id": "version:before 10.03.1",
                  "keyphrase": "before 10.03.1",
                  "type": "version"
                }
              ]
            },
            "similarity": 39.10140411158265
          }
        ]
      },
      "component:uniprint device": {
        "keyphrase": "uniprint device",
        "type": "component",
        "cwes": [
          {
            "metadata": {
              "doc_id": "134",
              "name": "Use of Externally-Controlled Format String",
              "source": "sparse",
              "original_content": "The product uses a function that accepts a format string as an argument, but the format string originates from an external source."
            },
            "similarity": 34.8688747543091
          },
          {
            "metadata": {
              "doc_id": "367",
              "name": "Time-of-check Time-of-use (TOCTOU) Race Condition",
              "source": "sparse",
              "original_content": "The product checks the state of a resource before using that resource, but the resource's state can change between the check and the use in a way that invalidates the results of the check. This can cause the product to perform invalid actions when the resource is in an unexpected state."
            },
            "similarity": 32.85662292987595
          },
          {
            "metadata": {
              "doc_id": "20",
              "name": "Improper Input Validation",
              "source": "sparse",
              "original_content": "The product receives input or data, but it does\n        not validate or incorrectly validates that the input has the\n        properties that are required to process the data safely and\n        correctly.",
              "keyphrase_sources": [
                {
                  "id": "component:uniprint device",
                  "keyphrase": "uniprint device",
                  "type": "component"
                }
              ]
            },
            "similarity": 32.24482522381193
          },
          {
            "metadata": {
              "doc_id": "95",
              "name": "Improper Neutralization of Directives in Dynamically Evaluated Code ('Eval Injection')",
              "source": "sparse",
              "original_content": "The product receives input from an upstream component, but it does not neutralize or incorrectly neutralizes code syntax before using the input in a dynamic evaluation call (e.g. \"eval\")."
            },
            "similarity": 32.0805561434569
          },
          {
            "metadata": {
              "doc_id": "457",
              "name": "Use of Uninitialized Variable",
              "source": "sparse",
              "original_content": "The code uses a variable that has not been initialized, leading to unpredictable or unintended results.",
              "keyphrase_sources": [
                {
                  "id": "component:uniprint device",
                  "keyphrase": "uniprint device",
                  "type": "component"
                }
              ]
            },
            "similarity": 31.56410300905893
          }
        ]
      }
    },
    "keyphrase_mapping": {
      "134": [
        {
          "id": "rootcause:format string injection",
          "keyphrase": "format string injection",
          "type": "rootcause"
        },
        {
          "id": "weakness:format string injection",
          "keyphrase": "format string injection",
          "type": "weakness"
        },
        {
          "id": "weakness:memory corruption",
          "keyphrase": "memory corruption",
          "type": "weakness"
        },
        {
          "id": "product:Artifex Ghostscript",
          "keyphrase": "Artifex Ghostscript",
          "type": "product"
        },
        {
          "id": "component:uniprint device",
          "keyphrase": "uniprint device",
          "type": "component"
        }
      ],
      "95": [
        {
          "id": "rootcause:format string injection",
          "keyphrase": "format string injection",
          "type": "rootcause"
        },
        {
          "id": "weakness:format string injection",
          "keyphrase": "format string injection",
          "type": "weakness"
        },
        {
          "id": "product:Artifex Ghostscript",
          "keyphrase": "Artifex Ghostscript",
          "type": "product"
        },
        {
          "id": "version:before 10.03.1",
          "keyphrase": "before 10.03.1",
          "type": "version"
        },
        {
          "id": "component:uniprint device",
          "keyphrase": "uniprint device",
          "type": "component"
        }
      ],
      "115": [
        {
          "id": "rootcause:format string injection",
          "keyphrase": "format string injection",
          "type": "rootcause"
        },
        {
          "id": "weakness:format string injection",
          "keyphrase": "format string injection",
          "type": "weakness"
        }
      ],
      "1286": [
        {
          "id": "rootcause:format string injection",
          "keyphrase": "format string injection",
          "type": "rootcause"
        },
        {
          "id": "weakness:format string injection",
          "keyphrase": "format string injection",
          "type": "weakness"
        }
      ],
      "78": [
        {
          "id": "rootcause:format string injection",
          "keyphrase": "format string injection",
          "type": "rootcause"
        },
        {
          "id": "weakness:format string injection",
          "keyphrase": "format string injection",
          "type": "weakness"
        },
        {
          "id": "version:before 10.03.1",
          "keyphrase": "before 10.03.1",
          "type": "version"
        }
      ],
      "787": [
        {
          "id": "weakness:memory corruption",
          "keyphrase": "memory corruption",
          "type": "weakness"
        },
        {
          "id": "product:Artifex Ghostscript",
          "keyphrase": "Artifex Ghostscript",
          "type": "product"
        }
      ],
      "122": [
        {
          "id": "weakness:memory corruption",
          "keyphrase": "memory corruption",
          "type": "weakness"
        },
        {
          "id": "weakness:sandbox bypass",
          "keyphrase": "sandbox bypass",
          "type": "weakness"
        },
        {
          "id": "impact:SAFER sandbox bypass",
          "keyphrase": "SAFER sandbox bypass",
          "type": "impact"
        },
        {
          "id": "product:Artifex Ghostscript",
          "keyphrase": "Artifex Ghostscript",
          "type": "product"
        }
      ],
      "843": [
        {
          "id": "weakness:memory corruption",
          "keyphrase": "memory corruption",
          "type": "weakness"
        }
      ],
      "367": [
        {
          "id": "weakness:memory corruption",
          "keyphrase": "memory corruption",
          "type": "weakness"
        },
        {
          "id": "weakness:sandbox bypass",
          "keyphrase": "sandbox bypass",
          "type": "weakness"
        },
        {
          "id": "impact:SAFER sandbox bypass",
          "keyphrase": "SAFER sandbox bypass",
          "type": "impact"
        },
        {
          "id": "product:Artifex Ghostscript",
          "keyphrase": "Artifex Ghostscript",
          "type": "product"
        },
        {
          "id": "component:uniprint device",
          "keyphrase": "uniprint device",
          "type": "component"
        }
      ],
      "183": [
        {
          "id": "weakness:sandbox bypass",
          "keyphrase": "sandbox bypass",
          "type": "weakness"
        },
        {
          "id": "impact:SAFER sandbox bypass",
          "keyphrase": "SAFER sandbox bypass",
          "type": "impact"
        }
      ],
      "653": [
        {
          "id": "weakness:sandbox bypass",
          "keyphrase": "sandbox bypass",
          "type": "weakness"
        },
        {
          "id": "impact:SAFER sandbox bypass",
          "keyphrase": "SAFER sandbox bypass",
          "type": "impact"
        }
      ],
      "470": [
        {
          "id": "weakness:sandbox bypass",
          "keyphrase": "sandbox bypass",
          "type": "weakness"
        },
        {
          "id": "impact:SAFER sandbox bypass",
          "keyphrase": "SAFER sandbox bypass",
          "type": "impact"
        }
      ],
      "121": [
        {
          "id": "version:before 10.03.1",
          "keyphrase": "before 10.03.1",
          "type": "version"
        }
      ],
      "36": [
        {
          "id": "version:before 10.03.1",
          "keyphrase": "before 10.03.1",
          "type": "version"
        }
      ],
      "284": [
        {
          "id": "version:before 10.03.1",
          "keyphrase": "before 10.03.1",
          "type": "version"
        }
      ],
      "20": [
        {
          "id": "component:uniprint device",
          "keyphrase": "uniprint device",
          "type": "component"
        }
      ],
      "457": [
        {
          "id": "component:uniprint device",
          "keyphrase": "uniprint device",
          "type": "component"
        }
      ]
    },
    "relevant_cwes": [
      {
        "metadata": {
          "doc_id": "134",
          "name": "Use of Externally-Controlled Format String",
          "source": "sparse",
          "original_content": "The product uses a function that accepts a format string as an argument, but the format string originates from an external source.",
          "keyphrase_sources": [
            {
              "id": "rootcause:format string injection",
              "keyphrase": "format string injection",
              "type": "rootcause"
            },
            {
              "id": "weakness:format string injection",
              "keyphrase": "format string injection",
              "type": "weakness"
            },
            {
              "id": "weakness:memory corruption",
              "keyphrase": "memory corruption",
              "type": "weakness"
            },
            {
              "id": "product:Artifex Ghostscript",
              "keyphrase": "Artifex Ghostscript",
              "type": "product"
            },
            {
              "id": "component:uniprint device",
              "keyphrase": "uniprint device",
              "type": "component"
            }
          ]
        },
        "similarity": 191.83597583697062
      },
      {
        "metadata": {
          "doc_id": "95",
          "name": "Improper Neutralization of Directives in Dynamically Evaluated Code ('Eval Injection')",
          "source": "sparse",
          "original_content": "The product receives input from an upstream component, but it does not neutralize or incorrectly neutralizes code syntax before using the input in a dynamic evaluation call (e.g. \"eval\").",
          "keyphrase_sources": [
            {
              "id": "rootcause:format string injection",
              "keyphrase": "format string injection",
              "type": "rootcause"
            },
            {
              "id": "weakness:format string injection",
              "keyphrase": "format string injection",
              "type": "weakness"
            },
            {
              "id": "product:Artifex Ghostscript",
              "keyphrase": "Artifex Ghostscript",
              "type": "product"
            },
            {
              "id": "version:before 10.03.1",
              "keyphrase": "before 10.03.1",
              "type": "version"
            },
            {
              "id": "component:uniprint device",
              "keyphrase": "uniprint device",
              "type": "component"
            }
          ]
        },
        "similarity": 145.7093165591434
      },
      {
        "metadata": {
          "doc_id": "115",
          "name": "Misinterpretation of Input",
          "source": "sparse",
          "original_content": "The product misinterprets an input, whether from an attacker or another product, in a security-relevant fashion.",
          "keyphrase_sources": [
            {
              "id": "rootcause:format string injection",
              "keyphrase": "format string injection",
              "type": "rootcause"
            },
            {
              "id": "weakness:format string injection",
              "keyphrase": "format string injection",
              "type": "weakness"
            }
          ]
        },
        "similarity": 145.01288591427547
      },
      {
        "metadata": {
          "doc_id": "1286",
          "name": "Improper Validation of Syntactic Correctness of Input",
          "source": "sparse",
          "original_content": "The product receives input that is expected to be well-formed - i.e., to comply with a certain syntax - but it does not validate or incorrectly validates that the input complies with the syntax.",
          "keyphrase_sources": [
            {
              "id": "rootcause:format string injection",
              "keyphrase": "format string injection",
              "type": "rootcause"
            },
            {
              "id": "weakness:format string injection",
              "keyphrase": "format string injection",
              "type": "weakness"
            }
          ]
        },
        "similarity": 128.17401990085366
      },
      {
        "metadata": {
          "doc_id": "787",
          "name": "Out-of-bounds Write",
          "source": "sparse",
          "original_content": "The product writes data past the end, or before the beginning, of the intended buffer.",
          "keyphrase_sources": [
            {
              "id": "weakness:memory corruption",
              "keyphrase": "memory corruption",
              "type": "weakness"
            },
            {
              "id": "product:Artifex Ghostscript",
              "keyphrase": "Artifex Ghostscript",
              "type": "product"
            }
          ]
        },
        "similarity": 126.82948395197059
      },
      {
        "metadata": {
          "doc_id": "122",
          "name": "Heap-based Buffer Overflow",
          "source": "sparse",
          "original_content": "A heap overflow condition is a buffer overflow, where the buffer that can be overwritten is allocated in the heap portion of memory, generally meaning that the buffer was allocated using a routine such as malloc().",
          "keyphrase_sources": [
            {
              "id": "weakness:memory corruption",
              "keyphrase": "memory corruption",
              "type": "weakness"
            },
            {
              "id": "weakness:sandbox bypass",
              "keyphrase": "sandbox bypass",
              "type": "weakness"
            },
            {
              "id": "impact:SAFER sandbox bypass",
              "keyphrase": "SAFER sandbox bypass",
              "type": "impact"
            },
            {
              "id": "product:Artifex Ghostscript",
              "keyphrase": "Artifex Ghostscript",
              "type": "product"
            }
          ]
        },
        "similarity": 121.00667522426139
      },
      {
        "metadata": {
          "doc_id": "843",
          "name": "Access of Resource Using Incompatible Type ('Type Confusion')",
          "source": "sparse",
          "original_content": "The product allocates or initializes a resource such as a pointer, object, or variable using one type, but it later accesses that resource using a type that is incompatible with the original type.",
          "keyphrase_sources": [
            {
              "id": "weakness:memory corruption",
              "keyphrase": "memory corruption",
              "type": "weakness"
            }
          ]
        },
        "similarity": 118.98596262872219
      },
      {
        "metadata": {
          "doc_id": "367",
          "name": "Time-of-check Time-of-use (TOCTOU) Race Condition",
          "source": "sparse",
          "original_content": "The product checks the state of a resource before using that resource, but the resource's state can change between the check and the use in a way that invalidates the results of the check. This can cause the product to perform invalid actions when the resource is in an unexpected state.",
          "keyphrase_sources": [
            {
              "id": "weakness:memory corruption",
              "keyphrase": "memory corruption",
              "type": "weakness"
            },
            {
              "id": "weakness:sandbox bypass",
              "keyphrase": "sandbox bypass",
              "type": "weakness"
            },
            {
              "id": "impact:SAFER sandbox bypass",
              "keyphrase": "SAFER sandbox bypass",
              "type": "impact"
            },
            {
              "id": "product:Artifex Ghostscript",
              "keyphrase": "Artifex Ghostscript",
              "type": "product"
            },
            {
              "id": "component:uniprint device",
              "keyphrase": "uniprint device",
              "type": "component"
            }
          ]
        },
        "similarity": 117.36899578073275
      },
      {
        "metadata": {
          "doc_id": "78",
          "name": "Improper Neutralization of Special Elements used in an OS Command ('OS Command Injection')",
          "source": "sparse",
          "original_content": "The product constructs all or part of an OS command using externally-influenced input from an upstream component, but it does not neutralize or incorrectly neutralizes special elements that could modify the intended OS command when it is sent to a downstream component.",
          "keyphrase_sources": [
            {
              "id": "rootcause:format string injection",
              "keyphrase": "format string injection",
              "type": "rootcause"
            },
            {
              "id": "weakness:format string injection",
              "keyphrase": "format string injection",
              "type": "weakness"
            },
            {
              "id": "version:before 10.03.1",
              "keyphrase": "before 10.03.1",
              "type": "version"
            }
          ]
        },
        "similarity": 116.70976179141692
      },
      {
        "metadata": {
          "doc_id": "183",
          "name": "Permissive List of Allowed Inputs",
          "source": "sparse",
          "original_content": "The product implements a protection mechanism that relies on a list of inputs (or properties of inputs) that are explicitly allowed by policy because the inputs are assumed to be safe, but the list is too permissive - that is, it allows an input that is unsafe, leading to resultant weaknesses.",
          "keyphrase_sources": [
            {
              "id": "weakness:sandbox bypass",
              "keyphrase": "sandbox bypass",
              "type": "weakness"
            },
            {
              "id": "impact:SAFER sandbox bypass",
              "keyphrase": "SAFER sandbox bypass",
              "type": "impact"
            }
          ]
        },
        "similarity": 104.58715860715738
      },
      {
        "metadata": {
          "doc_id": "653",
          "name": "Improper Isolation or Compartmentalization",
          "source": "sparse",
          "original_content": "The product does not properly compartmentalize or isolate functionality, processes, or resources that require different privilege levels, rights, or permissions.",
          "keyphrase_sources": [
            {
              "id": "weakness:sandbox bypass",
              "keyphrase": "sandbox bypass",
              "type": "weakness"
            },
            {
              "id": "impact:SAFER sandbox bypass",
              "keyphrase": "SAFER sandbox bypass",
              "type": "impact"
            }
          ]
        },
        "similarity": 98.32211556906523
      },
      {
        "metadata": {
          "doc_id": "470",
          "name": "Use of Externally-Controlled Input to Select Classes or Code ('Unsafe Reflection')",
          "source": "sparse",
          "original_content": "The product uses external input with reflection to select which classes or code to use, but it does not sufficiently prevent the input from selecting improper classes or code.",
          "keyphrase_sources": [
            {
              "id": "weakness:sandbox bypass",
              "keyphrase": "sandbox bypass",
              "type": "weakness"
            },
            {
              "id": "impact:SAFER sandbox bypass",
              "keyphrase": "SAFER sandbox bypass",
              "type": "impact"
            }
          ]
        },
        "similarity": 95.49953041487198
      },
      {
        "metadata": {
          "doc_id": "121",
          "name": "Stack-based Buffer Overflow",
          "source": "sparse",
          "original_content": "A stack-based buffer overflow condition is a condition where the buffer being overwritten is allocated on the stack (i.e., is a local variable or, rarely, a parameter to a function).",
          "keyphrase_sources": [
            {
              "id": "version:before 10.03.1",
              "keyphrase": "before 10.03.1",
              "type": "version"
            }
          ]
        },
        "similarity": 44.156970992300835
      },
      {
        "metadata": {
          "doc_id": "36",
          "name": "Absolute Path Traversal",
          "source": "sparse",
          "original_content": "The product uses external input to construct a pathname that should be within a restricted directory, but it does not properly neutralize absolute path sequences such as \"/abs/path\" that can resolve to a location that is outside of that directory.",
          "keyphrase_sources": [
            {
              "id": "version:before 10.03.1",
              "keyphrase": "before 10.03.1",
              "type": "version"
            }
          ]
        },
        "similarity": 39.1910043611661
      },
      {
        "metadata": {
          "doc_id": "284",
          "name": "Improper Access Control",
          "source": "sparse",
          "original_content": "The product does not restrict or incorrectly restricts access to a resource from an unauthorized actor.",
          "keyphrase_sources": [
            {
              "id": "version:before 10.03.1",
              "keyphrase": "before 10.03.1",
              "type": "version"
            }
          ]
        },
        "similarity": 39.10140411158265
      },
      {
        "metadata": {
          "doc_id": "20",
          "name": "Improper Input Validation",
          "source": "sparse",
          "original_content": "The product receives input or data, but it does\n        not validate or incorrectly validates that the input has the\n        properties that are required to process the data safely and\n        correctly.",
          "keyphrase_sources": [
            {
              "id": "component:uniprint device",
              "keyphrase": "uniprint device",
              "type": "component"
            }
          ]
        },
        "similarity": 32.24482522381193
      },
      {
        "metadata": {
          "doc_id": "457",
          "name": "Use of Uninitialized Variable",
          "source": "sparse",
          "original_content": "The code uses a variable that has not been initialized, leading to unpredictable or unintended results.",
          "keyphrase_sources": [
            {
              "id": "component:uniprint device",
              "keyphrase": "uniprint device",
              "type": "component"
            }
          ]
        },
        "similarity": 31.56410300905893
      }
    ],
    "enhanced_query": "# Vulnerability Description\n\n    Artifex Ghostscript before 10.03.1 allows **memory corruption**, and SAFER **sandbox bypass**, via ****format string injection**** with a uniprint device.\n\n    # Keyphrase-Specific CWE Analysis\n    This vulnerability contains multiple keyphrases that may map to different CWEs. \n    Please analyze each keyphrase separately and determine the most appropriate CWE(s) for each.\n\n    ## ROOTCAUSE: 'format string injection'\n\nRelevant CWEs for this ROOTCAUSE:\n\n### 1. CWE-134: Use of Externally-Controlled Format String (Score: 191.84)\n\nThe product uses a function that accepts a format string as an argument, but the format string originates from an external source....\n\n### 2. CWE-95: Improper Neutralization of Directives in Dynamically Evaluated Code ('Eval Injection') (Score: 145.71)\n\nThe product receives input from an upstream component, but it does not neutralize or incorrectly neutralizes code syntax before using the input in a dynamic evaluation call (e.g. \"eval\")....\n\n### 3. CWE-115: Misinterpretation of Input (Score: 145.01)\n\nThe product misinterprets an input, whether from an attacker or another product, in a security-relevant fashion....\n\n### 4. CWE-1286: Improper Validation of Syntactic Correctness of Input (Score: 128.17)\n\nThe product receives input that is expected to be well-formed - i.e., to comply with a certain syntax - but it does not validate or incorrectly validates that the input complies with the syntax....\n\n### 5. CWE-78: Improper Neutralization of Special Elements used in an OS Command ('OS Command Injection') (Score: 116.71)\n\nThe product constructs all or part of an OS command using externally-influenced input from an upstream component, but it does not neutralize or incorrectly neutralizes special elements that could modify the intended OS command when it is sent to a downstream component....\n\n## WEAKNESS: 'format string injection'\n\nRelevant CWEs for this WEAKNESS:\n\n### 1. CWE-134: Use of Externally-Controlled Format String (Score: 191.84)\n\nThe product uses a function that accepts a format string as an argument, but the format string originates from an external source....\n\n### 2. CWE-95: Improper Neutralization of Directives in Dynamically Evaluated Code ('Eval Injection') (Score: 145.71)\n\nThe product receives input from an upstream component, but it does not neutralize or incorrectly neutralizes code syntax before using the input in a dynamic evaluation call (e.g. \"eval\")....\n\n### 3. CWE-115: Misinterpretation of Input (Score: 145.01)\n\nThe product misinterprets an input, whether from an attacker or another product, in a security-relevant fashion....\n\n### 4. CWE-1286: Improper Validation of Syntactic Correctness of Input (Score: 128.17)\n\nThe product receives input that is expected to be well-formed - i.e., to comply with a certain syntax - but it does not validate or incorrectly validates that the input complies with the syntax....\n\n### 5. CWE-78: Improper Neutralization of Special Elements used in an OS Command ('OS Command Injection') (Score: 116.71)\n\nThe product constructs all or part of an OS command using externally-influenced input from an upstream component, but it does not neutralize or incorrectly neutralizes special elements that could modify the intended OS command when it is sent to a downstream component....\n\n## WEAKNESS: 'memory corruption'\n\nRelevant CWEs for this WEAKNESS:\n\n### 1. CWE-134: Use of Externally-Controlled Format String (Score: 191.84)\n\nThe product uses a function that accepts a format string as an argument, but the format string originates from an external source....\n\n### 2. CWE-787: Out-of-bounds Write (Score: 126.83)\n\nThe product writes data past the end, or before the beginning, of the intended buffer....\n\n### 3. CWE-122: Heap-based Buffer Overflow (Score: 121.01)\n\nA heap overflow condition is a buffer overflow, where the buffer that can be overwritten is allocated in the heap portion of memory, generally meaning that the buffer was allocated using a routine such as malloc()....\n\n### 4. CWE-843: Access of Resource Using Incompatible Type ('Type Confusion') (Score: 118.99)\n\nThe product allocates or initializes a resource such as a pointer, object, or variable using one type, but it later accesses that resource using a type that is incompatible with the original type....\n\n### 5. CWE-367: Time-of-check Time-of-use (TOCTOU) Race Condition (Score: 117.37)\n\nThe product checks the state of a resource before using that resource, but the resource's state can change between the check and the use in a way that invalidates the results of the check. This can cause the product to perform invalid actions when the resource is in an unexpected state....\n\n## PRODUCT: 'Artifex Ghostscript'\n\nRelevant CWEs for this PRODUCT:\n\n### 1. CWE-134: Use of Externally-Controlled Format String (Score: 191.84)\n\nThe product uses a function that accepts a format string as an argument, but the format string originates from an external source....\n\n### 2. CWE-95: Improper Neutralization of Directives in Dynamically Evaluated Code ('Eval Injection') (Score: 145.71)\n\nThe product receives input from an upstream component, but it does not neutralize or incorrectly neutralizes code syntax before using the input in a dynamic evaluation call (e.g. \"eval\")....\n\n### 3. CWE-787: Out-of-bounds Write (Score: 126.83)\n\nThe product writes data past the end, or before the beginning, of the intended buffer....\n\n### 4. CWE-122: Heap-based Buffer Overflow (Score: 121.01)\n\nA heap overflow condition is a buffer overflow, where the buffer that can be overwritten is allocated in the heap portion of memory, generally meaning that the buffer was allocated using a routine such as malloc()....\n\n### 5. CWE-367: Time-of-check Time-of-use (TOCTOU) Race Condition (Score: 117.37)\n\nThe product checks the state of a resource before using that resource, but the resource's state can change between the check and the use in a way that invalidates the results of the check. This can cause the product to perform invalid actions when the resource is in an unexpected state....\n\n## COMPONENT: 'uniprint device'\n\nRelevant CWEs for this COMPONENT:\n\n### 1. CWE-134: Use of Externally-Controlled Format String (Score: 191.84)\n\nThe product uses a function that accepts a format string as an argument, but the format string originates from an external source....\n\n### 2. CWE-95: Improper Neutralization of Directives in Dynamically Evaluated Code ('Eval Injection') (Score: 145.71)\n\nThe product receives input from an upstream component, but it does not neutralize or incorrectly neutralizes code syntax before using the input in a dynamic evaluation call (e.g. \"eval\")....\n\n### 3. CWE-367: Time-of-check Time-of-use (TOCTOU) Race Condition (Score: 117.37)\n\nThe product checks the state of a resource before using that resource, but the resource's state can change between the check and the use in a way that invalidates the results of the check. This can cause the product to perform invalid actions when the resource is in an unexpected state....\n\n### 4. CWE-20: Improper Input Validation (Score: 32.24)\n\nThe product receives input or data, but it does\n        not validate or incorrectly validates that the input has the\n        properties that are required to process the data safely and\n        correctly....\n\n### 5. CWE-457: Use of Uninitialized Variable (Score: 31.56)\n\nThe code uses a variable that has not been initialized, leading to unpredictable or unintended results....\n\n## VERSION: 'before 10.03.1'\n\nRelevant CWEs for this VERSION:\n\n### 1. CWE-95: Improper Neutralization of Directives in Dynamically Evaluated Code ('Eval Injection') (Score: 145.71)\n\nThe product receives input from an upstream component, but it does not neutralize or incorrectly neutralizes code syntax before using the input in a dynamic evaluation call (e.g. \"eval\")....\n\n### 2. CWE-78: Improper Neutralization of Special Elements used in an OS Command ('OS Command Injection') (Score: 116.71)\n\nThe product constructs all or part of an OS command using externally-influenced input from an upstream component, but it does not neutralize or incorrectly neutralizes special elements that could modify the intended OS command when it is sent to a downstream component....\n\n### 3. CWE-121: Stack-based Buffer Overflow (Score: 44.16)\n\nA stack-based buffer overflow condition is a condition where the buffer being overwritten is allocated on the stack (i.e., is a local variable or, rarely, a parameter to a function)....\n\n### 4. CWE-36: Absolute Path Traversal (Score: 39.19)\n\nThe product uses external input to construct a pathname that should be within a restricted directory, but it does not properly neutralize absolute path sequences such as \"/abs/path\" that can resolve to a location that is outside of that directory....\n\n### 5. CWE-284: Improper Access Control (Score: 39.10)\n\nThe product does not restrict or incorrectly restricts access to a resource from an unauthorized actor....\n\n## WEAKNESS: 'sandbox bypass'\n\nRelevant CWEs for this WEAKNESS:\n\n### 1. CWE-122: Heap-based Buffer Overflow (Score: 121.01)\n\nA heap overflow condition is a buffer overflow, where the buffer that can be overwritten is allocated in the heap portion of memory, generally meaning that the buffer was allocated using a routine such as malloc()....\n\n### 2. CWE-367: Time-of-check Time-of-use (TOCTOU) Race Condition (Score: 117.37)\n\nThe product checks the state of a resource before using that resource, but the resource's state can change between the check and the use in a way that invalidates the results of the check. This can cause the product to perform invalid actions when the resource is in an unexpected state....\n\n### 3. CWE-183: Permissive List of Allowed Inputs (Score: 104.59)\n\nThe product implements a protection mechanism that relies on a list of inputs (or properties of inputs) that are explicitly allowed by policy because the inputs are assumed to be safe, but the list is too permissive - that is, it allows an input that is unsafe, leading to resultant weaknesses....\n\n### 4. CWE-653: Improper Isolation or Compartmentalization (Score: 98.32)\n\nThe product does not properly compartmentalize or isolate functionality, processes, or resources that require different privilege levels, rights, or permissions....\n\n### 5. CWE-470: Use of Externally-Controlled Input to Select Classes or Code ('Unsafe Reflection') (Score: 95.50)\n\nThe product uses external input with reflection to select which classes or code to use, but it does not sufficiently prevent the input from selecting improper classes or code....\n\n## IMPACT: 'SAFER sandbox bypass'\n\nRelevant CWEs for this IMPACT:\n\n### 1. CWE-122: Heap-based Buffer Overflow (Score: 121.01)\n\nA heap overflow condition is a buffer overflow, where the buffer that can be overwritten is allocated in the heap portion of memory, generally meaning that the buffer was allocated using a routine such as malloc()....\n\n### 2. CWE-367: Time-of-check Time-of-use (TOCTOU) Race Condition (Score: 117.37)\n\nThe product checks the state of a resource before using that resource, but the resource's state can change between the check and the use in a way that invalidates the results of the check. This can cause the product to perform invalid actions when the resource is in an unexpected state....\n\n### 3. CWE-183: Permissive List of Allowed Inputs (Score: 104.59)\n\nThe product implements a protection mechanism that relies on a list of inputs (or properties of inputs) that are explicitly allowed by policy because the inputs are assumed to be safe, but the list is too permissive - that is, it allows an input that is unsafe, leading to resultant weaknesses....\n\n### 4. CWE-653: Improper Isolation or Compartmentalization (Score: 98.32)\n\nThe product does not properly compartmentalize or isolate functionality, processes, or resources that require different privilege levels, rights, or permissions....\n\n### 5. CWE-470: Use of Externally-Controlled Input to Select Classes or Code ('Unsafe Reflection') (Score: 95.50)\n\nThe product uses external input with reflection to select which classes or code to use, but it does not sufficiently prevent the input from selecting improper classes or code....\n\n\n    # Analysis Instructions\n    1. For each keyphrase, identify the most appropriate CWE(s) that represent the weakness.\n    2. Consider how the different keyphrases might relate to each other in the vulnerability chain.\n    3. Provide a final determination of primary CWE(s) and any secondary CWEs.\n    4. Format your response using the standard analysis template.\n\n    Please analyze how these different weaknesses interact and provide a comprehensive CWE classification.\n    "
  },
  "retrieval_time": 2.35807728767395
}