{
  "cve_id": "CVE-2025-20933",
  "description": "Out-of-bounds read in parsing bmp image in Samsung Notes prior to version 4.4.26.71 allows local attackers to read out-of-bounds memory.",
  "key_phrases": {
    "rootcause": "",
    "weakness": "out-of-bounds read",
    "impact": "read out-of-bounds memory",
    "vector": "",
    "attacker": "local attackers",
    "product": "Samsung Notes",
    "version": "prior to version 4.4.26.71",
    "component": ""
  },
  "reference_content": "```text\n- Root cause of vulnerability: Out-of-bounds write in parsing bmp image.\n- Weaknesses/vulnerabilities present: Out-of-bounds write.\n- Impact of exploitation: Allows local attackers to execute arbitrary code.\n- Attack vectors: Parsing bmp image in Samsung Notes.\n- Required attacker capabilities/position: Local attackers.\n- Mitigation or fix: The patch adds proper input validation.\n```",
  "similar_info": {
    "cwe_distribution": {},
    "cwe_consensus": "",
    "similarity_stats": {
      "thresholds": [],
      "total_samples_by_threshold": {},
      "top_cwes_by_threshold": {}
    }
  },
  "similarity_summary": {
    "consensus_cwe": "",
    "top_cwes": [],
    "confidence_levels": {},
    "total_samples": 0
  },
  "analysis": "# Summary\n| CWE ID  | CWE Name                      | Confidence | CWE Abstraction Level | CWE Vulnerability Mapping Label | CWE-Vulnerability Mapping Notes |\n| :-------- | :---------------------------- | :--------- | :-------------------- | :------------------------------ | :------------------------------ |\n| CWE-125   | Out-of-bounds Read            | 1.0        | Base                  | Primary                         | Allowed                         |\n| CWE-787   | Out-of-bounds Write           | 0.8        | Base                  | Secondary                       | Allowed                         |\n\n## Evidence and Confidence\n\n*   **Confidence Score:** 0.9\n*   **Evidence Strength:** HIGH\n\n## Relationship Analysis\nThe primary relationship to consider is the co-occurrence of **out-of-bounds read** (CWE-125) and **out-of-bounds write** (CWE-787), suggesting they might be related in the vulnerability. The description indicates an **out-of-bounds read**, but the root cause in the CVE summary indicates an **out-of-bounds write**. Both CWE-125 and CWE-787 are base-level CWEs, providing an appropriate level of specificity. Both are child of the class-level CWE-119.\n\n```mermaid\ngraph TD\n    cwe125[\"CWE-125: Out-of-bounds Read\"]\n    cwe787[\"CWE-787: Out-of-bounds Write\"]\n    cwe119[\"CWE-119: Improper Restriction of Operations within the Bounds of a Memory Buffer\"]\n    \n    cwe125 -->|CHILDOF| cwe119\n    cwe787 -->|CHILDOF| cwe119\n\n    classDef primary fill:#f96,stroke:#333,stroke-width:2px\n    classDef secondary fill:#69f,stroke:#333\n    classDef tertiary fill:#9e9,stroke:#333\n    class cwe125 primary\n    class cwe787 secondary\n    class cwe119 tertiary\n```\n\n## Vulnerability Chain\nThe vulnerability chain starts with an **out-of-bounds write** (CWE-787) in parsing a BMP image. This leads to an **out-of-bounds read** (CWE-125), allowing a local attacker to read out-of-bounds memory. The **out-of-bounds write** is the root cause, while the **out-of-bounds read** is the direct weakness exploited.\n\n## Summary of Analysis\nThe initial analysis identified CWE-125 (Out-of-bounds Read) as the primary weakness based on the vulnerability description. However, the CVE Reference Links Content Summary indicated that the root cause is an **out-of-bounds write** in parsing a BMP image. Therefore, CWE-787 (Out-of-bounds Write) is included as a secondary CWE to represent the root cause, with CWE-125 remaining the primary weakness as it is what is directly described in the vulnerability. Both CWEs are at the base level, providing an appropriate level of specificity. My assessment is highly based on the provided evidence. The vulnerability description explicitly states \"**out-of-bounds read**\" and the CVE summary states \"**Root cause of vulnerability: Out-of-bounds write in parsing bmp image**\".\n\nRelevant CWE Information:\n\n# Enhanced Context (25 CWEs)\nThe following CWEs were identified as potentially relevant to this vulnerability:\n\n## CWE-125: Out-of-bounds Read\n**Abstraction Level**: Base\n**Similarity Score**: 0.67\n**Source**: dense\n\n**Description**:\nThe product reads data past the end, or before the beginning, of the intended buffer.\n\n**Mapping Guidance**:\n- Usage: Allowed\n- Rationale: This CWE entry is at the Base level of abstraction, which is a preferred level of abstraction for mapping to the root causes of vulnerabilities.\n\n**Relationships**:\n- CANFOLLOW -> CWE-825\n- CANFOLLOW -> CWE-824\n- CANFOLLOW -> CWE-823\n- CANFOLLOW -> CWE-822\n- PARENTOF -> CWE-127\n\n## CWE-787: Out-of-bounds Write\n**Abstraction Level**: base\n**Similarity Score**: 4.33\n**Source**: graph\n\n**Description**:\nCWE-787: Out-of-bounds Write\n\n**Mapping Guidance**:\n- Usage: Allowed\n- Rationale: This CWE entry is at the Base level of abstraction, which is a preferred level of abstraction for mapping to the root causes of vulnerabilities.\n\n**Relationships**:\n- CANFOLLOW -> CWE-825\n- CANFOLLOW -> CWE-824\n- CANFOLLOW -> CWE-823\n- CANFOLLOW -> CWE-822\n- PARENTOF -> CWE-124\n\n## CWE-129: Improper Validation of Array Index\n**Abstraction Level**: Variant\n**Similarity Score**: 0.64\n**Source**: dense\n\n**Description**:\nThe product uses untrusted input when calculating or using an array index, but the product does not validate or incorrectly validates the index to ensure the index references a valid position within the array.\n\n**Mapping Guidance**:\n- Usage: Allowed\n- Rationale: This CWE entry is at the Variant level of abstraction, which is a preferred level of abstraction for mapping to the root causes of vulnerabilities.\n\n**Relationships**:\n- CANPRECEDE -> CWE-789\n- CANPRECEDE -> CWE-823\n- CANPRECEDE -> CWE-119\n- CHILDOF -> CWE-20\n- CHILDOF -> CWE-1285\n\n## CWE-190: Integer Overflow or Wraparound\n**Abstraction Level**: Base\n**Similarity Score**: 536.47\n**Source**: sparse\n\n**Description**:\nThe product performs a calculation that can\n         produce an integer overflow or wraparound when the logic\n         assumes that the resulting value will always be larger than\n         the original value. This occurs when an integer value is\n         incremented to a value that is too large to store in the\n         associated representation. When this occurs, the value may\n         become a very small or negative number.\n\n**Mapping Guidance**:\n- Usage: Allowed\n- Rationale: This CWE entry is at the Base level of abstraction, which is a preferred level of abstraction for mapping to the root causes of vulnerabilities.\n\n**Relationships**:\n- PARENTOF -> CWE-680\n- CANPRECEDE -> CWE-119\n- CHILDOF -> CWE-20\n- CHILDOF -> CWE-682\n- CHILDOF -> CWE-682\n\n### Other CWEs Considered:\n\n*   CWE-129 (Improper Validation of Array Index): While an improper index could lead to the out-of-bounds read, the description doesn't explicitly state a validation issue.\n*   CWE-190 (Integer Overflow or Wraparound): Not directly related to the vulnerability, as there is no mention of integer overflow.\n*   CWE-193 (Off-by-one Error): Possible, but not enough information to confirm.\n*   CWE-122 (Heap-based Buffer Overflow): Buffer overflows can lead to out-of-bounds reads and writes, but the location of the buffer (heap) is not specified.\n*   CWE-823 (Use of Out-of-range Pointer Offset): Similar to CWE-129, but the vulnerability description doesn't explicitly mention pointer arithmetic or offsets.\n*   CWE-126 (Buffer Over-read): This is essentially synonymous with CWE-125, so CWE-125 is preferred.\n*   CWE-131 (Incorrect Calculation of Buffer Size): While related to buffer overflows, the description doesn't specify that the buffer size calculation is incorrect, so it is not considered.",
  "analysis_with_relationships": "# Summary\n| CWE ID  | CWE Name                      | Confidence | CWE Abstraction Level | CWE Vulnerability Mapping Label | CWE-Vulnerability Mapping Notes |\n| :-------- | :---------------------------- | :--------- | :-------------------- | :------------------------------ | :------------------------------ |\n| CWE-125   | Out-of-bounds Read            | 1.0        | Base                  | Primary                         | Allowed                         |\n| CWE-787   | Out-of-bounds Write           | 0.8        | Base                  | Secondary                       | Allowed                         |\n\n## Evidence and Confidence\n\n*   **Confidence Score:** 0.9\n*   **Evidence Strength:** HIGH\n\n## Relationship Analysis\nThe primary relationship to consider is the co-occurrence of **out-of-bounds read** (CWE-125) and **out-of-bounds write** (CWE-787), suggesting they might be related in the vulnerability. The description indicates an **out-of-bounds read**, but the root cause in the CVE summary indicates an **out-of-bounds write**. Both CWE-125 and CWE-787 are base-level CWEs, providing an appropriate level of specificity. Both are child of the class-level CWE-119.\n\n```mermaid\ngraph TD\n    cwe125[\"CWE-125: Out-of-bounds Read\"]\n    cwe787[\"CWE-787: Out-of-bounds Write\"]\n    cwe119[\"CWE-119: Improper Restriction of Operations within the Bounds of a Memory Buffer\"]\n    \n    cwe125 -->|CHILDOF| cwe119\n    cwe787 -->|CHILDOF| cwe119\n\n    classDef primary fill:#f96,stroke:#333,stroke-width:2px\n    classDef secondary fill:#69f,stroke:#333\n    classDef tertiary fill:#9e9,stroke:#333\n    class cwe125 primary\n    class cwe787 secondary\n    class cwe119 tertiary\n```\n\n## Vulnerability Chain\nThe vulnerability chain starts with an **out-of-bounds write** (CWE-787) in parsing a BMP image. This leads to an **out-of-bounds read** (CWE-125), allowing a local attacker to read out-of-bounds memory. The **out-of-bounds write** is the root cause, while the **out-of-bounds read** is the direct weakness exploited.\n\n## Summary of Analysis\nThe initial analysis identified CWE-125 (Out-of-bounds Read) as the primary weakness based on the vulnerability description. However, the CVE Reference Links Content Summary indicated that the root cause is an **out-of-bounds write** in parsing a BMP image. Therefore, CWE-787 (Out-of-bounds Write) is included as a secondary CWE to represent the root cause, with CWE-125 remaining the primary weakness as it is what is directly described in the vulnerability. Both CWEs are at the base level, providing an appropriate level of specificity. My assessment is highly based on the provided evidence. The vulnerability description explicitly states \"**out-of-bounds read**\" and the CVE summary states \"**Root cause of vulnerability: Out-of-bounds write in parsing bmp image**\".\n\nRelevant CWE Information:\n\n# Enhanced Context (25 CWEs)\nThe following CWEs were identified as potentially relevant to this vulnerability:\n\n## CWE-125: Out-of-bounds Read\n**Abstraction Level**: Base\n**Similarity Score**: 0.67\n**Source**: dense\n\n**Description**:\nThe product reads data past the end, or before the beginning, of the intended buffer.\n\n**Mapping Guidance**:\n- Usage: Allowed\n- Rationale: This CWE entry is at the Base level of abstraction, which is a preferred level of abstraction for mapping to the root causes of vulnerabilities.\n\n**Relationships**:\n- CANFOLLOW -> CWE-825\n- CANFOLLOW -> CWE-824\n- CANFOLLOW -> CWE-823\n- CANFOLLOW -> CWE-822\n- PARENTOF -> CWE-127\n\n## CWE-787: Out-of-bounds Write\n**Abstraction Level**: base\n**Similarity Score**: 4.33\n**Source**: graph\n\n**Description**:\nCWE-787: Out-of-bounds Write\n\n**Mapping Guidance**:\n- Usage: Allowed\n- Rationale: This CWE entry is at the Base level of abstraction, which is a preferred level of abstraction for mapping to the root causes of vulnerabilities.\n\n**Relationships**:\n- CANFOLLOW -> CWE-825\n- CANFOLLOW -> CWE-824\n- CANFOLLOW -> CWE-823\n- CANFOLLOW -> CWE-822\n- PARENTOF -> CWE-124\n\n## CWE-129: Improper Validation of Array Index\n**Abstraction Level**: Variant\n**Similarity Score**: 0.64\n**Source**: dense\n\n**Description**:\nThe product uses untrusted input when calculating or using an array index, but the product does not validate or incorrectly validates the index to ensure the index references a valid position within the array.\n\n**Mapping Guidance**:\n- Usage: Allowed\n- Rationale: This CWE entry is at the Variant level of abstraction, which is a preferred level of abstraction for mapping to the root causes of vulnerabilities.\n\n**Relationships**:\n- CANPRECEDE -> CWE-789\n- CANPRECEDE -> CWE-823\n- CANPRECEDE -> CWE-119\n- CHILDOF -> CWE-20\n- CHILDOF -> CWE-1285\n\n## CWE-190: Integer Overflow or Wraparound\n**Abstraction Level**: Base\n**Similarity Score**: 536.47\n**Source**: sparse\n\n**Description**:\nThe product performs a calculation that can\n         produce an integer overflow or wraparound when the logic\n         assumes that the resulting value will always be larger than\n         the original value. This occurs when an integer value is\n         incremented to a value that is too large to store in the\n         associated representation. When this occurs, the value may\n         become a very small or negative number.\n\n**Mapping Guidance**:\n- Usage: Allowed\n- Rationale: This CWE entry is at the Base level of abstraction, which is a preferred level of abstraction for mapping to the root causes of vulnerabilities.\n\n**Relationships**:\n- PARENTOF -> CWE-680\n- CANPRECEDE -> CWE-119\n- CHILDOF -> CWE-20\n- CHILDOF -> CWE-682\n- CHILDOF -> CWE-682\n\n### Other CWEs Considered:\n\n*   CWE-129 (Improper Validation of Array Index): While an improper index could lead to the out-of-bounds read, the description doesn't explicitly state a validation issue.\n*   CWE-190 (Integer Overflow or Wraparound): Not directly related to the vulnerability, as there is no mention of integer overflow.\n*   CWE-193 (Off-by-one Error): Possible, but not enough information to confirm.\n*   CWE-122 (Heap-based Buffer Overflow): Buffer overflows can lead to out-of-bounds reads and writes, but the location of the buffer (heap) is not specified.\n*   CWE-823 (Use of Out-of-range Pointer Offset): Similar to CWE-129, but the vulnerability description doesn't explicitly mention pointer arithmetic or offsets.\n*   CWE-126 (Buffer Over-read): This is essentially synonymous with CWE-125, so CWE-125 is preferred.\n*   CWE-131 (Incorrect Calculation of Buffer Size): While related to buffer overflows, the description doesn't specify that the buffer size calculation is incorrect, so it is not considered.\n\n\n## CWE Relationship Analysis\n\nCurrent CWEs represent these abstraction levels: .\n\n\n### Vulnerability Chain Analysis\n\n**Chain starting from CWE-127:**\n- 127 (Buffer Under-read) - ROOT\n\n\n**Chain starting from CWE-125:**\n- 125 (Out-of-bounds Read) - ROOT\n\n\n\n### CWE Relationship Diagram\n\n```mermaid\ngraph TD\n    classDef primary fill:#f96,stroke:#333,stroke-width:2px\n    classDef secondary fill:#69f,stroke:#333\n    classDef tertiary fill:#9e9,stroke:#333\n```",
  "criticism": "",
  "resolution": "",
  "relevant_cwes": [
    {
      "metadata": {
        "doc_id": "125",
        "name": "Out-of-bounds Read",
        "source": "sparse"
      },
      "similarity": 226.69993623501617
    },
    {
      "metadata": {
        "doc_id": "129",
        "name": "Improper Validation of Array Index",
        "source": "sparse"
      },
      "similarity": 209.63038700292253
    },
    {
      "metadata": {
        "doc_id": "190",
        "name": "Integer Overflow or Wraparound",
        "source": "sparse"
      },
      "similarity": 203.72926843632385
    },
    {
      "metadata": {
        "doc_id": "787",
        "name": "Out-of-bounds Write",
        "source": "sparse"
      },
      "similarity": 196.9331676980961
    },
    {
      "metadata": {
        "doc_id": "193",
        "name": "Off-by-one Error",
        "source": "sparse"
      },
      "similarity": 194.75613964827238
    },
    {
      "metadata": {
        "doc_id": "122",
        "name": "Heap-based Buffer Overflow",
        "source": "sparse"
      },
      "similarity": 194.72192610848188
    },
    {
      "metadata": {
        "doc_id": "823",
        "name": "Use of Out-of-range Pointer Offset",
        "source": "sparse"
      },
      "similarity": 187.66712050540312
    },
    {
      "metadata": {
        "doc_id": "908",
        "name": "Use of Uninitialized Resource",
        "source": "sparse"
      },
      "similarity": 187.06003266434502
    },
    {
      "metadata": {
        "doc_id": "126",
        "name": "Buffer Over-read",
        "type": "Variant",
        "original_content": "The product reads from a buffer using buffer access mechanisms such as indexes or pointers that reference memory locations after the targeted buffer.",
        "keyphrase_source": "weakness:out-of-bounds read",
        "source": "dense",
        "mapping_notes": {
          "usage": "Allowed",
          "rationale": "This CWE entry is at the Variant level of abstraction, which is a preferred level of abstraction for mapping to the root causes of vulnerabilities.",
          "comments": "Carefully read both the name and description to ensure that this mapping is an appropriate fit. Do not try to 'force' a mapping to a lower-level Base/Variant simply to comply with this preferred level of abstraction.",
          "reasons": [
            "Acceptable-Use"
          ]
        },
        "score_info": {
          "retrievers": [
            "dense",
            "graph"
          ],
          "retriever_count": 2,
          "normalized_scores": {
            "dense": 0.5339191288408288,
            "graph": 2.3185631760322662
          }
        }
      },
      "similarity": 0.5339191288408288
    },
    {
      "doc_id": "128",
      "text": "CWE-128: Wrap-around Error",
      "score": 2.3868000000000005,
      "metadata": {
        "doc_id": "128",
        "name": "Wrap-around Error",
        "type": "base",
        "original_content": "CWE-128: Wrap-around Error",
        "relationships": [
          {
            "source_id": "128",
            "target_id": "190",
            "label": "PEEROF",
            "properties": {
              "view_id": "1000"
            }
          },
          {
            "source_id": "128",
            "target_id": "119",
            "label": "CANPRECEDE",
            "properties": {
              "view_id": "1000"
            }
          },
          {
            "source_id": "128",
            "target_id": "682",
            "label": "CHILDOF",
            "properties": {
              "ordinal": "Primary",
              "view_id": "1000"
            }
          },
          {
            "source_id": "682",
            "target_id": "128",
            "label": "PARENTOF",
            "properties": {
              "ordinal": "Primary",
              "view_id": "1000"
            }
          },
          {
            "source_id": "119",
            "target_id": "128",
            "label": "CANFOLLOW",
            "properties": {
              "view_id": "1000"
            }
          }
        ],
        "score_components": {
          "relationship_chain": 0.8,
          "sequence_path": 0.7200000000000001,
          "peer_group": 0.9
        },
        "abstraction_factor": 1.3,
        "graph_path_info": {
          "path_types": [
            "relationship_chain",
            "vulnerability_sequence_forward",
            "peer_relationship"
          ],
          "best_paths": {
            "relationship_chain": {
              "path": [
                [
                  "823",
                  "119",
                  "CHILDOF"
                ],
                [
                  "119",
                  "128",
                  "CANFOLLOW"
                ]
              ],
              "score": 0.8,
              "type": "relationship_chain",
              "source": "823"
            },
            "vulnerability_sequence_forward": {
              "path": [
                [
                  "129",
                  "119",
                  "CANPRECEDE"
                ],
                [
                  "119",
                  "128",
                  "CANFOLLOW"
                ]
              ],
              "score": 0.7200000000000001,
              "type": "vulnerability_sequence_forward",
              "source": "129"
            },
            "peer_relationship": {
              "path": [
                [
                  "128",
                  "190",
                  "PEEROF"
                ]
              ],
              "score": 0.9,
              "type": "peer_relationship",
              "source": "190"
            }
          }
        },
        "position": "after",
        "sources": [
          "graph"
        ],
        "source": "graph",
        "mapping_notes": {
          "usage": "Allowed",
          "rationale": "This CWE entry is at the Base level of abstraction, which is a preferred level of abstraction for mapping to the root causes of vulnerabilities.",
          "comments": "Carefully read both the name and description to ensure that this mapping is an appropriate fit. Do not try to 'force' a mapping to a lower-level Base/Variant simply to comply with this preferred level of abstraction.",
          "reasons": [
            "Acceptable-Use"
          ]
        },
        "score_info": {
          "retrievers": [
            "graph"
          ],
          "retriever_count": 1,
          "normalized_scores": {
            "graph": 2.3868000000000005
          }
        }
      },
      "similarity": 2.3868000000000005
    }
  ],
  "identified_cwes": {
    "analyzer": [
      "CWE-127",
      "CWE-125",
      "CWE-682",
      "CWE-787",
      "CWE-131",
      "CWE-193",
      "CWE-126",
      "CWE-20",
      "CWE-129",
      "CWE-823",
      "CWE-1285",
      "CWE-825",
      "CWE-122",
      "CWE-824",
      "CWE-789",
      "CWE-124",
      "CWE-190",
      "CWE-822",
      "CWE-680",
      "CWE-119"
    ],
    "critic_additional": []
  },
  "keyphrase_cwe_mapping": {}
}