{
  "vulnerability_info": "VulnerabilityInfo(cve_id='CVE-2025-43708', description='VisiCut 2.1 allows **stack consumption via an XML document with nested set elements**, as demonstrated by a java.util.HashMap **StackOverflowError** when reference=../../../set/set[2] is used, aka an **insecure **deserialization**** issue.', key_phrases={'rootcause': ['stack consumption via an XML document with nested set elements', 'insecure deserialization'], 'weakness': ['StackOverflowError', 'deserialization'], 'impact': '', 'vector': 'XML document with nested set elements', 'attacker': '', 'product': 'VisiCut', 'version': '2.1', 'component': ''}, reference_content='CVE-2025-43708 relates to a stack overflow vulnerability in VisiCut version 2.1 due to insecure deserialization. Here\\'s the extracted information from the provided content:\\n\\n**Root cause of vulnerability:** Insecure Deserialization\\n\\n**Weaknesses/vulnerabilities present:** Stack Overflow\\n\\n**Impact of exploitation:** The stack overflow vulnerability occurs, potentially leading to denial of service or arbitrary code execution (though the provided content doesn\\'t explicitly state code execution).  The application becomes unusable after triggering the vulnerability repeatedly.\\n\\n**Attack vectors:**\\n1.  Create a specially crafted `settings.xml` file containing a nested set structure designed to exploit the deserialization process.\\n2.  Package the `settings.xml` file within a folder named \"settings\" into a zip file.\\n3.  Upload the zip file to VisiCut via the \"FromFile\" option.\\n\\n**Required attacker capabilities/position:** The attacker needs to be able to provide a malicious zip file to the VisiCut application.  Local access is sufficient.\\n\\n**Mitigation or fix:** The content does not provide a specific fix, but implies updating to a version beyond 2.1 would resolve the issue.\\n\\n**Additional details (more detail than official CVE description):**\\n\\n*   The provided content includes a sample `settings.xml` payload that triggers the vulnerability.\\n*   Screenshots demonstrate the stack overflow occurring within the application.\\n*   The vulnerability affects versions up to and including v2.1 (latest stable release as of the provided information).\\n*   The exploit involves uploading a zip file containing a malicious XML configuration file.', similar_info={'cwe_distribution': {}, 'cwe_consensus': '', 'similarity_stats': {'thresholds': [], 'total_samples_by_threshold': {}, 'top_cwes_by_threshold': {}}}, similarity_summary=SimilarityInsight(consensus_cwe='', top_cwes=[], confidence_levels={}, total_samples=0), analysis='', analysis_with_relationships='', criticism='', resolution='', relevant_cwes=[{'metadata': {'doc_id': '674', 'name': 'Uncontrolled Recursion', 'source': 'sparse', 'original_content': 'The product does not properly control the amount of recursion that takes place,  consuming excessive resources, such as allocated memory or the program stack.', 'keyphrase_sources': [{'id': 'rootcause:stack consumption via an XML document with nested set elements', 'keyphrase': 'stack consumption via an XML document with nested set elements', 'type': 'rootcause'}, {'id': 'rootcause:insecure deserialization', 'keyphrase': 'insecure deserialization', 'type': 'rootcause'}, {'id': 'weakness:StackOverflowError', 'keyphrase': 'StackOverflowError', 'type': 'weakness'}, {'id': 'weakness:deserialization', 'keyphrase': 'deserialization', 'type': 'weakness'}, {'id': 'vector:XML document with nested set elements', 'keyphrase': 'XML document with nested set elements', 'type': 'vector'}, {'id': 'product:VisiCut', 'keyphrase': 'VisiCut', 'type': 'product'}, {'id': 'version:2.1', 'keyphrase': '2.1', 'type': 'version'}]}, 'similarity': np.float64(367.24823637363505)}, {'metadata': {'doc_id': '776', 'name': \"Improper Restriction of Recursive Entity References in DTDs ('XML Entity Expansion')\", 'source': 'sparse', 'original_content': 'The product uses XML documents and allows their structure to be defined with a Document Type Definition (DTD), but it does not properly control the number of recursive definitions of entities.', 'keyphrase_sources': [{'id': 'rootcause:stack consumption via an XML document with nested set elements', 'keyphrase': 'stack consumption via an XML document with nested set elements', 'type': 'rootcause'}, {'id': 'weakness:StackOverflowError', 'keyphrase': 'StackOverflowError', 'type': 'weakness'}, {'id': 'vector:XML document with nested set elements', 'keyphrase': 'XML document with nested set elements', 'type': 'vector'}, {'id': 'product:VisiCut', 'keyphrase': 'VisiCut', 'type': 'product'}, {'id': 'version:2.1', 'keyphrase': '2.1', 'type': 'version'}]}, 'similarity': np.float64(331.5010628863387)}, {'metadata': {'doc_id': '407', 'name': 'Inefficient Algorithmic Complexity', 'source': 'sparse', 'original_content': 'An algorithm in a product has an inefficient worst-case computational complexity that may be detrimental to system performance and can be triggered by an attacker, typically using crafted manipulations that ensure that the worst case is being reached.', 'keyphrase_sources': [{'id': 'rootcause:stack consumption via an XML document with nested set elements', 'keyphrase': 'stack consumption via an XML document with nested set elements', 'type': 'rootcause'}, {'id': 'weakness:StackOverflowError', 'keyphrase': 'StackOverflowError', 'type': 'weakness'}, {'id': 'weakness:deserialization', 'keyphrase': 'deserialization', 'type': 'weakness'}, {'id': 'product:VisiCut', 'keyphrase': 'VisiCut', 'type': 'product'}, {'id': 'version:2.1', 'keyphrase': '2.1', 'type': 'version'}]}, 'similarity': np.float64(270.98648669471316)}, {'metadata': {'doc_id': '835', 'name': \"Loop with Unreachable Exit Condition ('Infinite Loop')\", 'source': 'sparse', 'original_content': 'The product contains an iteration or loop with an exit condition that cannot be reached, i.e., an infinite loop.', 'keyphrase_sources': [{'id': 'rootcause:stack consumption via an XML document with nested set elements', 'keyphrase': 'stack consumption via an XML document with nested set elements', 'type': 'rootcause'}]}, 'similarity': np.float64(266.0724310804057)}, {'metadata': {'doc_id': '611', 'name': 'Improper Restriction of XML External Entity Reference', 'source': 'sparse', 'original_content': 'The product processes an XML document that can contain XML entities with URIs that resolve to documents outside of the intended sphere of control, causing the product to embed incorrect documents into its output.', 'keyphrase_sources': [{'id': 'rootcause:stack consumption via an XML document with nested set elements', 'keyphrase': 'stack consumption via an XML document with nested set elements', 'type': 'rootcause'}, {'id': 'weakness:StackOverflowError', 'keyphrase': 'StackOverflowError', 'type': 'weakness'}, {'id': 'vector:XML document with nested set elements', 'keyphrase': 'XML document with nested set elements', 'type': 'vector'}, {'id': 'product:VisiCut', 'keyphrase': 'VisiCut', 'type': 'product'}, {'id': 'version:2.1', 'keyphrase': '2.1', 'type': 'version'}]}, 'similarity': np.float64(253.45598697861737)}, {'metadata': {'doc_id': '502', 'name': 'Deserialization of Untrusted Data', 'source': 'sparse', 'original_content': 'The product deserializes untrusted data without sufficiently ensuring that the resulting data will be valid.', 'keyphrase_sources': [{'id': 'rootcause:insecure deserialization', 'keyphrase': 'insecure deserialization', 'type': 'rootcause'}, {'id': 'weakness:StackOverflowError', 'keyphrase': 'StackOverflowError', 'type': 'weakness'}, {'id': 'weakness:deserialization', 'keyphrase': 'deserialization', 'type': 'weakness'}, {'id': 'product:VisiCut', 'keyphrase': 'VisiCut', 'type': 'product'}, {'id': 'version:2.1', 'keyphrase': '2.1', 'type': 'version'}]}, 'similarity': np.float64(207.85975046587646)}, {'metadata': {'doc_id': '378', 'name': 'Creation of Temporary File With Insecure Permissions', 'source': 'sparse', 'original_content': 'Opening temporary files without appropriate measures or controls can leave the file, its contents and any function that it impacts vulnerable to attack.', 'keyphrase_sources': [{'id': 'rootcause:insecure deserialization', 'keyphrase': 'insecure deserialization', 'type': 'rootcause'}]}, 'similarity': np.float64(169.4574083520488)}, {'metadata': {'doc_id': '639', 'name': 'Authorization Bypass Through User-Controlled Key', 'source': 'sparse', 'original_content': \"The system's authorization functionality does not prevent one user from gaining access to another user's data or record by modifying the key value identifying the data.\", 'keyphrase_sources': [{'id': 'rootcause:insecure deserialization', 'keyphrase': 'insecure deserialization', 'type': 'rootcause'}]}, 'similarity': np.float64(168.1867147757289)}, {'metadata': {'doc_id': '183', 'name': 'Permissive List of Allowed Inputs', 'source': 'sparse', 'original_content': 'The product implements a protection mechanism that relies on a list of inputs (or properties of inputs) that are explicitly allowed by policy because the inputs are assumed to be safe, but the list is too permissive - that is, it allows an input that is unsafe, leading to resultant weaknesses.', 'keyphrase_sources': [{'id': 'rootcause:insecure deserialization', 'keyphrase': 'insecure deserialization', 'type': 'rootcause'}, {'id': 'weakness:deserialization', 'keyphrase': 'deserialization', 'type': 'weakness'}]}, 'similarity': np.float64(163.45730531967695)}, {'metadata': {'doc_id': '917', 'name': \"Improper Neutralization of Special Elements used in an Expression Language Statement ('Expression Language Injection')\", 'source': 'sparse', 'original_content': 'The product constructs all or part of an expression language (EL) statement in a framework such as a Java Server Page (JSP) using externally-influenced input from an upstream component, but it does not neutralize or incorrectly neutralizes special elements that could modify the intended EL statement before it is executed.', 'keyphrase_sources': [{'id': 'weakness:deserialization', 'keyphrase': 'deserialization', 'type': 'weakness'}]}, 'similarity': np.float64(148.33107238018536)}, {'metadata': {'doc_id': '112', 'name': 'Missing XML Validation', 'source': 'sparse', 'original_content': 'The product accepts XML from an untrusted source but does not validate the XML against the proper schema.', 'keyphrase_sources': [{'id': 'vector:XML document with nested set elements', 'keyphrase': 'XML document with nested set elements', 'type': 'vector'}]}, 'similarity': np.float64(75.07862761230726)}, {'metadata': {'doc_id': '116', 'name': 'Improper Encoding or Escaping of Output', 'source': 'sparse', 'original_content': 'The product prepares a structured message for communication with another component, but encoding or escaping of the data is either missing or done incorrectly. As a result, the intended structure of the message is not preserved.', 'keyphrase_sources': [{'id': 'vector:XML document with nested set elements', 'keyphrase': 'XML document with nested set elements', 'type': 'vector'}]}, 'similarity': np.float64(72.60747574227199)}], identified_cwes={'analyzer': [], 'critic_additional': []})",
  "retrieval_results": {
    "has_multiple_keyphrases": true,
    "keyphrase_cwe_sets": {
      "rootcause:stack consumption via an XML document with nested set elements": {
        "keyphrase": "stack consumption via an XML document with nested set elements",
        "type": "rootcause",
        "cwes": [
          {
            "metadata": {
              "doc_id": "674",
              "name": "Uncontrolled Recursion",
              "source": "sparse",
              "original_content": "The product does not properly control the amount of recursion that takes place,  consuming excessive resources, such as allocated memory or the program stack.",
              "keyphrase_sources": [
                {
                  "id": "rootcause:stack consumption via an XML document with nested set elements",
                  "keyphrase": "stack consumption via an XML document with nested set elements",
                  "type": "rootcause"
                },
                {
                  "id": "rootcause:insecure deserialization",
                  "keyphrase": "insecure deserialization",
                  "type": "rootcause"
                },
                {
                  "id": "weakness:StackOverflowError",
                  "keyphrase": "StackOverflowError",
                  "type": "weakness"
                },
                {
                  "id": "weakness:deserialization",
                  "keyphrase": "deserialization",
                  "type": "weakness"
                },
                {
                  "id": "vector:XML document with nested set elements",
                  "keyphrase": "XML document with nested set elements",
                  "type": "vector"
                },
                {
                  "id": "product:VisiCut",
                  "keyphrase": "VisiCut",
                  "type": "product"
                },
                {
                  "id": "version:2.1",
                  "keyphrase": "2.1",
                  "type": "version"
                }
              ]
            },
            "similarity": 367.24823637363505
          },
          {
            "metadata": {
              "doc_id": "776",
              "name": "Improper Restriction of Recursive Entity References in DTDs ('XML Entity Expansion')",
              "source": "sparse",
              "original_content": "The product uses XML documents and allows their structure to be defined with a Document Type Definition (DTD), but it does not properly control the number of recursive definitions of entities.",
              "keyphrase_sources": [
                {
                  "id": "rootcause:stack consumption via an XML document with nested set elements",
                  "keyphrase": "stack consumption via an XML document with nested set elements",
                  "type": "rootcause"
                },
                {
                  "id": "weakness:StackOverflowError",
                  "keyphrase": "StackOverflowError",
                  "type": "weakness"
                },
                {
                  "id": "vector:XML document with nested set elements",
                  "keyphrase": "XML document with nested set elements",
                  "type": "vector"
                },
                {
                  "id": "product:VisiCut",
                  "keyphrase": "VisiCut",
                  "type": "product"
                },
                {
                  "id": "version:2.1",
                  "keyphrase": "2.1",
                  "type": "version"
                }
              ]
            },
            "similarity": 331.5010628863387
          },
          {
            "metadata": {
              "doc_id": "407",
              "name": "Inefficient Algorithmic Complexity",
              "source": "sparse",
              "original_content": "An algorithm in a product has an inefficient worst-case computational complexity that may be detrimental to system performance and can be triggered by an attacker, typically using crafted manipulations that ensure that the worst case is being reached.",
              "keyphrase_sources": [
                {
                  "id": "rootcause:stack consumption via an XML document with nested set elements",
                  "keyphrase": "stack consumption via an XML document with nested set elements",
                  "type": "rootcause"
                },
                {
                  "id": "weakness:StackOverflowError",
                  "keyphrase": "StackOverflowError",
                  "type": "weakness"
                },
                {
                  "id": "weakness:deserialization",
                  "keyphrase": "deserialization",
                  "type": "weakness"
                },
                {
                  "id": "product:VisiCut",
                  "keyphrase": "VisiCut",
                  "type": "product"
                },
                {
                  "id": "version:2.1",
                  "keyphrase": "2.1",
                  "type": "version"
                }
              ]
            },
            "similarity": 270.98648669471316
          },
          {
            "metadata": {
              "doc_id": "835",
              "name": "Loop with Unreachable Exit Condition ('Infinite Loop')",
              "source": "sparse",
              "original_content": "The product contains an iteration or loop with an exit condition that cannot be reached, i.e., an infinite loop.",
              "keyphrase_sources": [
                {
                  "id": "rootcause:stack consumption via an XML document with nested set elements",
                  "keyphrase": "stack consumption via an XML document with nested set elements",
                  "type": "rootcause"
                }
              ]
            },
            "similarity": 266.0724310804057
          },
          {
            "metadata": {
              "doc_id": "611",
              "name": "Improper Restriction of XML External Entity Reference",
              "source": "sparse",
              "original_content": "The product processes an XML document that can contain XML entities with URIs that resolve to documents outside of the intended sphere of control, causing the product to embed incorrect documents into its output.",
              "keyphrase_sources": [
                {
                  "id": "rootcause:stack consumption via an XML document with nested set elements",
                  "keyphrase": "stack consumption via an XML document with nested set elements",
                  "type": "rootcause"
                },
                {
                  "id": "weakness:StackOverflowError",
                  "keyphrase": "StackOverflowError",
                  "type": "weakness"
                },
                {
                  "id": "vector:XML document with nested set elements",
                  "keyphrase": "XML document with nested set elements",
                  "type": "vector"
                },
                {
                  "id": "product:VisiCut",
                  "keyphrase": "VisiCut",
                  "type": "product"
                },
                {
                  "id": "version:2.1",
                  "keyphrase": "2.1",
                  "type": "version"
                }
              ]
            },
            "similarity": 253.45598697861737
          }
        ]
      },
      "rootcause:insecure deserialization": {
        "keyphrase": "insecure deserialization",
        "type": "rootcause",
        "cwes": [
          {
            "metadata": {
              "doc_id": "674",
              "name": "Uncontrolled Recursion",
              "source": "sparse",
              "original_content": "The product does not properly control the amount of recursion that takes place,  consuming excessive resources, such as allocated memory or the program stack."
            },
            "similarity": 208.54500096570268
          },
          {
            "metadata": {
              "doc_id": "502",
              "name": "Deserialization of Untrusted Data",
              "source": "sparse",
              "original_content": "The product deserializes untrusted data without sufficiently ensuring that the resulting data will be valid.",
              "keyphrase_sources": [
                {
                  "id": "rootcause:insecure deserialization",
                  "keyphrase": "insecure deserialization",
                  "type": "rootcause"
                },
                {
                  "id": "weakness:StackOverflowError",
                  "keyphrase": "StackOverflowError",
                  "type": "weakness"
                },
                {
                  "id": "weakness:deserialization",
                  "keyphrase": "deserialization",
                  "type": "weakness"
                },
                {
                  "id": "product:VisiCut",
                  "keyphrase": "VisiCut",
                  "type": "product"
                },
                {
                  "id": "version:2.1",
                  "keyphrase": "2.1",
                  "type": "version"
                }
              ]
            },
            "similarity": 207.85975046587646
          },
          {
            "metadata": {
              "doc_id": "378",
              "name": "Creation of Temporary File With Insecure Permissions",
              "source": "sparse",
              "original_content": "Opening temporary files without appropriate measures or controls can leave the file, its contents and any function that it impacts vulnerable to attack.",
              "keyphrase_sources": [
                {
                  "id": "rootcause:insecure deserialization",
                  "keyphrase": "insecure deserialization",
                  "type": "rootcause"
                }
              ]
            },
            "similarity": 169.4574083520488
          },
          {
            "metadata": {
              "doc_id": "639",
              "name": "Authorization Bypass Through User-Controlled Key",
              "source": "sparse",
              "original_content": "The system's authorization functionality does not prevent one user from gaining access to another user's data or record by modifying the key value identifying the data.",
              "keyphrase_sources": [
                {
                  "id": "rootcause:insecure deserialization",
                  "keyphrase": "insecure deserialization",
                  "type": "rootcause"
                }
              ]
            },
            "similarity": 168.1867147757289
          },
          {
            "metadata": {
              "doc_id": "183",
              "name": "Permissive List of Allowed Inputs",
              "source": "sparse",
              "original_content": "The product implements a protection mechanism that relies on a list of inputs (or properties of inputs) that are explicitly allowed by policy because the inputs are assumed to be safe, but the list is too permissive - that is, it allows an input that is unsafe, leading to resultant weaknesses.",
              "keyphrase_sources": [
                {
                  "id": "rootcause:insecure deserialization",
                  "keyphrase": "insecure deserialization",
                  "type": "rootcause"
                },
                {
                  "id": "weakness:deserialization",
                  "keyphrase": "deserialization",
                  "type": "weakness"
                }
              ]
            },
            "similarity": 163.45730531967695
          }
        ]
      },
      "weakness:StackOverflowError": {
        "keyphrase": "StackOverflowError",
        "type": "weakness",
        "cwes": [
          {
            "metadata": {
              "doc_id": "674",
              "name": "Uncontrolled Recursion",
              "source": "sparse",
              "original_content": "The product does not properly control the amount of recursion that takes place,  consuming excessive resources, such as allocated memory or the program stack."
            },
            "similarity": 216.71236776956962
          },
          {
            "metadata": {
              "doc_id": "407",
              "name": "Inefficient Algorithmic Complexity",
              "source": "sparse",
              "original_content": "An algorithm in a product has an inefficient worst-case computational complexity that may be detrimental to system performance and can be triggered by an attacker, typically using crafted manipulations that ensure that the worst case is being reached."
            },
            "similarity": 147.13220927969172
          },
          {
            "metadata": {
              "doc_id": "776",
              "name": "Improper Restriction of Recursive Entity References in DTDs ('XML Entity Expansion')",
              "source": "sparse",
              "original_content": "The product uses XML documents and allows their structure to be defined with a Document Type Definition (DTD), but it does not properly control the number of recursive definitions of entities."
            },
            "similarity": 137.86312054033831
          },
          {
            "metadata": {
              "doc_id": "502",
              "name": "Deserialization of Untrusted Data",
              "source": "sparse",
              "original_content": "The product deserializes untrusted data without sufficiently ensuring that the resulting data will be valid."
            },
            "similarity": 136.41646554608434
          },
          {
            "metadata": {
              "doc_id": "611",
              "name": "Improper Restriction of XML External Entity Reference",
              "source": "sparse",
              "original_content": "The product processes an XML document that can contain XML entities with URIs that resolve to documents outside of the intended sphere of control, causing the product to embed incorrect documents into its output."
            },
            "similarity": 134.25735237834675
          }
        ]
      },
      "weakness:deserialization": {
        "keyphrase": "deserialization",
        "type": "weakness",
        "cwes": [
          {
            "metadata": {
              "doc_id": "674",
              "name": "Uncontrolled Recursion",
              "source": "sparse",
              "original_content": "The product does not properly control the amount of recursion that takes place,  consuming excessive resources, such as allocated memory or the program stack."
            },
            "similarity": 194.64200090132252
          },
          {
            "metadata": {
              "doc_id": "502",
              "name": "Deserialization of Untrusted Data",
              "source": "sparse",
              "original_content": "The product deserializes untrusted data without sufficiently ensuring that the resulting data will be valid."
            },
            "similarity": 188.6234618157771
          },
          {
            "metadata": {
              "doc_id": "183",
              "name": "Permissive List of Allowed Inputs",
              "source": "sparse",
              "original_content": "The product implements a protection mechanism that relies on a list of inputs (or properties of inputs) that are explicitly allowed by policy because the inputs are assumed to be safe, but the list is too permissive - that is, it allows an input that is unsafe, leading to resultant weaknesses."
            },
            "similarity": 152.5601516316985
          },
          {
            "metadata": {
              "doc_id": "917",
              "name": "Improper Neutralization of Special Elements used in an Expression Language Statement ('Expression Language Injection')",
              "source": "sparse",
              "original_content": "The product constructs all or part of an expression language (EL) statement in a framework such as a Java Server Page (JSP) using externally-influenced input from an upstream component, but it does not neutralize or incorrectly neutralizes special elements that could modify the intended EL statement before it is executed.",
              "keyphrase_sources": [
                {
                  "id": "weakness:deserialization",
                  "keyphrase": "deserialization",
                  "type": "weakness"
                }
              ]
            },
            "similarity": 148.33107238018536
          },
          {
            "metadata": {
              "doc_id": "407",
              "name": "Inefficient Algorithmic Complexity",
              "source": "sparse",
              "original_content": "An algorithm in a product has an inefficient worst-case computational complexity that may be detrimental to system performance and can be triggered by an attacker, typically using crafted manipulations that ensure that the worst case is being reached."
            },
            "similarity": 147.13220927969172
          }
        ]
      },
      "vector:XML document with nested set elements": {
        "keyphrase": "XML document with nested set elements",
        "type": "vector",
        "cwes": [
          {
            "metadata": {
              "doc_id": "674",
              "name": "Uncontrolled Recursion",
              "source": "sparse",
              "original_content": "The product does not properly control the amount of recursion that takes place,  consuming excessive resources, such as allocated memory or the program stack."
            },
            "similarity": 96.86846839398787
          },
          {
            "metadata": {
              "doc_id": "776",
              "name": "Improper Restriction of Recursive Entity References in DTDs ('XML Entity Expansion')",
              "source": "sparse",
              "original_content": "The product uses XML documents and allows their structure to be defined with a Document Type Definition (DTD), but it does not properly control the number of recursive definitions of entities."
            },
            "similarity": 89.40125705514848
          },
          {
            "metadata": {
              "doc_id": "611",
              "name": "Improper Restriction of XML External Entity Reference",
              "source": "sparse",
              "original_content": "The product processes an XML document that can contain XML entities with URIs that resolve to documents outside of the intended sphere of control, causing the product to embed incorrect documents into its output."
            },
            "similarity": 75.88591017455747
          },
          {
            "metadata": {
              "doc_id": "112",
              "name": "Missing XML Validation",
              "source": "sparse",
              "original_content": "The product accepts XML from an untrusted source but does not validate the XML against the proper schema.",
              "keyphrase_sources": [
                {
                  "id": "vector:XML document with nested set elements",
                  "keyphrase": "XML document with nested set elements",
                  "type": "vector"
                }
              ]
            },
            "similarity": 75.07862761230726
          },
          {
            "metadata": {
              "doc_id": "116",
              "name": "Improper Encoding or Escaping of Output",
              "source": "sparse",
              "original_content": "The product prepares a structured message for communication with another component, but encoding or escaping of the data is either missing or done incorrectly. As a result, the intended structure of the message is not preserved.",
              "keyphrase_sources": [
                {
                  "id": "vector:XML document with nested set elements",
                  "keyphrase": "XML document with nested set elements",
                  "type": "vector"
                }
              ]
            },
            "similarity": 72.60747574227199
          }
        ]
      },
      "product:VisiCut": {
        "keyphrase": "VisiCut",
        "type": "product",
        "cwes": [
          {
            "metadata": {
              "doc_id": "674",
              "name": "Uncontrolled Recursion",
              "source": "sparse",
              "original_content": "The product does not properly control the amount of recursion that takes place,  consuming excessive resources, such as allocated memory or the program stack."
            },
            "similarity": 69.5150003219009
          },
          {
            "metadata": {
              "doc_id": "407",
              "name": "Inefficient Algorithmic Complexity",
              "source": "sparse",
              "original_content": "An algorithm in a product has an inefficient worst-case computational complexity that may be detrimental to system performance and can be triggered by an attacker, typically using crafted manipulations that ensure that the worst case is being reached."
            },
            "similarity": 52.547217599889905
          },
          {
            "metadata": {
              "doc_id": "776",
              "name": "Improper Restriction of Recursive Entity References in DTDs ('XML Entity Expansion')",
              "source": "sparse",
              "original_content": "The product uses XML documents and allows their structure to be defined with a Document Type Definition (DTD), but it does not properly control the number of recursive definitions of entities."
            },
            "similarity": 49.236828764406546
          },
          {
            "metadata": {
              "doc_id": "502",
              "name": "Deserialization of Untrusted Data",
              "source": "sparse",
              "original_content": "The product deserializes untrusted data without sufficiently ensuring that the resulting data will be valid."
            },
            "similarity": 48.7201662664587
          },
          {
            "metadata": {
              "doc_id": "611",
              "name": "Improper Restriction of XML External Entity Reference",
              "source": "sparse",
              "original_content": "The product processes an XML document that can contain XML entities with URIs that resolve to documents outside of the intended sphere of control, causing the product to embed incorrect documents into its output."
            },
            "similarity": 47.94905442083813
          }
        ]
      },
      "version:2.1": {
        "keyphrase": "2.1",
        "type": "version",
        "cwes": [
          {
            "metadata": {
              "doc_id": "674",
              "name": "Uncontrolled Recursion",
              "source": "sparse",
              "original_content": "The product does not properly control the amount of recursion that takes place,  consuming excessive resources, such as allocated memory or the program stack."
            },
            "similarity": 73.26168883033789
          },
          {
            "metadata": {
              "doc_id": "407",
              "name": "Inefficient Algorithmic Complexity",
              "source": "sparse",
              "original_content": "An algorithm in a product has an inefficient worst-case computational complexity that may be detrimental to system performance and can be triggered by an attacker, typically using crafted manipulations that ensure that the worst case is being reached."
            },
            "similarity": 55.71931912415485
          },
          {
            "metadata": {
              "doc_id": "776",
              "name": "Improper Restriction of Recursive Entity References in DTDs ('XML Entity Expansion')",
              "source": "sparse",
              "original_content": "The product uses XML documents and allows their structure to be defined with a Document Type Definition (DTD), but it does not properly control the number of recursive definitions of entities."
            },
            "similarity": 52.61867833297955
          },
          {
            "metadata": {
              "doc_id": "502",
              "name": "Deserialization of Untrusted Data",
              "source": "sparse",
              "original_content": "The product deserializes untrusted data without sufficiently ensuring that the resulting data will be valid."
            },
            "similarity": 52.44199750821304
          },
          {
            "metadata": {
              "doc_id": "611",
              "name": "Improper Restriction of XML External Entity Reference",
              "source": "sparse",
              "original_content": "The product processes an XML document that can contain XML entities with URIs that resolve to documents outside of the intended sphere of control, causing the product to embed incorrect documents into its output."
            },
            "similarity": 51.34156961356866
          }
        ]
      }
    },
    "keyphrase_mapping": {
      "674": [
        {
          "id": "rootcause:stack consumption via an XML document with nested set elements",
          "keyphrase": "stack consumption via an XML document with nested set elements",
          "type": "rootcause"
        },
        {
          "id": "rootcause:insecure deserialization",
          "keyphrase": "insecure deserialization",
          "type": "rootcause"
        },
        {
          "id": "weakness:StackOverflowError",
          "keyphrase": "StackOverflowError",
          "type": "weakness"
        },
        {
          "id": "weakness:deserialization",
          "keyphrase": "deserialization",
          "type": "weakness"
        },
        {
          "id": "vector:XML document with nested set elements",
          "keyphrase": "XML document with nested set elements",
          "type": "vector"
        },
        {
          "id": "product:VisiCut",
          "keyphrase": "VisiCut",
          "type": "product"
        },
        {
          "id": "version:2.1",
          "keyphrase": "2.1",
          "type": "version"
        }
      ],
      "776": [
        {
          "id": "rootcause:stack consumption via an XML document with nested set elements",
          "keyphrase": "stack consumption via an XML document with nested set elements",
          "type": "rootcause"
        },
        {
          "id": "weakness:StackOverflowError",
          "keyphrase": "StackOverflowError",
          "type": "weakness"
        },
        {
          "id": "vector:XML document with nested set elements",
          "keyphrase": "XML document with nested set elements",
          "type": "vector"
        },
        {
          "id": "product:VisiCut",
          "keyphrase": "VisiCut",
          "type": "product"
        },
        {
          "id": "version:2.1",
          "keyphrase": "2.1",
          "type": "version"
        }
      ],
      "407": [
        {
          "id": "rootcause:stack consumption via an XML document with nested set elements",
          "keyphrase": "stack consumption via an XML document with nested set elements",
          "type": "rootcause"
        },
        {
          "id": "weakness:StackOverflowError",
          "keyphrase": "StackOverflowError",
          "type": "weakness"
        },
        {
          "id": "weakness:deserialization",
          "keyphrase": "deserialization",
          "type": "weakness"
        },
        {
          "id": "product:VisiCut",
          "keyphrase": "VisiCut",
          "type": "product"
        },
        {
          "id": "version:2.1",
          "keyphrase": "2.1",
          "type": "version"
        }
      ],
      "835": [
        {
          "id": "rootcause:stack consumption via an XML document with nested set elements",
          "keyphrase": "stack consumption via an XML document with nested set elements",
          "type": "rootcause"
        }
      ],
      "611": [
        {
          "id": "rootcause:stack consumption via an XML document with nested set elements",
          "keyphrase": "stack consumption via an XML document with nested set elements",
          "type": "rootcause"
        },
        {
          "id": "weakness:StackOverflowError",
          "keyphrase": "StackOverflowError",
          "type": "weakness"
        },
        {
          "id": "vector:XML document with nested set elements",
          "keyphrase": "XML document with nested set elements",
          "type": "vector"
        },
        {
          "id": "product:VisiCut",
          "keyphrase": "VisiCut",
          "type": "product"
        },
        {
          "id": "version:2.1",
          "keyphrase": "2.1",
          "type": "version"
        }
      ],
      "502": [
        {
          "id": "rootcause:insecure deserialization",
          "keyphrase": "insecure deserialization",
          "type": "rootcause"
        },
        {
          "id": "weakness:StackOverflowError",
          "keyphrase": "StackOverflowError",
          "type": "weakness"
        },
        {
          "id": "weakness:deserialization",
          "keyphrase": "deserialization",
          "type": "weakness"
        },
        {
          "id": "product:VisiCut",
          "keyphrase": "VisiCut",
          "type": "product"
        },
        {
          "id": "version:2.1",
          "keyphrase": "2.1",
          "type": "version"
        }
      ],
      "378": [
        {
          "id": "rootcause:insecure deserialization",
          "keyphrase": "insecure deserialization",
          "type": "rootcause"
        }
      ],
      "639": [
        {
          "id": "rootcause:insecure deserialization",
          "keyphrase": "insecure deserialization",
          "type": "rootcause"
        }
      ],
      "183": [
        {
          "id": "rootcause:insecure deserialization",
          "keyphrase": "insecure deserialization",
          "type": "rootcause"
        },
        {
          "id": "weakness:deserialization",
          "keyphrase": "deserialization",
          "type": "weakness"
        }
      ],
      "917": [
        {
          "id": "weakness:deserialization",
          "keyphrase": "deserialization",
          "type": "weakness"
        }
      ],
      "112": [
        {
          "id": "vector:XML document with nested set elements",
          "keyphrase": "XML document with nested set elements",
          "type": "vector"
        }
      ],
      "116": [
        {
          "id": "vector:XML document with nested set elements",
          "keyphrase": "XML document with nested set elements",
          "type": "vector"
        }
      ]
    },
    "relevant_cwes": [
      {
        "metadata": {
          "doc_id": "674",
          "name": "Uncontrolled Recursion",
          "source": "sparse",
          "original_content": "The product does not properly control the amount of recursion that takes place,  consuming excessive resources, such as allocated memory or the program stack.",
          "keyphrase_sources": [
            {
              "id": "rootcause:stack consumption via an XML document with nested set elements",
              "keyphrase": "stack consumption via an XML document with nested set elements",
              "type": "rootcause"
            },
            {
              "id": "rootcause:insecure deserialization",
              "keyphrase": "insecure deserialization",
              "type": "rootcause"
            },
            {
              "id": "weakness:StackOverflowError",
              "keyphrase": "StackOverflowError",
              "type": "weakness"
            },
            {
              "id": "weakness:deserialization",
              "keyphrase": "deserialization",
              "type": "weakness"
            },
            {
              "id": "vector:XML document with nested set elements",
              "keyphrase": "XML document with nested set elements",
              "type": "vector"
            },
            {
              "id": "product:VisiCut",
              "keyphrase": "VisiCut",
              "type": "product"
            },
            {
              "id": "version:2.1",
              "keyphrase": "2.1",
              "type": "version"
            }
          ]
        },
        "similarity": 367.24823637363505
      },
      {
        "metadata": {
          "doc_id": "776",
          "name": "Improper Restriction of Recursive Entity References in DTDs ('XML Entity Expansion')",
          "source": "sparse",
          "original_content": "The product uses XML documents and allows their structure to be defined with a Document Type Definition (DTD), but it does not properly control the number of recursive definitions of entities.",
          "keyphrase_sources": [
            {
              "id": "rootcause:stack consumption via an XML document with nested set elements",
              "keyphrase": "stack consumption via an XML document with nested set elements",
              "type": "rootcause"
            },
            {
              "id": "weakness:StackOverflowError",
              "keyphrase": "StackOverflowError",
              "type": "weakness"
            },
            {
              "id": "vector:XML document with nested set elements",
              "keyphrase": "XML document with nested set elements",
              "type": "vector"
            },
            {
              "id": "product:VisiCut",
              "keyphrase": "VisiCut",
              "type": "product"
            },
            {
              "id": "version:2.1",
              "keyphrase": "2.1",
              "type": "version"
            }
          ]
        },
        "similarity": 331.5010628863387
      },
      {
        "metadata": {
          "doc_id": "407",
          "name": "Inefficient Algorithmic Complexity",
          "source": "sparse",
          "original_content": "An algorithm in a product has an inefficient worst-case computational complexity that may be detrimental to system performance and can be triggered by an attacker, typically using crafted manipulations that ensure that the worst case is being reached.",
          "keyphrase_sources": [
            {
              "id": "rootcause:stack consumption via an XML document with nested set elements",
              "keyphrase": "stack consumption via an XML document with nested set elements",
              "type": "rootcause"
            },
            {
              "id": "weakness:StackOverflowError",
              "keyphrase": "StackOverflowError",
              "type": "weakness"
            },
            {
              "id": "weakness:deserialization",
              "keyphrase": "deserialization",
              "type": "weakness"
            },
            {
              "id": "product:VisiCut",
              "keyphrase": "VisiCut",
              "type": "product"
            },
            {
              "id": "version:2.1",
              "keyphrase": "2.1",
              "type": "version"
            }
          ]
        },
        "similarity": 270.98648669471316
      },
      {
        "metadata": {
          "doc_id": "835",
          "name": "Loop with Unreachable Exit Condition ('Infinite Loop')",
          "source": "sparse",
          "original_content": "The product contains an iteration or loop with an exit condition that cannot be reached, i.e., an infinite loop.",
          "keyphrase_sources": [
            {
              "id": "rootcause:stack consumption via an XML document with nested set elements",
              "keyphrase": "stack consumption via an XML document with nested set elements",
              "type": "rootcause"
            }
          ]
        },
        "similarity": 266.0724310804057
      },
      {
        "metadata": {
          "doc_id": "611",
          "name": "Improper Restriction of XML External Entity Reference",
          "source": "sparse",
          "original_content": "The product processes an XML document that can contain XML entities with URIs that resolve to documents outside of the intended sphere of control, causing the product to embed incorrect documents into its output.",
          "keyphrase_sources": [
            {
              "id": "rootcause:stack consumption via an XML document with nested set elements",
              "keyphrase": "stack consumption via an XML document with nested set elements",
              "type": "rootcause"
            },
            {
              "id": "weakness:StackOverflowError",
              "keyphrase": "StackOverflowError",
              "type": "weakness"
            },
            {
              "id": "vector:XML document with nested set elements",
              "keyphrase": "XML document with nested set elements",
              "type": "vector"
            },
            {
              "id": "product:VisiCut",
              "keyphrase": "VisiCut",
              "type": "product"
            },
            {
              "id": "version:2.1",
              "keyphrase": "2.1",
              "type": "version"
            }
          ]
        },
        "similarity": 253.45598697861737
      },
      {
        "metadata": {
          "doc_id": "502",
          "name": "Deserialization of Untrusted Data",
          "source": "sparse",
          "original_content": "The product deserializes untrusted data without sufficiently ensuring that the resulting data will be valid.",
          "keyphrase_sources": [
            {
              "id": "rootcause:insecure deserialization",
              "keyphrase": "insecure deserialization",
              "type": "rootcause"
            },
            {
              "id": "weakness:StackOverflowError",
              "keyphrase": "StackOverflowError",
              "type": "weakness"
            },
            {
              "id": "weakness:deserialization",
              "keyphrase": "deserialization",
              "type": "weakness"
            },
            {
              "id": "product:VisiCut",
              "keyphrase": "VisiCut",
              "type": "product"
            },
            {
              "id": "version:2.1",
              "keyphrase": "2.1",
              "type": "version"
            }
          ]
        },
        "similarity": 207.85975046587646
      },
      {
        "metadata": {
          "doc_id": "378",
          "name": "Creation of Temporary File With Insecure Permissions",
          "source": "sparse",
          "original_content": "Opening temporary files without appropriate measures or controls can leave the file, its contents and any function that it impacts vulnerable to attack.",
          "keyphrase_sources": [
            {
              "id": "rootcause:insecure deserialization",
              "keyphrase": "insecure deserialization",
              "type": "rootcause"
            }
          ]
        },
        "similarity": 169.4574083520488
      },
      {
        "metadata": {
          "doc_id": "639",
          "name": "Authorization Bypass Through User-Controlled Key",
          "source": "sparse",
          "original_content": "The system's authorization functionality does not prevent one user from gaining access to another user's data or record by modifying the key value identifying the data.",
          "keyphrase_sources": [
            {
              "id": "rootcause:insecure deserialization",
              "keyphrase": "insecure deserialization",
              "type": "rootcause"
            }
          ]
        },
        "similarity": 168.1867147757289
      },
      {
        "metadata": {
          "doc_id": "183",
          "name": "Permissive List of Allowed Inputs",
          "source": "sparse",
          "original_content": "The product implements a protection mechanism that relies on a list of inputs (or properties of inputs) that are explicitly allowed by policy because the inputs are assumed to be safe, but the list is too permissive - that is, it allows an input that is unsafe, leading to resultant weaknesses.",
          "keyphrase_sources": [
            {
              "id": "rootcause:insecure deserialization",
              "keyphrase": "insecure deserialization",
              "type": "rootcause"
            },
            {
              "id": "weakness:deserialization",
              "keyphrase": "deserialization",
              "type": "weakness"
            }
          ]
        },
        "similarity": 163.45730531967695
      },
      {
        "metadata": {
          "doc_id": "917",
          "name": "Improper Neutralization of Special Elements used in an Expression Language Statement ('Expression Language Injection')",
          "source": "sparse",
          "original_content": "The product constructs all or part of an expression language (EL) statement in a framework such as a Java Server Page (JSP) using externally-influenced input from an upstream component, but it does not neutralize or incorrectly neutralizes special elements that could modify the intended EL statement before it is executed.",
          "keyphrase_sources": [
            {
              "id": "weakness:deserialization",
              "keyphrase": "deserialization",
              "type": "weakness"
            }
          ]
        },
        "similarity": 148.33107238018536
      },
      {
        "metadata": {
          "doc_id": "112",
          "name": "Missing XML Validation",
          "source": "sparse",
          "original_content": "The product accepts XML from an untrusted source but does not validate the XML against the proper schema.",
          "keyphrase_sources": [
            {
              "id": "vector:XML document with nested set elements",
              "keyphrase": "XML document with nested set elements",
              "type": "vector"
            }
          ]
        },
        "similarity": 75.07862761230726
      },
      {
        "metadata": {
          "doc_id": "116",
          "name": "Improper Encoding or Escaping of Output",
          "source": "sparse",
          "original_content": "The product prepares a structured message for communication with another component, but encoding or escaping of the data is either missing or done incorrectly. As a result, the intended structure of the message is not preserved.",
          "keyphrase_sources": [
            {
              "id": "vector:XML document with nested set elements",
              "keyphrase": "XML document with nested set elements",
              "type": "vector"
            }
          ]
        },
        "similarity": 72.60747574227199
      }
    ],
    "enhanced_query": "# Vulnerability Description\n\n    VisiCut 2.1 allows **stack consumption via an XML document with nested set elements**, as demonstrated by a java.util.HashMap **StackOverflowError** when reference=../../../set/set[2] is used, aka an **insecure **deserialization**** issue.\n\n    # Keyphrase-Specific CWE Analysis\n    This vulnerability contains multiple keyphrases that may map to different CWEs. \n    Please analyze each keyphrase separately and determine the most appropriate CWE(s) for each.\n\n    ## ROOTCAUSE: 'stack consumption via an XML document with nested set elements'\n\nRelevant CWEs for this ROOTCAUSE:\n\n### 1. CWE-674: Uncontrolled Recursion (Score: 367.25)\n\nThe product does not properly control the amount of recursion that takes place,  consuming excessive resources, such as allocated memory or the program stack....\n\n### 2. CWE-776: Improper Restriction of Recursive Entity References in DTDs ('XML Entity Expansion') (Score: 331.50)\n\nThe product uses XML documents and allows their structure to be defined with a Document Type Definition (DTD), but it does not properly control the number of recursive definitions of entities....\n\n### 3. CWE-407: Inefficient Algorithmic Complexity (Score: 270.99)\n\nAn algorithm in a product has an inefficient worst-case computational complexity that may be detrimental to system performance and can be triggered by an attacker, typically using crafted manipulations that ensure that the worst case is being reached....\n\n### 4. CWE-835: Loop with Unreachable Exit Condition ('Infinite Loop') (Score: 266.07)\n\nThe product contains an iteration or loop with an exit condition that cannot be reached, i.e., an infinite loop....\n\n### 5. CWE-611: Improper Restriction of XML External Entity Reference (Score: 253.46)\n\nThe product processes an XML document that can contain XML entities with URIs that resolve to documents outside of the intended sphere of control, causing the product to embed incorrect documents into its output....\n\n## ROOTCAUSE: 'insecure deserialization'\n\nRelevant CWEs for this ROOTCAUSE:\n\n### 1. CWE-674: Uncontrolled Recursion (Score: 367.25)\n\nThe product does not properly control the amount of recursion that takes place,  consuming excessive resources, such as allocated memory or the program stack....\n\n### 2. CWE-502: Deserialization of Untrusted Data (Score: 207.86)\n\nThe product deserializes untrusted data without sufficiently ensuring that the resulting data will be valid....\n\n### 3. CWE-378: Creation of Temporary File With Insecure Permissions (Score: 169.46)\n\nOpening temporary files without appropriate measures or controls can leave the file, its contents and any function that it impacts vulnerable to attack....\n\n### 4. CWE-639: Authorization Bypass Through User-Controlled Key (Score: 168.19)\n\nThe system's authorization functionality does not prevent one user from gaining access to another user's data or record by modifying the key value identifying the data....\n\n### 5. CWE-183: Permissive List of Allowed Inputs (Score: 163.46)\n\nThe product implements a protection mechanism that relies on a list of inputs (or properties of inputs) that are explicitly allowed by policy because the inputs are assumed to be safe, but the list is too permissive - that is, it allows an input that is unsafe, leading to resultant weaknesses....\n\n## WEAKNESS: 'StackOverflowError'\n\nRelevant CWEs for this WEAKNESS:\n\n### 1. CWE-674: Uncontrolled Recursion (Score: 367.25)\n\nThe product does not properly control the amount of recursion that takes place,  consuming excessive resources, such as allocated memory or the program stack....\n\n### 2. CWE-776: Improper Restriction of Recursive Entity References in DTDs ('XML Entity Expansion') (Score: 331.50)\n\nThe product uses XML documents and allows their structure to be defined with a Document Type Definition (DTD), but it does not properly control the number of recursive definitions of entities....\n\n### 3. CWE-407: Inefficient Algorithmic Complexity (Score: 270.99)\n\nAn algorithm in a product has an inefficient worst-case computational complexity that may be detrimental to system performance and can be triggered by an attacker, typically using crafted manipulations that ensure that the worst case is being reached....\n\n### 4. CWE-611: Improper Restriction of XML External Entity Reference (Score: 253.46)\n\nThe product processes an XML document that can contain XML entities with URIs that resolve to documents outside of the intended sphere of control, causing the product to embed incorrect documents into its output....\n\n### 5. CWE-502: Deserialization of Untrusted Data (Score: 207.86)\n\nThe product deserializes untrusted data without sufficiently ensuring that the resulting data will be valid....\n\n## WEAKNESS: 'deserialization'\n\nRelevant CWEs for this WEAKNESS:\n\n### 1. CWE-674: Uncontrolled Recursion (Score: 367.25)\n\nThe product does not properly control the amount of recursion that takes place,  consuming excessive resources, such as allocated memory or the program stack....\n\n### 2. CWE-407: Inefficient Algorithmic Complexity (Score: 270.99)\n\nAn algorithm in a product has an inefficient worst-case computational complexity that may be detrimental to system performance and can be triggered by an attacker, typically using crafted manipulations that ensure that the worst case is being reached....\n\n### 3. CWE-502: Deserialization of Untrusted Data (Score: 207.86)\n\nThe product deserializes untrusted data without sufficiently ensuring that the resulting data will be valid....\n\n### 4. CWE-183: Permissive List of Allowed Inputs (Score: 163.46)\n\nThe product implements a protection mechanism that relies on a list of inputs (or properties of inputs) that are explicitly allowed by policy because the inputs are assumed to be safe, but the list is too permissive - that is, it allows an input that is unsafe, leading to resultant weaknesses....\n\n### 5. CWE-917: Improper Neutralization of Special Elements used in an Expression Language Statement ('Expression Language Injection') (Score: 148.33)\n\nThe product constructs all or part of an expression language (EL) statement in a framework such as a Java Server Page (JSP) using externally-influenced input from an upstream component, but it does not neutralize or incorrectly neutralizes special elements that could modify the intended EL statement...\n\n## VECTOR: 'XML document with nested set elements'\n\nRelevant CWEs for this VECTOR:\n\n### 1. CWE-674: Uncontrolled Recursion (Score: 367.25)\n\nThe product does not properly control the amount of recursion that takes place,  consuming excessive resources, such as allocated memory or the program stack....\n\n### 2. CWE-776: Improper Restriction of Recursive Entity References in DTDs ('XML Entity Expansion') (Score: 331.50)\n\nThe product uses XML documents and allows their structure to be defined with a Document Type Definition (DTD), but it does not properly control the number of recursive definitions of entities....\n\n### 3. CWE-611: Improper Restriction of XML External Entity Reference (Score: 253.46)\n\nThe product processes an XML document that can contain XML entities with URIs that resolve to documents outside of the intended sphere of control, causing the product to embed incorrect documents into its output....\n\n### 4. CWE-112: Missing XML Validation (Score: 75.08)\n\nThe product accepts XML from an untrusted source but does not validate the XML against the proper schema....\n\n### 5. CWE-116: Improper Encoding or Escaping of Output (Score: 72.61)\n\nThe product prepares a structured message for communication with another component, but encoding or escaping of the data is either missing or done incorrectly. As a result, the intended structure of the message is not preserved....\n\n## PRODUCT: 'VisiCut'\n\nRelevant CWEs for this PRODUCT:\n\n### 1. CWE-674: Uncontrolled Recursion (Score: 367.25)\n\nThe product does not properly control the amount of recursion that takes place,  consuming excessive resources, such as allocated memory or the program stack....\n\n### 2. CWE-776: Improper Restriction of Recursive Entity References in DTDs ('XML Entity Expansion') (Score: 331.50)\n\nThe product uses XML documents and allows their structure to be defined with a Document Type Definition (DTD), but it does not properly control the number of recursive definitions of entities....\n\n### 3. CWE-407: Inefficient Algorithmic Complexity (Score: 270.99)\n\nAn algorithm in a product has an inefficient worst-case computational complexity that may be detrimental to system performance and can be triggered by an attacker, typically using crafted manipulations that ensure that the worst case is being reached....\n\n### 4. CWE-611: Improper Restriction of XML External Entity Reference (Score: 253.46)\n\nThe product processes an XML document that can contain XML entities with URIs that resolve to documents outside of the intended sphere of control, causing the product to embed incorrect documents into its output....\n\n### 5. CWE-502: Deserialization of Untrusted Data (Score: 207.86)\n\nThe product deserializes untrusted data without sufficiently ensuring that the resulting data will be valid....\n\n## VERSION: '2.1'\n\nRelevant CWEs for this VERSION:\n\n### 1. CWE-674: Uncontrolled Recursion (Score: 367.25)\n\nThe product does not properly control the amount of recursion that takes place,  consuming excessive resources, such as allocated memory or the program stack....\n\n### 2. CWE-776: Improper Restriction of Recursive Entity References in DTDs ('XML Entity Expansion') (Score: 331.50)\n\nThe product uses XML documents and allows their structure to be defined with a Document Type Definition (DTD), but it does not properly control the number of recursive definitions of entities....\n\n### 3. CWE-407: Inefficient Algorithmic Complexity (Score: 270.99)\n\nAn algorithm in a product has an inefficient worst-case computational complexity that may be detrimental to system performance and can be triggered by an attacker, typically using crafted manipulations that ensure that the worst case is being reached....\n\n### 4. CWE-611: Improper Restriction of XML External Entity Reference (Score: 253.46)\n\nThe product processes an XML document that can contain XML entities with URIs that resolve to documents outside of the intended sphere of control, causing the product to embed incorrect documents into its output....\n\n### 5. CWE-502: Deserialization of Untrusted Data (Score: 207.86)\n\nThe product deserializes untrusted data without sufficiently ensuring that the resulting data will be valid....\n\n\n    # Analysis Instructions\n    1. For each keyphrase, identify the most appropriate CWE(s) that represent the weakness.\n    2. Consider how the different keyphrases might relate to each other in the vulnerability chain.\n    3. Provide a final determination of primary CWE(s) and any secondary CWEs.\n    4. Format your response using the standard analysis template.\n\n    Please analyze how these different weaknesses interact and provide a comprehensive CWE classification.\n    "
  },
  "retrieval_time": 1.207395315170288
}