{
  "vulnerability_info": "VulnerabilityInfo(cve_id='CVE-2024-45167', description='An issue was discovered in UCI IDOL 2 (aka uciIDOL or IDOL2) through 2.12. Due to **improper input validation**, **improper **deserialization****, and **improper restriction of operations within the bounds of a memory buffer**, IDOL2 is vulnerable to Denial-of-Service (DoS) attacks and possibly remote code execution. A certain XmlMessage document causes 100% CPU consumption.', key_phrases={'rootcause': ['improper deserialization', 'improper input validation', 'improper restriction of operations within the bounds of a memory buffer'], 'weakness': 'deserialization', 'impact': ['CPU consumption', 'Denial-of-Service (DoS) attacks and possibly remote code execution'], 'vector': 'XmlMessage document', 'attacker': '', 'product': 'UCI IDOL 2', 'version': 'through 2.12', 'component': ''}, reference_content='Based on the provided content, here\\'s an analysis of CVE-2024-45167:\\n\\n**1. Verification of CVE Relevance:**\\n\\nThe provided content directly relates to CVE-2024-45167. The security advisories (SYSS-2024-050 and SYSS-2024-051) explicitly mention this CVE ID. The advisories describe vulnerabilities in \"IDOL2 (uciIDOL)\" due to improper input validation and memory buffer issues, which align with the typical nature of CVE entries.\\n\\n**2. Vulnerability Details:**\\n\\n*   **Root Cause:** The vulnerability stems from:\\n    *   **Improper Input Validation (CWE-20):** The IDOL2 application fails to properly validate input data.\\n    *   **Improper Deserialization:** The application handles deserialization of data improperly which could lead to vulnerabilities when processing crafted inputs.\\n    *   **Improper Restriction of Operations within the Bounds of a Memory Buffer (CWE-119):** The application does not properly restrict memory operations, leading to potential buffer overflows or other memory-related errors.\\n\\n*   **Weaknesses/Vulnerabilities Present:**\\n    *   The core vulnerabilities are related to how the IDOL2 client processes network messages. The software fails to validate the incoming data properly, leading to memory corruption when processing crafted payloads.\\n    *   Specifically, the provided PoC shows that sending a crafted message can lead to an access violation and EIP (Extended Instruction Pointer) overwrite or a denial of service due to excessive CPU usage.\\n\\n*   **Impact of Exploitation:**\\n    *   **Denial-of-Service (DoS):** An attacker can cause the IDOL2 client to crash or become unresponsive.\\n    *  **Possible Remote Code Execution (RCE):** The advisories suggest the possibility of RCE, though this might depend on further conditions not specifically described in the provided PoCs. The buffer overflow and EIP overwrite suggest the possibility of arbitrary code execution by providing shellcode in crafted messages.\\n\\n*   **Attack Vectors:**\\n    *   **Network-based:** The vulnerability is exploited by sending specially crafted network messages to the IDOL2 client. The provided PoC shows the use of a socket to send these messages to the vulnerable client.\\n\\n*   **Required Attacker Capabilities/Position:**\\n    *   **Network Access:** The attacker needs to be able to send network messages to the machine running the vulnerable IDOL2 client. This could mean being on the same network or having the ability to reach the target machine\\'s network port.\\n    *   **Basic Socket Programming:** The attacker needs to be able to create and send network data via sockets, as demonstrated in the provided Python PoC.\\n\\n**3. Additional Information:**\\n\\n*   **Affected Product:** IDOL2 (uciIDOL) is the affected software, a rich client application used for personnel time recording and other related tasks. The vulnerabilities are in client-side software and would require a connection to an affected server.\\n*   **Affected Versions:** Versions of IDOL2 up to and including 2.12 are vulnerable.\\n*   **Vendor Response:** The vendor was notified on 2024-06-26, but has not yet released a fix at the time of public disclosure (2024-08-19). The vendor declined an offer for a call to discuss the issue.\\n*   **Proof of Concept (PoC):** The advisory includes a Python script that demonstrates the vulnerability.\\n    *   The provided PoC shows how to crash the IDOL2 client by sending a small message `b\\'\\\\xB0\\\\x00\\' + b\\' EOF\\'` or by sending more complex crafted messages.\\n\\n**4. Summary of extracted information:**\\n    - Root cause of vulnerability: Improper Input Validation, improper deserialization, improper restriction of operations within a memory buffer\\n    - Weaknesses/vulnerabilities present: Failure to validate input data leading to memory corruption\\n    - Impact of exploitation: Denial of Service, Possible Remote Code Execution\\n    - Attack vectors: Network-based attack sending malicious messages\\n    - Required attacker capabilities/position: Network access, socket programming\\n\\nIn conclusion, the provided content provides a comprehensive view of CVE-2024-45167, detailing the root causes, impact, attack vectors, and requirements for exploitation, as well as a working PoC.', similar_info={'cwe_distribution': {}, 'cwe_consensus': '', 'similarity_stats': {'thresholds': [], 'total_samples_by_threshold': {}, 'top_cwes_by_threshold': {}}}, similarity_summary=SimilarityInsight(consensus_cwe='', top_cwes=[], confidence_levels={}, total_samples=0), analysis='', analysis_with_relationships='', criticism='', resolution='', relevant_cwes=[{'metadata': {'doc_id': '125', 'name': 'Out-of-bounds Read', 'source': 'sparse', 'original_content': 'The product reads data past the end, or before the beginning, of the intended buffer.', 'keyphrase_sources': [{'id': 'rootcause:improper restriction of operations within the bounds of a memory buffer', 'keyphrase': 'improper restriction of operations within the bounds of a memory buffer', 'type': 'rootcause'}]}, 'similarity': np.float64(460.3432024944727)}, {'metadata': {'doc_id': '122', 'name': 'Heap-based Buffer Overflow', 'source': 'sparse', 'original_content': 'A heap overflow condition is a buffer overflow, where the buffer that can be overwritten is allocated in the heap portion of memory, generally meaning that the buffer was allocated using a routine such as malloc().', 'keyphrase_sources': [{'id': 'rootcause:improper restriction of operations within the bounds of a memory buffer', 'keyphrase': 'improper restriction of operations within the bounds of a memory buffer', 'type': 'rootcause'}]}, 'similarity': np.float64(449.2766486420322)}, {'metadata': {'doc_id': '119', 'name': 'Improper Restriction of Operations within the Bounds of a Memory Buffer', 'source': 'sparse', 'original_content': \"The product performs operations on a memory buffer, but it reads from or writes to a memory location outside the buffer's intended boundary. This may result in read or write operations on unexpected memory locations that could be linked to other variables, data structures, or internal program data.\", 'keyphrase_sources': [{'id': 'rootcause:improper deserialization', 'keyphrase': 'improper deserialization', 'type': 'rootcause'}, {'id': 'rootcause:improper input validation', 'keyphrase': 'improper input validation', 'type': 'rootcause'}, {'id': 'rootcause:improper restriction of operations within the bounds of a memory buffer', 'keyphrase': 'improper restriction of operations within the bounds of a memory buffer', 'type': 'rootcause'}, {'id': 'weakness:deserialization', 'keyphrase': 'deserialization', 'type': 'weakness'}, {'id': 'impact:CPU consumption', 'keyphrase': 'CPU consumption', 'type': 'impact'}, {'id': 'impact:Denial-of-Service (DoS) attacks and possibly remote code execution', 'keyphrase': 'Denial-of-Service (DoS) attacks and possibly remote code execution', 'type': 'impact'}, {'id': 'vector:XmlMessage document', 'keyphrase': 'XmlMessage document', 'type': 'vector'}, {'id': 'product:UCI IDOL 2', 'keyphrase': 'UCI IDOL 2', 'type': 'product'}, {'id': 'version:through 2.12', 'keyphrase': 'through 2.12', 'type': 'version'}]}, 'similarity': np.float64(336.4639277717134)}, {'metadata': {'doc_id': '502', 'name': 'Deserialization of Untrusted Data', 'source': 'sparse', 'original_content': 'The product deserializes untrusted data without sufficiently ensuring that the resulting data will be valid.', 'keyphrase_sources': [{'id': 'rootcause:improper deserialization', 'keyphrase': 'improper deserialization', 'type': 'rootcause'}, {'id': 'weakness:deserialization', 'keyphrase': 'deserialization', 'type': 'weakness'}]}, 'similarity': np.float64(327.11946044926316)}, {'metadata': {'doc_id': '20', 'name': 'Improper Input Validation', 'source': 'sparse', 'original_content': 'The product receives input or data, but it does\\n        not validate or incorrectly validates that the input has the\\n        properties that are required to process the data safely and\\n        correctly.', 'keyphrase_sources': [{'id': 'rootcause:improper deserialization', 'keyphrase': 'improper deserialization', 'type': 'rootcause'}, {'id': 'rootcause:improper input validation', 'keyphrase': 'improper input validation', 'type': 'rootcause'}, {'id': 'weakness:deserialization', 'keyphrase': 'deserialization', 'type': 'weakness'}, {'id': 'impact:Denial-of-Service (DoS) attacks and possibly remote code execution', 'keyphrase': 'Denial-of-Service (DoS) attacks and possibly remote code execution', 'type': 'impact'}, {'id': 'vector:XmlMessage document', 'keyphrase': 'XmlMessage document', 'type': 'vector'}, {'id': 'product:UCI IDOL 2', 'keyphrase': 'UCI IDOL 2', 'type': 'product'}, {'id': 'version:through 2.12', 'keyphrase': 'through 2.12', 'type': 'version'}]}, 'similarity': np.float64(305.2237722113356)}, {'metadata': {'doc_id': '1285', 'name': 'Improper Validation of Specified Index, Position, or Offset in Input', 'source': 'sparse', 'original_content': 'The product receives input that is expected to specify an index, position, or offset into an indexable resource such as a buffer or file, but it does not validate or incorrectly validates that the specified index/position/offset has the required properties.', 'keyphrase_sources': [{'id': 'rootcause:improper input validation', 'keyphrase': 'improper input validation', 'type': 'rootcause'}]}, 'similarity': np.float64(302.4014724982968)}, {'metadata': {'doc_id': '1284', 'name': 'Improper Validation of Specified Quantity in Input', 'source': 'sparse', 'original_content': 'The product receives input that is expected to specify a quantity (such as size or length), but it does not validate or incorrectly validates that the quantity has the required properties.', 'keyphrase_sources': [{'id': 'rootcause:improper deserialization', 'keyphrase': 'improper deserialization', 'type': 'rootcause'}, {'id': 'rootcause:improper input validation', 'keyphrase': 'improper input validation', 'type': 'rootcause'}, {'id': 'rootcause:improper restriction of operations within the bounds of a memory buffer', 'keyphrase': 'improper restriction of operations within the bounds of a memory buffer', 'type': 'rootcause'}, {'id': 'weakness:deserialization', 'keyphrase': 'deserialization', 'type': 'weakness'}, {'id': 'impact:CPU consumption', 'keyphrase': 'CPU consumption', 'type': 'impact'}, {'id': 'impact:Denial-of-Service (DoS) attacks and possibly remote code execution', 'keyphrase': 'Denial-of-Service (DoS) attacks and possibly remote code execution', 'type': 'impact'}, {'id': 'vector:XmlMessage document', 'keyphrase': 'XmlMessage document', 'type': 'vector'}, {'id': 'product:UCI IDOL 2', 'keyphrase': 'UCI IDOL 2', 'type': 'product'}, {'id': 'version:through 2.12', 'keyphrase': 'through 2.12', 'type': 'version'}]}, 'similarity': np.float64(302.33029527394814)}, {'metadata': {'doc_id': '190', 'name': 'Integer Overflow or Wraparound', 'source': 'sparse', 'original_content': 'The product performs a calculation that can\\n         produce an integer overflow or wraparound when the logic\\n         assumes that the resulting value will always be larger than\\n         the original value. This occurs when an integer value is\\n         incremented to a value that is too large to store in the\\n         associated representation. When this occurs, the value may\\n         become a very small or negative number.', 'keyphrase_sources': [{'id': 'rootcause:improper deserialization', 'keyphrase': 'improper deserialization', 'type': 'rootcause'}, {'id': 'rootcause:improper input validation', 'keyphrase': 'improper input validation', 'type': 'rootcause'}, {'id': 'rootcause:improper restriction of operations within the bounds of a memory buffer', 'keyphrase': 'improper restriction of operations within the bounds of a memory buffer', 'type': 'rootcause'}, {'id': 'weakness:deserialization', 'keyphrase': 'deserialization', 'type': 'weakness'}, {'id': 'vector:XmlMessage document', 'keyphrase': 'XmlMessage document', 'type': 'vector'}, {'id': 'product:UCI IDOL 2', 'keyphrase': 'UCI IDOL 2', 'type': 'product'}, {'id': 'version:through 2.12', 'keyphrase': 'through 2.12', 'type': 'version'}]}, 'similarity': np.float64(294.5719851695843)}, {'metadata': {'doc_id': '121', 'name': 'Stack-based Buffer Overflow', 'source': 'sparse', 'original_content': 'A stack-based buffer overflow condition is a condition where the buffer being overwritten is allocated on the stack (i.e., is a local variable or, rarely, a parameter to a function).', 'keyphrase_sources': [{'id': 'impact:Denial-of-Service (DoS) attacks and possibly remote code execution', 'keyphrase': 'Denial-of-Service (DoS) attacks and possibly remote code execution', 'type': 'impact'}, {'id': 'vector:XmlMessage document', 'keyphrase': 'XmlMessage document', 'type': 'vector'}, {'id': 'product:UCI IDOL 2', 'keyphrase': 'UCI IDOL 2', 'type': 'product'}, {'id': 'version:through 2.12', 'keyphrase': 'through 2.12', 'type': 'version'}]}, 'similarity': np.float64(132.58084227610865)}, {'metadata': {'doc_id': '130', 'name': 'Improper Handling of Length Parameter Inconsistency', 'source': 'sparse', 'original_content': 'The product parses a formatted message or structure, but it does not handle or incorrectly handles a length field that is inconsistent with the actual length of the associated data.', 'keyphrase_sources': [{'id': 'impact:Denial-of-Service (DoS) attacks and possibly remote code execution', 'keyphrase': 'Denial-of-Service (DoS) attacks and possibly remote code execution', 'type': 'impact'}]}, 'similarity': np.float64(131.846381482813)}, {'metadata': {'doc_id': '407', 'name': 'Inefficient Algorithmic Complexity', 'source': 'sparse', 'original_content': 'An algorithm in a product has an inefficient worst-case computational complexity that may be detrimental to system performance and can be triggered by an attacker, typically using crafted manipulations that ensure that the worst case is being reached.', 'keyphrase_sources': [{'id': 'impact:CPU consumption', 'keyphrase': 'CPU consumption', 'type': 'impact'}]}, 'similarity': np.float64(110.52633503396007)}, {'metadata': {'doc_id': '400', 'name': 'Uncontrolled Resource Consumption', 'source': 'sparse', 'original_content': 'The product does not properly control the allocation and maintenance of a limited resource, thereby enabling an actor to influence the amount of resources consumed, eventually leading to the exhaustion of available resources.', 'keyphrase_sources': [{'id': 'impact:CPU consumption', 'keyphrase': 'CPU consumption', 'type': 'impact'}]}, 'similarity': np.float64(108.77496865339428)}, {'metadata': {'doc_id': '682', 'name': 'Incorrect Calculation', 'source': 'sparse', 'original_content': 'The product performs a calculation that generates incorrect or unintended results that are later used in security-critical decisions or resource management.', 'keyphrase_sources': [{'id': 'impact:CPU consumption', 'keyphrase': 'CPU consumption', 'type': 'impact'}]}, 'similarity': np.float64(105.74955975995562)}], identified_cwes={'analyzer': [], 'critic_additional': []})",
  "retrieval_results": {
    "has_multiple_keyphrases": true,
    "keyphrase_cwe_sets": {
      "rootcause:improper deserialization": {
        "keyphrase": "improper deserialization",
        "type": "rootcause",
        "cwes": [
          {
            "metadata": {
              "doc_id": "119",
              "name": "Improper Restriction of Operations within the Bounds of a Memory Buffer",
              "source": "sparse",
              "original_content": "The product performs operations on a memory buffer, but it reads from or writes to a memory location outside the buffer's intended boundary. This may result in read or write operations on unexpected memory locations that could be linked to other variables, data structures, or internal program data.",
              "keyphrase_sources": [
                {
                  "id": "rootcause:improper deserialization",
                  "keyphrase": "improper deserialization",
                  "type": "rootcause"
                },
                {
                  "id": "rootcause:improper input validation",
                  "keyphrase": "improper input validation",
                  "type": "rootcause"
                },
                {
                  "id": "rootcause:improper restriction of operations within the bounds of a memory buffer",
                  "keyphrase": "improper restriction of operations within the bounds of a memory buffer",
                  "type": "rootcause"
                },
                {
                  "id": "weakness:deserialization",
                  "keyphrase": "deserialization",
                  "type": "weakness"
                },
                {
                  "id": "impact:CPU consumption",
                  "keyphrase": "CPU consumption",
                  "type": "impact"
                },
                {
                  "id": "impact:Denial-of-Service (DoS) attacks and possibly remote code execution",
                  "keyphrase": "Denial-of-Service (DoS) attacks and possibly remote code execution",
                  "type": "impact"
                },
                {
                  "id": "vector:XmlMessage document",
                  "keyphrase": "XmlMessage document",
                  "type": "vector"
                },
                {
                  "id": "product:UCI IDOL 2",
                  "keyphrase": "UCI IDOL 2",
                  "type": "product"
                },
                {
                  "id": "version:through 2.12",
                  "keyphrase": "through 2.12",
                  "type": "version"
                }
              ]
            },
            "similarity": 336.4639277717134
          },
          {
            "metadata": {
              "doc_id": "502",
              "name": "Deserialization of Untrusted Data",
              "source": "sparse",
              "original_content": "The product deserializes untrusted data without sufficiently ensuring that the resulting data will be valid.",
              "keyphrase_sources": [
                {
                  "id": "rootcause:improper deserialization",
                  "keyphrase": "improper deserialization",
                  "type": "rootcause"
                },
                {
                  "id": "weakness:deserialization",
                  "keyphrase": "deserialization",
                  "type": "weakness"
                }
              ]
            },
            "similarity": 327.11946044926316
          },
          {
            "metadata": {
              "doc_id": "20",
              "name": "Improper Input Validation",
              "source": "sparse",
              "original_content": "The product receives input or data, but it does\n        not validate or incorrectly validates that the input has the\n        properties that are required to process the data safely and\n        correctly.",
              "keyphrase_sources": [
                {
                  "id": "rootcause:improper deserialization",
                  "keyphrase": "improper deserialization",
                  "type": "rootcause"
                },
                {
                  "id": "rootcause:improper input validation",
                  "keyphrase": "improper input validation",
                  "type": "rootcause"
                },
                {
                  "id": "weakness:deserialization",
                  "keyphrase": "deserialization",
                  "type": "weakness"
                },
                {
                  "id": "impact:Denial-of-Service (DoS) attacks and possibly remote code execution",
                  "keyphrase": "Denial-of-Service (DoS) attacks and possibly remote code execution",
                  "type": "impact"
                },
                {
                  "id": "vector:XmlMessage document",
                  "keyphrase": "XmlMessage document",
                  "type": "vector"
                },
                {
                  "id": "product:UCI IDOL 2",
                  "keyphrase": "UCI IDOL 2",
                  "type": "product"
                },
                {
                  "id": "version:through 2.12",
                  "keyphrase": "through 2.12",
                  "type": "version"
                }
              ]
            },
            "similarity": 305.2237722113356
          },
          {
            "metadata": {
              "doc_id": "1284",
              "name": "Improper Validation of Specified Quantity in Input",
              "source": "sparse",
              "original_content": "The product receives input that is expected to specify a quantity (such as size or length), but it does not validate or incorrectly validates that the quantity has the required properties.",
              "keyphrase_sources": [
                {
                  "id": "rootcause:improper deserialization",
                  "keyphrase": "improper deserialization",
                  "type": "rootcause"
                },
                {
                  "id": "rootcause:improper input validation",
                  "keyphrase": "improper input validation",
                  "type": "rootcause"
                },
                {
                  "id": "rootcause:improper restriction of operations within the bounds of a memory buffer",
                  "keyphrase": "improper restriction of operations within the bounds of a memory buffer",
                  "type": "rootcause"
                },
                {
                  "id": "weakness:deserialization",
                  "keyphrase": "deserialization",
                  "type": "weakness"
                },
                {
                  "id": "impact:CPU consumption",
                  "keyphrase": "CPU consumption",
                  "type": "impact"
                },
                {
                  "id": "impact:Denial-of-Service (DoS) attacks and possibly remote code execution",
                  "keyphrase": "Denial-of-Service (DoS) attacks and possibly remote code execution",
                  "type": "impact"
                },
                {
                  "id": "vector:XmlMessage document",
                  "keyphrase": "XmlMessage document",
                  "type": "vector"
                },
                {
                  "id": "product:UCI IDOL 2",
                  "keyphrase": "UCI IDOL 2",
                  "type": "product"
                },
                {
                  "id": "version:through 2.12",
                  "keyphrase": "through 2.12",
                  "type": "version"
                }
              ]
            },
            "similarity": 302.33029527394814
          },
          {
            "metadata": {
              "doc_id": "190",
              "name": "Integer Overflow or Wraparound",
              "source": "sparse",
              "original_content": "The product performs a calculation that can\n         produce an integer overflow or wraparound when the logic\n         assumes that the resulting value will always be larger than\n         the original value. This occurs when an integer value is\n         incremented to a value that is too large to store in the\n         associated representation. When this occurs, the value may\n         become a very small or negative number.",
              "keyphrase_sources": [
                {
                  "id": "rootcause:improper deserialization",
                  "keyphrase": "improper deserialization",
                  "type": "rootcause"
                },
                {
                  "id": "rootcause:improper input validation",
                  "keyphrase": "improper input validation",
                  "type": "rootcause"
                },
                {
                  "id": "rootcause:improper restriction of operations within the bounds of a memory buffer",
                  "keyphrase": "improper restriction of operations within the bounds of a memory buffer",
                  "type": "rootcause"
                },
                {
                  "id": "weakness:deserialization",
                  "keyphrase": "deserialization",
                  "type": "weakness"
                },
                {
                  "id": "vector:XmlMessage document",
                  "keyphrase": "XmlMessage document",
                  "type": "vector"
                },
                {
                  "id": "product:UCI IDOL 2",
                  "keyphrase": "UCI IDOL 2",
                  "type": "product"
                },
                {
                  "id": "version:through 2.12",
                  "keyphrase": "through 2.12",
                  "type": "version"
                }
              ]
            },
            "similarity": 294.5719851695843
          }
        ]
      },
      "rootcause:improper input validation": {
        "keyphrase": "improper input validation",
        "type": "rootcause",
        "cwes": [
          {
            "metadata": {
              "doc_id": "119",
              "name": "Improper Restriction of Operations within the Bounds of a Memory Buffer",
              "source": "sparse",
              "original_content": "The product performs operations on a memory buffer, but it reads from or writes to a memory location outside the buffer's intended boundary. This may result in read or write operations on unexpected memory locations that could be linked to other variables, data structures, or internal program data."
            },
            "similarity": 341.73180368833147
          },
          {
            "metadata": {
              "doc_id": "20",
              "name": "Improper Input Validation",
              "source": "sparse",
              "original_content": "The product receives input or data, but it does\n        not validate or incorrectly validates that the input has the\n        properties that are required to process the data safely and\n        correctly."
            },
            "similarity": 334.35597942701895
          },
          {
            "metadata": {
              "doc_id": "1284",
              "name": "Improper Validation of Specified Quantity in Input",
              "source": "sparse",
              "original_content": "The product receives input that is expected to specify a quantity (such as size or length), but it does not validate or incorrectly validates that the quantity has the required properties."
            },
            "similarity": 332.05701504103143
          },
          {
            "metadata": {
              "doc_id": "190",
              "name": "Integer Overflow or Wraparound",
              "source": "sparse",
              "original_content": "The product performs a calculation that can\n         produce an integer overflow or wraparound when the logic\n         assumes that the resulting value will always be larger than\n         the original value. This occurs when an integer value is\n         incremented to a value that is too large to store in the\n         associated representation. When this occurs, the value may\n         become a very small or negative number."
            },
            "similarity": 311.3103597177105
          },
          {
            "metadata": {
              "doc_id": "1285",
              "name": "Improper Validation of Specified Index, Position, or Offset in Input",
              "source": "sparse",
              "original_content": "The product receives input that is expected to specify an index, position, or offset into an indexable resource such as a buffer or file, but it does not validate or incorrectly validates that the specified index/position/offset has the required properties.",
              "keyphrase_sources": [
                {
                  "id": "rootcause:improper input validation",
                  "keyphrase": "improper input validation",
                  "type": "rootcause"
                }
              ]
            },
            "similarity": 302.4014724982968
          }
        ]
      },
      "rootcause:improper restriction of operations within the bounds of a memory buffer": {
        "keyphrase": "improper restriction of operations within the bounds of a memory buffer",
        "type": "rootcause",
        "cwes": [
          {
            "metadata": {
              "doc_id": "119",
              "name": "Improper Restriction of Operations within the Bounds of a Memory Buffer",
              "source": "sparse",
              "original_content": "The product performs operations on a memory buffer, but it reads from or writes to a memory location outside the buffer's intended boundary. This may result in read or write operations on unexpected memory locations that could be linked to other variables, data structures, or internal program data."
            },
            "similarity": 564.723595035049
          },
          {
            "metadata": {
              "doc_id": "190",
              "name": "Integer Overflow or Wraparound",
              "source": "sparse",
              "original_content": "The product performs a calculation that can\n         produce an integer overflow or wraparound when the logic\n         assumes that the resulting value will always be larger than\n         the original value. This occurs when an integer value is\n         incremented to a value that is too large to store in the\n         associated representation. When this occurs, the value may\n         become a very small or negative number."
            },
            "similarity": 473.6334729945248
          },
          {
            "metadata": {
              "doc_id": "125",
              "name": "Out-of-bounds Read",
              "source": "sparse",
              "original_content": "The product reads data past the end, or before the beginning, of the intended buffer.",
              "keyphrase_sources": [
                {
                  "id": "rootcause:improper restriction of operations within the bounds of a memory buffer",
                  "keyphrase": "improper restriction of operations within the bounds of a memory buffer",
                  "type": "rootcause"
                }
              ]
            },
            "similarity": 460.3432024944727
          },
          {
            "metadata": {
              "doc_id": "1284",
              "name": "Improper Validation of Specified Quantity in Input",
              "source": "sparse",
              "original_content": "The product receives input that is expected to specify a quantity (such as size or length), but it does not validate or incorrectly validates that the quantity has the required properties."
            },
            "similarity": 456.6742148560313
          },
          {
            "metadata": {
              "doc_id": "122",
              "name": "Heap-based Buffer Overflow",
              "source": "sparse",
              "original_content": "A heap overflow condition is a buffer overflow, where the buffer that can be overwritten is allocated in the heap portion of memory, generally meaning that the buffer was allocated using a routine such as malloc().",
              "keyphrase_sources": [
                {
                  "id": "rootcause:improper restriction of operations within the bounds of a memory buffer",
                  "keyphrase": "improper restriction of operations within the bounds of a memory buffer",
                  "type": "rootcause"
                }
              ]
            },
            "similarity": 449.2766486420322
          }
        ]
      },
      "weakness:deserialization": {
        "keyphrase": "deserialization",
        "type": "weakness",
        "cwes": [
          {
            "metadata": {
              "doc_id": "119",
              "name": "Improper Restriction of Operations within the Bounds of a Memory Buffer",
              "source": "sparse",
              "original_content": "The product performs operations on a memory buffer, but it reads from or writes to a memory location outside the buffer's intended boundary. This may result in read or write operations on unexpected memory locations that could be linked to other variables, data structures, or internal program data."
            },
            "similarity": 306.644943436167
          },
          {
            "metadata": {
              "doc_id": "502",
              "name": "Deserialization of Untrusted Data",
              "source": "sparse",
              "original_content": "The product deserializes untrusted data without sufficiently ensuring that the resulting data will be valid."
            },
            "similarity": 303.7472894201232
          },
          {
            "metadata": {
              "doc_id": "20",
              "name": "Improper Input Validation",
              "source": "sparse",
              "original_content": "The product receives input or data, but it does\n        not validate or incorrectly validates that the input has the\n        properties that are required to process the data safely and\n        correctly."
            },
            "similarity": 277.25214451141767
          },
          {
            "metadata": {
              "doc_id": "1284",
              "name": "Improper Validation of Specified Quantity in Input",
              "source": "sparse",
              "original_content": "The product receives input that is expected to specify a quantity (such as size or length), but it does not validate or incorrectly validates that the quantity has the required properties."
            },
            "similarity": 276.3296778176101
          },
          {
            "metadata": {
              "doc_id": "190",
              "name": "Integer Overflow or Wraparound",
              "source": "sparse",
              "original_content": "The product performs a calculation that can\n         produce an integer overflow or wraparound when the logic\n         assumes that the resulting value will always be larger than\n         the original value. This occurs when an integer value is\n         incremented to a value that is too large to store in the\n         associated representation. When this occurs, the value may\n         become a very small or negative number."
            },
            "similarity": 271.14487000370855
          }
        ]
      },
      "impact:CPU consumption": {
        "keyphrase": "CPU consumption",
        "type": "impact",
        "cwes": [
          {
            "metadata": {
              "doc_id": "119",
              "name": "Improper Restriction of Operations within the Bounds of a Memory Buffer",
              "source": "sparse",
              "original_content": "The product performs operations on a memory buffer, but it reads from or writes to a memory location outside the buffer's intended boundary. This may result in read or write operations on unexpected memory locations that could be linked to other variables, data structures, or internal program data."
            },
            "similarity": 118.7821883836594
          },
          {
            "metadata": {
              "doc_id": "407",
              "name": "Inefficient Algorithmic Complexity",
              "source": "sparse",
              "original_content": "An algorithm in a product has an inefficient worst-case computational complexity that may be detrimental to system performance and can be triggered by an attacker, typically using crafted manipulations that ensure that the worst case is being reached.",
              "keyphrase_sources": [
                {
                  "id": "impact:CPU consumption",
                  "keyphrase": "CPU consumption",
                  "type": "impact"
                }
              ]
            },
            "similarity": 110.52633503396007
          },
          {
            "metadata": {
              "doc_id": "400",
              "name": "Uncontrolled Resource Consumption",
              "source": "sparse",
              "original_content": "The product does not properly control the allocation and maintenance of a limited resource, thereby enabling an actor to influence the amount of resources consumed, eventually leading to the exhaustion of available resources.",
              "keyphrase_sources": [
                {
                  "id": "impact:CPU consumption",
                  "keyphrase": "CPU consumption",
                  "type": "impact"
                }
              ]
            },
            "similarity": 108.77496865339428
          },
          {
            "metadata": {
              "doc_id": "1284",
              "name": "Improper Validation of Specified Quantity in Input",
              "source": "sparse",
              "original_content": "The product receives input that is expected to specify a quantity (such as size or length), but it does not validate or incorrectly validates that the quantity has the required properties."
            },
            "similarity": 107.09573775202337
          },
          {
            "metadata": {
              "doc_id": "682",
              "name": "Incorrect Calculation",
              "source": "sparse",
              "original_content": "The product performs a calculation that generates incorrect or unintended results that are later used in security-critical decisions or resource management.",
              "keyphrase_sources": [
                {
                  "id": "impact:CPU consumption",
                  "keyphrase": "CPU consumption",
                  "type": "impact"
                }
              ]
            },
            "similarity": 105.74955975995562
          }
        ]
      },
      "impact:Denial-of-Service (DoS) attacks and possibly remote code execution": {
        "keyphrase": "Denial-of-Service (DoS) attacks and possibly remote code execution",
        "type": "impact",
        "cwes": [
          {
            "metadata": {
              "doc_id": "119",
              "name": "Improper Restriction of Operations within the Bounds of a Memory Buffer",
              "source": "sparse",
              "original_content": "The product performs operations on a memory buffer, but it reads from or writes to a memory location outside the buffer's intended boundary. This may result in read or write operations on unexpected memory locations that could be linked to other variables, data structures, or internal program data."
            },
            "similarity": 149.6339680542894
          },
          {
            "metadata": {
              "doc_id": "20",
              "name": "Improper Input Validation",
              "source": "sparse",
              "original_content": "The product receives input or data, but it does\n        not validate or incorrectly validates that the input has the\n        properties that are required to process the data safely and\n        correctly."
            },
            "similarity": 135.78625976058234
          },
          {
            "metadata": {
              "doc_id": "1284",
              "name": "Improper Validation of Specified Quantity in Input",
              "source": "sparse",
              "original_content": "The product receives input that is expected to specify a quantity (such as size or length), but it does not validate or incorrectly validates that the quantity has the required properties."
            },
            "similarity": 133.57798575766446
          },
          {
            "metadata": {
              "doc_id": "121",
              "name": "Stack-based Buffer Overflow",
              "source": "sparse",
              "original_content": "A stack-based buffer overflow condition is a condition where the buffer being overwritten is allocated on the stack (i.e., is a local variable or, rarely, a parameter to a function).",
              "keyphrase_sources": [
                {
                  "id": "impact:Denial-of-Service (DoS) attacks and possibly remote code execution",
                  "keyphrase": "Denial-of-Service (DoS) attacks and possibly remote code execution",
                  "type": "impact"
                },
                {
                  "id": "vector:XmlMessage document",
                  "keyphrase": "XmlMessage document",
                  "type": "vector"
                },
                {
                  "id": "product:UCI IDOL 2",
                  "keyphrase": "UCI IDOL 2",
                  "type": "product"
                },
                {
                  "id": "version:through 2.12",
                  "keyphrase": "through 2.12",
                  "type": "version"
                }
              ]
            },
            "similarity": 132.58084227610865
          },
          {
            "metadata": {
              "doc_id": "130",
              "name": "Improper Handling of Length Parameter Inconsistency",
              "source": "sparse",
              "original_content": "The product parses a formatted message or structure, but it does not handle or incorrectly handles a length field that is inconsistent with the actual length of the associated data.",
              "keyphrase_sources": [
                {
                  "id": "impact:Denial-of-Service (DoS) attacks and possibly remote code execution",
                  "keyphrase": "Denial-of-Service (DoS) attacks and possibly remote code execution",
                  "type": "impact"
                }
              ]
            },
            "similarity": 131.846381482813
          }
        ]
      },
      "vector:XmlMessage document": {
        "keyphrase": "XmlMessage document",
        "type": "vector",
        "cwes": [
          {
            "metadata": {
              "doc_id": "119",
              "name": "Improper Restriction of Operations within the Bounds of a Memory Buffer",
              "source": "sparse",
              "original_content": "The product performs operations on a memory buffer, but it reads from or writes to a memory location outside the buffer's intended boundary. This may result in read or write operations on unexpected memory locations that could be linked to other variables, data structures, or internal program data."
            },
            "similarity": 110.6734123515621
          },
          {
            "metadata": {
              "doc_id": "20",
              "name": "Improper Input Validation",
              "source": "sparse",
              "original_content": "The product receives input or data, but it does\n        not validate or incorrectly validates that the input has the\n        properties that are required to process the data safely and\n        correctly."
            },
            "similarity": 98.70994123601773
          },
          {
            "metadata": {
              "doc_id": "1284",
              "name": "Improper Validation of Specified Quantity in Input",
              "source": "sparse",
              "original_content": "The product receives input that is expected to specify a quantity (such as size or length), but it does not validate or incorrectly validates that the quantity has the required properties."
            },
            "similarity": 98.68917064914648
          },
          {
            "metadata": {
              "doc_id": "121",
              "name": "Stack-based Buffer Overflow",
              "source": "sparse",
              "original_content": "A stack-based buffer overflow condition is a condition where the buffer being overwritten is allocated on the stack (i.e., is a local variable or, rarely, a parameter to a function)."
            },
            "similarity": 96.95700356420376
          },
          {
            "metadata": {
              "doc_id": "190",
              "name": "Integer Overflow or Wraparound",
              "source": "sparse",
              "original_content": "The product performs a calculation that can\n         produce an integer overflow or wraparound when the logic\n         assumes that the resulting value will always be larger than\n         the original value. This occurs when an integer value is\n         incremented to a value that is too large to store in the\n         associated representation. When this occurs, the value may\n         become a very small or negative number."
            },
            "similarity": 96.83745357275306
          }
        ]
      },
      "product:UCI IDOL 2": {
        "keyphrase": "UCI IDOL 2",
        "type": "product",
        "cwes": [
          {
            "metadata": {
              "doc_id": "119",
              "name": "Improper Restriction of Operations within the Bounds of a Memory Buffer",
              "source": "sparse",
              "original_content": "The product performs operations on a memory buffer, but it reads from or writes to a memory location outside the buffer's intended boundary. This may result in read or write operations on unexpected memory locations that could be linked to other variables, data structures, or internal program data."
            },
            "similarity": 111.36188330126429
          },
          {
            "metadata": {
              "doc_id": "1284",
              "name": "Improper Validation of Specified Quantity in Input",
              "source": "sparse",
              "original_content": "The product receives input that is expected to specify a quantity (such as size or length), but it does not validate or incorrectly validates that the quantity has the required properties."
            },
            "similarity": 100.94325479182483
          },
          {
            "metadata": {
              "doc_id": "20",
              "name": "Improper Input Validation",
              "source": "sparse",
              "original_content": "The product receives input or data, but it does\n        not validate or incorrectly validates that the input has the\n        properties that are required to process the data safely and\n        correctly."
            },
            "similarity": 100.05345283254238
          },
          {
            "metadata": {
              "doc_id": "190",
              "name": "Integer Overflow or Wraparound",
              "source": "sparse",
              "original_content": "The product performs a calculation that can\n         produce an integer overflow or wraparound when the logic\n         assumes that the resulting value will always be larger than\n         the original value. This occurs when an integer value is\n         incremented to a value that is too large to store in the\n         associated representation. When this occurs, the value may\n         become a very small or negative number."
            },
            "similarity": 98.81324771106345
          },
          {
            "metadata": {
              "doc_id": "121",
              "name": "Stack-based Buffer Overflow",
              "source": "sparse",
              "original_content": "A stack-based buffer overflow condition is a condition where the buffer being overwritten is allocated on the stack (i.e., is a local variable or, rarely, a parameter to a function)."
            },
            "similarity": 96.79490985700558
          }
        ]
      },
      "version:through 2.12": {
        "keyphrase": "through 2.12",
        "type": "version",
        "cwes": [
          {
            "metadata": {
              "doc_id": "119",
              "name": "Improper Restriction of Operations within the Bounds of a Memory Buffer",
              "source": "sparse",
              "original_content": "The product performs operations on a memory buffer, but it reads from or writes to a memory location outside the buffer's intended boundary. This may result in read or write operations on unexpected memory locations that could be linked to other variables, data structures, or internal program data."
            },
            "similarity": 116.37878227146886
          },
          {
            "metadata": {
              "doc_id": "1284",
              "name": "Improper Validation of Specified Quantity in Input",
              "source": "sparse",
              "original_content": "The product receives input that is expected to specify a quantity (such as size or length), but it does not validate or incorrectly validates that the quantity has the required properties."
            },
            "similarity": 109.43048785350159
          },
          {
            "metadata": {
              "doc_id": "20",
              "name": "Improper Input Validation",
              "source": "sparse",
              "original_content": "The product receives input or data, but it does\n        not validate or incorrectly validates that the input has the\n        properties that are required to process the data safely and\n        correctly."
            },
            "similarity": 105.55201834054299
          },
          {
            "metadata": {
              "doc_id": "121",
              "name": "Stack-based Buffer Overflow",
              "source": "sparse",
              "original_content": "A stack-based buffer overflow condition is a condition where the buffer being overwritten is allocated on the stack (i.e., is a local variable or, rarely, a parameter to a function)."
            },
            "similarity": 105.34144565598619
          },
          {
            "metadata": {
              "doc_id": "190",
              "name": "Integer Overflow or Wraparound",
              "source": "sparse",
              "original_content": "The product performs a calculation that can\n         produce an integer overflow or wraparound when the logic\n         assumes that the resulting value will always be larger than\n         the original value. This occurs when an integer value is\n         incremented to a value that is too large to store in the\n         associated representation. When this occurs, the value may\n         become a very small or negative number."
            },
            "similarity": 104.30249027485037
          }
        ]
      }
    },
    "keyphrase_mapping": {
      "119": [
        {
          "id": "rootcause:improper deserialization",
          "keyphrase": "improper deserialization",
          "type": "rootcause"
        },
        {
          "id": "rootcause:improper input validation",
          "keyphrase": "improper input validation",
          "type": "rootcause"
        },
        {
          "id": "rootcause:improper restriction of operations within the bounds of a memory buffer",
          "keyphrase": "improper restriction of operations within the bounds of a memory buffer",
          "type": "rootcause"
        },
        {
          "id": "weakness:deserialization",
          "keyphrase": "deserialization",
          "type": "weakness"
        },
        {
          "id": "impact:CPU consumption",
          "keyphrase": "CPU consumption",
          "type": "impact"
        },
        {
          "id": "impact:Denial-of-Service (DoS) attacks and possibly remote code execution",
          "keyphrase": "Denial-of-Service (DoS) attacks and possibly remote code execution",
          "type": "impact"
        },
        {
          "id": "vector:XmlMessage document",
          "keyphrase": "XmlMessage document",
          "type": "vector"
        },
        {
          "id": "product:UCI IDOL 2",
          "keyphrase": "UCI IDOL 2",
          "type": "product"
        },
        {
          "id": "version:through 2.12",
          "keyphrase": "through 2.12",
          "type": "version"
        }
      ],
      "502": [
        {
          "id": "rootcause:improper deserialization",
          "keyphrase": "improper deserialization",
          "type": "rootcause"
        },
        {
          "id": "weakness:deserialization",
          "keyphrase": "deserialization",
          "type": "weakness"
        }
      ],
      "20": [
        {
          "id": "rootcause:improper deserialization",
          "keyphrase": "improper deserialization",
          "type": "rootcause"
        },
        {
          "id": "rootcause:improper input validation",
          "keyphrase": "improper input validation",
          "type": "rootcause"
        },
        {
          "id": "weakness:deserialization",
          "keyphrase": "deserialization",
          "type": "weakness"
        },
        {
          "id": "impact:Denial-of-Service (DoS) attacks and possibly remote code execution",
          "keyphrase": "Denial-of-Service (DoS) attacks and possibly remote code execution",
          "type": "impact"
        },
        {
          "id": "vector:XmlMessage document",
          "keyphrase": "XmlMessage document",
          "type": "vector"
        },
        {
          "id": "product:UCI IDOL 2",
          "keyphrase": "UCI IDOL 2",
          "type": "product"
        },
        {
          "id": "version:through 2.12",
          "keyphrase": "through 2.12",
          "type": "version"
        }
      ],
      "1284": [
        {
          "id": "rootcause:improper deserialization",
          "keyphrase": "improper deserialization",
          "type": "rootcause"
        },
        {
          "id": "rootcause:improper input validation",
          "keyphrase": "improper input validation",
          "type": "rootcause"
        },
        {
          "id": "rootcause:improper restriction of operations within the bounds of a memory buffer",
          "keyphrase": "improper restriction of operations within the bounds of a memory buffer",
          "type": "rootcause"
        },
        {
          "id": "weakness:deserialization",
          "keyphrase": "deserialization",
          "type": "weakness"
        },
        {
          "id": "impact:CPU consumption",
          "keyphrase": "CPU consumption",
          "type": "impact"
        },
        {
          "id": "impact:Denial-of-Service (DoS) attacks and possibly remote code execution",
          "keyphrase": "Denial-of-Service (DoS) attacks and possibly remote code execution",
          "type": "impact"
        },
        {
          "id": "vector:XmlMessage document",
          "keyphrase": "XmlMessage document",
          "type": "vector"
        },
        {
          "id": "product:UCI IDOL 2",
          "keyphrase": "UCI IDOL 2",
          "type": "product"
        },
        {
          "id": "version:through 2.12",
          "keyphrase": "through 2.12",
          "type": "version"
        }
      ],
      "190": [
        {
          "id": "rootcause:improper deserialization",
          "keyphrase": "improper deserialization",
          "type": "rootcause"
        },
        {
          "id": "rootcause:improper input validation",
          "keyphrase": "improper input validation",
          "type": "rootcause"
        },
        {
          "id": "rootcause:improper restriction of operations within the bounds of a memory buffer",
          "keyphrase": "improper restriction of operations within the bounds of a memory buffer",
          "type": "rootcause"
        },
        {
          "id": "weakness:deserialization",
          "keyphrase": "deserialization",
          "type": "weakness"
        },
        {
          "id": "vector:XmlMessage document",
          "keyphrase": "XmlMessage document",
          "type": "vector"
        },
        {
          "id": "product:UCI IDOL 2",
          "keyphrase": "UCI IDOL 2",
          "type": "product"
        },
        {
          "id": "version:through 2.12",
          "keyphrase": "through 2.12",
          "type": "version"
        }
      ],
      "1285": [
        {
          "id": "rootcause:improper input validation",
          "keyphrase": "improper input validation",
          "type": "rootcause"
        }
      ],
      "125": [
        {
          "id": "rootcause:improper restriction of operations within the bounds of a memory buffer",
          "keyphrase": "improper restriction of operations within the bounds of a memory buffer",
          "type": "rootcause"
        }
      ],
      "122": [
        {
          "id": "rootcause:improper restriction of operations within the bounds of a memory buffer",
          "keyphrase": "improper restriction of operations within the bounds of a memory buffer",
          "type": "rootcause"
        }
      ],
      "407": [
        {
          "id": "impact:CPU consumption",
          "keyphrase": "CPU consumption",
          "type": "impact"
        }
      ],
      "400": [
        {
          "id": "impact:CPU consumption",
          "keyphrase": "CPU consumption",
          "type": "impact"
        }
      ],
      "682": [
        {
          "id": "impact:CPU consumption",
          "keyphrase": "CPU consumption",
          "type": "impact"
        }
      ],
      "121": [
        {
          "id": "impact:Denial-of-Service (DoS) attacks and possibly remote code execution",
          "keyphrase": "Denial-of-Service (DoS) attacks and possibly remote code execution",
          "type": "impact"
        },
        {
          "id": "vector:XmlMessage document",
          "keyphrase": "XmlMessage document",
          "type": "vector"
        },
        {
          "id": "product:UCI IDOL 2",
          "keyphrase": "UCI IDOL 2",
          "type": "product"
        },
        {
          "id": "version:through 2.12",
          "keyphrase": "through 2.12",
          "type": "version"
        }
      ],
      "130": [
        {
          "id": "impact:Denial-of-Service (DoS) attacks and possibly remote code execution",
          "keyphrase": "Denial-of-Service (DoS) attacks and possibly remote code execution",
          "type": "impact"
        }
      ]
    },
    "relevant_cwes": [
      {
        "metadata": {
          "doc_id": "125",
          "name": "Out-of-bounds Read",
          "source": "sparse",
          "original_content": "The product reads data past the end, or before the beginning, of the intended buffer.",
          "keyphrase_sources": [
            {
              "id": "rootcause:improper restriction of operations within the bounds of a memory buffer",
              "keyphrase": "improper restriction of operations within the bounds of a memory buffer",
              "type": "rootcause"
            }
          ]
        },
        "similarity": 460.3432024944727
      },
      {
        "metadata": {
          "doc_id": "122",
          "name": "Heap-based Buffer Overflow",
          "source": "sparse",
          "original_content": "A heap overflow condition is a buffer overflow, where the buffer that can be overwritten is allocated in the heap portion of memory, generally meaning that the buffer was allocated using a routine such as malloc().",
          "keyphrase_sources": [
            {
              "id": "rootcause:improper restriction of operations within the bounds of a memory buffer",
              "keyphrase": "improper restriction of operations within the bounds of a memory buffer",
              "type": "rootcause"
            }
          ]
        },
        "similarity": 449.2766486420322
      },
      {
        "metadata": {
          "doc_id": "119",
          "name": "Improper Restriction of Operations within the Bounds of a Memory Buffer",
          "source": "sparse",
          "original_content": "The product performs operations on a memory buffer, but it reads from or writes to a memory location outside the buffer's intended boundary. This may result in read or write operations on unexpected memory locations that could be linked to other variables, data structures, or internal program data.",
          "keyphrase_sources": [
            {
              "id": "rootcause:improper deserialization",
              "keyphrase": "improper deserialization",
              "type": "rootcause"
            },
            {
              "id": "rootcause:improper input validation",
              "keyphrase": "improper input validation",
              "type": "rootcause"
            },
            {
              "id": "rootcause:improper restriction of operations within the bounds of a memory buffer",
              "keyphrase": "improper restriction of operations within the bounds of a memory buffer",
              "type": "rootcause"
            },
            {
              "id": "weakness:deserialization",
              "keyphrase": "deserialization",
              "type": "weakness"
            },
            {
              "id": "impact:CPU consumption",
              "keyphrase": "CPU consumption",
              "type": "impact"
            },
            {
              "id": "impact:Denial-of-Service (DoS) attacks and possibly remote code execution",
              "keyphrase": "Denial-of-Service (DoS) attacks and possibly remote code execution",
              "type": "impact"
            },
            {
              "id": "vector:XmlMessage document",
              "keyphrase": "XmlMessage document",
              "type": "vector"
            },
            {
              "id": "product:UCI IDOL 2",
              "keyphrase": "UCI IDOL 2",
              "type": "product"
            },
            {
              "id": "version:through 2.12",
              "keyphrase": "through 2.12",
              "type": "version"
            }
          ]
        },
        "similarity": 336.4639277717134
      },
      {
        "metadata": {
          "doc_id": "502",
          "name": "Deserialization of Untrusted Data",
          "source": "sparse",
          "original_content": "The product deserializes untrusted data without sufficiently ensuring that the resulting data will be valid.",
          "keyphrase_sources": [
            {
              "id": "rootcause:improper deserialization",
              "keyphrase": "improper deserialization",
              "type": "rootcause"
            },
            {
              "id": "weakness:deserialization",
              "keyphrase": "deserialization",
              "type": "weakness"
            }
          ]
        },
        "similarity": 327.11946044926316
      },
      {
        "metadata": {
          "doc_id": "20",
          "name": "Improper Input Validation",
          "source": "sparse",
          "original_content": "The product receives input or data, but it does\n        not validate or incorrectly validates that the input has the\n        properties that are required to process the data safely and\n        correctly.",
          "keyphrase_sources": [
            {
              "id": "rootcause:improper deserialization",
              "keyphrase": "improper deserialization",
              "type": "rootcause"
            },
            {
              "id": "rootcause:improper input validation",
              "keyphrase": "improper input validation",
              "type": "rootcause"
            },
            {
              "id": "weakness:deserialization",
              "keyphrase": "deserialization",
              "type": "weakness"
            },
            {
              "id": "impact:Denial-of-Service (DoS) attacks and possibly remote code execution",
              "keyphrase": "Denial-of-Service (DoS) attacks and possibly remote code execution",
              "type": "impact"
            },
            {
              "id": "vector:XmlMessage document",
              "keyphrase": "XmlMessage document",
              "type": "vector"
            },
            {
              "id": "product:UCI IDOL 2",
              "keyphrase": "UCI IDOL 2",
              "type": "product"
            },
            {
              "id": "version:through 2.12",
              "keyphrase": "through 2.12",
              "type": "version"
            }
          ]
        },
        "similarity": 305.2237722113356
      },
      {
        "metadata": {
          "doc_id": "1285",
          "name": "Improper Validation of Specified Index, Position, or Offset in Input",
          "source": "sparse",
          "original_content": "The product receives input that is expected to specify an index, position, or offset into an indexable resource such as a buffer or file, but it does not validate or incorrectly validates that the specified index/position/offset has the required properties.",
          "keyphrase_sources": [
            {
              "id": "rootcause:improper input validation",
              "keyphrase": "improper input validation",
              "type": "rootcause"
            }
          ]
        },
        "similarity": 302.4014724982968
      },
      {
        "metadata": {
          "doc_id": "1284",
          "name": "Improper Validation of Specified Quantity in Input",
          "source": "sparse",
          "original_content": "The product receives input that is expected to specify a quantity (such as size or length), but it does not validate or incorrectly validates that the quantity has the required properties.",
          "keyphrase_sources": [
            {
              "id": "rootcause:improper deserialization",
              "keyphrase": "improper deserialization",
              "type": "rootcause"
            },
            {
              "id": "rootcause:improper input validation",
              "keyphrase": "improper input validation",
              "type": "rootcause"
            },
            {
              "id": "rootcause:improper restriction of operations within the bounds of a memory buffer",
              "keyphrase": "improper restriction of operations within the bounds of a memory buffer",
              "type": "rootcause"
            },
            {
              "id": "weakness:deserialization",
              "keyphrase": "deserialization",
              "type": "weakness"
            },
            {
              "id": "impact:CPU consumption",
              "keyphrase": "CPU consumption",
              "type": "impact"
            },
            {
              "id": "impact:Denial-of-Service (DoS) attacks and possibly remote code execution",
              "keyphrase": "Denial-of-Service (DoS) attacks and possibly remote code execution",
              "type": "impact"
            },
            {
              "id": "vector:XmlMessage document",
              "keyphrase": "XmlMessage document",
              "type": "vector"
            },
            {
              "id": "product:UCI IDOL 2",
              "keyphrase": "UCI IDOL 2",
              "type": "product"
            },
            {
              "id": "version:through 2.12",
              "keyphrase": "through 2.12",
              "type": "version"
            }
          ]
        },
        "similarity": 302.33029527394814
      },
      {
        "metadata": {
          "doc_id": "190",
          "name": "Integer Overflow or Wraparound",
          "source": "sparse",
          "original_content": "The product performs a calculation that can\n         produce an integer overflow or wraparound when the logic\n         assumes that the resulting value will always be larger than\n         the original value. This occurs when an integer value is\n         incremented to a value that is too large to store in the\n         associated representation. When this occurs, the value may\n         become a very small or negative number.",
          "keyphrase_sources": [
            {
              "id": "rootcause:improper deserialization",
              "keyphrase": "improper deserialization",
              "type": "rootcause"
            },
            {
              "id": "rootcause:improper input validation",
              "keyphrase": "improper input validation",
              "type": "rootcause"
            },
            {
              "id": "rootcause:improper restriction of operations within the bounds of a memory buffer",
              "keyphrase": "improper restriction of operations within the bounds of a memory buffer",
              "type": "rootcause"
            },
            {
              "id": "weakness:deserialization",
              "keyphrase": "deserialization",
              "type": "weakness"
            },
            {
              "id": "vector:XmlMessage document",
              "keyphrase": "XmlMessage document",
              "type": "vector"
            },
            {
              "id": "product:UCI IDOL 2",
              "keyphrase": "UCI IDOL 2",
              "type": "product"
            },
            {
              "id": "version:through 2.12",
              "keyphrase": "through 2.12",
              "type": "version"
            }
          ]
        },
        "similarity": 294.5719851695843
      },
      {
        "metadata": {
          "doc_id": "121",
          "name": "Stack-based Buffer Overflow",
          "source": "sparse",
          "original_content": "A stack-based buffer overflow condition is a condition where the buffer being overwritten is allocated on the stack (i.e., is a local variable or, rarely, a parameter to a function).",
          "keyphrase_sources": [
            {
              "id": "impact:Denial-of-Service (DoS) attacks and possibly remote code execution",
              "keyphrase": "Denial-of-Service (DoS) attacks and possibly remote code execution",
              "type": "impact"
            },
            {
              "id": "vector:XmlMessage document",
              "keyphrase": "XmlMessage document",
              "type": "vector"
            },
            {
              "id": "product:UCI IDOL 2",
              "keyphrase": "UCI IDOL 2",
              "type": "product"
            },
            {
              "id": "version:through 2.12",
              "keyphrase": "through 2.12",
              "type": "version"
            }
          ]
        },
        "similarity": 132.58084227610865
      },
      {
        "metadata": {
          "doc_id": "130",
          "name": "Improper Handling of Length Parameter Inconsistency",
          "source": "sparse",
          "original_content": "The product parses a formatted message or structure, but it does not handle or incorrectly handles a length field that is inconsistent with the actual length of the associated data.",
          "keyphrase_sources": [
            {
              "id": "impact:Denial-of-Service (DoS) attacks and possibly remote code execution",
              "keyphrase": "Denial-of-Service (DoS) attacks and possibly remote code execution",
              "type": "impact"
            }
          ]
        },
        "similarity": 131.846381482813
      },
      {
        "metadata": {
          "doc_id": "407",
          "name": "Inefficient Algorithmic Complexity",
          "source": "sparse",
          "original_content": "An algorithm in a product has an inefficient worst-case computational complexity that may be detrimental to system performance and can be triggered by an attacker, typically using crafted manipulations that ensure that the worst case is being reached.",
          "keyphrase_sources": [
            {
              "id": "impact:CPU consumption",
              "keyphrase": "CPU consumption",
              "type": "impact"
            }
          ]
        },
        "similarity": 110.52633503396007
      },
      {
        "metadata": {
          "doc_id": "400",
          "name": "Uncontrolled Resource Consumption",
          "source": "sparse",
          "original_content": "The product does not properly control the allocation and maintenance of a limited resource, thereby enabling an actor to influence the amount of resources consumed, eventually leading to the exhaustion of available resources.",
          "keyphrase_sources": [
            {
              "id": "impact:CPU consumption",
              "keyphrase": "CPU consumption",
              "type": "impact"
            }
          ]
        },
        "similarity": 108.77496865339428
      },
      {
        "metadata": {
          "doc_id": "682",
          "name": "Incorrect Calculation",
          "source": "sparse",
          "original_content": "The product performs a calculation that generates incorrect or unintended results that are later used in security-critical decisions or resource management.",
          "keyphrase_sources": [
            {
              "id": "impact:CPU consumption",
              "keyphrase": "CPU consumption",
              "type": "impact"
            }
          ]
        },
        "similarity": 105.74955975995562
      }
    ],
    "enhanced_query": "# Vulnerability Description\n\n    An issue was discovered in UCI IDOL 2 (aka uciIDOL or IDOL2) through 2.12. Due to **improper input validation**, **improper **deserialization****, and **improper restriction of operations within the bounds of a memory buffer**, IDOL2 is vulnerable to Denial-of-Service (DoS) attacks and possibly remote code execution. A certain XmlMessage document causes 100% CPU consumption.\n\n    # Keyphrase-Specific CWE Analysis\n    This vulnerability contains multiple keyphrases that may map to different CWEs. \n    Please analyze each keyphrase separately and determine the most appropriate CWE(s) for each.\n\n    ## ROOTCAUSE: 'improper restriction of operations within the bounds of a memory buffer'\n\nRelevant CWEs for this ROOTCAUSE:\n\n### 1. CWE-125: Out-of-bounds Read (Score: 460.34)\n\nThe product reads data past the end, or before the beginning, of the intended buffer....\n\n### 2. CWE-122: Heap-based Buffer Overflow (Score: 449.28)\n\nA heap overflow condition is a buffer overflow, where the buffer that can be overwritten is allocated in the heap portion of memory, generally meaning that the buffer was allocated using a routine such as malloc()....\n\n### 3. CWE-119: Improper Restriction of Operations within the Bounds of a Memory Buffer (Score: 336.46)\n\nThe product performs operations on a memory buffer, but it reads from or writes to a memory location outside the buffer's intended boundary. This may result in read or write operations on unexpected memory locations that could be linked to other variables, data structures, or internal program data....\n\n### 4. CWE-1284: Improper Validation of Specified Quantity in Input (Score: 302.33)\n\nThe product receives input that is expected to specify a quantity (such as size or length), but it does not validate or incorrectly validates that the quantity has the required properties....\n\n### 5. CWE-190: Integer Overflow or Wraparound (Score: 294.57)\n\nThe product performs a calculation that can\n         produce an integer overflow or wraparound when the logic\n         assumes that the resulting value will always be larger than\n         the original value. This occurs when an integer value is\n         incremented to a value that is too large to st...\n\n## ROOTCAUSE: 'improper deserialization'\n\nRelevant CWEs for this ROOTCAUSE:\n\n### 1. CWE-119: Improper Restriction of Operations within the Bounds of a Memory Buffer (Score: 336.46)\n\nThe product performs operations on a memory buffer, but it reads from or writes to a memory location outside the buffer's intended boundary. This may result in read or write operations on unexpected memory locations that could be linked to other variables, data structures, or internal program data....\n\n### 2. CWE-502: Deserialization of Untrusted Data (Score: 327.12)\n\nThe product deserializes untrusted data without sufficiently ensuring that the resulting data will be valid....\n\n### 3. CWE-20: Improper Input Validation (Score: 305.22)\n\nThe product receives input or data, but it does\n        not validate or incorrectly validates that the input has the\n        properties that are required to process the data safely and\n        correctly....\n\n### 4. CWE-1284: Improper Validation of Specified Quantity in Input (Score: 302.33)\n\nThe product receives input that is expected to specify a quantity (such as size or length), but it does not validate or incorrectly validates that the quantity has the required properties....\n\n### 5. CWE-190: Integer Overflow or Wraparound (Score: 294.57)\n\nThe product performs a calculation that can\n         produce an integer overflow or wraparound when the logic\n         assumes that the resulting value will always be larger than\n         the original value. This occurs when an integer value is\n         incremented to a value that is too large to st...\n\n## ROOTCAUSE: 'improper input validation'\n\nRelevant CWEs for this ROOTCAUSE:\n\n### 1. CWE-119: Improper Restriction of Operations within the Bounds of a Memory Buffer (Score: 336.46)\n\nThe product performs operations on a memory buffer, but it reads from or writes to a memory location outside the buffer's intended boundary. This may result in read or write operations on unexpected memory locations that could be linked to other variables, data structures, or internal program data....\n\n### 2. CWE-20: Improper Input Validation (Score: 305.22)\n\nThe product receives input or data, but it does\n        not validate or incorrectly validates that the input has the\n        properties that are required to process the data safely and\n        correctly....\n\n### 3. CWE-1285: Improper Validation of Specified Index, Position, or Offset in Input (Score: 302.40)\n\nThe product receives input that is expected to specify an index, position, or offset into an indexable resource such as a buffer or file, but it does not validate or incorrectly validates that the specified index/position/offset has the required properties....\n\n### 4. CWE-1284: Improper Validation of Specified Quantity in Input (Score: 302.33)\n\nThe product receives input that is expected to specify a quantity (such as size or length), but it does not validate or incorrectly validates that the quantity has the required properties....\n\n### 5. CWE-190: Integer Overflow or Wraparound (Score: 294.57)\n\nThe product performs a calculation that can\n         produce an integer overflow or wraparound when the logic\n         assumes that the resulting value will always be larger than\n         the original value. This occurs when an integer value is\n         incremented to a value that is too large to st...\n\n## WEAKNESS: 'deserialization'\n\nRelevant CWEs for this WEAKNESS:\n\n### 1. CWE-119: Improper Restriction of Operations within the Bounds of a Memory Buffer (Score: 336.46)\n\nThe product performs operations on a memory buffer, but it reads from or writes to a memory location outside the buffer's intended boundary. This may result in read or write operations on unexpected memory locations that could be linked to other variables, data structures, or internal program data....\n\n### 2. CWE-502: Deserialization of Untrusted Data (Score: 327.12)\n\nThe product deserializes untrusted data without sufficiently ensuring that the resulting data will be valid....\n\n### 3. CWE-20: Improper Input Validation (Score: 305.22)\n\nThe product receives input or data, but it does\n        not validate or incorrectly validates that the input has the\n        properties that are required to process the data safely and\n        correctly....\n\n### 4. CWE-1284: Improper Validation of Specified Quantity in Input (Score: 302.33)\n\nThe product receives input that is expected to specify a quantity (such as size or length), but it does not validate or incorrectly validates that the quantity has the required properties....\n\n### 5. CWE-190: Integer Overflow or Wraparound (Score: 294.57)\n\nThe product performs a calculation that can\n         produce an integer overflow or wraparound when the logic\n         assumes that the resulting value will always be larger than\n         the original value. This occurs when an integer value is\n         incremented to a value that is too large to st...\n\n## IMPACT: 'CPU consumption'\n\nRelevant CWEs for this IMPACT:\n\n### 1. CWE-119: Improper Restriction of Operations within the Bounds of a Memory Buffer (Score: 336.46)\n\nThe product performs operations on a memory buffer, but it reads from or writes to a memory location outside the buffer's intended boundary. This may result in read or write operations on unexpected memory locations that could be linked to other variables, data structures, or internal program data....\n\n### 2. CWE-1284: Improper Validation of Specified Quantity in Input (Score: 302.33)\n\nThe product receives input that is expected to specify a quantity (such as size or length), but it does not validate or incorrectly validates that the quantity has the required properties....\n\n### 3. CWE-407: Inefficient Algorithmic Complexity (Score: 110.53)\n\nAn algorithm in a product has an inefficient worst-case computational complexity that may be detrimental to system performance and can be triggered by an attacker, typically using crafted manipulations that ensure that the worst case is being reached....\n\n### 4. CWE-400: Uncontrolled Resource Consumption (Score: 108.77)\n\nThe product does not properly control the allocation and maintenance of a limited resource, thereby enabling an actor to influence the amount of resources consumed, eventually leading to the exhaustion of available resources....\n\n### 5. CWE-682: Incorrect Calculation (Score: 105.75)\n\nThe product performs a calculation that generates incorrect or unintended results that are later used in security-critical decisions or resource management....\n\n## IMPACT: 'Denial-of-Service (DoS) attacks and possibly remote code execution'\n\nRelevant CWEs for this IMPACT:\n\n### 1. CWE-119: Improper Restriction of Operations within the Bounds of a Memory Buffer (Score: 336.46)\n\nThe product performs operations on a memory buffer, but it reads from or writes to a memory location outside the buffer's intended boundary. This may result in read or write operations on unexpected memory locations that could be linked to other variables, data structures, or internal program data....\n\n### 2. CWE-20: Improper Input Validation (Score: 305.22)\n\nThe product receives input or data, but it does\n        not validate or incorrectly validates that the input has the\n        properties that are required to process the data safely and\n        correctly....\n\n### 3. CWE-1284: Improper Validation of Specified Quantity in Input (Score: 302.33)\n\nThe product receives input that is expected to specify a quantity (such as size or length), but it does not validate or incorrectly validates that the quantity has the required properties....\n\n### 4. CWE-121: Stack-based Buffer Overflow (Score: 132.58)\n\nA stack-based buffer overflow condition is a condition where the buffer being overwritten is allocated on the stack (i.e., is a local variable or, rarely, a parameter to a function)....\n\n### 5. CWE-130: Improper Handling of Length Parameter Inconsistency (Score: 131.85)\n\nThe product parses a formatted message or structure, but it does not handle or incorrectly handles a length field that is inconsistent with the actual length of the associated data....\n\n## VECTOR: 'XmlMessage document'\n\nRelevant CWEs for this VECTOR:\n\n### 1. CWE-119: Improper Restriction of Operations within the Bounds of a Memory Buffer (Score: 336.46)\n\nThe product performs operations on a memory buffer, but it reads from or writes to a memory location outside the buffer's intended boundary. This may result in read or write operations on unexpected memory locations that could be linked to other variables, data structures, or internal program data....\n\n### 2. CWE-20: Improper Input Validation (Score: 305.22)\n\nThe product receives input or data, but it does\n        not validate or incorrectly validates that the input has the\n        properties that are required to process the data safely and\n        correctly....\n\n### 3. CWE-1284: Improper Validation of Specified Quantity in Input (Score: 302.33)\n\nThe product receives input that is expected to specify a quantity (such as size or length), but it does not validate or incorrectly validates that the quantity has the required properties....\n\n### 4. CWE-190: Integer Overflow or Wraparound (Score: 294.57)\n\nThe product performs a calculation that can\n         produce an integer overflow or wraparound when the logic\n         assumes that the resulting value will always be larger than\n         the original value. This occurs when an integer value is\n         incremented to a value that is too large to st...\n\n### 5. CWE-121: Stack-based Buffer Overflow (Score: 132.58)\n\nA stack-based buffer overflow condition is a condition where the buffer being overwritten is allocated on the stack (i.e., is a local variable or, rarely, a parameter to a function)....\n\n## PRODUCT: 'UCI IDOL 2'\n\nRelevant CWEs for this PRODUCT:\n\n### 1. CWE-119: Improper Restriction of Operations within the Bounds of a Memory Buffer (Score: 336.46)\n\nThe product performs operations on a memory buffer, but it reads from or writes to a memory location outside the buffer's intended boundary. This may result in read or write operations on unexpected memory locations that could be linked to other variables, data structures, or internal program data....\n\n### 2. CWE-20: Improper Input Validation (Score: 305.22)\n\nThe product receives input or data, but it does\n        not validate or incorrectly validates that the input has the\n        properties that are required to process the data safely and\n        correctly....\n\n### 3. CWE-1284: Improper Validation of Specified Quantity in Input (Score: 302.33)\n\nThe product receives input that is expected to specify a quantity (such as size or length), but it does not validate or incorrectly validates that the quantity has the required properties....\n\n### 4. CWE-190: Integer Overflow or Wraparound (Score: 294.57)\n\nThe product performs a calculation that can\n         produce an integer overflow or wraparound when the logic\n         assumes that the resulting value will always be larger than\n         the original value. This occurs when an integer value is\n         incremented to a value that is too large to st...\n\n### 5. CWE-121: Stack-based Buffer Overflow (Score: 132.58)\n\nA stack-based buffer overflow condition is a condition where the buffer being overwritten is allocated on the stack (i.e., is a local variable or, rarely, a parameter to a function)....\n\n## VERSION: 'through 2.12'\n\nRelevant CWEs for this VERSION:\n\n### 1. CWE-119: Improper Restriction of Operations within the Bounds of a Memory Buffer (Score: 336.46)\n\nThe product performs operations on a memory buffer, but it reads from or writes to a memory location outside the buffer's intended boundary. This may result in read or write operations on unexpected memory locations that could be linked to other variables, data structures, or internal program data....\n\n### 2. CWE-20: Improper Input Validation (Score: 305.22)\n\nThe product receives input or data, but it does\n        not validate or incorrectly validates that the input has the\n        properties that are required to process the data safely and\n        correctly....\n\n### 3. CWE-1284: Improper Validation of Specified Quantity in Input (Score: 302.33)\n\nThe product receives input that is expected to specify a quantity (such as size or length), but it does not validate or incorrectly validates that the quantity has the required properties....\n\n### 4. CWE-190: Integer Overflow or Wraparound (Score: 294.57)\n\nThe product performs a calculation that can\n         produce an integer overflow or wraparound when the logic\n         assumes that the resulting value will always be larger than\n         the original value. This occurs when an integer value is\n         incremented to a value that is too large to st...\n\n### 5. CWE-121: Stack-based Buffer Overflow (Score: 132.58)\n\nA stack-based buffer overflow condition is a condition where the buffer being overwritten is allocated on the stack (i.e., is a local variable or, rarely, a parameter to a function)....\n\n\n    # Analysis Instructions\n    1. For each keyphrase, identify the most appropriate CWE(s) that represent the weakness.\n    2. Consider how the different keyphrases might relate to each other in the vulnerability chain.\n    3. Provide a final determination of primary CWE(s) and any secondary CWEs.\n    4. Format your response using the standard analysis template.\n\n    Please analyze how these different weaknesses interact and provide a comprehensive CWE classification.\n    "
  },
  "retrieval_time": 1.3563358783721924
}