{
  "vulnerability_info": "VulnerabilityInfo(cve_id='CVE-2024-8936', description='CWE-20 **Improper Input Validation** vulnerability exists that could lead to loss of confidentiality of controller memory after a successful Man-In-The-Middle attack followed by sending a crafted Modbus function call used to tamper with memory.', key_phrases={'rootcause': ['Improper Input Validation', 'Input Validation vulnerability'], 'weakness': '', 'impact': 'loss of confidentiality of controller memory', 'vector': 'Man-In-The-Middle attack followed by sending a crafted Modbus function call', 'attacker': '', 'product': '', 'version': '', 'component': ''}, reference_content='Based on the provided document, here\\'s the breakdown of CVE-2024-8936:\\n\\n**Root cause of vulnerability:**\\n- Improper Input Validation. The vulnerability stems from the lack of proper validation of input data, specifically within Modbus function calls used to manipulate controller memory.\\n\\n**Weaknesses/vulnerabilities present:**\\n- CWE-20: Improper Input Validation. This vulnerability allows an attacker to potentially manipulate memory by sending crafted Modbus requests, bypassing input validation checks.\\n\\n**Impact of exploitation:**\\n- Loss of confidentiality of controller memory. An attacker could potentially read sensitive information from the controller\\'s memory.\\n\\n**Attack vectors:**\\n- Network-based attack, specifically through Modbus communication.\\n- Requires a Man-In-The-Middle (MITM) position to intercept and modify network traffic.\\n\\n**Required attacker capabilities/position:**\\n- The attacker must be able to perform a successful Man-in-the-Middle attack.\\n- The attacker needs to craft a malicious Modbus function call to target the memory.\\n- No authentication is explicitly required to perform this attack as it relies on improper input validation.\\n\\n**Additional details:**\\n\\n- The affected products include Modicon M340, MC80, and Momentum Unity M1E processors. However, only Modicon M340 is affected by CVE-2024-8936 and only versions prior to SV3.65.\\n- The vulnerability is classified as \"Medium\" severity with a CVSS v3.1 base score of 6.5 and a \"High\" severity with a CVSS v4.0 base score of 8.3.\\n- The exploit requires a high attack complexity (AC:H) and physical proximity (AT:P) under CVSS v4.0.\\n- The provided mitigations are centered around network segmentation, firewalling (blocking unauthorized access to port 502/TCP), and access control lists based on recommendations of the user manuals.', similar_info={'cwe_distribution': {}, 'cwe_consensus': '', 'similarity_stats': {'thresholds': [], 'total_samples_by_threshold': {}, 'top_cwes_by_threshold': {}}}, similarity_summary=SimilarityInsight(consensus_cwe='', top_cwes=[], confidence_levels={}, total_samples=0), analysis='', analysis_with_relationships='', criticism='', resolution='', relevant_cwes=[{'metadata': {'doc_id': '20', 'name': 'Improper Input Validation', 'source': 'sparse', 'original_content': 'The product receives input or data, but it does\\n        not validate or incorrectly validates that the input has the\\n        properties that are required to process the data safely and\\n        correctly.', 'keyphrase_sources': [{'id': 'rootcause:Improper Input Validation', 'keyphrase': 'Improper Input Validation', 'type': 'rootcause'}, {'id': 'rootcause:Input Validation vulnerability', 'keyphrase': 'Input Validation vulnerability', 'type': 'rootcause'}, {'id': 'impact:loss of confidentiality of controller memory', 'keyphrase': 'loss of confidentiality of controller memory', 'type': 'impact'}]}, 'similarity': np.float64(254.85465155000725)}, {'metadata': {'doc_id': '1284', 'name': 'Improper Validation of Specified Quantity in Input', 'source': 'sparse', 'original_content': 'The product receives input that is expected to specify a quantity (such as size or length), but it does not validate or incorrectly validates that the quantity has the required properties.', 'keyphrase_sources': [{'id': 'rootcause:Improper Input Validation', 'keyphrase': 'Improper Input Validation', 'type': 'rootcause'}, {'id': 'rootcause:Input Validation vulnerability', 'keyphrase': 'Input Validation vulnerability', 'type': 'rootcause'}]}, 'similarity': np.float64(237.90755088630112)}, {'metadata': {'doc_id': '1286', 'name': 'Improper Validation of Syntactic Correctness of Input', 'source': 'sparse', 'original_content': 'The product receives input that is expected to be well-formed - i.e., to comply with a certain syntax - but it does not validate or incorrectly validates that the input complies with the syntax.', 'keyphrase_sources': [{'id': 'rootcause:Improper Input Validation', 'keyphrase': 'Improper Input Validation', 'type': 'rootcause'}, {'id': 'rootcause:Input Validation vulnerability', 'keyphrase': 'Input Validation vulnerability', 'type': 'rootcause'}]}, 'similarity': np.float64(237.75762699210387)}, {'metadata': {'doc_id': '119', 'name': 'Improper Restriction of Operations within the Bounds of a Memory Buffer', 'source': 'sparse', 'original_content': \"The product performs operations on a memory buffer, but it reads from or writes to a memory location outside the buffer's intended boundary. This may result in read or write operations on unexpected memory locations that could be linked to other variables, data structures, or internal program data.\", 'keyphrase_sources': [{'id': 'rootcause:Improper Input Validation', 'keyphrase': 'Improper Input Validation', 'type': 'rootcause'}, {'id': 'rootcause:Input Validation vulnerability', 'keyphrase': 'Input Validation vulnerability', 'type': 'rootcause'}, {'id': 'impact:loss of confidentiality of controller memory', 'keyphrase': 'loss of confidentiality of controller memory', 'type': 'impact'}, {'id': 'vector:Man-In-The-Middle attack followed by sending a crafted Modbus function call', 'keyphrase': 'Man-In-The-Middle attack followed by sending a crafted Modbus function call', 'type': 'vector'}]}, 'similarity': np.float64(233.6893758595104)}, {'metadata': {'doc_id': '295', 'name': 'Improper Certificate Validation', 'source': 'sparse', 'original_content': 'The product does not validate, or incorrectly validates, a certificate.', 'keyphrase_sources': [{'id': 'rootcause:Improper Input Validation', 'keyphrase': 'Improper Input Validation', 'type': 'rootcause'}, {'id': 'rootcause:Input Validation vulnerability', 'keyphrase': 'Input Validation vulnerability', 'type': 'rootcause'}, {'id': 'impact:loss of confidentiality of controller memory', 'keyphrase': 'loss of confidentiality of controller memory', 'type': 'impact'}, {'id': 'vector:Man-In-The-Middle attack followed by sending a crafted Modbus function call', 'keyphrase': 'Man-In-The-Middle attack followed by sending a crafted Modbus function call', 'type': 'vector'}]}, 'similarity': np.float64(230.37733151337193)}, {'metadata': {'doc_id': '300', 'name': 'Channel Accessible by Non-Endpoint', 'source': 'sparse', 'original_content': 'The product does not adequately verify the identity of actors at both ends of a communication channel, or does not adequately ensure the integrity of the channel, in a way that allows the channel to be accessed or influenced by an actor that is not an endpoint.', 'keyphrase_sources': [{'id': 'vector:Man-In-The-Middle attack followed by sending a crafted Modbus function call', 'keyphrase': 'Man-In-The-Middle attack followed by sending a crafted Modbus function call', 'type': 'vector'}]}, 'similarity': np.float64(130.61595452525924)}, {'metadata': {'doc_id': '319', 'name': 'Cleartext Transmission of Sensitive Information', 'source': 'sparse', 'original_content': 'The product transmits sensitive or security-critical data in cleartext in a communication channel that can be sniffed by unauthorized actors.', 'keyphrase_sources': [{'id': 'vector:Man-In-The-Middle attack followed by sending a crafted Modbus function call', 'keyphrase': 'Man-In-The-Middle attack followed by sending a crafted Modbus function call', 'type': 'vector'}]}, 'similarity': np.float64(125.21015883704747)}, {'metadata': {'doc_id': '297', 'name': 'Improper Validation of Certificate with Host Mismatch', 'source': 'sparse', 'original_content': 'The product communicates with a host that provides a certificate, but the product does not properly ensure that the certificate is actually associated with that host.', 'keyphrase_sources': [{'id': 'vector:Man-In-The-Middle attack followed by sending a crafted Modbus function call', 'keyphrase': 'Man-In-The-Middle attack followed by sending a crafted Modbus function call', 'type': 'vector'}]}, 'similarity': np.float64(124.9788781838003)}, {'metadata': {'doc_id': '1262', 'name': 'Improper Access Control for Register Interface', 'source': 'sparse', 'original_content': 'The product uses memory-mapped I/O registers that act as an interface to hardware functionality from software, but there is improper access control to those registers.', 'keyphrase_sources': [{'id': 'impact:loss of confidentiality of controller memory', 'keyphrase': 'loss of confidentiality of controller memory', 'type': 'impact'}]}, 'similarity': np.float64(104.99037409701506)}, {'metadata': {'doc_id': '200', 'name': 'Exposure of Sensitive Information to an Unauthorized Actor', 'source': 'sparse', 'original_content': 'The product exposes sensitive information to an actor that is not explicitly authorized to have access to that information.', 'keyphrase_sources': [{'id': 'impact:loss of confidentiality of controller memory', 'keyphrase': 'loss of confidentiality of controller memory', 'type': 'impact'}]}, 'similarity': np.float64(99.3749794576577)}], identified_cwes={'analyzer': [], 'critic_additional': []})",
  "retrieval_results": {
    "has_multiple_keyphrases": true,
    "keyphrase_cwe_sets": {
      "rootcause:Improper Input Validation": {
        "keyphrase": "Improper Input Validation",
        "type": "rootcause",
        "cwes": [
          {
            "metadata": {
              "doc_id": "20",
              "name": "Improper Input Validation",
              "source": "sparse",
              "original_content": "The product receives input or data, but it does\n        not validate or incorrectly validates that the input has the\n        properties that are required to process the data safely and\n        correctly.",
              "keyphrase_sources": [
                {
                  "id": "rootcause:Improper Input Validation",
                  "keyphrase": "Improper Input Validation",
                  "type": "rootcause"
                },
                {
                  "id": "rootcause:Input Validation vulnerability",
                  "keyphrase": "Input Validation vulnerability",
                  "type": "rootcause"
                },
                {
                  "id": "impact:loss of confidentiality of controller memory",
                  "keyphrase": "loss of confidentiality of controller memory",
                  "type": "impact"
                }
              ]
            },
            "similarity": 254.85465155000725
          },
          {
            "metadata": {
              "doc_id": "1284",
              "name": "Improper Validation of Specified Quantity in Input",
              "source": "sparse",
              "original_content": "The product receives input that is expected to specify a quantity (such as size or length), but it does not validate or incorrectly validates that the quantity has the required properties.",
              "keyphrase_sources": [
                {
                  "id": "rootcause:Improper Input Validation",
                  "keyphrase": "Improper Input Validation",
                  "type": "rootcause"
                },
                {
                  "id": "rootcause:Input Validation vulnerability",
                  "keyphrase": "Input Validation vulnerability",
                  "type": "rootcause"
                }
              ]
            },
            "similarity": 237.90755088630112
          },
          {
            "metadata": {
              "doc_id": "1286",
              "name": "Improper Validation of Syntactic Correctness of Input",
              "source": "sparse",
              "original_content": "The product receives input that is expected to be well-formed - i.e., to comply with a certain syntax - but it does not validate or incorrectly validates that the input complies with the syntax.",
              "keyphrase_sources": [
                {
                  "id": "rootcause:Improper Input Validation",
                  "keyphrase": "Improper Input Validation",
                  "type": "rootcause"
                },
                {
                  "id": "rootcause:Input Validation vulnerability",
                  "keyphrase": "Input Validation vulnerability",
                  "type": "rootcause"
                }
              ]
            },
            "similarity": 237.75762699210387
          },
          {
            "metadata": {
              "doc_id": "119",
              "name": "Improper Restriction of Operations within the Bounds of a Memory Buffer",
              "source": "sparse",
              "original_content": "The product performs operations on a memory buffer, but it reads from or writes to a memory location outside the buffer's intended boundary. This may result in read or write operations on unexpected memory locations that could be linked to other variables, data structures, or internal program data.",
              "keyphrase_sources": [
                {
                  "id": "rootcause:Improper Input Validation",
                  "keyphrase": "Improper Input Validation",
                  "type": "rootcause"
                },
                {
                  "id": "rootcause:Input Validation vulnerability",
                  "keyphrase": "Input Validation vulnerability",
                  "type": "rootcause"
                },
                {
                  "id": "impact:loss of confidentiality of controller memory",
                  "keyphrase": "loss of confidentiality of controller memory",
                  "type": "impact"
                },
                {
                  "id": "vector:Man-In-The-Middle attack followed by sending a crafted Modbus function call",
                  "keyphrase": "Man-In-The-Middle attack followed by sending a crafted Modbus function call",
                  "type": "vector"
                }
              ]
            },
            "similarity": 233.6893758595104
          },
          {
            "metadata": {
              "doc_id": "295",
              "name": "Improper Certificate Validation",
              "source": "sparse",
              "original_content": "The product does not validate, or incorrectly validates, a certificate.",
              "keyphrase_sources": [
                {
                  "id": "rootcause:Improper Input Validation",
                  "keyphrase": "Improper Input Validation",
                  "type": "rootcause"
                },
                {
                  "id": "rootcause:Input Validation vulnerability",
                  "keyphrase": "Input Validation vulnerability",
                  "type": "rootcause"
                },
                {
                  "id": "impact:loss of confidentiality of controller memory",
                  "keyphrase": "loss of confidentiality of controller memory",
                  "type": "impact"
                },
                {
                  "id": "vector:Man-In-The-Middle attack followed by sending a crafted Modbus function call",
                  "keyphrase": "Man-In-The-Middle attack followed by sending a crafted Modbus function call",
                  "type": "vector"
                }
              ]
            },
            "similarity": 230.37733151337193
          }
        ]
      },
      "rootcause:Input Validation vulnerability": {
        "keyphrase": "Input Validation vulnerability",
        "type": "rootcause",
        "cwes": [
          {
            "metadata": {
              "doc_id": "20",
              "name": "Improper Input Validation",
              "source": "sparse",
              "original_content": "The product receives input or data, but it does\n        not validate or incorrectly validates that the input has the\n        properties that are required to process the data safely and\n        correctly."
            },
            "similarity": 250.10167303257282
          },
          {
            "metadata": {
              "doc_id": "1284",
              "name": "Improper Validation of Specified Quantity in Input",
              "source": "sparse",
              "original_content": "The product receives input that is expected to specify a quantity (such as size or length), but it does not validate or incorrectly validates that the quantity has the required properties."
            },
            "similarity": 234.85264102203143
          },
          {
            "metadata": {
              "doc_id": "1286",
              "name": "Improper Validation of Syntactic Correctness of Input",
              "source": "sparse",
              "original_content": "The product receives input that is expected to be well-formed - i.e., to comply with a certain syntax - but it does not validate or incorrectly validates that the input complies with the syntax."
            },
            "similarity": 233.65081732372641
          },
          {
            "metadata": {
              "doc_id": "119",
              "name": "Improper Restriction of Operations within the Bounds of a Memory Buffer",
              "source": "sparse",
              "original_content": "The product performs operations on a memory buffer, but it reads from or writes to a memory location outside the buffer's intended boundary. This may result in read or write operations on unexpected memory locations that could be linked to other variables, data structures, or internal program data."
            },
            "similarity": 229.22482452564424
          },
          {
            "metadata": {
              "doc_id": "295",
              "name": "Improper Certificate Validation",
              "source": "sparse",
              "original_content": "The product does not validate, or incorrectly validates, a certificate."
            },
            "similarity": 227.8833267173078
          }
        ]
      },
      "impact:loss of confidentiality of controller memory": {
        "keyphrase": "loss of confidentiality of controller memory",
        "type": "impact",
        "cwes": [
          {
            "metadata": {
              "doc_id": "119",
              "name": "Improper Restriction of Operations within the Bounds of a Memory Buffer",
              "source": "sparse",
              "original_content": "The product performs operations on a memory buffer, but it reads from or writes to a memory location outside the buffer's intended boundary. This may result in read or write operations on unexpected memory locations that could be linked to other variables, data structures, or internal program data."
            },
            "similarity": 105.68459189517743
          },
          {
            "metadata": {
              "doc_id": "1262",
              "name": "Improper Access Control for Register Interface",
              "source": "sparse",
              "original_content": "The product uses memory-mapped I/O registers that act as an interface to hardware functionality from software, but there is improper access control to those registers.",
              "keyphrase_sources": [
                {
                  "id": "impact:loss of confidentiality of controller memory",
                  "keyphrase": "loss of confidentiality of controller memory",
                  "type": "impact"
                }
              ]
            },
            "similarity": 104.99037409701506
          },
          {
            "metadata": {
              "doc_id": "200",
              "name": "Exposure of Sensitive Information to an Unauthorized Actor",
              "source": "sparse",
              "original_content": "The product exposes sensitive information to an actor that is not explicitly authorized to have access to that information.",
              "keyphrase_sources": [
                {
                  "id": "impact:loss of confidentiality of controller memory",
                  "keyphrase": "loss of confidentiality of controller memory",
                  "type": "impact"
                }
              ]
            },
            "similarity": 99.3749794576577
          },
          {
            "metadata": {
              "doc_id": "20",
              "name": "Improper Input Validation",
              "source": "sparse",
              "original_content": "The product receives input or data, but it does\n        not validate or incorrectly validates that the input has the\n        properties that are required to process the data safely and\n        correctly."
            },
            "similarity": 95.66818293229052
          },
          {
            "metadata": {
              "doc_id": "295",
              "name": "Improper Certificate Validation",
              "source": "sparse",
              "original_content": "The product does not validate, or incorrectly validates, a certificate."
            },
            "similarity": 93.73988572485015
          }
        ]
      },
      "vector:Man-In-The-Middle attack followed by sending a crafted Modbus function call": {
        "keyphrase": "Man-In-The-Middle attack followed by sending a crafted Modbus function call",
        "type": "vector",
        "cwes": [
          {
            "metadata": {
              "doc_id": "300",
              "name": "Channel Accessible by Non-Endpoint",
              "source": "sparse",
              "original_content": "The product does not adequately verify the identity of actors at both ends of a communication channel, or does not adequately ensure the integrity of the channel, in a way that allows the channel to be accessed or influenced by an actor that is not an endpoint.",
              "keyphrase_sources": [
                {
                  "id": "vector:Man-In-The-Middle attack followed by sending a crafted Modbus function call",
                  "keyphrase": "Man-In-The-Middle attack followed by sending a crafted Modbus function call",
                  "type": "vector"
                }
              ]
            },
            "similarity": 130.61595452525924
          },
          {
            "metadata": {
              "doc_id": "295",
              "name": "Improper Certificate Validation",
              "source": "sparse",
              "original_content": "The product does not validate, or incorrectly validates, a certificate."
            },
            "similarity": 126.69239253277055
          },
          {
            "metadata": {
              "doc_id": "319",
              "name": "Cleartext Transmission of Sensitive Information",
              "source": "sparse",
              "original_content": "The product transmits sensitive or security-critical data in cleartext in a communication channel that can be sniffed by unauthorized actors.",
              "keyphrase_sources": [
                {
                  "id": "vector:Man-In-The-Middle attack followed by sending a crafted Modbus function call",
                  "keyphrase": "Man-In-The-Middle attack followed by sending a crafted Modbus function call",
                  "type": "vector"
                }
              ]
            },
            "similarity": 125.21015883704747
          },
          {
            "metadata": {
              "doc_id": "297",
              "name": "Improper Validation of Certificate with Host Mismatch",
              "source": "sparse",
              "original_content": "The product communicates with a host that provides a certificate, but the product does not properly ensure that the certificate is actually associated with that host.",
              "keyphrase_sources": [
                {
                  "id": "vector:Man-In-The-Middle attack followed by sending a crafted Modbus function call",
                  "keyphrase": "Man-In-The-Middle attack followed by sending a crafted Modbus function call",
                  "type": "vector"
                }
              ]
            },
            "similarity": 124.9788781838003
          },
          {
            "metadata": {
              "doc_id": "119",
              "name": "Improper Restriction of Operations within the Bounds of a Memory Buffer",
              "source": "sparse",
              "original_content": "The product performs operations on a memory buffer, but it reads from or writes to a memory location outside the buffer's intended boundary. This may result in read or write operations on unexpected memory locations that could be linked to other variables, data structures, or internal program data."
            },
            "similarity": 119.66334179465677
          }
        ]
      }
    },
    "keyphrase_mapping": {
      "20": [
        {
          "id": "rootcause:Improper Input Validation",
          "keyphrase": "Improper Input Validation",
          "type": "rootcause"
        },
        {
          "id": "rootcause:Input Validation vulnerability",
          "keyphrase": "Input Validation vulnerability",
          "type": "rootcause"
        },
        {
          "id": "impact:loss of confidentiality of controller memory",
          "keyphrase": "loss of confidentiality of controller memory",
          "type": "impact"
        }
      ],
      "1284": [
        {
          "id": "rootcause:Improper Input Validation",
          "keyphrase": "Improper Input Validation",
          "type": "rootcause"
        },
        {
          "id": "rootcause:Input Validation vulnerability",
          "keyphrase": "Input Validation vulnerability",
          "type": "rootcause"
        }
      ],
      "1286": [
        {
          "id": "rootcause:Improper Input Validation",
          "keyphrase": "Improper Input Validation",
          "type": "rootcause"
        },
        {
          "id": "rootcause:Input Validation vulnerability",
          "keyphrase": "Input Validation vulnerability",
          "type": "rootcause"
        }
      ],
      "119": [
        {
          "id": "rootcause:Improper Input Validation",
          "keyphrase": "Improper Input Validation",
          "type": "rootcause"
        },
        {
          "id": "rootcause:Input Validation vulnerability",
          "keyphrase": "Input Validation vulnerability",
          "type": "rootcause"
        },
        {
          "id": "impact:loss of confidentiality of controller memory",
          "keyphrase": "loss of confidentiality of controller memory",
          "type": "impact"
        },
        {
          "id": "vector:Man-In-The-Middle attack followed by sending a crafted Modbus function call",
          "keyphrase": "Man-In-The-Middle attack followed by sending a crafted Modbus function call",
          "type": "vector"
        }
      ],
      "295": [
        {
          "id": "rootcause:Improper Input Validation",
          "keyphrase": "Improper Input Validation",
          "type": "rootcause"
        },
        {
          "id": "rootcause:Input Validation vulnerability",
          "keyphrase": "Input Validation vulnerability",
          "type": "rootcause"
        },
        {
          "id": "impact:loss of confidentiality of controller memory",
          "keyphrase": "loss of confidentiality of controller memory",
          "type": "impact"
        },
        {
          "id": "vector:Man-In-The-Middle attack followed by sending a crafted Modbus function call",
          "keyphrase": "Man-In-The-Middle attack followed by sending a crafted Modbus function call",
          "type": "vector"
        }
      ],
      "1262": [
        {
          "id": "impact:loss of confidentiality of controller memory",
          "keyphrase": "loss of confidentiality of controller memory",
          "type": "impact"
        }
      ],
      "200": [
        {
          "id": "impact:loss of confidentiality of controller memory",
          "keyphrase": "loss of confidentiality of controller memory",
          "type": "impact"
        }
      ],
      "300": [
        {
          "id": "vector:Man-In-The-Middle attack followed by sending a crafted Modbus function call",
          "keyphrase": "Man-In-The-Middle attack followed by sending a crafted Modbus function call",
          "type": "vector"
        }
      ],
      "319": [
        {
          "id": "vector:Man-In-The-Middle attack followed by sending a crafted Modbus function call",
          "keyphrase": "Man-In-The-Middle attack followed by sending a crafted Modbus function call",
          "type": "vector"
        }
      ],
      "297": [
        {
          "id": "vector:Man-In-The-Middle attack followed by sending a crafted Modbus function call",
          "keyphrase": "Man-In-The-Middle attack followed by sending a crafted Modbus function call",
          "type": "vector"
        }
      ]
    },
    "relevant_cwes": [
      {
        "metadata": {
          "doc_id": "20",
          "name": "Improper Input Validation",
          "source": "sparse",
          "original_content": "The product receives input or data, but it does\n        not validate or incorrectly validates that the input has the\n        properties that are required to process the data safely and\n        correctly.",
          "keyphrase_sources": [
            {
              "id": "rootcause:Improper Input Validation",
              "keyphrase": "Improper Input Validation",
              "type": "rootcause"
            },
            {
              "id": "rootcause:Input Validation vulnerability",
              "keyphrase": "Input Validation vulnerability",
              "type": "rootcause"
            },
            {
              "id": "impact:loss of confidentiality of controller memory",
              "keyphrase": "loss of confidentiality of controller memory",
              "type": "impact"
            }
          ]
        },
        "similarity": 254.85465155000725
      },
      {
        "metadata": {
          "doc_id": "1284",
          "name": "Improper Validation of Specified Quantity in Input",
          "source": "sparse",
          "original_content": "The product receives input that is expected to specify a quantity (such as size or length), but it does not validate or incorrectly validates that the quantity has the required properties.",
          "keyphrase_sources": [
            {
              "id": "rootcause:Improper Input Validation",
              "keyphrase": "Improper Input Validation",
              "type": "rootcause"
            },
            {
              "id": "rootcause:Input Validation vulnerability",
              "keyphrase": "Input Validation vulnerability",
              "type": "rootcause"
            }
          ]
        },
        "similarity": 237.90755088630112
      },
      {
        "metadata": {
          "doc_id": "1286",
          "name": "Improper Validation of Syntactic Correctness of Input",
          "source": "sparse",
          "original_content": "The product receives input that is expected to be well-formed - i.e., to comply with a certain syntax - but it does not validate or incorrectly validates that the input complies with the syntax.",
          "keyphrase_sources": [
            {
              "id": "rootcause:Improper Input Validation",
              "keyphrase": "Improper Input Validation",
              "type": "rootcause"
            },
            {
              "id": "rootcause:Input Validation vulnerability",
              "keyphrase": "Input Validation vulnerability",
              "type": "rootcause"
            }
          ]
        },
        "similarity": 237.75762699210387
      },
      {
        "metadata": {
          "doc_id": "119",
          "name": "Improper Restriction of Operations within the Bounds of a Memory Buffer",
          "source": "sparse",
          "original_content": "The product performs operations on a memory buffer, but it reads from or writes to a memory location outside the buffer's intended boundary. This may result in read or write operations on unexpected memory locations that could be linked to other variables, data structures, or internal program data.",
          "keyphrase_sources": [
            {
              "id": "rootcause:Improper Input Validation",
              "keyphrase": "Improper Input Validation",
              "type": "rootcause"
            },
            {
              "id": "rootcause:Input Validation vulnerability",
              "keyphrase": "Input Validation vulnerability",
              "type": "rootcause"
            },
            {
              "id": "impact:loss of confidentiality of controller memory",
              "keyphrase": "loss of confidentiality of controller memory",
              "type": "impact"
            },
            {
              "id": "vector:Man-In-The-Middle attack followed by sending a crafted Modbus function call",
              "keyphrase": "Man-In-The-Middle attack followed by sending a crafted Modbus function call",
              "type": "vector"
            }
          ]
        },
        "similarity": 233.6893758595104
      },
      {
        "metadata": {
          "doc_id": "295",
          "name": "Improper Certificate Validation",
          "source": "sparse",
          "original_content": "The product does not validate, or incorrectly validates, a certificate.",
          "keyphrase_sources": [
            {
              "id": "rootcause:Improper Input Validation",
              "keyphrase": "Improper Input Validation",
              "type": "rootcause"
            },
            {
              "id": "rootcause:Input Validation vulnerability",
              "keyphrase": "Input Validation vulnerability",
              "type": "rootcause"
            },
            {
              "id": "impact:loss of confidentiality of controller memory",
              "keyphrase": "loss of confidentiality of controller memory",
              "type": "impact"
            },
            {
              "id": "vector:Man-In-The-Middle attack followed by sending a crafted Modbus function call",
              "keyphrase": "Man-In-The-Middle attack followed by sending a crafted Modbus function call",
              "type": "vector"
            }
          ]
        },
        "similarity": 230.37733151337193
      },
      {
        "metadata": {
          "doc_id": "300",
          "name": "Channel Accessible by Non-Endpoint",
          "source": "sparse",
          "original_content": "The product does not adequately verify the identity of actors at both ends of a communication channel, or does not adequately ensure the integrity of the channel, in a way that allows the channel to be accessed or influenced by an actor that is not an endpoint.",
          "keyphrase_sources": [
            {
              "id": "vector:Man-In-The-Middle attack followed by sending a crafted Modbus function call",
              "keyphrase": "Man-In-The-Middle attack followed by sending a crafted Modbus function call",
              "type": "vector"
            }
          ]
        },
        "similarity": 130.61595452525924
      },
      {
        "metadata": {
          "doc_id": "319",
          "name": "Cleartext Transmission of Sensitive Information",
          "source": "sparse",
          "original_content": "The product transmits sensitive or security-critical data in cleartext in a communication channel that can be sniffed by unauthorized actors.",
          "keyphrase_sources": [
            {
              "id": "vector:Man-In-The-Middle attack followed by sending a crafted Modbus function call",
              "keyphrase": "Man-In-The-Middle attack followed by sending a crafted Modbus function call",
              "type": "vector"
            }
          ]
        },
        "similarity": 125.21015883704747
      },
      {
        "metadata": {
          "doc_id": "297",
          "name": "Improper Validation of Certificate with Host Mismatch",
          "source": "sparse",
          "original_content": "The product communicates with a host that provides a certificate, but the product does not properly ensure that the certificate is actually associated with that host.",
          "keyphrase_sources": [
            {
              "id": "vector:Man-In-The-Middle attack followed by sending a crafted Modbus function call",
              "keyphrase": "Man-In-The-Middle attack followed by sending a crafted Modbus function call",
              "type": "vector"
            }
          ]
        },
        "similarity": 124.9788781838003
      },
      {
        "metadata": {
          "doc_id": "1262",
          "name": "Improper Access Control for Register Interface",
          "source": "sparse",
          "original_content": "The product uses memory-mapped I/O registers that act as an interface to hardware functionality from software, but there is improper access control to those registers.",
          "keyphrase_sources": [
            {
              "id": "impact:loss of confidentiality of controller memory",
              "keyphrase": "loss of confidentiality of controller memory",
              "type": "impact"
            }
          ]
        },
        "similarity": 104.99037409701506
      },
      {
        "metadata": {
          "doc_id": "200",
          "name": "Exposure of Sensitive Information to an Unauthorized Actor",
          "source": "sparse",
          "original_content": "The product exposes sensitive information to an actor that is not explicitly authorized to have access to that information.",
          "keyphrase_sources": [
            {
              "id": "impact:loss of confidentiality of controller memory",
              "keyphrase": "loss of confidentiality of controller memory",
              "type": "impact"
            }
          ]
        },
        "similarity": 99.3749794576577
      }
    ],
    "enhanced_query": "# Vulnerability Description\n\n    CWE-20 **Improper Input Validation** vulnerability exists that could lead to loss of confidentiality of controller memory after a successful Man-In-The-Middle attack followed by sending a crafted Modbus function call used to tamper with memory.\n\n    # Keyphrase-Specific CWE Analysis\n    This vulnerability contains multiple keyphrases that may map to different CWEs. \n    Please analyze each keyphrase separately and determine the most appropriate CWE(s) for each.\n\n    ## ROOTCAUSE: 'Improper Input Validation'\n\nRelevant CWEs for this ROOTCAUSE:\n\n### 1. CWE-20: Improper Input Validation (Score: 254.85)\n\nThe product receives input or data, but it does\n        not validate or incorrectly validates that the input has the\n        properties that are required to process the data safely and\n        correctly....\n\n### 2. CWE-1284: Improper Validation of Specified Quantity in Input (Score: 237.91)\n\nThe product receives input that is expected to specify a quantity (such as size or length), but it does not validate or incorrectly validates that the quantity has the required properties....\n\n### 3. CWE-1286: Improper Validation of Syntactic Correctness of Input (Score: 237.76)\n\nThe product receives input that is expected to be well-formed - i.e., to comply with a certain syntax - but it does not validate or incorrectly validates that the input complies with the syntax....\n\n### 4. CWE-119: Improper Restriction of Operations within the Bounds of a Memory Buffer (Score: 233.69)\n\nThe product performs operations on a memory buffer, but it reads from or writes to a memory location outside the buffer's intended boundary. This may result in read or write operations on unexpected memory locations that could be linked to other variables, data structures, or internal program data....\n\n### 5. CWE-295: Improper Certificate Validation (Score: 230.38)\n\nThe product does not validate, or incorrectly validates, a certificate....\n\n## ROOTCAUSE: 'Input Validation vulnerability'\n\nRelevant CWEs for this ROOTCAUSE:\n\n### 1. CWE-20: Improper Input Validation (Score: 254.85)\n\nThe product receives input or data, but it does\n        not validate or incorrectly validates that the input has the\n        properties that are required to process the data safely and\n        correctly....\n\n### 2. CWE-1284: Improper Validation of Specified Quantity in Input (Score: 237.91)\n\nThe product receives input that is expected to specify a quantity (such as size or length), but it does not validate or incorrectly validates that the quantity has the required properties....\n\n### 3. CWE-1286: Improper Validation of Syntactic Correctness of Input (Score: 237.76)\n\nThe product receives input that is expected to be well-formed - i.e., to comply with a certain syntax - but it does not validate or incorrectly validates that the input complies with the syntax....\n\n### 4. CWE-119: Improper Restriction of Operations within the Bounds of a Memory Buffer (Score: 233.69)\n\nThe product performs operations on a memory buffer, but it reads from or writes to a memory location outside the buffer's intended boundary. This may result in read or write operations on unexpected memory locations that could be linked to other variables, data structures, or internal program data....\n\n### 5. CWE-295: Improper Certificate Validation (Score: 230.38)\n\nThe product does not validate, or incorrectly validates, a certificate....\n\n## IMPACT: 'loss of confidentiality of controller memory'\n\nRelevant CWEs for this IMPACT:\n\n### 1. CWE-20: Improper Input Validation (Score: 254.85)\n\nThe product receives input or data, but it does\n        not validate or incorrectly validates that the input has the\n        properties that are required to process the data safely and\n        correctly....\n\n### 2. CWE-119: Improper Restriction of Operations within the Bounds of a Memory Buffer (Score: 233.69)\n\nThe product performs operations on a memory buffer, but it reads from or writes to a memory location outside the buffer's intended boundary. This may result in read or write operations on unexpected memory locations that could be linked to other variables, data structures, or internal program data....\n\n### 3. CWE-295: Improper Certificate Validation (Score: 230.38)\n\nThe product does not validate, or incorrectly validates, a certificate....\n\n### 4. CWE-1262: Improper Access Control for Register Interface (Score: 104.99)\n\nThe product uses memory-mapped I/O registers that act as an interface to hardware functionality from software, but there is improper access control to those registers....\n\n### 5. CWE-200: Exposure of Sensitive Information to an Unauthorized Actor (Score: 99.37)\n\nThe product exposes sensitive information to an actor that is not explicitly authorized to have access to that information....\n\n## VECTOR: 'Man-In-The-Middle attack followed by sending a crafted Modbus function call'\n\nRelevant CWEs for this VECTOR:\n\n### 1. CWE-119: Improper Restriction of Operations within the Bounds of a Memory Buffer (Score: 233.69)\n\nThe product performs operations on a memory buffer, but it reads from or writes to a memory location outside the buffer's intended boundary. This may result in read or write operations on unexpected memory locations that could be linked to other variables, data structures, or internal program data....\n\n### 2. CWE-295: Improper Certificate Validation (Score: 230.38)\n\nThe product does not validate, or incorrectly validates, a certificate....\n\n### 3. CWE-300: Channel Accessible by Non-Endpoint (Score: 130.62)\n\nThe product does not adequately verify the identity of actors at both ends of a communication channel, or does not adequately ensure the integrity of the channel, in a way that allows the channel to be accessed or influenced by an actor that is not an endpoint....\n\n### 4. CWE-319: Cleartext Transmission of Sensitive Information (Score: 125.21)\n\nThe product transmits sensitive or security-critical data in cleartext in a communication channel that can be sniffed by unauthorized actors....\n\n### 5. CWE-297: Improper Validation of Certificate with Host Mismatch (Score: 124.98)\n\nThe product communicates with a host that provides a certificate, but the product does not properly ensure that the certificate is actually associated with that host....\n\n\n    # Analysis Instructions\n    1. For each keyphrase, identify the most appropriate CWE(s) that represent the weakness.\n    2. Consider how the different keyphrases might relate to each other in the vulnerability chain.\n    3. Provide a final determination of primary CWE(s) and any secondary CWEs.\n    4. Format your response using the standard analysis template.\n\n    Please analyze how these different weaknesses interact and provide a comprehensive CWE classification.\n    "
  },
  "retrieval_time": 1.0794005393981934
}