{
  "vulnerability_info": "VulnerabilityInfo(cve_id='CVE-2024-43249', description='**Unrestricted Upload of File with Dangerous Type** vulnerability in Bit Apps Bit Form Pro allows **Command Injection**.This issue affects Bit Form Pro from n/a through 2.6.4.', key_phrases={'rootcause': '', 'weakness': ['Command Injection', 'Unrestricted Upload of File with Dangerous Type'], 'impact': 'command injection', 'vector': '', 'attacker': '', 'product': 'Bit Apps Bit Form Pro', 'version': 'n/a through 2.6.4', 'component': ''}, reference_content=\"Based on the provided content, here's an analysis of the vulnerability:\\n\\n**Root Cause of Vulnerability:**\\nThe root cause is an arbitrary file upload vulnerability in the Bit Form Pro WordPress plugin.\\n\\n**Weaknesses/Vulnerabilities Present:**\\n- Arbitrary File Upload: The plugin allows uploading files without proper validation, potentially enabling malicious actors to upload any file type.\\n\\n**Impact of Exploitation:**\\n- Remote Code Execution: Successful exploitation allows attackers to upload malicious files like backdoors, which they can then execute to gain control of the website.\\n- Complete Website Takeover:  By gaining control of the website, attackers can perform a variety of malicious activities, including data theft, defacement, or further attacks.\\n\\n**Attack Vectors:**\\n- File Upload: Attackers upload a malicious file using the plugin's vulnerable upload functionality.\\n\\n**Required Attacker Capabilities/Position:**\\n- Subscriber Role: A user with at least a subscriber privilege is required for exploitation.\\n\\n**Additional Information:**\\n- The vulnerability is classified under OWASP Top 10 A1: Broken Access Control.\\n- The vulnerability has a high CVSS severity score of 9.9.\\n- The vulnerable versions of the plugin are <= 2.6.4, and the vulnerability is fixed in version 2.8.0.\\n- Patchstack has issued a virtual patch to mitigate this issue until users update to the fixed version.\", similar_info={'cwe_distribution': {}, 'cwe_consensus': '', 'similarity_stats': {'thresholds': [], 'total_samples_by_threshold': {}, 'top_cwes_by_threshold': {}}}, similarity_summary=SimilarityInsight(consensus_cwe='', top_cwes=[], confidence_levels={}, total_samples=0), analysis='', analysis_with_relationships='', criticism='', resolution='', relevant_cwes=[{'metadata': {'doc_id': '436', 'name': 'Interpretation Conflict', 'source': 'sparse', 'original_content': \"Product A handles inputs or steps differently than Product B, which causes A to perform incorrect actions based on its perception of B's state.\", 'keyphrase_sources': [{'id': 'weakness:Unrestricted Upload of File with Dangerous Type', 'keyphrase': 'Unrestricted Upload of File with Dangerous Type', 'type': 'weakness'}]}, 'similarity': np.float64(231.28175855562634)}, {'metadata': {'doc_id': '25', 'name': \"Path Traversal: '/../filedir'\", 'source': 'sparse', 'original_content': 'The product uses external input to construct a pathname that should be within a restricted directory, but it does not properly neutralize \"/../\" sequences that can resolve to a location that is outside of that directory.', 'keyphrase_sources': [{'id': 'weakness:Unrestricted Upload of File with Dangerous Type', 'keyphrase': 'Unrestricted Upload of File with Dangerous Type', 'type': 'weakness'}]}, 'similarity': np.float64(219.3239731479961)}, {'metadata': {'doc_id': '681', 'name': 'Incorrect Conversion between Numeric Types', 'source': 'sparse', 'original_content': 'When converting from one data type to another, such as long to integer, data can be omitted or translated in a way that produces unexpected values. If the resulting values are used in a sensitive context, then dangerous behaviors may occur.', 'keyphrase_sources': [{'id': 'weakness:Unrestricted Upload of File with Dangerous Type', 'keyphrase': 'Unrestricted Upload of File with Dangerous Type', 'type': 'weakness'}, {'id': 'product:Bit Apps Bit Form Pro', 'keyphrase': 'Bit Apps Bit Form Pro', 'type': 'product'}]}, 'similarity': np.float64(203.07382896093196)}, {'metadata': {'doc_id': '749', 'name': 'Exposed Dangerous Method or Function', 'source': 'sparse', 'original_content': 'The product provides an Applications Programming Interface (API) or similar interface for interaction with external actors, but the interface includes a dangerous method or function that is not properly restricted.', 'keyphrase_sources': [{'id': 'weakness:Unrestricted Upload of File with Dangerous Type', 'keyphrase': 'Unrestricted Upload of File with Dangerous Type', 'type': 'weakness'}]}, 'similarity': np.float64(201.33320633406169)}, {'metadata': {'doc_id': '434', 'name': 'Unrestricted Upload of File with Dangerous Type', 'source': 'sparse', 'original_content': 'The product allows the upload or transfer of dangerous file types that are automatically processed within its environment.', 'keyphrase_sources': [{'id': 'weakness:Command Injection', 'keyphrase': 'Command Injection', 'type': 'weakness'}, {'id': 'weakness:Unrestricted Upload of File with Dangerous Type', 'keyphrase': 'Unrestricted Upload of File with Dangerous Type', 'type': 'weakness'}, {'id': 'impact:command injection', 'keyphrase': 'command injection', 'type': 'impact'}, {'id': 'product:Bit Apps Bit Form Pro', 'keyphrase': 'Bit Apps Bit Form Pro', 'type': 'product'}, {'id': 'version:n/a through 2.6.4', 'keyphrase': 'n/a through 2.6.4', 'type': 'version'}]}, 'similarity': np.float64(198.70109197018718)}, {'metadata': {'doc_id': '88', 'name': \"Improper Neutralization of Argument Delimiters in a Command ('Argument Injection')\", 'source': 'sparse', 'original_content': 'The product constructs a string for a command to be executed by a separate component\\nin another control sphere, but it does not properly delimit the\\nintended arguments, options, or switches within that command string.', 'keyphrase_sources': [{'id': 'weakness:Command Injection', 'keyphrase': 'Command Injection', 'type': 'weakness'}, {'id': 'impact:command injection', 'keyphrase': 'command injection', 'type': 'impact'}]}, 'similarity': np.float64(166.72231625532922)}, {'metadata': {'doc_id': '790', 'name': 'Improper Filtering of Special Elements', 'source': 'sparse', 'original_content': 'The product receives data from an upstream component, but does not filter or incorrectly filters special elements before sending it to a downstream component.', 'keyphrase_sources': [{'id': 'weakness:Command Injection', 'keyphrase': 'Command Injection', 'type': 'weakness'}, {'id': 'impact:command injection', 'keyphrase': 'command injection', 'type': 'impact'}, {'id': 'version:n/a through 2.6.4', 'keyphrase': 'n/a through 2.6.4', 'type': 'version'}]}, 'similarity': np.float64(166.35628523704736)}, {'metadata': {'doc_id': '138', 'name': 'Improper Neutralization of Special Elements', 'source': 'sparse', 'original_content': 'The product receives input from an upstream component, but it does not neutralize or incorrectly neutralizes special elements that could be interpreted as control elements or syntactic markers when they are sent to a downstream component.', 'keyphrase_sources': [{'id': 'weakness:Command Injection', 'keyphrase': 'Command Injection', 'type': 'weakness'}, {'id': 'impact:command injection', 'keyphrase': 'command injection', 'type': 'impact'}]}, 'similarity': np.float64(163.25979875049256)}, {'metadata': {'doc_id': '89', 'name': \"Improper Neutralization of Special Elements used in an SQL Command ('SQL Injection')\", 'source': 'sparse', 'original_content': 'The product constructs all or part of an SQL command using externally-influenced input from an upstream component, but it does not neutralize or incorrectly neutralizes special elements that could modify the intended SQL command when it is sent to a downstream component. Without sufficient removal or quoting of SQL syntax in user-controllable inputs, the generated SQL query can cause those inputs to be interpreted as SQL instead of ordinary user data.', 'keyphrase_sources': [{'id': 'weakness:Command Injection', 'keyphrase': 'Command Injection', 'type': 'weakness'}, {'id': 'impact:command injection', 'keyphrase': 'command injection', 'type': 'impact'}]}, 'similarity': np.float64(160.28496033522373)}, {'metadata': {'doc_id': '347', 'name': 'Improper Verification of Cryptographic Signature', 'source': 'sparse', 'original_content': 'The product does not verify, or incorrectly verifies, the cryptographic signature for data.', 'keyphrase_sources': [{'id': 'version:n/a through 2.6.4', 'keyphrase': 'n/a through 2.6.4', 'type': 'version'}]}, 'similarity': np.float64(75.50705171298488)}, {'metadata': {'doc_id': '22', 'name': \"Improper Limitation of a Pathname to a Restricted Directory ('Path Traversal')\", 'source': 'sparse', 'original_content': 'The product uses external input to construct a pathname that is intended to identify a file or directory that is located underneath a restricted parent directory, but the product does not properly neutralize special elements within the pathname that can cause the pathname to resolve to a location that is outside of the restricted directory.', 'keyphrase_sources': [{'id': 'version:n/a through 2.6.4', 'keyphrase': 'n/a through 2.6.4', 'type': 'version'}]}, 'similarity': np.float64(73.32658164310385)}, {'metadata': {'doc_id': '93', 'name': \"Improper Neutralization of CRLF Sequences ('CRLF Injection')\", 'source': 'sparse', 'original_content': 'The product uses CRLF (carriage return line feeds) as a special element, e.g. to separate lines or records, but it does not neutralize or incorrectly neutralizes CRLF sequences from inputs.', 'keyphrase_sources': [{'id': 'version:n/a through 2.6.4', 'keyphrase': 'n/a through 2.6.4', 'type': 'version'}]}, 'similarity': np.float64(68.36525400359386)}, {'metadata': {'doc_id': '704', 'name': 'Incorrect Type Conversion or Cast', 'source': 'sparse', 'original_content': 'The product does not correctly convert an object, resource, or structure from one type to a different type.', 'keyphrase_sources': [{'id': 'product:Bit Apps Bit Form Pro', 'keyphrase': 'Bit Apps Bit Form Pro', 'type': 'product'}]}, 'similarity': np.float64(68.06045742131913)}, {'metadata': {'doc_id': '1342', 'name': 'Information Exposure through Microarchitectural State after Transient Execution', 'source': 'sparse', 'original_content': 'The processor does not properly clear microarchitectural state after incorrect microcode assists or speculative execution, resulting in transient execution.', 'keyphrase_sources': [{'id': 'product:Bit Apps Bit Form Pro', 'keyphrase': 'Bit Apps Bit Form Pro', 'type': 'product'}]}, 'similarity': np.float64(67.2677659870321)}, {'metadata': {'doc_id': '194', 'name': 'Unexpected Sign Extension', 'source': 'sparse', 'original_content': 'The product performs an operation on a number that causes it to be sign extended when it is transformed into a larger data type. When the original number is negative, this can produce unexpected values that lead to resultant weaknesses.', 'keyphrase_sources': [{'id': 'product:Bit Apps Bit Form Pro', 'keyphrase': 'Bit Apps Bit Form Pro', 'type': 'product'}]}, 'similarity': np.float64(67.1340030141395)}], identified_cwes={'analyzer': [], 'critic_additional': []})",
  "retrieval_results": {
    "has_multiple_keyphrases": true,
    "keyphrase_cwe_sets": {
      "weakness:Command Injection": {
        "keyphrase": "Command Injection",
        "type": "weakness",
        "cwes": [
          {
            "metadata": {
              "doc_id": "434",
              "name": "Unrestricted Upload of File with Dangerous Type",
              "source": "sparse",
              "original_content": "The product allows the upload or transfer of dangerous file types that are automatically processed within its environment.",
              "keyphrase_sources": [
                {
                  "id": "weakness:Command Injection",
                  "keyphrase": "Command Injection",
                  "type": "weakness"
                },
                {
                  "id": "weakness:Unrestricted Upload of File with Dangerous Type",
                  "keyphrase": "Unrestricted Upload of File with Dangerous Type",
                  "type": "weakness"
                },
                {
                  "id": "impact:command injection",
                  "keyphrase": "command injection",
                  "type": "impact"
                },
                {
                  "id": "product:Bit Apps Bit Form Pro",
                  "keyphrase": "Bit Apps Bit Form Pro",
                  "type": "product"
                },
                {
                  "id": "version:n/a through 2.6.4",
                  "keyphrase": "n/a through 2.6.4",
                  "type": "version"
                }
              ]
            },
            "similarity": 198.70109197018718
          },
          {
            "metadata": {
              "doc_id": "88",
              "name": "Improper Neutralization of Argument Delimiters in a Command ('Argument Injection')",
              "source": "sparse",
              "original_content": "The product constructs a string for a command to be executed by a separate component\nin another control sphere, but it does not properly delimit the\nintended arguments, options, or switches within that command string.",
              "keyphrase_sources": [
                {
                  "id": "weakness:Command Injection",
                  "keyphrase": "Command Injection",
                  "type": "weakness"
                },
                {
                  "id": "impact:command injection",
                  "keyphrase": "command injection",
                  "type": "impact"
                }
              ]
            },
            "similarity": 166.72231625532922
          },
          {
            "metadata": {
              "doc_id": "790",
              "name": "Improper Filtering of Special Elements",
              "source": "sparse",
              "original_content": "The product receives data from an upstream component, but does not filter or incorrectly filters special elements before sending it to a downstream component.",
              "keyphrase_sources": [
                {
                  "id": "weakness:Command Injection",
                  "keyphrase": "Command Injection",
                  "type": "weakness"
                },
                {
                  "id": "impact:command injection",
                  "keyphrase": "command injection",
                  "type": "impact"
                },
                {
                  "id": "version:n/a through 2.6.4",
                  "keyphrase": "n/a through 2.6.4",
                  "type": "version"
                }
              ]
            },
            "similarity": 166.35628523704736
          },
          {
            "metadata": {
              "doc_id": "138",
              "name": "Improper Neutralization of Special Elements",
              "source": "sparse",
              "original_content": "The product receives input from an upstream component, but it does not neutralize or incorrectly neutralizes special elements that could be interpreted as control elements or syntactic markers when they are sent to a downstream component.",
              "keyphrase_sources": [
                {
                  "id": "weakness:Command Injection",
                  "keyphrase": "Command Injection",
                  "type": "weakness"
                },
                {
                  "id": "impact:command injection",
                  "keyphrase": "command injection",
                  "type": "impact"
                }
              ]
            },
            "similarity": 163.25979875049256
          },
          {
            "metadata": {
              "doc_id": "89",
              "name": "Improper Neutralization of Special Elements used in an SQL Command ('SQL Injection')",
              "source": "sparse",
              "original_content": "The product constructs all or part of an SQL command using externally-influenced input from an upstream component, but it does not neutralize or incorrectly neutralizes special elements that could modify the intended SQL command when it is sent to a downstream component. Without sufficient removal or quoting of SQL syntax in user-controllable inputs, the generated SQL query can cause those inputs to be interpreted as SQL instead of ordinary user data.",
              "keyphrase_sources": [
                {
                  "id": "weakness:Command Injection",
                  "keyphrase": "Command Injection",
                  "type": "weakness"
                },
                {
                  "id": "impact:command injection",
                  "keyphrase": "command injection",
                  "type": "impact"
                }
              ]
            },
            "similarity": 160.28496033522373
          }
        ]
      },
      "weakness:Unrestricted Upload of File with Dangerous Type": {
        "keyphrase": "Unrestricted Upload of File with Dangerous Type",
        "type": "weakness",
        "cwes": [
          {
            "metadata": {
              "doc_id": "434",
              "name": "Unrestricted Upload of File with Dangerous Type",
              "source": "sparse",
              "original_content": "The product allows the upload or transfer of dangerous file types that are automatically processed within its environment."
            },
            "similarity": 333.23369029271817
          },
          {
            "metadata": {
              "doc_id": "436",
              "name": "Interpretation Conflict",
              "source": "sparse",
              "original_content": "Product A handles inputs or steps differently than Product B, which causes A to perform incorrect actions based on its perception of B's state.",
              "keyphrase_sources": [
                {
                  "id": "weakness:Unrestricted Upload of File with Dangerous Type",
                  "keyphrase": "Unrestricted Upload of File with Dangerous Type",
                  "type": "weakness"
                }
              ]
            },
            "similarity": 231.28175855562634
          },
          {
            "metadata": {
              "doc_id": "25",
              "name": "Path Traversal: '/../filedir'",
              "source": "sparse",
              "original_content": "The product uses external input to construct a pathname that should be within a restricted directory, but it does not properly neutralize \"/../\" sequences that can resolve to a location that is outside of that directory.",
              "keyphrase_sources": [
                {
                  "id": "weakness:Unrestricted Upload of File with Dangerous Type",
                  "keyphrase": "Unrestricted Upload of File with Dangerous Type",
                  "type": "weakness"
                }
              ]
            },
            "similarity": 219.3239731479961
          },
          {
            "metadata": {
              "doc_id": "681",
              "name": "Incorrect Conversion between Numeric Types",
              "source": "sparse",
              "original_content": "When converting from one data type to another, such as long to integer, data can be omitted or translated in a way that produces unexpected values. If the resulting values are used in a sensitive context, then dangerous behaviors may occur.",
              "keyphrase_sources": [
                {
                  "id": "weakness:Unrestricted Upload of File with Dangerous Type",
                  "keyphrase": "Unrestricted Upload of File with Dangerous Type",
                  "type": "weakness"
                },
                {
                  "id": "product:Bit Apps Bit Form Pro",
                  "keyphrase": "Bit Apps Bit Form Pro",
                  "type": "product"
                }
              ]
            },
            "similarity": 203.07382896093196
          },
          {
            "metadata": {
              "doc_id": "749",
              "name": "Exposed Dangerous Method or Function",
              "source": "sparse",
              "original_content": "The product provides an Applications Programming Interface (API) or similar interface for interaction with external actors, but the interface includes a dangerous method or function that is not properly restricted.",
              "keyphrase_sources": [
                {
                  "id": "weakness:Unrestricted Upload of File with Dangerous Type",
                  "keyphrase": "Unrestricted Upload of File with Dangerous Type",
                  "type": "weakness"
                }
              ]
            },
            "similarity": 201.33320633406169
          }
        ]
      },
      "impact:command injection": {
        "keyphrase": "command injection",
        "type": "impact",
        "cwes": [
          {
            "metadata": {
              "doc_id": "434",
              "name": "Unrestricted Upload of File with Dangerous Type",
              "source": "sparse",
              "original_content": "The product allows the upload or transfer of dangerous file types that are automatically processed within its environment."
            },
            "similarity": 70.96467570363828
          },
          {
            "metadata": {
              "doc_id": "88",
              "name": "Improper Neutralization of Argument Delimiters in a Command ('Argument Injection')",
              "source": "sparse",
              "original_content": "The product constructs a string for a command to be executed by a separate component\nin another control sphere, but it does not properly delimit the\nintended arguments, options, or switches within that command string."
            },
            "similarity": 59.5436843769033
          },
          {
            "metadata": {
              "doc_id": "790",
              "name": "Improper Filtering of Special Elements",
              "source": "sparse",
              "original_content": "The product receives data from an upstream component, but does not filter or incorrectly filters special elements before sending it to a downstream component."
            },
            "similarity": 59.4129590132312
          },
          {
            "metadata": {
              "doc_id": "138",
              "name": "Improper Neutralization of Special Elements",
              "source": "sparse",
              "original_content": "The product receives input from an upstream component, but it does not neutralize or incorrectly neutralizes special elements that could be interpreted as control elements or syntactic markers when they are sent to a downstream component."
            },
            "similarity": 58.30707098231878
          },
          {
            "metadata": {
              "doc_id": "89",
              "name": "Improper Neutralization of Special Elements used in an SQL Command ('SQL Injection')",
              "source": "sparse",
              "original_content": "The product constructs all or part of an SQL command using externally-influenced input from an upstream component, but it does not neutralize or incorrectly neutralizes special elements that could modify the intended SQL command when it is sent to a downstream component. Without sufficient removal or quoting of SQL syntax in user-controllable inputs, the generated SQL query can cause those inputs to be interpreted as SQL instead of ordinary user data."
            },
            "similarity": 57.244628691151334
          }
        ]
      },
      "product:Bit Apps Bit Form Pro": {
        "keyphrase": "Bit Apps Bit Form Pro",
        "type": "product",
        "cwes": [
          {
            "metadata": {
              "doc_id": "681",
              "name": "Incorrect Conversion between Numeric Types",
              "source": "sparse",
              "original_content": "When converting from one data type to another, such as long to integer, data can be omitted or translated in a way that produces unexpected values. If the resulting values are used in a sensitive context, then dangerous behaviors may occur."
            },
            "similarity": 69.5099181944829
          },
          {
            "metadata": {
              "doc_id": "434",
              "name": "Unrestricted Upload of File with Dangerous Type",
              "source": "sparse",
              "original_content": "The product allows the upload or transfer of dangerous file types that are automatically processed within its environment."
            },
            "similarity": 68.27120375651099
          },
          {
            "metadata": {
              "doc_id": "704",
              "name": "Incorrect Type Conversion or Cast",
              "source": "sparse",
              "original_content": "The product does not correctly convert an object, resource, or structure from one type to a different type.",
              "keyphrase_sources": [
                {
                  "id": "product:Bit Apps Bit Form Pro",
                  "keyphrase": "Bit Apps Bit Form Pro",
                  "type": "product"
                }
              ]
            },
            "similarity": 68.06045742131913
          },
          {
            "metadata": {
              "doc_id": "1342",
              "name": "Information Exposure through Microarchitectural State after Transient Execution",
              "source": "sparse",
              "original_content": "The processor does not properly clear microarchitectural state after incorrect microcode assists or speculative execution, resulting in transient execution.",
              "keyphrase_sources": [
                {
                  "id": "product:Bit Apps Bit Form Pro",
                  "keyphrase": "Bit Apps Bit Form Pro",
                  "type": "product"
                }
              ]
            },
            "similarity": 67.2677659870321
          },
          {
            "metadata": {
              "doc_id": "194",
              "name": "Unexpected Sign Extension",
              "source": "sparse",
              "original_content": "The product performs an operation on a number that causes it to be sign extended when it is transformed into a larger data type. When the original number is negative, this can produce unexpected values that lead to resultant weaknesses.",
              "keyphrase_sources": [
                {
                  "id": "product:Bit Apps Bit Form Pro",
                  "keyphrase": "Bit Apps Bit Form Pro",
                  "type": "product"
                }
              ]
            },
            "similarity": 67.1340030141395
          }
        ]
      },
      "version:n/a through 2.6.4": {
        "keyphrase": "n/a through 2.6.4",
        "type": "version",
        "cwes": [
          {
            "metadata": {
              "doc_id": "434",
              "name": "Unrestricted Upload of File with Dangerous Type",
              "source": "sparse",
              "original_content": "The product allows the upload or transfer of dangerous file types that are automatically processed within its environment."
            },
            "similarity": 84.27073603539804
          },
          {
            "metadata": {
              "doc_id": "347",
              "name": "Improper Verification of Cryptographic Signature",
              "source": "sparse",
              "original_content": "The product does not verify, or incorrectly verifies, the cryptographic signature for data.",
              "keyphrase_sources": [
                {
                  "id": "version:n/a through 2.6.4",
                  "keyphrase": "n/a through 2.6.4",
                  "type": "version"
                }
              ]
            },
            "similarity": 75.50705171298488
          },
          {
            "metadata": {
              "doc_id": "22",
              "name": "Improper Limitation of a Pathname to a Restricted Directory ('Path Traversal')",
              "source": "sparse",
              "original_content": "The product uses external input to construct a pathname that is intended to identify a file or directory that is located underneath a restricted parent directory, but the product does not properly neutralize special elements within the pathname that can cause the pathname to resolve to a location that is outside of the restricted directory.",
              "keyphrase_sources": [
                {
                  "id": "version:n/a through 2.6.4",
                  "keyphrase": "n/a through 2.6.4",
                  "type": "version"
                }
              ]
            },
            "similarity": 73.32658164310385
          },
          {
            "metadata": {
              "doc_id": "790",
              "name": "Improper Filtering of Special Elements",
              "source": "sparse",
              "original_content": "The product receives data from an upstream component, but does not filter or incorrectly filters special elements before sending it to a downstream component."
            },
            "similarity": 69.31600369205533
          },
          {
            "metadata": {
              "doc_id": "93",
              "name": "Improper Neutralization of CRLF Sequences ('CRLF Injection')",
              "source": "sparse",
              "original_content": "The product uses CRLF (carriage return line feeds) as a special element, e.g. to separate lines or records, but it does not neutralize or incorrectly neutralizes CRLF sequences from inputs.",
              "keyphrase_sources": [
                {
                  "id": "version:n/a through 2.6.4",
                  "keyphrase": "n/a through 2.6.4",
                  "type": "version"
                }
              ]
            },
            "similarity": 68.36525400359386
          }
        ]
      }
    },
    "keyphrase_mapping": {
      "434": [
        {
          "id": "weakness:Command Injection",
          "keyphrase": "Command Injection",
          "type": "weakness"
        },
        {
          "id": "weakness:Unrestricted Upload of File with Dangerous Type",
          "keyphrase": "Unrestricted Upload of File with Dangerous Type",
          "type": "weakness"
        },
        {
          "id": "impact:command injection",
          "keyphrase": "command injection",
          "type": "impact"
        },
        {
          "id": "product:Bit Apps Bit Form Pro",
          "keyphrase": "Bit Apps Bit Form Pro",
          "type": "product"
        },
        {
          "id": "version:n/a through 2.6.4",
          "keyphrase": "n/a through 2.6.4",
          "type": "version"
        }
      ],
      "88": [
        {
          "id": "weakness:Command Injection",
          "keyphrase": "Command Injection",
          "type": "weakness"
        },
        {
          "id": "impact:command injection",
          "keyphrase": "command injection",
          "type": "impact"
        }
      ],
      "790": [
        {
          "id": "weakness:Command Injection",
          "keyphrase": "Command Injection",
          "type": "weakness"
        },
        {
          "id": "impact:command injection",
          "keyphrase": "command injection",
          "type": "impact"
        },
        {
          "id": "version:n/a through 2.6.4",
          "keyphrase": "n/a through 2.6.4",
          "type": "version"
        }
      ],
      "138": [
        {
          "id": "weakness:Command Injection",
          "keyphrase": "Command Injection",
          "type": "weakness"
        },
        {
          "id": "impact:command injection",
          "keyphrase": "command injection",
          "type": "impact"
        }
      ],
      "89": [
        {
          "id": "weakness:Command Injection",
          "keyphrase": "Command Injection",
          "type": "weakness"
        },
        {
          "id": "impact:command injection",
          "keyphrase": "command injection",
          "type": "impact"
        }
      ],
      "436": [
        {
          "id": "weakness:Unrestricted Upload of File with Dangerous Type",
          "keyphrase": "Unrestricted Upload of File with Dangerous Type",
          "type": "weakness"
        }
      ],
      "25": [
        {
          "id": "weakness:Unrestricted Upload of File with Dangerous Type",
          "keyphrase": "Unrestricted Upload of File with Dangerous Type",
          "type": "weakness"
        }
      ],
      "681": [
        {
          "id": "weakness:Unrestricted Upload of File with Dangerous Type",
          "keyphrase": "Unrestricted Upload of File with Dangerous Type",
          "type": "weakness"
        },
        {
          "id": "product:Bit Apps Bit Form Pro",
          "keyphrase": "Bit Apps Bit Form Pro",
          "type": "product"
        }
      ],
      "749": [
        {
          "id": "weakness:Unrestricted Upload of File with Dangerous Type",
          "keyphrase": "Unrestricted Upload of File with Dangerous Type",
          "type": "weakness"
        }
      ],
      "704": [
        {
          "id": "product:Bit Apps Bit Form Pro",
          "keyphrase": "Bit Apps Bit Form Pro",
          "type": "product"
        }
      ],
      "1342": [
        {
          "id": "product:Bit Apps Bit Form Pro",
          "keyphrase": "Bit Apps Bit Form Pro",
          "type": "product"
        }
      ],
      "194": [
        {
          "id": "product:Bit Apps Bit Form Pro",
          "keyphrase": "Bit Apps Bit Form Pro",
          "type": "product"
        }
      ],
      "347": [
        {
          "id": "version:n/a through 2.6.4",
          "keyphrase": "n/a through 2.6.4",
          "type": "version"
        }
      ],
      "22": [
        {
          "id": "version:n/a through 2.6.4",
          "keyphrase": "n/a through 2.6.4",
          "type": "version"
        }
      ],
      "93": [
        {
          "id": "version:n/a through 2.6.4",
          "keyphrase": "n/a through 2.6.4",
          "type": "version"
        }
      ]
    },
    "relevant_cwes": [
      {
        "metadata": {
          "doc_id": "436",
          "name": "Interpretation Conflict",
          "source": "sparse",
          "original_content": "Product A handles inputs or steps differently than Product B, which causes A to perform incorrect actions based on its perception of B's state.",
          "keyphrase_sources": [
            {
              "id": "weakness:Unrestricted Upload of File with Dangerous Type",
              "keyphrase": "Unrestricted Upload of File with Dangerous Type",
              "type": "weakness"
            }
          ]
        },
        "similarity": 231.28175855562634
      },
      {
        "metadata": {
          "doc_id": "25",
          "name": "Path Traversal: '/../filedir'",
          "source": "sparse",
          "original_content": "The product uses external input to construct a pathname that should be within a restricted directory, but it does not properly neutralize \"/../\" sequences that can resolve to a location that is outside of that directory.",
          "keyphrase_sources": [
            {
              "id": "weakness:Unrestricted Upload of File with Dangerous Type",
              "keyphrase": "Unrestricted Upload of File with Dangerous Type",
              "type": "weakness"
            }
          ]
        },
        "similarity": 219.3239731479961
      },
      {
        "metadata": {
          "doc_id": "681",
          "name": "Incorrect Conversion between Numeric Types",
          "source": "sparse",
          "original_content": "When converting from one data type to another, such as long to integer, data can be omitted or translated in a way that produces unexpected values. If the resulting values are used in a sensitive context, then dangerous behaviors may occur.",
          "keyphrase_sources": [
            {
              "id": "weakness:Unrestricted Upload of File with Dangerous Type",
              "keyphrase": "Unrestricted Upload of File with Dangerous Type",
              "type": "weakness"
            },
            {
              "id": "product:Bit Apps Bit Form Pro",
              "keyphrase": "Bit Apps Bit Form Pro",
              "type": "product"
            }
          ]
        },
        "similarity": 203.07382896093196
      },
      {
        "metadata": {
          "doc_id": "749",
          "name": "Exposed Dangerous Method or Function",
          "source": "sparse",
          "original_content": "The product provides an Applications Programming Interface (API) or similar interface for interaction with external actors, but the interface includes a dangerous method or function that is not properly restricted.",
          "keyphrase_sources": [
            {
              "id": "weakness:Unrestricted Upload of File with Dangerous Type",
              "keyphrase": "Unrestricted Upload of File with Dangerous Type",
              "type": "weakness"
            }
          ]
        },
        "similarity": 201.33320633406169
      },
      {
        "metadata": {
          "doc_id": "434",
          "name": "Unrestricted Upload of File with Dangerous Type",
          "source": "sparse",
          "original_content": "The product allows the upload or transfer of dangerous file types that are automatically processed within its environment.",
          "keyphrase_sources": [
            {
              "id": "weakness:Command Injection",
              "keyphrase": "Command Injection",
              "type": "weakness"
            },
            {
              "id": "weakness:Unrestricted Upload of File with Dangerous Type",
              "keyphrase": "Unrestricted Upload of File with Dangerous Type",
              "type": "weakness"
            },
            {
              "id": "impact:command injection",
              "keyphrase": "command injection",
              "type": "impact"
            },
            {
              "id": "product:Bit Apps Bit Form Pro",
              "keyphrase": "Bit Apps Bit Form Pro",
              "type": "product"
            },
            {
              "id": "version:n/a through 2.6.4",
              "keyphrase": "n/a through 2.6.4",
              "type": "version"
            }
          ]
        },
        "similarity": 198.70109197018718
      },
      {
        "metadata": {
          "doc_id": "88",
          "name": "Improper Neutralization of Argument Delimiters in a Command ('Argument Injection')",
          "source": "sparse",
          "original_content": "The product constructs a string for a command to be executed by a separate component\nin another control sphere, but it does not properly delimit the\nintended arguments, options, or switches within that command string.",
          "keyphrase_sources": [
            {
              "id": "weakness:Command Injection",
              "keyphrase": "Command Injection",
              "type": "weakness"
            },
            {
              "id": "impact:command injection",
              "keyphrase": "command injection",
              "type": "impact"
            }
          ]
        },
        "similarity": 166.72231625532922
      },
      {
        "metadata": {
          "doc_id": "790",
          "name": "Improper Filtering of Special Elements",
          "source": "sparse",
          "original_content": "The product receives data from an upstream component, but does not filter or incorrectly filters special elements before sending it to a downstream component.",
          "keyphrase_sources": [
            {
              "id": "weakness:Command Injection",
              "keyphrase": "Command Injection",
              "type": "weakness"
            },
            {
              "id": "impact:command injection",
              "keyphrase": "command injection",
              "type": "impact"
            },
            {
              "id": "version:n/a through 2.6.4",
              "keyphrase": "n/a through 2.6.4",
              "type": "version"
            }
          ]
        },
        "similarity": 166.35628523704736
      },
      {
        "metadata": {
          "doc_id": "138",
          "name": "Improper Neutralization of Special Elements",
          "source": "sparse",
          "original_content": "The product receives input from an upstream component, but it does not neutralize or incorrectly neutralizes special elements that could be interpreted as control elements or syntactic markers when they are sent to a downstream component.",
          "keyphrase_sources": [
            {
              "id": "weakness:Command Injection",
              "keyphrase": "Command Injection",
              "type": "weakness"
            },
            {
              "id": "impact:command injection",
              "keyphrase": "command injection",
              "type": "impact"
            }
          ]
        },
        "similarity": 163.25979875049256
      },
      {
        "metadata": {
          "doc_id": "89",
          "name": "Improper Neutralization of Special Elements used in an SQL Command ('SQL Injection')",
          "source": "sparse",
          "original_content": "The product constructs all or part of an SQL command using externally-influenced input from an upstream component, but it does not neutralize or incorrectly neutralizes special elements that could modify the intended SQL command when it is sent to a downstream component. Without sufficient removal or quoting of SQL syntax in user-controllable inputs, the generated SQL query can cause those inputs to be interpreted as SQL instead of ordinary user data.",
          "keyphrase_sources": [
            {
              "id": "weakness:Command Injection",
              "keyphrase": "Command Injection",
              "type": "weakness"
            },
            {
              "id": "impact:command injection",
              "keyphrase": "command injection",
              "type": "impact"
            }
          ]
        },
        "similarity": 160.28496033522373
      },
      {
        "metadata": {
          "doc_id": "347",
          "name": "Improper Verification of Cryptographic Signature",
          "source": "sparse",
          "original_content": "The product does not verify, or incorrectly verifies, the cryptographic signature for data.",
          "keyphrase_sources": [
            {
              "id": "version:n/a through 2.6.4",
              "keyphrase": "n/a through 2.6.4",
              "type": "version"
            }
          ]
        },
        "similarity": 75.50705171298488
      },
      {
        "metadata": {
          "doc_id": "22",
          "name": "Improper Limitation of a Pathname to a Restricted Directory ('Path Traversal')",
          "source": "sparse",
          "original_content": "The product uses external input to construct a pathname that is intended to identify a file or directory that is located underneath a restricted parent directory, but the product does not properly neutralize special elements within the pathname that can cause the pathname to resolve to a location that is outside of the restricted directory.",
          "keyphrase_sources": [
            {
              "id": "version:n/a through 2.6.4",
              "keyphrase": "n/a through 2.6.4",
              "type": "version"
            }
          ]
        },
        "similarity": 73.32658164310385
      },
      {
        "metadata": {
          "doc_id": "93",
          "name": "Improper Neutralization of CRLF Sequences ('CRLF Injection')",
          "source": "sparse",
          "original_content": "The product uses CRLF (carriage return line feeds) as a special element, e.g. to separate lines or records, but it does not neutralize or incorrectly neutralizes CRLF sequences from inputs.",
          "keyphrase_sources": [
            {
              "id": "version:n/a through 2.6.4",
              "keyphrase": "n/a through 2.6.4",
              "type": "version"
            }
          ]
        },
        "similarity": 68.36525400359386
      },
      {
        "metadata": {
          "doc_id": "704",
          "name": "Incorrect Type Conversion or Cast",
          "source": "sparse",
          "original_content": "The product does not correctly convert an object, resource, or structure from one type to a different type.",
          "keyphrase_sources": [
            {
              "id": "product:Bit Apps Bit Form Pro",
              "keyphrase": "Bit Apps Bit Form Pro",
              "type": "product"
            }
          ]
        },
        "similarity": 68.06045742131913
      },
      {
        "metadata": {
          "doc_id": "1342",
          "name": "Information Exposure through Microarchitectural State after Transient Execution",
          "source": "sparse",
          "original_content": "The processor does not properly clear microarchitectural state after incorrect microcode assists or speculative execution, resulting in transient execution.",
          "keyphrase_sources": [
            {
              "id": "product:Bit Apps Bit Form Pro",
              "keyphrase": "Bit Apps Bit Form Pro",
              "type": "product"
            }
          ]
        },
        "similarity": 67.2677659870321
      },
      {
        "metadata": {
          "doc_id": "194",
          "name": "Unexpected Sign Extension",
          "source": "sparse",
          "original_content": "The product performs an operation on a number that causes it to be sign extended when it is transformed into a larger data type. When the original number is negative, this can produce unexpected values that lead to resultant weaknesses.",
          "keyphrase_sources": [
            {
              "id": "product:Bit Apps Bit Form Pro",
              "keyphrase": "Bit Apps Bit Form Pro",
              "type": "product"
            }
          ]
        },
        "similarity": 67.1340030141395
      }
    ],
    "enhanced_query": "# Vulnerability Description\n\n    **Unrestricted Upload of File with Dangerous Type** vulnerability in Bit Apps Bit Form Pro allows **Command Injection**.This issue affects Bit Form Pro from n/a through 2.6.4.\n\n    # Keyphrase-Specific CWE Analysis\n    This vulnerability contains multiple keyphrases that may map to different CWEs. \n    Please analyze each keyphrase separately and determine the most appropriate CWE(s) for each.\n\n    ## WEAKNESS: 'Unrestricted Upload of File with Dangerous Type'\n\nRelevant CWEs for this WEAKNESS:\n\n### 1. CWE-436: Interpretation Conflict (Score: 231.28)\n\nProduct A handles inputs or steps differently than Product B, which causes A to perform incorrect actions based on its perception of B's state....\n\n### 2. CWE-25: Path Traversal: '/../filedir' (Score: 219.32)\n\nThe product uses external input to construct a pathname that should be within a restricted directory, but it does not properly neutralize \"/../\" sequences that can resolve to a location that is outside of that directory....\n\n### 3. CWE-681: Incorrect Conversion between Numeric Types (Score: 203.07)\n\nWhen converting from one data type to another, such as long to integer, data can be omitted or translated in a way that produces unexpected values. If the resulting values are used in a sensitive context, then dangerous behaviors may occur....\n\n### 4. CWE-749: Exposed Dangerous Method or Function (Score: 201.33)\n\nThe product provides an Applications Programming Interface (API) or similar interface for interaction with external actors, but the interface includes a dangerous method or function that is not properly restricted....\n\n### 5. CWE-434: Unrestricted Upload of File with Dangerous Type (Score: 198.70)\n\nThe product allows the upload or transfer of dangerous file types that are automatically processed within its environment....\n\n## PRODUCT: 'Bit Apps Bit Form Pro'\n\nRelevant CWEs for this PRODUCT:\n\n### 1. CWE-681: Incorrect Conversion between Numeric Types (Score: 203.07)\n\nWhen converting from one data type to another, such as long to integer, data can be omitted or translated in a way that produces unexpected values. If the resulting values are used in a sensitive context, then dangerous behaviors may occur....\n\n### 2. CWE-434: Unrestricted Upload of File with Dangerous Type (Score: 198.70)\n\nThe product allows the upload or transfer of dangerous file types that are automatically processed within its environment....\n\n### 3. CWE-704: Incorrect Type Conversion or Cast (Score: 68.06)\n\nThe product does not correctly convert an object, resource, or structure from one type to a different type....\n\n### 4. CWE-1342: Information Exposure through Microarchitectural State after Transient Execution (Score: 67.27)\n\nThe processor does not properly clear microarchitectural state after incorrect microcode assists or speculative execution, resulting in transient execution....\n\n### 5. CWE-194: Unexpected Sign Extension (Score: 67.13)\n\nThe product performs an operation on a number that causes it to be sign extended when it is transformed into a larger data type. When the original number is negative, this can produce unexpected values that lead to resultant weaknesses....\n\n## WEAKNESS: 'Command Injection'\n\nRelevant CWEs for this WEAKNESS:\n\n### 1. CWE-434: Unrestricted Upload of File with Dangerous Type (Score: 198.70)\n\nThe product allows the upload or transfer of dangerous file types that are automatically processed within its environment....\n\n### 2. CWE-88: Improper Neutralization of Argument Delimiters in a Command ('Argument Injection') (Score: 166.72)\n\nThe product constructs a string for a command to be executed by a separate component\nin another control sphere, but it does not properly delimit the\nintended arguments, options, or switches within that command string....\n\n### 3. CWE-790: Improper Filtering of Special Elements (Score: 166.36)\n\nThe product receives data from an upstream component, but does not filter or incorrectly filters special elements before sending it to a downstream component....\n\n### 4. CWE-138: Improper Neutralization of Special Elements (Score: 163.26)\n\nThe product receives input from an upstream component, but it does not neutralize or incorrectly neutralizes special elements that could be interpreted as control elements or syntactic markers when they are sent to a downstream component....\n\n### 5. CWE-89: Improper Neutralization of Special Elements used in an SQL Command ('SQL Injection') (Score: 160.28)\n\nThe product constructs all or part of an SQL command using externally-influenced input from an upstream component, but it does not neutralize or incorrectly neutralizes special elements that could modify the intended SQL command when it is sent to a downstream component. Without sufficient removal o...\n\n## IMPACT: 'command injection'\n\nRelevant CWEs for this IMPACT:\n\n### 1. CWE-434: Unrestricted Upload of File with Dangerous Type (Score: 198.70)\n\nThe product allows the upload or transfer of dangerous file types that are automatically processed within its environment....\n\n### 2. CWE-88: Improper Neutralization of Argument Delimiters in a Command ('Argument Injection') (Score: 166.72)\n\nThe product constructs a string for a command to be executed by a separate component\nin another control sphere, but it does not properly delimit the\nintended arguments, options, or switches within that command string....\n\n### 3. CWE-790: Improper Filtering of Special Elements (Score: 166.36)\n\nThe product receives data from an upstream component, but does not filter or incorrectly filters special elements before sending it to a downstream component....\n\n### 4. CWE-138: Improper Neutralization of Special Elements (Score: 163.26)\n\nThe product receives input from an upstream component, but it does not neutralize or incorrectly neutralizes special elements that could be interpreted as control elements or syntactic markers when they are sent to a downstream component....\n\n### 5. CWE-89: Improper Neutralization of Special Elements used in an SQL Command ('SQL Injection') (Score: 160.28)\n\nThe product constructs all or part of an SQL command using externally-influenced input from an upstream component, but it does not neutralize or incorrectly neutralizes special elements that could modify the intended SQL command when it is sent to a downstream component. Without sufficient removal o...\n\n## VERSION: 'n/a through 2.6.4'\n\nRelevant CWEs for this VERSION:\n\n### 1. CWE-434: Unrestricted Upload of File with Dangerous Type (Score: 198.70)\n\nThe product allows the upload or transfer of dangerous file types that are automatically processed within its environment....\n\n### 2. CWE-790: Improper Filtering of Special Elements (Score: 166.36)\n\nThe product receives data from an upstream component, but does not filter or incorrectly filters special elements before sending it to a downstream component....\n\n### 3. CWE-347: Improper Verification of Cryptographic Signature (Score: 75.51)\n\nThe product does not verify, or incorrectly verifies, the cryptographic signature for data....\n\n### 4. CWE-22: Improper Limitation of a Pathname to a Restricted Directory ('Path Traversal') (Score: 73.33)\n\nThe product uses external input to construct a pathname that is intended to identify a file or directory that is located underneath a restricted parent directory, but the product does not properly neutralize special elements within the pathname that can cause the pathname to resolve to a location th...\n\n### 5. CWE-93: Improper Neutralization of CRLF Sequences ('CRLF Injection') (Score: 68.37)\n\nThe product uses CRLF (carriage return line feeds) as a special element, e.g. to separate lines or records, but it does not neutralize or incorrectly neutralizes CRLF sequences from inputs....\n\n\n    # Analysis Instructions\n    1. For each keyphrase, identify the most appropriate CWE(s) that represent the weakness.\n    2. Consider how the different keyphrases might relate to each other in the vulnerability chain.\n    3. Provide a final determination of primary CWE(s) and any secondary CWEs.\n    4. Format your response using the standard analysis template.\n\n    Please analyze how these different weaknesses interact and provide a comprehensive CWE classification.\n    "
  },
  "retrieval_time": 1.0264918804168701
}