{
  "vulnerability_info": "VulnerabilityInfo(cve_id='CVE-2024-53750', description='Cross-Site Request Forgery (CSRF) vulnerability in Maeve Lander PayPal Responder allows Stored **XSS**.This issue affects PayPal Responder from n/a through 1.2.', key_phrases={'rootcause': 'lack of CSRF protection', 'weakness': ['XSS', 'cross-site scripting'], 'impact': 'Stored XSS', 'vector': '', 'attacker': '', 'product': 'Maeve Lander PayPal Responder', 'version': 'n/a through 1.2', 'component': ''}, reference_content=\"Based on the provided content, here's a breakdown of the vulnerability:\\n\\n**Root Cause of Vulnerability:** The WordPress PayPal Responder plugin (versions 1.2 and earlier) is vulnerable to Cross-Site Request Forgery (CSRF).\\n\\n**Weaknesses/Vulnerabilities Present:**\\n*   **CSRF:** The plugin lacks proper protection against CSRF attacks. This means that an attacker can potentially force a logged-in user to perform unintended actions on the WordPress site.\\n\\n**Impact of Exploitation:**\\n*   A malicious actor could force a higher-privileged user (e.g. admin) to execute unwanted actions, such as modifying plugin settings, or other actions depending on the plugin functionality.\\n*   The specific impact varies case by case.\\n\\n**Attack Vectors:**\\n*   An attacker could craft a malicious web page, link, or email that triggers a request to the vulnerable WordPress plugin while a user is logged into the WordPress site.\\n\\n**Required Attacker Capabilities/Position:**\\n*   The attacker does not need to be authenticated with the WordPress site.\\n* The attacker needs to be able to get a user to visit a malicious site or open a malicious link/email, while that user is logged into the vulnerable wordpress site.\\n\\n**Additional Information:**\\n*   The vulnerability has a low severity impact and is unlikely to be exploited.\\n*   There is no official fix available for this vulnerability at the time of reporting.\\n*   The vulnerability is classified under OWASP Top 10 as A1: Broken Access Control.\\n*   The CVSS score is 7.1, considered low severity.\", similar_info={'cwe_distribution': {}, 'cwe_consensus': '', 'similarity_stats': {'thresholds': [], 'total_samples_by_threshold': {}, 'top_cwes_by_threshold': {}}}, similarity_summary=SimilarityInsight(consensus_cwe='', top_cwes=[], confidence_levels={}, total_samples=0), analysis='', analysis_with_relationships='', criticism='', resolution='', relevant_cwes=[{'metadata': {'doc_id': '352', 'name': 'Cross-Site Request Forgery (CSRF)', 'source': 'sparse', 'original_content': 'The web application does not, or can not, sufficiently verify whether a well-formed, valid, consistent request was intentionally provided by the user who submitted the request.', 'keyphrase_sources': [{'id': 'rootcause:lack of CSRF protection', 'keyphrase': 'lack of CSRF protection', 'type': 'rootcause'}, {'id': 'weakness:XSS', 'keyphrase': 'XSS', 'type': 'weakness'}, {'id': 'weakness:cross-site scripting', 'keyphrase': 'cross-site scripting', 'type': 'weakness'}, {'id': 'impact:Stored XSS', 'keyphrase': 'Stored XSS', 'type': 'impact'}, {'id': 'product:Maeve Lander PayPal Responder', 'keyphrase': 'Maeve Lander PayPal Responder', 'type': 'product'}, {'id': 'version:n/a through 1.2', 'keyphrase': 'n/a through 1.2', 'type': 'version'}]}, 'similarity': np.float64(275.9135274815367)}, {'metadata': {'doc_id': '434', 'name': 'Unrestricted Upload of File with Dangerous Type', 'source': 'sparse', 'original_content': 'The product allows the upload or transfer of dangerous file types that are automatically processed within its environment.', 'keyphrase_sources': [{'id': 'rootcause:lack of CSRF protection', 'keyphrase': 'lack of CSRF protection', 'type': 'rootcause'}, {'id': 'weakness:XSS', 'keyphrase': 'XSS', 'type': 'weakness'}, {'id': 'weakness:cross-site scripting', 'keyphrase': 'cross-site scripting', 'type': 'weakness'}, {'id': 'impact:Stored XSS', 'keyphrase': 'Stored XSS', 'type': 'impact'}, {'id': 'product:Maeve Lander PayPal Responder', 'keyphrase': 'Maeve Lander PayPal Responder', 'type': 'product'}, {'id': 'version:n/a through 1.2', 'keyphrase': 'n/a through 1.2', 'type': 'version'}]}, 'similarity': np.float64(215.52988764225748)}, {'metadata': {'doc_id': '116', 'name': 'Improper Encoding or Escaping of Output', 'source': 'sparse', 'original_content': 'The product prepares a structured message for communication with another component, but encoding or escaping of the data is either missing or done incorrectly. As a result, the intended structure of the message is not preserved.', 'keyphrase_sources': [{'id': 'rootcause:lack of CSRF protection', 'keyphrase': 'lack of CSRF protection', 'type': 'rootcause'}, {'id': 'impact:Stored XSS', 'keyphrase': 'Stored XSS', 'type': 'impact'}]}, 'similarity': np.float64(189.71179546387677)}, {'metadata': {'doc_id': '79', 'name': \"Improper Neutralization of Input During Web Page Generation ('Cross-site Scripting')\", 'source': 'sparse', 'original_content': 'The product does not neutralize or incorrectly neutralizes user-controllable input before it is placed in output that is used as a web page that is served to other users.', 'keyphrase_sources': [{'id': 'rootcause:lack of CSRF protection', 'keyphrase': 'lack of CSRF protection', 'type': 'rootcause'}, {'id': 'weakness:XSS', 'keyphrase': 'XSS', 'type': 'weakness'}, {'id': 'weakness:cross-site scripting', 'keyphrase': 'cross-site scripting', 'type': 'weakness'}, {'id': 'impact:Stored XSS', 'keyphrase': 'Stored XSS', 'type': 'impact'}, {'id': 'product:Maeve Lander PayPal Responder', 'keyphrase': 'Maeve Lander PayPal Responder', 'type': 'product'}, {'id': 'version:n/a through 1.2', 'keyphrase': 'n/a through 1.2', 'type': 'version'}]}, 'similarity': np.float64(186.17141781586872)}, {'metadata': {'doc_id': '1004', 'name': \"Sensitive Cookie Without 'HttpOnly' Flag\", 'source': 'sparse', 'original_content': 'The product uses a cookie to store sensitive information, but the cookie is not marked with the HttpOnly flag.', 'keyphrase_sources': [{'id': 'rootcause:lack of CSRF protection', 'keyphrase': 'lack of CSRF protection', 'type': 'rootcause'}, {'id': 'weakness:XSS', 'keyphrase': 'XSS', 'type': 'weakness'}, {'id': 'weakness:cross-site scripting', 'keyphrase': 'cross-site scripting', 'type': 'weakness'}]}, 'similarity': np.float64(176.1572382404116)}, {'metadata': {'doc_id': '80', 'name': 'Improper Neutralization of Script-Related HTML Tags in a Web Page (Basic XSS)', 'source': 'sparse', 'original_content': 'The product receives input from an upstream component, but it does not neutralize or incorrectly neutralizes special characters such as \"<\", \">\", and \"&\" that could be interpreted as web-scripting elements when they are sent to a downstream component that processes web pages.', 'keyphrase_sources': [{'id': 'weakness:XSS', 'keyphrase': 'XSS', 'type': 'weakness'}, {'id': 'weakness:cross-site scripting', 'keyphrase': 'cross-site scripting', 'type': 'weakness'}, {'id': 'impact:Stored XSS', 'keyphrase': 'Stored XSS', 'type': 'impact'}]}, 'similarity': np.float64(136.85207218275954)}, {'metadata': {'doc_id': '22', 'name': \"Improper Limitation of a Pathname to a Restricted Directory ('Path Traversal')\", 'source': 'sparse', 'original_content': 'The product uses external input to construct a pathname that is intended to identify a file or directory that is located underneath a restricted parent directory, but the product does not properly neutralize special elements within the pathname that can cause the pathname to resolve to a location that is outside of the restricted directory.', 'keyphrase_sources': [{'id': 'version:n/a through 1.2', 'keyphrase': 'n/a through 1.2', 'type': 'version'}]}, 'similarity': np.float64(57.03495505176883)}, {'metadata': {'doc_id': '89', 'name': \"Improper Neutralization of Special Elements used in an SQL Command ('SQL Injection')\", 'source': 'sparse', 'original_content': 'The product constructs all or part of an SQL command using externally-influenced input from an upstream component, but it does not neutralize or incorrectly neutralizes special elements that could modify the intended SQL command when it is sent to a downstream component. Without sufficient removal or quoting of SQL syntax in user-controllable inputs, the generated SQL query can cause those inputs to be interpreted as SQL instead of ordinary user data.', 'keyphrase_sources': [{'id': 'version:n/a through 1.2', 'keyphrase': 'n/a through 1.2', 'type': 'version'}]}, 'similarity': np.float64(56.285643466083684)}, {'metadata': {'doc_id': '1315', 'name': 'Improper Setting of Bus Controlling Capability in Fabric End-point', 'source': 'sparse', 'original_content': 'The bus controller enables bits in the fabric end-point to allow responder devices to control transactions on the fabric.', 'keyphrase_sources': [{'id': 'product:Maeve Lander PayPal Responder', 'keyphrase': 'Maeve Lander PayPal Responder', 'type': 'product'}]}, 'similarity': np.float64(54.53377979259862)}, {'metadata': {'doc_id': '771', 'name': 'Missing Reference to Active Allocated Resource', 'source': 'sparse', 'original_content': 'The product does not properly maintain a reference to a resource that has been allocated, which prevents the resource from being reclaimed.', 'keyphrase_sources': [{'id': 'product:Maeve Lander PayPal Responder', 'keyphrase': 'Maeve Lander PayPal Responder', 'type': 'product'}]}, 'similarity': np.float64(45.5110825378644)}], identified_cwes={'analyzer': [], 'critic_additional': []})",
  "retrieval_results": {
    "has_multiple_keyphrases": true,
    "keyphrase_cwe_sets": {
      "rootcause:lack of CSRF protection": {
        "keyphrase": "lack of CSRF protection",
        "type": "rootcause",
        "cwes": [
          {
            "metadata": {
              "doc_id": "352",
              "name": "Cross-Site Request Forgery (CSRF)",
              "source": "sparse",
              "original_content": "The web application does not, or can not, sufficiently verify whether a well-formed, valid, consistent request was intentionally provided by the user who submitted the request.",
              "keyphrase_sources": [
                {
                  "id": "rootcause:lack of CSRF protection",
                  "keyphrase": "lack of CSRF protection",
                  "type": "rootcause"
                },
                {
                  "id": "weakness:XSS",
                  "keyphrase": "XSS",
                  "type": "weakness"
                },
                {
                  "id": "weakness:cross-site scripting",
                  "keyphrase": "cross-site scripting",
                  "type": "weakness"
                },
                {
                  "id": "impact:Stored XSS",
                  "keyphrase": "Stored XSS",
                  "type": "impact"
                },
                {
                  "id": "product:Maeve Lander PayPal Responder",
                  "keyphrase": "Maeve Lander PayPal Responder",
                  "type": "product"
                },
                {
                  "id": "version:n/a through 1.2",
                  "keyphrase": "n/a through 1.2",
                  "type": "version"
                }
              ]
            },
            "similarity": 275.9135274815367
          },
          {
            "metadata": {
              "doc_id": "434",
              "name": "Unrestricted Upload of File with Dangerous Type",
              "source": "sparse",
              "original_content": "The product allows the upload or transfer of dangerous file types that are automatically processed within its environment.",
              "keyphrase_sources": [
                {
                  "id": "rootcause:lack of CSRF protection",
                  "keyphrase": "lack of CSRF protection",
                  "type": "rootcause"
                },
                {
                  "id": "weakness:XSS",
                  "keyphrase": "XSS",
                  "type": "weakness"
                },
                {
                  "id": "weakness:cross-site scripting",
                  "keyphrase": "cross-site scripting",
                  "type": "weakness"
                },
                {
                  "id": "impact:Stored XSS",
                  "keyphrase": "Stored XSS",
                  "type": "impact"
                },
                {
                  "id": "product:Maeve Lander PayPal Responder",
                  "keyphrase": "Maeve Lander PayPal Responder",
                  "type": "product"
                },
                {
                  "id": "version:n/a through 1.2",
                  "keyphrase": "n/a through 1.2",
                  "type": "version"
                }
              ]
            },
            "similarity": 215.52988764225748
          },
          {
            "metadata": {
              "doc_id": "116",
              "name": "Improper Encoding or Escaping of Output",
              "source": "sparse",
              "original_content": "The product prepares a structured message for communication with another component, but encoding or escaping of the data is either missing or done incorrectly. As a result, the intended structure of the message is not preserved.",
              "keyphrase_sources": [
                {
                  "id": "rootcause:lack of CSRF protection",
                  "keyphrase": "lack of CSRF protection",
                  "type": "rootcause"
                },
                {
                  "id": "impact:Stored XSS",
                  "keyphrase": "Stored XSS",
                  "type": "impact"
                }
              ]
            },
            "similarity": 189.71179546387677
          },
          {
            "metadata": {
              "doc_id": "79",
              "name": "Improper Neutralization of Input During Web Page Generation ('Cross-site Scripting')",
              "source": "sparse",
              "original_content": "The product does not neutralize or incorrectly neutralizes user-controllable input before it is placed in output that is used as a web page that is served to other users.",
              "keyphrase_sources": [
                {
                  "id": "rootcause:lack of CSRF protection",
                  "keyphrase": "lack of CSRF protection",
                  "type": "rootcause"
                },
                {
                  "id": "weakness:XSS",
                  "keyphrase": "XSS",
                  "type": "weakness"
                },
                {
                  "id": "weakness:cross-site scripting",
                  "keyphrase": "cross-site scripting",
                  "type": "weakness"
                },
                {
                  "id": "impact:Stored XSS",
                  "keyphrase": "Stored XSS",
                  "type": "impact"
                },
                {
                  "id": "product:Maeve Lander PayPal Responder",
                  "keyphrase": "Maeve Lander PayPal Responder",
                  "type": "product"
                },
                {
                  "id": "version:n/a through 1.2",
                  "keyphrase": "n/a through 1.2",
                  "type": "version"
                }
              ]
            },
            "similarity": 186.17141781586872
          },
          {
            "metadata": {
              "doc_id": "1004",
              "name": "Sensitive Cookie Without 'HttpOnly' Flag",
              "source": "sparse",
              "original_content": "The product uses a cookie to store sensitive information, but the cookie is not marked with the HttpOnly flag.",
              "keyphrase_sources": [
                {
                  "id": "rootcause:lack of CSRF protection",
                  "keyphrase": "lack of CSRF protection",
                  "type": "rootcause"
                },
                {
                  "id": "weakness:XSS",
                  "keyphrase": "XSS",
                  "type": "weakness"
                },
                {
                  "id": "weakness:cross-site scripting",
                  "keyphrase": "cross-site scripting",
                  "type": "weakness"
                }
              ]
            },
            "similarity": 176.1572382404116
          }
        ]
      },
      "weakness:XSS": {
        "keyphrase": "XSS",
        "type": "weakness",
        "cwes": [
          {
            "metadata": {
              "doc_id": "352",
              "name": "Cross-Site Request Forgery (CSRF)",
              "source": "sparse",
              "original_content": "The web application does not, or can not, sufficiently verify whether a well-formed, valid, consistent request was intentionally provided by the user who submitted the request."
            },
            "similarity": 185.27773675872047
          },
          {
            "metadata": {
              "doc_id": "79",
              "name": "Improper Neutralization of Input During Web Page Generation ('Cross-site Scripting')",
              "source": "sparse",
              "original_content": "The product does not neutralize or incorrectly neutralizes user-controllable input before it is placed in output that is used as a web page that is served to other users."
            },
            "similarity": 155.52238129511878
          },
          {
            "metadata": {
              "doc_id": "434",
              "name": "Unrestricted Upload of File with Dangerous Type",
              "source": "sparse",
              "original_content": "The product allows the upload or transfer of dangerous file types that are automatically processed within its environment."
            },
            "similarity": 151.3522560425953
          },
          {
            "metadata": {
              "doc_id": "1004",
              "name": "Sensitive Cookie Without 'HttpOnly' Flag",
              "source": "sparse",
              "original_content": "The product uses a cookie to store sensitive information, but the cookie is not marked with the HttpOnly flag."
            },
            "similarity": 143.3115416458354
          },
          {
            "metadata": {
              "doc_id": "80",
              "name": "Improper Neutralization of Script-Related HTML Tags in a Web Page (Basic XSS)",
              "source": "sparse",
              "original_content": "The product receives input from an upstream component, but it does not neutralize or incorrectly neutralizes special characters such as \"<\", \">\", and \"&\" that could be interpreted as web-scripting elements when they are sent to a downstream component that processes web pages.",
              "keyphrase_sources": [
                {
                  "id": "weakness:XSS",
                  "keyphrase": "XSS",
                  "type": "weakness"
                },
                {
                  "id": "weakness:cross-site scripting",
                  "keyphrase": "cross-site scripting",
                  "type": "weakness"
                },
                {
                  "id": "impact:Stored XSS",
                  "keyphrase": "Stored XSS",
                  "type": "impact"
                }
              ]
            },
            "similarity": 136.85207218275954
          }
        ]
      },
      "weakness:cross-site scripting": {
        "keyphrase": "cross-site scripting",
        "type": "weakness",
        "cwes": [
          {
            "metadata": {
              "doc_id": "352",
              "name": "Cross-Site Request Forgery (CSRF)",
              "source": "sparse",
              "original_content": "The web application does not, or can not, sufficiently verify whether a well-formed, valid, consistent request was intentionally provided by the user who submitted the request."
            },
            "similarity": 253.3008820348564
          },
          {
            "metadata": {
              "doc_id": "79",
              "name": "Improper Neutralization of Input During Web Page Generation ('Cross-site Scripting')",
              "source": "sparse",
              "original_content": "The product does not neutralize or incorrectly neutralizes user-controllable input before it is placed in output that is used as a web page that is served to other users."
            },
            "similarity": 217.48717265200494
          },
          {
            "metadata": {
              "doc_id": "80",
              "name": "Improper Neutralization of Script-Related HTML Tags in a Web Page (Basic XSS)",
              "source": "sparse",
              "original_content": "The product receives input from an upstream component, but it does not neutralize or incorrectly neutralizes special characters such as \"<\", \">\", and \"&\" that could be interpreted as web-scripting elements when they are sent to a downstream component that processes web pages."
            },
            "similarity": 193.53057540123785
          },
          {
            "metadata": {
              "doc_id": "434",
              "name": "Unrestricted Upload of File with Dangerous Type",
              "source": "sparse",
              "original_content": "The product allows the upload or transfer of dangerous file types that are automatically processed within its environment."
            },
            "similarity": 189.96082119087197
          },
          {
            "metadata": {
              "doc_id": "1004",
              "name": "Sensitive Cookie Without 'HttpOnly' Flag",
              "source": "sparse",
              "original_content": "The product uses a cookie to store sensitive information, but the cookie is not marked with the HttpOnly flag."
            },
            "similarity": 187.8633183919802
          }
        ]
      },
      "impact:Stored XSS": {
        "keyphrase": "Stored XSS",
        "type": "impact",
        "cwes": [
          {
            "metadata": {
              "doc_id": "352",
              "name": "Cross-Site Request Forgery (CSRF)",
              "source": "sparse",
              "original_content": "The web application does not, or can not, sufficiently verify whether a well-formed, valid, consistent request was intentionally provided by the user who submitted the request."
            },
            "similarity": 74.29387913772524
          },
          {
            "metadata": {
              "doc_id": "79",
              "name": "Improper Neutralization of Input During Web Page Generation ('Cross-site Scripting')",
              "source": "sparse",
              "original_content": "The product does not neutralize or incorrectly neutralizes user-controllable input before it is placed in output that is used as a web page that is served to other users."
            },
            "similarity": 61.55218011370554
          },
          {
            "metadata": {
              "doc_id": "434",
              "name": "Unrestricted Upload of File with Dangerous Type",
              "source": "sparse",
              "original_content": "The product allows the upload or transfer of dangerous file types that are automatically processed within its environment."
            },
            "similarity": 60.055556600969375
          },
          {
            "metadata": {
              "doc_id": "116",
              "name": "Improper Encoding or Escaping of Output",
              "source": "sparse",
              "original_content": "The product prepares a structured message for communication with another component, but encoding or escaping of the data is either missing or done incorrectly. As a result, the intended structure of the message is not preserved."
            },
            "similarity": 55.420104908731986
          },
          {
            "metadata": {
              "doc_id": "80",
              "name": "Improper Neutralization of Script-Related HTML Tags in a Web Page (Basic XSS)",
              "source": "sparse",
              "original_content": "The product receives input from an upstream component, but it does not neutralize or incorrectly neutralizes special characters such as \"<\", \">\", and \"&\" that could be interpreted as web-scripting elements when they are sent to a downstream component that processes web pages."
            },
            "similarity": 54.800125844781164
          }
        ]
      },
      "product:Maeve Lander PayPal Responder": {
        "keyphrase": "Maeve Lander PayPal Responder",
        "type": "product",
        "cwes": [
          {
            "metadata": {
              "doc_id": "352",
              "name": "Cross-Site Request Forgery (CSRF)",
              "source": "sparse",
              "original_content": "The web application does not, or can not, sufficiently verify whether a well-formed, valid, consistent request was intentionally provided by the user who submitted the request."
            },
            "similarity": 59.21170340592025
          },
          {
            "metadata": {
              "doc_id": "1315",
              "name": "Improper Setting of Bus Controlling Capability in Fabric End-point",
              "source": "sparse",
              "original_content": "The bus controller enables bits in the fabric end-point to allow responder devices to control transactions on the fabric.",
              "keyphrase_sources": [
                {
                  "id": "product:Maeve Lander PayPal Responder",
                  "keyphrase": "Maeve Lander PayPal Responder",
                  "type": "product"
                }
              ]
            },
            "similarity": 54.53377979259862
          },
          {
            "metadata": {
              "doc_id": "434",
              "name": "Unrestricted Upload of File with Dangerous Type",
              "source": "sparse",
              "original_content": "The product allows the upload or transfer of dangerous file types that are automatically processed within its environment."
            },
            "similarity": 52.387788331728764
          },
          {
            "metadata": {
              "doc_id": "771",
              "name": "Missing Reference to Active Allocated Resource",
              "source": "sparse",
              "original_content": "The product does not properly maintain a reference to a resource that has been allocated, which prevents the resource from being reclaimed.",
              "keyphrase_sources": [
                {
                  "id": "product:Maeve Lander PayPal Responder",
                  "keyphrase": "Maeve Lander PayPal Responder",
                  "type": "product"
                }
              ]
            },
            "similarity": 45.5110825378644
          },
          {
            "metadata": {
              "doc_id": "79",
              "name": "Improper Neutralization of Input During Web Page Generation ('Cross-site Scripting')",
              "source": "sparse",
              "original_content": "The product does not neutralize or incorrectly neutralizes user-controllable input before it is placed in output that is used as a web page that is served to other users."
            },
            "similarity": 44.97733921658136
          }
        ]
      },
      "version:n/a through 1.2": {
        "keyphrase": "n/a through 1.2",
        "type": "version",
        "cwes": [
          {
            "metadata": {
              "doc_id": "352",
              "name": "Cross-Site Request Forgery (CSRF)",
              "source": "sparse",
              "original_content": "The web application does not, or can not, sufficiently verify whether a well-formed, valid, consistent request was intentionally provided by the user who submitted the request."
            },
            "similarity": 70.88874394725819
          },
          {
            "metadata": {
              "doc_id": "434",
              "name": "Unrestricted Upload of File with Dangerous Type",
              "source": "sparse",
              "original_content": "The product allows the upload or transfer of dangerous file types that are automatically processed within its environment."
            },
            "similarity": 65.69116208944195
          },
          {
            "metadata": {
              "doc_id": "79",
              "name": "Improper Neutralization of Input During Web Page Generation ('Cross-site Scripting')",
              "source": "sparse",
              "original_content": "The product does not neutralize or incorrectly neutralizes user-controllable input before it is placed in output that is used as a web page that is served to other users."
            },
            "similarity": 58.11331632912904
          },
          {
            "metadata": {
              "doc_id": "22",
              "name": "Improper Limitation of a Pathname to a Restricted Directory ('Path Traversal')",
              "source": "sparse",
              "original_content": "The product uses external input to construct a pathname that is intended to identify a file or directory that is located underneath a restricted parent directory, but the product does not properly neutralize special elements within the pathname that can cause the pathname to resolve to a location that is outside of the restricted directory.",
              "keyphrase_sources": [
                {
                  "id": "version:n/a through 1.2",
                  "keyphrase": "n/a through 1.2",
                  "type": "version"
                }
              ]
            },
            "similarity": 57.03495505176883
          },
          {
            "metadata": {
              "doc_id": "89",
              "name": "Improper Neutralization of Special Elements used in an SQL Command ('SQL Injection')",
              "source": "sparse",
              "original_content": "The product constructs all or part of an SQL command using externally-influenced input from an upstream component, but it does not neutralize or incorrectly neutralizes special elements that could modify the intended SQL command when it is sent to a downstream component. Without sufficient removal or quoting of SQL syntax in user-controllable inputs, the generated SQL query can cause those inputs to be interpreted as SQL instead of ordinary user data.",
              "keyphrase_sources": [
                {
                  "id": "version:n/a through 1.2",
                  "keyphrase": "n/a through 1.2",
                  "type": "version"
                }
              ]
            },
            "similarity": 56.285643466083684
          }
        ]
      }
    },
    "keyphrase_mapping": {
      "352": [
        {
          "id": "rootcause:lack of CSRF protection",
          "keyphrase": "lack of CSRF protection",
          "type": "rootcause"
        },
        {
          "id": "weakness:XSS",
          "keyphrase": "XSS",
          "type": "weakness"
        },
        {
          "id": "weakness:cross-site scripting",
          "keyphrase": "cross-site scripting",
          "type": "weakness"
        },
        {
          "id": "impact:Stored XSS",
          "keyphrase": "Stored XSS",
          "type": "impact"
        },
        {
          "id": "product:Maeve Lander PayPal Responder",
          "keyphrase": "Maeve Lander PayPal Responder",
          "type": "product"
        },
        {
          "id": "version:n/a through 1.2",
          "keyphrase": "n/a through 1.2",
          "type": "version"
        }
      ],
      "434": [
        {
          "id": "rootcause:lack of CSRF protection",
          "keyphrase": "lack of CSRF protection",
          "type": "rootcause"
        },
        {
          "id": "weakness:XSS",
          "keyphrase": "XSS",
          "type": "weakness"
        },
        {
          "id": "weakness:cross-site scripting",
          "keyphrase": "cross-site scripting",
          "type": "weakness"
        },
        {
          "id": "impact:Stored XSS",
          "keyphrase": "Stored XSS",
          "type": "impact"
        },
        {
          "id": "product:Maeve Lander PayPal Responder",
          "keyphrase": "Maeve Lander PayPal Responder",
          "type": "product"
        },
        {
          "id": "version:n/a through 1.2",
          "keyphrase": "n/a through 1.2",
          "type": "version"
        }
      ],
      "116": [
        {
          "id": "rootcause:lack of CSRF protection",
          "keyphrase": "lack of CSRF protection",
          "type": "rootcause"
        },
        {
          "id": "impact:Stored XSS",
          "keyphrase": "Stored XSS",
          "type": "impact"
        }
      ],
      "79": [
        {
          "id": "rootcause:lack of CSRF protection",
          "keyphrase": "lack of CSRF protection",
          "type": "rootcause"
        },
        {
          "id": "weakness:XSS",
          "keyphrase": "XSS",
          "type": "weakness"
        },
        {
          "id": "weakness:cross-site scripting",
          "keyphrase": "cross-site scripting",
          "type": "weakness"
        },
        {
          "id": "impact:Stored XSS",
          "keyphrase": "Stored XSS",
          "type": "impact"
        },
        {
          "id": "product:Maeve Lander PayPal Responder",
          "keyphrase": "Maeve Lander PayPal Responder",
          "type": "product"
        },
        {
          "id": "version:n/a through 1.2",
          "keyphrase": "n/a through 1.2",
          "type": "version"
        }
      ],
      "1004": [
        {
          "id": "rootcause:lack of CSRF protection",
          "keyphrase": "lack of CSRF protection",
          "type": "rootcause"
        },
        {
          "id": "weakness:XSS",
          "keyphrase": "XSS",
          "type": "weakness"
        },
        {
          "id": "weakness:cross-site scripting",
          "keyphrase": "cross-site scripting",
          "type": "weakness"
        }
      ],
      "80": [
        {
          "id": "weakness:XSS",
          "keyphrase": "XSS",
          "type": "weakness"
        },
        {
          "id": "weakness:cross-site scripting",
          "keyphrase": "cross-site scripting",
          "type": "weakness"
        },
        {
          "id": "impact:Stored XSS",
          "keyphrase": "Stored XSS",
          "type": "impact"
        }
      ],
      "1315": [
        {
          "id": "product:Maeve Lander PayPal Responder",
          "keyphrase": "Maeve Lander PayPal Responder",
          "type": "product"
        }
      ],
      "771": [
        {
          "id": "product:Maeve Lander PayPal Responder",
          "keyphrase": "Maeve Lander PayPal Responder",
          "type": "product"
        }
      ],
      "22": [
        {
          "id": "version:n/a through 1.2",
          "keyphrase": "n/a through 1.2",
          "type": "version"
        }
      ],
      "89": [
        {
          "id": "version:n/a through 1.2",
          "keyphrase": "n/a through 1.2",
          "type": "version"
        }
      ]
    },
    "relevant_cwes": [
      {
        "metadata": {
          "doc_id": "352",
          "name": "Cross-Site Request Forgery (CSRF)",
          "source": "sparse",
          "original_content": "The web application does not, or can not, sufficiently verify whether a well-formed, valid, consistent request was intentionally provided by the user who submitted the request.",
          "keyphrase_sources": [
            {
              "id": "rootcause:lack of CSRF protection",
              "keyphrase": "lack of CSRF protection",
              "type": "rootcause"
            },
            {
              "id": "weakness:XSS",
              "keyphrase": "XSS",
              "type": "weakness"
            },
            {
              "id": "weakness:cross-site scripting",
              "keyphrase": "cross-site scripting",
              "type": "weakness"
            },
            {
              "id": "impact:Stored XSS",
              "keyphrase": "Stored XSS",
              "type": "impact"
            },
            {
              "id": "product:Maeve Lander PayPal Responder",
              "keyphrase": "Maeve Lander PayPal Responder",
              "type": "product"
            },
            {
              "id": "version:n/a through 1.2",
              "keyphrase": "n/a through 1.2",
              "type": "version"
            }
          ]
        },
        "similarity": 275.9135274815367
      },
      {
        "metadata": {
          "doc_id": "434",
          "name": "Unrestricted Upload of File with Dangerous Type",
          "source": "sparse",
          "original_content": "The product allows the upload or transfer of dangerous file types that are automatically processed within its environment.",
          "keyphrase_sources": [
            {
              "id": "rootcause:lack of CSRF protection",
              "keyphrase": "lack of CSRF protection",
              "type": "rootcause"
            },
            {
              "id": "weakness:XSS",
              "keyphrase": "XSS",
              "type": "weakness"
            },
            {
              "id": "weakness:cross-site scripting",
              "keyphrase": "cross-site scripting",
              "type": "weakness"
            },
            {
              "id": "impact:Stored XSS",
              "keyphrase": "Stored XSS",
              "type": "impact"
            },
            {
              "id": "product:Maeve Lander PayPal Responder",
              "keyphrase": "Maeve Lander PayPal Responder",
              "type": "product"
            },
            {
              "id": "version:n/a through 1.2",
              "keyphrase": "n/a through 1.2",
              "type": "version"
            }
          ]
        },
        "similarity": 215.52988764225748
      },
      {
        "metadata": {
          "doc_id": "116",
          "name": "Improper Encoding or Escaping of Output",
          "source": "sparse",
          "original_content": "The product prepares a structured message for communication with another component, but encoding or escaping of the data is either missing or done incorrectly. As a result, the intended structure of the message is not preserved.",
          "keyphrase_sources": [
            {
              "id": "rootcause:lack of CSRF protection",
              "keyphrase": "lack of CSRF protection",
              "type": "rootcause"
            },
            {
              "id": "impact:Stored XSS",
              "keyphrase": "Stored XSS",
              "type": "impact"
            }
          ]
        },
        "similarity": 189.71179546387677
      },
      {
        "metadata": {
          "doc_id": "79",
          "name": "Improper Neutralization of Input During Web Page Generation ('Cross-site Scripting')",
          "source": "sparse",
          "original_content": "The product does not neutralize or incorrectly neutralizes user-controllable input before it is placed in output that is used as a web page that is served to other users.",
          "keyphrase_sources": [
            {
              "id": "rootcause:lack of CSRF protection",
              "keyphrase": "lack of CSRF protection",
              "type": "rootcause"
            },
            {
              "id": "weakness:XSS",
              "keyphrase": "XSS",
              "type": "weakness"
            },
            {
              "id": "weakness:cross-site scripting",
              "keyphrase": "cross-site scripting",
              "type": "weakness"
            },
            {
              "id": "impact:Stored XSS",
              "keyphrase": "Stored XSS",
              "type": "impact"
            },
            {
              "id": "product:Maeve Lander PayPal Responder",
              "keyphrase": "Maeve Lander PayPal Responder",
              "type": "product"
            },
            {
              "id": "version:n/a through 1.2",
              "keyphrase": "n/a through 1.2",
              "type": "version"
            }
          ]
        },
        "similarity": 186.17141781586872
      },
      {
        "metadata": {
          "doc_id": "1004",
          "name": "Sensitive Cookie Without 'HttpOnly' Flag",
          "source": "sparse",
          "original_content": "The product uses a cookie to store sensitive information, but the cookie is not marked with the HttpOnly flag.",
          "keyphrase_sources": [
            {
              "id": "rootcause:lack of CSRF protection",
              "keyphrase": "lack of CSRF protection",
              "type": "rootcause"
            },
            {
              "id": "weakness:XSS",
              "keyphrase": "XSS",
              "type": "weakness"
            },
            {
              "id": "weakness:cross-site scripting",
              "keyphrase": "cross-site scripting",
              "type": "weakness"
            }
          ]
        },
        "similarity": 176.1572382404116
      },
      {
        "metadata": {
          "doc_id": "80",
          "name": "Improper Neutralization of Script-Related HTML Tags in a Web Page (Basic XSS)",
          "source": "sparse",
          "original_content": "The product receives input from an upstream component, but it does not neutralize or incorrectly neutralizes special characters such as \"<\", \">\", and \"&\" that could be interpreted as web-scripting elements when they are sent to a downstream component that processes web pages.",
          "keyphrase_sources": [
            {
              "id": "weakness:XSS",
              "keyphrase": "XSS",
              "type": "weakness"
            },
            {
              "id": "weakness:cross-site scripting",
              "keyphrase": "cross-site scripting",
              "type": "weakness"
            },
            {
              "id": "impact:Stored XSS",
              "keyphrase": "Stored XSS",
              "type": "impact"
            }
          ]
        },
        "similarity": 136.85207218275954
      },
      {
        "metadata": {
          "doc_id": "22",
          "name": "Improper Limitation of a Pathname to a Restricted Directory ('Path Traversal')",
          "source": "sparse",
          "original_content": "The product uses external input to construct a pathname that is intended to identify a file or directory that is located underneath a restricted parent directory, but the product does not properly neutralize special elements within the pathname that can cause the pathname to resolve to a location that is outside of the restricted directory.",
          "keyphrase_sources": [
            {
              "id": "version:n/a through 1.2",
              "keyphrase": "n/a through 1.2",
              "type": "version"
            }
          ]
        },
        "similarity": 57.03495505176883
      },
      {
        "metadata": {
          "doc_id": "89",
          "name": "Improper Neutralization of Special Elements used in an SQL Command ('SQL Injection')",
          "source": "sparse",
          "original_content": "The product constructs all or part of an SQL command using externally-influenced input from an upstream component, but it does not neutralize or incorrectly neutralizes special elements that could modify the intended SQL command when it is sent to a downstream component. Without sufficient removal or quoting of SQL syntax in user-controllable inputs, the generated SQL query can cause those inputs to be interpreted as SQL instead of ordinary user data.",
          "keyphrase_sources": [
            {
              "id": "version:n/a through 1.2",
              "keyphrase": "n/a through 1.2",
              "type": "version"
            }
          ]
        },
        "similarity": 56.285643466083684
      },
      {
        "metadata": {
          "doc_id": "1315",
          "name": "Improper Setting of Bus Controlling Capability in Fabric End-point",
          "source": "sparse",
          "original_content": "The bus controller enables bits in the fabric end-point to allow responder devices to control transactions on the fabric.",
          "keyphrase_sources": [
            {
              "id": "product:Maeve Lander PayPal Responder",
              "keyphrase": "Maeve Lander PayPal Responder",
              "type": "product"
            }
          ]
        },
        "similarity": 54.53377979259862
      },
      {
        "metadata": {
          "doc_id": "771",
          "name": "Missing Reference to Active Allocated Resource",
          "source": "sparse",
          "original_content": "The product does not properly maintain a reference to a resource that has been allocated, which prevents the resource from being reclaimed.",
          "keyphrase_sources": [
            {
              "id": "product:Maeve Lander PayPal Responder",
              "keyphrase": "Maeve Lander PayPal Responder",
              "type": "product"
            }
          ]
        },
        "similarity": 45.5110825378644
      }
    ],
    "enhanced_query": "# Vulnerability Description\n\n    Cross-Site Request Forgery (CSRF) vulnerability in Maeve Lander PayPal Responder allows Stored **XSS**.This issue affects PayPal Responder from n/a through 1.2.\n\n    # Keyphrase-Specific CWE Analysis\n    This vulnerability contains multiple keyphrases that may map to different CWEs. \n    Please analyze each keyphrase separately and determine the most appropriate CWE(s) for each.\n\n    ## ROOTCAUSE: 'lack of CSRF protection'\n\nRelevant CWEs for this ROOTCAUSE:\n\n### 1. CWE-352: Cross-Site Request Forgery (CSRF) (Score: 275.91)\n\nThe web application does not, or can not, sufficiently verify whether a well-formed, valid, consistent request was intentionally provided by the user who submitted the request....\n\n### 2. CWE-434: Unrestricted Upload of File with Dangerous Type (Score: 215.53)\n\nThe product allows the upload or transfer of dangerous file types that are automatically processed within its environment....\n\n### 3. CWE-116: Improper Encoding or Escaping of Output (Score: 189.71)\n\nThe product prepares a structured message for communication with another component, but encoding or escaping of the data is either missing or done incorrectly. As a result, the intended structure of the message is not preserved....\n\n### 4. CWE-79: Improper Neutralization of Input During Web Page Generation ('Cross-site Scripting') (Score: 186.17)\n\nThe product does not neutralize or incorrectly neutralizes user-controllable input before it is placed in output that is used as a web page that is served to other users....\n\n### 5. CWE-1004: Sensitive Cookie Without 'HttpOnly' Flag (Score: 176.16)\n\nThe product uses a cookie to store sensitive information, but the cookie is not marked with the HttpOnly flag....\n\n## WEAKNESS: 'XSS'\n\nRelevant CWEs for this WEAKNESS:\n\n### 1. CWE-352: Cross-Site Request Forgery (CSRF) (Score: 275.91)\n\nThe web application does not, or can not, sufficiently verify whether a well-formed, valid, consistent request was intentionally provided by the user who submitted the request....\n\n### 2. CWE-434: Unrestricted Upload of File with Dangerous Type (Score: 215.53)\n\nThe product allows the upload or transfer of dangerous file types that are automatically processed within its environment....\n\n### 3. CWE-79: Improper Neutralization of Input During Web Page Generation ('Cross-site Scripting') (Score: 186.17)\n\nThe product does not neutralize or incorrectly neutralizes user-controllable input before it is placed in output that is used as a web page that is served to other users....\n\n### 4. CWE-1004: Sensitive Cookie Without 'HttpOnly' Flag (Score: 176.16)\n\nThe product uses a cookie to store sensitive information, but the cookie is not marked with the HttpOnly flag....\n\n### 5. CWE-80: Improper Neutralization of Script-Related HTML Tags in a Web Page (Basic XSS) (Score: 136.85)\n\nThe product receives input from an upstream component, but it does not neutralize or incorrectly neutralizes special characters such as \"<\", \">\", and \"&\" that could be interpreted as web-scripting elements when they are sent to a downstream component that processes web pages....\n\n## WEAKNESS: 'cross-site scripting'\n\nRelevant CWEs for this WEAKNESS:\n\n### 1. CWE-352: Cross-Site Request Forgery (CSRF) (Score: 275.91)\n\nThe web application does not, or can not, sufficiently verify whether a well-formed, valid, consistent request was intentionally provided by the user who submitted the request....\n\n### 2. CWE-434: Unrestricted Upload of File with Dangerous Type (Score: 215.53)\n\nThe product allows the upload or transfer of dangerous file types that are automatically processed within its environment....\n\n### 3. CWE-79: Improper Neutralization of Input During Web Page Generation ('Cross-site Scripting') (Score: 186.17)\n\nThe product does not neutralize or incorrectly neutralizes user-controllable input before it is placed in output that is used as a web page that is served to other users....\n\n### 4. CWE-1004: Sensitive Cookie Without 'HttpOnly' Flag (Score: 176.16)\n\nThe product uses a cookie to store sensitive information, but the cookie is not marked with the HttpOnly flag....\n\n### 5. CWE-80: Improper Neutralization of Script-Related HTML Tags in a Web Page (Basic XSS) (Score: 136.85)\n\nThe product receives input from an upstream component, but it does not neutralize or incorrectly neutralizes special characters such as \"<\", \">\", and \"&\" that could be interpreted as web-scripting elements when they are sent to a downstream component that processes web pages....\n\n## IMPACT: 'Stored XSS'\n\nRelevant CWEs for this IMPACT:\n\n### 1. CWE-352: Cross-Site Request Forgery (CSRF) (Score: 275.91)\n\nThe web application does not, or can not, sufficiently verify whether a well-formed, valid, consistent request was intentionally provided by the user who submitted the request....\n\n### 2. CWE-434: Unrestricted Upload of File with Dangerous Type (Score: 215.53)\n\nThe product allows the upload or transfer of dangerous file types that are automatically processed within its environment....\n\n### 3. CWE-116: Improper Encoding or Escaping of Output (Score: 189.71)\n\nThe product prepares a structured message for communication with another component, but encoding or escaping of the data is either missing or done incorrectly. As a result, the intended structure of the message is not preserved....\n\n### 4. CWE-79: Improper Neutralization of Input During Web Page Generation ('Cross-site Scripting') (Score: 186.17)\n\nThe product does not neutralize or incorrectly neutralizes user-controllable input before it is placed in output that is used as a web page that is served to other users....\n\n### 5. CWE-80: Improper Neutralization of Script-Related HTML Tags in a Web Page (Basic XSS) (Score: 136.85)\n\nThe product receives input from an upstream component, but it does not neutralize or incorrectly neutralizes special characters such as \"<\", \">\", and \"&\" that could be interpreted as web-scripting elements when they are sent to a downstream component that processes web pages....\n\n## PRODUCT: 'Maeve Lander PayPal Responder'\n\nRelevant CWEs for this PRODUCT:\n\n### 1. CWE-352: Cross-Site Request Forgery (CSRF) (Score: 275.91)\n\nThe web application does not, or can not, sufficiently verify whether a well-formed, valid, consistent request was intentionally provided by the user who submitted the request....\n\n### 2. CWE-434: Unrestricted Upload of File with Dangerous Type (Score: 215.53)\n\nThe product allows the upload or transfer of dangerous file types that are automatically processed within its environment....\n\n### 3. CWE-79: Improper Neutralization of Input During Web Page Generation ('Cross-site Scripting') (Score: 186.17)\n\nThe product does not neutralize or incorrectly neutralizes user-controllable input before it is placed in output that is used as a web page that is served to other users....\n\n### 4. CWE-1315: Improper Setting of Bus Controlling Capability in Fabric End-point (Score: 54.53)\n\nThe bus controller enables bits in the fabric end-point to allow responder devices to control transactions on the fabric....\n\n### 5. CWE-771: Missing Reference to Active Allocated Resource (Score: 45.51)\n\nThe product does not properly maintain a reference to a resource that has been allocated, which prevents the resource from being reclaimed....\n\n## VERSION: 'n/a through 1.2'\n\nRelevant CWEs for this VERSION:\n\n### 1. CWE-352: Cross-Site Request Forgery (CSRF) (Score: 275.91)\n\nThe web application does not, or can not, sufficiently verify whether a well-formed, valid, consistent request was intentionally provided by the user who submitted the request....\n\n### 2. CWE-434: Unrestricted Upload of File with Dangerous Type (Score: 215.53)\n\nThe product allows the upload or transfer of dangerous file types that are automatically processed within its environment....\n\n### 3. CWE-79: Improper Neutralization of Input During Web Page Generation ('Cross-site Scripting') (Score: 186.17)\n\nThe product does not neutralize or incorrectly neutralizes user-controllable input before it is placed in output that is used as a web page that is served to other users....\n\n### 4. CWE-22: Improper Limitation of a Pathname to a Restricted Directory ('Path Traversal') (Score: 57.03)\n\nThe product uses external input to construct a pathname that is intended to identify a file or directory that is located underneath a restricted parent directory, but the product does not properly neutralize special elements within the pathname that can cause the pathname to resolve to a location th...\n\n### 5. CWE-89: Improper Neutralization of Special Elements used in an SQL Command ('SQL Injection') (Score: 56.29)\n\nThe product constructs all or part of an SQL command using externally-influenced input from an upstream component, but it does not neutralize or incorrectly neutralizes special elements that could modify the intended SQL command when it is sent to a downstream component. Without sufficient removal o...\n\n\n    # Analysis Instructions\n    1. For each keyphrase, identify the most appropriate CWE(s) that represent the weakness.\n    2. Consider how the different keyphrases might relate to each other in the vulnerability chain.\n    3. Provide a final determination of primary CWE(s) and any secondary CWEs.\n    4. Format your response using the standard analysis template.\n\n    Please analyze how these different weaknesses interact and provide a comprehensive CWE classification.\n    "
  },
  "retrieval_time": 1.0704939365386963
}