{
  "vulnerability_info": "VulnerabilityInfo(cve_id='CVE-2024-40240', description='An incorrect **access control issue** in HomeServe Home Repair android app - 3.3.4 allows a physically proximate attacker to escalate privileges via the fingerprint authentication function.', key_phrases={'rootcause': ['access control issue', 'incorrect access control'], 'weakness': '', 'impact': 'escalate privileges', 'vector': 'fingerprint authentication function', 'attacker': 'physically proximate attacker', 'product': 'HomeServe Home Repair android app', 'version': '3.3.4', 'component': ''}, reference_content='Based on the provided content, here\\'s an analysis:\\n\\n**Root cause of vulnerability:**\\n\\nThe root cause is improper implementation of fingerprint authentication in the \"HomeServe - Home Repair\" app, specifically related to how it handles changes to device fingerprints and disabling the fingerprint feature.\\n\\n**Weaknesses/vulnerabilities present:**\\n\\n1.  **Failure to invalidate fingerprint authentication on new fingerprint enrollment:** The app doesn\\'t disable or re-authenticate when a new fingerprint is added to the device. This allows a new fingerprint to bypass the existing authentication mechanism.\\n2.  **Lack of identity verification when disabling fingerprint feature:** The app doesn\\'t verify the user\\'s identity before disabling fingerprint authentication, making it easy to disable and bypass security.\\n\\n**Impact of exploitation:**\\n\\n*   **Unauthorized Access:** An attacker could gain unauthorized access to a user\\'s HomeServe account by registering a new fingerprint on the device.\\n*   **Compromised Fingerprint Protection:** The attacker can disable the fingerprint security, making the app vulnerable. This can lead to a complete bypass of fingerprint protection.\\n\\n**Attack vectors:**\\n\\n*   **Physical Access to Device:** The attacker needs physical access to the user\\'s unlocked device to register a new fingerprint.\\n\\n**Required attacker capabilities/position:**\\n\\n*   **Physical access to the victim\\'s device:** The attacker needs to have physical access to the victim\\'s device when it is unlocked\\n*   **Ability to add a new fingerprint:** The attacker needs to be able to add a new fingerprint to the device\\'s settings.', similar_info={'cwe_distribution': {}, 'cwe_consensus': '', 'similarity_stats': {'thresholds': [], 'total_samples_by_threshold': {}, 'top_cwes_by_threshold': {}}}, similarity_summary=SimilarityInsight(consensus_cwe='', top_cwes=[], confidence_levels={}, total_samples=0), analysis='', analysis_with_relationships='', criticism='', resolution='', relevant_cwes=[{'metadata': {'doc_id': '284', 'name': 'Improper Access Control', 'source': 'sparse', 'original_content': 'The product does not restrict or incorrectly restricts access to a resource from an unauthorized actor.', 'keyphrase_sources': [{'id': 'rootcause:access control issue', 'keyphrase': 'access control issue', 'type': 'rootcause'}, {'id': 'rootcause:incorrect access control', 'keyphrase': 'incorrect access control', 'type': 'rootcause'}, {'id': 'impact:escalate privileges', 'keyphrase': 'escalate privileges', 'type': 'impact'}, {'id': 'vector:fingerprint authentication function', 'keyphrase': 'fingerprint authentication function', 'type': 'vector'}, {'id': 'version:3.3.4', 'keyphrase': '3.3.4', 'type': 'version'}]}, 'similarity': np.float64(175.07524981561176)}, {'metadata': {'doc_id': '732', 'name': 'Incorrect Permission Assignment for Critical Resource', 'source': 'sparse', 'original_content': 'The product specifies permissions for a security-critical resource in a way that allows that resource to be read or modified by unintended actors.', 'keyphrase_sources': [{'id': 'rootcause:access control issue', 'keyphrase': 'access control issue', 'type': 'rootcause'}, {'id': 'rootcause:incorrect access control', 'keyphrase': 'incorrect access control', 'type': 'rootcause'}, {'id': 'impact:escalate privileges', 'keyphrase': 'escalate privileges', 'type': 'impact'}, {'id': 'product:HomeServe Home Repair android app', 'keyphrase': 'HomeServe Home Repair android app', 'type': 'product'}, {'id': 'version:3.3.4', 'keyphrase': '3.3.4', 'type': 'version'}]}, 'similarity': np.float64(172.98388646089)}, {'metadata': {'doc_id': '266', 'name': 'Incorrect Privilege Assignment', 'source': 'sparse', 'original_content': 'A product incorrectly assigns a privilege to a particular actor, creating an unintended sphere of control for that actor.', 'keyphrase_sources': [{'id': 'rootcause:incorrect access control', 'keyphrase': 'incorrect access control', 'type': 'rootcause'}, {'id': 'impact:escalate privileges', 'keyphrase': 'escalate privileges', 'type': 'impact'}]}, 'similarity': np.float64(170.61060397503084)}, {'metadata': {'doc_id': '1263', 'name': 'Improper Physical Access Control', 'source': 'sparse', 'original_content': 'The product is designed with access restricted to certain information, but it does not sufficiently protect against an unauthorized actor with physical access to these areas.', 'keyphrase_sources': [{'id': 'rootcause:access control issue', 'keyphrase': 'access control issue', 'type': 'rootcause'}, {'id': 'rootcause:incorrect access control', 'keyphrase': 'incorrect access control', 'type': 'rootcause'}, {'id': 'attacker:physically proximate attacker', 'keyphrase': 'physically proximate attacker', 'type': 'attacker'}]}, 'similarity': np.float64(169.59317251953746)}, {'metadata': {'doc_id': '863', 'name': 'Incorrect Authorization', 'source': 'sparse', 'original_content': 'The product performs an authorization check when an actor attempts to access a resource or perform an action, but it does not correctly perform the check.', 'keyphrase_sources': [{'id': 'rootcause:access control issue', 'keyphrase': 'access control issue', 'type': 'rootcause'}, {'id': 'rootcause:incorrect access control', 'keyphrase': 'incorrect access control', 'type': 'rootcause'}, {'id': 'vector:fingerprint authentication function', 'keyphrase': 'fingerprint authentication function', 'type': 'vector'}, {'id': 'version:3.3.4', 'keyphrase': '3.3.4', 'type': 'version'}]}, 'similarity': np.float64(167.59009620566172)}, {'metadata': {'doc_id': '290', 'name': 'Authentication Bypass by Spoofing', 'source': 'sparse', 'original_content': 'This attack-focused weakness is caused by incorrectly implemented authentication schemes that are subject to spoofing attacks.', 'keyphrase_sources': [{'id': 'rootcause:access control issue', 'keyphrase': 'access control issue', 'type': 'rootcause'}, {'id': 'vector:fingerprint authentication function', 'keyphrase': 'fingerprint authentication function', 'type': 'vector'}, {'id': 'product:HomeServe Home Repair android app', 'keyphrase': 'HomeServe Home Repair android app', 'type': 'product'}, {'id': 'version:3.3.4', 'keyphrase': '3.3.4', 'type': 'version'}]}, 'similarity': np.float64(166.39702747315332)}, {'metadata': {'doc_id': '311', 'name': 'Missing Encryption of Sensitive Data', 'source': 'sparse', 'original_content': 'The product does not encrypt sensitive or critical information before storage or transmission.', 'keyphrase_sources': [{'id': 'attacker:physically proximate attacker', 'keyphrase': 'physically proximate attacker', 'type': 'attacker'}]}, 'similarity': np.float64(70.98985077540881)}, {'metadata': {'doc_id': '1247', 'name': 'Improper Protection Against Voltage and Clock Glitches', 'source': 'sparse', 'original_content': 'The device does not contain or contains incorrectly implemented circuitry or sensors to detect and mitigate voltage and clock glitches and protect sensitive information or software contained on the device.', 'keyphrase_sources': [{'id': 'attacker:physically proximate attacker', 'keyphrase': 'physically proximate attacker', 'type': 'attacker'}]}, 'similarity': np.float64(68.68879918544867)}, {'metadata': {'doc_id': '549', 'name': 'Missing Password Field Masking', 'source': 'sparse', 'original_content': 'The product does not mask passwords during entry, increasing the potential for attackers to observe and capture passwords.', 'keyphrase_sources': [{'id': 'attacker:physically proximate attacker', 'keyphrase': 'physically proximate attacker', 'type': 'attacker'}]}, 'similarity': np.float64(67.9717550820775)}, {'metadata': {'doc_id': '707', 'name': 'Improper Neutralization', 'source': 'sparse', 'original_content': 'The product does not ensure or incorrectly ensures that structured messages or data are well-formed and that certain security properties are met before being read from an upstream component or sent to a downstream component.', 'keyphrase_sources': [{'id': 'attacker:physically proximate attacker', 'keyphrase': 'physically proximate attacker', 'type': 'attacker'}]}, 'similarity': np.float64(64.22319545640896)}, {'metadata': {'doc_id': '939', 'name': 'Improper Authorization in Handler for Custom URL Scheme', 'source': 'sparse', 'original_content': 'The product uses a handler for a custom URL scheme, but it does not properly restrict which actors can invoke the handler using the scheme.', 'keyphrase_sources': [{'id': 'product:HomeServe Home Repair android app', 'keyphrase': 'HomeServe Home Repair android app', 'type': 'product'}]}, 'similarity': np.float64(60.95287318795385)}, {'metadata': {'doc_id': '295', 'name': 'Improper Certificate Validation', 'source': 'sparse', 'original_content': 'The product does not validate, or incorrectly validates, a certificate.', 'keyphrase_sources': [{'id': 'product:HomeServe Home Repair android app', 'keyphrase': 'HomeServe Home Repair android app', 'type': 'product'}]}, 'similarity': np.float64(59.2839553278135)}, {'metadata': {'doc_id': '532', 'name': 'Insertion of Sensitive Information into Log File', 'source': 'sparse', 'original_content': 'The product writes sensitive information to a log file.', 'keyphrase_sources': [{'id': 'product:HomeServe Home Repair android app', 'keyphrase': 'HomeServe Home Repair android app', 'type': 'product'}]}, 'similarity': np.float64(58.494835951590126)}, {'metadata': {'doc_id': '250', 'name': 'Execution with Unnecessary Privileges', 'source': 'sparse', 'original_content': 'The product performs an operation at a privilege level that is higher than the minimum level required, which creates new weaknesses or amplifies the consequences of other weaknesses.', 'keyphrase_sources': [{'id': 'impact:escalate privileges', 'keyphrase': 'escalate privileges', 'type': 'impact'}]}, 'similarity': np.float64(58.42756265923809)}, {'metadata': {'doc_id': '269', 'name': 'Improper Privilege Management', 'source': 'sparse', 'original_content': 'The product does not properly assign, modify, track, or check privileges for an actor, creating an unintended sphere of control for that actor.', 'keyphrase_sources': [{'id': 'impact:escalate privileges', 'keyphrase': 'escalate privileges', 'type': 'impact'}]}, 'similarity': np.float64(54.280673794877615)}, {'metadata': {'doc_id': '287', 'name': 'Improper Authentication', 'source': 'sparse', 'original_content': 'When an actor claims to have a given identity, the product does not prove or insufficiently proves that the claim is correct.', 'keyphrase_sources': [{'id': 'vector:fingerprint authentication function', 'keyphrase': 'fingerprint authentication function', 'type': 'vector'}, {'id': 'version:3.3.4', 'keyphrase': '3.3.4', 'type': 'version'}]}, 'similarity': np.float64(53.24985137551129)}, {'metadata': {'doc_id': '345', 'name': 'Insufficient Verification of Data Authenticity', 'source': 'sparse', 'original_content': 'The product does not sufficiently verify the origin or authenticity of data, in a way that causes it to accept invalid data.', 'keyphrase_sources': [{'id': 'vector:fingerprint authentication function', 'keyphrase': 'fingerprint authentication function', 'type': 'vector'}]}, 'similarity': np.float64(53.13517067534659)}], identified_cwes={'analyzer': [], 'critic_additional': []})",
  "retrieval_results": {
    "has_multiple_keyphrases": true,
    "keyphrase_cwe_sets": {
      "rootcause:access control issue": {
        "keyphrase": "access control issue",
        "type": "rootcause",
        "cwes": [
          {
            "metadata": {
              "doc_id": "284",
              "name": "Improper Access Control",
              "source": "sparse",
              "original_content": "The product does not restrict or incorrectly restricts access to a resource from an unauthorized actor.",
              "keyphrase_sources": [
                {
                  "id": "rootcause:access control issue",
                  "keyphrase": "access control issue",
                  "type": "rootcause"
                },
                {
                  "id": "rootcause:incorrect access control",
                  "keyphrase": "incorrect access control",
                  "type": "rootcause"
                },
                {
                  "id": "impact:escalate privileges",
                  "keyphrase": "escalate privileges",
                  "type": "impact"
                },
                {
                  "id": "vector:fingerprint authentication function",
                  "keyphrase": "fingerprint authentication function",
                  "type": "vector"
                },
                {
                  "id": "version:3.3.4",
                  "keyphrase": "3.3.4",
                  "type": "version"
                }
              ]
            },
            "similarity": 175.07524981561176
          },
          {
            "metadata": {
              "doc_id": "732",
              "name": "Incorrect Permission Assignment for Critical Resource",
              "source": "sparse",
              "original_content": "The product specifies permissions for a security-critical resource in a way that allows that resource to be read or modified by unintended actors.",
              "keyphrase_sources": [
                {
                  "id": "rootcause:access control issue",
                  "keyphrase": "access control issue",
                  "type": "rootcause"
                },
                {
                  "id": "rootcause:incorrect access control",
                  "keyphrase": "incorrect access control",
                  "type": "rootcause"
                },
                {
                  "id": "impact:escalate privileges",
                  "keyphrase": "escalate privileges",
                  "type": "impact"
                },
                {
                  "id": "product:HomeServe Home Repair android app",
                  "keyphrase": "HomeServe Home Repair android app",
                  "type": "product"
                },
                {
                  "id": "version:3.3.4",
                  "keyphrase": "3.3.4",
                  "type": "version"
                }
              ]
            },
            "similarity": 172.98388646089
          },
          {
            "metadata": {
              "doc_id": "1263",
              "name": "Improper Physical Access Control",
              "source": "sparse",
              "original_content": "The product is designed with access restricted to certain information, but it does not sufficiently protect against an unauthorized actor with physical access to these areas.",
              "keyphrase_sources": [
                {
                  "id": "rootcause:access control issue",
                  "keyphrase": "access control issue",
                  "type": "rootcause"
                },
                {
                  "id": "rootcause:incorrect access control",
                  "keyphrase": "incorrect access control",
                  "type": "rootcause"
                },
                {
                  "id": "attacker:physically proximate attacker",
                  "keyphrase": "physically proximate attacker",
                  "type": "attacker"
                }
              ]
            },
            "similarity": 169.59317251953746
          },
          {
            "metadata": {
              "doc_id": "863",
              "name": "Incorrect Authorization",
              "source": "sparse",
              "original_content": "The product performs an authorization check when an actor attempts to access a resource or perform an action, but it does not correctly perform the check.",
              "keyphrase_sources": [
                {
                  "id": "rootcause:access control issue",
                  "keyphrase": "access control issue",
                  "type": "rootcause"
                },
                {
                  "id": "rootcause:incorrect access control",
                  "keyphrase": "incorrect access control",
                  "type": "rootcause"
                },
                {
                  "id": "vector:fingerprint authentication function",
                  "keyphrase": "fingerprint authentication function",
                  "type": "vector"
                },
                {
                  "id": "version:3.3.4",
                  "keyphrase": "3.3.4",
                  "type": "version"
                }
              ]
            },
            "similarity": 167.59009620566172
          },
          {
            "metadata": {
              "doc_id": "290",
              "name": "Authentication Bypass by Spoofing",
              "source": "sparse",
              "original_content": "This attack-focused weakness is caused by incorrectly implemented authentication schemes that are subject to spoofing attacks.",
              "keyphrase_sources": [
                {
                  "id": "rootcause:access control issue",
                  "keyphrase": "access control issue",
                  "type": "rootcause"
                },
                {
                  "id": "vector:fingerprint authentication function",
                  "keyphrase": "fingerprint authentication function",
                  "type": "vector"
                },
                {
                  "id": "product:HomeServe Home Repair android app",
                  "keyphrase": "HomeServe Home Repair android app",
                  "type": "product"
                },
                {
                  "id": "version:3.3.4",
                  "keyphrase": "3.3.4",
                  "type": "version"
                }
              ]
            },
            "similarity": 166.39702747315332
          }
        ]
      },
      "rootcause:incorrect access control": {
        "keyphrase": "incorrect access control",
        "type": "rootcause",
        "cwes": [
          {
            "metadata": {
              "doc_id": "732",
              "name": "Incorrect Permission Assignment for Critical Resource",
              "source": "sparse",
              "original_content": "The product specifies permissions for a security-critical resource in a way that allows that resource to be read or modified by unintended actors."
            },
            "similarity": 183.1617715547165
          },
          {
            "metadata": {
              "doc_id": "284",
              "name": "Improper Access Control",
              "source": "sparse",
              "original_content": "The product does not restrict or incorrectly restricts access to a resource from an unauthorized actor."
            },
            "similarity": 182.25126784657098
          },
          {
            "metadata": {
              "doc_id": "863",
              "name": "Incorrect Authorization",
              "source": "sparse",
              "original_content": "The product performs an authorization check when an actor attempts to access a resource or perform an action, but it does not correctly perform the check."
            },
            "similarity": 175.74716888499842
          },
          {
            "metadata": {
              "doc_id": "1263",
              "name": "Improper Physical Access Control",
              "source": "sparse",
              "original_content": "The product is designed with access restricted to certain information, but it does not sufficiently protect against an unauthorized actor with physical access to these areas."
            },
            "similarity": 174.8547555652797
          },
          {
            "metadata": {
              "doc_id": "266",
              "name": "Incorrect Privilege Assignment",
              "source": "sparse",
              "original_content": "A product incorrectly assigns a privilege to a particular actor, creating an unintended sphere of control for that actor.",
              "keyphrase_sources": [
                {
                  "id": "rootcause:incorrect access control",
                  "keyphrase": "incorrect access control",
                  "type": "rootcause"
                },
                {
                  "id": "impact:escalate privileges",
                  "keyphrase": "escalate privileges",
                  "type": "impact"
                }
              ]
            },
            "similarity": 170.61060397503084
          }
        ]
      },
      "impact:escalate privileges": {
        "keyphrase": "escalate privileges",
        "type": "impact",
        "cwes": [
          {
            "metadata": {
              "doc_id": "732",
              "name": "Incorrect Permission Assignment for Critical Resource",
              "source": "sparse",
              "original_content": "The product specifies permissions for a security-critical resource in a way that allows that resource to be read or modified by unintended actors."
            },
            "similarity": 60.440321186408326
          },
          {
            "metadata": {
              "doc_id": "250",
              "name": "Execution with Unnecessary Privileges",
              "source": "sparse",
              "original_content": "The product performs an operation at a privilege level that is higher than the minimum level required, which creates new weaknesses or amplifies the consequences of other weaknesses.",
              "keyphrase_sources": [
                {
                  "id": "impact:escalate privileges",
                  "keyphrase": "escalate privileges",
                  "type": "impact"
                }
              ]
            },
            "similarity": 58.42756265923809
          },
          {
            "metadata": {
              "doc_id": "266",
              "name": "Incorrect Privilege Assignment",
              "source": "sparse",
              "original_content": "A product incorrectly assigns a privilege to a particular actor, creating an unintended sphere of control for that actor."
            },
            "similarity": 55.91744691569797
          },
          {
            "metadata": {
              "doc_id": "269",
              "name": "Improper Privilege Management",
              "source": "sparse",
              "original_content": "The product does not properly assign, modify, track, or check privileges for an actor, creating an unintended sphere of control for that actor.",
              "keyphrase_sources": [
                {
                  "id": "impact:escalate privileges",
                  "keyphrase": "escalate privileges",
                  "type": "impact"
                }
              ]
            },
            "similarity": 54.280673794877615
          },
          {
            "metadata": {
              "doc_id": "284",
              "name": "Improper Access Control",
              "source": "sparse",
              "original_content": "The product does not restrict or incorrectly restricts access to a resource from an unauthorized actor."
            },
            "similarity": 52.7764182633738
          }
        ]
      },
      "vector:fingerprint authentication function": {
        "keyphrase": "fingerprint authentication function",
        "type": "vector",
        "cwes": [
          {
            "metadata": {
              "doc_id": "287",
              "name": "Improper Authentication",
              "source": "sparse",
              "original_content": "When an actor claims to have a given identity, the product does not prove or insufficiently proves that the claim is correct.",
              "keyphrase_sources": [
                {
                  "id": "vector:fingerprint authentication function",
                  "keyphrase": "fingerprint authentication function",
                  "type": "vector"
                },
                {
                  "id": "version:3.3.4",
                  "keyphrase": "3.3.4",
                  "type": "version"
                }
              ]
            },
            "similarity": 53.24985137551129
          },
          {
            "metadata": {
              "doc_id": "345",
              "name": "Insufficient Verification of Data Authenticity",
              "source": "sparse",
              "original_content": "The product does not sufficiently verify the origin or authenticity of data, in a way that causes it to accept invalid data.",
              "keyphrase_sources": [
                {
                  "id": "vector:fingerprint authentication function",
                  "keyphrase": "fingerprint authentication function",
                  "type": "vector"
                }
              ]
            },
            "similarity": 53.13517067534659
          },
          {
            "metadata": {
              "doc_id": "284",
              "name": "Improper Access Control",
              "source": "sparse",
              "original_content": "The product does not restrict or incorrectly restricts access to a resource from an unauthorized actor."
            },
            "similarity": 50.82089931372357
          },
          {
            "metadata": {
              "doc_id": "863",
              "name": "Incorrect Authorization",
              "source": "sparse",
              "original_content": "The product performs an authorization check when an actor attempts to access a resource or perform an action, but it does not correctly perform the check."
            },
            "similarity": 50.62665374021545
          },
          {
            "metadata": {
              "doc_id": "290",
              "name": "Authentication Bypass by Spoofing",
              "source": "sparse",
              "original_content": "This attack-focused weakness is caused by incorrectly implemented authentication schemes that are subject to spoofing attacks."
            },
            "similarity": 50.60936636476426
          }
        ]
      },
      "attacker:physically proximate attacker": {
        "keyphrase": "physically proximate attacker",
        "type": "attacker",
        "cwes": [
          {
            "metadata": {
              "doc_id": "1263",
              "name": "Improper Physical Access Control",
              "source": "sparse",
              "original_content": "The product is designed with access restricted to certain information, but it does not sufficiently protect against an unauthorized actor with physical access to these areas."
            },
            "similarity": 73.8080013941699
          },
          {
            "metadata": {
              "doc_id": "311",
              "name": "Missing Encryption of Sensitive Data",
              "source": "sparse",
              "original_content": "The product does not encrypt sensitive or critical information before storage or transmission.",
              "keyphrase_sources": [
                {
                  "id": "attacker:physically proximate attacker",
                  "keyphrase": "physically proximate attacker",
                  "type": "attacker"
                }
              ]
            },
            "similarity": 70.98985077540881
          },
          {
            "metadata": {
              "doc_id": "1247",
              "name": "Improper Protection Against Voltage and Clock Glitches",
              "source": "sparse",
              "original_content": "The device does not contain or contains incorrectly implemented circuitry or sensors to detect and mitigate voltage and clock glitches and protect sensitive information or software contained on the device.",
              "keyphrase_sources": [
                {
                  "id": "attacker:physically proximate attacker",
                  "keyphrase": "physically proximate attacker",
                  "type": "attacker"
                }
              ]
            },
            "similarity": 68.68879918544867
          },
          {
            "metadata": {
              "doc_id": "549",
              "name": "Missing Password Field Masking",
              "source": "sparse",
              "original_content": "The product does not mask passwords during entry, increasing the potential for attackers to observe and capture passwords.",
              "keyphrase_sources": [
                {
                  "id": "attacker:physically proximate attacker",
                  "keyphrase": "physically proximate attacker",
                  "type": "attacker"
                }
              ]
            },
            "similarity": 67.9717550820775
          },
          {
            "metadata": {
              "doc_id": "707",
              "name": "Improper Neutralization",
              "source": "sparse",
              "original_content": "The product does not ensure or incorrectly ensures that structured messages or data are well-formed and that certain security properties are met before being read from an upstream component or sent to a downstream component.",
              "keyphrase_sources": [
                {
                  "id": "attacker:physically proximate attacker",
                  "keyphrase": "physically proximate attacker",
                  "type": "attacker"
                }
              ]
            },
            "similarity": 64.22319545640896
          }
        ]
      },
      "product:HomeServe Home Repair android app": {
        "keyphrase": "HomeServe Home Repair android app",
        "type": "product",
        "cwes": [
          {
            "metadata": {
              "doc_id": "290",
              "name": "Authentication Bypass by Spoofing",
              "source": "sparse",
              "original_content": "This attack-focused weakness is caused by incorrectly implemented authentication schemes that are subject to spoofing attacks."
            },
            "similarity": 62.71830299149533
          },
          {
            "metadata": {
              "doc_id": "939",
              "name": "Improper Authorization in Handler for Custom URL Scheme",
              "source": "sparse",
              "original_content": "The product uses a handler for a custom URL scheme, but it does not properly restrict which actors can invoke the handler using the scheme.",
              "keyphrase_sources": [
                {
                  "id": "product:HomeServe Home Repair android app",
                  "keyphrase": "HomeServe Home Repair android app",
                  "type": "product"
                }
              ]
            },
            "similarity": 60.95287318795385
          },
          {
            "metadata": {
              "doc_id": "732",
              "name": "Incorrect Permission Assignment for Critical Resource",
              "source": "sparse",
              "original_content": "The product specifies permissions for a security-critical resource in a way that allows that resource to be read or modified by unintended actors."
            },
            "similarity": 60.68499730879557
          },
          {
            "metadata": {
              "doc_id": "295",
              "name": "Improper Certificate Validation",
              "source": "sparse",
              "original_content": "The product does not validate, or incorrectly validates, a certificate.",
              "keyphrase_sources": [
                {
                  "id": "product:HomeServe Home Repair android app",
                  "keyphrase": "HomeServe Home Repair android app",
                  "type": "product"
                }
              ]
            },
            "similarity": 59.2839553278135
          },
          {
            "metadata": {
              "doc_id": "532",
              "name": "Insertion of Sensitive Information into Log File",
              "source": "sparse",
              "original_content": "The product writes sensitive information to a log file.",
              "keyphrase_sources": [
                {
                  "id": "product:HomeServe Home Repair android app",
                  "keyphrase": "HomeServe Home Repair android app",
                  "type": "product"
                }
              ]
            },
            "similarity": 58.494835951590126
          }
        ]
      },
      "version:3.3.4": {
        "keyphrase": "3.3.4",
        "type": "version",
        "cwes": [
          {
            "metadata": {
              "doc_id": "732",
              "name": "Incorrect Permission Assignment for Critical Resource",
              "source": "sparse",
              "original_content": "The product specifies permissions for a security-critical resource in a way that allows that resource to be read or modified by unintended actors."
            },
            "similarity": 55.532933696496144
          },
          {
            "metadata": {
              "doc_id": "284",
              "name": "Improper Access Control",
              "source": "sparse",
              "original_content": "The product does not restrict or incorrectly restricts access to a resource from an unauthorized actor."
            },
            "similarity": 54.92359029390511
          },
          {
            "metadata": {
              "doc_id": "863",
              "name": "Incorrect Authorization",
              "source": "sparse",
              "original_content": "The product performs an authorization check when an actor attempts to access a resource or perform an action, but it does not correctly perform the check."
            },
            "similarity": 53.87823067827305
          },
          {
            "metadata": {
              "doc_id": "290",
              "name": "Authentication Bypass by Spoofing",
              "source": "sparse",
              "original_content": "This attack-focused weakness is caused by incorrectly implemented authentication schemes that are subject to spoofing attacks."
            },
            "similarity": 52.784785059871176
          },
          {
            "metadata": {
              "doc_id": "287",
              "name": "Improper Authentication",
              "source": "sparse",
              "original_content": "When an actor claims to have a given identity, the product does not prove or insufficiently proves that the claim is correct."
            },
            "similarity": 52.495748541737235
          }
        ]
      }
    },
    "keyphrase_mapping": {
      "284": [
        {
          "id": "rootcause:access control issue",
          "keyphrase": "access control issue",
          "type": "rootcause"
        },
        {
          "id": "rootcause:incorrect access control",
          "keyphrase": "incorrect access control",
          "type": "rootcause"
        },
        {
          "id": "impact:escalate privileges",
          "keyphrase": "escalate privileges",
          "type": "impact"
        },
        {
          "id": "vector:fingerprint authentication function",
          "keyphrase": "fingerprint authentication function",
          "type": "vector"
        },
        {
          "id": "version:3.3.4",
          "keyphrase": "3.3.4",
          "type": "version"
        }
      ],
      "732": [
        {
          "id": "rootcause:access control issue",
          "keyphrase": "access control issue",
          "type": "rootcause"
        },
        {
          "id": "rootcause:incorrect access control",
          "keyphrase": "incorrect access control",
          "type": "rootcause"
        },
        {
          "id": "impact:escalate privileges",
          "keyphrase": "escalate privileges",
          "type": "impact"
        },
        {
          "id": "product:HomeServe Home Repair android app",
          "keyphrase": "HomeServe Home Repair android app",
          "type": "product"
        },
        {
          "id": "version:3.3.4",
          "keyphrase": "3.3.4",
          "type": "version"
        }
      ],
      "1263": [
        {
          "id": "rootcause:access control issue",
          "keyphrase": "access control issue",
          "type": "rootcause"
        },
        {
          "id": "rootcause:incorrect access control",
          "keyphrase": "incorrect access control",
          "type": "rootcause"
        },
        {
          "id": "attacker:physically proximate attacker",
          "keyphrase": "physically proximate attacker",
          "type": "attacker"
        }
      ],
      "863": [
        {
          "id": "rootcause:access control issue",
          "keyphrase": "access control issue",
          "type": "rootcause"
        },
        {
          "id": "rootcause:incorrect access control",
          "keyphrase": "incorrect access control",
          "type": "rootcause"
        },
        {
          "id": "vector:fingerprint authentication function",
          "keyphrase": "fingerprint authentication function",
          "type": "vector"
        },
        {
          "id": "version:3.3.4",
          "keyphrase": "3.3.4",
          "type": "version"
        }
      ],
      "290": [
        {
          "id": "rootcause:access control issue",
          "keyphrase": "access control issue",
          "type": "rootcause"
        },
        {
          "id": "vector:fingerprint authentication function",
          "keyphrase": "fingerprint authentication function",
          "type": "vector"
        },
        {
          "id": "product:HomeServe Home Repair android app",
          "keyphrase": "HomeServe Home Repair android app",
          "type": "product"
        },
        {
          "id": "version:3.3.4",
          "keyphrase": "3.3.4",
          "type": "version"
        }
      ],
      "266": [
        {
          "id": "rootcause:incorrect access control",
          "keyphrase": "incorrect access control",
          "type": "rootcause"
        },
        {
          "id": "impact:escalate privileges",
          "keyphrase": "escalate privileges",
          "type": "impact"
        }
      ],
      "250": [
        {
          "id": "impact:escalate privileges",
          "keyphrase": "escalate privileges",
          "type": "impact"
        }
      ],
      "269": [
        {
          "id": "impact:escalate privileges",
          "keyphrase": "escalate privileges",
          "type": "impact"
        }
      ],
      "287": [
        {
          "id": "vector:fingerprint authentication function",
          "keyphrase": "fingerprint authentication function",
          "type": "vector"
        },
        {
          "id": "version:3.3.4",
          "keyphrase": "3.3.4",
          "type": "version"
        }
      ],
      "345": [
        {
          "id": "vector:fingerprint authentication function",
          "keyphrase": "fingerprint authentication function",
          "type": "vector"
        }
      ],
      "311": [
        {
          "id": "attacker:physically proximate attacker",
          "keyphrase": "physically proximate attacker",
          "type": "attacker"
        }
      ],
      "1247": [
        {
          "id": "attacker:physically proximate attacker",
          "keyphrase": "physically proximate attacker",
          "type": "attacker"
        }
      ],
      "549": [
        {
          "id": "attacker:physically proximate attacker",
          "keyphrase": "physically proximate attacker",
          "type": "attacker"
        }
      ],
      "707": [
        {
          "id": "attacker:physically proximate attacker",
          "keyphrase": "physically proximate attacker",
          "type": "attacker"
        }
      ],
      "939": [
        {
          "id": "product:HomeServe Home Repair android app",
          "keyphrase": "HomeServe Home Repair android app",
          "type": "product"
        }
      ],
      "295": [
        {
          "id": "product:HomeServe Home Repair android app",
          "keyphrase": "HomeServe Home Repair android app",
          "type": "product"
        }
      ],
      "532": [
        {
          "id": "product:HomeServe Home Repair android app",
          "keyphrase": "HomeServe Home Repair android app",
          "type": "product"
        }
      ]
    },
    "relevant_cwes": [
      {
        "metadata": {
          "doc_id": "284",
          "name": "Improper Access Control",
          "source": "sparse",
          "original_content": "The product does not restrict or incorrectly restricts access to a resource from an unauthorized actor.",
          "keyphrase_sources": [
            {
              "id": "rootcause:access control issue",
              "keyphrase": "access control issue",
              "type": "rootcause"
            },
            {
              "id": "rootcause:incorrect access control",
              "keyphrase": "incorrect access control",
              "type": "rootcause"
            },
            {
              "id": "impact:escalate privileges",
              "keyphrase": "escalate privileges",
              "type": "impact"
            },
            {
              "id": "vector:fingerprint authentication function",
              "keyphrase": "fingerprint authentication function",
              "type": "vector"
            },
            {
              "id": "version:3.3.4",
              "keyphrase": "3.3.4",
              "type": "version"
            }
          ]
        },
        "similarity": 175.07524981561176
      },
      {
        "metadata": {
          "doc_id": "732",
          "name": "Incorrect Permission Assignment for Critical Resource",
          "source": "sparse",
          "original_content": "The product specifies permissions for a security-critical resource in a way that allows that resource to be read or modified by unintended actors.",
          "keyphrase_sources": [
            {
              "id": "rootcause:access control issue",
              "keyphrase": "access control issue",
              "type": "rootcause"
            },
            {
              "id": "rootcause:incorrect access control",
              "keyphrase": "incorrect access control",
              "type": "rootcause"
            },
            {
              "id": "impact:escalate privileges",
              "keyphrase": "escalate privileges",
              "type": "impact"
            },
            {
              "id": "product:HomeServe Home Repair android app",
              "keyphrase": "HomeServe Home Repair android app",
              "type": "product"
            },
            {
              "id": "version:3.3.4",
              "keyphrase": "3.3.4",
              "type": "version"
            }
          ]
        },
        "similarity": 172.98388646089
      },
      {
        "metadata": {
          "doc_id": "266",
          "name": "Incorrect Privilege Assignment",
          "source": "sparse",
          "original_content": "A product incorrectly assigns a privilege to a particular actor, creating an unintended sphere of control for that actor.",
          "keyphrase_sources": [
            {
              "id": "rootcause:incorrect access control",
              "keyphrase": "incorrect access control",
              "type": "rootcause"
            },
            {
              "id": "impact:escalate privileges",
              "keyphrase": "escalate privileges",
              "type": "impact"
            }
          ]
        },
        "similarity": 170.61060397503084
      },
      {
        "metadata": {
          "doc_id": "1263",
          "name": "Improper Physical Access Control",
          "source": "sparse",
          "original_content": "The product is designed with access restricted to certain information, but it does not sufficiently protect against an unauthorized actor with physical access to these areas.",
          "keyphrase_sources": [
            {
              "id": "rootcause:access control issue",
              "keyphrase": "access control issue",
              "type": "rootcause"
            },
            {
              "id": "rootcause:incorrect access control",
              "keyphrase": "incorrect access control",
              "type": "rootcause"
            },
            {
              "id": "attacker:physically proximate attacker",
              "keyphrase": "physically proximate attacker",
              "type": "attacker"
            }
          ]
        },
        "similarity": 169.59317251953746
      },
      {
        "metadata": {
          "doc_id": "863",
          "name": "Incorrect Authorization",
          "source": "sparse",
          "original_content": "The product performs an authorization check when an actor attempts to access a resource or perform an action, but it does not correctly perform the check.",
          "keyphrase_sources": [
            {
              "id": "rootcause:access control issue",
              "keyphrase": "access control issue",
              "type": "rootcause"
            },
            {
              "id": "rootcause:incorrect access control",
              "keyphrase": "incorrect access control",
              "type": "rootcause"
            },
            {
              "id": "vector:fingerprint authentication function",
              "keyphrase": "fingerprint authentication function",
              "type": "vector"
            },
            {
              "id": "version:3.3.4",
              "keyphrase": "3.3.4",
              "type": "version"
            }
          ]
        },
        "similarity": 167.59009620566172
      },
      {
        "metadata": {
          "doc_id": "290",
          "name": "Authentication Bypass by Spoofing",
          "source": "sparse",
          "original_content": "This attack-focused weakness is caused by incorrectly implemented authentication schemes that are subject to spoofing attacks.",
          "keyphrase_sources": [
            {
              "id": "rootcause:access control issue",
              "keyphrase": "access control issue",
              "type": "rootcause"
            },
            {
              "id": "vector:fingerprint authentication function",
              "keyphrase": "fingerprint authentication function",
              "type": "vector"
            },
            {
              "id": "product:HomeServe Home Repair android app",
              "keyphrase": "HomeServe Home Repair android app",
              "type": "product"
            },
            {
              "id": "version:3.3.4",
              "keyphrase": "3.3.4",
              "type": "version"
            }
          ]
        },
        "similarity": 166.39702747315332
      },
      {
        "metadata": {
          "doc_id": "311",
          "name": "Missing Encryption of Sensitive Data",
          "source": "sparse",
          "original_content": "The product does not encrypt sensitive or critical information before storage or transmission.",
          "keyphrase_sources": [
            {
              "id": "attacker:physically proximate attacker",
              "keyphrase": "physically proximate attacker",
              "type": "attacker"
            }
          ]
        },
        "similarity": 70.98985077540881
      },
      {
        "metadata": {
          "doc_id": "1247",
          "name": "Improper Protection Against Voltage and Clock Glitches",
          "source": "sparse",
          "original_content": "The device does not contain or contains incorrectly implemented circuitry or sensors to detect and mitigate voltage and clock glitches and protect sensitive information or software contained on the device.",
          "keyphrase_sources": [
            {
              "id": "attacker:physically proximate attacker",
              "keyphrase": "physically proximate attacker",
              "type": "attacker"
            }
          ]
        },
        "similarity": 68.68879918544867
      },
      {
        "metadata": {
          "doc_id": "549",
          "name": "Missing Password Field Masking",
          "source": "sparse",
          "original_content": "The product does not mask passwords during entry, increasing the potential for attackers to observe and capture passwords.",
          "keyphrase_sources": [
            {
              "id": "attacker:physically proximate attacker",
              "keyphrase": "physically proximate attacker",
              "type": "attacker"
            }
          ]
        },
        "similarity": 67.9717550820775
      },
      {
        "metadata": {
          "doc_id": "707",
          "name": "Improper Neutralization",
          "source": "sparse",
          "original_content": "The product does not ensure or incorrectly ensures that structured messages or data are well-formed and that certain security properties are met before being read from an upstream component or sent to a downstream component.",
          "keyphrase_sources": [
            {
              "id": "attacker:physically proximate attacker",
              "keyphrase": "physically proximate attacker",
              "type": "attacker"
            }
          ]
        },
        "similarity": 64.22319545640896
      },
      {
        "metadata": {
          "doc_id": "939",
          "name": "Improper Authorization in Handler for Custom URL Scheme",
          "source": "sparse",
          "original_content": "The product uses a handler for a custom URL scheme, but it does not properly restrict which actors can invoke the handler using the scheme.",
          "keyphrase_sources": [
            {
              "id": "product:HomeServe Home Repair android app",
              "keyphrase": "HomeServe Home Repair android app",
              "type": "product"
            }
          ]
        },
        "similarity": 60.95287318795385
      },
      {
        "metadata": {
          "doc_id": "295",
          "name": "Improper Certificate Validation",
          "source": "sparse",
          "original_content": "The product does not validate, or incorrectly validates, a certificate.",
          "keyphrase_sources": [
            {
              "id": "product:HomeServe Home Repair android app",
              "keyphrase": "HomeServe Home Repair android app",
              "type": "product"
            }
          ]
        },
        "similarity": 59.2839553278135
      },
      {
        "metadata": {
          "doc_id": "532",
          "name": "Insertion of Sensitive Information into Log File",
          "source": "sparse",
          "original_content": "The product writes sensitive information to a log file.",
          "keyphrase_sources": [
            {
              "id": "product:HomeServe Home Repair android app",
              "keyphrase": "HomeServe Home Repair android app",
              "type": "product"
            }
          ]
        },
        "similarity": 58.494835951590126
      },
      {
        "metadata": {
          "doc_id": "250",
          "name": "Execution with Unnecessary Privileges",
          "source": "sparse",
          "original_content": "The product performs an operation at a privilege level that is higher than the minimum level required, which creates new weaknesses or amplifies the consequences of other weaknesses.",
          "keyphrase_sources": [
            {
              "id": "impact:escalate privileges",
              "keyphrase": "escalate privileges",
              "type": "impact"
            }
          ]
        },
        "similarity": 58.42756265923809
      },
      {
        "metadata": {
          "doc_id": "269",
          "name": "Improper Privilege Management",
          "source": "sparse",
          "original_content": "The product does not properly assign, modify, track, or check privileges for an actor, creating an unintended sphere of control for that actor.",
          "keyphrase_sources": [
            {
              "id": "impact:escalate privileges",
              "keyphrase": "escalate privileges",
              "type": "impact"
            }
          ]
        },
        "similarity": 54.280673794877615
      },
      {
        "metadata": {
          "doc_id": "287",
          "name": "Improper Authentication",
          "source": "sparse",
          "original_content": "When an actor claims to have a given identity, the product does not prove or insufficiently proves that the claim is correct.",
          "keyphrase_sources": [
            {
              "id": "vector:fingerprint authentication function",
              "keyphrase": "fingerprint authentication function",
              "type": "vector"
            },
            {
              "id": "version:3.3.4",
              "keyphrase": "3.3.4",
              "type": "version"
            }
          ]
        },
        "similarity": 53.24985137551129
      },
      {
        "metadata": {
          "doc_id": "345",
          "name": "Insufficient Verification of Data Authenticity",
          "source": "sparse",
          "original_content": "The product does not sufficiently verify the origin or authenticity of data, in a way that causes it to accept invalid data.",
          "keyphrase_sources": [
            {
              "id": "vector:fingerprint authentication function",
              "keyphrase": "fingerprint authentication function",
              "type": "vector"
            }
          ]
        },
        "similarity": 53.13517067534659
      }
    ],
    "enhanced_query": "# Vulnerability Description\n\n    An incorrect **access control issue** in HomeServe Home Repair android app - 3.3.4 allows a physically proximate attacker to escalate privileges via the fingerprint authentication function.\n\n    # Keyphrase-Specific CWE Analysis\n    This vulnerability contains multiple keyphrases that may map to different CWEs. \n    Please analyze each keyphrase separately and determine the most appropriate CWE(s) for each.\n\n    ## ROOTCAUSE: 'access control issue'\n\nRelevant CWEs for this ROOTCAUSE:\n\n### 1. CWE-284: Improper Access Control (Score: 175.08)\n\nThe product does not restrict or incorrectly restricts access to a resource from an unauthorized actor....\n\n### 2. CWE-732: Incorrect Permission Assignment for Critical Resource (Score: 172.98)\n\nThe product specifies permissions for a security-critical resource in a way that allows that resource to be read or modified by unintended actors....\n\n### 3. CWE-1263: Improper Physical Access Control (Score: 169.59)\n\nThe product is designed with access restricted to certain information, but it does not sufficiently protect against an unauthorized actor with physical access to these areas....\n\n### 4. CWE-863: Incorrect Authorization (Score: 167.59)\n\nThe product performs an authorization check when an actor attempts to access a resource or perform an action, but it does not correctly perform the check....\n\n### 5. CWE-290: Authentication Bypass by Spoofing (Score: 166.40)\n\nThis attack-focused weakness is caused by incorrectly implemented authentication schemes that are subject to spoofing attacks....\n\n## ROOTCAUSE: 'incorrect access control'\n\nRelevant CWEs for this ROOTCAUSE:\n\n### 1. CWE-284: Improper Access Control (Score: 175.08)\n\nThe product does not restrict or incorrectly restricts access to a resource from an unauthorized actor....\n\n### 2. CWE-732: Incorrect Permission Assignment for Critical Resource (Score: 172.98)\n\nThe product specifies permissions for a security-critical resource in a way that allows that resource to be read or modified by unintended actors....\n\n### 3. CWE-266: Incorrect Privilege Assignment (Score: 170.61)\n\nA product incorrectly assigns a privilege to a particular actor, creating an unintended sphere of control for that actor....\n\n### 4. CWE-1263: Improper Physical Access Control (Score: 169.59)\n\nThe product is designed with access restricted to certain information, but it does not sufficiently protect against an unauthorized actor with physical access to these areas....\n\n### 5. CWE-863: Incorrect Authorization (Score: 167.59)\n\nThe product performs an authorization check when an actor attempts to access a resource or perform an action, but it does not correctly perform the check....\n\n## IMPACT: 'escalate privileges'\n\nRelevant CWEs for this IMPACT:\n\n### 1. CWE-284: Improper Access Control (Score: 175.08)\n\nThe product does not restrict or incorrectly restricts access to a resource from an unauthorized actor....\n\n### 2. CWE-732: Incorrect Permission Assignment for Critical Resource (Score: 172.98)\n\nThe product specifies permissions for a security-critical resource in a way that allows that resource to be read or modified by unintended actors....\n\n### 3. CWE-266: Incorrect Privilege Assignment (Score: 170.61)\n\nA product incorrectly assigns a privilege to a particular actor, creating an unintended sphere of control for that actor....\n\n### 4. CWE-250: Execution with Unnecessary Privileges (Score: 58.43)\n\nThe product performs an operation at a privilege level that is higher than the minimum level required, which creates new weaknesses or amplifies the consequences of other weaknesses....\n\n### 5. CWE-269: Improper Privilege Management (Score: 54.28)\n\nThe product does not properly assign, modify, track, or check privileges for an actor, creating an unintended sphere of control for that actor....\n\n## VECTOR: 'fingerprint authentication function'\n\nRelevant CWEs for this VECTOR:\n\n### 1. CWE-284: Improper Access Control (Score: 175.08)\n\nThe product does not restrict or incorrectly restricts access to a resource from an unauthorized actor....\n\n### 2. CWE-863: Incorrect Authorization (Score: 167.59)\n\nThe product performs an authorization check when an actor attempts to access a resource or perform an action, but it does not correctly perform the check....\n\n### 3. CWE-290: Authentication Bypass by Spoofing (Score: 166.40)\n\nThis attack-focused weakness is caused by incorrectly implemented authentication schemes that are subject to spoofing attacks....\n\n### 4. CWE-287: Improper Authentication (Score: 53.25)\n\nWhen an actor claims to have a given identity, the product does not prove or insufficiently proves that the claim is correct....\n\n### 5. CWE-345: Insufficient Verification of Data Authenticity (Score: 53.14)\n\nThe product does not sufficiently verify the origin or authenticity of data, in a way that causes it to accept invalid data....\n\n## VERSION: '3.3.4'\n\nRelevant CWEs for this VERSION:\n\n### 1. CWE-284: Improper Access Control (Score: 175.08)\n\nThe product does not restrict or incorrectly restricts access to a resource from an unauthorized actor....\n\n### 2. CWE-732: Incorrect Permission Assignment for Critical Resource (Score: 172.98)\n\nThe product specifies permissions for a security-critical resource in a way that allows that resource to be read or modified by unintended actors....\n\n### 3. CWE-863: Incorrect Authorization (Score: 167.59)\n\nThe product performs an authorization check when an actor attempts to access a resource or perform an action, but it does not correctly perform the check....\n\n### 4. CWE-290: Authentication Bypass by Spoofing (Score: 166.40)\n\nThis attack-focused weakness is caused by incorrectly implemented authentication schemes that are subject to spoofing attacks....\n\n### 5. CWE-287: Improper Authentication (Score: 53.25)\n\nWhen an actor claims to have a given identity, the product does not prove or insufficiently proves that the claim is correct....\n\n## PRODUCT: 'HomeServe Home Repair android app'\n\nRelevant CWEs for this PRODUCT:\n\n### 1. CWE-732: Incorrect Permission Assignment for Critical Resource (Score: 172.98)\n\nThe product specifies permissions for a security-critical resource in a way that allows that resource to be read or modified by unintended actors....\n\n### 2. CWE-290: Authentication Bypass by Spoofing (Score: 166.40)\n\nThis attack-focused weakness is caused by incorrectly implemented authentication schemes that are subject to spoofing attacks....\n\n### 3. CWE-939: Improper Authorization in Handler for Custom URL Scheme (Score: 60.95)\n\nThe product uses a handler for a custom URL scheme, but it does not properly restrict which actors can invoke the handler using the scheme....\n\n### 4. CWE-295: Improper Certificate Validation (Score: 59.28)\n\nThe product does not validate, or incorrectly validates, a certificate....\n\n### 5. CWE-532: Insertion of Sensitive Information into Log File (Score: 58.49)\n\nThe product writes sensitive information to a log file....\n\n## ATTACKER: 'physically proximate attacker'\n\nRelevant CWEs for this ATTACKER:\n\n### 1. CWE-1263: Improper Physical Access Control (Score: 169.59)\n\nThe product is designed with access restricted to certain information, but it does not sufficiently protect against an unauthorized actor with physical access to these areas....\n\n### 2. CWE-311: Missing Encryption of Sensitive Data (Score: 70.99)\n\nThe product does not encrypt sensitive or critical information before storage or transmission....\n\n### 3. CWE-1247: Improper Protection Against Voltage and Clock Glitches (Score: 68.69)\n\nThe device does not contain or contains incorrectly implemented circuitry or sensors to detect and mitigate voltage and clock glitches and protect sensitive information or software contained on the device....\n\n### 4. CWE-549: Missing Password Field Masking (Score: 67.97)\n\nThe product does not mask passwords during entry, increasing the potential for attackers to observe and capture passwords....\n\n### 5. CWE-707: Improper Neutralization (Score: 64.22)\n\nThe product does not ensure or incorrectly ensures that structured messages or data are well-formed and that certain security properties are met before being read from an upstream component or sent to a downstream component....\n\n\n    # Analysis Instructions\n    1. For each keyphrase, identify the most appropriate CWE(s) that represent the weakness.\n    2. Consider how the different keyphrases might relate to each other in the vulnerability chain.\n    3. Provide a final determination of primary CWE(s) and any secondary CWEs.\n    4. Format your response using the standard analysis template.\n\n    Please analyze how these different weaknesses interact and provide a comprehensive CWE classification.\n    "
  },
  "retrieval_time": 1.0967469215393066
}