{
  "vulnerability_info": "VulnerabilityInfo(cve_id='CVE-2025-23656', description='**Missing Authorization vulnerability** in Saul Morales Pacheco Donate visa allows Stored **XSS**. This issue affects Donate visa from n/a through 1.0.0.', key_phrases={'rootcause': 'Missing Authorization vulnerability', 'weakness': ['cross-site scripting', 'XSS'], 'impact': '', 'vector': '', 'attacker': '', 'product': 'Saul Morales Pacheco Donate visa', 'version': 'n/a through 1.0.0', 'component': ''}, reference_content='- **Root cause of vulnerability:** Missing authorization, authentication or nonce token check in a function, leading to an unprivileged user executing a higher privileged action.\\n- **Weaknesses/vulnerabilities present:** Broken Access Control (A1:2021 OWASP Top 10)\\n- **Impact of exploitation:** Not specified beyond allowing an unprivileged user to execute a higher privileged action.\\n- **Attack vectors:** Not specified.\\n- **Required attacker capabilities/position:** Subscriber privilege is sufficient.\\n- **Mitigation or fix:** Patchstack has issued a virtual patch to mitigate the issue. No official fix is currently available.\\n- **Vulnerable versions:** <= 1.0.0\\n- **CVSS score:** 6.5 (Medium)\\n\\nThe content provides more detail than the placeholder CVE description by specifying the vulnerability type (Broken Access Control), the affected plugin (Donate visa), and the mitigation strategy (virtual patching by Patchstack). It also details the required privilege level for exploitation (Subscriber).', similar_info={'cwe_distribution': {}, 'cwe_consensus': '', 'similarity_stats': {'thresholds': [], 'total_samples_by_threshold': {}, 'top_cwes_by_threshold': {}}}, similarity_summary=SimilarityInsight(consensus_cwe='', top_cwes=[], confidence_levels={}, total_samples=0), analysis='', analysis_with_relationships='', criticism='', resolution='', relevant_cwes=[{'metadata': {'doc_id': '79', 'name': \"Improper Neutralization of Input During Web Page Generation ('Cross-site Scripting')\", 'source': 'sparse', 'original_content': 'The product does not neutralize or incorrectly neutralizes user-controllable input before it is placed in output that is used as a web page that is served to other users.', 'keyphrase_sources': [{'id': 'weakness:cross-site scripting', 'keyphrase': 'cross-site scripting', 'type': 'weakness'}, {'id': 'weakness:XSS', 'keyphrase': 'XSS', 'type': 'weakness'}, {'id': 'product:Saul Morales Pacheco Donate visa', 'keyphrase': 'Saul Morales Pacheco Donate visa', 'type': 'product'}]}, 'similarity': np.float64(177.27800061949705)}, {'metadata': {'doc_id': '80', 'name': 'Improper Neutralization of Script-Related HTML Tags in a Web Page (Basic XSS)', 'source': 'sparse', 'original_content': 'The product receives input from an upstream component, but it does not neutralize or incorrectly neutralizes special characters such as \"<\", \">\", and \"&\" that could be interpreted as web-scripting elements when they are sent to a downstream component that processes web pages.', 'keyphrase_sources': [{'id': 'weakness:cross-site scripting', 'keyphrase': 'cross-site scripting', 'type': 'weakness'}, {'id': 'weakness:XSS', 'keyphrase': 'XSS', 'type': 'weakness'}]}, 'similarity': np.float64(161.54787724050288)}, {'metadata': {'doc_id': '116', 'name': 'Improper Encoding or Escaping of Output', 'source': 'sparse', 'original_content': 'The product prepares a structured message for communication with another component, but encoding or escaping of the data is either missing or done incorrectly. As a result, the intended structure of the message is not preserved.', 'keyphrase_sources': [{'id': 'weakness:cross-site scripting', 'keyphrase': 'cross-site scripting', 'type': 'weakness'}, {'id': 'weakness:XSS', 'keyphrase': 'XSS', 'type': 'weakness'}]}, 'similarity': np.float64(151.31293082495742)}, {'metadata': {'doc_id': '862', 'name': 'Missing Authorization', 'source': 'sparse', 'original_content': 'The product does not perform an authorization check when an actor attempts to access a resource or perform an action.', 'keyphrase_sources': [{'id': 'rootcause:Missing Authorization vulnerability', 'keyphrase': 'Missing Authorization vulnerability', 'type': 'rootcause'}, {'id': 'product:Saul Morales Pacheco Donate visa', 'keyphrase': 'Saul Morales Pacheco Donate visa', 'type': 'product'}]}, 'similarity': np.float64(148.9963674356987)}, {'metadata': {'doc_id': '1004', 'name': \"Sensitive Cookie Without 'HttpOnly' Flag\", 'source': 'sparse', 'original_content': 'The product uses a cookie to store sensitive information, but the cookie is not marked with the HttpOnly flag.', 'keyphrase_sources': [{'id': 'weakness:cross-site scripting', 'keyphrase': 'cross-site scripting', 'type': 'weakness'}]}, 'similarity': np.float64(148.157585396911)}, {'metadata': {'doc_id': '352', 'name': 'Cross-Site Request Forgery (CSRF)', 'source': 'sparse', 'original_content': 'The web application does not, or can not, sufficiently verify whether a well-formed, valid, consistent request was intentionally provided by the user who submitted the request.', 'keyphrase_sources': [{'id': 'rootcause:Missing Authorization vulnerability', 'keyphrase': 'Missing Authorization vulnerability', 'type': 'rootcause'}, {'id': 'weakness:cross-site scripting', 'keyphrase': 'cross-site scripting', 'type': 'weakness'}, {'id': 'weakness:XSS', 'keyphrase': 'XSS', 'type': 'weakness'}, {'id': 'product:Saul Morales Pacheco Donate visa', 'keyphrase': 'Saul Morales Pacheco Donate visa', 'type': 'product'}, {'id': 'version:n/a through 1.0.0', 'keyphrase': 'n/a through 1.0.0', 'type': 'version'}]}, 'similarity': np.float64(128.914529571141)}, {'metadata': {'doc_id': '639', 'name': 'Authorization Bypass Through User-Controlled Key', 'source': 'sparse', 'original_content': \"The system's authorization functionality does not prevent one user from gaining access to another user's data or record by modifying the key value identifying the data.\", 'keyphrase_sources': [{'id': 'rootcause:Missing Authorization vulnerability', 'keyphrase': 'Missing Authorization vulnerability', 'type': 'rootcause'}]}, 'similarity': np.float64(119.60826601603148)}, {'metadata': {'doc_id': '306', 'name': 'Missing Authentication for Critical Function', 'source': 'sparse', 'original_content': 'The product does not perform any authentication for functionality that requires a provable user identity or consumes a significant amount of resources.', 'keyphrase_sources': [{'id': 'rootcause:Missing Authorization vulnerability', 'keyphrase': 'Missing Authorization vulnerability', 'type': 'rootcause'}]}, 'similarity': np.float64(116.79052435694935)}, {'metadata': {'doc_id': '325', 'name': 'Missing Cryptographic Step', 'source': 'sparse', 'original_content': 'The product does not implement a required step in a cryptographic algorithm, resulting in weaker encryption than advertised by the algorithm.', 'keyphrase_sources': [{'id': 'rootcause:Missing Authorization vulnerability', 'keyphrase': 'Missing Authorization vulnerability', 'type': 'rootcause'}]}, 'similarity': np.float64(116.73033388352609)}, {'metadata': {'doc_id': '434', 'name': 'Unrestricted Upload of File with Dangerous Type', 'source': 'sparse', 'original_content': 'The product allows the upload or transfer of dangerous file types that are automatically processed within its environment.', 'keyphrase_sources': [{'id': 'weakness:XSS', 'keyphrase': 'XSS', 'type': 'weakness'}, {'id': 'product:Saul Morales Pacheco Donate visa', 'keyphrase': 'Saul Morales Pacheco Donate visa', 'type': 'product'}, {'id': 'version:n/a through 1.0.0', 'keyphrase': 'n/a through 1.0.0', 'type': 'version'}]}, 'similarity': np.float64(106.21465427117928)}, {'metadata': {'doc_id': '611', 'name': 'Improper Restriction of XML External Entity Reference', 'source': 'sparse', 'original_content': 'The product processes an XML document that can contain XML entities with URIs that resolve to documents outside of the intended sphere of control, causing the product to embed incorrect documents into its output.', 'keyphrase_sources': [{'id': 'version:n/a through 1.0.0', 'keyphrase': 'n/a through 1.0.0', 'type': 'version'}]}, 'similarity': np.float64(49.377150149829426)}, {'metadata': {'doc_id': '444', 'name': \"Inconsistent Interpretation of HTTP Requests ('HTTP Request/Response Smuggling')\", 'source': 'sparse', 'original_content': 'The product acts as an intermediary HTTP agent\\n         (such as a proxy or firewall) in the data flow between two\\n         entities such as a client and server, but it does not\\n         interpret malformed HTTP requests or responses in ways that\\n         are consistent with how the messages will be processed by\\n         those entities that are at the ultimate destination.', 'keyphrase_sources': [{'id': 'version:n/a through 1.0.0', 'keyphrase': 'n/a through 1.0.0', 'type': 'version'}]}, 'similarity': np.float64(49.08385634205847)}, {'metadata': {'doc_id': '22', 'name': \"Improper Limitation of a Pathname to a Restricted Directory ('Path Traversal')\", 'source': 'sparse', 'original_content': 'The product uses external input to construct a pathname that is intended to identify a file or directory that is located underneath a restricted parent directory, but the product does not properly neutralize special elements within the pathname that can cause the pathname to resolve to a location that is outside of the restricted directory.', 'keyphrase_sources': [{'id': 'product:Saul Morales Pacheco Donate visa', 'keyphrase': 'Saul Morales Pacheco Donate visa', 'type': 'product'}, {'id': 'version:n/a through 1.0.0', 'keyphrase': 'n/a through 1.0.0', 'type': 'version'}]}, 'similarity': np.float64(28.928402106759567)}], identified_cwes={'analyzer': [], 'critic_additional': []})",
  "retrieval_results": {
    "has_multiple_keyphrases": true,
    "keyphrase_cwe_sets": {
      "rootcause:Missing Authorization vulnerability": {
        "keyphrase": "Missing Authorization vulnerability",
        "type": "rootcause",
        "cwes": [
          {
            "metadata": {
              "doc_id": "862",
              "name": "Missing Authorization",
              "source": "sparse",
              "original_content": "The product does not perform an authorization check when an actor attempts to access a resource or perform an action.",
              "keyphrase_sources": [
                {
                  "id": "rootcause:Missing Authorization vulnerability",
                  "keyphrase": "Missing Authorization vulnerability",
                  "type": "rootcause"
                },
                {
                  "id": "product:Saul Morales Pacheco Donate visa",
                  "keyphrase": "Saul Morales Pacheco Donate visa",
                  "type": "product"
                }
              ]
            },
            "similarity": 148.9963674356987
          },
          {
            "metadata": {
              "doc_id": "352",
              "name": "Cross-Site Request Forgery (CSRF)",
              "source": "sparse",
              "original_content": "The web application does not, or can not, sufficiently verify whether a well-formed, valid, consistent request was intentionally provided by the user who submitted the request.",
              "keyphrase_sources": [
                {
                  "id": "rootcause:Missing Authorization vulnerability",
                  "keyphrase": "Missing Authorization vulnerability",
                  "type": "rootcause"
                },
                {
                  "id": "weakness:cross-site scripting",
                  "keyphrase": "cross-site scripting",
                  "type": "weakness"
                },
                {
                  "id": "weakness:XSS",
                  "keyphrase": "XSS",
                  "type": "weakness"
                },
                {
                  "id": "product:Saul Morales Pacheco Donate visa",
                  "keyphrase": "Saul Morales Pacheco Donate visa",
                  "type": "product"
                },
                {
                  "id": "version:n/a through 1.0.0",
                  "keyphrase": "n/a through 1.0.0",
                  "type": "version"
                }
              ]
            },
            "similarity": 128.914529571141
          },
          {
            "metadata": {
              "doc_id": "639",
              "name": "Authorization Bypass Through User-Controlled Key",
              "source": "sparse",
              "original_content": "The system's authorization functionality does not prevent one user from gaining access to another user's data or record by modifying the key value identifying the data.",
              "keyphrase_sources": [
                {
                  "id": "rootcause:Missing Authorization vulnerability",
                  "keyphrase": "Missing Authorization vulnerability",
                  "type": "rootcause"
                }
              ]
            },
            "similarity": 119.60826601603148
          },
          {
            "metadata": {
              "doc_id": "306",
              "name": "Missing Authentication for Critical Function",
              "source": "sparse",
              "original_content": "The product does not perform any authentication for functionality that requires a provable user identity or consumes a significant amount of resources.",
              "keyphrase_sources": [
                {
                  "id": "rootcause:Missing Authorization vulnerability",
                  "keyphrase": "Missing Authorization vulnerability",
                  "type": "rootcause"
                }
              ]
            },
            "similarity": 116.79052435694935
          },
          {
            "metadata": {
              "doc_id": "325",
              "name": "Missing Cryptographic Step",
              "source": "sparse",
              "original_content": "The product does not implement a required step in a cryptographic algorithm, resulting in weaker encryption than advertised by the algorithm.",
              "keyphrase_sources": [
                {
                  "id": "rootcause:Missing Authorization vulnerability",
                  "keyphrase": "Missing Authorization vulnerability",
                  "type": "rootcause"
                }
              ]
            },
            "similarity": 116.73033388352609
          }
        ]
      },
      "weakness:cross-site scripting": {
        "keyphrase": "cross-site scripting",
        "type": "weakness",
        "cwes": [
          {
            "metadata": {
              "doc_id": "352",
              "name": "Cross-Site Request Forgery (CSRF)",
              "source": "sparse",
              "original_content": "The web application does not, or can not, sufficiently verify whether a well-formed, valid, consistent request was intentionally provided by the user who submitted the request."
            },
            "similarity": 189.65579797118505
          },
          {
            "metadata": {
              "doc_id": "79",
              "name": "Improper Neutralization of Input During Web Page Generation ('Cross-site Scripting')",
              "source": "sparse",
              "original_content": "The product does not neutralize or incorrectly neutralizes user-controllable input before it is placed in output that is used as a web page that is served to other users.",
              "keyphrase_sources": [
                {
                  "id": "weakness:cross-site scripting",
                  "keyphrase": "cross-site scripting",
                  "type": "weakness"
                },
                {
                  "id": "weakness:XSS",
                  "keyphrase": "XSS",
                  "type": "weakness"
                },
                {
                  "id": "product:Saul Morales Pacheco Donate visa",
                  "keyphrase": "Saul Morales Pacheco Donate visa",
                  "type": "product"
                }
              ]
            },
            "similarity": 177.27800061949705
          },
          {
            "metadata": {
              "doc_id": "80",
              "name": "Improper Neutralization of Script-Related HTML Tags in a Web Page (Basic XSS)",
              "source": "sparse",
              "original_content": "The product receives input from an upstream component, but it does not neutralize or incorrectly neutralizes special characters such as \"<\", \">\", and \"&\" that could be interpreted as web-scripting elements when they are sent to a downstream component that processes web pages.",
              "keyphrase_sources": [
                {
                  "id": "weakness:cross-site scripting",
                  "keyphrase": "cross-site scripting",
                  "type": "weakness"
                },
                {
                  "id": "weakness:XSS",
                  "keyphrase": "XSS",
                  "type": "weakness"
                }
              ]
            },
            "similarity": 161.54787724050288
          },
          {
            "metadata": {
              "doc_id": "116",
              "name": "Improper Encoding or Escaping of Output",
              "source": "sparse",
              "original_content": "The product prepares a structured message for communication with another component, but encoding or escaping of the data is either missing or done incorrectly. As a result, the intended structure of the message is not preserved.",
              "keyphrase_sources": [
                {
                  "id": "weakness:cross-site scripting",
                  "keyphrase": "cross-site scripting",
                  "type": "weakness"
                },
                {
                  "id": "weakness:XSS",
                  "keyphrase": "XSS",
                  "type": "weakness"
                }
              ]
            },
            "similarity": 151.31293082495742
          },
          {
            "metadata": {
              "doc_id": "1004",
              "name": "Sensitive Cookie Without 'HttpOnly' Flag",
              "source": "sparse",
              "original_content": "The product uses a cookie to store sensitive information, but the cookie is not marked with the HttpOnly flag.",
              "keyphrase_sources": [
                {
                  "id": "weakness:cross-site scripting",
                  "keyphrase": "cross-site scripting",
                  "type": "weakness"
                }
              ]
            },
            "similarity": 148.157585396911
          }
        ]
      },
      "weakness:XSS": {
        "keyphrase": "XSS",
        "type": "weakness",
        "cwes": [
          {
            "metadata": {
              "doc_id": "352",
              "name": "Cross-Site Request Forgery (CSRF)",
              "source": "sparse",
              "original_content": "The web application does not, or can not, sufficiently verify whether a well-formed, valid, consistent request was intentionally provided by the user who submitted the request."
            },
            "similarity": 121.63265269504913
          },
          {
            "metadata": {
              "doc_id": "79",
              "name": "Improper Neutralization of Input During Web Page Generation ('Cross-site Scripting')",
              "source": "sparse",
              "original_content": "The product does not neutralize or incorrectly neutralizes user-controllable input before it is placed in output that is used as a web page that is served to other users."
            },
            "similarity": 115.31320926261088
          },
          {
            "metadata": {
              "doc_id": "434",
              "name": "Unrestricted Upload of File with Dangerous Type",
              "source": "sparse",
              "original_content": "The product allows the upload or transfer of dangerous file types that are automatically processed within its environment.",
              "keyphrase_sources": [
                {
                  "id": "weakness:XSS",
                  "keyphrase": "XSS",
                  "type": "weakness"
                },
                {
                  "id": "product:Saul Morales Pacheco Donate visa",
                  "keyphrase": "Saul Morales Pacheco Donate visa",
                  "type": "product"
                },
                {
                  "id": "version:n/a through 1.0.0",
                  "keyphrase": "n/a through 1.0.0",
                  "type": "version"
                }
              ]
            },
            "similarity": 106.21465427117928
          },
          {
            "metadata": {
              "doc_id": "80",
              "name": "Improper Neutralization of Script-Related HTML Tags in a Web Page (Basic XSS)",
              "source": "sparse",
              "original_content": "The product receives input from an upstream component, but it does not neutralize or incorrectly neutralizes special characters such as \"<\", \">\", and \"&\" that could be interpreted as web-scripting elements when they are sent to a downstream component that processes web pages."
            },
            "similarity": 104.86937402202457
          },
          {
            "metadata": {
              "doc_id": "116",
              "name": "Improper Encoding or Escaping of Output",
              "source": "sparse",
              "original_content": "The product prepares a structured message for communication with another component, but encoding or escaping of the data is either missing or done incorrectly. As a result, the intended structure of the message is not preserved."
            },
            "similarity": 104.142702940797
          }
        ]
      },
      "product:Saul Morales Pacheco Donate visa": {
        "keyphrase": "Saul Morales Pacheco Donate visa",
        "type": "product",
        "cwes": [
          {
            "metadata": {
              "doc_id": "352",
              "name": "Cross-Site Request Forgery (CSRF)",
              "source": "sparse",
              "original_content": "The web application does not, or can not, sufficiently verify whether a well-formed, valid, consistent request was intentionally provided by the user who submitted the request."
            },
            "similarity": 37.29591156917923
          },
          {
            "metadata": {
              "doc_id": "862",
              "name": "Missing Authorization",
              "source": "sparse",
              "original_content": "The product does not perform an authorization check when an actor attempts to access a resource or perform an action."
            },
            "similarity": 31.477139648633102
          },
          {
            "metadata": {
              "doc_id": "79",
              "name": "Improper Neutralization of Input During Web Page Generation ('Cross-site Scripting')",
              "source": "sparse",
              "original_content": "The product does not neutralize or incorrectly neutralizes user-controllable input before it is placed in output that is used as a web page that is served to other users."
            },
            "similarity": 30.61692063354283
          },
          {
            "metadata": {
              "doc_id": "434",
              "name": "Unrestricted Upload of File with Dangerous Type",
              "source": "sparse",
              "original_content": "The product allows the upload or transfer of dangerous file types that are automatically processed within its environment."
            },
            "similarity": 30.396053708230532
          },
          {
            "metadata": {
              "doc_id": "22",
              "name": "Improper Limitation of a Pathname to a Restricted Directory ('Path Traversal')",
              "source": "sparse",
              "original_content": "The product uses external input to construct a pathname that is intended to identify a file or directory that is located underneath a restricted parent directory, but the product does not properly neutralize special elements within the pathname that can cause the pathname to resolve to a location that is outside of the restricted directory.",
              "keyphrase_sources": [
                {
                  "id": "product:Saul Morales Pacheco Donate visa",
                  "keyphrase": "Saul Morales Pacheco Donate visa",
                  "type": "product"
                },
                {
                  "id": "version:n/a through 1.0.0",
                  "keyphrase": "n/a through 1.0.0",
                  "type": "version"
                }
              ]
            },
            "similarity": 28.928402106759567
          }
        ]
      },
      "version:n/a through 1.0.0": {
        "keyphrase": "n/a through 1.0.0",
        "type": "version",
        "cwes": [
          {
            "metadata": {
              "doc_id": "22",
              "name": "Improper Limitation of a Pathname to a Restricted Directory ('Path Traversal')",
              "source": "sparse",
              "original_content": "The product uses external input to construct a pathname that is intended to identify a file or directory that is located underneath a restricted parent directory, but the product does not properly neutralize special elements within the pathname that can cause the pathname to resolve to a location that is outside of the restricted directory."
            },
            "similarity": 54.04128466686619
          },
          {
            "metadata": {
              "doc_id": "434",
              "name": "Unrestricted Upload of File with Dangerous Type",
              "source": "sparse",
              "original_content": "The product allows the upload or transfer of dangerous file types that are automatically processed within its environment."
            },
            "similarity": 50.74247737855179
          },
          {
            "metadata": {
              "doc_id": "611",
              "name": "Improper Restriction of XML External Entity Reference",
              "source": "sparse",
              "original_content": "The product processes an XML document that can contain XML entities with URIs that resolve to documents outside of the intended sphere of control, causing the product to embed incorrect documents into its output.",
              "keyphrase_sources": [
                {
                  "id": "version:n/a through 1.0.0",
                  "keyphrase": "n/a through 1.0.0",
                  "type": "version"
                }
              ]
            },
            "similarity": 49.377150149829426
          },
          {
            "metadata": {
              "doc_id": "352",
              "name": "Cross-Site Request Forgery (CSRF)",
              "source": "sparse",
              "original_content": "The web application does not, or can not, sufficiently verify whether a well-formed, valid, consistent request was intentionally provided by the user who submitted the request."
            },
            "similarity": 49.19181167445263
          },
          {
            "metadata": {
              "doc_id": "444",
              "name": "Inconsistent Interpretation of HTTP Requests ('HTTP Request/Response Smuggling')",
              "source": "sparse",
              "original_content": "The product acts as an intermediary HTTP agent\n         (such as a proxy or firewall) in the data flow between two\n         entities such as a client and server, but it does not\n         interpret malformed HTTP requests or responses in ways that\n         are consistent with how the messages will be processed by\n         those entities that are at the ultimate destination.",
              "keyphrase_sources": [
                {
                  "id": "version:n/a through 1.0.0",
                  "keyphrase": "n/a through 1.0.0",
                  "type": "version"
                }
              ]
            },
            "similarity": 49.08385634205847
          }
        ]
      }
    },
    "keyphrase_mapping": {
      "862": [
        {
          "id": "rootcause:Missing Authorization vulnerability",
          "keyphrase": "Missing Authorization vulnerability",
          "type": "rootcause"
        },
        {
          "id": "product:Saul Morales Pacheco Donate visa",
          "keyphrase": "Saul Morales Pacheco Donate visa",
          "type": "product"
        }
      ],
      "352": [
        {
          "id": "rootcause:Missing Authorization vulnerability",
          "keyphrase": "Missing Authorization vulnerability",
          "type": "rootcause"
        },
        {
          "id": "weakness:cross-site scripting",
          "keyphrase": "cross-site scripting",
          "type": "weakness"
        },
        {
          "id": "weakness:XSS",
          "keyphrase": "XSS",
          "type": "weakness"
        },
        {
          "id": "product:Saul Morales Pacheco Donate visa",
          "keyphrase": "Saul Morales Pacheco Donate visa",
          "type": "product"
        },
        {
          "id": "version:n/a through 1.0.0",
          "keyphrase": "n/a through 1.0.0",
          "type": "version"
        }
      ],
      "639": [
        {
          "id": "rootcause:Missing Authorization vulnerability",
          "keyphrase": "Missing Authorization vulnerability",
          "type": "rootcause"
        }
      ],
      "306": [
        {
          "id": "rootcause:Missing Authorization vulnerability",
          "keyphrase": "Missing Authorization vulnerability",
          "type": "rootcause"
        }
      ],
      "325": [
        {
          "id": "rootcause:Missing Authorization vulnerability",
          "keyphrase": "Missing Authorization vulnerability",
          "type": "rootcause"
        }
      ],
      "79": [
        {
          "id": "weakness:cross-site scripting",
          "keyphrase": "cross-site scripting",
          "type": "weakness"
        },
        {
          "id": "weakness:XSS",
          "keyphrase": "XSS",
          "type": "weakness"
        },
        {
          "id": "product:Saul Morales Pacheco Donate visa",
          "keyphrase": "Saul Morales Pacheco Donate visa",
          "type": "product"
        }
      ],
      "80": [
        {
          "id": "weakness:cross-site scripting",
          "keyphrase": "cross-site scripting",
          "type": "weakness"
        },
        {
          "id": "weakness:XSS",
          "keyphrase": "XSS",
          "type": "weakness"
        }
      ],
      "116": [
        {
          "id": "weakness:cross-site scripting",
          "keyphrase": "cross-site scripting",
          "type": "weakness"
        },
        {
          "id": "weakness:XSS",
          "keyphrase": "XSS",
          "type": "weakness"
        }
      ],
      "1004": [
        {
          "id": "weakness:cross-site scripting",
          "keyphrase": "cross-site scripting",
          "type": "weakness"
        }
      ],
      "434": [
        {
          "id": "weakness:XSS",
          "keyphrase": "XSS",
          "type": "weakness"
        },
        {
          "id": "product:Saul Morales Pacheco Donate visa",
          "keyphrase": "Saul Morales Pacheco Donate visa",
          "type": "product"
        },
        {
          "id": "version:n/a through 1.0.0",
          "keyphrase": "n/a through 1.0.0",
          "type": "version"
        }
      ],
      "22": [
        {
          "id": "product:Saul Morales Pacheco Donate visa",
          "keyphrase": "Saul Morales Pacheco Donate visa",
          "type": "product"
        },
        {
          "id": "version:n/a through 1.0.0",
          "keyphrase": "n/a through 1.0.0",
          "type": "version"
        }
      ],
      "611": [
        {
          "id": "version:n/a through 1.0.0",
          "keyphrase": "n/a through 1.0.0",
          "type": "version"
        }
      ],
      "444": [
        {
          "id": "version:n/a through 1.0.0",
          "keyphrase": "n/a through 1.0.0",
          "type": "version"
        }
      ]
    },
    "relevant_cwes": [
      {
        "metadata": {
          "doc_id": "79",
          "name": "Improper Neutralization of Input During Web Page Generation ('Cross-site Scripting')",
          "source": "sparse",
          "original_content": "The product does not neutralize or incorrectly neutralizes user-controllable input before it is placed in output that is used as a web page that is served to other users.",
          "keyphrase_sources": [
            {
              "id": "weakness:cross-site scripting",
              "keyphrase": "cross-site scripting",
              "type": "weakness"
            },
            {
              "id": "weakness:XSS",
              "keyphrase": "XSS",
              "type": "weakness"
            },
            {
              "id": "product:Saul Morales Pacheco Donate visa",
              "keyphrase": "Saul Morales Pacheco Donate visa",
              "type": "product"
            }
          ]
        },
        "similarity": 177.27800061949705
      },
      {
        "metadata": {
          "doc_id": "80",
          "name": "Improper Neutralization of Script-Related HTML Tags in a Web Page (Basic XSS)",
          "source": "sparse",
          "original_content": "The product receives input from an upstream component, but it does not neutralize or incorrectly neutralizes special characters such as \"<\", \">\", and \"&\" that could be interpreted as web-scripting elements when they are sent to a downstream component that processes web pages.",
          "keyphrase_sources": [
            {
              "id": "weakness:cross-site scripting",
              "keyphrase": "cross-site scripting",
              "type": "weakness"
            },
            {
              "id": "weakness:XSS",
              "keyphrase": "XSS",
              "type": "weakness"
            }
          ]
        },
        "similarity": 161.54787724050288
      },
      {
        "metadata": {
          "doc_id": "116",
          "name": "Improper Encoding or Escaping of Output",
          "source": "sparse",
          "original_content": "The product prepares a structured message for communication with another component, but encoding or escaping of the data is either missing or done incorrectly. As a result, the intended structure of the message is not preserved.",
          "keyphrase_sources": [
            {
              "id": "weakness:cross-site scripting",
              "keyphrase": "cross-site scripting",
              "type": "weakness"
            },
            {
              "id": "weakness:XSS",
              "keyphrase": "XSS",
              "type": "weakness"
            }
          ]
        },
        "similarity": 151.31293082495742
      },
      {
        "metadata": {
          "doc_id": "862",
          "name": "Missing Authorization",
          "source": "sparse",
          "original_content": "The product does not perform an authorization check when an actor attempts to access a resource or perform an action.",
          "keyphrase_sources": [
            {
              "id": "rootcause:Missing Authorization vulnerability",
              "keyphrase": "Missing Authorization vulnerability",
              "type": "rootcause"
            },
            {
              "id": "product:Saul Morales Pacheco Donate visa",
              "keyphrase": "Saul Morales Pacheco Donate visa",
              "type": "product"
            }
          ]
        },
        "similarity": 148.9963674356987
      },
      {
        "metadata": {
          "doc_id": "1004",
          "name": "Sensitive Cookie Without 'HttpOnly' Flag",
          "source": "sparse",
          "original_content": "The product uses a cookie to store sensitive information, but the cookie is not marked with the HttpOnly flag.",
          "keyphrase_sources": [
            {
              "id": "weakness:cross-site scripting",
              "keyphrase": "cross-site scripting",
              "type": "weakness"
            }
          ]
        },
        "similarity": 148.157585396911
      },
      {
        "metadata": {
          "doc_id": "352",
          "name": "Cross-Site Request Forgery (CSRF)",
          "source": "sparse",
          "original_content": "The web application does not, or can not, sufficiently verify whether a well-formed, valid, consistent request was intentionally provided by the user who submitted the request.",
          "keyphrase_sources": [
            {
              "id": "rootcause:Missing Authorization vulnerability",
              "keyphrase": "Missing Authorization vulnerability",
              "type": "rootcause"
            },
            {
              "id": "weakness:cross-site scripting",
              "keyphrase": "cross-site scripting",
              "type": "weakness"
            },
            {
              "id": "weakness:XSS",
              "keyphrase": "XSS",
              "type": "weakness"
            },
            {
              "id": "product:Saul Morales Pacheco Donate visa",
              "keyphrase": "Saul Morales Pacheco Donate visa",
              "type": "product"
            },
            {
              "id": "version:n/a through 1.0.0",
              "keyphrase": "n/a through 1.0.0",
              "type": "version"
            }
          ]
        },
        "similarity": 128.914529571141
      },
      {
        "metadata": {
          "doc_id": "639",
          "name": "Authorization Bypass Through User-Controlled Key",
          "source": "sparse",
          "original_content": "The system's authorization functionality does not prevent one user from gaining access to another user's data or record by modifying the key value identifying the data.",
          "keyphrase_sources": [
            {
              "id": "rootcause:Missing Authorization vulnerability",
              "keyphrase": "Missing Authorization vulnerability",
              "type": "rootcause"
            }
          ]
        },
        "similarity": 119.60826601603148
      },
      {
        "metadata": {
          "doc_id": "306",
          "name": "Missing Authentication for Critical Function",
          "source": "sparse",
          "original_content": "The product does not perform any authentication for functionality that requires a provable user identity or consumes a significant amount of resources.",
          "keyphrase_sources": [
            {
              "id": "rootcause:Missing Authorization vulnerability",
              "keyphrase": "Missing Authorization vulnerability",
              "type": "rootcause"
            }
          ]
        },
        "similarity": 116.79052435694935
      },
      {
        "metadata": {
          "doc_id": "325",
          "name": "Missing Cryptographic Step",
          "source": "sparse",
          "original_content": "The product does not implement a required step in a cryptographic algorithm, resulting in weaker encryption than advertised by the algorithm.",
          "keyphrase_sources": [
            {
              "id": "rootcause:Missing Authorization vulnerability",
              "keyphrase": "Missing Authorization vulnerability",
              "type": "rootcause"
            }
          ]
        },
        "similarity": 116.73033388352609
      },
      {
        "metadata": {
          "doc_id": "434",
          "name": "Unrestricted Upload of File with Dangerous Type",
          "source": "sparse",
          "original_content": "The product allows the upload or transfer of dangerous file types that are automatically processed within its environment.",
          "keyphrase_sources": [
            {
              "id": "weakness:XSS",
              "keyphrase": "XSS",
              "type": "weakness"
            },
            {
              "id": "product:Saul Morales Pacheco Donate visa",
              "keyphrase": "Saul Morales Pacheco Donate visa",
              "type": "product"
            },
            {
              "id": "version:n/a through 1.0.0",
              "keyphrase": "n/a through 1.0.0",
              "type": "version"
            }
          ]
        },
        "similarity": 106.21465427117928
      },
      {
        "metadata": {
          "doc_id": "611",
          "name": "Improper Restriction of XML External Entity Reference",
          "source": "sparse",
          "original_content": "The product processes an XML document that can contain XML entities with URIs that resolve to documents outside of the intended sphere of control, causing the product to embed incorrect documents into its output.",
          "keyphrase_sources": [
            {
              "id": "version:n/a through 1.0.0",
              "keyphrase": "n/a through 1.0.0",
              "type": "version"
            }
          ]
        },
        "similarity": 49.377150149829426
      },
      {
        "metadata": {
          "doc_id": "444",
          "name": "Inconsistent Interpretation of HTTP Requests ('HTTP Request/Response Smuggling')",
          "source": "sparse",
          "original_content": "The product acts as an intermediary HTTP agent\n         (such as a proxy or firewall) in the data flow between two\n         entities such as a client and server, but it does not\n         interpret malformed HTTP requests or responses in ways that\n         are consistent with how the messages will be processed by\n         those entities that are at the ultimate destination.",
          "keyphrase_sources": [
            {
              "id": "version:n/a through 1.0.0",
              "keyphrase": "n/a through 1.0.0",
              "type": "version"
            }
          ]
        },
        "similarity": 49.08385634205847
      },
      {
        "metadata": {
          "doc_id": "22",
          "name": "Improper Limitation of a Pathname to a Restricted Directory ('Path Traversal')",
          "source": "sparse",
          "original_content": "The product uses external input to construct a pathname that is intended to identify a file or directory that is located underneath a restricted parent directory, but the product does not properly neutralize special elements within the pathname that can cause the pathname to resolve to a location that is outside of the restricted directory.",
          "keyphrase_sources": [
            {
              "id": "product:Saul Morales Pacheco Donate visa",
              "keyphrase": "Saul Morales Pacheco Donate visa",
              "type": "product"
            },
            {
              "id": "version:n/a through 1.0.0",
              "keyphrase": "n/a through 1.0.0",
              "type": "version"
            }
          ]
        },
        "similarity": 28.928402106759567
      }
    ],
    "enhanced_query": "# Vulnerability Description\n\n    **Missing Authorization vulnerability** in Saul Morales Pacheco Donate visa allows Stored **XSS**. This issue affects Donate visa from n/a through 1.0.0.\n\n    # Keyphrase-Specific CWE Analysis\n    This vulnerability contains multiple keyphrases that may map to different CWEs. \n    Please analyze each keyphrase separately and determine the most appropriate CWE(s) for each.\n\n    ## WEAKNESS: 'cross-site scripting'\n\nRelevant CWEs for this WEAKNESS:\n\n### 1. CWE-79: Improper Neutralization of Input During Web Page Generation ('Cross-site Scripting') (Score: 177.28)\n\nThe product does not neutralize or incorrectly neutralizes user-controllable input before it is placed in output that is used as a web page that is served to other users....\n\n### 2. CWE-80: Improper Neutralization of Script-Related HTML Tags in a Web Page (Basic XSS) (Score: 161.55)\n\nThe product receives input from an upstream component, but it does not neutralize or incorrectly neutralizes special characters such as \"<\", \">\", and \"&\" that could be interpreted as web-scripting elements when they are sent to a downstream component that processes web pages....\n\n### 3. CWE-116: Improper Encoding or Escaping of Output (Score: 151.31)\n\nThe product prepares a structured message for communication with another component, but encoding or escaping of the data is either missing or done incorrectly. As a result, the intended structure of the message is not preserved....\n\n### 4. CWE-1004: Sensitive Cookie Without 'HttpOnly' Flag (Score: 148.16)\n\nThe product uses a cookie to store sensitive information, but the cookie is not marked with the HttpOnly flag....\n\n### 5. CWE-352: Cross-Site Request Forgery (CSRF) (Score: 128.91)\n\nThe web application does not, or can not, sufficiently verify whether a well-formed, valid, consistent request was intentionally provided by the user who submitted the request....\n\n## WEAKNESS: 'XSS'\n\nRelevant CWEs for this WEAKNESS:\n\n### 1. CWE-79: Improper Neutralization of Input During Web Page Generation ('Cross-site Scripting') (Score: 177.28)\n\nThe product does not neutralize or incorrectly neutralizes user-controllable input before it is placed in output that is used as a web page that is served to other users....\n\n### 2. CWE-80: Improper Neutralization of Script-Related HTML Tags in a Web Page (Basic XSS) (Score: 161.55)\n\nThe product receives input from an upstream component, but it does not neutralize or incorrectly neutralizes special characters such as \"<\", \">\", and \"&\" that could be interpreted as web-scripting elements when they are sent to a downstream component that processes web pages....\n\n### 3. CWE-116: Improper Encoding or Escaping of Output (Score: 151.31)\n\nThe product prepares a structured message for communication with another component, but encoding or escaping of the data is either missing or done incorrectly. As a result, the intended structure of the message is not preserved....\n\n### 4. CWE-352: Cross-Site Request Forgery (CSRF) (Score: 128.91)\n\nThe web application does not, or can not, sufficiently verify whether a well-formed, valid, consistent request was intentionally provided by the user who submitted the request....\n\n### 5. CWE-434: Unrestricted Upload of File with Dangerous Type (Score: 106.21)\n\nThe product allows the upload or transfer of dangerous file types that are automatically processed within its environment....\n\n## PRODUCT: 'Saul Morales Pacheco Donate visa'\n\nRelevant CWEs for this PRODUCT:\n\n### 1. CWE-79: Improper Neutralization of Input During Web Page Generation ('Cross-site Scripting') (Score: 177.28)\n\nThe product does not neutralize or incorrectly neutralizes user-controllable input before it is placed in output that is used as a web page that is served to other users....\n\n### 2. CWE-862: Missing Authorization (Score: 149.00)\n\nThe product does not perform an authorization check when an actor attempts to access a resource or perform an action....\n\n### 3. CWE-352: Cross-Site Request Forgery (CSRF) (Score: 128.91)\n\nThe web application does not, or can not, sufficiently verify whether a well-formed, valid, consistent request was intentionally provided by the user who submitted the request....\n\n### 4. CWE-434: Unrestricted Upload of File with Dangerous Type (Score: 106.21)\n\nThe product allows the upload or transfer of dangerous file types that are automatically processed within its environment....\n\n### 5. CWE-22: Improper Limitation of a Pathname to a Restricted Directory ('Path Traversal') (Score: 28.93)\n\nThe product uses external input to construct a pathname that is intended to identify a file or directory that is located underneath a restricted parent directory, but the product does not properly neutralize special elements within the pathname that can cause the pathname to resolve to a location th...\n\n## ROOTCAUSE: 'Missing Authorization vulnerability'\n\nRelevant CWEs for this ROOTCAUSE:\n\n### 1. CWE-862: Missing Authorization (Score: 149.00)\n\nThe product does not perform an authorization check when an actor attempts to access a resource or perform an action....\n\n### 2. CWE-352: Cross-Site Request Forgery (CSRF) (Score: 128.91)\n\nThe web application does not, or can not, sufficiently verify whether a well-formed, valid, consistent request was intentionally provided by the user who submitted the request....\n\n### 3. CWE-639: Authorization Bypass Through User-Controlled Key (Score: 119.61)\n\nThe system's authorization functionality does not prevent one user from gaining access to another user's data or record by modifying the key value identifying the data....\n\n### 4. CWE-306: Missing Authentication for Critical Function (Score: 116.79)\n\nThe product does not perform any authentication for functionality that requires a provable user identity or consumes a significant amount of resources....\n\n### 5. CWE-325: Missing Cryptographic Step (Score: 116.73)\n\nThe product does not implement a required step in a cryptographic algorithm, resulting in weaker encryption than advertised by the algorithm....\n\n## VERSION: 'n/a through 1.0.0'\n\nRelevant CWEs for this VERSION:\n\n### 1. CWE-352: Cross-Site Request Forgery (CSRF) (Score: 128.91)\n\nThe web application does not, or can not, sufficiently verify whether a well-formed, valid, consistent request was intentionally provided by the user who submitted the request....\n\n### 2. CWE-434: Unrestricted Upload of File with Dangerous Type (Score: 106.21)\n\nThe product allows the upload or transfer of dangerous file types that are automatically processed within its environment....\n\n### 3. CWE-611: Improper Restriction of XML External Entity Reference (Score: 49.38)\n\nThe product processes an XML document that can contain XML entities with URIs that resolve to documents outside of the intended sphere of control, causing the product to embed incorrect documents into its output....\n\n### 4. CWE-444: Inconsistent Interpretation of HTTP Requests ('HTTP Request/Response Smuggling') (Score: 49.08)\n\nThe product acts as an intermediary HTTP agent\n         (such as a proxy or firewall) in the data flow between two\n         entities such as a client and server, but it does not\n         interpret malformed HTTP requests or responses in ways that\n         are consistent with how the messages will be...\n\n### 5. CWE-22: Improper Limitation of a Pathname to a Restricted Directory ('Path Traversal') (Score: 28.93)\n\nThe product uses external input to construct a pathname that is intended to identify a file or directory that is located underneath a restricted parent directory, but the product does not properly neutralize special elements within the pathname that can cause the pathname to resolve to a location th...\n\n\n    # Analysis Instructions\n    1. For each keyphrase, identify the most appropriate CWE(s) that represent the weakness.\n    2. Consider how the different keyphrases might relate to each other in the vulnerability chain.\n    3. Provide a final determination of primary CWE(s) and any secondary CWEs.\n    4. Format your response using the standard analysis template.\n\n    Please analyze how these different weaknesses interact and provide a comprehensive CWE classification.\n    "
  },
  "retrieval_time": 1.2135424613952637
}