{
  "cve_id": "CVE-2024-38554",
  "description": "In the Linux kernel, the following vulnerability has been resolved ax25 Fix **reference count leak** issue of net_device There is a **reference count leak** issue of the object net_device in ax25_dev_device_down(). When the ax25 device is shutting down, the ax25_dev_device_down() drops the reference count of net_device one or zero times depending on if we goto unlock_put or not, which will cause **memory leak**. In order to solve the above issue, decrease the reference count of net_device after dev->ax25_ptr is set to null.",
  "key_phrases": {
    "rootcause": "",
    "weakness": [
      "memory leak",
      "reference count leak"
    ],
    "impact": "",
    "vector": "",
    "attacker": "",
    "product": "Linux kernel",
    "version": "",
    "component": "ax25_dev_device_down()"
  },
  "reference_content": "The provided content describes a fix for a reference count leak issue in the Linux kernel's AX.25 networking module. This corresponds to the provided CVE description.\n\n**Root cause of vulnerability:**\n- The `ax25_dev_device_down()` function in `net/ax25/ax25_dev.c` was not consistently decrementing the reference count of the `net_device` object during device shutdown. The reference count decrement was conditional on whether the code branched to the `unlock_put` label or not. If the condition is not met, the reference counter will not be decremented, leading to a leak.\n\n**Weaknesses/vulnerabilities present:**\n- **Reference count leak**: The `net_device` object's reference counter could be decremented zero or one times leading to a memory leak on certain shutdown paths.\n\n**Impact of exploitation:**\n- Memory leak: Repeatedly creating and shutting down AX.25 devices could lead to memory exhaustion as the `net_device` objects are not freed.\n\n**Attack vectors:**\n- Triggering the device shutdown path in the AX.25 networking module.\n\n**Required attacker capabilities/position:**\n- The attacker needs the ability to create and shutdown AX.25 network devices in the system.\n\n**Additional details:**\n- The fix involves removing the conditional `goto unlock_put` branch, and unconditionally decrementing the `net_device` reference count after setting `dev->ax25_ptr` to NULL.\n- The fix was backported to various stable kernel branches.\n- The fix addresses the issue introduced by the commit \"ax25: add refcount in ax25_dev to avoid UAF bugs\" (d01ffb9eee4a).",
  "similar_info": {
    "cwe_distribution": {},
    "cwe_consensus": "",
    "similarity_stats": {
      "thresholds": [],
      "total_samples_by_threshold": {},
      "top_cwes_by_threshold": {}
    }
  },
  "similarity_summary": {
    "consensus_cwe": "",
    "top_cwes": [],
    "confidence_levels": {},
    "total_samples": 0
  },
  "analysis": "# Summary\n\n| CWE ID | CWE Name | Confidence | CWE Abstraction Level | CWE Vulnerability Mapping Label | CWE-Vulnerability Mapping Notes |\n|---|---|---|---|---|---|\n| CWE-911 | Improper Update of Reference Count | 1.0 | Base | Primary | Allowed |\n| CWE-401 | Missing Release of Memory after Effective Lifetime | 0.7 | Class | Secondary | Allowed-with-Review |\n\n## Evidence and Confidence\n\n*   **Confidence Score:** 0.9\n*   **Evidence Strength:** HIGH\n\n## Relationship Analysis\n\nThe primary CWE is CWE-911, which is a Base level CWE. CWE-401 is a Class-level CWE and a parent of CWE-772, Missing Release of Resource after Effective Lifetime, but since the description specifies **reference count**, CWE-911 is a better fit.\n\n```mermaid\ngraph TD\n    cwe911[\"CWE-911: Improper Update of Reference Count\"]\n    cwe401[\"CWE-401: Missing Release of Memory after Effective Lifetime\"]\n    cwe772[\"CWE-772: Missing Release of Resource after Effective Lifetime\"]\n\n    cwe772 -->|CHILDOF| cwe401\n    \n    classDef primary fill:#f96,stroke:#333,stroke-width:2px\n    classDef secondary fill:#69f,stroke:#333\n    classDef tertiary fill:#9e9,stroke:#333\n    class cwe911 primary\n    class cwe401 secondary\n```\n\n## Vulnerability Chain\n\nThe vulnerability chain starts with an **improper update of the reference count** (CWE-911), which leads to a **memory leak**, because the memory is not released after its effective lifetime (CWE-401).\n\n## Summary of Analysis\n\nThe vulnerability description clearly states a **reference count leak** issue in the Linux kernel. The `ax25_dev_device_down()` function **drops the reference count** of `net_device` one or zero times, depending on the execution path. This leads to a **memory leak**.\n\nCWE-911 (Improper Update of Reference Count) is the most appropriate primary CWE, as it directly addresses the **root cause** of the vulnerability. The description explicitly mentions the **improper update of the reference count**, making CWE-911 a precise match. The evidence for this is the vulnerability description and the Keyphrase-Specific CWE Analysis, specifically the WEAKNESS: `reference count leak`.\n\nCWE-401 (Missing Release of Memory after Effective Lifetime) can be considered a secondary CWE. While the vulnerability ultimately results in a memory leak, the **root cause** is the **improper handling of the reference count**. The description clearly states, \"When the ax25 device is shutting down, the ax25_dev_device_down() drops the reference count of net_device one or zero times depending on if we goto unlock_put or not, which will cause **memory leak**\". The evidence for this is the vulnerability description and the Keyphrase-Specific CWE Analysis, specifically the WEAKNESS: `memory leak`.\n\nI am overriding the general mapping guidance to map both the root cause and resulting impact as the relationship is clear in the description.\n\nRelevant CWE Information:\n\n# Enhanced Context (25 CWEs)\nThe following CWEs were identified as potentially relevant to this vulnerability:\n\n## CWE-911: Improper Update of Reference Count\n**Abstraction Level**: Base\n**Similarity Score**: 0.76\n**Source**: dense\n\n**Description**:\nThe product uses a reference count to manage a resource, but it does not update or incorrectly updates the reference count.\n\n**Mapping Guidance**:\n- Usage: Allowed\n- Rationale: This CWE entry is at the Base level of abstraction, which is a preferred level of abstraction for mapping to the root causes of vulnerabilities.\n\n## CWE-401: Missing Release of Memory after Effective Lifetime\n**Abstraction Level**: Class\n**Similarity Score**: 0.72\n**Source**: dense\n\n**Description**:\nThe product does not sufficiently track and release allocated memory after it has been used, which slowly consumes remaining memory....\n\n**Mapping Guidance**:\n- Usage: Allowed-with-Review\n- Rationale: This CWE entry is a Class and might have Base-level children that would be more appropriate\n\n## CWE-190: Integer Overflow or Wraparound\n**Abstraction Level**: Base\n**Similarity Score**: 0.72\n**Source**: dense\n\n**Description**:\nThe product performs a calculation that can\n         produce an integer overflow or wraparound when the logic\n         assumes that the resulting value will always be larger than\n         the original value. This occurs when an integer value is\n         incremented to a value that is too large to store in the\n         associated representation. When this occurs, the value may\n         become a very small or negative number.\n\n**Mapping Guidance**:\n- Usage: Allowed\n- Rationale: This CWE entry is at the Base level of abstraction, which is a preferred level of abstraction for mapping to the root causes of vulnerabilities.\n\n## CWE-362: Concurrent Execution using Shared Resource with Improper Synchronization ('Race Condition')\n**Abstraction Level**: Class\n**Similarity Score**: 0.73\n**Source**: dense\n\n**Description**:\nThe product contains a concurrent code sequence that requires temporary, exclusive access to a shared resource, but a timing window exists in which the shared resource can be modified by another code sequence operating concurrently.\n\n**Mapping Guidance**:\n- Usage: Allowed-with-Review\n- Rationale: This CWE entry is a Class and might have Base-level children that would be more appropriate\n\n## CWE-775: Missing Release of File Descriptor or Handle after Effective Lifetime\n**Abstraction Level**: Base\n**Similarity Score**: 0.73\n**Source**: dense\n\n**Description**:\nThe product does not release a file descriptor or handle after its effective lifetime has ended, i.e., after the file descriptor/handle is no longer needed.\n\n**Mapping Guidance**:\n- Usage: Allowed\n- Rationale: This CWE entry is at the Base level of abstraction, which is a preferred level of abstraction for mapping to the root causes of vulnerabilities.\n\n## CWE-909: Missing Initialization of Resource\n**Abstraction Level**: Class\n**Similarity Score**: 0.73\n**Source**: dense\n\n**Description**:\nThe product does not initialize a critical resource.\n\n**Mapping Guidance**:\n- Usage: Allowed-with-Review\n- Rationale: This CWE entry is a Class and might have Base-level children that would be more appropriate\n\n## CWE-824: Access of Uninitialized Pointer\n**Abstraction Level**: Base\n**Similarity Score**: 0.74\n**Source**: dense\n\n**Description**:\nThe product accesses or uses a pointer that has not been initialized.\n\n**Mapping Guidance**:\n- Usage: Allowed\n- Rationale: This CWE entry is at the Base level of abstraction, which is a preferred level of abstraction for mapping to the root causes of vulnerabilities.",
  "analysis_with_relationships": "# Summary\n\n| CWE ID | CWE Name | Confidence | CWE Abstraction Level | CWE Vulnerability Mapping Label | CWE-Vulnerability Mapping Notes |\n|---|---|---|---|---|---|\n| CWE-911 | Improper Update of Reference Count | 1.0 | Base | Primary | Allowed |\n| CWE-401 | Missing Release of Memory after Effective Lifetime | 0.7 | Class | Secondary | Allowed-with-Review |\n\n## Evidence and Confidence\n\n*   **Confidence Score:** 0.9\n*   **Evidence Strength:** HIGH\n\n## Relationship Analysis\n\nThe primary CWE is CWE-911, which is a Base level CWE. CWE-401 is a Class-level CWE and a parent of CWE-772, Missing Release of Resource after Effective Lifetime, but since the description specifies **reference count**, CWE-911 is a better fit.\n\n```mermaid\ngraph TD\n    cwe911[\"CWE-911: Improper Update of Reference Count\"]\n    cwe401[\"CWE-401: Missing Release of Memory after Effective Lifetime\"]\n    cwe772[\"CWE-772: Missing Release of Resource after Effective Lifetime\"]\n\n    cwe772 -->|CHILDOF| cwe401\n    \n    classDef primary fill:#f96,stroke:#333,stroke-width:2px\n    classDef secondary fill:#69f,stroke:#333\n    classDef tertiary fill:#9e9,stroke:#333\n    class cwe911 primary\n    class cwe401 secondary\n```\n\n## Vulnerability Chain\n\nThe vulnerability chain starts with an **improper update of the reference count** (CWE-911), which leads to a **memory leak**, because the memory is not released after its effective lifetime (CWE-401).\n\n## Summary of Analysis\n\nThe vulnerability description clearly states a **reference count leak** issue in the Linux kernel. The `ax25_dev_device_down()` function **drops the reference count** of `net_device` one or zero times, depending on the execution path. This leads to a **memory leak**.\n\nCWE-911 (Improper Update of Reference Count) is the most appropriate primary CWE, as it directly addresses the **root cause** of the vulnerability. The description explicitly mentions the **improper update of the reference count**, making CWE-911 a precise match. The evidence for this is the vulnerability description and the Keyphrase-Specific CWE Analysis, specifically the WEAKNESS: `reference count leak`.\n\nCWE-401 (Missing Release of Memory after Effective Lifetime) can be considered a secondary CWE. While the vulnerability ultimately results in a memory leak, the **root cause** is the **improper handling of the reference count**. The description clearly states, \"When the ax25 device is shutting down, the ax25_dev_device_down() drops the reference count of net_device one or zero times depending on if we goto unlock_put or not, which will cause **memory leak**\". The evidence for this is the vulnerability description and the Keyphrase-Specific CWE Analysis, specifically the WEAKNESS: `memory leak`.\n\nI am overriding the general mapping guidance to map both the root cause and resulting impact as the relationship is clear in the description.\n\nRelevant CWE Information:\n\n# Enhanced Context (25 CWEs)\nThe following CWEs were identified as potentially relevant to this vulnerability:\n\n## CWE-911: Improper Update of Reference Count\n**Abstraction Level**: Base\n**Similarity Score**: 0.76\n**Source**: dense\n\n**Description**:\nThe product uses a reference count to manage a resource, but it does not update or incorrectly updates the reference count.\n\n**Mapping Guidance**:\n- Usage: Allowed\n- Rationale: This CWE entry is at the Base level of abstraction, which is a preferred level of abstraction for mapping to the root causes of vulnerabilities.\n\n## CWE-401: Missing Release of Memory after Effective Lifetime\n**Abstraction Level**: Class\n**Similarity Score**: 0.72\n**Source**: dense\n\n**Description**:\nThe product does not sufficiently track and release allocated memory after it has been used, which slowly consumes remaining memory....\n\n**Mapping Guidance**:\n- Usage: Allowed-with-Review\n- Rationale: This CWE entry is a Class and might have Base-level children that would be more appropriate\n\n## CWE-190: Integer Overflow or Wraparound\n**Abstraction Level**: Base\n**Similarity Score**: 0.72\n**Source**: dense\n\n**Description**:\nThe product performs a calculation that can\n         produce an integer overflow or wraparound when the logic\n         assumes that the resulting value will always be larger than\n         the original value. This occurs when an integer value is\n         incremented to a value that is too large to store in the\n         associated representation. When this occurs, the value may\n         become a very small or negative number.\n\n**Mapping Guidance**:\n- Usage: Allowed\n- Rationale: This CWE entry is at the Base level of abstraction, which is a preferred level of abstraction for mapping to the root causes of vulnerabilities.\n\n## CWE-362: Concurrent Execution using Shared Resource with Improper Synchronization ('Race Condition')\n**Abstraction Level**: Class\n**Similarity Score**: 0.73\n**Source**: dense\n\n**Description**:\nThe product contains a concurrent code sequence that requires temporary, exclusive access to a shared resource, but a timing window exists in which the shared resource can be modified by another code sequence operating concurrently.\n\n**Mapping Guidance**:\n- Usage: Allowed-with-Review\n- Rationale: This CWE entry is a Class and might have Base-level children that would be more appropriate\n\n## CWE-775: Missing Release of File Descriptor or Handle after Effective Lifetime\n**Abstraction Level**: Base\n**Similarity Score**: 0.73\n**Source**: dense\n\n**Description**:\nThe product does not release a file descriptor or handle after its effective lifetime has ended, i.e., after the file descriptor/handle is no longer needed.\n\n**Mapping Guidance**:\n- Usage: Allowed\n- Rationale: This CWE entry is at the Base level of abstraction, which is a preferred level of abstraction for mapping to the root causes of vulnerabilities.\n\n## CWE-909: Missing Initialization of Resource\n**Abstraction Level**: Class\n**Similarity Score**: 0.73\n**Source**: dense\n\n**Description**:\nThe product does not initialize a critical resource.\n\n**Mapping Guidance**:\n- Usage: Allowed-with-Review\n- Rationale: This CWE entry is a Class and might have Base-level children that would be more appropriate\n\n## CWE-824: Access of Uninitialized Pointer\n**Abstraction Level**: Base\n**Similarity Score**: 0.74\n**Source**: dense\n\n**Description**:\nThe product accesses or uses a pointer that has not been initialized.\n\n**Mapping Guidance**:\n- Usage: Allowed\n- Rationale: This CWE entry is at the Base level of abstraction, which is a preferred level of abstraction for mapping to the root causes of vulnerabilities.\n\n\n## CWE Relationship Analysis\n\nCurrent CWEs represent these abstraction levels: .\n\n\n### Vulnerability Chain Analysis\n\n**Chain starting from CWE-911:**\n- 911 (Improper Update of Reference Count) - ROOT\n\n\n**Chain starting from CWE-775:**\n- 775 (Missing Release of File Descriptor or Handle after Effective Lifetime) - ROOT\n\n\n\n### CWE Relationship Diagram\n\n```mermaid\ngraph TD\n    classDef primary fill:#f96,stroke:#333,stroke-width:2px\n    classDef secondary fill:#69f,stroke:#333\n    classDef tertiary fill:#9e9,stroke:#333\n```",
  "criticism": "",
  "resolution": "",
  "relevant_cwes": [
    {
      "metadata": {
        "doc_id": "911",
        "name": "Improper Update of Reference Count",
        "source": "sparse",
        "original_content": "The product uses a reference count to manage a resource, but it does not update or incorrectly updates the reference count.",
        "keyphrase_sources": [
          {
            "id": "weakness:memory leak",
            "keyphrase": "memory leak",
            "type": "weakness"
          },
          {
            "id": "weakness:reference count leak",
            "keyphrase": "reference count leak",
            "type": "weakness"
          },
          {
            "id": "product:Linux kernel",
            "keyphrase": "Linux kernel",
            "type": "product"
          },
          {
            "id": "component:ax25_dev_device_down()",
            "keyphrase": "ax25_dev_device_down()",
            "type": "component"
          }
        ]
      },
      "similarity": 578.9753102984918
    },
    {
      "metadata": {
        "doc_id": "401",
        "name": "Missing Release of Memory after Effective Lifetime",
        "source": "sparse",
        "original_content": "The product does not sufficiently track and release allocated memory after it has been used, which slowly consumes remaining memory.",
        "keyphrase_sources": [
          {
            "id": "weakness:memory leak",
            "keyphrase": "memory leak",
            "type": "weakness"
          },
          {
            "id": "weakness:reference count leak",
            "keyphrase": "reference count leak",
            "type": "weakness"
          },
          {
            "id": "product:Linux kernel",
            "keyphrase": "Linux kernel",
            "type": "product"
          },
          {
            "id": "component:ax25_dev_device_down()",
            "keyphrase": "ax25_dev_device_down()",
            "type": "component"
          }
        ]
      },
      "similarity": 468.0627957372682
    },
    {
      "metadata": {
        "doc_id": "190",
        "name": "Integer Overflow or Wraparound",
        "source": "sparse",
        "original_content": "The product performs a calculation that can\n         produce an integer overflow or wraparound when the logic\n         assumes that the resulting value will always be larger than\n         the original value. This occurs when an integer value is\n         incremented to a value that is too large to store in the\n         associated representation. When this occurs, the value may\n         become a very small or negative number.",
        "keyphrase_sources": [
          {
            "id": "weakness:memory leak",
            "keyphrase": "memory leak",
            "type": "weakness"
          },
          {
            "id": "weakness:reference count leak",
            "keyphrase": "reference count leak",
            "type": "weakness"
          },
          {
            "id": "product:Linux kernel",
            "keyphrase": "Linux kernel",
            "type": "product"
          },
          {
            "id": "component:ax25_dev_device_down()",
            "keyphrase": "ax25_dev_device_down()",
            "type": "component"
          }
        ]
      },
      "similarity": 444.17213554965423
    },
    {
      "metadata": {
        "doc_id": "362",
        "name": "Concurrent Execution using Shared Resource with Improper Synchronization ('Race Condition')",
        "source": "sparse",
        "original_content": "The product contains a concurrent code sequence that requires temporary, exclusive access to a shared resource, but a timing window exists in which the shared resource can be modified by another code sequence operating concurrently.",
        "keyphrase_sources": [
          {
            "id": "weakness:memory leak",
            "keyphrase": "memory leak",
            "type": "weakness"
          },
          {
            "id": "weakness:reference count leak",
            "keyphrase": "reference count leak",
            "type": "weakness"
          },
          {
            "id": "product:Linux kernel",
            "keyphrase": "Linux kernel",
            "type": "product"
          },
          {
            "id": "component:ax25_dev_device_down()",
            "keyphrase": "ax25_dev_device_down()",
            "type": "component"
          }
        ]
      },
      "similarity": 439.0037736393269
    },
    {
      "metadata": {
        "doc_id": "775",
        "name": "Missing Release of File Descriptor or Handle after Effective Lifetime",
        "source": "sparse",
        "original_content": "The product does not release a file descriptor or handle after its effective lifetime has ended, i.e., after the file descriptor/handle is no longer needed.",
        "keyphrase_sources": [
          {
            "id": "weakness:reference count leak",
            "keyphrase": "reference count leak",
            "type": "weakness"
          }
        ]
      },
      "similarity": 434.81503634168666
    },
    {
      "metadata": {
        "doc_id": "909",
        "name": "Missing Initialization of Resource",
        "source": "sparse",
        "original_content": "The product does not initialize a critical resource.",
        "keyphrase_sources": [
          {
            "id": "weakness:memory leak",
            "keyphrase": "memory leak",
            "type": "weakness"
          },
          {
            "id": "product:Linux kernel",
            "keyphrase": "Linux kernel",
            "type": "product"
          }
        ]
      },
      "similarity": 425.2696855584396
    },
    {
      "metadata": {
        "doc_id": "824",
        "name": "Access of Uninitialized Pointer",
        "source": "sparse",
        "original_content": "The product accesses or uses a pointer that has not been initialized.",
        "keyphrase_sources": [
          {
            "id": "component:ax25_dev_device_down()",
            "keyphrase": "ax25_dev_device_down()",
            "type": "component"
          }
        ]
      },
      "similarity": 142.8343084440436
    }
  ],
  "identified_cwes": {
    "analyzer": [
      "CWE-911",
      "CWE-775",
      "CWE-401",
      "CWE-909",
      "CWE-190",
      "CWE-362",
      "CWE-824",
      "CWE-772"
    ],
    "critic_additional": []
  },
  "keyphrase_cwe_mapping": {
    "911": [
      {
        "id": "weakness:memory leak",
        "keyphrase": "memory leak",
        "type": "weakness"
      },
      {
        "id": "weakness:reference count leak",
        "keyphrase": "reference count leak",
        "type": "weakness"
      },
      {
        "id": "product:Linux kernel",
        "keyphrase": "Linux kernel",
        "type": "product"
      },
      {
        "id": "component:ax25_dev_device_down()",
        "keyphrase": "ax25_dev_device_down()",
        "type": "component"
      }
    ],
    "401": [
      {
        "id": "weakness:memory leak",
        "keyphrase": "memory leak",
        "type": "weakness"
      },
      {
        "id": "weakness:reference count leak",
        "keyphrase": "reference count leak",
        "type": "weakness"
      },
      {
        "id": "product:Linux kernel",
        "keyphrase": "Linux kernel",
        "type": "product"
      },
      {
        "id": "component:ax25_dev_device_down()",
        "keyphrase": "ax25_dev_device_down()",
        "type": "component"
      }
    ],
    "190": [
      {
        "id": "weakness:memory leak",
        "keyphrase": "memory leak",
        "type": "weakness"
      },
      {
        "id": "weakness:reference count leak",
        "keyphrase": "reference count leak",
        "type": "weakness"
      },
      {
        "id": "product:Linux kernel",
        "keyphrase": "Linux kernel",
        "type": "product"
      },
      {
        "id": "component:ax25_dev_device_down()",
        "keyphrase": "ax25_dev_device_down()",
        "type": "component"
      }
    ],
    "362": [
      {
        "id": "weakness:memory leak",
        "keyphrase": "memory leak",
        "type": "weakness"
      },
      {
        "id": "weakness:reference count leak",
        "keyphrase": "reference count leak",
        "type": "weakness"
      },
      {
        "id": "product:Linux kernel",
        "keyphrase": "Linux kernel",
        "type": "product"
      },
      {
        "id": "component:ax25_dev_device_down()",
        "keyphrase": "ax25_dev_device_down()",
        "type": "component"
      }
    ],
    "909": [
      {
        "id": "weakness:memory leak",
        "keyphrase": "memory leak",
        "type": "weakness"
      },
      {
        "id": "product:Linux kernel",
        "keyphrase": "Linux kernel",
        "type": "product"
      }
    ],
    "775": [
      {
        "id": "weakness:reference count leak",
        "keyphrase": "reference count leak",
        "type": "weakness"
      }
    ],
    "824": [
      {
        "id": "component:ax25_dev_device_down()",
        "keyphrase": "ax25_dev_device_down()",
        "type": "component"
      }
    ]
  }
}