{
  "vulnerability_info": "VulnerabilityInfo(cve_id='CVE-2025-31399', description='Cross-Site Request Forgery (CSRF) vulnerability in Chandan Garg CG Scroll To Top allows Stored **XSS**. This issue affects CG Scroll To Top from n/a through 3.5.', key_phrases={'rootcause': 'lack of CSRF protection', 'weakness': ['Cross-Site Scripting', 'XSS'], 'impact': '', 'vector': '', 'attacker': '', 'product': 'Chandan Garg CG Scroll To Top', 'version': 'n/a through 3.5', 'component': ''}, reference_content='Root cause of vulnerability:\\nCross Site Request Forgery (CSRF) vulnerability.\\n\\nWeaknesses/vulnerabilities present:\\nCSRF allows a malicious actor to force higher privileged users to execute unwanted actions under their current authentication.\\n\\nImpact of exploitation:\\nA malicious actor can force higher privileged users to execute unwanted actions. The specific impact varies case by case.\\n\\nAttack vectors:\\nNot specified in the content.\\n\\nRequired attacker capabilities/position:\\nUnauthenticated.\\n\\nMitigation or fix:\\nNo official fix available. Patchstack vPatching can auto-mitigate the vulnerability.\\n\\nAdditional details:\\n- CVSS score: 7.1 (Low severity)\\n- OWASP Top 10: A5: Broken Access Control\\n- Vulnerable versions: <= 3.5\\n- Plugin: CG Scroll To Top\\n- Reported by: johska\\n- Published by Patchstack: 09 April 2025', similar_info={'cwe_distribution': {}, 'cwe_consensus': '', 'similarity_stats': {'thresholds': [], 'total_samples_by_threshold': {}, 'top_cwes_by_threshold': {}}}, similarity_summary=SimilarityInsight(consensus_cwe='', top_cwes=[], confidence_levels={}, total_samples=0), analysis='', analysis_with_relationships='', criticism='', resolution='', relevant_cwes=[{'metadata': {'doc_id': '352', 'name': 'Cross-Site Request Forgery (CSRF)', 'source': 'sparse', 'original_content': 'The web application does not, or can not, sufficiently verify whether a well-formed, valid, consistent request was intentionally provided by the user who submitted the request.', 'keyphrase_sources': [{'id': 'rootcause:lack of CSRF protection', 'keyphrase': 'lack of CSRF protection', 'type': 'rootcause'}, {'id': 'weakness:Cross-Site Scripting', 'keyphrase': 'Cross-Site Scripting', 'type': 'weakness'}, {'id': 'weakness:XSS', 'keyphrase': 'XSS', 'type': 'weakness'}, {'id': 'product:Chandan Garg CG Scroll To Top', 'keyphrase': 'Chandan Garg CG Scroll To Top', 'type': 'product'}, {'id': 'version:n/a through 3.5', 'keyphrase': 'n/a through 3.5', 'type': 'version'}]}, 'similarity': np.float64(316.0067962775897)}, {'metadata': {'doc_id': '434', 'name': 'Unrestricted Upload of File with Dangerous Type', 'source': 'sparse', 'original_content': 'The product allows the upload or transfer of dangerous file types that are automatically processed within its environment.', 'keyphrase_sources': [{'id': 'rootcause:lack of CSRF protection', 'keyphrase': 'lack of CSRF protection', 'type': 'rootcause'}, {'id': 'version:n/a through 3.5', 'keyphrase': 'n/a through 3.5', 'type': 'version'}]}, 'similarity': np.float64(227.1322135453874)}, {'metadata': {'doc_id': '116', 'name': 'Improper Encoding or Escaping of Output', 'source': 'sparse', 'original_content': 'The product prepares a structured message for communication with another component, but encoding or escaping of the data is either missing or done incorrectly. As a result, the intended structure of the message is not preserved.', 'keyphrase_sources': [{'id': 'rootcause:lack of CSRF protection', 'keyphrase': 'lack of CSRF protection', 'type': 'rootcause'}, {'id': 'weakness:Cross-Site Scripting', 'keyphrase': 'Cross-Site Scripting', 'type': 'weakness'}, {'id': 'weakness:XSS', 'keyphrase': 'XSS', 'type': 'weakness'}, {'id': 'product:Chandan Garg CG Scroll To Top', 'keyphrase': 'Chandan Garg CG Scroll To Top', 'type': 'product'}]}, 'similarity': np.float64(224.59156572449848)}, {'metadata': {'doc_id': '80', 'name': 'Improper Neutralization of Script-Related HTML Tags in a Web Page (Basic XSS)', 'source': 'sparse', 'original_content': 'The product receives input from an upstream component, but it does not neutralize or incorrectly neutralizes special characters such as \"<\", \">\", and \"&\" that could be interpreted as web-scripting elements when they are sent to a downstream component that processes web pages.', 'keyphrase_sources': [{'id': 'weakness:Cross-Site Scripting', 'keyphrase': 'Cross-Site Scripting', 'type': 'weakness'}]}, 'similarity': np.float64(217.4729039106975)}, {'metadata': {'doc_id': '79', 'name': \"Improper Neutralization of Input During Web Page Generation ('Cross-site Scripting')\", 'source': 'sparse', 'original_content': 'The product does not neutralize or incorrectly neutralizes user-controllable input before it is placed in output that is used as a web page that is served to other users.', 'keyphrase_sources': [{'id': 'rootcause:lack of CSRF protection', 'keyphrase': 'lack of CSRF protection', 'type': 'rootcause'}, {'id': 'weakness:Cross-Site Scripting', 'keyphrase': 'Cross-Site Scripting', 'type': 'weakness'}, {'id': 'weakness:XSS', 'keyphrase': 'XSS', 'type': 'weakness'}, {'id': 'product:Chandan Garg CG Scroll To Top', 'keyphrase': 'Chandan Garg CG Scroll To Top', 'type': 'product'}, {'id': 'version:n/a through 3.5', 'keyphrase': 'n/a through 3.5', 'type': 'version'}]}, 'similarity': np.float64(213.5290433984859)}, {'metadata': {'doc_id': '1004', 'name': \"Sensitive Cookie Without 'HttpOnly' Flag\", 'source': 'sparse', 'original_content': 'The product uses a cookie to store sensitive information, but the cookie is not marked with the HttpOnly flag.', 'keyphrase_sources': [{'id': 'rootcause:lack of CSRF protection', 'keyphrase': 'lack of CSRF protection', 'type': 'rootcause'}, {'id': 'weakness:Cross-Site Scripting', 'keyphrase': 'Cross-Site Scripting', 'type': 'weakness'}, {'id': 'weakness:XSS', 'keyphrase': 'XSS', 'type': 'weakness'}]}, 'similarity': np.float64(205.93727124441548)}, {'metadata': {'doc_id': '918', 'name': 'Server-Side Request Forgery (SSRF)', 'source': 'sparse', 'original_content': 'The web server receives a URL or similar request from an upstream component and retrieves the contents of this URL, but it does not sufficiently ensure that the request is being sent to the expected destination.', 'keyphrase_sources': [{'id': 'weakness:XSS', 'keyphrase': 'XSS', 'type': 'weakness'}]}, 'similarity': np.float64(163.750366822664)}, {'metadata': {'doc_id': '22', 'name': \"Improper Limitation of a Pathname to a Restricted Directory ('Path Traversal')\", 'source': 'sparse', 'original_content': 'The product uses external input to construct a pathname that is intended to identify a file or directory that is located underneath a restricted parent directory, but the product does not properly neutralize special elements within the pathname that can cause the pathname to resolve to a location that is outside of the restricted directory.', 'keyphrase_sources': [{'id': 'version:n/a through 3.5', 'keyphrase': 'n/a through 3.5', 'type': 'version'}]}, 'similarity': np.float64(68.83897229867003)}, {'metadata': {'doc_id': '611', 'name': 'Improper Restriction of XML External Entity Reference', 'source': 'sparse', 'original_content': 'The product processes an XML document that can contain XML entities with URIs that resolve to documents outside of the intended sphere of control, causing the product to embed incorrect documents into its output.', 'keyphrase_sources': [{'id': 'version:n/a through 3.5', 'keyphrase': 'n/a through 3.5', 'type': 'version'}]}, 'similarity': np.float64(68.72314712289672)}, {'metadata': {'doc_id': '259', 'name': 'Use of Hard-coded Password', 'source': 'sparse', 'original_content': 'The product contains a hard-coded password, which it uses for its own inbound authentication or for outbound communication to external components.', 'keyphrase_sources': [{'id': 'product:Chandan Garg CG Scroll To Top', 'keyphrase': 'Chandan Garg CG Scroll To Top', 'type': 'product'}]}, 'similarity': np.float64(64.85920201704103)}, {'metadata': {'doc_id': '24', 'name': \"Path Traversal: '../filedir'\", 'source': 'sparse', 'original_content': 'The product uses external input to construct a pathname that should be within a restricted directory, but it does not properly neutralize \"../\" sequences that can resolve to a location that is outside of that directory.', 'keyphrase_sources': [{'id': 'product:Chandan Garg CG Scroll To Top', 'keyphrase': 'Chandan Garg CG Scroll To Top', 'type': 'product'}]}, 'similarity': np.float64(64.81177866554567)}], identified_cwes={'analyzer': [], 'critic_additional': []})",
  "retrieval_results": {
    "has_multiple_keyphrases": true,
    "keyphrase_cwe_sets": {
      "rootcause:lack of CSRF protection": {
        "keyphrase": "lack of CSRF protection",
        "type": "rootcause",
        "cwes": [
          {
            "metadata": {
              "doc_id": "352",
              "name": "Cross-Site Request Forgery (CSRF)",
              "source": "sparse",
              "original_content": "The web application does not, or can not, sufficiently verify whether a well-formed, valid, consistent request was intentionally provided by the user who submitted the request.",
              "keyphrase_sources": [
                {
                  "id": "rootcause:lack of CSRF protection",
                  "keyphrase": "lack of CSRF protection",
                  "type": "rootcause"
                },
                {
                  "id": "weakness:Cross-Site Scripting",
                  "keyphrase": "Cross-Site Scripting",
                  "type": "weakness"
                },
                {
                  "id": "weakness:XSS",
                  "keyphrase": "XSS",
                  "type": "weakness"
                },
                {
                  "id": "product:Chandan Garg CG Scroll To Top",
                  "keyphrase": "Chandan Garg CG Scroll To Top",
                  "type": "product"
                },
                {
                  "id": "version:n/a through 3.5",
                  "keyphrase": "n/a through 3.5",
                  "type": "version"
                }
              ]
            },
            "similarity": 316.0067962775897
          },
          {
            "metadata": {
              "doc_id": "434",
              "name": "Unrestricted Upload of File with Dangerous Type",
              "source": "sparse",
              "original_content": "The product allows the upload or transfer of dangerous file types that are automatically processed within its environment.",
              "keyphrase_sources": [
                {
                  "id": "rootcause:lack of CSRF protection",
                  "keyphrase": "lack of CSRF protection",
                  "type": "rootcause"
                },
                {
                  "id": "version:n/a through 3.5",
                  "keyphrase": "n/a through 3.5",
                  "type": "version"
                }
              ]
            },
            "similarity": 227.1322135453874
          },
          {
            "metadata": {
              "doc_id": "116",
              "name": "Improper Encoding or Escaping of Output",
              "source": "sparse",
              "original_content": "The product prepares a structured message for communication with another component, but encoding or escaping of the data is either missing or done incorrectly. As a result, the intended structure of the message is not preserved.",
              "keyphrase_sources": [
                {
                  "id": "rootcause:lack of CSRF protection",
                  "keyphrase": "lack of CSRF protection",
                  "type": "rootcause"
                },
                {
                  "id": "weakness:Cross-Site Scripting",
                  "keyphrase": "Cross-Site Scripting",
                  "type": "weakness"
                },
                {
                  "id": "weakness:XSS",
                  "keyphrase": "XSS",
                  "type": "weakness"
                },
                {
                  "id": "product:Chandan Garg CG Scroll To Top",
                  "keyphrase": "Chandan Garg CG Scroll To Top",
                  "type": "product"
                }
              ]
            },
            "similarity": 224.59156572449848
          },
          {
            "metadata": {
              "doc_id": "79",
              "name": "Improper Neutralization of Input During Web Page Generation ('Cross-site Scripting')",
              "source": "sparse",
              "original_content": "The product does not neutralize or incorrectly neutralizes user-controllable input before it is placed in output that is used as a web page that is served to other users.",
              "keyphrase_sources": [
                {
                  "id": "rootcause:lack of CSRF protection",
                  "keyphrase": "lack of CSRF protection",
                  "type": "rootcause"
                },
                {
                  "id": "weakness:Cross-Site Scripting",
                  "keyphrase": "Cross-Site Scripting",
                  "type": "weakness"
                },
                {
                  "id": "weakness:XSS",
                  "keyphrase": "XSS",
                  "type": "weakness"
                },
                {
                  "id": "product:Chandan Garg CG Scroll To Top",
                  "keyphrase": "Chandan Garg CG Scroll To Top",
                  "type": "product"
                },
                {
                  "id": "version:n/a through 3.5",
                  "keyphrase": "n/a through 3.5",
                  "type": "version"
                }
              ]
            },
            "similarity": 213.5290433984859
          },
          {
            "metadata": {
              "doc_id": "1004",
              "name": "Sensitive Cookie Without 'HttpOnly' Flag",
              "source": "sparse",
              "original_content": "The product uses a cookie to store sensitive information, but the cookie is not marked with the HttpOnly flag.",
              "keyphrase_sources": [
                {
                  "id": "rootcause:lack of CSRF protection",
                  "keyphrase": "lack of CSRF protection",
                  "type": "rootcause"
                },
                {
                  "id": "weakness:Cross-Site Scripting",
                  "keyphrase": "Cross-Site Scripting",
                  "type": "weakness"
                },
                {
                  "id": "weakness:XSS",
                  "keyphrase": "XSS",
                  "type": "weakness"
                }
              ]
            },
            "similarity": 205.93727124441548
          }
        ]
      },
      "weakness:Cross-Site Scripting": {
        "keyphrase": "Cross-Site Scripting",
        "type": "weakness",
        "cwes": [
          {
            "metadata": {
              "doc_id": "352",
              "name": "Cross-Site Request Forgery (CSRF)",
              "source": "sparse",
              "original_content": "The web application does not, or can not, sufficiently verify whether a well-formed, valid, consistent request was intentionally provided by the user who submitted the request."
            },
            "similarity": 290.7212662445059
          },
          {
            "metadata": {
              "doc_id": "79",
              "name": "Improper Neutralization of Input During Web Page Generation ('Cross-site Scripting')",
              "source": "sparse",
              "original_content": "The product does not neutralize or incorrectly neutralizes user-controllable input before it is placed in output that is used as a web page that is served to other users."
            },
            "similarity": 243.02095652911422
          },
          {
            "metadata": {
              "doc_id": "80",
              "name": "Improper Neutralization of Script-Related HTML Tags in a Web Page (Basic XSS)",
              "source": "sparse",
              "original_content": "The product receives input from an upstream component, but it does not neutralize or incorrectly neutralizes special characters such as \"<\", \">\", and \"&\" that could be interpreted as web-scripting elements when they are sent to a downstream component that processes web pages.",
              "keyphrase_sources": [
                {
                  "id": "weakness:Cross-Site Scripting",
                  "keyphrase": "Cross-Site Scripting",
                  "type": "weakness"
                }
              ]
            },
            "similarity": 217.4729039106975
          },
          {
            "metadata": {
              "doc_id": "116",
              "name": "Improper Encoding or Escaping of Output",
              "source": "sparse",
              "original_content": "The product prepares a structured message for communication with another component, but encoding or escaping of the data is either missing or done incorrectly. As a result, the intended structure of the message is not preserved."
            },
            "similarity": 216.22573697463983
          },
          {
            "metadata": {
              "doc_id": "1004",
              "name": "Sensitive Cookie Without 'HttpOnly' Flag",
              "source": "sparse",
              "original_content": "The product uses a cookie to store sensitive information, but the cookie is not marked with the HttpOnly flag."
            },
            "similarity": 215.65801586238376
          }
        ]
      },
      "weakness:XSS": {
        "keyphrase": "XSS",
        "type": "weakness",
        "cwes": [
          {
            "metadata": {
              "doc_id": "352",
              "name": "Cross-Site Request Forgery (CSRF)",
              "source": "sparse",
              "original_content": "The web application does not, or can not, sufficiently verify whether a well-formed, valid, consistent request was intentionally provided by the user who submitted the request."
            },
            "similarity": 222.69812096836995
          },
          {
            "metadata": {
              "doc_id": "79",
              "name": "Improper Neutralization of Input During Web Page Generation ('Cross-site Scripting')",
              "source": "sparse",
              "original_content": "The product does not neutralize or incorrectly neutralizes user-controllable input before it is placed in output that is used as a web page that is served to other users."
            },
            "similarity": 181.05616517222808
          },
          {
            "metadata": {
              "doc_id": "1004",
              "name": "Sensitive Cookie Without 'HttpOnly' Flag",
              "source": "sparse",
              "original_content": "The product uses a cookie to store sensitive information, but the cookie is not marked with the HttpOnly flag."
            },
            "similarity": 171.106239116239
          },
          {
            "metadata": {
              "doc_id": "116",
              "name": "Improper Encoding or Escaping of Output",
              "source": "sparse",
              "original_content": "The product prepares a structured message for communication with another component, but encoding or escaping of the data is either missing or done incorrectly. As a result, the intended structure of the message is not preserved."
            },
            "similarity": 169.05550909047938
          },
          {
            "metadata": {
              "doc_id": "918",
              "name": "Server-Side Request Forgery (SSRF)",
              "source": "sparse",
              "original_content": "The web server receives a URL or similar request from an upstream component and retrieves the contents of this URL, but it does not sufficiently ensure that the request is being sent to the expected destination.",
              "keyphrase_sources": [
                {
                  "id": "weakness:XSS",
                  "keyphrase": "XSS",
                  "type": "weakness"
                }
              ]
            },
            "similarity": 163.750366822664
          }
        ]
      },
      "product:Chandan Garg CG Scroll To Top": {
        "keyphrase": "Chandan Garg CG Scroll To Top",
        "type": "product",
        "cwes": [
          {
            "metadata": {
              "doc_id": "352",
              "name": "Cross-Site Request Forgery (CSRF)",
              "source": "sparse",
              "original_content": "The web application does not, or can not, sufficiently verify whether a well-formed, valid, consistent request was intentionally provided by the user who submitted the request."
            },
            "similarity": 84.8466049375838
          },
          {
            "metadata": {
              "doc_id": "259",
              "name": "Use of Hard-coded Password",
              "source": "sparse",
              "original_content": "The product contains a hard-coded password, which it uses for its own inbound authentication or for outbound communication to external components.",
              "keyphrase_sources": [
                {
                  "id": "product:Chandan Garg CG Scroll To Top",
                  "keyphrase": "Chandan Garg CG Scroll To Top",
                  "type": "product"
                }
              ]
            },
            "similarity": 64.85920201704103
          },
          {
            "metadata": {
              "doc_id": "24",
              "name": "Path Traversal: '../filedir'",
              "source": "sparse",
              "original_content": "The product uses external input to construct a pathname that should be within a restricted directory, but it does not properly neutralize \"../\" sequences that can resolve to a location that is outside of that directory.",
              "keyphrase_sources": [
                {
                  "id": "product:Chandan Garg CG Scroll To Top",
                  "keyphrase": "Chandan Garg CG Scroll To Top",
                  "type": "product"
                }
              ]
            },
            "similarity": 64.81177866554567
          },
          {
            "metadata": {
              "doc_id": "79",
              "name": "Improper Neutralization of Input During Web Page Generation ('Cross-site Scripting')",
              "source": "sparse",
              "original_content": "The product does not neutralize or incorrectly neutralizes user-controllable input before it is placed in output that is used as a web page that is served to other users."
            },
            "similarity": 62.15917401176086
          },
          {
            "metadata": {
              "doc_id": "116",
              "name": "Improper Encoding or Escaping of Output",
              "source": "sparse",
              "original_content": "The product prepares a structured message for communication with another component, but encoding or escaping of the data is either missing or done incorrectly. As a result, the intended structure of the message is not preserved."
            },
            "similarity": 62.128066927061596
          }
        ]
      },
      "version:n/a through 3.5": {
        "keyphrase": "n/a through 3.5",
        "type": "version",
        "cwes": [
          {
            "metadata": {
              "doc_id": "352",
              "name": "Cross-Site Request Forgery (CSRF)",
              "source": "sparse",
              "original_content": "The web application does not, or can not, sufficiently verify whether a well-formed, valid, consistent request was intentionally provided by the user who submitted the request."
            },
            "similarity": 86.44105554401943
          },
          {
            "metadata": {
              "doc_id": "434",
              "name": "Unrestricted Upload of File with Dangerous Type",
              "source": "sparse",
              "original_content": "The product allows the upload or transfer of dangerous file types that are automatically processed within its environment."
            },
            "similarity": 71.13725789070415
          },
          {
            "metadata": {
              "doc_id": "79",
              "name": "Improper Neutralization of Input During Web Page Generation ('Cross-site Scripting')",
              "source": "sparse",
              "original_content": "The product does not neutralize or incorrectly neutralizes user-controllable input before it is placed in output that is used as a web page that is served to other users."
            },
            "similarity": 69.34568937646526
          },
          {
            "metadata": {
              "doc_id": "22",
              "name": "Improper Limitation of a Pathname to a Restricted Directory ('Path Traversal')",
              "source": "sparse",
              "original_content": "The product uses external input to construct a pathname that is intended to identify a file or directory that is located underneath a restricted parent directory, but the product does not properly neutralize special elements within the pathname that can cause the pathname to resolve to a location that is outside of the restricted directory.",
              "keyphrase_sources": [
                {
                  "id": "version:n/a through 3.5",
                  "keyphrase": "n/a through 3.5",
                  "type": "version"
                }
              ]
            },
            "similarity": 68.83897229867003
          },
          {
            "metadata": {
              "doc_id": "611",
              "name": "Improper Restriction of XML External Entity Reference",
              "source": "sparse",
              "original_content": "The product processes an XML document that can contain XML entities with URIs that resolve to documents outside of the intended sphere of control, causing the product to embed incorrect documents into its output.",
              "keyphrase_sources": [
                {
                  "id": "version:n/a through 3.5",
                  "keyphrase": "n/a through 3.5",
                  "type": "version"
                }
              ]
            },
            "similarity": 68.72314712289672
          }
        ]
      }
    },
    "keyphrase_mapping": {
      "352": [
        {
          "id": "rootcause:lack of CSRF protection",
          "keyphrase": "lack of CSRF protection",
          "type": "rootcause"
        },
        {
          "id": "weakness:Cross-Site Scripting",
          "keyphrase": "Cross-Site Scripting",
          "type": "weakness"
        },
        {
          "id": "weakness:XSS",
          "keyphrase": "XSS",
          "type": "weakness"
        },
        {
          "id": "product:Chandan Garg CG Scroll To Top",
          "keyphrase": "Chandan Garg CG Scroll To Top",
          "type": "product"
        },
        {
          "id": "version:n/a through 3.5",
          "keyphrase": "n/a through 3.5",
          "type": "version"
        }
      ],
      "434": [
        {
          "id": "rootcause:lack of CSRF protection",
          "keyphrase": "lack of CSRF protection",
          "type": "rootcause"
        },
        {
          "id": "version:n/a through 3.5",
          "keyphrase": "n/a through 3.5",
          "type": "version"
        }
      ],
      "116": [
        {
          "id": "rootcause:lack of CSRF protection",
          "keyphrase": "lack of CSRF protection",
          "type": "rootcause"
        },
        {
          "id": "weakness:Cross-Site Scripting",
          "keyphrase": "Cross-Site Scripting",
          "type": "weakness"
        },
        {
          "id": "weakness:XSS",
          "keyphrase": "XSS",
          "type": "weakness"
        },
        {
          "id": "product:Chandan Garg CG Scroll To Top",
          "keyphrase": "Chandan Garg CG Scroll To Top",
          "type": "product"
        }
      ],
      "79": [
        {
          "id": "rootcause:lack of CSRF protection",
          "keyphrase": "lack of CSRF protection",
          "type": "rootcause"
        },
        {
          "id": "weakness:Cross-Site Scripting",
          "keyphrase": "Cross-Site Scripting",
          "type": "weakness"
        },
        {
          "id": "weakness:XSS",
          "keyphrase": "XSS",
          "type": "weakness"
        },
        {
          "id": "product:Chandan Garg CG Scroll To Top",
          "keyphrase": "Chandan Garg CG Scroll To Top",
          "type": "product"
        },
        {
          "id": "version:n/a through 3.5",
          "keyphrase": "n/a through 3.5",
          "type": "version"
        }
      ],
      "1004": [
        {
          "id": "rootcause:lack of CSRF protection",
          "keyphrase": "lack of CSRF protection",
          "type": "rootcause"
        },
        {
          "id": "weakness:Cross-Site Scripting",
          "keyphrase": "Cross-Site Scripting",
          "type": "weakness"
        },
        {
          "id": "weakness:XSS",
          "keyphrase": "XSS",
          "type": "weakness"
        }
      ],
      "80": [
        {
          "id": "weakness:Cross-Site Scripting",
          "keyphrase": "Cross-Site Scripting",
          "type": "weakness"
        }
      ],
      "918": [
        {
          "id": "weakness:XSS",
          "keyphrase": "XSS",
          "type": "weakness"
        }
      ],
      "259": [
        {
          "id": "product:Chandan Garg CG Scroll To Top",
          "keyphrase": "Chandan Garg CG Scroll To Top",
          "type": "product"
        }
      ],
      "24": [
        {
          "id": "product:Chandan Garg CG Scroll To Top",
          "keyphrase": "Chandan Garg CG Scroll To Top",
          "type": "product"
        }
      ],
      "22": [
        {
          "id": "version:n/a through 3.5",
          "keyphrase": "n/a through 3.5",
          "type": "version"
        }
      ],
      "611": [
        {
          "id": "version:n/a through 3.5",
          "keyphrase": "n/a through 3.5",
          "type": "version"
        }
      ]
    },
    "relevant_cwes": [
      {
        "metadata": {
          "doc_id": "352",
          "name": "Cross-Site Request Forgery (CSRF)",
          "source": "sparse",
          "original_content": "The web application does not, or can not, sufficiently verify whether a well-formed, valid, consistent request was intentionally provided by the user who submitted the request.",
          "keyphrase_sources": [
            {
              "id": "rootcause:lack of CSRF protection",
              "keyphrase": "lack of CSRF protection",
              "type": "rootcause"
            },
            {
              "id": "weakness:Cross-Site Scripting",
              "keyphrase": "Cross-Site Scripting",
              "type": "weakness"
            },
            {
              "id": "weakness:XSS",
              "keyphrase": "XSS",
              "type": "weakness"
            },
            {
              "id": "product:Chandan Garg CG Scroll To Top",
              "keyphrase": "Chandan Garg CG Scroll To Top",
              "type": "product"
            },
            {
              "id": "version:n/a through 3.5",
              "keyphrase": "n/a through 3.5",
              "type": "version"
            }
          ]
        },
        "similarity": 316.0067962775897
      },
      {
        "metadata": {
          "doc_id": "434",
          "name": "Unrestricted Upload of File with Dangerous Type",
          "source": "sparse",
          "original_content": "The product allows the upload or transfer of dangerous file types that are automatically processed within its environment.",
          "keyphrase_sources": [
            {
              "id": "rootcause:lack of CSRF protection",
              "keyphrase": "lack of CSRF protection",
              "type": "rootcause"
            },
            {
              "id": "version:n/a through 3.5",
              "keyphrase": "n/a through 3.5",
              "type": "version"
            }
          ]
        },
        "similarity": 227.1322135453874
      },
      {
        "metadata": {
          "doc_id": "116",
          "name": "Improper Encoding or Escaping of Output",
          "source": "sparse",
          "original_content": "The product prepares a structured message for communication with another component, but encoding or escaping of the data is either missing or done incorrectly. As a result, the intended structure of the message is not preserved.",
          "keyphrase_sources": [
            {
              "id": "rootcause:lack of CSRF protection",
              "keyphrase": "lack of CSRF protection",
              "type": "rootcause"
            },
            {
              "id": "weakness:Cross-Site Scripting",
              "keyphrase": "Cross-Site Scripting",
              "type": "weakness"
            },
            {
              "id": "weakness:XSS",
              "keyphrase": "XSS",
              "type": "weakness"
            },
            {
              "id": "product:Chandan Garg CG Scroll To Top",
              "keyphrase": "Chandan Garg CG Scroll To Top",
              "type": "product"
            }
          ]
        },
        "similarity": 224.59156572449848
      },
      {
        "metadata": {
          "doc_id": "80",
          "name": "Improper Neutralization of Script-Related HTML Tags in a Web Page (Basic XSS)",
          "source": "sparse",
          "original_content": "The product receives input from an upstream component, but it does not neutralize or incorrectly neutralizes special characters such as \"<\", \">\", and \"&\" that could be interpreted as web-scripting elements when they are sent to a downstream component that processes web pages.",
          "keyphrase_sources": [
            {
              "id": "weakness:Cross-Site Scripting",
              "keyphrase": "Cross-Site Scripting",
              "type": "weakness"
            }
          ]
        },
        "similarity": 217.4729039106975
      },
      {
        "metadata": {
          "doc_id": "79",
          "name": "Improper Neutralization of Input During Web Page Generation ('Cross-site Scripting')",
          "source": "sparse",
          "original_content": "The product does not neutralize or incorrectly neutralizes user-controllable input before it is placed in output that is used as a web page that is served to other users.",
          "keyphrase_sources": [
            {
              "id": "rootcause:lack of CSRF protection",
              "keyphrase": "lack of CSRF protection",
              "type": "rootcause"
            },
            {
              "id": "weakness:Cross-Site Scripting",
              "keyphrase": "Cross-Site Scripting",
              "type": "weakness"
            },
            {
              "id": "weakness:XSS",
              "keyphrase": "XSS",
              "type": "weakness"
            },
            {
              "id": "product:Chandan Garg CG Scroll To Top",
              "keyphrase": "Chandan Garg CG Scroll To Top",
              "type": "product"
            },
            {
              "id": "version:n/a through 3.5",
              "keyphrase": "n/a through 3.5",
              "type": "version"
            }
          ]
        },
        "similarity": 213.5290433984859
      },
      {
        "metadata": {
          "doc_id": "1004",
          "name": "Sensitive Cookie Without 'HttpOnly' Flag",
          "source": "sparse",
          "original_content": "The product uses a cookie to store sensitive information, but the cookie is not marked with the HttpOnly flag.",
          "keyphrase_sources": [
            {
              "id": "rootcause:lack of CSRF protection",
              "keyphrase": "lack of CSRF protection",
              "type": "rootcause"
            },
            {
              "id": "weakness:Cross-Site Scripting",
              "keyphrase": "Cross-Site Scripting",
              "type": "weakness"
            },
            {
              "id": "weakness:XSS",
              "keyphrase": "XSS",
              "type": "weakness"
            }
          ]
        },
        "similarity": 205.93727124441548
      },
      {
        "metadata": {
          "doc_id": "918",
          "name": "Server-Side Request Forgery (SSRF)",
          "source": "sparse",
          "original_content": "The web server receives a URL or similar request from an upstream component and retrieves the contents of this URL, but it does not sufficiently ensure that the request is being sent to the expected destination.",
          "keyphrase_sources": [
            {
              "id": "weakness:XSS",
              "keyphrase": "XSS",
              "type": "weakness"
            }
          ]
        },
        "similarity": 163.750366822664
      },
      {
        "metadata": {
          "doc_id": "22",
          "name": "Improper Limitation of a Pathname to a Restricted Directory ('Path Traversal')",
          "source": "sparse",
          "original_content": "The product uses external input to construct a pathname that is intended to identify a file or directory that is located underneath a restricted parent directory, but the product does not properly neutralize special elements within the pathname that can cause the pathname to resolve to a location that is outside of the restricted directory.",
          "keyphrase_sources": [
            {
              "id": "version:n/a through 3.5",
              "keyphrase": "n/a through 3.5",
              "type": "version"
            }
          ]
        },
        "similarity": 68.83897229867003
      },
      {
        "metadata": {
          "doc_id": "611",
          "name": "Improper Restriction of XML External Entity Reference",
          "source": "sparse",
          "original_content": "The product processes an XML document that can contain XML entities with URIs that resolve to documents outside of the intended sphere of control, causing the product to embed incorrect documents into its output.",
          "keyphrase_sources": [
            {
              "id": "version:n/a through 3.5",
              "keyphrase": "n/a through 3.5",
              "type": "version"
            }
          ]
        },
        "similarity": 68.72314712289672
      },
      {
        "metadata": {
          "doc_id": "259",
          "name": "Use of Hard-coded Password",
          "source": "sparse",
          "original_content": "The product contains a hard-coded password, which it uses for its own inbound authentication or for outbound communication to external components.",
          "keyphrase_sources": [
            {
              "id": "product:Chandan Garg CG Scroll To Top",
              "keyphrase": "Chandan Garg CG Scroll To Top",
              "type": "product"
            }
          ]
        },
        "similarity": 64.85920201704103
      },
      {
        "metadata": {
          "doc_id": "24",
          "name": "Path Traversal: '../filedir'",
          "source": "sparse",
          "original_content": "The product uses external input to construct a pathname that should be within a restricted directory, but it does not properly neutralize \"../\" sequences that can resolve to a location that is outside of that directory.",
          "keyphrase_sources": [
            {
              "id": "product:Chandan Garg CG Scroll To Top",
              "keyphrase": "Chandan Garg CG Scroll To Top",
              "type": "product"
            }
          ]
        },
        "similarity": 64.81177866554567
      }
    ],
    "enhanced_query": "# Vulnerability Description\n\n    Cross-Site Request Forgery (CSRF) vulnerability in Chandan Garg CG Scroll To Top allows Stored **XSS**. This issue affects CG Scroll To Top from n/a through 3.5.\n\n    # Keyphrase-Specific CWE Analysis\n    This vulnerability contains multiple keyphrases that may map to different CWEs. \n    Please analyze each keyphrase separately and determine the most appropriate CWE(s) for each.\n\n    ## ROOTCAUSE: 'lack of CSRF protection'\n\nRelevant CWEs for this ROOTCAUSE:\n\n### 1. CWE-352: Cross-Site Request Forgery (CSRF) (Score: 316.01)\n\nThe web application does not, or can not, sufficiently verify whether a well-formed, valid, consistent request was intentionally provided by the user who submitted the request....\n\n### 2. CWE-434: Unrestricted Upload of File with Dangerous Type (Score: 227.13)\n\nThe product allows the upload or transfer of dangerous file types that are automatically processed within its environment....\n\n### 3. CWE-116: Improper Encoding or Escaping of Output (Score: 224.59)\n\nThe product prepares a structured message for communication with another component, but encoding or escaping of the data is either missing or done incorrectly. As a result, the intended structure of the message is not preserved....\n\n### 4. CWE-79: Improper Neutralization of Input During Web Page Generation ('Cross-site Scripting') (Score: 213.53)\n\nThe product does not neutralize or incorrectly neutralizes user-controllable input before it is placed in output that is used as a web page that is served to other users....\n\n### 5. CWE-1004: Sensitive Cookie Without 'HttpOnly' Flag (Score: 205.94)\n\nThe product uses a cookie to store sensitive information, but the cookie is not marked with the HttpOnly flag....\n\n## WEAKNESS: 'Cross-Site Scripting'\n\nRelevant CWEs for this WEAKNESS:\n\n### 1. CWE-352: Cross-Site Request Forgery (CSRF) (Score: 316.01)\n\nThe web application does not, or can not, sufficiently verify whether a well-formed, valid, consistent request was intentionally provided by the user who submitted the request....\n\n### 2. CWE-116: Improper Encoding or Escaping of Output (Score: 224.59)\n\nThe product prepares a structured message for communication with another component, but encoding or escaping of the data is either missing or done incorrectly. As a result, the intended structure of the message is not preserved....\n\n### 3. CWE-80: Improper Neutralization of Script-Related HTML Tags in a Web Page (Basic XSS) (Score: 217.47)\n\nThe product receives input from an upstream component, but it does not neutralize or incorrectly neutralizes special characters such as \"<\", \">\", and \"&\" that could be interpreted as web-scripting elements when they are sent to a downstream component that processes web pages....\n\n### 4. CWE-79: Improper Neutralization of Input During Web Page Generation ('Cross-site Scripting') (Score: 213.53)\n\nThe product does not neutralize or incorrectly neutralizes user-controllable input before it is placed in output that is used as a web page that is served to other users....\n\n### 5. CWE-1004: Sensitive Cookie Without 'HttpOnly' Flag (Score: 205.94)\n\nThe product uses a cookie to store sensitive information, but the cookie is not marked with the HttpOnly flag....\n\n## WEAKNESS: 'XSS'\n\nRelevant CWEs for this WEAKNESS:\n\n### 1. CWE-352: Cross-Site Request Forgery (CSRF) (Score: 316.01)\n\nThe web application does not, or can not, sufficiently verify whether a well-formed, valid, consistent request was intentionally provided by the user who submitted the request....\n\n### 2. CWE-116: Improper Encoding or Escaping of Output (Score: 224.59)\n\nThe product prepares a structured message for communication with another component, but encoding or escaping of the data is either missing or done incorrectly. As a result, the intended structure of the message is not preserved....\n\n### 3. CWE-79: Improper Neutralization of Input During Web Page Generation ('Cross-site Scripting') (Score: 213.53)\n\nThe product does not neutralize or incorrectly neutralizes user-controllable input before it is placed in output that is used as a web page that is served to other users....\n\n### 4. CWE-1004: Sensitive Cookie Without 'HttpOnly' Flag (Score: 205.94)\n\nThe product uses a cookie to store sensitive information, but the cookie is not marked with the HttpOnly flag....\n\n### 5. CWE-918: Server-Side Request Forgery (SSRF) (Score: 163.75)\n\nThe web server receives a URL or similar request from an upstream component and retrieves the contents of this URL, but it does not sufficiently ensure that the request is being sent to the expected destination....\n\n## PRODUCT: 'Chandan Garg CG Scroll To Top'\n\nRelevant CWEs for this PRODUCT:\n\n### 1. CWE-352: Cross-Site Request Forgery (CSRF) (Score: 316.01)\n\nThe web application does not, or can not, sufficiently verify whether a well-formed, valid, consistent request was intentionally provided by the user who submitted the request....\n\n### 2. CWE-116: Improper Encoding or Escaping of Output (Score: 224.59)\n\nThe product prepares a structured message for communication with another component, but encoding or escaping of the data is either missing or done incorrectly. As a result, the intended structure of the message is not preserved....\n\n### 3. CWE-79: Improper Neutralization of Input During Web Page Generation ('Cross-site Scripting') (Score: 213.53)\n\nThe product does not neutralize or incorrectly neutralizes user-controllable input before it is placed in output that is used as a web page that is served to other users....\n\n### 4. CWE-259: Use of Hard-coded Password (Score: 64.86)\n\nThe product contains a hard-coded password, which it uses for its own inbound authentication or for outbound communication to external components....\n\n### 5. CWE-24: Path Traversal: '../filedir' (Score: 64.81)\n\nThe product uses external input to construct a pathname that should be within a restricted directory, but it does not properly neutralize \"../\" sequences that can resolve to a location that is outside of that directory....\n\n## VERSION: 'n/a through 3.5'\n\nRelevant CWEs for this VERSION:\n\n### 1. CWE-352: Cross-Site Request Forgery (CSRF) (Score: 316.01)\n\nThe web application does not, or can not, sufficiently verify whether a well-formed, valid, consistent request was intentionally provided by the user who submitted the request....\n\n### 2. CWE-434: Unrestricted Upload of File with Dangerous Type (Score: 227.13)\n\nThe product allows the upload or transfer of dangerous file types that are automatically processed within its environment....\n\n### 3. CWE-79: Improper Neutralization of Input During Web Page Generation ('Cross-site Scripting') (Score: 213.53)\n\nThe product does not neutralize or incorrectly neutralizes user-controllable input before it is placed in output that is used as a web page that is served to other users....\n\n### 4. CWE-22: Improper Limitation of a Pathname to a Restricted Directory ('Path Traversal') (Score: 68.84)\n\nThe product uses external input to construct a pathname that is intended to identify a file or directory that is located underneath a restricted parent directory, but the product does not properly neutralize special elements within the pathname that can cause the pathname to resolve to a location th...\n\n### 5. CWE-611: Improper Restriction of XML External Entity Reference (Score: 68.72)\n\nThe product processes an XML document that can contain XML entities with URIs that resolve to documents outside of the intended sphere of control, causing the product to embed incorrect documents into its output....\n\n\n    # Analysis Instructions\n    1. For each keyphrase, identify the most appropriate CWE(s) that represent the weakness.\n    2. Consider how the different keyphrases might relate to each other in the vulnerability chain.\n    3. Provide a final determination of primary CWE(s) and any secondary CWEs.\n    4. Format your response using the standard analysis template.\n\n    Please analyze how these different weaknesses interact and provide a comprehensive CWE classification.\n    "
  },
  "retrieval_time": 1.031341314315796
}