{
  "vulnerability_info": "VulnerabilityInfo(cve_id='CVE-2024-8599', description='A **maliciously crafted STP file** when parsed in ACTranslators.exe through Autodesk AutoCAD can force a **Memory Corruption** vulnerability. A malicious actor can leverage this vulnerability to cause a crash, write sensitive data, or execute arbitrary code in the context of the current process.', key_phrases={'rootcause': '', 'weakness': ['Memory Corruption', 'maliciously crafted STP file'], 'impact': ['cause a crash', 'execute arbitrary code', 'write sensitive data'], 'vector': '', 'attacker': '', 'product': 'Autodesk AutoCAD', 'version': '', 'component': 'ACTranslators.exe'}, reference_content='The provided content is related to CVE-2024-8599.\\n\\n**Root cause of vulnerability:**\\nA maliciously crafted STP file, when parsed in `ACTranslators.exe` through affected Autodesk applications, can trigger a memory corruption vulnerability.\\n\\n**Weaknesses/vulnerabilities present:**\\nMemory Corruption\\n\\n**Impact of exploitation:**\\nSuccessful exploitation can lead to a crash, writing of sensitive data, or execution of arbitrary code in the context of the current process.\\n\\n**Attack vectors:**\\nThe vulnerability is triggered by parsing a maliciously crafted STP file in the affected application.\\n\\n**Required attacker capabilities/position:**\\nThe attacker needs the ability to create a malicious STP file and to convince a user to open the file using an affected Autodesk application. User interaction is required for exploitation.', similar_info={'cwe_distribution': {95: {'cwe_counts': defaultdict(<class 'int'>, {'CWE-787': 3}), 'total_samples': 3, 'distribution': [{'cwes': ['CWE-787'], 'frequency': 3, 'proportion': 1.0}]}, 90: {'cwe_counts': defaultdict(<class 'int'>, {'CWE-787': 7, 'CWE-416': 3}), 'total_samples': 10, 'distribution': [{'cwes': ['CWE-787'], 'frequency': 7, 'proportion': 0.7}, {'cwes': ['CWE-416'], 'frequency': 3, 'proportion': 0.3}]}, 85: {'cwe_counts': defaultdict(<class 'int'>, {'CWE-787': 15, 'CWE-908': 1}), 'total_samples': 20, 'distribution': [{'cwes': ['CWE-787'], 'frequency': 15, 'proportion': 0.75}, {'cwes': [], 'frequency': 4, 'proportion': 0.2}, {'cwes': ['CWE-908'], 'frequency': 1, 'proportion': 0.05}]}, 80: {'cwe_counts': defaultdict(<class 'int'>, {'CWE-787': 23, 'CWE-125': 5, 'CWE-416': 4, 'CWE-190': 1, 'CWE-908': 1}), 'total_samples': 72, 'distribution': [{'cwes': [], 'frequency': 38, 'proportion': 0.528}, {'cwes': ['CWE-787'], 'frequency': 23, 'proportion': 0.319}, {'cwes': ['CWE-125'], 'frequency': 5, 'proportion': 0.069}, {'cwes': ['CWE-416'], 'frequency': 4, 'proportion': 0.056}, {'cwes': ['CWE-190'], 'frequency': 1, 'proportion': 0.014}, {'cwes': ['CWE-908'], 'frequency': 1, 'proportion': 0.014}]}, 75: {'cwe_counts': defaultdict(<class 'int'>, {'CWE-787': 25, 'CWE-125': 5, 'CWE-416': 4, 'CWE-755': 1, 'CWE-908': 1, 'CWE-190': 1}), 'total_samples': 80, 'distribution': [{'cwes': [], 'frequency': 43, 'proportion': 0.537}, {'cwes': ['CWE-787'], 'frequency': 25, 'proportion': 0.312}, {'cwes': ['CWE-125'], 'frequency': 5, 'proportion': 0.062}, {'cwes': ['CWE-416'], 'frequency': 4, 'proportion': 0.05}, {'cwes': ['CWE-755'], 'frequency': 1, 'proportion': 0.013}, {'cwes': ['CWE-908'], 'frequency': 1, 'proportion': 0.013}, {'cwes': ['CWE-190'], 'frequency': 1, 'proportion': 0.013}]}, 70: {'cwe_counts': defaultdict(<class 'int'>, {'CWE-787': 26, 'CWE-125': 5, 'CWE-416': 4, 'CWE-755': 1, 'CWE-908': 1, 'CWE-190': 1}), 'total_samples': 82, 'distribution': [{'cwes': [], 'frequency': 44, 'proportion': 0.537}, {'cwes': ['CWE-787'], 'frequency': 26, 'proportion': 0.317}, {'cwes': ['CWE-125'], 'frequency': 5, 'proportion': 0.061}, {'cwes': ['CWE-416'], 'frequency': 4, 'proportion': 0.049}, {'cwes': ['CWE-755'], 'frequency': 1, 'proportion': 0.012}, {'cwes': ['CWE-908'], 'frequency': 1, 'proportion': 0.012}, {'cwes': ['CWE-190'], 'frequency': 1, 'proportion': 0.012}]}}, 'cwe_consensus': 'CWE-787', 'similarity_stats': {'thresholds': [95, 90, 85, 80, 75, 70], 'total_samples_by_threshold': {95: 3, 90: 10, 85: 20, 80: 72, 75: 80, 70: 82}, 'top_cwes_by_threshold': {95: [('CWE-787', 3)], 90: [('CWE-787', 7), ('CWE-416', 3)], 85: [('CWE-787', 15), ('CWE-908', 1)], 80: [('CWE-787', 23), ('CWE-125', 5), ('CWE-416', 4)], 75: [('CWE-787', 25), ('CWE-125', 5), ('CWE-416', 4)], 70: [('CWE-787', 26), ('CWE-125', 5), ('CWE-416', 4)]}}, 'raw_matches': [{'similarity': 95, 'cwes': ['787'], 'total': 3, 'frequency': 3, 'proportion': 1.0}, {'similarity': 90, 'cwes': ['787'], 'total': 10, 'frequency': 7, 'proportion': 0.7}, {'similarity': 90, 'cwes': ['416'], 'total': 10, 'frequency': 3, 'proportion': 0.3}, {'similarity': 85, 'cwes': ['787'], 'total': 20, 'frequency': 15, 'proportion': 0.75}, {'similarity': 85, 'cwes': [], 'total': 20, 'frequency': 4, 'proportion': 0.2}, {'similarity': 85, 'cwes': ['908'], 'total': 20, 'frequency': 1, 'proportion': 0.05}, {'similarity': 80, 'cwes': [], 'total': 72, 'frequency': 38, 'proportion': 0.528}, {'similarity': 80, 'cwes': ['787'], 'total': 72, 'frequency': 23, 'proportion': 0.319}, {'similarity': 80, 'cwes': ['125'], 'total': 72, 'frequency': 5, 'proportion': 0.069}, {'similarity': 80, 'cwes': ['416'], 'total': 72, 'frequency': 4, 'proportion': 0.056}, {'similarity': 80, 'cwes': ['190'], 'total': 72, 'frequency': 1, 'proportion': 0.014}, {'similarity': 80, 'cwes': ['908'], 'total': 72, 'frequency': 1, 'proportion': 0.014}, {'similarity': 75, 'cwes': [], 'total': 80, 'frequency': 43, 'proportion': 0.537}, {'similarity': 75, 'cwes': ['787'], 'total': 80, 'frequency': 25, 'proportion': 0.312}, {'similarity': 75, 'cwes': ['125'], 'total': 80, 'frequency': 5, 'proportion': 0.062}, {'similarity': 75, 'cwes': ['416'], 'total': 80, 'frequency': 4, 'proportion': 0.05}, {'similarity': 75, 'cwes': ['755'], 'total': 80, 'frequency': 1, 'proportion': 0.013}, {'similarity': 75, 'cwes': ['908'], 'total': 80, 'frequency': 1, 'proportion': 0.013}, {'similarity': 75, 'cwes': ['190'], 'total': 80, 'frequency': 1, 'proportion': 0.013}, {'similarity': 70, 'cwes': [], 'total': 82, 'frequency': 44, 'proportion': 0.537}, {'similarity': 70, 'cwes': ['787'], 'total': 82, 'frequency': 26, 'proportion': 0.317}, {'similarity': 70, 'cwes': ['125'], 'total': 82, 'frequency': 5, 'proportion': 0.061}, {'similarity': 70, 'cwes': ['416'], 'total': 82, 'frequency': 4, 'proportion': 0.049}, {'similarity': 70, 'cwes': ['755'], 'total': 82, 'frequency': 1, 'proportion': 0.012}, {'similarity': 70, 'cwes': ['908'], 'total': 82, 'frequency': 1, 'proportion': 0.012}, {'similarity': 70, 'cwes': ['190'], 'total': 82, 'frequency': 1, 'proportion': 0.012}]}, similarity_summary=SimilarityInsight(consensus_cwe='CWE-787', top_cwes=[('CWE-787', 99), ('CWE-416', 15), ('CWE-125', 15)], confidence_levels={'high': [], 'medium': [], 'low': []}, total_samples=267), analysis='', analysis_with_relationships='', criticism='', resolution='', relevant_cwes=[{'metadata': {'doc_id': '787', 'name': 'Out-of-bounds Write', 'source': 'sparse', 'original_content': 'The product writes data past the end, or before the beginning, of the intended buffer.', 'keyphrase_sources': [{'id': 'weakness:Memory Corruption', 'keyphrase': 'Memory Corruption', 'type': 'weakness'}, {'id': 'weakness:maliciously crafted STP file', 'keyphrase': 'maliciously crafted STP file', 'type': 'weakness'}, {'id': 'impact:cause a crash', 'keyphrase': 'cause a crash', 'type': 'impact'}, {'id': 'impact:execute arbitrary code', 'keyphrase': 'execute arbitrary code', 'type': 'impact'}, {'id': 'impact:write sensitive data', 'keyphrase': 'write sensitive data', 'type': 'impact'}, {'id': 'product:Autodesk AutoCAD', 'keyphrase': 'Autodesk AutoCAD', 'type': 'product'}, {'id': 'component:ACTranslators.exe', 'keyphrase': 'ACTranslators.exe', 'type': 'component'}]}, 'similarity': np.float64(326.3747083621021)}, {'metadata': {'doc_id': '122', 'name': 'Heap-based Buffer Overflow', 'source': 'sparse', 'original_content': 'A heap overflow condition is a buffer overflow, where the buffer that can be overwritten is allocated in the heap portion of memory, generally meaning that the buffer was allocated using a routine such as malloc().', 'keyphrase_sources': [{'id': 'weakness:Memory Corruption', 'keyphrase': 'Memory Corruption', 'type': 'weakness'}, {'id': 'weakness:maliciously crafted STP file', 'keyphrase': 'maliciously crafted STP file', 'type': 'weakness'}, {'id': 'impact:cause a crash', 'keyphrase': 'cause a crash', 'type': 'impact'}, {'id': 'impact:execute arbitrary code', 'keyphrase': 'execute arbitrary code', 'type': 'impact'}, {'id': 'impact:write sensitive data', 'keyphrase': 'write sensitive data', 'type': 'impact'}, {'id': 'product:Autodesk AutoCAD', 'keyphrase': 'Autodesk AutoCAD', 'type': 'product'}]}, 'similarity': np.float64(283.41188042666863)}, {'metadata': {'doc_id': '788', 'name': 'Access of Memory Location After End of Buffer', 'source': 'sparse', 'original_content': 'The product reads or writes to a buffer using an index or pointer that references a memory location after the end of the buffer.', 'keyphrase_sources': [{'id': 'weakness:Memory Corruption', 'keyphrase': 'Memory Corruption', 'type': 'weakness'}]}, 'similarity': np.float64(275.4755323316423)}, {'metadata': {'doc_id': '190', 'name': 'Integer Overflow or Wraparound', 'source': 'sparse', 'original_content': 'The product performs a calculation that can\\n         produce an integer overflow or wraparound when the logic\\n         assumes that the resulting value will always be larger than\\n         the original value. This occurs when an integer value is\\n         incremented to a value that is too large to store in the\\n         associated representation. When this occurs, the value may\\n         become a very small or negative number.', 'keyphrase_sources': [{'id': 'weakness:Memory Corruption', 'keyphrase': 'Memory Corruption', 'type': 'weakness'}]}, 'similarity': np.float64(272.172815602269)}, {'metadata': {'doc_id': '121', 'name': 'Stack-based Buffer Overflow', 'source': 'sparse', 'original_content': 'A stack-based buffer overflow condition is a condition where the buffer being overwritten is allocated on the stack (i.e., is a local variable or, rarely, a parameter to a function).', 'keyphrase_sources': [{'id': 'weakness:maliciously crafted STP file', 'keyphrase': 'maliciously crafted STP file', 'type': 'weakness'}, {'id': 'impact:cause a crash', 'keyphrase': 'cause a crash', 'type': 'impact'}, {'id': 'impact:execute arbitrary code', 'keyphrase': 'execute arbitrary code', 'type': 'impact'}, {'id': 'impact:write sensitive data', 'keyphrase': 'write sensitive data', 'type': 'impact'}, {'id': 'product:Autodesk AutoCAD', 'keyphrase': 'Autodesk AutoCAD', 'type': 'product'}, {'id': 'component:ACTranslators.exe', 'keyphrase': 'ACTranslators.exe', 'type': 'component'}]}, 'similarity': np.float64(267.1213855244518)}, {'metadata': {'doc_id': '843', 'name': \"Access of Resource Using Incompatible Type ('Type Confusion')\", 'source': 'sparse', 'original_content': 'The product allocates or initializes a resource such as a pointer, object, or variable using one type, but it later accesses that resource using a type that is incompatible with the original type.', 'keyphrase_sources': [{'id': 'weakness:Memory Corruption', 'keyphrase': 'Memory Corruption', 'type': 'weakness'}]}, 'similarity': np.float64(267.0094875962169)}, {'metadata': {'doc_id': '20', 'name': 'Improper Input Validation', 'source': 'sparse', 'original_content': 'The product receives input or data, but it does\\n        not validate or incorrectly validates that the input has the\\n        properties that are required to process the data safely and\\n        correctly.', 'keyphrase_sources': [{'id': 'weakness:maliciously crafted STP file', 'keyphrase': 'maliciously crafted STP file', 'type': 'weakness'}, {'id': 'impact:cause a crash', 'keyphrase': 'cause a crash', 'type': 'impact'}, {'id': 'impact:execute arbitrary code', 'keyphrase': 'execute arbitrary code', 'type': 'impact'}, {'id': 'impact:write sensitive data', 'keyphrase': 'write sensitive data', 'type': 'impact'}]}, 'similarity': np.float64(264.99028235792923)}, {'metadata': {'doc_id': '125', 'name': 'Out-of-bounds Read', 'source': 'sparse', 'original_content': 'The product reads data past the end, or before the beginning, of the intended buffer.', 'keyphrase_sources': [{'id': 'weakness:maliciously crafted STP file', 'keyphrase': 'maliciously crafted STP file', 'type': 'weakness'}, {'id': 'impact:cause a crash', 'keyphrase': 'cause a crash', 'type': 'impact'}, {'id': 'impact:write sensitive data', 'keyphrase': 'write sensitive data', 'type': 'impact'}, {'id': 'product:Autodesk AutoCAD', 'keyphrase': 'Autodesk AutoCAD', 'type': 'product'}]}, 'similarity': np.float64(260.65810974269414)}, {'metadata': {'doc_id': '119', 'name': 'Improper Restriction of Operations within the Bounds of a Memory Buffer', 'source': 'sparse', 'original_content': \"The product performs operations on a memory buffer, but it reads from or writes to a memory location outside the buffer's intended boundary. This may result in read or write operations on unexpected memory locations that could be linked to other variables, data structures, or internal program data.\", 'keyphrase_sources': [{'id': 'impact:execute arbitrary code', 'keyphrase': 'execute arbitrary code', 'type': 'impact'}, {'id': 'component:ACTranslators.exe', 'keyphrase': 'ACTranslators.exe', 'type': 'component'}]}, 'similarity': np.float64(90.58580459917943)}, {'metadata': {'doc_id': '427', 'name': 'Uncontrolled Search Path Element', 'source': 'sparse', 'original_content': 'The product uses a fixed or controlled search path to find resources, but one or more locations in that path can be under the control of unintended actors.', 'keyphrase_sources': [{'id': 'component:ACTranslators.exe', 'keyphrase': 'ACTranslators.exe', 'type': 'component'}]}, 'similarity': np.float64(90.16598911812883)}, {'metadata': {'doc_id': '123', 'name': 'Write-what-where Condition', 'source': 'sparse', 'original_content': 'Any condition where the attacker has the ability to write an arbitrary value to an arbitrary location, often as the result of a buffer overflow.', 'keyphrase_sources': [{'id': 'product:Autodesk AutoCAD', 'keyphrase': 'Autodesk AutoCAD', 'type': 'product'}]}, 'similarity': np.float64(88.8824902736127)}, {'metadata': {'doc_id': '276', 'name': 'Incorrect Default Permissions', 'source': 'sparse', 'original_content': 'During installation, installed file permissions are set to allow anyone to modify those files.', 'keyphrase_sources': [{'id': 'component:ACTranslators.exe', 'keyphrase': 'ACTranslators.exe', 'type': 'component'}]}, 'similarity': np.float64(88.37007997077774)}], identified_cwes={'analyzer': [], 'critic_additional': []})",
  "retrieval_results": {
    "has_multiple_keyphrases": true,
    "keyphrase_cwe_sets": {
      "weakness:Memory Corruption": {
        "keyphrase": "Memory Corruption",
        "type": "weakness",
        "cwes": [
          {
            "metadata": {
              "doc_id": "787",
              "name": "Out-of-bounds Write",
              "source": "sparse",
              "original_content": "The product writes data past the end, or before the beginning, of the intended buffer.",
              "keyphrase_sources": [
                {
                  "id": "weakness:Memory Corruption",
                  "keyphrase": "Memory Corruption",
                  "type": "weakness"
                },
                {
                  "id": "weakness:maliciously crafted STP file",
                  "keyphrase": "maliciously crafted STP file",
                  "type": "weakness"
                },
                {
                  "id": "impact:cause a crash",
                  "keyphrase": "cause a crash",
                  "type": "impact"
                },
                {
                  "id": "impact:execute arbitrary code",
                  "keyphrase": "execute arbitrary code",
                  "type": "impact"
                },
                {
                  "id": "impact:write sensitive data",
                  "keyphrase": "write sensitive data",
                  "type": "impact"
                },
                {
                  "id": "product:Autodesk AutoCAD",
                  "keyphrase": "Autodesk AutoCAD",
                  "type": "product"
                },
                {
                  "id": "component:ACTranslators.exe",
                  "keyphrase": "ACTranslators.exe",
                  "type": "component"
                }
              ]
            },
            "similarity": 326.3747083621021
          },
          {
            "metadata": {
              "doc_id": "122",
              "name": "Heap-based Buffer Overflow",
              "source": "sparse",
              "original_content": "A heap overflow condition is a buffer overflow, where the buffer that can be overwritten is allocated in the heap portion of memory, generally meaning that the buffer was allocated using a routine such as malloc().",
              "keyphrase_sources": [
                {
                  "id": "weakness:Memory Corruption",
                  "keyphrase": "Memory Corruption",
                  "type": "weakness"
                },
                {
                  "id": "weakness:maliciously crafted STP file",
                  "keyphrase": "maliciously crafted STP file",
                  "type": "weakness"
                },
                {
                  "id": "impact:cause a crash",
                  "keyphrase": "cause a crash",
                  "type": "impact"
                },
                {
                  "id": "impact:execute arbitrary code",
                  "keyphrase": "execute arbitrary code",
                  "type": "impact"
                },
                {
                  "id": "impact:write sensitive data",
                  "keyphrase": "write sensitive data",
                  "type": "impact"
                },
                {
                  "id": "product:Autodesk AutoCAD",
                  "keyphrase": "Autodesk AutoCAD",
                  "type": "product"
                }
              ]
            },
            "similarity": 283.41188042666863
          },
          {
            "metadata": {
              "doc_id": "788",
              "name": "Access of Memory Location After End of Buffer",
              "source": "sparse",
              "original_content": "The product reads or writes to a buffer using an index or pointer that references a memory location after the end of the buffer.",
              "keyphrase_sources": [
                {
                  "id": "weakness:Memory Corruption",
                  "keyphrase": "Memory Corruption",
                  "type": "weakness"
                }
              ]
            },
            "similarity": 275.4755323316423
          },
          {
            "metadata": {
              "doc_id": "190",
              "name": "Integer Overflow or Wraparound",
              "source": "sparse",
              "original_content": "The product performs a calculation that can\n         produce an integer overflow or wraparound when the logic\n         assumes that the resulting value will always be larger than\n         the original value. This occurs when an integer value is\n         incremented to a value that is too large to store in the\n         associated representation. When this occurs, the value may\n         become a very small or negative number.",
              "keyphrase_sources": [
                {
                  "id": "weakness:Memory Corruption",
                  "keyphrase": "Memory Corruption",
                  "type": "weakness"
                }
              ]
            },
            "similarity": 272.172815602269
          },
          {
            "metadata": {
              "doc_id": "843",
              "name": "Access of Resource Using Incompatible Type ('Type Confusion')",
              "source": "sparse",
              "original_content": "The product allocates or initializes a resource such as a pointer, object, or variable using one type, but it later accesses that resource using a type that is incompatible with the original type.",
              "keyphrase_sources": [
                {
                  "id": "weakness:Memory Corruption",
                  "keyphrase": "Memory Corruption",
                  "type": "weakness"
                }
              ]
            },
            "similarity": 267.0094875962169
          }
        ]
      },
      "weakness:maliciously crafted STP file": {
        "keyphrase": "maliciously crafted STP file",
        "type": "weakness",
        "cwes": [
          {
            "metadata": {
              "doc_id": "787",
              "name": "Out-of-bounds Write",
              "source": "sparse",
              "original_content": "The product writes data past the end, or before the beginning, of the intended buffer."
            },
            "similarity": 316.04663008168774
          },
          {
            "metadata": {
              "doc_id": "122",
              "name": "Heap-based Buffer Overflow",
              "source": "sparse",
              "original_content": "A heap overflow condition is a buffer overflow, where the buffer that can be overwritten is allocated in the heap portion of memory, generally meaning that the buffer was allocated using a routine such as malloc()."
            },
            "similarity": 274.2740076273203
          },
          {
            "metadata": {
              "doc_id": "121",
              "name": "Stack-based Buffer Overflow",
              "source": "sparse",
              "original_content": "A stack-based buffer overflow condition is a condition where the buffer being overwritten is allocated on the stack (i.e., is a local variable or, rarely, a parameter to a function).",
              "keyphrase_sources": [
                {
                  "id": "weakness:maliciously crafted STP file",
                  "keyphrase": "maliciously crafted STP file",
                  "type": "weakness"
                },
                {
                  "id": "impact:cause a crash",
                  "keyphrase": "cause a crash",
                  "type": "impact"
                },
                {
                  "id": "impact:execute arbitrary code",
                  "keyphrase": "execute arbitrary code",
                  "type": "impact"
                },
                {
                  "id": "impact:write sensitive data",
                  "keyphrase": "write sensitive data",
                  "type": "impact"
                },
                {
                  "id": "product:Autodesk AutoCAD",
                  "keyphrase": "Autodesk AutoCAD",
                  "type": "product"
                },
                {
                  "id": "component:ACTranslators.exe",
                  "keyphrase": "ACTranslators.exe",
                  "type": "component"
                }
              ]
            },
            "similarity": 267.1213855244518
          },
          {
            "metadata": {
              "doc_id": "20",
              "name": "Improper Input Validation",
              "source": "sparse",
              "original_content": "The product receives input or data, but it does\n        not validate or incorrectly validates that the input has the\n        properties that are required to process the data safely and\n        correctly.",
              "keyphrase_sources": [
                {
                  "id": "weakness:maliciously crafted STP file",
                  "keyphrase": "maliciously crafted STP file",
                  "type": "weakness"
                },
                {
                  "id": "impact:cause a crash",
                  "keyphrase": "cause a crash",
                  "type": "impact"
                },
                {
                  "id": "impact:execute arbitrary code",
                  "keyphrase": "execute arbitrary code",
                  "type": "impact"
                },
                {
                  "id": "impact:write sensitive data",
                  "keyphrase": "write sensitive data",
                  "type": "impact"
                }
              ]
            },
            "similarity": 264.99028235792923
          },
          {
            "metadata": {
              "doc_id": "125",
              "name": "Out-of-bounds Read",
              "source": "sparse",
              "original_content": "The product reads data past the end, or before the beginning, of the intended buffer.",
              "keyphrase_sources": [
                {
                  "id": "weakness:maliciously crafted STP file",
                  "keyphrase": "maliciously crafted STP file",
                  "type": "weakness"
                },
                {
                  "id": "impact:cause a crash",
                  "keyphrase": "cause a crash",
                  "type": "impact"
                },
                {
                  "id": "impact:write sensitive data",
                  "keyphrase": "write sensitive data",
                  "type": "impact"
                },
                {
                  "id": "product:Autodesk AutoCAD",
                  "keyphrase": "Autodesk AutoCAD",
                  "type": "product"
                }
              ]
            },
            "similarity": 260.65810974269414
          }
        ]
      },
      "impact:cause a crash": {
        "keyphrase": "cause a crash",
        "type": "impact",
        "cwes": [
          {
            "metadata": {
              "doc_id": "787",
              "name": "Out-of-bounds Write",
              "source": "sparse",
              "original_content": "The product writes data past the end, or before the beginning, of the intended buffer."
            },
            "similarity": 115.47961337135966
          },
          {
            "metadata": {
              "doc_id": "121",
              "name": "Stack-based Buffer Overflow",
              "source": "sparse",
              "original_content": "A stack-based buffer overflow condition is a condition where the buffer being overwritten is allocated on the stack (i.e., is a local variable or, rarely, a parameter to a function)."
            },
            "similarity": 102.60707263612525
          },
          {
            "metadata": {
              "doc_id": "122",
              "name": "Heap-based Buffer Overflow",
              "source": "sparse",
              "original_content": "A heap overflow condition is a buffer overflow, where the buffer that can be overwritten is allocated in the heap portion of memory, generally meaning that the buffer was allocated using a routine such as malloc()."
            },
            "similarity": 101.61741825985887
          },
          {
            "metadata": {
              "doc_id": "125",
              "name": "Out-of-bounds Read",
              "source": "sparse",
              "original_content": "The product reads data past the end, or before the beginning, of the intended buffer."
            },
            "similarity": 100.37199047800092
          },
          {
            "metadata": {
              "doc_id": "20",
              "name": "Improper Input Validation",
              "source": "sparse",
              "original_content": "The product receives input or data, but it does\n        not validate or incorrectly validates that the input has the\n        properties that are required to process the data safely and\n        correctly."
            },
            "similarity": 99.2461316724348
          }
        ]
      },
      "impact:execute arbitrary code": {
        "keyphrase": "execute arbitrary code",
        "type": "impact",
        "cwes": [
          {
            "metadata": {
              "doc_id": "787",
              "name": "Out-of-bounds Write",
              "source": "sparse",
              "original_content": "The product writes data past the end, or before the beginning, of the intended buffer."
            },
            "similarity": 109.1927938937328
          },
          {
            "metadata": {
              "doc_id": "121",
              "name": "Stack-based Buffer Overflow",
              "source": "sparse",
              "original_content": "A stack-based buffer overflow condition is a condition where the buffer being overwritten is allocated on the stack (i.e., is a local variable or, rarely, a parameter to a function)."
            },
            "similarity": 96.02819964037442
          },
          {
            "metadata": {
              "doc_id": "122",
              "name": "Heap-based Buffer Overflow",
              "source": "sparse",
              "original_content": "A heap overflow condition is a buffer overflow, where the buffer that can be overwritten is allocated in the heap portion of memory, generally meaning that the buffer was allocated using a routine such as malloc()."
            },
            "similarity": 94.5939964916089
          },
          {
            "metadata": {
              "doc_id": "20",
              "name": "Improper Input Validation",
              "source": "sparse",
              "original_content": "The product receives input or data, but it does\n        not validate or incorrectly validates that the input has the\n        properties that are required to process the data safely and\n        correctly."
            },
            "similarity": 93.84629298813557
          },
          {
            "metadata": {
              "doc_id": "119",
              "name": "Improper Restriction of Operations within the Bounds of a Memory Buffer",
              "source": "sparse",
              "original_content": "The product performs operations on a memory buffer, but it reads from or writes to a memory location outside the buffer's intended boundary. This may result in read or write operations on unexpected memory locations that could be linked to other variables, data structures, or internal program data.",
              "keyphrase_sources": [
                {
                  "id": "impact:execute arbitrary code",
                  "keyphrase": "execute arbitrary code",
                  "type": "impact"
                },
                {
                  "id": "component:ACTranslators.exe",
                  "keyphrase": "ACTranslators.exe",
                  "type": "component"
                }
              ]
            },
            "similarity": 90.58580459917943
          }
        ]
      },
      "impact:write sensitive data": {
        "keyphrase": "write sensitive data",
        "type": "impact",
        "cwes": [
          {
            "metadata": {
              "doc_id": "787",
              "name": "Out-of-bounds Write",
              "source": "sparse",
              "original_content": "The product writes data past the end, or before the beginning, of the intended buffer."
            },
            "similarity": 106.91277513718403
          },
          {
            "metadata": {
              "doc_id": "122",
              "name": "Heap-based Buffer Overflow",
              "source": "sparse",
              "original_content": "A heap overflow condition is a buffer overflow, where the buffer that can be overwritten is allocated in the heap portion of memory, generally meaning that the buffer was allocated using a routine such as malloc()."
            },
            "similarity": 92.89573266018307
          },
          {
            "metadata": {
              "doc_id": "125",
              "name": "Out-of-bounds Read",
              "source": "sparse",
              "original_content": "The product reads data past the end, or before the beginning, of the intended buffer."
            },
            "similarity": 91.64261367918719
          },
          {
            "metadata": {
              "doc_id": "20",
              "name": "Improper Input Validation",
              "source": "sparse",
              "original_content": "The product receives input or data, but it does\n        not validate or incorrectly validates that the input has the\n        properties that are required to process the data safely and\n        correctly."
            },
            "similarity": 90.32575287676353
          },
          {
            "metadata": {
              "doc_id": "121",
              "name": "Stack-based Buffer Overflow",
              "source": "sparse",
              "original_content": "A stack-based buffer overflow condition is a condition where the buffer being overwritten is allocated on the stack (i.e., is a local variable or, rarely, a parameter to a function)."
            },
            "similarity": 89.64127032660883
          }
        ]
      },
      "product:Autodesk AutoCAD": {
        "keyphrase": "Autodesk AutoCAD",
        "type": "product",
        "cwes": [
          {
            "metadata": {
              "doc_id": "787",
              "name": "Out-of-bounds Write",
              "source": "sparse",
              "original_content": "The product writes data past the end, or before the beginning, of the intended buffer."
            },
            "similarity": 99.71678236276684
          },
          {
            "metadata": {
              "doc_id": "121",
              "name": "Stack-based Buffer Overflow",
              "source": "sparse",
              "original_content": "A stack-based buffer overflow condition is a condition where the buffer being overwritten is allocated on the stack (i.e., is a local variable or, rarely, a parameter to a function)."
            },
            "similarity": 91.06367889968854
          },
          {
            "metadata": {
              "doc_id": "123",
              "name": "Write-what-where Condition",
              "source": "sparse",
              "original_content": "Any condition where the attacker has the ability to write an arbitrary value to an arbitrary location, often as the result of a buffer overflow.",
              "keyphrase_sources": [
                {
                  "id": "product:Autodesk AutoCAD",
                  "keyphrase": "Autodesk AutoCAD",
                  "type": "product"
                }
              ]
            },
            "similarity": 88.8824902736127
          },
          {
            "metadata": {
              "doc_id": "122",
              "name": "Heap-based Buffer Overflow",
              "source": "sparse",
              "original_content": "A heap overflow condition is a buffer overflow, where the buffer that can be overwritten is allocated in the heap portion of memory, generally meaning that the buffer was allocated using a routine such as malloc()."
            },
            "similarity": 88.04075600683383
          },
          {
            "metadata": {
              "doc_id": "125",
              "name": "Out-of-bounds Read",
              "source": "sparse",
              "original_content": "The product reads data past the end, or before the beginning, of the intended buffer."
            },
            "similarity": 87.61602437147486
          }
        ]
      },
      "component:ACTranslators.exe": {
        "keyphrase": "ACTranslators.exe",
        "type": "component",
        "cwes": [
          {
            "metadata": {
              "doc_id": "787",
              "name": "Out-of-bounds Write",
              "source": "sparse",
              "original_content": "The product writes data past the end, or before the beginning, of the intended buffer."
            },
            "similarity": 99.71678236276684
          },
          {
            "metadata": {
              "doc_id": "121",
              "name": "Stack-based Buffer Overflow",
              "source": "sparse",
              "original_content": "A stack-based buffer overflow condition is a condition where the buffer being overwritten is allocated on the stack (i.e., is a local variable or, rarely, a parameter to a function)."
            },
            "similarity": 93.49164603606758
          },
          {
            "metadata": {
              "doc_id": "427",
              "name": "Uncontrolled Search Path Element",
              "source": "sparse",
              "original_content": "The product uses a fixed or controlled search path to find resources, but one or more locations in that path can be under the control of unintended actors.",
              "keyphrase_sources": [
                {
                  "id": "component:ACTranslators.exe",
                  "keyphrase": "ACTranslators.exe",
                  "type": "component"
                }
              ]
            },
            "similarity": 90.16598911812883
          },
          {
            "metadata": {
              "doc_id": "119",
              "name": "Improper Restriction of Operations within the Bounds of a Memory Buffer",
              "source": "sparse",
              "original_content": "The product performs operations on a memory buffer, but it reads from or writes to a memory location outside the buffer's intended boundary. This may result in read or write operations on unexpected memory locations that could be linked to other variables, data structures, or internal program data."
            },
            "similarity": 90.04571432836548
          },
          {
            "metadata": {
              "doc_id": "276",
              "name": "Incorrect Default Permissions",
              "source": "sparse",
              "original_content": "During installation, installed file permissions are set to allow anyone to modify those files.",
              "keyphrase_sources": [
                {
                  "id": "component:ACTranslators.exe",
                  "keyphrase": "ACTranslators.exe",
                  "type": "component"
                }
              ]
            },
            "similarity": 88.37007997077774
          }
        ]
      }
    },
    "keyphrase_mapping": {
      "787": [
        {
          "id": "weakness:Memory Corruption",
          "keyphrase": "Memory Corruption",
          "type": "weakness"
        },
        {
          "id": "weakness:maliciously crafted STP file",
          "keyphrase": "maliciously crafted STP file",
          "type": "weakness"
        },
        {
          "id": "impact:cause a crash",
          "keyphrase": "cause a crash",
          "type": "impact"
        },
        {
          "id": "impact:execute arbitrary code",
          "keyphrase": "execute arbitrary code",
          "type": "impact"
        },
        {
          "id": "impact:write sensitive data",
          "keyphrase": "write sensitive data",
          "type": "impact"
        },
        {
          "id": "product:Autodesk AutoCAD",
          "keyphrase": "Autodesk AutoCAD",
          "type": "product"
        },
        {
          "id": "component:ACTranslators.exe",
          "keyphrase": "ACTranslators.exe",
          "type": "component"
        }
      ],
      "122": [
        {
          "id": "weakness:Memory Corruption",
          "keyphrase": "Memory Corruption",
          "type": "weakness"
        },
        {
          "id": "weakness:maliciously crafted STP file",
          "keyphrase": "maliciously crafted STP file",
          "type": "weakness"
        },
        {
          "id": "impact:cause a crash",
          "keyphrase": "cause a crash",
          "type": "impact"
        },
        {
          "id": "impact:execute arbitrary code",
          "keyphrase": "execute arbitrary code",
          "type": "impact"
        },
        {
          "id": "impact:write sensitive data",
          "keyphrase": "write sensitive data",
          "type": "impact"
        },
        {
          "id": "product:Autodesk AutoCAD",
          "keyphrase": "Autodesk AutoCAD",
          "type": "product"
        }
      ],
      "788": [
        {
          "id": "weakness:Memory Corruption",
          "keyphrase": "Memory Corruption",
          "type": "weakness"
        }
      ],
      "190": [
        {
          "id": "weakness:Memory Corruption",
          "keyphrase": "Memory Corruption",
          "type": "weakness"
        }
      ],
      "843": [
        {
          "id": "weakness:Memory Corruption",
          "keyphrase": "Memory Corruption",
          "type": "weakness"
        }
      ],
      "121": [
        {
          "id": "weakness:maliciously crafted STP file",
          "keyphrase": "maliciously crafted STP file",
          "type": "weakness"
        },
        {
          "id": "impact:cause a crash",
          "keyphrase": "cause a crash",
          "type": "impact"
        },
        {
          "id": "impact:execute arbitrary code",
          "keyphrase": "execute arbitrary code",
          "type": "impact"
        },
        {
          "id": "impact:write sensitive data",
          "keyphrase": "write sensitive data",
          "type": "impact"
        },
        {
          "id": "product:Autodesk AutoCAD",
          "keyphrase": "Autodesk AutoCAD",
          "type": "product"
        },
        {
          "id": "component:ACTranslators.exe",
          "keyphrase": "ACTranslators.exe",
          "type": "component"
        }
      ],
      "20": [
        {
          "id": "weakness:maliciously crafted STP file",
          "keyphrase": "maliciously crafted STP file",
          "type": "weakness"
        },
        {
          "id": "impact:cause a crash",
          "keyphrase": "cause a crash",
          "type": "impact"
        },
        {
          "id": "impact:execute arbitrary code",
          "keyphrase": "execute arbitrary code",
          "type": "impact"
        },
        {
          "id": "impact:write sensitive data",
          "keyphrase": "write sensitive data",
          "type": "impact"
        }
      ],
      "125": [
        {
          "id": "weakness:maliciously crafted STP file",
          "keyphrase": "maliciously crafted STP file",
          "type": "weakness"
        },
        {
          "id": "impact:cause a crash",
          "keyphrase": "cause a crash",
          "type": "impact"
        },
        {
          "id": "impact:write sensitive data",
          "keyphrase": "write sensitive data",
          "type": "impact"
        },
        {
          "id": "product:Autodesk AutoCAD",
          "keyphrase": "Autodesk AutoCAD",
          "type": "product"
        }
      ],
      "119": [
        {
          "id": "impact:execute arbitrary code",
          "keyphrase": "execute arbitrary code",
          "type": "impact"
        },
        {
          "id": "component:ACTranslators.exe",
          "keyphrase": "ACTranslators.exe",
          "type": "component"
        }
      ],
      "123": [
        {
          "id": "product:Autodesk AutoCAD",
          "keyphrase": "Autodesk AutoCAD",
          "type": "product"
        }
      ],
      "427": [
        {
          "id": "component:ACTranslators.exe",
          "keyphrase": "ACTranslators.exe",
          "type": "component"
        }
      ],
      "276": [
        {
          "id": "component:ACTranslators.exe",
          "keyphrase": "ACTranslators.exe",
          "type": "component"
        }
      ]
    },
    "relevant_cwes": [
      {
        "metadata": {
          "doc_id": "787",
          "name": "Out-of-bounds Write",
          "source": "sparse",
          "original_content": "The product writes data past the end, or before the beginning, of the intended buffer.",
          "keyphrase_sources": [
            {
              "id": "weakness:Memory Corruption",
              "keyphrase": "Memory Corruption",
              "type": "weakness"
            },
            {
              "id": "weakness:maliciously crafted STP file",
              "keyphrase": "maliciously crafted STP file",
              "type": "weakness"
            },
            {
              "id": "impact:cause a crash",
              "keyphrase": "cause a crash",
              "type": "impact"
            },
            {
              "id": "impact:execute arbitrary code",
              "keyphrase": "execute arbitrary code",
              "type": "impact"
            },
            {
              "id": "impact:write sensitive data",
              "keyphrase": "write sensitive data",
              "type": "impact"
            },
            {
              "id": "product:Autodesk AutoCAD",
              "keyphrase": "Autodesk AutoCAD",
              "type": "product"
            },
            {
              "id": "component:ACTranslators.exe",
              "keyphrase": "ACTranslators.exe",
              "type": "component"
            }
          ]
        },
        "similarity": 326.3747083621021
      },
      {
        "metadata": {
          "doc_id": "122",
          "name": "Heap-based Buffer Overflow",
          "source": "sparse",
          "original_content": "A heap overflow condition is a buffer overflow, where the buffer that can be overwritten is allocated in the heap portion of memory, generally meaning that the buffer was allocated using a routine such as malloc().",
          "keyphrase_sources": [
            {
              "id": "weakness:Memory Corruption",
              "keyphrase": "Memory Corruption",
              "type": "weakness"
            },
            {
              "id": "weakness:maliciously crafted STP file",
              "keyphrase": "maliciously crafted STP file",
              "type": "weakness"
            },
            {
              "id": "impact:cause a crash",
              "keyphrase": "cause a crash",
              "type": "impact"
            },
            {
              "id": "impact:execute arbitrary code",
              "keyphrase": "execute arbitrary code",
              "type": "impact"
            },
            {
              "id": "impact:write sensitive data",
              "keyphrase": "write sensitive data",
              "type": "impact"
            },
            {
              "id": "product:Autodesk AutoCAD",
              "keyphrase": "Autodesk AutoCAD",
              "type": "product"
            }
          ]
        },
        "similarity": 283.41188042666863
      },
      {
        "metadata": {
          "doc_id": "788",
          "name": "Access of Memory Location After End of Buffer",
          "source": "sparse",
          "original_content": "The product reads or writes to a buffer using an index or pointer that references a memory location after the end of the buffer.",
          "keyphrase_sources": [
            {
              "id": "weakness:Memory Corruption",
              "keyphrase": "Memory Corruption",
              "type": "weakness"
            }
          ]
        },
        "similarity": 275.4755323316423
      },
      {
        "metadata": {
          "doc_id": "190",
          "name": "Integer Overflow or Wraparound",
          "source": "sparse",
          "original_content": "The product performs a calculation that can\n         produce an integer overflow or wraparound when the logic\n         assumes that the resulting value will always be larger than\n         the original value. This occurs when an integer value is\n         incremented to a value that is too large to store in the\n         associated representation. When this occurs, the value may\n         become a very small or negative number.",
          "keyphrase_sources": [
            {
              "id": "weakness:Memory Corruption",
              "keyphrase": "Memory Corruption",
              "type": "weakness"
            }
          ]
        },
        "similarity": 272.172815602269
      },
      {
        "metadata": {
          "doc_id": "121",
          "name": "Stack-based Buffer Overflow",
          "source": "sparse",
          "original_content": "A stack-based buffer overflow condition is a condition where the buffer being overwritten is allocated on the stack (i.e., is a local variable or, rarely, a parameter to a function).",
          "keyphrase_sources": [
            {
              "id": "weakness:maliciously crafted STP file",
              "keyphrase": "maliciously crafted STP file",
              "type": "weakness"
            },
            {
              "id": "impact:cause a crash",
              "keyphrase": "cause a crash",
              "type": "impact"
            },
            {
              "id": "impact:execute arbitrary code",
              "keyphrase": "execute arbitrary code",
              "type": "impact"
            },
            {
              "id": "impact:write sensitive data",
              "keyphrase": "write sensitive data",
              "type": "impact"
            },
            {
              "id": "product:Autodesk AutoCAD",
              "keyphrase": "Autodesk AutoCAD",
              "type": "product"
            },
            {
              "id": "component:ACTranslators.exe",
              "keyphrase": "ACTranslators.exe",
              "type": "component"
            }
          ]
        },
        "similarity": 267.1213855244518
      },
      {
        "metadata": {
          "doc_id": "843",
          "name": "Access of Resource Using Incompatible Type ('Type Confusion')",
          "source": "sparse",
          "original_content": "The product allocates or initializes a resource such as a pointer, object, or variable using one type, but it later accesses that resource using a type that is incompatible with the original type.",
          "keyphrase_sources": [
            {
              "id": "weakness:Memory Corruption",
              "keyphrase": "Memory Corruption",
              "type": "weakness"
            }
          ]
        },
        "similarity": 267.0094875962169
      },
      {
        "metadata": {
          "doc_id": "20",
          "name": "Improper Input Validation",
          "source": "sparse",
          "original_content": "The product receives input or data, but it does\n        not validate or incorrectly validates that the input has the\n        properties that are required to process the data safely and\n        correctly.",
          "keyphrase_sources": [
            {
              "id": "weakness:maliciously crafted STP file",
              "keyphrase": "maliciously crafted STP file",
              "type": "weakness"
            },
            {
              "id": "impact:cause a crash",
              "keyphrase": "cause a crash",
              "type": "impact"
            },
            {
              "id": "impact:execute arbitrary code",
              "keyphrase": "execute arbitrary code",
              "type": "impact"
            },
            {
              "id": "impact:write sensitive data",
              "keyphrase": "write sensitive data",
              "type": "impact"
            }
          ]
        },
        "similarity": 264.99028235792923
      },
      {
        "metadata": {
          "doc_id": "125",
          "name": "Out-of-bounds Read",
          "source": "sparse",
          "original_content": "The product reads data past the end, or before the beginning, of the intended buffer.",
          "keyphrase_sources": [
            {
              "id": "weakness:maliciously crafted STP file",
              "keyphrase": "maliciously crafted STP file",
              "type": "weakness"
            },
            {
              "id": "impact:cause a crash",
              "keyphrase": "cause a crash",
              "type": "impact"
            },
            {
              "id": "impact:write sensitive data",
              "keyphrase": "write sensitive data",
              "type": "impact"
            },
            {
              "id": "product:Autodesk AutoCAD",
              "keyphrase": "Autodesk AutoCAD",
              "type": "product"
            }
          ]
        },
        "similarity": 260.65810974269414
      },
      {
        "metadata": {
          "doc_id": "119",
          "name": "Improper Restriction of Operations within the Bounds of a Memory Buffer",
          "source": "sparse",
          "original_content": "The product performs operations on a memory buffer, but it reads from or writes to a memory location outside the buffer's intended boundary. This may result in read or write operations on unexpected memory locations that could be linked to other variables, data structures, or internal program data.",
          "keyphrase_sources": [
            {
              "id": "impact:execute arbitrary code",
              "keyphrase": "execute arbitrary code",
              "type": "impact"
            },
            {
              "id": "component:ACTranslators.exe",
              "keyphrase": "ACTranslators.exe",
              "type": "component"
            }
          ]
        },
        "similarity": 90.58580459917943
      },
      {
        "metadata": {
          "doc_id": "427",
          "name": "Uncontrolled Search Path Element",
          "source": "sparse",
          "original_content": "The product uses a fixed or controlled search path to find resources, but one or more locations in that path can be under the control of unintended actors.",
          "keyphrase_sources": [
            {
              "id": "component:ACTranslators.exe",
              "keyphrase": "ACTranslators.exe",
              "type": "component"
            }
          ]
        },
        "similarity": 90.16598911812883
      },
      {
        "metadata": {
          "doc_id": "123",
          "name": "Write-what-where Condition",
          "source": "sparse",
          "original_content": "Any condition where the attacker has the ability to write an arbitrary value to an arbitrary location, often as the result of a buffer overflow.",
          "keyphrase_sources": [
            {
              "id": "product:Autodesk AutoCAD",
              "keyphrase": "Autodesk AutoCAD",
              "type": "product"
            }
          ]
        },
        "similarity": 88.8824902736127
      },
      {
        "metadata": {
          "doc_id": "276",
          "name": "Incorrect Default Permissions",
          "source": "sparse",
          "original_content": "During installation, installed file permissions are set to allow anyone to modify those files.",
          "keyphrase_sources": [
            {
              "id": "component:ACTranslators.exe",
              "keyphrase": "ACTranslators.exe",
              "type": "component"
            }
          ]
        },
        "similarity": 88.37007997077774
      }
    ],
    "enhanced_query": "# Vulnerability Description\n\n    A **maliciously crafted STP file** when parsed in ACTranslators.exe through Autodesk AutoCAD can force a **Memory Corruption** vulnerability. A malicious actor can leverage this vulnerability to cause a crash, write sensitive data, or execute arbitrary code in the context of the current process.\n\n    # Keyphrase-Specific CWE Analysis\n    This vulnerability contains multiple keyphrases that may map to different CWEs. \n    Please analyze each keyphrase separately and determine the most appropriate CWE(s) for each.\n\n    ## WEAKNESS: 'Memory Corruption'\n\nRelevant CWEs for this WEAKNESS:\n\n### 1. CWE-787: Out-of-bounds Write (Score: 326.37)\n\nThe product writes data past the end, or before the beginning, of the intended buffer....\n\n### 2. CWE-122: Heap-based Buffer Overflow (Score: 283.41)\n\nA heap overflow condition is a buffer overflow, where the buffer that can be overwritten is allocated in the heap portion of memory, generally meaning that the buffer was allocated using a routine such as malloc()....\n\n### 3. CWE-788: Access of Memory Location After End of Buffer (Score: 275.48)\n\nThe product reads or writes to a buffer using an index or pointer that references a memory location after the end of the buffer....\n\n### 4. CWE-190: Integer Overflow or Wraparound (Score: 272.17)\n\nThe product performs a calculation that can\n         produce an integer overflow or wraparound when the logic\n         assumes that the resulting value will always be larger than\n         the original value. This occurs when an integer value is\n         incremented to a value that is too large to st...\n\n### 5. CWE-843: Access of Resource Using Incompatible Type ('Type Confusion') (Score: 267.01)\n\nThe product allocates or initializes a resource such as a pointer, object, or variable using one type, but it later accesses that resource using a type that is incompatible with the original type....\n\n## WEAKNESS: 'maliciously crafted STP file'\n\nRelevant CWEs for this WEAKNESS:\n\n### 1. CWE-787: Out-of-bounds Write (Score: 326.37)\n\nThe product writes data past the end, or before the beginning, of the intended buffer....\n\n### 2. CWE-122: Heap-based Buffer Overflow (Score: 283.41)\n\nA heap overflow condition is a buffer overflow, where the buffer that can be overwritten is allocated in the heap portion of memory, generally meaning that the buffer was allocated using a routine such as malloc()....\n\n### 3. CWE-121: Stack-based Buffer Overflow (Score: 267.12)\n\nA stack-based buffer overflow condition is a condition where the buffer being overwritten is allocated on the stack (i.e., is a local variable or, rarely, a parameter to a function)....\n\n### 4. CWE-20: Improper Input Validation (Score: 264.99)\n\nThe product receives input or data, but it does\n        not validate or incorrectly validates that the input has the\n        properties that are required to process the data safely and\n        correctly....\n\n### 5. CWE-125: Out-of-bounds Read (Score: 260.66)\n\nThe product reads data past the end, or before the beginning, of the intended buffer....\n\n## IMPACT: 'cause a crash'\n\nRelevant CWEs for this IMPACT:\n\n### 1. CWE-787: Out-of-bounds Write (Score: 326.37)\n\nThe product writes data past the end, or before the beginning, of the intended buffer....\n\n### 2. CWE-122: Heap-based Buffer Overflow (Score: 283.41)\n\nA heap overflow condition is a buffer overflow, where the buffer that can be overwritten is allocated in the heap portion of memory, generally meaning that the buffer was allocated using a routine such as malloc()....\n\n### 3. CWE-121: Stack-based Buffer Overflow (Score: 267.12)\n\nA stack-based buffer overflow condition is a condition where the buffer being overwritten is allocated on the stack (i.e., is a local variable or, rarely, a parameter to a function)....\n\n### 4. CWE-20: Improper Input Validation (Score: 264.99)\n\nThe product receives input or data, but it does\n        not validate or incorrectly validates that the input has the\n        properties that are required to process the data safely and\n        correctly....\n\n### 5. CWE-125: Out-of-bounds Read (Score: 260.66)\n\nThe product reads data past the end, or before the beginning, of the intended buffer....\n\n## IMPACT: 'execute arbitrary code'\n\nRelevant CWEs for this IMPACT:\n\n### 1. CWE-787: Out-of-bounds Write (Score: 326.37)\n\nThe product writes data past the end, or before the beginning, of the intended buffer....\n\n### 2. CWE-122: Heap-based Buffer Overflow (Score: 283.41)\n\nA heap overflow condition is a buffer overflow, where the buffer that can be overwritten is allocated in the heap portion of memory, generally meaning that the buffer was allocated using a routine such as malloc()....\n\n### 3. CWE-121: Stack-based Buffer Overflow (Score: 267.12)\n\nA stack-based buffer overflow condition is a condition where the buffer being overwritten is allocated on the stack (i.e., is a local variable or, rarely, a parameter to a function)....\n\n### 4. CWE-20: Improper Input Validation (Score: 264.99)\n\nThe product receives input or data, but it does\n        not validate or incorrectly validates that the input has the\n        properties that are required to process the data safely and\n        correctly....\n\n### 5. CWE-119: Improper Restriction of Operations within the Bounds of a Memory Buffer (Score: 90.59)\n\nThe product performs operations on a memory buffer, but it reads from or writes to a memory location outside the buffer's intended boundary. This may result in read or write operations on unexpected memory locations that could be linked to other variables, data structures, or internal program data....\n\n## IMPACT: 'write sensitive data'\n\nRelevant CWEs for this IMPACT:\n\n### 1. CWE-787: Out-of-bounds Write (Score: 326.37)\n\nThe product writes data past the end, or before the beginning, of the intended buffer....\n\n### 2. CWE-122: Heap-based Buffer Overflow (Score: 283.41)\n\nA heap overflow condition is a buffer overflow, where the buffer that can be overwritten is allocated in the heap portion of memory, generally meaning that the buffer was allocated using a routine such as malloc()....\n\n### 3. CWE-121: Stack-based Buffer Overflow (Score: 267.12)\n\nA stack-based buffer overflow condition is a condition where the buffer being overwritten is allocated on the stack (i.e., is a local variable or, rarely, a parameter to a function)....\n\n### 4. CWE-20: Improper Input Validation (Score: 264.99)\n\nThe product receives input or data, but it does\n        not validate or incorrectly validates that the input has the\n        properties that are required to process the data safely and\n        correctly....\n\n### 5. CWE-125: Out-of-bounds Read (Score: 260.66)\n\nThe product reads data past the end, or before the beginning, of the intended buffer....\n\n## PRODUCT: 'Autodesk AutoCAD'\n\nRelevant CWEs for this PRODUCT:\n\n### 1. CWE-787: Out-of-bounds Write (Score: 326.37)\n\nThe product writes data past the end, or before the beginning, of the intended buffer....\n\n### 2. CWE-122: Heap-based Buffer Overflow (Score: 283.41)\n\nA heap overflow condition is a buffer overflow, where the buffer that can be overwritten is allocated in the heap portion of memory, generally meaning that the buffer was allocated using a routine such as malloc()....\n\n### 3. CWE-121: Stack-based Buffer Overflow (Score: 267.12)\n\nA stack-based buffer overflow condition is a condition where the buffer being overwritten is allocated on the stack (i.e., is a local variable or, rarely, a parameter to a function)....\n\n### 4. CWE-125: Out-of-bounds Read (Score: 260.66)\n\nThe product reads data past the end, or before the beginning, of the intended buffer....\n\n### 5. CWE-123: Write-what-where Condition (Score: 88.88)\n\nAny condition where the attacker has the ability to write an arbitrary value to an arbitrary location, often as the result of a buffer overflow....\n\n## COMPONENT: 'ACTranslators.exe'\n\nRelevant CWEs for this COMPONENT:\n\n### 1. CWE-787: Out-of-bounds Write (Score: 326.37)\n\nThe product writes data past the end, or before the beginning, of the intended buffer....\n\n### 2. CWE-121: Stack-based Buffer Overflow (Score: 267.12)\n\nA stack-based buffer overflow condition is a condition where the buffer being overwritten is allocated on the stack (i.e., is a local variable or, rarely, a parameter to a function)....\n\n### 3. CWE-119: Improper Restriction of Operations within the Bounds of a Memory Buffer (Score: 90.59)\n\nThe product performs operations on a memory buffer, but it reads from or writes to a memory location outside the buffer's intended boundary. This may result in read or write operations on unexpected memory locations that could be linked to other variables, data structures, or internal program data....\n\n### 4. CWE-427: Uncontrolled Search Path Element (Score: 90.17)\n\nThe product uses a fixed or controlled search path to find resources, but one or more locations in that path can be under the control of unintended actors....\n\n### 5. CWE-276: Incorrect Default Permissions (Score: 88.37)\n\nDuring installation, installed file permissions are set to allow anyone to modify those files....\n\n\n    # Analysis Instructions\n    1. For each keyphrase, identify the most appropriate CWE(s) that represent the weakness.\n    2. Consider how the different keyphrases might relate to each other in the vulnerability chain.\n    3. Provide a final determination of primary CWE(s) and any secondary CWEs.\n    4. Format your response using the standard analysis template.\n\n    Please analyze how these different weaknesses interact and provide a comprehensive CWE classification.\n    "
  },
  "retrieval_time": 1.2389237880706787
}