{
  "vulnerability_info": "VulnerabilityInfo(cve_id='CVE-2024-8534', description='**Memory safety vulnerability** leading to **memory corruption** and Denial of Servicein NetScaler ADC and Gateway if the appliance must be configured as a Gateway (VPN Vserver) with RDP Feature enabledOR the appliance must be configured as a Gateway (VPN Vserver) and RDP Proxy Server Profile is created and set to Gateway (VPN Vserver)OR the appliance must be configured as a Auth Server (AAA Vserver) with RDP Feature enabled', key_phrases={'rootcause': '', 'weakness': ['Memory safety vulnerability', 'memory corruption'], 'impact': 'memory corruption and Denial of Service', 'vector': '', 'attacker': '', 'product': 'NetScaler ADC and Gateway', 'version': '', 'component': ''}, reference_content='## CVE-2024-8534 Analysis\\n\\nThis content is **RELEVANT** to CVE-2024-8534.\\n\\n**Root cause of vulnerability:**\\n\\nMemory safety vulnerability leading to memory corruption.\\n\\n**Weaknesses/vulnerabilities present:**\\n\\n*   CWE-119: Improper Restriction of Operations within the Bounds of a Memory Buffer\\n\\n**Impact of exploitation:**\\n\\nDenial of Service\\n\\n**Attack vectors:**\\n\\nThe vulnerability is triggered when the appliance is configured in one of the following ways:\\n\\n*   As a Gateway (VPN Vserver) with RDP Feature enabled\\n*   As a Gateway (VPN Vserver) and an RDP Proxy Server Profile is created and set to the Gateway (VPN Vserver)\\n*   As an Auth Server (AAA Vserver) with RDP Feature enabled\\n\\n**Required attacker capabilities/position:**\\n\\nThe attacker can exploit the vulnerability without authentication (PR:N). The attack requires network access (AV:N) and has low attack complexity (AC:L).\\n\\n**Mitigation or fix:**\\n\\n*   Upgrade to NetScaler ADC and NetScaler Gateway 14.1-29.72 or later releases.\\n*   Upgrade to NetScaler ADC and NetScaler Gateway 13.1-55.34 or later releases of 13.1.\\n*   Upgrade to NetScaler ADC 13.1-FIPS 13.1-37.207 or later releases of 13.1-FIPS.\\n*   Upgrade to NetScaler ADC 12.1-FIPS 12.1-55.321 or later releases of 12.1-FIPS.\\n*   Upgrade to NetScaler ADC 12.1-NDcPP 12.1-55.321 or later releases of 12.1-NDcPP.\\n*   Customers on EOL versions (12.1 and 13.0) are recommended to upgrade.\\n\\n**Additional Details (more than official CVE description):**\\n\\n*   The document provides specific `ns.conf` strings to help customers determine if their appliance is vulnerable.\\n*   CVSS v4.0 Base Score: 8.4 (CVSS:4.0/AV:N/AC:L/AT:P/PR:N/UI:N/VC:L/VI:H/VA:H/SC:N/SI:N/SA:L)\\n*   The bulletin also addresses CVE-2024-8535.\\n*   Acknowledgments are given to researchers who reported the vulnerability.\\n*   Instructions are provided for HA/Cluster setups.\\n*   A command to flush Kerberos tickets after upgrading is provided (`nsapimgr_wr.sh -ys call=ns_aaa_flush_kerberos_tickets`).', similar_info={'cwe_distribution': {}, 'cwe_consensus': '', 'similarity_stats': {'thresholds': [], 'total_samples_by_threshold': {}, 'top_cwes_by_threshold': {}}}, similarity_summary=SimilarityInsight(consensus_cwe='', top_cwes=[], confidence_levels={}, total_samples=0), analysis='', analysis_with_relationships='', criticism='', resolution='', relevant_cwes=[{'metadata': {'doc_id': '345', 'name': 'Insufficient Verification of Data Authenticity', 'source': 'sparse', 'original_content': 'The product does not sufficiently verify the origin or authenticity of data, in a way that causes it to accept invalid data.', 'keyphrase_sources': [{'id': 'weakness:Memory safety vulnerability', 'keyphrase': 'Memory safety vulnerability', 'type': 'weakness'}]}, 'similarity': np.float64(368.7358251981653)}, {'metadata': {'doc_id': '400', 'name': 'Uncontrolled Resource Consumption', 'source': 'sparse', 'original_content': 'The product does not properly control the allocation and maintenance of a limited resource, thereby enabling an actor to influence the amount of resources consumed, eventually leading to the exhaustion of available resources.', 'keyphrase_sources': [{'id': 'weakness:Memory safety vulnerability', 'keyphrase': 'Memory safety vulnerability', 'type': 'weakness'}, {'id': 'weakness:memory corruption', 'keyphrase': 'memory corruption', 'type': 'weakness'}, {'id': 'impact:memory corruption and Denial of Service', 'keyphrase': 'memory corruption and Denial of Service', 'type': 'impact'}, {'id': 'product:NetScaler ADC and Gateway', 'keyphrase': 'NetScaler ADC and Gateway', 'type': 'product'}]}, 'similarity': np.float64(363.6118741098516)}, {'metadata': {'doc_id': '787', 'name': 'Out-of-bounds Write', 'source': 'sparse', 'original_content': 'The product writes data past the end, or before the beginning, of the intended buffer.', 'keyphrase_sources': [{'id': 'weakness:Memory safety vulnerability', 'keyphrase': 'Memory safety vulnerability', 'type': 'weakness'}, {'id': 'weakness:memory corruption', 'keyphrase': 'memory corruption', 'type': 'weakness'}, {'id': 'impact:memory corruption and Denial of Service', 'keyphrase': 'memory corruption and Denial of Service', 'type': 'impact'}]}, 'similarity': np.float64(353.5369688278797)}, {'metadata': {'doc_id': '367', 'name': 'Time-of-check Time-of-use (TOCTOU) Race Condition', 'source': 'sparse', 'original_content': \"The product checks the state of a resource before using that resource, but the resource's state can change between the check and the use in a way that invalidates the results of the check. This can cause the product to perform invalid actions when the resource is in an unexpected state.\", 'keyphrase_sources': [{'id': 'weakness:Memory safety vulnerability', 'keyphrase': 'Memory safety vulnerability', 'type': 'weakness'}, {'id': 'weakness:memory corruption', 'keyphrase': 'memory corruption', 'type': 'weakness'}, {'id': 'impact:memory corruption and Denial of Service', 'keyphrase': 'memory corruption and Denial of Service', 'type': 'impact'}]}, 'similarity': np.float64(352.5162041987615)}, {'metadata': {'doc_id': '287', 'name': 'Improper Authentication', 'source': 'sparse', 'original_content': 'When an actor claims to have a given identity, the product does not prove or insufficiently proves that the claim is correct.', 'keyphrase_sources': [{'id': 'weakness:Memory safety vulnerability', 'keyphrase': 'Memory safety vulnerability', 'type': 'weakness'}, {'id': 'weakness:memory corruption', 'keyphrase': 'memory corruption', 'type': 'weakness'}, {'id': 'impact:memory corruption and Denial of Service', 'keyphrase': 'memory corruption and Denial of Service', 'type': 'impact'}, {'id': 'product:NetScaler ADC and Gateway', 'keyphrase': 'NetScaler ADC and Gateway', 'type': 'product'}]}, 'similarity': np.float64(350.28494125179685)}, {'metadata': {'doc_id': '863', 'name': 'Incorrect Authorization', 'source': 'sparse', 'original_content': 'The product performs an authorization check when an actor attempts to access a resource or perform an action, but it does not correctly perform the check.', 'keyphrase_sources': [{'id': 'weakness:memory corruption', 'keyphrase': 'memory corruption', 'type': 'weakness'}, {'id': 'product:NetScaler ADC and Gateway', 'keyphrase': 'NetScaler ADC and Gateway', 'type': 'product'}]}, 'similarity': np.float64(346.04030572866384)}, {'metadata': {'doc_id': '20', 'name': 'Improper Input Validation', 'source': 'sparse', 'original_content': 'The product receives input or data, but it does\\n        not validate or incorrectly validates that the input has the\\n        properties that are required to process the data safely and\\n        correctly.', 'keyphrase_sources': [{'id': 'impact:memory corruption and Denial of Service', 'keyphrase': 'memory corruption and Denial of Service', 'type': 'impact'}]}, 'similarity': np.float64(141.9874147575434)}, {'metadata': {'doc_id': '346', 'name': 'Origin Validation Error', 'source': 'sparse', 'original_content': 'The product does not properly verify that the source of data or communication is valid.', 'keyphrase_sources': [{'id': 'product:NetScaler ADC and Gateway', 'keyphrase': 'NetScaler ADC and Gateway', 'type': 'product'}]}, 'similarity': np.float64(139.22987076210583)}, {'metadata': {'doc_id': '1390', 'name': 'Weak Authentication', 'source': 'sparse', 'original_content': 'The product uses an authentication mechanism to restrict access to specific users or identities, but the mechanism does not sufficiently prove that the claimed identity is correct.', 'keyphrase_sources': [{'id': 'product:NetScaler ADC and Gateway', 'keyphrase': 'NetScaler ADC and Gateway', 'type': 'product'}]}, 'similarity': np.float64(129.73773644230286)}], identified_cwes={'analyzer': [], 'critic_additional': []})",
  "retrieval_results": {
    "has_multiple_keyphrases": true,
    "keyphrase_cwe_sets": {
      "weakness:Memory safety vulnerability": {
        "keyphrase": "Memory safety vulnerability",
        "type": "weakness",
        "cwes": [
          {
            "metadata": {
              "doc_id": "345",
              "name": "Insufficient Verification of Data Authenticity",
              "source": "sparse",
              "original_content": "The product does not sufficiently verify the origin or authenticity of data, in a way that causes it to accept invalid data.",
              "keyphrase_sources": [
                {
                  "id": "weakness:Memory safety vulnerability",
                  "keyphrase": "Memory safety vulnerability",
                  "type": "weakness"
                }
              ]
            },
            "similarity": 368.7358251981653
          },
          {
            "metadata": {
              "doc_id": "400",
              "name": "Uncontrolled Resource Consumption",
              "source": "sparse",
              "original_content": "The product does not properly control the allocation and maintenance of a limited resource, thereby enabling an actor to influence the amount of resources consumed, eventually leading to the exhaustion of available resources.",
              "keyphrase_sources": [
                {
                  "id": "weakness:Memory safety vulnerability",
                  "keyphrase": "Memory safety vulnerability",
                  "type": "weakness"
                },
                {
                  "id": "weakness:memory corruption",
                  "keyphrase": "memory corruption",
                  "type": "weakness"
                },
                {
                  "id": "impact:memory corruption and Denial of Service",
                  "keyphrase": "memory corruption and Denial of Service",
                  "type": "impact"
                },
                {
                  "id": "product:NetScaler ADC and Gateway",
                  "keyphrase": "NetScaler ADC and Gateway",
                  "type": "product"
                }
              ]
            },
            "similarity": 363.6118741098516
          },
          {
            "metadata": {
              "doc_id": "787",
              "name": "Out-of-bounds Write",
              "source": "sparse",
              "original_content": "The product writes data past the end, or before the beginning, of the intended buffer.",
              "keyphrase_sources": [
                {
                  "id": "weakness:Memory safety vulnerability",
                  "keyphrase": "Memory safety vulnerability",
                  "type": "weakness"
                },
                {
                  "id": "weakness:memory corruption",
                  "keyphrase": "memory corruption",
                  "type": "weakness"
                },
                {
                  "id": "impact:memory corruption and Denial of Service",
                  "keyphrase": "memory corruption and Denial of Service",
                  "type": "impact"
                }
              ]
            },
            "similarity": 353.5369688278797
          },
          {
            "metadata": {
              "doc_id": "367",
              "name": "Time-of-check Time-of-use (TOCTOU) Race Condition",
              "source": "sparse",
              "original_content": "The product checks the state of a resource before using that resource, but the resource's state can change between the check and the use in a way that invalidates the results of the check. This can cause the product to perform invalid actions when the resource is in an unexpected state.",
              "keyphrase_sources": [
                {
                  "id": "weakness:Memory safety vulnerability",
                  "keyphrase": "Memory safety vulnerability",
                  "type": "weakness"
                },
                {
                  "id": "weakness:memory corruption",
                  "keyphrase": "memory corruption",
                  "type": "weakness"
                },
                {
                  "id": "impact:memory corruption and Denial of Service",
                  "keyphrase": "memory corruption and Denial of Service",
                  "type": "impact"
                }
              ]
            },
            "similarity": 352.5162041987615
          },
          {
            "metadata": {
              "doc_id": "287",
              "name": "Improper Authentication",
              "source": "sparse",
              "original_content": "When an actor claims to have a given identity, the product does not prove or insufficiently proves that the claim is correct.",
              "keyphrase_sources": [
                {
                  "id": "weakness:Memory safety vulnerability",
                  "keyphrase": "Memory safety vulnerability",
                  "type": "weakness"
                },
                {
                  "id": "weakness:memory corruption",
                  "keyphrase": "memory corruption",
                  "type": "weakness"
                },
                {
                  "id": "impact:memory corruption and Denial of Service",
                  "keyphrase": "memory corruption and Denial of Service",
                  "type": "impact"
                },
                {
                  "id": "product:NetScaler ADC and Gateway",
                  "keyphrase": "NetScaler ADC and Gateway",
                  "type": "product"
                }
              ]
            },
            "similarity": 350.28494125179685
          }
        ]
      },
      "weakness:memory corruption": {
        "keyphrase": "memory corruption",
        "type": "weakness",
        "cwes": [
          {
            "metadata": {
              "doc_id": "367",
              "name": "Time-of-check Time-of-use (TOCTOU) Race Condition",
              "source": "sparse",
              "original_content": "The product checks the state of a resource before using that resource, but the resource's state can change between the check and the use in a way that invalidates the results of the check. This can cause the product to perform invalid actions when the resource is in an unexpected state."
            },
            "similarity": 363.8976558112221
          },
          {
            "metadata": {
              "doc_id": "400",
              "name": "Uncontrolled Resource Consumption",
              "source": "sparse",
              "original_content": "The product does not properly control the allocation and maintenance of a limited resource, thereby enabling an actor to influence the amount of resources consumed, eventually leading to the exhaustion of available resources."
            },
            "similarity": 360.6153559956835
          },
          {
            "metadata": {
              "doc_id": "287",
              "name": "Improper Authentication",
              "source": "sparse",
              "original_content": "When an actor claims to have a given identity, the product does not prove or insufficiently proves that the claim is correct."
            },
            "similarity": 349.31466209212044
          },
          {
            "metadata": {
              "doc_id": "787",
              "name": "Out-of-bounds Write",
              "source": "sparse",
              "original_content": "The product writes data past the end, or before the beginning, of the intended buffer."
            },
            "similarity": 347.15344418587273
          },
          {
            "metadata": {
              "doc_id": "863",
              "name": "Incorrect Authorization",
              "source": "sparse",
              "original_content": "The product performs an authorization check when an actor attempts to access a resource or perform an action, but it does not correctly perform the check.",
              "keyphrase_sources": [
                {
                  "id": "weakness:memory corruption",
                  "keyphrase": "memory corruption",
                  "type": "weakness"
                },
                {
                  "id": "product:NetScaler ADC and Gateway",
                  "keyphrase": "NetScaler ADC and Gateway",
                  "type": "product"
                }
              ]
            },
            "similarity": 346.04030572866384
          }
        ]
      },
      "impact:memory corruption and Denial of Service": {
        "keyphrase": "memory corruption and Denial of Service",
        "type": "impact",
        "cwes": [
          {
            "metadata": {
              "doc_id": "400",
              "name": "Uncontrolled Resource Consumption",
              "source": "sparse",
              "original_content": "The product does not properly control the allocation and maintenance of a limited resource, thereby enabling an actor to influence the amount of resources consumed, eventually leading to the exhaustion of available resources."
            },
            "similarity": 152.15436946092697
          },
          {
            "metadata": {
              "doc_id": "367",
              "name": "Time-of-check Time-of-use (TOCTOU) Race Condition",
              "source": "sparse",
              "original_content": "The product checks the state of a resource before using that resource, but the resource's state can change between the check and the use in a way that invalidates the results of the check. This can cause the product to perform invalid actions when the resource is in an unexpected state."
            },
            "similarity": 150.37319115927536
          },
          {
            "metadata": {
              "doc_id": "787",
              "name": "Out-of-bounds Write",
              "source": "sparse",
              "original_content": "The product writes data past the end, or before the beginning, of the intended buffer."
            },
            "similarity": 145.92311290330775
          },
          {
            "metadata": {
              "doc_id": "287",
              "name": "Improper Authentication",
              "source": "sparse",
              "original_content": "When an actor claims to have a given identity, the product does not prove or insufficiently proves that the claim is correct."
            },
            "similarity": 143.399524669057
          },
          {
            "metadata": {
              "doc_id": "20",
              "name": "Improper Input Validation",
              "source": "sparse",
              "original_content": "The product receives input or data, but it does\n        not validate or incorrectly validates that the input has the\n        properties that are required to process the data safely and\n        correctly.",
              "keyphrase_sources": [
                {
                  "id": "impact:memory corruption and Denial of Service",
                  "keyphrase": "memory corruption and Denial of Service",
                  "type": "impact"
                }
              ]
            },
            "similarity": 141.9874147575434
          }
        ]
      },
      "product:NetScaler ADC and Gateway": {
        "keyphrase": "NetScaler ADC and Gateway",
        "type": "product",
        "cwes": [
          {
            "metadata": {
              "doc_id": "400",
              "name": "Uncontrolled Resource Consumption",
              "source": "sparse",
              "original_content": "The product does not properly control the allocation and maintenance of a limited resource, thereby enabling an actor to influence the amount of resources consumed, eventually leading to the exhaustion of available resources."
            },
            "similarity": 141.68940422192813
          },
          {
            "metadata": {
              "doc_id": "346",
              "name": "Origin Validation Error",
              "source": "sparse",
              "original_content": "The product does not properly verify that the source of data or communication is valid.",
              "keyphrase_sources": [
                {
                  "id": "product:NetScaler ADC and Gateway",
                  "keyphrase": "NetScaler ADC and Gateway",
                  "type": "product"
                }
              ]
            },
            "similarity": 139.22987076210583
          },
          {
            "metadata": {
              "doc_id": "287",
              "name": "Improper Authentication",
              "source": "sparse",
              "original_content": "When an actor claims to have a given identity, the product does not prove or insufficiently proves that the claim is correct."
            },
            "similarity": 135.34421377961593
          },
          {
            "metadata": {
              "doc_id": "863",
              "name": "Incorrect Authorization",
              "source": "sparse",
              "original_content": "The product performs an authorization check when an actor attempts to access a resource or perform an action, but it does not correctly perform the check."
            },
            "similarity": 133.19547855315042
          },
          {
            "metadata": {
              "doc_id": "1390",
              "name": "Weak Authentication",
              "source": "sparse",
              "original_content": "The product uses an authentication mechanism to restrict access to specific users or identities, but the mechanism does not sufficiently prove that the claimed identity is correct.",
              "keyphrase_sources": [
                {
                  "id": "product:NetScaler ADC and Gateway",
                  "keyphrase": "NetScaler ADC and Gateway",
                  "type": "product"
                }
              ]
            },
            "similarity": 129.73773644230286
          }
        ]
      }
    },
    "keyphrase_mapping": {
      "345": [
        {
          "id": "weakness:Memory safety vulnerability",
          "keyphrase": "Memory safety vulnerability",
          "type": "weakness"
        }
      ],
      "400": [
        {
          "id": "weakness:Memory safety vulnerability",
          "keyphrase": "Memory safety vulnerability",
          "type": "weakness"
        },
        {
          "id": "weakness:memory corruption",
          "keyphrase": "memory corruption",
          "type": "weakness"
        },
        {
          "id": "impact:memory corruption and Denial of Service",
          "keyphrase": "memory corruption and Denial of Service",
          "type": "impact"
        },
        {
          "id": "product:NetScaler ADC and Gateway",
          "keyphrase": "NetScaler ADC and Gateway",
          "type": "product"
        }
      ],
      "787": [
        {
          "id": "weakness:Memory safety vulnerability",
          "keyphrase": "Memory safety vulnerability",
          "type": "weakness"
        },
        {
          "id": "weakness:memory corruption",
          "keyphrase": "memory corruption",
          "type": "weakness"
        },
        {
          "id": "impact:memory corruption and Denial of Service",
          "keyphrase": "memory corruption and Denial of Service",
          "type": "impact"
        }
      ],
      "367": [
        {
          "id": "weakness:Memory safety vulnerability",
          "keyphrase": "Memory safety vulnerability",
          "type": "weakness"
        },
        {
          "id": "weakness:memory corruption",
          "keyphrase": "memory corruption",
          "type": "weakness"
        },
        {
          "id": "impact:memory corruption and Denial of Service",
          "keyphrase": "memory corruption and Denial of Service",
          "type": "impact"
        }
      ],
      "287": [
        {
          "id": "weakness:Memory safety vulnerability",
          "keyphrase": "Memory safety vulnerability",
          "type": "weakness"
        },
        {
          "id": "weakness:memory corruption",
          "keyphrase": "memory corruption",
          "type": "weakness"
        },
        {
          "id": "impact:memory corruption and Denial of Service",
          "keyphrase": "memory corruption and Denial of Service",
          "type": "impact"
        },
        {
          "id": "product:NetScaler ADC and Gateway",
          "keyphrase": "NetScaler ADC and Gateway",
          "type": "product"
        }
      ],
      "863": [
        {
          "id": "weakness:memory corruption",
          "keyphrase": "memory corruption",
          "type": "weakness"
        },
        {
          "id": "product:NetScaler ADC and Gateway",
          "keyphrase": "NetScaler ADC and Gateway",
          "type": "product"
        }
      ],
      "20": [
        {
          "id": "impact:memory corruption and Denial of Service",
          "keyphrase": "memory corruption and Denial of Service",
          "type": "impact"
        }
      ],
      "346": [
        {
          "id": "product:NetScaler ADC and Gateway",
          "keyphrase": "NetScaler ADC and Gateway",
          "type": "product"
        }
      ],
      "1390": [
        {
          "id": "product:NetScaler ADC and Gateway",
          "keyphrase": "NetScaler ADC and Gateway",
          "type": "product"
        }
      ]
    },
    "relevant_cwes": [
      {
        "metadata": {
          "doc_id": "345",
          "name": "Insufficient Verification of Data Authenticity",
          "source": "sparse",
          "original_content": "The product does not sufficiently verify the origin or authenticity of data, in a way that causes it to accept invalid data.",
          "keyphrase_sources": [
            {
              "id": "weakness:Memory safety vulnerability",
              "keyphrase": "Memory safety vulnerability",
              "type": "weakness"
            }
          ]
        },
        "similarity": 368.7358251981653
      },
      {
        "metadata": {
          "doc_id": "400",
          "name": "Uncontrolled Resource Consumption",
          "source": "sparse",
          "original_content": "The product does not properly control the allocation and maintenance of a limited resource, thereby enabling an actor to influence the amount of resources consumed, eventually leading to the exhaustion of available resources.",
          "keyphrase_sources": [
            {
              "id": "weakness:Memory safety vulnerability",
              "keyphrase": "Memory safety vulnerability",
              "type": "weakness"
            },
            {
              "id": "weakness:memory corruption",
              "keyphrase": "memory corruption",
              "type": "weakness"
            },
            {
              "id": "impact:memory corruption and Denial of Service",
              "keyphrase": "memory corruption and Denial of Service",
              "type": "impact"
            },
            {
              "id": "product:NetScaler ADC and Gateway",
              "keyphrase": "NetScaler ADC and Gateway",
              "type": "product"
            }
          ]
        },
        "similarity": 363.6118741098516
      },
      {
        "metadata": {
          "doc_id": "787",
          "name": "Out-of-bounds Write",
          "source": "sparse",
          "original_content": "The product writes data past the end, or before the beginning, of the intended buffer.",
          "keyphrase_sources": [
            {
              "id": "weakness:Memory safety vulnerability",
              "keyphrase": "Memory safety vulnerability",
              "type": "weakness"
            },
            {
              "id": "weakness:memory corruption",
              "keyphrase": "memory corruption",
              "type": "weakness"
            },
            {
              "id": "impact:memory corruption and Denial of Service",
              "keyphrase": "memory corruption and Denial of Service",
              "type": "impact"
            }
          ]
        },
        "similarity": 353.5369688278797
      },
      {
        "metadata": {
          "doc_id": "367",
          "name": "Time-of-check Time-of-use (TOCTOU) Race Condition",
          "source": "sparse",
          "original_content": "The product checks the state of a resource before using that resource, but the resource's state can change between the check and the use in a way that invalidates the results of the check. This can cause the product to perform invalid actions when the resource is in an unexpected state.",
          "keyphrase_sources": [
            {
              "id": "weakness:Memory safety vulnerability",
              "keyphrase": "Memory safety vulnerability",
              "type": "weakness"
            },
            {
              "id": "weakness:memory corruption",
              "keyphrase": "memory corruption",
              "type": "weakness"
            },
            {
              "id": "impact:memory corruption and Denial of Service",
              "keyphrase": "memory corruption and Denial of Service",
              "type": "impact"
            }
          ]
        },
        "similarity": 352.5162041987615
      },
      {
        "metadata": {
          "doc_id": "287",
          "name": "Improper Authentication",
          "source": "sparse",
          "original_content": "When an actor claims to have a given identity, the product does not prove or insufficiently proves that the claim is correct.",
          "keyphrase_sources": [
            {
              "id": "weakness:Memory safety vulnerability",
              "keyphrase": "Memory safety vulnerability",
              "type": "weakness"
            },
            {
              "id": "weakness:memory corruption",
              "keyphrase": "memory corruption",
              "type": "weakness"
            },
            {
              "id": "impact:memory corruption and Denial of Service",
              "keyphrase": "memory corruption and Denial of Service",
              "type": "impact"
            },
            {
              "id": "product:NetScaler ADC and Gateway",
              "keyphrase": "NetScaler ADC and Gateway",
              "type": "product"
            }
          ]
        },
        "similarity": 350.28494125179685
      },
      {
        "metadata": {
          "doc_id": "863",
          "name": "Incorrect Authorization",
          "source": "sparse",
          "original_content": "The product performs an authorization check when an actor attempts to access a resource or perform an action, but it does not correctly perform the check.",
          "keyphrase_sources": [
            {
              "id": "weakness:memory corruption",
              "keyphrase": "memory corruption",
              "type": "weakness"
            },
            {
              "id": "product:NetScaler ADC and Gateway",
              "keyphrase": "NetScaler ADC and Gateway",
              "type": "product"
            }
          ]
        },
        "similarity": 346.04030572866384
      },
      {
        "metadata": {
          "doc_id": "20",
          "name": "Improper Input Validation",
          "source": "sparse",
          "original_content": "The product receives input or data, but it does\n        not validate or incorrectly validates that the input has the\n        properties that are required to process the data safely and\n        correctly.",
          "keyphrase_sources": [
            {
              "id": "impact:memory corruption and Denial of Service",
              "keyphrase": "memory corruption and Denial of Service",
              "type": "impact"
            }
          ]
        },
        "similarity": 141.9874147575434
      },
      {
        "metadata": {
          "doc_id": "346",
          "name": "Origin Validation Error",
          "source": "sparse",
          "original_content": "The product does not properly verify that the source of data or communication is valid.",
          "keyphrase_sources": [
            {
              "id": "product:NetScaler ADC and Gateway",
              "keyphrase": "NetScaler ADC and Gateway",
              "type": "product"
            }
          ]
        },
        "similarity": 139.22987076210583
      },
      {
        "metadata": {
          "doc_id": "1390",
          "name": "Weak Authentication",
          "source": "sparse",
          "original_content": "The product uses an authentication mechanism to restrict access to specific users or identities, but the mechanism does not sufficiently prove that the claimed identity is correct.",
          "keyphrase_sources": [
            {
              "id": "product:NetScaler ADC and Gateway",
              "keyphrase": "NetScaler ADC and Gateway",
              "type": "product"
            }
          ]
        },
        "similarity": 129.73773644230286
      }
    ],
    "enhanced_query": "# Vulnerability Description\n\n    **Memory safety vulnerability** leading to **memory corruption** and Denial of Servicein NetScaler ADC and Gateway if the appliance must be configured as a Gateway (VPN Vserver) with RDP Feature enabledOR the appliance must be configured as a Gateway (VPN Vserver) and RDP Proxy Server Profile is created and set to Gateway (VPN Vserver)OR the appliance must be configured as a Auth Server (AAA Vserver) with RDP Feature enabled\n\n    # Keyphrase-Specific CWE Analysis\n    This vulnerability contains multiple keyphrases that may map to different CWEs. \n    Please analyze each keyphrase separately and determine the most appropriate CWE(s) for each.\n\n    ## WEAKNESS: 'Memory safety vulnerability'\n\nRelevant CWEs for this WEAKNESS:\n\n### 1. CWE-345: Insufficient Verification of Data Authenticity (Score: 368.74)\n\nThe product does not sufficiently verify the origin or authenticity of data, in a way that causes it to accept invalid data....\n\n### 2. CWE-400: Uncontrolled Resource Consumption (Score: 363.61)\n\nThe product does not properly control the allocation and maintenance of a limited resource, thereby enabling an actor to influence the amount of resources consumed, eventually leading to the exhaustion of available resources....\n\n### 3. CWE-787: Out-of-bounds Write (Score: 353.54)\n\nThe product writes data past the end, or before the beginning, of the intended buffer....\n\n### 4. CWE-367: Time-of-check Time-of-use (TOCTOU) Race Condition (Score: 352.52)\n\nThe product checks the state of a resource before using that resource, but the resource's state can change between the check and the use in a way that invalidates the results of the check. This can cause the product to perform invalid actions when the resource is in an unexpected state....\n\n### 5. CWE-287: Improper Authentication (Score: 350.28)\n\nWhen an actor claims to have a given identity, the product does not prove or insufficiently proves that the claim is correct....\n\n## WEAKNESS: 'memory corruption'\n\nRelevant CWEs for this WEAKNESS:\n\n### 1. CWE-400: Uncontrolled Resource Consumption (Score: 363.61)\n\nThe product does not properly control the allocation and maintenance of a limited resource, thereby enabling an actor to influence the amount of resources consumed, eventually leading to the exhaustion of available resources....\n\n### 2. CWE-787: Out-of-bounds Write (Score: 353.54)\n\nThe product writes data past the end, or before the beginning, of the intended buffer....\n\n### 3. CWE-367: Time-of-check Time-of-use (TOCTOU) Race Condition (Score: 352.52)\n\nThe product checks the state of a resource before using that resource, but the resource's state can change between the check and the use in a way that invalidates the results of the check. This can cause the product to perform invalid actions when the resource is in an unexpected state....\n\n### 4. CWE-287: Improper Authentication (Score: 350.28)\n\nWhen an actor claims to have a given identity, the product does not prove or insufficiently proves that the claim is correct....\n\n### 5. CWE-863: Incorrect Authorization (Score: 346.04)\n\nThe product performs an authorization check when an actor attempts to access a resource or perform an action, but it does not correctly perform the check....\n\n## IMPACT: 'memory corruption and Denial of Service'\n\nRelevant CWEs for this IMPACT:\n\n### 1. CWE-400: Uncontrolled Resource Consumption (Score: 363.61)\n\nThe product does not properly control the allocation and maintenance of a limited resource, thereby enabling an actor to influence the amount of resources consumed, eventually leading to the exhaustion of available resources....\n\n### 2. CWE-787: Out-of-bounds Write (Score: 353.54)\n\nThe product writes data past the end, or before the beginning, of the intended buffer....\n\n### 3. CWE-367: Time-of-check Time-of-use (TOCTOU) Race Condition (Score: 352.52)\n\nThe product checks the state of a resource before using that resource, but the resource's state can change between the check and the use in a way that invalidates the results of the check. This can cause the product to perform invalid actions when the resource is in an unexpected state....\n\n### 4. CWE-287: Improper Authentication (Score: 350.28)\n\nWhen an actor claims to have a given identity, the product does not prove or insufficiently proves that the claim is correct....\n\n### 5. CWE-20: Improper Input Validation (Score: 141.99)\n\nThe product receives input or data, but it does\n        not validate or incorrectly validates that the input has the\n        properties that are required to process the data safely and\n        correctly....\n\n## PRODUCT: 'NetScaler ADC and Gateway'\n\nRelevant CWEs for this PRODUCT:\n\n### 1. CWE-400: Uncontrolled Resource Consumption (Score: 363.61)\n\nThe product does not properly control the allocation and maintenance of a limited resource, thereby enabling an actor to influence the amount of resources consumed, eventually leading to the exhaustion of available resources....\n\n### 2. CWE-287: Improper Authentication (Score: 350.28)\n\nWhen an actor claims to have a given identity, the product does not prove or insufficiently proves that the claim is correct....\n\n### 3. CWE-863: Incorrect Authorization (Score: 346.04)\n\nThe product performs an authorization check when an actor attempts to access a resource or perform an action, but it does not correctly perform the check....\n\n### 4. CWE-346: Origin Validation Error (Score: 139.23)\n\nThe product does not properly verify that the source of data or communication is valid....\n\n### 5. CWE-1390: Weak Authentication (Score: 129.74)\n\nThe product uses an authentication mechanism to restrict access to specific users or identities, but the mechanism does not sufficiently prove that the claimed identity is correct....\n\n\n    # Analysis Instructions\n    1. For each keyphrase, identify the most appropriate CWE(s) that represent the weakness.\n    2. Consider how the different keyphrases might relate to each other in the vulnerability chain.\n    3. Provide a final determination of primary CWE(s) and any secondary CWEs.\n    4. Format your response using the standard analysis template.\n\n    Please analyze how these different weaknesses interact and provide a comprehensive CWE classification.\n    "
  },
  "retrieval_time": 1.115818977355957
}