{
  "vulnerability_info": "VulnerabilityInfo(cve_id='CVE-2025-32481', description='Cross-Site Request Forgery (CSRF) vulnerability in ninotheme Nino Social Connect allows Stored **XSS**. This issue affects Nino Social Connect from n/a through 2.0.', key_phrases={'rootcause': 'improper CSRF protection', 'weakness': ['cross-site scripting', 'XSS'], 'impact': '', 'vector': '', 'attacker': '', 'product': 'ninotheme Nino Social Connect', 'version': 'n/a through 2.0', 'component': ''}, reference_content='Root cause of vulnerability:\\nThe Nino Social Connect WordPress plugin is vulnerable to Cross Site Request Forgery (CSRF).\\n\\nWeaknesses/vulnerabilities present:\\nCross Site Request Forgery (CSRF) vulnerability.\\n\\nImpact of exploitation:\\nA malicious actor could force higher privileged users to execute unwanted actions under their current authentication. The impact varies case by case.\\n\\nAttack vectors:\\nNot specified in the content.\\n\\nRequired attacker capabilities/position:\\nUnauthenticated.\\n\\nMitigation or fix:\\nNo official fix is available. Patchstack vPatching can auto-mitigate the vulnerability.\\n\\nAdditional details:\\n- CVSS score: 7.1 (Low severity)\\n- Vulnerable versions: <= 2.0\\n- Fixed in: N/A\\n- OWASP Top 10: A3: Injection\\n- Reported by: johska\\n- Published by Patchstack: 09 April 2025\\n- Plugin: Nino Social Connect\\n- PSID: b4443b1d9ebc\\n\\nThe content provides more detail than the placeholder CVE description.', similar_info={'cwe_distribution': {}, 'cwe_consensus': '', 'similarity_stats': {'thresholds': [], 'total_samples_by_threshold': {}, 'top_cwes_by_threshold': {}}}, similarity_summary=SimilarityInsight(consensus_cwe='', top_cwes=[], confidence_levels={}, total_samples=0), analysis='', analysis_with_relationships='', criticism='', resolution='', relevant_cwes=[{'metadata': {'doc_id': '352', 'name': 'Cross-Site Request Forgery (CSRF)', 'source': 'sparse', 'original_content': 'The web application does not, or can not, sufficiently verify whether a well-formed, valid, consistent request was intentionally provided by the user who submitted the request.', 'keyphrase_sources': [{'id': 'rootcause:improper CSRF protection', 'keyphrase': 'improper CSRF protection', 'type': 'rootcause'}, {'id': 'weakness:cross-site scripting', 'keyphrase': 'cross-site scripting', 'type': 'weakness'}, {'id': 'weakness:XSS', 'keyphrase': 'XSS', 'type': 'weakness'}, {'id': 'product:ninotheme Nino Social Connect', 'keyphrase': 'ninotheme Nino Social Connect', 'type': 'product'}, {'id': 'version:n/a through 2.0', 'keyphrase': 'n/a through 2.0', 'type': 'version'}]}, 'similarity': np.float64(229.00662834901993)}, {'metadata': {'doc_id': '80', 'name': 'Improper Neutralization of Script-Related HTML Tags in a Web Page (Basic XSS)', 'source': 'sparse', 'original_content': 'The product receives input from an upstream component, but it does not neutralize or incorrectly neutralizes special characters such as \"<\", \">\", and \"&\" that could be interpreted as web-scripting elements when they are sent to a downstream component that processes web pages.', 'keyphrase_sources': [{'id': 'weakness:cross-site scripting', 'keyphrase': 'cross-site scripting', 'type': 'weakness'}]}, 'similarity': np.float64(193.32280291817787)}, {'metadata': {'doc_id': '918', 'name': 'Server-Side Request Forgery (SSRF)', 'source': 'sparse', 'original_content': 'The web server receives a URL or similar request from an upstream component and retrieves the contents of this URL, but it does not sufficiently ensure that the request is being sent to the expected destination.', 'keyphrase_sources': [{'id': 'weakness:cross-site scripting', 'keyphrase': 'cross-site scripting', 'type': 'weakness'}, {'id': 'weakness:XSS', 'keyphrase': 'XSS', 'type': 'weakness'}, {'id': 'product:ninotheme Nino Social Connect', 'keyphrase': 'ninotheme Nino Social Connect', 'type': 'product'}, {'id': 'version:n/a through 2.0', 'keyphrase': 'n/a through 2.0', 'type': 'version'}]}, 'similarity': np.float64(192.96312770122697)}, {'metadata': {'doc_id': '1004', 'name': \"Sensitive Cookie Without 'HttpOnly' Flag\", 'source': 'sparse', 'original_content': 'The product uses a cookie to store sensitive information, but the cookie is not marked with the HttpOnly flag.', 'keyphrase_sources': [{'id': 'weakness:cross-site scripting', 'keyphrase': 'cross-site scripting', 'type': 'weakness'}, {'id': 'weakness:XSS', 'keyphrase': 'XSS', 'type': 'weakness'}]}, 'similarity': np.float64(188.1101769184704)}, {'metadata': {'doc_id': '79', 'name': \"Improper Neutralization of Input During Web Page Generation ('Cross-site Scripting')\", 'source': 'sparse', 'original_content': 'The product does not neutralize or incorrectly neutralizes user-controllable input before it is placed in output that is used as a web page that is served to other users.', 'keyphrase_sources': [{'id': 'rootcause:improper CSRF protection', 'keyphrase': 'improper CSRF protection', 'type': 'rootcause'}, {'id': 'weakness:cross-site scripting', 'keyphrase': 'cross-site scripting', 'type': 'weakness'}, {'id': 'weakness:XSS', 'keyphrase': 'XSS', 'type': 'weakness'}, {'id': 'product:ninotheme Nino Social Connect', 'keyphrase': 'ninotheme Nino Social Connect', 'type': 'product'}, {'id': 'version:n/a through 2.0', 'keyphrase': 'n/a through 2.0', 'type': 'version'}]}, 'similarity': np.float64(180.44915053424052)}, {'metadata': {'doc_id': '434', 'name': 'Unrestricted Upload of File with Dangerous Type', 'source': 'sparse', 'original_content': 'The product allows the upload or transfer of dangerous file types that are automatically processed within its environment.', 'keyphrase_sources': [{'id': 'rootcause:improper CSRF protection', 'keyphrase': 'improper CSRF protection', 'type': 'rootcause'}, {'id': 'weakness:XSS', 'keyphrase': 'XSS', 'type': 'weakness'}, {'id': 'product:ninotheme Nino Social Connect', 'keyphrase': 'ninotheme Nino Social Connect', 'type': 'product'}, {'id': 'version:n/a through 2.0', 'keyphrase': 'n/a through 2.0', 'type': 'version'}]}, 'similarity': np.float64(167.08514852976361)}, {'metadata': {'doc_id': '116', 'name': 'Improper Encoding or Escaping of Output', 'source': 'sparse', 'original_content': 'The product prepares a structured message for communication with another component, but encoding or escaping of the data is either missing or done incorrectly. As a result, the intended structure of the message is not preserved.', 'keyphrase_sources': [{'id': 'rootcause:improper CSRF protection', 'keyphrase': 'improper CSRF protection', 'type': 'rootcause'}]}, 'similarity': np.float64(162.5029904184208)}, {'metadata': {'doc_id': '862', 'name': 'Missing Authorization', 'source': 'sparse', 'original_content': 'The product does not perform an authorization check when an actor attempts to access a resource or perform an action.', 'keyphrase_sources': [{'id': 'rootcause:improper CSRF protection', 'keyphrase': 'improper CSRF protection', 'type': 'rootcause'}, {'id': 'product:ninotheme Nino Social Connect', 'keyphrase': 'ninotheme Nino Social Connect', 'type': 'product'}]}, 'similarity': np.float64(161.8390666624667)}, {'metadata': {'doc_id': '611', 'name': 'Improper Restriction of XML External Entity Reference', 'source': 'sparse', 'original_content': 'The product processes an XML document that can contain XML entities with URIs that resolve to documents outside of the intended sphere of control, causing the product to embed incorrect documents into its output.', 'keyphrase_sources': [{'id': 'version:n/a through 2.0', 'keyphrase': 'n/a through 2.0', 'type': 'version'}]}, 'similarity': np.float64(59.74853031787906)}], identified_cwes={'analyzer': [], 'critic_additional': []})",
  "retrieval_results": {
    "has_multiple_keyphrases": true,
    "keyphrase_cwe_sets": {
      "rootcause:improper CSRF protection": {
        "keyphrase": "improper CSRF protection",
        "type": "rootcause",
        "cwes": [
          {
            "metadata": {
              "doc_id": "352",
              "name": "Cross-Site Request Forgery (CSRF)",
              "source": "sparse",
              "original_content": "The web application does not, or can not, sufficiently verify whether a well-formed, valid, consistent request was intentionally provided by the user who submitted the request.",
              "keyphrase_sources": [
                {
                  "id": "rootcause:improper CSRF protection",
                  "keyphrase": "improper CSRF protection",
                  "type": "rootcause"
                },
                {
                  "id": "weakness:cross-site scripting",
                  "keyphrase": "cross-site scripting",
                  "type": "weakness"
                },
                {
                  "id": "weakness:XSS",
                  "keyphrase": "XSS",
                  "type": "weakness"
                },
                {
                  "id": "product:ninotheme Nino Social Connect",
                  "keyphrase": "ninotheme Nino Social Connect",
                  "type": "product"
                },
                {
                  "id": "version:n/a through 2.0",
                  "keyphrase": "n/a through 2.0",
                  "type": "version"
                }
              ]
            },
            "similarity": 229.00662834901993
          },
          {
            "metadata": {
              "doc_id": "79",
              "name": "Improper Neutralization of Input During Web Page Generation ('Cross-site Scripting')",
              "source": "sparse",
              "original_content": "The product does not neutralize or incorrectly neutralizes user-controllable input before it is placed in output that is used as a web page that is served to other users.",
              "keyphrase_sources": [
                {
                  "id": "rootcause:improper CSRF protection",
                  "keyphrase": "improper CSRF protection",
                  "type": "rootcause"
                },
                {
                  "id": "weakness:cross-site scripting",
                  "keyphrase": "cross-site scripting",
                  "type": "weakness"
                },
                {
                  "id": "weakness:XSS",
                  "keyphrase": "XSS",
                  "type": "weakness"
                },
                {
                  "id": "product:ninotheme Nino Social Connect",
                  "keyphrase": "ninotheme Nino Social Connect",
                  "type": "product"
                },
                {
                  "id": "version:n/a through 2.0",
                  "keyphrase": "n/a through 2.0",
                  "type": "version"
                }
              ]
            },
            "similarity": 180.44915053424052
          },
          {
            "metadata": {
              "doc_id": "434",
              "name": "Unrestricted Upload of File with Dangerous Type",
              "source": "sparse",
              "original_content": "The product allows the upload or transfer of dangerous file types that are automatically processed within its environment.",
              "keyphrase_sources": [
                {
                  "id": "rootcause:improper CSRF protection",
                  "keyphrase": "improper CSRF protection",
                  "type": "rootcause"
                },
                {
                  "id": "weakness:XSS",
                  "keyphrase": "XSS",
                  "type": "weakness"
                },
                {
                  "id": "product:ninotheme Nino Social Connect",
                  "keyphrase": "ninotheme Nino Social Connect",
                  "type": "product"
                },
                {
                  "id": "version:n/a through 2.0",
                  "keyphrase": "n/a through 2.0",
                  "type": "version"
                }
              ]
            },
            "similarity": 167.08514852976361
          },
          {
            "metadata": {
              "doc_id": "116",
              "name": "Improper Encoding or Escaping of Output",
              "source": "sparse",
              "original_content": "The product prepares a structured message for communication with another component, but encoding or escaping of the data is either missing or done incorrectly. As a result, the intended structure of the message is not preserved.",
              "keyphrase_sources": [
                {
                  "id": "rootcause:improper CSRF protection",
                  "keyphrase": "improper CSRF protection",
                  "type": "rootcause"
                }
              ]
            },
            "similarity": 162.5029904184208
          },
          {
            "metadata": {
              "doc_id": "862",
              "name": "Missing Authorization",
              "source": "sparse",
              "original_content": "The product does not perform an authorization check when an actor attempts to access a resource or perform an action.",
              "keyphrase_sources": [
                {
                  "id": "rootcause:improper CSRF protection",
                  "keyphrase": "improper CSRF protection",
                  "type": "rootcause"
                },
                {
                  "id": "product:ninotheme Nino Social Connect",
                  "keyphrase": "ninotheme Nino Social Connect",
                  "type": "product"
                }
              ]
            },
            "similarity": 161.8390666624667
          }
        ]
      },
      "weakness:cross-site scripting": {
        "keyphrase": "cross-site scripting",
        "type": "weakness",
        "cwes": [
          {
            "metadata": {
              "doc_id": "352",
              "name": "Cross-Site Request Forgery (CSRF)",
              "source": "sparse",
              "original_content": "The web application does not, or can not, sufficiently verify whether a well-formed, valid, consistent request was intentionally provided by the user who submitted the request."
            },
            "similarity": 252.04980667482982
          },
          {
            "metadata": {
              "doc_id": "79",
              "name": "Improper Neutralization of Input During Web Page Generation ('Cross-site Scripting')",
              "source": "sparse",
              "original_content": "The product does not neutralize or incorrectly neutralizes user-controllable input before it is placed in output that is used as a web page that is served to other users."
            },
            "similarity": 232.18476554209536
          },
          {
            "metadata": {
              "doc_id": "80",
              "name": "Improper Neutralization of Script-Related HTML Tags in a Web Page (Basic XSS)",
              "source": "sparse",
              "original_content": "The product receives input from an upstream component, but it does not neutralize or incorrectly neutralizes special characters such as \"<\", \">\", and \"&\" that could be interpreted as web-scripting elements when they are sent to a downstream component that processes web pages.",
              "keyphrase_sources": [
                {
                  "id": "weakness:cross-site scripting",
                  "keyphrase": "cross-site scripting",
                  "type": "weakness"
                }
              ]
            },
            "similarity": 193.32280291817787
          },
          {
            "metadata": {
              "doc_id": "918",
              "name": "Server-Side Request Forgery (SSRF)",
              "source": "sparse",
              "original_content": "The web server receives a URL or similar request from an upstream component and retrieves the contents of this URL, but it does not sufficiently ensure that the request is being sent to the expected destination.",
              "keyphrase_sources": [
                {
                  "id": "weakness:cross-site scripting",
                  "keyphrase": "cross-site scripting",
                  "type": "weakness"
                },
                {
                  "id": "weakness:XSS",
                  "keyphrase": "XSS",
                  "type": "weakness"
                },
                {
                  "id": "product:ninotheme Nino Social Connect",
                  "keyphrase": "ninotheme Nino Social Connect",
                  "type": "product"
                },
                {
                  "id": "version:n/a through 2.0",
                  "keyphrase": "n/a through 2.0",
                  "type": "version"
                }
              ]
            },
            "similarity": 192.96312770122697
          },
          {
            "metadata": {
              "doc_id": "1004",
              "name": "Sensitive Cookie Without 'HttpOnly' Flag",
              "source": "sparse",
              "original_content": "The product uses a cookie to store sensitive information, but the cookie is not marked with the HttpOnly flag.",
              "keyphrase_sources": [
                {
                  "id": "weakness:cross-site scripting",
                  "keyphrase": "cross-site scripting",
                  "type": "weakness"
                },
                {
                  "id": "weakness:XSS",
                  "keyphrase": "XSS",
                  "type": "weakness"
                }
              ]
            },
            "similarity": 188.1101769184704
          }
        ]
      },
      "weakness:XSS": {
        "keyphrase": "XSS",
        "type": "weakness",
        "cwes": [
          {
            "metadata": {
              "doc_id": "352",
              "name": "Cross-Site Request Forgery (CSRF)",
              "source": "sparse",
              "original_content": "The web application does not, or can not, sufficiently verify whether a well-formed, valid, consistent request was intentionally provided by the user who submitted the request."
            },
            "similarity": 184.0266613986939
          },
          {
            "metadata": {
              "doc_id": "79",
              "name": "Improper Neutralization of Input During Web Page Generation ('Cross-site Scripting')",
              "source": "sparse",
              "original_content": "The product does not neutralize or incorrectly neutralizes user-controllable input before it is placed in output that is used as a web page that is served to other users."
            },
            "similarity": 170.21997418520922
          },
          {
            "metadata": {
              "doc_id": "918",
              "name": "Server-Side Request Forgery (SSRF)",
              "source": "sparse",
              "original_content": "The web server receives a URL or similar request from an upstream component and retrieves the contents of this URL, but it does not sufficiently ensure that the request is being sent to the expected destination."
            },
            "similarity": 153.98897615133657
          },
          {
            "metadata": {
              "doc_id": "434",
              "name": "Unrestricted Upload of File with Dangerous Type",
              "source": "sparse",
              "original_content": "The product allows the upload or transfer of dangerous file types that are automatically processed within its environment."
            },
            "similarity": 143.69718231780146
          },
          {
            "metadata": {
              "doc_id": "1004",
              "name": "Sensitive Cookie Without 'HttpOnly' Flag",
              "source": "sparse",
              "original_content": "The product uses a cookie to store sensitive information, but the cookie is not marked with the HttpOnly flag."
            },
            "similarity": 143.55840017232558
          }
        ]
      },
      "product:ninotheme Nino Social Connect": {
        "keyphrase": "ninotheme Nino Social Connect",
        "type": "product",
        "cwes": [
          {
            "metadata": {
              "doc_id": "352",
              "name": "Cross-Site Request Forgery (CSRF)",
              "source": "sparse",
              "original_content": "The web application does not, or can not, sufficiently verify whether a well-formed, valid, consistent request was intentionally provided by the user who submitted the request."
            },
            "similarity": 58.362298157670196
          },
          {
            "metadata": {
              "doc_id": "79",
              "name": "Improper Neutralization of Input During Web Page Generation ('Cross-site Scripting')",
              "source": "sparse",
              "original_content": "The product does not neutralize or incorrectly neutralizes user-controllable input before it is placed in output that is used as a web page that is served to other users."
            },
            "similarity": 55.43770073042603
          },
          {
            "metadata": {
              "doc_id": "918",
              "name": "Server-Side Request Forgery (SSRF)",
              "source": "sparse",
              "original_content": "The web server receives a URL or similar request from an upstream component and retrieves the contents of this URL, but it does not sufficiently ensure that the request is being sent to the expected destination."
            },
            "similarity": 54.43190410412996
          },
          {
            "metadata": {
              "doc_id": "862",
              "name": "Missing Authorization",
              "source": "sparse",
              "original_content": "The product does not perform an authorization check when an actor attempts to access a resource or perform an action."
            },
            "similarity": 49.04617207982884
          },
          {
            "metadata": {
              "doc_id": "434",
              "name": "Unrestricted Upload of File with Dangerous Type",
              "source": "sparse",
              "original_content": "The product allows the upload or transfer of dangerous file types that are automatically processed within its environment."
            },
            "similarity": 46.91591439535843
          }
        ]
      },
      "version:n/a through 2.0": {
        "keyphrase": "n/a through 2.0",
        "type": "version",
        "cwes": [
          {
            "metadata": {
              "doc_id": "352",
              "name": "Cross-Site Request Forgery (CSRF)",
              "source": "sparse",
              "original_content": "The web application does not, or can not, sufficiently verify whether a well-formed, valid, consistent request was intentionally provided by the user who submitted the request."
            },
            "similarity": 70.35349130085372
          },
          {
            "metadata": {
              "doc_id": "79",
              "name": "Improper Neutralization of Input During Web Page Generation ('Cross-site Scripting')",
              "source": "sparse",
              "original_content": "The product does not neutralize or incorrectly neutralizes user-controllable input before it is placed in output that is used as a web page that is served to other users."
            },
            "similarity": 63.43829489088695
          },
          {
            "metadata": {
              "doc_id": "434",
              "name": "Unrestricted Upload of File with Dangerous Type",
              "source": "sparse",
              "original_content": "The product allows the upload or transfer of dangerous file types that are automatically processed within its environment."
            },
            "similarity": 62.96513545362225
          },
          {
            "metadata": {
              "doc_id": "918",
              "name": "Server-Side Request Forgery (SSRF)",
              "source": "sparse",
              "original_content": "The web server receives a URL or similar request from an upstream component and retrieves the contents of this URL, but it does not sufficiently ensure that the request is being sent to the expected destination."
            },
            "similarity": 61.38898001585874
          },
          {
            "metadata": {
              "doc_id": "611",
              "name": "Improper Restriction of XML External Entity Reference",
              "source": "sparse",
              "original_content": "The product processes an XML document that can contain XML entities with URIs that resolve to documents outside of the intended sphere of control, causing the product to embed incorrect documents into its output.",
              "keyphrase_sources": [
                {
                  "id": "version:n/a through 2.0",
                  "keyphrase": "n/a through 2.0",
                  "type": "version"
                }
              ]
            },
            "similarity": 59.74853031787906
          }
        ]
      }
    },
    "keyphrase_mapping": {
      "352": [
        {
          "id": "rootcause:improper CSRF protection",
          "keyphrase": "improper CSRF protection",
          "type": "rootcause"
        },
        {
          "id": "weakness:cross-site scripting",
          "keyphrase": "cross-site scripting",
          "type": "weakness"
        },
        {
          "id": "weakness:XSS",
          "keyphrase": "XSS",
          "type": "weakness"
        },
        {
          "id": "product:ninotheme Nino Social Connect",
          "keyphrase": "ninotheme Nino Social Connect",
          "type": "product"
        },
        {
          "id": "version:n/a through 2.0",
          "keyphrase": "n/a through 2.0",
          "type": "version"
        }
      ],
      "79": [
        {
          "id": "rootcause:improper CSRF protection",
          "keyphrase": "improper CSRF protection",
          "type": "rootcause"
        },
        {
          "id": "weakness:cross-site scripting",
          "keyphrase": "cross-site scripting",
          "type": "weakness"
        },
        {
          "id": "weakness:XSS",
          "keyphrase": "XSS",
          "type": "weakness"
        },
        {
          "id": "product:ninotheme Nino Social Connect",
          "keyphrase": "ninotheme Nino Social Connect",
          "type": "product"
        },
        {
          "id": "version:n/a through 2.0",
          "keyphrase": "n/a through 2.0",
          "type": "version"
        }
      ],
      "434": [
        {
          "id": "rootcause:improper CSRF protection",
          "keyphrase": "improper CSRF protection",
          "type": "rootcause"
        },
        {
          "id": "weakness:XSS",
          "keyphrase": "XSS",
          "type": "weakness"
        },
        {
          "id": "product:ninotheme Nino Social Connect",
          "keyphrase": "ninotheme Nino Social Connect",
          "type": "product"
        },
        {
          "id": "version:n/a through 2.0",
          "keyphrase": "n/a through 2.0",
          "type": "version"
        }
      ],
      "116": [
        {
          "id": "rootcause:improper CSRF protection",
          "keyphrase": "improper CSRF protection",
          "type": "rootcause"
        }
      ],
      "862": [
        {
          "id": "rootcause:improper CSRF protection",
          "keyphrase": "improper CSRF protection",
          "type": "rootcause"
        },
        {
          "id": "product:ninotheme Nino Social Connect",
          "keyphrase": "ninotheme Nino Social Connect",
          "type": "product"
        }
      ],
      "80": [
        {
          "id": "weakness:cross-site scripting",
          "keyphrase": "cross-site scripting",
          "type": "weakness"
        }
      ],
      "918": [
        {
          "id": "weakness:cross-site scripting",
          "keyphrase": "cross-site scripting",
          "type": "weakness"
        },
        {
          "id": "weakness:XSS",
          "keyphrase": "XSS",
          "type": "weakness"
        },
        {
          "id": "product:ninotheme Nino Social Connect",
          "keyphrase": "ninotheme Nino Social Connect",
          "type": "product"
        },
        {
          "id": "version:n/a through 2.0",
          "keyphrase": "n/a through 2.0",
          "type": "version"
        }
      ],
      "1004": [
        {
          "id": "weakness:cross-site scripting",
          "keyphrase": "cross-site scripting",
          "type": "weakness"
        },
        {
          "id": "weakness:XSS",
          "keyphrase": "XSS",
          "type": "weakness"
        }
      ],
      "611": [
        {
          "id": "version:n/a through 2.0",
          "keyphrase": "n/a through 2.0",
          "type": "version"
        }
      ]
    },
    "relevant_cwes": [
      {
        "metadata": {
          "doc_id": "352",
          "name": "Cross-Site Request Forgery (CSRF)",
          "source": "sparse",
          "original_content": "The web application does not, or can not, sufficiently verify whether a well-formed, valid, consistent request was intentionally provided by the user who submitted the request.",
          "keyphrase_sources": [
            {
              "id": "rootcause:improper CSRF protection",
              "keyphrase": "improper CSRF protection",
              "type": "rootcause"
            },
            {
              "id": "weakness:cross-site scripting",
              "keyphrase": "cross-site scripting",
              "type": "weakness"
            },
            {
              "id": "weakness:XSS",
              "keyphrase": "XSS",
              "type": "weakness"
            },
            {
              "id": "product:ninotheme Nino Social Connect",
              "keyphrase": "ninotheme Nino Social Connect",
              "type": "product"
            },
            {
              "id": "version:n/a through 2.0",
              "keyphrase": "n/a through 2.0",
              "type": "version"
            }
          ]
        },
        "similarity": 229.00662834901993
      },
      {
        "metadata": {
          "doc_id": "80",
          "name": "Improper Neutralization of Script-Related HTML Tags in a Web Page (Basic XSS)",
          "source": "sparse",
          "original_content": "The product receives input from an upstream component, but it does not neutralize or incorrectly neutralizes special characters such as \"<\", \">\", and \"&\" that could be interpreted as web-scripting elements when they are sent to a downstream component that processes web pages.",
          "keyphrase_sources": [
            {
              "id": "weakness:cross-site scripting",
              "keyphrase": "cross-site scripting",
              "type": "weakness"
            }
          ]
        },
        "similarity": 193.32280291817787
      },
      {
        "metadata": {
          "doc_id": "918",
          "name": "Server-Side Request Forgery (SSRF)",
          "source": "sparse",
          "original_content": "The web server receives a URL or similar request from an upstream component and retrieves the contents of this URL, but it does not sufficiently ensure that the request is being sent to the expected destination.",
          "keyphrase_sources": [
            {
              "id": "weakness:cross-site scripting",
              "keyphrase": "cross-site scripting",
              "type": "weakness"
            },
            {
              "id": "weakness:XSS",
              "keyphrase": "XSS",
              "type": "weakness"
            },
            {
              "id": "product:ninotheme Nino Social Connect",
              "keyphrase": "ninotheme Nino Social Connect",
              "type": "product"
            },
            {
              "id": "version:n/a through 2.0",
              "keyphrase": "n/a through 2.0",
              "type": "version"
            }
          ]
        },
        "similarity": 192.96312770122697
      },
      {
        "metadata": {
          "doc_id": "1004",
          "name": "Sensitive Cookie Without 'HttpOnly' Flag",
          "source": "sparse",
          "original_content": "The product uses a cookie to store sensitive information, but the cookie is not marked with the HttpOnly flag.",
          "keyphrase_sources": [
            {
              "id": "weakness:cross-site scripting",
              "keyphrase": "cross-site scripting",
              "type": "weakness"
            },
            {
              "id": "weakness:XSS",
              "keyphrase": "XSS",
              "type": "weakness"
            }
          ]
        },
        "similarity": 188.1101769184704
      },
      {
        "metadata": {
          "doc_id": "79",
          "name": "Improper Neutralization of Input During Web Page Generation ('Cross-site Scripting')",
          "source": "sparse",
          "original_content": "The product does not neutralize or incorrectly neutralizes user-controllable input before it is placed in output that is used as a web page that is served to other users.",
          "keyphrase_sources": [
            {
              "id": "rootcause:improper CSRF protection",
              "keyphrase": "improper CSRF protection",
              "type": "rootcause"
            },
            {
              "id": "weakness:cross-site scripting",
              "keyphrase": "cross-site scripting",
              "type": "weakness"
            },
            {
              "id": "weakness:XSS",
              "keyphrase": "XSS",
              "type": "weakness"
            },
            {
              "id": "product:ninotheme Nino Social Connect",
              "keyphrase": "ninotheme Nino Social Connect",
              "type": "product"
            },
            {
              "id": "version:n/a through 2.0",
              "keyphrase": "n/a through 2.0",
              "type": "version"
            }
          ]
        },
        "similarity": 180.44915053424052
      },
      {
        "metadata": {
          "doc_id": "434",
          "name": "Unrestricted Upload of File with Dangerous Type",
          "source": "sparse",
          "original_content": "The product allows the upload or transfer of dangerous file types that are automatically processed within its environment.",
          "keyphrase_sources": [
            {
              "id": "rootcause:improper CSRF protection",
              "keyphrase": "improper CSRF protection",
              "type": "rootcause"
            },
            {
              "id": "weakness:XSS",
              "keyphrase": "XSS",
              "type": "weakness"
            },
            {
              "id": "product:ninotheme Nino Social Connect",
              "keyphrase": "ninotheme Nino Social Connect",
              "type": "product"
            },
            {
              "id": "version:n/a through 2.0",
              "keyphrase": "n/a through 2.0",
              "type": "version"
            }
          ]
        },
        "similarity": 167.08514852976361
      },
      {
        "metadata": {
          "doc_id": "116",
          "name": "Improper Encoding or Escaping of Output",
          "source": "sparse",
          "original_content": "The product prepares a structured message for communication with another component, but encoding or escaping of the data is either missing or done incorrectly. As a result, the intended structure of the message is not preserved.",
          "keyphrase_sources": [
            {
              "id": "rootcause:improper CSRF protection",
              "keyphrase": "improper CSRF protection",
              "type": "rootcause"
            }
          ]
        },
        "similarity": 162.5029904184208
      },
      {
        "metadata": {
          "doc_id": "862",
          "name": "Missing Authorization",
          "source": "sparse",
          "original_content": "The product does not perform an authorization check when an actor attempts to access a resource or perform an action.",
          "keyphrase_sources": [
            {
              "id": "rootcause:improper CSRF protection",
              "keyphrase": "improper CSRF protection",
              "type": "rootcause"
            },
            {
              "id": "product:ninotheme Nino Social Connect",
              "keyphrase": "ninotheme Nino Social Connect",
              "type": "product"
            }
          ]
        },
        "similarity": 161.8390666624667
      },
      {
        "metadata": {
          "doc_id": "611",
          "name": "Improper Restriction of XML External Entity Reference",
          "source": "sparse",
          "original_content": "The product processes an XML document that can contain XML entities with URIs that resolve to documents outside of the intended sphere of control, causing the product to embed incorrect documents into its output.",
          "keyphrase_sources": [
            {
              "id": "version:n/a through 2.0",
              "keyphrase": "n/a through 2.0",
              "type": "version"
            }
          ]
        },
        "similarity": 59.74853031787906
      }
    ],
    "enhanced_query": "# Vulnerability Description\n\n    Cross-Site Request Forgery (CSRF) vulnerability in ninotheme Nino Social Connect allows Stored **XSS**. This issue affects Nino Social Connect from n/a through 2.0.\n\n    # Keyphrase-Specific CWE Analysis\n    This vulnerability contains multiple keyphrases that may map to different CWEs. \n    Please analyze each keyphrase separately and determine the most appropriate CWE(s) for each.\n\n    ## ROOTCAUSE: 'improper CSRF protection'\n\nRelevant CWEs for this ROOTCAUSE:\n\n### 1. CWE-352: Cross-Site Request Forgery (CSRF) (Score: 229.01)\n\nThe web application does not, or can not, sufficiently verify whether a well-formed, valid, consistent request was intentionally provided by the user who submitted the request....\n\n### 2. CWE-79: Improper Neutralization of Input During Web Page Generation ('Cross-site Scripting') (Score: 180.45)\n\nThe product does not neutralize or incorrectly neutralizes user-controllable input before it is placed in output that is used as a web page that is served to other users....\n\n### 3. CWE-434: Unrestricted Upload of File with Dangerous Type (Score: 167.09)\n\nThe product allows the upload or transfer of dangerous file types that are automatically processed within its environment....\n\n### 4. CWE-116: Improper Encoding or Escaping of Output (Score: 162.50)\n\nThe product prepares a structured message for communication with another component, but encoding or escaping of the data is either missing or done incorrectly. As a result, the intended structure of the message is not preserved....\n\n### 5. CWE-862: Missing Authorization (Score: 161.84)\n\nThe product does not perform an authorization check when an actor attempts to access a resource or perform an action....\n\n## WEAKNESS: 'cross-site scripting'\n\nRelevant CWEs for this WEAKNESS:\n\n### 1. CWE-352: Cross-Site Request Forgery (CSRF) (Score: 229.01)\n\nThe web application does not, or can not, sufficiently verify whether a well-formed, valid, consistent request was intentionally provided by the user who submitted the request....\n\n### 2. CWE-80: Improper Neutralization of Script-Related HTML Tags in a Web Page (Basic XSS) (Score: 193.32)\n\nThe product receives input from an upstream component, but it does not neutralize or incorrectly neutralizes special characters such as \"<\", \">\", and \"&\" that could be interpreted as web-scripting elements when they are sent to a downstream component that processes web pages....\n\n### 3. CWE-918: Server-Side Request Forgery (SSRF) (Score: 192.96)\n\nThe web server receives a URL or similar request from an upstream component and retrieves the contents of this URL, but it does not sufficiently ensure that the request is being sent to the expected destination....\n\n### 4. CWE-1004: Sensitive Cookie Without 'HttpOnly' Flag (Score: 188.11)\n\nThe product uses a cookie to store sensitive information, but the cookie is not marked with the HttpOnly flag....\n\n### 5. CWE-79: Improper Neutralization of Input During Web Page Generation ('Cross-site Scripting') (Score: 180.45)\n\nThe product does not neutralize or incorrectly neutralizes user-controllable input before it is placed in output that is used as a web page that is served to other users....\n\n## WEAKNESS: 'XSS'\n\nRelevant CWEs for this WEAKNESS:\n\n### 1. CWE-352: Cross-Site Request Forgery (CSRF) (Score: 229.01)\n\nThe web application does not, or can not, sufficiently verify whether a well-formed, valid, consistent request was intentionally provided by the user who submitted the request....\n\n### 2. CWE-918: Server-Side Request Forgery (SSRF) (Score: 192.96)\n\nThe web server receives a URL or similar request from an upstream component and retrieves the contents of this URL, but it does not sufficiently ensure that the request is being sent to the expected destination....\n\n### 3. CWE-1004: Sensitive Cookie Without 'HttpOnly' Flag (Score: 188.11)\n\nThe product uses a cookie to store sensitive information, but the cookie is not marked with the HttpOnly flag....\n\n### 4. CWE-79: Improper Neutralization of Input During Web Page Generation ('Cross-site Scripting') (Score: 180.45)\n\nThe product does not neutralize or incorrectly neutralizes user-controllable input before it is placed in output that is used as a web page that is served to other users....\n\n### 5. CWE-434: Unrestricted Upload of File with Dangerous Type (Score: 167.09)\n\nThe product allows the upload or transfer of dangerous file types that are automatically processed within its environment....\n\n## PRODUCT: 'ninotheme Nino Social Connect'\n\nRelevant CWEs for this PRODUCT:\n\n### 1. CWE-352: Cross-Site Request Forgery (CSRF) (Score: 229.01)\n\nThe web application does not, or can not, sufficiently verify whether a well-formed, valid, consistent request was intentionally provided by the user who submitted the request....\n\n### 2. CWE-918: Server-Side Request Forgery (SSRF) (Score: 192.96)\n\nThe web server receives a URL or similar request from an upstream component and retrieves the contents of this URL, but it does not sufficiently ensure that the request is being sent to the expected destination....\n\n### 3. CWE-79: Improper Neutralization of Input During Web Page Generation ('Cross-site Scripting') (Score: 180.45)\n\nThe product does not neutralize or incorrectly neutralizes user-controllable input before it is placed in output that is used as a web page that is served to other users....\n\n### 4. CWE-434: Unrestricted Upload of File with Dangerous Type (Score: 167.09)\n\nThe product allows the upload or transfer of dangerous file types that are automatically processed within its environment....\n\n### 5. CWE-862: Missing Authorization (Score: 161.84)\n\nThe product does not perform an authorization check when an actor attempts to access a resource or perform an action....\n\n## VERSION: 'n/a through 2.0'\n\nRelevant CWEs for this VERSION:\n\n### 1. CWE-352: Cross-Site Request Forgery (CSRF) (Score: 229.01)\n\nThe web application does not, or can not, sufficiently verify whether a well-formed, valid, consistent request was intentionally provided by the user who submitted the request....\n\n### 2. CWE-918: Server-Side Request Forgery (SSRF) (Score: 192.96)\n\nThe web server receives a URL or similar request from an upstream component and retrieves the contents of this URL, but it does not sufficiently ensure that the request is being sent to the expected destination....\n\n### 3. CWE-79: Improper Neutralization of Input During Web Page Generation ('Cross-site Scripting') (Score: 180.45)\n\nThe product does not neutralize or incorrectly neutralizes user-controllable input before it is placed in output that is used as a web page that is served to other users....\n\n### 4. CWE-434: Unrestricted Upload of File with Dangerous Type (Score: 167.09)\n\nThe product allows the upload or transfer of dangerous file types that are automatically processed within its environment....\n\n### 5. CWE-611: Improper Restriction of XML External Entity Reference (Score: 59.75)\n\nThe product processes an XML document that can contain XML entities with URIs that resolve to documents outside of the intended sphere of control, causing the product to embed incorrect documents into its output....\n\n\n    # Analysis Instructions\n    1. For each keyphrase, identify the most appropriate CWE(s) that represent the weakness.\n    2. Consider how the different keyphrases might relate to each other in the vulnerability chain.\n    3. Provide a final determination of primary CWE(s) and any secondary CWEs.\n    4. Format your response using the standard analysis template.\n\n    Please analyze how these different weaknesses interact and provide a comprehensive CWE classification.\n    "
  },
  "retrieval_time": 1.1435198783874512
}