{
  "cve_id": "CVE-2024-5791",
  "description": "The Online Booking & Scheduling Calendar for WordPress by vcita plugin for WordPress is vulnerable to Stored Cross-Site Scripting via the wp_id parameter in all versions up to, and including, 4.4.2 due to **missing authorization checks** on processAction function, as well as **insufficient input sanitization and output escaping**. This makes it possible for unauthenticated attackers to inject arbitrary web scripts that will execute whenever a user accesses a wp-admin dashboard.",
  "key_phrases": {
    "rootcause": [
      "insufficient input sanitization and output escaping",
      "missing authorization checks"
    ],
    "weakness": "cross-site scripting",
    "impact": [
      "execute arbitrary web scripts",
      "inject arbitrary web scripts"
    ],
    "vector": "wp_id parameter",
    "attacker": "unauthenticated attackers",
    "product": "Online Booking & Scheduling Calendar for WordPress by vcita",
    "version": "up to and including 4.4.2",
    "component": "processAction function"
  },
  "reference_content": "Based on the provided information, here's an analysis of CVE-2024-5791:\n\n**Root Cause of Vulnerability:**\n\n*   The vulnerability stems from a missing authorization check in the `processAction` function within the `vcita-api-functions.php` file of the \"Online Booking & Scheduling Calendar for WordPress by vcita\" plugin.\n*   Additionally, there's a lack of sufficient input sanitization and output escaping when handling the 'wp_id' parameter.\n\n**Weaknesses/Vulnerabilities Present:**\n\n*   **Missing Authorization:** The `processAction` function, specifically when processing the 'install' action, does not verify the user's permissions, allowing unauthenticated users to trigger the function.\n*   **Stored Cross-Site Scripting (XSS):** The `wp_id` parameter is not properly sanitized, allowing malicious script injection. This injected script is stored in the WordPress database and executed when an administrator accesses the WordPress admin dashboard.\n*   **Insufficient Input Sanitization:** The plugin does not sanitize the 'wp_id' parameter before storing it in the database.\n*   **Insufficient Output Escaping:** The plugin does not escape the 'wp_id' when outputting it in the admin dashboard.\n\n**Impact of Exploitation:**\n\n*   **Arbitrary Script Execution:** An unauthenticated attacker can inject malicious JavaScript into the WordPress database.\n*   **Admin Dashboard Compromise:** When an administrator accesses the wp-admin dashboard, the stored malicious script will be executed in their browser.\n*   **Potential Account Takeover:** The attacker could potentially perform actions as the administrator, potentially leading to account takeover, data theft or other malicious activities.\n\n**Attack Vectors:**\n\n*   **Unauthenticated HTTP Request:** The attacker can send a crafted POST or GET request to the WordPress site's REST API endpoint, utilizing the vulnerable `vcita_callback` function with the 'install' action and malicious code in the 'wp_id' parameter\n*   **Direct Interaction with REST Endpoint:** The vulnerability can be exploited through direct interaction with the plugin's REST API endpoint.\n\n**Required Attacker Capabilities/Position:**\n\n*   **No Authentication Required:** The attacker does not need to be logged into the WordPress site.\n*   **Network Access:** The attacker needs to be able to send HTTP requests to the vulnerable WordPress site.\n*   **Knowledge of vulnerable endpoint/parameter:** The attacker needs to know the vulnerable plugin endpoint and the vulnerable parameter `wp_id`.\n\n**Additional Details:**\n\n*   The vulnerable code is located in the `vcita-api-functions.php` file, specifically around line 40 which contains the `processAction` function\n*   The vulnerability exists in versions of the \"Online Booking & Scheduling Calendar for WordPress by vcita\" plugin up to and including version 4.4.2\n*   The vulnerability was fixed in version 4.4.3.",
  "similar_info": {
    "cwe_distribution": {},
    "cwe_consensus": "",
    "similarity_stats": {
      "thresholds": [],
      "total_samples_by_threshold": {},
      "top_cwes_by_threshold": {}
    }
  },
  "similarity_summary": {
    "consensus_cwe": "",
    "top_cwes": [],
    "confidence_levels": {},
    "total_samples": 0
  },
  "analysis": "# Summary\n\n| CWE ID  | CWE Name                                                                  | Confidence | CWE Abstraction Level | CWE Vulnerability Mapping Label | CWE-Vulnerability Mapping Notes |\n| :-------- | :------------------------------------------------------------------------ | :--------- | :---------------------- | :------------------------------ | :------------------------------ |\n| CWE-862   | Missing Authorization                                                     | 0.95       | Base                    | Primary                         | Allowed                       |\n| CWE-79    | Improper Neutralization of Input During Web Page Generation ('Cross-site Scripting') | 0.95       | Base                    | Secondary                       | Allowed                       |\n\n## Evidence and Confidence\n\n*   **Confidence Score:** 0.95\n*   **Evidence Strength:** HIGH\n\n## Relationship Analysis\n\nThe primary weakness is the **missing authorization** check (CWE-862), which allows unauthenticated attackers to perform actions they should not be able to. The secondary weakness stems from **insufficient input sanitization and output escaping**, leading to the injection of arbitrary web scripts (CWE-79). CWE-862 can precede CWE-79 because **missing authorization** allows for malicious input to be processed, and if that input is not properly neutralized, it can lead to cross-site scripting.\n\n```mermaid\ngraph TD\n    cwe862[\"CWE-862: Missing Authorization\"]\n    cwe79[\"CWE-79: Improper Neutralization of Input During Web Page Generation ('Cross-site Scripting')\"]\n    cwe116[\"CWE-116: Improper Encoding or Escaping of Output\"]\n    \n    cwe79 -->|CHILDOF| cwe116\n    cwe862 -->|CANPRECEDE| cwe79\n    \n    classDef primary fill:#f96,stroke:#333,stroke-width:2px\n    classDef secondary fill:#69f,stroke:#333\n    classDef tertiary fill:#9e9,stroke:#333\n    class cwe862 primary\n    class cwe79 secondary\n    class cwe116 tertiary\n```\n\n## Vulnerability Chain\n\nThe vulnerability chain begins with **missing authorization** checks in the `processAction` function (CWE-862). This allows unauthenticated attackers to inject arbitrary web scripts due to **insufficient input sanitization and output escaping**. This leads to stored cross-site scripting (CWE-79), where the injected scripts are executed whenever a user accesses a wp-admin dashboard.\n\nCWE-862 (Missing Authorization) -> CWE-79 (Improper Neutralization of Input During Web Page Generation) -> Impact: Execution of arbitrary web scripts.\n\n## Summary of Analysis\n\nThe analysis is based on the provided vulnerability description, which explicitly states the **missing authorization checks** and **insufficient input sanitization and output escaping** as the root causes. The description also clearly states the resulting stored cross-site scripting vulnerability.\n\nThe vulnerability description explicitly mentions \"missing authorization checks\" as the primary issue, making CWE-862 the most suitable choice. The subsequent **insufficient input sanitization and output escaping** leads directly to the stored XSS vulnerability, making CWE-79 a strong secondary candidate.\n\nThe CWEs selected are at the Base level of abstraction, providing the most specific representation of the weaknesses described.\n\nThe provided text clearly states: \"The Online Booking & Scheduling Calendar for WordPress by vcita plugin for WordPress is vulnerable to Stored Cross-Site Scripting via the wp_id parameter in all versions up to, and including, 4.4.2 due to **missing authorization checks** on processAction function, as well as **insufficient input sanitization and output escaping**.\"\n\nRelevant CWE Information:\n\n*   **CWE-862: Missing Authorization:** The product does not perform an authorization check when an actor attempts to access a resource or perform an action. This aligns directly with the \"**missing authorization checks**\" mentioned in the vulnerability description.\n*   **CWE-79: Improper Neutralization of Input During Web Page Generation ('Cross-site Scripting'):** The product does not neutralize or incorrectly neutralizes user-controllable input before it is placed in output that is used as a web page that is served to other users. This aligns with the \"**insufficient input sanitization and output escaping**\" and the resulting stored XSS vulnerability.\n\nCWE-116, CWE-352, CWE-138, CWE-89, CWE-425, CWE-472, CWE-184, CWE-303, CWE-1391, CWE-707, CWE-494, CWE-471, CWE-113, CWE-94, CWE-78, CWE-120, and CWE-73 were considered but not selected. CWE-116, CWE-138, and CWE-707 are too general. CWE-352 is not directly applicable as CSRF is not the primary issue. CWE-89, CWE-78, CWE-94, CWE-120, CWE-73, CWE-425, CWE-472, CWE-184, CWE-303, CWE-1391, CWE-494, CWE-471, and CWE-113 do not accurately reflect the specific weaknesses described in the vulnerability.",
  "analysis_with_relationships": "# Summary\n\n| CWE ID  | CWE Name                                                                  | Confidence | CWE Abstraction Level | CWE Vulnerability Mapping Label | CWE-Vulnerability Mapping Notes |\n| :-------- | :------------------------------------------------------------------------ | :--------- | :---------------------- | :------------------------------ | :------------------------------ |\n| CWE-862   | Missing Authorization                                                     | 0.95       | Base                    | Primary                         | Allowed                       |\n| CWE-79    | Improper Neutralization of Input During Web Page Generation ('Cross-site Scripting') | 0.95       | Base                    | Secondary                       | Allowed                       |\n\n## Evidence and Confidence\n\n*   **Confidence Score:** 0.95\n*   **Evidence Strength:** HIGH\n\n## Relationship Analysis\n\nThe primary weakness is the **missing authorization** check (CWE-862), which allows unauthenticated attackers to perform actions they should not be able to. The secondary weakness stems from **insufficient input sanitization and output escaping**, leading to the injection of arbitrary web scripts (CWE-79). CWE-862 can precede CWE-79 because **missing authorization** allows for malicious input to be processed, and if that input is not properly neutralized, it can lead to cross-site scripting.\n\n```mermaid\ngraph TD\n    cwe862[\"CWE-862: Missing Authorization\"]\n    cwe79[\"CWE-79: Improper Neutralization of Input During Web Page Generation ('Cross-site Scripting')\"]\n    cwe116[\"CWE-116: Improper Encoding or Escaping of Output\"]\n    \n    cwe79 -->|CHILDOF| cwe116\n    cwe862 -->|CANPRECEDE| cwe79\n    \n    classDef primary fill:#f96,stroke:#333,stroke-width:2px\n    classDef secondary fill:#69f,stroke:#333\n    classDef tertiary fill:#9e9,stroke:#333\n    class cwe862 primary\n    class cwe79 secondary\n    class cwe116 tertiary\n```\n\n## Vulnerability Chain\n\nThe vulnerability chain begins with **missing authorization** checks in the `processAction` function (CWE-862). This allows unauthenticated attackers to inject arbitrary web scripts due to **insufficient input sanitization and output escaping**. This leads to stored cross-site scripting (CWE-79), where the injected scripts are executed whenever a user accesses a wp-admin dashboard.\n\nCWE-862 (Missing Authorization) -> CWE-79 (Improper Neutralization of Input During Web Page Generation) -> Impact: Execution of arbitrary web scripts.\n\n## Summary of Analysis\n\nThe analysis is based on the provided vulnerability description, which explicitly states the **missing authorization checks** and **insufficient input sanitization and output escaping** as the root causes. The description also clearly states the resulting stored cross-site scripting vulnerability.\n\nThe vulnerability description explicitly mentions \"missing authorization checks\" as the primary issue, making CWE-862 the most suitable choice. The subsequent **insufficient input sanitization and output escaping** leads directly to the stored XSS vulnerability, making CWE-79 a strong secondary candidate.\n\nThe CWEs selected are at the Base level of abstraction, providing the most specific representation of the weaknesses described.\n\nThe provided text clearly states: \"The Online Booking & Scheduling Calendar for WordPress by vcita plugin for WordPress is vulnerable to Stored Cross-Site Scripting via the wp_id parameter in all versions up to, and including, 4.4.2 due to **missing authorization checks** on processAction function, as well as **insufficient input sanitization and output escaping**.\"\n\nRelevant CWE Information:\n\n*   **CWE-862: Missing Authorization:** The product does not perform an authorization check when an actor attempts to access a resource or perform an action. This aligns directly with the \"**missing authorization checks**\" mentioned in the vulnerability description.\n*   **CWE-79: Improper Neutralization of Input During Web Page Generation ('Cross-site Scripting'):** The product does not neutralize or incorrectly neutralizes user-controllable input before it is placed in output that is used as a web page that is served to other users. This aligns with the \"**insufficient input sanitization and output escaping**\" and the resulting stored XSS vulnerability.\n\nCWE-116, CWE-352, CWE-138, CWE-89, CWE-425, CWE-472, CWE-184, CWE-303, CWE-1391, CWE-707, CWE-494, CWE-471, CWE-113, CWE-94, CWE-78, CWE-120, and CWE-73 were considered but not selected. CWE-116, CWE-138, and CWE-707 are too general. CWE-352 is not directly applicable as CSRF is not the primary issue. CWE-89, CWE-78, CWE-94, CWE-120, CWE-73, CWE-425, CWE-472, CWE-184, CWE-303, CWE-1391, CWE-494, CWE-471, and CWE-113 do not accurately reflect the specific weaknesses described in the vulnerability.\n\n\n## CWE Relationship Analysis\n\nCurrent CWEs represent these abstraction levels: .\n\n\n### Vulnerability Chain Analysis\n\n**Chain starting from CWE-471:**\n- 471 (Modification of Assumed-Immutable Data (MAID)) - ROOT\n\n\n**Chain starting from CWE-94:**\n- 94 (Improper Control of Generation of Code ('Code Injection')) - ROOT\n\n\n\n### CWE Relationship Diagram\n\n```mermaid\ngraph TD\n    classDef primary fill:#f96,stroke:#333,stroke-width:2px\n    classDef secondary fill:#69f,stroke:#333\n    classDef tertiary fill:#9e9,stroke:#333\n```",
  "criticism": "",
  "resolution": "",
  "relevant_cwes": [
    {
      "metadata": {
        "doc_id": "116",
        "name": "Improper Encoding or Escaping of Output",
        "source": "sparse",
        "original_content": "The product prepares a structured message for communication with another component, but encoding or escaping of the data is either missing or done incorrectly. As a result, the intended structure of the message is not preserved.",
        "keyphrase_sources": [
          {
            "id": "rootcause:insufficient input sanitization and output escaping",
            "keyphrase": "insufficient input sanitization and output escaping",
            "type": "rootcause"
          },
          {
            "id": "rootcause:missing authorization checks",
            "keyphrase": "missing authorization checks",
            "type": "rootcause"
          },
          {
            "id": "weakness:cross-site scripting",
            "keyphrase": "cross-site scripting",
            "type": "weakness"
          },
          {
            "id": "impact:execute arbitrary web scripts",
            "keyphrase": "execute arbitrary web scripts",
            "type": "impact"
          },
          {
            "id": "impact:inject arbitrary web scripts",
            "keyphrase": "inject arbitrary web scripts",
            "type": "impact"
          },
          {
            "id": "vector:wp_id parameter",
            "keyphrase": "wp_id parameter",
            "type": "vector"
          },
          {
            "id": "attacker:unauthenticated attackers",
            "keyphrase": "unauthenticated attackers",
            "type": "attacker"
          },
          {
            "id": "product:Online Booking & Scheduling Calendar for WordPress by vcita",
            "keyphrase": "Online Booking & Scheduling Calendar for WordPress by vcita",
            "type": "product"
          },
          {
            "id": "version:up to and including 4.4.2",
            "keyphrase": "up to and including 4.4.2",
            "type": "version"
          },
          {
            "id": "component:processAction function",
            "keyphrase": "processAction function",
            "type": "component"
          }
        ]
      },
      "similarity": 652.2337351697691
    },
    {
      "metadata": {
        "doc_id": "352",
        "name": "Cross-Site Request Forgery (CSRF)",
        "source": "sparse",
        "original_content": "The web application does not, or can not, sufficiently verify whether a well-formed, valid, consistent request was intentionally provided by the user who submitted the request.",
        "keyphrase_sources": [
          {
            "id": "rootcause:insufficient input sanitization and output escaping",
            "keyphrase": "insufficient input sanitization and output escaping",
            "type": "rootcause"
          },
          {
            "id": "rootcause:missing authorization checks",
            "keyphrase": "missing authorization checks",
            "type": "rootcause"
          },
          {
            "id": "weakness:cross-site scripting",
            "keyphrase": "cross-site scripting",
            "type": "weakness"
          },
          {
            "id": "impact:execute arbitrary web scripts",
            "keyphrase": "execute arbitrary web scripts",
            "type": "impact"
          },
          {
            "id": "impact:inject arbitrary web scripts",
            "keyphrase": "inject arbitrary web scripts",
            "type": "impact"
          },
          {
            "id": "vector:wp_id parameter",
            "keyphrase": "wp_id parameter",
            "type": "vector"
          },
          {
            "id": "attacker:unauthenticated attackers",
            "keyphrase": "unauthenticated attackers",
            "type": "attacker"
          },
          {
            "id": "product:Online Booking & Scheduling Calendar for WordPress by vcita",
            "keyphrase": "Online Booking & Scheduling Calendar for WordPress by vcita",
            "type": "product"
          },
          {
            "id": "version:up to and including 4.4.2",
            "keyphrase": "up to and including 4.4.2",
            "type": "version"
          },
          {
            "id": "component:processAction function",
            "keyphrase": "processAction function",
            "type": "component"
          }
        ]
      },
      "similarity": 636.6255954260492
    },
    {
      "metadata": {
        "doc_id": "138",
        "name": "Improper Neutralization of Special Elements",
        "source": "sparse",
        "original_content": "The product receives input from an upstream component, but it does not neutralize or incorrectly neutralizes special elements that could be interpreted as control elements or syntactic markers when they are sent to a downstream component.",
        "keyphrase_sources": [
          {
            "id": "rootcause:insufficient input sanitization and output escaping",
            "keyphrase": "insufficient input sanitization and output escaping",
            "type": "rootcause"
          },
          {
            "id": "rootcause:missing authorization checks",
            "keyphrase": "missing authorization checks",
            "type": "rootcause"
          },
          {
            "id": "weakness:cross-site scripting",
            "keyphrase": "cross-site scripting",
            "type": "weakness"
          },
          {
            "id": "impact:execute arbitrary web scripts",
            "keyphrase": "execute arbitrary web scripts",
            "type": "impact"
          },
          {
            "id": "impact:inject arbitrary web scripts",
            "keyphrase": "inject arbitrary web scripts",
            "type": "impact"
          },
          {
            "id": "vector:wp_id parameter",
            "keyphrase": "wp_id parameter",
            "type": "vector"
          },
          {
            "id": "attacker:unauthenticated attackers",
            "keyphrase": "unauthenticated attackers",
            "type": "attacker"
          },
          {
            "id": "version:up to and including 4.4.2",
            "keyphrase": "up to and including 4.4.2",
            "type": "version"
          },
          {
            "id": "component:processAction function",
            "keyphrase": "processAction function",
            "type": "component"
          }
        ]
      },
      "similarity": 569.4983830244734
    },
    {
      "metadata": {
        "doc_id": "79",
        "name": "Improper Neutralization of Input During Web Page Generation ('Cross-site Scripting')",
        "source": "sparse",
        "original_content": "The product does not neutralize or incorrectly neutralizes user-controllable input before it is placed in output that is used as a web page that is served to other users.",
        "keyphrase_sources": [
          {
            "id": "rootcause:insufficient input sanitization and output escaping",
            "keyphrase": "insufficient input sanitization and output escaping",
            "type": "rootcause"
          },
          {
            "id": "rootcause:missing authorization checks",
            "keyphrase": "missing authorization checks",
            "type": "rootcause"
          },
          {
            "id": "weakness:cross-site scripting",
            "keyphrase": "cross-site scripting",
            "type": "weakness"
          },
          {
            "id": "impact:execute arbitrary web scripts",
            "keyphrase": "execute arbitrary web scripts",
            "type": "impact"
          },
          {
            "id": "impact:inject arbitrary web scripts",
            "keyphrase": "inject arbitrary web scripts",
            "type": "impact"
          },
          {
            "id": "vector:wp_id parameter",
            "keyphrase": "wp_id parameter",
            "type": "vector"
          },
          {
            "id": "attacker:unauthenticated attackers",
            "keyphrase": "unauthenticated attackers",
            "type": "attacker"
          },
          {
            "id": "product:Online Booking & Scheduling Calendar for WordPress by vcita",
            "keyphrase": "Online Booking & Scheduling Calendar for WordPress by vcita",
            "type": "product"
          },
          {
            "id": "version:up to and including 4.4.2",
            "keyphrase": "up to and including 4.4.2",
            "type": "version"
          },
          {
            "id": "component:processAction function",
            "keyphrase": "processAction function",
            "type": "component"
          }
        ]
      },
      "similarity": 522.8511414096208
    },
    {
      "metadata": {
        "doc_id": "862",
        "name": "Missing Authorization",
        "source": "sparse",
        "original_content": "The product does not perform an authorization check when an actor attempts to access a resource or perform an action.",
        "keyphrase_sources": [
          {
            "id": "rootcause:insufficient input sanitization and output escaping",
            "keyphrase": "insufficient input sanitization and output escaping",
            "type": "rootcause"
          },
          {
            "id": "rootcause:missing authorization checks",
            "keyphrase": "missing authorization checks",
            "type": "rootcause"
          },
          {
            "id": "weakness:cross-site scripting",
            "keyphrase": "cross-site scripting",
            "type": "weakness"
          },
          {
            "id": "impact:execute arbitrary web scripts",
            "keyphrase": "execute arbitrary web scripts",
            "type": "impact"
          },
          {
            "id": "impact:inject arbitrary web scripts",
            "keyphrase": "inject arbitrary web scripts",
            "type": "impact"
          },
          {
            "id": "vector:wp_id parameter",
            "keyphrase": "wp_id parameter",
            "type": "vector"
          },
          {
            "id": "attacker:unauthenticated attackers",
            "keyphrase": "unauthenticated attackers",
            "type": "attacker"
          },
          {
            "id": "product:Online Booking & Scheduling Calendar for WordPress by vcita",
            "keyphrase": "Online Booking & Scheduling Calendar for WordPress by vcita",
            "type": "product"
          },
          {
            "id": "version:up to and including 4.4.2",
            "keyphrase": "up to and including 4.4.2",
            "type": "version"
          },
          {
            "id": "component:processAction function",
            "keyphrase": "processAction function",
            "type": "component"
          }
        ]
      },
      "similarity": 496.2363634090324
    },
    {
      "metadata": {
        "doc_id": "89",
        "name": "Improper Neutralization of Special Elements used in an SQL Command ('SQL Injection')",
        "source": "sparse",
        "original_content": "The product constructs all or part of an SQL command using externally-influenced input from an upstream component, but it does not neutralize or incorrectly neutralizes special elements that could modify the intended SQL command when it is sent to a downstream component. Without sufficient removal or quoting of SQL syntax in user-controllable inputs, the generated SQL query can cause those inputs to be interpreted as SQL instead of ordinary user data.",
        "keyphrase_sources": [
          {
            "id": "product:Online Booking & Scheduling Calendar for WordPress by vcita",
            "keyphrase": "Online Booking & Scheduling Calendar for WordPress by vcita",
            "type": "product"
          }
        ]
      },
      "similarity": 175.54139700842597
    }
  ],
  "identified_cwes": {
    "analyzer": [
      "CWE-471",
      "CWE-94",
      "CWE-494",
      "CWE-862",
      "CWE-79",
      "CWE-113",
      "CWE-184",
      "CWE-89",
      "CWE-73",
      "CWE-352",
      "CWE-120",
      "CWE-425",
      "CWE-707",
      "CWE-138",
      "CWE-1391",
      "CWE-78",
      "CWE-116",
      "CWE-472",
      "CWE-303"
    ],
    "critic_additional": []
  },
  "keyphrase_cwe_mapping": {
    "116": [
      {
        "id": "rootcause:insufficient input sanitization and output escaping",
        "keyphrase": "insufficient input sanitization and output escaping",
        "type": "rootcause"
      },
      {
        "id": "rootcause:missing authorization checks",
        "keyphrase": "missing authorization checks",
        "type": "rootcause"
      },
      {
        "id": "weakness:cross-site scripting",
        "keyphrase": "cross-site scripting",
        "type": "weakness"
      },
      {
        "id": "impact:execute arbitrary web scripts",
        "keyphrase": "execute arbitrary web scripts",
        "type": "impact"
      },
      {
        "id": "impact:inject arbitrary web scripts",
        "keyphrase": "inject arbitrary web scripts",
        "type": "impact"
      },
      {
        "id": "vector:wp_id parameter",
        "keyphrase": "wp_id parameter",
        "type": "vector"
      },
      {
        "id": "attacker:unauthenticated attackers",
        "keyphrase": "unauthenticated attackers",
        "type": "attacker"
      },
      {
        "id": "product:Online Booking & Scheduling Calendar for WordPress by vcita",
        "keyphrase": "Online Booking & Scheduling Calendar for WordPress by vcita",
        "type": "product"
      },
      {
        "id": "version:up to and including 4.4.2",
        "keyphrase": "up to and including 4.4.2",
        "type": "version"
      },
      {
        "id": "component:processAction function",
        "keyphrase": "processAction function",
        "type": "component"
      }
    ],
    "352": [
      {
        "id": "rootcause:insufficient input sanitization and output escaping",
        "keyphrase": "insufficient input sanitization and output escaping",
        "type": "rootcause"
      },
      {
        "id": "rootcause:missing authorization checks",
        "keyphrase": "missing authorization checks",
        "type": "rootcause"
      },
      {
        "id": "weakness:cross-site scripting",
        "keyphrase": "cross-site scripting",
        "type": "weakness"
      },
      {
        "id": "impact:execute arbitrary web scripts",
        "keyphrase": "execute arbitrary web scripts",
        "type": "impact"
      },
      {
        "id": "impact:inject arbitrary web scripts",
        "keyphrase": "inject arbitrary web scripts",
        "type": "impact"
      },
      {
        "id": "vector:wp_id parameter",
        "keyphrase": "wp_id parameter",
        "type": "vector"
      },
      {
        "id": "attacker:unauthenticated attackers",
        "keyphrase": "unauthenticated attackers",
        "type": "attacker"
      },
      {
        "id": "product:Online Booking & Scheduling Calendar for WordPress by vcita",
        "keyphrase": "Online Booking & Scheduling Calendar for WordPress by vcita",
        "type": "product"
      },
      {
        "id": "version:up to and including 4.4.2",
        "keyphrase": "up to and including 4.4.2",
        "type": "version"
      },
      {
        "id": "component:processAction function",
        "keyphrase": "processAction function",
        "type": "component"
      }
    ],
    "138": [
      {
        "id": "rootcause:insufficient input sanitization and output escaping",
        "keyphrase": "insufficient input sanitization and output escaping",
        "type": "rootcause"
      },
      {
        "id": "rootcause:missing authorization checks",
        "keyphrase": "missing authorization checks",
        "type": "rootcause"
      },
      {
        "id": "weakness:cross-site scripting",
        "keyphrase": "cross-site scripting",
        "type": "weakness"
      },
      {
        "id": "impact:execute arbitrary web scripts",
        "keyphrase": "execute arbitrary web scripts",
        "type": "impact"
      },
      {
        "id": "impact:inject arbitrary web scripts",
        "keyphrase": "inject arbitrary web scripts",
        "type": "impact"
      },
      {
        "id": "vector:wp_id parameter",
        "keyphrase": "wp_id parameter",
        "type": "vector"
      },
      {
        "id": "attacker:unauthenticated attackers",
        "keyphrase": "unauthenticated attackers",
        "type": "attacker"
      },
      {
        "id": "version:up to and including 4.4.2",
        "keyphrase": "up to and including 4.4.2",
        "type": "version"
      },
      {
        "id": "component:processAction function",
        "keyphrase": "processAction function",
        "type": "component"
      }
    ],
    "79": [
      {
        "id": "rootcause:insufficient input sanitization and output escaping",
        "keyphrase": "insufficient input sanitization and output escaping",
        "type": "rootcause"
      },
      {
        "id": "rootcause:missing authorization checks",
        "keyphrase": "missing authorization checks",
        "type": "rootcause"
      },
      {
        "id": "weakness:cross-site scripting",
        "keyphrase": "cross-site scripting",
        "type": "weakness"
      },
      {
        "id": "impact:execute arbitrary web scripts",
        "keyphrase": "execute arbitrary web scripts",
        "type": "impact"
      },
      {
        "id": "impact:inject arbitrary web scripts",
        "keyphrase": "inject arbitrary web scripts",
        "type": "impact"
      },
      {
        "id": "vector:wp_id parameter",
        "keyphrase": "wp_id parameter",
        "type": "vector"
      },
      {
        "id": "attacker:unauthenticated attackers",
        "keyphrase": "unauthenticated attackers",
        "type": "attacker"
      },
      {
        "id": "product:Online Booking & Scheduling Calendar for WordPress by vcita",
        "keyphrase": "Online Booking & Scheduling Calendar for WordPress by vcita",
        "type": "product"
      },
      {
        "id": "version:up to and including 4.4.2",
        "keyphrase": "up to and including 4.4.2",
        "type": "version"
      },
      {
        "id": "component:processAction function",
        "keyphrase": "processAction function",
        "type": "component"
      }
    ],
    "862": [
      {
        "id": "rootcause:insufficient input sanitization and output escaping",
        "keyphrase": "insufficient input sanitization and output escaping",
        "type": "rootcause"
      },
      {
        "id": "rootcause:missing authorization checks",
        "keyphrase": "missing authorization checks",
        "type": "rootcause"
      },
      {
        "id": "weakness:cross-site scripting",
        "keyphrase": "cross-site scripting",
        "type": "weakness"
      },
      {
        "id": "impact:execute arbitrary web scripts",
        "keyphrase": "execute arbitrary web scripts",
        "type": "impact"
      },
      {
        "id": "impact:inject arbitrary web scripts",
        "keyphrase": "inject arbitrary web scripts",
        "type": "impact"
      },
      {
        "id": "vector:wp_id parameter",
        "keyphrase": "wp_id parameter",
        "type": "vector"
      },
      {
        "id": "attacker:unauthenticated attackers",
        "keyphrase": "unauthenticated attackers",
        "type": "attacker"
      },
      {
        "id": "product:Online Booking & Scheduling Calendar for WordPress by vcita",
        "keyphrase": "Online Booking & Scheduling Calendar for WordPress by vcita",
        "type": "product"
      },
      {
        "id": "version:up to and including 4.4.2",
        "keyphrase": "up to and including 4.4.2",
        "type": "version"
      },
      {
        "id": "component:processAction function",
        "keyphrase": "processAction function",
        "type": "component"
      }
    ],
    "89": [
      {
        "id": "product:Online Booking & Scheduling Calendar for WordPress by vcita",
        "keyphrase": "Online Booking & Scheduling Calendar for WordPress by vcita",
        "type": "product"
      }
    ]
  }
}