{
  "vulnerability_info": "VulnerabilityInfo(cve_id='CVE-2024-53787', description='**Improper Neutralization of Input During Web Page Generation** (Cross-site Scripting) vulnerability in vinoth06 Random Banner allows Stored **XSS**.This issue affects Random Banner from n/a through 4.2.9.', key_phrases={'rootcause': 'Improper Neutralization of Input During Web Page Generation', 'weakness': ['XSS', 'cross-site scripting'], 'impact': '', 'vector': '', 'attacker': '', 'product': 'vinoth06 Random Banner', 'version': 'n/a through 4.2.9', 'component': ''}, reference_content='```\\n{\\n  \"Root cause of vulnerability\": \"The Random Banner plugin for WordPress is vulnerable to Cross-Site Scripting (XSS).\",\\n  \"Weaknesses/vulnerabilities present\": \"Cross-Site Scripting (XSS)\",\\n  \"Impact of exploitation\": \"A malicious actor can inject malicious scripts, such as redirects, advertisements, and other HTML payloads into the website, which will be executed when guests visit the site.\",\\n  \"Attack vectors\": \"Malicious script injection through the vulnerable plugin.\",\\n  \"Required attacker capabilities/position\": \"The attacker needs to be able to inject malicious scripts into the website, likely through a vulnerable input field or other insecure mechanism within the plugin. Requires at least Contributor level access.\"\\n}\\n```', similar_info={'cwe_distribution': {95: {'cwe_counts': defaultdict(<class 'int'>, {}), 'total_samples': 1, 'distribution': [{'cwes': [], 'frequency': 1, 'proportion': 1.0}]}, 90: {'cwe_counts': defaultdict(<class 'int'>, {'CWE-79': 4}), 'total_samples': 6, 'distribution': [{'cwes': ['CWE-79'], 'frequency': 4, 'proportion': 0.667}, {'cwes': [], 'frequency': 2, 'proportion': 0.333}]}, 85: {'cwe_counts': defaultdict(<class 'int'>, {'CWE-79': 5}), 'total_samples': 15, 'distribution': [{'cwes': [], 'frequency': 10, 'proportion': 0.667}, {'cwes': ['CWE-79'], 'frequency': 5, 'proportion': 0.333}]}, 80: {'cwe_counts': defaultdict(<class 'int'>, {'CWE-79': 7}), 'total_samples': 23, 'distribution': [{'cwes': [], 'frequency': 16, 'proportion': 0.696}, {'cwes': ['CWE-79'], 'frequency': 7, 'proportion': 0.304}]}, 75: {'cwe_counts': defaultdict(<class 'int'>, {'CWE-79': 3}), 'total_samples': 12, 'distribution': [{'cwes': [], 'frequency': 9, 'proportion': 0.75}, {'cwes': ['CWE-79'], 'frequency': 3, 'proportion': 0.25}]}, 70: {'cwe_counts': defaultdict(<class 'int'>, {'CWE-79': 24}), 'total_samples': 81, 'distribution': [{'cwes': [], 'frequency': 57, 'proportion': 0.704}, {'cwes': ['CWE-79'], 'frequency': 24, 'proportion': 0.296}]}}, 'cwe_consensus': 'CWE-79', 'similarity_stats': {'thresholds': [95, 90, 85, 80, 75, 70], 'total_samples_by_threshold': {95: 1, 90: 6, 85: 15, 80: 23, 75: 12, 70: 81}, 'top_cwes_by_threshold': {95: [], 90: [('CWE-79', 4)], 85: [('CWE-79', 5)], 80: [('CWE-79', 7)], 75: [('CWE-79', 3)], 70: [('CWE-79', 24)]}}, 'raw_matches': [{'similarity': 95, 'cwes': [], 'total': 1, 'frequency': 1, 'proportion': 1.0}, {'similarity': 90, 'cwes': ['79'], 'total': 6, 'frequency': 4, 'proportion': 0.667}, {'similarity': 90, 'cwes': [], 'total': 6, 'frequency': 2, 'proportion': 0.333}, {'similarity': 85, 'cwes': [], 'total': 15, 'frequency': 10, 'proportion': 0.667}, {'similarity': 85, 'cwes': ['79'], 'total': 15, 'frequency': 5, 'proportion': 0.333}, {'similarity': 80, 'cwes': [], 'total': 23, 'frequency': 16, 'proportion': 0.696}, {'similarity': 80, 'cwes': ['79'], 'total': 23, 'frequency': 7, 'proportion': 0.304}, {'similarity': 75, 'cwes': [], 'total': 12, 'frequency': 9, 'proportion': 0.75}, {'similarity': 75, 'cwes': ['79'], 'total': 12, 'frequency': 3, 'proportion': 0.25}, {'similarity': 70, 'cwes': [], 'total': 81, 'frequency': 57, 'proportion': 0.704}, {'similarity': 70, 'cwes': ['79'], 'total': 81, 'frequency': 24, 'proportion': 0.296}]}, similarity_summary=SimilarityInsight(consensus_cwe='CWE-79', top_cwes=[('CWE-79', 43)], confidence_levels={'high': [], 'medium': [], 'low': []}, total_samples=138), analysis='', analysis_with_relationships='', criticism='', resolution='', relevant_cwes=[{'metadata': {'doc_id': '79', 'name': \"Improper Neutralization of Input During Web Page Generation ('Cross-site Scripting')\", 'source': 'sparse', 'original_content': 'The product does not neutralize or incorrectly neutralizes user-controllable input before it is placed in output that is used as a web page that is served to other users.', 'keyphrase_sources': [{'id': 'rootcause:Improper Neutralization of Input During Web Page Generation', 'keyphrase': 'Improper Neutralization of Input During Web Page Generation', 'type': 'rootcause'}, {'id': 'weakness:XSS', 'keyphrase': 'XSS', 'type': 'weakness'}, {'id': 'weakness:cross-site scripting', 'keyphrase': 'cross-site scripting', 'type': 'weakness'}, {'id': 'product:vinoth06 Random Banner', 'keyphrase': 'vinoth06 Random Banner', 'type': 'product'}, {'id': 'version:n/a through 4.2.9', 'keyphrase': 'n/a through 4.2.9', 'type': 'version'}]}, 'similarity': np.float64(292.90379668287176)}, {'metadata': {'doc_id': '80', 'name': 'Improper Neutralization of Script-Related HTML Tags in a Web Page (Basic XSS)', 'source': 'sparse', 'original_content': 'The product receives input from an upstream component, but it does not neutralize or incorrectly neutralizes special characters such as \"<\", \">\", and \"&\" that could be interpreted as web-scripting elements when they are sent to a downstream component that processes web pages.', 'keyphrase_sources': [{'id': 'rootcause:Improper Neutralization of Input During Web Page Generation', 'keyphrase': 'Improper Neutralization of Input During Web Page Generation', 'type': 'rootcause'}, {'id': 'weakness:XSS', 'keyphrase': 'XSS', 'type': 'weakness'}, {'id': 'weakness:cross-site scripting', 'keyphrase': 'cross-site scripting', 'type': 'weakness'}, {'id': 'product:vinoth06 Random Banner', 'keyphrase': 'vinoth06 Random Banner', 'type': 'product'}, {'id': 'version:n/a through 4.2.9', 'keyphrase': 'n/a through 4.2.9', 'type': 'version'}]}, 'similarity': np.float64(280.00401477133397)}, {'metadata': {'doc_id': '116', 'name': 'Improper Encoding or Escaping of Output', 'source': 'sparse', 'original_content': 'The product prepares a structured message for communication with another component, but encoding or escaping of the data is either missing or done incorrectly. As a result, the intended structure of the message is not preserved.', 'keyphrase_sources': [{'id': 'rootcause:Improper Neutralization of Input During Web Page Generation', 'keyphrase': 'Improper Neutralization of Input During Web Page Generation', 'type': 'rootcause'}, {'id': 'weakness:XSS', 'keyphrase': 'XSS', 'type': 'weakness'}, {'id': 'weakness:cross-site scripting', 'keyphrase': 'cross-site scripting', 'type': 'weakness'}, {'id': 'product:vinoth06 Random Banner', 'keyphrase': 'vinoth06 Random Banner', 'type': 'product'}, {'id': 'version:n/a through 4.2.9', 'keyphrase': 'n/a through 4.2.9', 'type': 'version'}]}, 'similarity': np.float64(259.0001279212921)}, {'metadata': {'doc_id': '89', 'name': \"Improper Neutralization of Special Elements used in an SQL Command ('SQL Injection')\", 'source': 'sparse', 'original_content': 'The product constructs all or part of an SQL command using externally-influenced input from an upstream component, but it does not neutralize or incorrectly neutralizes special elements that could modify the intended SQL command when it is sent to a downstream component. Without sufficient removal or quoting of SQL syntax in user-controllable inputs, the generated SQL query can cause those inputs to be interpreted as SQL instead of ordinary user data.', 'keyphrase_sources': [{'id': 'rootcause:Improper Neutralization of Input During Web Page Generation', 'keyphrase': 'Improper Neutralization of Input During Web Page Generation', 'type': 'rootcause'}]}, 'similarity': np.float64(240.44901627564565)}, {'metadata': {'doc_id': '352', 'name': 'Cross-Site Request Forgery (CSRF)', 'source': 'sparse', 'original_content': 'The web application does not, or can not, sufficiently verify whether a well-formed, valid, consistent request was intentionally provided by the user who submitted the request.', 'keyphrase_sources': [{'id': 'rootcause:Improper Neutralization of Input During Web Page Generation', 'keyphrase': 'Improper Neutralization of Input During Web Page Generation', 'type': 'rootcause'}, {'id': 'weakness:XSS', 'keyphrase': 'XSS', 'type': 'weakness'}, {'id': 'weakness:cross-site scripting', 'keyphrase': 'cross-site scripting', 'type': 'weakness'}, {'id': 'product:vinoth06 Random Banner', 'keyphrase': 'vinoth06 Random Banner', 'type': 'product'}, {'id': 'version:n/a through 4.2.9', 'keyphrase': 'n/a through 4.2.9', 'type': 'version'}]}, 'similarity': np.float64(237.2695683778421)}, {'metadata': {'doc_id': '434', 'name': 'Unrestricted Upload of File with Dangerous Type', 'source': 'sparse', 'original_content': 'The product allows the upload or transfer of dangerous file types that are automatically processed within its environment.', 'keyphrase_sources': [{'id': 'weakness:XSS', 'keyphrase': 'XSS', 'type': 'weakness'}, {'id': 'weakness:cross-site scripting', 'keyphrase': 'cross-site scripting', 'type': 'weakness'}, {'id': 'product:vinoth06 Random Banner', 'keyphrase': 'vinoth06 Random Banner', 'type': 'product'}, {'id': 'version:n/a through 4.2.9', 'keyphrase': 'n/a through 4.2.9', 'type': 'version'}]}, 'similarity': np.float64(182.81753952789558)}], identified_cwes={'analyzer': [], 'critic_additional': []})",
  "retrieval_results": {
    "has_multiple_keyphrases": true,
    "keyphrase_cwe_sets": {
      "rootcause:Improper Neutralization of Input During Web Page Generation": {
        "keyphrase": "Improper Neutralization of Input During Web Page Generation",
        "type": "rootcause",
        "cwes": [
          {
            "metadata": {
              "doc_id": "79",
              "name": "Improper Neutralization of Input During Web Page Generation ('Cross-site Scripting')",
              "source": "sparse",
              "original_content": "The product does not neutralize or incorrectly neutralizes user-controllable input before it is placed in output that is used as a web page that is served to other users.",
              "keyphrase_sources": [
                {
                  "id": "rootcause:Improper Neutralization of Input During Web Page Generation",
                  "keyphrase": "Improper Neutralization of Input During Web Page Generation",
                  "type": "rootcause"
                },
                {
                  "id": "weakness:XSS",
                  "keyphrase": "XSS",
                  "type": "weakness"
                },
                {
                  "id": "weakness:cross-site scripting",
                  "keyphrase": "cross-site scripting",
                  "type": "weakness"
                },
                {
                  "id": "product:vinoth06 Random Banner",
                  "keyphrase": "vinoth06 Random Banner",
                  "type": "product"
                },
                {
                  "id": "version:n/a through 4.2.9",
                  "keyphrase": "n/a through 4.2.9",
                  "type": "version"
                }
              ]
            },
            "similarity": 292.90379668287176
          },
          {
            "metadata": {
              "doc_id": "80",
              "name": "Improper Neutralization of Script-Related HTML Tags in a Web Page (Basic XSS)",
              "source": "sparse",
              "original_content": "The product receives input from an upstream component, but it does not neutralize or incorrectly neutralizes special characters such as \"<\", \">\", and \"&\" that could be interpreted as web-scripting elements when they are sent to a downstream component that processes web pages.",
              "keyphrase_sources": [
                {
                  "id": "rootcause:Improper Neutralization of Input During Web Page Generation",
                  "keyphrase": "Improper Neutralization of Input During Web Page Generation",
                  "type": "rootcause"
                },
                {
                  "id": "weakness:XSS",
                  "keyphrase": "XSS",
                  "type": "weakness"
                },
                {
                  "id": "weakness:cross-site scripting",
                  "keyphrase": "cross-site scripting",
                  "type": "weakness"
                },
                {
                  "id": "product:vinoth06 Random Banner",
                  "keyphrase": "vinoth06 Random Banner",
                  "type": "product"
                },
                {
                  "id": "version:n/a through 4.2.9",
                  "keyphrase": "n/a through 4.2.9",
                  "type": "version"
                }
              ]
            },
            "similarity": 280.00401477133397
          },
          {
            "metadata": {
              "doc_id": "116",
              "name": "Improper Encoding or Escaping of Output",
              "source": "sparse",
              "original_content": "The product prepares a structured message for communication with another component, but encoding or escaping of the data is either missing or done incorrectly. As a result, the intended structure of the message is not preserved.",
              "keyphrase_sources": [
                {
                  "id": "rootcause:Improper Neutralization of Input During Web Page Generation",
                  "keyphrase": "Improper Neutralization of Input During Web Page Generation",
                  "type": "rootcause"
                },
                {
                  "id": "weakness:XSS",
                  "keyphrase": "XSS",
                  "type": "weakness"
                },
                {
                  "id": "weakness:cross-site scripting",
                  "keyphrase": "cross-site scripting",
                  "type": "weakness"
                },
                {
                  "id": "product:vinoth06 Random Banner",
                  "keyphrase": "vinoth06 Random Banner",
                  "type": "product"
                },
                {
                  "id": "version:n/a through 4.2.9",
                  "keyphrase": "n/a through 4.2.9",
                  "type": "version"
                }
              ]
            },
            "similarity": 259.0001279212921
          },
          {
            "metadata": {
              "doc_id": "89",
              "name": "Improper Neutralization of Special Elements used in an SQL Command ('SQL Injection')",
              "source": "sparse",
              "original_content": "The product constructs all or part of an SQL command using externally-influenced input from an upstream component, but it does not neutralize or incorrectly neutralizes special elements that could modify the intended SQL command when it is sent to a downstream component. Without sufficient removal or quoting of SQL syntax in user-controllable inputs, the generated SQL query can cause those inputs to be interpreted as SQL instead of ordinary user data.",
              "keyphrase_sources": [
                {
                  "id": "rootcause:Improper Neutralization of Input During Web Page Generation",
                  "keyphrase": "Improper Neutralization of Input During Web Page Generation",
                  "type": "rootcause"
                }
              ]
            },
            "similarity": 240.44901627564565
          },
          {
            "metadata": {
              "doc_id": "352",
              "name": "Cross-Site Request Forgery (CSRF)",
              "source": "sparse",
              "original_content": "The web application does not, or can not, sufficiently verify whether a well-formed, valid, consistent request was intentionally provided by the user who submitted the request.",
              "keyphrase_sources": [
                {
                  "id": "rootcause:Improper Neutralization of Input During Web Page Generation",
                  "keyphrase": "Improper Neutralization of Input During Web Page Generation",
                  "type": "rootcause"
                },
                {
                  "id": "weakness:XSS",
                  "keyphrase": "XSS",
                  "type": "weakness"
                },
                {
                  "id": "weakness:cross-site scripting",
                  "keyphrase": "cross-site scripting",
                  "type": "weakness"
                },
                {
                  "id": "product:vinoth06 Random Banner",
                  "keyphrase": "vinoth06 Random Banner",
                  "type": "product"
                },
                {
                  "id": "version:n/a through 4.2.9",
                  "keyphrase": "n/a through 4.2.9",
                  "type": "version"
                }
              ]
            },
            "similarity": 237.2695683778421
          }
        ]
      },
      "weakness:XSS": {
        "keyphrase": "XSS",
        "type": "weakness",
        "cwes": [
          {
            "metadata": {
              "doc_id": "79",
              "name": "Improper Neutralization of Input During Web Page Generation ('Cross-site Scripting')",
              "source": "sparse",
              "original_content": "The product does not neutralize or incorrectly neutralizes user-controllable input before it is placed in output that is used as a web page that is served to other users."
            },
            "similarity": 210.3865836616188
          },
          {
            "metadata": {
              "doc_id": "116",
              "name": "Improper Encoding or Escaping of Output",
              "source": "sparse",
              "original_content": "The product prepares a structured message for communication with another component, but encoding or escaping of the data is either missing or done incorrectly. As a result, the intended structure of the message is not preserved."
            },
            "similarity": 203.0407441835983
          },
          {
            "metadata": {
              "doc_id": "80",
              "name": "Improper Neutralization of Script-Related HTML Tags in a Web Page (Basic XSS)",
              "source": "sparse",
              "original_content": "The product receives input from an upstream component, but it does not neutralize or incorrectly neutralizes special characters such as \"<\", \">\", and \"&\" that could be interpreted as web-scripting elements when they are sent to a downstream component that processes web pages."
            },
            "similarity": 198.72848867763693
          },
          {
            "metadata": {
              "doc_id": "352",
              "name": "Cross-Site Request Forgery (CSRF)",
              "source": "sparse",
              "original_content": "The web application does not, or can not, sufficiently verify whether a well-formed, valid, consistent request was intentionally provided by the user who submitted the request."
            },
            "similarity": 196.6798817237615
          },
          {
            "metadata": {
              "doc_id": "434",
              "name": "Unrestricted Upload of File with Dangerous Type",
              "source": "sparse",
              "original_content": "The product allows the upload or transfer of dangerous file types that are automatically processed within its environment.",
              "keyphrase_sources": [
                {
                  "id": "weakness:XSS",
                  "keyphrase": "XSS",
                  "type": "weakness"
                },
                {
                  "id": "weakness:cross-site scripting",
                  "keyphrase": "cross-site scripting",
                  "type": "weakness"
                },
                {
                  "id": "product:vinoth06 Random Banner",
                  "keyphrase": "vinoth06 Random Banner",
                  "type": "product"
                },
                {
                  "id": "version:n/a through 4.2.9",
                  "keyphrase": "n/a through 4.2.9",
                  "type": "version"
                }
              ]
            },
            "similarity": 182.81753952789558
          }
        ]
      },
      "weakness:cross-site scripting": {
        "keyphrase": "cross-site scripting",
        "type": "weakness",
        "cwes": [
          {
            "metadata": {
              "doc_id": "79",
              "name": "Improper Neutralization of Input During Web Page Generation ('Cross-site Scripting')",
              "source": "sparse",
              "original_content": "The product does not neutralize or incorrectly neutralizes user-controllable input before it is placed in output that is used as a web page that is served to other users."
            },
            "similarity": 272.35137501850494
          },
          {
            "metadata": {
              "doc_id": "352",
              "name": "Cross-Site Request Forgery (CSRF)",
              "source": "sparse",
              "original_content": "The web application does not, or can not, sufficiently verify whether a well-formed, valid, consistent request was intentionally provided by the user who submitted the request."
            },
            "similarity": 264.7030269998974
          },
          {
            "metadata": {
              "doc_id": "80",
              "name": "Improper Neutralization of Script-Related HTML Tags in a Web Page (Basic XSS)",
              "source": "sparse",
              "original_content": "The product receives input from an upstream component, but it does not neutralize or incorrectly neutralizes special characters such as \"<\", \">\", and \"&\" that could be interpreted as web-scripting elements when they are sent to a downstream component that processes web pages."
            },
            "similarity": 255.40699189611524
          },
          {
            "metadata": {
              "doc_id": "116",
              "name": "Improper Encoding or Escaping of Output",
              "source": "sparse",
              "original_content": "The product prepares a structured message for communication with another component, but encoding or escaping of the data is either missing or done incorrectly. As a result, the intended structure of the message is not preserved."
            },
            "similarity": 250.21097206775875
          },
          {
            "metadata": {
              "doc_id": "434",
              "name": "Unrestricted Upload of File with Dangerous Type",
              "source": "sparse",
              "original_content": "The product allows the upload or transfer of dangerous file types that are automatically processed within its environment."
            },
            "similarity": 221.42610467617232
          }
        ]
      },
      "product:vinoth06 Random Banner": {
        "keyphrase": "vinoth06 Random Banner",
        "type": "product",
        "cwes": [
          {
            "metadata": {
              "doc_id": "116",
              "name": "Improper Encoding or Escaping of Output",
              "source": "sparse",
              "original_content": "The product prepares a structured message for communication with another component, but encoding or escaping of the data is either missing or done incorrectly. As a result, the intended structure of the message is not preserved."
            },
            "similarity": 75.06221524406642
          },
          {
            "metadata": {
              "doc_id": "352",
              "name": "Cross-Site Request Forgery (CSRF)",
              "source": "sparse",
              "original_content": "The web application does not, or can not, sufficiently verify whether a well-formed, valid, consistent request was intentionally provided by the user who submitted the request."
            },
            "similarity": 67.3213326785787
          },
          {
            "metadata": {
              "doc_id": "434",
              "name": "Unrestricted Upload of File with Dangerous Type",
              "source": "sparse",
              "original_content": "The product allows the upload or transfer of dangerous file types that are automatically processed within its environment."
            },
            "similarity": 67.10341167545758
          },
          {
            "metadata": {
              "doc_id": "79",
              "name": "Improper Neutralization of Input During Web Page Generation ('Cross-site Scripting')",
              "source": "sparse",
              "original_content": "The product does not neutralize or incorrectly neutralizes user-controllable input before it is placed in output that is used as a web page that is served to other users."
            },
            "similarity": 66.13859488916522
          },
          {
            "metadata": {
              "doc_id": "80",
              "name": "Improper Neutralization of Script-Related HTML Tags in a Web Page (Basic XSS)",
              "source": "sparse",
              "original_content": "The product receives input from an upstream component, but it does not neutralize or incorrectly neutralizes special characters such as \"<\", \">\", and \"&\" that could be interpreted as web-scripting elements when they are sent to a downstream component that processes web pages."
            },
            "similarity": 60.489721164724145
          }
        ]
      },
      "version:n/a through 4.2.9": {
        "keyphrase": "n/a through 4.2.9",
        "type": "version",
        "cwes": [
          {
            "metadata": {
              "doc_id": "434",
              "name": "Unrestricted Upload of File with Dangerous Type",
              "source": "sparse",
              "original_content": "The product allows the upload or transfer of dangerous file types that are automatically processed within its environment."
            },
            "similarity": 82.22269394092348
          },
          {
            "metadata": {
              "doc_id": "79",
              "name": "Improper Neutralization of Input During Web Page Generation ('Cross-site Scripting')",
              "source": "sparse",
              "original_content": "The product does not neutralize or incorrectly neutralizes user-controllable input before it is placed in output that is used as a web page that is served to other users."
            },
            "similarity": 81.95409351641833
          },
          {
            "metadata": {
              "doc_id": "116",
              "name": "Improper Encoding or Escaping of Output",
              "source": "sparse",
              "original_content": "The product prepares a structured message for communication with another component, but encoding or escaping of the data is either missing or done incorrectly. As a result, the intended structure of the message is not preserved."
            },
            "similarity": 80.71872249792513
          },
          {
            "metadata": {
              "doc_id": "352",
              "name": "Cross-Site Request Forgery (CSRF)",
              "source": "sparse",
              "original_content": "The web application does not, or can not, sufficiently verify whether a well-formed, valid, consistent request was intentionally provided by the user who submitted the request."
            },
            "similarity": 79.19133359188476
          },
          {
            "metadata": {
              "doc_id": "80",
              "name": "Improper Neutralization of Script-Related HTML Tags in a Web Page (Basic XSS)",
              "source": "sparse",
              "original_content": "The product receives input from an upstream component, but it does not neutralize or incorrectly neutralizes special characters such as \"<\", \">\", and \"&\" that could be interpreted as web-scripting elements when they are sent to a downstream component that processes web pages."
            },
            "similarity": 75.32022239871883
          }
        ]
      }
    },
    "keyphrase_mapping": {
      "79": [
        {
          "id": "rootcause:Improper Neutralization of Input During Web Page Generation",
          "keyphrase": "Improper Neutralization of Input During Web Page Generation",
          "type": "rootcause"
        },
        {
          "id": "weakness:XSS",
          "keyphrase": "XSS",
          "type": "weakness"
        },
        {
          "id": "weakness:cross-site scripting",
          "keyphrase": "cross-site scripting",
          "type": "weakness"
        },
        {
          "id": "product:vinoth06 Random Banner",
          "keyphrase": "vinoth06 Random Banner",
          "type": "product"
        },
        {
          "id": "version:n/a through 4.2.9",
          "keyphrase": "n/a through 4.2.9",
          "type": "version"
        }
      ],
      "80": [
        {
          "id": "rootcause:Improper Neutralization of Input During Web Page Generation",
          "keyphrase": "Improper Neutralization of Input During Web Page Generation",
          "type": "rootcause"
        },
        {
          "id": "weakness:XSS",
          "keyphrase": "XSS",
          "type": "weakness"
        },
        {
          "id": "weakness:cross-site scripting",
          "keyphrase": "cross-site scripting",
          "type": "weakness"
        },
        {
          "id": "product:vinoth06 Random Banner",
          "keyphrase": "vinoth06 Random Banner",
          "type": "product"
        },
        {
          "id": "version:n/a through 4.2.9",
          "keyphrase": "n/a through 4.2.9",
          "type": "version"
        }
      ],
      "116": [
        {
          "id": "rootcause:Improper Neutralization of Input During Web Page Generation",
          "keyphrase": "Improper Neutralization of Input During Web Page Generation",
          "type": "rootcause"
        },
        {
          "id": "weakness:XSS",
          "keyphrase": "XSS",
          "type": "weakness"
        },
        {
          "id": "weakness:cross-site scripting",
          "keyphrase": "cross-site scripting",
          "type": "weakness"
        },
        {
          "id": "product:vinoth06 Random Banner",
          "keyphrase": "vinoth06 Random Banner",
          "type": "product"
        },
        {
          "id": "version:n/a through 4.2.9",
          "keyphrase": "n/a through 4.2.9",
          "type": "version"
        }
      ],
      "89": [
        {
          "id": "rootcause:Improper Neutralization of Input During Web Page Generation",
          "keyphrase": "Improper Neutralization of Input During Web Page Generation",
          "type": "rootcause"
        }
      ],
      "352": [
        {
          "id": "rootcause:Improper Neutralization of Input During Web Page Generation",
          "keyphrase": "Improper Neutralization of Input During Web Page Generation",
          "type": "rootcause"
        },
        {
          "id": "weakness:XSS",
          "keyphrase": "XSS",
          "type": "weakness"
        },
        {
          "id": "weakness:cross-site scripting",
          "keyphrase": "cross-site scripting",
          "type": "weakness"
        },
        {
          "id": "product:vinoth06 Random Banner",
          "keyphrase": "vinoth06 Random Banner",
          "type": "product"
        },
        {
          "id": "version:n/a through 4.2.9",
          "keyphrase": "n/a through 4.2.9",
          "type": "version"
        }
      ],
      "434": [
        {
          "id": "weakness:XSS",
          "keyphrase": "XSS",
          "type": "weakness"
        },
        {
          "id": "weakness:cross-site scripting",
          "keyphrase": "cross-site scripting",
          "type": "weakness"
        },
        {
          "id": "product:vinoth06 Random Banner",
          "keyphrase": "vinoth06 Random Banner",
          "type": "product"
        },
        {
          "id": "version:n/a through 4.2.9",
          "keyphrase": "n/a through 4.2.9",
          "type": "version"
        }
      ]
    },
    "relevant_cwes": [
      {
        "metadata": {
          "doc_id": "79",
          "name": "Improper Neutralization of Input During Web Page Generation ('Cross-site Scripting')",
          "source": "sparse",
          "original_content": "The product does not neutralize or incorrectly neutralizes user-controllable input before it is placed in output that is used as a web page that is served to other users.",
          "keyphrase_sources": [
            {
              "id": "rootcause:Improper Neutralization of Input During Web Page Generation",
              "keyphrase": "Improper Neutralization of Input During Web Page Generation",
              "type": "rootcause"
            },
            {
              "id": "weakness:XSS",
              "keyphrase": "XSS",
              "type": "weakness"
            },
            {
              "id": "weakness:cross-site scripting",
              "keyphrase": "cross-site scripting",
              "type": "weakness"
            },
            {
              "id": "product:vinoth06 Random Banner",
              "keyphrase": "vinoth06 Random Banner",
              "type": "product"
            },
            {
              "id": "version:n/a through 4.2.9",
              "keyphrase": "n/a through 4.2.9",
              "type": "version"
            }
          ]
        },
        "similarity": 292.90379668287176
      },
      {
        "metadata": {
          "doc_id": "80",
          "name": "Improper Neutralization of Script-Related HTML Tags in a Web Page (Basic XSS)",
          "source": "sparse",
          "original_content": "The product receives input from an upstream component, but it does not neutralize or incorrectly neutralizes special characters such as \"<\", \">\", and \"&\" that could be interpreted as web-scripting elements when they are sent to a downstream component that processes web pages.",
          "keyphrase_sources": [
            {
              "id": "rootcause:Improper Neutralization of Input During Web Page Generation",
              "keyphrase": "Improper Neutralization of Input During Web Page Generation",
              "type": "rootcause"
            },
            {
              "id": "weakness:XSS",
              "keyphrase": "XSS",
              "type": "weakness"
            },
            {
              "id": "weakness:cross-site scripting",
              "keyphrase": "cross-site scripting",
              "type": "weakness"
            },
            {
              "id": "product:vinoth06 Random Banner",
              "keyphrase": "vinoth06 Random Banner",
              "type": "product"
            },
            {
              "id": "version:n/a through 4.2.9",
              "keyphrase": "n/a through 4.2.9",
              "type": "version"
            }
          ]
        },
        "similarity": 280.00401477133397
      },
      {
        "metadata": {
          "doc_id": "116",
          "name": "Improper Encoding or Escaping of Output",
          "source": "sparse",
          "original_content": "The product prepares a structured message for communication with another component, but encoding or escaping of the data is either missing or done incorrectly. As a result, the intended structure of the message is not preserved.",
          "keyphrase_sources": [
            {
              "id": "rootcause:Improper Neutralization of Input During Web Page Generation",
              "keyphrase": "Improper Neutralization of Input During Web Page Generation",
              "type": "rootcause"
            },
            {
              "id": "weakness:XSS",
              "keyphrase": "XSS",
              "type": "weakness"
            },
            {
              "id": "weakness:cross-site scripting",
              "keyphrase": "cross-site scripting",
              "type": "weakness"
            },
            {
              "id": "product:vinoth06 Random Banner",
              "keyphrase": "vinoth06 Random Banner",
              "type": "product"
            },
            {
              "id": "version:n/a through 4.2.9",
              "keyphrase": "n/a through 4.2.9",
              "type": "version"
            }
          ]
        },
        "similarity": 259.0001279212921
      },
      {
        "metadata": {
          "doc_id": "89",
          "name": "Improper Neutralization of Special Elements used in an SQL Command ('SQL Injection')",
          "source": "sparse",
          "original_content": "The product constructs all or part of an SQL command using externally-influenced input from an upstream component, but it does not neutralize or incorrectly neutralizes special elements that could modify the intended SQL command when it is sent to a downstream component. Without sufficient removal or quoting of SQL syntax in user-controllable inputs, the generated SQL query can cause those inputs to be interpreted as SQL instead of ordinary user data.",
          "keyphrase_sources": [
            {
              "id": "rootcause:Improper Neutralization of Input During Web Page Generation",
              "keyphrase": "Improper Neutralization of Input During Web Page Generation",
              "type": "rootcause"
            }
          ]
        },
        "similarity": 240.44901627564565
      },
      {
        "metadata": {
          "doc_id": "352",
          "name": "Cross-Site Request Forgery (CSRF)",
          "source": "sparse",
          "original_content": "The web application does not, or can not, sufficiently verify whether a well-formed, valid, consistent request was intentionally provided by the user who submitted the request.",
          "keyphrase_sources": [
            {
              "id": "rootcause:Improper Neutralization of Input During Web Page Generation",
              "keyphrase": "Improper Neutralization of Input During Web Page Generation",
              "type": "rootcause"
            },
            {
              "id": "weakness:XSS",
              "keyphrase": "XSS",
              "type": "weakness"
            },
            {
              "id": "weakness:cross-site scripting",
              "keyphrase": "cross-site scripting",
              "type": "weakness"
            },
            {
              "id": "product:vinoth06 Random Banner",
              "keyphrase": "vinoth06 Random Banner",
              "type": "product"
            },
            {
              "id": "version:n/a through 4.2.9",
              "keyphrase": "n/a through 4.2.9",
              "type": "version"
            }
          ]
        },
        "similarity": 237.2695683778421
      },
      {
        "metadata": {
          "doc_id": "434",
          "name": "Unrestricted Upload of File with Dangerous Type",
          "source": "sparse",
          "original_content": "The product allows the upload or transfer of dangerous file types that are automatically processed within its environment.",
          "keyphrase_sources": [
            {
              "id": "weakness:XSS",
              "keyphrase": "XSS",
              "type": "weakness"
            },
            {
              "id": "weakness:cross-site scripting",
              "keyphrase": "cross-site scripting",
              "type": "weakness"
            },
            {
              "id": "product:vinoth06 Random Banner",
              "keyphrase": "vinoth06 Random Banner",
              "type": "product"
            },
            {
              "id": "version:n/a through 4.2.9",
              "keyphrase": "n/a through 4.2.9",
              "type": "version"
            }
          ]
        },
        "similarity": 182.81753952789558
      }
    ],
    "enhanced_query": "# Vulnerability Description\n\n    **Improper Neutralization of Input During Web Page Generation** (Cross-site Scripting) vulnerability in vinoth06 Random Banner allows Stored **XSS**.This issue affects Random Banner from n/a through 4.2.9.\n\n    # Keyphrase-Specific CWE Analysis\n    This vulnerability contains multiple keyphrases that may map to different CWEs. \n    Please analyze each keyphrase separately and determine the most appropriate CWE(s) for each.\n\n    ## ROOTCAUSE: 'Improper Neutralization of Input During Web Page Generation'\n\nRelevant CWEs for this ROOTCAUSE:\n\n### 1. CWE-79: Improper Neutralization of Input During Web Page Generation ('Cross-site Scripting') (Score: 292.90)\n\nThe product does not neutralize or incorrectly neutralizes user-controllable input before it is placed in output that is used as a web page that is served to other users....\n\n### 2. CWE-80: Improper Neutralization of Script-Related HTML Tags in a Web Page (Basic XSS) (Score: 280.00)\n\nThe product receives input from an upstream component, but it does not neutralize or incorrectly neutralizes special characters such as \"<\", \">\", and \"&\" that could be interpreted as web-scripting elements when they are sent to a downstream component that processes web pages....\n\n### 3. CWE-116: Improper Encoding or Escaping of Output (Score: 259.00)\n\nThe product prepares a structured message for communication with another component, but encoding or escaping of the data is either missing or done incorrectly. As a result, the intended structure of the message is not preserved....\n\n### 4. CWE-89: Improper Neutralization of Special Elements used in an SQL Command ('SQL Injection') (Score: 240.45)\n\nThe product constructs all or part of an SQL command using externally-influenced input from an upstream component, but it does not neutralize or incorrectly neutralizes special elements that could modify the intended SQL command when it is sent to a downstream component. Without sufficient removal o...\n\n### 5. CWE-352: Cross-Site Request Forgery (CSRF) (Score: 237.27)\n\nThe web application does not, or can not, sufficiently verify whether a well-formed, valid, consistent request was intentionally provided by the user who submitted the request....\n\n## WEAKNESS: 'XSS'\n\nRelevant CWEs for this WEAKNESS:\n\n### 1. CWE-79: Improper Neutralization of Input During Web Page Generation ('Cross-site Scripting') (Score: 292.90)\n\nThe product does not neutralize or incorrectly neutralizes user-controllable input before it is placed in output that is used as a web page that is served to other users....\n\n### 2. CWE-80: Improper Neutralization of Script-Related HTML Tags in a Web Page (Basic XSS) (Score: 280.00)\n\nThe product receives input from an upstream component, but it does not neutralize or incorrectly neutralizes special characters such as \"<\", \">\", and \"&\" that could be interpreted as web-scripting elements when they are sent to a downstream component that processes web pages....\n\n### 3. CWE-116: Improper Encoding or Escaping of Output (Score: 259.00)\n\nThe product prepares a structured message for communication with another component, but encoding or escaping of the data is either missing or done incorrectly. As a result, the intended structure of the message is not preserved....\n\n### 4. CWE-352: Cross-Site Request Forgery (CSRF) (Score: 237.27)\n\nThe web application does not, or can not, sufficiently verify whether a well-formed, valid, consistent request was intentionally provided by the user who submitted the request....\n\n### 5. CWE-434: Unrestricted Upload of File with Dangerous Type (Score: 182.82)\n\nThe product allows the upload or transfer of dangerous file types that are automatically processed within its environment....\n\n## WEAKNESS: 'cross-site scripting'\n\nRelevant CWEs for this WEAKNESS:\n\n### 1. CWE-79: Improper Neutralization of Input During Web Page Generation ('Cross-site Scripting') (Score: 292.90)\n\nThe product does not neutralize or incorrectly neutralizes user-controllable input before it is placed in output that is used as a web page that is served to other users....\n\n### 2. CWE-80: Improper Neutralization of Script-Related HTML Tags in a Web Page (Basic XSS) (Score: 280.00)\n\nThe product receives input from an upstream component, but it does not neutralize or incorrectly neutralizes special characters such as \"<\", \">\", and \"&\" that could be interpreted as web-scripting elements when they are sent to a downstream component that processes web pages....\n\n### 3. CWE-116: Improper Encoding or Escaping of Output (Score: 259.00)\n\nThe product prepares a structured message for communication with another component, but encoding or escaping of the data is either missing or done incorrectly. As a result, the intended structure of the message is not preserved....\n\n### 4. CWE-352: Cross-Site Request Forgery (CSRF) (Score: 237.27)\n\nThe web application does not, or can not, sufficiently verify whether a well-formed, valid, consistent request was intentionally provided by the user who submitted the request....\n\n### 5. CWE-434: Unrestricted Upload of File with Dangerous Type (Score: 182.82)\n\nThe product allows the upload or transfer of dangerous file types that are automatically processed within its environment....\n\n## PRODUCT: 'vinoth06 Random Banner'\n\nRelevant CWEs for this PRODUCT:\n\n### 1. CWE-79: Improper Neutralization of Input During Web Page Generation ('Cross-site Scripting') (Score: 292.90)\n\nThe product does not neutralize or incorrectly neutralizes user-controllable input before it is placed in output that is used as a web page that is served to other users....\n\n### 2. CWE-80: Improper Neutralization of Script-Related HTML Tags in a Web Page (Basic XSS) (Score: 280.00)\n\nThe product receives input from an upstream component, but it does not neutralize or incorrectly neutralizes special characters such as \"<\", \">\", and \"&\" that could be interpreted as web-scripting elements when they are sent to a downstream component that processes web pages....\n\n### 3. CWE-116: Improper Encoding or Escaping of Output (Score: 259.00)\n\nThe product prepares a structured message for communication with another component, but encoding or escaping of the data is either missing or done incorrectly. As a result, the intended structure of the message is not preserved....\n\n### 4. CWE-352: Cross-Site Request Forgery (CSRF) (Score: 237.27)\n\nThe web application does not, or can not, sufficiently verify whether a well-formed, valid, consistent request was intentionally provided by the user who submitted the request....\n\n### 5. CWE-434: Unrestricted Upload of File with Dangerous Type (Score: 182.82)\n\nThe product allows the upload or transfer of dangerous file types that are automatically processed within its environment....\n\n## VERSION: 'n/a through 4.2.9'\n\nRelevant CWEs for this VERSION:\n\n### 1. CWE-79: Improper Neutralization of Input During Web Page Generation ('Cross-site Scripting') (Score: 292.90)\n\nThe product does not neutralize or incorrectly neutralizes user-controllable input before it is placed in output that is used as a web page that is served to other users....\n\n### 2. CWE-80: Improper Neutralization of Script-Related HTML Tags in a Web Page (Basic XSS) (Score: 280.00)\n\nThe product receives input from an upstream component, but it does not neutralize or incorrectly neutralizes special characters such as \"<\", \">\", and \"&\" that could be interpreted as web-scripting elements when they are sent to a downstream component that processes web pages....\n\n### 3. CWE-116: Improper Encoding or Escaping of Output (Score: 259.00)\n\nThe product prepares a structured message for communication with another component, but encoding or escaping of the data is either missing or done incorrectly. As a result, the intended structure of the message is not preserved....\n\n### 4. CWE-352: Cross-Site Request Forgery (CSRF) (Score: 237.27)\n\nThe web application does not, or can not, sufficiently verify whether a well-formed, valid, consistent request was intentionally provided by the user who submitted the request....\n\n### 5. CWE-434: Unrestricted Upload of File with Dangerous Type (Score: 182.82)\n\nThe product allows the upload or transfer of dangerous file types that are automatically processed within its environment....\n\n\n    # Analysis Instructions\n    1. For each keyphrase, identify the most appropriate CWE(s) that represent the weakness.\n    2. Consider how the different keyphrases might relate to each other in the vulnerability chain.\n    3. Provide a final determination of primary CWE(s) and any secondary CWEs.\n    4. Format your response using the standard analysis template.\n\n    Please analyze how these different weaknesses interact and provide a comprehensive CWE classification.\n    "
  },
  "retrieval_time": 1.0041968822479248
}