{
  "vulnerability_info": "VulnerabilityInfo(cve_id='CVE-2025-26702', description='Improper **Input Validation vulnerability** in ZTE GoldenDB allows Input Data Manipulation.This issue affects GoldenDB from 6.1.03 through 6.1.03.04.', key_phrases={'rootcause': ['Input Validation vulnerability', 'Improper Input Validation'], 'weakness': '', 'impact': 'Input Data Manipulation', 'vector': '', 'attacker': '', 'product': 'ZTE GoldenDB', 'version': '6.1.03 through 6.1.03.04', 'component': ''}, reference_content='UNRELATED', similar_info={'cwe_distribution': {}, 'cwe_consensus': '', 'similarity_stats': {'thresholds': [], 'total_samples_by_threshold': {}, 'top_cwes_by_threshold': {}}}, similarity_summary=SimilarityInsight(consensus_cwe='', top_cwes=[], confidence_levels={}, total_samples=0), analysis='', analysis_with_relationships='', criticism='', resolution='', relevant_cwes=[{'metadata': {'doc_id': '20', 'name': 'Improper Input Validation', 'source': 'sparse', 'original_content': 'The product receives input or data, but it does\\n        not validate or incorrectly validates that the input has the\\n        properties that are required to process the data safely and\\n        correctly.', 'keyphrase_sources': [{'id': 'rootcause:Input Validation vulnerability', 'keyphrase': 'Input Validation vulnerability', 'type': 'rootcause'}, {'id': 'rootcause:Improper Input Validation', 'keyphrase': 'Improper Input Validation', 'type': 'rootcause'}]}, 'similarity': np.float64(127.55130534657977)}, {'metadata': {'doc_id': '345', 'name': 'Insufficient Verification of Data Authenticity', 'source': 'sparse', 'original_content': 'The product does not sufficiently verify the origin or authenticity of data, in a way that causes it to accept invalid data.', 'keyphrase_sources': [{'id': 'rootcause:Input Validation vulnerability', 'keyphrase': 'Input Validation vulnerability', 'type': 'rootcause'}, {'id': 'rootcause:Improper Input Validation', 'keyphrase': 'Improper Input Validation', 'type': 'rootcause'}, {'id': 'impact:Input Data Manipulation', 'keyphrase': 'Input Data Manipulation', 'type': 'impact'}, {'id': 'product:ZTE GoldenDB', 'keyphrase': 'ZTE GoldenDB', 'type': 'product'}, {'id': 'version:6.1.03 through 6.1.03.04', 'keyphrase': '6.1.03 through 6.1.03.04', 'type': 'version'}]}, 'similarity': np.float64(123.77126062103444)}, {'metadata': {'doc_id': '36', 'name': 'Absolute Path Traversal', 'source': 'sparse', 'original_content': 'The product uses external input to construct a pathname that should be within a restricted directory, but it does not properly neutralize absolute path sequences such as \"/abs/path\" that can resolve to a location that is outside of that directory.', 'keyphrase_sources': [{'id': 'rootcause:Input Validation vulnerability', 'keyphrase': 'Input Validation vulnerability', 'type': 'rootcause'}, {'id': 'rootcause:Improper Input Validation', 'keyphrase': 'Improper Input Validation', 'type': 'rootcause'}, {'id': 'impact:Input Data Manipulation', 'keyphrase': 'Input Data Manipulation', 'type': 'impact'}, {'id': 'product:ZTE GoldenDB', 'keyphrase': 'ZTE GoldenDB', 'type': 'product'}, {'id': 'version:6.1.03 through 6.1.03.04', 'keyphrase': '6.1.03 through 6.1.03.04', 'type': 'version'}]}, 'similarity': np.float64(121.73867916397896)}, {'metadata': {'doc_id': '1285', 'name': 'Improper Validation of Specified Index, Position, or Offset in Input', 'source': 'sparse', 'original_content': 'The product receives input that is expected to specify an index, position, or offset into an indexable resource such as a buffer or file, but it does not validate or incorrectly validates that the specified index/position/offset has the required properties.', 'keyphrase_sources': [{'id': 'rootcause:Improper Input Validation', 'keyphrase': 'Improper Input Validation', 'type': 'rootcause'}]}, 'similarity': np.float64(116.75484404594202)}, {'metadata': {'doc_id': '95', 'name': \"Improper Neutralization of Directives in Dynamically Evaluated Code ('Eval Injection')\", 'source': 'sparse', 'original_content': 'The product receives input from an upstream component, but it does not neutralize or incorrectly neutralizes code syntax before using the input in a dynamic evaluation call (e.g. \"eval\").', 'keyphrase_sources': [{'id': 'rootcause:Input Validation vulnerability', 'keyphrase': 'Input Validation vulnerability', 'type': 'rootcause'}, {'id': 'rootcause:Improper Input Validation', 'keyphrase': 'Improper Input Validation', 'type': 'rootcause'}, {'id': 'product:ZTE GoldenDB', 'keyphrase': 'ZTE GoldenDB', 'type': 'product'}]}, 'similarity': np.float64(115.73798201495947)}, {'metadata': {'doc_id': '93', 'name': \"Improper Neutralization of CRLF Sequences ('CRLF Injection')\", 'source': 'sparse', 'original_content': 'The product uses CRLF (carriage return line feeds) as a special element, e.g. to separate lines or records, but it does not neutralize or incorrectly neutralizes CRLF sequences from inputs.', 'keyphrase_sources': [{'id': 'rootcause:Input Validation vulnerability', 'keyphrase': 'Input Validation vulnerability', 'type': 'rootcause'}, {'id': 'impact:Input Data Manipulation', 'keyphrase': 'Input Data Manipulation', 'type': 'impact'}, {'id': 'product:ZTE GoldenDB', 'keyphrase': 'ZTE GoldenDB', 'type': 'product'}]}, 'similarity': np.float64(114.73457209691452)}, {'metadata': {'doc_id': '653', 'name': 'Improper Isolation or Compartmentalization', 'source': 'sparse', 'original_content': 'The product does not properly compartmentalize or isolate functionality, processes, or resources that require different privilege levels, rights, or permissions.', 'keyphrase_sources': [{'id': 'version:6.1.03 through 6.1.03.04', 'keyphrase': '6.1.03 through 6.1.03.04', 'type': 'version'}]}, 'similarity': np.float64(73.53974257165852)}, {'metadata': {'doc_id': '657', 'name': 'Violation of Secure Design Principles', 'source': 'sparse', 'original_content': 'The product violates well-established principles for secure design.', 'keyphrase_sources': [{'id': 'version:6.1.03 through 6.1.03.04', 'keyphrase': '6.1.03 through 6.1.03.04', 'type': 'version'}]}, 'similarity': np.float64(65.52941256054339)}, {'metadata': {'doc_id': '302', 'name': 'Authentication Bypass by Assumed-Immutable Data', 'source': 'sparse', 'original_content': 'The authentication scheme or implementation uses key data elements that are assumed to be immutable, but can be controlled or modified by the attacker.', 'keyphrase_sources': [{'id': 'version:6.1.03 through 6.1.03.04', 'keyphrase': '6.1.03 through 6.1.03.04', 'type': 'version'}]}, 'similarity': np.float64(65.17114802653965)}, {'metadata': {'doc_id': '89', 'name': \"Improper Neutralization of Special Elements used in an SQL Command ('SQL Injection')\", 'source': 'sparse', 'original_content': 'The product constructs all or part of an SQL command using externally-influenced input from an upstream component, but it does not neutralize or incorrectly neutralizes special elements that could modify the intended SQL command when it is sent to a downstream component. Without sufficient removal or quoting of SQL syntax in user-controllable inputs, the generated SQL query can cause those inputs to be interpreted as SQL instead of ordinary user data.', 'keyphrase_sources': [{'id': 'impact:Input Data Manipulation', 'keyphrase': 'Input Data Manipulation', 'type': 'impact'}]}, 'similarity': np.float64(40.70743522677693)}, {'metadata': {'doc_id': '79', 'name': \"Improper Neutralization of Input During Web Page Generation ('Cross-site Scripting')\", 'source': 'sparse', 'original_content': 'The product does not neutralize or incorrectly neutralizes user-controllable input before it is placed in output that is used as a web page that is served to other users.', 'keyphrase_sources': [{'id': 'impact:Input Data Manipulation', 'keyphrase': 'Input Data Manipulation', 'type': 'impact'}]}, 'similarity': np.float64(39.83311272226361)}, {'metadata': {'doc_id': '121', 'name': 'Stack-based Buffer Overflow', 'source': 'sparse', 'original_content': 'A stack-based buffer overflow condition is a condition where the buffer being overwritten is allocated on the stack (i.e., is a local variable or, rarely, a parameter to a function).', 'keyphrase_sources': [{'id': 'product:ZTE GoldenDB', 'keyphrase': 'ZTE GoldenDB', 'type': 'product'}]}, 'similarity': np.float64(33.93604344570234)}], identified_cwes={'analyzer': [], 'critic_additional': []})",
  "retrieval_results": {
    "has_multiple_keyphrases": true,
    "keyphrase_cwe_sets": {
      "rootcause:Input Validation vulnerability": {
        "keyphrase": "Input Validation vulnerability",
        "type": "rootcause",
        "cwes": [
          {
            "metadata": {
              "doc_id": "20",
              "name": "Improper Input Validation",
              "source": "sparse",
              "original_content": "The product receives input or data, but it does\n        not validate or incorrectly validates that the input has the\n        properties that are required to process the data safely and\n        correctly.",
              "keyphrase_sources": [
                {
                  "id": "rootcause:Input Validation vulnerability",
                  "keyphrase": "Input Validation vulnerability",
                  "type": "rootcause"
                },
                {
                  "id": "rootcause:Improper Input Validation",
                  "keyphrase": "Improper Input Validation",
                  "type": "rootcause"
                }
              ]
            },
            "similarity": 127.55130534657977
          },
          {
            "metadata": {
              "doc_id": "345",
              "name": "Insufficient Verification of Data Authenticity",
              "source": "sparse",
              "original_content": "The product does not sufficiently verify the origin or authenticity of data, in a way that causes it to accept invalid data.",
              "keyphrase_sources": [
                {
                  "id": "rootcause:Input Validation vulnerability",
                  "keyphrase": "Input Validation vulnerability",
                  "type": "rootcause"
                },
                {
                  "id": "rootcause:Improper Input Validation",
                  "keyphrase": "Improper Input Validation",
                  "type": "rootcause"
                },
                {
                  "id": "impact:Input Data Manipulation",
                  "keyphrase": "Input Data Manipulation",
                  "type": "impact"
                },
                {
                  "id": "product:ZTE GoldenDB",
                  "keyphrase": "ZTE GoldenDB",
                  "type": "product"
                },
                {
                  "id": "version:6.1.03 through 6.1.03.04",
                  "keyphrase": "6.1.03 through 6.1.03.04",
                  "type": "version"
                }
              ]
            },
            "similarity": 123.77126062103444
          },
          {
            "metadata": {
              "doc_id": "36",
              "name": "Absolute Path Traversal",
              "source": "sparse",
              "original_content": "The product uses external input to construct a pathname that should be within a restricted directory, but it does not properly neutralize absolute path sequences such as \"/abs/path\" that can resolve to a location that is outside of that directory.",
              "keyphrase_sources": [
                {
                  "id": "rootcause:Input Validation vulnerability",
                  "keyphrase": "Input Validation vulnerability",
                  "type": "rootcause"
                },
                {
                  "id": "rootcause:Improper Input Validation",
                  "keyphrase": "Improper Input Validation",
                  "type": "rootcause"
                },
                {
                  "id": "impact:Input Data Manipulation",
                  "keyphrase": "Input Data Manipulation",
                  "type": "impact"
                },
                {
                  "id": "product:ZTE GoldenDB",
                  "keyphrase": "ZTE GoldenDB",
                  "type": "product"
                },
                {
                  "id": "version:6.1.03 through 6.1.03.04",
                  "keyphrase": "6.1.03 through 6.1.03.04",
                  "type": "version"
                }
              ]
            },
            "similarity": 121.73867916397896
          },
          {
            "metadata": {
              "doc_id": "95",
              "name": "Improper Neutralization of Directives in Dynamically Evaluated Code ('Eval Injection')",
              "source": "sparse",
              "original_content": "The product receives input from an upstream component, but it does not neutralize or incorrectly neutralizes code syntax before using the input in a dynamic evaluation call (e.g. \"eval\").",
              "keyphrase_sources": [
                {
                  "id": "rootcause:Input Validation vulnerability",
                  "keyphrase": "Input Validation vulnerability",
                  "type": "rootcause"
                },
                {
                  "id": "rootcause:Improper Input Validation",
                  "keyphrase": "Improper Input Validation",
                  "type": "rootcause"
                },
                {
                  "id": "product:ZTE GoldenDB",
                  "keyphrase": "ZTE GoldenDB",
                  "type": "product"
                }
              ]
            },
            "similarity": 115.73798201495947
          },
          {
            "metadata": {
              "doc_id": "93",
              "name": "Improper Neutralization of CRLF Sequences ('CRLF Injection')",
              "source": "sparse",
              "original_content": "The product uses CRLF (carriage return line feeds) as a special element, e.g. to separate lines or records, but it does not neutralize or incorrectly neutralizes CRLF sequences from inputs.",
              "keyphrase_sources": [
                {
                  "id": "rootcause:Input Validation vulnerability",
                  "keyphrase": "Input Validation vulnerability",
                  "type": "rootcause"
                },
                {
                  "id": "impact:Input Data Manipulation",
                  "keyphrase": "Input Data Manipulation",
                  "type": "impact"
                },
                {
                  "id": "product:ZTE GoldenDB",
                  "keyphrase": "ZTE GoldenDB",
                  "type": "product"
                }
              ]
            },
            "similarity": 114.73457209691452
          }
        ]
      },
      "rootcause:Improper Input Validation": {
        "keyphrase": "Improper Input Validation",
        "type": "rootcause",
        "cwes": [
          {
            "metadata": {
              "doc_id": "20",
              "name": "Improper Input Validation",
              "source": "sparse",
              "original_content": "The product receives input or data, but it does\n        not validate or incorrectly validates that the input has the\n        properties that are required to process the data safely and\n        correctly."
            },
            "similarity": 132.30428386401422
          },
          {
            "metadata": {
              "doc_id": "345",
              "name": "Insufficient Verification of Data Authenticity",
              "source": "sparse",
              "original_content": "The product does not sufficiently verify the origin or authenticity of data, in a way that causes it to accept invalid data."
            },
            "similarity": 125.0053424536839
          },
          {
            "metadata": {
              "doc_id": "36",
              "name": "Absolute Path Traversal",
              "source": "sparse",
              "original_content": "The product uses external input to construct a pathname that should be within a restricted directory, but it does not properly neutralize absolute path sequences such as \"/abs/path\" that can resolve to a location that is outside of that directory."
            },
            "similarity": 121.36454577460363
          },
          {
            "metadata": {
              "doc_id": "95",
              "name": "Improper Neutralization of Directives in Dynamically Evaluated Code ('Eval Injection')",
              "source": "sparse",
              "original_content": "The product receives input from an upstream component, but it does not neutralize or incorrectly neutralizes code syntax before using the input in a dynamic evaluation call (e.g. \"eval\")."
            },
            "similarity": 117.08092907294213
          },
          {
            "metadata": {
              "doc_id": "1285",
              "name": "Improper Validation of Specified Index, Position, or Offset in Input",
              "source": "sparse",
              "original_content": "The product receives input that is expected to specify an index, position, or offset into an indexable resource such as a buffer or file, but it does not validate or incorrectly validates that the specified index/position/offset has the required properties.",
              "keyphrase_sources": [
                {
                  "id": "rootcause:Improper Input Validation",
                  "keyphrase": "Improper Input Validation",
                  "type": "rootcause"
                }
              ]
            },
            "similarity": 116.75484404594202
          }
        ]
      },
      "impact:Input Data Manipulation": {
        "keyphrase": "Input Data Manipulation",
        "type": "impact",
        "cwes": [
          {
            "metadata": {
              "doc_id": "345",
              "name": "Insufficient Verification of Data Authenticity",
              "source": "sparse",
              "original_content": "The product does not sufficiently verify the origin or authenticity of data, in a way that causes it to accept invalid data."
            },
            "similarity": 41.07060365505804
          },
          {
            "metadata": {
              "doc_id": "89",
              "name": "Improper Neutralization of Special Elements used in an SQL Command ('SQL Injection')",
              "source": "sparse",
              "original_content": "The product constructs all or part of an SQL command using externally-influenced input from an upstream component, but it does not neutralize or incorrectly neutralizes special elements that could modify the intended SQL command when it is sent to a downstream component. Without sufficient removal or quoting of SQL syntax in user-controllable inputs, the generated SQL query can cause those inputs to be interpreted as SQL instead of ordinary user data.",
              "keyphrase_sources": [
                {
                  "id": "impact:Input Data Manipulation",
                  "keyphrase": "Input Data Manipulation",
                  "type": "impact"
                }
              ]
            },
            "similarity": 40.70743522677693
          },
          {
            "metadata": {
              "doc_id": "79",
              "name": "Improper Neutralization of Input During Web Page Generation ('Cross-site Scripting')",
              "source": "sparse",
              "original_content": "The product does not neutralize or incorrectly neutralizes user-controllable input before it is placed in output that is used as a web page that is served to other users.",
              "keyphrase_sources": [
                {
                  "id": "impact:Input Data Manipulation",
                  "keyphrase": "Input Data Manipulation",
                  "type": "impact"
                }
              ]
            },
            "similarity": 39.83311272226361
          },
          {
            "metadata": {
              "doc_id": "93",
              "name": "Improper Neutralization of CRLF Sequences ('CRLF Injection')",
              "source": "sparse",
              "original_content": "The product uses CRLF (carriage return line feeds) as a special element, e.g. to separate lines or records, but it does not neutralize or incorrectly neutralizes CRLF sequences from inputs."
            },
            "similarity": 37.89797038570503
          },
          {
            "metadata": {
              "doc_id": "36",
              "name": "Absolute Path Traversal",
              "source": "sparse",
              "original_content": "The product uses external input to construct a pathname that should be within a restricted directory, but it does not properly neutralize absolute path sequences such as \"/abs/path\" that can resolve to a location that is outside of that directory."
            },
            "similarity": 36.83700683691919
          }
        ]
      },
      "product:ZTE GoldenDB": {
        "keyphrase": "ZTE GoldenDB",
        "type": "product",
        "cwes": [
          {
            "metadata": {
              "doc_id": "93",
              "name": "Improper Neutralization of CRLF Sequences ('CRLF Injection')",
              "source": "sparse",
              "original_content": "The product uses CRLF (carriage return line feeds) as a special element, e.g. to separate lines or records, but it does not neutralize or incorrectly neutralizes CRLF sequences from inputs."
            },
            "similarity": 37.20455589712402
          },
          {
            "metadata": {
              "doc_id": "345",
              "name": "Insufficient Verification of Data Authenticity",
              "source": "sparse",
              "original_content": "The product does not sufficiently verify the origin or authenticity of data, in a way that causes it to accept invalid data."
            },
            "similarity": 35.3871970674886
          },
          {
            "metadata": {
              "doc_id": "121",
              "name": "Stack-based Buffer Overflow",
              "source": "sparse",
              "original_content": "A stack-based buffer overflow condition is a condition where the buffer being overwritten is allocated on the stack (i.e., is a local variable or, rarely, a parameter to a function).",
              "keyphrase_sources": [
                {
                  "id": "product:ZTE GoldenDB",
                  "keyphrase": "ZTE GoldenDB",
                  "type": "product"
                }
              ]
            },
            "similarity": 33.93604344570234
          },
          {
            "metadata": {
              "doc_id": "36",
              "name": "Absolute Path Traversal",
              "source": "sparse",
              "original_content": "The product uses external input to construct a pathname that should be within a restricted directory, but it does not properly neutralize absolute path sequences such as \"/abs/path\" that can resolve to a location that is outside of that directory."
            },
            "similarity": 33.80004191293956
          },
          {
            "metadata": {
              "doc_id": "95",
              "name": "Improper Neutralization of Directives in Dynamically Evaluated Code ('Eval Injection')",
              "source": "sparse",
              "original_content": "The product receives input from an upstream component, but it does not neutralize or incorrectly neutralizes code syntax before using the input in a dynamic evaluation call (e.g. \"eval\")."
            },
            "similarity": 32.422260659023515
          }
        ]
      },
      "version:6.1.03 through 6.1.03.04": {
        "keyphrase": "6.1.03 through 6.1.03.04",
        "type": "version",
        "cwes": [
          {
            "metadata": {
              "doc_id": "36",
              "name": "Absolute Path Traversal",
              "source": "sparse",
              "original_content": "The product uses external input to construct a pathname that should be within a restricted directory, but it does not properly neutralize absolute path sequences such as \"/abs/path\" that can resolve to a location that is outside of that directory."
            },
            "similarity": 74.8608668681272
          },
          {
            "metadata": {
              "doc_id": "653",
              "name": "Improper Isolation or Compartmentalization",
              "source": "sparse",
              "original_content": "The product does not properly compartmentalize or isolate functionality, processes, or resources that require different privilege levels, rights, or permissions.",
              "keyphrase_sources": [
                {
                  "id": "version:6.1.03 through 6.1.03.04",
                  "keyphrase": "6.1.03 through 6.1.03.04",
                  "type": "version"
                }
              ]
            },
            "similarity": 73.53974257165852
          },
          {
            "metadata": {
              "doc_id": "345",
              "name": "Insufficient Verification of Data Authenticity",
              "source": "sparse",
              "original_content": "The product does not sufficiently verify the origin or authenticity of data, in a way that causes it to accept invalid data."
            },
            "similarity": 71.51963000111374
          },
          {
            "metadata": {
              "doc_id": "657",
              "name": "Violation of Secure Design Principles",
              "source": "sparse",
              "original_content": "The product violates well-established principles for secure design.",
              "keyphrase_sources": [
                {
                  "id": "version:6.1.03 through 6.1.03.04",
                  "keyphrase": "6.1.03 through 6.1.03.04",
                  "type": "version"
                }
              ]
            },
            "similarity": 65.52941256054339
          },
          {
            "metadata": {
              "doc_id": "302",
              "name": "Authentication Bypass by Assumed-Immutable Data",
              "source": "sparse",
              "original_content": "The authentication scheme or implementation uses key data elements that are assumed to be immutable, but can be controlled or modified by the attacker.",
              "keyphrase_sources": [
                {
                  "id": "version:6.1.03 through 6.1.03.04",
                  "keyphrase": "6.1.03 through 6.1.03.04",
                  "type": "version"
                }
              ]
            },
            "similarity": 65.17114802653965
          }
        ]
      }
    },
    "keyphrase_mapping": {
      "20": [
        {
          "id": "rootcause:Input Validation vulnerability",
          "keyphrase": "Input Validation vulnerability",
          "type": "rootcause"
        },
        {
          "id": "rootcause:Improper Input Validation",
          "keyphrase": "Improper Input Validation",
          "type": "rootcause"
        }
      ],
      "345": [
        {
          "id": "rootcause:Input Validation vulnerability",
          "keyphrase": "Input Validation vulnerability",
          "type": "rootcause"
        },
        {
          "id": "rootcause:Improper Input Validation",
          "keyphrase": "Improper Input Validation",
          "type": "rootcause"
        },
        {
          "id": "impact:Input Data Manipulation",
          "keyphrase": "Input Data Manipulation",
          "type": "impact"
        },
        {
          "id": "product:ZTE GoldenDB",
          "keyphrase": "ZTE GoldenDB",
          "type": "product"
        },
        {
          "id": "version:6.1.03 through 6.1.03.04",
          "keyphrase": "6.1.03 through 6.1.03.04",
          "type": "version"
        }
      ],
      "36": [
        {
          "id": "rootcause:Input Validation vulnerability",
          "keyphrase": "Input Validation vulnerability",
          "type": "rootcause"
        },
        {
          "id": "rootcause:Improper Input Validation",
          "keyphrase": "Improper Input Validation",
          "type": "rootcause"
        },
        {
          "id": "impact:Input Data Manipulation",
          "keyphrase": "Input Data Manipulation",
          "type": "impact"
        },
        {
          "id": "product:ZTE GoldenDB",
          "keyphrase": "ZTE GoldenDB",
          "type": "product"
        },
        {
          "id": "version:6.1.03 through 6.1.03.04",
          "keyphrase": "6.1.03 through 6.1.03.04",
          "type": "version"
        }
      ],
      "95": [
        {
          "id": "rootcause:Input Validation vulnerability",
          "keyphrase": "Input Validation vulnerability",
          "type": "rootcause"
        },
        {
          "id": "rootcause:Improper Input Validation",
          "keyphrase": "Improper Input Validation",
          "type": "rootcause"
        },
        {
          "id": "product:ZTE GoldenDB",
          "keyphrase": "ZTE GoldenDB",
          "type": "product"
        }
      ],
      "93": [
        {
          "id": "rootcause:Input Validation vulnerability",
          "keyphrase": "Input Validation vulnerability",
          "type": "rootcause"
        },
        {
          "id": "impact:Input Data Manipulation",
          "keyphrase": "Input Data Manipulation",
          "type": "impact"
        },
        {
          "id": "product:ZTE GoldenDB",
          "keyphrase": "ZTE GoldenDB",
          "type": "product"
        }
      ],
      "1285": [
        {
          "id": "rootcause:Improper Input Validation",
          "keyphrase": "Improper Input Validation",
          "type": "rootcause"
        }
      ],
      "89": [
        {
          "id": "impact:Input Data Manipulation",
          "keyphrase": "Input Data Manipulation",
          "type": "impact"
        }
      ],
      "79": [
        {
          "id": "impact:Input Data Manipulation",
          "keyphrase": "Input Data Manipulation",
          "type": "impact"
        }
      ],
      "121": [
        {
          "id": "product:ZTE GoldenDB",
          "keyphrase": "ZTE GoldenDB",
          "type": "product"
        }
      ],
      "653": [
        {
          "id": "version:6.1.03 through 6.1.03.04",
          "keyphrase": "6.1.03 through 6.1.03.04",
          "type": "version"
        }
      ],
      "657": [
        {
          "id": "version:6.1.03 through 6.1.03.04",
          "keyphrase": "6.1.03 through 6.1.03.04",
          "type": "version"
        }
      ],
      "302": [
        {
          "id": "version:6.1.03 through 6.1.03.04",
          "keyphrase": "6.1.03 through 6.1.03.04",
          "type": "version"
        }
      ]
    },
    "relevant_cwes": [
      {
        "metadata": {
          "doc_id": "20",
          "name": "Improper Input Validation",
          "source": "sparse",
          "original_content": "The product receives input or data, but it does\n        not validate or incorrectly validates that the input has the\n        properties that are required to process the data safely and\n        correctly.",
          "keyphrase_sources": [
            {
              "id": "rootcause:Input Validation vulnerability",
              "keyphrase": "Input Validation vulnerability",
              "type": "rootcause"
            },
            {
              "id": "rootcause:Improper Input Validation",
              "keyphrase": "Improper Input Validation",
              "type": "rootcause"
            }
          ]
        },
        "similarity": 127.55130534657977
      },
      {
        "metadata": {
          "doc_id": "345",
          "name": "Insufficient Verification of Data Authenticity",
          "source": "sparse",
          "original_content": "The product does not sufficiently verify the origin or authenticity of data, in a way that causes it to accept invalid data.",
          "keyphrase_sources": [
            {
              "id": "rootcause:Input Validation vulnerability",
              "keyphrase": "Input Validation vulnerability",
              "type": "rootcause"
            },
            {
              "id": "rootcause:Improper Input Validation",
              "keyphrase": "Improper Input Validation",
              "type": "rootcause"
            },
            {
              "id": "impact:Input Data Manipulation",
              "keyphrase": "Input Data Manipulation",
              "type": "impact"
            },
            {
              "id": "product:ZTE GoldenDB",
              "keyphrase": "ZTE GoldenDB",
              "type": "product"
            },
            {
              "id": "version:6.1.03 through 6.1.03.04",
              "keyphrase": "6.1.03 through 6.1.03.04",
              "type": "version"
            }
          ]
        },
        "similarity": 123.77126062103444
      },
      {
        "metadata": {
          "doc_id": "36",
          "name": "Absolute Path Traversal",
          "source": "sparse",
          "original_content": "The product uses external input to construct a pathname that should be within a restricted directory, but it does not properly neutralize absolute path sequences such as \"/abs/path\" that can resolve to a location that is outside of that directory.",
          "keyphrase_sources": [
            {
              "id": "rootcause:Input Validation vulnerability",
              "keyphrase": "Input Validation vulnerability",
              "type": "rootcause"
            },
            {
              "id": "rootcause:Improper Input Validation",
              "keyphrase": "Improper Input Validation",
              "type": "rootcause"
            },
            {
              "id": "impact:Input Data Manipulation",
              "keyphrase": "Input Data Manipulation",
              "type": "impact"
            },
            {
              "id": "product:ZTE GoldenDB",
              "keyphrase": "ZTE GoldenDB",
              "type": "product"
            },
            {
              "id": "version:6.1.03 through 6.1.03.04",
              "keyphrase": "6.1.03 through 6.1.03.04",
              "type": "version"
            }
          ]
        },
        "similarity": 121.73867916397896
      },
      {
        "metadata": {
          "doc_id": "1285",
          "name": "Improper Validation of Specified Index, Position, or Offset in Input",
          "source": "sparse",
          "original_content": "The product receives input that is expected to specify an index, position, or offset into an indexable resource such as a buffer or file, but it does not validate or incorrectly validates that the specified index/position/offset has the required properties.",
          "keyphrase_sources": [
            {
              "id": "rootcause:Improper Input Validation",
              "keyphrase": "Improper Input Validation",
              "type": "rootcause"
            }
          ]
        },
        "similarity": 116.75484404594202
      },
      {
        "metadata": {
          "doc_id": "95",
          "name": "Improper Neutralization of Directives in Dynamically Evaluated Code ('Eval Injection')",
          "source": "sparse",
          "original_content": "The product receives input from an upstream component, but it does not neutralize or incorrectly neutralizes code syntax before using the input in a dynamic evaluation call (e.g. \"eval\").",
          "keyphrase_sources": [
            {
              "id": "rootcause:Input Validation vulnerability",
              "keyphrase": "Input Validation vulnerability",
              "type": "rootcause"
            },
            {
              "id": "rootcause:Improper Input Validation",
              "keyphrase": "Improper Input Validation",
              "type": "rootcause"
            },
            {
              "id": "product:ZTE GoldenDB",
              "keyphrase": "ZTE GoldenDB",
              "type": "product"
            }
          ]
        },
        "similarity": 115.73798201495947
      },
      {
        "metadata": {
          "doc_id": "93",
          "name": "Improper Neutralization of CRLF Sequences ('CRLF Injection')",
          "source": "sparse",
          "original_content": "The product uses CRLF (carriage return line feeds) as a special element, e.g. to separate lines or records, but it does not neutralize or incorrectly neutralizes CRLF sequences from inputs.",
          "keyphrase_sources": [
            {
              "id": "rootcause:Input Validation vulnerability",
              "keyphrase": "Input Validation vulnerability",
              "type": "rootcause"
            },
            {
              "id": "impact:Input Data Manipulation",
              "keyphrase": "Input Data Manipulation",
              "type": "impact"
            },
            {
              "id": "product:ZTE GoldenDB",
              "keyphrase": "ZTE GoldenDB",
              "type": "product"
            }
          ]
        },
        "similarity": 114.73457209691452
      },
      {
        "metadata": {
          "doc_id": "653",
          "name": "Improper Isolation or Compartmentalization",
          "source": "sparse",
          "original_content": "The product does not properly compartmentalize or isolate functionality, processes, or resources that require different privilege levels, rights, or permissions.",
          "keyphrase_sources": [
            {
              "id": "version:6.1.03 through 6.1.03.04",
              "keyphrase": "6.1.03 through 6.1.03.04",
              "type": "version"
            }
          ]
        },
        "similarity": 73.53974257165852
      },
      {
        "metadata": {
          "doc_id": "657",
          "name": "Violation of Secure Design Principles",
          "source": "sparse",
          "original_content": "The product violates well-established principles for secure design.",
          "keyphrase_sources": [
            {
              "id": "version:6.1.03 through 6.1.03.04",
              "keyphrase": "6.1.03 through 6.1.03.04",
              "type": "version"
            }
          ]
        },
        "similarity": 65.52941256054339
      },
      {
        "metadata": {
          "doc_id": "302",
          "name": "Authentication Bypass by Assumed-Immutable Data",
          "source": "sparse",
          "original_content": "The authentication scheme or implementation uses key data elements that are assumed to be immutable, but can be controlled or modified by the attacker.",
          "keyphrase_sources": [
            {
              "id": "version:6.1.03 through 6.1.03.04",
              "keyphrase": "6.1.03 through 6.1.03.04",
              "type": "version"
            }
          ]
        },
        "similarity": 65.17114802653965
      },
      {
        "metadata": {
          "doc_id": "89",
          "name": "Improper Neutralization of Special Elements used in an SQL Command ('SQL Injection')",
          "source": "sparse",
          "original_content": "The product constructs all or part of an SQL command using externally-influenced input from an upstream component, but it does not neutralize or incorrectly neutralizes special elements that could modify the intended SQL command when it is sent to a downstream component. Without sufficient removal or quoting of SQL syntax in user-controllable inputs, the generated SQL query can cause those inputs to be interpreted as SQL instead of ordinary user data.",
          "keyphrase_sources": [
            {
              "id": "impact:Input Data Manipulation",
              "keyphrase": "Input Data Manipulation",
              "type": "impact"
            }
          ]
        },
        "similarity": 40.70743522677693
      },
      {
        "metadata": {
          "doc_id": "79",
          "name": "Improper Neutralization of Input During Web Page Generation ('Cross-site Scripting')",
          "source": "sparse",
          "original_content": "The product does not neutralize or incorrectly neutralizes user-controllable input before it is placed in output that is used as a web page that is served to other users.",
          "keyphrase_sources": [
            {
              "id": "impact:Input Data Manipulation",
              "keyphrase": "Input Data Manipulation",
              "type": "impact"
            }
          ]
        },
        "similarity": 39.83311272226361
      },
      {
        "metadata": {
          "doc_id": "121",
          "name": "Stack-based Buffer Overflow",
          "source": "sparse",
          "original_content": "A stack-based buffer overflow condition is a condition where the buffer being overwritten is allocated on the stack (i.e., is a local variable or, rarely, a parameter to a function).",
          "keyphrase_sources": [
            {
              "id": "product:ZTE GoldenDB",
              "keyphrase": "ZTE GoldenDB",
              "type": "product"
            }
          ]
        },
        "similarity": 33.93604344570234
      }
    ],
    "enhanced_query": "# Vulnerability Description\n\n    Improper **Input Validation vulnerability** in ZTE GoldenDB allows Input Data Manipulation.This issue affects GoldenDB from 6.1.03 through 6.1.03.04.\n\n    # Keyphrase-Specific CWE Analysis\n    This vulnerability contains multiple keyphrases that may map to different CWEs. \n    Please analyze each keyphrase separately and determine the most appropriate CWE(s) for each.\n\n    ## ROOTCAUSE: 'Input Validation vulnerability'\n\nRelevant CWEs for this ROOTCAUSE:\n\n### 1. CWE-20: Improper Input Validation (Score: 127.55)\n\nThe product receives input or data, but it does\n        not validate or incorrectly validates that the input has the\n        properties that are required to process the data safely and\n        correctly....\n\n### 2. CWE-345: Insufficient Verification of Data Authenticity (Score: 123.77)\n\nThe product does not sufficiently verify the origin or authenticity of data, in a way that causes it to accept invalid data....\n\n### 3. CWE-36: Absolute Path Traversal (Score: 121.74)\n\nThe product uses external input to construct a pathname that should be within a restricted directory, but it does not properly neutralize absolute path sequences such as \"/abs/path\" that can resolve to a location that is outside of that directory....\n\n### 4. CWE-95: Improper Neutralization of Directives in Dynamically Evaluated Code ('Eval Injection') (Score: 115.74)\n\nThe product receives input from an upstream component, but it does not neutralize or incorrectly neutralizes code syntax before using the input in a dynamic evaluation call (e.g. \"eval\")....\n\n### 5. CWE-93: Improper Neutralization of CRLF Sequences ('CRLF Injection') (Score: 114.73)\n\nThe product uses CRLF (carriage return line feeds) as a special element, e.g. to separate lines or records, but it does not neutralize or incorrectly neutralizes CRLF sequences from inputs....\n\n## ROOTCAUSE: 'Improper Input Validation'\n\nRelevant CWEs for this ROOTCAUSE:\n\n### 1. CWE-20: Improper Input Validation (Score: 127.55)\n\nThe product receives input or data, but it does\n        not validate or incorrectly validates that the input has the\n        properties that are required to process the data safely and\n        correctly....\n\n### 2. CWE-345: Insufficient Verification of Data Authenticity (Score: 123.77)\n\nThe product does not sufficiently verify the origin or authenticity of data, in a way that causes it to accept invalid data....\n\n### 3. CWE-36: Absolute Path Traversal (Score: 121.74)\n\nThe product uses external input to construct a pathname that should be within a restricted directory, but it does not properly neutralize absolute path sequences such as \"/abs/path\" that can resolve to a location that is outside of that directory....\n\n### 4. CWE-1285: Improper Validation of Specified Index, Position, or Offset in Input (Score: 116.75)\n\nThe product receives input that is expected to specify an index, position, or offset into an indexable resource such as a buffer or file, but it does not validate or incorrectly validates that the specified index/position/offset has the required properties....\n\n### 5. CWE-95: Improper Neutralization of Directives in Dynamically Evaluated Code ('Eval Injection') (Score: 115.74)\n\nThe product receives input from an upstream component, but it does not neutralize or incorrectly neutralizes code syntax before using the input in a dynamic evaluation call (e.g. \"eval\")....\n\n## IMPACT: 'Input Data Manipulation'\n\nRelevant CWEs for this IMPACT:\n\n### 1. CWE-345: Insufficient Verification of Data Authenticity (Score: 123.77)\n\nThe product does not sufficiently verify the origin or authenticity of data, in a way that causes it to accept invalid data....\n\n### 2. CWE-36: Absolute Path Traversal (Score: 121.74)\n\nThe product uses external input to construct a pathname that should be within a restricted directory, but it does not properly neutralize absolute path sequences such as \"/abs/path\" that can resolve to a location that is outside of that directory....\n\n### 3. CWE-93: Improper Neutralization of CRLF Sequences ('CRLF Injection') (Score: 114.73)\n\nThe product uses CRLF (carriage return line feeds) as a special element, e.g. to separate lines or records, but it does not neutralize or incorrectly neutralizes CRLF sequences from inputs....\n\n### 4. CWE-89: Improper Neutralization of Special Elements used in an SQL Command ('SQL Injection') (Score: 40.71)\n\nThe product constructs all or part of an SQL command using externally-influenced input from an upstream component, but it does not neutralize or incorrectly neutralizes special elements that could modify the intended SQL command when it is sent to a downstream component. Without sufficient removal o...\n\n### 5. CWE-79: Improper Neutralization of Input During Web Page Generation ('Cross-site Scripting') (Score: 39.83)\n\nThe product does not neutralize or incorrectly neutralizes user-controllable input before it is placed in output that is used as a web page that is served to other users....\n\n## PRODUCT: 'ZTE GoldenDB'\n\nRelevant CWEs for this PRODUCT:\n\n### 1. CWE-345: Insufficient Verification of Data Authenticity (Score: 123.77)\n\nThe product does not sufficiently verify the origin or authenticity of data, in a way that causes it to accept invalid data....\n\n### 2. CWE-36: Absolute Path Traversal (Score: 121.74)\n\nThe product uses external input to construct a pathname that should be within a restricted directory, but it does not properly neutralize absolute path sequences such as \"/abs/path\" that can resolve to a location that is outside of that directory....\n\n### 3. CWE-95: Improper Neutralization of Directives in Dynamically Evaluated Code ('Eval Injection') (Score: 115.74)\n\nThe product receives input from an upstream component, but it does not neutralize or incorrectly neutralizes code syntax before using the input in a dynamic evaluation call (e.g. \"eval\")....\n\n### 4. CWE-93: Improper Neutralization of CRLF Sequences ('CRLF Injection') (Score: 114.73)\n\nThe product uses CRLF (carriage return line feeds) as a special element, e.g. to separate lines or records, but it does not neutralize or incorrectly neutralizes CRLF sequences from inputs....\n\n### 5. CWE-121: Stack-based Buffer Overflow (Score: 33.94)\n\nA stack-based buffer overflow condition is a condition where the buffer being overwritten is allocated on the stack (i.e., is a local variable or, rarely, a parameter to a function)....\n\n## VERSION: '6.1.03 through 6.1.03.04'\n\nRelevant CWEs for this VERSION:\n\n### 1. CWE-345: Insufficient Verification of Data Authenticity (Score: 123.77)\n\nThe product does not sufficiently verify the origin or authenticity of data, in a way that causes it to accept invalid data....\n\n### 2. CWE-36: Absolute Path Traversal (Score: 121.74)\n\nThe product uses external input to construct a pathname that should be within a restricted directory, but it does not properly neutralize absolute path sequences such as \"/abs/path\" that can resolve to a location that is outside of that directory....\n\n### 3. CWE-653: Improper Isolation or Compartmentalization (Score: 73.54)\n\nThe product does not properly compartmentalize or isolate functionality, processes, or resources that require different privilege levels, rights, or permissions....\n\n### 4. CWE-657: Violation of Secure Design Principles (Score: 65.53)\n\nThe product violates well-established principles for secure design....\n\n### 5. CWE-302: Authentication Bypass by Assumed-Immutable Data (Score: 65.17)\n\nThe authentication scheme or implementation uses key data elements that are assumed to be immutable, but can be controlled or modified by the attacker....\n\n\n    # Analysis Instructions\n    1. For each keyphrase, identify the most appropriate CWE(s) that represent the weakness.\n    2. Consider how the different keyphrases might relate to each other in the vulnerability chain.\n    3. Provide a final determination of primary CWE(s) and any secondary CWEs.\n    4. Format your response using the standard analysis template.\n\n    Please analyze how these different weaknesses interact and provide a comprehensive CWE classification.\n    "
  },
  "retrieval_time": 1.4066627025604248
}