{
  "cve_id": "CVE-2024-38408",
  "description": "**Cryptographic issue** when a controller receives an LMP start encryption command under unexpected conditions.",
  "key_phrases": {
    "rootcause": "",
    "weakness": "Cryptographic issue",
    "impact": "",
    "vector": "",
    "attacker": "",
    "product": "",
    "version": "",
    "component": "controller"
  },
  "reference_content": null,
  "similar_info": {
    "cwe_distribution": {},
    "cwe_consensus": "",
    "similarity_stats": {
      "thresholds": [],
      "total_samples_by_threshold": {},
      "top_cwes_by_threshold": {}
    }
  },
  "similarity_summary": {
    "consensus_cwe": "",
    "top_cwes": [],
    "confidence_levels": {},
    "total_samples": 0
  },
  "analysis": "# Summary\n\n| CWE ID  | CWE Name                                                                                    | Confidence | CWE Abstraction Level | CWE Vulnerability Mapping Label | CWE-Vulnerability Mapping Notes |\n| ------- | ------------------------------------------------------------------------------------------- | ---------- | ----------------------- | ------------------------------- | ----------------------------- |\n| CWE-325 | Missing Cryptographic Step                                                                  | 0.75       | Base                    | Primary                         | Allowed                       |\n\n## Evidence and Confidence\n\n*   **Confidence Score:** 0.75\n*   **Evidence Strength:** LOW\n\n## Relationship Analysis\n\nThe primary CWE is CWE-325, which is a Base level CWE. No parent or child relationships are directly relevant in this case due to the limited information.\n\n```mermaid\ngraph TD\n    cwe325[\"CWE-325: Missing Cryptographic Step\"]\n    classDef primary fill:#f96,stroke:#333,stroke-width:2px\n    class cwe325 primary\n```\n\n## Vulnerability Chain\n\nThe vulnerability chain starts with a **missing cryptographic step**, leading to a **cryptographic issue**. This is a simple chain with only one identified weakness.\n\n## Summary of Analysis\n\nThe vulnerability description is very brief, stating only \"**Cryptographic issue** when a controller receives an LMP start encryption command under unexpected conditions.\" The key phrase identified is \"**Cryptographic issue**\".\n\nThe retriever results suggest several CWEs related to cryptography. Given the limited information, the most appropriate CWE seems to be CWE-325 (Missing Cryptographic Step). This is because the description mentions a \"cryptographic issue\" occurring under \"unexpected conditions\" when starting encryption. It is plausible that a step in the encryption process is **missing** when these unexpected conditions are met.\n\nCWE-327 (Use of a Broken or Risky Cryptographic Algorithm) and CWE-1240 (Use of a Cryptographic Primitive with a Risky Implementation) are also possibilities, but they imply the existence of a cryptographic algorithm that is inherently flawed, whereas CWE-325 implies a correct algorithm that is simply not fully implemented in certain cases. The description leans slightly more towards the latter.\n\nI am not selecting CWE-321 (Use of Hard-coded Cryptographic Key), CWE-1204 (Generation of Weak Initialization Vector (IV)), CWE-347 (Improper Verification of Cryptographic Signature), CWE-1188 (Initialization of a Resource with an Insecure Default), CWE-649 (Reliance on Obfuscation or Encryption of Security-Relevant Inputs without Integrity Checking) as these are more specific types of cryptographic errors, and the limited evidence doesn't justify such specific classifications.\n\nThe assessment is based on the provided evidence alone, which is weak. More information about the nature of the \"cryptographic issue\" and the \"unexpected conditions\" would be needed for a more accurate classification.\n\nRelevant CWE Information:\n\n# Enhanced Context (25 CWEs)\nThe following CWEs were identified as potentially relevant to this vulnerability:\n\n## CWE-1391: Use of Weak Credentials\n**Abstraction Level**: Class\n**Similarity Score**: 0.74\n**Source**: dense\n\n**Description**:\nThe product uses weak credentials (such as a default key or hard-coded password) that can be calculated, derived, reused, or guessed by an attacker.\n\n**Mapping Guidance**:\n- Usage: Allowed-with-Review\n- Rationale: This CWE entry is a Class and might have Base-level children that would be more appropriate\n\n## CWE-330: Use of Insufficiently Random Values\n**Abstraction Level**: Class\n**Similarity Score**: 0.72\n**Source**: dense\n\n**Description**:\nThe product uses insufficiently random numbers or values in a security context that depends on unpredictable numbers.\n\n**Mapping Guidance**:\n- Usage: Discouraged\n- Rationale: This CWE entry is a level-1 Class (i.e., a child of a Pillar). It might have lower-level children that would be more appropriate\n\n## CWE-294: Authentication Bypass by Capture-replay\n**Abstraction Level**: Base\n**Similarity Score**: 0.71\n**Source**: dense\n\n**Description**:\nA capture-replay flaw exists when the design of the product makes it possible for a malicious user to sniff network traffic and bypass authentication by replaying it to the server in question to the same effect as the original message (or with minor changes).\n\n**Mapping Guidance**:\n- Usage: Allowed\n- Rationale: This CWE entry is at the Base level of abstraction, which is a preferred level of abstraction for mapping to the root causes of vulnerabilities.\n\n## CWE-1204: Generation of Weak Initialization Vector (IV)\n**Abstraction Level**: Base\n**Similarity Score**: 0.71\n**Source**: dense\n\n**Description**:\nThe product uses a cryptographic primitive that uses an Initialization\n\t\t\tVector (IV), but the product does not generate IVs that are\n\t\t\tsufficiently unpredictable or unique according to the expected\n\t\t\tcryptographic requirements for that primitive.\n\t\t\t\n\n**Mapping Guidance**:\n- Usage: Allowed\n- Rationale: This CWE entry is at the Base level of abstraction, which is a preferred level of abstraction for mapping to the root causes of vulnerabilities.\n\n## CWE-303: Incorrect Implementation of Authentication Algorithm\n**Abstraction Level**: Base\n**Similarity Score**: 0.71\n**Source**: dense\n\n**Description**:\nThe requirements for the product dictate the use of an established authentication algorithm, but the implementation of the algorithm is incorrect.\n\n**Mapping Guidance**:\n- Usage: Allowed\n- Rationale: This CWE entry is at the Base level of abstraction, which is a preferred level of abstraction for mapping to the root causes of vulnerabilities.\n\n## CWE-325: Missing Cryptographic Step\n**Abstraction Level**: Base\n**Similarity Score**: 0.71\n**Source**: dense\n\n**Description**:\nThe product does not implement a required step in a cryptographic algorithm, resulting in weaker encryption than advertised by the algorithm.\n\n**Mapping Guidance**:\n- Usage: Allowed\n- Rationale: This CWE entry is at the Base level of abstraction, which is a preferred level of abstraction for mapping to the root causes of vulnerabilities.\n\n## CWE-1240: Use of a Cryptographic Primitive with a Risky Implementation\n**Abstraction Level**: Base\n**Similarity Score**: 0.71\n**Source**: dense\n\n**Description**:\nTo fulfill the need for a cryptographic primitive, the product implements a cryptographic algorithm using a non-standard, unproven, or disallowed/non-compliant cryptographic implementation.\n\n**Mapping Guidance**:\n- Usage: Allowed\n- Rationale: This CWE entry is at the Base level of abstraction, which is a preferred level of abstraction for mapping to the root causes of vulnerabilities.\n\n## CWE-328: Use of Weak Hash\n**Abstraction Level**: Base\n**Similarity Score**: 0.71\n**Source**: dense\n\n**Description**:\nThe product uses an algorithm that produces a digest (output value) that does not meet security expectations for a hash function that allows an adversary to reasonably determine the original input (preimage attack), find another input that can produce the same hash (2nd preimage attack), or find multiple inputs that evaluate to the same hash (birthday attack).\n\n**Mapping Guidance**:\n- Usage: Allowed\n- Rationale: This CWE entry is at the Base level of abstraction, which is a preferred level of abstraction for mapping to the root causes of vulnerabilities.\n\n## CWE-703: Improper Check or Handling of Exceptional Conditions\n**Abstraction Level**: Pillar\n**Similarity Score**: 0.70\n**Source**: dense\n\n**Description**:\nThe product does not properly anticipate or handle exceptional conditions that rarely occur during normal operation of the product.\n\n**Mapping Guidance**:\n- Usage: Discouraged\n- Rationale: This CWE entry is extremely high-level, a Pillar.\n\n## CWE-208: Observable Timing Discrepancy\n**Abstraction Level**: Base\n**Similarity Score**: 0.70\n**Source**: dense\n\n**Description**:\nTwo separate operations in a product require different amounts of time to complete, in a way that is observable to an actor and reveals security-relevant information about the state of the product, such as whether a particular operation was successful or not.\n\n**Mapping Guidance**:\n- Usage: Allowed\n- Rationale: This CWE entry is at the Base level of abstraction, which is a preferred level of abstraction for mapping to the root causes of vulnerabilities.\n\n## CWE-1240: Use of a Cryptographic Primitive with a Risky Implementation\n**Abstraction Level**: Base\n**Similarity Score**: 415.39\n**Source**: sparse\n\n**Description**:\nTo fulfill the need for a cryptographic primitive, the product implements a cryptographic algorithm using a non-standard, unproven, or disallowed/non-compliant cryptographic implementation.\n\n**Mapping Guidance**:\n- Usage: Allowed\n- Rationale: This CWE entry is at the Base level of abstraction, which is a preferred level of abstraction for mapping to the root causes of vulnerabilities.\n\n## CWE-327: Use of a Broken or Risky Cryptographic Algorithm\n**Abstraction Level**: Class\n**Similarity Score**: 390.99\n**Source**: sparse\n\n**Description**:\nThe product uses a broken or risky cryptographic algorithm or protocol.\n\n**Mapping Guidance**:\n- Usage: Allowed-with-Review\n- Rationale: This CWE entry is a Class and might have Base-level children that would be more appropriate\n\n## CWE-1204: Generation of Weak Initialization Vector (",
  "analysis_with_relationships": "# Summary\n\n| CWE ID  | CWE Name                                                                                    | Confidence | CWE Abstraction Level | CWE Vulnerability Mapping Label | CWE-Vulnerability Mapping Notes |\n| ------- | ------------------------------------------------------------------------------------------- | ---------- | ----------------------- | ------------------------------- | ----------------------------- |\n| CWE-325 | Missing Cryptographic Step                                                                  | 0.75       | Base                    | Primary                         | Allowed                       |\n\n## Evidence and Confidence\n\n*   **Confidence Score:** 0.75\n*   **Evidence Strength:** LOW\n\n## Relationship Analysis\n\nThe primary CWE is CWE-325, which is a Base level CWE. No parent or child relationships are directly relevant in this case due to the limited information.\n\n```mermaid\ngraph TD\n    cwe325[\"CWE-325: Missing Cryptographic Step\"]\n    classDef primary fill:#f96,stroke:#333,stroke-width:2px\n    class cwe325 primary\n```\n\n## Vulnerability Chain\n\nThe vulnerability chain starts with a **missing cryptographic step**, leading to a **cryptographic issue**. This is a simple chain with only one identified weakness.\n\n## Summary of Analysis\n\nThe vulnerability description is very brief, stating only \"**Cryptographic issue** when a controller receives an LMP start encryption command under unexpected conditions.\" The key phrase identified is \"**Cryptographic issue**\".\n\nThe retriever results suggest several CWEs related to cryptography. Given the limited information, the most appropriate CWE seems to be CWE-325 (Missing Cryptographic Step). This is because the description mentions a \"cryptographic issue\" occurring under \"unexpected conditions\" when starting encryption. It is plausible that a step in the encryption process is **missing** when these unexpected conditions are met.\n\nCWE-327 (Use of a Broken or Risky Cryptographic Algorithm) and CWE-1240 (Use of a Cryptographic Primitive with a Risky Implementation) are also possibilities, but they imply the existence of a cryptographic algorithm that is inherently flawed, whereas CWE-325 implies a correct algorithm that is simply not fully implemented in certain cases. The description leans slightly more towards the latter.\n\nI am not selecting CWE-321 (Use of Hard-coded Cryptographic Key), CWE-1204 (Generation of Weak Initialization Vector (IV)), CWE-347 (Improper Verification of Cryptographic Signature), CWE-1188 (Initialization of a Resource with an Insecure Default), CWE-649 (Reliance on Obfuscation or Encryption of Security-Relevant Inputs without Integrity Checking) as these are more specific types of cryptographic errors, and the limited evidence doesn't justify such specific classifications.\n\nThe assessment is based on the provided evidence alone, which is weak. More information about the nature of the \"cryptographic issue\" and the \"unexpected conditions\" would be needed for a more accurate classification.\n\nRelevant CWE Information:\n\n# Enhanced Context (25 CWEs)\nThe following CWEs were identified as potentially relevant to this vulnerability:\n\n## CWE-1391: Use of Weak Credentials\n**Abstraction Level**: Class\n**Similarity Score**: 0.74\n**Source**: dense\n\n**Description**:\nThe product uses weak credentials (such as a default key or hard-coded password) that can be calculated, derived, reused, or guessed by an attacker.\n\n**Mapping Guidance**:\n- Usage: Allowed-with-Review\n- Rationale: This CWE entry is a Class and might have Base-level children that would be more appropriate\n\n## CWE-330: Use of Insufficiently Random Values\n**Abstraction Level**: Class\n**Similarity Score**: 0.72\n**Source**: dense\n\n**Description**:\nThe product uses insufficiently random numbers or values in a security context that depends on unpredictable numbers.\n\n**Mapping Guidance**:\n- Usage: Discouraged\n- Rationale: This CWE entry is a level-1 Class (i.e., a child of a Pillar). It might have lower-level children that would be more appropriate\n\n## CWE-294: Authentication Bypass by Capture-replay\n**Abstraction Level**: Base\n**Similarity Score**: 0.71\n**Source**: dense\n\n**Description**:\nA capture-replay flaw exists when the design of the product makes it possible for a malicious user to sniff network traffic and bypass authentication by replaying it to the server in question to the same effect as the original message (or with minor changes).\n\n**Mapping Guidance**:\n- Usage: Allowed\n- Rationale: This CWE entry is at the Base level of abstraction, which is a preferred level of abstraction for mapping to the root causes of vulnerabilities.\n\n## CWE-1204: Generation of Weak Initialization Vector (IV)\n**Abstraction Level**: Base\n**Similarity Score**: 0.71\n**Source**: dense\n\n**Description**:\nThe product uses a cryptographic primitive that uses an Initialization\n\t\t\tVector (IV), but the product does not generate IVs that are\n\t\t\tsufficiently unpredictable or unique according to the expected\n\t\t\tcryptographic requirements for that primitive.\n\t\t\t\n\n**Mapping Guidance**:\n- Usage: Allowed\n- Rationale: This CWE entry is at the Base level of abstraction, which is a preferred level of abstraction for mapping to the root causes of vulnerabilities.\n\n## CWE-303: Incorrect Implementation of Authentication Algorithm\n**Abstraction Level**: Base\n**Similarity Score**: 0.71\n**Source**: dense\n\n**Description**:\nThe requirements for the product dictate the use of an established authentication algorithm, but the implementation of the algorithm is incorrect.\n\n**Mapping Guidance**:\n- Usage: Allowed\n- Rationale: This CWE entry is at the Base level of abstraction, which is a preferred level of abstraction for mapping to the root causes of vulnerabilities.\n\n## CWE-325: Missing Cryptographic Step\n**Abstraction Level**: Base\n**Similarity Score**: 0.71\n**Source**: dense\n\n**Description**:\nThe product does not implement a required step in a cryptographic algorithm, resulting in weaker encryption than advertised by the algorithm.\n\n**Mapping Guidance**:\n- Usage: Allowed\n- Rationale: This CWE entry is at the Base level of abstraction, which is a preferred level of abstraction for mapping to the root causes of vulnerabilities.\n\n## CWE-1240: Use of a Cryptographic Primitive with a Risky Implementation\n**Abstraction Level**: Base\n**Similarity Score**: 0.71\n**Source**: dense\n\n**Description**:\nTo fulfill the need for a cryptographic primitive, the product implements a cryptographic algorithm using a non-standard, unproven, or disallowed/non-compliant cryptographic implementation.\n\n**Mapping Guidance**:\n- Usage: Allowed\n- Rationale: This CWE entry is at the Base level of abstraction, which is a preferred level of abstraction for mapping to the root causes of vulnerabilities.\n\n## CWE-328: Use of Weak Hash\n**Abstraction Level**: Base\n**Similarity Score**: 0.71\n**Source**: dense\n\n**Description**:\nThe product uses an algorithm that produces a digest (output value) that does not meet security expectations for a hash function that allows an adversary to reasonably determine the original input (preimage attack), find another input that can produce the same hash (2nd preimage attack), or find multiple inputs that evaluate to the same hash (birthday attack).\n\n**Mapping Guidance**:\n- Usage: Allowed\n- Rationale: This CWE entry is at the Base level of abstraction, which is a preferred level of abstraction for mapping to the root causes of vulnerabilities.\n\n## CWE-703: Improper Check or Handling of Exceptional Conditions\n**Abstraction Level**: Pillar\n**Similarity Score**: 0.70\n**Source**: dense\n\n**Description**:\nThe product does not properly anticipate or handle exceptional conditions that rarely occur during normal operation of the product.\n\n**Mapping Guidance**:\n- Usage: Discouraged\n- Rationale: This CWE entry is extremely high-level, a Pillar.\n\n## CWE-208: Observable Timing Discrepancy\n**Abstraction Level**: Base\n**Similarity Score**: 0.70\n**Source**: dense\n\n**Description**:\nTwo separate operations in a product require different amounts of time to complete, in a way that is observable to an actor and reveals security-relevant information about the state of the product, such as whether a particular operation was successful or not.\n\n**Mapping Guidance**:\n- Usage: Allowed\n- Rationale: This CWE entry is at the Base level of abstraction, which is a preferred level of abstraction for mapping to the root causes of vulnerabilities.\n\n## CWE-1240: Use of a Cryptographic Primitive with a Risky Implementation\n**Abstraction Level**: Base\n**Similarity Score**: 415.39\n**Source**: sparse\n\n**Description**:\nTo fulfill the need for a cryptographic primitive, the product implements a cryptographic algorithm using a non-standard, unproven, or disallowed/non-compliant cryptographic implementation.\n\n**Mapping Guidance**:\n- Usage: Allowed\n- Rationale: This CWE entry is at the Base level of abstraction, which is a preferred level of abstraction for mapping to the root causes of vulnerabilities.\n\n## CWE-327: Use of a Broken or Risky Cryptographic Algorithm\n**Abstraction Level**: Class\n**Similarity Score**: 390.99\n**Source**: sparse\n\n**Description**:\nThe product uses a broken or risky cryptographic algorithm or protocol.\n\n**Mapping Guidance**:\n- Usage: Allowed-with-Review\n- Rationale: This CWE entry is a Class and might have Base-level children that would be more appropriate\n\n## CWE-1204: Generation of Weak Initialization Vector (\n\n\n## CWE Relationship Analysis\n\nCurrent CWEs represent these abstraction levels: .\n\n\n### Vulnerability Chain Analysis\n\n**Chain starting from CWE-321:**\n- 321 (Use of Hard-coded Cryptographic Key) - ROOT\n\n\n**Chain starting from CWE-649:**\n- 649 (Reliance on Obfuscation or Encryption of Security-Relevant Inputs without Integrity Checking) - ROOT\n\n\n\n### CWE Relationship Diagram\n\n```mermaid\ngraph TD\n    classDef primary fill:#f96,stroke:#333,stroke-width:2px\n    classDef secondary fill:#69f,stroke:#333\n    classDef tertiary fill:#9e9,stroke:#333\n```",
  "criticism": "",
  "resolution": "",
  "relevant_cwes": [
    {
      "metadata": {
        "doc_id": "833",
        "name": "Deadlock",
        "source": "sparse"
      },
      "similarity": 83.96025116673385
    },
    {
      "metadata": {
        "doc_id": "327",
        "name": "Use of a Broken or Risky Cryptographic Algorithm",
        "source": "sparse"
      },
      "similarity": 82.89620090661252
    },
    {
      "metadata": {
        "doc_id": "321",
        "name": "Use of Hard-coded Cryptographic Key",
        "source": "sparse"
      },
      "similarity": 79.24615878726891
    },
    {
      "metadata": {
        "doc_id": "1204",
        "name": "Generation of Weak Initialization Vector (IV)",
        "source": "sparse"
      },
      "similarity": 77.69019870764339
    },
    {
      "metadata": {
        "doc_id": "325",
        "name": "Missing Cryptographic Step",
        "source": "sparse"
      },
      "similarity": 76.39265545225659
    },
    {
      "metadata": {
        "doc_id": "347",
        "name": "Improper Verification of Cryptographic Signature",
        "source": "sparse"
      },
      "similarity": 75.94430291945322
    },
    {
      "metadata": {
        "doc_id": "1240",
        "name": "Use of a Cryptographic Primitive with a Risky Implementation",
        "source": "sparse"
      },
      "similarity": 74.34438497992004
    },
    {
      "metadata": {
        "doc_id": "1188",
        "name": "Initialization of a Resource with an Insecure Default",
        "source": "sparse"
      },
      "similarity": 73.32324654756512
    },
    {
      "metadata": {
        "doc_id": "649",
        "name": "Reliance on Obfuscation or Encryption of Security-Relevant Inputs without Integrity Checking",
        "type": "Base",
        "original_content": "The product uses obfuscation or encryption of inputs that should not be mutable by an external actor, but the product does not use integrity checks to detect if those inputs have been modified.",
        "keyphrase_source": "weakness:Cryptographic issue",
        "source": "dense",
        "mapping_notes": {
          "usage": "Allowed",
          "rationale": "This CWE entry is at the Base level of abstraction, which is a preferred level of abstraction for mapping to the root causes of vulnerabilities.",
          "comments": "Carefully read both the name and description to ensure that this mapping is an appropriate fit. Do not try to 'force' a mapping to a lower-level Base/Variant simply to comply with this preferred level of abstraction.",
          "reasons": [
            "Acceptable-Use"
          ]
        },
        "score_info": {
          "retrievers": [
            "dense",
            "graph"
          ],
          "retriever_count": 2,
          "normalized_scores": {
            "dense": 0.5400591737022329,
            "graph": 1.6423233380353583
          }
        }
      },
      "similarity": 0.5400591737022329
    },
    {
      "doc_id": "208",
      "text": "CWE-208: Observable Timing Discrepancy",
      "score": 2.2100000000000004,
      "metadata": {
        "doc_id": "208",
        "name": "Observable Timing Discrepancy",
        "type": "base",
        "original_content": "CWE-208: Observable Timing Discrepancy",
        "relationships": [
          {
            "source_id": "208",
            "target_id": "1254",
            "label": "PARENTOF",
            "properties": {
              "ordinal": "Primary",
              "view_id": "1000"
            }
          },
          {
            "source_id": "208",
            "target_id": "327",
            "label": "CANPRECEDE",
            "properties": {
              "view_id": "1000"
            }
          },
          {
            "source_id": "208",
            "target_id": "385",
            "label": "CANPRECEDE",
            "properties": {
              "view_id": "1000"
            }
          },
          {
            "source_id": "208",
            "target_id": "203",
            "label": "CHILDOF",
            "properties": {
              "ordinal": "Primary",
              "view_id": "1000"
            }
          },
          {
            "source_id": "385",
            "target_id": "208",
            "label": "CANFOLLOW",
            "properties": {
              "view_id": "1000"
            }
          },
          {
            "source_id": "327",
            "target_id": "208",
            "label": "CANFOLLOW",
            "properties": {
              "view_id": "1000"
            }
          },
          {
            "source_id": "203",
            "target_id": "208",
            "label": "PARENTOF",
            "properties": {
              "ordinal": "Primary",
              "view_id": "1000"
            }
          },
          {
            "source_id": "1254",
            "target_id": "208",
            "label": "CHILDOF",
            "properties": {
              "ordinal": "Primary",
              "view_id": "1000"
            }
          }
        ],
        "score_components": {
          "relationship_chain": 1.0,
          "sequence_path": 1.0
        },
        "abstraction_factor": 1.3,
        "graph_path_info": {
          "path_types": [
            "relationship_chain",
            "vulnerability_sequence_forward",
            "vulnerability_sequence_backward"
          ],
          "best_paths": {
            "relationship_chain": {
              "path": [
                [
                  "327",
                  "208",
                  "CANFOLLOW"
                ]
              ],
              "score": 1.0,
              "type": "relationship_chain",
              "source": "327"
            },
            "vulnerability_sequence_forward": {
              "path": [
                [
                  "327",
                  "208",
                  "CANFOLLOW"
                ]
              ],
              "score": 0.9,
              "type": "vulnerability_sequence_forward",
              "source": "327"
            },
            "vulnerability_sequence_backward": {
              "path": [
                [
                  "208",
                  "327",
                  "CANPRECEDE"
                ]
              ],
              "score": 1.0,
              "type": "vulnerability_sequence_backward",
              "source": "327"
            }
          }
        },
        "position": "before",
        "sources": [
          "graph"
        ],
        "source": "graph",
        "mapping_notes": {
          "usage": "Allowed",
          "rationale": "This CWE entry is at the Base level of abstraction, which is a preferred level of abstraction for mapping to the root causes of vulnerabilities.",
          "comments": "Carefully read both the name and description to ensure that this mapping is an appropriate fit. Do not try to 'force' a mapping to a lower-level Base/Variant simply to comply with this preferred level of abstraction.",
          "reasons": [
            "Acceptable-Use"
          ]
        },
        "score_info": {
          "retrievers": [
            "graph"
          ],
          "retriever_count": 1,
          "normalized_scores": {
            "graph": 2.2100000000000004
          }
        }
      },
      "similarity": 2.2100000000000004
    }
  ],
  "identified_cwes": {
    "analyzer": [
      "CWE-321",
      "CWE-649",
      "CWE-327",
      "CWE-330",
      "CWE-1204",
      "CWE-347",
      "CWE-294",
      "CWE-303",
      "CWE-1391",
      "CWE-328",
      "CWE-1188",
      "CWE-325",
      "CWE-208",
      "CWE-703",
      "CWE-1240"
    ],
    "critic_additional": []
  },
  "keyphrase_cwe_mapping": {}
}