{
  "cve_id": "CVE-2025-22960",
  "description": "A **session hijacking** vulnerability exists in the web-based management interface of GatesAir Maxiva UAXT, VAXT transmitters. Unauthenticated attackers can access exposed log files (/logs/debug/xteLog*), potentially revealing sensitive session-related information such as session IDs (sess_id) and authentication success tokens (user_check_password OK). Exploiting this flaw could allow attackers to hijack active sessions, gain unauthorized access, and escalate privileges on affected devices.",
  "key_phrases": {
    "rootcause": "",
    "weakness": "session hijacking",
    "impact": "hijack active sessions, gain unauthorized access, and escalate privileges",
    "vector": "",
    "attacker": "unauthenticated attackers",
    "product": "GatesAir Maxiva UAXT, VAXT transmitters",
    "version": "",
    "component": "web-based management interface"
  },
  "reference_content": null,
  "similar_info": {
    "cwe_distribution": {},
    "cwe_consensus": "",
    "similarity_stats": {
      "thresholds": [],
      "total_samples_by_threshold": {},
      "top_cwes_by_threshold": {}
    }
  },
  "similarity_summary": {
    "consensus_cwe": "",
    "top_cwes": [],
    "confidence_levels": {},
    "total_samples": 0
  },
  "analysis": "# Summary\n| CWE ID | CWE Name | Confidence | CWE Abstraction Level | CWE Vulnerability Mapping Label | CWE-Vulnerability Mapping Notes |\n|---|---|---|---|---|---|\n| CWE-532 | Insertion of Sensitive Information into Log File | 0.9 | Base | Allowed | Primary CWE. The vulnerability lies in the logging of sensitive session information. |\n| CWE-613 | Insufficient Session Expiration | 0.7 | Base | Allowed | Secondary Candidate. This is a possible weakness that could be related, but not the primary issue. |\n\n## Evidence and Confidence\n\n*   **Confidence Score:** 0.8\n*   **Evidence Strength:** MEDIUM\n\n## Relationship Analysis\nThe primary CWE is CWE-532, which is a Base level CWE. CWE-613 (Insufficient Session Expiration) is a secondary consideration, as the logged session information could be exploited if sessions do not expire appropriately. There are no direct parent-child relationships that significantly influence the choice.\n\n```mermaid\ngraph TD\n    cwe532[\"CWE-532: Insertion of Sensitive Information into Log File\"]\n    cwe613[\"CWE-613: Insufficient Session Expiration\"]\n    cwe672[\"CWE-672: Operation on a Resource after Expiration or Release\"]\n    \n    cwe613 -->|CHILDOF| cwe672\n    \n    classDef primary fill:#f96,stroke:#333,stroke-width:2px\n    classDef secondary fill:#69f,stroke:#333\n    class cwe532 primary\n    class cwe613 secondary\n```\n\n## Vulnerability Chain\nThe vulnerability chain starts with the **insertion of sensitive information into log files** (CWE-532). This leads to potential exposure of session IDs and authentication tokens. If these tokens are valid for an extended period (potentially due to **insufficient session expiration**, CWE-613), an attacker could hijack active sessions and gain unauthorized access.\n\n## Summary of Analysis\nThe primary vulnerability is the logging of sensitive session information, which directly corresponds to CWE-532. The vulnerability description explicitly mentions the exposure of session IDs and authentication tokens in log files. While session hijacking is the impact, the root cause is the exposure of the session information, making CWE-532 the most appropriate primary CWE.\n\nCWE-613 was considered as a secondary factor because the duration of the session validity influences the window of opportunity for session hijacking. However, the primary issue remains the logging of sensitive data.\n\nThe selection of CWE-532 is based on the explicit description of sensitive information being logged. It's a base-level CWE, which is the preferred level of abstraction.\n\nRelevant CWE Information:\n\n# Enhanced Context (25 CWEs)\nThe following CWEs were identified as potentially relevant to this vulnerability:\n\n## CWE-532: Insertion of Sensitive Information into Log File\n**Abstraction Level**: Base\n**Similarity Score**: 0.298\n**Source**: sparse\n\n**Description**:\nThe product logs sensitive information in a log file, which could expose the information to unauthorized actors.\n\n**Mapping Guidance**:\n- Usage: Allowed\n- Rationale: This CWE entry is at the Base level of abstraction, which is a preferred level of abstraction for mapping to the root causes of vulnerabilities.\n\n## CWE-613: Insufficient Session Expiration\n**Abstraction Level**: base\n**Similarity Score**: 0.277\n**Source**: sparse\n\n**Description**:\nCWE-613: Insufficient Session Expiration\n\n**Mapping Guidance**:\n- Usage: Allowed\n- Rationale: This CWE entry is at the Base level of abstraction, which is a preferred level of abstraction for mapping to the root causes of vulnerabilities.\n\n**Relationships**:\n- REQUIREDBY -> CWE-352\n- CANPRECEDE -> CWE-287\n- CHILDOF -> CWE-672\n- CHILDOF -> CWE-672\n- PARENTOF -> CWE-613\nCWEs considered but not used as primary:\n\n*   CWE-287 (Improper Authentication), CWE-290 (Authentication Bypass by Spoofing), CWE-306 (Missing Authentication for Critical Function), CWE-1390 (Weak Authentication): These relate to authentication issues. The vulnerability description states that **unauthenticated attackers** can access the log files. However, the core issue isn't a broken authentication mechanism but the logging of sensitive data. If authentication were properly implemented, the log files would not be accessible to unauthenticated users, and the vulnerability would not exist. Therefore these are incorrect.\n*   CWE-330 (Use of Insufficiently Random Values), CWE-804 (Guessable CAPTCHA): These are related to randomness and CAPTCHA, which are not mentioned in the description.\n*   CWE-384 (Session Fixation): This is a compound CWE that involves multiple weaknesses, but the primary root cause in this case is the logging of session information.\n*   CWE-425 (Direct Request ('Forced Browsing')): While related to direct access, this does not describe the root cause.",
  "analysis_with_relationships": "# Summary\n| CWE ID | CWE Name | Confidence | CWE Abstraction Level | CWE Vulnerability Mapping Label | CWE-Vulnerability Mapping Notes |\n|---|---|---|---|---|---|\n| CWE-532 | Insertion of Sensitive Information into Log File | 0.9 | Base | Allowed | Primary CWE. The vulnerability lies in the logging of sensitive session information. |\n| CWE-613 | Insufficient Session Expiration | 0.7 | Base | Allowed | Secondary Candidate. This is a possible weakness that could be related, but not the primary issue. |\n\n## Evidence and Confidence\n\n*   **Confidence Score:** 0.8\n*   **Evidence Strength:** MEDIUM\n\n## Relationship Analysis\nThe primary CWE is CWE-532, which is a Base level CWE. CWE-613 (Insufficient Session Expiration) is a secondary consideration, as the logged session information could be exploited if sessions do not expire appropriately. There are no direct parent-child relationships that significantly influence the choice.\n\n```mermaid\ngraph TD\n    cwe532[\"CWE-532: Insertion of Sensitive Information into Log File\"]\n    cwe613[\"CWE-613: Insufficient Session Expiration\"]\n    cwe672[\"CWE-672: Operation on a Resource after Expiration or Release\"]\n    \n    cwe613 -->|CHILDOF| cwe672\n    \n    classDef primary fill:#f96,stroke:#333,stroke-width:2px\n    classDef secondary fill:#69f,stroke:#333\n    class cwe532 primary\n    class cwe613 secondary\n```\n\n## Vulnerability Chain\nThe vulnerability chain starts with the **insertion of sensitive information into log files** (CWE-532). This leads to potential exposure of session IDs and authentication tokens. If these tokens are valid for an extended period (potentially due to **insufficient session expiration**, CWE-613), an attacker could hijack active sessions and gain unauthorized access.\n\n## Summary of Analysis\nThe primary vulnerability is the logging of sensitive session information, which directly corresponds to CWE-532. The vulnerability description explicitly mentions the exposure of session IDs and authentication tokens in log files. While session hijacking is the impact, the root cause is the exposure of the session information, making CWE-532 the most appropriate primary CWE.\n\nCWE-613 was considered as a secondary factor because the duration of the session validity influences the window of opportunity for session hijacking. However, the primary issue remains the logging of sensitive data.\n\nThe selection of CWE-532 is based on the explicit description of sensitive information being logged. It's a base-level CWE, which is the preferred level of abstraction.\n\nRelevant CWE Information:\n\n# Enhanced Context (25 CWEs)\nThe following CWEs were identified as potentially relevant to this vulnerability:\n\n## CWE-532: Insertion of Sensitive Information into Log File\n**Abstraction Level**: Base\n**Similarity Score**: 0.298\n**Source**: sparse\n\n**Description**:\nThe product logs sensitive information in a log file, which could expose the information to unauthorized actors.\n\n**Mapping Guidance**:\n- Usage: Allowed\n- Rationale: This CWE entry is at the Base level of abstraction, which is a preferred level of abstraction for mapping to the root causes of vulnerabilities.\n\n## CWE-613: Insufficient Session Expiration\n**Abstraction Level**: base\n**Similarity Score**: 0.277\n**Source**: sparse\n\n**Description**:\nCWE-613: Insufficient Session Expiration\n\n**Mapping Guidance**:\n- Usage: Allowed\n- Rationale: This CWE entry is at the Base level of abstraction, which is a preferred level of abstraction for mapping to the root causes of vulnerabilities.\n\n**Relationships**:\n- REQUIREDBY -> CWE-352\n- CANPRECEDE -> CWE-287\n- CHILDOF -> CWE-672\n- CHILDOF -> CWE-672\n- PARENTOF -> CWE-613\nCWEs considered but not used as primary:\n\n*   CWE-287 (Improper Authentication), CWE-290 (Authentication Bypass by Spoofing), CWE-306 (Missing Authentication for Critical Function), CWE-1390 (Weak Authentication): These relate to authentication issues. The vulnerability description states that **unauthenticated attackers** can access the log files. However, the core issue isn't a broken authentication mechanism but the logging of sensitive data. If authentication were properly implemented, the log files would not be accessible to unauthenticated users, and the vulnerability would not exist. Therefore these are incorrect.\n*   CWE-330 (Use of Insufficiently Random Values), CWE-804 (Guessable CAPTCHA): These are related to randomness and CAPTCHA, which are not mentioned in the description.\n*   CWE-384 (Session Fixation): This is a compound CWE that involves multiple weaknesses, but the primary root cause in this case is the logging of session information.\n*   CWE-425 (Direct Request ('Forced Browsing')): While related to direct access, this does not describe the root cause.\n\n\n## CWE Relationship Analysis\n\nCurrent CWEs represent these abstraction levels: .\n\n\n### Vulnerability Chain Analysis\n\n**Chain starting from CWE-672:**\n- 672 (Operation on a Resource after Expiration or Release) - ROOT\n\n\n**Chain starting from CWE-1390:**\n- 1390 (Weak Authentication) - ROOT\n\n\n\n### CWE Relationship Diagram\n\n```mermaid\ngraph TD\n    classDef primary fill:#f96,stroke:#333,stroke-width:2px\n    classDef secondary fill:#69f,stroke:#333\n    classDef tertiary fill:#9e9,stroke:#333\n```",
  "criticism": "",
  "resolution": "",
  "relevant_cwes": [
    {
      "metadata": {
        "doc_id": "532",
        "name": "Insertion of Sensitive Information into Log File",
        "source": "sparse"
      },
      "similarity": 297.88794444996347
    },
    {
      "metadata": {
        "doc_id": "287",
        "name": "Improper Authentication",
        "source": "sparse"
      },
      "similarity": 290.09992868029127
    },
    {
      "metadata": {
        "doc_id": "290",
        "name": "Authentication Bypass by Spoofing",
        "source": "sparse"
      },
      "similarity": 280.036332917451
    },
    {
      "metadata": {
        "doc_id": "330",
        "name": "Use of Insufficiently Random Values",
        "source": "sparse"
      },
      "similarity": 279.9565279956342
    },
    {
      "metadata": {
        "doc_id": "613",
        "name": "Insufficient Session Expiration",
        "source": "sparse"
      },
      "similarity": 276.8458981025622
    },
    {
      "metadata": {
        "doc_id": "306",
        "name": "Missing Authentication for Critical Function",
        "source": "sparse"
      },
      "similarity": 270.9061392596458
    },
    {
      "metadata": {
        "doc_id": "1390",
        "name": "Weak Authentication",
        "source": "sparse"
      },
      "similarity": 263.4292429912771
    },
    {
      "metadata": {
        "doc_id": "425",
        "name": "Direct Request ('Forced Browsing')",
        "source": "sparse"
      },
      "similarity": 258.64385068316665
    },
    {
      "metadata": {
        "doc_id": "384",
        "name": "Session Fixation",
        "type": "Compound",
        "original_content": "Authenticating a user, or otherwise establishing a new user session, without invalidating any existing session identifier gives an attacker the opportunity to steal authenticated sessions.",
        "keyphrase_source": "weakness:session hijacking",
        "source": "dense",
        "mapping_notes": {
          "usage": "Allowed",
          "rationale": "This is a well-known Composite of multiple weaknesses that must all occur simultaneously, although it is attack-oriented in nature.",
          "comments": "While attack-oriented composites are supported in CWE, they have not been a focus of research. There is a chance that future research or CWE scope clarifications will change or deprecate them. Perform root-cause analysis to determine which weaknesses allow session fixation to occur, and map to those weaknesses. For example, predictable session identifiers might enable session fixation attacks to succeed; if this occurs, they might be better characterized as randomness/predictability weaknesses.",
          "reasons": [
            "Other"
          ]
        },
        "score_info": {
          "retrievers": [
            "dense",
            "graph"
          ],
          "retriever_count": 2,
          "normalized_scores": {
            "dense": 0.5502496344316345,
            "graph": 1.5506217510115439
          }
        }
      },
      "similarity": 0.5502496344316345
    },
    {
      "doc_id": "804",
      "text": "CWE-804: Guessable CAPTCHA",
      "score": 2.73416,
      "metadata": {
        "doc_id": "804",
        "name": "Guessable CAPTCHA",
        "type": "base",
        "original_content": "CWE-804: Guessable CAPTCHA",
        "relationships": [
          {
            "source_id": "804",
            "target_id": "330",
            "label": "CANFOLLOW",
            "properties": {
              "view_id": "1000"
            }
          },
          {
            "source_id": "804",
            "target_id": "1390",
            "label": "CHILDOF",
            "properties": {
              "view_id": "1000"
            }
          },
          {
            "source_id": "804",
            "target_id": "863",
            "label": "CHILDOF",
            "properties": {
              "ordinal": "Primary",
              "view_id": "1000"
            }
          },
          {
            "source_id": "863",
            "target_id": "804",
            "label": "PARENTOF",
            "properties": {
              "ordinal": "Primary",
              "view_id": "1000"
            }
          },
          {
            "source_id": "330",
            "target_id": "804",
            "label": "CANPRECEDE",
            "properties": {
              "view_id": "1000"
            }
          },
          {
            "source_id": "1390",
            "target_id": "804",
            "label": "PARENTOF",
            "properties": {
              "view_id": "1000"
            }
          }
        ],
        "score_components": {
          "relationship_chain": 1.0,
          "abstraction_path": 0.5760000000000002,
          "sequence_path": 1.0
        },
        "abstraction_factor": 1.3,
        "graph_path_info": {
          "path_types": [
            "relationship_chain",
            "abstraction_path_down",
            "vulnerability_sequence_forward"
          ],
          "best_paths": {
            "relationship_chain": {
              "path": [
                [
                  "330",
                  "804",
                  "CANPRECEDE"
                ]
              ],
              "score": 1.0,
              "type": "relationship_chain",
              "source": "330"
            },
            "abstraction_path_down": {
              "path": [
                [
                  "287",
                  "1390",
                  "PARENTOF"
                ],
                [
                  "1390",
                  "804",
                  "PARENTOF"
                ]
              ],
              "score": 0.5760000000000002,
              "type": "abstraction_path_down",
              "source": "287"
            },
            "vulnerability_sequence_forward": {
              "path": [
                [
                  "330",
                  "804",
                  "CANPRECEDE"
                ]
              ],
              "score": 1.0,
              "type": "vulnerability_sequence_forward",
              "source": "330"
            }
          }
        },
        "abstraction_level": "base",
        "position": "after",
        "sources": [
          "graph"
        ],
        "source": "graph",
        "mapping_notes": {
          "usage": "Allowed",
          "rationale": "This CWE entry is at the Base level of abstraction, which is a preferred level of abstraction for mapping to the root causes of vulnerabilities.",
          "comments": "Carefully read both the name and description to ensure that this mapping is an appropriate fit. Do not try to 'force' a mapping to a lower-level Base/Variant simply to comply with this preferred level of abstraction.",
          "reasons": [
            "Acceptable-Use"
          ]
        },
        "score_info": {
          "retrievers": [
            "graph"
          ],
          "retriever_count": 1,
          "normalized_scores": {
            "graph": 2.73416
          }
        }
      },
      "similarity": 2.73416
    }
  ],
  "identified_cwes": {
    "analyzer": [
      "CWE-672",
      "CWE-1390",
      "CWE-290",
      "CWE-330",
      "CWE-306",
      "CWE-613",
      "CWE-804",
      "CWE-352",
      "CWE-384",
      "CWE-287",
      "CWE-425",
      "CWE-532"
    ],
    "critic_additional": []
  },
  "keyphrase_cwe_mapping": {}
}