{
  "vulnerability_info": "VulnerabilityInfo(cve_id='CVE-2024-45169', description='An issue was discovered in UCI IDOL 2 (aka uciIDOL or IDOL2) through 2.12. Due to **improper input validation**, **improper **deserialization****, **and improper restriction of operations within the bounds of a memory buffer**, IDOL2 is vulnerable to Denial-of-Service (DoS) attacks and possibly remote code execution via the \\\\xB0\\\\x00\\\\x3c byte sequence.', key_phrases={'rootcause': ['improper input validation', 'improper deserialization', 'and improper restriction of operations within the bounds of a memory buffer'], 'weakness': 'deserialization', 'impact': 'Denial-of-Service (DoS) attacks and possibly remote code execution', 'vector': 'the \\\\xB0\\\\x00\\\\x3c byte sequence', 'attacker': '', 'product': 'UCI IDOL 2', 'version': 'through 2.12', 'component': ''}, reference_content=\"Based on the provided content, here's a breakdown of the vulnerability:\\n\\n**CVE ID:** CVE-2024-45169\\n\\n**Root Cause:**\\n*   Improper input validation.\\n*   Improper deserialization.\\n*   Improper restriction of operations within the bounds of a memory buffer.\\n\\n**Weaknesses/Vulnerabilities Present:**\\n*   **CWE-20:** Improper Input Validation. The application fails to adequately validate user-supplied input, which can lead to unexpected behavior.\\n*  **CWE-119:** Improper Restriction of Operations within the Bounds of a Memory Buffer. The application does not properly manage memory buffers, potentially allowing attackers to write data outside of the allocated space.\\n\\n**Impact of Exploitation:**\\n*   **Denial of Service (DoS):** An attacker can cause the application to crash or become unresponsive, denying service to legitimate users.\\n*   **Possible Remote Code Execution (RCE):** The vulnerability could potentially allow an attacker to execute arbitrary code on the target system, though this is not confirmed by the provided information.\\n\\n**Attack Vectors:**\\n*   The vulnerability can be exploited over the network by sending specially crafted data to the application on port 2113, as shown in the Proof of Concept (PoC).\\n\\n**Required Attacker Capabilities/Position:**\\n*   The attacker needs to be able to send network traffic to the vulnerable application's port (2113). No specific position on the network is mentioned.\\n\\n**Additional Details:**\\n*   The vulnerability affects IDOL2 client versions up to and including 2.12.\\n*   The PoC demonstrates sending a message starting with the bytes `\\\\xB0\\\\x00\\\\x3c` followed by an arbitrary sequence of bytes (e.g. `\\\\x41` repeated). This seems to trigger a crash.\\n*   The vendor was notified of the vulnerability on 2024-06-26 but rejected an offer for a call to discuss it.\\n*   The public disclosure happened on 2024-08-19.\\n\\nThe provided information gives more details than the official CVE description placeholder, as it includes the specific software affected, the nature of the vulnerabilities, the impact, the attack vector, a proof of concept and the timeline of disclosure.\", similar_info={'cwe_distribution': {}, 'cwe_consensus': '', 'similarity_stats': {'thresholds': [], 'total_samples_by_threshold': {}, 'top_cwes_by_threshold': {}}}, similarity_summary=SimilarityInsight(consensus_cwe='', top_cwes=[], confidence_levels={}, total_samples=0), analysis='', analysis_with_relationships='', criticism='', resolution='', relevant_cwes=[{'metadata': {'doc_id': '125', 'name': 'Out-of-bounds Read', 'source': 'sparse', 'original_content': 'The product reads data past the end, or before the beginning, of the intended buffer.', 'keyphrase_sources': [{'id': 'rootcause:and improper restriction of operations within the bounds of a memory buffer', 'keyphrase': 'and improper restriction of operations within the bounds of a memory buffer', 'type': 'rootcause'}, {'id': 'vector:the \\\\xB0\\\\x00\\\\x3c byte sequence', 'keyphrase': 'the \\\\xB0\\\\x00\\\\x3c byte sequence', 'type': 'vector'}, {'id': 'product:UCI IDOL 2', 'keyphrase': 'UCI IDOL 2', 'type': 'product'}]}, 'similarity': np.float64(487.3183453846036)}, {'metadata': {'doc_id': '190', 'name': 'Integer Overflow or Wraparound', 'source': 'sparse', 'original_content': 'The product performs a calculation that can\\n         produce an integer overflow or wraparound when the logic\\n         assumes that the resulting value will always be larger than\\n         the original value. This occurs when an integer value is\\n         incremented to a value that is too large to store in the\\n         associated representation. When this occurs, the value may\\n         become a very small or negative number.', 'keyphrase_sources': [{'id': 'rootcause:and improper restriction of operations within the bounds of a memory buffer', 'keyphrase': 'and improper restriction of operations within the bounds of a memory buffer', 'type': 'rootcause'}]}, 'similarity': np.float64(480.0342304903063)}, {'metadata': {'doc_id': '122', 'name': 'Heap-based Buffer Overflow', 'source': 'sparse', 'original_content': 'A heap overflow condition is a buffer overflow, where the buffer that can be overwritten is allocated in the heap portion of memory, generally meaning that the buffer was allocated using a routine such as malloc().', 'keyphrase_sources': [{'id': 'rootcause:and improper restriction of operations within the bounds of a memory buffer', 'keyphrase': 'and improper restriction of operations within the bounds of a memory buffer', 'type': 'rootcause'}, {'id': 'version:through 2.12', 'keyphrase': 'through 2.12', 'type': 'version'}]}, 'similarity': np.float64(465.3625870208492)}, {'metadata': {'doc_id': '119', 'name': 'Improper Restriction of Operations within the Bounds of a Memory Buffer', 'source': 'sparse', 'original_content': \"The product performs operations on a memory buffer, but it reads from or writes to a memory location outside the buffer's intended boundary. This may result in read or write operations on unexpected memory locations that could be linked to other variables, data structures, or internal program data.\", 'keyphrase_sources': [{'id': 'rootcause:improper input validation', 'keyphrase': 'improper input validation', 'type': 'rootcause'}, {'id': 'rootcause:improper deserialization', 'keyphrase': 'improper deserialization', 'type': 'rootcause'}, {'id': 'rootcause:and improper restriction of operations within the bounds of a memory buffer', 'keyphrase': 'and improper restriction of operations within the bounds of a memory buffer', 'type': 'rootcause'}, {'id': 'weakness:deserialization', 'keyphrase': 'deserialization', 'type': 'weakness'}, {'id': 'impact:Denial-of-Service (DoS) attacks and possibly remote code execution', 'keyphrase': 'Denial-of-Service (DoS) attacks and possibly remote code execution', 'type': 'impact'}, {'id': 'vector:the \\\\xB0\\\\x00\\\\x3c byte sequence', 'keyphrase': 'the \\\\xB0\\\\x00\\\\x3c byte sequence', 'type': 'vector'}, {'id': 'product:UCI IDOL 2', 'keyphrase': 'UCI IDOL 2', 'type': 'product'}, {'id': 'version:through 2.12', 'keyphrase': 'through 2.12', 'type': 'version'}]}, 'similarity': np.float64(324.3104510265156)}, {'metadata': {'doc_id': '1284', 'name': 'Improper Validation of Specified Quantity in Input', 'source': 'sparse', 'original_content': 'The product receives input that is expected to specify a quantity (such as size or length), but it does not validate or incorrectly validates that the quantity has the required properties.', 'keyphrase_sources': [{'id': 'rootcause:improper input validation', 'keyphrase': 'improper input validation', 'type': 'rootcause'}, {'id': 'rootcause:improper deserialization', 'keyphrase': 'improper deserialization', 'type': 'rootcause'}, {'id': 'rootcause:and improper restriction of operations within the bounds of a memory buffer', 'keyphrase': 'and improper restriction of operations within the bounds of a memory buffer', 'type': 'rootcause'}, {'id': 'weakness:deserialization', 'keyphrase': 'deserialization', 'type': 'weakness'}, {'id': 'impact:Denial-of-Service (DoS) attacks and possibly remote code execution', 'keyphrase': 'Denial-of-Service (DoS) attacks and possibly remote code execution', 'type': 'impact'}, {'id': 'vector:the \\\\xB0\\\\x00\\\\x3c byte sequence', 'keyphrase': 'the \\\\xB0\\\\x00\\\\x3c byte sequence', 'type': 'vector'}, {'id': 'product:UCI IDOL 2', 'keyphrase': 'UCI IDOL 2', 'type': 'product'}, {'id': 'version:through 2.12', 'keyphrase': 'through 2.12', 'type': 'version'}]}, 'similarity': np.float64(321.7229722829796)}, {'metadata': {'doc_id': '20', 'name': 'Improper Input Validation', 'source': 'sparse', 'original_content': 'The product receives input or data, but it does\\n        not validate or incorrectly validates that the input has the\\n        properties that are required to process the data safely and\\n        correctly.', 'keyphrase_sources': [{'id': 'rootcause:improper input validation', 'keyphrase': 'improper input validation', 'type': 'rootcause'}, {'id': 'rootcause:improper deserialization', 'keyphrase': 'improper deserialization', 'type': 'rootcause'}, {'id': 'weakness:deserialization', 'keyphrase': 'deserialization', 'type': 'weakness'}, {'id': 'impact:Denial-of-Service (DoS) attacks and possibly remote code execution', 'keyphrase': 'Denial-of-Service (DoS) attacks and possibly remote code execution', 'type': 'impact'}, {'id': 'product:UCI IDOL 2', 'keyphrase': 'UCI IDOL 2', 'type': 'product'}]}, 'similarity': np.float64(320.44997839408865)}, {'metadata': {'doc_id': '502', 'name': 'Deserialization of Untrusted Data', 'source': 'sparse', 'original_content': 'The product deserializes untrusted data without sufficiently ensuring that the resulting data will be valid.', 'keyphrase_sources': [{'id': 'rootcause:improper deserialization', 'keyphrase': 'improper deserialization', 'type': 'rootcause'}, {'id': 'weakness:deserialization', 'keyphrase': 'deserialization', 'type': 'weakness'}]}, 'similarity': np.float64(313.5657362930267)}, {'metadata': {'doc_id': '193', 'name': 'Off-by-one Error', 'source': 'sparse', 'original_content': 'A product calculates or uses an incorrect maximum or minimum value that is 1 more, or 1 less, than the correct value.', 'keyphrase_sources': [{'id': 'rootcause:improper input validation', 'keyphrase': 'improper input validation', 'type': 'rootcause'}, {'id': 'rootcause:improper deserialization', 'keyphrase': 'improper deserialization', 'type': 'rootcause'}, {'id': 'weakness:deserialization', 'keyphrase': 'deserialization', 'type': 'weakness'}, {'id': 'impact:Denial-of-Service (DoS) attacks and possibly remote code execution', 'keyphrase': 'Denial-of-Service (DoS) attacks and possibly remote code execution', 'type': 'impact'}, {'id': 'vector:the \\\\xB0\\\\x00\\\\x3c byte sequence', 'keyphrase': 'the \\\\xB0\\\\x00\\\\x3c byte sequence', 'type': 'vector'}, {'id': 'product:UCI IDOL 2', 'keyphrase': 'UCI IDOL 2', 'type': 'product'}]}, 'similarity': np.float64(307.6707764241428)}, {'metadata': {'doc_id': '1285', 'name': 'Improper Validation of Specified Index, Position, or Offset in Input', 'source': 'sparse', 'original_content': 'The product receives input that is expected to specify an index, position, or offset into an indexable resource such as a buffer or file, but it does not validate or incorrectly validates that the specified index/position/offset has the required properties.', 'keyphrase_sources': [{'id': 'rootcause:improper input validation', 'keyphrase': 'improper input validation', 'type': 'rootcause'}]}, 'similarity': np.float64(302.6993778142302)}, {'metadata': {'doc_id': '126', 'name': 'Buffer Over-read', 'source': 'sparse', 'original_content': 'The product reads from a buffer using buffer access mechanisms such as indexes or pointers that reference memory locations after the targeted buffer.', 'keyphrase_sources': [{'id': 'impact:Denial-of-Service (DoS) attacks and possibly remote code execution', 'keyphrase': 'Denial-of-Service (DoS) attacks and possibly remote code execution', 'type': 'impact'}, {'id': 'vector:the \\\\xB0\\\\x00\\\\x3c byte sequence', 'keyphrase': 'the \\\\xB0\\\\x00\\\\x3c byte sequence', 'type': 'vector'}, {'id': 'version:through 2.12', 'keyphrase': 'through 2.12', 'type': 'version'}]}, 'similarity': np.float64(130.2138268619382)}, {'metadata': {'doc_id': '121', 'name': 'Stack-based Buffer Overflow', 'source': 'sparse', 'original_content': 'A stack-based buffer overflow condition is a condition where the buffer being overwritten is allocated on the stack (i.e., is a local variable or, rarely, a parameter to a function).', 'keyphrase_sources': [{'id': 'version:through 2.12', 'keyphrase': 'through 2.12', 'type': 'version'}]}, 'similarity': np.float64(102.48137836756713)}], identified_cwes={'analyzer': [], 'critic_additional': []})",
  "retrieval_results": {
    "has_multiple_keyphrases": true,
    "keyphrase_cwe_sets": {
      "rootcause:improper input validation": {
        "keyphrase": "improper input validation",
        "type": "rootcause",
        "cwes": [
          {
            "metadata": {
              "doc_id": "119",
              "name": "Improper Restriction of Operations within the Bounds of a Memory Buffer",
              "source": "sparse",
              "original_content": "The product performs operations on a memory buffer, but it reads from or writes to a memory location outside the buffer's intended boundary. This may result in read or write operations on unexpected memory locations that could be linked to other variables, data structures, or internal program data.",
              "keyphrase_sources": [
                {
                  "id": "rootcause:improper input validation",
                  "keyphrase": "improper input validation",
                  "type": "rootcause"
                },
                {
                  "id": "rootcause:improper deserialization",
                  "keyphrase": "improper deserialization",
                  "type": "rootcause"
                },
                {
                  "id": "rootcause:and improper restriction of operations within the bounds of a memory buffer",
                  "keyphrase": "and improper restriction of operations within the bounds of a memory buffer",
                  "type": "rootcause"
                },
                {
                  "id": "weakness:deserialization",
                  "keyphrase": "deserialization",
                  "type": "weakness"
                },
                {
                  "id": "impact:Denial-of-Service (DoS) attacks and possibly remote code execution",
                  "keyphrase": "Denial-of-Service (DoS) attacks and possibly remote code execution",
                  "type": "impact"
                },
                {
                  "id": "vector:the \\xB0\\x00\\x3c byte sequence",
                  "keyphrase": "the \\xB0\\x00\\x3c byte sequence",
                  "type": "vector"
                },
                {
                  "id": "product:UCI IDOL 2",
                  "keyphrase": "UCI IDOL 2",
                  "type": "product"
                },
                {
                  "id": "version:through 2.12",
                  "keyphrase": "through 2.12",
                  "type": "version"
                }
              ]
            },
            "similarity": 324.3104510265156
          },
          {
            "metadata": {
              "doc_id": "1284",
              "name": "Improper Validation of Specified Quantity in Input",
              "source": "sparse",
              "original_content": "The product receives input that is expected to specify a quantity (such as size or length), but it does not validate or incorrectly validates that the quantity has the required properties.",
              "keyphrase_sources": [
                {
                  "id": "rootcause:improper input validation",
                  "keyphrase": "improper input validation",
                  "type": "rootcause"
                },
                {
                  "id": "rootcause:improper deserialization",
                  "keyphrase": "improper deserialization",
                  "type": "rootcause"
                },
                {
                  "id": "rootcause:and improper restriction of operations within the bounds of a memory buffer",
                  "keyphrase": "and improper restriction of operations within the bounds of a memory buffer",
                  "type": "rootcause"
                },
                {
                  "id": "weakness:deserialization",
                  "keyphrase": "deserialization",
                  "type": "weakness"
                },
                {
                  "id": "impact:Denial-of-Service (DoS) attacks and possibly remote code execution",
                  "keyphrase": "Denial-of-Service (DoS) attacks and possibly remote code execution",
                  "type": "impact"
                },
                {
                  "id": "vector:the \\xB0\\x00\\x3c byte sequence",
                  "keyphrase": "the \\xB0\\x00\\x3c byte sequence",
                  "type": "vector"
                },
                {
                  "id": "product:UCI IDOL 2",
                  "keyphrase": "UCI IDOL 2",
                  "type": "product"
                },
                {
                  "id": "version:through 2.12",
                  "keyphrase": "through 2.12",
                  "type": "version"
                }
              ]
            },
            "similarity": 321.7229722829796
          },
          {
            "metadata": {
              "doc_id": "20",
              "name": "Improper Input Validation",
              "source": "sparse",
              "original_content": "The product receives input or data, but it does\n        not validate or incorrectly validates that the input has the\n        properties that are required to process the data safely and\n        correctly.",
              "keyphrase_sources": [
                {
                  "id": "rootcause:improper input validation",
                  "keyphrase": "improper input validation",
                  "type": "rootcause"
                },
                {
                  "id": "rootcause:improper deserialization",
                  "keyphrase": "improper deserialization",
                  "type": "rootcause"
                },
                {
                  "id": "weakness:deserialization",
                  "keyphrase": "deserialization",
                  "type": "weakness"
                },
                {
                  "id": "impact:Denial-of-Service (DoS) attacks and possibly remote code execution",
                  "keyphrase": "Denial-of-Service (DoS) attacks and possibly remote code execution",
                  "type": "impact"
                },
                {
                  "id": "product:UCI IDOL 2",
                  "keyphrase": "UCI IDOL 2",
                  "type": "product"
                }
              ]
            },
            "similarity": 320.44997839408865
          },
          {
            "metadata": {
              "doc_id": "193",
              "name": "Off-by-one Error",
              "source": "sparse",
              "original_content": "A product calculates or uses an incorrect maximum or minimum value that is 1 more, or 1 less, than the correct value.",
              "keyphrase_sources": [
                {
                  "id": "rootcause:improper input validation",
                  "keyphrase": "improper input validation",
                  "type": "rootcause"
                },
                {
                  "id": "rootcause:improper deserialization",
                  "keyphrase": "improper deserialization",
                  "type": "rootcause"
                },
                {
                  "id": "weakness:deserialization",
                  "keyphrase": "deserialization",
                  "type": "weakness"
                },
                {
                  "id": "impact:Denial-of-Service (DoS) attacks and possibly remote code execution",
                  "keyphrase": "Denial-of-Service (DoS) attacks and possibly remote code execution",
                  "type": "impact"
                },
                {
                  "id": "vector:the \\xB0\\x00\\x3c byte sequence",
                  "keyphrase": "the \\xB0\\x00\\x3c byte sequence",
                  "type": "vector"
                },
                {
                  "id": "product:UCI IDOL 2",
                  "keyphrase": "UCI IDOL 2",
                  "type": "product"
                }
              ]
            },
            "similarity": 307.6707764241428
          },
          {
            "metadata": {
              "doc_id": "1285",
              "name": "Improper Validation of Specified Index, Position, or Offset in Input",
              "source": "sparse",
              "original_content": "The product receives input that is expected to specify an index, position, or offset into an indexable resource such as a buffer or file, but it does not validate or incorrectly validates that the specified index/position/offset has the required properties.",
              "keyphrase_sources": [
                {
                  "id": "rootcause:improper input validation",
                  "keyphrase": "improper input validation",
                  "type": "rootcause"
                }
              ]
            },
            "similarity": 302.6993778142302
          }
        ]
      },
      "rootcause:improper deserialization": {
        "keyphrase": "improper deserialization",
        "type": "rootcause",
        "cwes": [
          {
            "metadata": {
              "doc_id": "119",
              "name": "Improper Restriction of Operations within the Bounds of a Memory Buffer",
              "source": "sparse",
              "original_content": "The product performs operations on a memory buffer, but it reads from or writes to a memory location outside the buffer's intended boundary. This may result in read or write operations on unexpected memory locations that could be linked to other variables, data structures, or internal program data."
            },
            "similarity": 319.0425751098975
          },
          {
            "metadata": {
              "doc_id": "502",
              "name": "Deserialization of Untrusted Data",
              "source": "sparse",
              "original_content": "The product deserializes untrusted data without sufficiently ensuring that the resulting data will be valid.",
              "keyphrase_sources": [
                {
                  "id": "rootcause:improper deserialization",
                  "keyphrase": "improper deserialization",
                  "type": "rootcause"
                },
                {
                  "id": "weakness:deserialization",
                  "keyphrase": "deserialization",
                  "type": "weakness"
                }
              ]
            },
            "similarity": 313.5657362930267
          },
          {
            "metadata": {
              "doc_id": "1284",
              "name": "Improper Validation of Specified Quantity in Input",
              "source": "sparse",
              "original_content": "The product receives input that is expected to specify a quantity (such as size or length), but it does not validate or incorrectly validates that the quantity has the required properties."
            },
            "similarity": 291.9962525158963
          },
          {
            "metadata": {
              "doc_id": "20",
              "name": "Improper Input Validation",
              "source": "sparse",
              "original_content": "The product receives input or data, but it does\n        not validate or incorrectly validates that the input has the\n        properties that are required to process the data safely and\n        correctly."
            },
            "similarity": 291.3177711784052
          },
          {
            "metadata": {
              "doc_id": "193",
              "name": "Off-by-one Error",
              "source": "sparse",
              "original_content": "A product calculates or uses an incorrect maximum or minimum value that is 1 more, or 1 less, than the correct value."
            },
            "similarity": 288.3303168999238
          }
        ]
      },
      "rootcause:and improper restriction of operations within the bounds of a memory buffer": {
        "keyphrase": "and improper restriction of operations within the bounds of a memory buffer",
        "type": "rootcause",
        "cwes": [
          {
            "metadata": {
              "doc_id": "119",
              "name": "Improper Restriction of Operations within the Bounds of a Memory Buffer",
              "source": "sparse",
              "original_content": "The product performs operations on a memory buffer, but it reads from or writes to a memory location outside the buffer's intended boundary. This may result in read or write operations on unexpected memory locations that could be linked to other variables, data structures, or internal program data."
            },
            "similarity": 567.8488915614852
          },
          {
            "metadata": {
              "doc_id": "125",
              "name": "Out-of-bounds Read",
              "source": "sparse",
              "original_content": "The product reads data past the end, or before the beginning, of the intended buffer.",
              "keyphrase_sources": [
                {
                  "id": "rootcause:and improper restriction of operations within the bounds of a memory buffer",
                  "keyphrase": "and improper restriction of operations within the bounds of a memory buffer",
                  "type": "rootcause"
                },
                {
                  "id": "vector:the \\xB0\\x00\\x3c byte sequence",
                  "keyphrase": "the \\xB0\\x00\\x3c byte sequence",
                  "type": "vector"
                },
                {
                  "id": "product:UCI IDOL 2",
                  "keyphrase": "UCI IDOL 2",
                  "type": "product"
                }
              ]
            },
            "similarity": 487.3183453846036
          },
          {
            "metadata": {
              "doc_id": "190",
              "name": "Integer Overflow or Wraparound",
              "source": "sparse",
              "original_content": "The product performs a calculation that can\n         produce an integer overflow or wraparound when the logic\n         assumes that the resulting value will always be larger than\n         the original value. This occurs when an integer value is\n         incremented to a value that is too large to store in the\n         associated representation. When this occurs, the value may\n         become a very small or negative number.",
              "keyphrase_sources": [
                {
                  "id": "rootcause:and improper restriction of operations within the bounds of a memory buffer",
                  "keyphrase": "and improper restriction of operations within the bounds of a memory buffer",
                  "type": "rootcause"
                }
              ]
            },
            "similarity": 480.0342304903063
          },
          {
            "metadata": {
              "doc_id": "1284",
              "name": "Improper Validation of Specified Quantity in Input",
              "source": "sparse",
              "original_content": "The product receives input that is expected to specify a quantity (such as size or length), but it does not validate or incorrectly validates that the quantity has the required properties."
            },
            "similarity": 466.6620058328788
          },
          {
            "metadata": {
              "doc_id": "122",
              "name": "Heap-based Buffer Overflow",
              "source": "sparse",
              "original_content": "A heap overflow condition is a buffer overflow, where the buffer that can be overwritten is allocated in the heap portion of memory, generally meaning that the buffer was allocated using a routine such as malloc().",
              "keyphrase_sources": [
                {
                  "id": "rootcause:and improper restriction of operations within the bounds of a memory buffer",
                  "keyphrase": "and improper restriction of operations within the bounds of a memory buffer",
                  "type": "rootcause"
                },
                {
                  "id": "version:through 2.12",
                  "keyphrase": "through 2.12",
                  "type": "version"
                }
              ]
            },
            "similarity": 465.3625870208492
          }
        ]
      },
      "weakness:deserialization": {
        "keyphrase": "deserialization",
        "type": "weakness",
        "cwes": [
          {
            "metadata": {
              "doc_id": "502",
              "name": "Deserialization of Untrusted Data",
              "source": "sparse",
              "original_content": "The product deserializes untrusted data without sufficiently ensuring that the resulting data will be valid."
            },
            "similarity": 291.0971468743025
          },
          {
            "metadata": {
              "doc_id": "119",
              "name": "Improper Restriction of Operations within the Bounds of a Memory Buffer",
              "source": "sparse",
              "original_content": "The product performs operations on a memory buffer, but it reads from or writes to a memory location outside the buffer's intended boundary. This may result in read or write operations on unexpected memory locations that could be linked to other variables, data structures, or internal program data."
            },
            "similarity": 290.3850142851388
          },
          {
            "metadata": {
              "doc_id": "1284",
              "name": "Improper Validation of Specified Quantity in Input",
              "source": "sparse",
              "original_content": "The product receives input that is expected to specify a quantity (such as size or length), but it does not validate or incorrectly validates that the quantity has the required properties."
            },
            "similarity": 266.68457124342837
          },
          {
            "metadata": {
              "doc_id": "193",
              "name": "Off-by-one Error",
              "source": "sparse",
              "original_content": "A product calculates or uses an incorrect maximum or minimum value that is 1 more, or 1 less, than the correct value."
            },
            "similarity": 266.33580518796646
          },
          {
            "metadata": {
              "doc_id": "20",
              "name": "Improper Input Validation",
              "source": "sparse",
              "original_content": "The product receives input or data, but it does\n        not validate or incorrectly validates that the input has the\n        properties that are required to process the data safely and\n        correctly."
            },
            "similarity": 264.27321021401605
          }
        ]
      },
      "impact:Denial-of-Service (DoS) attacks and possibly remote code execution": {
        "keyphrase": "Denial-of-Service (DoS) attacks and possibly remote code execution",
        "type": "impact",
        "cwes": [
          {
            "metadata": {
              "doc_id": "119",
              "name": "Improper Restriction of Operations within the Bounds of a Memory Buffer",
              "source": "sparse",
              "original_content": "The product performs operations on a memory buffer, but it reads from or writes to a memory location outside the buffer's intended boundary. This may result in read or write operations on unexpected memory locations that could be linked to other variables, data structures, or internal program data."
            },
            "similarity": 143.82685050035073
          },
          {
            "metadata": {
              "doc_id": "193",
              "name": "Off-by-one Error",
              "source": "sparse",
              "original_content": "A product calculates or uses an incorrect maximum or minimum value that is 1 more, or 1 less, than the correct value."
            },
            "similarity": 135.18101483768797
          },
          {
            "metadata": {
              "doc_id": "20",
              "name": "Improper Input Validation",
              "source": "sparse",
              "original_content": "The product receives input or data, but it does\n        not validate or incorrectly validates that the input has the\n        properties that are required to process the data safely and\n        correctly."
            },
            "similarity": 131.1509260829389
          },
          {
            "metadata": {
              "doc_id": "126",
              "name": "Buffer Over-read",
              "source": "sparse",
              "original_content": "The product reads from a buffer using buffer access mechanisms such as indexes or pointers that reference memory locations after the targeted buffer.",
              "keyphrase_sources": [
                {
                  "id": "impact:Denial-of-Service (DoS) attacks and possibly remote code execution",
                  "keyphrase": "Denial-of-Service (DoS) attacks and possibly remote code execution",
                  "type": "impact"
                },
                {
                  "id": "vector:the \\xB0\\x00\\x3c byte sequence",
                  "keyphrase": "the \\xB0\\x00\\x3c byte sequence",
                  "type": "vector"
                },
                {
                  "id": "version:through 2.12",
                  "keyphrase": "through 2.12",
                  "type": "version"
                }
              ]
            },
            "similarity": 130.2138268619382
          },
          {
            "metadata": {
              "doc_id": "1284",
              "name": "Improper Validation of Specified Quantity in Input",
              "source": "sparse",
              "original_content": "The product receives input that is expected to specify a quantity (such as size or length), but it does not validate or incorrectly validates that the quantity has the required properties."
            },
            "similarity": 130.13330483831388
          }
        ]
      },
      "vector:the \\xB0\\x00\\x3c byte sequence": {
        "keyphrase": "the \\xB0\\x00\\x3c byte sequence",
        "type": "vector",
        "cwes": [
          {
            "metadata": {
              "doc_id": "193",
              "name": "Off-by-one Error",
              "source": "sparse",
              "original_content": "A product calculates or uses an incorrect maximum or minimum value that is 1 more, or 1 less, than the correct value."
            },
            "similarity": 113.5377823551483
          },
          {
            "metadata": {
              "doc_id": "119",
              "name": "Improper Restriction of Operations within the Bounds of a Memory Buffer",
              "source": "sparse",
              "original_content": "The product performs operations on a memory buffer, but it reads from or writes to a memory location outside the buffer's intended boundary. This may result in read or write operations on unexpected memory locations that could be linked to other variables, data structures, or internal program data."
            },
            "similarity": 112.10173078297463
          },
          {
            "metadata": {
              "doc_id": "125",
              "name": "Out-of-bounds Read",
              "source": "sparse",
              "original_content": "The product reads data past the end, or before the beginning, of the intended buffer."
            },
            "similarity": 108.23143622444643
          },
          {
            "metadata": {
              "doc_id": "1284",
              "name": "Improper Validation of Specified Quantity in Input",
              "source": "sparse",
              "original_content": "The product receives input that is expected to specify a quantity (such as size or length), but it does not validate or incorrectly validates that the quantity has the required properties."
            },
            "similarity": 106.54952072554819
          },
          {
            "metadata": {
              "doc_id": "126",
              "name": "Buffer Over-read",
              "source": "sparse",
              "original_content": "The product reads from a buffer using buffer access mechanisms such as indexes or pointers that reference memory locations after the targeted buffer."
            },
            "similarity": 105.85947896840209
          }
        ]
      },
      "product:UCI IDOL 2": {
        "keyphrase": "UCI IDOL 2",
        "type": "product",
        "cwes": [
          {
            "metadata": {
              "doc_id": "119",
              "name": "Improper Restriction of Operations within the Bounds of a Memory Buffer",
              "source": "sparse",
              "original_content": "The product performs operations on a memory buffer, but it reads from or writes to a memory location outside the buffer's intended boundary. This may result in read or write operations on unexpected memory locations that could be linked to other variables, data structures, or internal program data."
            },
            "similarity": 105.55476574732565
          },
          {
            "metadata": {
              "doc_id": "1284",
              "name": "Improper Validation of Specified Quantity in Input",
              "source": "sparse",
              "original_content": "The product receives input that is expected to specify a quantity (such as size or length), but it does not validate or incorrectly validates that the quantity has the required properties."
            },
            "similarity": 97.49857387247421
          },
          {
            "metadata": {
              "doc_id": "193",
              "name": "Off-by-one Error",
              "source": "sparse",
              "original_content": "A product calculates or uses an incorrect maximum or minimum value that is 1 more, or 1 less, than the correct value."
            },
            "similarity": 97.1309547081105
          },
          {
            "metadata": {
              "doc_id": "20",
              "name": "Improper Input Validation",
              "source": "sparse",
              "original_content": "The product receives input or data, but it does\n        not validate or incorrectly validates that the input has the\n        properties that are required to process the data safely and\n        correctly."
            },
            "similarity": 95.41811915489893
          },
          {
            "metadata": {
              "doc_id": "125",
              "name": "Out-of-bounds Read",
              "source": "sparse",
              "original_content": "The product reads data past the end, or before the beginning, of the intended buffer."
            },
            "similarity": 95.18836229505204
          }
        ]
      },
      "version:through 2.12": {
        "keyphrase": "through 2.12",
        "type": "version",
        "cwes": [
          {
            "metadata": {
              "doc_id": "119",
              "name": "Improper Restriction of Operations within the Bounds of a Memory Buffer",
              "source": "sparse",
              "original_content": "The product performs operations on a memory buffer, but it reads from or writes to a memory location outside the buffer's intended boundary. This may result in read or write operations on unexpected memory locations that could be linked to other variables, data structures, or internal program data."
            },
            "similarity": 110.57166471753023
          },
          {
            "metadata": {
              "doc_id": "1284",
              "name": "Improper Validation of Specified Quantity in Input",
              "source": "sparse",
              "original_content": "The product receives input that is expected to specify a quantity (such as size or length), but it does not validate or incorrectly validates that the quantity has the required properties."
            },
            "similarity": 105.98580693415097
          },
          {
            "metadata": {
              "doc_id": "121",
              "name": "Stack-based Buffer Overflow",
              "source": "sparse",
              "original_content": "A stack-based buffer overflow condition is a condition where the buffer being overwritten is allocated on the stack (i.e., is a local variable or, rarely, a parameter to a function).",
              "keyphrase_sources": [
                {
                  "id": "version:through 2.12",
                  "keyphrase": "through 2.12",
                  "type": "version"
                }
              ]
            },
            "similarity": 102.48137836756713
          },
          {
            "metadata": {
              "doc_id": "122",
              "name": "Heap-based Buffer Overflow",
              "source": "sparse",
              "original_content": "A heap overflow condition is a buffer overflow, where the buffer that can be overwritten is allocated in the heap portion of memory, generally meaning that the buffer was allocated using a routine such as malloc()."
            },
            "similarity": 102.0295299816076
          },
          {
            "metadata": {
              "doc_id": "126",
              "name": "Buffer Over-read",
              "source": "sparse",
              "original_content": "The product reads from a buffer using buffer access mechanisms such as indexes or pointers that reference memory locations after the targeted buffer."
            },
            "similarity": 101.25568698845568
          }
        ]
      }
    },
    "keyphrase_mapping": {
      "119": [
        {
          "id": "rootcause:improper input validation",
          "keyphrase": "improper input validation",
          "type": "rootcause"
        },
        {
          "id": "rootcause:improper deserialization",
          "keyphrase": "improper deserialization",
          "type": "rootcause"
        },
        {
          "id": "rootcause:and improper restriction of operations within the bounds of a memory buffer",
          "keyphrase": "and improper restriction of operations within the bounds of a memory buffer",
          "type": "rootcause"
        },
        {
          "id": "weakness:deserialization",
          "keyphrase": "deserialization",
          "type": "weakness"
        },
        {
          "id": "impact:Denial-of-Service (DoS) attacks and possibly remote code execution",
          "keyphrase": "Denial-of-Service (DoS) attacks and possibly remote code execution",
          "type": "impact"
        },
        {
          "id": "vector:the \\xB0\\x00\\x3c byte sequence",
          "keyphrase": "the \\xB0\\x00\\x3c byte sequence",
          "type": "vector"
        },
        {
          "id": "product:UCI IDOL 2",
          "keyphrase": "UCI IDOL 2",
          "type": "product"
        },
        {
          "id": "version:through 2.12",
          "keyphrase": "through 2.12",
          "type": "version"
        }
      ],
      "1284": [
        {
          "id": "rootcause:improper input validation",
          "keyphrase": "improper input validation",
          "type": "rootcause"
        },
        {
          "id": "rootcause:improper deserialization",
          "keyphrase": "improper deserialization",
          "type": "rootcause"
        },
        {
          "id": "rootcause:and improper restriction of operations within the bounds of a memory buffer",
          "keyphrase": "and improper restriction of operations within the bounds of a memory buffer",
          "type": "rootcause"
        },
        {
          "id": "weakness:deserialization",
          "keyphrase": "deserialization",
          "type": "weakness"
        },
        {
          "id": "impact:Denial-of-Service (DoS) attacks and possibly remote code execution",
          "keyphrase": "Denial-of-Service (DoS) attacks and possibly remote code execution",
          "type": "impact"
        },
        {
          "id": "vector:the \\xB0\\x00\\x3c byte sequence",
          "keyphrase": "the \\xB0\\x00\\x3c byte sequence",
          "type": "vector"
        },
        {
          "id": "product:UCI IDOL 2",
          "keyphrase": "UCI IDOL 2",
          "type": "product"
        },
        {
          "id": "version:through 2.12",
          "keyphrase": "through 2.12",
          "type": "version"
        }
      ],
      "20": [
        {
          "id": "rootcause:improper input validation",
          "keyphrase": "improper input validation",
          "type": "rootcause"
        },
        {
          "id": "rootcause:improper deserialization",
          "keyphrase": "improper deserialization",
          "type": "rootcause"
        },
        {
          "id": "weakness:deserialization",
          "keyphrase": "deserialization",
          "type": "weakness"
        },
        {
          "id": "impact:Denial-of-Service (DoS) attacks and possibly remote code execution",
          "keyphrase": "Denial-of-Service (DoS) attacks and possibly remote code execution",
          "type": "impact"
        },
        {
          "id": "product:UCI IDOL 2",
          "keyphrase": "UCI IDOL 2",
          "type": "product"
        }
      ],
      "193": [
        {
          "id": "rootcause:improper input validation",
          "keyphrase": "improper input validation",
          "type": "rootcause"
        },
        {
          "id": "rootcause:improper deserialization",
          "keyphrase": "improper deserialization",
          "type": "rootcause"
        },
        {
          "id": "weakness:deserialization",
          "keyphrase": "deserialization",
          "type": "weakness"
        },
        {
          "id": "impact:Denial-of-Service (DoS) attacks and possibly remote code execution",
          "keyphrase": "Denial-of-Service (DoS) attacks and possibly remote code execution",
          "type": "impact"
        },
        {
          "id": "vector:the \\xB0\\x00\\x3c byte sequence",
          "keyphrase": "the \\xB0\\x00\\x3c byte sequence",
          "type": "vector"
        },
        {
          "id": "product:UCI IDOL 2",
          "keyphrase": "UCI IDOL 2",
          "type": "product"
        }
      ],
      "1285": [
        {
          "id": "rootcause:improper input validation",
          "keyphrase": "improper input validation",
          "type": "rootcause"
        }
      ],
      "502": [
        {
          "id": "rootcause:improper deserialization",
          "keyphrase": "improper deserialization",
          "type": "rootcause"
        },
        {
          "id": "weakness:deserialization",
          "keyphrase": "deserialization",
          "type": "weakness"
        }
      ],
      "125": [
        {
          "id": "rootcause:and improper restriction of operations within the bounds of a memory buffer",
          "keyphrase": "and improper restriction of operations within the bounds of a memory buffer",
          "type": "rootcause"
        },
        {
          "id": "vector:the \\xB0\\x00\\x3c byte sequence",
          "keyphrase": "the \\xB0\\x00\\x3c byte sequence",
          "type": "vector"
        },
        {
          "id": "product:UCI IDOL 2",
          "keyphrase": "UCI IDOL 2",
          "type": "product"
        }
      ],
      "190": [
        {
          "id": "rootcause:and improper restriction of operations within the bounds of a memory buffer",
          "keyphrase": "and improper restriction of operations within the bounds of a memory buffer",
          "type": "rootcause"
        }
      ],
      "122": [
        {
          "id": "rootcause:and improper restriction of operations within the bounds of a memory buffer",
          "keyphrase": "and improper restriction of operations within the bounds of a memory buffer",
          "type": "rootcause"
        },
        {
          "id": "version:through 2.12",
          "keyphrase": "through 2.12",
          "type": "version"
        }
      ],
      "126": [
        {
          "id": "impact:Denial-of-Service (DoS) attacks and possibly remote code execution",
          "keyphrase": "Denial-of-Service (DoS) attacks and possibly remote code execution",
          "type": "impact"
        },
        {
          "id": "vector:the \\xB0\\x00\\x3c byte sequence",
          "keyphrase": "the \\xB0\\x00\\x3c byte sequence",
          "type": "vector"
        },
        {
          "id": "version:through 2.12",
          "keyphrase": "through 2.12",
          "type": "version"
        }
      ],
      "121": [
        {
          "id": "version:through 2.12",
          "keyphrase": "through 2.12",
          "type": "version"
        }
      ]
    },
    "relevant_cwes": [
      {
        "metadata": {
          "doc_id": "125",
          "name": "Out-of-bounds Read",
          "source": "sparse",
          "original_content": "The product reads data past the end, or before the beginning, of the intended buffer.",
          "keyphrase_sources": [
            {
              "id": "rootcause:and improper restriction of operations within the bounds of a memory buffer",
              "keyphrase": "and improper restriction of operations within the bounds of a memory buffer",
              "type": "rootcause"
            },
            {
              "id": "vector:the \\xB0\\x00\\x3c byte sequence",
              "keyphrase": "the \\xB0\\x00\\x3c byte sequence",
              "type": "vector"
            },
            {
              "id": "product:UCI IDOL 2",
              "keyphrase": "UCI IDOL 2",
              "type": "product"
            }
          ]
        },
        "similarity": 487.3183453846036
      },
      {
        "metadata": {
          "doc_id": "190",
          "name": "Integer Overflow or Wraparound",
          "source": "sparse",
          "original_content": "The product performs a calculation that can\n         produce an integer overflow or wraparound when the logic\n         assumes that the resulting value will always be larger than\n         the original value. This occurs when an integer value is\n         incremented to a value that is too large to store in the\n         associated representation. When this occurs, the value may\n         become a very small or negative number.",
          "keyphrase_sources": [
            {
              "id": "rootcause:and improper restriction of operations within the bounds of a memory buffer",
              "keyphrase": "and improper restriction of operations within the bounds of a memory buffer",
              "type": "rootcause"
            }
          ]
        },
        "similarity": 480.0342304903063
      },
      {
        "metadata": {
          "doc_id": "122",
          "name": "Heap-based Buffer Overflow",
          "source": "sparse",
          "original_content": "A heap overflow condition is a buffer overflow, where the buffer that can be overwritten is allocated in the heap portion of memory, generally meaning that the buffer was allocated using a routine such as malloc().",
          "keyphrase_sources": [
            {
              "id": "rootcause:and improper restriction of operations within the bounds of a memory buffer",
              "keyphrase": "and improper restriction of operations within the bounds of a memory buffer",
              "type": "rootcause"
            },
            {
              "id": "version:through 2.12",
              "keyphrase": "through 2.12",
              "type": "version"
            }
          ]
        },
        "similarity": 465.3625870208492
      },
      {
        "metadata": {
          "doc_id": "119",
          "name": "Improper Restriction of Operations within the Bounds of a Memory Buffer",
          "source": "sparse",
          "original_content": "The product performs operations on a memory buffer, but it reads from or writes to a memory location outside the buffer's intended boundary. This may result in read or write operations on unexpected memory locations that could be linked to other variables, data structures, or internal program data.",
          "keyphrase_sources": [
            {
              "id": "rootcause:improper input validation",
              "keyphrase": "improper input validation",
              "type": "rootcause"
            },
            {
              "id": "rootcause:improper deserialization",
              "keyphrase": "improper deserialization",
              "type": "rootcause"
            },
            {
              "id": "rootcause:and improper restriction of operations within the bounds of a memory buffer",
              "keyphrase": "and improper restriction of operations within the bounds of a memory buffer",
              "type": "rootcause"
            },
            {
              "id": "weakness:deserialization",
              "keyphrase": "deserialization",
              "type": "weakness"
            },
            {
              "id": "impact:Denial-of-Service (DoS) attacks and possibly remote code execution",
              "keyphrase": "Denial-of-Service (DoS) attacks and possibly remote code execution",
              "type": "impact"
            },
            {
              "id": "vector:the \\xB0\\x00\\x3c byte sequence",
              "keyphrase": "the \\xB0\\x00\\x3c byte sequence",
              "type": "vector"
            },
            {
              "id": "product:UCI IDOL 2",
              "keyphrase": "UCI IDOL 2",
              "type": "product"
            },
            {
              "id": "version:through 2.12",
              "keyphrase": "through 2.12",
              "type": "version"
            }
          ]
        },
        "similarity": 324.3104510265156
      },
      {
        "metadata": {
          "doc_id": "1284",
          "name": "Improper Validation of Specified Quantity in Input",
          "source": "sparse",
          "original_content": "The product receives input that is expected to specify a quantity (such as size or length), but it does not validate or incorrectly validates that the quantity has the required properties.",
          "keyphrase_sources": [
            {
              "id": "rootcause:improper input validation",
              "keyphrase": "improper input validation",
              "type": "rootcause"
            },
            {
              "id": "rootcause:improper deserialization",
              "keyphrase": "improper deserialization",
              "type": "rootcause"
            },
            {
              "id": "rootcause:and improper restriction of operations within the bounds of a memory buffer",
              "keyphrase": "and improper restriction of operations within the bounds of a memory buffer",
              "type": "rootcause"
            },
            {
              "id": "weakness:deserialization",
              "keyphrase": "deserialization",
              "type": "weakness"
            },
            {
              "id": "impact:Denial-of-Service (DoS) attacks and possibly remote code execution",
              "keyphrase": "Denial-of-Service (DoS) attacks and possibly remote code execution",
              "type": "impact"
            },
            {
              "id": "vector:the \\xB0\\x00\\x3c byte sequence",
              "keyphrase": "the \\xB0\\x00\\x3c byte sequence",
              "type": "vector"
            },
            {
              "id": "product:UCI IDOL 2",
              "keyphrase": "UCI IDOL 2",
              "type": "product"
            },
            {
              "id": "version:through 2.12",
              "keyphrase": "through 2.12",
              "type": "version"
            }
          ]
        },
        "similarity": 321.7229722829796
      },
      {
        "metadata": {
          "doc_id": "20",
          "name": "Improper Input Validation",
          "source": "sparse",
          "original_content": "The product receives input or data, but it does\n        not validate or incorrectly validates that the input has the\n        properties that are required to process the data safely and\n        correctly.",
          "keyphrase_sources": [
            {
              "id": "rootcause:improper input validation",
              "keyphrase": "improper input validation",
              "type": "rootcause"
            },
            {
              "id": "rootcause:improper deserialization",
              "keyphrase": "improper deserialization",
              "type": "rootcause"
            },
            {
              "id": "weakness:deserialization",
              "keyphrase": "deserialization",
              "type": "weakness"
            },
            {
              "id": "impact:Denial-of-Service (DoS) attacks and possibly remote code execution",
              "keyphrase": "Denial-of-Service (DoS) attacks and possibly remote code execution",
              "type": "impact"
            },
            {
              "id": "product:UCI IDOL 2",
              "keyphrase": "UCI IDOL 2",
              "type": "product"
            }
          ]
        },
        "similarity": 320.44997839408865
      },
      {
        "metadata": {
          "doc_id": "502",
          "name": "Deserialization of Untrusted Data",
          "source": "sparse",
          "original_content": "The product deserializes untrusted data without sufficiently ensuring that the resulting data will be valid.",
          "keyphrase_sources": [
            {
              "id": "rootcause:improper deserialization",
              "keyphrase": "improper deserialization",
              "type": "rootcause"
            },
            {
              "id": "weakness:deserialization",
              "keyphrase": "deserialization",
              "type": "weakness"
            }
          ]
        },
        "similarity": 313.5657362930267
      },
      {
        "metadata": {
          "doc_id": "193",
          "name": "Off-by-one Error",
          "source": "sparse",
          "original_content": "A product calculates or uses an incorrect maximum or minimum value that is 1 more, or 1 less, than the correct value.",
          "keyphrase_sources": [
            {
              "id": "rootcause:improper input validation",
              "keyphrase": "improper input validation",
              "type": "rootcause"
            },
            {
              "id": "rootcause:improper deserialization",
              "keyphrase": "improper deserialization",
              "type": "rootcause"
            },
            {
              "id": "weakness:deserialization",
              "keyphrase": "deserialization",
              "type": "weakness"
            },
            {
              "id": "impact:Denial-of-Service (DoS) attacks and possibly remote code execution",
              "keyphrase": "Denial-of-Service (DoS) attacks and possibly remote code execution",
              "type": "impact"
            },
            {
              "id": "vector:the \\xB0\\x00\\x3c byte sequence",
              "keyphrase": "the \\xB0\\x00\\x3c byte sequence",
              "type": "vector"
            },
            {
              "id": "product:UCI IDOL 2",
              "keyphrase": "UCI IDOL 2",
              "type": "product"
            }
          ]
        },
        "similarity": 307.6707764241428
      },
      {
        "metadata": {
          "doc_id": "1285",
          "name": "Improper Validation of Specified Index, Position, or Offset in Input",
          "source": "sparse",
          "original_content": "The product receives input that is expected to specify an index, position, or offset into an indexable resource such as a buffer or file, but it does not validate or incorrectly validates that the specified index/position/offset has the required properties.",
          "keyphrase_sources": [
            {
              "id": "rootcause:improper input validation",
              "keyphrase": "improper input validation",
              "type": "rootcause"
            }
          ]
        },
        "similarity": 302.6993778142302
      },
      {
        "metadata": {
          "doc_id": "126",
          "name": "Buffer Over-read",
          "source": "sparse",
          "original_content": "The product reads from a buffer using buffer access mechanisms such as indexes or pointers that reference memory locations after the targeted buffer.",
          "keyphrase_sources": [
            {
              "id": "impact:Denial-of-Service (DoS) attacks and possibly remote code execution",
              "keyphrase": "Denial-of-Service (DoS) attacks and possibly remote code execution",
              "type": "impact"
            },
            {
              "id": "vector:the \\xB0\\x00\\x3c byte sequence",
              "keyphrase": "the \\xB0\\x00\\x3c byte sequence",
              "type": "vector"
            },
            {
              "id": "version:through 2.12",
              "keyphrase": "through 2.12",
              "type": "version"
            }
          ]
        },
        "similarity": 130.2138268619382
      },
      {
        "metadata": {
          "doc_id": "121",
          "name": "Stack-based Buffer Overflow",
          "source": "sparse",
          "original_content": "A stack-based buffer overflow condition is a condition where the buffer being overwritten is allocated on the stack (i.e., is a local variable or, rarely, a parameter to a function).",
          "keyphrase_sources": [
            {
              "id": "version:through 2.12",
              "keyphrase": "through 2.12",
              "type": "version"
            }
          ]
        },
        "similarity": 102.48137836756713
      }
    ],
    "enhanced_query": "# Vulnerability Description\n\n    An issue was discovered in UCI IDOL 2 (aka uciIDOL or IDOL2) through 2.12. Due to **improper input validation**, **improper **deserialization****, **and improper restriction of operations within the bounds of a memory buffer**, IDOL2 is vulnerable to Denial-of-Service (DoS) attacks and possibly remote code execution via the \\xB0\\x00\\x3c byte sequence.\n\n    # Keyphrase-Specific CWE Analysis\n    This vulnerability contains multiple keyphrases that may map to different CWEs. \n    Please analyze each keyphrase separately and determine the most appropriate CWE(s) for each.\n\n    ## ROOTCAUSE: 'and improper restriction of operations within the bounds of a memory buffer'\n\nRelevant CWEs for this ROOTCAUSE:\n\n### 1. CWE-125: Out-of-bounds Read (Score: 487.32)\n\nThe product reads data past the end, or before the beginning, of the intended buffer....\n\n### 2. CWE-190: Integer Overflow or Wraparound (Score: 480.03)\n\nThe product performs a calculation that can\n         produce an integer overflow or wraparound when the logic\n         assumes that the resulting value will always be larger than\n         the original value. This occurs when an integer value is\n         incremented to a value that is too large to st...\n\n### 3. CWE-122: Heap-based Buffer Overflow (Score: 465.36)\n\nA heap overflow condition is a buffer overflow, where the buffer that can be overwritten is allocated in the heap portion of memory, generally meaning that the buffer was allocated using a routine such as malloc()....\n\n### 4. CWE-119: Improper Restriction of Operations within the Bounds of a Memory Buffer (Score: 324.31)\n\nThe product performs operations on a memory buffer, but it reads from or writes to a memory location outside the buffer's intended boundary. This may result in read or write operations on unexpected memory locations that could be linked to other variables, data structures, or internal program data....\n\n### 5. CWE-1284: Improper Validation of Specified Quantity in Input (Score: 321.72)\n\nThe product receives input that is expected to specify a quantity (such as size or length), but it does not validate or incorrectly validates that the quantity has the required properties....\n\n## VECTOR: 'the \\xB0\\x00\\x3c byte sequence'\n\nRelevant CWEs for this VECTOR:\n\n### 1. CWE-125: Out-of-bounds Read (Score: 487.32)\n\nThe product reads data past the end, or before the beginning, of the intended buffer....\n\n### 2. CWE-119: Improper Restriction of Operations within the Bounds of a Memory Buffer (Score: 324.31)\n\nThe product performs operations on a memory buffer, but it reads from or writes to a memory location outside the buffer's intended boundary. This may result in read or write operations on unexpected memory locations that could be linked to other variables, data structures, or internal program data....\n\n### 3. CWE-1284: Improper Validation of Specified Quantity in Input (Score: 321.72)\n\nThe product receives input that is expected to specify a quantity (such as size or length), but it does not validate or incorrectly validates that the quantity has the required properties....\n\n### 4. CWE-193: Off-by-one Error (Score: 307.67)\n\nA product calculates or uses an incorrect maximum or minimum value that is 1 more, or 1 less, than the correct value....\n\n### 5. CWE-126: Buffer Over-read (Score: 130.21)\n\nThe product reads from a buffer using buffer access mechanisms such as indexes or pointers that reference memory locations after the targeted buffer....\n\n## PRODUCT: 'UCI IDOL 2'\n\nRelevant CWEs for this PRODUCT:\n\n### 1. CWE-125: Out-of-bounds Read (Score: 487.32)\n\nThe product reads data past the end, or before the beginning, of the intended buffer....\n\n### 2. CWE-119: Improper Restriction of Operations within the Bounds of a Memory Buffer (Score: 324.31)\n\nThe product performs operations on a memory buffer, but it reads from or writes to a memory location outside the buffer's intended boundary. This may result in read or write operations on unexpected memory locations that could be linked to other variables, data structures, or internal program data....\n\n### 3. CWE-1284: Improper Validation of Specified Quantity in Input (Score: 321.72)\n\nThe product receives input that is expected to specify a quantity (such as size or length), but it does not validate or incorrectly validates that the quantity has the required properties....\n\n### 4. CWE-20: Improper Input Validation (Score: 320.45)\n\nThe product receives input or data, but it does\n        not validate or incorrectly validates that the input has the\n        properties that are required to process the data safely and\n        correctly....\n\n### 5. CWE-193: Off-by-one Error (Score: 307.67)\n\nA product calculates or uses an incorrect maximum or minimum value that is 1 more, or 1 less, than the correct value....\n\n## VERSION: 'through 2.12'\n\nRelevant CWEs for this VERSION:\n\n### 1. CWE-122: Heap-based Buffer Overflow (Score: 465.36)\n\nA heap overflow condition is a buffer overflow, where the buffer that can be overwritten is allocated in the heap portion of memory, generally meaning that the buffer was allocated using a routine such as malloc()....\n\n### 2. CWE-119: Improper Restriction of Operations within the Bounds of a Memory Buffer (Score: 324.31)\n\nThe product performs operations on a memory buffer, but it reads from or writes to a memory location outside the buffer's intended boundary. This may result in read or write operations on unexpected memory locations that could be linked to other variables, data structures, or internal program data....\n\n### 3. CWE-1284: Improper Validation of Specified Quantity in Input (Score: 321.72)\n\nThe product receives input that is expected to specify a quantity (such as size or length), but it does not validate or incorrectly validates that the quantity has the required properties....\n\n### 4. CWE-126: Buffer Over-read (Score: 130.21)\n\nThe product reads from a buffer using buffer access mechanisms such as indexes or pointers that reference memory locations after the targeted buffer....\n\n### 5. CWE-121: Stack-based Buffer Overflow (Score: 102.48)\n\nA stack-based buffer overflow condition is a condition where the buffer being overwritten is allocated on the stack (i.e., is a local variable or, rarely, a parameter to a function)....\n\n## ROOTCAUSE: 'improper input validation'\n\nRelevant CWEs for this ROOTCAUSE:\n\n### 1. CWE-119: Improper Restriction of Operations within the Bounds of a Memory Buffer (Score: 324.31)\n\nThe product performs operations on a memory buffer, but it reads from or writes to a memory location outside the buffer's intended boundary. This may result in read or write operations on unexpected memory locations that could be linked to other variables, data structures, or internal program data....\n\n### 2. CWE-1284: Improper Validation of Specified Quantity in Input (Score: 321.72)\n\nThe product receives input that is expected to specify a quantity (such as size or length), but it does not validate or incorrectly validates that the quantity has the required properties....\n\n### 3. CWE-20: Improper Input Validation (Score: 320.45)\n\nThe product receives input or data, but it does\n        not validate or incorrectly validates that the input has the\n        properties that are required to process the data safely and\n        correctly....\n\n### 4. CWE-193: Off-by-one Error (Score: 307.67)\n\nA product calculates or uses an incorrect maximum or minimum value that is 1 more, or 1 less, than the correct value....\n\n### 5. CWE-1285: Improper Validation of Specified Index, Position, or Offset in Input (Score: 302.70)\n\nThe product receives input that is expected to specify an index, position, or offset into an indexable resource such as a buffer or file, but it does not validate or incorrectly validates that the specified index/position/offset has the required properties....\n\n## ROOTCAUSE: 'improper deserialization'\n\nRelevant CWEs for this ROOTCAUSE:\n\n### 1. CWE-119: Improper Restriction of Operations within the Bounds of a Memory Buffer (Score: 324.31)\n\nThe product performs operations on a memory buffer, but it reads from or writes to a memory location outside the buffer's intended boundary. This may result in read or write operations on unexpected memory locations that could be linked to other variables, data structures, or internal program data....\n\n### 2. CWE-1284: Improper Validation of Specified Quantity in Input (Score: 321.72)\n\nThe product receives input that is expected to specify a quantity (such as size or length), but it does not validate or incorrectly validates that the quantity has the required properties....\n\n### 3. CWE-20: Improper Input Validation (Score: 320.45)\n\nThe product receives input or data, but it does\n        not validate or incorrectly validates that the input has the\n        properties that are required to process the data safely and\n        correctly....\n\n### 4. CWE-502: Deserialization of Untrusted Data (Score: 313.57)\n\nThe product deserializes untrusted data without sufficiently ensuring that the resulting data will be valid....\n\n### 5. CWE-193: Off-by-one Error (Score: 307.67)\n\nA product calculates or uses an incorrect maximum or minimum value that is 1 more, or 1 less, than the correct value....\n\n## WEAKNESS: 'deserialization'\n\nRelevant CWEs for this WEAKNESS:\n\n### 1. CWE-119: Improper Restriction of Operations within the Bounds of a Memory Buffer (Score: 324.31)\n\nThe product performs operations on a memory buffer, but it reads from or writes to a memory location outside the buffer's intended boundary. This may result in read or write operations on unexpected memory locations that could be linked to other variables, data structures, or internal program data....\n\n### 2. CWE-1284: Improper Validation of Specified Quantity in Input (Score: 321.72)\n\nThe product receives input that is expected to specify a quantity (such as size or length), but it does not validate or incorrectly validates that the quantity has the required properties....\n\n### 3. CWE-20: Improper Input Validation (Score: 320.45)\n\nThe product receives input or data, but it does\n        not validate or incorrectly validates that the input has the\n        properties that are required to process the data safely and\n        correctly....\n\n### 4. CWE-502: Deserialization of Untrusted Data (Score: 313.57)\n\nThe product deserializes untrusted data without sufficiently ensuring that the resulting data will be valid....\n\n### 5. CWE-193: Off-by-one Error (Score: 307.67)\n\nA product calculates or uses an incorrect maximum or minimum value that is 1 more, or 1 less, than the correct value....\n\n## IMPACT: 'Denial-of-Service (DoS) attacks and possibly remote code execution'\n\nRelevant CWEs for this IMPACT:\n\n### 1. CWE-119: Improper Restriction of Operations within the Bounds of a Memory Buffer (Score: 324.31)\n\nThe product performs operations on a memory buffer, but it reads from or writes to a memory location outside the buffer's intended boundary. This may result in read or write operations on unexpected memory locations that could be linked to other variables, data structures, or internal program data....\n\n### 2. CWE-1284: Improper Validation of Specified Quantity in Input (Score: 321.72)\n\nThe product receives input that is expected to specify a quantity (such as size or length), but it does not validate or incorrectly validates that the quantity has the required properties....\n\n### 3. CWE-20: Improper Input Validation (Score: 320.45)\n\nThe product receives input or data, but it does\n        not validate or incorrectly validates that the input has the\n        properties that are required to process the data safely and\n        correctly....\n\n### 4. CWE-193: Off-by-one Error (Score: 307.67)\n\nA product calculates or uses an incorrect maximum or minimum value that is 1 more, or 1 less, than the correct value....\n\n### 5. CWE-126: Buffer Over-read (Score: 130.21)\n\nThe product reads from a buffer using buffer access mechanisms such as indexes or pointers that reference memory locations after the targeted buffer....\n\n\n    # Analysis Instructions\n    1. For each keyphrase, identify the most appropriate CWE(s) that represent the weakness.\n    2. Consider how the different keyphrases might relate to each other in the vulnerability chain.\n    3. Provide a final determination of primary CWE(s) and any secondary CWEs.\n    4. Format your response using the standard analysis template.\n\n    Please analyze how these different weaknesses interact and provide a comprehensive CWE classification.\n    "
  },
  "retrieval_time": 1.2635467052459717
}