{
  "vulnerability_info": "VulnerabilityInfo(cve_id='CVE-2025-20158', description='A vulnerability in the debug shell of Cisco Video Phone 8875 and Cisco Desk Phone 9800 Series could allow an authenticated, local attacker to access sensitive information on an affected device. To exploit this vulnerability, the attacker must have valid administrative credentials with SSH access on the affected device. SSH access is disabled by default. This vulnerability is due to **insufficient validation of user-supplied input** by the debug shell of an affected device. An attacker could exploit this vulnerability by sending a crafted SSH client command to the CLI. A successful exploit could allow the attacker to access sensitive information on the underlying operating system.', key_phrases={'rootcause': ['insufficient validation of user-supplied input', 'insufficient input validation'], 'weakness': '', 'impact': 'access sensitive information', 'vector': 'crafted SSH client command', 'attacker': 'authenticated local attacker', 'product': ['Cisco Desk Phone 9800 Series', 'Cisco Video Phone 8875'], 'version': '', 'component': 'debug shell'}, reference_content=\"## Analysis of CVE-2025-20158 based on provided content:\\n\\nThe provided content **is relevant** to CVE-2025-20158. It details a vulnerability in Cisco Video Phone 8875 and Desk Phone 9800 Series. Here's a breakdown of the information extracted:\\n\\n**Root cause of vulnerability:**\\n\\n*   Insufficient validation of user-supplied input by the debug shell of the affected devices.\\n\\n**Weaknesses/vulnerabilities present:**\\n\\n*   Information Disclosure - An attacker can access sensitive information on the underlying operating system.\\n*   The vulnerability exists in the debug shell.\\n\\n**Impact of exploitation:**\\n\\n*   An authenticated, local attacker can access sensitive information on the affected device.\\n\\n**Attack vectors:**\\n\\n*   Crafted SSH client command sent to the CLI.\\n*   Requires valid administrative credentials with SSH access. (SSH access is disabled by default)\\n\\n**Required attacker capabilities/position:**\\n\\n*   Authenticated, local attacker.\\n*   Valid administrative credentials.\\n*   SSH access enabled on the affected device.\\n\\n**Mitigation or fix:**\\n\\n*   Cisco has released software updates that address this vulnerability.\\n*   No workarounds are available.\\n*   Affected products can be upgraded to version 3.3(1) or later (from 3.2(1) and earlier).\\n\\n**Additional Details (more than official CVE description):**\\n\\n*   **CWE-200:**  Identifies the vulnerability type as CWE-200 (Improper Input Validation).\\n*   **CVSS Score:** Base Score: 4.4 (CVSS:3.1/AV:L/AC:L/PR:H/UI:N/S:U/C:H/I:N/A:N)\\n*   **Cisco Bug IDs:** CSCwn51779, CSCwn58742, CSCwn58744\\n*   The vulnerability was discovered during internal security testing by Zach Sanchez of the Cisco Advanced Security Initiatives Group (ASIG).\\n*   The advisory is available at: <https://sec.cloudapps.cisco.com/security/center/content/CiscoSecurityAdvisory/cisco-sa-phone-info-disc-YyxsWStK>\\n*   The content includes a detailed CVSS v3.1 breakdown.\", similar_info={'cwe_distribution': {}, 'cwe_consensus': '', 'similarity_stats': {'thresholds': [], 'total_samples_by_threshold': {}, 'top_cwes_by_threshold': {}}}, similarity_summary=SimilarityInsight(consensus_cwe='', top_cwes=[], confidence_levels={}, total_samples=0), analysis='', analysis_with_relationships='', criticism='', resolution='', relevant_cwes=[{'metadata': {'doc_id': '20', 'name': 'Improper Input Validation', 'source': 'sparse', 'original_content': 'The product receives input or data, but it does\\n        not validate or incorrectly validates that the input has the\\n        properties that are required to process the data safely and\\n        correctly.', 'keyphrase_sources': [{'id': 'rootcause:insufficient validation of user-supplied input', 'keyphrase': 'insufficient validation of user-supplied input', 'type': 'rootcause'}, {'id': 'rootcause:insufficient input validation', 'keyphrase': 'insufficient input validation', 'type': 'rootcause'}, {'id': 'impact:access sensitive information', 'keyphrase': 'access sensitive information', 'type': 'impact'}, {'id': 'vector:crafted SSH client command', 'keyphrase': 'crafted SSH client command', 'type': 'vector'}, {'id': 'attacker:authenticated local attacker', 'keyphrase': 'authenticated local attacker', 'type': 'attacker'}, {'id': 'product:Cisco Desk Phone 9800 Series', 'keyphrase': 'Cisco Desk Phone 9800 Series', 'type': 'product'}, {'id': 'product:Cisco Video Phone 8875', 'keyphrase': 'Cisco Video Phone 8875', 'type': 'product'}, {'id': 'component:debug shell', 'keyphrase': 'debug shell', 'type': 'component'}]}, 'similarity': np.float64(792.832826414002)}, {'metadata': {'doc_id': '798', 'name': 'Use of Hard-coded Credentials', 'source': 'sparse', 'original_content': 'The product contains hard-coded credentials, such as a password or cryptographic key.', 'keyphrase_sources': [{'id': 'rootcause:insufficient validation of user-supplied input', 'keyphrase': 'insufficient validation of user-supplied input', 'type': 'rootcause'}, {'id': 'rootcause:insufficient input validation', 'keyphrase': 'insufficient input validation', 'type': 'rootcause'}, {'id': 'impact:access sensitive information', 'keyphrase': 'access sensitive information', 'type': 'impact'}, {'id': 'vector:crafted SSH client command', 'keyphrase': 'crafted SSH client command', 'type': 'vector'}, {'id': 'attacker:authenticated local attacker', 'keyphrase': 'authenticated local attacker', 'type': 'attacker'}, {'id': 'product:Cisco Desk Phone 9800 Series', 'keyphrase': 'Cisco Desk Phone 9800 Series', 'type': 'product'}, {'id': 'product:Cisco Video Phone 8875', 'keyphrase': 'Cisco Video Phone 8875', 'type': 'product'}, {'id': 'component:debug shell', 'keyphrase': 'debug shell', 'type': 'component'}]}, 'similarity': np.float64(723.3066169403913)}, {'metadata': {'doc_id': '78', 'name': \"Improper Neutralization of Special Elements used in an OS Command ('OS Command Injection')\", 'source': 'sparse', 'original_content': 'The product constructs all or part of an OS command using externally-influenced input from an upstream component, but it does not neutralize or incorrectly neutralizes special elements that could modify the intended OS command when it is sent to a downstream component.', 'keyphrase_sources': [{'id': 'rootcause:insufficient validation of user-supplied input', 'keyphrase': 'insufficient validation of user-supplied input', 'type': 'rootcause'}, {'id': 'rootcause:insufficient input validation', 'keyphrase': 'insufficient input validation', 'type': 'rootcause'}, {'id': 'vector:crafted SSH client command', 'keyphrase': 'crafted SSH client command', 'type': 'vector'}, {'id': 'attacker:authenticated local attacker', 'keyphrase': 'authenticated local attacker', 'type': 'attacker'}, {'id': 'product:Cisco Desk Phone 9800 Series', 'keyphrase': 'Cisco Desk Phone 9800 Series', 'type': 'product'}, {'id': 'component:debug shell', 'keyphrase': 'debug shell', 'type': 'component'}]}, 'similarity': np.float64(706.0319254076163)}, {'metadata': {'doc_id': '284', 'name': 'Improper Access Control', 'source': 'sparse', 'original_content': 'The product does not restrict or incorrectly restricts access to a resource from an unauthorized actor.', 'keyphrase_sources': [{'id': 'rootcause:insufficient validation of user-supplied input', 'keyphrase': 'insufficient validation of user-supplied input', 'type': 'rootcause'}, {'id': 'rootcause:insufficient input validation', 'keyphrase': 'insufficient input validation', 'type': 'rootcause'}, {'id': 'impact:access sensitive information', 'keyphrase': 'access sensitive information', 'type': 'impact'}, {'id': 'attacker:authenticated local attacker', 'keyphrase': 'authenticated local attacker', 'type': 'attacker'}, {'id': 'product:Cisco Desk Phone 9800 Series', 'keyphrase': 'Cisco Desk Phone 9800 Series', 'type': 'product'}, {'id': 'product:Cisco Video Phone 8875', 'keyphrase': 'Cisco Video Phone 8875', 'type': 'product'}, {'id': 'component:debug shell', 'keyphrase': 'debug shell', 'type': 'component'}]}, 'similarity': np.float64(703.7173455493453)}, {'metadata': {'doc_id': '138', 'name': 'Improper Neutralization of Special Elements', 'source': 'sparse', 'original_content': 'The product receives input from an upstream component, but it does not neutralize or incorrectly neutralizes special elements that could be interpreted as control elements or syntactic markers when they are sent to a downstream component.', 'keyphrase_sources': [{'id': 'rootcause:insufficient validation of user-supplied input', 'keyphrase': 'insufficient validation of user-supplied input', 'type': 'rootcause'}]}, 'similarity': np.float64(699.6990006515691)}, {'metadata': {'doc_id': '287', 'name': 'Improper Authentication', 'source': 'sparse', 'original_content': 'When an actor claims to have a given identity, the product does not prove or insufficiently proves that the claim is correct.', 'keyphrase_sources': [{'id': 'rootcause:insufficient input validation', 'keyphrase': 'insufficient input validation', 'type': 'rootcause'}]}, 'similarity': np.float64(673.4854246872175)}, {'metadata': {'doc_id': '321', 'name': 'Use of Hard-coded Cryptographic Key', 'source': 'sparse', 'original_content': 'The use of a hard-coded cryptographic key significantly increases the possibility that encrypted data may be recovered.', 'keyphrase_sources': [{'id': 'vector:crafted SSH client command', 'keyphrase': 'crafted SSH client command', 'type': 'vector'}, {'id': 'product:Cisco Video Phone 8875', 'keyphrase': 'Cisco Video Phone 8875', 'type': 'product'}, {'id': 'component:debug shell', 'keyphrase': 'debug shell', 'type': 'component'}]}, 'similarity': np.float64(231.97449090034797)}, {'metadata': {'doc_id': '250', 'name': 'Execution with Unnecessary Privileges', 'source': 'sparse', 'original_content': 'The product performs an operation at a privilege level that is higher than the minimum level required, which creates new weaknesses or amplifies the consequences of other weaknesses.', 'keyphrase_sources': [{'id': 'vector:crafted SSH client command', 'keyphrase': 'crafted SSH client command', 'type': 'vector'}]}, 'similarity': np.float64(230.9804731495117)}, {'metadata': {'doc_id': '532', 'name': 'Insertion of Sensitive Information into Log File', 'source': 'sparse', 'original_content': 'The product writes sensitive information to a log file.', 'keyphrase_sources': [{'id': 'impact:access sensitive information', 'keyphrase': 'access sensitive information', 'type': 'impact'}]}, 'similarity': np.float64(230.42988156317938)}, {'metadata': {'doc_id': '269', 'name': 'Improper Privilege Management', 'source': 'sparse', 'original_content': 'The product does not properly assign, modify, track, or check privileges for an actor, creating an unintended sphere of control for that actor.', 'keyphrase_sources': [{'id': 'impact:access sensitive information', 'keyphrase': 'access sensitive information', 'type': 'impact'}, {'id': 'attacker:authenticated local attacker', 'keyphrase': 'authenticated local attacker', 'type': 'attacker'}, {'id': 'product:Cisco Desk Phone 9800 Series', 'keyphrase': 'Cisco Desk Phone 9800 Series', 'type': 'product'}, {'id': 'product:Cisco Video Phone 8875', 'keyphrase': 'Cisco Video Phone 8875', 'type': 'product'}]}, 'similarity': np.float64(230.1406217033529)}], identified_cwes={'analyzer': [], 'critic_additional': []})",
  "retrieval_results": {
    "has_multiple_keyphrases": true,
    "keyphrase_cwe_sets": {
      "rootcause:insufficient validation of user-supplied input": {
        "keyphrase": "insufficient validation of user-supplied input",
        "type": "rootcause",
        "cwes": [
          {
            "metadata": {
              "doc_id": "20",
              "name": "Improper Input Validation",
              "source": "sparse",
              "original_content": "The product receives input or data, but it does\n        not validate or incorrectly validates that the input has the\n        properties that are required to process the data safely and\n        correctly.",
              "keyphrase_sources": [
                {
                  "id": "rootcause:insufficient validation of user-supplied input",
                  "keyphrase": "insufficient validation of user-supplied input",
                  "type": "rootcause"
                },
                {
                  "id": "rootcause:insufficient input validation",
                  "keyphrase": "insufficient input validation",
                  "type": "rootcause"
                },
                {
                  "id": "impact:access sensitive information",
                  "keyphrase": "access sensitive information",
                  "type": "impact"
                },
                {
                  "id": "vector:crafted SSH client command",
                  "keyphrase": "crafted SSH client command",
                  "type": "vector"
                },
                {
                  "id": "attacker:authenticated local attacker",
                  "keyphrase": "authenticated local attacker",
                  "type": "attacker"
                },
                {
                  "id": "product:Cisco Desk Phone 9800 Series",
                  "keyphrase": "Cisco Desk Phone 9800 Series",
                  "type": "product"
                },
                {
                  "id": "product:Cisco Video Phone 8875",
                  "keyphrase": "Cisco Video Phone 8875",
                  "type": "product"
                },
                {
                  "id": "component:debug shell",
                  "keyphrase": "debug shell",
                  "type": "component"
                }
              ]
            },
            "similarity": 792.832826414002
          },
          {
            "metadata": {
              "doc_id": "798",
              "name": "Use of Hard-coded Credentials",
              "source": "sparse",
              "original_content": "The product contains hard-coded credentials, such as a password or cryptographic key.",
              "keyphrase_sources": [
                {
                  "id": "rootcause:insufficient validation of user-supplied input",
                  "keyphrase": "insufficient validation of user-supplied input",
                  "type": "rootcause"
                },
                {
                  "id": "rootcause:insufficient input validation",
                  "keyphrase": "insufficient input validation",
                  "type": "rootcause"
                },
                {
                  "id": "impact:access sensitive information",
                  "keyphrase": "access sensitive information",
                  "type": "impact"
                },
                {
                  "id": "vector:crafted SSH client command",
                  "keyphrase": "crafted SSH client command",
                  "type": "vector"
                },
                {
                  "id": "attacker:authenticated local attacker",
                  "keyphrase": "authenticated local attacker",
                  "type": "attacker"
                },
                {
                  "id": "product:Cisco Desk Phone 9800 Series",
                  "keyphrase": "Cisco Desk Phone 9800 Series",
                  "type": "product"
                },
                {
                  "id": "product:Cisco Video Phone 8875",
                  "keyphrase": "Cisco Video Phone 8875",
                  "type": "product"
                },
                {
                  "id": "component:debug shell",
                  "keyphrase": "debug shell",
                  "type": "component"
                }
              ]
            },
            "similarity": 723.3066169403913
          },
          {
            "metadata": {
              "doc_id": "78",
              "name": "Improper Neutralization of Special Elements used in an OS Command ('OS Command Injection')",
              "source": "sparse",
              "original_content": "The product constructs all or part of an OS command using externally-influenced input from an upstream component, but it does not neutralize or incorrectly neutralizes special elements that could modify the intended OS command when it is sent to a downstream component.",
              "keyphrase_sources": [
                {
                  "id": "rootcause:insufficient validation of user-supplied input",
                  "keyphrase": "insufficient validation of user-supplied input",
                  "type": "rootcause"
                },
                {
                  "id": "rootcause:insufficient input validation",
                  "keyphrase": "insufficient input validation",
                  "type": "rootcause"
                },
                {
                  "id": "vector:crafted SSH client command",
                  "keyphrase": "crafted SSH client command",
                  "type": "vector"
                },
                {
                  "id": "attacker:authenticated local attacker",
                  "keyphrase": "authenticated local attacker",
                  "type": "attacker"
                },
                {
                  "id": "product:Cisco Desk Phone 9800 Series",
                  "keyphrase": "Cisco Desk Phone 9800 Series",
                  "type": "product"
                },
                {
                  "id": "component:debug shell",
                  "keyphrase": "debug shell",
                  "type": "component"
                }
              ]
            },
            "similarity": 706.0319254076163
          },
          {
            "metadata": {
              "doc_id": "284",
              "name": "Improper Access Control",
              "source": "sparse",
              "original_content": "The product does not restrict or incorrectly restricts access to a resource from an unauthorized actor.",
              "keyphrase_sources": [
                {
                  "id": "rootcause:insufficient validation of user-supplied input",
                  "keyphrase": "insufficient validation of user-supplied input",
                  "type": "rootcause"
                },
                {
                  "id": "rootcause:insufficient input validation",
                  "keyphrase": "insufficient input validation",
                  "type": "rootcause"
                },
                {
                  "id": "impact:access sensitive information",
                  "keyphrase": "access sensitive information",
                  "type": "impact"
                },
                {
                  "id": "attacker:authenticated local attacker",
                  "keyphrase": "authenticated local attacker",
                  "type": "attacker"
                },
                {
                  "id": "product:Cisco Desk Phone 9800 Series",
                  "keyphrase": "Cisco Desk Phone 9800 Series",
                  "type": "product"
                },
                {
                  "id": "product:Cisco Video Phone 8875",
                  "keyphrase": "Cisco Video Phone 8875",
                  "type": "product"
                },
                {
                  "id": "component:debug shell",
                  "keyphrase": "debug shell",
                  "type": "component"
                }
              ]
            },
            "similarity": 703.7173455493453
          },
          {
            "metadata": {
              "doc_id": "138",
              "name": "Improper Neutralization of Special Elements",
              "source": "sparse",
              "original_content": "The product receives input from an upstream component, but it does not neutralize or incorrectly neutralizes special elements that could be interpreted as control elements or syntactic markers when they are sent to a downstream component.",
              "keyphrase_sources": [
                {
                  "id": "rootcause:insufficient validation of user-supplied input",
                  "keyphrase": "insufficient validation of user-supplied input",
                  "type": "rootcause"
                }
              ]
            },
            "similarity": 699.6990006515691
          }
        ]
      },
      "rootcause:insufficient input validation": {
        "keyphrase": "insufficient input validation",
        "type": "rootcause",
        "cwes": [
          {
            "metadata": {
              "doc_id": "20",
              "name": "Improper Input Validation",
              "source": "sparse",
              "original_content": "The product receives input or data, but it does\n        not validate or incorrectly validates that the input has the\n        properties that are required to process the data safely and\n        correctly."
            },
            "similarity": 749.8857145717421
          },
          {
            "metadata": {
              "doc_id": "798",
              "name": "Use of Hard-coded Credentials",
              "source": "sparse",
              "original_content": "The product contains hard-coded credentials, such as a password or cryptographic key."
            },
            "similarity": 702.3790060406079
          },
          {
            "metadata": {
              "doc_id": "284",
              "name": "Improper Access Control",
              "source": "sparse",
              "original_content": "The product does not restrict or incorrectly restricts access to a resource from an unauthorized actor."
            },
            "similarity": 681.6410314114734
          },
          {
            "metadata": {
              "doc_id": "78",
              "name": "Improper Neutralization of Special Elements used in an OS Command ('OS Command Injection')",
              "source": "sparse",
              "original_content": "The product constructs all or part of an OS command using externally-influenced input from an upstream component, but it does not neutralize or incorrectly neutralizes special elements that could modify the intended OS command when it is sent to a downstream component."
            },
            "similarity": 681.0443132807444
          },
          {
            "metadata": {
              "doc_id": "287",
              "name": "Improper Authentication",
              "source": "sparse",
              "original_content": "When an actor claims to have a given identity, the product does not prove or insufficiently proves that the claim is correct.",
              "keyphrase_sources": [
                {
                  "id": "rootcause:insufficient input validation",
                  "keyphrase": "insufficient input validation",
                  "type": "rootcause"
                }
              ]
            },
            "similarity": 673.4854246872175
          }
        ]
      },
      "impact:access sensitive information": {
        "keyphrase": "access sensitive information",
        "type": "impact",
        "cwes": [
          {
            "metadata": {
              "doc_id": "798",
              "name": "Use of Hard-coded Credentials",
              "source": "sparse",
              "original_content": "The product contains hard-coded credentials, such as a password or cryptographic key."
            },
            "similarity": 244.30953597204464
          },
          {
            "metadata": {
              "doc_id": "20",
              "name": "Improper Input Validation",
              "source": "sparse",
              "original_content": "The product receives input or data, but it does\n        not validate or incorrectly validates that the input has the\n        properties that are required to process the data safely and\n        correctly."
            },
            "similarity": 241.3890472973052
          },
          {
            "metadata": {
              "doc_id": "284",
              "name": "Improper Access Control",
              "source": "sparse",
              "original_content": "The product does not restrict or incorrectly restricts access to a resource from an unauthorized actor."
            },
            "similarity": 233.56412935246323
          },
          {
            "metadata": {
              "doc_id": "532",
              "name": "Insertion of Sensitive Information into Log File",
              "source": "sparse",
              "original_content": "The product writes sensitive information to a log file.",
              "keyphrase_sources": [
                {
                  "id": "impact:access sensitive information",
                  "keyphrase": "access sensitive information",
                  "type": "impact"
                }
              ]
            },
            "similarity": 230.42988156317938
          },
          {
            "metadata": {
              "doc_id": "269",
              "name": "Improper Privilege Management",
              "source": "sparse",
              "original_content": "The product does not properly assign, modify, track, or check privileges for an actor, creating an unintended sphere of control for that actor.",
              "keyphrase_sources": [
                {
                  "id": "impact:access sensitive information",
                  "keyphrase": "access sensitive information",
                  "type": "impact"
                },
                {
                  "id": "attacker:authenticated local attacker",
                  "keyphrase": "authenticated local attacker",
                  "type": "attacker"
                },
                {
                  "id": "product:Cisco Desk Phone 9800 Series",
                  "keyphrase": "Cisco Desk Phone 9800 Series",
                  "type": "product"
                },
                {
                  "id": "product:Cisco Video Phone 8875",
                  "keyphrase": "Cisco Video Phone 8875",
                  "type": "product"
                }
              ]
            },
            "similarity": 230.1406217033529
          }
        ]
      },
      "vector:crafted SSH client command": {
        "keyphrase": "crafted SSH client command",
        "type": "vector",
        "cwes": [
          {
            "metadata": {
              "doc_id": "20",
              "name": "Improper Input Validation",
              "source": "sparse",
              "original_content": "The product receives input or data, but it does\n        not validate or incorrectly validates that the input has the\n        properties that are required to process the data safely and\n        correctly."
            },
            "similarity": 244.77098849402896
          },
          {
            "metadata": {
              "doc_id": "798",
              "name": "Use of Hard-coded Credentials",
              "source": "sparse",
              "original_content": "The product contains hard-coded credentials, such as a password or cryptographic key."
            },
            "similarity": 241.73227243567933
          },
          {
            "metadata": {
              "doc_id": "78",
              "name": "Improper Neutralization of Special Elements used in an OS Command ('OS Command Injection')",
              "source": "sparse",
              "original_content": "The product constructs all or part of an OS command using externally-influenced input from an upstream component, but it does not neutralize or incorrectly neutralizes special elements that could modify the intended OS command when it is sent to a downstream component."
            },
            "similarity": 237.27577785081243
          },
          {
            "metadata": {
              "doc_id": "321",
              "name": "Use of Hard-coded Cryptographic Key",
              "source": "sparse",
              "original_content": "The use of a hard-coded cryptographic key significantly increases the possibility that encrypted data may be recovered.",
              "keyphrase_sources": [
                {
                  "id": "vector:crafted SSH client command",
                  "keyphrase": "crafted SSH client command",
                  "type": "vector"
                },
                {
                  "id": "product:Cisco Video Phone 8875",
                  "keyphrase": "Cisco Video Phone 8875",
                  "type": "product"
                },
                {
                  "id": "component:debug shell",
                  "keyphrase": "debug shell",
                  "type": "component"
                }
              ]
            },
            "similarity": 231.97449090034797
          },
          {
            "metadata": {
              "doc_id": "250",
              "name": "Execution with Unnecessary Privileges",
              "source": "sparse",
              "original_content": "The product performs an operation at a privilege level that is higher than the minimum level required, which creates new weaknesses or amplifies the consequences of other weaknesses.",
              "keyphrase_sources": [
                {
                  "id": "vector:crafted SSH client command",
                  "keyphrase": "crafted SSH client command",
                  "type": "vector"
                }
              ]
            },
            "similarity": 230.9804731495117
          }
        ]
      },
      "attacker:authenticated local attacker": {
        "keyphrase": "authenticated local attacker",
        "type": "attacker",
        "cwes": [
          {
            "metadata": {
              "doc_id": "20",
              "name": "Improper Input Validation",
              "source": "sparse",
              "original_content": "The product receives input or data, but it does\n        not validate or incorrectly validates that the input has the\n        properties that are required to process the data safely and\n        correctly."
            },
            "similarity": 248.68310449118556
          },
          {
            "metadata": {
              "doc_id": "798",
              "name": "Use of Hard-coded Credentials",
              "source": "sparse",
              "original_content": "The product contains hard-coded credentials, such as a password or cryptographic key."
            },
            "similarity": 242.72353838878522
          },
          {
            "metadata": {
              "doc_id": "284",
              "name": "Improper Access Control",
              "source": "sparse",
              "original_content": "The product does not restrict or incorrectly restricts access to a resource from an unauthorized actor."
            },
            "similarity": 237.30838492720267
          },
          {
            "metadata": {
              "doc_id": "269",
              "name": "Improper Privilege Management",
              "source": "sparse",
              "original_content": "The product does not properly assign, modify, track, or check privileges for an actor, creating an unintended sphere of control for that actor."
            },
            "similarity": 235.83695383785647
          },
          {
            "metadata": {
              "doc_id": "78",
              "name": "Improper Neutralization of Special Elements used in an OS Command ('OS Command Injection')",
              "source": "sparse",
              "original_content": "The product constructs all or part of an OS command using externally-influenced input from an upstream component, but it does not neutralize or incorrectly neutralizes special elements that could modify the intended OS command when it is sent to a downstream component."
            },
            "similarity": 234.5835728876601
          }
        ]
      },
      "product:Cisco Desk Phone 9800 Series": {
        "keyphrase": "Cisco Desk Phone 9800 Series",
        "type": "product",
        "cwes": [
          {
            "metadata": {
              "doc_id": "20",
              "name": "Improper Input Validation",
              "source": "sparse",
              "original_content": "The product receives input or data, but it does\n        not validate or incorrectly validates that the input has the\n        properties that are required to process the data safely and\n        correctly."
            },
            "similarity": 248.57792401521974
          },
          {
            "metadata": {
              "doc_id": "798",
              "name": "Use of Hard-coded Credentials",
              "source": "sparse",
              "original_content": "The product contains hard-coded credentials, such as a password or cryptographic key."
            },
            "similarity": 245.4050689534657
          },
          {
            "metadata": {
              "doc_id": "284",
              "name": "Improper Access Control",
              "source": "sparse",
              "original_content": "The product does not restrict or incorrectly restricts access to a resource from an unauthorized actor."
            },
            "similarity": 234.18267767916808
          },
          {
            "metadata": {
              "doc_id": "269",
              "name": "Improper Privilege Management",
              "source": "sparse",
              "original_content": "The product does not properly assign, modify, track, or check privileges for an actor, creating an unintended sphere of control for that actor."
            },
            "similarity": 230.1691379349803
          },
          {
            "metadata": {
              "doc_id": "78",
              "name": "Improper Neutralization of Special Elements used in an OS Command ('OS Command Injection')",
              "source": "sparse",
              "original_content": "The product constructs all or part of an OS command using externally-influenced input from an upstream component, but it does not neutralize or incorrectly neutralizes special elements that could modify the intended OS command when it is sent to a downstream component."
            },
            "similarity": 229.95848365170085
          }
        ]
      },
      "product:Cisco Video Phone 8875": {
        "keyphrase": "Cisco Video Phone 8875",
        "type": "product",
        "cwes": [
          {
            "metadata": {
              "doc_id": "20",
              "name": "Improper Input Validation",
              "source": "sparse",
              "original_content": "The product receives input or data, but it does\n        not validate or incorrectly validates that the input has the\n        properties that are required to process the data safely and\n        correctly."
            },
            "similarity": 243.4181797386257
          },
          {
            "metadata": {
              "doc_id": "798",
              "name": "Use of Hard-coded Credentials",
              "source": "sparse",
              "original_content": "The product contains hard-coded credentials, such as a password or cryptographic key."
            },
            "similarity": 239.2933812651158
          },
          {
            "metadata": {
              "doc_id": "269",
              "name": "Improper Privilege Management",
              "source": "sparse",
              "original_content": "The product does not properly assign, modify, track, or check privileges for an actor, creating an unintended sphere of control for that actor."
            },
            "similarity": 233.22415329450803
          },
          {
            "metadata": {
              "doc_id": "284",
              "name": "Improper Access Control",
              "source": "sparse",
              "original_content": "The product does not restrict or incorrectly restricts access to a resource from an unauthorized actor."
            },
            "similarity": 232.26196903632217
          },
          {
            "metadata": {
              "doc_id": "321",
              "name": "Use of Hard-coded Cryptographic Key",
              "source": "sparse",
              "original_content": "The use of a hard-coded cryptographic key significantly increases the possibility that encrypted data may be recovered."
            },
            "similarity": 230.4589379040563
          }
        ]
      },
      "component:debug shell": {
        "keyphrase": "debug shell",
        "type": "component",
        "cwes": [
          {
            "metadata": {
              "doc_id": "798",
              "name": "Use of Hard-coded Credentials",
              "source": "sparse",
              "original_content": "The product contains hard-coded credentials, such as a password or cryptographic key."
            },
            "similarity": 245.10320513445893
          },
          {
            "metadata": {
              "doc_id": "20",
              "name": "Improper Input Validation",
              "source": "sparse",
              "original_content": "The product receives input or data, but it does\n        not validate or incorrectly validates that the input has the\n        properties that are required to process the data safely and\n        correctly."
            },
            "similarity": 234.2465556231643
          },
          {
            "metadata": {
              "doc_id": "78",
              "name": "Improper Neutralization of Special Elements used in an OS Command ('OS Command Injection')",
              "source": "sparse",
              "original_content": "The product constructs all or part of an OS command using externally-influenced input from an upstream component, but it does not neutralize or incorrectly neutralizes special elements that could modify the intended OS command when it is sent to a downstream component."
            },
            "similarity": 230.6333276104344
          },
          {
            "metadata": {
              "doc_id": "321",
              "name": "Use of Hard-coded Cryptographic Key",
              "source": "sparse",
              "original_content": "The use of a hard-coded cryptographic key significantly increases the possibility that encrypted data may be recovered."
            },
            "similarity": 226.26439386692545
          },
          {
            "metadata": {
              "doc_id": "284",
              "name": "Improper Access Control",
              "source": "sparse",
              "original_content": "The product does not restrict or incorrectly restricts access to a resource from an unauthorized actor."
            },
            "similarity": 224.88898984871093
          }
        ]
      }
    },
    "keyphrase_mapping": {
      "20": [
        {
          "id": "rootcause:insufficient validation of user-supplied input",
          "keyphrase": "insufficient validation of user-supplied input",
          "type": "rootcause"
        },
        {
          "id": "rootcause:insufficient input validation",
          "keyphrase": "insufficient input validation",
          "type": "rootcause"
        },
        {
          "id": "impact:access sensitive information",
          "keyphrase": "access sensitive information",
          "type": "impact"
        },
        {
          "id": "vector:crafted SSH client command",
          "keyphrase": "crafted SSH client command",
          "type": "vector"
        },
        {
          "id": "attacker:authenticated local attacker",
          "keyphrase": "authenticated local attacker",
          "type": "attacker"
        },
        {
          "id": "product:Cisco Desk Phone 9800 Series",
          "keyphrase": "Cisco Desk Phone 9800 Series",
          "type": "product"
        },
        {
          "id": "product:Cisco Video Phone 8875",
          "keyphrase": "Cisco Video Phone 8875",
          "type": "product"
        },
        {
          "id": "component:debug shell",
          "keyphrase": "debug shell",
          "type": "component"
        }
      ],
      "798": [
        {
          "id": "rootcause:insufficient validation of user-supplied input",
          "keyphrase": "insufficient validation of user-supplied input",
          "type": "rootcause"
        },
        {
          "id": "rootcause:insufficient input validation",
          "keyphrase": "insufficient input validation",
          "type": "rootcause"
        },
        {
          "id": "impact:access sensitive information",
          "keyphrase": "access sensitive information",
          "type": "impact"
        },
        {
          "id": "vector:crafted SSH client command",
          "keyphrase": "crafted SSH client command",
          "type": "vector"
        },
        {
          "id": "attacker:authenticated local attacker",
          "keyphrase": "authenticated local attacker",
          "type": "attacker"
        },
        {
          "id": "product:Cisco Desk Phone 9800 Series",
          "keyphrase": "Cisco Desk Phone 9800 Series",
          "type": "product"
        },
        {
          "id": "product:Cisco Video Phone 8875",
          "keyphrase": "Cisco Video Phone 8875",
          "type": "product"
        },
        {
          "id": "component:debug shell",
          "keyphrase": "debug shell",
          "type": "component"
        }
      ],
      "78": [
        {
          "id": "rootcause:insufficient validation of user-supplied input",
          "keyphrase": "insufficient validation of user-supplied input",
          "type": "rootcause"
        },
        {
          "id": "rootcause:insufficient input validation",
          "keyphrase": "insufficient input validation",
          "type": "rootcause"
        },
        {
          "id": "vector:crafted SSH client command",
          "keyphrase": "crafted SSH client command",
          "type": "vector"
        },
        {
          "id": "attacker:authenticated local attacker",
          "keyphrase": "authenticated local attacker",
          "type": "attacker"
        },
        {
          "id": "product:Cisco Desk Phone 9800 Series",
          "keyphrase": "Cisco Desk Phone 9800 Series",
          "type": "product"
        },
        {
          "id": "component:debug shell",
          "keyphrase": "debug shell",
          "type": "component"
        }
      ],
      "284": [
        {
          "id": "rootcause:insufficient validation of user-supplied input",
          "keyphrase": "insufficient validation of user-supplied input",
          "type": "rootcause"
        },
        {
          "id": "rootcause:insufficient input validation",
          "keyphrase": "insufficient input validation",
          "type": "rootcause"
        },
        {
          "id": "impact:access sensitive information",
          "keyphrase": "access sensitive information",
          "type": "impact"
        },
        {
          "id": "attacker:authenticated local attacker",
          "keyphrase": "authenticated local attacker",
          "type": "attacker"
        },
        {
          "id": "product:Cisco Desk Phone 9800 Series",
          "keyphrase": "Cisco Desk Phone 9800 Series",
          "type": "product"
        },
        {
          "id": "product:Cisco Video Phone 8875",
          "keyphrase": "Cisco Video Phone 8875",
          "type": "product"
        },
        {
          "id": "component:debug shell",
          "keyphrase": "debug shell",
          "type": "component"
        }
      ],
      "138": [
        {
          "id": "rootcause:insufficient validation of user-supplied input",
          "keyphrase": "insufficient validation of user-supplied input",
          "type": "rootcause"
        }
      ],
      "287": [
        {
          "id": "rootcause:insufficient input validation",
          "keyphrase": "insufficient input validation",
          "type": "rootcause"
        }
      ],
      "532": [
        {
          "id": "impact:access sensitive information",
          "keyphrase": "access sensitive information",
          "type": "impact"
        }
      ],
      "269": [
        {
          "id": "impact:access sensitive information",
          "keyphrase": "access sensitive information",
          "type": "impact"
        },
        {
          "id": "attacker:authenticated local attacker",
          "keyphrase": "authenticated local attacker",
          "type": "attacker"
        },
        {
          "id": "product:Cisco Desk Phone 9800 Series",
          "keyphrase": "Cisco Desk Phone 9800 Series",
          "type": "product"
        },
        {
          "id": "product:Cisco Video Phone 8875",
          "keyphrase": "Cisco Video Phone 8875",
          "type": "product"
        }
      ],
      "321": [
        {
          "id": "vector:crafted SSH client command",
          "keyphrase": "crafted SSH client command",
          "type": "vector"
        },
        {
          "id": "product:Cisco Video Phone 8875",
          "keyphrase": "Cisco Video Phone 8875",
          "type": "product"
        },
        {
          "id": "component:debug shell",
          "keyphrase": "debug shell",
          "type": "component"
        }
      ],
      "250": [
        {
          "id": "vector:crafted SSH client command",
          "keyphrase": "crafted SSH client command",
          "type": "vector"
        }
      ]
    },
    "relevant_cwes": [
      {
        "metadata": {
          "doc_id": "20",
          "name": "Improper Input Validation",
          "source": "sparse",
          "original_content": "The product receives input or data, but it does\n        not validate or incorrectly validates that the input has the\n        properties that are required to process the data safely and\n        correctly.",
          "keyphrase_sources": [
            {
              "id": "rootcause:insufficient validation of user-supplied input",
              "keyphrase": "insufficient validation of user-supplied input",
              "type": "rootcause"
            },
            {
              "id": "rootcause:insufficient input validation",
              "keyphrase": "insufficient input validation",
              "type": "rootcause"
            },
            {
              "id": "impact:access sensitive information",
              "keyphrase": "access sensitive information",
              "type": "impact"
            },
            {
              "id": "vector:crafted SSH client command",
              "keyphrase": "crafted SSH client command",
              "type": "vector"
            },
            {
              "id": "attacker:authenticated local attacker",
              "keyphrase": "authenticated local attacker",
              "type": "attacker"
            },
            {
              "id": "product:Cisco Desk Phone 9800 Series",
              "keyphrase": "Cisco Desk Phone 9800 Series",
              "type": "product"
            },
            {
              "id": "product:Cisco Video Phone 8875",
              "keyphrase": "Cisco Video Phone 8875",
              "type": "product"
            },
            {
              "id": "component:debug shell",
              "keyphrase": "debug shell",
              "type": "component"
            }
          ]
        },
        "similarity": 792.832826414002
      },
      {
        "metadata": {
          "doc_id": "798",
          "name": "Use of Hard-coded Credentials",
          "source": "sparse",
          "original_content": "The product contains hard-coded credentials, such as a password or cryptographic key.",
          "keyphrase_sources": [
            {
              "id": "rootcause:insufficient validation of user-supplied input",
              "keyphrase": "insufficient validation of user-supplied input",
              "type": "rootcause"
            },
            {
              "id": "rootcause:insufficient input validation",
              "keyphrase": "insufficient input validation",
              "type": "rootcause"
            },
            {
              "id": "impact:access sensitive information",
              "keyphrase": "access sensitive information",
              "type": "impact"
            },
            {
              "id": "vector:crafted SSH client command",
              "keyphrase": "crafted SSH client command",
              "type": "vector"
            },
            {
              "id": "attacker:authenticated local attacker",
              "keyphrase": "authenticated local attacker",
              "type": "attacker"
            },
            {
              "id": "product:Cisco Desk Phone 9800 Series",
              "keyphrase": "Cisco Desk Phone 9800 Series",
              "type": "product"
            },
            {
              "id": "product:Cisco Video Phone 8875",
              "keyphrase": "Cisco Video Phone 8875",
              "type": "product"
            },
            {
              "id": "component:debug shell",
              "keyphrase": "debug shell",
              "type": "component"
            }
          ]
        },
        "similarity": 723.3066169403913
      },
      {
        "metadata": {
          "doc_id": "78",
          "name": "Improper Neutralization of Special Elements used in an OS Command ('OS Command Injection')",
          "source": "sparse",
          "original_content": "The product constructs all or part of an OS command using externally-influenced input from an upstream component, but it does not neutralize or incorrectly neutralizes special elements that could modify the intended OS command when it is sent to a downstream component.",
          "keyphrase_sources": [
            {
              "id": "rootcause:insufficient validation of user-supplied input",
              "keyphrase": "insufficient validation of user-supplied input",
              "type": "rootcause"
            },
            {
              "id": "rootcause:insufficient input validation",
              "keyphrase": "insufficient input validation",
              "type": "rootcause"
            },
            {
              "id": "vector:crafted SSH client command",
              "keyphrase": "crafted SSH client command",
              "type": "vector"
            },
            {
              "id": "attacker:authenticated local attacker",
              "keyphrase": "authenticated local attacker",
              "type": "attacker"
            },
            {
              "id": "product:Cisco Desk Phone 9800 Series",
              "keyphrase": "Cisco Desk Phone 9800 Series",
              "type": "product"
            },
            {
              "id": "component:debug shell",
              "keyphrase": "debug shell",
              "type": "component"
            }
          ]
        },
        "similarity": 706.0319254076163
      },
      {
        "metadata": {
          "doc_id": "284",
          "name": "Improper Access Control",
          "source": "sparse",
          "original_content": "The product does not restrict or incorrectly restricts access to a resource from an unauthorized actor.",
          "keyphrase_sources": [
            {
              "id": "rootcause:insufficient validation of user-supplied input",
              "keyphrase": "insufficient validation of user-supplied input",
              "type": "rootcause"
            },
            {
              "id": "rootcause:insufficient input validation",
              "keyphrase": "insufficient input validation",
              "type": "rootcause"
            },
            {
              "id": "impact:access sensitive information",
              "keyphrase": "access sensitive information",
              "type": "impact"
            },
            {
              "id": "attacker:authenticated local attacker",
              "keyphrase": "authenticated local attacker",
              "type": "attacker"
            },
            {
              "id": "product:Cisco Desk Phone 9800 Series",
              "keyphrase": "Cisco Desk Phone 9800 Series",
              "type": "product"
            },
            {
              "id": "product:Cisco Video Phone 8875",
              "keyphrase": "Cisco Video Phone 8875",
              "type": "product"
            },
            {
              "id": "component:debug shell",
              "keyphrase": "debug shell",
              "type": "component"
            }
          ]
        },
        "similarity": 703.7173455493453
      },
      {
        "metadata": {
          "doc_id": "138",
          "name": "Improper Neutralization of Special Elements",
          "source": "sparse",
          "original_content": "The product receives input from an upstream component, but it does not neutralize or incorrectly neutralizes special elements that could be interpreted as control elements or syntactic markers when they are sent to a downstream component.",
          "keyphrase_sources": [
            {
              "id": "rootcause:insufficient validation of user-supplied input",
              "keyphrase": "insufficient validation of user-supplied input",
              "type": "rootcause"
            }
          ]
        },
        "similarity": 699.6990006515691
      },
      {
        "metadata": {
          "doc_id": "287",
          "name": "Improper Authentication",
          "source": "sparse",
          "original_content": "When an actor claims to have a given identity, the product does not prove or insufficiently proves that the claim is correct.",
          "keyphrase_sources": [
            {
              "id": "rootcause:insufficient input validation",
              "keyphrase": "insufficient input validation",
              "type": "rootcause"
            }
          ]
        },
        "similarity": 673.4854246872175
      },
      {
        "metadata": {
          "doc_id": "321",
          "name": "Use of Hard-coded Cryptographic Key",
          "source": "sparse",
          "original_content": "The use of a hard-coded cryptographic key significantly increases the possibility that encrypted data may be recovered.",
          "keyphrase_sources": [
            {
              "id": "vector:crafted SSH client command",
              "keyphrase": "crafted SSH client command",
              "type": "vector"
            },
            {
              "id": "product:Cisco Video Phone 8875",
              "keyphrase": "Cisco Video Phone 8875",
              "type": "product"
            },
            {
              "id": "component:debug shell",
              "keyphrase": "debug shell",
              "type": "component"
            }
          ]
        },
        "similarity": 231.97449090034797
      },
      {
        "metadata": {
          "doc_id": "250",
          "name": "Execution with Unnecessary Privileges",
          "source": "sparse",
          "original_content": "The product performs an operation at a privilege level that is higher than the minimum level required, which creates new weaknesses or amplifies the consequences of other weaknesses.",
          "keyphrase_sources": [
            {
              "id": "vector:crafted SSH client command",
              "keyphrase": "crafted SSH client command",
              "type": "vector"
            }
          ]
        },
        "similarity": 230.9804731495117
      },
      {
        "metadata": {
          "doc_id": "532",
          "name": "Insertion of Sensitive Information into Log File",
          "source": "sparse",
          "original_content": "The product writes sensitive information to a log file.",
          "keyphrase_sources": [
            {
              "id": "impact:access sensitive information",
              "keyphrase": "access sensitive information",
              "type": "impact"
            }
          ]
        },
        "similarity": 230.42988156317938
      },
      {
        "metadata": {
          "doc_id": "269",
          "name": "Improper Privilege Management",
          "source": "sparse",
          "original_content": "The product does not properly assign, modify, track, or check privileges for an actor, creating an unintended sphere of control for that actor.",
          "keyphrase_sources": [
            {
              "id": "impact:access sensitive information",
              "keyphrase": "access sensitive information",
              "type": "impact"
            },
            {
              "id": "attacker:authenticated local attacker",
              "keyphrase": "authenticated local attacker",
              "type": "attacker"
            },
            {
              "id": "product:Cisco Desk Phone 9800 Series",
              "keyphrase": "Cisco Desk Phone 9800 Series",
              "type": "product"
            },
            {
              "id": "product:Cisco Video Phone 8875",
              "keyphrase": "Cisco Video Phone 8875",
              "type": "product"
            }
          ]
        },
        "similarity": 230.1406217033529
      }
    ],
    "enhanced_query": "# Vulnerability Description\n\n    A vulnerability in the debug shell of Cisco Video Phone 8875 and Cisco Desk Phone 9800 Series could allow an authenticated, local attacker to access sensitive information on an affected device. To exploit this vulnerability, the attacker must have valid administrative credentials with SSH access on the affected device. SSH access is disabled by default. This vulnerability is due to **insufficient validation of user-supplied input** by the debug shell of an affected device. An attacker could exploit this vulnerability by sending a crafted SSH client command to the CLI. A successful exploit could allow the attacker to access sensitive information on the underlying operating system.\n\n    # Keyphrase-Specific CWE Analysis\n    This vulnerability contains multiple keyphrases that may map to different CWEs. \n    Please analyze each keyphrase separately and determine the most appropriate CWE(s) for each.\n\n    ## ROOTCAUSE: 'insufficient validation of user-supplied input'\n\nRelevant CWEs for this ROOTCAUSE:\n\n### 1. CWE-20: Improper Input Validation (Score: 792.83)\n\nThe product receives input or data, but it does\n        not validate or incorrectly validates that the input has the\n        properties that are required to process the data safely and\n        correctly....\n\n### 2. CWE-798: Use of Hard-coded Credentials (Score: 723.31)\n\nThe product contains hard-coded credentials, such as a password or cryptographic key....\n\n### 3. CWE-78: Improper Neutralization of Special Elements used in an OS Command ('OS Command Injection') (Score: 706.03)\n\nThe product constructs all or part of an OS command using externally-influenced input from an upstream component, but it does not neutralize or incorrectly neutralizes special elements that could modify the intended OS command when it is sent to a downstream component....\n\n### 4. CWE-284: Improper Access Control (Score: 703.72)\n\nThe product does not restrict or incorrectly restricts access to a resource from an unauthorized actor....\n\n### 5. CWE-138: Improper Neutralization of Special Elements (Score: 699.70)\n\nThe product receives input from an upstream component, but it does not neutralize or incorrectly neutralizes special elements that could be interpreted as control elements or syntactic markers when they are sent to a downstream component....\n\n## ROOTCAUSE: 'insufficient input validation'\n\nRelevant CWEs for this ROOTCAUSE:\n\n### 1. CWE-20: Improper Input Validation (Score: 792.83)\n\nThe product receives input or data, but it does\n        not validate or incorrectly validates that the input has the\n        properties that are required to process the data safely and\n        correctly....\n\n### 2. CWE-798: Use of Hard-coded Credentials (Score: 723.31)\n\nThe product contains hard-coded credentials, such as a password or cryptographic key....\n\n### 3. CWE-78: Improper Neutralization of Special Elements used in an OS Command ('OS Command Injection') (Score: 706.03)\n\nThe product constructs all or part of an OS command using externally-influenced input from an upstream component, but it does not neutralize or incorrectly neutralizes special elements that could modify the intended OS command when it is sent to a downstream component....\n\n### 4. CWE-284: Improper Access Control (Score: 703.72)\n\nThe product does not restrict or incorrectly restricts access to a resource from an unauthorized actor....\n\n### 5. CWE-287: Improper Authentication (Score: 673.49)\n\nWhen an actor claims to have a given identity, the product does not prove or insufficiently proves that the claim is correct....\n\n## IMPACT: 'access sensitive information'\n\nRelevant CWEs for this IMPACT:\n\n### 1. CWE-20: Improper Input Validation (Score: 792.83)\n\nThe product receives input or data, but it does\n        not validate or incorrectly validates that the input has the\n        properties that are required to process the data safely and\n        correctly....\n\n### 2. CWE-798: Use of Hard-coded Credentials (Score: 723.31)\n\nThe product contains hard-coded credentials, such as a password or cryptographic key....\n\n### 3. CWE-284: Improper Access Control (Score: 703.72)\n\nThe product does not restrict or incorrectly restricts access to a resource from an unauthorized actor....\n\n### 4. CWE-532: Insertion of Sensitive Information into Log File (Score: 230.43)\n\nThe product writes sensitive information to a log file....\n\n### 5. CWE-269: Improper Privilege Management (Score: 230.14)\n\nThe product does not properly assign, modify, track, or check privileges for an actor, creating an unintended sphere of control for that actor....\n\n## VECTOR: 'crafted SSH client command'\n\nRelevant CWEs for this VECTOR:\n\n### 1. CWE-20: Improper Input Validation (Score: 792.83)\n\nThe product receives input or data, but it does\n        not validate or incorrectly validates that the input has the\n        properties that are required to process the data safely and\n        correctly....\n\n### 2. CWE-798: Use of Hard-coded Credentials (Score: 723.31)\n\nThe product contains hard-coded credentials, such as a password or cryptographic key....\n\n### 3. CWE-78: Improper Neutralization of Special Elements used in an OS Command ('OS Command Injection') (Score: 706.03)\n\nThe product constructs all or part of an OS command using externally-influenced input from an upstream component, but it does not neutralize or incorrectly neutralizes special elements that could modify the intended OS command when it is sent to a downstream component....\n\n### 4. CWE-321: Use of Hard-coded Cryptographic Key (Score: 231.97)\n\nThe use of a hard-coded cryptographic key significantly increases the possibility that encrypted data may be recovered....\n\n### 5. CWE-250: Execution with Unnecessary Privileges (Score: 230.98)\n\nThe product performs an operation at a privilege level that is higher than the minimum level required, which creates new weaknesses or amplifies the consequences of other weaknesses....\n\n## ATTACKER: 'authenticated local attacker'\n\nRelevant CWEs for this ATTACKER:\n\n### 1. CWE-20: Improper Input Validation (Score: 792.83)\n\nThe product receives input or data, but it does\n        not validate or incorrectly validates that the input has the\n        properties that are required to process the data safely and\n        correctly....\n\n### 2. CWE-798: Use of Hard-coded Credentials (Score: 723.31)\n\nThe product contains hard-coded credentials, such as a password or cryptographic key....\n\n### 3. CWE-78: Improper Neutralization of Special Elements used in an OS Command ('OS Command Injection') (Score: 706.03)\n\nThe product constructs all or part of an OS command using externally-influenced input from an upstream component, but it does not neutralize or incorrectly neutralizes special elements that could modify the intended OS command when it is sent to a downstream component....\n\n### 4. CWE-284: Improper Access Control (Score: 703.72)\n\nThe product does not restrict or incorrectly restricts access to a resource from an unauthorized actor....\n\n### 5. CWE-269: Improper Privilege Management (Score: 230.14)\n\nThe product does not properly assign, modify, track, or check privileges for an actor, creating an unintended sphere of control for that actor....\n\n## PRODUCT: 'Cisco Desk Phone 9800 Series'\n\nRelevant CWEs for this PRODUCT:\n\n### 1. CWE-20: Improper Input Validation (Score: 792.83)\n\nThe product receives input or data, but it does\n        not validate or incorrectly validates that the input has the\n        properties that are required to process the data safely and\n        correctly....\n\n### 2. CWE-798: Use of Hard-coded Credentials (Score: 723.31)\n\nThe product contains hard-coded credentials, such as a password or cryptographic key....\n\n### 3. CWE-78: Improper Neutralization of Special Elements used in an OS Command ('OS Command Injection') (Score: 706.03)\n\nThe product constructs all or part of an OS command using externally-influenced input from an upstream component, but it does not neutralize or incorrectly neutralizes special elements that could modify the intended OS command when it is sent to a downstream component....\n\n### 4. CWE-284: Improper Access Control (Score: 703.72)\n\nThe product does not restrict or incorrectly restricts access to a resource from an unauthorized actor....\n\n### 5. CWE-269: Improper Privilege Management (Score: 230.14)\n\nThe product does not properly assign, modify, track, or check privileges for an actor, creating an unintended sphere of control for that actor....\n\n## PRODUCT: 'Cisco Video Phone 8875'\n\nRelevant CWEs for this PRODUCT:\n\n### 1. CWE-20: Improper Input Validation (Score: 792.83)\n\nThe product receives input or data, but it does\n        not validate or incorrectly validates that the input has the\n        properties that are required to process the data safely and\n        correctly....\n\n### 2. CWE-798: Use of Hard-coded Credentials (Score: 723.31)\n\nThe product contains hard-coded credentials, such as a password or cryptographic key....\n\n### 3. CWE-284: Improper Access Control (Score: 703.72)\n\nThe product does not restrict or incorrectly restricts access to a resource from an unauthorized actor....\n\n### 4. CWE-321: Use of Hard-coded Cryptographic Key (Score: 231.97)\n\nThe use of a hard-coded cryptographic key significantly increases the possibility that encrypted data may be recovered....\n\n### 5. CWE-269: Improper Privilege Management (Score: 230.14)\n\nThe product does not properly assign, modify, track, or check privileges for an actor, creating an unintended sphere of control for that actor....\n\n## COMPONENT: 'debug shell'\n\nRelevant CWEs for this COMPONENT:\n\n### 1. CWE-20: Improper Input Validation (Score: 792.83)\n\nThe product receives input or data, but it does\n        not validate or incorrectly validates that the input has the\n        properties that are required to process the data safely and\n        correctly....\n\n### 2. CWE-798: Use of Hard-coded Credentials (Score: 723.31)\n\nThe product contains hard-coded credentials, such as a password or cryptographic key....\n\n### 3. CWE-78: Improper Neutralization of Special Elements used in an OS Command ('OS Command Injection') (Score: 706.03)\n\nThe product constructs all or part of an OS command using externally-influenced input from an upstream component, but it does not neutralize or incorrectly neutralizes special elements that could modify the intended OS command when it is sent to a downstream component....\n\n### 4. CWE-284: Improper Access Control (Score: 703.72)\n\nThe product does not restrict or incorrectly restricts access to a resource from an unauthorized actor....\n\n### 5. CWE-321: Use of Hard-coded Cryptographic Key (Score: 231.97)\n\nThe use of a hard-coded cryptographic key significantly increases the possibility that encrypted data may be recovered....\n\n\n    # Analysis Instructions\n    1. For each keyphrase, identify the most appropriate CWE(s) that represent the weakness.\n    2. Consider how the different keyphrases might relate to each other in the vulnerability chain.\n    3. Provide a final determination of primary CWE(s) and any secondary CWEs.\n    4. Format your response using the standard analysis template.\n\n    Please analyze how these different weaknesses interact and provide a comprehensive CWE classification.\n    "
  },
  "retrieval_time": 1.6021819114685059
}