{
  "cve_id": "CVE-2024-45584",
  "description": "Memory corruption can occur when a compat IOCTL call is followed by a normal IOCTL call from userspace.",
  "key_phrases": {
    "rootcause": "",
    "weakness": "memory corruption",
    "impact": "",
    "vector": "",
    "attacker": "",
    "product": "",
    "version": "",
    "component": "compat IOCTL call followed by normal IOCTL call"
  },
  "reference_content": null,
  "similar_info": {
    "cwe_distribution": {},
    "cwe_consensus": "",
    "similarity_stats": {
      "thresholds": [],
      "total_samples_by_threshold": {},
      "top_cwes_by_threshold": {}
    }
  },
  "similarity_summary": {
    "consensus_cwe": "",
    "top_cwes": [],
    "confidence_levels": {},
    "total_samples": 0
  },
  "analysis": "# Summary\n| CWE ID | CWE Name | Confidence | CWE Abstraction Level | CWE Vulnerability Mapping Label | CWE-Vulnerability Mapping Notes |\n|---|---|---|---|---|---|\n| CWE-787 | Out-of-bounds Write | 0.8 | Base | Primary | Allowed |\n| CWE-782 | Exposed IOCTL with Insufficient Access Control | 0.4 | Variant | Secondary | Allowed |\n\n## Evidence and Confidence\n\n*   **Confidence Score:** 0.6\n*   **Evidence Strength:** LOW\n\n## Relationship Analysis\nThe primary relationship considered was the parent-child relationship between CWE-119 (Improper Restriction of Operations within the Bounds of a Memory Buffer) and CWE-787, where CWE-787 is a specific type of out-of-bounds write. The weakness involves memory corruption caused by a specific sequence of IOCTL calls, which hints at a potential issue with access control, motivating the consideration of CWE-782.\n\n```mermaid\ngraph TD\n    cwe787[\"CWE-787: Out-of-bounds Write\"]\n    cwe782[\"CWE-782: Exposed IOCTL with Insufficient Access Control\"]\n    cwe119[\"CWE-119: Improper Restriction of Operations within the Bounds of a Memory Buffer\"]\n    \n    cwe787 -->|CHILDOF| cwe119\n    cwe782 -->|RELATED TO| cwe787\n    \n    classDef primary fill:#f96,stroke:#333,stroke-width:2px\n    classDef secondary fill:#69f,stroke:#333\n    classDef tertiary fill:#9e9,stroke:#333\n    class cwe787 primary\n    class cwe782 secondary\n```\n\n## Vulnerability Chain\nThe vulnerability chain starts with the specific sequence of \"compat IOCTL call followed by normal IOCTL call,\" leading to the root cause of **memory corruption**, which is manifested as an out-of-bounds write.\n\n## Summary of Analysis\nThe initial assessment identified CWE-787 as the primary candidate due to the description of **memory corruption**, which is a strong indicator of out-of-bounds write. The retriever results also listed CWE-787 as the top candidate. However, the vulnerability description mentions that this **memory corruption** occurs due to a \"compat IOCTL call followed by normal IOCTL call from userspace,\" suggesting a potential issue related to exposed IOCTLs with insufficient access control, leading to the consideration of CWE-782.\n\nThe evidence is weak because the description is not detailed enough to pinpoint the exact mechanism causing the **memory corruption**. The selection of CWE-787 is primarily based on the general description of **memory corruption**. The inclusion of CWE-782 is speculative and based on the context of IOCTL calls.\n\nThe selected CWEs are at the base and variant level, respectively, which offers a balance between specificity and coverage of the observed vulnerability.\n\nRelevant CWE Information:\n\n# Enhanced Context (25 CWEs)\nThe following CWEs were identified as potentially relevant to this vulnerability:\n\n## CWE-782: Exposed IOCTL with Insufficient Access Control\n**Abstraction Level**: Variant\n**Similarity Score**: 0.74\n**Source**: dense\n\n**Description**:\nThe product implements an IOCTL with functionality that should be restricted, but it does not properly enforce access control for the IOCTL.\n\n**Mapping Guidance**:\n- Usage: Allowed\n- Rationale: This CWE entry is at the Variant level of abstraction, which is a preferred level of abstraction for mapping to the root causes of vulnerabilities.\n\n## CWE-787: Out-of-bounds Write\n**Abstraction Level**: Base\n**Similarity Score**: 4.33\n**Source**: graph\n\n**Description**:\nCWE-787: Out-of-bounds Write\n\n**Mapping Guidance**:\n- Usage: Allowed\n- Rationale: This CWE entry is at the Base level of abstraction, which is a preferred level of abstraction for mapping to the root causes of vulnerabilities.\n\n**Relationships**:\n- CANFOLLOW -> CWE-825\n- CANFOLLOW -> CWE-824\n- CANFOLLOW -> CWE-823\n- CANFOLLOW -> CWE-822\n- PARENTOF -> CWE-124\n\n**CWE-787: Out-of-bounds Write**\n*   **Technical Explanation:** The vulnerability description explicitly mentions **memory corruption**, which aligns directly with the characteristics of CWE-787 (Out-of-bounds Write). This occurs when data is written outside the intended buffer boundaries.\n*   **Security Implications:** This can lead to arbitrary code execution, denial of service, or information disclosure.\n*   **Relationship Analysis:** CWE-787 is a child of CWE-119 (Improper Restriction of Operations within the Bounds of a Memory Buffer), indicating a more specific instance of a broader class of buffer-related vulnerabilities.\n*   **Mapping Guidance:** The MITRE mapping guidance allows for the use of CWE-787 at the Base level.\n*   **Primary/Secondary:** Primary\n\n**CWE-782: Exposed IOCTL with Insufficient Access Control**\n*   **Technical Explanation:** The vulnerability involves a \"compat IOCTL call followed by normal IOCTL call from userspace.\" This sequence suggests that an IOCTL, which should be restricted, might be accessible due to **insufficient access control**.\n*   **Security Implications:** An attacker could potentially exploit this **insufficient access control** to trigger unintended operations or bypass security mechanisms.\n*   **Relationship Analysis:** There is no direct hierarchical relationship, but the IOCTL context suggests this as a potential contributing factor.\n*   **Mapping Guidance:** The MITRE mapping guidance allows for the use of CWE-782 at the Variant level.\n*   **Primary/Secondary:** Secondary\n\n**CWEs Considered But Not Used:**\n\n*   CWE-131 (Incorrect Calculation of Buffer Size): While a buffer overflow could be the root cause of the **memory corruption**, the description does not provide enough information to confirm this.\n*   CWE-415 (Double Free) and CWE-416 (Use After Free): These are other potential causes of memory corruption, but the description does not point to these specifically.\n*   CWE-823 (Use of Out-of-range Pointer Offset) and CWE-822 (Untrusted Pointer Dereference): These CWEs are related to pointer manipulation, but the description doesn't provide enough detail to determine if they are involved.\n*   CWE-134 (Use of Externally-Controlled Format String): This is unlikely in the context of IOCTL calls.\n*   CWE-394 (Unexpected Status Code or Return Value): The description doesn't focus on status code issues, but rather memory corruption.\n*   CWE-909 (Missing Initialization of Resource): The vulnerability description doesn't indicate missing initialization.\n*   CWE-762 (Mismatched Memory Management Routines): There is no specific evidence of mismatched memory management routines.\n*   CWE-123 (Write-what-where Condition): This is a more specific type of memory corruption, but the description doesn't provide enough information to confirm this.",
  "analysis_with_relationships": "# Summary\n| CWE ID | CWE Name | Confidence | CWE Abstraction Level | CWE Vulnerability Mapping Label | CWE-Vulnerability Mapping Notes |\n|---|---|---|---|---|---|\n| CWE-787 | Out-of-bounds Write | 0.8 | Base | Primary | Allowed |\n| CWE-782 | Exposed IOCTL with Insufficient Access Control | 0.4 | Variant | Secondary | Allowed |\n\n## Evidence and Confidence\n\n*   **Confidence Score:** 0.6\n*   **Evidence Strength:** LOW\n\n## Relationship Analysis\nThe primary relationship considered was the parent-child relationship between CWE-119 (Improper Restriction of Operations within the Bounds of a Memory Buffer) and CWE-787, where CWE-787 is a specific type of out-of-bounds write. The weakness involves memory corruption caused by a specific sequence of IOCTL calls, which hints at a potential issue with access control, motivating the consideration of CWE-782.\n\n```mermaid\ngraph TD\n    cwe787[\"CWE-787: Out-of-bounds Write\"]\n    cwe782[\"CWE-782: Exposed IOCTL with Insufficient Access Control\"]\n    cwe119[\"CWE-119: Improper Restriction of Operations within the Bounds of a Memory Buffer\"]\n    \n    cwe787 -->|CHILDOF| cwe119\n    cwe782 -->|RELATED TO| cwe787\n    \n    classDef primary fill:#f96,stroke:#333,stroke-width:2px\n    classDef secondary fill:#69f,stroke:#333\n    classDef tertiary fill:#9e9,stroke:#333\n    class cwe787 primary\n    class cwe782 secondary\n```\n\n## Vulnerability Chain\nThe vulnerability chain starts with the specific sequence of \"compat IOCTL call followed by normal IOCTL call,\" leading to the root cause of **memory corruption**, which is manifested as an out-of-bounds write.\n\n## Summary of Analysis\nThe initial assessment identified CWE-787 as the primary candidate due to the description of **memory corruption**, which is a strong indicator of out-of-bounds write. The retriever results also listed CWE-787 as the top candidate. However, the vulnerability description mentions that this **memory corruption** occurs due to a \"compat IOCTL call followed by normal IOCTL call from userspace,\" suggesting a potential issue related to exposed IOCTLs with insufficient access control, leading to the consideration of CWE-782.\n\nThe evidence is weak because the description is not detailed enough to pinpoint the exact mechanism causing the **memory corruption**. The selection of CWE-787 is primarily based on the general description of **memory corruption**. The inclusion of CWE-782 is speculative and based on the context of IOCTL calls.\n\nThe selected CWEs are at the base and variant level, respectively, which offers a balance between specificity and coverage of the observed vulnerability.\n\nRelevant CWE Information:\n\n# Enhanced Context (25 CWEs)\nThe following CWEs were identified as potentially relevant to this vulnerability:\n\n## CWE-782: Exposed IOCTL with Insufficient Access Control\n**Abstraction Level**: Variant\n**Similarity Score**: 0.74\n**Source**: dense\n\n**Description**:\nThe product implements an IOCTL with functionality that should be restricted, but it does not properly enforce access control for the IOCTL.\n\n**Mapping Guidance**:\n- Usage: Allowed\n- Rationale: This CWE entry is at the Variant level of abstraction, which is a preferred level of abstraction for mapping to the root causes of vulnerabilities.\n\n## CWE-787: Out-of-bounds Write\n**Abstraction Level**: Base\n**Similarity Score**: 4.33\n**Source**: graph\n\n**Description**:\nCWE-787: Out-of-bounds Write\n\n**Mapping Guidance**:\n- Usage: Allowed\n- Rationale: This CWE entry is at the Base level of abstraction, which is a preferred level of abstraction for mapping to the root causes of vulnerabilities.\n\n**Relationships**:\n- CANFOLLOW -> CWE-825\n- CANFOLLOW -> CWE-824\n- CANFOLLOW -> CWE-823\n- CANFOLLOW -> CWE-822\n- PARENTOF -> CWE-124\n\n**CWE-787: Out-of-bounds Write**\n*   **Technical Explanation:** The vulnerability description explicitly mentions **memory corruption**, which aligns directly with the characteristics of CWE-787 (Out-of-bounds Write). This occurs when data is written outside the intended buffer boundaries.\n*   **Security Implications:** This can lead to arbitrary code execution, denial of service, or information disclosure.\n*   **Relationship Analysis:** CWE-787 is a child of CWE-119 (Improper Restriction of Operations within the Bounds of a Memory Buffer), indicating a more specific instance of a broader class of buffer-related vulnerabilities.\n*   **Mapping Guidance:** The MITRE mapping guidance allows for the use of CWE-787 at the Base level.\n*   **Primary/Secondary:** Primary\n\n**CWE-782: Exposed IOCTL with Insufficient Access Control**\n*   **Technical Explanation:** The vulnerability involves a \"compat IOCTL call followed by normal IOCTL call from userspace.\" This sequence suggests that an IOCTL, which should be restricted, might be accessible due to **insufficient access control**.\n*   **Security Implications:** An attacker could potentially exploit this **insufficient access control** to trigger unintended operations or bypass security mechanisms.\n*   **Relationship Analysis:** There is no direct hierarchical relationship, but the IOCTL context suggests this as a potential contributing factor.\n*   **Mapping Guidance:** The MITRE mapping guidance allows for the use of CWE-782 at the Variant level.\n*   **Primary/Secondary:** Secondary\n\n**CWEs Considered But Not Used:**\n\n*   CWE-131 (Incorrect Calculation of Buffer Size): While a buffer overflow could be the root cause of the **memory corruption**, the description does not provide enough information to confirm this.\n*   CWE-415 (Double Free) and CWE-416 (Use After Free): These are other potential causes of memory corruption, but the description does not point to these specifically.\n*   CWE-823 (Use of Out-of-range Pointer Offset) and CWE-822 (Untrusted Pointer Dereference): These CWEs are related to pointer manipulation, but the description doesn't provide enough detail to determine if they are involved.\n*   CWE-134 (Use of Externally-Controlled Format String): This is unlikely in the context of IOCTL calls.\n*   CWE-394 (Unexpected Status Code or Return Value): The description doesn't focus on status code issues, but rather memory corruption.\n*   CWE-909 (Missing Initialization of Resource): The vulnerability description doesn't indicate missing initialization.\n*   CWE-762 (Mismatched Memory Management Routines): There is no specific evidence of mismatched memory management routines.\n*   CWE-123 (Write-what-where Condition): This is a more specific type of memory corruption, but the description doesn't provide enough information to confirm this.\n\n\n## CWE Relationship Analysis\n\nCurrent CWEs represent these abstraction levels: .\n\n\n### Vulnerability Chain Analysis\n\n**Chain starting from CWE-123:**\n- 123 (Write-what-where Condition) - ROOT\n\n\n**Chain starting from CWE-394:**\n- 394 (Unexpected Status Code or Return Value) - ROOT\n\n\n\n### CWE Relationship Diagram\n\n```mermaid\ngraph TD\n    classDef primary fill:#f96,stroke:#333,stroke-width:2px\n    classDef secondary fill:#69f,stroke:#333\n    classDef tertiary fill:#9e9,stroke:#333\n```",
  "criticism": "",
  "resolution": "",
  "relevant_cwes": [
    {
      "metadata": {
        "doc_id": "787",
        "name": "Out-of-bounds Write",
        "source": "alternate_terms",
        "original_matched_text": "AlternateTerms: Memory Corruption",
        "match_reason": "exact_match_whole_phrase"
      },
      "similarity": 1000.0,
      "alternate_term_match": true
    },
    {
      "metadata": {
        "doc_id": "782",
        "name": "Exposed IOCTL with Insufficient Access Control",
        "source": "sparse"
      },
      "similarity": 142.40461291801955
    },
    {
      "metadata": {
        "doc_id": "394",
        "name": "Unexpected Status Code or Return Value",
        "source": "sparse"
      },
      "similarity": 125.32430027286412
    },
    {
      "metadata": {
        "doc_id": "131",
        "name": "Incorrect Calculation of Buffer Size",
        "source": "sparse"
      },
      "similarity": 124.61135262756629
    },
    {
      "metadata": {
        "doc_id": "909",
        "name": "Missing Initialization of Resource",
        "source": "sparse"
      },
      "similarity": 121.1784211766137
    },
    {
      "metadata": {
        "doc_id": "415",
        "name": "Double Free",
        "source": "sparse"
      },
      "similarity": 119.49567697995785
    },
    {
      "metadata": {
        "doc_id": "822",
        "name": "Untrusted Pointer Dereference",
        "source": "sparse"
      },
      "similarity": 117.59415369919581
    },
    {
      "metadata": {
        "doc_id": "134",
        "name": "Use of Externally-Controlled Format String",
        "source": "sparse"
      },
      "similarity": 117.51573228599277
    },
    {
      "metadata": {
        "doc_id": "762",
        "name": "Mismatched Memory Management Routines",
        "type": "Variant",
        "original_content": "The product attempts to return a memory resource to the system, but it calls a release function that is not compatible with the function that was originally used to allocate that resource.",
        "keyphrase_source": "weakness:memory corruption",
        "source": "dense",
        "mapping_notes": {
          "usage": "Allowed",
          "rationale": "This CWE entry is at the Variant level of abstraction, which is a preferred level of abstraction for mapping to the root causes of vulnerabilities.",
          "comments": "Carefully read both the name and description to ensure that this mapping is an appropriate fit. Do not try to 'force' a mapping to a lower-level Base/Variant simply to comply with this preferred level of abstraction.",
          "reasons": [
            "Acceptable-Use"
          ]
        },
        "score_info": {
          "retrievers": [
            "dense"
          ],
          "retriever_count": 1,
          "normalized_scores": {
            "dense": 0.5421595858741912
          }
        }
      },
      "similarity": 0.5421595858741912
    },
    {
      "doc_id": "123",
      "text": "CWE-123: Write-what-where Condition",
      "score": 2.8651999999999997,
      "metadata": {
        "doc_id": "123",
        "name": "Write-what-where Condition",
        "type": "base",
        "original_content": "CWE-123: Write-what-where Condition",
        "relationships": [
          {
            "source_id": "123",
            "target_id": "590",
            "label": "CANFOLLOW",
            "properties": {
              "view_id": "1000"
            }
          },
          {
            "source_id": "123",
            "target_id": "479",
            "label": "CANFOLLOW",
            "properties": {
              "view_id": "1000"
            }
          },
          {
            "source_id": "123",
            "target_id": "416",
            "label": "CANFOLLOW",
            "properties": {
              "view_id": "1000"
            }
          },
          {
            "source_id": "123",
            "target_id": "364",
            "label": "CANFOLLOW",
            "properties": {
              "view_id": "1000"
            }
          },
          {
            "source_id": "123",
            "target_id": "134",
            "label": "CANFOLLOW",
            "properties": {
              "view_id": "1000"
            }
          },
          {
            "source_id": "123",
            "target_id": "120",
            "label": "CANFOLLOW",
            "properties": {
              "view_id": "1000"
            }
          },
          {
            "source_id": "123",
            "target_id": "119",
            "label": "CHILDOF",
            "properties": {
              "ordinal": "Primary",
              "view_id": "1340"
            }
          },
          {
            "source_id": "123",
            "target_id": "119",
            "label": "CHILDOF",
            "properties": {
              "ordinal": "Primary",
              "view_id": "1305"
            }
          },
          {
            "source_id": "123",
            "target_id": "787",
            "label": "CHILDOF",
            "properties": {
              "ordinal": "Primary",
              "view_id": "1000"
            }
          },
          {
            "source_id": "787",
            "target_id": "123",
            "label": "PARENTOF",
            "properties": {
              "ordinal": "Primary",
              "view_id": "1000"
            }
          },
          {
            "source_id": "590",
            "target_id": "123",
            "label": "CANPRECEDE",
            "properties": {
              "view_id": "1000"
            }
          },
          {
            "source_id": "479",
            "target_id": "123",
            "label": "CANPRECEDE",
            "properties": {
              "view_id": "1000"
            }
          },
          {
            "source_id": "416",
            "target_id": "123",
            "label": "CANPRECEDE",
            "properties": {
              "view_id": "1000"
            }
          },
          {
            "source_id": "415",
            "target_id": "123",
            "label": "PEEROF",
            "properties": {
              "view_id": "1000"
            }
          },
          {
            "source_id": "364",
            "target_id": "123",
            "label": "CANPRECEDE",
            "properties": {
              "view_id": "1000"
            }
          },
          {
            "source_id": "134",
            "target_id": "123",
            "label": "CANPRECEDE",
            "properties": {
              "view_id": "1000"
            }
          },
          {
            "source_id": "120",
            "target_id": "123",
            "label": "CANPRECEDE",
            "properties": {
              "view_id": "1000"
            }
          },
          {
            "source_id": "119",
            "target_id": "123",
            "label": "PARENTOF",
            "properties": {
              "ordinal": "Primary",
              "view_id": "1305"
            }
          }
        ],
        "score_components": {
          "relationship_chain": 1.0,
          "abstraction_path": 0.7200000000000001,
          "sequence_path": 1.0
        },
        "abstraction_factor": 1.3,
        "graph_path_info": {
          "path_types": [
            "relationship_chain",
            "abstraction_path_down",
            "vulnerability_sequence_forward"
          ],
          "best_paths": {
            "relationship_chain": {
              "path": [
                [
                  "590",
                  "123",
                  "CANPRECEDE"
                ]
              ],
              "score": 1.0,
              "type": "relationship_chain",
              "source": "590"
            },
            "abstraction_path_down": {
              "path": [
                [
                  "787",
                  "123",
                  "PARENTOF"
                ]
              ],
              "score": 0.7200000000000001,
              "type": "abstraction_path_down",
              "source": "787"
            },
            "vulnerability_sequence_forward": {
              "path": [
                [
                  "590",
                  "123",
                  "CANPRECEDE"
                ]
              ],
              "score": 1.0,
              "type": "vulnerability_sequence_forward",
              "source": "590"
            }
          }
        },
        "abstraction_level": "base",
        "position": "after",
        "sources": [
          "graph"
        ],
        "source": "graph",
        "mapping_notes": {
          "usage": "Allowed",
          "rationale": "This CWE entry is at the Base level of abstraction, which is a preferred level of abstraction for mapping to the root causes of vulnerabilities.",
          "comments": "Carefully read both the name and description to ensure that this mapping is an appropriate fit. Do not try to 'force' a mapping to a lower-level Base/Variant simply to comply with this preferred level of abstraction.",
          "reasons": [
            "Acceptable-Use"
          ]
        },
        "score_info": {
          "retrievers": [
            "graph"
          ],
          "retriever_count": 1,
          "normalized_scores": {
            "graph": 2.8651999999999997
          }
        }
      },
      "similarity": 2.8651999999999997
    }
  ],
  "identified_cwes": {
    "analyzer": [
      "CWE-123",
      "CWE-394",
      "CWE-416",
      "CWE-823",
      "CWE-131",
      "CWE-787",
      "CWE-762",
      "CWE-909",
      "CWE-124",
      "CWE-825",
      "CWE-782",
      "CWE-822",
      "CWE-824",
      "CWE-119",
      "CWE-134",
      "CWE-415"
    ],
    "critic_additional": []
  },
  "keyphrase_cwe_mapping": {}
}