{
  "cve_id": "CVE-2025-3277",
  "description": "An **integer overflow** can be triggered in SQLites `concat_ws()` function. The resulting, truncated integer is then used to allocate a buffer. When SQLite then writes the resulting string to the buffer, it uses the original, untruncated size and thus a wild Heap **Buffer overflow** of size ~4GB can be triggered. This can result in arbitrary code execution.",
  "key_phrases": {
    "rootcause": "",
    "weakness": [
      "integer overflow",
      "Buffer overflow"
    ],
    "impact": "arbitrary code execution",
    "vector": "",
    "attacker": "",
    "product": "SQLite",
    "version": "",
    "component": "concat_ws() function"
  },
  "reference_content": "The content relates to a fix for a potential 32-bit integer overflow in the `concat_ws()` function of SQLite.\n\n**Root cause of vulnerability:**\nA 32-bit integer overflow can occur in the `concat_ws()` function when dealing with a large separator value and many arguments.\n\n**Weaknesses/vulnerabilities present:**\nInteger overflow.\n\n**Impact of exploitation:**\nThe integer overflow could lead to unexpected behavior or potentially memory issues.\n\n**Attack vectors:**\nProviding a large separator value and a large number of arguments to the `concat_ws()` function.\n\n**Required attacker capabilities/position:**\nAn attacker needs to be able to control the input to the `concat_ws()` function.\n\n**Mitigation or fix:**\nA typecast was added to avoid the 32-bit integer overflow. Specifically, `n += (argc-1)*nSep;` was changed to `n += (argc-1)*(i64)nSep;` to cast `nSep` to a 64-bit integer before multiplication.\n\nThis content provides more detail than the placeholder CVE description.",
  "similar_info": {
    "cwe_distribution": {},
    "cwe_consensus": "",
    "similarity_stats": {
      "thresholds": [],
      "total_samples_by_threshold": {},
      "top_cwes_by_threshold": {}
    }
  },
  "similarity_summary": {
    "consensus_cwe": "",
    "top_cwes": [],
    "confidence_levels": {},
    "total_samples": 0
  },
  "analysis": "```markdown\n# Summary\n| CWE ID    | CWE Name                                                      | Confidence | CWE Abstraction Level | CWE Vulnerability Mapping Label | CWE-Vulnerability Mapping Notes |\n| --------- | ------------------------------------------------------------- | ---------- | --------------------- | ------------------------------- | ------------------------------- |\n| CWE-190   | Integer Overflow or Wraparound                                | 0.9        | Base                  | Primary                         | Allowed                         |\n| CWE-131   | Incorrect Calculation of Buffer Size                          | 0.8        | Base                  | Secondary                       | Allowed                         |\n| CWE-121   | Stack-based Buffer Overflow                                   | 0.7        | Base                  | Secondary                       | Allowed                         |\n| CWE-787   | Out-of-bounds Write                                           | 0.7        | Base                  | Secondary                       | Allowed                         |\n\n## Evidence and Confidence\n\n*   **Confidence Score:** 0.8\n*   **Evidence Strength:** HIGH\n\n## Relationship Analysis\nThe primary weakness is **CWE-190 Integer Overflow or Wraparound**, which leads to **CWE-131 Incorrect Calculation of Buffer Size**. This incorrect size calculation results in a **CWE-787 Out-of-bounds Write** when data larger than the allocated buffer is written. All of these CWEs are at the Base level of abstraction.\n\n```mermaid\ngraph TD\n    cwe190[\"CWE-190: Integer Overflow or Wraparound\"]\n    cwe131[\"CWE-131: Incorrect Calculation of Buffer Size\"]\n    cwe787[\"CWE-787: Out-of-bounds Write\"]\n    cwe121[\"CWE-121: Stack-based Buffer Overflow\"]\n\n    cwe131 -->|CANPRECEDE| cwe787\n    cwe190 -->|CANPRECEDE| cwe131\n    cwe787 --|> cwe121\n\n    classDef primary fill:#f96,stroke:#333,stroke-width:2px\n    classDef secondary fill:#69f,stroke:#333\n    classDef tertiary fill:#9e9,stroke:#333\n    class cwe190 primary\n    class cwe131,cwe787,cwe121 secondary\n```\n\n## Vulnerability Chain\nThe vulnerability chain starts with an **integer overflow (CWE-190)** in the `concat_ws()` function. This overflow leads to an incorrect calculation of the buffer size **(CWE-131)**, resulting in a smaller-than-expected buffer being allocated. When the function attempts to write data based on the original (untruncated) size, it causes an **out-of-bounds write (CWE-787)**, leading to arbitrary code execution.\n\n## Summary of Analysis\nThe analysis is based on the provided evidence, which clearly states that an **integer overflow** in SQLite's `concat_ws()` function results in a truncated integer being used to allocate a buffer. The subsequent write operation, using the original untruncated size, triggers a **buffer overflow**.\n\nThe graph relationships show how the **CWE-190 (Integer Overflow or Wraparound)** leads to **CWE-131 (Incorrect Calculation of Buffer Size)**, which subsequently results in **CWE-787 (Out-of-bounds Write)**.\n\nThe selected CWEs are at the optimal level of specificity, as they accurately represent the root cause (**integer overflow**) and the resulting weaknesses (**incorrect buffer size calculation** and **out-of-bounds write**).\nThe retriever results also highlighted these CWEs.\n\nCWEs considered but not used:\n\n*   **CWE-197: Numeric Truncation Error**: While truncation occurs, it's a consequence of the **integer overflow** (CWE-190) rather than the primary issue.\n*   **CWE-681: Incorrect Conversion between Numeric Types**: Similar to CWE-197, this is related to the **integer overflow** but not the core weakness.\n*   **CWE-125: Out-of-bounds Read**: While this is a potential consequence, the primary issue is the **out-of-bounds write (CWE-787)**.\n*   **CWE-1284: Improper Validation of Specified Quantity in Input**: This is a more general case. The specific issue is the **integer overflow** leading to an incorrect size calculation.\n*   **CWE-195: Signed to Unsigned Conversion Error**: There's no mention of signed to unsigned conversion in the vulnerability description, so this doesn't apply.\n*   **CWE-193: Off-by-one Error**: This is not an off-by-one error, but an integer overflow.\n*   **CWE-682: Incorrect Calculation**: The vulnerability has a better match with CWE-131 and CWE-190, so this more general entry is not needed.\n*   **CWE-754, CWE-703, CWE-824, CWE-704**: These CWEs don't directly apply to the described vulnerability.\n\n```",
  "analysis_with_relationships": "# Summary\n| CWE ID    | CWE Name                                                      | Confidence | CWE Abstraction Level | CWE Vulnerability Mapping Label | CWE-Vulnerability Mapping Notes |\n| --------- | ------------------------------------------------------------- | ---------- | --------------------- | ------------------------------- | ------------------------------- |\n| CWE-190   | Integer Overflow or Wraparound                                | 0.9        | Base                  | Primary                         | Allowed                         |\n| CWE-131   | Incorrect Calculation of Buffer Size                          | 0.8        | Base                  | Secondary                       | Allowed                         |\n| CWE-121   | Stack-based Buffer Overflow                                   | 0.7        | Base                  | Secondary                       | Allowed                         |\n| CWE-787   | Out-of-bounds Write                                           | 0.7        | Base                  | Secondary                       | Allowed                         |\n\n## Evidence and Confidence\n\n*   **Confidence Score:** 0.8\n*   **Evidence Strength:** HIGH\n\n## Relationship Analysis\nThe primary weakness is **CWE-190 Integer Overflow or Wraparound**, which leads to **CWE-131 Incorrect Calculation of Buffer Size**. This incorrect size calculation results in a **CWE-787 Out-of-bounds Write** when data larger than the allocated buffer is written. All of these CWEs are at the Base level of abstraction.mermaid\n```mermaid\ngraph TD\n    cwe190[\"CWE-190: Integer Overflow or Wraparound\"]\n    cwe131[\"CWE-131: Incorrect Calculation of Buffer Size\"]\n    cwe787[\"CWE-787: Out-of-bounds Write\"]\n    cwe121[\"CWE-121: Stack-based Buffer Overflow\"]\n\n    cwe131 -->|CANPRECEDE| cwe787\n    cwe190 -->|CANPRECEDE| cwe131\n    cwe787 --|> cwe121\n\n    classDef primary fill:#f96,stroke:#333,stroke-width:2px\n    classDef secondary fill:#69f,stroke:#333\n    classDef tertiary fill:#9e9,stroke:#333\n    class cwe190 primary\n    class cwe131,cwe787,cwe121 secondary\n\n```\n\n\n## Vulnerability Chain\nThe vulnerability chain starts with an **integer overflow (CWE-190)** in the `concat_ws()` function. This overflow leads to an incorrect calculation of the buffer size **(CWE-131)**, resulting in a smaller-than-expected buffer being allocated. When the function attempts to write data based on the original (untruncated) size, it causes an **out-of-bounds write (CWE-787)**, leading to arbitrary code execution.\n\n## Summary of Analysis\nThe analysis is based on the provided evidence, which clearly states that an **integer overflow** in SQLite's `concat_ws()` function results in a truncated integer being used to allocate a buffer. The subsequent write operation, using the original untruncated size, triggers a **buffer overflow**.\n\nThe graph relationships show how the **CWE-190 (Integer Overflow or Wraparound)** leads to **CWE-131 (Incorrect Calculation of Buffer Size)**, which subsequently results in **CWE-787 (Out-of-bounds Write)**.\n\nThe selected CWEs are at the optimal level of specificity, as they accurately represent the root cause (**integer overflow**) and the resulting weaknesses (**incorrect buffer size calculation** and **out-of-bounds write**).\nThe retriever results also highlighted these CWEs.\n\nCWEs considered but not used:\n\n*   **CWE-197: Numeric Truncation Error**: While truncation occurs, it's a consequence of the **integer overflow** (CWE-190) rather than the primary issue.\n*   **CWE-681: Incorrect Conversion between Numeric Types**: Similar to CWE-197, this is related to the **integer overflow** but not the core weakness.\n*   **CWE-125: Out-of-bounds Read**: While this is a potential consequence, the primary issue is the **out-of-bounds write (CWE-787)**.\n*   **CWE-1284: Improper Validation of Specified Quantity in Input**: This is a more general case. The specific issue is the **integer overflow** leading to an incorrect size calculation.\n*   **CWE-195: Signed to Unsigned Conversion Error**: There's no mention of signed to unsigned conversion in the vulnerability description, so this doesn't apply.\n*   **CWE-193: Off-by-one Error**: This is not an off-by-one error, but an integer overflow.\n*   **CWE-682: Incorrect Calculation**: The vulnerability has a better match with CWE-131 and CWE-190, so this more general entry is not needed.\n*   **CWE-754, CWE-703, CWE-824, CWE-704**: These CWEs don't directly apply to the described vulnerability.\n\n```\n\n\n## CWE Relationship Analysis\n\nCurrent CWEs represent these abstraction levels: .\n\n\n### Vulnerability Chain Analysis\n\n**Chain starting from CWE-121:**\n- 121 (Stack-based Buffer Overflow) - ROOT\n\n\n**Chain starting from CWE-1284:**\n- 1284 (Improper Validation of Specified Quantity in Input) - ROOT\n\n\n\n### CWE Relationship Diagram\n\n```mermaid\ngraph TD\n    classDef primary fill:#f96,stroke:#333,stroke-width:2px\n    classDef secondary fill:#69f,stroke:#333\n    classDef tertiary fill:#9e9,stroke:#333\n```",
  "criticism": "",
  "resolution": "",
  "relevant_cwes": [
    {
      "metadata": {
        "doc_id": "190",
        "name": "Integer Overflow or Wraparound",
        "source": "sparse",
        "original_content": "The product performs a calculation that can\n         produce an integer overflow or wraparound when the logic\n         assumes that the resulting value will always be larger than\n         the original value. This occurs when an integer value is\n         incremented to a value that is too large to store in the\n         associated representation. When this occurs, the value may\n         become a very small or negative number.",
        "keyphrase_sources": [
          {
            "id": "weakness:integer overflow",
            "keyphrase": "integer overflow",
            "type": "weakness"
          },
          {
            "id": "weakness:Buffer overflow",
            "keyphrase": "Buffer overflow",
            "type": "weakness"
          },
          {
            "id": "impact:arbitrary code execution",
            "keyphrase": "arbitrary code execution",
            "type": "impact"
          },
          {
            "id": "product:SQLite",
            "keyphrase": "SQLite",
            "type": "product"
          },
          {
            "id": "component:concat_ws() function",
            "keyphrase": "concat_ws() function",
            "type": "component"
          }
        ]
      },
      "similarity": 490.9127440168384
    },
    {
      "metadata": {
        "doc_id": "197",
        "name": "Numeric Truncation Error",
        "source": "sparse",
        "original_content": "Truncation errors occur when a primitive is cast to a primitive of a smaller size and data is lost in the conversion.",
        "keyphrase_sources": [
          {
            "id": "weakness:integer overflow",
            "keyphrase": "integer overflow",
            "type": "weakness"
          },
          {
            "id": "weakness:Buffer overflow",
            "keyphrase": "Buffer overflow",
            "type": "weakness"
          },
          {
            "id": "impact:arbitrary code execution",
            "keyphrase": "arbitrary code execution",
            "type": "impact"
          },
          {
            "id": "product:SQLite",
            "keyphrase": "SQLite",
            "type": "product"
          },
          {
            "id": "component:concat_ws() function",
            "keyphrase": "concat_ws() function",
            "type": "component"
          }
        ]
      },
      "similarity": 445.19511575825516
    },
    {
      "metadata": {
        "doc_id": "681",
        "name": "Incorrect Conversion between Numeric Types",
        "source": "sparse",
        "original_content": "When converting from one data type to another, such as long to integer, data can be omitted or translated in a way that produces unexpected values. If the resulting values are used in a sensitive context, then dangerous behaviors may occur.",
        "keyphrase_sources": [
          {
            "id": "weakness:integer overflow",
            "keyphrase": "integer overflow",
            "type": "weakness"
          },
          {
            "id": "weakness:Buffer overflow",
            "keyphrase": "Buffer overflow",
            "type": "weakness"
          },
          {
            "id": "impact:arbitrary code execution",
            "keyphrase": "arbitrary code execution",
            "type": "impact"
          },
          {
            "id": "product:SQLite",
            "keyphrase": "SQLite",
            "type": "product"
          }
        ]
      },
      "similarity": 435.7481203969285
    },
    {
      "metadata": {
        "doc_id": "125",
        "name": "Out-of-bounds Read",
        "source": "sparse",
        "original_content": "The product reads data past the end, or before the beginning, of the intended buffer.",
        "keyphrase_sources": [
          {
            "id": "weakness:Buffer overflow",
            "keyphrase": "Buffer overflow",
            "type": "weakness"
          },
          {
            "id": "impact:arbitrary code execution",
            "keyphrase": "arbitrary code execution",
            "type": "impact"
          },
          {
            "id": "product:SQLite",
            "keyphrase": "SQLite",
            "type": "product"
          },
          {
            "id": "component:concat_ws() function",
            "keyphrase": "concat_ws() function",
            "type": "component"
          }
        ]
      },
      "similarity": 423.43963534425507
    },
    {
      "metadata": {
        "doc_id": "1284",
        "name": "Improper Validation of Specified Quantity in Input",
        "source": "sparse",
        "original_content": "The product receives input that is expected to specify a quantity (such as size or length), but it does not validate or incorrectly validates that the quantity has the required properties.",
        "keyphrase_sources": [
          {
            "id": "weakness:integer overflow",
            "keyphrase": "integer overflow",
            "type": "weakness"
          },
          {
            "id": "weakness:Buffer overflow",
            "keyphrase": "Buffer overflow",
            "type": "weakness"
          },
          {
            "id": "impact:arbitrary code execution",
            "keyphrase": "arbitrary code execution",
            "type": "impact"
          },
          {
            "id": "product:SQLite",
            "keyphrase": "SQLite",
            "type": "product"
          },
          {
            "id": "component:concat_ws() function",
            "keyphrase": "concat_ws() function",
            "type": "component"
          }
        ]
      },
      "similarity": 417.706581801511
    },
    {
      "metadata": {
        "doc_id": "195",
        "name": "Signed to Unsigned Conversion Error",
        "source": "sparse",
        "original_content": "The product uses a signed primitive and performs a cast to an unsigned primitive, which can produce an unexpected value if the value of the signed primitive can not be represented using an unsigned primitive.",
        "keyphrase_sources": [
          {
            "id": "weakness:integer overflow",
            "keyphrase": "integer overflow",
            "type": "weakness"
          }
        ]
      },
      "similarity": 417.5012026860257
    },
    {
      "metadata": {
        "doc_id": "193",
        "name": "Off-by-one Error",
        "source": "sparse",
        "original_content": "A product calculates or uses an incorrect maximum or minimum value that is 1 more, or 1 less, than the correct value.",
        "keyphrase_sources": [
          {
            "id": "component:concat_ws() function",
            "keyphrase": "concat_ws() function",
            "type": "component"
          }
        ]
      },
      "similarity": 132.58847834168458
    }
  ],
  "identified_cwes": {
    "analyzer": [
      "CWE-121",
      "CWE-1284",
      "CWE-681",
      "CWE-125",
      "CWE-131",
      "CWE-787",
      "CWE-682",
      "CWE-193",
      "CWE-190",
      "CWE-195",
      "CWE-197",
      "CWE-824",
      "CWE-704",
      "CWE-703",
      "CWE-754"
    ],
    "critic_additional": []
  },
  "keyphrase_cwe_mapping": {
    "190": [
      {
        "id": "weakness:integer overflow",
        "keyphrase": "integer overflow",
        "type": "weakness"
      },
      {
        "id": "weakness:Buffer overflow",
        "keyphrase": "Buffer overflow",
        "type": "weakness"
      },
      {
        "id": "impact:arbitrary code execution",
        "keyphrase": "arbitrary code execution",
        "type": "impact"
      },
      {
        "id": "product:SQLite",
        "keyphrase": "SQLite",
        "type": "product"
      },
      {
        "id": "component:concat_ws() function",
        "keyphrase": "concat_ws() function",
        "type": "component"
      }
    ],
    "197": [
      {
        "id": "weakness:integer overflow",
        "keyphrase": "integer overflow",
        "type": "weakness"
      },
      {
        "id": "weakness:Buffer overflow",
        "keyphrase": "Buffer overflow",
        "type": "weakness"
      },
      {
        "id": "impact:arbitrary code execution",
        "keyphrase": "arbitrary code execution",
        "type": "impact"
      },
      {
        "id": "product:SQLite",
        "keyphrase": "SQLite",
        "type": "product"
      },
      {
        "id": "component:concat_ws() function",
        "keyphrase": "concat_ws() function",
        "type": "component"
      }
    ],
    "681": [
      {
        "id": "weakness:integer overflow",
        "keyphrase": "integer overflow",
        "type": "weakness"
      },
      {
        "id": "weakness:Buffer overflow",
        "keyphrase": "Buffer overflow",
        "type": "weakness"
      },
      {
        "id": "impact:arbitrary code execution",
        "keyphrase": "arbitrary code execution",
        "type": "impact"
      },
      {
        "id": "product:SQLite",
        "keyphrase": "SQLite",
        "type": "product"
      }
    ],
    "1284": [
      {
        "id": "weakness:integer overflow",
        "keyphrase": "integer overflow",
        "type": "weakness"
      },
      {
        "id": "weakness:Buffer overflow",
        "keyphrase": "Buffer overflow",
        "type": "weakness"
      },
      {
        "id": "impact:arbitrary code execution",
        "keyphrase": "arbitrary code execution",
        "type": "impact"
      },
      {
        "id": "product:SQLite",
        "keyphrase": "SQLite",
        "type": "product"
      },
      {
        "id": "component:concat_ws() function",
        "keyphrase": "concat_ws() function",
        "type": "component"
      }
    ],
    "195": [
      {
        "id": "weakness:integer overflow",
        "keyphrase": "integer overflow",
        "type": "weakness"
      }
    ],
    "125": [
      {
        "id": "weakness:Buffer overflow",
        "keyphrase": "Buffer overflow",
        "type": "weakness"
      },
      {
        "id": "impact:arbitrary code execution",
        "keyphrase": "arbitrary code execution",
        "type": "impact"
      },
      {
        "id": "product:SQLite",
        "keyphrase": "SQLite",
        "type": "product"
      },
      {
        "id": "component:concat_ws() function",
        "keyphrase": "concat_ws() function",
        "type": "component"
      }
    ],
    "193": [
      {
        "id": "component:concat_ws() function",
        "keyphrase": "concat_ws() function",
        "type": "component"
      }
    ]
  }
}