{
  "cve_id": "CVE-2024-34606",
  "description": "**Improper access control** in SmartThingsService prior to SMR Aug-2024 Release 1 allows local attackers to bypass restrictions on starting services from the background.",
  "key_phrases": {
    "rootcause": "Improper access control",
    "weakness": "",
    "impact": "bypass restrictions on starting services from the background",
    "vector": "",
    "attacker": "local attackers",
    "product": "SmartThingsService",
    "version": "prior to SMR Aug-2024 Release 1",
    "component": ""
  },
  "reference_content": "The provided document contains information about various security vulnerabilities in Samsung devices and their corresponding patches, focusing on monthly Security Maintenance Releases (SMR).\n\nBased on the provided text, CVE-2024-34606 is associated with **SVE-2023-1910**:\n\n*   **Root cause of vulnerability**: Improper access control in several system services.\n*   **Weaknesses/vulnerabilities present**: Improper access control leading to the ability to bypass restrictions on starting services from the background.\n*   **Impact of exploitation**: Local attackers can bypass restrictions on starting services from the background.\n*   **Attack vectors**: Local access.\n*   **Required attacker capabilities/position**: The attacker needs to be local.\n\nThe vulnerability is present in Android versions 12, 13, and 14 prior to the SMR Aug-2024 Release 1.",
  "similar_info": {
    "cwe_distribution": {
      "95": {
        "cwe_counts": {
          "CWE-NVD-Other": 1
        },
        "total_samples": 1,
        "distribution": [
          {
            "cwes": [
              "CWE-NVD-Other"
            ],
            "frequency": 1,
            "proportion": 1.0
          }
        ]
      },
      "90": {
        "cwe_counts": {
          "CWE-NVD-Other": 5
        },
        "total_samples": 5,
        "distribution": [
          {
            "cwes": [
              "CWE-NVD-Other"
            ],
            "frequency": 5,
            "proportion": 1.0
          }
        ]
      },
      "85": {
        "cwe_counts": {
          "CWE-NVD-Other": 5
        },
        "total_samples": 5,
        "distribution": [
          {
            "cwes": [
              "CWE-NVD-Other"
            ],
            "frequency": 5,
            "proportion": 1.0
          }
        ]
      },
      "80": {
        "cwe_counts": {
          "CWE-NVD-Other": 6
        },
        "total_samples": 6,
        "distribution": [
          {
            "cwes": [
              "CWE-NVD-Other"
            ],
            "frequency": 6,
            "proportion": 1.0
          }
        ]
      },
      "75": {
        "cwe_counts": {
          "CWE-NVD-Other": 6,
          "CWE-287": 1
        },
        "total_samples": 7,
        "distribution": [
          {
            "cwes": [
              "CWE-NVD-Other"
            ],
            "frequency": 6,
            "proportion": 0.857
          },
          {
            "cwes": [
              "CWE-287"
            ],
            "frequency": 1,
            "proportion": 0.143
          }
        ]
      },
      "70": {
        "cwe_counts": {
          "CWE-NVD-Other": 5,
          "CWE-NVD-noinfo": 1
        },
        "total_samples": 6,
        "distribution": [
          {
            "cwes": [
              "CWE-NVD-Other"
            ],
            "frequency": 5,
            "proportion": 0.833
          },
          {
            "cwes": [
              "CWE-NVD-noinfo"
            ],
            "frequency": 1,
            "proportion": 0.167
          }
        ]
      }
    },
    "cwe_consensus": "CWE-NVD-Other",
    "similarity_stats": {
      "thresholds": [
        95,
        90,
        85,
        80,
        75,
        70
      ],
      "total_samples_by_threshold": {
        "95": 1,
        "90": 5,
        "85": 5,
        "80": 6,
        "75": 7,
        "70": 6
      },
      "top_cwes_by_threshold": {
        "95": [
          [
            "CWE-NVD-Other",
            1
          ]
        ],
        "90": [
          [
            "CWE-NVD-Other",
            5
          ]
        ],
        "85": [
          [
            "CWE-NVD-Other",
            5
          ]
        ],
        "80": [
          [
            "CWE-NVD-Other",
            6
          ]
        ],
        "75": [
          [
            "CWE-NVD-Other",
            6
          ],
          [
            "CWE-287",
            1
          ]
        ],
        "70": [
          [
            "CWE-NVD-Other",
            5
          ],
          [
            "CWE-NVD-noinfo",
            1
          ]
        ]
      }
    },
    "raw_matches": [
      {
        "similarity": 95,
        "cwes": [
          "NVD-Other"
        ],
        "total": 1,
        "frequency": 1,
        "proportion": 1.0
      },
      {
        "similarity": 90,
        "cwes": [
          "NVD-Other"
        ],
        "total": 5,
        "frequency": 5,
        "proportion": 1.0
      },
      {
        "similarity": 85,
        "cwes": [
          "NVD-Other"
        ],
        "total": 5,
        "frequency": 5,
        "proportion": 1.0
      },
      {
        "similarity": 80,
        "cwes": [
          "NVD-Other"
        ],
        "total": 6,
        "frequency": 6,
        "proportion": 1.0
      },
      {
        "similarity": 75,
        "cwes": [
          "NVD-Other"
        ],
        "total": 7,
        "frequency": 6,
        "proportion": 0.857
      },
      {
        "similarity": 75,
        "cwes": [
          "287"
        ],
        "total": 7,
        "frequency": 1,
        "proportion": 0.143
      },
      {
        "similarity": 70,
        "cwes": [
          "NVD-Other"
        ],
        "total": 6,
        "frequency": 5,
        "proportion": 0.833
      },
      {
        "similarity": 70,
        "cwes": [
          "NVD-noinfo"
        ],
        "total": 6,
        "frequency": 1,
        "proportion": 0.167
      }
    ]
  },
  "similarity_summary": {
    "consensus_cwe": "CWE-NVD-Other",
    "top_cwes": [
      [
        "CWE-NVD-Other",
        28
      ],
      [
        "CWE-287",
        1
      ],
      [
        "CWE-NVD-noinfo",
        1
      ]
    ],
    "confidence_levels": {
      "high": [],
      "medium": [],
      "low": []
    },
    "total_samples": 30
  },
  "analysis": "# Summary\n| CWE ID  | CWE Name                      | Confidence | CWE Abstraction Level | CWE Vulnerability Mapping Label | CWE-Vulnerability Mapping Notes |\n| :------- | :----------------------------- | :--------- | :-------------------- | :------------------------------ | :----------------------------- |\n| CWE-284 | Improper Access Control       | 0.85       | Pillar                | Primary CWE                     | Discouraged                  |\n| CWE-306 | Missing Authentication for Critical Function | 0.65   | Base              | Secondary Candidate               | Allowed                   |\n| CWE-862 | Missing Authorization | 0.65   | Base              | Secondary Candidate               | Allowed                   |\n\n## Evidence and Confidence\n\n*   **Confidence Score:** 0.80\n*   **Evidence Strength:** MEDIUM\n\n## Relationship Analysis\n\nThe primary relationship influencing the CWE selection is the hierarchical structure related to access control. CWE-284 is a high-level category, while CWE-306 and CWE-862 are more specific. The vulnerability description mentions \"**Improper access control**\", making CWE-284 a reasonable initial choice. However, it lacks detail to definitively pinpoint whether the access control issue stems from missing authentication (CWE-306) or missing authorization (CWE-862). Since it is unclear whether identity was checked (authentication) or authorization was missing/incorrect, the higher level CWE-284 is preferred. If more information were available, a more specific CWE could be selected.\n\n```mermaid\ngraph TD\n    cwe284[\"CWE-284: Improper Access Control\"]\n    cwe306[\"CWE-306: Missing Authentication for Critical Function\"]\n    cwe862[\"CWE-862: Missing Authorization\"]\n\n    cwe306 -->|CHILDOF| cwe284\n    cwe862 -->|CHILDOF| cwe284\n\n    classDef primary fill:#f96,stroke:#333,stroke-width:2px\n    classDef secondary fill:#69f,stroke:#333\n    classDef tertiary fill:#9e9,stroke:#333\n    class cwe284 primary\n    class cwe306,cwe862 secondary\n```\n\n## Vulnerability Chain\n\nThe vulnerability chain starts with \"**Improper access control**\" (CWE-284), which allows local attackers to bypass restrictions on starting services from the background. The chain is:\n\n1.  **Root Cause:** CWE-284 (**Improper access control**)\n2.  **Impact:** Bypass restrictions on starting services from the background.\n\nThe description does not provide sufficient detail to determine whether the **improper access control** is due to missing authentication or missing authorization.\n\n## Summary of Analysis\n\nThe initial assessment, based on the \"**Improper access control**\" key phrase, pointed towards CWE-284. The retriever results also highlighted CWE-285 (**Improper Authorization**), CWE-863 (**Incorrect Authorization**), and CWE-306 (**Missing Authentication for Critical Function**) as potential candidates.\n\nThe guidance on Authentication vs Authorization vs Access Control helped refine the selection. The guidance emphasizes that if the root cause is unclear, using CWE-284 is acceptable, but if it can be determined whether identity was checked or not, then CWE-306 or CWE-862, respectively, should be used.\n\nThe available evidence does not provide enough information to definitively choose between authentication and authorization issues. Therefore, CWE-284 (**Improper Access Control**) remains the primary CWE due to its broad applicability to access control failures. However, due to the commonality of Authentication and Authorization issues, CWE-306 and CWE-862 are listed as secondary candidates.\n\nRelevant CWE Information:\n\n# Enhanced Context (10 CWEs)\nThe following CWEs were identified as potentially relevant to this vulnerability:\n\n## CWE-284: Improper Access Control\n**Abstraction Level**: Pillar\n**Description**: The software does not restrict access to resources (data, files, actions, etc.) to only the intended privileged actors (users, processes, etc.).\n**Mapping Guidance**:\n- Usage: Discouraged\n- Rationale: CWE-284 is high-level and lower-level CWEs can frequently be used instead. It is a level-1 Class (i.e., a child of a Pillar).\n**Relationships**:\n- PARENTOF -> CWE-602\n- PARENTOF -> CWE-538\n- PARENTOF -> CWE-732\n- PARENTOF -> CWE-264\n- PARENTOF -> CWE-266\n- PARENTOF -> CWE-269\n- PARENTOF -> CWE-285\n- PARENTOF -> CWE-287\n- PARENTOF -> CWE-425\n- PARENTOF -> CWE-664\n- PARENTOF -> CWE-924\n- PARENTOF -> CWE-1004\n- PARENTOF -> CWE-1304\n- CANFOLLOW -> CWE-41\n- CANFOLLOW -> CWE-22\n- CANFOLLOW -> CWE-73\n- CANFOLLOW -> CWE-99\n- CANFOLLOW -> CWE-269\n\n## CWE-285: Improper Authorization\n**Abstraction Level**: Class\n**Description**: The product does not perform or incorrectly performs an authorization check when an actor attempts to access a resource or perform an action.\n**Mapping Guidance**:\n- Usage: Discouraged\n- Rationale: CWE-285 is high-level and lower-level CWEs can frequently be used instead. It is a level-1 Class (i.e., a child of a Pillar).\n\n## CWE-863: Incorrect Authorization\n**Abstraction Level**: Class\n**Description**: The product performs an authorization check when an actor attempts to access a resource or perform an action, but it does not correctly perform the check.\n**Mapping Guidance**:\n- Usage: Allowed-with-Review\n- Rationale: This CWE entry is a Class and might have Base-level children that would be more appropriate\n\n## CWE-269: Improper Privilege Management\n**Abstraction Level**: Class\n**Description**: The software does not properly manage privileges, possibly including privilege assignment, privilege checking, or elevation of privileges.\n**Mapping Guidance**:\n- Usage: Discouraged\n- Rationale: This CWE entry is a Class and might have Base-level children that would be more appropriate\n\n## CWE-927: Use of Implicit Intent for Sensitive Communication\n**Abstraction Level**: Variant\n**Description**: The application uses an implicit intent to send sensitive information to a component, but this may result in the unintended exposure of the information if the target component is not properly secured.\n**Mapping Guidance**:\n- Usage: Allowed\n- Rationale: This CWE entry is at the Variant level of abstraction, which is a preferred level of abstraction for mapping to the root causes of vulnerabilities.\n\n## CWE-287: Improper Authentication\n**Abstraction Level**: Class\n**Description**: When an actor claims to have a given identity, the product does not prove or insufficiently proves that the claim is correct.\n**Mapping Guidance**:\n- Usage: Discouraged\n- Rationale: This CWE entry might be misused when lower-level CWE entries are likely to be applicable. It is a level-1 Class (i.e., a child of a Pillar).\n\n## CWE-1285: Improper Validation of Specified Index, Position, or Offset in Input\n**Abstraction Level**: Base\n**Description**: The software receives an index, position, or offset as input, but it does not validate or incorrectly validates that the value is within the expected bounds, which could lead to read or write operations in unintended memory locations.\n**Mapping Guidance**:\n- Usage: Allowed\n- Rationale: This CWE entry is at the Base level of abstraction, which is a preferred level of abstraction for mapping to the root causes of vulnerabilities.\n\n## CWE-923: Improper Restriction of Communication Channel to Intended Endpoints\n**Abstraction Level**: Class\n**Description**: The software does not properly restrict the communication channel to only the intended endpoints, which could allow unintended parties to eavesdrop on or interfere with communications.\n**Mapping Guidance**:\n- Usage: Allowed-with-Review\n- Rationale: This CWE entry is a Class and might have Base-level children that would be more appropriate\n\n## CWE-306: Missing Authentication for Critical Function\n**Abstraction Level**: Base\n**Description**: The product does not perform any authentication for functionality that requires a provable user identity or consumes a significant amount of resources.\n**Mapping Guidance**:\n- Usage: Allowed\n- Rationale: This CWE entry is at the Base level of abstraction, which is a preferred level of abstraction for mapping to the root causes of vulnerabilities.\n\n## CWE-613: Insufficient Session Expiration\n**Abstraction Level**: Base\n**Description**: The application does not sufficiently expire or invalidate a user session after a certain period of inactivity or after a logout, which could allow an attacker to reuse the session and gain unauthorized access to the application.\n**Mapping Guidance**:\n- Usage: Allowed\n- Rationale: This CWE entry is at the Base level of abstraction, which is a preferred level of abstraction for mapping to the root causes of vulnerabilities.",
  "analysis_with_relationships": "# Summary\n| CWE ID  | CWE Name                      | Confidence | CWE Abstraction Level | CWE Vulnerability Mapping Label | CWE-Vulnerability Mapping Notes |\n| :------- | :----------------------------- | :--------- | :-------------------- | :------------------------------ | :----------------------------- |\n| CWE-284 | Improper Access Control       | 0.85       | Pillar                | Primary CWE                     | Discouraged                  |\n| CWE-306 | Missing Authentication for Critical Function | 0.65   | Base              | Secondary Candidate               | Allowed                   |\n| CWE-862 | Missing Authorization | 0.65   | Base              | Secondary Candidate               | Allowed                   |\n\n## Evidence and Confidence\n\n*   **Confidence Score:** 0.80\n*   **Evidence Strength:** MEDIUM\n\n## Relationship Analysis\n\nThe primary relationship influencing the CWE selection is the hierarchical structure related to access control. CWE-284 is a high-level category, while CWE-306 and CWE-862 are more specific. The vulnerability description mentions \"**Improper access control**\", making CWE-284 a reasonable initial choice. However, it lacks detail to definitively pinpoint whether the access control issue stems from missing authentication (CWE-306) or missing authorization (CWE-862). Since it is unclear whether identity was checked (authentication) or authorization was missing/incorrect, the higher level CWE-284 is preferred. If more information were available, a more specific CWE could be selected.\n\n```mermaid\ngraph TD\n    cwe284[\"CWE-284: Improper Access Control\"]\n    cwe306[\"CWE-306: Missing Authentication for Critical Function\"]\n    cwe862[\"CWE-862: Missing Authorization\"]\n\n    cwe306 -->|CHILDOF| cwe284\n    cwe862 -->|CHILDOF| cwe284\n\n    classDef primary fill:#f96,stroke:#333,stroke-width:2px\n    classDef secondary fill:#69f,stroke:#333\n    classDef tertiary fill:#9e9,stroke:#333\n    class cwe284 primary\n    class cwe306,cwe862 secondary\n```\n\n## Vulnerability Chain\n\nThe vulnerability chain starts with \"**Improper access control**\" (CWE-284), which allows local attackers to bypass restrictions on starting services from the background. The chain is:\n\n1.  **Root Cause:** CWE-284 (**Improper access control**)\n2.  **Impact:** Bypass restrictions on starting services from the background.\n\nThe description does not provide sufficient detail to determine whether the **improper access control** is due to missing authentication or missing authorization.\n\n## Summary of Analysis\n\nThe initial assessment, based on the \"**Improper access control**\" key phrase, pointed towards CWE-284. The retriever results also highlighted CWE-285 (**Improper Authorization**), CWE-863 (**Incorrect Authorization**), and CWE-306 (**Missing Authentication for Critical Function**) as potential candidates.\n\nThe guidance on Authentication vs Authorization vs Access Control helped refine the selection. The guidance emphasizes that if the root cause is unclear, using CWE-284 is acceptable, but if it can be determined whether identity was checked or not, then CWE-306 or CWE-862, respectively, should be used.\n\nThe available evidence does not provide enough information to definitively choose between authentication and authorization issues. Therefore, CWE-284 (**Improper Access Control**) remains the primary CWE due to its broad applicability to access control failures. However, due to the commonality of Authentication and Authorization issues, CWE-306 and CWE-862 are listed as secondary candidates.\n\nRelevant CWE Information:\n\n# Enhanced Context (10 CWEs)\nThe following CWEs were identified as potentially relevant to this vulnerability:\n\n## CWE-284: Improper Access Control\n**Abstraction Level**: Pillar\n**Description**: The software does not restrict access to resources (data, files, actions, etc.) to only the intended privileged actors (users, processes, etc.).\n**Mapping Guidance**:\n- Usage: Discouraged\n- Rationale: CWE-284 is high-level and lower-level CWEs can frequently be used instead. It is a level-1 Class (i.e., a child of a Pillar).\n**Relationships**:\n- PARENTOF -> CWE-602\n- PARENTOF -> CWE-538\n- PARENTOF -> CWE-732\n- PARENTOF -> CWE-264\n- PARENTOF -> CWE-266\n- PARENTOF -> CWE-269\n- PARENTOF -> CWE-285\n- PARENTOF -> CWE-287\n- PARENTOF -> CWE-425\n- PARENTOF -> CWE-664\n- PARENTOF -> CWE-924\n- PARENTOF -> CWE-1004\n- PARENTOF -> CWE-1304\n- CANFOLLOW -> CWE-41\n- CANFOLLOW -> CWE-22\n- CANFOLLOW -> CWE-73\n- CANFOLLOW -> CWE-99\n- CANFOLLOW -> CWE-269\n\n## CWE-285: Improper Authorization\n**Abstraction Level**: Class\n**Description**: The product does not perform or incorrectly performs an authorization check when an actor attempts to access a resource or perform an action.\n**Mapping Guidance**:\n- Usage: Discouraged\n- Rationale: CWE-285 is high-level and lower-level CWEs can frequently be used instead. It is a level-1 Class (i.e., a child of a Pillar).\n\n## CWE-863: Incorrect Authorization\n**Abstraction Level**: Class\n**Description**: The product performs an authorization check when an actor attempts to access a resource or perform an action, but it does not correctly perform the check.\n**Mapping Guidance**:\n- Usage: Allowed-with-Review\n- Rationale: This CWE entry is a Class and might have Base-level children that would be more appropriate\n\n## CWE-269: Improper Privilege Management\n**Abstraction Level**: Class\n**Description**: The software does not properly manage privileges, possibly including privilege assignment, privilege checking, or elevation of privileges.\n**Mapping Guidance**:\n- Usage: Discouraged\n- Rationale: This CWE entry is a Class and might have Base-level children that would be more appropriate\n\n## CWE-927: Use of Implicit Intent for Sensitive Communication\n**Abstraction Level**: Variant\n**Description**: The application uses an implicit intent to send sensitive information to a component, but this may result in the unintended exposure of the information if the target component is not properly secured.\n**Mapping Guidance**:\n- Usage: Allowed\n- Rationale: This CWE entry is at the Variant level of abstraction, which is a preferred level of abstraction for mapping to the root causes of vulnerabilities.\n\n## CWE-287: Improper Authentication\n**Abstraction Level**: Class\n**Description**: When an actor claims to have a given identity, the product does not prove or insufficiently proves that the claim is correct.\n**Mapping Guidance**:\n- Usage: Discouraged\n- Rationale: This CWE entry might be misused when lower-level CWE entries are likely to be applicable. It is a level-1 Class (i.e., a child of a Pillar).\n\n## CWE-1285: Improper Validation of Specified Index, Position, or Offset in Input\n**Abstraction Level**: Base\n**Description**: The software receives an index, position, or offset as input, but it does not validate or incorrectly validates that the value is within the expected bounds, which could lead to read or write operations in unintended memory locations.\n**Mapping Guidance**:\n- Usage: Allowed\n- Rationale: This CWE entry is at the Base level of abstraction, which is a preferred level of abstraction for mapping to the root causes of vulnerabilities.\n\n## CWE-923: Improper Restriction of Communication Channel to Intended Endpoints\n**Abstraction Level**: Class\n**Description**: The software does not properly restrict the communication channel to only the intended endpoints, which could allow unintended parties to eavesdrop on or interfere with communications.\n**Mapping Guidance**:\n- Usage: Allowed-with-Review\n- Rationale: This CWE entry is a Class and might have Base-level children that would be more appropriate\n\n## CWE-306: Missing Authentication for Critical Function\n**Abstraction Level**: Base\n**Description**: The product does not perform any authentication for functionality that requires a provable user identity or consumes a significant amount of resources.\n**Mapping Guidance**:\n- Usage: Allowed\n- Rationale: This CWE entry is at the Base level of abstraction, which is a preferred level of abstraction for mapping to the root causes of vulnerabilities.\n\n## CWE-613: Insufficient Session Expiration\n**Abstraction Level**: Base\n**Description**: The application does not sufficiently expire or invalidate a user session after a certain period of inactivity or after a logout, which could allow an attacker to reuse the session and gain unauthorized access to the application.\n**Mapping Guidance**:\n- Usage: Allowed\n- Rationale: This CWE entry is at the Base level of abstraction, which is a preferred level of abstraction for mapping to the root causes of vulnerabilities.\n\n\n## CWE Relationship Analysis\n\nCurrent CWEs represent these abstraction levels: .\n\n\n### Vulnerability Chain Analysis\n\n**Chain starting from CWE-862:**\n- 862 (Missing Authorization) - ROOT\n\n\n**Chain starting from CWE-269:**\n- 269 (Improper Privilege Management) - ROOT\n\n\n\n### CWE Relationship Diagram\n\n```mermaid\ngraph TD\n    classDef primary fill:#f96,stroke:#333,stroke-width:2px\n    classDef secondary fill:#69f,stroke:#333\n    classDef tertiary fill:#9e9,stroke:#333\n```",
  "criticism": "",
  "resolution": "",
  "relevant_cwes": [
    {
      "metadata": {
        "doc_id": "284",
        "name": "Improper Access Control",
        "source": "sparse"
      },
      "similarity": 171.96931680517542
    },
    {
      "metadata": {
        "doc_id": "285",
        "name": "Improper Authorization",
        "source": "sparse"
      },
      "similarity": 167.83859856808732
    },
    {
      "metadata": {
        "doc_id": "863",
        "name": "Incorrect Authorization",
        "source": "sparse"
      },
      "similarity": 148.54553686322043
    },
    {
      "metadata": {
        "doc_id": "269",
        "name": "Improper Privilege Management",
        "source": "sparse"
      },
      "similarity": 144.658431849814
    },
    {
      "metadata": {
        "doc_id": "927",
        "name": "Use of Implicit Intent for Sensitive Communication",
        "source": "sparse"
      },
      "similarity": 142.09245410172613
    },
    {
      "metadata": {
        "doc_id": "287",
        "name": "Improper Authentication",
        "source": "sparse"
      },
      "similarity": 138.86162397025234
    },
    {
      "metadata": {
        "doc_id": "1285",
        "name": "Improper Validation of Specified Index, Position, or Offset in Input",
        "source": "sparse"
      },
      "similarity": 138.39205847630777
    },
    {
      "metadata": {
        "doc_id": "923",
        "name": "Improper Restriction of Communication Channel to Intended Endpoints",
        "source": "sparse"
      },
      "similarity": 136.99745643164323
    },
    {
      "metadata": {
        "doc_id": "306",
        "name": "Missing Authentication for Critical Function",
        "type": "Base",
        "original_content": "The product does not perform any authentication for functionality that requires a provable user identity or consumes a significant amount of resources.",
        "keyphrase_source": "rootcause:Improper access control",
        "source": "dense",
        "mapping_notes": {
          "usage": "Allowed",
          "rationale": "This CWE entry is at the Base level of abstraction, which is a preferred level of abstraction for mapping to the root causes of vulnerabilities.",
          "comments": "Carefully read both the name and description to ensure that this mapping is an appropriate fit. Do not try to 'force' a mapping to a lower-level Base/Variant simply to comply with this preferred level of abstraction.",
          "reasons": [
            "Acceptable-Use"
          ]
        },
        "score_info": {
          "retrievers": [
            "dense",
            "graph"
          ],
          "retriever_count": 2,
          "normalized_scores": {
            "dense": 0.553054159965982,
            "graph": 1.7311982205858694
          }
        }
      },
      "similarity": 0.553054159965982
    },
    {
      "doc_id": "613",
      "text": "CWE-613: Insufficient Session Expiration",
      "score": 2.2100000000000004,
      "metadata": {
        "doc_id": "613",
        "name": "Insufficient Session Expiration",
        "type": "base",
        "original_content": "CWE-613: Insufficient Session Expiration",
        "relationships": [
          {
            "source_id": "613",
            "target_id": "352",
            "label": "REQUIREDBY",
            "properties": {
              "view_id": "1000"
            }
          },
          {
            "source_id": "613",
            "target_id": "287",
            "label": "CANPRECEDE",
            "properties": {
              "view_id": "1000"
            }
          },
          {
            "source_id": "613",
            "target_id": "672",
            "label": "CHILDOF",
            "properties": {
              "ordinal": "Primary",
              "view_id": "1003"
            }
          },
          {
            "source_id": "613",
            "target_id": "672",
            "label": "CHILDOF",
            "properties": {
              "ordinal": "Primary",
              "view_id": "1000"
            }
          },
          {
            "source_id": "672",
            "target_id": "613",
            "label": "PARENTOF",
            "properties": {
              "ordinal": "Primary",
              "view_id": "1000"
            }
          },
          {
            "source_id": "352",
            "target_id": "613",
            "label": "REQUIRES",
            "properties": {
              "view_id": "1000"
            }
          },
          {
            "source_id": "287",
            "target_id": "613",
            "label": "CANFOLLOW",
            "properties": {
              "view_id": "1000"
            }
          }
        ],
        "score_components": {
          "relationship_chain": 1.0,
          "sequence_path": 1.0
        },
        "abstraction_factor": 1.3,
        "graph_path_info": {
          "path_types": [
            "relationship_chain",
            "vulnerability_sequence_forward",
            "vulnerability_sequence_backward"
          ],
          "best_paths": {
            "relationship_chain": {
              "path": [
                [
                  "287",
                  "613",
                  "CANFOLLOW"
                ]
              ],
              "score": 1.0,
              "type": "relationship_chain",
              "source": "287"
            },
            "vulnerability_sequence_forward": {
              "path": [
                [
                  "287",
                  "613",
                  "CANFOLLOW"
                ]
              ],
              "score": 0.9,
              "type": "vulnerability_sequence_forward",
              "source": "287"
            },
            "vulnerability_sequence_backward": {
              "path": [
                [
                  "613",
                  "287",
                  "CANPRECEDE"
                ]
              ],
              "score": 1.0,
              "type": "vulnerability_sequence_backward",
              "source": "287"
            }
          }
        },
        "position": "before",
        "sources": [
          "graph"
        ],
        "source": "graph",
        "mapping_notes": {
          "usage": "Allowed",
          "rationale": "This CWE entry is at the Base level of abstraction, which is a preferred level of abstraction for mapping to the root causes of vulnerabilities.",
          "comments": "Carefully read both the name and description to ensure that this mapping is an appropriate fit. Do not try to 'force' a mapping to a lower-level Base/Variant simply to comply with this preferred level of abstraction.",
          "reasons": [
            "Acceptable-Use"
          ]
        },
        "score_info": {
          "retrievers": [
            "graph"
          ],
          "retriever_count": 1,
          "normalized_scores": {
            "graph": 2.2100000000000004
          }
        }
      },
      "similarity": 2.2100000000000004
    }
  ],
  "identified_cwes": {
    "analyzer": [
      "CWE-264",
      "CWE-862",
      "CWE-269",
      "CWE-285",
      "CWE-99",
      "CWE-306",
      "CWE-73",
      "CWE-613",
      "CWE-1004",
      "CWE-927",
      "CWE-664",
      "CWE-266",
      "CWE-425",
      "CWE-41",
      "CWE-863",
      "CWE-923",
      "CWE-1285",
      "CWE-284",
      "CWE-924",
      "CWE-287",
      "CWE-602",
      "CWE-732",
      "CWE-22",
      "CWE-1304",
      "CWE-538"
    ],
    "critic_additional": []
  },
  "keyphrase_cwe_mapping": {}
}