{
  "vulnerability_info": "VulnerabilityInfo(cve_id='CVE-2024-52481', description='**Improper Limitation of a Pathname to a Restricted Directory** (Path Traversal) vulnerability in Astoundify Jobify - Job Board WordPress Theme allows Relative Path Traversal.This issue affects Jobify - Job Board WordPress Theme from n/a through 4.2.3.', key_phrases={'rootcause': ['Improper Limitation of a Pathname to a Restricted Directory', 'Improper path traversal'], 'weakness': '', 'impact': 'relative path traversal', 'vector': '', 'attacker': '', 'product': 'Astoundify Jobify - Job Board WordPress Theme', 'version': 'n/a through 4.2.3', 'component': ''}, reference_content=\"Based on the provided content, here's a breakdown of the vulnerability:\\n\\n**Vulnerability:** Arbitrary File Download\\n\\n**Affected Software:** Jobify - Job Board WordPress Theme\\n\\n**Vulnerable Versions:** <= 4.2.3\\n\\n**Root Cause:** The vulnerability allows a malicious actor to download any file from the website. This likely stems from insecure handling of file paths or insufficient access controls on file retrieval mechanisms.\\n\\n**Weaknesses/Vulnerabilities:**\\n*   **Arbitrary File Download:** The primary vulnerability is the ability to download arbitrary files. This suggests a lack of proper input validation, sanitization, or access control checks when processing file requests.\\n*   **Security Misconfiguration:** The vulnerability is also classified under OWASP Top 10 A5: Security Misconfiguration, which implies the theme is not configured to prevent unauthorized access to files.\\n\\n**Impact of Exploitation:**\\n*   **Data Breach:** Attackers can download sensitive files, including those containing login credentials, configuration settings, or database backups, leading to potential data breaches.\\n*   **Website Compromise:** The downloaded information could be used to further compromise the website or its server.\\n*   **Loss of Confidentiality:** The confidentiality of sensitive data is compromised.\\n\\n**Attack Vectors:**\\n*   The vulnerability is remotely exploitable. The specific method is not detailed, but it would involve sending a specially crafted request to the web server that exploits the flaw in how file downloads are handled.\\n*   **Unauthenticated access:** This attack can be performed without needing to log into the WordPress site.\\n\\n**Required Attacker Capabilities/Position:**\\n*   The attacker needs to be able to send HTTP requests to the server hosting the vulnerable WordPress site.\\n*   No authentication is required.\\n\\n**Additional Information:**\\n\\n*   Patchstack has issued a virtual patch to mitigate this issue.\\n*   The vulnerability has a CVSS score of 7.5, indicating a high severity.\\n\\n**Summary of Relevant Information:**\\nThe Jobify WordPress theme is vulnerable to arbitrary file download, allowing unauthenticated attackers to download any file from the server. This is due to insufficient access controls or improper handling of file requests, and can lead to a significant breach of sensitive information, and potential website takeover.\", similar_info={'cwe_distribution': {}, 'cwe_consensus': '', 'similarity_stats': {'thresholds': [], 'total_samples_by_threshold': {}, 'top_cwes_by_threshold': {}}}, similarity_summary=SimilarityInsight(consensus_cwe='', top_cwes=[], confidence_levels={}, total_samples=0), analysis='', analysis_with_relationships='', criticism='', resolution='', relevant_cwes=[{'metadata': {'doc_id': '22', 'name': \"Improper Limitation of a Pathname to a Restricted Directory ('Path Traversal')\", 'source': 'sparse', 'original_content': 'The product uses external input to construct a pathname that is intended to identify a file or directory that is located underneath a restricted parent directory, but the product does not properly neutralize special elements within the pathname that can cause the pathname to resolve to a location that is outside of the restricted directory.', 'keyphrase_sources': [{'id': 'rootcause:Improper Limitation of a Pathname to a Restricted Directory', 'keyphrase': 'Improper Limitation of a Pathname to a Restricted Directory', 'type': 'rootcause'}, {'id': 'rootcause:Improper path traversal', 'keyphrase': 'Improper path traversal', 'type': 'rootcause'}, {'id': 'impact:relative path traversal', 'keyphrase': 'relative path traversal', 'type': 'impact'}, {'id': 'product:Astoundify Jobify - Job Board WordPress Theme', 'keyphrase': 'Astoundify Jobify - Job Board WordPress Theme', 'type': 'product'}, {'id': 'version:n/a through 4.2.3', 'keyphrase': 'n/a through 4.2.3', 'type': 'version'}]}, 'similarity': np.float64(464.22028759951615)}, {'metadata': {'doc_id': '23', 'name': 'Relative Path Traversal', 'source': 'sparse', 'original_content': 'The product uses external input to construct a pathname that should be within a restricted directory, but it does not properly neutralize sequences such as \"..\" that can resolve to a location that is outside of that directory.', 'keyphrase_sources': [{'id': 'rootcause:Improper Limitation of a Pathname to a Restricted Directory', 'keyphrase': 'Improper Limitation of a Pathname to a Restricted Directory', 'type': 'rootcause'}, {'id': 'rootcause:Improper path traversal', 'keyphrase': 'Improper path traversal', 'type': 'rootcause'}, {'id': 'impact:relative path traversal', 'keyphrase': 'relative path traversal', 'type': 'impact'}, {'id': 'product:Astoundify Jobify - Job Board WordPress Theme', 'keyphrase': 'Astoundify Jobify - Job Board WordPress Theme', 'type': 'product'}, {'id': 'version:n/a through 4.2.3', 'keyphrase': 'n/a through 4.2.3', 'type': 'version'}]}, 'similarity': np.float64(384.6310214931923)}, {'metadata': {'doc_id': '24', 'name': \"Path Traversal: '../filedir'\", 'source': 'sparse', 'original_content': 'The product uses external input to construct a pathname that should be within a restricted directory, but it does not properly neutralize \"../\" sequences that can resolve to a location that is outside of that directory.', 'keyphrase_sources': [{'id': 'rootcause:Improper Limitation of a Pathname to a Restricted Directory', 'keyphrase': 'Improper Limitation of a Pathname to a Restricted Directory', 'type': 'rootcause'}, {'id': 'rootcause:Improper path traversal', 'keyphrase': 'Improper path traversal', 'type': 'rootcause'}, {'id': 'impact:relative path traversal', 'keyphrase': 'relative path traversal', 'type': 'impact'}]}, 'similarity': np.float64(350.45432818513876)}, {'metadata': {'doc_id': '36', 'name': 'Absolute Path Traversal', 'source': 'sparse', 'original_content': 'The product uses external input to construct a pathname that should be within a restricted directory, but it does not properly neutralize absolute path sequences such as \"/abs/path\" that can resolve to a location that is outside of that directory.', 'keyphrase_sources': [{'id': 'rootcause:Improper Limitation of a Pathname to a Restricted Directory', 'keyphrase': 'Improper Limitation of a Pathname to a Restricted Directory', 'type': 'rootcause'}, {'id': 'rootcause:Improper path traversal', 'keyphrase': 'Improper path traversal', 'type': 'rootcause'}, {'id': 'impact:relative path traversal', 'keyphrase': 'relative path traversal', 'type': 'impact'}, {'id': 'version:n/a through 4.2.3', 'keyphrase': 'n/a through 4.2.3', 'type': 'version'}]}, 'similarity': np.float64(346.3231996167128)}, {'metadata': {'doc_id': '29', 'name': \"Path Traversal: '\\\\..\\\\filename'\", 'source': 'sparse', 'original_content': \"The product uses external input to construct a pathname that should be within a restricted directory, but it does not properly neutralize '\\\\..\\\\filename' (leading backslash dot dot) sequences that can resolve to a location that is outside of that directory.\", 'keyphrase_sources': [{'id': 'rootcause:Improper Limitation of a Pathname to a Restricted Directory', 'keyphrase': 'Improper Limitation of a Pathname to a Restricted Directory', 'type': 'rootcause'}]}, 'similarity': np.float64(329.56320555163325)}, {'metadata': {'doc_id': '73', 'name': 'External Control of File Name or Path', 'source': 'sparse', 'original_content': 'The product allows user input to control or influence paths or file names that are used in filesystem operations.', 'keyphrase_sources': [{'id': 'rootcause:Improper path traversal', 'keyphrase': 'Improper path traversal', 'type': 'rootcause'}]}, 'similarity': np.float64(237.0099011210729)}, {'metadata': {'doc_id': '98', 'name': \"Improper Control of Filename for Include/Require Statement in PHP Program ('PHP Remote File Inclusion')\", 'source': 'sparse', 'original_content': 'The PHP application receives input from an upstream component, but it does not restrict or incorrectly restricts the input before its usage in \"require,\" \"include,\" or similar functions.', 'keyphrase_sources': [{'id': 'impact:relative path traversal', 'keyphrase': 'relative path traversal', 'type': 'impact'}]}, 'similarity': np.float64(89.3001487624816)}, {'metadata': {'doc_id': '548', 'name': 'Exposure of Information Through Directory Listing', 'source': 'sparse', 'original_content': 'A directory listing is inappropriately exposed, yielding potentially sensitive information to attackers.', 'keyphrase_sources': [{'id': 'product:Astoundify Jobify - Job Board WordPress Theme', 'keyphrase': 'Astoundify Jobify - Job Board WordPress Theme', 'type': 'product'}]}, 'similarity': np.float64(88.73084888163717)}, {'metadata': {'doc_id': '306', 'name': 'Missing Authentication for Critical Function', 'source': 'sparse', 'original_content': 'The product does not perform any authentication for functionality that requires a provable user identity or consumes a significant amount of resources.', 'keyphrase_sources': [{'id': 'product:Astoundify Jobify - Job Board WordPress Theme', 'keyphrase': 'Astoundify Jobify - Job Board WordPress Theme', 'type': 'product'}, {'id': 'version:n/a through 4.2.3', 'keyphrase': 'n/a through 4.2.3', 'type': 'version'}]}, 'similarity': np.float64(81.21909766324933)}, {'metadata': {'doc_id': '434', 'name': 'Unrestricted Upload of File with Dangerous Type', 'source': 'sparse', 'original_content': 'The product allows the upload or transfer of dangerous file types that are automatically processed within its environment.', 'keyphrase_sources': [{'id': 'product:Astoundify Jobify - Job Board WordPress Theme', 'keyphrase': 'Astoundify Jobify - Job Board WordPress Theme', 'type': 'product'}, {'id': 'version:n/a through 4.2.3', 'keyphrase': 'n/a through 4.2.3', 'type': 'version'}]}, 'similarity': np.float64(80.84590742134448)}], identified_cwes={'analyzer': [], 'critic_additional': []})",
  "retrieval_results": {
    "has_multiple_keyphrases": true,
    "keyphrase_cwe_sets": {
      "rootcause:Improper Limitation of a Pathname to a Restricted Directory": {
        "keyphrase": "Improper Limitation of a Pathname to a Restricted Directory",
        "type": "rootcause",
        "cwes": [
          {
            "metadata": {
              "doc_id": "22",
              "name": "Improper Limitation of a Pathname to a Restricted Directory ('Path Traversal')",
              "source": "sparse",
              "original_content": "The product uses external input to construct a pathname that is intended to identify a file or directory that is located underneath a restricted parent directory, but the product does not properly neutralize special elements within the pathname that can cause the pathname to resolve to a location that is outside of the restricted directory.",
              "keyphrase_sources": [
                {
                  "id": "rootcause:Improper Limitation of a Pathname to a Restricted Directory",
                  "keyphrase": "Improper Limitation of a Pathname to a Restricted Directory",
                  "type": "rootcause"
                },
                {
                  "id": "rootcause:Improper path traversal",
                  "keyphrase": "Improper path traversal",
                  "type": "rootcause"
                },
                {
                  "id": "impact:relative path traversal",
                  "keyphrase": "relative path traversal",
                  "type": "impact"
                },
                {
                  "id": "product:Astoundify Jobify - Job Board WordPress Theme",
                  "keyphrase": "Astoundify Jobify - Job Board WordPress Theme",
                  "type": "product"
                },
                {
                  "id": "version:n/a through 4.2.3",
                  "keyphrase": "n/a through 4.2.3",
                  "type": "version"
                }
              ]
            },
            "similarity": 464.22028759951615
          },
          {
            "metadata": {
              "doc_id": "23",
              "name": "Relative Path Traversal",
              "source": "sparse",
              "original_content": "The product uses external input to construct a pathname that should be within a restricted directory, but it does not properly neutralize sequences such as \"..\" that can resolve to a location that is outside of that directory.",
              "keyphrase_sources": [
                {
                  "id": "rootcause:Improper Limitation of a Pathname to a Restricted Directory",
                  "keyphrase": "Improper Limitation of a Pathname to a Restricted Directory",
                  "type": "rootcause"
                },
                {
                  "id": "rootcause:Improper path traversal",
                  "keyphrase": "Improper path traversal",
                  "type": "rootcause"
                },
                {
                  "id": "impact:relative path traversal",
                  "keyphrase": "relative path traversal",
                  "type": "impact"
                },
                {
                  "id": "product:Astoundify Jobify - Job Board WordPress Theme",
                  "keyphrase": "Astoundify Jobify - Job Board WordPress Theme",
                  "type": "product"
                },
                {
                  "id": "version:n/a through 4.2.3",
                  "keyphrase": "n/a through 4.2.3",
                  "type": "version"
                }
              ]
            },
            "similarity": 384.6310214931923
          },
          {
            "metadata": {
              "doc_id": "24",
              "name": "Path Traversal: '../filedir'",
              "source": "sparse",
              "original_content": "The product uses external input to construct a pathname that should be within a restricted directory, but it does not properly neutralize \"../\" sequences that can resolve to a location that is outside of that directory.",
              "keyphrase_sources": [
                {
                  "id": "rootcause:Improper Limitation of a Pathname to a Restricted Directory",
                  "keyphrase": "Improper Limitation of a Pathname to a Restricted Directory",
                  "type": "rootcause"
                },
                {
                  "id": "rootcause:Improper path traversal",
                  "keyphrase": "Improper path traversal",
                  "type": "rootcause"
                },
                {
                  "id": "impact:relative path traversal",
                  "keyphrase": "relative path traversal",
                  "type": "impact"
                }
              ]
            },
            "similarity": 350.45432818513876
          },
          {
            "metadata": {
              "doc_id": "36",
              "name": "Absolute Path Traversal",
              "source": "sparse",
              "original_content": "The product uses external input to construct a pathname that should be within a restricted directory, but it does not properly neutralize absolute path sequences such as \"/abs/path\" that can resolve to a location that is outside of that directory.",
              "keyphrase_sources": [
                {
                  "id": "rootcause:Improper Limitation of a Pathname to a Restricted Directory",
                  "keyphrase": "Improper Limitation of a Pathname to a Restricted Directory",
                  "type": "rootcause"
                },
                {
                  "id": "rootcause:Improper path traversal",
                  "keyphrase": "Improper path traversal",
                  "type": "rootcause"
                },
                {
                  "id": "impact:relative path traversal",
                  "keyphrase": "relative path traversal",
                  "type": "impact"
                },
                {
                  "id": "version:n/a through 4.2.3",
                  "keyphrase": "n/a through 4.2.3",
                  "type": "version"
                }
              ]
            },
            "similarity": 346.3231996167128
          },
          {
            "metadata": {
              "doc_id": "29",
              "name": "Path Traversal: '\\..\\filename'",
              "source": "sparse",
              "original_content": "The product uses external input to construct a pathname that should be within a restricted directory, but it does not properly neutralize '\\..\\filename' (leading backslash dot dot) sequences that can resolve to a location that is outside of that directory.",
              "keyphrase_sources": [
                {
                  "id": "rootcause:Improper Limitation of a Pathname to a Restricted Directory",
                  "keyphrase": "Improper Limitation of a Pathname to a Restricted Directory",
                  "type": "rootcause"
                }
              ]
            },
            "similarity": 329.56320555163325
          }
        ]
      },
      "rootcause:Improper path traversal": {
        "keyphrase": "Improper path traversal",
        "type": "rootcause",
        "cwes": [
          {
            "metadata": {
              "doc_id": "22",
              "name": "Improper Limitation of a Pathname to a Restricted Directory ('Path Traversal')",
              "source": "sparse",
              "original_content": "The product uses external input to construct a pathname that is intended to identify a file or directory that is located underneath a restricted parent directory, but the product does not properly neutralize special elements within the pathname that can cause the pathname to resolve to a location that is outside of the restricted directory."
            },
            "similarity": 332.5355867779224
          },
          {
            "metadata": {
              "doc_id": "23",
              "name": "Relative Path Traversal",
              "source": "sparse",
              "original_content": "The product uses external input to construct a pathname that should be within a restricted directory, but it does not properly neutralize sequences such as \"..\" that can resolve to a location that is outside of that directory."
            },
            "similarity": 296.1979389300783
          },
          {
            "metadata": {
              "doc_id": "36",
              "name": "Absolute Path Traversal",
              "source": "sparse",
              "original_content": "The product uses external input to construct a pathname that should be within a restricted directory, but it does not properly neutralize absolute path sequences such as \"/abs/path\" that can resolve to a location that is outside of that directory."
            },
            "similarity": 264.79584621599156
          },
          {
            "metadata": {
              "doc_id": "24",
              "name": "Path Traversal: '../filedir'",
              "source": "sparse",
              "original_content": "The product uses external input to construct a pathname that should be within a restricted directory, but it does not properly neutralize \"../\" sequences that can resolve to a location that is outside of that directory."
            },
            "similarity": 246.69824460490486
          },
          {
            "metadata": {
              "doc_id": "73",
              "name": "External Control of File Name or Path",
              "source": "sparse",
              "original_content": "The product allows user input to control or influence paths or file names that are used in filesystem operations.",
              "keyphrase_sources": [
                {
                  "id": "rootcause:Improper path traversal",
                  "keyphrase": "Improper path traversal",
                  "type": "rootcause"
                }
              ]
            },
            "similarity": 237.0099011210729
          }
        ]
      },
      "impact:relative path traversal": {
        "keyphrase": "relative path traversal",
        "type": "impact",
        "cwes": [
          {
            "metadata": {
              "doc_id": "23",
              "name": "Relative Path Traversal",
              "source": "sparse",
              "original_content": "The product uses external input to construct a pathname that should be within a restricted directory, but it does not properly neutralize sequences such as \"..\" that can resolve to a location that is outside of that directory."
            },
            "similarity": 115.68008446534824
          },
          {
            "metadata": {
              "doc_id": "22",
              "name": "Improper Limitation of a Pathname to a Restricted Directory ('Path Traversal')",
              "source": "sparse",
              "original_content": "The product uses external input to construct a pathname that is intended to identify a file or directory that is located underneath a restricted parent directory, but the product does not properly neutralize special elements within the pathname that can cause the pathname to resolve to a location that is outside of the restricted directory."
            },
            "similarity": 113.07050264911203
          },
          {
            "metadata": {
              "doc_id": "98",
              "name": "Improper Control of Filename for Include/Require Statement in PHP Program ('PHP Remote File Inclusion')",
              "source": "sparse",
              "original_content": "The PHP application receives input from an upstream component, but it does not restrict or incorrectly restricts the input before its usage in \"require,\" \"include,\" or similar functions.",
              "keyphrase_sources": [
                {
                  "id": "impact:relative path traversal",
                  "keyphrase": "relative path traversal",
                  "type": "impact"
                }
              ]
            },
            "similarity": 89.3001487624816
          },
          {
            "metadata": {
              "doc_id": "36",
              "name": "Absolute Path Traversal",
              "source": "sparse",
              "original_content": "The product uses external input to construct a pathname that should be within a restricted directory, but it does not properly neutralize absolute path sequences such as \"/abs/path\" that can resolve to a location that is outside of that directory."
            },
            "similarity": 87.37714861170889
          },
          {
            "metadata": {
              "doc_id": "24",
              "name": "Path Traversal: '../filedir'",
              "source": "sparse",
              "original_content": "The product uses external input to construct a pathname that should be within a restricted directory, but it does not properly neutralize \"../\" sequences that can resolve to a location that is outside of that directory."
            },
            "similarity": 80.62131751371852
          }
        ]
      },
      "product:Astoundify Jobify - Job Board WordPress Theme": {
        "keyphrase": "Astoundify Jobify - Job Board WordPress Theme",
        "type": "product",
        "cwes": [
          {
            "metadata": {
              "doc_id": "22",
              "name": "Improper Limitation of a Pathname to a Restricted Directory ('Path Traversal')",
              "source": "sparse",
              "original_content": "The product uses external input to construct a pathname that is intended to identify a file or directory that is located underneath a restricted parent directory, but the product does not properly neutralize special elements within the pathname that can cause the pathname to resolve to a location that is outside of the restricted directory."
            },
            "similarity": 100.52701195082234
          },
          {
            "metadata": {
              "doc_id": "548",
              "name": "Exposure of Information Through Directory Listing",
              "source": "sparse",
              "original_content": "A directory listing is inappropriately exposed, yielding potentially sensitive information to attackers.",
              "keyphrase_sources": [
                {
                  "id": "product:Astoundify Jobify - Job Board WordPress Theme",
                  "keyphrase": "Astoundify Jobify - Job Board WordPress Theme",
                  "type": "product"
                }
              ]
            },
            "similarity": 88.73084888163717
          },
          {
            "metadata": {
              "doc_id": "23",
              "name": "Relative Path Traversal",
              "source": "sparse",
              "original_content": "The product uses external input to construct a pathname that should be within a restricted directory, but it does not properly neutralize sequences such as \"..\" that can resolve to a location that is outside of that directory."
            },
            "similarity": 85.76824328495536
          },
          {
            "metadata": {
              "doc_id": "306",
              "name": "Missing Authentication for Critical Function",
              "source": "sparse",
              "original_content": "The product does not perform any authentication for functionality that requires a provable user identity or consumes a significant amount of resources.",
              "keyphrase_sources": [
                {
                  "id": "product:Astoundify Jobify - Job Board WordPress Theme",
                  "keyphrase": "Astoundify Jobify - Job Board WordPress Theme",
                  "type": "product"
                },
                {
                  "id": "version:n/a through 4.2.3",
                  "keyphrase": "n/a through 4.2.3",
                  "type": "version"
                }
              ]
            },
            "similarity": 81.21909766324933
          },
          {
            "metadata": {
              "doc_id": "434",
              "name": "Unrestricted Upload of File with Dangerous Type",
              "source": "sparse",
              "original_content": "The product allows the upload or transfer of dangerous file types that are automatically processed within its environment.",
              "keyphrase_sources": [
                {
                  "id": "product:Astoundify Jobify - Job Board WordPress Theme",
                  "keyphrase": "Astoundify Jobify - Job Board WordPress Theme",
                  "type": "product"
                },
                {
                  "id": "version:n/a through 4.2.3",
                  "keyphrase": "n/a through 4.2.3",
                  "type": "version"
                }
              ]
            },
            "similarity": 80.84590742134448
          }
        ]
      },
      "version:n/a through 4.2.3": {
        "keyphrase": "n/a through 4.2.3",
        "type": "version",
        "cwes": [
          {
            "metadata": {
              "doc_id": "22",
              "name": "Improper Limitation of a Pathname to a Restricted Directory ('Path Traversal')",
              "source": "sparse",
              "original_content": "The product uses external input to construct a pathname that is intended to identify a file or directory that is located underneath a restricted parent directory, but the product does not properly neutralize special elements within the pathname that can cause the pathname to resolve to a location that is outside of the restricted directory."
            },
            "similarity": 118.97648371789866
          },
          {
            "metadata": {
              "doc_id": "23",
              "name": "Relative Path Traversal",
              "source": "sparse",
              "original_content": "The product uses external input to construct a pathname that should be within a restricted directory, but it does not properly neutralize sequences such as \"..\" that can resolve to a location that is outside of that directory."
            },
            "similarity": 98.08496178126046
          },
          {
            "metadata": {
              "doc_id": "36",
              "name": "Absolute Path Traversal",
              "source": "sparse",
              "original_content": "The product uses external input to construct a pathname that should be within a restricted directory, but it does not properly neutralize absolute path sequences such as \"/abs/path\" that can resolve to a location that is outside of that directory."
            },
            "similarity": 91.97846744981464
          },
          {
            "metadata": {
              "doc_id": "434",
              "name": "Unrestricted Upload of File with Dangerous Type",
              "source": "sparse",
              "original_content": "The product allows the upload or transfer of dangerous file types that are automatically processed within its environment."
            },
            "similarity": 88.06456641804384
          },
          {
            "metadata": {
              "doc_id": "306",
              "name": "Missing Authentication for Critical Function",
              "source": "sparse",
              "original_content": "The product does not perform any authentication for functionality that requires a provable user identity or consumes a significant amount of resources."
            },
            "similarity": 83.7621331439968
          }
        ]
      }
    },
    "keyphrase_mapping": {
      "22": [
        {
          "id": "rootcause:Improper Limitation of a Pathname to a Restricted Directory",
          "keyphrase": "Improper Limitation of a Pathname to a Restricted Directory",
          "type": "rootcause"
        },
        {
          "id": "rootcause:Improper path traversal",
          "keyphrase": "Improper path traversal",
          "type": "rootcause"
        },
        {
          "id": "impact:relative path traversal",
          "keyphrase": "relative path traversal",
          "type": "impact"
        },
        {
          "id": "product:Astoundify Jobify - Job Board WordPress Theme",
          "keyphrase": "Astoundify Jobify - Job Board WordPress Theme",
          "type": "product"
        },
        {
          "id": "version:n/a through 4.2.3",
          "keyphrase": "n/a through 4.2.3",
          "type": "version"
        }
      ],
      "23": [
        {
          "id": "rootcause:Improper Limitation of a Pathname to a Restricted Directory",
          "keyphrase": "Improper Limitation of a Pathname to a Restricted Directory",
          "type": "rootcause"
        },
        {
          "id": "rootcause:Improper path traversal",
          "keyphrase": "Improper path traversal",
          "type": "rootcause"
        },
        {
          "id": "impact:relative path traversal",
          "keyphrase": "relative path traversal",
          "type": "impact"
        },
        {
          "id": "product:Astoundify Jobify - Job Board WordPress Theme",
          "keyphrase": "Astoundify Jobify - Job Board WordPress Theme",
          "type": "product"
        },
        {
          "id": "version:n/a through 4.2.3",
          "keyphrase": "n/a through 4.2.3",
          "type": "version"
        }
      ],
      "24": [
        {
          "id": "rootcause:Improper Limitation of a Pathname to a Restricted Directory",
          "keyphrase": "Improper Limitation of a Pathname to a Restricted Directory",
          "type": "rootcause"
        },
        {
          "id": "rootcause:Improper path traversal",
          "keyphrase": "Improper path traversal",
          "type": "rootcause"
        },
        {
          "id": "impact:relative path traversal",
          "keyphrase": "relative path traversal",
          "type": "impact"
        }
      ],
      "36": [
        {
          "id": "rootcause:Improper Limitation of a Pathname to a Restricted Directory",
          "keyphrase": "Improper Limitation of a Pathname to a Restricted Directory",
          "type": "rootcause"
        },
        {
          "id": "rootcause:Improper path traversal",
          "keyphrase": "Improper path traversal",
          "type": "rootcause"
        },
        {
          "id": "impact:relative path traversal",
          "keyphrase": "relative path traversal",
          "type": "impact"
        },
        {
          "id": "version:n/a through 4.2.3",
          "keyphrase": "n/a through 4.2.3",
          "type": "version"
        }
      ],
      "29": [
        {
          "id": "rootcause:Improper Limitation of a Pathname to a Restricted Directory",
          "keyphrase": "Improper Limitation of a Pathname to a Restricted Directory",
          "type": "rootcause"
        }
      ],
      "73": [
        {
          "id": "rootcause:Improper path traversal",
          "keyphrase": "Improper path traversal",
          "type": "rootcause"
        }
      ],
      "98": [
        {
          "id": "impact:relative path traversal",
          "keyphrase": "relative path traversal",
          "type": "impact"
        }
      ],
      "548": [
        {
          "id": "product:Astoundify Jobify - Job Board WordPress Theme",
          "keyphrase": "Astoundify Jobify - Job Board WordPress Theme",
          "type": "product"
        }
      ],
      "306": [
        {
          "id": "product:Astoundify Jobify - Job Board WordPress Theme",
          "keyphrase": "Astoundify Jobify - Job Board WordPress Theme",
          "type": "product"
        },
        {
          "id": "version:n/a through 4.2.3",
          "keyphrase": "n/a through 4.2.3",
          "type": "version"
        }
      ],
      "434": [
        {
          "id": "product:Astoundify Jobify - Job Board WordPress Theme",
          "keyphrase": "Astoundify Jobify - Job Board WordPress Theme",
          "type": "product"
        },
        {
          "id": "version:n/a through 4.2.3",
          "keyphrase": "n/a through 4.2.3",
          "type": "version"
        }
      ]
    },
    "relevant_cwes": [
      {
        "metadata": {
          "doc_id": "22",
          "name": "Improper Limitation of a Pathname to a Restricted Directory ('Path Traversal')",
          "source": "sparse",
          "original_content": "The product uses external input to construct a pathname that is intended to identify a file or directory that is located underneath a restricted parent directory, but the product does not properly neutralize special elements within the pathname that can cause the pathname to resolve to a location that is outside of the restricted directory.",
          "keyphrase_sources": [
            {
              "id": "rootcause:Improper Limitation of a Pathname to a Restricted Directory",
              "keyphrase": "Improper Limitation of a Pathname to a Restricted Directory",
              "type": "rootcause"
            },
            {
              "id": "rootcause:Improper path traversal",
              "keyphrase": "Improper path traversal",
              "type": "rootcause"
            },
            {
              "id": "impact:relative path traversal",
              "keyphrase": "relative path traversal",
              "type": "impact"
            },
            {
              "id": "product:Astoundify Jobify - Job Board WordPress Theme",
              "keyphrase": "Astoundify Jobify - Job Board WordPress Theme",
              "type": "product"
            },
            {
              "id": "version:n/a through 4.2.3",
              "keyphrase": "n/a through 4.2.3",
              "type": "version"
            }
          ]
        },
        "similarity": 464.22028759951615
      },
      {
        "metadata": {
          "doc_id": "23",
          "name": "Relative Path Traversal",
          "source": "sparse",
          "original_content": "The product uses external input to construct a pathname that should be within a restricted directory, but it does not properly neutralize sequences such as \"..\" that can resolve to a location that is outside of that directory.",
          "keyphrase_sources": [
            {
              "id": "rootcause:Improper Limitation of a Pathname to a Restricted Directory",
              "keyphrase": "Improper Limitation of a Pathname to a Restricted Directory",
              "type": "rootcause"
            },
            {
              "id": "rootcause:Improper path traversal",
              "keyphrase": "Improper path traversal",
              "type": "rootcause"
            },
            {
              "id": "impact:relative path traversal",
              "keyphrase": "relative path traversal",
              "type": "impact"
            },
            {
              "id": "product:Astoundify Jobify - Job Board WordPress Theme",
              "keyphrase": "Astoundify Jobify - Job Board WordPress Theme",
              "type": "product"
            },
            {
              "id": "version:n/a through 4.2.3",
              "keyphrase": "n/a through 4.2.3",
              "type": "version"
            }
          ]
        },
        "similarity": 384.6310214931923
      },
      {
        "metadata": {
          "doc_id": "24",
          "name": "Path Traversal: '../filedir'",
          "source": "sparse",
          "original_content": "The product uses external input to construct a pathname that should be within a restricted directory, but it does not properly neutralize \"../\" sequences that can resolve to a location that is outside of that directory.",
          "keyphrase_sources": [
            {
              "id": "rootcause:Improper Limitation of a Pathname to a Restricted Directory",
              "keyphrase": "Improper Limitation of a Pathname to a Restricted Directory",
              "type": "rootcause"
            },
            {
              "id": "rootcause:Improper path traversal",
              "keyphrase": "Improper path traversal",
              "type": "rootcause"
            },
            {
              "id": "impact:relative path traversal",
              "keyphrase": "relative path traversal",
              "type": "impact"
            }
          ]
        },
        "similarity": 350.45432818513876
      },
      {
        "metadata": {
          "doc_id": "36",
          "name": "Absolute Path Traversal",
          "source": "sparse",
          "original_content": "The product uses external input to construct a pathname that should be within a restricted directory, but it does not properly neutralize absolute path sequences such as \"/abs/path\" that can resolve to a location that is outside of that directory.",
          "keyphrase_sources": [
            {
              "id": "rootcause:Improper Limitation of a Pathname to a Restricted Directory",
              "keyphrase": "Improper Limitation of a Pathname to a Restricted Directory",
              "type": "rootcause"
            },
            {
              "id": "rootcause:Improper path traversal",
              "keyphrase": "Improper path traversal",
              "type": "rootcause"
            },
            {
              "id": "impact:relative path traversal",
              "keyphrase": "relative path traversal",
              "type": "impact"
            },
            {
              "id": "version:n/a through 4.2.3",
              "keyphrase": "n/a through 4.2.3",
              "type": "version"
            }
          ]
        },
        "similarity": 346.3231996167128
      },
      {
        "metadata": {
          "doc_id": "29",
          "name": "Path Traversal: '\\..\\filename'",
          "source": "sparse",
          "original_content": "The product uses external input to construct a pathname that should be within a restricted directory, but it does not properly neutralize '\\..\\filename' (leading backslash dot dot) sequences that can resolve to a location that is outside of that directory.",
          "keyphrase_sources": [
            {
              "id": "rootcause:Improper Limitation of a Pathname to a Restricted Directory",
              "keyphrase": "Improper Limitation of a Pathname to a Restricted Directory",
              "type": "rootcause"
            }
          ]
        },
        "similarity": 329.56320555163325
      },
      {
        "metadata": {
          "doc_id": "73",
          "name": "External Control of File Name or Path",
          "source": "sparse",
          "original_content": "The product allows user input to control or influence paths or file names that are used in filesystem operations.",
          "keyphrase_sources": [
            {
              "id": "rootcause:Improper path traversal",
              "keyphrase": "Improper path traversal",
              "type": "rootcause"
            }
          ]
        },
        "similarity": 237.0099011210729
      },
      {
        "metadata": {
          "doc_id": "98",
          "name": "Improper Control of Filename for Include/Require Statement in PHP Program ('PHP Remote File Inclusion')",
          "source": "sparse",
          "original_content": "The PHP application receives input from an upstream component, but it does not restrict or incorrectly restricts the input before its usage in \"require,\" \"include,\" or similar functions.",
          "keyphrase_sources": [
            {
              "id": "impact:relative path traversal",
              "keyphrase": "relative path traversal",
              "type": "impact"
            }
          ]
        },
        "similarity": 89.3001487624816
      },
      {
        "metadata": {
          "doc_id": "548",
          "name": "Exposure of Information Through Directory Listing",
          "source": "sparse",
          "original_content": "A directory listing is inappropriately exposed, yielding potentially sensitive information to attackers.",
          "keyphrase_sources": [
            {
              "id": "product:Astoundify Jobify - Job Board WordPress Theme",
              "keyphrase": "Astoundify Jobify - Job Board WordPress Theme",
              "type": "product"
            }
          ]
        },
        "similarity": 88.73084888163717
      },
      {
        "metadata": {
          "doc_id": "306",
          "name": "Missing Authentication for Critical Function",
          "source": "sparse",
          "original_content": "The product does not perform any authentication for functionality that requires a provable user identity or consumes a significant amount of resources.",
          "keyphrase_sources": [
            {
              "id": "product:Astoundify Jobify - Job Board WordPress Theme",
              "keyphrase": "Astoundify Jobify - Job Board WordPress Theme",
              "type": "product"
            },
            {
              "id": "version:n/a through 4.2.3",
              "keyphrase": "n/a through 4.2.3",
              "type": "version"
            }
          ]
        },
        "similarity": 81.21909766324933
      },
      {
        "metadata": {
          "doc_id": "434",
          "name": "Unrestricted Upload of File with Dangerous Type",
          "source": "sparse",
          "original_content": "The product allows the upload or transfer of dangerous file types that are automatically processed within its environment.",
          "keyphrase_sources": [
            {
              "id": "product:Astoundify Jobify - Job Board WordPress Theme",
              "keyphrase": "Astoundify Jobify - Job Board WordPress Theme",
              "type": "product"
            },
            {
              "id": "version:n/a through 4.2.3",
              "keyphrase": "n/a through 4.2.3",
              "type": "version"
            }
          ]
        },
        "similarity": 80.84590742134448
      }
    ],
    "enhanced_query": "# Vulnerability Description\n\n    **Improper Limitation of a Pathname to a Restricted Directory** (Path Traversal) vulnerability in Astoundify Jobify - Job Board WordPress Theme allows Relative Path Traversal.This issue affects Jobify - Job Board WordPress Theme from n/a through 4.2.3.\n\n    # Keyphrase-Specific CWE Analysis\n    This vulnerability contains multiple keyphrases that may map to different CWEs. \n    Please analyze each keyphrase separately and determine the most appropriate CWE(s) for each.\n\n    ## ROOTCAUSE: 'Improper Limitation of a Pathname to a Restricted Directory'\n\nRelevant CWEs for this ROOTCAUSE:\n\n### 1. CWE-22: Improper Limitation of a Pathname to a Restricted Directory ('Path Traversal') (Score: 464.22)\n\nThe product uses external input to construct a pathname that is intended to identify a file or directory that is located underneath a restricted parent directory, but the product does not properly neutralize special elements within the pathname that can cause the pathname to resolve to a location th...\n\n### 2. CWE-23: Relative Path Traversal (Score: 384.63)\n\nThe product uses external input to construct a pathname that should be within a restricted directory, but it does not properly neutralize sequences such as \"..\" that can resolve to a location that is outside of that directory....\n\n### 3. CWE-24: Path Traversal: '../filedir' (Score: 350.45)\n\nThe product uses external input to construct a pathname that should be within a restricted directory, but it does not properly neutralize \"../\" sequences that can resolve to a location that is outside of that directory....\n\n### 4. CWE-36: Absolute Path Traversal (Score: 346.32)\n\nThe product uses external input to construct a pathname that should be within a restricted directory, but it does not properly neutralize absolute path sequences such as \"/abs/path\" that can resolve to a location that is outside of that directory....\n\n### 5. CWE-29: Path Traversal: '\\..\\filename' (Score: 329.56)\n\nThe product uses external input to construct a pathname that should be within a restricted directory, but it does not properly neutralize '\\..\\filename' (leading backslash dot dot) sequences that can resolve to a location that is outside of that directory....\n\n## ROOTCAUSE: 'Improper path traversal'\n\nRelevant CWEs for this ROOTCAUSE:\n\n### 1. CWE-22: Improper Limitation of a Pathname to a Restricted Directory ('Path Traversal') (Score: 464.22)\n\nThe product uses external input to construct a pathname that is intended to identify a file or directory that is located underneath a restricted parent directory, but the product does not properly neutralize special elements within the pathname that can cause the pathname to resolve to a location th...\n\n### 2. CWE-23: Relative Path Traversal (Score: 384.63)\n\nThe product uses external input to construct a pathname that should be within a restricted directory, but it does not properly neutralize sequences such as \"..\" that can resolve to a location that is outside of that directory....\n\n### 3. CWE-24: Path Traversal: '../filedir' (Score: 350.45)\n\nThe product uses external input to construct a pathname that should be within a restricted directory, but it does not properly neutralize \"../\" sequences that can resolve to a location that is outside of that directory....\n\n### 4. CWE-36: Absolute Path Traversal (Score: 346.32)\n\nThe product uses external input to construct a pathname that should be within a restricted directory, but it does not properly neutralize absolute path sequences such as \"/abs/path\" that can resolve to a location that is outside of that directory....\n\n### 5. CWE-73: External Control of File Name or Path (Score: 237.01)\n\nThe product allows user input to control or influence paths or file names that are used in filesystem operations....\n\n## IMPACT: 'relative path traversal'\n\nRelevant CWEs for this IMPACT:\n\n### 1. CWE-22: Improper Limitation of a Pathname to a Restricted Directory ('Path Traversal') (Score: 464.22)\n\nThe product uses external input to construct a pathname that is intended to identify a file or directory that is located underneath a restricted parent directory, but the product does not properly neutralize special elements within the pathname that can cause the pathname to resolve to a location th...\n\n### 2. CWE-23: Relative Path Traversal (Score: 384.63)\n\nThe product uses external input to construct a pathname that should be within a restricted directory, but it does not properly neutralize sequences such as \"..\" that can resolve to a location that is outside of that directory....\n\n### 3. CWE-24: Path Traversal: '../filedir' (Score: 350.45)\n\nThe product uses external input to construct a pathname that should be within a restricted directory, but it does not properly neutralize \"../\" sequences that can resolve to a location that is outside of that directory....\n\n### 4. CWE-36: Absolute Path Traversal (Score: 346.32)\n\nThe product uses external input to construct a pathname that should be within a restricted directory, but it does not properly neutralize absolute path sequences such as \"/abs/path\" that can resolve to a location that is outside of that directory....\n\n### 5. CWE-98: Improper Control of Filename for Include/Require Statement in PHP Program ('PHP Remote File Inclusion') (Score: 89.30)\n\nThe PHP application receives input from an upstream component, but it does not restrict or incorrectly restricts the input before its usage in \"require,\" \"include,\" or similar functions....\n\n## PRODUCT: 'Astoundify Jobify - Job Board WordPress Theme'\n\nRelevant CWEs for this PRODUCT:\n\n### 1. CWE-22: Improper Limitation of a Pathname to a Restricted Directory ('Path Traversal') (Score: 464.22)\n\nThe product uses external input to construct a pathname that is intended to identify a file or directory that is located underneath a restricted parent directory, but the product does not properly neutralize special elements within the pathname that can cause the pathname to resolve to a location th...\n\n### 2. CWE-23: Relative Path Traversal (Score: 384.63)\n\nThe product uses external input to construct a pathname that should be within a restricted directory, but it does not properly neutralize sequences such as \"..\" that can resolve to a location that is outside of that directory....\n\n### 3. CWE-548: Exposure of Information Through Directory Listing (Score: 88.73)\n\nA directory listing is inappropriately exposed, yielding potentially sensitive information to attackers....\n\n### 4. CWE-306: Missing Authentication for Critical Function (Score: 81.22)\n\nThe product does not perform any authentication for functionality that requires a provable user identity or consumes a significant amount of resources....\n\n### 5. CWE-434: Unrestricted Upload of File with Dangerous Type (Score: 80.85)\n\nThe product allows the upload or transfer of dangerous file types that are automatically processed within its environment....\n\n## VERSION: 'n/a through 4.2.3'\n\nRelevant CWEs for this VERSION:\n\n### 1. CWE-22: Improper Limitation of a Pathname to a Restricted Directory ('Path Traversal') (Score: 464.22)\n\nThe product uses external input to construct a pathname that is intended to identify a file or directory that is located underneath a restricted parent directory, but the product does not properly neutralize special elements within the pathname that can cause the pathname to resolve to a location th...\n\n### 2. CWE-23: Relative Path Traversal (Score: 384.63)\n\nThe product uses external input to construct a pathname that should be within a restricted directory, but it does not properly neutralize sequences such as \"..\" that can resolve to a location that is outside of that directory....\n\n### 3. CWE-36: Absolute Path Traversal (Score: 346.32)\n\nThe product uses external input to construct a pathname that should be within a restricted directory, but it does not properly neutralize absolute path sequences such as \"/abs/path\" that can resolve to a location that is outside of that directory....\n\n### 4. CWE-306: Missing Authentication for Critical Function (Score: 81.22)\n\nThe product does not perform any authentication for functionality that requires a provable user identity or consumes a significant amount of resources....\n\n### 5. CWE-434: Unrestricted Upload of File with Dangerous Type (Score: 80.85)\n\nThe product allows the upload or transfer of dangerous file types that are automatically processed within its environment....\n\n\n    # Analysis Instructions\n    1. For each keyphrase, identify the most appropriate CWE(s) that represent the weakness.\n    2. Consider how the different keyphrases might relate to each other in the vulnerability chain.\n    3. Provide a final determination of primary CWE(s) and any secondary CWEs.\n    4. Format your response using the standard analysis template.\n\n    Please analyze how these different weaknesses interact and provide a comprehensive CWE classification.\n    "
  },
  "retrieval_time": 1.0808734893798828
}