{
  "vulnerability_info": "VulnerabilityInfo(cve_id='CVE-2024-13676', description='The Categorized Gallery Plugin plugin for WordPress is vulnerable to **SQL Injection** via the field attribute of the image_gallery shortcode in all versions up to, and including, 2.0 due to **insufficient escaping on the user supplied parameter and lack of sufficient preparation on the existing SQL query**. This makes it possible for authenticated attackers, with Contributor-level access and above, to append additional SQL queries into already existing queries that can be used to extract sensitive information from the database.', key_phrases={'rootcause': ['insufficient escaping on the user supplied parameter and lack of sufficient preparation on the existing SQL query', 'insufficient escaping on user-supplied parameter'], 'weakness': 'SQL Injection', 'impact': 'extract sensitive information from the database', 'vector': '', 'attacker': 'authenticated attackers with Contributor-level access and above', 'product': 'Categorized Gallery Plugin for WordPress', 'version': 'all versions up to and including 2.0', 'component': 'image_gallery shortcode'}, reference_content='This content relates to CVE-2024-13676, as it is source code from the \"categorized-gallery\" WordPress plugin, which is the affected product. The content provides more detail than the official CVE description.\\n\\n**Root cause of vulnerability:**\\n\\nThe code creates database tables (`galcategory` and `galimage`) and defines functions to interact with them. The vulnerability likely stems from insufficient input validation or sanitization when handling user-supplied data that is used in these database queries. While the code itself doesn\\'t *show* the vulnerability, it establishes the foundation where such a vulnerability could exist.\\n\\n**Weaknesses/vulnerabilities present:**\\n\\n*   **Potential SQL Injection:** The code uses direct string concatenation to build SQL queries (lines 38-49, 53-67, 175-178). This is a classic SQL injection vulnerability if user-supplied data is not properly sanitized before being included in these queries.\\n*   **File Upload Vulnerabilities:** The code handles file uploads (lines 11-32).  There\\'s no explicit check for file types or sizes, which could lead to arbitrary file uploads.\\n*   **Path Traversal:** The code uses `plugin_dir_path(__FILE__)` to define the base directory, but the subsequent handling of file paths (e.g., in file operations) could be vulnerable to path traversal if not carefully managed.\\n*   **Cross-Site Scripting (XSS):** The code retrieves data from the database and displays it (e.g., image titles, category names). If this data is not properly escaped before being output, it could lead to XSS vulnerabilities.\\n\\n**Impact of exploitation:**\\n\\n*   **SQL Injection:** An attacker could potentially read, modify, or delete data in the WordPress database, leading to complete compromise of the website.\\n*   **Arbitrary File Upload:** An attacker could upload malicious files (e.g., PHP scripts) to the server, potentially gaining remote code execution.\\n*   **Path Traversal:** An attacker could access sensitive files on the server.\\n*   **XSS:** An attacker could inject malicious JavaScript code into the website, potentially stealing user credentials or defacing the website.\\n\\n**Attack vectors:**\\n\\n*   **SQL Injection:** Through plugin settings, shortcode attributes, or any other input field that is used in a database query.\\n*   **Arbitrary File Upload:** Through the plugin\\'s file upload functionality.\\n*   **Path Traversal:** Through manipulated file paths in plugin settings or shortcode attributes.\\n*   **XSS:** Through user-supplied data that is displayed on the website without proper escaping.\\n\\n**Required attacker capabilities/position:**\\n\\n*   **SQL Injection:** An attacker needs to be able to inject malicious SQL code into an input field. This could require a low-privilege user account or the ability to manipulate plugin settings.\\n*   **Arbitrary File Upload:** An attacker needs to be able to upload files to the server through the plugin\\'s file upload functionality.\\n*   **Path Traversal:** An attacker needs to be able to manipulate file paths in plugin settings or shortcode attributes.\\n*   **XSS:** An attacker needs to be able to inject malicious JavaScript code into an input field that is displayed on the website.\\n\\n**Mitigation or fix:**\\n\\n*   **Prepared Statements:** Use prepared statements with parameterized queries to prevent SQL injection.\\n*   **Input Validation and Sanitization:** Validate and sanitize all user-supplied data before using it in database queries or file operations.\\n*   **File Type and Size Validation:** Implement strict file type and size validation to prevent arbitrary file uploads.\\n*   **Path Sanitization:** Sanitize file paths to prevent path traversal.\\n*   **Output Encoding:** Encode all data before displaying it on the website to prevent XSS.\\n*   **Principle of Least Privilege:** Ensure that the plugin only has the necessary permissions to perform its functions.', similar_info={'cwe_distribution': {}, 'cwe_consensus': '', 'similarity_stats': {'thresholds': [], 'total_samples_by_threshold': {}, 'top_cwes_by_threshold': {}}}, similarity_summary=SimilarityInsight(consensus_cwe='', top_cwes=[], confidence_levels={}, total_samples=0), analysis='', analysis_with_relationships='', criticism='', resolution='', relevant_cwes=[{'metadata': {'doc_id': '116', 'name': 'Improper Encoding or Escaping of Output', 'source': 'sparse', 'original_content': 'The product prepares a structured message for communication with another component, but encoding or escaping of the data is either missing or done incorrectly. As a result, the intended structure of the message is not preserved.', 'keyphrase_sources': [{'id': 'rootcause:insufficient escaping on the user supplied parameter and lack of sufficient preparation on the existing SQL query', 'keyphrase': 'insufficient escaping on the user supplied parameter and lack of sufficient preparation on the existing SQL query', 'type': 'rootcause'}, {'id': 'rootcause:insufficient escaping on user-supplied parameter', 'keyphrase': 'insufficient escaping on user-supplied parameter', 'type': 'rootcause'}, {'id': 'weakness:SQL Injection', 'keyphrase': 'SQL Injection', 'type': 'weakness'}, {'id': 'impact:extract sensitive information from the database', 'keyphrase': 'extract sensitive information from the database', 'type': 'impact'}, {'id': 'attacker:authenticated attackers with Contributor-level access and above', 'keyphrase': 'authenticated attackers with Contributor-level access and above', 'type': 'attacker'}, {'id': 'product:Categorized Gallery Plugin for WordPress', 'keyphrase': 'Categorized Gallery Plugin for WordPress', 'type': 'product'}, {'id': 'version:all versions up to and including 2.0', 'keyphrase': 'all versions up to and including 2.0', 'type': 'version'}, {'id': 'component:image_gallery shortcode', 'keyphrase': 'image_gallery shortcode', 'type': 'component'}]}, 'similarity': np.float64(765.765703409179)}, {'metadata': {'doc_id': '89', 'name': \"Improper Neutralization of Special Elements used in an SQL Command ('SQL Injection')\", 'source': 'sparse', 'original_content': 'The product constructs all or part of an SQL command using externally-influenced input from an upstream component, but it does not neutralize or incorrectly neutralizes special elements that could modify the intended SQL command when it is sent to a downstream component. Without sufficient removal or quoting of SQL syntax in user-controllable inputs, the generated SQL query can cause those inputs to be interpreted as SQL instead of ordinary user data.', 'keyphrase_sources': [{'id': 'rootcause:insufficient escaping on the user supplied parameter and lack of sufficient preparation on the existing SQL query', 'keyphrase': 'insufficient escaping on the user supplied parameter and lack of sufficient preparation on the existing SQL query', 'type': 'rootcause'}, {'id': 'rootcause:insufficient escaping on user-supplied parameter', 'keyphrase': 'insufficient escaping on user-supplied parameter', 'type': 'rootcause'}, {'id': 'weakness:SQL Injection', 'keyphrase': 'SQL Injection', 'type': 'weakness'}, {'id': 'impact:extract sensitive information from the database', 'keyphrase': 'extract sensitive information from the database', 'type': 'impact'}, {'id': 'attacker:authenticated attackers with Contributor-level access and above', 'keyphrase': 'authenticated attackers with Contributor-level access and above', 'type': 'attacker'}, {'id': 'product:Categorized Gallery Plugin for WordPress', 'keyphrase': 'Categorized Gallery Plugin for WordPress', 'type': 'product'}, {'id': 'version:all versions up to and including 2.0', 'keyphrase': 'all versions up to and including 2.0', 'type': 'version'}, {'id': 'component:image_gallery shortcode', 'keyphrase': 'image_gallery shortcode', 'type': 'component'}]}, 'similarity': np.float64(754.5125471309423)}, {'metadata': {'doc_id': '352', 'name': 'Cross-Site Request Forgery (CSRF)', 'source': 'sparse', 'original_content': 'The web application does not, or can not, sufficiently verify whether a well-formed, valid, consistent request was intentionally provided by the user who submitted the request.', 'keyphrase_sources': [{'id': 'rootcause:insufficient escaping on the user supplied parameter and lack of sufficient preparation on the existing SQL query', 'keyphrase': 'insufficient escaping on the user supplied parameter and lack of sufficient preparation on the existing SQL query', 'type': 'rootcause'}, {'id': 'rootcause:insufficient escaping on user-supplied parameter', 'keyphrase': 'insufficient escaping on user-supplied parameter', 'type': 'rootcause'}, {'id': 'weakness:SQL Injection', 'keyphrase': 'SQL Injection', 'type': 'weakness'}, {'id': 'impact:extract sensitive information from the database', 'keyphrase': 'extract sensitive information from the database', 'type': 'impact'}, {'id': 'attacker:authenticated attackers with Contributor-level access and above', 'keyphrase': 'authenticated attackers with Contributor-level access and above', 'type': 'attacker'}, {'id': 'product:Categorized Gallery Plugin for WordPress', 'keyphrase': 'Categorized Gallery Plugin for WordPress', 'type': 'product'}, {'id': 'version:all versions up to and including 2.0', 'keyphrase': 'all versions up to and including 2.0', 'type': 'version'}, {'id': 'component:image_gallery shortcode', 'keyphrase': 'image_gallery shortcode', 'type': 'component'}]}, 'similarity': np.float64(713.0766316253419)}, {'metadata': {'doc_id': '90', 'name': \"Improper Neutralization of Special Elements used in an LDAP Query ('LDAP Injection')\", 'source': 'sparse', 'original_content': 'The product constructs all or part of an LDAP query using externally-influenced input from an upstream component, but it does not neutralize or incorrectly neutralizes special elements that could modify the intended LDAP query when it is sent to a downstream component.', 'keyphrase_sources': [{'id': 'rootcause:insufficient escaping on the user supplied parameter and lack of sufficient preparation on the existing SQL query', 'keyphrase': 'insufficient escaping on the user supplied parameter and lack of sufficient preparation on the existing SQL query', 'type': 'rootcause'}, {'id': 'rootcause:insufficient escaping on user-supplied parameter', 'keyphrase': 'insufficient escaping on user-supplied parameter', 'type': 'rootcause'}, {'id': 'weakness:SQL Injection', 'keyphrase': 'SQL Injection', 'type': 'weakness'}, {'id': 'impact:extract sensitive information from the database', 'keyphrase': 'extract sensitive information from the database', 'type': 'impact'}, {'id': 'version:all versions up to and including 2.0', 'keyphrase': 'all versions up to and including 2.0', 'type': 'version'}, {'id': 'component:image_gallery shortcode', 'keyphrase': 'image_gallery shortcode', 'type': 'component'}]}, 'similarity': np.float64(708.8211331127097)}, {'metadata': {'doc_id': '790', 'name': 'Improper Filtering of Special Elements', 'source': 'sparse', 'original_content': 'The product receives data from an upstream component, but does not filter or incorrectly filters special elements before sending it to a downstream component.', 'keyphrase_sources': [{'id': 'rootcause:insufficient escaping on the user supplied parameter and lack of sufficient preparation on the existing SQL query', 'keyphrase': 'insufficient escaping on the user supplied parameter and lack of sufficient preparation on the existing SQL query', 'type': 'rootcause'}, {'id': 'rootcause:insufficient escaping on user-supplied parameter', 'keyphrase': 'insufficient escaping on user-supplied parameter', 'type': 'rootcause'}]}, 'similarity': np.float64(654.1421537842625)}, {'metadata': {'doc_id': '502', 'name': 'Deserialization of Untrusted Data', 'source': 'sparse', 'original_content': 'The product deserializes untrusted data without sufficiently ensuring that the resulting data will be valid.', 'keyphrase_sources': [{'id': 'weakness:SQL Injection', 'keyphrase': 'SQL Injection', 'type': 'weakness'}]}, 'similarity': np.float64(463.33118435086993)}, {'metadata': {'doc_id': '862', 'name': 'Missing Authorization', 'source': 'sparse', 'original_content': 'The product does not perform an authorization check when an actor attempts to access a resource or perform an action.', 'keyphrase_sources': [{'id': 'attacker:authenticated attackers with Contributor-level access and above', 'keyphrase': 'authenticated attackers with Contributor-level access and above', 'type': 'attacker'}, {'id': 'product:Categorized Gallery Plugin for WordPress', 'keyphrase': 'Categorized Gallery Plugin for WordPress', 'type': 'product'}]}, 'similarity': np.float64(186.32129857150235)}, {'metadata': {'doc_id': '863', 'name': 'Incorrect Authorization', 'source': 'sparse', 'original_content': 'The product performs an authorization check when an actor attempts to access a resource or perform an action, but it does not correctly perform the check.', 'keyphrase_sources': [{'id': 'impact:extract sensitive information from the database', 'keyphrase': 'extract sensitive information from the database', 'type': 'impact'}, {'id': 'attacker:authenticated attackers with Contributor-level access and above', 'keyphrase': 'authenticated attackers with Contributor-level access and above', 'type': 'attacker'}, {'id': 'product:Categorized Gallery Plugin for WordPress', 'keyphrase': 'Categorized Gallery Plugin for WordPress', 'type': 'product'}, {'id': 'version:all versions up to and including 2.0', 'keyphrase': 'all versions up to and including 2.0', 'type': 'version'}, {'id': 'component:image_gallery shortcode', 'keyphrase': 'image_gallery shortcode', 'type': 'component'}]}, 'similarity': np.float64(180.13363953009707)}], identified_cwes={'analyzer': [], 'critic_additional': []})",
  "retrieval_results": {
    "has_multiple_keyphrases": true,
    "keyphrase_cwe_sets": {
      "rootcause:insufficient escaping on the user supplied parameter and lack of sufficient preparation on the existing SQL query": {
        "keyphrase": "insufficient escaping on the user supplied parameter and lack of sufficient preparation on the existing SQL query",
        "type": "rootcause",
        "cwes": [
          {
            "metadata": {
              "doc_id": "116",
              "name": "Improper Encoding or Escaping of Output",
              "source": "sparse",
              "original_content": "The product prepares a structured message for communication with another component, but encoding or escaping of the data is either missing or done incorrectly. As a result, the intended structure of the message is not preserved.",
              "keyphrase_sources": [
                {
                  "id": "rootcause:insufficient escaping on the user supplied parameter and lack of sufficient preparation on the existing SQL query",
                  "keyphrase": "insufficient escaping on the user supplied parameter and lack of sufficient preparation on the existing SQL query",
                  "type": "rootcause"
                },
                {
                  "id": "rootcause:insufficient escaping on user-supplied parameter",
                  "keyphrase": "insufficient escaping on user-supplied parameter",
                  "type": "rootcause"
                },
                {
                  "id": "weakness:SQL Injection",
                  "keyphrase": "SQL Injection",
                  "type": "weakness"
                },
                {
                  "id": "impact:extract sensitive information from the database",
                  "keyphrase": "extract sensitive information from the database",
                  "type": "impact"
                },
                {
                  "id": "attacker:authenticated attackers with Contributor-level access and above",
                  "keyphrase": "authenticated attackers with Contributor-level access and above",
                  "type": "attacker"
                },
                {
                  "id": "product:Categorized Gallery Plugin for WordPress",
                  "keyphrase": "Categorized Gallery Plugin for WordPress",
                  "type": "product"
                },
                {
                  "id": "version:all versions up to and including 2.0",
                  "keyphrase": "all versions up to and including 2.0",
                  "type": "version"
                },
                {
                  "id": "component:image_gallery shortcode",
                  "keyphrase": "image_gallery shortcode",
                  "type": "component"
                }
              ]
            },
            "similarity": 765.765703409179
          },
          {
            "metadata": {
              "doc_id": "89",
              "name": "Improper Neutralization of Special Elements used in an SQL Command ('SQL Injection')",
              "source": "sparse",
              "original_content": "The product constructs all or part of an SQL command using externally-influenced input from an upstream component, but it does not neutralize or incorrectly neutralizes special elements that could modify the intended SQL command when it is sent to a downstream component. Without sufficient removal or quoting of SQL syntax in user-controllable inputs, the generated SQL query can cause those inputs to be interpreted as SQL instead of ordinary user data.",
              "keyphrase_sources": [
                {
                  "id": "rootcause:insufficient escaping on the user supplied parameter and lack of sufficient preparation on the existing SQL query",
                  "keyphrase": "insufficient escaping on the user supplied parameter and lack of sufficient preparation on the existing SQL query",
                  "type": "rootcause"
                },
                {
                  "id": "rootcause:insufficient escaping on user-supplied parameter",
                  "keyphrase": "insufficient escaping on user-supplied parameter",
                  "type": "rootcause"
                },
                {
                  "id": "weakness:SQL Injection",
                  "keyphrase": "SQL Injection",
                  "type": "weakness"
                },
                {
                  "id": "impact:extract sensitive information from the database",
                  "keyphrase": "extract sensitive information from the database",
                  "type": "impact"
                },
                {
                  "id": "attacker:authenticated attackers with Contributor-level access and above",
                  "keyphrase": "authenticated attackers with Contributor-level access and above",
                  "type": "attacker"
                },
                {
                  "id": "product:Categorized Gallery Plugin for WordPress",
                  "keyphrase": "Categorized Gallery Plugin for WordPress",
                  "type": "product"
                },
                {
                  "id": "version:all versions up to and including 2.0",
                  "keyphrase": "all versions up to and including 2.0",
                  "type": "version"
                },
                {
                  "id": "component:image_gallery shortcode",
                  "keyphrase": "image_gallery shortcode",
                  "type": "component"
                }
              ]
            },
            "similarity": 754.5125471309423
          },
          {
            "metadata": {
              "doc_id": "352",
              "name": "Cross-Site Request Forgery (CSRF)",
              "source": "sparse",
              "original_content": "The web application does not, or can not, sufficiently verify whether a well-formed, valid, consistent request was intentionally provided by the user who submitted the request.",
              "keyphrase_sources": [
                {
                  "id": "rootcause:insufficient escaping on the user supplied parameter and lack of sufficient preparation on the existing SQL query",
                  "keyphrase": "insufficient escaping on the user supplied parameter and lack of sufficient preparation on the existing SQL query",
                  "type": "rootcause"
                },
                {
                  "id": "rootcause:insufficient escaping on user-supplied parameter",
                  "keyphrase": "insufficient escaping on user-supplied parameter",
                  "type": "rootcause"
                },
                {
                  "id": "weakness:SQL Injection",
                  "keyphrase": "SQL Injection",
                  "type": "weakness"
                },
                {
                  "id": "impact:extract sensitive information from the database",
                  "keyphrase": "extract sensitive information from the database",
                  "type": "impact"
                },
                {
                  "id": "attacker:authenticated attackers with Contributor-level access and above",
                  "keyphrase": "authenticated attackers with Contributor-level access and above",
                  "type": "attacker"
                },
                {
                  "id": "product:Categorized Gallery Plugin for WordPress",
                  "keyphrase": "Categorized Gallery Plugin for WordPress",
                  "type": "product"
                },
                {
                  "id": "version:all versions up to and including 2.0",
                  "keyphrase": "all versions up to and including 2.0",
                  "type": "version"
                },
                {
                  "id": "component:image_gallery shortcode",
                  "keyphrase": "image_gallery shortcode",
                  "type": "component"
                }
              ]
            },
            "similarity": 713.0766316253419
          },
          {
            "metadata": {
              "doc_id": "90",
              "name": "Improper Neutralization of Special Elements used in an LDAP Query ('LDAP Injection')",
              "source": "sparse",
              "original_content": "The product constructs all or part of an LDAP query using externally-influenced input from an upstream component, but it does not neutralize or incorrectly neutralizes special elements that could modify the intended LDAP query when it is sent to a downstream component.",
              "keyphrase_sources": [
                {
                  "id": "rootcause:insufficient escaping on the user supplied parameter and lack of sufficient preparation on the existing SQL query",
                  "keyphrase": "insufficient escaping on the user supplied parameter and lack of sufficient preparation on the existing SQL query",
                  "type": "rootcause"
                },
                {
                  "id": "rootcause:insufficient escaping on user-supplied parameter",
                  "keyphrase": "insufficient escaping on user-supplied parameter",
                  "type": "rootcause"
                },
                {
                  "id": "weakness:SQL Injection",
                  "keyphrase": "SQL Injection",
                  "type": "weakness"
                },
                {
                  "id": "impact:extract sensitive information from the database",
                  "keyphrase": "extract sensitive information from the database",
                  "type": "impact"
                },
                {
                  "id": "version:all versions up to and including 2.0",
                  "keyphrase": "all versions up to and including 2.0",
                  "type": "version"
                },
                {
                  "id": "component:image_gallery shortcode",
                  "keyphrase": "image_gallery shortcode",
                  "type": "component"
                }
              ]
            },
            "similarity": 708.8211331127097
          },
          {
            "metadata": {
              "doc_id": "790",
              "name": "Improper Filtering of Special Elements",
              "source": "sparse",
              "original_content": "The product receives data from an upstream component, but does not filter or incorrectly filters special elements before sending it to a downstream component.",
              "keyphrase_sources": [
                {
                  "id": "rootcause:insufficient escaping on the user supplied parameter and lack of sufficient preparation on the existing SQL query",
                  "keyphrase": "insufficient escaping on the user supplied parameter and lack of sufficient preparation on the existing SQL query",
                  "type": "rootcause"
                },
                {
                  "id": "rootcause:insufficient escaping on user-supplied parameter",
                  "keyphrase": "insufficient escaping on user-supplied parameter",
                  "type": "rootcause"
                }
              ]
            },
            "similarity": 654.1421537842625
          }
        ]
      },
      "rootcause:insufficient escaping on user-supplied parameter": {
        "keyphrase": "insufficient escaping on user-supplied parameter",
        "type": "rootcause",
        "cwes": [
          {
            "metadata": {
              "doc_id": "116",
              "name": "Improper Encoding or Escaping of Output",
              "source": "sparse",
              "original_content": "The product prepares a structured message for communication with another component, but encoding or escaping of the data is either missing or done incorrectly. As a result, the intended structure of the message is not preserved."
            },
            "similarity": 623.2774671435442
          },
          {
            "metadata": {
              "doc_id": "89",
              "name": "Improper Neutralization of Special Elements used in an SQL Command ('SQL Injection')",
              "source": "sparse",
              "original_content": "The product constructs all or part of an SQL command using externally-influenced input from an upstream component, but it does not neutralize or incorrectly neutralizes special elements that could modify the intended SQL command when it is sent to a downstream component. Without sufficient removal or quoting of SQL syntax in user-controllable inputs, the generated SQL query can cause those inputs to be interpreted as SQL instead of ordinary user data."
            },
            "similarity": 585.6988878640886
          },
          {
            "metadata": {
              "doc_id": "352",
              "name": "Cross-Site Request Forgery (CSRF)",
              "source": "sparse",
              "original_content": "The web application does not, or can not, sufficiently verify whether a well-formed, valid, consistent request was intentionally provided by the user who submitted the request."
            },
            "similarity": 571.4075669102897
          },
          {
            "metadata": {
              "doc_id": "90",
              "name": "Improper Neutralization of Special Elements used in an LDAP Query ('LDAP Injection')",
              "source": "sparse",
              "original_content": "The product constructs all or part of an LDAP query using externally-influenced input from an upstream component, but it does not neutralize or incorrectly neutralizes special elements that could modify the intended LDAP query when it is sent to a downstream component."
            },
            "similarity": 566.36276100132
          },
          {
            "metadata": {
              "doc_id": "790",
              "name": "Improper Filtering of Special Elements",
              "source": "sparse",
              "original_content": "The product receives data from an upstream component, but does not filter or incorrectly filters special elements before sending it to a downstream component."
            },
            "similarity": 539.5208858634063
          }
        ]
      },
      "weakness:SQL Injection": {
        "keyphrase": "SQL Injection",
        "type": "weakness",
        "cwes": [
          {
            "metadata": {
              "doc_id": "89",
              "name": "Improper Neutralization of Special Elements used in an SQL Command ('SQL Injection')",
              "source": "sparse",
              "original_content": "The product constructs all or part of an SQL command using externally-influenced input from an upstream component, but it does not neutralize or incorrectly neutralizes special elements that could modify the intended SQL command when it is sent to a downstream component. Without sufficient removal or quoting of SQL syntax in user-controllable inputs, the generated SQL query can cause those inputs to be interpreted as SQL instead of ordinary user data."
            },
            "similarity": 554.0562310306047
          },
          {
            "metadata": {
              "doc_id": "116",
              "name": "Improper Encoding or Escaping of Output",
              "source": "sparse",
              "original_content": "The product prepares a structured message for communication with another component, but encoding or escaping of the data is either missing or done incorrectly. As a result, the intended structure of the message is not preserved."
            },
            "similarity": 509.1416384415887
          },
          {
            "metadata": {
              "doc_id": "90",
              "name": "Improper Neutralization of Special Elements used in an LDAP Query ('LDAP Injection')",
              "source": "sparse",
              "original_content": "The product constructs all or part of an LDAP query using externally-influenced input from an upstream component, but it does not neutralize or incorrectly neutralizes special elements that could modify the intended LDAP query when it is sent to a downstream component."
            },
            "similarity": 478.5740210237516
          },
          {
            "metadata": {
              "doc_id": "352",
              "name": "Cross-Site Request Forgery (CSRF)",
              "source": "sparse",
              "original_content": "The web application does not, or can not, sufficiently verify whether a well-formed, valid, consistent request was intentionally provided by the user who submitted the request."
            },
            "similarity": 473.70000056030597
          },
          {
            "metadata": {
              "doc_id": "502",
              "name": "Deserialization of Untrusted Data",
              "source": "sparse",
              "original_content": "The product deserializes untrusted data without sufficiently ensuring that the resulting data will be valid.",
              "keyphrase_sources": [
                {
                  "id": "weakness:SQL Injection",
                  "keyphrase": "SQL Injection",
                  "type": "weakness"
                }
              ]
            },
            "similarity": 463.33118435086993
          }
        ]
      },
      "impact:extract sensitive information from the database": {
        "keyphrase": "extract sensitive information from the database",
        "type": "impact",
        "cwes": [
          {
            "metadata": {
              "doc_id": "89",
              "name": "Improper Neutralization of Special Elements used in an SQL Command ('SQL Injection')",
              "source": "sparse",
              "original_content": "The product constructs all or part of an SQL command using externally-influenced input from an upstream component, but it does not neutralize or incorrectly neutralizes special elements that could modify the intended SQL command when it is sent to a downstream component. Without sufficient removal or quoting of SQL syntax in user-controllable inputs, the generated SQL query can cause those inputs to be interpreted as SQL instead of ordinary user data."
            },
            "similarity": 202.67763575771056
          },
          {
            "metadata": {
              "doc_id": "116",
              "name": "Improper Encoding or Escaping of Output",
              "source": "sparse",
              "original_content": "The product prepares a structured message for communication with another component, but encoding or escaping of the data is either missing or done incorrectly. As a result, the intended structure of the message is not preserved."
            },
            "similarity": 182.2717012077509
          },
          {
            "metadata": {
              "doc_id": "90",
              "name": "Improper Neutralization of Special Elements used in an LDAP Query ('LDAP Injection')",
              "source": "sparse",
              "original_content": "The product constructs all or part of an LDAP query using externally-influenced input from an upstream component, but it does not neutralize or incorrectly neutralizes special elements that could modify the intended LDAP query when it is sent to a downstream component."
            },
            "similarity": 181.74430054637844
          },
          {
            "metadata": {
              "doc_id": "863",
              "name": "Incorrect Authorization",
              "source": "sparse",
              "original_content": "The product performs an authorization check when an actor attempts to access a resource or perform an action, but it does not correctly perform the check.",
              "keyphrase_sources": [
                {
                  "id": "impact:extract sensitive information from the database",
                  "keyphrase": "extract sensitive information from the database",
                  "type": "impact"
                },
                {
                  "id": "attacker:authenticated attackers with Contributor-level access and above",
                  "keyphrase": "authenticated attackers with Contributor-level access and above",
                  "type": "attacker"
                },
                {
                  "id": "product:Categorized Gallery Plugin for WordPress",
                  "keyphrase": "Categorized Gallery Plugin for WordPress",
                  "type": "product"
                },
                {
                  "id": "version:all versions up to and including 2.0",
                  "keyphrase": "all versions up to and including 2.0",
                  "type": "version"
                },
                {
                  "id": "component:image_gallery shortcode",
                  "keyphrase": "image_gallery shortcode",
                  "type": "component"
                }
              ]
            },
            "similarity": 180.13363953009707
          },
          {
            "metadata": {
              "doc_id": "352",
              "name": "Cross-Site Request Forgery (CSRF)",
              "source": "sparse",
              "original_content": "The web application does not, or can not, sufficiently verify whether a well-formed, valid, consistent request was intentionally provided by the user who submitted the request."
            },
            "similarity": 177.53871438215097
          }
        ]
      },
      "attacker:authenticated attackers with Contributor-level access and above": {
        "keyphrase": "authenticated attackers with Contributor-level access and above",
        "type": "attacker",
        "cwes": [
          {
            "metadata": {
              "doc_id": "89",
              "name": "Improper Neutralization of Special Elements used in an SQL Command ('SQL Injection')",
              "source": "sparse",
              "original_content": "The product constructs all or part of an SQL command using externally-influenced input from an upstream component, but it does not neutralize or incorrectly neutralizes special elements that could modify the intended SQL command when it is sent to a downstream component. Without sufficient removal or quoting of SQL syntax in user-controllable inputs, the generated SQL query can cause those inputs to be interpreted as SQL instead of ordinary user data."
            },
            "similarity": 202.40915155342242
          },
          {
            "metadata": {
              "doc_id": "863",
              "name": "Incorrect Authorization",
              "source": "sparse",
              "original_content": "The product performs an authorization check when an actor attempts to access a resource or perform an action, but it does not correctly perform the check."
            },
            "similarity": 197.8796986933881
          },
          {
            "metadata": {
              "doc_id": "352",
              "name": "Cross-Site Request Forgery (CSRF)",
              "source": "sparse",
              "original_content": "The web application does not, or can not, sufficiently verify whether a well-formed, valid, consistent request was intentionally provided by the user who submitted the request."
            },
            "similarity": 193.17098538404937
          },
          {
            "metadata": {
              "doc_id": "116",
              "name": "Improper Encoding or Escaping of Output",
              "source": "sparse",
              "original_content": "The product prepares a structured message for communication with another component, but encoding or escaping of the data is either missing or done incorrectly. As a result, the intended structure of the message is not preserved."
            },
            "similarity": 192.40889292196871
          },
          {
            "metadata": {
              "doc_id": "862",
              "name": "Missing Authorization",
              "source": "sparse",
              "original_content": "The product does not perform an authorization check when an actor attempts to access a resource or perform an action.",
              "keyphrase_sources": [
                {
                  "id": "attacker:authenticated attackers with Contributor-level access and above",
                  "keyphrase": "authenticated attackers with Contributor-level access and above",
                  "type": "attacker"
                },
                {
                  "id": "product:Categorized Gallery Plugin for WordPress",
                  "keyphrase": "Categorized Gallery Plugin for WordPress",
                  "type": "product"
                }
              ]
            },
            "similarity": 186.32129857150235
          }
        ]
      },
      "product:Categorized Gallery Plugin for WordPress": {
        "keyphrase": "Categorized Gallery Plugin for WordPress",
        "type": "product",
        "cwes": [
          {
            "metadata": {
              "doc_id": "89",
              "name": "Improper Neutralization of Special Elements used in an SQL Command ('SQL Injection')",
              "source": "sparse",
              "original_content": "The product constructs all or part of an SQL command using externally-influenced input from an upstream component, but it does not neutralize or incorrectly neutralizes special elements that could modify the intended SQL command when it is sent to a downstream component. Without sufficient removal or quoting of SQL syntax in user-controllable inputs, the generated SQL query can cause those inputs to be interpreted as SQL instead of ordinary user data."
            },
            "similarity": 198.7759769048434
          },
          {
            "metadata": {
              "doc_id": "352",
              "name": "Cross-Site Request Forgery (CSRF)",
              "source": "sparse",
              "original_content": "The web application does not, or can not, sufficiently verify whether a well-formed, valid, consistent request was intentionally provided by the user who submitted the request."
            },
            "similarity": 198.26025499450142
          },
          {
            "metadata": {
              "doc_id": "116",
              "name": "Improper Encoding or Escaping of Output",
              "source": "sparse",
              "original_content": "The product prepares a structured message for communication with another component, but encoding or escaping of the data is either missing or done incorrectly. As a result, the intended structure of the message is not preserved."
            },
            "similarity": 191.4822022584574
          },
          {
            "metadata": {
              "doc_id": "863",
              "name": "Incorrect Authorization",
              "source": "sparse",
              "original_content": "The product performs an authorization check when an actor attempts to access a resource or perform an action, but it does not correctly perform the check."
            },
            "similarity": 184.97846322718888
          },
          {
            "metadata": {
              "doc_id": "862",
              "name": "Missing Authorization",
              "source": "sparse",
              "original_content": "The product does not perform an authorization check when an actor attempts to access a resource or perform an action."
            },
            "similarity": 183.55437869250855
          }
        ]
      },
      "version:all versions up to and including 2.0": {
        "keyphrase": "all versions up to and including 2.0",
        "type": "version",
        "cwes": [
          {
            "metadata": {
              "doc_id": "89",
              "name": "Improper Neutralization of Special Elements used in an SQL Command ('SQL Injection')",
              "source": "sparse",
              "original_content": "The product constructs all or part of an SQL command using externally-influenced input from an upstream component, but it does not neutralize or incorrectly neutralizes special elements that could modify the intended SQL command when it is sent to a downstream component. Without sufficient removal or quoting of SQL syntax in user-controllable inputs, the generated SQL query can cause those inputs to be interpreted as SQL instead of ordinary user data."
            },
            "similarity": 199.36763142005856
          },
          {
            "metadata": {
              "doc_id": "116",
              "name": "Improper Encoding or Escaping of Output",
              "source": "sparse",
              "original_content": "The product prepares a structured message for communication with another component, but encoding or escaping of the data is either missing or done incorrectly. As a result, the intended structure of the message is not preserved."
            },
            "similarity": 197.51699102644906
          },
          {
            "metadata": {
              "doc_id": "352",
              "name": "Cross-Site Request Forgery (CSRF)",
              "source": "sparse",
              "original_content": "The web application does not, or can not, sufficiently verify whether a well-formed, valid, consistent request was intentionally provided by the user who submitted the request."
            },
            "similarity": 192.76145344697017
          },
          {
            "metadata": {
              "doc_id": "863",
              "name": "Incorrect Authorization",
              "source": "sparse",
              "original_content": "The product performs an authorization check when an actor attempts to access a resource or perform an action, but it does not correctly perform the check."
            },
            "similarity": 189.3413137756341
          },
          {
            "metadata": {
              "doc_id": "90",
              "name": "Improper Neutralization of Special Elements used in an LDAP Query ('LDAP Injection')",
              "source": "sparse",
              "original_content": "The product constructs all or part of an LDAP query using externally-influenced input from an upstream component, but it does not neutralize or incorrectly neutralizes special elements that could modify the intended LDAP query when it is sent to a downstream component."
            },
            "similarity": 188.0374990070813
          }
        ]
      },
      "component:image_gallery shortcode": {
        "keyphrase": "image_gallery shortcode",
        "type": "component",
        "cwes": [
          {
            "metadata": {
              "doc_id": "89",
              "name": "Improper Neutralization of Special Elements used in an SQL Command ('SQL Injection')",
              "source": "sparse",
              "original_content": "The product constructs all or part of an SQL command using externally-influenced input from an upstream component, but it does not neutralize or incorrectly neutralizes special elements that could modify the intended SQL command when it is sent to a downstream component. Without sufficient removal or quoting of SQL syntax in user-controllable inputs, the generated SQL query can cause those inputs to be interpreted as SQL instead of ordinary user data."
            },
            "similarity": 178.60112344102737
          },
          {
            "metadata": {
              "doc_id": "116",
              "name": "Improper Encoding or Escaping of Output",
              "source": "sparse",
              "original_content": "The product prepares a structured message for communication with another component, but encoding or escaping of the data is either missing or done incorrectly. As a result, the intended structure of the message is not preserved."
            },
            "similarity": 168.46194269420945
          },
          {
            "metadata": {
              "doc_id": "352",
              "name": "Cross-Site Request Forgery (CSRF)",
              "source": "sparse",
              "original_content": "The web application does not, or can not, sufficiently verify whether a well-formed, valid, consistent request was intentionally provided by the user who submitted the request."
            },
            "similarity": 164.36471032729767
          },
          {
            "metadata": {
              "doc_id": "863",
              "name": "Incorrect Authorization",
              "source": "sparse",
              "original_content": "The product performs an authorization check when an actor attempts to access a resource or perform an action, but it does not correctly perform the check."
            },
            "similarity": 163.3501238896369
          },
          {
            "metadata": {
              "doc_id": "90",
              "name": "Improper Neutralization of Special Elements used in an LDAP Query ('LDAP Injection')",
              "source": "sparse",
              "original_content": "The product constructs all or part of an LDAP query using externally-influenced input from an upstream component, but it does not neutralize or incorrectly neutralizes special elements that could modify the intended LDAP query when it is sent to a downstream component."
            },
            "similarity": 162.9205331951299
          }
        ]
      }
    },
    "keyphrase_mapping": {
      "116": [
        {
          "id": "rootcause:insufficient escaping on the user supplied parameter and lack of sufficient preparation on the existing SQL query",
          "keyphrase": "insufficient escaping on the user supplied parameter and lack of sufficient preparation on the existing SQL query",
          "type": "rootcause"
        },
        {
          "id": "rootcause:insufficient escaping on user-supplied parameter",
          "keyphrase": "insufficient escaping on user-supplied parameter",
          "type": "rootcause"
        },
        {
          "id": "weakness:SQL Injection",
          "keyphrase": "SQL Injection",
          "type": "weakness"
        },
        {
          "id": "impact:extract sensitive information from the database",
          "keyphrase": "extract sensitive information from the database",
          "type": "impact"
        },
        {
          "id": "attacker:authenticated attackers with Contributor-level access and above",
          "keyphrase": "authenticated attackers with Contributor-level access and above",
          "type": "attacker"
        },
        {
          "id": "product:Categorized Gallery Plugin for WordPress",
          "keyphrase": "Categorized Gallery Plugin for WordPress",
          "type": "product"
        },
        {
          "id": "version:all versions up to and including 2.0",
          "keyphrase": "all versions up to and including 2.0",
          "type": "version"
        },
        {
          "id": "component:image_gallery shortcode",
          "keyphrase": "image_gallery shortcode",
          "type": "component"
        }
      ],
      "89": [
        {
          "id": "rootcause:insufficient escaping on the user supplied parameter and lack of sufficient preparation on the existing SQL query",
          "keyphrase": "insufficient escaping on the user supplied parameter and lack of sufficient preparation on the existing SQL query",
          "type": "rootcause"
        },
        {
          "id": "rootcause:insufficient escaping on user-supplied parameter",
          "keyphrase": "insufficient escaping on user-supplied parameter",
          "type": "rootcause"
        },
        {
          "id": "weakness:SQL Injection",
          "keyphrase": "SQL Injection",
          "type": "weakness"
        },
        {
          "id": "impact:extract sensitive information from the database",
          "keyphrase": "extract sensitive information from the database",
          "type": "impact"
        },
        {
          "id": "attacker:authenticated attackers with Contributor-level access and above",
          "keyphrase": "authenticated attackers with Contributor-level access and above",
          "type": "attacker"
        },
        {
          "id": "product:Categorized Gallery Plugin for WordPress",
          "keyphrase": "Categorized Gallery Plugin for WordPress",
          "type": "product"
        },
        {
          "id": "version:all versions up to and including 2.0",
          "keyphrase": "all versions up to and including 2.0",
          "type": "version"
        },
        {
          "id": "component:image_gallery shortcode",
          "keyphrase": "image_gallery shortcode",
          "type": "component"
        }
      ],
      "352": [
        {
          "id": "rootcause:insufficient escaping on the user supplied parameter and lack of sufficient preparation on the existing SQL query",
          "keyphrase": "insufficient escaping on the user supplied parameter and lack of sufficient preparation on the existing SQL query",
          "type": "rootcause"
        },
        {
          "id": "rootcause:insufficient escaping on user-supplied parameter",
          "keyphrase": "insufficient escaping on user-supplied parameter",
          "type": "rootcause"
        },
        {
          "id": "weakness:SQL Injection",
          "keyphrase": "SQL Injection",
          "type": "weakness"
        },
        {
          "id": "impact:extract sensitive information from the database",
          "keyphrase": "extract sensitive information from the database",
          "type": "impact"
        },
        {
          "id": "attacker:authenticated attackers with Contributor-level access and above",
          "keyphrase": "authenticated attackers with Contributor-level access and above",
          "type": "attacker"
        },
        {
          "id": "product:Categorized Gallery Plugin for WordPress",
          "keyphrase": "Categorized Gallery Plugin for WordPress",
          "type": "product"
        },
        {
          "id": "version:all versions up to and including 2.0",
          "keyphrase": "all versions up to and including 2.0",
          "type": "version"
        },
        {
          "id": "component:image_gallery shortcode",
          "keyphrase": "image_gallery shortcode",
          "type": "component"
        }
      ],
      "90": [
        {
          "id": "rootcause:insufficient escaping on the user supplied parameter and lack of sufficient preparation on the existing SQL query",
          "keyphrase": "insufficient escaping on the user supplied parameter and lack of sufficient preparation on the existing SQL query",
          "type": "rootcause"
        },
        {
          "id": "rootcause:insufficient escaping on user-supplied parameter",
          "keyphrase": "insufficient escaping on user-supplied parameter",
          "type": "rootcause"
        },
        {
          "id": "weakness:SQL Injection",
          "keyphrase": "SQL Injection",
          "type": "weakness"
        },
        {
          "id": "impact:extract sensitive information from the database",
          "keyphrase": "extract sensitive information from the database",
          "type": "impact"
        },
        {
          "id": "version:all versions up to and including 2.0",
          "keyphrase": "all versions up to and including 2.0",
          "type": "version"
        },
        {
          "id": "component:image_gallery shortcode",
          "keyphrase": "image_gallery shortcode",
          "type": "component"
        }
      ],
      "790": [
        {
          "id": "rootcause:insufficient escaping on the user supplied parameter and lack of sufficient preparation on the existing SQL query",
          "keyphrase": "insufficient escaping on the user supplied parameter and lack of sufficient preparation on the existing SQL query",
          "type": "rootcause"
        },
        {
          "id": "rootcause:insufficient escaping on user-supplied parameter",
          "keyphrase": "insufficient escaping on user-supplied parameter",
          "type": "rootcause"
        }
      ],
      "502": [
        {
          "id": "weakness:SQL Injection",
          "keyphrase": "SQL Injection",
          "type": "weakness"
        }
      ],
      "863": [
        {
          "id": "impact:extract sensitive information from the database",
          "keyphrase": "extract sensitive information from the database",
          "type": "impact"
        },
        {
          "id": "attacker:authenticated attackers with Contributor-level access and above",
          "keyphrase": "authenticated attackers with Contributor-level access and above",
          "type": "attacker"
        },
        {
          "id": "product:Categorized Gallery Plugin for WordPress",
          "keyphrase": "Categorized Gallery Plugin for WordPress",
          "type": "product"
        },
        {
          "id": "version:all versions up to and including 2.0",
          "keyphrase": "all versions up to and including 2.0",
          "type": "version"
        },
        {
          "id": "component:image_gallery shortcode",
          "keyphrase": "image_gallery shortcode",
          "type": "component"
        }
      ],
      "862": [
        {
          "id": "attacker:authenticated attackers with Contributor-level access and above",
          "keyphrase": "authenticated attackers with Contributor-level access and above",
          "type": "attacker"
        },
        {
          "id": "product:Categorized Gallery Plugin for WordPress",
          "keyphrase": "Categorized Gallery Plugin for WordPress",
          "type": "product"
        }
      ]
    },
    "relevant_cwes": [
      {
        "metadata": {
          "doc_id": "116",
          "name": "Improper Encoding or Escaping of Output",
          "source": "sparse",
          "original_content": "The product prepares a structured message for communication with another component, but encoding or escaping of the data is either missing or done incorrectly. As a result, the intended structure of the message is not preserved.",
          "keyphrase_sources": [
            {
              "id": "rootcause:insufficient escaping on the user supplied parameter and lack of sufficient preparation on the existing SQL query",
              "keyphrase": "insufficient escaping on the user supplied parameter and lack of sufficient preparation on the existing SQL query",
              "type": "rootcause"
            },
            {
              "id": "rootcause:insufficient escaping on user-supplied parameter",
              "keyphrase": "insufficient escaping on user-supplied parameter",
              "type": "rootcause"
            },
            {
              "id": "weakness:SQL Injection",
              "keyphrase": "SQL Injection",
              "type": "weakness"
            },
            {
              "id": "impact:extract sensitive information from the database",
              "keyphrase": "extract sensitive information from the database",
              "type": "impact"
            },
            {
              "id": "attacker:authenticated attackers with Contributor-level access and above",
              "keyphrase": "authenticated attackers with Contributor-level access and above",
              "type": "attacker"
            },
            {
              "id": "product:Categorized Gallery Plugin for WordPress",
              "keyphrase": "Categorized Gallery Plugin for WordPress",
              "type": "product"
            },
            {
              "id": "version:all versions up to and including 2.0",
              "keyphrase": "all versions up to and including 2.0",
              "type": "version"
            },
            {
              "id": "component:image_gallery shortcode",
              "keyphrase": "image_gallery shortcode",
              "type": "component"
            }
          ]
        },
        "similarity": 765.765703409179
      },
      {
        "metadata": {
          "doc_id": "89",
          "name": "Improper Neutralization of Special Elements used in an SQL Command ('SQL Injection')",
          "source": "sparse",
          "original_content": "The product constructs all or part of an SQL command using externally-influenced input from an upstream component, but it does not neutralize or incorrectly neutralizes special elements that could modify the intended SQL command when it is sent to a downstream component. Without sufficient removal or quoting of SQL syntax in user-controllable inputs, the generated SQL query can cause those inputs to be interpreted as SQL instead of ordinary user data.",
          "keyphrase_sources": [
            {
              "id": "rootcause:insufficient escaping on the user supplied parameter and lack of sufficient preparation on the existing SQL query",
              "keyphrase": "insufficient escaping on the user supplied parameter and lack of sufficient preparation on the existing SQL query",
              "type": "rootcause"
            },
            {
              "id": "rootcause:insufficient escaping on user-supplied parameter",
              "keyphrase": "insufficient escaping on user-supplied parameter",
              "type": "rootcause"
            },
            {
              "id": "weakness:SQL Injection",
              "keyphrase": "SQL Injection",
              "type": "weakness"
            },
            {
              "id": "impact:extract sensitive information from the database",
              "keyphrase": "extract sensitive information from the database",
              "type": "impact"
            },
            {
              "id": "attacker:authenticated attackers with Contributor-level access and above",
              "keyphrase": "authenticated attackers with Contributor-level access and above",
              "type": "attacker"
            },
            {
              "id": "product:Categorized Gallery Plugin for WordPress",
              "keyphrase": "Categorized Gallery Plugin for WordPress",
              "type": "product"
            },
            {
              "id": "version:all versions up to and including 2.0",
              "keyphrase": "all versions up to and including 2.0",
              "type": "version"
            },
            {
              "id": "component:image_gallery shortcode",
              "keyphrase": "image_gallery shortcode",
              "type": "component"
            }
          ]
        },
        "similarity": 754.5125471309423
      },
      {
        "metadata": {
          "doc_id": "352",
          "name": "Cross-Site Request Forgery (CSRF)",
          "source": "sparse",
          "original_content": "The web application does not, or can not, sufficiently verify whether a well-formed, valid, consistent request was intentionally provided by the user who submitted the request.",
          "keyphrase_sources": [
            {
              "id": "rootcause:insufficient escaping on the user supplied parameter and lack of sufficient preparation on the existing SQL query",
              "keyphrase": "insufficient escaping on the user supplied parameter and lack of sufficient preparation on the existing SQL query",
              "type": "rootcause"
            },
            {
              "id": "rootcause:insufficient escaping on user-supplied parameter",
              "keyphrase": "insufficient escaping on user-supplied parameter",
              "type": "rootcause"
            },
            {
              "id": "weakness:SQL Injection",
              "keyphrase": "SQL Injection",
              "type": "weakness"
            },
            {
              "id": "impact:extract sensitive information from the database",
              "keyphrase": "extract sensitive information from the database",
              "type": "impact"
            },
            {
              "id": "attacker:authenticated attackers with Contributor-level access and above",
              "keyphrase": "authenticated attackers with Contributor-level access and above",
              "type": "attacker"
            },
            {
              "id": "product:Categorized Gallery Plugin for WordPress",
              "keyphrase": "Categorized Gallery Plugin for WordPress",
              "type": "product"
            },
            {
              "id": "version:all versions up to and including 2.0",
              "keyphrase": "all versions up to and including 2.0",
              "type": "version"
            },
            {
              "id": "component:image_gallery shortcode",
              "keyphrase": "image_gallery shortcode",
              "type": "component"
            }
          ]
        },
        "similarity": 713.0766316253419
      },
      {
        "metadata": {
          "doc_id": "90",
          "name": "Improper Neutralization of Special Elements used in an LDAP Query ('LDAP Injection')",
          "source": "sparse",
          "original_content": "The product constructs all or part of an LDAP query using externally-influenced input from an upstream component, but it does not neutralize or incorrectly neutralizes special elements that could modify the intended LDAP query when it is sent to a downstream component.",
          "keyphrase_sources": [
            {
              "id": "rootcause:insufficient escaping on the user supplied parameter and lack of sufficient preparation on the existing SQL query",
              "keyphrase": "insufficient escaping on the user supplied parameter and lack of sufficient preparation on the existing SQL query",
              "type": "rootcause"
            },
            {
              "id": "rootcause:insufficient escaping on user-supplied parameter",
              "keyphrase": "insufficient escaping on user-supplied parameter",
              "type": "rootcause"
            },
            {
              "id": "weakness:SQL Injection",
              "keyphrase": "SQL Injection",
              "type": "weakness"
            },
            {
              "id": "impact:extract sensitive information from the database",
              "keyphrase": "extract sensitive information from the database",
              "type": "impact"
            },
            {
              "id": "version:all versions up to and including 2.0",
              "keyphrase": "all versions up to and including 2.0",
              "type": "version"
            },
            {
              "id": "component:image_gallery shortcode",
              "keyphrase": "image_gallery shortcode",
              "type": "component"
            }
          ]
        },
        "similarity": 708.8211331127097
      },
      {
        "metadata": {
          "doc_id": "790",
          "name": "Improper Filtering of Special Elements",
          "source": "sparse",
          "original_content": "The product receives data from an upstream component, but does not filter or incorrectly filters special elements before sending it to a downstream component.",
          "keyphrase_sources": [
            {
              "id": "rootcause:insufficient escaping on the user supplied parameter and lack of sufficient preparation on the existing SQL query",
              "keyphrase": "insufficient escaping on the user supplied parameter and lack of sufficient preparation on the existing SQL query",
              "type": "rootcause"
            },
            {
              "id": "rootcause:insufficient escaping on user-supplied parameter",
              "keyphrase": "insufficient escaping on user-supplied parameter",
              "type": "rootcause"
            }
          ]
        },
        "similarity": 654.1421537842625
      },
      {
        "metadata": {
          "doc_id": "502",
          "name": "Deserialization of Untrusted Data",
          "source": "sparse",
          "original_content": "The product deserializes untrusted data without sufficiently ensuring that the resulting data will be valid.",
          "keyphrase_sources": [
            {
              "id": "weakness:SQL Injection",
              "keyphrase": "SQL Injection",
              "type": "weakness"
            }
          ]
        },
        "similarity": 463.33118435086993
      },
      {
        "metadata": {
          "doc_id": "862",
          "name": "Missing Authorization",
          "source": "sparse",
          "original_content": "The product does not perform an authorization check when an actor attempts to access a resource or perform an action.",
          "keyphrase_sources": [
            {
              "id": "attacker:authenticated attackers with Contributor-level access and above",
              "keyphrase": "authenticated attackers with Contributor-level access and above",
              "type": "attacker"
            },
            {
              "id": "product:Categorized Gallery Plugin for WordPress",
              "keyphrase": "Categorized Gallery Plugin for WordPress",
              "type": "product"
            }
          ]
        },
        "similarity": 186.32129857150235
      },
      {
        "metadata": {
          "doc_id": "863",
          "name": "Incorrect Authorization",
          "source": "sparse",
          "original_content": "The product performs an authorization check when an actor attempts to access a resource or perform an action, but it does not correctly perform the check.",
          "keyphrase_sources": [
            {
              "id": "impact:extract sensitive information from the database",
              "keyphrase": "extract sensitive information from the database",
              "type": "impact"
            },
            {
              "id": "attacker:authenticated attackers with Contributor-level access and above",
              "keyphrase": "authenticated attackers with Contributor-level access and above",
              "type": "attacker"
            },
            {
              "id": "product:Categorized Gallery Plugin for WordPress",
              "keyphrase": "Categorized Gallery Plugin for WordPress",
              "type": "product"
            },
            {
              "id": "version:all versions up to and including 2.0",
              "keyphrase": "all versions up to and including 2.0",
              "type": "version"
            },
            {
              "id": "component:image_gallery shortcode",
              "keyphrase": "image_gallery shortcode",
              "type": "component"
            }
          ]
        },
        "similarity": 180.13363953009707
      }
    ],
    "enhanced_query": "# Vulnerability Description\n\n    The Categorized Gallery Plugin plugin for WordPress is vulnerable to **SQL Injection** via the field attribute of the image_gallery shortcode in all versions up to, and including, 2.0 due to **insufficient escaping on the user supplied parameter and lack of sufficient preparation on the existing SQL query**. This makes it possible for authenticated attackers, with Contributor-level access and above, to append additional SQL queries into already existing queries that can be used to extract sensitive information from the database.\n\n    # Keyphrase-Specific CWE Analysis\n    This vulnerability contains multiple keyphrases that may map to different CWEs. \n    Please analyze each keyphrase separately and determine the most appropriate CWE(s) for each.\n\n    ## ROOTCAUSE: 'insufficient escaping on the user supplied parameter and lack of sufficient preparation on the existing SQL query'\n\nRelevant CWEs for this ROOTCAUSE:\n\n### 1. CWE-116: Improper Encoding or Escaping of Output (Score: 765.77)\n\nThe product prepares a structured message for communication with another component, but encoding or escaping of the data is either missing or done incorrectly. As a result, the intended structure of the message is not preserved....\n\n### 2. CWE-89: Improper Neutralization of Special Elements used in an SQL Command ('SQL Injection') (Score: 754.51)\n\nThe product constructs all or part of an SQL command using externally-influenced input from an upstream component, but it does not neutralize or incorrectly neutralizes special elements that could modify the intended SQL command when it is sent to a downstream component. Without sufficient removal o...\n\n### 3. CWE-352: Cross-Site Request Forgery (CSRF) (Score: 713.08)\n\nThe web application does not, or can not, sufficiently verify whether a well-formed, valid, consistent request was intentionally provided by the user who submitted the request....\n\n### 4. CWE-90: Improper Neutralization of Special Elements used in an LDAP Query ('LDAP Injection') (Score: 708.82)\n\nThe product constructs all or part of an LDAP query using externally-influenced input from an upstream component, but it does not neutralize or incorrectly neutralizes special elements that could modify the intended LDAP query when it is sent to a downstream component....\n\n### 5. CWE-790: Improper Filtering of Special Elements (Score: 654.14)\n\nThe product receives data from an upstream component, but does not filter or incorrectly filters special elements before sending it to a downstream component....\n\n## ROOTCAUSE: 'insufficient escaping on user-supplied parameter'\n\nRelevant CWEs for this ROOTCAUSE:\n\n### 1. CWE-116: Improper Encoding or Escaping of Output (Score: 765.77)\n\nThe product prepares a structured message for communication with another component, but encoding or escaping of the data is either missing or done incorrectly. As a result, the intended structure of the message is not preserved....\n\n### 2. CWE-89: Improper Neutralization of Special Elements used in an SQL Command ('SQL Injection') (Score: 754.51)\n\nThe product constructs all or part of an SQL command using externally-influenced input from an upstream component, but it does not neutralize or incorrectly neutralizes special elements that could modify the intended SQL command when it is sent to a downstream component. Without sufficient removal o...\n\n### 3. CWE-352: Cross-Site Request Forgery (CSRF) (Score: 713.08)\n\nThe web application does not, or can not, sufficiently verify whether a well-formed, valid, consistent request was intentionally provided by the user who submitted the request....\n\n### 4. CWE-90: Improper Neutralization of Special Elements used in an LDAP Query ('LDAP Injection') (Score: 708.82)\n\nThe product constructs all or part of an LDAP query using externally-influenced input from an upstream component, but it does not neutralize or incorrectly neutralizes special elements that could modify the intended LDAP query when it is sent to a downstream component....\n\n### 5. CWE-790: Improper Filtering of Special Elements (Score: 654.14)\n\nThe product receives data from an upstream component, but does not filter or incorrectly filters special elements before sending it to a downstream component....\n\n## WEAKNESS: 'SQL Injection'\n\nRelevant CWEs for this WEAKNESS:\n\n### 1. CWE-116: Improper Encoding or Escaping of Output (Score: 765.77)\n\nThe product prepares a structured message for communication with another component, but encoding or escaping of the data is either missing or done incorrectly. As a result, the intended structure of the message is not preserved....\n\n### 2. CWE-89: Improper Neutralization of Special Elements used in an SQL Command ('SQL Injection') (Score: 754.51)\n\nThe product constructs all or part of an SQL command using externally-influenced input from an upstream component, but it does not neutralize or incorrectly neutralizes special elements that could modify the intended SQL command when it is sent to a downstream component. Without sufficient removal o...\n\n### 3. CWE-352: Cross-Site Request Forgery (CSRF) (Score: 713.08)\n\nThe web application does not, or can not, sufficiently verify whether a well-formed, valid, consistent request was intentionally provided by the user who submitted the request....\n\n### 4. CWE-90: Improper Neutralization of Special Elements used in an LDAP Query ('LDAP Injection') (Score: 708.82)\n\nThe product constructs all or part of an LDAP query using externally-influenced input from an upstream component, but it does not neutralize or incorrectly neutralizes special elements that could modify the intended LDAP query when it is sent to a downstream component....\n\n### 5. CWE-502: Deserialization of Untrusted Data (Score: 463.33)\n\nThe product deserializes untrusted data without sufficiently ensuring that the resulting data will be valid....\n\n## IMPACT: 'extract sensitive information from the database'\n\nRelevant CWEs for this IMPACT:\n\n### 1. CWE-116: Improper Encoding or Escaping of Output (Score: 765.77)\n\nThe product prepares a structured message for communication with another component, but encoding or escaping of the data is either missing or done incorrectly. As a result, the intended structure of the message is not preserved....\n\n### 2. CWE-89: Improper Neutralization of Special Elements used in an SQL Command ('SQL Injection') (Score: 754.51)\n\nThe product constructs all or part of an SQL command using externally-influenced input from an upstream component, but it does not neutralize or incorrectly neutralizes special elements that could modify the intended SQL command when it is sent to a downstream component. Without sufficient removal o...\n\n### 3. CWE-352: Cross-Site Request Forgery (CSRF) (Score: 713.08)\n\nThe web application does not, or can not, sufficiently verify whether a well-formed, valid, consistent request was intentionally provided by the user who submitted the request....\n\n### 4. CWE-90: Improper Neutralization of Special Elements used in an LDAP Query ('LDAP Injection') (Score: 708.82)\n\nThe product constructs all or part of an LDAP query using externally-influenced input from an upstream component, but it does not neutralize or incorrectly neutralizes special elements that could modify the intended LDAP query when it is sent to a downstream component....\n\n### 5. CWE-863: Incorrect Authorization (Score: 180.13)\n\nThe product performs an authorization check when an actor attempts to access a resource or perform an action, but it does not correctly perform the check....\n\n## ATTACKER: 'authenticated attackers with Contributor-level access and above'\n\nRelevant CWEs for this ATTACKER:\n\n### 1. CWE-116: Improper Encoding or Escaping of Output (Score: 765.77)\n\nThe product prepares a structured message for communication with another component, but encoding or escaping of the data is either missing or done incorrectly. As a result, the intended structure of the message is not preserved....\n\n### 2. CWE-89: Improper Neutralization of Special Elements used in an SQL Command ('SQL Injection') (Score: 754.51)\n\nThe product constructs all or part of an SQL command using externally-influenced input from an upstream component, but it does not neutralize or incorrectly neutralizes special elements that could modify the intended SQL command when it is sent to a downstream component. Without sufficient removal o...\n\n### 3. CWE-352: Cross-Site Request Forgery (CSRF) (Score: 713.08)\n\nThe web application does not, or can not, sufficiently verify whether a well-formed, valid, consistent request was intentionally provided by the user who submitted the request....\n\n### 4. CWE-862: Missing Authorization (Score: 186.32)\n\nThe product does not perform an authorization check when an actor attempts to access a resource or perform an action....\n\n### 5. CWE-863: Incorrect Authorization (Score: 180.13)\n\nThe product performs an authorization check when an actor attempts to access a resource or perform an action, but it does not correctly perform the check....\n\n## PRODUCT: 'Categorized Gallery Plugin for WordPress'\n\nRelevant CWEs for this PRODUCT:\n\n### 1. CWE-116: Improper Encoding or Escaping of Output (Score: 765.77)\n\nThe product prepares a structured message for communication with another component, but encoding or escaping of the data is either missing or done incorrectly. As a result, the intended structure of the message is not preserved....\n\n### 2. CWE-89: Improper Neutralization of Special Elements used in an SQL Command ('SQL Injection') (Score: 754.51)\n\nThe product constructs all or part of an SQL command using externally-influenced input from an upstream component, but it does not neutralize or incorrectly neutralizes special elements that could modify the intended SQL command when it is sent to a downstream component. Without sufficient removal o...\n\n### 3. CWE-352: Cross-Site Request Forgery (CSRF) (Score: 713.08)\n\nThe web application does not, or can not, sufficiently verify whether a well-formed, valid, consistent request was intentionally provided by the user who submitted the request....\n\n### 4. CWE-862: Missing Authorization (Score: 186.32)\n\nThe product does not perform an authorization check when an actor attempts to access a resource or perform an action....\n\n### 5. CWE-863: Incorrect Authorization (Score: 180.13)\n\nThe product performs an authorization check when an actor attempts to access a resource or perform an action, but it does not correctly perform the check....\n\n## VERSION: 'all versions up to and including 2.0'\n\nRelevant CWEs for this VERSION:\n\n### 1. CWE-116: Improper Encoding or Escaping of Output (Score: 765.77)\n\nThe product prepares a structured message for communication with another component, but encoding or escaping of the data is either missing or done incorrectly. As a result, the intended structure of the message is not preserved....\n\n### 2. CWE-89: Improper Neutralization of Special Elements used in an SQL Command ('SQL Injection') (Score: 754.51)\n\nThe product constructs all or part of an SQL command using externally-influenced input from an upstream component, but it does not neutralize or incorrectly neutralizes special elements that could modify the intended SQL command when it is sent to a downstream component. Without sufficient removal o...\n\n### 3. CWE-352: Cross-Site Request Forgery (CSRF) (Score: 713.08)\n\nThe web application does not, or can not, sufficiently verify whether a well-formed, valid, consistent request was intentionally provided by the user who submitted the request....\n\n### 4. CWE-90: Improper Neutralization of Special Elements used in an LDAP Query ('LDAP Injection') (Score: 708.82)\n\nThe product constructs all or part of an LDAP query using externally-influenced input from an upstream component, but it does not neutralize or incorrectly neutralizes special elements that could modify the intended LDAP query when it is sent to a downstream component....\n\n### 5. CWE-863: Incorrect Authorization (Score: 180.13)\n\nThe product performs an authorization check when an actor attempts to access a resource or perform an action, but it does not correctly perform the check....\n\n## COMPONENT: 'image_gallery shortcode'\n\nRelevant CWEs for this COMPONENT:\n\n### 1. CWE-116: Improper Encoding or Escaping of Output (Score: 765.77)\n\nThe product prepares a structured message for communication with another component, but encoding or escaping of the data is either missing or done incorrectly. As a result, the intended structure of the message is not preserved....\n\n### 2. CWE-89: Improper Neutralization of Special Elements used in an SQL Command ('SQL Injection') (Score: 754.51)\n\nThe product constructs all or part of an SQL command using externally-influenced input from an upstream component, but it does not neutralize or incorrectly neutralizes special elements that could modify the intended SQL command when it is sent to a downstream component. Without sufficient removal o...\n\n### 3. CWE-352: Cross-Site Request Forgery (CSRF) (Score: 713.08)\n\nThe web application does not, or can not, sufficiently verify whether a well-formed, valid, consistent request was intentionally provided by the user who submitted the request....\n\n### 4. CWE-90: Improper Neutralization of Special Elements used in an LDAP Query ('LDAP Injection') (Score: 708.82)\n\nThe product constructs all or part of an LDAP query using externally-influenced input from an upstream component, but it does not neutralize or incorrectly neutralizes special elements that could modify the intended LDAP query when it is sent to a downstream component....\n\n### 5. CWE-863: Incorrect Authorization (Score: 180.13)\n\nThe product performs an authorization check when an actor attempts to access a resource or perform an action, but it does not correctly perform the check....\n\n\n    # Analysis Instructions\n    1. For each keyphrase, identify the most appropriate CWE(s) that represent the weakness.\n    2. Consider how the different keyphrases might relate to each other in the vulnerability chain.\n    3. Provide a final determination of primary CWE(s) and any secondary CWEs.\n    4. Format your response using the standard analysis template.\n\n    Please analyze how these different weaknesses interact and provide a comprehensive CWE classification.\n    "
  },
  "retrieval_time": 2.5655248165130615
}