{
  "cve_id": "CVE-2025-26004",
  "description": "Telesquare TLR-2005KSH 1.1.4 is vulnerable to unauthorized **stack buffer overflow vulnerability** when requesting admin.cgi parameter with setDdns.",
  "key_phrases": {
    "rootcause": "",
    "weakness": "stack buffer overflow vulnerability",
    "impact": "unauthorized access",
    "vector": "",
    "attacker": "",
    "product": "Telesquare TLR-2005KSH",
    "version": "1.1.4",
    "component": "admin.cgi"
  },
  "reference_content": null,
  "similar_info": {
    "cwe_distribution": {},
    "cwe_consensus": "",
    "similarity_stats": {
      "thresholds": [],
      "total_samples_by_threshold": {},
      "top_cwes_by_threshold": {}
    }
  },
  "similarity_summary": {
    "consensus_cwe": "",
    "top_cwes": [],
    "confidence_levels": {},
    "total_samples": 0
  },
  "analysis": "# Summary\n| CWE ID | CWE Name | Confidence | CWE Abstraction Level | CWE Vulnerability Mapping Label | CWE-Vulnerability Mapping Notes |\n|---|---|---|---|---|---|\n| CWE-121 | Stack-based Buffer Overflow | 1.0 | Variant | Allowed | Primary CWE |\n| CWE-119 | Improper Restriction of Operations within the Bounds of a Memory Buffer | 0.7 | Class | Discouraged | Secondary Candidate |\n\n## Evidence and Confidence\n\n*   **Confidence Score:** 0.9\n*   **Evidence Strength:** HIGH\n\n## Relationship Analysis\nThe primary weakness is a stack-based buffer overflow (CWE-121), a variant of the more general class, Improper Restriction of Operations within the Bounds of a Memory Buffer (CWE-119). The analysis focuses on identifying the most specific CWE that accurately reflects the vulnerability.\n\n```mermaid\ngraph TD\n    cwe121[\"CWE-121: Stack-based Buffer Overflow\"]\n    cwe119[\"CWE-119: Improper Restriction of Operations within the Bounds of a Memory Buffer\"]\n\n    cwe121 -->|CHILDOF| cwe119\n\n    classDef primary fill:#f96,stroke:#333,stroke-width:2px\n    classDef secondary fill:#69f,stroke:#333\n    class cwe121 primary\n    class cwe119 secondary\n```\n\n## Vulnerability Chain\nThe vulnerability chain starts with a **stack buffer overflow vulnerability** (CWE-121), leading to unauthorized access. The root cause is the insufficient validation of input size before copying data to a stack-allocated buffer, resulting in overwriting adjacent memory regions on the stack.\n\n## Summary of Analysis\nThe vulnerability description clearly states a \"**stack buffer overflow vulnerability**\" when requesting a specific parameter. The Retriever Results also list CWE-121 as a potential candidate. The final decision is based on the explicit mention of \"stack buffer overflow\" in the vulnerability description, which makes CWE-121 the most appropriate and specific choice. CWE-119 is considered as a secondary candidate as it is the parent class of CWE-121.\n\nRelevant CWE Information:\n\n# Enhanced Context (25 CWEs)\nThe following CWEs were identified as potentially relevant to this vulnerability:\n\n## CWE-121: Stack-based Buffer Overflow\n**Abstraction Level**: Variant\n**Similarity Score**: 0.71\n**Source**: dense\n\n**Description**:\nA stack-based buffer overflow condition is a condition where the buffer being overwritten is allocated on the stack (i.e., is a local variable or, rarely, a parameter to a function).\n\n**Mapping Guidance**:\n- Usage: Allowed\n- Rationale: This CWE entry is at the Variant level of abstraction, which is a preferred level of abstraction for mapping to the root causes of vulnerabilities.\n\n## CWE-119: Improper Restriction of Operations within the Bounds of a Memory Buffer\n**Abstraction Level**: Class\n**Similarity Score**: 0.80\n**Source**: alternate_terms\n\n**Description**: The product performs an operation on a memory buffer, but it does not correctly perform bounds checking, which can lead to read or write operations outside of the intended buffer.\n\n## Vulnerability Description\nTelesquare TLR-2005KSH 1.1.4 is vulnerable to unauthorized **stack buffer overflow vulnerability** when requesting admin.cgi parameter with setDdns.\n\n### Vulnerability Description Key Phrases\n- **weakness:** **stack buffer overflow vulnerability**\n- **impact:** unauthorized access\n- **product:** Telesquare TLR-2005KSH\n- **version:** 1.1.4\n- **component:** admin.cgi\n\n## Retriever Results\n\n### Top Combined Results\n\n| Rank | CWE ID | Name | Abstraction | Usage  | Retrievers | Individual Scores |\n|------|--------|------|-------------|-------|------------|-------------------|\n| 1 | 119 | Improper Restriction of Operations within the Bounds of a Memory Buffer | Class | Discouraged | alternate_terms | 0.800 |\n| 2 | 190 | Integer Overflow or Wraparound | Base | Allowed | alternate_terms | 0.800 |\n| 3 | 121 | Stack-based Buffer Overflow | Variant | Allowed | sparse | 0.155 |\n| 4 | 120 | Buffer Copy without Checking Size of Input ('Classic Buffer Overflow') | Base | Allowed-with-Review | sparse | 0.133 |\n\n**CWE-121: Stack-based Buffer Overflow**\n*   **Explanation:** The vulnerability description explicitly mentions a \"**stack buffer overflow vulnerability**\". This directly aligns with the definition of CWE-121, which involves overflowing a buffer allocated on the stack.\n*   **Security Implications:** Stack-based buffer overflows can allow attackers to overwrite return addresses, function pointers, or other critical data on the stack, leading to arbitrary code execution.\n*   **Relationship:** CWE-121 is a variant (more specific type) of CWE-119 (Improper Restriction of Operations within the Bounds of a Memory Buffer).\n*   **Mapping Guidance:** The usage is \"Allowed\" and the Abstraction Level is Variant which is the preferred level.\n*   **Confidence:** 1.0\n\n**CWE-119: Improper Restriction of Operations within the Bounds of a Memory Buffer**\n*   **Explanation:** This is a more general class of weakness that includes buffer overflows. While relevant, it is less specific than CWE-121, given the explicit mention of \"stack\" in the vulnerability description.\n*   **Security Implications:** Can lead to memory corruption, information disclosure, or arbitrary code execution.\n*   **Relationship:** It is the parent class of CWE-121.\n*   **Mapping Guidance:** The usage is \"Discouraged\" and the Abstraction Level is Class. This CWE entry is a Class and might have Base-level children that would be more appropriate\n*   **Confidence:** 0.7\n\n**CWEs Considered but Not Used:**\n\n*   CWE-120: Buffer Copy without Checking Size of Input ('Classic Buffer Overflow'): While this CWE also deals with buffer overflows, it doesn't specify that the buffer is stack-based. The vulnerability description explicitly states \"stack buffer overflow,\" making CWE-121 a more precise fit.\n*   CWE-190: Integer Overflow or Wraparound: This CWE is related to integer calculations, and there's no information in the vulnerability description to suggest an integer overflow is the root cause.\n*   CWE-125: Out-of-bounds Read: This CWE involves reading data outside the intended buffer, while the vulnerability description indicates a buffer overflow (write), making it less relevant.\n*   CWE-193: Off-by-one Error: This CWE involves incorrect maximum or minimum values, which is not directly indicated in the vulnerability description.\n*   CWE-1284: Improper Validation of Specified Quantity in Input: While input validation might be a factor, the core issue is the stack buffer overflow, making CWE-121 the more direct and accurate classification.\n*   CWE-674: Uncontrolled Recursion: This CWE is about uncontrolled recursion, not memory corruption.\n*   CWE-78: Improper Neutralization of Special Elements used in an OS Command ('OS Command Injection'): There's no indication of OS command injection in the vulnerability description.\n*   CWE-128: Wrap-around Error: This CWE is about wrap-around errors, and there's no information in the vulnerability description to suggest this type of error.\n*   CWE-131: Incorrect Calculation of Buffer Size: While the buffer size may be incorrect, the explicit mention of a *stack* buffer overflow makes CWE-121 a better fit.",
  "analysis_with_relationships": "# Summary\n| CWE ID | CWE Name | Confidence | CWE Abstraction Level | CWE Vulnerability Mapping Label | CWE-Vulnerability Mapping Notes |\n|---|---|---|---|---|---|\n| CWE-121 | Stack-based Buffer Overflow | 1.0 | Variant | Allowed | Primary CWE |\n| CWE-119 | Improper Restriction of Operations within the Bounds of a Memory Buffer | 0.7 | Class | Discouraged | Secondary Candidate |\n\n## Evidence and Confidence\n\n*   **Confidence Score:** 0.9\n*   **Evidence Strength:** HIGH\n\n## Relationship Analysis\nThe primary weakness is a stack-based buffer overflow (CWE-121), a variant of the more general class, Improper Restriction of Operations within the Bounds of a Memory Buffer (CWE-119). The analysis focuses on identifying the most specific CWE that accurately reflects the vulnerability.\n\n```mermaid\ngraph TD\n    cwe121[\"CWE-121: Stack-based Buffer Overflow\"]\n    cwe119[\"CWE-119: Improper Restriction of Operations within the Bounds of a Memory Buffer\"]\n\n    cwe121 -->|CHILDOF| cwe119\n\n    classDef primary fill:#f96,stroke:#333,stroke-width:2px\n    classDef secondary fill:#69f,stroke:#333\n    class cwe121 primary\n    class cwe119 secondary\n```\n\n## Vulnerability Chain\nThe vulnerability chain starts with a **stack buffer overflow vulnerability** (CWE-121), leading to unauthorized access. The root cause is the insufficient validation of input size before copying data to a stack-allocated buffer, resulting in overwriting adjacent memory regions on the stack.\n\n## Summary of Analysis\nThe vulnerability description clearly states a \"**stack buffer overflow vulnerability**\" when requesting a specific parameter. The Retriever Results also list CWE-121 as a potential candidate. The final decision is based on the explicit mention of \"stack buffer overflow\" in the vulnerability description, which makes CWE-121 the most appropriate and specific choice. CWE-119 is considered as a secondary candidate as it is the parent class of CWE-121.\n\nRelevant CWE Information:\n\n# Enhanced Context (25 CWEs)\nThe following CWEs were identified as potentially relevant to this vulnerability:\n\n## CWE-121: Stack-based Buffer Overflow\n**Abstraction Level**: Variant\n**Similarity Score**: 0.71\n**Source**: dense\n\n**Description**:\nA stack-based buffer overflow condition is a condition where the buffer being overwritten is allocated on the stack (i.e., is a local variable or, rarely, a parameter to a function).\n\n**Mapping Guidance**:\n- Usage: Allowed\n- Rationale: This CWE entry is at the Variant level of abstraction, which is a preferred level of abstraction for mapping to the root causes of vulnerabilities.\n\n## CWE-119: Improper Restriction of Operations within the Bounds of a Memory Buffer\n**Abstraction Level**: Class\n**Similarity Score**: 0.80\n**Source**: alternate_terms\n\n**Description**: The product performs an operation on a memory buffer, but it does not correctly perform bounds checking, which can lead to read or write operations outside of the intended buffer.\n\n## Vulnerability Description\nTelesquare TLR-2005KSH 1.1.4 is vulnerable to unauthorized **stack buffer overflow vulnerability** when requesting admin.cgi parameter with setDdns.\n\n### Vulnerability Description Key Phrases\n- **weakness:** **stack buffer overflow vulnerability**\n- **impact:** unauthorized access\n- **product:** Telesquare TLR-2005KSH\n- **version:** 1.1.4\n- **component:** admin.cgi\n\n## Retriever Results\n\n### Top Combined Results\n\n| Rank | CWE ID | Name | Abstraction | Usage  | Retrievers | Individual Scores |\n|------|--------|------|-------------|-------|------------|-------------------|\n| 1 | 119 | Improper Restriction of Operations within the Bounds of a Memory Buffer | Class | Discouraged | alternate_terms | 0.800 |\n| 2 | 190 | Integer Overflow or Wraparound | Base | Allowed | alternate_terms | 0.800 |\n| 3 | 121 | Stack-based Buffer Overflow | Variant | Allowed | sparse | 0.155 |\n| 4 | 120 | Buffer Copy without Checking Size of Input ('Classic Buffer Overflow') | Base | Allowed-with-Review | sparse | 0.133 |\n\n**CWE-121: Stack-based Buffer Overflow**\n*   **Explanation:** The vulnerability description explicitly mentions a \"**stack buffer overflow vulnerability**\". This directly aligns with the definition of CWE-121, which involves overflowing a buffer allocated on the stack.\n*   **Security Implications:** Stack-based buffer overflows can allow attackers to overwrite return addresses, function pointers, or other critical data on the stack, leading to arbitrary code execution.\n*   **Relationship:** CWE-121 is a variant (more specific type) of CWE-119 (Improper Restriction of Operations within the Bounds of a Memory Buffer).\n*   **Mapping Guidance:** The usage is \"Allowed\" and the Abstraction Level is Variant which is the preferred level.\n*   **Confidence:** 1.0\n\n**CWE-119: Improper Restriction of Operations within the Bounds of a Memory Buffer**\n*   **Explanation:** This is a more general class of weakness that includes buffer overflows. While relevant, it is less specific than CWE-121, given the explicit mention of \"stack\" in the vulnerability description.\n*   **Security Implications:** Can lead to memory corruption, information disclosure, or arbitrary code execution.\n*   **Relationship:** It is the parent class of CWE-121.\n*   **Mapping Guidance:** The usage is \"Discouraged\" and the Abstraction Level is Class. This CWE entry is a Class and might have Base-level children that would be more appropriate\n*   **Confidence:** 0.7\n\n**CWEs Considered but Not Used:**\n\n*   CWE-120: Buffer Copy without Checking Size of Input ('Classic Buffer Overflow'): While this CWE also deals with buffer overflows, it doesn't specify that the buffer is stack-based. The vulnerability description explicitly states \"stack buffer overflow,\" making CWE-121 a more precise fit.\n*   CWE-190: Integer Overflow or Wraparound: This CWE is related to integer calculations, and there's no information in the vulnerability description to suggest an integer overflow is the root cause.\n*   CWE-125: Out-of-bounds Read: This CWE involves reading data outside the intended buffer, while the vulnerability description indicates a buffer overflow (write), making it less relevant.\n*   CWE-193: Off-by-one Error: This CWE involves incorrect maximum or minimum values, which is not directly indicated in the vulnerability description.\n*   CWE-1284: Improper Validation of Specified Quantity in Input: While input validation might be a factor, the core issue is the stack buffer overflow, making CWE-121 the more direct and accurate classification.\n*   CWE-674: Uncontrolled Recursion: This CWE is about uncontrolled recursion, not memory corruption.\n*   CWE-78: Improper Neutralization of Special Elements used in an OS Command ('OS Command Injection'): There's no indication of OS command injection in the vulnerability description.\n*   CWE-128: Wrap-around Error: This CWE is about wrap-around errors, and there's no information in the vulnerability description to suggest this type of error.\n*   CWE-131: Incorrect Calculation of Buffer Size: While the buffer size may be incorrect, the explicit mention of a *stack* buffer overflow makes CWE-121 a better fit.\n\n\n## CWE Relationship Analysis\n\nCurrent CWEs represent these abstraction levels: .\n\n\n### Vulnerability Chain Analysis\n\n**Chain starting from CWE-121:**\n- 121 (Stack-based Buffer Overflow) - ROOT\n\n\n**Chain starting from CWE-1284:**\n- 1284 (Improper Validation of Specified Quantity in Input) - ROOT\n\n\n\n### CWE Relationship Diagram\n\n```mermaid\ngraph TD\n    classDef primary fill:#f96,stroke:#333,stroke-width:2px\n    classDef secondary fill:#69f,stroke:#333\n    classDef tertiary fill:#9e9,stroke:#333\n```",
  "criticism": "",
  "resolution": "",
  "relevant_cwes": [
    {
      "metadata": {
        "doc_id": "119",
        "name": "Improper Restriction of Operations within the Bounds of a Memory Buffer",
        "source": "alternate_terms",
        "original_matched_text": "AlternateTerms: Buffer Overflow",
        "match_reason": "term_in_phrase_whole_phrase"
      },
      "similarity": 800.0,
      "alternate_term_match": true
    },
    {
      "metadata": {
        "doc_id": "190",
        "name": "Integer Overflow or Wraparound",
        "source": "alternate_terms",
        "original_matched_text": "AlternateTerms: Overflow",
        "match_reason": "term_in_phrase_whole_phrase"
      },
      "similarity": 800.0,
      "alternate_term_match": true
    },
    {
      "metadata": {
        "doc_id": "121",
        "name": "Stack-based Buffer Overflow",
        "source": "sparse"
      },
      "similarity": 155.3489263838504
    },
    {
      "metadata": {
        "doc_id": "120",
        "name": "Buffer Copy without Checking Size of Input ('Classic Buffer Overflow')",
        "source": "sparse"
      },
      "similarity": 133.25803744210256
    },
    {
      "metadata": {
        "doc_id": "1284",
        "name": "Improper Validation of Specified Quantity in Input",
        "source": "sparse"
      },
      "similarity": 126.03749568246
    },
    {
      "metadata": {
        "doc_id": "674",
        "name": "Uncontrolled Recursion",
        "source": "sparse"
      },
      "similarity": 119.96572872763083
    },
    {
      "metadata": {
        "doc_id": "193",
        "name": "Off-by-one Error",
        "source": "sparse"
      },
      "similarity": 118.27665367722021
    },
    {
      "metadata": {
        "doc_id": "125",
        "name": "Out-of-bounds Read",
        "source": "sparse"
      },
      "similarity": 117.43540631429433
    },
    {
      "metadata": {
        "doc_id": "78",
        "name": "Improper Neutralization of Special Elements used in an OS Command ('OS Command Injection')",
        "type": "Base",
        "original_content": "The product constructs all or part of an OS command using externally-influenced input from an upstream component, but it does not neutralize or incorrectly neutralizes special elements that could modify the intended OS command when it is sent to a downstream component.",
        "source": "dense",
        "mapping_notes": {
          "usage": "Allowed",
          "rationale": "This CWE entry is at the Base level of abstraction, which is a preferred level of abstraction for mapping to the root causes of vulnerabilities.",
          "comments": "Carefully read both the name and description to ensure that this mapping is an appropriate fit. Do not try to 'force' a mapping to a lower-level Base/Variant simply to comply with this preferred level of abstraction.",
          "reasons": [
            "Acceptable-Use"
          ]
        },
        "score_info": {
          "retrievers": [
            "dense"
          ],
          "retriever_count": 1,
          "normalized_scores": {
            "dense": 0.5712394652870292
          }
        }
      },
      "similarity": 0.5712394652870292
    },
    {
      "doc_id": "128",
      "text": "CWE-128: Wrap-around Error",
      "score": 2.9120000000000004,
      "metadata": {
        "doc_id": "128",
        "name": "Wrap-around Error",
        "type": "base",
        "original_content": "CWE-128: Wrap-around Error",
        "relationships": [
          {
            "source_id": "128",
            "target_id": "190",
            "label": "PEEROF",
            "properties": {
              "view_id": "1000"
            }
          },
          {
            "source_id": "128",
            "target_id": "119",
            "label": "CANPRECEDE",
            "properties": {
              "view_id": "1000"
            }
          },
          {
            "source_id": "128",
            "target_id": "682",
            "label": "CHILDOF",
            "properties": {
              "ordinal": "Primary",
              "view_id": "1000"
            }
          },
          {
            "source_id": "682",
            "target_id": "128",
            "label": "PARENTOF",
            "properties": {
              "ordinal": "Primary",
              "view_id": "1000"
            }
          },
          {
            "source_id": "119",
            "target_id": "128",
            "label": "CANFOLLOW",
            "properties": {
              "view_id": "1000"
            }
          }
        ],
        "score_components": {
          "relationship_chain": 1.0,
          "sequence_path": 1.0,
          "peer_group": 0.9
        },
        "abstraction_factor": 1.3,
        "graph_path_info": {
          "path_types": [
            "relationship_chain",
            "vulnerability_sequence_forward",
            "vulnerability_sequence_backward",
            "peer_relationship"
          ],
          "best_paths": {
            "relationship_chain": {
              "path": [
                [
                  "119",
                  "128",
                  "CANFOLLOW"
                ]
              ],
              "score": 1.0,
              "type": "relationship_chain",
              "source": "119"
            },
            "vulnerability_sequence_forward": {
              "path": [
                [
                  "119",
                  "128",
                  "CANFOLLOW"
                ]
              ],
              "score": 0.9,
              "type": "vulnerability_sequence_forward",
              "source": "119"
            },
            "vulnerability_sequence_backward": {
              "path": [
                [
                  "128",
                  "119",
                  "CANPRECEDE"
                ]
              ],
              "score": 1.0,
              "type": "vulnerability_sequence_backward",
              "source": "119"
            },
            "peer_relationship": {
              "path": [
                [
                  "128",
                  "190",
                  "PEEROF"
                ]
              ],
              "score": 0.9,
              "type": "peer_relationship",
              "source": "190"
            }
          }
        },
        "position": "before",
        "sources": [
          "graph"
        ],
        "source": "graph",
        "mapping_notes": {
          "usage": "Allowed",
          "rationale": "This CWE entry is at the Base level of abstraction, which is a preferred level of abstraction for mapping to the root causes of vulnerabilities.",
          "comments": "Carefully read both the name and description to ensure that this mapping is an appropriate fit. Do not try to 'force' a mapping to a lower-level Base/Variant simply to comply with this preferred level of abstraction.",
          "reasons": [
            "Acceptable-Use"
          ]
        },
        "score_info": {
          "retrievers": [
            "graph"
          ],
          "retriever_count": 1,
          "normalized_scores": {
            "graph": 2.9120000000000004
          }
        }
      },
      "similarity": 2.9120000000000004
    }
  ],
  "identified_cwes": {
    "analyzer": [
      "CWE-121",
      "CWE-1284",
      "CWE-125",
      "CWE-131",
      "CWE-193",
      "CWE-190",
      "CWE-674",
      "CWE-78",
      "CWE-119",
      "CWE-120",
      "CWE-128"
    ],
    "critic_additional": []
  },
  "keyphrase_cwe_mapping": {}
}