{
  "vulnerability_info": "VulnerabilityInfo(cve_id='CVE-2024-47687', description='In the Linux kernel, the following vulnerability has been resolved vdpa/mlx5 Fix **invalid mr resource destroy** Certain error paths from mlx5_vdpa_dev_add() can end up releasing mr resources which never got initialized in the first place. This patch adds the **missing check** in mlx5_vdpa_destroy_mr_resources() to block releasing non-initialized mr resources. Reference trace mlx5_core 00000800.2 mlx5_vdpa_dev_add3274(pid 2700) warning No mac address provisioned? BUG kernel NULL pointer dereference, address 0000000000000000 #PF supervisor read access in kernel mode #PF error_code(0x0000) - not-present page PGD 140216067 P4D 0 Oops 0000 [#1] PREEMPT SMP NOPTI CPU 8 PID 2700 Comm vdpa Kdump loaded Not tainted 5.14.0-496.el9.x86_64 #1 Hardware name QEMU Standard PC (Q35 + ICH9, 2009), BIOS rel-1.13.0-0-gf21b5a4aeb02-prebuilt.qemu.org 04/01/2014 RIP 0010vhost_iotlb_del_range+0xf/0xe0 [vhost_iotlb] Code [...] RSP 0018ff1c823ac23077f0 EFLAGS 00010246 RAX ffffffffc1a21a60 RBX ffffffff899567a0 RCX 0000000000000000 RDX ffffffffffffffff RSI 0000000000000000 RDI 0000000000000000 RBP ff1bda1f7c21e800 R08 0000000000000000 R09 ff1c823ac2307670 R10 ff1c823ac2307668 R11 ffffffff8a9e7b68 R12 0000000000000000 R13 0000000000000000 R14 ff1bda1f43e341a0 R15 00000000ffffffea FS 00007f56eba7c740(0000) GSff1bda269f800000(0000) knlGS0000000000000000 CS 0010 DS 0000 ES 0000 CR0 0000000080050033 CR2 0000000000000000 CR', key_phrases={'rootcause': ['invalid mr resource destroy', 'missing check'], 'weakness': '', 'impact': ['Oops', 'read access'], 'vector': '', 'attacker': '', 'product': 'Linux kernel', 'version': '', 'component': ''}, reference_content='Based on the provided information, this content is related to CVE-2024-47687.\\n\\n**Root cause of vulnerability:**\\nThe vulnerability stems from missing checks in the `mlx5_vdpa_destroy_mr_resources()` function. Certain error paths within `mlx5_vdpa_dev_add()` can lead to the release of memory region (mr) resources that were never properly initialized.\\n\\n**Weaknesses/vulnerabilities present:**\\n- **Use-after-free or double-free:** The core issue is attempting to free memory resources (mr) that were not allocated or initialized. If certain error conditions occur during device setup, the teardown process tries to free these resources, resulting in a double-free or use-after-free scenario.\\n\\n**Impact of exploitation:**\\n- **Kernel crash:** The provided reference trace demonstrates a kernel NULL pointer dereference leading to a crash, specifically in `vhost_iotlb_del_range`. This can lead to a denial of service.\\n\\n**Attack vectors:**\\n- **Error conditions during device setup:** The vulnerability is triggered by specific error conditions occurring during the `mlx5_vdpa_dev_add()` function, which is part of the virtual data path accelerator (vdpa) device setup. This suggests that an attacker needs some control over vdpa device configuration or resource provisioning to trigger the vulnerability.\\n- **vdpa device interaction:** It is likely an attacker would need to interact with the vdpa device through a virtualized environment, possibly using netlink commands to trigger the error condition.\\n\\n**Required attacker capabilities/position:**\\n- **Privileged access:** The attacker would likely need some level of privilege or control over the virtualized environment to trigger the error during device setup.  The crash occurs in kernel space, indicating a privileged context is involved in triggering this bug.\\n- **vdpa specific setup:** The attacker would need the ability to configure or manipulate vdpa devices or resources to reach the vulnerable code path.\\n\\n**Additional details:**\\n\\n- The fix adds a check to verify if the `mvdev->res.valid` flag is set before attempting to release the memory resources inside the `mlx5_vdpa_destroy_mr_resources()` function.\\n- The issue was detected from a kernel crash report demonstrating the NULL pointer dereference.\\n- The fix has been backported to multiple stable kernel branches.\\n- The issue relates to memory management within the Mellanox (mlx5) virtual data path acceleration driver.', similar_info={'cwe_distribution': {}, 'cwe_consensus': '', 'similarity_stats': {'thresholds': [], 'total_samples_by_threshold': {}, 'top_cwes_by_threshold': {}}}, similarity_summary=SimilarityInsight(consensus_cwe='', top_cwes=[], confidence_levels={}, total_samples=0), analysis='', analysis_with_relationships='', criticism='', resolution='', relevant_cwes=[{'metadata': {'doc_id': '909', 'name': 'Missing Initialization of Resource', 'source': 'sparse', 'original_content': 'The product does not initialize a critical resource.', 'keyphrase_sources': [{'id': 'rootcause:invalid mr resource destroy', 'keyphrase': 'invalid mr resource destroy', 'type': 'rootcause'}, {'id': 'rootcause:missing check', 'keyphrase': 'missing check', 'type': 'rootcause'}, {'id': 'impact:Oops', 'keyphrase': 'Oops', 'type': 'impact'}, {'id': 'impact:read access', 'keyphrase': 'read access', 'type': 'impact'}, {'id': 'product:Linux kernel', 'keyphrase': 'Linux kernel', 'type': 'product'}]}, 'similarity': np.float64(461.289362302365)}, {'metadata': {'doc_id': '400', 'name': 'Uncontrolled Resource Consumption', 'source': 'sparse', 'original_content': 'The product does not properly control the allocation and maintenance of a limited resource, thereby enabling an actor to influence the amount of resources consumed, eventually leading to the exhaustion of available resources.', 'keyphrase_sources': [{'id': 'rootcause:invalid mr resource destroy', 'keyphrase': 'invalid mr resource destroy', 'type': 'rootcause'}, {'id': 'impact:Oops', 'keyphrase': 'Oops', 'type': 'impact'}, {'id': 'impact:read access', 'keyphrase': 'read access', 'type': 'impact'}, {'id': 'product:Linux kernel', 'keyphrase': 'Linux kernel', 'type': 'product'}]}, 'similarity': np.float64(431.04278654628786)}, {'metadata': {'doc_id': '667', 'name': 'Improper Locking', 'source': 'sparse', 'original_content': 'The product does not properly acquire or release a lock on a resource, leading to unexpected resource state changes and behaviors.', 'keyphrase_sources': [{'id': 'rootcause:invalid mr resource destroy', 'keyphrase': 'invalid mr resource destroy', 'type': 'rootcause'}, {'id': 'rootcause:missing check', 'keyphrase': 'missing check', 'type': 'rootcause'}, {'id': 'impact:Oops', 'keyphrase': 'Oops', 'type': 'impact'}, {'id': 'impact:read access', 'keyphrase': 'read access', 'type': 'impact'}, {'id': 'product:Linux kernel', 'keyphrase': 'Linux kernel', 'type': 'product'}]}, 'similarity': np.float64(414.6972777444188)}, {'metadata': {'doc_id': '362', 'name': \"Concurrent Execution using Shared Resource with Improper Synchronization ('Race Condition')\", 'source': 'sparse', 'original_content': 'The product contains a concurrent code sequence that requires temporary, exclusive access to a shared resource, but a timing window exists in which the shared resource can be modified by another code sequence operating concurrently.', 'keyphrase_sources': [{'id': 'rootcause:invalid mr resource destroy', 'keyphrase': 'invalid mr resource destroy', 'type': 'rootcause'}, {'id': 'rootcause:missing check', 'keyphrase': 'missing check', 'type': 'rootcause'}, {'id': 'impact:Oops', 'keyphrase': 'Oops', 'type': 'impact'}, {'id': 'impact:read access', 'keyphrase': 'read access', 'type': 'impact'}, {'id': 'product:Linux kernel', 'keyphrase': 'Linux kernel', 'type': 'product'}]}, 'similarity': np.float64(411.79872987498044)}, {'metadata': {'doc_id': '824', 'name': 'Access of Uninitialized Pointer', 'source': 'sparse', 'original_content': 'The product accesses or uses a pointer that has not been initialized.', 'keyphrase_sources': [{'id': 'rootcause:invalid mr resource destroy', 'keyphrase': 'invalid mr resource destroy', 'type': 'rootcause'}, {'id': 'rootcause:missing check', 'keyphrase': 'missing check', 'type': 'rootcause'}, {'id': 'impact:Oops', 'keyphrase': 'Oops', 'type': 'impact'}, {'id': 'impact:read access', 'keyphrase': 'read access', 'type': 'impact'}]}, 'similarity': np.float64(409.8240959911765)}, {'metadata': {'doc_id': '476', 'name': 'NULL Pointer Dereference', 'source': 'sparse', 'original_content': 'The product dereferences a pointer that it expects to be valid but is NULL.', 'keyphrase_sources': [{'id': 'rootcause:missing check', 'keyphrase': 'missing check', 'type': 'rootcause'}]}, 'similarity': np.float64(405.0373028281116)}, {'metadata': {'doc_id': '833', 'name': 'Deadlock', 'source': 'sparse', 'original_content': 'The product contains multiple threads or executable segments that are waiting for each other to release a necessary lock, resulting in deadlock.', 'keyphrase_sources': [{'id': 'product:Linux kernel', 'keyphrase': 'Linux kernel', 'type': 'product'}]}, 'similarity': np.float64(139.8157714412309)}], identified_cwes={'analyzer': [], 'critic_additional': []})",
  "retrieval_results": {
    "has_multiple_keyphrases": true,
    "keyphrase_cwe_sets": {
      "rootcause:invalid mr resource destroy": {
        "keyphrase": "invalid mr resource destroy",
        "type": "rootcause",
        "cwes": [
          {
            "metadata": {
              "doc_id": "909",
              "name": "Missing Initialization of Resource",
              "source": "sparse",
              "original_content": "The product does not initialize a critical resource.",
              "keyphrase_sources": [
                {
                  "id": "rootcause:invalid mr resource destroy",
                  "keyphrase": "invalid mr resource destroy",
                  "type": "rootcause"
                },
                {
                  "id": "rootcause:missing check",
                  "keyphrase": "missing check",
                  "type": "rootcause"
                },
                {
                  "id": "impact:Oops",
                  "keyphrase": "Oops",
                  "type": "impact"
                },
                {
                  "id": "impact:read access",
                  "keyphrase": "read access",
                  "type": "impact"
                },
                {
                  "id": "product:Linux kernel",
                  "keyphrase": "Linux kernel",
                  "type": "product"
                }
              ]
            },
            "similarity": 461.289362302365
          },
          {
            "metadata": {
              "doc_id": "400",
              "name": "Uncontrolled Resource Consumption",
              "source": "sparse",
              "original_content": "The product does not properly control the allocation and maintenance of a limited resource, thereby enabling an actor to influence the amount of resources consumed, eventually leading to the exhaustion of available resources.",
              "keyphrase_sources": [
                {
                  "id": "rootcause:invalid mr resource destroy",
                  "keyphrase": "invalid mr resource destroy",
                  "type": "rootcause"
                },
                {
                  "id": "impact:Oops",
                  "keyphrase": "Oops",
                  "type": "impact"
                },
                {
                  "id": "impact:read access",
                  "keyphrase": "read access",
                  "type": "impact"
                },
                {
                  "id": "product:Linux kernel",
                  "keyphrase": "Linux kernel",
                  "type": "product"
                }
              ]
            },
            "similarity": 431.04278654628786
          },
          {
            "metadata": {
              "doc_id": "667",
              "name": "Improper Locking",
              "source": "sparse",
              "original_content": "The product does not properly acquire or release a lock on a resource, leading to unexpected resource state changes and behaviors.",
              "keyphrase_sources": [
                {
                  "id": "rootcause:invalid mr resource destroy",
                  "keyphrase": "invalid mr resource destroy",
                  "type": "rootcause"
                },
                {
                  "id": "rootcause:missing check",
                  "keyphrase": "missing check",
                  "type": "rootcause"
                },
                {
                  "id": "impact:Oops",
                  "keyphrase": "Oops",
                  "type": "impact"
                },
                {
                  "id": "impact:read access",
                  "keyphrase": "read access",
                  "type": "impact"
                },
                {
                  "id": "product:Linux kernel",
                  "keyphrase": "Linux kernel",
                  "type": "product"
                }
              ]
            },
            "similarity": 414.6972777444188
          },
          {
            "metadata": {
              "doc_id": "362",
              "name": "Concurrent Execution using Shared Resource with Improper Synchronization ('Race Condition')",
              "source": "sparse",
              "original_content": "The product contains a concurrent code sequence that requires temporary, exclusive access to a shared resource, but a timing window exists in which the shared resource can be modified by another code sequence operating concurrently.",
              "keyphrase_sources": [
                {
                  "id": "rootcause:invalid mr resource destroy",
                  "keyphrase": "invalid mr resource destroy",
                  "type": "rootcause"
                },
                {
                  "id": "rootcause:missing check",
                  "keyphrase": "missing check",
                  "type": "rootcause"
                },
                {
                  "id": "impact:Oops",
                  "keyphrase": "Oops",
                  "type": "impact"
                },
                {
                  "id": "impact:read access",
                  "keyphrase": "read access",
                  "type": "impact"
                },
                {
                  "id": "product:Linux kernel",
                  "keyphrase": "Linux kernel",
                  "type": "product"
                }
              ]
            },
            "similarity": 411.79872987498044
          },
          {
            "metadata": {
              "doc_id": "824",
              "name": "Access of Uninitialized Pointer",
              "source": "sparse",
              "original_content": "The product accesses or uses a pointer that has not been initialized.",
              "keyphrase_sources": [
                {
                  "id": "rootcause:invalid mr resource destroy",
                  "keyphrase": "invalid mr resource destroy",
                  "type": "rootcause"
                },
                {
                  "id": "rootcause:missing check",
                  "keyphrase": "missing check",
                  "type": "rootcause"
                },
                {
                  "id": "impact:Oops",
                  "keyphrase": "Oops",
                  "type": "impact"
                },
                {
                  "id": "impact:read access",
                  "keyphrase": "read access",
                  "type": "impact"
                }
              ]
            },
            "similarity": 409.8240959911765
          }
        ]
      },
      "rootcause:missing check": {
        "keyphrase": "missing check",
        "type": "rootcause",
        "cwes": [
          {
            "metadata": {
              "doc_id": "909",
              "name": "Missing Initialization of Resource",
              "source": "sparse",
              "original_content": "The product does not initialize a critical resource."
            },
            "similarity": 414.3783217535764
          },
          {
            "metadata": {
              "doc_id": "824",
              "name": "Access of Uninitialized Pointer",
              "source": "sparse",
              "original_content": "The product accesses or uses a pointer that has not been initialized."
            },
            "similarity": 411.7814520881452
          },
          {
            "metadata": {
              "doc_id": "476",
              "name": "NULL Pointer Dereference",
              "source": "sparse",
              "original_content": "The product dereferences a pointer that it expects to be valid but is NULL.",
              "keyphrase_sources": [
                {
                  "id": "rootcause:missing check",
                  "keyphrase": "missing check",
                  "type": "rootcause"
                }
              ]
            },
            "similarity": 405.0373028281116
          },
          {
            "metadata": {
              "doc_id": "667",
              "name": "Improper Locking",
              "source": "sparse",
              "original_content": "The product does not properly acquire or release a lock on a resource, leading to unexpected resource state changes and behaviors."
            },
            "similarity": 403.8681682816881
          },
          {
            "metadata": {
              "doc_id": "362",
              "name": "Concurrent Execution using Shared Resource with Improper Synchronization ('Race Condition')",
              "source": "sparse",
              "original_content": "The product contains a concurrent code sequence that requires temporary, exclusive access to a shared resource, but a timing window exists in which the shared resource can be modified by another code sequence operating concurrently."
            },
            "similarity": 403.58896605688443
          }
        ]
      },
      "impact:Oops": {
        "keyphrase": "Oops",
        "type": "impact",
        "cwes": [
          {
            "metadata": {
              "doc_id": "400",
              "name": "Uncontrolled Resource Consumption",
              "source": "sparse",
              "original_content": "The product does not properly control the allocation and maintenance of a limited resource, thereby enabling an actor to influence the amount of resources consumed, eventually leading to the exhaustion of available resources."
            },
            "similarity": 132.5695878523353
          },
          {
            "metadata": {
              "doc_id": "909",
              "name": "Missing Initialization of Resource",
              "source": "sparse",
              "original_content": "The product does not initialize a critical resource."
            },
            "similarity": 132.3282105321814
          },
          {
            "metadata": {
              "doc_id": "667",
              "name": "Improper Locking",
              "source": "sparse",
              "original_content": "The product does not properly acquire or release a lock on a resource, leading to unexpected resource state changes and behaviors."
            },
            "similarity": 130.03538058752096
          },
          {
            "metadata": {
              "doc_id": "362",
              "name": "Concurrent Execution using Shared Resource with Improper Synchronization ('Race Condition')",
              "source": "sparse",
              "original_content": "The product contains a concurrent code sequence that requires temporary, exclusive access to a shared resource, but a timing window exists in which the shared resource can be modified by another code sequence operating concurrently."
            },
            "similarity": 129.6992435620914
          },
          {
            "metadata": {
              "doc_id": "824",
              "name": "Access of Uninitialized Pointer",
              "source": "sparse",
              "original_content": "The product accesses or uses a pointer that has not been initialized."
            },
            "similarity": 128.8984046307153
          }
        ]
      },
      "impact:read access": {
        "keyphrase": "read access",
        "type": "impact",
        "cwes": [
          {
            "metadata": {
              "doc_id": "909",
              "name": "Missing Initialization of Resource",
              "source": "sparse",
              "original_content": "The product does not initialize a critical resource."
            },
            "similarity": 139.7417979328659
          },
          {
            "metadata": {
              "doc_id": "824",
              "name": "Access of Uninitialized Pointer",
              "source": "sparse",
              "original_content": "The product accesses or uses a pointer that has not been initialized."
            },
            "similarity": 138.1793373100335
          },
          {
            "metadata": {
              "doc_id": "400",
              "name": "Uncontrolled Resource Consumption",
              "source": "sparse",
              "original_content": "The product does not properly control the allocation and maintenance of a limited resource, thereby enabling an actor to influence the amount of resources consumed, eventually leading to the exhaustion of available resources."
            },
            "similarity": 138.04233703541485
          },
          {
            "metadata": {
              "doc_id": "362",
              "name": "Concurrent Execution using Shared Resource with Improper Synchronization ('Race Condition')",
              "source": "sparse",
              "original_content": "The product contains a concurrent code sequence that requires temporary, exclusive access to a shared resource, but a timing window exists in which the shared resource can be modified by another code sequence operating concurrently."
            },
            "similarity": 137.98870302884126
          },
          {
            "metadata": {
              "doc_id": "667",
              "name": "Improper Locking",
              "source": "sparse",
              "original_content": "The product does not properly acquire or release a lock on a resource, leading to unexpected resource state changes and behaviors."
            },
            "similarity": 136.13173590537681
          }
        ]
      },
      "product:Linux kernel": {
        "keyphrase": "Linux kernel",
        "type": "product",
        "cwes": [
          {
            "metadata": {
              "doc_id": "909",
              "name": "Missing Initialization of Resource",
              "source": "sparse",
              "original_content": "The product does not initialize a critical resource."
            },
            "similarity": 148.78896405866112
          },
          {
            "metadata": {
              "doc_id": "362",
              "name": "Concurrent Execution using Shared Resource with Improper Synchronization ('Race Condition')",
              "source": "sparse",
              "original_content": "The product contains a concurrent code sequence that requires temporary, exclusive access to a shared resource, but a timing window exists in which the shared resource can be modified by another code sequence operating concurrently."
            },
            "similarity": 144.6463807868319
          },
          {
            "metadata": {
              "doc_id": "667",
              "name": "Improper Locking",
              "source": "sparse",
              "original_content": "The product does not properly acquire or release a lock on a resource, leading to unexpected resource state changes and behaviors."
            },
            "similarity": 144.35607673024427
          },
          {
            "metadata": {
              "doc_id": "833",
              "name": "Deadlock",
              "source": "sparse",
              "original_content": "The product contains multiple threads or executable segments that are waiting for each other to release a necessary lock, resulting in deadlock.",
              "keyphrase_sources": [
                {
                  "id": "product:Linux kernel",
                  "keyphrase": "Linux kernel",
                  "type": "product"
                }
              ]
            },
            "similarity": 139.8157714412309
          },
          {
            "metadata": {
              "doc_id": "400",
              "name": "Uncontrolled Resource Consumption",
              "source": "sparse",
              "original_content": "The product does not properly control the allocation and maintenance of a limited resource, thereby enabling an actor to influence the amount of resources consumed, eventually leading to the exhaustion of available resources."
            },
            "similarity": 136.9387098617271
          }
        ]
      }
    },
    "keyphrase_mapping": {
      "909": [
        {
          "id": "rootcause:invalid mr resource destroy",
          "keyphrase": "invalid mr resource destroy",
          "type": "rootcause"
        },
        {
          "id": "rootcause:missing check",
          "keyphrase": "missing check",
          "type": "rootcause"
        },
        {
          "id": "impact:Oops",
          "keyphrase": "Oops",
          "type": "impact"
        },
        {
          "id": "impact:read access",
          "keyphrase": "read access",
          "type": "impact"
        },
        {
          "id": "product:Linux kernel",
          "keyphrase": "Linux kernel",
          "type": "product"
        }
      ],
      "400": [
        {
          "id": "rootcause:invalid mr resource destroy",
          "keyphrase": "invalid mr resource destroy",
          "type": "rootcause"
        },
        {
          "id": "impact:Oops",
          "keyphrase": "Oops",
          "type": "impact"
        },
        {
          "id": "impact:read access",
          "keyphrase": "read access",
          "type": "impact"
        },
        {
          "id": "product:Linux kernel",
          "keyphrase": "Linux kernel",
          "type": "product"
        }
      ],
      "667": [
        {
          "id": "rootcause:invalid mr resource destroy",
          "keyphrase": "invalid mr resource destroy",
          "type": "rootcause"
        },
        {
          "id": "rootcause:missing check",
          "keyphrase": "missing check",
          "type": "rootcause"
        },
        {
          "id": "impact:Oops",
          "keyphrase": "Oops",
          "type": "impact"
        },
        {
          "id": "impact:read access",
          "keyphrase": "read access",
          "type": "impact"
        },
        {
          "id": "product:Linux kernel",
          "keyphrase": "Linux kernel",
          "type": "product"
        }
      ],
      "362": [
        {
          "id": "rootcause:invalid mr resource destroy",
          "keyphrase": "invalid mr resource destroy",
          "type": "rootcause"
        },
        {
          "id": "rootcause:missing check",
          "keyphrase": "missing check",
          "type": "rootcause"
        },
        {
          "id": "impact:Oops",
          "keyphrase": "Oops",
          "type": "impact"
        },
        {
          "id": "impact:read access",
          "keyphrase": "read access",
          "type": "impact"
        },
        {
          "id": "product:Linux kernel",
          "keyphrase": "Linux kernel",
          "type": "product"
        }
      ],
      "824": [
        {
          "id": "rootcause:invalid mr resource destroy",
          "keyphrase": "invalid mr resource destroy",
          "type": "rootcause"
        },
        {
          "id": "rootcause:missing check",
          "keyphrase": "missing check",
          "type": "rootcause"
        },
        {
          "id": "impact:Oops",
          "keyphrase": "Oops",
          "type": "impact"
        },
        {
          "id": "impact:read access",
          "keyphrase": "read access",
          "type": "impact"
        }
      ],
      "476": [
        {
          "id": "rootcause:missing check",
          "keyphrase": "missing check",
          "type": "rootcause"
        }
      ],
      "833": [
        {
          "id": "product:Linux kernel",
          "keyphrase": "Linux kernel",
          "type": "product"
        }
      ]
    },
    "relevant_cwes": [
      {
        "metadata": {
          "doc_id": "909",
          "name": "Missing Initialization of Resource",
          "source": "sparse",
          "original_content": "The product does not initialize a critical resource.",
          "keyphrase_sources": [
            {
              "id": "rootcause:invalid mr resource destroy",
              "keyphrase": "invalid mr resource destroy",
              "type": "rootcause"
            },
            {
              "id": "rootcause:missing check",
              "keyphrase": "missing check",
              "type": "rootcause"
            },
            {
              "id": "impact:Oops",
              "keyphrase": "Oops",
              "type": "impact"
            },
            {
              "id": "impact:read access",
              "keyphrase": "read access",
              "type": "impact"
            },
            {
              "id": "product:Linux kernel",
              "keyphrase": "Linux kernel",
              "type": "product"
            }
          ]
        },
        "similarity": 461.289362302365
      },
      {
        "metadata": {
          "doc_id": "400",
          "name": "Uncontrolled Resource Consumption",
          "source": "sparse",
          "original_content": "The product does not properly control the allocation and maintenance of a limited resource, thereby enabling an actor to influence the amount of resources consumed, eventually leading to the exhaustion of available resources.",
          "keyphrase_sources": [
            {
              "id": "rootcause:invalid mr resource destroy",
              "keyphrase": "invalid mr resource destroy",
              "type": "rootcause"
            },
            {
              "id": "impact:Oops",
              "keyphrase": "Oops",
              "type": "impact"
            },
            {
              "id": "impact:read access",
              "keyphrase": "read access",
              "type": "impact"
            },
            {
              "id": "product:Linux kernel",
              "keyphrase": "Linux kernel",
              "type": "product"
            }
          ]
        },
        "similarity": 431.04278654628786
      },
      {
        "metadata": {
          "doc_id": "667",
          "name": "Improper Locking",
          "source": "sparse",
          "original_content": "The product does not properly acquire or release a lock on a resource, leading to unexpected resource state changes and behaviors.",
          "keyphrase_sources": [
            {
              "id": "rootcause:invalid mr resource destroy",
              "keyphrase": "invalid mr resource destroy",
              "type": "rootcause"
            },
            {
              "id": "rootcause:missing check",
              "keyphrase": "missing check",
              "type": "rootcause"
            },
            {
              "id": "impact:Oops",
              "keyphrase": "Oops",
              "type": "impact"
            },
            {
              "id": "impact:read access",
              "keyphrase": "read access",
              "type": "impact"
            },
            {
              "id": "product:Linux kernel",
              "keyphrase": "Linux kernel",
              "type": "product"
            }
          ]
        },
        "similarity": 414.6972777444188
      },
      {
        "metadata": {
          "doc_id": "362",
          "name": "Concurrent Execution using Shared Resource with Improper Synchronization ('Race Condition')",
          "source": "sparse",
          "original_content": "The product contains a concurrent code sequence that requires temporary, exclusive access to a shared resource, but a timing window exists in which the shared resource can be modified by another code sequence operating concurrently.",
          "keyphrase_sources": [
            {
              "id": "rootcause:invalid mr resource destroy",
              "keyphrase": "invalid mr resource destroy",
              "type": "rootcause"
            },
            {
              "id": "rootcause:missing check",
              "keyphrase": "missing check",
              "type": "rootcause"
            },
            {
              "id": "impact:Oops",
              "keyphrase": "Oops",
              "type": "impact"
            },
            {
              "id": "impact:read access",
              "keyphrase": "read access",
              "type": "impact"
            },
            {
              "id": "product:Linux kernel",
              "keyphrase": "Linux kernel",
              "type": "product"
            }
          ]
        },
        "similarity": 411.79872987498044
      },
      {
        "metadata": {
          "doc_id": "824",
          "name": "Access of Uninitialized Pointer",
          "source": "sparse",
          "original_content": "The product accesses or uses a pointer that has not been initialized.",
          "keyphrase_sources": [
            {
              "id": "rootcause:invalid mr resource destroy",
              "keyphrase": "invalid mr resource destroy",
              "type": "rootcause"
            },
            {
              "id": "rootcause:missing check",
              "keyphrase": "missing check",
              "type": "rootcause"
            },
            {
              "id": "impact:Oops",
              "keyphrase": "Oops",
              "type": "impact"
            },
            {
              "id": "impact:read access",
              "keyphrase": "read access",
              "type": "impact"
            }
          ]
        },
        "similarity": 409.8240959911765
      },
      {
        "metadata": {
          "doc_id": "476",
          "name": "NULL Pointer Dereference",
          "source": "sparse",
          "original_content": "The product dereferences a pointer that it expects to be valid but is NULL.",
          "keyphrase_sources": [
            {
              "id": "rootcause:missing check",
              "keyphrase": "missing check",
              "type": "rootcause"
            }
          ]
        },
        "similarity": 405.0373028281116
      },
      {
        "metadata": {
          "doc_id": "833",
          "name": "Deadlock",
          "source": "sparse",
          "original_content": "The product contains multiple threads or executable segments that are waiting for each other to release a necessary lock, resulting in deadlock.",
          "keyphrase_sources": [
            {
              "id": "product:Linux kernel",
              "keyphrase": "Linux kernel",
              "type": "product"
            }
          ]
        },
        "similarity": 139.8157714412309
      }
    ],
    "enhanced_query": "# Vulnerability Description\n\n    In the Linux kernel, the following vulnerability has been resolved vdpa/mlx5 Fix **invalid mr resource destroy** Certain error paths from mlx5_vdpa_dev_add() can end up releasing mr resources which never got initialized in the first place. This patch adds the **missing check** in mlx5_vdpa_destroy_mr_resources() to block releasing non-initialized mr resources. Reference trace mlx5_core 00000800.2 mlx5_vdpa_dev_add3274(pid 2700) warning No mac address provisioned? BUG kernel NULL pointer dereference, address 0000000000000000 #PF supervisor read access in kernel mode #PF error_code(0x0000) - not-present page PGD 140216067 P4D 0 Oops 0000 [#1] PREEMPT SMP NOPTI CPU 8 PID 2700 Comm vdpa Kdump loaded Not tainted 5.14.0-496.el9.x86_64 #1 Hardware name QEMU Standard PC (Q35 + ICH9, 2009), BIOS rel-1.13.0-0-gf21b5a4aeb02-prebuilt.qemu.org 04/01/2014 RIP 0010vhost_iotlb_del_range+0xf/0xe0 [vhost_iotlb] Code [...] RSP 0018ff1c823ac23077f0 EFLAGS 00010246 RAX ffffffffc1a21a60 RBX ffffffff899567a0 RCX 0000000000000000 RDX ffffffffffffffff RSI 0000000000000000 RDI 0000000000000000 RBP ff1bda1f7c21e800 R08 0000000000000000 R09 ff1c823ac2307670 R10 ff1c823ac2307668 R11 ffffffff8a9e7b68 R12 0000000000000000 R13 0000000000000000 R14 ff1bda1f43e341a0 R15 00000000ffffffea FS 00007f56eba7c740(0000) GSff1bda269f800000(0000) knlGS0000000000000000 CS 0010 DS 0000 ES 0000 CR0 0000000080050033 CR2 0000000000000000 CR\n\n    # Keyphrase-Specific CWE Analysis\n    This vulnerability contains multiple keyphrases that may map to different CWEs. \n    Please analyze each keyphrase separately and determine the most appropriate CWE(s) for each.\n\n    ## ROOTCAUSE: 'invalid mr resource destroy'\n\nRelevant CWEs for this ROOTCAUSE:\n\n### 1. CWE-909: Missing Initialization of Resource (Score: 461.29)\n\nThe product does not initialize a critical resource....\n\n### 2. CWE-400: Uncontrolled Resource Consumption (Score: 431.04)\n\nThe product does not properly control the allocation and maintenance of a limited resource, thereby enabling an actor to influence the amount of resources consumed, eventually leading to the exhaustion of available resources....\n\n### 3. CWE-667: Improper Locking (Score: 414.70)\n\nThe product does not properly acquire or release a lock on a resource, leading to unexpected resource state changes and behaviors....\n\n### 4. CWE-362: Concurrent Execution using Shared Resource with Improper Synchronization ('Race Condition') (Score: 411.80)\n\nThe product contains a concurrent code sequence that requires temporary, exclusive access to a shared resource, but a timing window exists in which the shared resource can be modified by another code sequence operating concurrently....\n\n### 5. CWE-824: Access of Uninitialized Pointer (Score: 409.82)\n\nThe product accesses or uses a pointer that has not been initialized....\n\n## ROOTCAUSE: 'missing check'\n\nRelevant CWEs for this ROOTCAUSE:\n\n### 1. CWE-909: Missing Initialization of Resource (Score: 461.29)\n\nThe product does not initialize a critical resource....\n\n### 2. CWE-667: Improper Locking (Score: 414.70)\n\nThe product does not properly acquire or release a lock on a resource, leading to unexpected resource state changes and behaviors....\n\n### 3. CWE-362: Concurrent Execution using Shared Resource with Improper Synchronization ('Race Condition') (Score: 411.80)\n\nThe product contains a concurrent code sequence that requires temporary, exclusive access to a shared resource, but a timing window exists in which the shared resource can be modified by another code sequence operating concurrently....\n\n### 4. CWE-824: Access of Uninitialized Pointer (Score: 409.82)\n\nThe product accesses or uses a pointer that has not been initialized....\n\n### 5. CWE-476: NULL Pointer Dereference (Score: 405.04)\n\nThe product dereferences a pointer that it expects to be valid but is NULL....\n\n## IMPACT: 'Oops'\n\nRelevant CWEs for this IMPACT:\n\n### 1. CWE-909: Missing Initialization of Resource (Score: 461.29)\n\nThe product does not initialize a critical resource....\n\n### 2. CWE-400: Uncontrolled Resource Consumption (Score: 431.04)\n\nThe product does not properly control the allocation and maintenance of a limited resource, thereby enabling an actor to influence the amount of resources consumed, eventually leading to the exhaustion of available resources....\n\n### 3. CWE-667: Improper Locking (Score: 414.70)\n\nThe product does not properly acquire or release a lock on a resource, leading to unexpected resource state changes and behaviors....\n\n### 4. CWE-362: Concurrent Execution using Shared Resource with Improper Synchronization ('Race Condition') (Score: 411.80)\n\nThe product contains a concurrent code sequence that requires temporary, exclusive access to a shared resource, but a timing window exists in which the shared resource can be modified by another code sequence operating concurrently....\n\n### 5. CWE-824: Access of Uninitialized Pointer (Score: 409.82)\n\nThe product accesses or uses a pointer that has not been initialized....\n\n## IMPACT: 'read access'\n\nRelevant CWEs for this IMPACT:\n\n### 1. CWE-909: Missing Initialization of Resource (Score: 461.29)\n\nThe product does not initialize a critical resource....\n\n### 2. CWE-400: Uncontrolled Resource Consumption (Score: 431.04)\n\nThe product does not properly control the allocation and maintenance of a limited resource, thereby enabling an actor to influence the amount of resources consumed, eventually leading to the exhaustion of available resources....\n\n### 3. CWE-667: Improper Locking (Score: 414.70)\n\nThe product does not properly acquire or release a lock on a resource, leading to unexpected resource state changes and behaviors....\n\n### 4. CWE-362: Concurrent Execution using Shared Resource with Improper Synchronization ('Race Condition') (Score: 411.80)\n\nThe product contains a concurrent code sequence that requires temporary, exclusive access to a shared resource, but a timing window exists in which the shared resource can be modified by another code sequence operating concurrently....\n\n### 5. CWE-824: Access of Uninitialized Pointer (Score: 409.82)\n\nThe product accesses or uses a pointer that has not been initialized....\n\n## PRODUCT: 'Linux kernel'\n\nRelevant CWEs for this PRODUCT:\n\n### 1. CWE-909: Missing Initialization of Resource (Score: 461.29)\n\nThe product does not initialize a critical resource....\n\n### 2. CWE-400: Uncontrolled Resource Consumption (Score: 431.04)\n\nThe product does not properly control the allocation and maintenance of a limited resource, thereby enabling an actor to influence the amount of resources consumed, eventually leading to the exhaustion of available resources....\n\n### 3. CWE-667: Improper Locking (Score: 414.70)\n\nThe product does not properly acquire or release a lock on a resource, leading to unexpected resource state changes and behaviors....\n\n### 4. CWE-362: Concurrent Execution using Shared Resource with Improper Synchronization ('Race Condition') (Score: 411.80)\n\nThe product contains a concurrent code sequence that requires temporary, exclusive access to a shared resource, but a timing window exists in which the shared resource can be modified by another code sequence operating concurrently....\n\n### 5. CWE-833: Deadlock (Score: 139.82)\n\nThe product contains multiple threads or executable segments that are waiting for each other to release a necessary lock, resulting in deadlock....\n\n\n    # Analysis Instructions\n    1. For each keyphrase, identify the most appropriate CWE(s) that represent the weakness.\n    2. Consider how the different keyphrases might relate to each other in the vulnerability chain.\n    3. Provide a final determination of primary CWE(s) and any secondary CWEs.\n    4. Format your response using the standard analysis template.\n\n    Please analyze how these different weaknesses interact and provide a comprehensive CWE classification.\n    "
  },
  "retrieval_time": 1.536851167678833
}