{
  "cve_id": "CVE-2024-1609",
  "description": "In OPPOStore iOS App, theres a possible escalation of privilege due to **improper input validation**.",
  "key_phrases": {
    "rootcause": "improper input validation",
    "weakness": "",
    "impact": "escalation of privilege",
    "vector": "",
    "attacker": "",
    "product": "OPPOStore iOS App",
    "version": "",
    "component": ""
  },
  "reference_content": "The provided content is a webpage from OPPO's security center. It includes navigation links, login/signup options, and links to OPPO's official website, ColorOS, privacy policy, and social media. However, there is no information about any specific CVE, including CVE-2024-1609.\n\nTherefore, the response is:\n\nNOINFO",
  "similar_info": {
    "cwe_distribution": {
      "95": {
        "cwe_counts": {},
        "total_samples": 1,
        "distribution": [
          {
            "cwes": [],
            "frequency": 1,
            "proportion": 1.0
          }
        ]
      },
      "90": {
        "cwe_counts": {},
        "total_samples": 1,
        "distribution": [
          {
            "cwes": [],
            "frequency": 1,
            "proportion": 1.0
          }
        ]
      },
      "85": {
        "cwe_counts": {},
        "total_samples": 1,
        "distribution": [
          {
            "cwes": [],
            "frequency": 1,
            "proportion": 1.0
          }
        ]
      },
      "80": {
        "cwe_counts": {},
        "total_samples": 1,
        "distribution": [
          {
            "cwes": [],
            "frequency": 1,
            "proportion": 1.0
          }
        ]
      },
      "75": {
        "cwe_counts": {},
        "total_samples": 1,
        "distribution": [
          {
            "cwes": [],
            "frequency": 1,
            "proportion": 1.0
          }
        ]
      },
      "70": {
        "cwe_counts": {},
        "total_samples": 1,
        "distribution": [
          {
            "cwes": [],
            "frequency": 1,
            "proportion": 1.0
          }
        ]
      }
    },
    "cwe_consensus": "",
    "similarity_stats": {
      "thresholds": [
        95,
        90,
        85,
        80,
        75,
        70
      ],
      "total_samples_by_threshold": {
        "95": 1,
        "90": 1,
        "85": 1,
        "80": 1,
        "75": 1,
        "70": 1
      },
      "top_cwes_by_threshold": {
        "95": [],
        "90": [],
        "85": [],
        "80": [],
        "75": [],
        "70": []
      }
    },
    "raw_matches": [
      {
        "similarity": 95,
        "cwes": [],
        "total": 1,
        "frequency": 1,
        "proportion": 1.0
      },
      {
        "similarity": 90,
        "cwes": [],
        "total": 1,
        "frequency": 1,
        "proportion": 1.0
      },
      {
        "similarity": 85,
        "cwes": [],
        "total": 1,
        "frequency": 1,
        "proportion": 1.0
      },
      {
        "similarity": 80,
        "cwes": [],
        "total": 1,
        "frequency": 1,
        "proportion": 1.0
      },
      {
        "similarity": 75,
        "cwes": [],
        "total": 1,
        "frequency": 1,
        "proportion": 1.0
      },
      {
        "similarity": 70,
        "cwes": [],
        "total": 1,
        "frequency": 1,
        "proportion": 1.0
      }
    ]
  },
  "similarity_summary": {
    "consensus_cwe": "",
    "top_cwes": [],
    "confidence_levels": {
      "high": [],
      "medium": [],
      "low": []
    },
    "total_samples": 6
  },
  "analysis": "# Summary\n| CWE ID | CWE Name | Confidence | CWE Abstraction Level | CWE Vulnerability Mapping Label | CWE-Vulnerability Mapping Notes |\n|---|---|---|---|---|---|\n| CWE-20 | Improper Input Validation | 0.9 | Class | Primary CWE | Discouraged: High-level, but best fit based on available information. |\n| CWE-269 | Improper Privilege Management | 0.5 | Class | Secondary Candidate | Discouraged: Considered, but lack of specifics makes CWE-20 more appropriate |\n| CWE-862 | Missing Authorization | 0.3 | Class | Secondary Candidate | Allowed-with-Review: Considered but there is no evidence authorization is missing |\n\n## Evidence and Confidence\n\n*   **Confidence Score:** 0.9\n*   **Evidence Strength:** MEDIUM\n\n## Relationship Analysis\nThe primary relationship considered was the parent-child relationship between CWE-20 (Improper Input Validation) and its potential children. However, the description lacks the specificity to pinpoint a more precise variant. CWE-269 and CWE-862 were considered due to the \"privilege escalation\" impact, but the root cause points directly to input validation.\n\n```mermaid\ngraph TD\n    cwe20[\"CWE-20: Improper Input Validation\"]\n    cwe269[\"CWE-269: Improper Privilege Management\"]\n    cwe862[\"CWE-862: Missing Authorization\"]\n    \n    cwe269 -- Considered --> cwe20\n    cwe862 -- Considered --> cwe20\n    \n    classDef primary fill:#f96,stroke:#333,stroke-width:2px\n    classDef secondary fill:#69f,stroke:#333\n    classDef tertiary fill:#9e9,stroke:#333\n    class cwe20 primary\n    class cwe269,cwe862 secondary\n```\n\n## Vulnerability Chain\nThe vulnerability chain starts with **improper input validation** (CWE-20), which leads to a possible escalation of privilege. The description does not provide further details about how the **improper input validation** is exploited to achieve privilege escalation.\n\n## Summary of Analysis\nThe primary CWE assigned is CWE-20 (Improper Input Validation) because the vulnerability description explicitly states that the root cause is **improper input validation**. The evidence from the Vulnerability Description Key Phrases supports this: \"**rootcause:** **improper input validation**\".\n\nCWE-269 (Improper Privilege Management) was considered because the impact is \"escalation of privilege\". However, the CWE guidance explicitly states that CWE-269 is discouraged when a more specific root cause is known.\n\nCWE-862 (Missing Authorization) was considered but rejected because the description doesn't mention missing authorization.\n\nThe selected CWE (CWE-20) is at the Class level. While more specific Base or Variant level CWEs are generally preferred, the lack of detail in the vulnerability description makes it difficult to pinpoint the exact nature of the input validation issue. Therefore, the Class level is the most appropriate level of specificity based on the available evidence.\n\nRelevant CWE Information:\n\n# Enhanced Context (25 CWEs)\nThe following CWEs were identified as potentially relevant to this vulnerability:\n\n## CWE-20: Improper Input Validation\n**Abstraction Level**: Class\n**Similarity Score**: 0.121\n**Source**: sparse\n\n**Description**:\nThe product does not validate or incorrectly validates input that it receives. If the input is not validated, an attacker can supply crafted input that causes the system to perform an unintended operation.\n\n**Mapping Guidance**:\n- Usage: Discouraged\n- Rationale: This CWE entry is very high level and should only be used if a more specific input validation issue cannot be identified.\n\n\n\n## CWE-1284: Improper Validation of Specified Quantity in Input\n**Abstraction Level**: Base\n**Similarity Score**: 0.102\n**Source**: sparse\n\n**Description**:\nThe product receives an input value that specifies a quantity, but it does not validate or incorrectly validates that the quantity is within the expected bounds.\n\n**Mapping Guidance**:\n- Usage: Allowed\n- Rationale: This CWE entry is at the Base level of abstraction, which is a preferred level of abstraction for mapping to the root causes of vulnerabilities.\n\n\n\n## CWE-295: Improper Certificate Validation\n**Abstraction Level**: Base\n**Similarity Score**: 0.100\n**Source**: sparse\n\n**Description**:\nThe product does not validate, or improperly validates, the certificate presented to it by the remote end. This can occur in various ways, such as not checking the revocation status, not verifying the hostname, or using an expired certificate.\n\n**Mapping Guidance**:\n- Usage: Allowed\n- Rationale: This CWE entry is at the Base level of abstraction, which is a preferred level of abstraction for mapping to the root causes of vulnerabilities.\n\n\n\n## CWE-1285: Improper Validation of Specified Index, Position, or Offset in Input\n**Abstraction Level**: Base\n**Similarity Score**: 0.100\n**Source**: sparse\n\n**Description**:\nThe product receives an input value that is used as an index, position, or offset, but it does not validate or incorrectly validates that the input is within the expected bounds.\n\n**Mapping Guidance**:\n- Usage: Allowed\n- Rationale: This CWE entry is at the Base level of abstraction, which is a preferred level of abstraction for mapping to the root causes of vulnerabilities.\n\n\n\n## CWE-787: Out-of-bounds Write\n**Abstraction Level**: base\n**Similarity Score**: 0.099\n**Source**: sparse\n\n**Description**:\nCWE-787: Out-of-bounds Write\n\n**Mapping Guidance**:\n- Usage: Allowed\n- Rationale: This CWE entry is at the Base level of abstraction, which is a preferred level of abstraction for mapping to the root causes of vulnerabilities.\n\n**Relationships**:\n- CANFOLLOW -> CWE-825\n- CANFOLLOW -> CWE-824\n- CANFOLLOW -> CWE-823\n- CANFOLLOW -> CWE-822\n- PARENTOF -> CWE-124\n\n\n\n## CWE-367: Time-of-check Time-of-use (TOCTOU) Race Condition\n**Abstraction Level**: Base\n**Similarity Score**: 0.099\n**Source**: sparse\n\n**Description**:\nThe product checks the state of a resource before using that resource, but the resource's state can change between the check and the use in a way that invalidates the results of the check. This can cause the product to perform invalid actions when the resource is in an unexpected state.\n\n**Mapping Guidance**:\n- Usage: Allowed\n- Rationale: This CWE entry is at the Base level of abstraction, which is a preferred level of abstraction for mapping to the root causes of vulnerabilities.\n\n\n\n## CWE-665: Improper Initialization\n**Abstraction Level**: Class\n**Similarity Score**: 0.095\n**Source**: sparse\n\n**Description**:\nThe product does not properly initialize a resource.\n\n**Mapping Guidance**:\n- Usage: Discouraged\n- Rationale: This CWE entry is very high level and should only be used if a more specific initialization issue cannot be identified.\n\n\n\n## CWE-862: Missing Authorization\n**Abstraction Level**: Class\n**Similarity Score**: 0.093\n**Source**: sparse\n\n**Description**:\nThe product does not perform any authorization checks when an actor attempts to access a resource or perform an action.\n\n**Mapping Guidance**:\n- Usage: Allowed-with-Review\n- Rationale: This CWE entry is a Class and might have Base-level children that would be more appropriate\n\n\n\n## CWE-939: Improper Authorization in Handler for Custom URL Scheme\n**Abstraction Level**: base\n**Similarity Score**: 0.531\n**Source**: dense\n\n**Description**:\nCWE-939: Improper Authorization in Handler for Custom URL Scheme\n\n**Mapping Guidance**:\n- Usage: Allowed\n- Rationale: This CWE entry is at the Base level of abstraction, which is a preferred level of abstraction for mapping to the root causes of vulnerabilities.\n\n**Relationships**:\n- CHILDOF -> CWE-862\n- PARENTOF -> CWE-939\n\n\n\n## CWE-781: Improper Address Validation in IOCTL with METHOD_NEITHER I/O Control Code\n**Abstraction Level**: variant\n**Similarity Score**: 0.002\n**Source**: graph\n\n**Description**:\nCWE-781: Improper Address Validation in IOCTL with METHOD_NEITHER I/O Control Code\n\n**Mapping Guidance**:\n- Usage: Allowed\n- Rationale: This CWE entry is at the Variant level of abstraction, which is a preferred level of abstraction for mapping to the root causes of vulnerabilities.\n\n**Relationships**:\n- CANFOLLOW -> CWE-782\n- CANPRECEDE -> CWE-822\n- CHILDOF -> CWE-1285\n- CANFOLLOW -> CWE-781\n- CANPRECEDE -> CWE-781",
  "analysis_with_relationships": "# Summary\n| CWE ID | CWE Name | Confidence | CWE Abstraction Level | CWE Vulnerability Mapping Label | CWE-Vulnerability Mapping Notes |\n|---|---|---|---|---|---|\n| CWE-20 | Improper Input Validation | 0.9 | Class | Primary CWE | Discouraged: High-level, but best fit based on available information. |\n| CWE-269 | Improper Privilege Management | 0.5 | Class | Secondary Candidate | Discouraged: Considered, but lack of specifics makes CWE-20 more appropriate |\n| CWE-862 | Missing Authorization | 0.3 | Class | Secondary Candidate | Allowed-with-Review: Considered but there is no evidence authorization is missing |\n\n## Evidence and Confidence\n\n*   **Confidence Score:** 0.9\n*   **Evidence Strength:** MEDIUM\n\n## Relationship Analysis\nThe primary relationship considered was the parent-child relationship between CWE-20 (Improper Input Validation) and its potential children. However, the description lacks the specificity to pinpoint a more precise variant. CWE-269 and CWE-862 were considered due to the \"privilege escalation\" impact, but the root cause points directly to input validation.\n\n```mermaid\ngraph TD\n    cwe20[\"CWE-20: Improper Input Validation\"]\n    cwe269[\"CWE-269: Improper Privilege Management\"]\n    cwe862[\"CWE-862: Missing Authorization\"]\n    \n    cwe269 -- Considered --> cwe20\n    cwe862 -- Considered --> cwe20\n    \n    classDef primary fill:#f96,stroke:#333,stroke-width:2px\n    classDef secondary fill:#69f,stroke:#333\n    classDef tertiary fill:#9e9,stroke:#333\n    class cwe20 primary\n    class cwe269,cwe862 secondary\n```\n\n## Vulnerability Chain\nThe vulnerability chain starts with **improper input validation** (CWE-20), which leads to a possible escalation of privilege. The description does not provide further details about how the **improper input validation** is exploited to achieve privilege escalation.\n\n## Summary of Analysis\nThe primary CWE assigned is CWE-20 (Improper Input Validation) because the vulnerability description explicitly states that the root cause is **improper input validation**. The evidence from the Vulnerability Description Key Phrases supports this: \"**rootcause:** **improper input validation**\".\n\nCWE-269 (Improper Privilege Management) was considered because the impact is \"escalation of privilege\". However, the CWE guidance explicitly states that CWE-269 is discouraged when a more specific root cause is known.\n\nCWE-862 (Missing Authorization) was considered but rejected because the description doesn't mention missing authorization.\n\nThe selected CWE (CWE-20) is at the Class level. While more specific Base or Variant level CWEs are generally preferred, the lack of detail in the vulnerability description makes it difficult to pinpoint the exact nature of the input validation issue. Therefore, the Class level is the most appropriate level of specificity based on the available evidence.\n\nRelevant CWE Information:\n\n# Enhanced Context (25 CWEs)\nThe following CWEs were identified as potentially relevant to this vulnerability:\n\n## CWE-20: Improper Input Validation\n**Abstraction Level**: Class\n**Similarity Score**: 0.121\n**Source**: sparse\n\n**Description**:\nThe product does not validate or incorrectly validates input that it receives. If the input is not validated, an attacker can supply crafted input that causes the system to perform an unintended operation.\n\n**Mapping Guidance**:\n- Usage: Discouraged\n- Rationale: This CWE entry is very high level and should only be used if a more specific input validation issue cannot be identified.\n\n\n\n## CWE-1284: Improper Validation of Specified Quantity in Input\n**Abstraction Level**: Base\n**Similarity Score**: 0.102\n**Source**: sparse\n\n**Description**:\nThe product receives an input value that specifies a quantity, but it does not validate or incorrectly validates that the quantity is within the expected bounds.\n\n**Mapping Guidance**:\n- Usage: Allowed\n- Rationale: This CWE entry is at the Base level of abstraction, which is a preferred level of abstraction for mapping to the root causes of vulnerabilities.\n\n\n\n## CWE-295: Improper Certificate Validation\n**Abstraction Level**: Base\n**Similarity Score**: 0.100\n**Source**: sparse\n\n**Description**:\nThe product does not validate, or improperly validates, the certificate presented to it by the remote end. This can occur in various ways, such as not checking the revocation status, not verifying the hostname, or using an expired certificate.\n\n**Mapping Guidance**:\n- Usage: Allowed\n- Rationale: This CWE entry is at the Base level of abstraction, which is a preferred level of abstraction for mapping to the root causes of vulnerabilities.\n\n\n\n## CWE-1285: Improper Validation of Specified Index, Position, or Offset in Input\n**Abstraction Level**: Base\n**Similarity Score**: 0.100\n**Source**: sparse\n\n**Description**:\nThe product receives an input value that is used as an index, position, or offset, but it does not validate or incorrectly validates that the input is within the expected bounds.\n\n**Mapping Guidance**:\n- Usage: Allowed\n- Rationale: This CWE entry is at the Base level of abstraction, which is a preferred level of abstraction for mapping to the root causes of vulnerabilities.\n\n\n\n## CWE-787: Out-of-bounds Write\n**Abstraction Level**: base\n**Similarity Score**: 0.099\n**Source**: sparse\n\n**Description**:\nCWE-787: Out-of-bounds Write\n\n**Mapping Guidance**:\n- Usage: Allowed\n- Rationale: This CWE entry is at the Base level of abstraction, which is a preferred level of abstraction for mapping to the root causes of vulnerabilities.\n\n**Relationships**:\n- CANFOLLOW -> CWE-825\n- CANFOLLOW -> CWE-824\n- CANFOLLOW -> CWE-823\n- CANFOLLOW -> CWE-822\n- PARENTOF -> CWE-124\n\n\n\n## CWE-367: Time-of-check Time-of-use (TOCTOU) Race Condition\n**Abstraction Level**: Base\n**Similarity Score**: 0.099\n**Source**: sparse\n\n**Description**:\nThe product checks the state of a resource before using that resource, but the resource's state can change between the check and the use in a way that invalidates the results of the check. This can cause the product to perform invalid actions when the resource is in an unexpected state.\n\n**Mapping Guidance**:\n- Usage: Allowed\n- Rationale: This CWE entry is at the Base level of abstraction, which is a preferred level of abstraction for mapping to the root causes of vulnerabilities.\n\n\n\n## CWE-665: Improper Initialization\n**Abstraction Level**: Class\n**Similarity Score**: 0.095\n**Source**: sparse\n\n**Description**:\nThe product does not properly initialize a resource.\n\n**Mapping Guidance**:\n- Usage: Discouraged\n- Rationale: This CWE entry is very high level and should only be used if a more specific initialization issue cannot be identified.\n\n\n\n## CWE-862: Missing Authorization\n**Abstraction Level**: Class\n**Similarity Score**: 0.093\n**Source**: sparse\n\n**Description**:\nThe product does not perform any authorization checks when an actor attempts to access a resource or perform an action.\n\n**Mapping Guidance**:\n- Usage: Allowed-with-Review\n- Rationale: This CWE entry is a Class and might have Base-level children that would be more appropriate\n\n\n\n## CWE-939: Improper Authorization in Handler for Custom URL Scheme\n**Abstraction Level**: base\n**Similarity Score**: 0.531\n**Source**: dense\n\n**Description**:\nCWE-939: Improper Authorization in Handler for Custom URL Scheme\n\n**Mapping Guidance**:\n- Usage: Allowed\n- Rationale: This CWE entry is at the Base level of abstraction, which is a preferred level of abstraction for mapping to the root causes of vulnerabilities.\n\n**Relationships**:\n- CHILDOF -> CWE-862\n- PARENTOF -> CWE-939\n\n\n\n## CWE-781: Improper Address Validation in IOCTL with METHOD_NEITHER I/O Control Code\n**Abstraction Level**: variant\n**Similarity Score**: 0.002\n**Source**: graph\n\n**Description**:\nCWE-781: Improper Address Validation in IOCTL with METHOD_NEITHER I/O Control Code\n\n**Mapping Guidance**:\n- Usage: Allowed\n- Rationale: This CWE entry is at the Variant level of abstraction, which is a preferred level of abstraction for mapping to the root causes of vulnerabilities.\n\n**Relationships**:\n- CANFOLLOW -> CWE-782\n- CANPRECEDE -> CWE-822\n- CHILDOF -> CWE-1285\n- CANFOLLOW -> CWE-781\n- CANPRECEDE -> CWE-781\n\n\n## CWE Relationship Analysis\n\nCurrent CWEs represent these abstraction levels: .\n\n\n### Vulnerability Chain Analysis\n\n**Chain starting from CWE-1284:**\n- 1284 (Improper Validation of Specified Quantity in Input) - ROOT\n\n\n**Chain starting from CWE-823:**\n- 823 (Use of Out-of-range Pointer Offset) - ROOT\n\n\n\n### CWE Relationship Diagram\n\n```mermaid\ngraph TD\n    classDef primary fill:#f96,stroke:#333,stroke-width:2px\n    classDef secondary fill:#69f,stroke:#333\n    classDef tertiary fill:#9e9,stroke:#333\n```",
  "criticism": "",
  "resolution": "",
  "relevant_cwes": [
    {
      "metadata": {
        "doc_id": "20",
        "name": "Improper Input Validation",
        "source": "sparse"
      },
      "similarity": 121.28101924293524
    },
    {
      "metadata": {
        "doc_id": "1284",
        "name": "Improper Validation of Specified Quantity in Input",
        "source": "sparse"
      },
      "similarity": 101.6478008876665
    },
    {
      "metadata": {
        "doc_id": "295",
        "name": "Improper Certificate Validation",
        "source": "sparse"
      },
      "similarity": 100.21991929490528
    },
    {
      "metadata": {
        "doc_id": "1285",
        "name": "Improper Validation of Specified Index, Position, or Offset in Input",
        "source": "sparse"
      },
      "similarity": 99.68847128448684
    },
    {
      "metadata": {
        "doc_id": "787",
        "name": "Out-of-bounds Write",
        "source": "sparse"
      },
      "similarity": 99.36636459755081
    },
    {
      "metadata": {
        "doc_id": "367",
        "name": "Time-of-check Time-of-use (TOCTOU) Race Condition",
        "source": "sparse"
      },
      "similarity": 99.35483140311442
    },
    {
      "metadata": {
        "doc_id": "665",
        "name": "Improper Initialization",
        "source": "sparse"
      },
      "similarity": 95.43086211163312
    },
    {
      "metadata": {
        "doc_id": "862",
        "name": "Missing Authorization",
        "source": "sparse"
      },
      "similarity": 92.97805257166502
    },
    {
      "metadata": {
        "doc_id": "939",
        "name": "Improper Authorization in Handler for Custom URL Scheme",
        "type": "Base",
        "original_content": "The product uses a handler for a custom URL scheme, but it does not properly restrict which actors can invoke the handler using the scheme.",
        "source": "dense",
        "mapping_notes": {
          "usage": "Allowed",
          "rationale": "This CWE entry is at the Base level of abstraction, which is a preferred level of abstraction for mapping to the root causes of vulnerabilities.",
          "comments": "Carefully read both the name and description to ensure that this mapping is an appropriate fit. Do not try to 'force' a mapping to a lower-level Base/Variant simply to comply with this preferred level of abstraction.",
          "reasons": [
            "Acceptable-Use"
          ]
        },
        "score_info": {
          "retrievers": [
            "dense"
          ],
          "retriever_count": 1,
          "normalized_scores": {
            "dense": 0.5305041680359244
          }
        }
      },
      "similarity": 0.5305041680359244
    },
    {
      "doc_id": "781",
      "text": "CWE-781: Improper Address Validation in IOCTL with METHOD_NEITHER I/O Control Code",
      "score": 2.2704,
      "metadata": {
        "doc_id": "781",
        "name": "Improper Address Validation in IOCTL with METHOD_NEITHER I/O Control Code",
        "type": "variant",
        "original_content": "CWE-781: Improper Address Validation in IOCTL with METHOD_NEITHER I/O Control Code",
        "relationships": [
          {
            "source_id": "781",
            "target_id": "782",
            "label": "CANFOLLOW",
            "properties": {
              "view_id": "1000"
            }
          },
          {
            "source_id": "781",
            "target_id": "822",
            "label": "CANPRECEDE",
            "properties": {
              "view_id": "1000"
            }
          },
          {
            "source_id": "781",
            "target_id": "1285",
            "label": "CHILDOF",
            "properties": {
              "ordinal": "Primary",
              "view_id": "1000"
            }
          },
          {
            "source_id": "822",
            "target_id": "781",
            "label": "CANFOLLOW",
            "properties": {
              "view_id": "1000"
            }
          },
          {
            "source_id": "782",
            "target_id": "781",
            "label": "CANPRECEDE",
            "properties": {
              "view_id": "1000"
            }
          },
          {
            "source_id": "1285",
            "target_id": "781",
            "label": "PARENTOF",
            "properties": {
              "ordinal": "Primary",
              "view_id": "1000"
            }
          }
        ],
        "score_components": {
          "relationship_chain": 0.8,
          "abstraction_path": 0.76,
          "sequence_path": 0.8
        },
        "abstraction_factor": 1.2,
        "graph_path_info": {
          "path_types": [
            "relationship_chain",
            "abstraction_path_down",
            "vulnerability_sequence_forward",
            "vulnerability_sequence_backward"
          ],
          "best_paths": {
            "relationship_chain": {
              "path": [
                [
                  "787",
                  "822",
                  "CANFOLLOW"
                ],
                [
                  "822",
                  "781",
                  "CANFOLLOW"
                ]
              ],
              "score": 0.8,
              "type": "relationship_chain",
              "source": "787"
            },
            "abstraction_path_down": {
              "path": [
                [
                  "1285",
                  "781",
                  "PARENTOF"
                ]
              ],
              "score": 0.76,
              "type": "abstraction_path_down",
              "source": "1285"
            },
            "vulnerability_sequence_forward": {
              "path": [
                [
                  "787",
                  "822",
                  "CANFOLLOW"
                ],
                [
                  "822",
                  "781",
                  "CANFOLLOW"
                ]
              ],
              "score": 0.7200000000000001,
              "type": "vulnerability_sequence_forward",
              "source": "787"
            },
            "vulnerability_sequence_backward": {
              "path": [
                [
                  "822",
                  "787",
                  "CANPRECEDE"
                ],
                [
                  "781",
                  "822",
                  "CANPRECEDE"
                ]
              ],
              "score": 0.8,
              "type": "vulnerability_sequence_backward",
              "source": "787"
            }
          }
        },
        "abstraction_level": "variant",
        "position": "before",
        "sources": [
          "graph"
        ],
        "source": "graph",
        "mapping_notes": {
          "usage": "Allowed",
          "rationale": "This CWE entry is at the Variant level of abstraction, which is a preferred level of abstraction for mapping to the root causes of vulnerabilities.",
          "comments": "Carefully read both the name and description to ensure that this mapping is an appropriate fit. Do not try to 'force' a mapping to a lower-level Base/Variant simply to comply with this preferred level of abstraction.",
          "reasons": [
            "Acceptable-Use"
          ]
        },
        "score_info": {
          "retrievers": [
            "graph"
          ],
          "retriever_count": 1,
          "normalized_scores": {
            "graph": 2.2704
          }
        }
      },
      "similarity": 2.2704
    }
  ],
  "identified_cwes": {
    "analyzer": [
      "CWE-1284",
      "CWE-823",
      "CWE-939",
      "CWE-862",
      "CWE-787",
      "CWE-1285",
      "CWE-124",
      "CWE-825",
      "CWE-782",
      "CWE-269",
      "CWE-781",
      "CWE-822",
      "CWE-20",
      "CWE-824",
      "CWE-367",
      "CWE-295",
      "CWE-665"
    ],
    "critic_additional": []
  },
  "keyphrase_cwe_mapping": {}
}