{
  "vulnerability_info": "VulnerabilityInfo(cve_id='CVE-2024-10934', description='In OpenBSD 7.5 before errata 008 and OpenBSD 7.4 before errata 021, avoid possible mbuf **double free** in NFS client and server implementation, do not **use uninitialized variable** in error handling of NFS server.', key_phrases={'rootcause': '', 'weakness': ['double free', 'use uninitialized variable'], 'impact': '', 'vector': '', 'attacker': '', 'product': 'OpenBSD', 'version': ['7.5 before errata 008', '7.4 before errata 021'], 'component': 'NFS client and server implementation'}, reference_content='The provided content relates to CVE-2024-10934.\\n\\n**Root cause of vulnerability:**\\nThe vulnerability stems from a potential double free of an mbuf (memory buffer) in the Network File System (NFS) client and server implementation within OpenBSD. Specifically, the `info.nmi_mrep` member could be freed multiple times under specific error conditions. Additionally, an uninitialized variable was used in the error handling of the NFS server.\\n\\n**Weaknesses/vulnerabilities present:**\\n- **Double Free:** The primary weakness is a double free vulnerability, which occurs when the same memory is released multiple times. This can lead to memory corruption, crashes, and potentially arbitrary code execution.\\n- **Use of Uninitialized Variable:** The use of an uninitialized variable in error handling could lead to undefined behavior and potentially further vulnerabilities.\\n\\n**Impact of exploitation:**\\n- **Memory Corruption:** A successful exploit could lead to memory corruption due to the double free.\\n- **Denial of Service (DoS):** The double free could result in a system crash, leading to denial of service.\\n- **Potential Arbitrary Code Execution:** In some scenarios, memory corruption vulnerabilities can be chained to achieve arbitrary code execution.\\n\\n**Attack vectors:**\\nThe attack vectors involve sending specially crafted NFS requests to either the client or the server. The specific circumstances that trigger the double free likely involve specific error conditions.\\n\\n**Required attacker capabilities/position:**\\n- **Network Access:** The attacker would need to have the ability to send NFS requests to a vulnerable OpenBSD system.\\n- **Knowledge of NFS Protocol:** The attacker would need a good understanding of the NFS protocol to craft the malicious requests.', similar_info={'cwe_distribution': {}, 'cwe_consensus': '', 'similarity_stats': {'thresholds': [], 'total_samples_by_threshold': {}, 'top_cwes_by_threshold': {}}}, similarity_summary=SimilarityInsight(consensus_cwe='', top_cwes=[], confidence_levels={}, total_samples=0), analysis='', analysis_with_relationships='', criticism='', resolution='', relevant_cwes=[{'metadata': {'doc_id': '415', 'name': 'Double Free', 'source': 'sparse', 'original_content': 'The product calls free() twice on the same memory address, potentially leading to modification of unexpected memory locations.', 'keyphrase_sources': [{'id': 'weakness:double free', 'keyphrase': 'double free', 'type': 'weakness'}, {'id': 'product:OpenBSD', 'keyphrase': 'OpenBSD', 'type': 'product'}, {'id': 'version:7.5 before errata 008', 'keyphrase': '7.5 before errata 008', 'type': 'version'}, {'id': 'version:7.4 before errata 021', 'keyphrase': '7.4 before errata 021', 'type': 'version'}]}, 'similarity': np.float64(217.4736049617001)}, {'metadata': {'doc_id': '665', 'name': 'Improper Initialization', 'source': 'sparse', 'original_content': 'The product does not initialize or incorrectly initializes a resource, which might leave the resource in an unexpected state when it is accessed or used.', 'keyphrase_sources': [{'id': 'weakness:double free', 'keyphrase': 'double free', 'type': 'weakness'}, {'id': 'weakness:use uninitialized variable', 'keyphrase': 'use uninitialized variable', 'type': 'weakness'}, {'id': 'product:OpenBSD', 'keyphrase': 'OpenBSD', 'type': 'product'}, {'id': 'version:7.5 before errata 008', 'keyphrase': '7.5 before errata 008', 'type': 'version'}, {'id': 'version:7.4 before errata 021', 'keyphrase': '7.4 before errata 021', 'type': 'version'}, {'id': 'component:NFS client and server implementation', 'keyphrase': 'NFS client and server implementation', 'type': 'component'}]}, 'similarity': np.float64(204.18437768125415)}, {'metadata': {'doc_id': '908', 'name': 'Use of Uninitialized Resource', 'source': 'sparse', 'original_content': 'The product uses or accesses a resource that has not been initialized.', 'keyphrase_sources': [{'id': 'weakness:double free', 'keyphrase': 'double free', 'type': 'weakness'}, {'id': 'weakness:use uninitialized variable', 'keyphrase': 'use uninitialized variable', 'type': 'weakness'}, {'id': 'product:OpenBSD', 'keyphrase': 'OpenBSD', 'type': 'product'}, {'id': 'version:7.5 before errata 008', 'keyphrase': '7.5 before errata 008', 'type': 'version'}, {'id': 'version:7.4 before errata 021', 'keyphrase': '7.4 before errata 021', 'type': 'version'}, {'id': 'component:NFS client and server implementation', 'keyphrase': 'NFS client and server implementation', 'type': 'component'}]}, 'similarity': np.float64(203.57233543559843)}, {'metadata': {'doc_id': '457', 'name': 'Use of Uninitialized Variable', 'source': 'sparse', 'original_content': 'The code uses a variable that has not been initialized, leading to unpredictable or unintended results.', 'keyphrase_sources': [{'id': 'weakness:use uninitialized variable', 'keyphrase': 'use uninitialized variable', 'type': 'weakness'}]}, 'similarity': np.float64(203.23912730867067)}, {'metadata': {'doc_id': '909', 'name': 'Missing Initialization of Resource', 'source': 'sparse', 'original_content': 'The product does not initialize a critical resource.', 'keyphrase_sources': [{'id': 'weakness:use uninitialized variable', 'keyphrase': 'use uninitialized variable', 'type': 'weakness'}, {'id': 'version:7.5 before errata 008', 'keyphrase': '7.5 before errata 008', 'type': 'version'}]}, 'similarity': np.float64(192.34265458458103)}, {'metadata': {'doc_id': '252', 'name': 'Unchecked Return Value', 'source': 'sparse', 'original_content': 'The product does not check the return value from a method or function, which can prevent it from detecting unexpected states and conditions.', 'keyphrase_sources': [{'id': 'weakness:use uninitialized variable', 'keyphrase': 'use uninitialized variable', 'type': 'weakness'}]}, 'similarity': np.float64(184.45093117545738)}, {'metadata': {'doc_id': '364', 'name': 'Signal Handler Race Condition', 'source': 'sparse', 'original_content': 'The product uses a signal handler that introduces a race condition.', 'keyphrase_sources': [{'id': 'weakness:double free', 'keyphrase': 'double free', 'type': 'weakness'}]}, 'similarity': np.float64(173.7381155487043)}, {'metadata': {'doc_id': '362', 'name': \"Concurrent Execution using Shared Resource with Improper Synchronization ('Race Condition')\", 'source': 'sparse', 'original_content': 'The product contains a concurrent code sequence that requires temporary, exclusive access to a shared resource, but a timing window exists in which the shared resource can be modified by another code sequence operating concurrently.', 'keyphrase_sources': [{'id': 'weakness:double free', 'keyphrase': 'double free', 'type': 'weakness'}]}, 'similarity': np.float64(169.45250087831576)}, {'metadata': {'doc_id': '325', 'name': 'Missing Cryptographic Step', 'source': 'sparse', 'original_content': 'The product does not implement a required step in a cryptographic algorithm, resulting in weaker encryption than advertised by the algorithm.', 'keyphrase_sources': [{'id': 'component:NFS client and server implementation', 'keyphrase': 'NFS client and server implementation', 'type': 'component'}]}, 'similarity': np.float64(63.90091292958128)}, {'metadata': {'doc_id': '195', 'name': 'Signed to Unsigned Conversion Error', 'source': 'sparse', 'original_content': 'The product uses a signed primitive and performs a cast to an unsigned primitive, which can produce an unexpected value if the value of the signed primitive can not be represented using an unsigned primitive.', 'keyphrase_sources': [{'id': 'product:OpenBSD', 'keyphrase': 'OpenBSD', 'type': 'product'}]}, 'similarity': np.float64(63.29021933594912)}, {'metadata': {'doc_id': '250', 'name': 'Execution with Unnecessary Privileges', 'source': 'sparse', 'original_content': 'The product performs an operation at a privilege level that is higher than the minimum level required, which creates new weaknesses or amplifies the consequences of other weaknesses.', 'keyphrase_sources': [{'id': 'version:7.5 before errata 008', 'keyphrase': '7.5 before errata 008', 'type': 'version'}]}, 'similarity': np.float64(59.07916317296568)}, {'metadata': {'doc_id': '755', 'name': 'Improper Handling of Exceptional Conditions', 'source': 'sparse', 'original_content': 'The product does not handle or incorrectly handles an exceptional condition.', 'keyphrase_sources': [{'id': 'version:7.4 before errata 021', 'keyphrase': '7.4 before errata 021', 'type': 'version'}, {'id': 'component:NFS client and server implementation', 'keyphrase': 'NFS client and server implementation', 'type': 'component'}]}, 'similarity': np.float64(57.36765219051006)}, {'metadata': {'doc_id': '1333', 'name': 'Inefficient Regular Expression Complexity', 'source': 'sparse', 'original_content': 'The product uses a regular expression with an inefficient, possibly exponential worst-case computational complexity that consumes excessive CPU cycles.', 'keyphrase_sources': [{'id': 'version:7.4 before errata 021', 'keyphrase': '7.4 before errata 021', 'type': 'version'}]}, 'similarity': np.float64(56.242372287230396)}, {'metadata': {'doc_id': '392', 'name': 'Missing Report of Error Condition', 'source': 'sparse', 'original_content': 'The product encounters an error but does not provide a status code or return value to indicate that an error has occurred.', 'keyphrase_sources': [{'id': 'product:OpenBSD', 'keyphrase': 'OpenBSD', 'type': 'product'}, {'id': 'component:NFS client and server implementation', 'keyphrase': 'NFS client and server implementation', 'type': 'component'}]}, 'similarity': np.float64(49.11575337222318)}], identified_cwes={'analyzer': [], 'critic_additional': []})",
  "retrieval_results": {
    "has_multiple_keyphrases": true,
    "keyphrase_cwe_sets": {
      "weakness:double free": {
        "keyphrase": "double free",
        "type": "weakness",
        "cwes": [
          {
            "metadata": {
              "doc_id": "415",
              "name": "Double Free",
              "source": "sparse",
              "original_content": "The product calls free() twice on the same memory address, potentially leading to modification of unexpected memory locations.",
              "keyphrase_sources": [
                {
                  "id": "weakness:double free",
                  "keyphrase": "double free",
                  "type": "weakness"
                },
                {
                  "id": "product:OpenBSD",
                  "keyphrase": "OpenBSD",
                  "type": "product"
                },
                {
                  "id": "version:7.5 before errata 008",
                  "keyphrase": "7.5 before errata 008",
                  "type": "version"
                },
                {
                  "id": "version:7.4 before errata 021",
                  "keyphrase": "7.4 before errata 021",
                  "type": "version"
                }
              ]
            },
            "similarity": 217.4736049617001
          },
          {
            "metadata": {
              "doc_id": "665",
              "name": "Improper Initialization",
              "source": "sparse",
              "original_content": "The product does not initialize or incorrectly initializes a resource, which might leave the resource in an unexpected state when it is accessed or used.",
              "keyphrase_sources": [
                {
                  "id": "weakness:double free",
                  "keyphrase": "double free",
                  "type": "weakness"
                },
                {
                  "id": "weakness:use uninitialized variable",
                  "keyphrase": "use uninitialized variable",
                  "type": "weakness"
                },
                {
                  "id": "product:OpenBSD",
                  "keyphrase": "OpenBSD",
                  "type": "product"
                },
                {
                  "id": "version:7.5 before errata 008",
                  "keyphrase": "7.5 before errata 008",
                  "type": "version"
                },
                {
                  "id": "version:7.4 before errata 021",
                  "keyphrase": "7.4 before errata 021",
                  "type": "version"
                },
                {
                  "id": "component:NFS client and server implementation",
                  "keyphrase": "NFS client and server implementation",
                  "type": "component"
                }
              ]
            },
            "similarity": 204.18437768125415
          },
          {
            "metadata": {
              "doc_id": "908",
              "name": "Use of Uninitialized Resource",
              "source": "sparse",
              "original_content": "The product uses or accesses a resource that has not been initialized.",
              "keyphrase_sources": [
                {
                  "id": "weakness:double free",
                  "keyphrase": "double free",
                  "type": "weakness"
                },
                {
                  "id": "weakness:use uninitialized variable",
                  "keyphrase": "use uninitialized variable",
                  "type": "weakness"
                },
                {
                  "id": "product:OpenBSD",
                  "keyphrase": "OpenBSD",
                  "type": "product"
                },
                {
                  "id": "version:7.5 before errata 008",
                  "keyphrase": "7.5 before errata 008",
                  "type": "version"
                },
                {
                  "id": "version:7.4 before errata 021",
                  "keyphrase": "7.4 before errata 021",
                  "type": "version"
                },
                {
                  "id": "component:NFS client and server implementation",
                  "keyphrase": "NFS client and server implementation",
                  "type": "component"
                }
              ]
            },
            "similarity": 203.57233543559843
          },
          {
            "metadata": {
              "doc_id": "364",
              "name": "Signal Handler Race Condition",
              "source": "sparse",
              "original_content": "The product uses a signal handler that introduces a race condition.",
              "keyphrase_sources": [
                {
                  "id": "weakness:double free",
                  "keyphrase": "double free",
                  "type": "weakness"
                }
              ]
            },
            "similarity": 173.7381155487043
          },
          {
            "metadata": {
              "doc_id": "362",
              "name": "Concurrent Execution using Shared Resource with Improper Synchronization ('Race Condition')",
              "source": "sparse",
              "original_content": "The product contains a concurrent code sequence that requires temporary, exclusive access to a shared resource, but a timing window exists in which the shared resource can be modified by another code sequence operating concurrently.",
              "keyphrase_sources": [
                {
                  "id": "weakness:double free",
                  "keyphrase": "double free",
                  "type": "weakness"
                }
              ]
            },
            "similarity": 169.45250087831576
          }
        ]
      },
      "weakness:use uninitialized variable": {
        "keyphrase": "use uninitialized variable",
        "type": "weakness",
        "cwes": [
          {
            "metadata": {
              "doc_id": "665",
              "name": "Improper Initialization",
              "source": "sparse",
              "original_content": "The product does not initialize or incorrectly initializes a resource, which might leave the resource in an unexpected state when it is accessed or used."
            },
            "similarity": 232.82339683438943
          },
          {
            "metadata": {
              "doc_id": "908",
              "name": "Use of Uninitialized Resource",
              "source": "sparse",
              "original_content": "The product uses or accesses a resource that has not been initialized."
            },
            "similarity": 226.73512365229212
          },
          {
            "metadata": {
              "doc_id": "457",
              "name": "Use of Uninitialized Variable",
              "source": "sparse",
              "original_content": "The code uses a variable that has not been initialized, leading to unpredictable or unintended results.",
              "keyphrase_sources": [
                {
                  "id": "weakness:use uninitialized variable",
                  "keyphrase": "use uninitialized variable",
                  "type": "weakness"
                }
              ]
            },
            "similarity": 203.23912730867067
          },
          {
            "metadata": {
              "doc_id": "909",
              "name": "Missing Initialization of Resource",
              "source": "sparse",
              "original_content": "The product does not initialize a critical resource.",
              "keyphrase_sources": [
                {
                  "id": "weakness:use uninitialized variable",
                  "keyphrase": "use uninitialized variable",
                  "type": "weakness"
                },
                {
                  "id": "version:7.5 before errata 008",
                  "keyphrase": "7.5 before errata 008",
                  "type": "version"
                }
              ]
            },
            "similarity": 192.34265458458103
          },
          {
            "metadata": {
              "doc_id": "252",
              "name": "Unchecked Return Value",
              "source": "sparse",
              "original_content": "The product does not check the return value from a method or function, which can prevent it from detecting unexpected states and conditions.",
              "keyphrase_sources": [
                {
                  "id": "weakness:use uninitialized variable",
                  "keyphrase": "use uninitialized variable",
                  "type": "weakness"
                }
              ]
            },
            "similarity": 184.45093117545738
          }
        ]
      },
      "product:OpenBSD": {
        "keyphrase": "OpenBSD",
        "type": "product",
        "cwes": [
          {
            "metadata": {
              "doc_id": "195",
              "name": "Signed to Unsigned Conversion Error",
              "source": "sparse",
              "original_content": "The product uses a signed primitive and performs a cast to an unsigned primitive, which can produce an unexpected value if the value of the signed primitive can not be represented using an unsigned primitive.",
              "keyphrase_sources": [
                {
                  "id": "product:OpenBSD",
                  "keyphrase": "OpenBSD",
                  "type": "product"
                }
              ]
            },
            "similarity": 63.29021933594912
          },
          {
            "metadata": {
              "doc_id": "665",
              "name": "Improper Initialization",
              "source": "sparse",
              "original_content": "The product does not initialize or incorrectly initializes a resource, which might leave the resource in an unexpected state when it is accessed or used."
            },
            "similarity": 59.86632483243677
          },
          {
            "metadata": {
              "doc_id": "908",
              "name": "Use of Uninitialized Resource",
              "source": "sparse",
              "original_content": "The product uses or accesses a resource that has not been initialized."
            },
            "similarity": 56.87941347276426
          },
          {
            "metadata": {
              "doc_id": "415",
              "name": "Double Free",
              "source": "sparse",
              "original_content": "The product calls free() twice on the same memory address, potentially leading to modification of unexpected memory locations."
            },
            "similarity": 50.76637485442802
          },
          {
            "metadata": {
              "doc_id": "392",
              "name": "Missing Report of Error Condition",
              "source": "sparse",
              "original_content": "The product encounters an error but does not provide a status code or return value to indicate that an error has occurred.",
              "keyphrase_sources": [
                {
                  "id": "product:OpenBSD",
                  "keyphrase": "OpenBSD",
                  "type": "product"
                },
                {
                  "id": "component:NFS client and server implementation",
                  "keyphrase": "NFS client and server implementation",
                  "type": "component"
                }
              ]
            },
            "similarity": 49.11575337222318
          }
        ]
      },
      "version:7.5 before errata 008": {
        "keyphrase": "7.5 before errata 008",
        "type": "version",
        "cwes": [
          {
            "metadata": {
              "doc_id": "665",
              "name": "Improper Initialization",
              "source": "sparse",
              "original_content": "The product does not initialize or incorrectly initializes a resource, which might leave the resource in an unexpected state when it is accessed or used."
            },
            "similarity": 69.22526947184394
          },
          {
            "metadata": {
              "doc_id": "908",
              "name": "Use of Uninitialized Resource",
              "source": "sparse",
              "original_content": "The product uses or accesses a resource that has not been initialized."
            },
            "similarity": 59.223862073273075
          },
          {
            "metadata": {
              "doc_id": "250",
              "name": "Execution with Unnecessary Privileges",
              "source": "sparse",
              "original_content": "The product performs an operation at a privilege level that is higher than the minimum level required, which creates new weaknesses or amplifies the consequences of other weaknesses.",
              "keyphrase_sources": [
                {
                  "id": "version:7.5 before errata 008",
                  "keyphrase": "7.5 before errata 008",
                  "type": "version"
                }
              ]
            },
            "similarity": 59.07916317296568
          },
          {
            "metadata": {
              "doc_id": "415",
              "name": "Double Free",
              "source": "sparse",
              "original_content": "The product calls free() twice on the same memory address, potentially leading to modification of unexpected memory locations."
            },
            "similarity": 57.37206671167132
          },
          {
            "metadata": {
              "doc_id": "909",
              "name": "Missing Initialization of Resource",
              "source": "sparse",
              "original_content": "The product does not initialize a critical resource."
            },
            "similarity": 56.75660274314351
          }
        ]
      },
      "version:7.4 before errata 021": {
        "keyphrase": "7.4 before errata 021",
        "type": "version",
        "cwes": [
          {
            "metadata": {
              "doc_id": "665",
              "name": "Improper Initialization",
              "source": "sparse",
              "original_content": "The product does not initialize or incorrectly initializes a resource, which might leave the resource in an unexpected state when it is accessed or used."
            },
            "similarity": 68.48197747729125
          },
          {
            "metadata": {
              "doc_id": "908",
              "name": "Use of Uninitialized Resource",
              "source": "sparse",
              "original_content": "The product uses or accesses a resource that has not been initialized."
            },
            "similarity": 61.46476175357564
          },
          {
            "metadata": {
              "doc_id": "755",
              "name": "Improper Handling of Exceptional Conditions",
              "source": "sparse",
              "original_content": "The product does not handle or incorrectly handles an exceptional condition.",
              "keyphrase_sources": [
                {
                  "id": "version:7.4 before errata 021",
                  "keyphrase": "7.4 before errata 021",
                  "type": "version"
                },
                {
                  "id": "component:NFS client and server implementation",
                  "keyphrase": "NFS client and server implementation",
                  "type": "component"
                }
              ]
            },
            "similarity": 57.36765219051006
          },
          {
            "metadata": {
              "doc_id": "415",
              "name": "Double Free",
              "source": "sparse",
              "original_content": "The product calls free() twice on the same memory address, potentially leading to modification of unexpected memory locations."
            },
            "similarity": 56.47233787514239
          },
          {
            "metadata": {
              "doc_id": "1333",
              "name": "Inefficient Regular Expression Complexity",
              "source": "sparse",
              "original_content": "The product uses a regular expression with an inefficient, possibly exponential worst-case computational complexity that consumes excessive CPU cycles.",
              "keyphrase_sources": [
                {
                  "id": "version:7.4 before errata 021",
                  "keyphrase": "7.4 before errata 021",
                  "type": "version"
                }
              ]
            },
            "similarity": 56.242372287230396
          }
        ]
      },
      "component:NFS client and server implementation": {
        "keyphrase": "NFS client and server implementation",
        "type": "component",
        "cwes": [
          {
            "metadata": {
              "doc_id": "908",
              "name": "Use of Uninitialized Resource",
              "source": "sparse",
              "original_content": "The product uses or accesses a resource that has not been initialized."
            },
            "similarity": 70.92360942447048
          },
          {
            "metadata": {
              "doc_id": "392",
              "name": "Missing Report of Error Condition",
              "source": "sparse",
              "original_content": "The product encounters an error but does not provide a status code or return value to indicate that an error has occurred."
            },
            "similarity": 70.49544479661013
          },
          {
            "metadata": {
              "doc_id": "665",
              "name": "Improper Initialization",
              "source": "sparse",
              "original_content": "The product does not initialize or incorrectly initializes a resource, which might leave the resource in an unexpected state when it is accessed or used."
            },
            "similarity": 67.9902862643159
          },
          {
            "metadata": {
              "doc_id": "325",
              "name": "Missing Cryptographic Step",
              "source": "sparse",
              "original_content": "The product does not implement a required step in a cryptographic algorithm, resulting in weaker encryption than advertised by the algorithm.",
              "keyphrase_sources": [
                {
                  "id": "component:NFS client and server implementation",
                  "keyphrase": "NFS client and server implementation",
                  "type": "component"
                }
              ]
            },
            "similarity": 63.90091292958128
          },
          {
            "metadata": {
              "doc_id": "755",
              "name": "Improper Handling of Exceptional Conditions",
              "source": "sparse",
              "original_content": "The product does not handle or incorrectly handles an exceptional condition."
            },
            "similarity": 63.47338031336763
          }
        ]
      }
    },
    "keyphrase_mapping": {
      "415": [
        {
          "id": "weakness:double free",
          "keyphrase": "double free",
          "type": "weakness"
        },
        {
          "id": "product:OpenBSD",
          "keyphrase": "OpenBSD",
          "type": "product"
        },
        {
          "id": "version:7.5 before errata 008",
          "keyphrase": "7.5 before errata 008",
          "type": "version"
        },
        {
          "id": "version:7.4 before errata 021",
          "keyphrase": "7.4 before errata 021",
          "type": "version"
        }
      ],
      "665": [
        {
          "id": "weakness:double free",
          "keyphrase": "double free",
          "type": "weakness"
        },
        {
          "id": "weakness:use uninitialized variable",
          "keyphrase": "use uninitialized variable",
          "type": "weakness"
        },
        {
          "id": "product:OpenBSD",
          "keyphrase": "OpenBSD",
          "type": "product"
        },
        {
          "id": "version:7.5 before errata 008",
          "keyphrase": "7.5 before errata 008",
          "type": "version"
        },
        {
          "id": "version:7.4 before errata 021",
          "keyphrase": "7.4 before errata 021",
          "type": "version"
        },
        {
          "id": "component:NFS client and server implementation",
          "keyphrase": "NFS client and server implementation",
          "type": "component"
        }
      ],
      "908": [
        {
          "id": "weakness:double free",
          "keyphrase": "double free",
          "type": "weakness"
        },
        {
          "id": "weakness:use uninitialized variable",
          "keyphrase": "use uninitialized variable",
          "type": "weakness"
        },
        {
          "id": "product:OpenBSD",
          "keyphrase": "OpenBSD",
          "type": "product"
        },
        {
          "id": "version:7.5 before errata 008",
          "keyphrase": "7.5 before errata 008",
          "type": "version"
        },
        {
          "id": "version:7.4 before errata 021",
          "keyphrase": "7.4 before errata 021",
          "type": "version"
        },
        {
          "id": "component:NFS client and server implementation",
          "keyphrase": "NFS client and server implementation",
          "type": "component"
        }
      ],
      "364": [
        {
          "id": "weakness:double free",
          "keyphrase": "double free",
          "type": "weakness"
        }
      ],
      "362": [
        {
          "id": "weakness:double free",
          "keyphrase": "double free",
          "type": "weakness"
        }
      ],
      "457": [
        {
          "id": "weakness:use uninitialized variable",
          "keyphrase": "use uninitialized variable",
          "type": "weakness"
        }
      ],
      "909": [
        {
          "id": "weakness:use uninitialized variable",
          "keyphrase": "use uninitialized variable",
          "type": "weakness"
        },
        {
          "id": "version:7.5 before errata 008",
          "keyphrase": "7.5 before errata 008",
          "type": "version"
        }
      ],
      "252": [
        {
          "id": "weakness:use uninitialized variable",
          "keyphrase": "use uninitialized variable",
          "type": "weakness"
        }
      ],
      "195": [
        {
          "id": "product:OpenBSD",
          "keyphrase": "OpenBSD",
          "type": "product"
        }
      ],
      "392": [
        {
          "id": "product:OpenBSD",
          "keyphrase": "OpenBSD",
          "type": "product"
        },
        {
          "id": "component:NFS client and server implementation",
          "keyphrase": "NFS client and server implementation",
          "type": "component"
        }
      ],
      "250": [
        {
          "id": "version:7.5 before errata 008",
          "keyphrase": "7.5 before errata 008",
          "type": "version"
        }
      ],
      "755": [
        {
          "id": "version:7.4 before errata 021",
          "keyphrase": "7.4 before errata 021",
          "type": "version"
        },
        {
          "id": "component:NFS client and server implementation",
          "keyphrase": "NFS client and server implementation",
          "type": "component"
        }
      ],
      "1333": [
        {
          "id": "version:7.4 before errata 021",
          "keyphrase": "7.4 before errata 021",
          "type": "version"
        }
      ],
      "325": [
        {
          "id": "component:NFS client and server implementation",
          "keyphrase": "NFS client and server implementation",
          "type": "component"
        }
      ]
    },
    "relevant_cwes": [
      {
        "metadata": {
          "doc_id": "415",
          "name": "Double Free",
          "source": "sparse",
          "original_content": "The product calls free() twice on the same memory address, potentially leading to modification of unexpected memory locations.",
          "keyphrase_sources": [
            {
              "id": "weakness:double free",
              "keyphrase": "double free",
              "type": "weakness"
            },
            {
              "id": "product:OpenBSD",
              "keyphrase": "OpenBSD",
              "type": "product"
            },
            {
              "id": "version:7.5 before errata 008",
              "keyphrase": "7.5 before errata 008",
              "type": "version"
            },
            {
              "id": "version:7.4 before errata 021",
              "keyphrase": "7.4 before errata 021",
              "type": "version"
            }
          ]
        },
        "similarity": 217.4736049617001
      },
      {
        "metadata": {
          "doc_id": "665",
          "name": "Improper Initialization",
          "source": "sparse",
          "original_content": "The product does not initialize or incorrectly initializes a resource, which might leave the resource in an unexpected state when it is accessed or used.",
          "keyphrase_sources": [
            {
              "id": "weakness:double free",
              "keyphrase": "double free",
              "type": "weakness"
            },
            {
              "id": "weakness:use uninitialized variable",
              "keyphrase": "use uninitialized variable",
              "type": "weakness"
            },
            {
              "id": "product:OpenBSD",
              "keyphrase": "OpenBSD",
              "type": "product"
            },
            {
              "id": "version:7.5 before errata 008",
              "keyphrase": "7.5 before errata 008",
              "type": "version"
            },
            {
              "id": "version:7.4 before errata 021",
              "keyphrase": "7.4 before errata 021",
              "type": "version"
            },
            {
              "id": "component:NFS client and server implementation",
              "keyphrase": "NFS client and server implementation",
              "type": "component"
            }
          ]
        },
        "similarity": 204.18437768125415
      },
      {
        "metadata": {
          "doc_id": "908",
          "name": "Use of Uninitialized Resource",
          "source": "sparse",
          "original_content": "The product uses or accesses a resource that has not been initialized.",
          "keyphrase_sources": [
            {
              "id": "weakness:double free",
              "keyphrase": "double free",
              "type": "weakness"
            },
            {
              "id": "weakness:use uninitialized variable",
              "keyphrase": "use uninitialized variable",
              "type": "weakness"
            },
            {
              "id": "product:OpenBSD",
              "keyphrase": "OpenBSD",
              "type": "product"
            },
            {
              "id": "version:7.5 before errata 008",
              "keyphrase": "7.5 before errata 008",
              "type": "version"
            },
            {
              "id": "version:7.4 before errata 021",
              "keyphrase": "7.4 before errata 021",
              "type": "version"
            },
            {
              "id": "component:NFS client and server implementation",
              "keyphrase": "NFS client and server implementation",
              "type": "component"
            }
          ]
        },
        "similarity": 203.57233543559843
      },
      {
        "metadata": {
          "doc_id": "457",
          "name": "Use of Uninitialized Variable",
          "source": "sparse",
          "original_content": "The code uses a variable that has not been initialized, leading to unpredictable or unintended results.",
          "keyphrase_sources": [
            {
              "id": "weakness:use uninitialized variable",
              "keyphrase": "use uninitialized variable",
              "type": "weakness"
            }
          ]
        },
        "similarity": 203.23912730867067
      },
      {
        "metadata": {
          "doc_id": "909",
          "name": "Missing Initialization of Resource",
          "source": "sparse",
          "original_content": "The product does not initialize a critical resource.",
          "keyphrase_sources": [
            {
              "id": "weakness:use uninitialized variable",
              "keyphrase": "use uninitialized variable",
              "type": "weakness"
            },
            {
              "id": "version:7.5 before errata 008",
              "keyphrase": "7.5 before errata 008",
              "type": "version"
            }
          ]
        },
        "similarity": 192.34265458458103
      },
      {
        "metadata": {
          "doc_id": "252",
          "name": "Unchecked Return Value",
          "source": "sparse",
          "original_content": "The product does not check the return value from a method or function, which can prevent it from detecting unexpected states and conditions.",
          "keyphrase_sources": [
            {
              "id": "weakness:use uninitialized variable",
              "keyphrase": "use uninitialized variable",
              "type": "weakness"
            }
          ]
        },
        "similarity": 184.45093117545738
      },
      {
        "metadata": {
          "doc_id": "364",
          "name": "Signal Handler Race Condition",
          "source": "sparse",
          "original_content": "The product uses a signal handler that introduces a race condition.",
          "keyphrase_sources": [
            {
              "id": "weakness:double free",
              "keyphrase": "double free",
              "type": "weakness"
            }
          ]
        },
        "similarity": 173.7381155487043
      },
      {
        "metadata": {
          "doc_id": "362",
          "name": "Concurrent Execution using Shared Resource with Improper Synchronization ('Race Condition')",
          "source": "sparse",
          "original_content": "The product contains a concurrent code sequence that requires temporary, exclusive access to a shared resource, but a timing window exists in which the shared resource can be modified by another code sequence operating concurrently.",
          "keyphrase_sources": [
            {
              "id": "weakness:double free",
              "keyphrase": "double free",
              "type": "weakness"
            }
          ]
        },
        "similarity": 169.45250087831576
      },
      {
        "metadata": {
          "doc_id": "325",
          "name": "Missing Cryptographic Step",
          "source": "sparse",
          "original_content": "The product does not implement a required step in a cryptographic algorithm, resulting in weaker encryption than advertised by the algorithm.",
          "keyphrase_sources": [
            {
              "id": "component:NFS client and server implementation",
              "keyphrase": "NFS client and server implementation",
              "type": "component"
            }
          ]
        },
        "similarity": 63.90091292958128
      },
      {
        "metadata": {
          "doc_id": "195",
          "name": "Signed to Unsigned Conversion Error",
          "source": "sparse",
          "original_content": "The product uses a signed primitive and performs a cast to an unsigned primitive, which can produce an unexpected value if the value of the signed primitive can not be represented using an unsigned primitive.",
          "keyphrase_sources": [
            {
              "id": "product:OpenBSD",
              "keyphrase": "OpenBSD",
              "type": "product"
            }
          ]
        },
        "similarity": 63.29021933594912
      },
      {
        "metadata": {
          "doc_id": "250",
          "name": "Execution with Unnecessary Privileges",
          "source": "sparse",
          "original_content": "The product performs an operation at a privilege level that is higher than the minimum level required, which creates new weaknesses or amplifies the consequences of other weaknesses.",
          "keyphrase_sources": [
            {
              "id": "version:7.5 before errata 008",
              "keyphrase": "7.5 before errata 008",
              "type": "version"
            }
          ]
        },
        "similarity": 59.07916317296568
      },
      {
        "metadata": {
          "doc_id": "755",
          "name": "Improper Handling of Exceptional Conditions",
          "source": "sparse",
          "original_content": "The product does not handle or incorrectly handles an exceptional condition.",
          "keyphrase_sources": [
            {
              "id": "version:7.4 before errata 021",
              "keyphrase": "7.4 before errata 021",
              "type": "version"
            },
            {
              "id": "component:NFS client and server implementation",
              "keyphrase": "NFS client and server implementation",
              "type": "component"
            }
          ]
        },
        "similarity": 57.36765219051006
      },
      {
        "metadata": {
          "doc_id": "1333",
          "name": "Inefficient Regular Expression Complexity",
          "source": "sparse",
          "original_content": "The product uses a regular expression with an inefficient, possibly exponential worst-case computational complexity that consumes excessive CPU cycles.",
          "keyphrase_sources": [
            {
              "id": "version:7.4 before errata 021",
              "keyphrase": "7.4 before errata 021",
              "type": "version"
            }
          ]
        },
        "similarity": 56.242372287230396
      },
      {
        "metadata": {
          "doc_id": "392",
          "name": "Missing Report of Error Condition",
          "source": "sparse",
          "original_content": "The product encounters an error but does not provide a status code or return value to indicate that an error has occurred.",
          "keyphrase_sources": [
            {
              "id": "product:OpenBSD",
              "keyphrase": "OpenBSD",
              "type": "product"
            },
            {
              "id": "component:NFS client and server implementation",
              "keyphrase": "NFS client and server implementation",
              "type": "component"
            }
          ]
        },
        "similarity": 49.11575337222318
      }
    ],
    "enhanced_query": "# Vulnerability Description\n\n    In OpenBSD 7.5 before errata 008 and OpenBSD 7.4 before errata 021, avoid possible mbuf **double free** in NFS client and server implementation, do not **use uninitialized variable** in error handling of NFS server.\n\n    # Keyphrase-Specific CWE Analysis\n    This vulnerability contains multiple keyphrases that may map to different CWEs. \n    Please analyze each keyphrase separately and determine the most appropriate CWE(s) for each.\n\n    ## WEAKNESS: 'double free'\n\nRelevant CWEs for this WEAKNESS:\n\n### 1. CWE-415: Double Free (Score: 217.47)\n\nThe product calls free() twice on the same memory address, potentially leading to modification of unexpected memory locations....\n\n### 2. CWE-665: Improper Initialization (Score: 204.18)\n\nThe product does not initialize or incorrectly initializes a resource, which might leave the resource in an unexpected state when it is accessed or used....\n\n### 3. CWE-908: Use of Uninitialized Resource (Score: 203.57)\n\nThe product uses or accesses a resource that has not been initialized....\n\n### 4. CWE-364: Signal Handler Race Condition (Score: 173.74)\n\nThe product uses a signal handler that introduces a race condition....\n\n### 5. CWE-362: Concurrent Execution using Shared Resource with Improper Synchronization ('Race Condition') (Score: 169.45)\n\nThe product contains a concurrent code sequence that requires temporary, exclusive access to a shared resource, but a timing window exists in which the shared resource can be modified by another code sequence operating concurrently....\n\n## PRODUCT: 'OpenBSD'\n\nRelevant CWEs for this PRODUCT:\n\n### 1. CWE-415: Double Free (Score: 217.47)\n\nThe product calls free() twice on the same memory address, potentially leading to modification of unexpected memory locations....\n\n### 2. CWE-665: Improper Initialization (Score: 204.18)\n\nThe product does not initialize or incorrectly initializes a resource, which might leave the resource in an unexpected state when it is accessed or used....\n\n### 3. CWE-908: Use of Uninitialized Resource (Score: 203.57)\n\nThe product uses or accesses a resource that has not been initialized....\n\n### 4. CWE-195: Signed to Unsigned Conversion Error (Score: 63.29)\n\nThe product uses a signed primitive and performs a cast to an unsigned primitive, which can produce an unexpected value if the value of the signed primitive can not be represented using an unsigned primitive....\n\n### 5. CWE-392: Missing Report of Error Condition (Score: 49.12)\n\nThe product encounters an error but does not provide a status code or return value to indicate that an error has occurred....\n\n## VERSION: '7.5 before errata 008'\n\nRelevant CWEs for this VERSION:\n\n### 1. CWE-415: Double Free (Score: 217.47)\n\nThe product calls free() twice on the same memory address, potentially leading to modification of unexpected memory locations....\n\n### 2. CWE-665: Improper Initialization (Score: 204.18)\n\nThe product does not initialize or incorrectly initializes a resource, which might leave the resource in an unexpected state when it is accessed or used....\n\n### 3. CWE-908: Use of Uninitialized Resource (Score: 203.57)\n\nThe product uses or accesses a resource that has not been initialized....\n\n### 4. CWE-909: Missing Initialization of Resource (Score: 192.34)\n\nThe product does not initialize a critical resource....\n\n### 5. CWE-250: Execution with Unnecessary Privileges (Score: 59.08)\n\nThe product performs an operation at a privilege level that is higher than the minimum level required, which creates new weaknesses or amplifies the consequences of other weaknesses....\n\n## VERSION: '7.4 before errata 021'\n\nRelevant CWEs for this VERSION:\n\n### 1. CWE-415: Double Free (Score: 217.47)\n\nThe product calls free() twice on the same memory address, potentially leading to modification of unexpected memory locations....\n\n### 2. CWE-665: Improper Initialization (Score: 204.18)\n\nThe product does not initialize or incorrectly initializes a resource, which might leave the resource in an unexpected state when it is accessed or used....\n\n### 3. CWE-908: Use of Uninitialized Resource (Score: 203.57)\n\nThe product uses or accesses a resource that has not been initialized....\n\n### 4. CWE-755: Improper Handling of Exceptional Conditions (Score: 57.37)\n\nThe product does not handle or incorrectly handles an exceptional condition....\n\n### 5. CWE-1333: Inefficient Regular Expression Complexity (Score: 56.24)\n\nThe product uses a regular expression with an inefficient, possibly exponential worst-case computational complexity that consumes excessive CPU cycles....\n\n## WEAKNESS: 'use uninitialized variable'\n\nRelevant CWEs for this WEAKNESS:\n\n### 1. CWE-665: Improper Initialization (Score: 204.18)\n\nThe product does not initialize or incorrectly initializes a resource, which might leave the resource in an unexpected state when it is accessed or used....\n\n### 2. CWE-908: Use of Uninitialized Resource (Score: 203.57)\n\nThe product uses or accesses a resource that has not been initialized....\n\n### 3. CWE-457: Use of Uninitialized Variable (Score: 203.24)\n\nThe code uses a variable that has not been initialized, leading to unpredictable or unintended results....\n\n### 4. CWE-909: Missing Initialization of Resource (Score: 192.34)\n\nThe product does not initialize a critical resource....\n\n### 5. CWE-252: Unchecked Return Value (Score: 184.45)\n\nThe product does not check the return value from a method or function, which can prevent it from detecting unexpected states and conditions....\n\n## COMPONENT: 'NFS client and server implementation'\n\nRelevant CWEs for this COMPONENT:\n\n### 1. CWE-665: Improper Initialization (Score: 204.18)\n\nThe product does not initialize or incorrectly initializes a resource, which might leave the resource in an unexpected state when it is accessed or used....\n\n### 2. CWE-908: Use of Uninitialized Resource (Score: 203.57)\n\nThe product uses or accesses a resource that has not been initialized....\n\n### 3. CWE-325: Missing Cryptographic Step (Score: 63.90)\n\nThe product does not implement a required step in a cryptographic algorithm, resulting in weaker encryption than advertised by the algorithm....\n\n### 4. CWE-755: Improper Handling of Exceptional Conditions (Score: 57.37)\n\nThe product does not handle or incorrectly handles an exceptional condition....\n\n### 5. CWE-392: Missing Report of Error Condition (Score: 49.12)\n\nThe product encounters an error but does not provide a status code or return value to indicate that an error has occurred....\n\n\n    # Analysis Instructions\n    1. For each keyphrase, identify the most appropriate CWE(s) that represent the weakness.\n    2. Consider how the different keyphrases might relate to each other in the vulnerability chain.\n    3. Provide a final determination of primary CWE(s) and any secondary CWEs.\n    4. Format your response using the standard analysis template.\n\n    Please analyze how these different weaknesses interact and provide a comprehensive CWE classification.\n    "
  },
  "retrieval_time": 1.0398893356323242
}