{
  "vulnerability_info": "VulnerabilityInfo(cve_id='CVE-2024-33027', description='**Memory corruption** can occur when **arbitrary user-space app gains kernel level privilege** to modify DDR memory by corrupting the GPU page table.', key_phrases={'rootcause': '', 'weakness': ['Memory corruption', 'arbitrary user-space app gains kernel level privilege'], 'impact': '', 'vector': '', 'attacker': '', 'product': '', 'version': '', 'component': 'GPU page table'}, reference_content=None, similar_info={'cwe_distribution': {}, 'cwe_consensus': '', 'similarity_stats': {'thresholds': [], 'total_samples_by_threshold': {}, 'top_cwes_by_threshold': {}}}, similarity_summary=SimilarityInsight(consensus_cwe='', top_cwes=[], confidence_levels={}, total_samples=0), analysis='', analysis_with_relationships='', criticism='', resolution='', relevant_cwes=[{'metadata': {'doc_id': '226', 'name': 'Sensitive Information in Resource Not Removed Before Reuse', 'source': 'sparse', 'original_content': 'The product releases a resource such as memory or a file so that it can be made available for reuse, but it does not clear or \"zeroize\" the information contained in the resource before the product performs a critical state transition or makes the resource available for reuse by other entities.', 'keyphrase_sources': [{'id': 'weakness:arbitrary user-space app gains kernel level privilege', 'keyphrase': 'arbitrary user-space app gains kernel level privilege', 'type': 'weakness'}]}, 'similarity': np.float64(174.2155903775743)}, {'metadata': {'doc_id': '367', 'name': 'Time-of-check Time-of-use (TOCTOU) Race Condition', 'source': 'sparse', 'original_content': \"The product checks the state of a resource before using that resource, but the resource's state can change between the check and the use in a way that invalidates the results of the check. This can cause the product to perform invalid actions when the resource is in an unexpected state.\", 'keyphrase_sources': [{'id': 'weakness:arbitrary user-space app gains kernel level privilege', 'keyphrase': 'arbitrary user-space app gains kernel level privilege', 'type': 'weakness'}]}, 'similarity': np.float64(168.92109112022104)}, {'metadata': {'doc_id': '787', 'name': 'Out-of-bounds Write', 'source': 'sparse', 'original_content': 'The product writes data past the end, or before the beginning, of the intended buffer.', 'keyphrase_sources': [{'id': 'weakness:Memory corruption', 'keyphrase': 'Memory corruption', 'type': 'weakness'}, {'id': 'weakness:arbitrary user-space app gains kernel level privilege', 'keyphrase': 'arbitrary user-space app gains kernel level privilege', 'type': 'weakness'}, {'id': 'component:GPU page table', 'keyphrase': 'GPU page table', 'type': 'component'}]}, 'similarity': np.float64(164.84379329214931)}, {'metadata': {'doc_id': '362', 'name': \"Concurrent Execution using Shared Resource with Improper Synchronization ('Race Condition')\", 'source': 'sparse', 'original_content': 'The product contains a concurrent code sequence that requires temporary, exclusive access to a shared resource, but a timing window exists in which the shared resource can be modified by another code sequence operating concurrently.', 'keyphrase_sources': [{'id': 'weakness:Memory corruption', 'keyphrase': 'Memory corruption', 'type': 'weakness'}, {'id': 'weakness:arbitrary user-space app gains kernel level privilege', 'keyphrase': 'arbitrary user-space app gains kernel level privilege', 'type': 'weakness'}, {'id': 'component:GPU page table', 'keyphrase': 'GPU page table', 'type': 'component'}]}, 'similarity': np.float64(157.23810321319755)}, {'metadata': {'doc_id': '415', 'name': 'Double Free', 'source': 'sparse', 'original_content': 'The product calls free() twice on the same memory address, potentially leading to modification of unexpected memory locations.', 'keyphrase_sources': [{'id': 'weakness:Memory corruption', 'keyphrase': 'Memory corruption', 'type': 'weakness'}, {'id': 'component:GPU page table', 'keyphrase': 'GPU page table', 'type': 'component'}]}, 'similarity': np.float64(156.51389203954017)}, {'metadata': {'doc_id': '667', 'name': 'Improper Locking', 'source': 'sparse', 'original_content': 'The product does not properly acquire or release a lock on a resource, leading to unexpected resource state changes and behaviors.', 'keyphrase_sources': [{'id': 'weakness:Memory corruption', 'keyphrase': 'Memory corruption', 'type': 'weakness'}, {'id': 'weakness:arbitrary user-space app gains kernel level privilege', 'keyphrase': 'arbitrary user-space app gains kernel level privilege', 'type': 'weakness'}]}, 'similarity': np.float64(153.9156722098714)}, {'metadata': {'doc_id': '908', 'name': 'Use of Uninitialized Resource', 'source': 'sparse', 'original_content': 'The product uses or accesses a resource that has not been initialized.', 'keyphrase_sources': [{'id': 'weakness:Memory corruption', 'keyphrase': 'Memory corruption', 'type': 'weakness'}]}, 'similarity': np.float64(151.55011999972464)}, {'metadata': {'doc_id': '472', 'name': 'External Control of Assumed-Immutable Web Parameter', 'source': 'sparse', 'original_content': 'The web application does not sufficiently verify inputs that are assumed to be immutable but are actually externally controllable, such as hidden form fields.', 'keyphrase_sources': [{'id': 'component:GPU page table', 'keyphrase': 'GPU page table', 'type': 'component'}]}, 'similarity': np.float64(55.44497926620404)}, {'metadata': {'doc_id': '416', 'name': 'Use After Free', 'source': 'sparse', 'original_content': 'The product reuses or references memory after it has been freed. At some point afterward, the memory may be allocated again and saved in another pointer, while the original pointer references a location somewhere within the new allocation. Any operations using the original pointer are no longer valid because the memory \"belongs\" to the code that operates on the new pointer.', 'keyphrase_sources': [{'id': 'component:GPU page table', 'keyphrase': 'GPU page table', 'type': 'component'}]}, 'similarity': np.float64(50.94876153538176)}], identified_cwes={'analyzer': [], 'critic_additional': []})",
  "retrieval_results": {
    "has_multiple_keyphrases": true,
    "keyphrase_cwe_sets": {
      "weakness:Memory corruption": {
        "keyphrase": "Memory corruption",
        "type": "weakness",
        "cwes": [
          {
            "metadata": {
              "doc_id": "787",
              "name": "Out-of-bounds Write",
              "source": "sparse",
              "original_content": "The product writes data past the end, or before the beginning, of the intended buffer.",
              "keyphrase_sources": [
                {
                  "id": "weakness:Memory corruption",
                  "keyphrase": "Memory corruption",
                  "type": "weakness"
                },
                {
                  "id": "weakness:arbitrary user-space app gains kernel level privilege",
                  "keyphrase": "arbitrary user-space app gains kernel level privilege",
                  "type": "weakness"
                },
                {
                  "id": "component:GPU page table",
                  "keyphrase": "GPU page table",
                  "type": "component"
                }
              ]
            },
            "similarity": 164.84379329214931
          },
          {
            "metadata": {
              "doc_id": "362",
              "name": "Concurrent Execution using Shared Resource with Improper Synchronization ('Race Condition')",
              "source": "sparse",
              "original_content": "The product contains a concurrent code sequence that requires temporary, exclusive access to a shared resource, but a timing window exists in which the shared resource can be modified by another code sequence operating concurrently.",
              "keyphrase_sources": [
                {
                  "id": "weakness:Memory corruption",
                  "keyphrase": "Memory corruption",
                  "type": "weakness"
                },
                {
                  "id": "weakness:arbitrary user-space app gains kernel level privilege",
                  "keyphrase": "arbitrary user-space app gains kernel level privilege",
                  "type": "weakness"
                },
                {
                  "id": "component:GPU page table",
                  "keyphrase": "GPU page table",
                  "type": "component"
                }
              ]
            },
            "similarity": 157.23810321319755
          },
          {
            "metadata": {
              "doc_id": "415",
              "name": "Double Free",
              "source": "sparse",
              "original_content": "The product calls free() twice on the same memory address, potentially leading to modification of unexpected memory locations.",
              "keyphrase_sources": [
                {
                  "id": "weakness:Memory corruption",
                  "keyphrase": "Memory corruption",
                  "type": "weakness"
                },
                {
                  "id": "component:GPU page table",
                  "keyphrase": "GPU page table",
                  "type": "component"
                }
              ]
            },
            "similarity": 156.51389203954017
          },
          {
            "metadata": {
              "doc_id": "667",
              "name": "Improper Locking",
              "source": "sparse",
              "original_content": "The product does not properly acquire or release a lock on a resource, leading to unexpected resource state changes and behaviors.",
              "keyphrase_sources": [
                {
                  "id": "weakness:Memory corruption",
                  "keyphrase": "Memory corruption",
                  "type": "weakness"
                },
                {
                  "id": "weakness:arbitrary user-space app gains kernel level privilege",
                  "keyphrase": "arbitrary user-space app gains kernel level privilege",
                  "type": "weakness"
                }
              ]
            },
            "similarity": 153.9156722098714
          },
          {
            "metadata": {
              "doc_id": "908",
              "name": "Use of Uninitialized Resource",
              "source": "sparse",
              "original_content": "The product uses or accesses a resource that has not been initialized.",
              "keyphrase_sources": [
                {
                  "id": "weakness:Memory corruption",
                  "keyphrase": "Memory corruption",
                  "type": "weakness"
                }
              ]
            },
            "similarity": 151.55011999972464
          }
        ]
      },
      "weakness:arbitrary user-space app gains kernel level privilege": {
        "keyphrase": "arbitrary user-space app gains kernel level privilege",
        "type": "weakness",
        "cwes": [
          {
            "metadata": {
              "doc_id": "667",
              "name": "Improper Locking",
              "source": "sparse",
              "original_content": "The product does not properly acquire or release a lock on a resource, leading to unexpected resource state changes and behaviors."
            },
            "similarity": 180.1675225848345
          },
          {
            "metadata": {
              "doc_id": "226",
              "name": "Sensitive Information in Resource Not Removed Before Reuse",
              "source": "sparse",
              "original_content": "The product releases a resource such as memory or a file so that it can be made available for reuse, but it does not clear or \"zeroize\" the information contained in the resource before the product performs a critical state transition or makes the resource available for reuse by other entities.",
              "keyphrase_sources": [
                {
                  "id": "weakness:arbitrary user-space app gains kernel level privilege",
                  "keyphrase": "arbitrary user-space app gains kernel level privilege",
                  "type": "weakness"
                }
              ]
            },
            "similarity": 174.2155903775743
          },
          {
            "metadata": {
              "doc_id": "787",
              "name": "Out-of-bounds Write",
              "source": "sparse",
              "original_content": "The product writes data past the end, or before the beginning, of the intended buffer."
            },
            "similarity": 172.38349600547988
          },
          {
            "metadata": {
              "doc_id": "367",
              "name": "Time-of-check Time-of-use (TOCTOU) Race Condition",
              "source": "sparse",
              "original_content": "The product checks the state of a resource before using that resource, but the resource's state can change between the check and the use in a way that invalidates the results of the check. This can cause the product to perform invalid actions when the resource is in an unexpected state.",
              "keyphrase_sources": [
                {
                  "id": "weakness:arbitrary user-space app gains kernel level privilege",
                  "keyphrase": "arbitrary user-space app gains kernel level privilege",
                  "type": "weakness"
                }
              ]
            },
            "similarity": 168.92109112022104
          },
          {
            "metadata": {
              "doc_id": "362",
              "name": "Concurrent Execution using Shared Resource with Improper Synchronization ('Race Condition')",
              "source": "sparse",
              "original_content": "The product contains a concurrent code sequence that requires temporary, exclusive access to a shared resource, but a timing window exists in which the shared resource can be modified by another code sequence operating concurrently."
            },
            "similarity": 167.76801829105148
          }
        ]
      },
      "component:GPU page table": {
        "keyphrase": "GPU page table",
        "type": "component",
        "cwes": [
          {
            "metadata": {
              "doc_id": "362",
              "name": "Concurrent Execution using Shared Resource with Improper Synchronization ('Race Condition')",
              "source": "sparse",
              "original_content": "The product contains a concurrent code sequence that requires temporary, exclusive access to a shared resource, but a timing window exists in which the shared resource can be modified by another code sequence operating concurrently."
            },
            "similarity": 57.38853107262465
          },
          {
            "metadata": {
              "doc_id": "415",
              "name": "Double Free",
              "source": "sparse",
              "original_content": "The product calls free() twice on the same memory address, potentially leading to modification of unexpected memory locations."
            },
            "similarity": 55.56320889720952
          },
          {
            "metadata": {
              "doc_id": "472",
              "name": "External Control of Assumed-Immutable Web Parameter",
              "source": "sparse",
              "original_content": "The web application does not sufficiently verify inputs that are assumed to be immutable but are actually externally controllable, such as hidden form fields.",
              "keyphrase_sources": [
                {
                  "id": "component:GPU page table",
                  "keyphrase": "GPU page table",
                  "type": "component"
                }
              ]
            },
            "similarity": 55.44497926620404
          },
          {
            "metadata": {
              "doc_id": "787",
              "name": "Out-of-bounds Write",
              "source": "sparse",
              "original_content": "The product writes data past the end, or before the beginning, of the intended buffer."
            },
            "similarity": 51.57312873602614
          },
          {
            "metadata": {
              "doc_id": "416",
              "name": "Use After Free",
              "source": "sparse",
              "original_content": "The product reuses or references memory after it has been freed. At some point afterward, the memory may be allocated again and saved in another pointer, while the original pointer references a location somewhere within the new allocation. Any operations using the original pointer are no longer valid because the memory \"belongs\" to the code that operates on the new pointer.",
              "keyphrase_sources": [
                {
                  "id": "component:GPU page table",
                  "keyphrase": "GPU page table",
                  "type": "component"
                }
              ]
            },
            "similarity": 50.94876153538176
          }
        ]
      }
    },
    "keyphrase_mapping": {
      "787": [
        {
          "id": "weakness:Memory corruption",
          "keyphrase": "Memory corruption",
          "type": "weakness"
        },
        {
          "id": "weakness:arbitrary user-space app gains kernel level privilege",
          "keyphrase": "arbitrary user-space app gains kernel level privilege",
          "type": "weakness"
        },
        {
          "id": "component:GPU page table",
          "keyphrase": "GPU page table",
          "type": "component"
        }
      ],
      "362": [
        {
          "id": "weakness:Memory corruption",
          "keyphrase": "Memory corruption",
          "type": "weakness"
        },
        {
          "id": "weakness:arbitrary user-space app gains kernel level privilege",
          "keyphrase": "arbitrary user-space app gains kernel level privilege",
          "type": "weakness"
        },
        {
          "id": "component:GPU page table",
          "keyphrase": "GPU page table",
          "type": "component"
        }
      ],
      "415": [
        {
          "id": "weakness:Memory corruption",
          "keyphrase": "Memory corruption",
          "type": "weakness"
        },
        {
          "id": "component:GPU page table",
          "keyphrase": "GPU page table",
          "type": "component"
        }
      ],
      "667": [
        {
          "id": "weakness:Memory corruption",
          "keyphrase": "Memory corruption",
          "type": "weakness"
        },
        {
          "id": "weakness:arbitrary user-space app gains kernel level privilege",
          "keyphrase": "arbitrary user-space app gains kernel level privilege",
          "type": "weakness"
        }
      ],
      "908": [
        {
          "id": "weakness:Memory corruption",
          "keyphrase": "Memory corruption",
          "type": "weakness"
        }
      ],
      "226": [
        {
          "id": "weakness:arbitrary user-space app gains kernel level privilege",
          "keyphrase": "arbitrary user-space app gains kernel level privilege",
          "type": "weakness"
        }
      ],
      "367": [
        {
          "id": "weakness:arbitrary user-space app gains kernel level privilege",
          "keyphrase": "arbitrary user-space app gains kernel level privilege",
          "type": "weakness"
        }
      ],
      "472": [
        {
          "id": "component:GPU page table",
          "keyphrase": "GPU page table",
          "type": "component"
        }
      ],
      "416": [
        {
          "id": "component:GPU page table",
          "keyphrase": "GPU page table",
          "type": "component"
        }
      ]
    },
    "relevant_cwes": [
      {
        "metadata": {
          "doc_id": "226",
          "name": "Sensitive Information in Resource Not Removed Before Reuse",
          "source": "sparse",
          "original_content": "The product releases a resource such as memory or a file so that it can be made available for reuse, but it does not clear or \"zeroize\" the information contained in the resource before the product performs a critical state transition or makes the resource available for reuse by other entities.",
          "keyphrase_sources": [
            {
              "id": "weakness:arbitrary user-space app gains kernel level privilege",
              "keyphrase": "arbitrary user-space app gains kernel level privilege",
              "type": "weakness"
            }
          ]
        },
        "similarity": 174.2155903775743
      },
      {
        "metadata": {
          "doc_id": "367",
          "name": "Time-of-check Time-of-use (TOCTOU) Race Condition",
          "source": "sparse",
          "original_content": "The product checks the state of a resource before using that resource, but the resource's state can change between the check and the use in a way that invalidates the results of the check. This can cause the product to perform invalid actions when the resource is in an unexpected state.",
          "keyphrase_sources": [
            {
              "id": "weakness:arbitrary user-space app gains kernel level privilege",
              "keyphrase": "arbitrary user-space app gains kernel level privilege",
              "type": "weakness"
            }
          ]
        },
        "similarity": 168.92109112022104
      },
      {
        "metadata": {
          "doc_id": "787",
          "name": "Out-of-bounds Write",
          "source": "sparse",
          "original_content": "The product writes data past the end, or before the beginning, of the intended buffer.",
          "keyphrase_sources": [
            {
              "id": "weakness:Memory corruption",
              "keyphrase": "Memory corruption",
              "type": "weakness"
            },
            {
              "id": "weakness:arbitrary user-space app gains kernel level privilege",
              "keyphrase": "arbitrary user-space app gains kernel level privilege",
              "type": "weakness"
            },
            {
              "id": "component:GPU page table",
              "keyphrase": "GPU page table",
              "type": "component"
            }
          ]
        },
        "similarity": 164.84379329214931
      },
      {
        "metadata": {
          "doc_id": "362",
          "name": "Concurrent Execution using Shared Resource with Improper Synchronization ('Race Condition')",
          "source": "sparse",
          "original_content": "The product contains a concurrent code sequence that requires temporary, exclusive access to a shared resource, but a timing window exists in which the shared resource can be modified by another code sequence operating concurrently.",
          "keyphrase_sources": [
            {
              "id": "weakness:Memory corruption",
              "keyphrase": "Memory corruption",
              "type": "weakness"
            },
            {
              "id": "weakness:arbitrary user-space app gains kernel level privilege",
              "keyphrase": "arbitrary user-space app gains kernel level privilege",
              "type": "weakness"
            },
            {
              "id": "component:GPU page table",
              "keyphrase": "GPU page table",
              "type": "component"
            }
          ]
        },
        "similarity": 157.23810321319755
      },
      {
        "metadata": {
          "doc_id": "415",
          "name": "Double Free",
          "source": "sparse",
          "original_content": "The product calls free() twice on the same memory address, potentially leading to modification of unexpected memory locations.",
          "keyphrase_sources": [
            {
              "id": "weakness:Memory corruption",
              "keyphrase": "Memory corruption",
              "type": "weakness"
            },
            {
              "id": "component:GPU page table",
              "keyphrase": "GPU page table",
              "type": "component"
            }
          ]
        },
        "similarity": 156.51389203954017
      },
      {
        "metadata": {
          "doc_id": "667",
          "name": "Improper Locking",
          "source": "sparse",
          "original_content": "The product does not properly acquire or release a lock on a resource, leading to unexpected resource state changes and behaviors.",
          "keyphrase_sources": [
            {
              "id": "weakness:Memory corruption",
              "keyphrase": "Memory corruption",
              "type": "weakness"
            },
            {
              "id": "weakness:arbitrary user-space app gains kernel level privilege",
              "keyphrase": "arbitrary user-space app gains kernel level privilege",
              "type": "weakness"
            }
          ]
        },
        "similarity": 153.9156722098714
      },
      {
        "metadata": {
          "doc_id": "908",
          "name": "Use of Uninitialized Resource",
          "source": "sparse",
          "original_content": "The product uses or accesses a resource that has not been initialized.",
          "keyphrase_sources": [
            {
              "id": "weakness:Memory corruption",
              "keyphrase": "Memory corruption",
              "type": "weakness"
            }
          ]
        },
        "similarity": 151.55011999972464
      },
      {
        "metadata": {
          "doc_id": "472",
          "name": "External Control of Assumed-Immutable Web Parameter",
          "source": "sparse",
          "original_content": "The web application does not sufficiently verify inputs that are assumed to be immutable but are actually externally controllable, such as hidden form fields.",
          "keyphrase_sources": [
            {
              "id": "component:GPU page table",
              "keyphrase": "GPU page table",
              "type": "component"
            }
          ]
        },
        "similarity": 55.44497926620404
      },
      {
        "metadata": {
          "doc_id": "416",
          "name": "Use After Free",
          "source": "sparse",
          "original_content": "The product reuses or references memory after it has been freed. At some point afterward, the memory may be allocated again and saved in another pointer, while the original pointer references a location somewhere within the new allocation. Any operations using the original pointer are no longer valid because the memory \"belongs\" to the code that operates on the new pointer.",
          "keyphrase_sources": [
            {
              "id": "component:GPU page table",
              "keyphrase": "GPU page table",
              "type": "component"
            }
          ]
        },
        "similarity": 50.94876153538176
      }
    ],
    "enhanced_query": "# Vulnerability Description\n\n    **Memory corruption** can occur when **arbitrary user-space app gains kernel level privilege** to modify DDR memory by corrupting the GPU page table.\n\n    # Keyphrase-Specific CWE Analysis\n    This vulnerability contains multiple keyphrases that may map to different CWEs. \n    Please analyze each keyphrase separately and determine the most appropriate CWE(s) for each.\n\n    ## WEAKNESS: 'arbitrary user-space app gains kernel level privilege'\n\nRelevant CWEs for this WEAKNESS:\n\n### 1. CWE-226: Sensitive Information in Resource Not Removed Before Reuse (Score: 174.22)\n\nThe product releases a resource such as memory or a file so that it can be made available for reuse, but it does not clear or \"zeroize\" the information contained in the resource before the product performs a critical state transition or makes the resource available for reuse by other entities....\n\n### 2. CWE-367: Time-of-check Time-of-use (TOCTOU) Race Condition (Score: 168.92)\n\nThe product checks the state of a resource before using that resource, but the resource's state can change between the check and the use in a way that invalidates the results of the check. This can cause the product to perform invalid actions when the resource is in an unexpected state....\n\n### 3. CWE-787: Out-of-bounds Write (Score: 164.84)\n\nThe product writes data past the end, or before the beginning, of the intended buffer....\n\n### 4. CWE-362: Concurrent Execution using Shared Resource with Improper Synchronization ('Race Condition') (Score: 157.24)\n\nThe product contains a concurrent code sequence that requires temporary, exclusive access to a shared resource, but a timing window exists in which the shared resource can be modified by another code sequence operating concurrently....\n\n### 5. CWE-667: Improper Locking (Score: 153.92)\n\nThe product does not properly acquire or release a lock on a resource, leading to unexpected resource state changes and behaviors....\n\n## WEAKNESS: 'Memory corruption'\n\nRelevant CWEs for this WEAKNESS:\n\n### 1. CWE-787: Out-of-bounds Write (Score: 164.84)\n\nThe product writes data past the end, or before the beginning, of the intended buffer....\n\n### 2. CWE-362: Concurrent Execution using Shared Resource with Improper Synchronization ('Race Condition') (Score: 157.24)\n\nThe product contains a concurrent code sequence that requires temporary, exclusive access to a shared resource, but a timing window exists in which the shared resource can be modified by another code sequence operating concurrently....\n\n### 3. CWE-415: Double Free (Score: 156.51)\n\nThe product calls free() twice on the same memory address, potentially leading to modification of unexpected memory locations....\n\n### 4. CWE-667: Improper Locking (Score: 153.92)\n\nThe product does not properly acquire or release a lock on a resource, leading to unexpected resource state changes and behaviors....\n\n### 5. CWE-908: Use of Uninitialized Resource (Score: 151.55)\n\nThe product uses or accesses a resource that has not been initialized....\n\n## COMPONENT: 'GPU page table'\n\nRelevant CWEs for this COMPONENT:\n\n### 1. CWE-787: Out-of-bounds Write (Score: 164.84)\n\nThe product writes data past the end, or before the beginning, of the intended buffer....\n\n### 2. CWE-362: Concurrent Execution using Shared Resource with Improper Synchronization ('Race Condition') (Score: 157.24)\n\nThe product contains a concurrent code sequence that requires temporary, exclusive access to a shared resource, but a timing window exists in which the shared resource can be modified by another code sequence operating concurrently....\n\n### 3. CWE-415: Double Free (Score: 156.51)\n\nThe product calls free() twice on the same memory address, potentially leading to modification of unexpected memory locations....\n\n### 4. CWE-472: External Control of Assumed-Immutable Web Parameter (Score: 55.44)\n\nThe web application does not sufficiently verify inputs that are assumed to be immutable but are actually externally controllable, such as hidden form fields....\n\n### 5. CWE-416: Use After Free (Score: 50.95)\n\nThe product reuses or references memory after it has been freed. At some point afterward, the memory may be allocated again and saved in another pointer, while the original pointer references a location somewhere within the new allocation. Any operations using the original pointer are no longer vali...\n\n\n    # Analysis Instructions\n    1. For each keyphrase, identify the most appropriate CWE(s) that represent the weakness.\n    2. Consider how the different keyphrases might relate to each other in the vulnerability chain.\n    3. Provide a final determination of primary CWE(s) and any secondary CWEs.\n    4. Format your response using the standard analysis template.\n\n    Please analyze how these different weaknesses interact and provide a comprehensive CWE classification.\n    "
  },
  "retrieval_time": 1.7415425777435303
}