{
  "cve_id": "CVE-2025-25793",
  "description": "SeaCMS v13.3 was discovered to contain a remote code execution (RCE) vulnerability via the component admin_notify.php.",
  "key_phrases": {
    "rootcause": "",
    "weakness": "",
    "impact": "remote code execution",
    "vector": "",
    "attacker": "",
    "product": "SeaCMS",
    "version": "v13.3",
    "component": "admin_notify.php"
  },
  "reference_content": null,
  "similar_info": {
    "cwe_distribution": {},
    "cwe_consensus": "",
    "similarity_stats": {
      "thresholds": [],
      "total_samples_by_threshold": {},
      "top_cwes_by_threshold": {}
    }
  },
  "similarity_summary": {
    "consensus_cwe": "",
    "top_cwes": [],
    "confidence_levels": {},
    "total_samples": 0
  },
  "analysis": "# Summary\n| CWE ID | CWE Name | Confidence | CWE Abstraction Level | CWE Vulnerability Mapping Label | CWE-Vulnerability Mapping Notes |\n|---|---|---|---|---|---|\n| CWE-94 | Improper Control of Generation of Code ('Code Injection') | 0.6 | Base | Primary | Allowed-with-Review |\n\n## Evidence and Confidence\n\n*   **Confidence Score:** 0.6\n*   **Evidence Strength:** LOW\n\n## Relationship Analysis\nThe primary relationship considered was the parent-child relationship between CWE-94 and its children (CWE-96, CWE-95, CWE-1336). While those children offer more specificity, the provided information does not allow for selecting one over the other. Thus, I opted for the parent, CWE-94.\n\n```mermaid\ngraph TD\n    cwe94[\"CWE-94: Improper Control of Generation of Code\"]\n    cwe96[\"CWE-96: Improper Neutralization of Directives in Statically Saved Code\"]\n    cwe95[\"CWE-95: Improper Neutralization of Directives in Dynamically Evaluated Code\"]\n    cwe1336[\"CWE-1336: Improper Neutralization of Special Elements Used in a Template Engine\"]\n\n    cwe96 -->|CHILDOF| cwe94\n    cwe95 -->|CHILDOF| cwe94\n    cwe1336 -->|CHILDOF| cwe94\n\n    classDef primary fill:#f96,stroke:#333,stroke-width:2px\n    classDef secondary fill:#69f,stroke:#333\n    class cwe94 primary\n    class cwe96,cwe95,cwe1336 secondary\n```\n\n## Vulnerability Chain\nThe vulnerability chain starts with **improper control of code generation** which directly leads to remote code execution.\n\n## Summary of Analysis\nThe vulnerability description indicates a remote code execution (RCE) vulnerability in SeaCMS v13.3 via the component admin_notify.php. The key phrase \"remote code execution\" suggests a weakness related to code injection. However, the provided information lacks specifics on the exact injection type.\n\nThe Retriever Results list several potential CWEs, including:\n* CWE-96: Improper Neutralization of Directives in Statically Saved Code ('Static Code Injection')\n* CWE-790: Improper Filtering of Special Elements\n* CWE-95: Improper Neutralization of Directives in Dynamically Evaluated Code ('Eval Injection')\n* CWE-78: Improper Neutralization of Special Elements used in an OS Command ('OS Command Injection')\n* CWE-434: Unrestricted Upload of File with Dangerous Type\n* CWE-1336: Improper Neutralization of Special Elements Used in a Template Engine\n* CWE-77: Improper Neutralization of Special Elements used in a Command ('Command Injection')\n* CWE-502: Deserialization of Untrusted Data\n* CWE-89: Improper Neutralization of Special Elements used in an SQL Command ('SQL Injection')\n* CWE-73: External Control of File Name or Path\n\nGiven the high-level description and the lack of specific details about the injection mechanism, I chose CWE-94 Improper Control of Generation of Code ('Code Injection') as the most appropriate primary CWE. It is a parent of other CWEs listed and it better fits the overall description. While the retriever results suggest more specific CWEs like CWE-96, CWE-95, and CWE-1336, there isn't enough evidence to select one of them.\n\nThe MITRE mapping guidance for CWE-94 suggests \"Allowed-with-Review\" and states that it is frequently misused for vulnerabilities with a technical impact of \"code execution,\" which does not by itself indicate a root cause weakness. However, given the lack of detailed information, it serves as the best starting point.\n\nRelevant CWE Information:\n\n# Enhanced Context (25 CWEs)\nThe following CWEs were identified as potentially relevant to this vulnerability:\n\n## CWE-96: Improper Neutralization of Directives in Statically Saved Code ('Static Code Injection')\n**Abstraction Level**: Base\n**Similarity Score**: 0.78\n**Source**: dense\n\n**Description**:\nThe product receives input from an upstream component, but it does not neutralize or incorrectly neutralizes code syntax before inserting the input into an executable resource, such as a library, configuration file, or template.\n\n**Mapping Guidance**:\n- Usage: Allowed\n- Rationale: This CWE entry is at the Base level of abstraction, which is a preferred level of abstraction for mapping to the root causes of vulnerabilities.\n\n## CWE-94: Improper Control of Generation of Code ('Code Injection')\n**Abstraction Level**: base\n**Similarity Score**: 2.28\n**Source**: graph\n\n**Description**:\nCWE-94: Improper Control of Generation of Code ('Code Injection')\n\n**Mapping Guidance**:\n- Usage: Allowed-with-Review\n- Rationale: This entry is frequently misused for vulnerabilities with a technical impact of \"code execution,\" which does not by itself indicate a root cause weakness, since dozens of weaknesses can enable code execution.\n\n**Relationships**:\n- CANFOLLOW -> CWE-98\n- PARENTOF -> CWE-96\n- PARENTOF -> CWE-95\n- PARENTOF -> CWE-1336\n- CHILDOF -> CWE-913",
  "analysis_with_relationships": "# Summary\n| CWE ID | CWE Name | Confidence | CWE Abstraction Level | CWE Vulnerability Mapping Label | CWE-Vulnerability Mapping Notes |\n|---|---|---|---|---|---|\n| CWE-94 | Improper Control of Generation of Code ('Code Injection') | 0.6 | Base | Primary | Allowed-with-Review |\n\n## Evidence and Confidence\n\n*   **Confidence Score:** 0.6\n*   **Evidence Strength:** LOW\n\n## Relationship Analysis\nThe primary relationship considered was the parent-child relationship between CWE-94 and its children (CWE-96, CWE-95, CWE-1336). While those children offer more specificity, the provided information does not allow for selecting one over the other. Thus, I opted for the parent, CWE-94.\n\n```mermaid\ngraph TD\n    cwe94[\"CWE-94: Improper Control of Generation of Code\"]\n    cwe96[\"CWE-96: Improper Neutralization of Directives in Statically Saved Code\"]\n    cwe95[\"CWE-95: Improper Neutralization of Directives in Dynamically Evaluated Code\"]\n    cwe1336[\"CWE-1336: Improper Neutralization of Special Elements Used in a Template Engine\"]\n\n    cwe96 -->|CHILDOF| cwe94\n    cwe95 -->|CHILDOF| cwe94\n    cwe1336 -->|CHILDOF| cwe94\n\n    classDef primary fill:#f96,stroke:#333,stroke-width:2px\n    classDef secondary fill:#69f,stroke:#333\n    class cwe94 primary\n    class cwe96,cwe95,cwe1336 secondary\n```\n\n## Vulnerability Chain\nThe vulnerability chain starts with **improper control of code generation** which directly leads to remote code execution.\n\n## Summary of Analysis\nThe vulnerability description indicates a remote code execution (RCE) vulnerability in SeaCMS v13.3 via the component admin_notify.php. The key phrase \"remote code execution\" suggests a weakness related to code injection. However, the provided information lacks specifics on the exact injection type.\n\nThe Retriever Results list several potential CWEs, including:\n* CWE-96: Improper Neutralization of Directives in Statically Saved Code ('Static Code Injection')\n* CWE-790: Improper Filtering of Special Elements\n* CWE-95: Improper Neutralization of Directives in Dynamically Evaluated Code ('Eval Injection')\n* CWE-78: Improper Neutralization of Special Elements used in an OS Command ('OS Command Injection')\n* CWE-434: Unrestricted Upload of File with Dangerous Type\n* CWE-1336: Improper Neutralization of Special Elements Used in a Template Engine\n* CWE-77: Improper Neutralization of Special Elements used in a Command ('Command Injection')\n* CWE-502: Deserialization of Untrusted Data\n* CWE-89: Improper Neutralization of Special Elements used in an SQL Command ('SQL Injection')\n* CWE-73: External Control of File Name or Path\n\nGiven the high-level description and the lack of specific details about the injection mechanism, I chose CWE-94 Improper Control of Generation of Code ('Code Injection') as the most appropriate primary CWE. It is a parent of other CWEs listed and it better fits the overall description. While the retriever results suggest more specific CWEs like CWE-96, CWE-95, and CWE-1336, there isn't enough evidence to select one of them.\n\nThe MITRE mapping guidance for CWE-94 suggests \"Allowed-with-Review\" and states that it is frequently misused for vulnerabilities with a technical impact of \"code execution,\" which does not by itself indicate a root cause weakness. However, given the lack of detailed information, it serves as the best starting point.\n\nRelevant CWE Information:\n\n# Enhanced Context (25 CWEs)\nThe following CWEs were identified as potentially relevant to this vulnerability:\n\n## CWE-96: Improper Neutralization of Directives in Statically Saved Code ('Static Code Injection')\n**Abstraction Level**: Base\n**Similarity Score**: 0.78\n**Source**: dense\n\n**Description**:\nThe product receives input from an upstream component, but it does not neutralize or incorrectly neutralizes code syntax before inserting the input into an executable resource, such as a library, configuration file, or template.\n\n**Mapping Guidance**:\n- Usage: Allowed\n- Rationale: This CWE entry is at the Base level of abstraction, which is a preferred level of abstraction for mapping to the root causes of vulnerabilities.\n\n## CWE-94: Improper Control of Generation of Code ('Code Injection')\n**Abstraction Level**: base\n**Similarity Score**: 2.28\n**Source**: graph\n\n**Description**:\nCWE-94: Improper Control of Generation of Code ('Code Injection')\n\n**Mapping Guidance**:\n- Usage: Allowed-with-Review\n- Rationale: This entry is frequently misused for vulnerabilities with a technical impact of \"code execution,\" which does not by itself indicate a root cause weakness, since dozens of weaknesses can enable code execution.\n\n**Relationships**:\n- CANFOLLOW -> CWE-98\n- PARENTOF -> CWE-96\n- PARENTOF -> CWE-95\n- PARENTOF -> CWE-1336\n- CHILDOF -> CWE-913\n\n\n## CWE Relationship Analysis\n\nCurrent CWEs represent these abstraction levels: .\n\n\n### Vulnerability Chain Analysis\n\n**Chain starting from CWE-502:**\n- 502 (Deserialization of Untrusted Data) - ROOT\n\n\n**Chain starting from CWE-89:**\n- 89 (Improper Neutralization of Special Elements used in an SQL Command ('SQL Injection')) - ROOT\n\n\n\n### CWE Relationship Diagram\n\n```mermaid\ngraph TD\n    classDef primary fill:#f96,stroke:#333,stroke-width:2px\n    classDef secondary fill:#69f,stroke:#333\n    classDef tertiary fill:#9e9,stroke:#333\n```",
  "criticism": "",
  "resolution": "",
  "relevant_cwes": [
    {
      "metadata": {
        "doc_id": "96",
        "name": "Improper Neutralization of Directives in Statically Saved Code ('Static Code Injection')",
        "source": "sparse"
      },
      "similarity": 53.18189965917822
    },
    {
      "metadata": {
        "doc_id": "790",
        "name": "Improper Filtering of Special Elements",
        "source": "sparse"
      },
      "similarity": 33.83406258639027
    },
    {
      "metadata": {
        "doc_id": "95",
        "name": "Improper Neutralization of Directives in Dynamically Evaluated Code ('Eval Injection')",
        "source": "sparse"
      },
      "similarity": 32.93288288303527
    },
    {
      "metadata": {
        "doc_id": "78",
        "name": "Improper Neutralization of Special Elements used in an OS Command ('OS Command Injection')",
        "source": "sparse"
      },
      "similarity": 32.52135770725598
    },
    {
      "metadata": {
        "doc_id": "434",
        "name": "Unrestricted Upload of File with Dangerous Type",
        "source": "sparse"
      },
      "similarity": 32.17317139644764
    },
    {
      "metadata": {
        "doc_id": "1336",
        "name": "Improper Neutralization of Special Elements Used in a Template Engine",
        "source": "sparse"
      },
      "similarity": 32.04324856390241
    },
    {
      "metadata": {
        "doc_id": "77",
        "name": "Improper Neutralization of Special Elements used in a Command ('Command Injection')",
        "source": "sparse"
      },
      "similarity": 31.62002114418649
    },
    {
      "metadata": {
        "doc_id": "502",
        "name": "Deserialization of Untrusted Data",
        "source": "sparse"
      },
      "similarity": 31.45480587941132
    },
    {
      "metadata": {
        "doc_id": "89",
        "name": "Improper Neutralization of Special Elements used in an SQL Command ('SQL Injection')",
        "type": "Base",
        "original_content": "The product constructs all or part of an SQL command using externally-influenced input from an upstream component, but it does not neutralize or incorrectly neutralizes special elements that could modify the intended SQL command when it is sent to a downstream component. Without sufficient removal or quoting of SQL syntax in user-controllable inputs, the generated SQL query can cause those inputs to be interpreted as SQL instead of ordinary user data.",
        "source": "dense",
        "mapping_notes": {
          "usage": "Allowed",
          "rationale": "This CWE entry is at the Base level of abstraction, which is a preferred level of abstraction for mapping to the root causes of vulnerabilities.",
          "comments": "Carefully read both the name and description to ensure that this mapping is an appropriate fit. Do not try to 'force' a mapping to a lower-level Base/Variant simply to comply with this preferred level of abstraction.",
          "reasons": [
            "Acceptable-Use"
          ]
        },
        "score_info": {
          "retrievers": [
            "dense",
            "graph"
          ],
          "retriever_count": 2,
          "normalized_scores": {
            "dense": 0.593624945555825,
            "graph": 1.5316999619145346
          }
        }
      },
      "similarity": 0.593624945555825
    },
    {
      "doc_id": "73",
      "text": "CWE-73: External Control of File Name or Path",
      "score": 2.2100000000000004,
      "metadata": {
        "doc_id": "73",
        "name": "External Control of File Name or Path",
        "type": "base",
        "original_content": "CWE-73: External Control of File Name or Path",
        "relationships": [
          {
            "source_id": "73",
            "target_id": "114",
            "label": "PARENTOF",
            "properties": {
              "ordinal": "Primary",
              "view_id": "1000"
            }
          },
          {
            "source_id": "73",
            "target_id": "59",
            "label": "CANPRECEDE",
            "properties": {
              "view_id": "1000"
            }
          },
          {
            "source_id": "73",
            "target_id": "434",
            "label": "CANPRECEDE",
            "properties": {
              "view_id": "1000"
            }
          },
          {
            "source_id": "73",
            "target_id": "98",
            "label": "CANPRECEDE",
            "properties": {
              "view_id": "1000"
            }
          },
          {
            "source_id": "73",
            "target_id": "41",
            "label": "CANPRECEDE",
            "properties": {
              "view_id": "1000"
            }
          },
          {
            "source_id": "73",
            "target_id": "22",
            "label": "CANPRECEDE",
            "properties": {
              "view_id": "1000"
            }
          },
          {
            "source_id": "73",
            "target_id": "20",
            "label": "CHILDOF",
            "properties": {
              "ordinal": "Primary",
              "view_id": "700"
            }
          },
          {
            "source_id": "73",
            "target_id": "610",
            "label": "CHILDOF",
            "properties": {
              "view_id": "1000"
            }
          },
          {
            "source_id": "73",
            "target_id": "642",
            "label": "CHILDOF",
            "properties": {
              "ordinal": "Primary",
              "view_id": "1000"
            }
          },
          {
            "source_id": "99",
            "target_id": "73",
            "label": "CANALSOBE",
            "properties": {
              "view_id": "1000"
            }
          },
          {
            "source_id": "98",
            "target_id": "73",
            "label": "CANFOLLOW",
            "properties": {
              "view_id": "1000"
            }
          },
          {
            "source_id": "642",
            "target_id": "73",
            "label": "PARENTOF",
            "properties": {
              "ordinal": "Primary",
              "view_id": "1000"
            }
          },
          {
            "source_id": "610",
            "target_id": "73",
            "label": "PARENTOF",
            "properties": {
              "view_id": "1000"
            }
          },
          {
            "source_id": "59",
            "target_id": "73",
            "label": "CANFOLLOW",
            "properties": {
              "view_id": "1000"
            }
          },
          {
            "source_id": "434",
            "target_id": "73",
            "label": "CANFOLLOW",
            "properties": {
              "view_id": "1000"
            }
          },
          {
            "source_id": "41",
            "target_id": "73",
            "label": "CANFOLLOW",
            "properties": {
              "view_id": "1000"
            }
          },
          {
            "source_id": "22",
            "target_id": "73",
            "label": "CANFOLLOW",
            "properties": {
              "view_id": "1000"
            }
          },
          {
            "source_id": "20",
            "target_id": "73",
            "label": "PARENTOF",
            "properties": {
              "ordinal": "Primary",
              "view_id": "700"
            }
          },
          {
            "source_id": "114",
            "target_id": "73",
            "label": "CHILDOF",
            "properties": {
              "ordinal": "Primary",
              "view_id": "1000"
            }
          }
        ],
        "score_components": {
          "relationship_chain": 1.0,
          "sequence_path": 1.0
        },
        "abstraction_factor": 1.3,
        "graph_path_info": {
          "path_types": [
            "relationship_chain",
            "vulnerability_sequence_forward",
            "vulnerability_sequence_backward"
          ],
          "best_paths": {
            "relationship_chain": {
              "path": [
                [
                  "434",
                  "73",
                  "CANFOLLOW"
                ]
              ],
              "score": 1.0,
              "type": "relationship_chain",
              "source": "434"
            },
            "vulnerability_sequence_forward": {
              "path": [
                [
                  "434",
                  "73",
                  "CANFOLLOW"
                ]
              ],
              "score": 0.9,
              "type": "vulnerability_sequence_forward",
              "source": "434"
            },
            "vulnerability_sequence_backward": {
              "path": [
                [
                  "73",
                  "434",
                  "CANPRECEDE"
                ]
              ],
              "score": 1.0,
              "type": "vulnerability_sequence_backward",
              "source": "434"
            }
          }
        },
        "position": "after",
        "sources": [
          "graph"
        ],
        "source": "graph",
        "mapping_notes": {
          "usage": "Allowed",
          "rationale": "This CWE entry is at the Base level of abstraction, which is a preferred level of abstraction for mapping to the root causes of vulnerabilities.",
          "comments": "Carefully read both the name and description to ensure that this mapping is an appropriate fit. Do not try to 'force' a mapping to a lower-level Base/Variant simply to comply with this preferred level of abstraction.",
          "reasons": [
            "Acceptable-Use"
          ]
        },
        "score_info": {
          "retrievers": [
            "graph"
          ],
          "retriever_count": 1,
          "normalized_scores": {
            "graph": 2.2100000000000004
          }
        }
      },
      "similarity": 2.2100000000000004
    }
  ],
  "identified_cwes": {
    "analyzer": [
      "CWE-502",
      "CWE-89",
      "CWE-94",
      "CWE-77",
      "CWE-73",
      "CWE-1336",
      "CWE-98",
      "CWE-790",
      "CWE-95",
      "CWE-913",
      "CWE-78",
      "CWE-96",
      "CWE-434"
    ],
    "critic_additional": []
  },
  "keyphrase_cwe_mapping": {}
}