{
  "cve_id": "CVE-2024-50061",
  "description": "In the Linux kernel, the following vulnerability has been resolved i3c master cdns Fix **use after free** vulnerability in cdns_i3c_master Driver Due to Race Condition In the cdns_i3c_master_probe function, &master->hj_work is bound with cdns_i3c_master_hj. And cdns_i3c_master_interrupt can call cnds_i3c_master_demux_ibis function to start the work. If we remove the module which will call cdns_i3c_master_remove to make cleanup, it will free master->base through i3c_master_unregister while the work mentioned above will be used. The sequence of operations that may lead to a UAF bug is as follows CPU0 CPU1 | cdns_i3c_master_hj cdns_i3c_master_remove | i3c_master_unregister(&master->base) | device_unregister(&master->dev) | device_release | //free master->base | | i3c_master_do_daa(&master->base) | //use master->base Fix it by ensuring that the work is canceled before proceeding with the cleanup in cdns_i3c_master_remove.",
  "key_phrases": {
    "rootcause": [
      "race condition",
      "use after free"
    ],
    "weakness": "",
    "impact": "",
    "vector": "",
    "attacker": "",
    "product": "Linux kernel",
    "version": "",
    "component": "cdns_i3c_master Driver"
  },
  "reference_content": "Based on the provided information, here's an analysis of the vulnerability:\n\n**Root Cause:**\nThe vulnerability stems from a race condition within the Cadence I3C master driver (`cdns_i3c_master`). Specifically, when the driver module is unloaded, the cleanup process frees the `master->base` structure while a work item (`master->hj_work`), associated with the hardware, might still be using it.\n\n**Weaknesses/Vulnerabilities Present:**\n- **Use-After-Free (UAF):** The core issue is a use-after-free vulnerability. The `master->base` is freed during module removal, but a workqueue task might still attempt to access it, leading to a crash or unpredictable behavior.\n- **Race Condition:** The vulnerability is triggered by a race condition between the module removal process (cleanup) and the execution of the work item.\n\n**Impact of Exploitation:**\n- A successful exploitation can lead to a kernel crash, due to the use of freed memory, potentially disrupting the system.\n- In some cases, it could lead to arbitrary code execution if an attacker can control the freed memory content.\n\n**Attack Vectors:**\n- **Module Unload Race:** The primary attack vector is through unloading the `cdns_i3c_master` module at a precise moment when a work item associated with the I3C master is still scheduled or running.\n\n**Required Attacker Capabilities/Position:**\n- The attacker must be able to unload kernel modules. This usually requires root privileges.\n- The attacker also needs to be able to time the unloading in such a way that the `hj_work` is running after the `master->base` has been freed.\n\n**Technical Details:**\n- The `cdns_i3c_master_probe` function initializes the work item `master->hj_work` and binds it with `cdns_i3c_master_hj`.\n- The `cdns_i3c_master_interrupt` can trigger the work item by calling `cnds_i3c_master_demux_ibis`.\n- The `cdns_i3c_master_remove` function is called during module unloading. It used to free `master->base` via `i3c_master_unregister` and other associated resources like the device struct.\n- The work item uses the `master->base` pointer.\n- If the work item is active while `cdns_i3c_master_remove` is called, `master->base` can be freed while still in use, leading to the UAF.\n- The fix involves adding `cancel_work_sync(&master->hj_work)` at the beginning of `cdns_i3c_master_remove`, ensuring that the work is cancelled before the cleanup process begins, thus preventing the UAF condition.\n\nThis vulnerability is specific to the Cadence I3C master driver and highlights the importance of proper resource management and synchronization, especially during module loading and unloading.",
  "similar_info": {
    "cwe_distribution": {},
    "cwe_consensus": "",
    "similarity_stats": {
      "thresholds": [],
      "total_samples_by_threshold": {},
      "top_cwes_by_threshold": {}
    }
  },
  "similarity_summary": {
    "consensus_cwe": "",
    "top_cwes": [],
    "confidence_levels": {},
    "total_samples": 0
  },
  "analysis": "# Summary\n| CWE ID | CWE Name | Confidence | CWE Abstraction Level | CWE Vulnerability Mapping Label | CWE-Vulnerability Mapping Notes |\n|---|---|---|---|---|---|\n| CWE-416 | Use After Free | 0.9 | Variant |  Primary | Allowed |\n| CWE-362 | Concurrent Execution using Shared Resource with Improper Synchronization ('Race Condition') | 0.8 | Class | Secondary | Allowed-with-Review |\n\n## Evidence and Confidence\n\n*   **Confidence Score:** 0.85\n*   **Evidence Strength:** HIGH\n\n## Relationship Analysis\nThe primary weakness is CWE-416 **Use After Free**, which occurs due to a **race condition**, CWE-362 Concurrent Execution using Shared Resource with Improper Synchronization ('Race Condition'). CWE-416 is a variant, while CWE-362 is a Class. The race condition allows the memory to be freed while it is still being used, leading to the use-after-free vulnerability.\n\n```mermaid\ngraph TD\n    cwe416[\"CWE-416: Use After Free\"]\n    cwe362[\"CWE-362: Concurrent Execution using Shared Resource with Improper Synchronization ('Race Condition')\"]\n    cwe119[\"CWE-119: Improper Restriction of Operations within a Memory Buffer\"]\n    cwe664[\"CWE-664: Improper Control of Stored Name\"]\n    \n    cwe416 -->|CANFOLLOW| cwe119\n    cwe416 -->|CANFOLLOW| cwe664\n    \n    classDef primary fill:#f96,stroke:#333,stroke-width:2px\n    classDef secondary fill:#69f,stroke:#333\n    classDef tertiary fill:#9e9,stroke:#333\n    class cwe416 primary\n    class cwe362 secondary\n```\n\n## Vulnerability Chain\nThe vulnerability chain starts with a **race condition** (CWE-362), which allows the `master->base` memory to be freed prematurely. Subsequently, a thread attempts to access the freed memory (`master->base`), resulting in a **use-after-free** (CWE-416) vulnerability.\n\nCWE-362 (Race Condition) -> CWE-416 (Use After Free)\n\n## Summary of Analysis\nThe vulnerability is a **use-after-free** (CWE-416) caused by a **race condition** (CWE-362) in the cdns_i3c_master driver of the Linux kernel. The provided evidence clearly states: \"Fix **use after free** vulnerability in cdns_i3c_master Driver Due to **Race Condition**\". The sequence of operations leading to the vulnerability involves a race between the `cdns_i3c_master_hj` work function and the `cdns_i3c_master_remove` function, where the latter frees the `master->base` memory while the former might still be using it. This confirms that the **use-after-free** is a direct consequence of the **race condition**.\n\nCWE-416 is chosen as the primary CWE because the vulnerability description explicitly mentions \"**use after free** vulnerability\". The description provides a clear sequence of events where the `master->base` memory is freed while a work function might still be accessing it, leading to the **use-after-free** condition. This aligns perfectly with the definition of CWE-416.\n\nCWE-362 is chosen as a secondary CWE because the **use-after-free** is triggered by a **race condition**. The vulnerability description highlights the race between the `cdns_i3c_master_hj` work function and the `cdns_i3c_master_remove` function. This race allows the memory to be freed prematurely, leading to the **use-after-free** when the work function attempts to access the freed memory. The \"Fix it by ensuring that the work is canceled before proceeding with the cleanup in cdns_i3c_master_remove.\" clearly indicates that the race condition is the underlying cause that must be addressed.\n\nOther CWEs considered but not used:\n\n*   CWE-61 (UNIX Symbolic Link (Symlink) Following): This CWE is not relevant because the vulnerability does not involve symbolic links.\n*   CWE-415 (Double Free): This CWE is not relevant because the vulnerability involves freeing memory and then using it, not freeing the same memory twice.\n*   CWE-367 (Time-of-check Time-of-use (TOCTOU) Race Condition): While a race condition is present, it is not a TOCTOU race condition where the state of a resource changes between a check and its use.\n*   CWE-667 (Improper Locking): The provided description does not explicitly mention issues with locking mechanisms.\n\n# Enhanced Context (25 CWEs)\nThe following CWEs were identified as potentially relevant to this vulnerability:\n\n## CWE-667: Improper Locking\n**Abstraction Level**: Class\n**Similarity Score**: 0.75\n**Source**: dense\n\n**Description**:\nThe product does not properly acquire or release a lock on a resource, leading to unexpected resource state changes and behaviors.\n\n**Mapping Guidance**:\n- Usage: Allowed-with-Review\n- Rationale: This CWE entry is a Class and might have Base-level children that would be more appropriate\n\n\n\n## CWE-362: Concurrent Execution using Shared Resource with Improper Synchronization ('Race Condition')\n**Abstraction Level**: Class\n**Similarity Score**: 0.74\n**Source**: dense\n\n**Description**:\nThe product contains a concurrent code sequence that requires temporary, exclusive access to a shared resource, but a timing window exists in which the shared resource can be modified by another code sequence operating concurrently.\n\n**Mapping Guidance**:\n- Usage: Allowed-with-Review\n- Rationale: This CWE entry is a Class and might have Base-level children that would be more appropriate\n\n\n\n## CWE-366: Race Condition within a Thread\n**Abstraction Level**: Base\n**Similarity Score**: 0.74\n**Source**: dense\n\n**Description**:\nIf two threads of execution use a resource simultaneously, there exists the possibility that resources may be used while invalid, in turn making the state of execution undefined.\n\n**Mapping Guidance**:\n- Usage: Allowed\n- Rationale: This CWE entry is at the Base level of abstraction, which is a preferred level of abstraction for mapping to the root causes of vulnerabilities.\n\n\n\n## CWE-367: Time-of-check Time-of-use (TOCTOU) Race Condition\n**Abstraction Level**: Base\n**Similarity Score**: 0.73\n**Source**: dense\n\n**Description**:\nThe product checks the state of a resource before using that resource, but the resource's state can change between the check and the use in a way that invalidates the results of the check. This can cause the product to perform invalid actions when the resource is in an unexpected state.\n\n**Mapping Guidance**:\n- Usage: Allowed\n- Rationale: This CWE entry is at the Base level of abstraction, which is a preferred level of abstraction for mapping to the root causes of vulnerabilities.\n\n\n\n## CWE-703: Improper Check or Handling of Exceptional Conditions\n**Abstraction Level**: Pillar\n**Similarity Score**: 0.72\n**Source**: dense\n\n**Description**:\nThe product does not properly anticipate or handle exceptional conditions that rarely occur during normal operation of the product.\n\n**Mapping Guidance**:\n- Usage: Discouraged\n- Rationale: This CWE entry is extremely high-level, a Pillar.\n\n\n\n## CWE-824: Access of Uninitialized Pointer\n**Abstraction Level**: Base\n**Similarity Score**: 0.71\n**Source**: dense\n\n**Description**:\nThe product accesses or uses a pointer that has not been initialized.\n\n**Mapping Guidance**:\n- Usage: Allowed\n- Rationale: This CWE entry is at the Base level of abstraction, which is a preferred level of abstraction for mapping to the root causes of vulnerabilities.\n\n\n\n## CWE-754: Improper Check for Unusual or Exceptional Conditions\n**Abstraction Level**: Class\n**Similarity Score**: 0.71\n**Source**: dense\n\n**Description**:\nThe product does not check or incorrectly checks for unusual or exceptional conditions that are not expected to occur frequently during day to day operation of the product.\n\n**Mapping Guidance**:\n- Usage: Allowed-with-Review\n- Rationale: This CWE entry is a Class and might have Base-level children that would be more appropriate\n\n\n\n## CWE-665: Improper Initialization\n**Abstraction Level**: Class\n**Similarity Score**: 0.71\n**Source**: dense\n\n**Description**:\nThe product does not initialize or incorrectly initializes a resource, which might leave the resource in an unexpected state when it is accessed or used.\n\n**Mapping Guidance**:\n- Usage: Discouraged\n- Rationale: This CWE entry is a level-1 Class (i.e., a child of a Pillar). It might have lower-level children that would be more appropriate\n\n\n\n## CWE-696: Incorrect Behavior Order\n**Abstraction Level**: Class\n**Similarity Score**: 0.71\n**Source**: dense\n\n**Description**:\nThe product performs multiple related behaviors, but the behaviors are performed in the wrong order in ways which may produce resultant weaknesses.\n\n**Mapping Guidance**:\n-",
  "analysis_with_relationships": "# Summary\n| CWE ID | CWE Name | Confidence | CWE Abstraction Level | CWE Vulnerability Mapping Label | CWE-Vulnerability Mapping Notes |\n|---|---|---|---|---|---|\n| CWE-416 | Use After Free | 0.9 | Variant |  Primary | Allowed |\n| CWE-362 | Concurrent Execution using Shared Resource with Improper Synchronization ('Race Condition') | 0.8 | Class | Secondary | Allowed-with-Review |\n\n## Evidence and Confidence\n\n*   **Confidence Score:** 0.85\n*   **Evidence Strength:** HIGH\n\n## Relationship Analysis\nThe primary weakness is CWE-416 **Use After Free**, which occurs due to a **race condition**, CWE-362 Concurrent Execution using Shared Resource with Improper Synchronization ('Race Condition'). CWE-416 is a variant, while CWE-362 is a Class. The race condition allows the memory to be freed while it is still being used, leading to the use-after-free vulnerability.\n\n```mermaid\ngraph TD\n    cwe416[\"CWE-416: Use After Free\"]\n    cwe362[\"CWE-362: Concurrent Execution using Shared Resource with Improper Synchronization ('Race Condition')\"]\n    cwe119[\"CWE-119: Improper Restriction of Operations within a Memory Buffer\"]\n    cwe664[\"CWE-664: Improper Control of Stored Name\"]\n    \n    cwe416 -->|CANFOLLOW| cwe119\n    cwe416 -->|CANFOLLOW| cwe664\n    \n    classDef primary fill:#f96,stroke:#333,stroke-width:2px\n    classDef secondary fill:#69f,stroke:#333\n    classDef tertiary fill:#9e9,stroke:#333\n    class cwe416 primary\n    class cwe362 secondary\n```\n\n## Vulnerability Chain\nThe vulnerability chain starts with a **race condition** (CWE-362), which allows the `master->base` memory to be freed prematurely. Subsequently, a thread attempts to access the freed memory (`master->base`), resulting in a **use-after-free** (CWE-416) vulnerability.\n\nCWE-362 (Race Condition) -> CWE-416 (Use After Free)\n\n## Summary of Analysis\nThe vulnerability is a **use-after-free** (CWE-416) caused by a **race condition** (CWE-362) in the cdns_i3c_master driver of the Linux kernel. The provided evidence clearly states: \"Fix **use after free** vulnerability in cdns_i3c_master Driver Due to **Race Condition**\". The sequence of operations leading to the vulnerability involves a race between the `cdns_i3c_master_hj` work function and the `cdns_i3c_master_remove` function, where the latter frees the `master->base` memory while the former might still be using it. This confirms that the **use-after-free** is a direct consequence of the **race condition**.\n\nCWE-416 is chosen as the primary CWE because the vulnerability description explicitly mentions \"**use after free** vulnerability\". The description provides a clear sequence of events where the `master->base` memory is freed while a work function might still be accessing it, leading to the **use-after-free** condition. This aligns perfectly with the definition of CWE-416.\n\nCWE-362 is chosen as a secondary CWE because the **use-after-free** is triggered by a **race condition**. The vulnerability description highlights the race between the `cdns_i3c_master_hj` work function and the `cdns_i3c_master_remove` function. This race allows the memory to be freed prematurely, leading to the **use-after-free** when the work function attempts to access the freed memory. The \"Fix it by ensuring that the work is canceled before proceeding with the cleanup in cdns_i3c_master_remove.\" clearly indicates that the race condition is the underlying cause that must be addressed.\n\nOther CWEs considered but not used:\n\n*   CWE-61 (UNIX Symbolic Link (Symlink) Following): This CWE is not relevant because the vulnerability does not involve symbolic links.\n*   CWE-415 (Double Free): This CWE is not relevant because the vulnerability involves freeing memory and then using it, not freeing the same memory twice.\n*   CWE-367 (Time-of-check Time-of-use (TOCTOU) Race Condition): While a race condition is present, it is not a TOCTOU race condition where the state of a resource changes between a check and its use.\n*   CWE-667 (Improper Locking): The provided description does not explicitly mention issues with locking mechanisms.\n\n# Enhanced Context (25 CWEs)\nThe following CWEs were identified as potentially relevant to this vulnerability:\n\n## CWE-667: Improper Locking\n**Abstraction Level**: Class\n**Similarity Score**: 0.75\n**Source**: dense\n\n**Description**:\nThe product does not properly acquire or release a lock on a resource, leading to unexpected resource state changes and behaviors.\n\n**Mapping Guidance**:\n- Usage: Allowed-with-Review\n- Rationale: This CWE entry is a Class and might have Base-level children that would be more appropriate\n\n\n\n## CWE-362: Concurrent Execution using Shared Resource with Improper Synchronization ('Race Condition')\n**Abstraction Level**: Class\n**Similarity Score**: 0.74\n**Source**: dense\n\n**Description**:\nThe product contains a concurrent code sequence that requires temporary, exclusive access to a shared resource, but a timing window exists in which the shared resource can be modified by another code sequence operating concurrently.\n\n**Mapping Guidance**:\n- Usage: Allowed-with-Review\n- Rationale: This CWE entry is a Class and might have Base-level children that would be more appropriate\n\n\n\n## CWE-366: Race Condition within a Thread\n**Abstraction Level**: Base\n**Similarity Score**: 0.74\n**Source**: dense\n\n**Description**:\nIf two threads of execution use a resource simultaneously, there exists the possibility that resources may be used while invalid, in turn making the state of execution undefined.\n\n**Mapping Guidance**:\n- Usage: Allowed\n- Rationale: This CWE entry is at the Base level of abstraction, which is a preferred level of abstraction for mapping to the root causes of vulnerabilities.\n\n\n\n## CWE-367: Time-of-check Time-of-use (TOCTOU) Race Condition\n**Abstraction Level**: Base\n**Similarity Score**: 0.73\n**Source**: dense\n\n**Description**:\nThe product checks the state of a resource before using that resource, but the resource's state can change between the check and the use in a way that invalidates the results of the check. This can cause the product to perform invalid actions when the resource is in an unexpected state.\n\n**Mapping Guidance**:\n- Usage: Allowed\n- Rationale: This CWE entry is at the Base level of abstraction, which is a preferred level of abstraction for mapping to the root causes of vulnerabilities.\n\n\n\n## CWE-703: Improper Check or Handling of Exceptional Conditions\n**Abstraction Level**: Pillar\n**Similarity Score**: 0.72\n**Source**: dense\n\n**Description**:\nThe product does not properly anticipate or handle exceptional conditions that rarely occur during normal operation of the product.\n\n**Mapping Guidance**:\n- Usage: Discouraged\n- Rationale: This CWE entry is extremely high-level, a Pillar.\n\n\n\n## CWE-824: Access of Uninitialized Pointer\n**Abstraction Level**: Base\n**Similarity Score**: 0.71\n**Source**: dense\n\n**Description**:\nThe product accesses or uses a pointer that has not been initialized.\n\n**Mapping Guidance**:\n- Usage: Allowed\n- Rationale: This CWE entry is at the Base level of abstraction, which is a preferred level of abstraction for mapping to the root causes of vulnerabilities.\n\n\n\n## CWE-754: Improper Check for Unusual or Exceptional Conditions\n**Abstraction Level**: Class\n**Similarity Score**: 0.71\n**Source**: dense\n\n**Description**:\nThe product does not check or incorrectly checks for unusual or exceptional conditions that are not expected to occur frequently during day to day operation of the product.\n\n**Mapping Guidance**:\n- Usage: Allowed-with-Review\n- Rationale: This CWE entry is a Class and might have Base-level children that would be more appropriate\n\n\n\n## CWE-665: Improper Initialization\n**Abstraction Level**: Class\n**Similarity Score**: 0.71\n**Source**: dense\n\n**Description**:\nThe product does not initialize or incorrectly initializes a resource, which might leave the resource in an unexpected state when it is accessed or used.\n\n**Mapping Guidance**:\n- Usage: Discouraged\n- Rationale: This CWE entry is a level-1 Class (i.e., a child of a Pillar). It might have lower-level children that would be more appropriate\n\n\n\n## CWE-696: Incorrect Behavior Order\n**Abstraction Level**: Class\n**Similarity Score**: 0.71\n**Source**: dense\n\n**Description**:\nThe product performs multiple related behaviors, but the behaviors are performed in the wrong order in ways which may produce resultant weaknesses.\n\n**Mapping Guidance**:\n-\n\n\n## CWE Relationship Analysis\n\nCurrent CWEs represent these abstraction levels: .\n\n\n### Vulnerability Chain Analysis\n\n**Chain starting from CWE-665:**\n- 665 (Improper Initialization) - ROOT\n\n\n**Chain starting from CWE-416:**\n- 416 (Use After Free) - ROOT\n\n\n\n### CWE Relationship Diagram\n\n```mermaid\ngraph TD\n    classDef primary fill:#f96,stroke:#333,stroke-width:2px\n    classDef secondary fill:#69f,stroke:#333\n    classDef tertiary fill:#9e9,stroke:#333\n```",
  "criticism": "",
  "resolution": "",
  "relevant_cwes": [
    {
      "metadata": {
        "doc_id": "362",
        "name": "Concurrent Execution using Shared Resource with Improper Synchronization ('Race Condition')",
        "source": "sparse",
        "original_content": "The product contains a concurrent code sequence that requires temporary, exclusive access to a shared resource, but a timing window exists in which the shared resource can be modified by another code sequence operating concurrently.",
        "keyphrase_sources": [
          {
            "id": "rootcause:race condition",
            "keyphrase": "race condition",
            "type": "rootcause"
          },
          {
            "id": "rootcause:use after free",
            "keyphrase": "use after free",
            "type": "rootcause"
          },
          {
            "id": "product:Linux kernel",
            "keyphrase": "Linux kernel",
            "type": "product"
          },
          {
            "id": "component:cdns_i3c_master Driver",
            "keyphrase": "cdns_i3c_master Driver",
            "type": "component"
          }
        ]
      },
      "similarity": 655.351792362623
    },
    {
      "metadata": {
        "doc_id": "61",
        "name": "UNIX Symbolic Link (Symlink) Following",
        "source": "sparse",
        "original_content": "The product, when opening a file or directory, does not sufficiently account for when the file is a symbolic link that resolves to a target outside of the intended control sphere. This could allow an attacker to cause the product to operate on unauthorized files.",
        "keyphrase_sources": [
          {
            "id": "rootcause:race condition",
            "keyphrase": "race condition",
            "type": "rootcause"
          },
          {
            "id": "rootcause:use after free",
            "keyphrase": "use after free",
            "type": "rootcause"
          },
          {
            "id": "product:Linux kernel",
            "keyphrase": "Linux kernel",
            "type": "product"
          },
          {
            "id": "component:cdns_i3c_master Driver",
            "keyphrase": "cdns_i3c_master Driver",
            "type": "component"
          }
        ]
      },
      "similarity": 605.9408383575693
    },
    {
      "metadata": {
        "doc_id": "415",
        "name": "Double Free",
        "source": "sparse",
        "original_content": "The product calls free() twice on the same memory address, potentially leading to modification of unexpected memory locations.",
        "keyphrase_sources": [
          {
            "id": "rootcause:race condition",
            "keyphrase": "race condition",
            "type": "rootcause"
          },
          {
            "id": "rootcause:use after free",
            "keyphrase": "use after free",
            "type": "rootcause"
          },
          {
            "id": "product:Linux kernel",
            "keyphrase": "Linux kernel",
            "type": "product"
          },
          {
            "id": "component:cdns_i3c_master Driver",
            "keyphrase": "cdns_i3c_master Driver",
            "type": "component"
          }
        ]
      },
      "similarity": 593.6015149623247
    },
    {
      "metadata": {
        "doc_id": "367",
        "name": "Time-of-check Time-of-use (TOCTOU) Race Condition",
        "source": "sparse",
        "original_content": "The product checks the state of a resource before using that resource, but the resource's state can change between the check and the use in a way that invalidates the results of the check. This can cause the product to perform invalid actions when the resource is in an unexpected state.",
        "keyphrase_sources": [
          {
            "id": "rootcause:race condition",
            "keyphrase": "race condition",
            "type": "rootcause"
          },
          {
            "id": "rootcause:use after free",
            "keyphrase": "use after free",
            "type": "rootcause"
          },
          {
            "id": "product:Linux kernel",
            "keyphrase": "Linux kernel",
            "type": "product"
          },
          {
            "id": "component:cdns_i3c_master Driver",
            "keyphrase": "cdns_i3c_master Driver",
            "type": "component"
          }
        ]
      },
      "similarity": 589.7740113138225
    },
    {
      "metadata": {
        "doc_id": "667",
        "name": "Improper Locking",
        "source": "sparse",
        "original_content": "The product does not properly acquire or release a lock on a resource, leading to unexpected resource state changes and behaviors.",
        "keyphrase_sources": [
          {
            "id": "rootcause:race condition",
            "keyphrase": "race condition",
            "type": "rootcause"
          },
          {
            "id": "rootcause:use after free",
            "keyphrase": "use after free",
            "type": "rootcause"
          },
          {
            "id": "product:Linux kernel",
            "keyphrase": "Linux kernel",
            "type": "product"
          },
          {
            "id": "component:cdns_i3c_master Driver",
            "keyphrase": "cdns_i3c_master Driver",
            "type": "component"
          }
        ]
      },
      "similarity": 583.7097026919848
    }
  ],
  "identified_cwes": {
    "analyzer": [
      "CWE-665",
      "CWE-416",
      "CWE-754",
      "CWE-667",
      "CWE-824",
      "CWE-362",
      "CWE-696",
      "CWE-664",
      "CWE-119",
      "CWE-366",
      "CWE-367",
      "CWE-415",
      "CWE-61",
      "CWE-703"
    ],
    "critic_additional": []
  },
  "keyphrase_cwe_mapping": {
    "362": [
      {
        "id": "rootcause:race condition",
        "keyphrase": "race condition",
        "type": "rootcause"
      },
      {
        "id": "rootcause:use after free",
        "keyphrase": "use after free",
        "type": "rootcause"
      },
      {
        "id": "product:Linux kernel",
        "keyphrase": "Linux kernel",
        "type": "product"
      },
      {
        "id": "component:cdns_i3c_master Driver",
        "keyphrase": "cdns_i3c_master Driver",
        "type": "component"
      }
    ],
    "61": [
      {
        "id": "rootcause:race condition",
        "keyphrase": "race condition",
        "type": "rootcause"
      },
      {
        "id": "rootcause:use after free",
        "keyphrase": "use after free",
        "type": "rootcause"
      },
      {
        "id": "product:Linux kernel",
        "keyphrase": "Linux kernel",
        "type": "product"
      },
      {
        "id": "component:cdns_i3c_master Driver",
        "keyphrase": "cdns_i3c_master Driver",
        "type": "component"
      }
    ],
    "415": [
      {
        "id": "rootcause:race condition",
        "keyphrase": "race condition",
        "type": "rootcause"
      },
      {
        "id": "rootcause:use after free",
        "keyphrase": "use after free",
        "type": "rootcause"
      },
      {
        "id": "product:Linux kernel",
        "keyphrase": "Linux kernel",
        "type": "product"
      },
      {
        "id": "component:cdns_i3c_master Driver",
        "keyphrase": "cdns_i3c_master Driver",
        "type": "component"
      }
    ],
    "367": [
      {
        "id": "rootcause:race condition",
        "keyphrase": "race condition",
        "type": "rootcause"
      },
      {
        "id": "rootcause:use after free",
        "keyphrase": "use after free",
        "type": "rootcause"
      },
      {
        "id": "product:Linux kernel",
        "keyphrase": "Linux kernel",
        "type": "product"
      },
      {
        "id": "component:cdns_i3c_master Driver",
        "keyphrase": "cdns_i3c_master Driver",
        "type": "component"
      }
    ],
    "667": [
      {
        "id": "rootcause:race condition",
        "keyphrase": "race condition",
        "type": "rootcause"
      },
      {
        "id": "rootcause:use after free",
        "keyphrase": "use after free",
        "type": "rootcause"
      },
      {
        "id": "product:Linux kernel",
        "keyphrase": "Linux kernel",
        "type": "product"
      },
      {
        "id": "component:cdns_i3c_master Driver",
        "keyphrase": "cdns_i3c_master Driver",
        "type": "component"
      }
    ]
  }
}