{
  "vulnerability_info": "VulnerabilityInfo(cve_id='CVE-2024-51647', description='Cross-Site Request Forgery (CSRF) vulnerability in Chaser324 Featured Posts Scroll allows Stored **XSS**.This issue affects Featured Posts Scroll from n/a through 1.25.', key_phrases={'rootcause': 'improper access control', 'weakness': ['XSS', 'cross-site request forgery'], 'impact': 'stored cross-site scripting', 'vector': '', 'attacker': '', 'product': 'Chaser324 Featured Posts Scroll', 'version': 'n/a through 1.25', 'component': ''}, reference_content='```\\n{\\n  \"Root cause of vulnerability\": \"The WordPress Featured Posts Scroll plugin is vulnerable to Cross-Site Request Forgery (CSRF).\",\\n  \"Weaknesses/vulnerabilities present\": \"Cross-Site Request Forgery (CSRF). The plugin does not properly validate requests, allowing an attacker to potentially force a logged-in user to perform unintended actions.\",\\n  \"Impact of exploitation\": \"A malicious actor could force higher privileged users to execute unwanted actions under their current authentication.\",\\n  \"Attack vectors\": \"An attacker can craft a malicious request and trick a logged-in user into executing it (e.g., via a link or embedded HTML) to perform unintended actions within the vulnerable plugin.\",\\n  \"Required attacker capabilities/position\": \"The attacker needs to be able to trick a logged-in user with sufficient privileges into clicking a malicious link or visiting a malicious page containing the crafted CSRF request.\"\\n}\\n```', similar_info={'cwe_distribution': {}, 'cwe_consensus': '', 'similarity_stats': {'thresholds': [], 'total_samples_by_threshold': {}, 'top_cwes_by_threshold': {}}}, similarity_summary=SimilarityInsight(consensus_cwe='', top_cwes=[], confidence_levels={}, total_samples=0), analysis='', analysis_with_relationships='', criticism='', resolution='', relevant_cwes=[{'metadata': {'doc_id': '918', 'name': 'Server-Side Request Forgery (SSRF)', 'source': 'sparse', 'original_content': 'The web server receives a URL or similar request from an upstream component and retrieves the contents of this URL, but it does not sufficiently ensure that the request is being sent to the expected destination.', 'keyphrase_sources': [{'id': 'weakness:cross-site request forgery', 'keyphrase': 'cross-site request forgery', 'type': 'weakness'}]}, 'similarity': np.float64(218.4317049680898)}, {'metadata': {'doc_id': '352', 'name': 'Cross-Site Request Forgery (CSRF)', 'source': 'sparse', 'original_content': 'The web application does not, or can not, sufficiently verify whether a well-formed, valid, consistent request was intentionally provided by the user who submitted the request.', 'keyphrase_sources': [{'id': 'rootcause:improper access control', 'keyphrase': 'improper access control', 'type': 'rootcause'}, {'id': 'weakness:XSS', 'keyphrase': 'XSS', 'type': 'weakness'}, {'id': 'weakness:cross-site request forgery', 'keyphrase': 'cross-site request forgery', 'type': 'weakness'}, {'id': 'impact:stored cross-site scripting', 'keyphrase': 'stored cross-site scripting', 'type': 'impact'}, {'id': 'product:Chaser324 Featured Posts Scroll', 'keyphrase': 'Chaser324 Featured Posts Scroll', 'type': 'product'}, {'id': 'version:n/a through 1.25', 'keyphrase': 'n/a through 1.25', 'type': 'version'}]}, 'similarity': np.float64(211.75349380845316)}, {'metadata': {'doc_id': '601', 'name': \"URL Redirection to Untrusted Site ('Open Redirect')\", 'source': 'sparse', 'original_content': 'The web application accepts a user-controlled input that specifies a link to an external site, and uses that link in a redirect.', 'keyphrase_sources': [{'id': 'weakness:cross-site request forgery', 'keyphrase': 'cross-site request forgery', 'type': 'weakness'}]}, 'similarity': np.float64(210.35963251368332)}, {'metadata': {'doc_id': '79', 'name': \"Improper Neutralization of Input During Web Page Generation ('Cross-site Scripting')\", 'source': 'sparse', 'original_content': 'The product does not neutralize or incorrectly neutralizes user-controllable input before it is placed in output that is used as a web page that is served to other users.', 'keyphrase_sources': [{'id': 'rootcause:improper access control', 'keyphrase': 'improper access control', 'type': 'rootcause'}, {'id': 'weakness:XSS', 'keyphrase': 'XSS', 'type': 'weakness'}, {'id': 'weakness:cross-site request forgery', 'keyphrase': 'cross-site request forgery', 'type': 'weakness'}, {'id': 'impact:stored cross-site scripting', 'keyphrase': 'stored cross-site scripting', 'type': 'impact'}, {'id': 'product:Chaser324 Featured Posts Scroll', 'keyphrase': 'Chaser324 Featured Posts Scroll', 'type': 'product'}, {'id': 'version:n/a through 1.25', 'keyphrase': 'n/a through 1.25', 'type': 'version'}]}, 'similarity': np.float64(161.32588070313324)}, {'metadata': {'doc_id': '116', 'name': 'Improper Encoding or Escaping of Output', 'source': 'sparse', 'original_content': 'The product prepares a structured message for communication with another component, but encoding or escaping of the data is either missing or done incorrectly. As a result, the intended structure of the message is not preserved.', 'keyphrase_sources': [{'id': 'rootcause:improper access control', 'keyphrase': 'improper access control', 'type': 'rootcause'}, {'id': 'weakness:XSS', 'keyphrase': 'XSS', 'type': 'weakness'}, {'id': 'impact:stored cross-site scripting', 'keyphrase': 'stored cross-site scripting', 'type': 'impact'}, {'id': 'product:Chaser324 Featured Posts Scroll', 'keyphrase': 'Chaser324 Featured Posts Scroll', 'type': 'product'}, {'id': 'version:n/a through 1.25', 'keyphrase': 'n/a through 1.25', 'type': 'version'}]}, 'similarity': np.float64(160.01506424261714)}, {'metadata': {'doc_id': '1004', 'name': \"Sensitive Cookie Without 'HttpOnly' Flag\", 'source': 'sparse', 'original_content': 'The product uses a cookie to store sensitive information, but the cookie is not marked with the HttpOnly flag.', 'keyphrase_sources': [{'id': 'rootcause:improper access control', 'keyphrase': 'improper access control', 'type': 'rootcause'}, {'id': 'weakness:XSS', 'keyphrase': 'XSS', 'type': 'weakness'}, {'id': 'impact:stored cross-site scripting', 'keyphrase': 'stored cross-site scripting', 'type': 'impact'}]}, 'similarity': np.float64(148.75178485095134)}, {'metadata': {'doc_id': '89', 'name': \"Improper Neutralization of Special Elements used in an SQL Command ('SQL Injection')\", 'source': 'sparse', 'original_content': 'The product constructs all or part of an SQL command using externally-influenced input from an upstream component, but it does not neutralize or incorrectly neutralizes special elements that could modify the intended SQL command when it is sent to a downstream component. Without sufficient removal or quoting of SQL syntax in user-controllable inputs, the generated SQL query can cause those inputs to be interpreted as SQL instead of ordinary user data.', 'keyphrase_sources': [{'id': 'rootcause:improper access control', 'keyphrase': 'improper access control', 'type': 'rootcause'}, {'id': 'weakness:cross-site request forgery', 'keyphrase': 'cross-site request forgery', 'type': 'weakness'}]}, 'similarity': np.float64(147.16899774127148)}, {'metadata': {'doc_id': '80', 'name': 'Improper Neutralization of Script-Related HTML Tags in a Web Page (Basic XSS)', 'source': 'sparse', 'original_content': 'The product receives input from an upstream component, but it does not neutralize or incorrectly neutralizes special characters such as \"<\", \">\", and \"&\" that could be interpreted as web-scripting elements when they are sent to a downstream component that processes web pages.', 'keyphrase_sources': [{'id': 'weakness:XSS', 'keyphrase': 'XSS', 'type': 'weakness'}, {'id': 'impact:stored cross-site scripting', 'keyphrase': 'stored cross-site scripting', 'type': 'impact'}]}, 'similarity': np.float64(138.59295500868797)}, {'metadata': {'doc_id': '434', 'name': 'Unrestricted Upload of File with Dangerous Type', 'source': 'sparse', 'original_content': 'The product allows the upload or transfer of dangerous file types that are automatically processed within its environment.', 'keyphrase_sources': [{'id': 'version:n/a through 1.25', 'keyphrase': 'n/a through 1.25', 'type': 'version'}]}, 'similarity': np.float64(59.63217181493006)}, {'metadata': {'doc_id': '22', 'name': \"Improper Limitation of a Pathname to a Restricted Directory ('Path Traversal')\", 'source': 'sparse', 'original_content': 'The product uses external input to construct a pathname that is intended to identify a file or directory that is located underneath a restricted parent directory, but the product does not properly neutralize special elements within the pathname that can cause the pathname to resolve to a location that is outside of the restricted directory.', 'keyphrase_sources': [{'id': 'version:n/a through 1.25', 'keyphrase': 'n/a through 1.25', 'type': 'version'}]}, 'similarity': np.float64(57.475904316174635)}, {'metadata': {'doc_id': '453', 'name': 'Insecure Default Variable Initialization', 'source': 'sparse', 'original_content': 'The product, by default, initializes an internal variable with an insecure or less secure value than is possible.', 'keyphrase_sources': [{'id': 'product:Chaser324 Featured Posts Scroll', 'keyphrase': 'Chaser324 Featured Posts Scroll', 'type': 'product'}]}, 'similarity': np.float64(51.69660964038647)}, {'metadata': {'doc_id': '201', 'name': 'Insertion of Sensitive Information Into Sent Data', 'source': 'sparse', 'original_content': 'The code transmits data to another actor, but a portion of the data includes sensitive information that should not be accessible to that actor.', 'keyphrase_sources': [{'id': 'product:Chaser324 Featured Posts Scroll', 'keyphrase': 'Chaser324 Featured Posts Scroll', 'type': 'product'}]}, 'similarity': np.float64(44.46617621343377)}], identified_cwes={'analyzer': [], 'critic_additional': []})",
  "retrieval_results": {
    "has_multiple_keyphrases": true,
    "keyphrase_cwe_sets": {
      "rootcause:improper access control": {
        "keyphrase": "improper access control",
        "type": "rootcause",
        "cwes": [
          {
            "metadata": {
              "doc_id": "352",
              "name": "Cross-Site Request Forgery (CSRF)",
              "source": "sparse",
              "original_content": "The web application does not, or can not, sufficiently verify whether a well-formed, valid, consistent request was intentionally provided by the user who submitted the request.",
              "keyphrase_sources": [
                {
                  "id": "rootcause:improper access control",
                  "keyphrase": "improper access control",
                  "type": "rootcause"
                },
                {
                  "id": "weakness:XSS",
                  "keyphrase": "XSS",
                  "type": "weakness"
                },
                {
                  "id": "weakness:cross-site request forgery",
                  "keyphrase": "cross-site request forgery",
                  "type": "weakness"
                },
                {
                  "id": "impact:stored cross-site scripting",
                  "keyphrase": "stored cross-site scripting",
                  "type": "impact"
                },
                {
                  "id": "product:Chaser324 Featured Posts Scroll",
                  "keyphrase": "Chaser324 Featured Posts Scroll",
                  "type": "product"
                },
                {
                  "id": "version:n/a through 1.25",
                  "keyphrase": "n/a through 1.25",
                  "type": "version"
                }
              ]
            },
            "similarity": 211.75349380845316
          },
          {
            "metadata": {
              "doc_id": "79",
              "name": "Improper Neutralization of Input During Web Page Generation ('Cross-site Scripting')",
              "source": "sparse",
              "original_content": "The product does not neutralize or incorrectly neutralizes user-controllable input before it is placed in output that is used as a web page that is served to other users.",
              "keyphrase_sources": [
                {
                  "id": "rootcause:improper access control",
                  "keyphrase": "improper access control",
                  "type": "rootcause"
                },
                {
                  "id": "weakness:XSS",
                  "keyphrase": "XSS",
                  "type": "weakness"
                },
                {
                  "id": "weakness:cross-site request forgery",
                  "keyphrase": "cross-site request forgery",
                  "type": "weakness"
                },
                {
                  "id": "impact:stored cross-site scripting",
                  "keyphrase": "stored cross-site scripting",
                  "type": "impact"
                },
                {
                  "id": "product:Chaser324 Featured Posts Scroll",
                  "keyphrase": "Chaser324 Featured Posts Scroll",
                  "type": "product"
                },
                {
                  "id": "version:n/a through 1.25",
                  "keyphrase": "n/a through 1.25",
                  "type": "version"
                }
              ]
            },
            "similarity": 161.32588070313324
          },
          {
            "metadata": {
              "doc_id": "116",
              "name": "Improper Encoding or Escaping of Output",
              "source": "sparse",
              "original_content": "The product prepares a structured message for communication with another component, but encoding or escaping of the data is either missing or done incorrectly. As a result, the intended structure of the message is not preserved.",
              "keyphrase_sources": [
                {
                  "id": "rootcause:improper access control",
                  "keyphrase": "improper access control",
                  "type": "rootcause"
                },
                {
                  "id": "weakness:XSS",
                  "keyphrase": "XSS",
                  "type": "weakness"
                },
                {
                  "id": "impact:stored cross-site scripting",
                  "keyphrase": "stored cross-site scripting",
                  "type": "impact"
                },
                {
                  "id": "product:Chaser324 Featured Posts Scroll",
                  "keyphrase": "Chaser324 Featured Posts Scroll",
                  "type": "product"
                },
                {
                  "id": "version:n/a through 1.25",
                  "keyphrase": "n/a through 1.25",
                  "type": "version"
                }
              ]
            },
            "similarity": 160.01506424261714
          },
          {
            "metadata": {
              "doc_id": "1004",
              "name": "Sensitive Cookie Without 'HttpOnly' Flag",
              "source": "sparse",
              "original_content": "The product uses a cookie to store sensitive information, but the cookie is not marked with the HttpOnly flag.",
              "keyphrase_sources": [
                {
                  "id": "rootcause:improper access control",
                  "keyphrase": "improper access control",
                  "type": "rootcause"
                },
                {
                  "id": "weakness:XSS",
                  "keyphrase": "XSS",
                  "type": "weakness"
                },
                {
                  "id": "impact:stored cross-site scripting",
                  "keyphrase": "stored cross-site scripting",
                  "type": "impact"
                }
              ]
            },
            "similarity": 148.75178485095134
          },
          {
            "metadata": {
              "doc_id": "89",
              "name": "Improper Neutralization of Special Elements used in an SQL Command ('SQL Injection')",
              "source": "sparse",
              "original_content": "The product constructs all or part of an SQL command using externally-influenced input from an upstream component, but it does not neutralize or incorrectly neutralizes special elements that could modify the intended SQL command when it is sent to a downstream component. Without sufficient removal or quoting of SQL syntax in user-controllable inputs, the generated SQL query can cause those inputs to be interpreted as SQL instead of ordinary user data.",
              "keyphrase_sources": [
                {
                  "id": "rootcause:improper access control",
                  "keyphrase": "improper access control",
                  "type": "rootcause"
                },
                {
                  "id": "weakness:cross-site request forgery",
                  "keyphrase": "cross-site request forgery",
                  "type": "weakness"
                }
              ]
            },
            "similarity": 147.16899774127148
          }
        ]
      },
      "weakness:XSS": {
        "keyphrase": "XSS",
        "type": "weakness",
        "cwes": [
          {
            "metadata": {
              "doc_id": "352",
              "name": "Cross-Site Request Forgery (CSRF)",
              "source": "sparse",
              "original_content": "The web application does not, or can not, sufficiently verify whether a well-formed, valid, consistent request was intentionally provided by the user who submitted the request."
            },
            "similarity": 208.80897789709798
          },
          {
            "metadata": {
              "doc_id": "79",
              "name": "Improper Neutralization of Input During Web Page Generation ('Cross-site Scripting')",
              "source": "sparse",
              "original_content": "The product does not neutralize or incorrectly neutralizes user-controllable input before it is placed in output that is used as a web page that is served to other users."
            },
            "similarity": 161.76336016343132
          },
          {
            "metadata": {
              "doc_id": "116",
              "name": "Improper Encoding or Escaping of Output",
              "source": "sparse",
              "original_content": "The product prepares a structured message for communication with another component, but encoding or escaping of the data is either missing or done incorrectly. As a result, the intended structure of the message is not preserved."
            },
            "similarity": 153.9452543142194
          },
          {
            "metadata": {
              "doc_id": "1004",
              "name": "Sensitive Cookie Without 'HttpOnly' Flag",
              "source": "sparse",
              "original_content": "The product uses a cookie to store sensitive information, but the cookie is not marked with the HttpOnly flag."
            },
            "similarity": 144.05521142279477
          },
          {
            "metadata": {
              "doc_id": "80",
              "name": "Improper Neutralization of Script-Related HTML Tags in a Web Page (Basic XSS)",
              "source": "sparse",
              "original_content": "The product receives input from an upstream component, but it does not neutralize or incorrectly neutralizes special characters such as \"<\", \">\", and \"&\" that could be interpreted as web-scripting elements when they are sent to a downstream component that processes web pages.",
              "keyphrase_sources": [
                {
                  "id": "weakness:XSS",
                  "keyphrase": "XSS",
                  "type": "weakness"
                },
                {
                  "id": "impact:stored cross-site scripting",
                  "keyphrase": "stored cross-site scripting",
                  "type": "impact"
                }
              ]
            },
            "similarity": 138.59295500868797
          }
        ]
      },
      "weakness:cross-site request forgery": {
        "keyphrase": "cross-site request forgery",
        "type": "weakness",
        "cwes": [
          {
            "metadata": {
              "doc_id": "352",
              "name": "Cross-Site Request Forgery (CSRF)",
              "source": "sparse",
              "original_content": "The web application does not, or can not, sufficiently verify whether a well-formed, valid, consistent request was intentionally provided by the user who submitted the request."
            },
            "similarity": 294.9887275104158
          },
          {
            "metadata": {
              "doc_id": "89",
              "name": "Improper Neutralization of Special Elements used in an SQL Command ('SQL Injection')",
              "source": "sparse",
              "original_content": "The product constructs all or part of an SQL command using externally-influenced input from an upstream component, but it does not neutralize or incorrectly neutralizes special elements that could modify the intended SQL command when it is sent to a downstream component. Without sufficient removal or quoting of SQL syntax in user-controllable inputs, the generated SQL query can cause those inputs to be interpreted as SQL instead of ordinary user data."
            },
            "similarity": 226.0779029516251
          },
          {
            "metadata": {
              "doc_id": "918",
              "name": "Server-Side Request Forgery (SSRF)",
              "source": "sparse",
              "original_content": "The web server receives a URL or similar request from an upstream component and retrieves the contents of this URL, but it does not sufficiently ensure that the request is being sent to the expected destination.",
              "keyphrase_sources": [
                {
                  "id": "weakness:cross-site request forgery",
                  "keyphrase": "cross-site request forgery",
                  "type": "weakness"
                }
              ]
            },
            "similarity": 218.4317049680898
          },
          {
            "metadata": {
              "doc_id": "601",
              "name": "URL Redirection to Untrusted Site ('Open Redirect')",
              "source": "sparse",
              "original_content": "The web application accepts a user-controlled input that specifies a link to an external site, and uses that link in a redirect.",
              "keyphrase_sources": [
                {
                  "id": "weakness:cross-site request forgery",
                  "keyphrase": "cross-site request forgery",
                  "type": "weakness"
                }
              ]
            },
            "similarity": 210.35963251368332
          },
          {
            "metadata": {
              "doc_id": "79",
              "name": "Improper Neutralization of Input During Web Page Generation ('Cross-site Scripting')",
              "source": "sparse",
              "original_content": "The product does not neutralize or incorrectly neutralizes user-controllable input before it is placed in output that is used as a web page that is served to other users."
            },
            "similarity": 204.563742143439
          }
        ]
      },
      "impact:stored cross-site scripting": {
        "keyphrase": "stored cross-site scripting",
        "type": "impact",
        "cwes": [
          {
            "metadata": {
              "doc_id": "352",
              "name": "Cross-Site Request Forgery (CSRF)",
              "source": "sparse",
              "original_content": "The web application does not, or can not, sufficiently verify whether a well-formed, valid, consistent request was intentionally provided by the user who submitted the request."
            },
            "similarity": 106.99187428576576
          },
          {
            "metadata": {
              "doc_id": "79",
              "name": "Improper Neutralization of Input During Web Page Generation ('Cross-site Scripting')",
              "source": "sparse",
              "original_content": "The product does not neutralize or incorrectly neutralizes user-controllable input before it is placed in output that is used as a web page that is served to other users."
            },
            "similarity": 85.9113837655622
          },
          {
            "metadata": {
              "doc_id": "116",
              "name": "Improper Encoding or Escaping of Output",
              "source": "sparse",
              "original_content": "The product prepares a structured message for communication with another component, but encoding or escaping of the data is either missing or done incorrectly. As a result, the intended structure of the message is not preserved."
            },
            "similarity": 78.49668539128461
          },
          {
            "metadata": {
              "doc_id": "80",
              "name": "Improper Neutralization of Script-Related HTML Tags in a Web Page (Basic XSS)",
              "source": "sparse",
              "original_content": "The product receives input from an upstream component, but it does not neutralize or incorrectly neutralizes special characters such as \"<\", \">\", and \"&\" that could be interpreted as web-scripting elements when they are sent to a downstream component that processes web pages."
            },
            "similarity": 75.66419228921214
          },
          {
            "metadata": {
              "doc_id": "1004",
              "name": "Sensitive Cookie Without 'HttpOnly' Flag",
              "source": "sparse",
              "original_content": "The product uses a cookie to store sensitive information, but the cookie is not marked with the HttpOnly flag."
            },
            "similarity": 70.75486390377706
          }
        ]
      },
      "product:Chaser324 Featured Posts Scroll": {
        "keyphrase": "Chaser324 Featured Posts Scroll",
        "type": "product",
        "cwes": [
          {
            "metadata": {
              "doc_id": "352",
              "name": "Cross-Site Request Forgery (CSRF)",
              "source": "sparse",
              "original_content": "The web application does not, or can not, sufficiently verify whether a well-formed, valid, consistent request was intentionally provided by the user who submitted the request."
            },
            "similarity": 76.36967915015015
          },
          {
            "metadata": {
              "doc_id": "116",
              "name": "Improper Encoding or Escaping of Output",
              "source": "sparse",
              "original_content": "The product prepares a structured message for communication with another component, but encoding or escaping of the data is either missing or done incorrectly. As a result, the intended structure of the message is not preserved."
            },
            "similarity": 52.68713369873029
          },
          {
            "metadata": {
              "doc_id": "453",
              "name": "Insecure Default Variable Initialization",
              "source": "sparse",
              "original_content": "The product, by default, initializes an internal variable with an insecure or less secure value than is possible.",
              "keyphrase_sources": [
                {
                  "id": "product:Chaser324 Featured Posts Scroll",
                  "keyphrase": "Chaser324 Featured Posts Scroll",
                  "type": "product"
                }
              ]
            },
            "similarity": 51.69660964038647
          },
          {
            "metadata": {
              "doc_id": "79",
              "name": "Improper Neutralization of Input During Web Page Generation ('Cross-site Scripting')",
              "source": "sparse",
              "original_content": "The product does not neutralize or incorrectly neutralizes user-controllable input before it is placed in output that is used as a web page that is served to other users."
            },
            "similarity": 49.6816584203644
          },
          {
            "metadata": {
              "doc_id": "201",
              "name": "Insertion of Sensitive Information Into Sent Data",
              "source": "sparse",
              "original_content": "The code transmits data to another actor, but a portion of the data includes sensitive information that should not be accessible to that actor.",
              "keyphrase_sources": [
                {
                  "id": "product:Chaser324 Featured Posts Scroll",
                  "keyphrase": "Chaser324 Featured Posts Scroll",
                  "type": "product"
                }
              ]
            },
            "similarity": 44.46617621343377
          }
        ]
      },
      "version:n/a through 1.25": {
        "keyphrase": "n/a through 1.25",
        "type": "version",
        "cwes": [
          {
            "metadata": {
              "doc_id": "352",
              "name": "Cross-Site Request Forgery (CSRF)",
              "source": "sparse",
              "original_content": "The web application does not, or can not, sufficiently verify whether a well-formed, valid, consistent request was intentionally provided by the user who submitted the request."
            },
            "similarity": 78.59286592018685
          },
          {
            "metadata": {
              "doc_id": "79",
              "name": "Improper Neutralization of Input During Web Page Generation ('Cross-site Scripting')",
              "source": "sparse",
              "original_content": "The product does not neutralize or incorrectly neutralizes user-controllable input before it is placed in output that is used as a web page that is served to other users."
            },
            "similarity": 59.84928304354962
          },
          {
            "metadata": {
              "doc_id": "434",
              "name": "Unrestricted Upload of File with Dangerous Type",
              "source": "sparse",
              "original_content": "The product allows the upload or transfer of dangerous file types that are automatically processed within its environment.",
              "keyphrase_sources": [
                {
                  "id": "version:n/a through 1.25",
                  "keyphrase": "n/a through 1.25",
                  "type": "version"
                }
              ]
            },
            "similarity": 59.63217181493006
          },
          {
            "metadata": {
              "doc_id": "116",
              "name": "Improper Encoding or Escaping of Output",
              "source": "sparse",
              "original_content": "The product prepares a structured message for communication with another component, but encoding or escaping of the data is either missing or done incorrectly. As a result, the intended structure of the message is not preserved."
            },
            "similarity": 57.990220509046495
          },
          {
            "metadata": {
              "doc_id": "22",
              "name": "Improper Limitation of a Pathname to a Restricted Directory ('Path Traversal')",
              "source": "sparse",
              "original_content": "The product uses external input to construct a pathname that is intended to identify a file or directory that is located underneath a restricted parent directory, but the product does not properly neutralize special elements within the pathname that can cause the pathname to resolve to a location that is outside of the restricted directory.",
              "keyphrase_sources": [
                {
                  "id": "version:n/a through 1.25",
                  "keyphrase": "n/a through 1.25",
                  "type": "version"
                }
              ]
            },
            "similarity": 57.475904316174635
          }
        ]
      }
    },
    "keyphrase_mapping": {
      "352": [
        {
          "id": "rootcause:improper access control",
          "keyphrase": "improper access control",
          "type": "rootcause"
        },
        {
          "id": "weakness:XSS",
          "keyphrase": "XSS",
          "type": "weakness"
        },
        {
          "id": "weakness:cross-site request forgery",
          "keyphrase": "cross-site request forgery",
          "type": "weakness"
        },
        {
          "id": "impact:stored cross-site scripting",
          "keyphrase": "stored cross-site scripting",
          "type": "impact"
        },
        {
          "id": "product:Chaser324 Featured Posts Scroll",
          "keyphrase": "Chaser324 Featured Posts Scroll",
          "type": "product"
        },
        {
          "id": "version:n/a through 1.25",
          "keyphrase": "n/a through 1.25",
          "type": "version"
        }
      ],
      "79": [
        {
          "id": "rootcause:improper access control",
          "keyphrase": "improper access control",
          "type": "rootcause"
        },
        {
          "id": "weakness:XSS",
          "keyphrase": "XSS",
          "type": "weakness"
        },
        {
          "id": "weakness:cross-site request forgery",
          "keyphrase": "cross-site request forgery",
          "type": "weakness"
        },
        {
          "id": "impact:stored cross-site scripting",
          "keyphrase": "stored cross-site scripting",
          "type": "impact"
        },
        {
          "id": "product:Chaser324 Featured Posts Scroll",
          "keyphrase": "Chaser324 Featured Posts Scroll",
          "type": "product"
        },
        {
          "id": "version:n/a through 1.25",
          "keyphrase": "n/a through 1.25",
          "type": "version"
        }
      ],
      "116": [
        {
          "id": "rootcause:improper access control",
          "keyphrase": "improper access control",
          "type": "rootcause"
        },
        {
          "id": "weakness:XSS",
          "keyphrase": "XSS",
          "type": "weakness"
        },
        {
          "id": "impact:stored cross-site scripting",
          "keyphrase": "stored cross-site scripting",
          "type": "impact"
        },
        {
          "id": "product:Chaser324 Featured Posts Scroll",
          "keyphrase": "Chaser324 Featured Posts Scroll",
          "type": "product"
        },
        {
          "id": "version:n/a through 1.25",
          "keyphrase": "n/a through 1.25",
          "type": "version"
        }
      ],
      "1004": [
        {
          "id": "rootcause:improper access control",
          "keyphrase": "improper access control",
          "type": "rootcause"
        },
        {
          "id": "weakness:XSS",
          "keyphrase": "XSS",
          "type": "weakness"
        },
        {
          "id": "impact:stored cross-site scripting",
          "keyphrase": "stored cross-site scripting",
          "type": "impact"
        }
      ],
      "89": [
        {
          "id": "rootcause:improper access control",
          "keyphrase": "improper access control",
          "type": "rootcause"
        },
        {
          "id": "weakness:cross-site request forgery",
          "keyphrase": "cross-site request forgery",
          "type": "weakness"
        }
      ],
      "80": [
        {
          "id": "weakness:XSS",
          "keyphrase": "XSS",
          "type": "weakness"
        },
        {
          "id": "impact:stored cross-site scripting",
          "keyphrase": "stored cross-site scripting",
          "type": "impact"
        }
      ],
      "918": [
        {
          "id": "weakness:cross-site request forgery",
          "keyphrase": "cross-site request forgery",
          "type": "weakness"
        }
      ],
      "601": [
        {
          "id": "weakness:cross-site request forgery",
          "keyphrase": "cross-site request forgery",
          "type": "weakness"
        }
      ],
      "453": [
        {
          "id": "product:Chaser324 Featured Posts Scroll",
          "keyphrase": "Chaser324 Featured Posts Scroll",
          "type": "product"
        }
      ],
      "201": [
        {
          "id": "product:Chaser324 Featured Posts Scroll",
          "keyphrase": "Chaser324 Featured Posts Scroll",
          "type": "product"
        }
      ],
      "434": [
        {
          "id": "version:n/a through 1.25",
          "keyphrase": "n/a through 1.25",
          "type": "version"
        }
      ],
      "22": [
        {
          "id": "version:n/a through 1.25",
          "keyphrase": "n/a through 1.25",
          "type": "version"
        }
      ]
    },
    "relevant_cwes": [
      {
        "metadata": {
          "doc_id": "918",
          "name": "Server-Side Request Forgery (SSRF)",
          "source": "sparse",
          "original_content": "The web server receives a URL or similar request from an upstream component and retrieves the contents of this URL, but it does not sufficiently ensure that the request is being sent to the expected destination.",
          "keyphrase_sources": [
            {
              "id": "weakness:cross-site request forgery",
              "keyphrase": "cross-site request forgery",
              "type": "weakness"
            }
          ]
        },
        "similarity": 218.4317049680898
      },
      {
        "metadata": {
          "doc_id": "352",
          "name": "Cross-Site Request Forgery (CSRF)",
          "source": "sparse",
          "original_content": "The web application does not, or can not, sufficiently verify whether a well-formed, valid, consistent request was intentionally provided by the user who submitted the request.",
          "keyphrase_sources": [
            {
              "id": "rootcause:improper access control",
              "keyphrase": "improper access control",
              "type": "rootcause"
            },
            {
              "id": "weakness:XSS",
              "keyphrase": "XSS",
              "type": "weakness"
            },
            {
              "id": "weakness:cross-site request forgery",
              "keyphrase": "cross-site request forgery",
              "type": "weakness"
            },
            {
              "id": "impact:stored cross-site scripting",
              "keyphrase": "stored cross-site scripting",
              "type": "impact"
            },
            {
              "id": "product:Chaser324 Featured Posts Scroll",
              "keyphrase": "Chaser324 Featured Posts Scroll",
              "type": "product"
            },
            {
              "id": "version:n/a through 1.25",
              "keyphrase": "n/a through 1.25",
              "type": "version"
            }
          ]
        },
        "similarity": 211.75349380845316
      },
      {
        "metadata": {
          "doc_id": "601",
          "name": "URL Redirection to Untrusted Site ('Open Redirect')",
          "source": "sparse",
          "original_content": "The web application accepts a user-controlled input that specifies a link to an external site, and uses that link in a redirect.",
          "keyphrase_sources": [
            {
              "id": "weakness:cross-site request forgery",
              "keyphrase": "cross-site request forgery",
              "type": "weakness"
            }
          ]
        },
        "similarity": 210.35963251368332
      },
      {
        "metadata": {
          "doc_id": "79",
          "name": "Improper Neutralization of Input During Web Page Generation ('Cross-site Scripting')",
          "source": "sparse",
          "original_content": "The product does not neutralize or incorrectly neutralizes user-controllable input before it is placed in output that is used as a web page that is served to other users.",
          "keyphrase_sources": [
            {
              "id": "rootcause:improper access control",
              "keyphrase": "improper access control",
              "type": "rootcause"
            },
            {
              "id": "weakness:XSS",
              "keyphrase": "XSS",
              "type": "weakness"
            },
            {
              "id": "weakness:cross-site request forgery",
              "keyphrase": "cross-site request forgery",
              "type": "weakness"
            },
            {
              "id": "impact:stored cross-site scripting",
              "keyphrase": "stored cross-site scripting",
              "type": "impact"
            },
            {
              "id": "product:Chaser324 Featured Posts Scroll",
              "keyphrase": "Chaser324 Featured Posts Scroll",
              "type": "product"
            },
            {
              "id": "version:n/a through 1.25",
              "keyphrase": "n/a through 1.25",
              "type": "version"
            }
          ]
        },
        "similarity": 161.32588070313324
      },
      {
        "metadata": {
          "doc_id": "116",
          "name": "Improper Encoding or Escaping of Output",
          "source": "sparse",
          "original_content": "The product prepares a structured message for communication with another component, but encoding or escaping of the data is either missing or done incorrectly. As a result, the intended structure of the message is not preserved.",
          "keyphrase_sources": [
            {
              "id": "rootcause:improper access control",
              "keyphrase": "improper access control",
              "type": "rootcause"
            },
            {
              "id": "weakness:XSS",
              "keyphrase": "XSS",
              "type": "weakness"
            },
            {
              "id": "impact:stored cross-site scripting",
              "keyphrase": "stored cross-site scripting",
              "type": "impact"
            },
            {
              "id": "product:Chaser324 Featured Posts Scroll",
              "keyphrase": "Chaser324 Featured Posts Scroll",
              "type": "product"
            },
            {
              "id": "version:n/a through 1.25",
              "keyphrase": "n/a through 1.25",
              "type": "version"
            }
          ]
        },
        "similarity": 160.01506424261714
      },
      {
        "metadata": {
          "doc_id": "1004",
          "name": "Sensitive Cookie Without 'HttpOnly' Flag",
          "source": "sparse",
          "original_content": "The product uses a cookie to store sensitive information, but the cookie is not marked with the HttpOnly flag.",
          "keyphrase_sources": [
            {
              "id": "rootcause:improper access control",
              "keyphrase": "improper access control",
              "type": "rootcause"
            },
            {
              "id": "weakness:XSS",
              "keyphrase": "XSS",
              "type": "weakness"
            },
            {
              "id": "impact:stored cross-site scripting",
              "keyphrase": "stored cross-site scripting",
              "type": "impact"
            }
          ]
        },
        "similarity": 148.75178485095134
      },
      {
        "metadata": {
          "doc_id": "89",
          "name": "Improper Neutralization of Special Elements used in an SQL Command ('SQL Injection')",
          "source": "sparse",
          "original_content": "The product constructs all or part of an SQL command using externally-influenced input from an upstream component, but it does not neutralize or incorrectly neutralizes special elements that could modify the intended SQL command when it is sent to a downstream component. Without sufficient removal or quoting of SQL syntax in user-controllable inputs, the generated SQL query can cause those inputs to be interpreted as SQL instead of ordinary user data.",
          "keyphrase_sources": [
            {
              "id": "rootcause:improper access control",
              "keyphrase": "improper access control",
              "type": "rootcause"
            },
            {
              "id": "weakness:cross-site request forgery",
              "keyphrase": "cross-site request forgery",
              "type": "weakness"
            }
          ]
        },
        "similarity": 147.16899774127148
      },
      {
        "metadata": {
          "doc_id": "80",
          "name": "Improper Neutralization of Script-Related HTML Tags in a Web Page (Basic XSS)",
          "source": "sparse",
          "original_content": "The product receives input from an upstream component, but it does not neutralize or incorrectly neutralizes special characters such as \"<\", \">\", and \"&\" that could be interpreted as web-scripting elements when they are sent to a downstream component that processes web pages.",
          "keyphrase_sources": [
            {
              "id": "weakness:XSS",
              "keyphrase": "XSS",
              "type": "weakness"
            },
            {
              "id": "impact:stored cross-site scripting",
              "keyphrase": "stored cross-site scripting",
              "type": "impact"
            }
          ]
        },
        "similarity": 138.59295500868797
      },
      {
        "metadata": {
          "doc_id": "434",
          "name": "Unrestricted Upload of File with Dangerous Type",
          "source": "sparse",
          "original_content": "The product allows the upload or transfer of dangerous file types that are automatically processed within its environment.",
          "keyphrase_sources": [
            {
              "id": "version:n/a through 1.25",
              "keyphrase": "n/a through 1.25",
              "type": "version"
            }
          ]
        },
        "similarity": 59.63217181493006
      },
      {
        "metadata": {
          "doc_id": "22",
          "name": "Improper Limitation of a Pathname to a Restricted Directory ('Path Traversal')",
          "source": "sparse",
          "original_content": "The product uses external input to construct a pathname that is intended to identify a file or directory that is located underneath a restricted parent directory, but the product does not properly neutralize special elements within the pathname that can cause the pathname to resolve to a location that is outside of the restricted directory.",
          "keyphrase_sources": [
            {
              "id": "version:n/a through 1.25",
              "keyphrase": "n/a through 1.25",
              "type": "version"
            }
          ]
        },
        "similarity": 57.475904316174635
      },
      {
        "metadata": {
          "doc_id": "453",
          "name": "Insecure Default Variable Initialization",
          "source": "sparse",
          "original_content": "The product, by default, initializes an internal variable with an insecure or less secure value than is possible.",
          "keyphrase_sources": [
            {
              "id": "product:Chaser324 Featured Posts Scroll",
              "keyphrase": "Chaser324 Featured Posts Scroll",
              "type": "product"
            }
          ]
        },
        "similarity": 51.69660964038647
      },
      {
        "metadata": {
          "doc_id": "201",
          "name": "Insertion of Sensitive Information Into Sent Data",
          "source": "sparse",
          "original_content": "The code transmits data to another actor, but a portion of the data includes sensitive information that should not be accessible to that actor.",
          "keyphrase_sources": [
            {
              "id": "product:Chaser324 Featured Posts Scroll",
              "keyphrase": "Chaser324 Featured Posts Scroll",
              "type": "product"
            }
          ]
        },
        "similarity": 44.46617621343377
      }
    ],
    "enhanced_query": "# Vulnerability Description\n\n    Cross-Site Request Forgery (CSRF) vulnerability in Chaser324 Featured Posts Scroll allows Stored **XSS**.This issue affects Featured Posts Scroll from n/a through 1.25.\n\n    # Keyphrase-Specific CWE Analysis\n    This vulnerability contains multiple keyphrases that may map to different CWEs. \n    Please analyze each keyphrase separately and determine the most appropriate CWE(s) for each.\n\n    ## WEAKNESS: 'cross-site request forgery'\n\nRelevant CWEs for this WEAKNESS:\n\n### 1. CWE-918: Server-Side Request Forgery (SSRF) (Score: 218.43)\n\nThe web server receives a URL or similar request from an upstream component and retrieves the contents of this URL, but it does not sufficiently ensure that the request is being sent to the expected destination....\n\n### 2. CWE-352: Cross-Site Request Forgery (CSRF) (Score: 211.75)\n\nThe web application does not, or can not, sufficiently verify whether a well-formed, valid, consistent request was intentionally provided by the user who submitted the request....\n\n### 3. CWE-601: URL Redirection to Untrusted Site ('Open Redirect') (Score: 210.36)\n\nThe web application accepts a user-controlled input that specifies a link to an external site, and uses that link in a redirect....\n\n### 4. CWE-79: Improper Neutralization of Input During Web Page Generation ('Cross-site Scripting') (Score: 161.33)\n\nThe product does not neutralize or incorrectly neutralizes user-controllable input before it is placed in output that is used as a web page that is served to other users....\n\n### 5. CWE-89: Improper Neutralization of Special Elements used in an SQL Command ('SQL Injection') (Score: 147.17)\n\nThe product constructs all or part of an SQL command using externally-influenced input from an upstream component, but it does not neutralize or incorrectly neutralizes special elements that could modify the intended SQL command when it is sent to a downstream component. Without sufficient removal o...\n\n## ROOTCAUSE: 'improper access control'\n\nRelevant CWEs for this ROOTCAUSE:\n\n### 1. CWE-352: Cross-Site Request Forgery (CSRF) (Score: 211.75)\n\nThe web application does not, or can not, sufficiently verify whether a well-formed, valid, consistent request was intentionally provided by the user who submitted the request....\n\n### 2. CWE-79: Improper Neutralization of Input During Web Page Generation ('Cross-site Scripting') (Score: 161.33)\n\nThe product does not neutralize or incorrectly neutralizes user-controllable input before it is placed in output that is used as a web page that is served to other users....\n\n### 3. CWE-116: Improper Encoding or Escaping of Output (Score: 160.02)\n\nThe product prepares a structured message for communication with another component, but encoding or escaping of the data is either missing or done incorrectly. As a result, the intended structure of the message is not preserved....\n\n### 4. CWE-1004: Sensitive Cookie Without 'HttpOnly' Flag (Score: 148.75)\n\nThe product uses a cookie to store sensitive information, but the cookie is not marked with the HttpOnly flag....\n\n### 5. CWE-89: Improper Neutralization of Special Elements used in an SQL Command ('SQL Injection') (Score: 147.17)\n\nThe product constructs all or part of an SQL command using externally-influenced input from an upstream component, but it does not neutralize or incorrectly neutralizes special elements that could modify the intended SQL command when it is sent to a downstream component. Without sufficient removal o...\n\n## WEAKNESS: 'XSS'\n\nRelevant CWEs for this WEAKNESS:\n\n### 1. CWE-352: Cross-Site Request Forgery (CSRF) (Score: 211.75)\n\nThe web application does not, or can not, sufficiently verify whether a well-formed, valid, consistent request was intentionally provided by the user who submitted the request....\n\n### 2. CWE-79: Improper Neutralization of Input During Web Page Generation ('Cross-site Scripting') (Score: 161.33)\n\nThe product does not neutralize or incorrectly neutralizes user-controllable input before it is placed in output that is used as a web page that is served to other users....\n\n### 3. CWE-116: Improper Encoding or Escaping of Output (Score: 160.02)\n\nThe product prepares a structured message for communication with another component, but encoding or escaping of the data is either missing or done incorrectly. As a result, the intended structure of the message is not preserved....\n\n### 4. CWE-1004: Sensitive Cookie Without 'HttpOnly' Flag (Score: 148.75)\n\nThe product uses a cookie to store sensitive information, but the cookie is not marked with the HttpOnly flag....\n\n### 5. CWE-80: Improper Neutralization of Script-Related HTML Tags in a Web Page (Basic XSS) (Score: 138.59)\n\nThe product receives input from an upstream component, but it does not neutralize or incorrectly neutralizes special characters such as \"<\", \">\", and \"&\" that could be interpreted as web-scripting elements when they are sent to a downstream component that processes web pages....\n\n## IMPACT: 'stored cross-site scripting'\n\nRelevant CWEs for this IMPACT:\n\n### 1. CWE-352: Cross-Site Request Forgery (CSRF) (Score: 211.75)\n\nThe web application does not, or can not, sufficiently verify whether a well-formed, valid, consistent request was intentionally provided by the user who submitted the request....\n\n### 2. CWE-79: Improper Neutralization of Input During Web Page Generation ('Cross-site Scripting') (Score: 161.33)\n\nThe product does not neutralize or incorrectly neutralizes user-controllable input before it is placed in output that is used as a web page that is served to other users....\n\n### 3. CWE-116: Improper Encoding or Escaping of Output (Score: 160.02)\n\nThe product prepares a structured message for communication with another component, but encoding or escaping of the data is either missing or done incorrectly. As a result, the intended structure of the message is not preserved....\n\n### 4. CWE-1004: Sensitive Cookie Without 'HttpOnly' Flag (Score: 148.75)\n\nThe product uses a cookie to store sensitive information, but the cookie is not marked with the HttpOnly flag....\n\n### 5. CWE-80: Improper Neutralization of Script-Related HTML Tags in a Web Page (Basic XSS) (Score: 138.59)\n\nThe product receives input from an upstream component, but it does not neutralize or incorrectly neutralizes special characters such as \"<\", \">\", and \"&\" that could be interpreted as web-scripting elements when they are sent to a downstream component that processes web pages....\n\n## PRODUCT: 'Chaser324 Featured Posts Scroll'\n\nRelevant CWEs for this PRODUCT:\n\n### 1. CWE-352: Cross-Site Request Forgery (CSRF) (Score: 211.75)\n\nThe web application does not, or can not, sufficiently verify whether a well-formed, valid, consistent request was intentionally provided by the user who submitted the request....\n\n### 2. CWE-79: Improper Neutralization of Input During Web Page Generation ('Cross-site Scripting') (Score: 161.33)\n\nThe product does not neutralize or incorrectly neutralizes user-controllable input before it is placed in output that is used as a web page that is served to other users....\n\n### 3. CWE-116: Improper Encoding or Escaping of Output (Score: 160.02)\n\nThe product prepares a structured message for communication with another component, but encoding or escaping of the data is either missing or done incorrectly. As a result, the intended structure of the message is not preserved....\n\n### 4. CWE-453: Insecure Default Variable Initialization (Score: 51.70)\n\nThe product, by default, initializes an internal variable with an insecure or less secure value than is possible....\n\n### 5. CWE-201: Insertion of Sensitive Information Into Sent Data (Score: 44.47)\n\nThe code transmits data to another actor, but a portion of the data includes sensitive information that should not be accessible to that actor....\n\n## VERSION: 'n/a through 1.25'\n\nRelevant CWEs for this VERSION:\n\n### 1. CWE-352: Cross-Site Request Forgery (CSRF) (Score: 211.75)\n\nThe web application does not, or can not, sufficiently verify whether a well-formed, valid, consistent request was intentionally provided by the user who submitted the request....\n\n### 2. CWE-79: Improper Neutralization of Input During Web Page Generation ('Cross-site Scripting') (Score: 161.33)\n\nThe product does not neutralize or incorrectly neutralizes user-controllable input before it is placed in output that is used as a web page that is served to other users....\n\n### 3. CWE-116: Improper Encoding or Escaping of Output (Score: 160.02)\n\nThe product prepares a structured message for communication with another component, but encoding or escaping of the data is either missing or done incorrectly. As a result, the intended structure of the message is not preserved....\n\n### 4. CWE-434: Unrestricted Upload of File with Dangerous Type (Score: 59.63)\n\nThe product allows the upload or transfer of dangerous file types that are automatically processed within its environment....\n\n### 5. CWE-22: Improper Limitation of a Pathname to a Restricted Directory ('Path Traversal') (Score: 57.48)\n\nThe product uses external input to construct a pathname that is intended to identify a file or directory that is located underneath a restricted parent directory, but the product does not properly neutralize special elements within the pathname that can cause the pathname to resolve to a location th...\n\n\n    # Analysis Instructions\n    1. For each keyphrase, identify the most appropriate CWE(s) that represent the weakness.\n    2. Consider how the different keyphrases might relate to each other in the vulnerability chain.\n    3. Provide a final determination of primary CWE(s) and any secondary CWEs.\n    4. Format your response using the standard analysis template.\n\n    Please analyze how these different weaknesses interact and provide a comprehensive CWE classification.\n    "
  },
  "retrieval_time": 1.001570701599121
}