{
  "vulnerability_info": "VulnerabilityInfo(cve_id='CVE-2025-32079', description='Improper **Input Validation vulnerability** in The Wikimedia Foundation Mediawiki - GrowthExperiments allows HTTP DoS.This issue affects Mediawiki - GrowthExperiments from 1.39 through 1.43.', key_phrases={'rootcause': ['Input Validation vulnerability', 'Improper Input Validation'], 'weakness': '', 'impact': 'HTTP DoS', 'vector': '', 'attacker': '', 'product': 'The Wikimedia Foundation Mediawiki', 'version': 'GrowthExperiments from 1.39 through 1.43', 'component': 'Mediawiki - GrowthExperiments'}, reference_content='## CVE-2025-32079 Analysis\\n\\nThe provided content relates to CVE-2025-32079. The first content excerpt from phabricator.wikimedia.org details a security task addressing a potential denial-of-service (DoS) vulnerability.\\n\\n**Root cause of vulnerability:**\\n\\nThe validation of content written to `MediaWiki:GrowthMentors.json` was broken due to a side effect of a deprecation change (T383330). This allowed for the injection of invalid data.\\n\\n**Weaknesses/vulnerabilities present:**\\n\\n*   Broken validation of user-supplied data.\\n*   Lack of proper input sanitization for `MediaWiki:GrowthMentors.json`.\\n*   Potential for DoS by providing invalid data that causes fatal errors.\\n\\n**Impact of exploitation:**\\n\\nAn attacker with write access to `MediaWiki:GrowthMentors.json` could cause fatal errors for users who have a mentor assigned, potentially taking down the site for those users.\\n\\n**Attack vectors:**\\n\\n*   An administrator (or user with write access) modifies the `MediaWiki:GrowthMentors.json` file with malicious content.\\n\\n**Required attacker capabilities/position:**\\n\\n*   Write access to the `MediaWiki:GrowthMentors.json` file (requires administrator privileges or equivalent permissions).\\n*   Knowledge of the vulnerability and the format of the `MediaWiki:GrowthMentors.json` file.\\n\\n**Mitigation or fix:**\\n\\n*   The vulnerability was fixed by re-enabling the validation of the `MediaWiki:GrowthMentors.json` file using the `CommunityStructuredMentorListValidator`. (Implemented in patch F58239732 and merged via Gerrit change #1114020).\\n*   A follow-up task (T384445) was created to address remaining issues related to validation warnings.\\n\\n**Additional Details:**\\n\\nThe content provides more detail than the placeholder CVE description. It includes a specific example of malicious content (`{\"Mentors\": {\"43912\": {\"weight\": \"tramvaj\"}}}`) that triggers the vulnerability and a stack trace of the resulting error. The content also details the steps taken to fix the vulnerability and related tasks.', similar_info={'cwe_distribution': {}, 'cwe_consensus': '', 'similarity_stats': {'thresholds': [], 'total_samples_by_threshold': {}, 'top_cwes_by_threshold': {}}}, similarity_summary=SimilarityInsight(consensus_cwe='', top_cwes=[], confidence_levels={}, total_samples=0), analysis='', analysis_with_relationships='', criticism='', resolution='', relevant_cwes=[{'metadata': {'doc_id': '20', 'name': 'Improper Input Validation', 'source': 'sparse', 'original_content': 'The product receives input or data, but it does\\n        not validate or incorrectly validates that the input has the\\n        properties that are required to process the data safely and\\n        correctly.', 'keyphrase_sources': [{'id': 'rootcause:Input Validation vulnerability', 'keyphrase': 'Input Validation vulnerability', 'type': 'rootcause'}, {'id': 'rootcause:Improper Input Validation', 'keyphrase': 'Improper Input Validation', 'type': 'rootcause'}, {'id': 'impact:HTTP DoS', 'keyphrase': 'HTTP DoS', 'type': 'impact'}]}, 'similarity': np.float64(129.09567350950795)}, {'metadata': {'doc_id': '1284', 'name': 'Improper Validation of Specified Quantity in Input', 'source': 'sparse', 'original_content': 'The product receives input that is expected to specify a quantity (such as size or length), but it does not validate or incorrectly validates that the quantity has the required properties.', 'keyphrase_sources': [{'id': 'rootcause:Input Validation vulnerability', 'keyphrase': 'Input Validation vulnerability', 'type': 'rootcause'}, {'id': 'rootcause:Improper Input Validation', 'keyphrase': 'Improper Input Validation', 'type': 'rootcause'}]}, 'similarity': np.float64(126.50782600400842)}, {'metadata': {'doc_id': '1286', 'name': 'Improper Validation of Syntactic Correctness of Input', 'source': 'sparse', 'original_content': 'The product receives input that is expected to be well-formed - i.e., to comply with a certain syntax - but it does not validate or incorrectly validates that the input complies with the syntax.', 'keyphrase_sources': [{'id': 'rootcause:Input Validation vulnerability', 'keyphrase': 'Input Validation vulnerability', 'type': 'rootcause'}, {'id': 'rootcause:Improper Input Validation', 'keyphrase': 'Improper Input Validation', 'type': 'rootcause'}, {'id': 'impact:HTTP DoS', 'keyphrase': 'HTTP DoS', 'type': 'impact'}]}, 'similarity': np.float64(120.64902289221499)}, {'metadata': {'doc_id': '1285', 'name': 'Improper Validation of Specified Index, Position, or Offset in Input', 'source': 'sparse', 'original_content': 'The product receives input that is expected to specify an index, position, or offset into an indexable resource such as a buffer or file, but it does not validate or incorrectly validates that the specified index/position/offset has the required properties.', 'keyphrase_sources': [{'id': 'rootcause:Input Validation vulnerability', 'keyphrase': 'Input Validation vulnerability', 'type': 'rootcause'}, {'id': 'rootcause:Improper Input Validation', 'keyphrase': 'Improper Input Validation', 'type': 'rootcause'}]}, 'similarity': np.float64(120.17727443972922)}, {'metadata': {'doc_id': '1333', 'name': 'Inefficient Regular Expression Complexity', 'source': 'sparse', 'original_content': 'The product uses a regular expression with an inefficient, possibly exponential worst-case computational complexity that consumes excessive CPU cycles.', 'keyphrase_sources': [{'id': 'rootcause:Input Validation vulnerability', 'keyphrase': 'Input Validation vulnerability', 'type': 'rootcause'}]}, 'similarity': np.float64(118.0073585612681)}, {'metadata': {'doc_id': '113', 'name': \"Improper Neutralization of CRLF Sequences in HTTP Headers ('HTTP Request/Response Splitting')\", 'source': 'sparse', 'original_content': 'The product receives data from an HTTP agent/component (e.g., web server, proxy, browser, etc.), but it does not neutralize or incorrectly neutralizes CR and LF characters before the data is included in outgoing HTTP headers.', 'keyphrase_sources': [{'id': 'rootcause:Improper Input Validation', 'keyphrase': 'Improper Input Validation', 'type': 'rootcause'}, {'id': 'impact:HTTP DoS', 'keyphrase': 'HTTP DoS', 'type': 'impact'}, {'id': 'product:The Wikimedia Foundation Mediawiki', 'keyphrase': 'The Wikimedia Foundation Mediawiki', 'type': 'product'}]}, 'similarity': np.float64(117.17845651070917)}, {'metadata': {'doc_id': '288', 'name': 'Authentication Bypass Using an Alternate Path or Channel', 'source': 'sparse', 'original_content': 'The product requires authentication, but the product has an alternate path or channel that does not require authentication.', 'keyphrase_sources': [{'id': 'version:GrowthExperiments from 1.39 through 1.43', 'keyphrase': 'GrowthExperiments from 1.39 through 1.43', 'type': 'version'}, {'id': 'component:Mediawiki - GrowthExperiments', 'keyphrase': 'Mediawiki - GrowthExperiments', 'type': 'component'}]}, 'similarity': np.float64(53.253458274730995)}, {'metadata': {'doc_id': '820', 'name': 'Missing Synchronization', 'source': 'sparse', 'original_content': 'The product utilizes a shared resource in a concurrent manner but does not attempt to synchronize access to the resource.', 'keyphrase_sources': [{'id': 'version:GrowthExperiments from 1.39 through 1.43', 'keyphrase': 'GrowthExperiments from 1.39 through 1.43', 'type': 'version'}]}, 'similarity': np.float64(53.00137712983053)}, {'metadata': {'doc_id': '201', 'name': 'Insertion of Sensitive Information Into Sent Data', 'source': 'sparse', 'original_content': 'The code transmits data to another actor, but a portion of the data includes sensitive information that should not be accessible to that actor.', 'keyphrase_sources': [{'id': 'product:The Wikimedia Foundation Mediawiki', 'keyphrase': 'The Wikimedia Foundation Mediawiki', 'type': 'product'}, {'id': 'version:GrowthExperiments from 1.39 through 1.43', 'keyphrase': 'GrowthExperiments from 1.39 through 1.43', 'type': 'version'}, {'id': 'component:Mediawiki - GrowthExperiments', 'keyphrase': 'Mediawiki - GrowthExperiments', 'type': 'component'}]}, 'similarity': np.float64(51.44354061697595)}, {'metadata': {'doc_id': '912', 'name': 'Hidden Functionality', 'source': 'sparse', 'original_content': \"The product contains functionality that is not documented, not part of the specification, and not accessible through an interface or command sequence that is obvious to the product's users or administrators.\", 'keyphrase_sources': [{'id': 'version:GrowthExperiments from 1.39 through 1.43', 'keyphrase': 'GrowthExperiments from 1.39 through 1.43', 'type': 'version'}]}, 'similarity': np.float64(51.07516059398563)}, {'metadata': {'doc_id': '805', 'name': 'Buffer Access with Incorrect Length Value', 'source': 'sparse', 'original_content': 'The product uses a sequential operation to read or write a buffer, but it uses an incorrect length value that causes it to access memory that is outside of the bounds of the buffer.', 'keyphrase_sources': [{'id': 'version:GrowthExperiments from 1.39 through 1.43', 'keyphrase': 'GrowthExperiments from 1.39 through 1.43', 'type': 'version'}]}, 'similarity': np.float64(48.96484979068844)}, {'metadata': {'doc_id': '267', 'name': 'Privilege Defined With Unsafe Actions', 'source': 'sparse', 'original_content': 'A particular privilege, role, capability, or right can be used to perform unsafe actions that were not intended, even when it is assigned to the correct entity.', 'keyphrase_sources': [{'id': 'product:The Wikimedia Foundation Mediawiki', 'keyphrase': 'The Wikimedia Foundation Mediawiki', 'type': 'product'}, {'id': 'component:Mediawiki - GrowthExperiments', 'keyphrase': 'Mediawiki - GrowthExperiments', 'type': 'component'}]}, 'similarity': np.float64(48.175732163649194)}, {'metadata': {'doc_id': '453', 'name': 'Insecure Default Variable Initialization', 'source': 'sparse', 'original_content': 'The product, by default, initializes an internal variable with an insecure or less secure value than is possible.', 'keyphrase_sources': [{'id': 'product:The Wikimedia Foundation Mediawiki', 'keyphrase': 'The Wikimedia Foundation Mediawiki', 'type': 'product'}]}, 'similarity': np.float64(45.07234734607373)}, {'metadata': {'doc_id': '674', 'name': 'Uncontrolled Recursion', 'source': 'sparse', 'original_content': 'The product does not properly control the amount of recursion that takes place,  consuming excessive resources, such as allocated memory or the program stack.', 'keyphrase_sources': [{'id': 'impact:HTTP DoS', 'keyphrase': 'HTTP DoS', 'type': 'impact'}, {'id': 'product:The Wikimedia Foundation Mediawiki', 'keyphrase': 'The Wikimedia Foundation Mediawiki', 'type': 'product'}, {'id': 'component:Mediawiki - GrowthExperiments', 'keyphrase': 'Mediawiki - GrowthExperiments', 'type': 'component'}]}, 'similarity': np.float64(44.95075825958928)}, {'metadata': {'doc_id': '400', 'name': 'Uncontrolled Resource Consumption', 'source': 'sparse', 'original_content': 'The product does not properly control the allocation and maintenance of a limited resource, thereby enabling an actor to influence the amount of resources consumed, eventually leading to the exhaustion of available resources.', 'keyphrase_sources': [{'id': 'impact:HTTP DoS', 'keyphrase': 'HTTP DoS', 'type': 'impact'}]}, 'similarity': np.float64(41.793559989516254)}, {'metadata': {'doc_id': '524', 'name': 'Use of Cache Containing Sensitive Information', 'source': 'sparse', 'original_content': 'The code uses a cache that contains sensitive information, but the cache can be read by an actor outside of the intended control sphere.', 'keyphrase_sources': [{'id': 'component:Mediawiki - GrowthExperiments', 'keyphrase': 'Mediawiki - GrowthExperiments', 'type': 'component'}]}, 'similarity': np.float64(36.06347343475687)}], identified_cwes={'analyzer': [], 'critic_additional': []})",
  "retrieval_results": {
    "has_multiple_keyphrases": true,
    "keyphrase_cwe_sets": {
      "rootcause:Input Validation vulnerability": {
        "keyphrase": "Input Validation vulnerability",
        "type": "rootcause",
        "cwes": [
          {
            "metadata": {
              "doc_id": "20",
              "name": "Improper Input Validation",
              "source": "sparse",
              "original_content": "The product receives input or data, but it does\n        not validate or incorrectly validates that the input has the\n        properties that are required to process the data safely and\n        correctly.",
              "keyphrase_sources": [
                {
                  "id": "rootcause:Input Validation vulnerability",
                  "keyphrase": "Input Validation vulnerability",
                  "type": "rootcause"
                },
                {
                  "id": "rootcause:Improper Input Validation",
                  "keyphrase": "Improper Input Validation",
                  "type": "rootcause"
                },
                {
                  "id": "impact:HTTP DoS",
                  "keyphrase": "HTTP DoS",
                  "type": "impact"
                }
              ]
            },
            "similarity": 129.09567350950795
          },
          {
            "metadata": {
              "doc_id": "1284",
              "name": "Improper Validation of Specified Quantity in Input",
              "source": "sparse",
              "original_content": "The product receives input that is expected to specify a quantity (such as size or length), but it does not validate or incorrectly validates that the quantity has the required properties.",
              "keyphrase_sources": [
                {
                  "id": "rootcause:Input Validation vulnerability",
                  "keyphrase": "Input Validation vulnerability",
                  "type": "rootcause"
                },
                {
                  "id": "rootcause:Improper Input Validation",
                  "keyphrase": "Improper Input Validation",
                  "type": "rootcause"
                }
              ]
            },
            "similarity": 126.50782600400842
          },
          {
            "metadata": {
              "doc_id": "1286",
              "name": "Improper Validation of Syntactic Correctness of Input",
              "source": "sparse",
              "original_content": "The product receives input that is expected to be well-formed - i.e., to comply with a certain syntax - but it does not validate or incorrectly validates that the input complies with the syntax.",
              "keyphrase_sources": [
                {
                  "id": "rootcause:Input Validation vulnerability",
                  "keyphrase": "Input Validation vulnerability",
                  "type": "rootcause"
                },
                {
                  "id": "rootcause:Improper Input Validation",
                  "keyphrase": "Improper Input Validation",
                  "type": "rootcause"
                },
                {
                  "id": "impact:HTTP DoS",
                  "keyphrase": "HTTP DoS",
                  "type": "impact"
                }
              ]
            },
            "similarity": 120.64902289221499
          },
          {
            "metadata": {
              "doc_id": "1285",
              "name": "Improper Validation of Specified Index, Position, or Offset in Input",
              "source": "sparse",
              "original_content": "The product receives input that is expected to specify an index, position, or offset into an indexable resource such as a buffer or file, but it does not validate or incorrectly validates that the specified index/position/offset has the required properties.",
              "keyphrase_sources": [
                {
                  "id": "rootcause:Input Validation vulnerability",
                  "keyphrase": "Input Validation vulnerability",
                  "type": "rootcause"
                },
                {
                  "id": "rootcause:Improper Input Validation",
                  "keyphrase": "Improper Input Validation",
                  "type": "rootcause"
                }
              ]
            },
            "similarity": 120.17727443972922
          },
          {
            "metadata": {
              "doc_id": "1333",
              "name": "Inefficient Regular Expression Complexity",
              "source": "sparse",
              "original_content": "The product uses a regular expression with an inefficient, possibly exponential worst-case computational complexity that consumes excessive CPU cycles.",
              "keyphrase_sources": [
                {
                  "id": "rootcause:Input Validation vulnerability",
                  "keyphrase": "Input Validation vulnerability",
                  "type": "rootcause"
                }
              ]
            },
            "similarity": 118.0073585612681
          }
        ]
      },
      "rootcause:Improper Input Validation": {
        "keyphrase": "Improper Input Validation",
        "type": "rootcause",
        "cwes": [
          {
            "metadata": {
              "doc_id": "20",
              "name": "Improper Input Validation",
              "source": "sparse",
              "original_content": "The product receives input or data, but it does\n        not validate or incorrectly validates that the input has the\n        properties that are required to process the data safely and\n        correctly."
            },
            "similarity": 133.84865202694235
          },
          {
            "metadata": {
              "doc_id": "1284",
              "name": "Improper Validation of Specified Quantity in Input",
              "source": "sparse",
              "original_content": "The product receives input that is expected to specify a quantity (such as size or length), but it does not validate or incorrectly validates that the quantity has the required properties."
            },
            "similarity": 129.56273586827817
          },
          {
            "metadata": {
              "doc_id": "1286",
              "name": "Improper Validation of Syntactic Correctness of Input",
              "source": "sparse",
              "original_content": "The product receives input that is expected to be well-formed - i.e., to comply with a certain syntax - but it does not validate or incorrectly validates that the input complies with the syntax."
            },
            "similarity": 124.75583256059235
          },
          {
            "metadata": {
              "doc_id": "1285",
              "name": "Improper Validation of Specified Index, Position, or Offset in Input",
              "source": "sparse",
              "original_content": "The product receives input that is expected to specify an index, position, or offset into an indexable resource such as a buffer or file, but it does not validate or incorrectly validates that the specified index/position/offset has the required properties."
            },
            "similarity": 124.48640419913347
          },
          {
            "metadata": {
              "doc_id": "113",
              "name": "Improper Neutralization of CRLF Sequences in HTTP Headers ('HTTP Request/Response Splitting')",
              "source": "sparse",
              "original_content": "The product receives data from an HTTP agent/component (e.g., web server, proxy, browser, etc.), but it does not neutralize or incorrectly neutralizes CR and LF characters before the data is included in outgoing HTTP headers.",
              "keyphrase_sources": [
                {
                  "id": "rootcause:Improper Input Validation",
                  "keyphrase": "Improper Input Validation",
                  "type": "rootcause"
                },
                {
                  "id": "impact:HTTP DoS",
                  "keyphrase": "HTTP DoS",
                  "type": "impact"
                },
                {
                  "id": "product:The Wikimedia Foundation Mediawiki",
                  "keyphrase": "The Wikimedia Foundation Mediawiki",
                  "type": "product"
                }
              ]
            },
            "similarity": 117.17845651070917
          }
        ]
      },
      "impact:HTTP DoS": {
        "keyphrase": "HTTP DoS",
        "type": "impact",
        "cwes": [
          {
            "metadata": {
              "doc_id": "674",
              "name": "Uncontrolled Recursion",
              "source": "sparse",
              "original_content": "The product does not properly control the amount of recursion that takes place,  consuming excessive resources, such as allocated memory or the program stack.",
              "keyphrase_sources": [
                {
                  "id": "impact:HTTP DoS",
                  "keyphrase": "HTTP DoS",
                  "type": "impact"
                },
                {
                  "id": "product:The Wikimedia Foundation Mediawiki",
                  "keyphrase": "The Wikimedia Foundation Mediawiki",
                  "type": "product"
                },
                {
                  "id": "component:Mediawiki - GrowthExperiments",
                  "keyphrase": "Mediawiki - GrowthExperiments",
                  "type": "component"
                }
              ]
            },
            "similarity": 44.95075825958928
          },
          {
            "metadata": {
              "doc_id": "400",
              "name": "Uncontrolled Resource Consumption",
              "source": "sparse",
              "original_content": "The product does not properly control the allocation and maintenance of a limited resource, thereby enabling an actor to influence the amount of resources consumed, eventually leading to the exhaustion of available resources.",
              "keyphrase_sources": [
                {
                  "id": "impact:HTTP DoS",
                  "keyphrase": "HTTP DoS",
                  "type": "impact"
                }
              ]
            },
            "similarity": 41.793559989516254
          },
          {
            "metadata": {
              "doc_id": "113",
              "name": "Improper Neutralization of CRLF Sequences in HTTP Headers ('HTTP Request/Response Splitting')",
              "source": "sparse",
              "original_content": "The product receives data from an HTTP agent/component (e.g., web server, proxy, browser, etc.), but it does not neutralize or incorrectly neutralizes CR and LF characters before the data is included in outgoing HTTP headers."
            },
            "similarity": 41.15762423600755
          },
          {
            "metadata": {
              "doc_id": "20",
              "name": "Improper Input Validation",
              "source": "sparse",
              "original_content": "The product receives input or data, but it does\n        not validate or incorrectly validates that the input has the\n        properties that are required to process the data safely and\n        correctly."
            },
            "similarity": 40.82925554339517
          },
          {
            "metadata": {
              "doc_id": "1286",
              "name": "Improper Validation of Syntactic Correctness of Input",
              "source": "sparse",
              "original_content": "The product receives input that is expected to be well-formed - i.e., to comply with a certain syntax - but it does not validate or incorrectly validates that the input complies with the syntax."
            },
            "similarity": 39.86078795347041
          }
        ]
      },
      "product:The Wikimedia Foundation Mediawiki": {
        "keyphrase": "The Wikimedia Foundation Mediawiki",
        "type": "product",
        "cwes": [
          {
            "metadata": {
              "doc_id": "201",
              "name": "Insertion of Sensitive Information Into Sent Data",
              "source": "sparse",
              "original_content": "The code transmits data to another actor, but a portion of the data includes sensitive information that should not be accessible to that actor.",
              "keyphrase_sources": [
                {
                  "id": "product:The Wikimedia Foundation Mediawiki",
                  "keyphrase": "The Wikimedia Foundation Mediawiki",
                  "type": "product"
                },
                {
                  "id": "version:GrowthExperiments from 1.39 through 1.43",
                  "keyphrase": "GrowthExperiments from 1.39 through 1.43",
                  "type": "version"
                },
                {
                  "id": "component:Mediawiki - GrowthExperiments",
                  "keyphrase": "Mediawiki - GrowthExperiments",
                  "type": "component"
                }
              ]
            },
            "similarity": 51.44354061697595
          },
          {
            "metadata": {
              "doc_id": "674",
              "name": "Uncontrolled Recursion",
              "source": "sparse",
              "original_content": "The product does not properly control the amount of recursion that takes place,  consuming excessive resources, such as allocated memory or the program stack."
            },
            "similarity": 49.0952042738037
          },
          {
            "metadata": {
              "doc_id": "267",
              "name": "Privilege Defined With Unsafe Actions",
              "source": "sparse",
              "original_content": "A particular privilege, role, capability, or right can be used to perform unsafe actions that were not intended, even when it is assigned to the correct entity.",
              "keyphrase_sources": [
                {
                  "id": "product:The Wikimedia Foundation Mediawiki",
                  "keyphrase": "The Wikimedia Foundation Mediawiki",
                  "type": "product"
                },
                {
                  "id": "component:Mediawiki - GrowthExperiments",
                  "keyphrase": "Mediawiki - GrowthExperiments",
                  "type": "component"
                }
              ]
            },
            "similarity": 48.175732163649194
          },
          {
            "metadata": {
              "doc_id": "113",
              "name": "Improper Neutralization of CRLF Sequences in HTTP Headers ('HTTP Request/Response Splitting')",
              "source": "sparse",
              "original_content": "The product receives data from an HTTP agent/component (e.g., web server, proxy, browser, etc.), but it does not neutralize or incorrectly neutralizes CR and LF characters before the data is included in outgoing HTTP headers."
            },
            "similarity": 47.346792310960126
          },
          {
            "metadata": {
              "doc_id": "453",
              "name": "Insecure Default Variable Initialization",
              "source": "sparse",
              "original_content": "The product, by default, initializes an internal variable with an insecure or less secure value than is possible.",
              "keyphrase_sources": [
                {
                  "id": "product:The Wikimedia Foundation Mediawiki",
                  "keyphrase": "The Wikimedia Foundation Mediawiki",
                  "type": "product"
                }
              ]
            },
            "similarity": 45.07234734607373
          }
        ]
      },
      "version:GrowthExperiments from 1.39 through 1.43": {
        "keyphrase": "GrowthExperiments from 1.39 through 1.43",
        "type": "version",
        "cwes": [
          {
            "metadata": {
              "doc_id": "288",
              "name": "Authentication Bypass Using an Alternate Path or Channel",
              "source": "sparse",
              "original_content": "The product requires authentication, but the product has an alternate path or channel that does not require authentication.",
              "keyphrase_sources": [
                {
                  "id": "version:GrowthExperiments from 1.39 through 1.43",
                  "keyphrase": "GrowthExperiments from 1.39 through 1.43",
                  "type": "version"
                },
                {
                  "id": "component:Mediawiki - GrowthExperiments",
                  "keyphrase": "Mediawiki - GrowthExperiments",
                  "type": "component"
                }
              ]
            },
            "similarity": 53.253458274730995
          },
          {
            "metadata": {
              "doc_id": "820",
              "name": "Missing Synchronization",
              "source": "sparse",
              "original_content": "The product utilizes a shared resource in a concurrent manner but does not attempt to synchronize access to the resource.",
              "keyphrase_sources": [
                {
                  "id": "version:GrowthExperiments from 1.39 through 1.43",
                  "keyphrase": "GrowthExperiments from 1.39 through 1.43",
                  "type": "version"
                }
              ]
            },
            "similarity": 53.00137712983053
          },
          {
            "metadata": {
              "doc_id": "912",
              "name": "Hidden Functionality",
              "source": "sparse",
              "original_content": "The product contains functionality that is not documented, not part of the specification, and not accessible through an interface or command sequence that is obvious to the product's users or administrators.",
              "keyphrase_sources": [
                {
                  "id": "version:GrowthExperiments from 1.39 through 1.43",
                  "keyphrase": "GrowthExperiments from 1.39 through 1.43",
                  "type": "version"
                }
              ]
            },
            "similarity": 51.07516059398563
          },
          {
            "metadata": {
              "doc_id": "805",
              "name": "Buffer Access with Incorrect Length Value",
              "source": "sparse",
              "original_content": "The product uses a sequential operation to read or write a buffer, but it uses an incorrect length value that causes it to access memory that is outside of the bounds of the buffer.",
              "keyphrase_sources": [
                {
                  "id": "version:GrowthExperiments from 1.39 through 1.43",
                  "keyphrase": "GrowthExperiments from 1.39 through 1.43",
                  "type": "version"
                }
              ]
            },
            "similarity": 48.96484979068844
          },
          {
            "metadata": {
              "doc_id": "201",
              "name": "Insertion of Sensitive Information Into Sent Data",
              "source": "sparse",
              "original_content": "The code transmits data to another actor, but a portion of the data includes sensitive information that should not be accessible to that actor."
            },
            "similarity": 48.71840552923781
          }
        ]
      },
      "component:Mediawiki - GrowthExperiments": {
        "keyphrase": "Mediawiki - GrowthExperiments",
        "type": "component",
        "cwes": [
          {
            "metadata": {
              "doc_id": "201",
              "name": "Insertion of Sensitive Information Into Sent Data",
              "source": "sparse",
              "original_content": "The code transmits data to another actor, but a portion of the data includes sensitive information that should not be accessible to that actor."
            },
            "similarity": 44.24345926165165
          },
          {
            "metadata": {
              "doc_id": "267",
              "name": "Privilege Defined With Unsafe Actions",
              "source": "sparse",
              "original_content": "A particular privilege, role, capability, or right can be used to perform unsafe actions that were not intended, even when it is assigned to the correct entity."
            },
            "similarity": 41.10779759049263
          },
          {
            "metadata": {
              "doc_id": "674",
              "name": "Uncontrolled Recursion",
              "source": "sparse",
              "original_content": "The product does not properly control the amount of recursion that takes place,  consuming excessive resources, such as allocated memory or the program stack."
            },
            "similarity": 37.21492208761529
          },
          {
            "metadata": {
              "doc_id": "524",
              "name": "Use of Cache Containing Sensitive Information",
              "source": "sparse",
              "original_content": "The code uses a cache that contains sensitive information, but the cache can be read by an actor outside of the intended control sphere.",
              "keyphrase_sources": [
                {
                  "id": "component:Mediawiki - GrowthExperiments",
                  "keyphrase": "Mediawiki - GrowthExperiments",
                  "type": "component"
                }
              ]
            },
            "similarity": 36.06347343475687
          },
          {
            "metadata": {
              "doc_id": "288",
              "name": "Authentication Bypass Using an Alternate Path or Channel",
              "source": "sparse",
              "original_content": "The product requires authentication, but the product has an alternate path or channel that does not require authentication."
            },
            "similarity": 35.11269614154161
          }
        ]
      }
    },
    "keyphrase_mapping": {
      "20": [
        {
          "id": "rootcause:Input Validation vulnerability",
          "keyphrase": "Input Validation vulnerability",
          "type": "rootcause"
        },
        {
          "id": "rootcause:Improper Input Validation",
          "keyphrase": "Improper Input Validation",
          "type": "rootcause"
        },
        {
          "id": "impact:HTTP DoS",
          "keyphrase": "HTTP DoS",
          "type": "impact"
        }
      ],
      "1284": [
        {
          "id": "rootcause:Input Validation vulnerability",
          "keyphrase": "Input Validation vulnerability",
          "type": "rootcause"
        },
        {
          "id": "rootcause:Improper Input Validation",
          "keyphrase": "Improper Input Validation",
          "type": "rootcause"
        }
      ],
      "1286": [
        {
          "id": "rootcause:Input Validation vulnerability",
          "keyphrase": "Input Validation vulnerability",
          "type": "rootcause"
        },
        {
          "id": "rootcause:Improper Input Validation",
          "keyphrase": "Improper Input Validation",
          "type": "rootcause"
        },
        {
          "id": "impact:HTTP DoS",
          "keyphrase": "HTTP DoS",
          "type": "impact"
        }
      ],
      "1285": [
        {
          "id": "rootcause:Input Validation vulnerability",
          "keyphrase": "Input Validation vulnerability",
          "type": "rootcause"
        },
        {
          "id": "rootcause:Improper Input Validation",
          "keyphrase": "Improper Input Validation",
          "type": "rootcause"
        }
      ],
      "1333": [
        {
          "id": "rootcause:Input Validation vulnerability",
          "keyphrase": "Input Validation vulnerability",
          "type": "rootcause"
        }
      ],
      "113": [
        {
          "id": "rootcause:Improper Input Validation",
          "keyphrase": "Improper Input Validation",
          "type": "rootcause"
        },
        {
          "id": "impact:HTTP DoS",
          "keyphrase": "HTTP DoS",
          "type": "impact"
        },
        {
          "id": "product:The Wikimedia Foundation Mediawiki",
          "keyphrase": "The Wikimedia Foundation Mediawiki",
          "type": "product"
        }
      ],
      "674": [
        {
          "id": "impact:HTTP DoS",
          "keyphrase": "HTTP DoS",
          "type": "impact"
        },
        {
          "id": "product:The Wikimedia Foundation Mediawiki",
          "keyphrase": "The Wikimedia Foundation Mediawiki",
          "type": "product"
        },
        {
          "id": "component:Mediawiki - GrowthExperiments",
          "keyphrase": "Mediawiki - GrowthExperiments",
          "type": "component"
        }
      ],
      "400": [
        {
          "id": "impact:HTTP DoS",
          "keyphrase": "HTTP DoS",
          "type": "impact"
        }
      ],
      "201": [
        {
          "id": "product:The Wikimedia Foundation Mediawiki",
          "keyphrase": "The Wikimedia Foundation Mediawiki",
          "type": "product"
        },
        {
          "id": "version:GrowthExperiments from 1.39 through 1.43",
          "keyphrase": "GrowthExperiments from 1.39 through 1.43",
          "type": "version"
        },
        {
          "id": "component:Mediawiki - GrowthExperiments",
          "keyphrase": "Mediawiki - GrowthExperiments",
          "type": "component"
        }
      ],
      "267": [
        {
          "id": "product:The Wikimedia Foundation Mediawiki",
          "keyphrase": "The Wikimedia Foundation Mediawiki",
          "type": "product"
        },
        {
          "id": "component:Mediawiki - GrowthExperiments",
          "keyphrase": "Mediawiki - GrowthExperiments",
          "type": "component"
        }
      ],
      "453": [
        {
          "id": "product:The Wikimedia Foundation Mediawiki",
          "keyphrase": "The Wikimedia Foundation Mediawiki",
          "type": "product"
        }
      ],
      "288": [
        {
          "id": "version:GrowthExperiments from 1.39 through 1.43",
          "keyphrase": "GrowthExperiments from 1.39 through 1.43",
          "type": "version"
        },
        {
          "id": "component:Mediawiki - GrowthExperiments",
          "keyphrase": "Mediawiki - GrowthExperiments",
          "type": "component"
        }
      ],
      "820": [
        {
          "id": "version:GrowthExperiments from 1.39 through 1.43",
          "keyphrase": "GrowthExperiments from 1.39 through 1.43",
          "type": "version"
        }
      ],
      "912": [
        {
          "id": "version:GrowthExperiments from 1.39 through 1.43",
          "keyphrase": "GrowthExperiments from 1.39 through 1.43",
          "type": "version"
        }
      ],
      "805": [
        {
          "id": "version:GrowthExperiments from 1.39 through 1.43",
          "keyphrase": "GrowthExperiments from 1.39 through 1.43",
          "type": "version"
        }
      ],
      "524": [
        {
          "id": "component:Mediawiki - GrowthExperiments",
          "keyphrase": "Mediawiki - GrowthExperiments",
          "type": "component"
        }
      ]
    },
    "relevant_cwes": [
      {
        "metadata": {
          "doc_id": "20",
          "name": "Improper Input Validation",
          "source": "sparse",
          "original_content": "The product receives input or data, but it does\n        not validate or incorrectly validates that the input has the\n        properties that are required to process the data safely and\n        correctly.",
          "keyphrase_sources": [
            {
              "id": "rootcause:Input Validation vulnerability",
              "keyphrase": "Input Validation vulnerability",
              "type": "rootcause"
            },
            {
              "id": "rootcause:Improper Input Validation",
              "keyphrase": "Improper Input Validation",
              "type": "rootcause"
            },
            {
              "id": "impact:HTTP DoS",
              "keyphrase": "HTTP DoS",
              "type": "impact"
            }
          ]
        },
        "similarity": 129.09567350950795
      },
      {
        "metadata": {
          "doc_id": "1284",
          "name": "Improper Validation of Specified Quantity in Input",
          "source": "sparse",
          "original_content": "The product receives input that is expected to specify a quantity (such as size or length), but it does not validate or incorrectly validates that the quantity has the required properties.",
          "keyphrase_sources": [
            {
              "id": "rootcause:Input Validation vulnerability",
              "keyphrase": "Input Validation vulnerability",
              "type": "rootcause"
            },
            {
              "id": "rootcause:Improper Input Validation",
              "keyphrase": "Improper Input Validation",
              "type": "rootcause"
            }
          ]
        },
        "similarity": 126.50782600400842
      },
      {
        "metadata": {
          "doc_id": "1286",
          "name": "Improper Validation of Syntactic Correctness of Input",
          "source": "sparse",
          "original_content": "The product receives input that is expected to be well-formed - i.e., to comply with a certain syntax - but it does not validate or incorrectly validates that the input complies with the syntax.",
          "keyphrase_sources": [
            {
              "id": "rootcause:Input Validation vulnerability",
              "keyphrase": "Input Validation vulnerability",
              "type": "rootcause"
            },
            {
              "id": "rootcause:Improper Input Validation",
              "keyphrase": "Improper Input Validation",
              "type": "rootcause"
            },
            {
              "id": "impact:HTTP DoS",
              "keyphrase": "HTTP DoS",
              "type": "impact"
            }
          ]
        },
        "similarity": 120.64902289221499
      },
      {
        "metadata": {
          "doc_id": "1285",
          "name": "Improper Validation of Specified Index, Position, or Offset in Input",
          "source": "sparse",
          "original_content": "The product receives input that is expected to specify an index, position, or offset into an indexable resource such as a buffer or file, but it does not validate or incorrectly validates that the specified index/position/offset has the required properties.",
          "keyphrase_sources": [
            {
              "id": "rootcause:Input Validation vulnerability",
              "keyphrase": "Input Validation vulnerability",
              "type": "rootcause"
            },
            {
              "id": "rootcause:Improper Input Validation",
              "keyphrase": "Improper Input Validation",
              "type": "rootcause"
            }
          ]
        },
        "similarity": 120.17727443972922
      },
      {
        "metadata": {
          "doc_id": "1333",
          "name": "Inefficient Regular Expression Complexity",
          "source": "sparse",
          "original_content": "The product uses a regular expression with an inefficient, possibly exponential worst-case computational complexity that consumes excessive CPU cycles.",
          "keyphrase_sources": [
            {
              "id": "rootcause:Input Validation vulnerability",
              "keyphrase": "Input Validation vulnerability",
              "type": "rootcause"
            }
          ]
        },
        "similarity": 118.0073585612681
      },
      {
        "metadata": {
          "doc_id": "113",
          "name": "Improper Neutralization of CRLF Sequences in HTTP Headers ('HTTP Request/Response Splitting')",
          "source": "sparse",
          "original_content": "The product receives data from an HTTP agent/component (e.g., web server, proxy, browser, etc.), but it does not neutralize or incorrectly neutralizes CR and LF characters before the data is included in outgoing HTTP headers.",
          "keyphrase_sources": [
            {
              "id": "rootcause:Improper Input Validation",
              "keyphrase": "Improper Input Validation",
              "type": "rootcause"
            },
            {
              "id": "impact:HTTP DoS",
              "keyphrase": "HTTP DoS",
              "type": "impact"
            },
            {
              "id": "product:The Wikimedia Foundation Mediawiki",
              "keyphrase": "The Wikimedia Foundation Mediawiki",
              "type": "product"
            }
          ]
        },
        "similarity": 117.17845651070917
      },
      {
        "metadata": {
          "doc_id": "288",
          "name": "Authentication Bypass Using an Alternate Path or Channel",
          "source": "sparse",
          "original_content": "The product requires authentication, but the product has an alternate path or channel that does not require authentication.",
          "keyphrase_sources": [
            {
              "id": "version:GrowthExperiments from 1.39 through 1.43",
              "keyphrase": "GrowthExperiments from 1.39 through 1.43",
              "type": "version"
            },
            {
              "id": "component:Mediawiki - GrowthExperiments",
              "keyphrase": "Mediawiki - GrowthExperiments",
              "type": "component"
            }
          ]
        },
        "similarity": 53.253458274730995
      },
      {
        "metadata": {
          "doc_id": "820",
          "name": "Missing Synchronization",
          "source": "sparse",
          "original_content": "The product utilizes a shared resource in a concurrent manner but does not attempt to synchronize access to the resource.",
          "keyphrase_sources": [
            {
              "id": "version:GrowthExperiments from 1.39 through 1.43",
              "keyphrase": "GrowthExperiments from 1.39 through 1.43",
              "type": "version"
            }
          ]
        },
        "similarity": 53.00137712983053
      },
      {
        "metadata": {
          "doc_id": "201",
          "name": "Insertion of Sensitive Information Into Sent Data",
          "source": "sparse",
          "original_content": "The code transmits data to another actor, but a portion of the data includes sensitive information that should not be accessible to that actor.",
          "keyphrase_sources": [
            {
              "id": "product:The Wikimedia Foundation Mediawiki",
              "keyphrase": "The Wikimedia Foundation Mediawiki",
              "type": "product"
            },
            {
              "id": "version:GrowthExperiments from 1.39 through 1.43",
              "keyphrase": "GrowthExperiments from 1.39 through 1.43",
              "type": "version"
            },
            {
              "id": "component:Mediawiki - GrowthExperiments",
              "keyphrase": "Mediawiki - GrowthExperiments",
              "type": "component"
            }
          ]
        },
        "similarity": 51.44354061697595
      },
      {
        "metadata": {
          "doc_id": "912",
          "name": "Hidden Functionality",
          "source": "sparse",
          "original_content": "The product contains functionality that is not documented, not part of the specification, and not accessible through an interface or command sequence that is obvious to the product's users or administrators.",
          "keyphrase_sources": [
            {
              "id": "version:GrowthExperiments from 1.39 through 1.43",
              "keyphrase": "GrowthExperiments from 1.39 through 1.43",
              "type": "version"
            }
          ]
        },
        "similarity": 51.07516059398563
      },
      {
        "metadata": {
          "doc_id": "805",
          "name": "Buffer Access with Incorrect Length Value",
          "source": "sparse",
          "original_content": "The product uses a sequential operation to read or write a buffer, but it uses an incorrect length value that causes it to access memory that is outside of the bounds of the buffer.",
          "keyphrase_sources": [
            {
              "id": "version:GrowthExperiments from 1.39 through 1.43",
              "keyphrase": "GrowthExperiments from 1.39 through 1.43",
              "type": "version"
            }
          ]
        },
        "similarity": 48.96484979068844
      },
      {
        "metadata": {
          "doc_id": "267",
          "name": "Privilege Defined With Unsafe Actions",
          "source": "sparse",
          "original_content": "A particular privilege, role, capability, or right can be used to perform unsafe actions that were not intended, even when it is assigned to the correct entity.",
          "keyphrase_sources": [
            {
              "id": "product:The Wikimedia Foundation Mediawiki",
              "keyphrase": "The Wikimedia Foundation Mediawiki",
              "type": "product"
            },
            {
              "id": "component:Mediawiki - GrowthExperiments",
              "keyphrase": "Mediawiki - GrowthExperiments",
              "type": "component"
            }
          ]
        },
        "similarity": 48.175732163649194
      },
      {
        "metadata": {
          "doc_id": "453",
          "name": "Insecure Default Variable Initialization",
          "source": "sparse",
          "original_content": "The product, by default, initializes an internal variable with an insecure or less secure value than is possible.",
          "keyphrase_sources": [
            {
              "id": "product:The Wikimedia Foundation Mediawiki",
              "keyphrase": "The Wikimedia Foundation Mediawiki",
              "type": "product"
            }
          ]
        },
        "similarity": 45.07234734607373
      },
      {
        "metadata": {
          "doc_id": "674",
          "name": "Uncontrolled Recursion",
          "source": "sparse",
          "original_content": "The product does not properly control the amount of recursion that takes place,  consuming excessive resources, such as allocated memory or the program stack.",
          "keyphrase_sources": [
            {
              "id": "impact:HTTP DoS",
              "keyphrase": "HTTP DoS",
              "type": "impact"
            },
            {
              "id": "product:The Wikimedia Foundation Mediawiki",
              "keyphrase": "The Wikimedia Foundation Mediawiki",
              "type": "product"
            },
            {
              "id": "component:Mediawiki - GrowthExperiments",
              "keyphrase": "Mediawiki - GrowthExperiments",
              "type": "component"
            }
          ]
        },
        "similarity": 44.95075825958928
      },
      {
        "metadata": {
          "doc_id": "400",
          "name": "Uncontrolled Resource Consumption",
          "source": "sparse",
          "original_content": "The product does not properly control the allocation and maintenance of a limited resource, thereby enabling an actor to influence the amount of resources consumed, eventually leading to the exhaustion of available resources.",
          "keyphrase_sources": [
            {
              "id": "impact:HTTP DoS",
              "keyphrase": "HTTP DoS",
              "type": "impact"
            }
          ]
        },
        "similarity": 41.793559989516254
      },
      {
        "metadata": {
          "doc_id": "524",
          "name": "Use of Cache Containing Sensitive Information",
          "source": "sparse",
          "original_content": "The code uses a cache that contains sensitive information, but the cache can be read by an actor outside of the intended control sphere.",
          "keyphrase_sources": [
            {
              "id": "component:Mediawiki - GrowthExperiments",
              "keyphrase": "Mediawiki - GrowthExperiments",
              "type": "component"
            }
          ]
        },
        "similarity": 36.06347343475687
      }
    ],
    "enhanced_query": "# Vulnerability Description\n\n    Improper **Input Validation vulnerability** in The Wikimedia Foundation Mediawiki - GrowthExperiments allows HTTP DoS.This issue affects Mediawiki - GrowthExperiments from 1.39 through 1.43.\n\n    # Keyphrase-Specific CWE Analysis\n    This vulnerability contains multiple keyphrases that may map to different CWEs. \n    Please analyze each keyphrase separately and determine the most appropriate CWE(s) for each.\n\n    ## ROOTCAUSE: 'Input Validation vulnerability'\n\nRelevant CWEs for this ROOTCAUSE:\n\n### 1. CWE-20: Improper Input Validation (Score: 129.10)\n\nThe product receives input or data, but it does\n        not validate or incorrectly validates that the input has the\n        properties that are required to process the data safely and\n        correctly....\n\n### 2. CWE-1284: Improper Validation of Specified Quantity in Input (Score: 126.51)\n\nThe product receives input that is expected to specify a quantity (such as size or length), but it does not validate or incorrectly validates that the quantity has the required properties....\n\n### 3. CWE-1286: Improper Validation of Syntactic Correctness of Input (Score: 120.65)\n\nThe product receives input that is expected to be well-formed - i.e., to comply with a certain syntax - but it does not validate or incorrectly validates that the input complies with the syntax....\n\n### 4. CWE-1285: Improper Validation of Specified Index, Position, or Offset in Input (Score: 120.18)\n\nThe product receives input that is expected to specify an index, position, or offset into an indexable resource such as a buffer or file, but it does not validate or incorrectly validates that the specified index/position/offset has the required properties....\n\n### 5. CWE-1333: Inefficient Regular Expression Complexity (Score: 118.01)\n\nThe product uses a regular expression with an inefficient, possibly exponential worst-case computational complexity that consumes excessive CPU cycles....\n\n## ROOTCAUSE: 'Improper Input Validation'\n\nRelevant CWEs for this ROOTCAUSE:\n\n### 1. CWE-20: Improper Input Validation (Score: 129.10)\n\nThe product receives input or data, but it does\n        not validate or incorrectly validates that the input has the\n        properties that are required to process the data safely and\n        correctly....\n\n### 2. CWE-1284: Improper Validation of Specified Quantity in Input (Score: 126.51)\n\nThe product receives input that is expected to specify a quantity (such as size or length), but it does not validate or incorrectly validates that the quantity has the required properties....\n\n### 3. CWE-1286: Improper Validation of Syntactic Correctness of Input (Score: 120.65)\n\nThe product receives input that is expected to be well-formed - i.e., to comply with a certain syntax - but it does not validate or incorrectly validates that the input complies with the syntax....\n\n### 4. CWE-1285: Improper Validation of Specified Index, Position, or Offset in Input (Score: 120.18)\n\nThe product receives input that is expected to specify an index, position, or offset into an indexable resource such as a buffer or file, but it does not validate or incorrectly validates that the specified index/position/offset has the required properties....\n\n### 5. CWE-113: Improper Neutralization of CRLF Sequences in HTTP Headers ('HTTP Request/Response Splitting') (Score: 117.18)\n\nThe product receives data from an HTTP agent/component (e.g., web server, proxy, browser, etc.), but it does not neutralize or incorrectly neutralizes CR and LF characters before the data is included in outgoing HTTP headers....\n\n## IMPACT: 'HTTP DoS'\n\nRelevant CWEs for this IMPACT:\n\n### 1. CWE-20: Improper Input Validation (Score: 129.10)\n\nThe product receives input or data, but it does\n        not validate or incorrectly validates that the input has the\n        properties that are required to process the data safely and\n        correctly....\n\n### 2. CWE-1286: Improper Validation of Syntactic Correctness of Input (Score: 120.65)\n\nThe product receives input that is expected to be well-formed - i.e., to comply with a certain syntax - but it does not validate or incorrectly validates that the input complies with the syntax....\n\n### 3. CWE-113: Improper Neutralization of CRLF Sequences in HTTP Headers ('HTTP Request/Response Splitting') (Score: 117.18)\n\nThe product receives data from an HTTP agent/component (e.g., web server, proxy, browser, etc.), but it does not neutralize or incorrectly neutralizes CR and LF characters before the data is included in outgoing HTTP headers....\n\n### 4. CWE-674: Uncontrolled Recursion (Score: 44.95)\n\nThe product does not properly control the amount of recursion that takes place,  consuming excessive resources, such as allocated memory or the program stack....\n\n### 5. CWE-400: Uncontrolled Resource Consumption (Score: 41.79)\n\nThe product does not properly control the allocation and maintenance of a limited resource, thereby enabling an actor to influence the amount of resources consumed, eventually leading to the exhaustion of available resources....\n\n## PRODUCT: 'The Wikimedia Foundation Mediawiki'\n\nRelevant CWEs for this PRODUCT:\n\n### 1. CWE-113: Improper Neutralization of CRLF Sequences in HTTP Headers ('HTTP Request/Response Splitting') (Score: 117.18)\n\nThe product receives data from an HTTP agent/component (e.g., web server, proxy, browser, etc.), but it does not neutralize or incorrectly neutralizes CR and LF characters before the data is included in outgoing HTTP headers....\n\n### 2. CWE-201: Insertion of Sensitive Information Into Sent Data (Score: 51.44)\n\nThe code transmits data to another actor, but a portion of the data includes sensitive information that should not be accessible to that actor....\n\n### 3. CWE-267: Privilege Defined With Unsafe Actions (Score: 48.18)\n\nA particular privilege, role, capability, or right can be used to perform unsafe actions that were not intended, even when it is assigned to the correct entity....\n\n### 4. CWE-453: Insecure Default Variable Initialization (Score: 45.07)\n\nThe product, by default, initializes an internal variable with an insecure or less secure value than is possible....\n\n### 5. CWE-674: Uncontrolled Recursion (Score: 44.95)\n\nThe product does not properly control the amount of recursion that takes place,  consuming excessive resources, such as allocated memory or the program stack....\n\n## VERSION: 'GrowthExperiments from 1.39 through 1.43'\n\nRelevant CWEs for this VERSION:\n\n### 1. CWE-288: Authentication Bypass Using an Alternate Path or Channel (Score: 53.25)\n\nThe product requires authentication, but the product has an alternate path or channel that does not require authentication....\n\n### 2. CWE-820: Missing Synchronization (Score: 53.00)\n\nThe product utilizes a shared resource in a concurrent manner but does not attempt to synchronize access to the resource....\n\n### 3. CWE-201: Insertion of Sensitive Information Into Sent Data (Score: 51.44)\n\nThe code transmits data to another actor, but a portion of the data includes sensitive information that should not be accessible to that actor....\n\n### 4. CWE-912: Hidden Functionality (Score: 51.08)\n\nThe product contains functionality that is not documented, not part of the specification, and not accessible through an interface or command sequence that is obvious to the product's users or administrators....\n\n### 5. CWE-805: Buffer Access with Incorrect Length Value (Score: 48.96)\n\nThe product uses a sequential operation to read or write a buffer, but it uses an incorrect length value that causes it to access memory that is outside of the bounds of the buffer....\n\n## COMPONENT: 'Mediawiki - GrowthExperiments'\n\nRelevant CWEs for this COMPONENT:\n\n### 1. CWE-288: Authentication Bypass Using an Alternate Path or Channel (Score: 53.25)\n\nThe product requires authentication, but the product has an alternate path or channel that does not require authentication....\n\n### 2. CWE-201: Insertion of Sensitive Information Into Sent Data (Score: 51.44)\n\nThe code transmits data to another actor, but a portion of the data includes sensitive information that should not be accessible to that actor....\n\n### 3. CWE-267: Privilege Defined With Unsafe Actions (Score: 48.18)\n\nA particular privilege, role, capability, or right can be used to perform unsafe actions that were not intended, even when it is assigned to the correct entity....\n\n### 4. CWE-674: Uncontrolled Recursion (Score: 44.95)\n\nThe product does not properly control the amount of recursion that takes place,  consuming excessive resources, such as allocated memory or the program stack....\n\n### 5. CWE-524: Use of Cache Containing Sensitive Information (Score: 36.06)\n\nThe code uses a cache that contains sensitive information, but the cache can be read by an actor outside of the intended control sphere....\n\n\n    # Analysis Instructions\n    1. For each keyphrase, identify the most appropriate CWE(s) that represent the weakness.\n    2. Consider how the different keyphrases might relate to each other in the vulnerability chain.\n    3. Provide a final determination of primary CWE(s) and any secondary CWEs.\n    4. Format your response using the standard analysis template.\n\n    Please analyze how these different weaknesses interact and provide a comprehensive CWE classification.\n    "
  },
  "retrieval_time": 1.0617718696594238
}