{
  "vulnerability_info": "VulnerabilityInfo(cve_id='CVE-2024-51656', description='Cross-Site Request Forgery (CSRF) vulnerability in litefeel Flash Show And Hide Box allows Stored **XSS**.This issue affects Flash Show And Hide Box from n/a through 1.6.', key_phrases={'rootcause': 'lack of CSRF protection', 'weakness': ['XSS', 'cross-site scripting'], 'impact': '', 'vector': '', 'attacker': '', 'product': 'litefeel Flash Show And Hide Box', 'version': 'n/a through 1.6', 'component': ''}, reference_content='```\\n{\\n  \"Root cause of vulnerability\": \"The WordPress Flash Show And Hide Box plugin is vulnerable to Cross-Site Request Forgery (CSRF).\",\\n  \"Weaknesses/vulnerabilities present\": \"Cross-Site Request Forgery (CSRF)\",\\n  \"Impact of exploitation\": \"A malicious actor could force higher-privileged users to execute unwanted actions under their current authentication.\",\\n  \"Attack vectors\": \"The vulnerability is exploited by tricking a user into making a request they did not intend.\",\\n  \"Required attacker capabilities/position\": \"The attacker needs to be able to trick a logged-in user into clicking a link or visiting a webpage which triggers a malicious request. The attacker does not need to be authenticated.\"\\n}\\n```', similar_info={'cwe_distribution': {}, 'cwe_consensus': '', 'similarity_stats': {'thresholds': [], 'total_samples_by_threshold': {}, 'top_cwes_by_threshold': {}}}, similarity_summary=SimilarityInsight(consensus_cwe='', top_cwes=[], confidence_levels={}, total_samples=0), analysis='', analysis_with_relationships='', criticism='', resolution='', relevant_cwes=[{'metadata': {'doc_id': '352', 'name': 'Cross-Site Request Forgery (CSRF)', 'source': 'sparse', 'original_content': 'The web application does not, or can not, sufficiently verify whether a well-formed, valid, consistent request was intentionally provided by the user who submitted the request.', 'keyphrase_sources': [{'id': 'rootcause:lack of CSRF protection', 'keyphrase': 'lack of CSRF protection', 'type': 'rootcause'}, {'id': 'weakness:XSS', 'keyphrase': 'XSS', 'type': 'weakness'}, {'id': 'weakness:cross-site scripting', 'keyphrase': 'cross-site scripting', 'type': 'weakness'}, {'id': 'product:litefeel Flash Show And Hide Box', 'keyphrase': 'litefeel Flash Show And Hide Box', 'type': 'product'}, {'id': 'version:n/a through 1.6', 'keyphrase': 'n/a through 1.6', 'type': 'version'}]}, 'similarity': np.float64(297.53616991076615)}, {'metadata': {'doc_id': '434', 'name': 'Unrestricted Upload of File with Dangerous Type', 'source': 'sparse', 'original_content': 'The product allows the upload or transfer of dangerous file types that are automatically processed within its environment.', 'keyphrase_sources': [{'id': 'rootcause:lack of CSRF protection', 'keyphrase': 'lack of CSRF protection', 'type': 'rootcause'}, {'id': 'version:n/a through 1.6', 'keyphrase': 'n/a through 1.6', 'type': 'version'}]}, 'similarity': np.float64(219.27013010871588)}, {'metadata': {'doc_id': '1004', 'name': \"Sensitive Cookie Without 'HttpOnly' Flag\", 'source': 'sparse', 'original_content': 'The product uses a cookie to store sensitive information, but the cookie is not marked with the HttpOnly flag.', 'keyphrase_sources': [{'id': 'rootcause:lack of CSRF protection', 'keyphrase': 'lack of CSRF protection', 'type': 'rootcause'}, {'id': 'weakness:XSS', 'keyphrase': 'XSS', 'type': 'weakness'}, {'id': 'weakness:cross-site scripting', 'keyphrase': 'cross-site scripting', 'type': 'weakness'}, {'id': 'product:litefeel Flash Show And Hide Box', 'keyphrase': 'litefeel Flash Show And Hide Box', 'type': 'product'}, {'id': 'version:n/a through 1.6', 'keyphrase': 'n/a through 1.6', 'type': 'version'}]}, 'similarity': np.float64(218.08831812618024)}, {'metadata': {'doc_id': '79', 'name': \"Improper Neutralization of Input During Web Page Generation ('Cross-site Scripting')\", 'source': 'sparse', 'original_content': 'The product does not neutralize or incorrectly neutralizes user-controllable input before it is placed in output that is used as a web page that is served to other users.', 'keyphrase_sources': [{'id': 'rootcause:lack of CSRF protection', 'keyphrase': 'lack of CSRF protection', 'type': 'rootcause'}, {'id': 'weakness:XSS', 'keyphrase': 'XSS', 'type': 'weakness'}, {'id': 'weakness:cross-site scripting', 'keyphrase': 'cross-site scripting', 'type': 'weakness'}, {'id': 'version:n/a through 1.6', 'keyphrase': 'n/a through 1.6', 'type': 'version'}]}, 'similarity': np.float64(215.37095783690359)}, {'metadata': {'doc_id': '116', 'name': 'Improper Encoding or Escaping of Output', 'source': 'sparse', 'original_content': 'The product prepares a structured message for communication with another component, but encoding or escaping of the data is either missing or done incorrectly. As a result, the intended structure of the message is not preserved.', 'keyphrase_sources': [{'id': 'rootcause:lack of CSRF protection', 'keyphrase': 'lack of CSRF protection', 'type': 'rootcause'}, {'id': 'weakness:XSS', 'keyphrase': 'XSS', 'type': 'weakness'}]}, 'similarity': np.float64(213.29824338970292)}, {'metadata': {'doc_id': '644', 'name': 'Improper Neutralization of HTTP Headers for Scripting Syntax', 'source': 'sparse', 'original_content': 'The product does not neutralize or incorrectly neutralizes web scripting syntax in HTTP headers that can be used by web browser components that can process raw headers, such as Flash.', 'keyphrase_sources': [{'id': 'weakness:cross-site scripting', 'keyphrase': 'cross-site scripting', 'type': 'weakness'}]}, 'similarity': np.float64(207.3545741993043)}, {'metadata': {'doc_id': '942', 'name': 'Permissive Cross-domain Policy with Untrusted Domains', 'source': 'sparse', 'original_content': 'The product uses a cross-domain policy file that includes domains that should not be trusted.', 'keyphrase_sources': [{'id': 'weakness:XSS', 'keyphrase': 'XSS', 'type': 'weakness'}, {'id': 'weakness:cross-site scripting', 'keyphrase': 'cross-site scripting', 'type': 'weakness'}, {'id': 'product:litefeel Flash Show And Hide Box', 'keyphrase': 'litefeel Flash Show And Hide Box', 'type': 'product'}]}, 'similarity': np.float64(166.59917163837355)}, {'metadata': {'doc_id': '451', 'name': 'User Interface (UI) Misrepresentation of Critical Information', 'source': 'sparse', 'original_content': 'The user interface (UI) does not properly represent critical information to the user, allowing the information - or its source - to be obscured or spoofed. This is often a component in phishing attacks.', 'keyphrase_sources': [{'id': 'product:litefeel Flash Show And Hide Box', 'keyphrase': 'litefeel Flash Show And Hide Box', 'type': 'product'}]}, 'similarity': np.float64(93.8065349924827)}, {'metadata': {'doc_id': '22', 'name': \"Improper Limitation of a Pathname to a Restricted Directory ('Path Traversal')\", 'source': 'sparse', 'original_content': 'The product uses external input to construct a pathname that is intended to identify a file or directory that is located underneath a restricted parent directory, but the product does not properly neutralize special elements within the pathname that can cause the pathname to resolve to a location that is outside of the restricted directory.', 'keyphrase_sources': [{'id': 'version:n/a through 1.6', 'keyphrase': 'n/a through 1.6', 'type': 'version'}]}, 'similarity': np.float64(73.18532161962058)}, {'metadata': {'doc_id': '1191', 'name': 'On-Chip Debug and Test Interface With Improper Access Control', 'source': 'sparse', 'original_content': 'The chip does not implement or does not correctly perform access control to check whether users are authorized to access internal registers and test modes through the physical debug/test interface.', 'keyphrase_sources': [{'id': 'product:litefeel Flash Show And Hide Box', 'keyphrase': 'litefeel Flash Show And Hide Box', 'type': 'product'}]}, 'similarity': np.float64(66.25779960196925)}], identified_cwes={'analyzer': [], 'critic_additional': []})",
  "retrieval_results": {
    "has_multiple_keyphrases": true,
    "keyphrase_cwe_sets": {
      "rootcause:lack of CSRF protection": {
        "keyphrase": "lack of CSRF protection",
        "type": "rootcause",
        "cwes": [
          {
            "metadata": {
              "doc_id": "352",
              "name": "Cross-Site Request Forgery (CSRF)",
              "source": "sparse",
              "original_content": "The web application does not, or can not, sufficiently verify whether a well-formed, valid, consistent request was intentionally provided by the user who submitted the request.",
              "keyphrase_sources": [
                {
                  "id": "rootcause:lack of CSRF protection",
                  "keyphrase": "lack of CSRF protection",
                  "type": "rootcause"
                },
                {
                  "id": "weakness:XSS",
                  "keyphrase": "XSS",
                  "type": "weakness"
                },
                {
                  "id": "weakness:cross-site scripting",
                  "keyphrase": "cross-site scripting",
                  "type": "weakness"
                },
                {
                  "id": "product:litefeel Flash Show And Hide Box",
                  "keyphrase": "litefeel Flash Show And Hide Box",
                  "type": "product"
                },
                {
                  "id": "version:n/a through 1.6",
                  "keyphrase": "n/a through 1.6",
                  "type": "version"
                }
              ]
            },
            "similarity": 297.53616991076615
          },
          {
            "metadata": {
              "doc_id": "434",
              "name": "Unrestricted Upload of File with Dangerous Type",
              "source": "sparse",
              "original_content": "The product allows the upload or transfer of dangerous file types that are automatically processed within its environment.",
              "keyphrase_sources": [
                {
                  "id": "rootcause:lack of CSRF protection",
                  "keyphrase": "lack of CSRF protection",
                  "type": "rootcause"
                },
                {
                  "id": "version:n/a through 1.6",
                  "keyphrase": "n/a through 1.6",
                  "type": "version"
                }
              ]
            },
            "similarity": 219.27013010871588
          },
          {
            "metadata": {
              "doc_id": "1004",
              "name": "Sensitive Cookie Without 'HttpOnly' Flag",
              "source": "sparse",
              "original_content": "The product uses a cookie to store sensitive information, but the cookie is not marked with the HttpOnly flag.",
              "keyphrase_sources": [
                {
                  "id": "rootcause:lack of CSRF protection",
                  "keyphrase": "lack of CSRF protection",
                  "type": "rootcause"
                },
                {
                  "id": "weakness:XSS",
                  "keyphrase": "XSS",
                  "type": "weakness"
                },
                {
                  "id": "weakness:cross-site scripting",
                  "keyphrase": "cross-site scripting",
                  "type": "weakness"
                },
                {
                  "id": "product:litefeel Flash Show And Hide Box",
                  "keyphrase": "litefeel Flash Show And Hide Box",
                  "type": "product"
                },
                {
                  "id": "version:n/a through 1.6",
                  "keyphrase": "n/a through 1.6",
                  "type": "version"
                }
              ]
            },
            "similarity": 218.08831812618024
          },
          {
            "metadata": {
              "doc_id": "79",
              "name": "Improper Neutralization of Input During Web Page Generation ('Cross-site Scripting')",
              "source": "sparse",
              "original_content": "The product does not neutralize or incorrectly neutralizes user-controllable input before it is placed in output that is used as a web page that is served to other users.",
              "keyphrase_sources": [
                {
                  "id": "rootcause:lack of CSRF protection",
                  "keyphrase": "lack of CSRF protection",
                  "type": "rootcause"
                },
                {
                  "id": "weakness:XSS",
                  "keyphrase": "XSS",
                  "type": "weakness"
                },
                {
                  "id": "weakness:cross-site scripting",
                  "keyphrase": "cross-site scripting",
                  "type": "weakness"
                },
                {
                  "id": "version:n/a through 1.6",
                  "keyphrase": "n/a through 1.6",
                  "type": "version"
                }
              ]
            },
            "similarity": 215.37095783690359
          },
          {
            "metadata": {
              "doc_id": "116",
              "name": "Improper Encoding or Escaping of Output",
              "source": "sparse",
              "original_content": "The product prepares a structured message for communication with another component, but encoding or escaping of the data is either missing or done incorrectly. As a result, the intended structure of the message is not preserved.",
              "keyphrase_sources": [
                {
                  "id": "rootcause:lack of CSRF protection",
                  "keyphrase": "lack of CSRF protection",
                  "type": "rootcause"
                },
                {
                  "id": "weakness:XSS",
                  "keyphrase": "XSS",
                  "type": "weakness"
                }
              ]
            },
            "similarity": 213.29824338970292
          }
        ]
      },
      "weakness:XSS": {
        "keyphrase": "XSS",
        "type": "weakness",
        "cwes": [
          {
            "metadata": {
              "doc_id": "352",
              "name": "Cross-Site Request Forgery (CSRF)",
              "source": "sparse",
              "original_content": "The web application does not, or can not, sufficiently verify whether a well-formed, valid, consistent request was intentionally provided by the user who submitted the request."
            },
            "similarity": 205.45886969266803
          },
          {
            "metadata": {
              "doc_id": "79",
              "name": "Improper Neutralization of Input During Web Page Generation ('Cross-site Scripting')",
              "source": "sparse",
              "original_content": "The product does not neutralize or incorrectly neutralizes user-controllable input before it is placed in output that is used as a web page that is served to other users."
            },
            "similarity": 182.77528531475124
          },
          {
            "metadata": {
              "doc_id": "1004",
              "name": "Sensitive Cookie Without 'HttpOnly' Flag",
              "source": "sparse",
              "original_content": "The product uses a cookie to store sensitive information, but the cookie is not marked with the HttpOnly flag."
            },
            "similarity": 182.4472162058861
          },
          {
            "metadata": {
              "doc_id": "942",
              "name": "Permissive Cross-domain Policy with Untrusted Domains",
              "source": "sparse",
              "original_content": "The product uses a cross-domain policy file that includes domains that should not be trusted.",
              "keyphrase_sources": [
                {
                  "id": "weakness:XSS",
                  "keyphrase": "XSS",
                  "type": "weakness"
                },
                {
                  "id": "weakness:cross-site scripting",
                  "keyphrase": "cross-site scripting",
                  "type": "weakness"
                },
                {
                  "id": "product:litefeel Flash Show And Hide Box",
                  "keyphrase": "litefeel Flash Show And Hide Box",
                  "type": "product"
                }
              ]
            },
            "similarity": 166.59917163837355
          },
          {
            "metadata": {
              "doc_id": "116",
              "name": "Improper Encoding or Escaping of Output",
              "source": "sparse",
              "original_content": "The product prepares a structured message for communication with another component, but encoding or escaping of the data is either missing or done incorrectly. As a result, the intended structure of the message is not preserved."
            },
            "similarity": 158.51507491133685
          }
        ]
      },
      "weakness:cross-site scripting": {
        "keyphrase": "cross-site scripting",
        "type": "weakness",
        "cwes": [
          {
            "metadata": {
              "doc_id": "352",
              "name": "Cross-Site Request Forgery (CSRF)",
              "source": "sparse",
              "original_content": "The web application does not, or can not, sufficiently verify whether a well-formed, valid, consistent request was intentionally provided by the user who submitted the request."
            },
            "similarity": 273.4820149688039
          },
          {
            "metadata": {
              "doc_id": "79",
              "name": "Improper Neutralization of Input During Web Page Generation ('Cross-site Scripting')",
              "source": "sparse",
              "original_content": "The product does not neutralize or incorrectly neutralizes user-controllable input before it is placed in output that is used as a web page that is served to other users."
            },
            "similarity": 244.74007667163738
          },
          {
            "metadata": {
              "doc_id": "942",
              "name": "Permissive Cross-domain Policy with Untrusted Domains",
              "source": "sparse",
              "original_content": "The product uses a cross-domain policy file that includes domains that should not be trusted."
            },
            "similarity": 235.58931696771756
          },
          {
            "metadata": {
              "doc_id": "1004",
              "name": "Sensitive Cookie Without 'HttpOnly' Flag",
              "source": "sparse",
              "original_content": "The product uses a cookie to store sensitive information, but the cookie is not marked with the HttpOnly flag."
            },
            "similarity": 226.99899295203082
          },
          {
            "metadata": {
              "doc_id": "644",
              "name": "Improper Neutralization of HTTP Headers for Scripting Syntax",
              "source": "sparse",
              "original_content": "The product does not neutralize or incorrectly neutralizes web scripting syntax in HTTP headers that can be used by web browser components that can process raw headers, such as Flash.",
              "keyphrase_sources": [
                {
                  "id": "weakness:cross-site scripting",
                  "keyphrase": "cross-site scripting",
                  "type": "weakness"
                }
              ]
            },
            "similarity": 207.3545741993043
          }
        ]
      },
      "product:litefeel Flash Show And Hide Box": {
        "keyphrase": "litefeel Flash Show And Hide Box",
        "type": "product",
        "cwes": [
          {
            "metadata": {
              "doc_id": "451",
              "name": "User Interface (UI) Misrepresentation of Critical Information",
              "source": "sparse",
              "original_content": "The user interface (UI) does not properly represent critical information to the user, allowing the information - or its source - to be obscured or spoofed. This is often a component in phishing attacks.",
              "keyphrase_sources": [
                {
                  "id": "product:litefeel Flash Show And Hide Box",
                  "keyphrase": "litefeel Flash Show And Hide Box",
                  "type": "product"
                }
              ]
            },
            "similarity": 93.8065349924827
          },
          {
            "metadata": {
              "doc_id": "942",
              "name": "Permissive Cross-domain Policy with Untrusted Domains",
              "source": "sparse",
              "original_content": "The product uses a cross-domain policy file that includes domains that should not be trusted."
            },
            "similarity": 75.20557199509261
          },
          {
            "metadata": {
              "doc_id": "352",
              "name": "Cross-Site Request Forgery (CSRF)",
              "source": "sparse",
              "original_content": "The web application does not, or can not, sufficiently verify whether a well-formed, valid, consistent request was intentionally provided by the user who submitted the request."
            },
            "similarity": 72.91549647626866
          },
          {
            "metadata": {
              "doc_id": "1004",
              "name": "Sensitive Cookie Without 'HttpOnly' Flag",
              "source": "sparse",
              "original_content": "The product uses a cookie to store sensitive information, but the cookie is not marked with the HttpOnly flag."
            },
            "similarity": 69.19067953808522
          },
          {
            "metadata": {
              "doc_id": "1191",
              "name": "On-Chip Debug and Test Interface With Improper Access Control",
              "source": "sparse",
              "original_content": "The chip does not implement or does not correctly perform access control to check whether users are authorized to access internal registers and test modes through the physical debug/test interface.",
              "keyphrase_sources": [
                {
                  "id": "product:litefeel Flash Show And Hide Box",
                  "keyphrase": "litefeel Flash Show And Hide Box",
                  "type": "product"
                }
              ]
            },
            "similarity": 66.25779960196925
          }
        ]
      },
      "version:n/a through 1.6": {
        "keyphrase": "n/a through 1.6",
        "type": "version",
        "cwes": [
          {
            "metadata": {
              "doc_id": "352",
              "name": "Cross-Site Request Forgery (CSRF)",
              "source": "sparse",
              "original_content": "The web application does not, or can not, sufficiently verify whether a well-formed, valid, consistent request was intentionally provided by the user who submitted the request."
            },
            "similarity": 79.51889518861057
          },
          {
            "metadata": {
              "doc_id": "22",
              "name": "Improper Limitation of a Pathname to a Restricted Directory ('Path Traversal')",
              "source": "sparse",
              "original_content": "The product uses external input to construct a pathname that is intended to identify a file or directory that is located underneath a restricted parent directory, but the product does not properly neutralize special elements within the pathname that can cause the pathname to resolve to a location that is outside of the restricted directory.",
              "keyphrase_sources": [
                {
                  "id": "version:n/a through 1.6",
                  "keyphrase": "n/a through 1.6",
                  "type": "version"
                }
              ]
            },
            "similarity": 73.18532161962058
          },
          {
            "metadata": {
              "doc_id": "1004",
              "name": "Sensitive Cookie Without 'HttpOnly' Flag",
              "source": "sparse",
              "original_content": "The product uses a cookie to store sensitive information, but the cookie is not marked with the HttpOnly flag."
            },
            "similarity": 71.0507947228208
          },
          {
            "metadata": {
              "doc_id": "79",
              "name": "Improper Neutralization of Input During Web Page Generation ('Cross-site Scripting')",
              "source": "sparse",
              "original_content": "The product does not neutralize or incorrectly neutralizes user-controllable input before it is placed in output that is used as a web page that is served to other users."
            },
            "similarity": 68.92813592421662
          },
          {
            "metadata": {
              "doc_id": "434",
              "name": "Unrestricted Upload of File with Dangerous Type",
              "source": "sparse",
              "original_content": "The product allows the upload or transfer of dangerous file types that are automatically processed within its environment."
            },
            "similarity": 67.38213537023304
          }
        ]
      }
    },
    "keyphrase_mapping": {
      "352": [
        {
          "id": "rootcause:lack of CSRF protection",
          "keyphrase": "lack of CSRF protection",
          "type": "rootcause"
        },
        {
          "id": "weakness:XSS",
          "keyphrase": "XSS",
          "type": "weakness"
        },
        {
          "id": "weakness:cross-site scripting",
          "keyphrase": "cross-site scripting",
          "type": "weakness"
        },
        {
          "id": "product:litefeel Flash Show And Hide Box",
          "keyphrase": "litefeel Flash Show And Hide Box",
          "type": "product"
        },
        {
          "id": "version:n/a through 1.6",
          "keyphrase": "n/a through 1.6",
          "type": "version"
        }
      ],
      "434": [
        {
          "id": "rootcause:lack of CSRF protection",
          "keyphrase": "lack of CSRF protection",
          "type": "rootcause"
        },
        {
          "id": "version:n/a through 1.6",
          "keyphrase": "n/a through 1.6",
          "type": "version"
        }
      ],
      "1004": [
        {
          "id": "rootcause:lack of CSRF protection",
          "keyphrase": "lack of CSRF protection",
          "type": "rootcause"
        },
        {
          "id": "weakness:XSS",
          "keyphrase": "XSS",
          "type": "weakness"
        },
        {
          "id": "weakness:cross-site scripting",
          "keyphrase": "cross-site scripting",
          "type": "weakness"
        },
        {
          "id": "product:litefeel Flash Show And Hide Box",
          "keyphrase": "litefeel Flash Show And Hide Box",
          "type": "product"
        },
        {
          "id": "version:n/a through 1.6",
          "keyphrase": "n/a through 1.6",
          "type": "version"
        }
      ],
      "79": [
        {
          "id": "rootcause:lack of CSRF protection",
          "keyphrase": "lack of CSRF protection",
          "type": "rootcause"
        },
        {
          "id": "weakness:XSS",
          "keyphrase": "XSS",
          "type": "weakness"
        },
        {
          "id": "weakness:cross-site scripting",
          "keyphrase": "cross-site scripting",
          "type": "weakness"
        },
        {
          "id": "version:n/a through 1.6",
          "keyphrase": "n/a through 1.6",
          "type": "version"
        }
      ],
      "116": [
        {
          "id": "rootcause:lack of CSRF protection",
          "keyphrase": "lack of CSRF protection",
          "type": "rootcause"
        },
        {
          "id": "weakness:XSS",
          "keyphrase": "XSS",
          "type": "weakness"
        }
      ],
      "942": [
        {
          "id": "weakness:XSS",
          "keyphrase": "XSS",
          "type": "weakness"
        },
        {
          "id": "weakness:cross-site scripting",
          "keyphrase": "cross-site scripting",
          "type": "weakness"
        },
        {
          "id": "product:litefeel Flash Show And Hide Box",
          "keyphrase": "litefeel Flash Show And Hide Box",
          "type": "product"
        }
      ],
      "644": [
        {
          "id": "weakness:cross-site scripting",
          "keyphrase": "cross-site scripting",
          "type": "weakness"
        }
      ],
      "451": [
        {
          "id": "product:litefeel Flash Show And Hide Box",
          "keyphrase": "litefeel Flash Show And Hide Box",
          "type": "product"
        }
      ],
      "1191": [
        {
          "id": "product:litefeel Flash Show And Hide Box",
          "keyphrase": "litefeel Flash Show And Hide Box",
          "type": "product"
        }
      ],
      "22": [
        {
          "id": "version:n/a through 1.6",
          "keyphrase": "n/a through 1.6",
          "type": "version"
        }
      ]
    },
    "relevant_cwes": [
      {
        "metadata": {
          "doc_id": "352",
          "name": "Cross-Site Request Forgery (CSRF)",
          "source": "sparse",
          "original_content": "The web application does not, or can not, sufficiently verify whether a well-formed, valid, consistent request was intentionally provided by the user who submitted the request.",
          "keyphrase_sources": [
            {
              "id": "rootcause:lack of CSRF protection",
              "keyphrase": "lack of CSRF protection",
              "type": "rootcause"
            },
            {
              "id": "weakness:XSS",
              "keyphrase": "XSS",
              "type": "weakness"
            },
            {
              "id": "weakness:cross-site scripting",
              "keyphrase": "cross-site scripting",
              "type": "weakness"
            },
            {
              "id": "product:litefeel Flash Show And Hide Box",
              "keyphrase": "litefeel Flash Show And Hide Box",
              "type": "product"
            },
            {
              "id": "version:n/a through 1.6",
              "keyphrase": "n/a through 1.6",
              "type": "version"
            }
          ]
        },
        "similarity": 297.53616991076615
      },
      {
        "metadata": {
          "doc_id": "434",
          "name": "Unrestricted Upload of File with Dangerous Type",
          "source": "sparse",
          "original_content": "The product allows the upload or transfer of dangerous file types that are automatically processed within its environment.",
          "keyphrase_sources": [
            {
              "id": "rootcause:lack of CSRF protection",
              "keyphrase": "lack of CSRF protection",
              "type": "rootcause"
            },
            {
              "id": "version:n/a through 1.6",
              "keyphrase": "n/a through 1.6",
              "type": "version"
            }
          ]
        },
        "similarity": 219.27013010871588
      },
      {
        "metadata": {
          "doc_id": "1004",
          "name": "Sensitive Cookie Without 'HttpOnly' Flag",
          "source": "sparse",
          "original_content": "The product uses a cookie to store sensitive information, but the cookie is not marked with the HttpOnly flag.",
          "keyphrase_sources": [
            {
              "id": "rootcause:lack of CSRF protection",
              "keyphrase": "lack of CSRF protection",
              "type": "rootcause"
            },
            {
              "id": "weakness:XSS",
              "keyphrase": "XSS",
              "type": "weakness"
            },
            {
              "id": "weakness:cross-site scripting",
              "keyphrase": "cross-site scripting",
              "type": "weakness"
            },
            {
              "id": "product:litefeel Flash Show And Hide Box",
              "keyphrase": "litefeel Flash Show And Hide Box",
              "type": "product"
            },
            {
              "id": "version:n/a through 1.6",
              "keyphrase": "n/a through 1.6",
              "type": "version"
            }
          ]
        },
        "similarity": 218.08831812618024
      },
      {
        "metadata": {
          "doc_id": "79",
          "name": "Improper Neutralization of Input During Web Page Generation ('Cross-site Scripting')",
          "source": "sparse",
          "original_content": "The product does not neutralize or incorrectly neutralizes user-controllable input before it is placed in output that is used as a web page that is served to other users.",
          "keyphrase_sources": [
            {
              "id": "rootcause:lack of CSRF protection",
              "keyphrase": "lack of CSRF protection",
              "type": "rootcause"
            },
            {
              "id": "weakness:XSS",
              "keyphrase": "XSS",
              "type": "weakness"
            },
            {
              "id": "weakness:cross-site scripting",
              "keyphrase": "cross-site scripting",
              "type": "weakness"
            },
            {
              "id": "version:n/a through 1.6",
              "keyphrase": "n/a through 1.6",
              "type": "version"
            }
          ]
        },
        "similarity": 215.37095783690359
      },
      {
        "metadata": {
          "doc_id": "116",
          "name": "Improper Encoding or Escaping of Output",
          "source": "sparse",
          "original_content": "The product prepares a structured message for communication with another component, but encoding or escaping of the data is either missing or done incorrectly. As a result, the intended structure of the message is not preserved.",
          "keyphrase_sources": [
            {
              "id": "rootcause:lack of CSRF protection",
              "keyphrase": "lack of CSRF protection",
              "type": "rootcause"
            },
            {
              "id": "weakness:XSS",
              "keyphrase": "XSS",
              "type": "weakness"
            }
          ]
        },
        "similarity": 213.29824338970292
      },
      {
        "metadata": {
          "doc_id": "644",
          "name": "Improper Neutralization of HTTP Headers for Scripting Syntax",
          "source": "sparse",
          "original_content": "The product does not neutralize or incorrectly neutralizes web scripting syntax in HTTP headers that can be used by web browser components that can process raw headers, such as Flash.",
          "keyphrase_sources": [
            {
              "id": "weakness:cross-site scripting",
              "keyphrase": "cross-site scripting",
              "type": "weakness"
            }
          ]
        },
        "similarity": 207.3545741993043
      },
      {
        "metadata": {
          "doc_id": "942",
          "name": "Permissive Cross-domain Policy with Untrusted Domains",
          "source": "sparse",
          "original_content": "The product uses a cross-domain policy file that includes domains that should not be trusted.",
          "keyphrase_sources": [
            {
              "id": "weakness:XSS",
              "keyphrase": "XSS",
              "type": "weakness"
            },
            {
              "id": "weakness:cross-site scripting",
              "keyphrase": "cross-site scripting",
              "type": "weakness"
            },
            {
              "id": "product:litefeel Flash Show And Hide Box",
              "keyphrase": "litefeel Flash Show And Hide Box",
              "type": "product"
            }
          ]
        },
        "similarity": 166.59917163837355
      },
      {
        "metadata": {
          "doc_id": "451",
          "name": "User Interface (UI) Misrepresentation of Critical Information",
          "source": "sparse",
          "original_content": "The user interface (UI) does not properly represent critical information to the user, allowing the information - or its source - to be obscured or spoofed. This is often a component in phishing attacks.",
          "keyphrase_sources": [
            {
              "id": "product:litefeel Flash Show And Hide Box",
              "keyphrase": "litefeel Flash Show And Hide Box",
              "type": "product"
            }
          ]
        },
        "similarity": 93.8065349924827
      },
      {
        "metadata": {
          "doc_id": "22",
          "name": "Improper Limitation of a Pathname to a Restricted Directory ('Path Traversal')",
          "source": "sparse",
          "original_content": "The product uses external input to construct a pathname that is intended to identify a file or directory that is located underneath a restricted parent directory, but the product does not properly neutralize special elements within the pathname that can cause the pathname to resolve to a location that is outside of the restricted directory.",
          "keyphrase_sources": [
            {
              "id": "version:n/a through 1.6",
              "keyphrase": "n/a through 1.6",
              "type": "version"
            }
          ]
        },
        "similarity": 73.18532161962058
      },
      {
        "metadata": {
          "doc_id": "1191",
          "name": "On-Chip Debug and Test Interface With Improper Access Control",
          "source": "sparse",
          "original_content": "The chip does not implement or does not correctly perform access control to check whether users are authorized to access internal registers and test modes through the physical debug/test interface.",
          "keyphrase_sources": [
            {
              "id": "product:litefeel Flash Show And Hide Box",
              "keyphrase": "litefeel Flash Show And Hide Box",
              "type": "product"
            }
          ]
        },
        "similarity": 66.25779960196925
      }
    ],
    "enhanced_query": "# Vulnerability Description\n\n    Cross-Site Request Forgery (CSRF) vulnerability in litefeel Flash Show And Hide Box allows Stored **XSS**.This issue affects Flash Show And Hide Box from n/a through 1.6.\n\n    # Keyphrase-Specific CWE Analysis\n    This vulnerability contains multiple keyphrases that may map to different CWEs. \n    Please analyze each keyphrase separately and determine the most appropriate CWE(s) for each.\n\n    ## ROOTCAUSE: 'lack of CSRF protection'\n\nRelevant CWEs for this ROOTCAUSE:\n\n### 1. CWE-352: Cross-Site Request Forgery (CSRF) (Score: 297.54)\n\nThe web application does not, or can not, sufficiently verify whether a well-formed, valid, consistent request was intentionally provided by the user who submitted the request....\n\n### 2. CWE-434: Unrestricted Upload of File with Dangerous Type (Score: 219.27)\n\nThe product allows the upload or transfer of dangerous file types that are automatically processed within its environment....\n\n### 3. CWE-1004: Sensitive Cookie Without 'HttpOnly' Flag (Score: 218.09)\n\nThe product uses a cookie to store sensitive information, but the cookie is not marked with the HttpOnly flag....\n\n### 4. CWE-79: Improper Neutralization of Input During Web Page Generation ('Cross-site Scripting') (Score: 215.37)\n\nThe product does not neutralize or incorrectly neutralizes user-controllable input before it is placed in output that is used as a web page that is served to other users....\n\n### 5. CWE-116: Improper Encoding or Escaping of Output (Score: 213.30)\n\nThe product prepares a structured message for communication with another component, but encoding or escaping of the data is either missing or done incorrectly. As a result, the intended structure of the message is not preserved....\n\n## WEAKNESS: 'XSS'\n\nRelevant CWEs for this WEAKNESS:\n\n### 1. CWE-352: Cross-Site Request Forgery (CSRF) (Score: 297.54)\n\nThe web application does not, or can not, sufficiently verify whether a well-formed, valid, consistent request was intentionally provided by the user who submitted the request....\n\n### 2. CWE-1004: Sensitive Cookie Without 'HttpOnly' Flag (Score: 218.09)\n\nThe product uses a cookie to store sensitive information, but the cookie is not marked with the HttpOnly flag....\n\n### 3. CWE-79: Improper Neutralization of Input During Web Page Generation ('Cross-site Scripting') (Score: 215.37)\n\nThe product does not neutralize or incorrectly neutralizes user-controllable input before it is placed in output that is used as a web page that is served to other users....\n\n### 4. CWE-116: Improper Encoding or Escaping of Output (Score: 213.30)\n\nThe product prepares a structured message for communication with another component, but encoding or escaping of the data is either missing or done incorrectly. As a result, the intended structure of the message is not preserved....\n\n### 5. CWE-942: Permissive Cross-domain Policy with Untrusted Domains (Score: 166.60)\n\nThe product uses a cross-domain policy file that includes domains that should not be trusted....\n\n## WEAKNESS: 'cross-site scripting'\n\nRelevant CWEs for this WEAKNESS:\n\n### 1. CWE-352: Cross-Site Request Forgery (CSRF) (Score: 297.54)\n\nThe web application does not, or can not, sufficiently verify whether a well-formed, valid, consistent request was intentionally provided by the user who submitted the request....\n\n### 2. CWE-1004: Sensitive Cookie Without 'HttpOnly' Flag (Score: 218.09)\n\nThe product uses a cookie to store sensitive information, but the cookie is not marked with the HttpOnly flag....\n\n### 3. CWE-79: Improper Neutralization of Input During Web Page Generation ('Cross-site Scripting') (Score: 215.37)\n\nThe product does not neutralize or incorrectly neutralizes user-controllable input before it is placed in output that is used as a web page that is served to other users....\n\n### 4. CWE-644: Improper Neutralization of HTTP Headers for Scripting Syntax (Score: 207.35)\n\nThe product does not neutralize or incorrectly neutralizes web scripting syntax in HTTP headers that can be used by web browser components that can process raw headers, such as Flash....\n\n### 5. CWE-942: Permissive Cross-domain Policy with Untrusted Domains (Score: 166.60)\n\nThe product uses a cross-domain policy file that includes domains that should not be trusted....\n\n## PRODUCT: 'litefeel Flash Show And Hide Box'\n\nRelevant CWEs for this PRODUCT:\n\n### 1. CWE-352: Cross-Site Request Forgery (CSRF) (Score: 297.54)\n\nThe web application does not, or can not, sufficiently verify whether a well-formed, valid, consistent request was intentionally provided by the user who submitted the request....\n\n### 2. CWE-1004: Sensitive Cookie Without 'HttpOnly' Flag (Score: 218.09)\n\nThe product uses a cookie to store sensitive information, but the cookie is not marked with the HttpOnly flag....\n\n### 3. CWE-942: Permissive Cross-domain Policy with Untrusted Domains (Score: 166.60)\n\nThe product uses a cross-domain policy file that includes domains that should not be trusted....\n\n### 4. CWE-451: User Interface (UI) Misrepresentation of Critical Information (Score: 93.81)\n\nThe user interface (UI) does not properly represent critical information to the user, allowing the information - or its source - to be obscured or spoofed. This is often a component in phishing attacks....\n\n### 5. CWE-1191: On-Chip Debug and Test Interface With Improper Access Control (Score: 66.26)\n\nThe chip does not implement or does not correctly perform access control to check whether users are authorized to access internal registers and test modes through the physical debug/test interface....\n\n## VERSION: 'n/a through 1.6'\n\nRelevant CWEs for this VERSION:\n\n### 1. CWE-352: Cross-Site Request Forgery (CSRF) (Score: 297.54)\n\nThe web application does not, or can not, sufficiently verify whether a well-formed, valid, consistent request was intentionally provided by the user who submitted the request....\n\n### 2. CWE-434: Unrestricted Upload of File with Dangerous Type (Score: 219.27)\n\nThe product allows the upload or transfer of dangerous file types that are automatically processed within its environment....\n\n### 3. CWE-1004: Sensitive Cookie Without 'HttpOnly' Flag (Score: 218.09)\n\nThe product uses a cookie to store sensitive information, but the cookie is not marked with the HttpOnly flag....\n\n### 4. CWE-79: Improper Neutralization of Input During Web Page Generation ('Cross-site Scripting') (Score: 215.37)\n\nThe product does not neutralize or incorrectly neutralizes user-controllable input before it is placed in output that is used as a web page that is served to other users....\n\n### 5. CWE-22: Improper Limitation of a Pathname to a Restricted Directory ('Path Traversal') (Score: 73.19)\n\nThe product uses external input to construct a pathname that is intended to identify a file or directory that is located underneath a restricted parent directory, but the product does not properly neutralize special elements within the pathname that can cause the pathname to resolve to a location th...\n\n\n    # Analysis Instructions\n    1. For each keyphrase, identify the most appropriate CWE(s) that represent the weakness.\n    2. Consider how the different keyphrases might relate to each other in the vulnerability chain.\n    3. Provide a final determination of primary CWE(s) and any secondary CWEs.\n    4. Format your response using the standard analysis template.\n\n    Please analyze how these different weaknesses interact and provide a comprehensive CWE classification.\n    "
  },
  "retrieval_time": 0.9913694858551025
}