{
  "vulnerability_info": "VulnerabilityInfo(cve_id='CVE-2024-13606', description='The JS Help Desk The Ultimate Help Desk & Support Plugin plugin for WordPress is vulnerable to **Sensitive Information Exposure** in all versions up to, and including, 2.8.8 via the jssupportticketdata directory. This makes it possible for unauthenticated attackers to extract sensitive data stored insecurely in the /wp-content/uploads/jssupportticketdata directory which can contain file attachments included in support tickets.', key_phrases={'rootcause': 'insecure file access permissions', 'weakness': ['Sensitive Information Exposure', 'sensitive data disclosure', 'information disclosure'], 'impact': 'extract sensitive data', 'vector': 'unauthenticated access to jssupportticketdata directory', 'attacker': 'unauthenticated attackers', 'product': 'JS Help Desk', 'version': 'all versions up to and including 2.8.8', 'component': '/wp-content/uploads/jssupportticketdata directory'}, reference_content=\"Based on the provided content, here's an analysis related to potential vulnerabilities, keeping in mind the need to adhere to the guidelines:\\n\\n**CVE ID:** CVE-2024-13606 (PLACEHOLDER - Implement CVE description retrieval)\\n\\n**Analysis:**\\n\\nThe code snippet is from the `uploads.php` file within the `js-support-ticket` WordPress plugin (version 2.8.8). It handles file uploads for various functionalities within the plugin: tickets, articles, downloads, categories, agent profiles, and desktop notifications.\\n\\n**Root cause of vulnerability:**\\n\\nThe code appears to have several potential vulnerabilities related to file uploads, specifically:\\n\\n*   **Unrestricted File Uploads:** The code checks file extensions against a configuration value (`$document_file_types`, `$image_file_types`), but it's possible this check can be bypassed or is insufficient.  The use of `wp_check_filetype` is a good start, but the configuration itself needs to be carefully managed.\\n*   **Path Traversal:** The code constructs file paths based on user-provided data (e.g., `$this->ticketid`, `$this->articleid`, `$foldername`). While it attempts to sanitize with `esc_sql` and `sanitize_file_name`, improper handling could lead to path traversal vulnerabilities, allowing attackers to write files outside the intended directories.\\n*   **File Size Limitations:** The code checks file size against `$filesize` (configured in `jssupportticket::$_config['file_maximum_size']`), but the configuration itself might be vulnerable to manipulation.\\n*   **Lack of Input Validation/Sanitization:** The code uses `JSST_sanitizeData()` which is described as using WordPress sanitize functions, but the specific sanitization applied to various inputs (e.g., file names, types) needs to be thoroughly reviewed.\\n*   **Use of `wp_handle_upload`:** While `wp_handle_upload` is a WordPress function designed for secure uploads, its security relies on proper configuration and usage.  The code relies heavily on this function, and any misconfiguration or improper handling of its results could introduce vulnerabilities.\\n\\n**Weaknesses/vulnerabilities present:**\\n\\n*   CWE-431: Insufficient Restriction of Operations within the Bounds of a Safe Operation\\n*   CWE-78: Improper Neutralization of Special Elements used in an OS Command ('Command Injection') - potential path traversal.\\n*   CWE-20: Improper Input Validation\\n*   CWE-73: External Control of File Name or Path\\n\\n**Impact of exploitation:**\\n\\nSuccessful exploitation could lead to:\\n\\n*   **Remote Code Execution (RCE):**  If an attacker can upload a malicious file (e.g., a PHP script) and execute it, they could gain control of the server.\\n*   **Cross-Site Scripting (XSS):** If an attacker can upload a file containing malicious JavaScript code, they could inject it into the website and compromise user accounts.\\n*   **Denial of Service (DoS):**  Uploading large or malicious files could exhaust server resources and cause a denial of service.\\n*   **Information Disclosure:**  An attacker might be able to access sensitive files or information stored on the server.\\n\\n**Attack vectors:**\\n\\n*   Uploading files through the ticket attachment functionality (`storeTicketAttachment`).\\n*   Uploading files through the article attachment functionality (`storeArticleAttachment`).\\n*   Uploading files through the download attachment functionality (`storeDownloadAttachment`).\\n*   Uploading category logos (`uploadCategoryLogo`).\\n*   Uploading staff logos (`uploadStaffLogo`).\\n*   Uploading files via custom fields (`storeTicketCustomUploadFile`).\\n*   Uploading internal note attachments.\\n*   Uploading desktop notification logos (`uploadDesktopNotificationLogo`).\\n\\n**Required attacker capabilities/position:**\\n\\n*   An attacker would need to be able to upload files to the server, which typically requires at least a low-privilege user account (e.g., a registered user who can submit tickets).\\n*   Knowledge of file upload mechanisms and potential vulnerabilities.\\n*   Ability to craft malicious files that bypass security checks.\\n\\n**Mitigation or fix:**\\n\\n*   **Strict File Type Validation:** Implement a robust whitelist of allowed file types and reject any files that do not match the whitelist.  Do not rely solely on file extensions. Use `wp_check_filetype` and verify the MIME type.\\n*   **Strong Path Sanitization:**  Thoroughly sanitize all user-provided data used to construct file paths. Use `wp_normalize_path` to remove any potentially malicious characters.\\n*   **Secure File Storage:** Store uploaded files outside the webroot or in a directory with restricted access permissions.\\n*   **Regular Security Audits:** Conduct regular security audits of the code to identify and address potential vulnerabilities.\\n*   **Keep Plugin Updated:** Ensure the plugin is updated to the latest version to benefit from any security fixes.\\n*   **Content Security Policy (CSP):** Implement a CSP to mitigate the risk of XSS attacks.\\n*   **Limit File Size:** Enforce strict file size limits.\\n*   **Disable Unnecessary Upload Functionality:** If certain upload features are not needed, disable them to reduce the attack surface.\\n\\n**Note:** This analysis is based solely on the provided code snippet. A complete security assessment would require a more comprehensive review of the entire plugin and its interactions with the WordPress environment. The content provides more detail than the official CVE description (which is currently a placeholder).\", similar_info={'cwe_distribution': {}, 'cwe_consensus': '', 'similarity_stats': {'thresholds': [], 'total_samples_by_threshold': {}, 'top_cwes_by_threshold': {}}}, similarity_summary=SimilarityInsight(consensus_cwe='', top_cwes=[], confidence_levels={}, total_samples=0), analysis='', analysis_with_relationships='', criticism='', resolution='', relevant_cwes=[{'metadata': {'doc_id': '639', 'name': 'Authorization Bypass Through User-Controlled Key', 'source': 'sparse', 'original_content': \"The system's authorization functionality does not prevent one user from gaining access to another user's data or record by modifying the key value identifying the data.\", 'keyphrase_sources': [{'id': 'rootcause:insecure file access permissions', 'keyphrase': 'insecure file access permissions', 'type': 'rootcause'}, {'id': 'weakness:Sensitive Information Exposure', 'keyphrase': 'Sensitive Information Exposure', 'type': 'weakness'}, {'id': 'weakness:sensitive data disclosure', 'keyphrase': 'sensitive data disclosure', 'type': 'weakness'}, {'id': 'weakness:information disclosure', 'keyphrase': 'information disclosure', 'type': 'weakness'}, {'id': 'impact:extract sensitive data', 'keyphrase': 'extract sensitive data', 'type': 'impact'}, {'id': 'attacker:unauthenticated attackers', 'keyphrase': 'unauthenticated attackers', 'type': 'attacker'}, {'id': 'product:JS Help Desk', 'keyphrase': 'JS Help Desk', 'type': 'product'}]}, 'similarity': np.float64(393.07069704438493)}, {'metadata': {'doc_id': '425', 'name': \"Direct Request ('Forced Browsing')\", 'source': 'sparse', 'original_content': 'The web application does not adequately enforce appropriate authorization on all restricted URLs, scripts, or files.', 'keyphrase_sources': [{'id': 'rootcause:insecure file access permissions', 'keyphrase': 'insecure file access permissions', 'type': 'rootcause'}, {'id': 'weakness:Sensitive Information Exposure', 'keyphrase': 'Sensitive Information Exposure', 'type': 'weakness'}, {'id': 'weakness:sensitive data disclosure', 'keyphrase': 'sensitive data disclosure', 'type': 'weakness'}, {'id': 'vector:unauthenticated access to jssupportticketdata directory', 'keyphrase': 'unauthenticated access to jssupportticketdata directory', 'type': 'vector'}, {'id': 'component:/wp-content/uploads/jssupportticketdata directory', 'keyphrase': '/wp-content/uploads/jssupportticketdata directory', 'type': 'component'}]}, 'similarity': np.float64(380.63365585001026)}, {'metadata': {'doc_id': '522', 'name': 'Insufficiently Protected Credentials', 'source': 'sparse', 'original_content': 'The product transmits or stores authentication credentials, but it uses an insecure method that is susceptible to unauthorized interception and/or retrieval.', 'keyphrase_sources': [{'id': 'rootcause:insecure file access permissions', 'keyphrase': 'insecure file access permissions', 'type': 'rootcause'}, {'id': 'weakness:sensitive data disclosure', 'keyphrase': 'sensitive data disclosure', 'type': 'weakness'}, {'id': 'weakness:information disclosure', 'keyphrase': 'information disclosure', 'type': 'weakness'}, {'id': 'impact:extract sensitive data', 'keyphrase': 'extract sensitive data', 'type': 'impact'}, {'id': 'product:JS Help Desk', 'keyphrase': 'JS Help Desk', 'type': 'product'}, {'id': 'version:all versions up to and including 2.8.8', 'keyphrase': 'all versions up to and including 2.8.8', 'type': 'version'}]}, 'similarity': np.float64(376.64952446239806)}, {'metadata': {'doc_id': '863', 'name': 'Incorrect Authorization', 'source': 'sparse', 'original_content': 'The product performs an authorization check when an actor attempts to access a resource or perform an action, but it does not correctly perform the check.', 'keyphrase_sources': [{'id': 'rootcause:insecure file access permissions', 'keyphrase': 'insecure file access permissions', 'type': 'rootcause'}, {'id': 'weakness:Sensitive Information Exposure', 'keyphrase': 'Sensitive Information Exposure', 'type': 'weakness'}, {'id': 'weakness:information disclosure', 'keyphrase': 'information disclosure', 'type': 'weakness'}, {'id': 'impact:extract sensitive data', 'keyphrase': 'extract sensitive data', 'type': 'impact'}, {'id': 'vector:unauthenticated access to jssupportticketdata directory', 'keyphrase': 'unauthenticated access to jssupportticketdata directory', 'type': 'vector'}, {'id': 'product:JS Help Desk', 'keyphrase': 'JS Help Desk', 'type': 'product'}, {'id': 'version:all versions up to and including 2.8.8', 'keyphrase': 'all versions up to and including 2.8.8', 'type': 'version'}, {'id': 'component:/wp-content/uploads/jssupportticketdata directory', 'keyphrase': '/wp-content/uploads/jssupportticketdata directory', 'type': 'component'}]}, 'similarity': np.float64(371.80412990626246)}, {'metadata': {'doc_id': '862', 'name': 'Missing Authorization', 'source': 'sparse', 'original_content': 'The product does not perform an authorization check when an actor attempts to access a resource or perform an action.', 'keyphrase_sources': [{'id': 'rootcause:insecure file access permissions', 'keyphrase': 'insecure file access permissions', 'type': 'rootcause'}, {'id': 'weakness:sensitive data disclosure', 'keyphrase': 'sensitive data disclosure', 'type': 'weakness'}, {'id': 'weakness:information disclosure', 'keyphrase': 'information disclosure', 'type': 'weakness'}, {'id': 'impact:extract sensitive data', 'keyphrase': 'extract sensitive data', 'type': 'impact'}, {'id': 'attacker:unauthenticated attackers', 'keyphrase': 'unauthenticated attackers', 'type': 'attacker'}, {'id': 'version:all versions up to and including 2.8.8', 'keyphrase': 'all versions up to and including 2.8.8', 'type': 'version'}]}, 'similarity': np.float64(369.05108917346104)}, {'metadata': {'doc_id': '201', 'name': 'Insertion of Sensitive Information Into Sent Data', 'source': 'sparse', 'original_content': 'The code transmits data to another actor, but a portion of the data includes sensitive information that should not be accessible to that actor.', 'keyphrase_sources': [{'id': 'weakness:Sensitive Information Exposure', 'keyphrase': 'Sensitive Information Exposure', 'type': 'weakness'}, {'id': 'weakness:sensitive data disclosure', 'keyphrase': 'sensitive data disclosure', 'type': 'weakness'}, {'id': 'weakness:information disclosure', 'keyphrase': 'information disclosure', 'type': 'weakness'}, {'id': 'impact:extract sensitive data', 'keyphrase': 'extract sensitive data', 'type': 'impact'}, {'id': 'product:JS Help Desk', 'keyphrase': 'JS Help Desk', 'type': 'product'}, {'id': 'version:all versions up to and including 2.8.8', 'keyphrase': 'all versions up to and including 2.8.8', 'type': 'version'}]}, 'similarity': np.float64(337.9770082294699)}, {'metadata': {'doc_id': '200', 'name': 'Exposure of Sensitive Information to an Unauthorized Actor', 'source': 'sparse', 'original_content': 'The product exposes sensitive information to an actor that is not explicitly authorized to have access to that information.', 'keyphrase_sources': [{'id': 'weakness:Sensitive Information Exposure', 'keyphrase': 'Sensitive Information Exposure', 'type': 'weakness'}]}, 'similarity': np.float64(334.60609951425613)}, {'metadata': {'doc_id': '434', 'name': 'Unrestricted Upload of File with Dangerous Type', 'source': 'sparse', 'original_content': 'The product allows the upload or transfer of dangerous file types that are automatically processed within its environment.', 'keyphrase_sources': [{'id': 'vector:unauthenticated access to jssupportticketdata directory', 'keyphrase': 'unauthenticated access to jssupportticketdata directory', 'type': 'vector'}, {'id': 'attacker:unauthenticated attackers', 'keyphrase': 'unauthenticated attackers', 'type': 'attacker'}, {'id': 'component:/wp-content/uploads/jssupportticketdata directory', 'keyphrase': '/wp-content/uploads/jssupportticketdata directory', 'type': 'component'}]}, 'similarity': np.float64(132.4745050748759)}, {'metadata': {'doc_id': '24', 'name': \"Path Traversal: '../filedir'\", 'source': 'sparse', 'original_content': 'The product uses external input to construct a pathname that should be within a restricted directory, but it does not properly neutralize \"../\" sequences that can resolve to a location that is outside of that directory.', 'keyphrase_sources': [{'id': 'vector:unauthenticated access to jssupportticketdata directory', 'keyphrase': 'unauthenticated access to jssupportticketdata directory', 'type': 'vector'}, {'id': 'attacker:unauthenticated attackers', 'keyphrase': 'unauthenticated attackers', 'type': 'attacker'}, {'id': 'component:/wp-content/uploads/jssupportticketdata directory', 'keyphrase': '/wp-content/uploads/jssupportticketdata directory', 'type': 'component'}]}, 'similarity': np.float64(132.04320778806377)}, {'metadata': {'doc_id': '352', 'name': 'Cross-Site Request Forgery (CSRF)', 'source': 'sparse', 'original_content': 'The web application does not, or can not, sufficiently verify whether a well-formed, valid, consistent request was intentionally provided by the user who submitted the request.', 'keyphrase_sources': [{'id': 'vector:unauthenticated access to jssupportticketdata directory', 'keyphrase': 'unauthenticated access to jssupportticketdata directory', 'type': 'vector'}, {'id': 'attacker:unauthenticated attackers', 'keyphrase': 'unauthenticated attackers', 'type': 'attacker'}, {'id': 'product:JS Help Desk', 'keyphrase': 'JS Help Desk', 'type': 'product'}, {'id': 'version:all versions up to and including 2.8.8', 'keyphrase': 'all versions up to and including 2.8.8', 'type': 'version'}, {'id': 'component:/wp-content/uploads/jssupportticketdata directory', 'keyphrase': '/wp-content/uploads/jssupportticketdata directory', 'type': 'component'}]}, 'similarity': np.float64(129.95093956382422)}], identified_cwes={'analyzer': [], 'critic_additional': []})",
  "retrieval_results": {
    "has_multiple_keyphrases": true,
    "keyphrase_cwe_sets": {
      "rootcause:insecure file access permissions": {
        "keyphrase": "insecure file access permissions",
        "type": "rootcause",
        "cwes": [
          {
            "metadata": {
              "doc_id": "639",
              "name": "Authorization Bypass Through User-Controlled Key",
              "source": "sparse",
              "original_content": "The system's authorization functionality does not prevent one user from gaining access to another user's data or record by modifying the key value identifying the data.",
              "keyphrase_sources": [
                {
                  "id": "rootcause:insecure file access permissions",
                  "keyphrase": "insecure file access permissions",
                  "type": "rootcause"
                },
                {
                  "id": "weakness:Sensitive Information Exposure",
                  "keyphrase": "Sensitive Information Exposure",
                  "type": "weakness"
                },
                {
                  "id": "weakness:sensitive data disclosure",
                  "keyphrase": "sensitive data disclosure",
                  "type": "weakness"
                },
                {
                  "id": "weakness:information disclosure",
                  "keyphrase": "information disclosure",
                  "type": "weakness"
                },
                {
                  "id": "impact:extract sensitive data",
                  "keyphrase": "extract sensitive data",
                  "type": "impact"
                },
                {
                  "id": "attacker:unauthenticated attackers",
                  "keyphrase": "unauthenticated attackers",
                  "type": "attacker"
                },
                {
                  "id": "product:JS Help Desk",
                  "keyphrase": "JS Help Desk",
                  "type": "product"
                }
              ]
            },
            "similarity": 393.07069704438493
          },
          {
            "metadata": {
              "doc_id": "425",
              "name": "Direct Request ('Forced Browsing')",
              "source": "sparse",
              "original_content": "The web application does not adequately enforce appropriate authorization on all restricted URLs, scripts, or files.",
              "keyphrase_sources": [
                {
                  "id": "rootcause:insecure file access permissions",
                  "keyphrase": "insecure file access permissions",
                  "type": "rootcause"
                },
                {
                  "id": "weakness:Sensitive Information Exposure",
                  "keyphrase": "Sensitive Information Exposure",
                  "type": "weakness"
                },
                {
                  "id": "weakness:sensitive data disclosure",
                  "keyphrase": "sensitive data disclosure",
                  "type": "weakness"
                },
                {
                  "id": "vector:unauthenticated access to jssupportticketdata directory",
                  "keyphrase": "unauthenticated access to jssupportticketdata directory",
                  "type": "vector"
                },
                {
                  "id": "component:/wp-content/uploads/jssupportticketdata directory",
                  "keyphrase": "/wp-content/uploads/jssupportticketdata directory",
                  "type": "component"
                }
              ]
            },
            "similarity": 380.63365585001026
          },
          {
            "metadata": {
              "doc_id": "522",
              "name": "Insufficiently Protected Credentials",
              "source": "sparse",
              "original_content": "The product transmits or stores authentication credentials, but it uses an insecure method that is susceptible to unauthorized interception and/or retrieval.",
              "keyphrase_sources": [
                {
                  "id": "rootcause:insecure file access permissions",
                  "keyphrase": "insecure file access permissions",
                  "type": "rootcause"
                },
                {
                  "id": "weakness:sensitive data disclosure",
                  "keyphrase": "sensitive data disclosure",
                  "type": "weakness"
                },
                {
                  "id": "weakness:information disclosure",
                  "keyphrase": "information disclosure",
                  "type": "weakness"
                },
                {
                  "id": "impact:extract sensitive data",
                  "keyphrase": "extract sensitive data",
                  "type": "impact"
                },
                {
                  "id": "product:JS Help Desk",
                  "keyphrase": "JS Help Desk",
                  "type": "product"
                },
                {
                  "id": "version:all versions up to and including 2.8.8",
                  "keyphrase": "all versions up to and including 2.8.8",
                  "type": "version"
                }
              ]
            },
            "similarity": 376.64952446239806
          },
          {
            "metadata": {
              "doc_id": "863",
              "name": "Incorrect Authorization",
              "source": "sparse",
              "original_content": "The product performs an authorization check when an actor attempts to access a resource or perform an action, but it does not correctly perform the check.",
              "keyphrase_sources": [
                {
                  "id": "rootcause:insecure file access permissions",
                  "keyphrase": "insecure file access permissions",
                  "type": "rootcause"
                },
                {
                  "id": "weakness:Sensitive Information Exposure",
                  "keyphrase": "Sensitive Information Exposure",
                  "type": "weakness"
                },
                {
                  "id": "weakness:information disclosure",
                  "keyphrase": "information disclosure",
                  "type": "weakness"
                },
                {
                  "id": "impact:extract sensitive data",
                  "keyphrase": "extract sensitive data",
                  "type": "impact"
                },
                {
                  "id": "vector:unauthenticated access to jssupportticketdata directory",
                  "keyphrase": "unauthenticated access to jssupportticketdata directory",
                  "type": "vector"
                },
                {
                  "id": "product:JS Help Desk",
                  "keyphrase": "JS Help Desk",
                  "type": "product"
                },
                {
                  "id": "version:all versions up to and including 2.8.8",
                  "keyphrase": "all versions up to and including 2.8.8",
                  "type": "version"
                },
                {
                  "id": "component:/wp-content/uploads/jssupportticketdata directory",
                  "keyphrase": "/wp-content/uploads/jssupportticketdata directory",
                  "type": "component"
                }
              ]
            },
            "similarity": 371.80412990626246
          },
          {
            "metadata": {
              "doc_id": "862",
              "name": "Missing Authorization",
              "source": "sparse",
              "original_content": "The product does not perform an authorization check when an actor attempts to access a resource or perform an action.",
              "keyphrase_sources": [
                {
                  "id": "rootcause:insecure file access permissions",
                  "keyphrase": "insecure file access permissions",
                  "type": "rootcause"
                },
                {
                  "id": "weakness:sensitive data disclosure",
                  "keyphrase": "sensitive data disclosure",
                  "type": "weakness"
                },
                {
                  "id": "weakness:information disclosure",
                  "keyphrase": "information disclosure",
                  "type": "weakness"
                },
                {
                  "id": "impact:extract sensitive data",
                  "keyphrase": "extract sensitive data",
                  "type": "impact"
                },
                {
                  "id": "attacker:unauthenticated attackers",
                  "keyphrase": "unauthenticated attackers",
                  "type": "attacker"
                },
                {
                  "id": "version:all versions up to and including 2.8.8",
                  "keyphrase": "all versions up to and including 2.8.8",
                  "type": "version"
                }
              ]
            },
            "similarity": 369.05108917346104
          }
        ]
      },
      "weakness:Sensitive Information Exposure": {
        "keyphrase": "Sensitive Information Exposure",
        "type": "weakness",
        "cwes": [
          {
            "metadata": {
              "doc_id": "201",
              "name": "Insertion of Sensitive Information Into Sent Data",
              "source": "sparse",
              "original_content": "The code transmits data to another actor, but a portion of the data includes sensitive information that should not be accessible to that actor.",
              "keyphrase_sources": [
                {
                  "id": "weakness:Sensitive Information Exposure",
                  "keyphrase": "Sensitive Information Exposure",
                  "type": "weakness"
                },
                {
                  "id": "weakness:sensitive data disclosure",
                  "keyphrase": "sensitive data disclosure",
                  "type": "weakness"
                },
                {
                  "id": "weakness:information disclosure",
                  "keyphrase": "information disclosure",
                  "type": "weakness"
                },
                {
                  "id": "impact:extract sensitive data",
                  "keyphrase": "extract sensitive data",
                  "type": "impact"
                },
                {
                  "id": "product:JS Help Desk",
                  "keyphrase": "JS Help Desk",
                  "type": "product"
                },
                {
                  "id": "version:all versions up to and including 2.8.8",
                  "keyphrase": "all versions up to and including 2.8.8",
                  "type": "version"
                }
              ]
            },
            "similarity": 337.9770082294699
          },
          {
            "metadata": {
              "doc_id": "200",
              "name": "Exposure of Sensitive Information to an Unauthorized Actor",
              "source": "sparse",
              "original_content": "The product exposes sensitive information to an actor that is not explicitly authorized to have access to that information.",
              "keyphrase_sources": [
                {
                  "id": "weakness:Sensitive Information Exposure",
                  "keyphrase": "Sensitive Information Exposure",
                  "type": "weakness"
                }
              ]
            },
            "similarity": 334.60609951425613
          },
          {
            "metadata": {
              "doc_id": "425",
              "name": "Direct Request ('Forced Browsing')",
              "source": "sparse",
              "original_content": "The web application does not adequately enforce appropriate authorization on all restricted URLs, scripts, or files."
            },
            "similarity": 331.9008282624706
          },
          {
            "metadata": {
              "doc_id": "639",
              "name": "Authorization Bypass Through User-Controlled Key",
              "source": "sparse",
              "original_content": "The system's authorization functionality does not prevent one user from gaining access to another user's data or record by modifying the key value identifying the data."
            },
            "similarity": 330.30623570698907
          },
          {
            "metadata": {
              "doc_id": "863",
              "name": "Incorrect Authorization",
              "source": "sparse",
              "original_content": "The product performs an authorization check when an actor attempts to access a resource or perform an action, but it does not correctly perform the check."
            },
            "similarity": 328.36030724083236
          }
        ]
      },
      "weakness:sensitive data disclosure": {
        "keyphrase": "sensitive data disclosure",
        "type": "weakness",
        "cwes": [
          {
            "metadata": {
              "doc_id": "201",
              "name": "Insertion of Sensitive Information Into Sent Data",
              "source": "sparse",
              "original_content": "The code transmits data to another actor, but a portion of the data includes sensitive information that should not be accessible to that actor."
            },
            "similarity": 337.3483763367833
          },
          {
            "metadata": {
              "doc_id": "639",
              "name": "Authorization Bypass Through User-Controlled Key",
              "source": "sparse",
              "original_content": "The system's authorization functionality does not prevent one user from gaining access to another user's data or record by modifying the key value identifying the data."
            },
            "similarity": 334.4971324696457
          },
          {
            "metadata": {
              "doc_id": "862",
              "name": "Missing Authorization",
              "source": "sparse",
              "original_content": "The product does not perform an authorization check when an actor attempts to access a resource or perform an action."
            },
            "similarity": 334.2456052049175
          },
          {
            "metadata": {
              "doc_id": "522",
              "name": "Insufficiently Protected Credentials",
              "source": "sparse",
              "original_content": "The product transmits or stores authentication credentials, but it uses an insecure method that is susceptible to unauthorized interception and/or retrieval."
            },
            "similarity": 330.3543982049832
          },
          {
            "metadata": {
              "doc_id": "425",
              "name": "Direct Request ('Forced Browsing')",
              "source": "sparse",
              "original_content": "The web application does not adequately enforce appropriate authorization on all restricted URLs, scripts, or files."
            },
            "similarity": 327.4772463865309
          }
        ]
      },
      "weakness:information disclosure": {
        "keyphrase": "information disclosure",
        "type": "weakness",
        "cwes": [
          {
            "metadata": {
              "doc_id": "862",
              "name": "Missing Authorization",
              "source": "sparse",
              "original_content": "The product does not perform an authorization check when an actor attempts to access a resource or perform an action."
            },
            "similarity": 331.71488613682857
          },
          {
            "metadata": {
              "doc_id": "201",
              "name": "Insertion of Sensitive Information Into Sent Data",
              "source": "sparse",
              "original_content": "The code transmits data to another actor, but a portion of the data includes sensitive information that should not be accessible to that actor."
            },
            "similarity": 330.90537086018713
          },
          {
            "metadata": {
              "doc_id": "639",
              "name": "Authorization Bypass Through User-Controlled Key",
              "source": "sparse",
              "original_content": "The system's authorization functionality does not prevent one user from gaining access to another user's data or record by modifying the key value identifying the data."
            },
            "similarity": 328.59718307574116
          },
          {
            "metadata": {
              "doc_id": "522",
              "name": "Insufficiently Protected Credentials",
              "source": "sparse",
              "original_content": "The product transmits or stores authentication credentials, but it uses an insecure method that is susceptible to unauthorized interception and/or retrieval."
            },
            "similarity": 324.99166875539794
          },
          {
            "metadata": {
              "doc_id": "863",
              "name": "Incorrect Authorization",
              "source": "sparse",
              "original_content": "The product performs an authorization check when an actor attempts to access a resource or perform an action, but it does not correctly perform the check."
            },
            "similarity": 321.8270910908438
          }
        ]
      },
      "impact:extract sensitive data": {
        "keyphrase": "extract sensitive data",
        "type": "impact",
        "cwes": [
          {
            "metadata": {
              "doc_id": "201",
              "name": "Insertion of Sensitive Information Into Sent Data",
              "source": "sparse",
              "original_content": "The code transmits data to another actor, but a portion of the data includes sensitive information that should not be accessible to that actor."
            },
            "similarity": 116.76814157751141
          },
          {
            "metadata": {
              "doc_id": "522",
              "name": "Insufficiently Protected Credentials",
              "source": "sparse",
              "original_content": "The product transmits or stores authentication credentials, but it uses an insecure method that is susceptible to unauthorized interception and/or retrieval."
            },
            "similarity": 115.37667743955863
          },
          {
            "metadata": {
              "doc_id": "639",
              "name": "Authorization Bypass Through User-Controlled Key",
              "source": "sparse",
              "original_content": "The system's authorization functionality does not prevent one user from gaining access to another user's data or record by modifying the key value identifying the data."
            },
            "similarity": 114.90111087033932
          },
          {
            "metadata": {
              "doc_id": "863",
              "name": "Incorrect Authorization",
              "source": "sparse",
              "original_content": "The product performs an authorization check when an actor attempts to access a resource or perform an action, but it does not correctly perform the check."
            },
            "similarity": 114.63209057419992
          },
          {
            "metadata": {
              "doc_id": "862",
              "name": "Missing Authorization",
              "source": "sparse",
              "original_content": "The product does not perform an authorization check when an actor attempts to access a resource or perform an action."
            },
            "similarity": 112.94149267467853
          }
        ]
      },
      "vector:unauthenticated access to jssupportticketdata directory": {
        "keyphrase": "unauthenticated access to jssupportticketdata directory",
        "type": "vector",
        "cwes": [
          {
            "metadata": {
              "doc_id": "434",
              "name": "Unrestricted Upload of File with Dangerous Type",
              "source": "sparse",
              "original_content": "The product allows the upload or transfer of dangerous file types that are automatically processed within its environment.",
              "keyphrase_sources": [
                {
                  "id": "vector:unauthenticated access to jssupportticketdata directory",
                  "keyphrase": "unauthenticated access to jssupportticketdata directory",
                  "type": "vector"
                },
                {
                  "id": "attacker:unauthenticated attackers",
                  "keyphrase": "unauthenticated attackers",
                  "type": "attacker"
                },
                {
                  "id": "component:/wp-content/uploads/jssupportticketdata directory",
                  "keyphrase": "/wp-content/uploads/jssupportticketdata directory",
                  "type": "component"
                }
              ]
            },
            "similarity": 132.4745050748759
          },
          {
            "metadata": {
              "doc_id": "24",
              "name": "Path Traversal: '../filedir'",
              "source": "sparse",
              "original_content": "The product uses external input to construct a pathname that should be within a restricted directory, but it does not properly neutralize \"../\" sequences that can resolve to a location that is outside of that directory.",
              "keyphrase_sources": [
                {
                  "id": "vector:unauthenticated access to jssupportticketdata directory",
                  "keyphrase": "unauthenticated access to jssupportticketdata directory",
                  "type": "vector"
                },
                {
                  "id": "attacker:unauthenticated attackers",
                  "keyphrase": "unauthenticated attackers",
                  "type": "attacker"
                },
                {
                  "id": "component:/wp-content/uploads/jssupportticketdata directory",
                  "keyphrase": "/wp-content/uploads/jssupportticketdata directory",
                  "type": "component"
                }
              ]
            },
            "similarity": 132.04320778806377
          },
          {
            "metadata": {
              "doc_id": "425",
              "name": "Direct Request ('Forced Browsing')",
              "source": "sparse",
              "original_content": "The web application does not adequately enforce appropriate authorization on all restricted URLs, scripts, or files."
            },
            "similarity": 130.67798886369934
          },
          {
            "metadata": {
              "doc_id": "352",
              "name": "Cross-Site Request Forgery (CSRF)",
              "source": "sparse",
              "original_content": "The web application does not, or can not, sufficiently verify whether a well-formed, valid, consistent request was intentionally provided by the user who submitted the request.",
              "keyphrase_sources": [
                {
                  "id": "vector:unauthenticated access to jssupportticketdata directory",
                  "keyphrase": "unauthenticated access to jssupportticketdata directory",
                  "type": "vector"
                },
                {
                  "id": "attacker:unauthenticated attackers",
                  "keyphrase": "unauthenticated attackers",
                  "type": "attacker"
                },
                {
                  "id": "product:JS Help Desk",
                  "keyphrase": "JS Help Desk",
                  "type": "product"
                },
                {
                  "id": "version:all versions up to and including 2.8.8",
                  "keyphrase": "all versions up to and including 2.8.8",
                  "type": "version"
                },
                {
                  "id": "component:/wp-content/uploads/jssupportticketdata directory",
                  "keyphrase": "/wp-content/uploads/jssupportticketdata directory",
                  "type": "component"
                }
              ]
            },
            "similarity": 129.95093956382422
          },
          {
            "metadata": {
              "doc_id": "863",
              "name": "Incorrect Authorization",
              "source": "sparse",
              "original_content": "The product performs an authorization check when an actor attempts to access a resource or perform an action, but it does not correctly perform the check."
            },
            "similarity": 129.2288213624166
          }
        ]
      },
      "attacker:unauthenticated attackers": {
        "keyphrase": "unauthenticated attackers",
        "type": "attacker",
        "cwes": [
          {
            "metadata": {
              "doc_id": "352",
              "name": "Cross-Site Request Forgery (CSRF)",
              "source": "sparse",
              "original_content": "The web application does not, or can not, sufficiently verify whether a well-formed, valid, consistent request was intentionally provided by the user who submitted the request."
            },
            "similarity": 118.98729028169741
          },
          {
            "metadata": {
              "doc_id": "639",
              "name": "Authorization Bypass Through User-Controlled Key",
              "source": "sparse",
              "original_content": "The system's authorization functionality does not prevent one user from gaining access to another user's data or record by modifying the key value identifying the data."
            },
            "similarity": 116.7421929856834
          },
          {
            "metadata": {
              "doc_id": "434",
              "name": "Unrestricted Upload of File with Dangerous Type",
              "source": "sparse",
              "original_content": "The product allows the upload or transfer of dangerous file types that are automatically processed within its environment."
            },
            "similarity": 116.44735071399761
          },
          {
            "metadata": {
              "doc_id": "862",
              "name": "Missing Authorization",
              "source": "sparse",
              "original_content": "The product does not perform an authorization check when an actor attempts to access a resource or perform an action."
            },
            "similarity": 115.93652122630266
          },
          {
            "metadata": {
              "doc_id": "24",
              "name": "Path Traversal: '../filedir'",
              "source": "sparse",
              "original_content": "The product uses external input to construct a pathname that should be within a restricted directory, but it does not properly neutralize \"../\" sequences that can resolve to a location that is outside of that directory."
            },
            "similarity": 115.74786012473534
          }
        ]
      },
      "product:JS Help Desk": {
        "keyphrase": "JS Help Desk",
        "type": "product",
        "cwes": [
          {
            "metadata": {
              "doc_id": "639",
              "name": "Authorization Bypass Through User-Controlled Key",
              "source": "sparse",
              "original_content": "The system's authorization functionality does not prevent one user from gaining access to another user's data or record by modifying the key value identifying the data."
            },
            "similarity": 119.69016138425033
          },
          {
            "metadata": {
              "doc_id": "201",
              "name": "Insertion of Sensitive Information Into Sent Data",
              "source": "sparse",
              "original_content": "The code transmits data to another actor, but a portion of the data includes sensitive information that should not be accessible to that actor."
            },
            "similarity": 117.97303193112535
          },
          {
            "metadata": {
              "doc_id": "352",
              "name": "Cross-Site Request Forgery (CSRF)",
              "source": "sparse",
              "original_content": "The web application does not, or can not, sufficiently verify whether a well-formed, valid, consistent request was intentionally provided by the user who submitted the request."
            },
            "similarity": 113.82934761628634
          },
          {
            "metadata": {
              "doc_id": "863",
              "name": "Incorrect Authorization",
              "source": "sparse",
              "original_content": "The product performs an authorization check when an actor attempts to access a resource or perform an action, but it does not correctly perform the check."
            },
            "similarity": 113.07621106583836
          },
          {
            "metadata": {
              "doc_id": "522",
              "name": "Insufficiently Protected Credentials",
              "source": "sparse",
              "original_content": "The product transmits or stores authentication credentials, but it uses an insecure method that is susceptible to unauthorized interception and/or retrieval."
            },
            "similarity": 112.06202021686964
          }
        ]
      },
      "version:all versions up to and including 2.8.8": {
        "keyphrase": "all versions up to and including 2.8.8",
        "type": "version",
        "cwes": [
          {
            "metadata": {
              "doc_id": "522",
              "name": "Insufficiently Protected Credentials",
              "source": "sparse",
              "original_content": "The product transmits or stores authentication credentials, but it uses an insecure method that is susceptible to unauthorized interception and/or retrieval."
            },
            "similarity": 146.55812404390423
          },
          {
            "metadata": {
              "doc_id": "863",
              "name": "Incorrect Authorization",
              "source": "sparse",
              "original_content": "The product performs an authorization check when an actor attempts to access a resource or perform an action, but it does not correctly perform the check."
            },
            "similarity": 145.48020223679225
          },
          {
            "metadata": {
              "doc_id": "201",
              "name": "Insertion of Sensitive Information Into Sent Data",
              "source": "sparse",
              "original_content": "The code transmits data to another actor, but a portion of the data includes sensitive information that should not be accessible to that actor."
            },
            "similarity": 145.37161902689624
          },
          {
            "metadata": {
              "doc_id": "862",
              "name": "Missing Authorization",
              "source": "sparse",
              "original_content": "The product does not perform an authorization check when an actor attempts to access a resource or perform an action."
            },
            "similarity": 144.21715636372969
          },
          {
            "metadata": {
              "doc_id": "352",
              "name": "Cross-Site Request Forgery (CSRF)",
              "source": "sparse",
              "original_content": "The web application does not, or can not, sufficiently verify whether a well-formed, valid, consistent request was intentionally provided by the user who submitted the request."
            },
            "similarity": 143.6824765504079
          }
        ]
      },
      "component:/wp-content/uploads/jssupportticketdata directory": {
        "keyphrase": "/wp-content/uploads/jssupportticketdata directory",
        "type": "component",
        "cwes": [
          {
            "metadata": {
              "doc_id": "24",
              "name": "Path Traversal: '../filedir'",
              "source": "sparse",
              "original_content": "The product uses external input to construct a pathname that should be within a restricted directory, but it does not properly neutralize \"../\" sequences that can resolve to a location that is outside of that directory."
            },
            "similarity": 137.8500127126151
          },
          {
            "metadata": {
              "doc_id": "434",
              "name": "Unrestricted Upload of File with Dangerous Type",
              "source": "sparse",
              "original_content": "The product allows the upload or transfer of dangerous file types that are automatically processed within its environment."
            },
            "similarity": 136.56982435457812
          },
          {
            "metadata": {
              "doc_id": "352",
              "name": "Cross-Site Request Forgery (CSRF)",
              "source": "sparse",
              "original_content": "The web application does not, or can not, sufficiently verify whether a well-formed, valid, consistent request was intentionally provided by the user who submitted the request."
            },
            "similarity": 128.0259219491104
          },
          {
            "metadata": {
              "doc_id": "425",
              "name": "Direct Request ('Forced Browsing')",
              "source": "sparse",
              "original_content": "The web application does not adequately enforce appropriate authorization on all restricted URLs, scripts, or files."
            },
            "similarity": 127.58679335142085
          },
          {
            "metadata": {
              "doc_id": "863",
              "name": "Incorrect Authorization",
              "source": "sparse",
              "original_content": "The product performs an authorization check when an actor attempts to access a resource or perform an action, but it does not correctly perform the check."
            },
            "similarity": 122.8915671854585
          }
        ]
      }
    },
    "keyphrase_mapping": {
      "639": [
        {
          "id": "rootcause:insecure file access permissions",
          "keyphrase": "insecure file access permissions",
          "type": "rootcause"
        },
        {
          "id": "weakness:Sensitive Information Exposure",
          "keyphrase": "Sensitive Information Exposure",
          "type": "weakness"
        },
        {
          "id": "weakness:sensitive data disclosure",
          "keyphrase": "sensitive data disclosure",
          "type": "weakness"
        },
        {
          "id": "weakness:information disclosure",
          "keyphrase": "information disclosure",
          "type": "weakness"
        },
        {
          "id": "impact:extract sensitive data",
          "keyphrase": "extract sensitive data",
          "type": "impact"
        },
        {
          "id": "attacker:unauthenticated attackers",
          "keyphrase": "unauthenticated attackers",
          "type": "attacker"
        },
        {
          "id": "product:JS Help Desk",
          "keyphrase": "JS Help Desk",
          "type": "product"
        }
      ],
      "425": [
        {
          "id": "rootcause:insecure file access permissions",
          "keyphrase": "insecure file access permissions",
          "type": "rootcause"
        },
        {
          "id": "weakness:Sensitive Information Exposure",
          "keyphrase": "Sensitive Information Exposure",
          "type": "weakness"
        },
        {
          "id": "weakness:sensitive data disclosure",
          "keyphrase": "sensitive data disclosure",
          "type": "weakness"
        },
        {
          "id": "vector:unauthenticated access to jssupportticketdata directory",
          "keyphrase": "unauthenticated access to jssupportticketdata directory",
          "type": "vector"
        },
        {
          "id": "component:/wp-content/uploads/jssupportticketdata directory",
          "keyphrase": "/wp-content/uploads/jssupportticketdata directory",
          "type": "component"
        }
      ],
      "522": [
        {
          "id": "rootcause:insecure file access permissions",
          "keyphrase": "insecure file access permissions",
          "type": "rootcause"
        },
        {
          "id": "weakness:sensitive data disclosure",
          "keyphrase": "sensitive data disclosure",
          "type": "weakness"
        },
        {
          "id": "weakness:information disclosure",
          "keyphrase": "information disclosure",
          "type": "weakness"
        },
        {
          "id": "impact:extract sensitive data",
          "keyphrase": "extract sensitive data",
          "type": "impact"
        },
        {
          "id": "product:JS Help Desk",
          "keyphrase": "JS Help Desk",
          "type": "product"
        },
        {
          "id": "version:all versions up to and including 2.8.8",
          "keyphrase": "all versions up to and including 2.8.8",
          "type": "version"
        }
      ],
      "863": [
        {
          "id": "rootcause:insecure file access permissions",
          "keyphrase": "insecure file access permissions",
          "type": "rootcause"
        },
        {
          "id": "weakness:Sensitive Information Exposure",
          "keyphrase": "Sensitive Information Exposure",
          "type": "weakness"
        },
        {
          "id": "weakness:information disclosure",
          "keyphrase": "information disclosure",
          "type": "weakness"
        },
        {
          "id": "impact:extract sensitive data",
          "keyphrase": "extract sensitive data",
          "type": "impact"
        },
        {
          "id": "vector:unauthenticated access to jssupportticketdata directory",
          "keyphrase": "unauthenticated access to jssupportticketdata directory",
          "type": "vector"
        },
        {
          "id": "product:JS Help Desk",
          "keyphrase": "JS Help Desk",
          "type": "product"
        },
        {
          "id": "version:all versions up to and including 2.8.8",
          "keyphrase": "all versions up to and including 2.8.8",
          "type": "version"
        },
        {
          "id": "component:/wp-content/uploads/jssupportticketdata directory",
          "keyphrase": "/wp-content/uploads/jssupportticketdata directory",
          "type": "component"
        }
      ],
      "862": [
        {
          "id": "rootcause:insecure file access permissions",
          "keyphrase": "insecure file access permissions",
          "type": "rootcause"
        },
        {
          "id": "weakness:sensitive data disclosure",
          "keyphrase": "sensitive data disclosure",
          "type": "weakness"
        },
        {
          "id": "weakness:information disclosure",
          "keyphrase": "information disclosure",
          "type": "weakness"
        },
        {
          "id": "impact:extract sensitive data",
          "keyphrase": "extract sensitive data",
          "type": "impact"
        },
        {
          "id": "attacker:unauthenticated attackers",
          "keyphrase": "unauthenticated attackers",
          "type": "attacker"
        },
        {
          "id": "version:all versions up to and including 2.8.8",
          "keyphrase": "all versions up to and including 2.8.8",
          "type": "version"
        }
      ],
      "201": [
        {
          "id": "weakness:Sensitive Information Exposure",
          "keyphrase": "Sensitive Information Exposure",
          "type": "weakness"
        },
        {
          "id": "weakness:sensitive data disclosure",
          "keyphrase": "sensitive data disclosure",
          "type": "weakness"
        },
        {
          "id": "weakness:information disclosure",
          "keyphrase": "information disclosure",
          "type": "weakness"
        },
        {
          "id": "impact:extract sensitive data",
          "keyphrase": "extract sensitive data",
          "type": "impact"
        },
        {
          "id": "product:JS Help Desk",
          "keyphrase": "JS Help Desk",
          "type": "product"
        },
        {
          "id": "version:all versions up to and including 2.8.8",
          "keyphrase": "all versions up to and including 2.8.8",
          "type": "version"
        }
      ],
      "200": [
        {
          "id": "weakness:Sensitive Information Exposure",
          "keyphrase": "Sensitive Information Exposure",
          "type": "weakness"
        }
      ],
      "434": [
        {
          "id": "vector:unauthenticated access to jssupportticketdata directory",
          "keyphrase": "unauthenticated access to jssupportticketdata directory",
          "type": "vector"
        },
        {
          "id": "attacker:unauthenticated attackers",
          "keyphrase": "unauthenticated attackers",
          "type": "attacker"
        },
        {
          "id": "component:/wp-content/uploads/jssupportticketdata directory",
          "keyphrase": "/wp-content/uploads/jssupportticketdata directory",
          "type": "component"
        }
      ],
      "24": [
        {
          "id": "vector:unauthenticated access to jssupportticketdata directory",
          "keyphrase": "unauthenticated access to jssupportticketdata directory",
          "type": "vector"
        },
        {
          "id": "attacker:unauthenticated attackers",
          "keyphrase": "unauthenticated attackers",
          "type": "attacker"
        },
        {
          "id": "component:/wp-content/uploads/jssupportticketdata directory",
          "keyphrase": "/wp-content/uploads/jssupportticketdata directory",
          "type": "component"
        }
      ],
      "352": [
        {
          "id": "vector:unauthenticated access to jssupportticketdata directory",
          "keyphrase": "unauthenticated access to jssupportticketdata directory",
          "type": "vector"
        },
        {
          "id": "attacker:unauthenticated attackers",
          "keyphrase": "unauthenticated attackers",
          "type": "attacker"
        },
        {
          "id": "product:JS Help Desk",
          "keyphrase": "JS Help Desk",
          "type": "product"
        },
        {
          "id": "version:all versions up to and including 2.8.8",
          "keyphrase": "all versions up to and including 2.8.8",
          "type": "version"
        },
        {
          "id": "component:/wp-content/uploads/jssupportticketdata directory",
          "keyphrase": "/wp-content/uploads/jssupportticketdata directory",
          "type": "component"
        }
      ]
    },
    "relevant_cwes": [
      {
        "metadata": {
          "doc_id": "639",
          "name": "Authorization Bypass Through User-Controlled Key",
          "source": "sparse",
          "original_content": "The system's authorization functionality does not prevent one user from gaining access to another user's data or record by modifying the key value identifying the data.",
          "keyphrase_sources": [
            {
              "id": "rootcause:insecure file access permissions",
              "keyphrase": "insecure file access permissions",
              "type": "rootcause"
            },
            {
              "id": "weakness:Sensitive Information Exposure",
              "keyphrase": "Sensitive Information Exposure",
              "type": "weakness"
            },
            {
              "id": "weakness:sensitive data disclosure",
              "keyphrase": "sensitive data disclosure",
              "type": "weakness"
            },
            {
              "id": "weakness:information disclosure",
              "keyphrase": "information disclosure",
              "type": "weakness"
            },
            {
              "id": "impact:extract sensitive data",
              "keyphrase": "extract sensitive data",
              "type": "impact"
            },
            {
              "id": "attacker:unauthenticated attackers",
              "keyphrase": "unauthenticated attackers",
              "type": "attacker"
            },
            {
              "id": "product:JS Help Desk",
              "keyphrase": "JS Help Desk",
              "type": "product"
            }
          ]
        },
        "similarity": 393.07069704438493
      },
      {
        "metadata": {
          "doc_id": "425",
          "name": "Direct Request ('Forced Browsing')",
          "source": "sparse",
          "original_content": "The web application does not adequately enforce appropriate authorization on all restricted URLs, scripts, or files.",
          "keyphrase_sources": [
            {
              "id": "rootcause:insecure file access permissions",
              "keyphrase": "insecure file access permissions",
              "type": "rootcause"
            },
            {
              "id": "weakness:Sensitive Information Exposure",
              "keyphrase": "Sensitive Information Exposure",
              "type": "weakness"
            },
            {
              "id": "weakness:sensitive data disclosure",
              "keyphrase": "sensitive data disclosure",
              "type": "weakness"
            },
            {
              "id": "vector:unauthenticated access to jssupportticketdata directory",
              "keyphrase": "unauthenticated access to jssupportticketdata directory",
              "type": "vector"
            },
            {
              "id": "component:/wp-content/uploads/jssupportticketdata directory",
              "keyphrase": "/wp-content/uploads/jssupportticketdata directory",
              "type": "component"
            }
          ]
        },
        "similarity": 380.63365585001026
      },
      {
        "metadata": {
          "doc_id": "522",
          "name": "Insufficiently Protected Credentials",
          "source": "sparse",
          "original_content": "The product transmits or stores authentication credentials, but it uses an insecure method that is susceptible to unauthorized interception and/or retrieval.",
          "keyphrase_sources": [
            {
              "id": "rootcause:insecure file access permissions",
              "keyphrase": "insecure file access permissions",
              "type": "rootcause"
            },
            {
              "id": "weakness:sensitive data disclosure",
              "keyphrase": "sensitive data disclosure",
              "type": "weakness"
            },
            {
              "id": "weakness:information disclosure",
              "keyphrase": "information disclosure",
              "type": "weakness"
            },
            {
              "id": "impact:extract sensitive data",
              "keyphrase": "extract sensitive data",
              "type": "impact"
            },
            {
              "id": "product:JS Help Desk",
              "keyphrase": "JS Help Desk",
              "type": "product"
            },
            {
              "id": "version:all versions up to and including 2.8.8",
              "keyphrase": "all versions up to and including 2.8.8",
              "type": "version"
            }
          ]
        },
        "similarity": 376.64952446239806
      },
      {
        "metadata": {
          "doc_id": "863",
          "name": "Incorrect Authorization",
          "source": "sparse",
          "original_content": "The product performs an authorization check when an actor attempts to access a resource or perform an action, but it does not correctly perform the check.",
          "keyphrase_sources": [
            {
              "id": "rootcause:insecure file access permissions",
              "keyphrase": "insecure file access permissions",
              "type": "rootcause"
            },
            {
              "id": "weakness:Sensitive Information Exposure",
              "keyphrase": "Sensitive Information Exposure",
              "type": "weakness"
            },
            {
              "id": "weakness:information disclosure",
              "keyphrase": "information disclosure",
              "type": "weakness"
            },
            {
              "id": "impact:extract sensitive data",
              "keyphrase": "extract sensitive data",
              "type": "impact"
            },
            {
              "id": "vector:unauthenticated access to jssupportticketdata directory",
              "keyphrase": "unauthenticated access to jssupportticketdata directory",
              "type": "vector"
            },
            {
              "id": "product:JS Help Desk",
              "keyphrase": "JS Help Desk",
              "type": "product"
            },
            {
              "id": "version:all versions up to and including 2.8.8",
              "keyphrase": "all versions up to and including 2.8.8",
              "type": "version"
            },
            {
              "id": "component:/wp-content/uploads/jssupportticketdata directory",
              "keyphrase": "/wp-content/uploads/jssupportticketdata directory",
              "type": "component"
            }
          ]
        },
        "similarity": 371.80412990626246
      },
      {
        "metadata": {
          "doc_id": "862",
          "name": "Missing Authorization",
          "source": "sparse",
          "original_content": "The product does not perform an authorization check when an actor attempts to access a resource or perform an action.",
          "keyphrase_sources": [
            {
              "id": "rootcause:insecure file access permissions",
              "keyphrase": "insecure file access permissions",
              "type": "rootcause"
            },
            {
              "id": "weakness:sensitive data disclosure",
              "keyphrase": "sensitive data disclosure",
              "type": "weakness"
            },
            {
              "id": "weakness:information disclosure",
              "keyphrase": "information disclosure",
              "type": "weakness"
            },
            {
              "id": "impact:extract sensitive data",
              "keyphrase": "extract sensitive data",
              "type": "impact"
            },
            {
              "id": "attacker:unauthenticated attackers",
              "keyphrase": "unauthenticated attackers",
              "type": "attacker"
            },
            {
              "id": "version:all versions up to and including 2.8.8",
              "keyphrase": "all versions up to and including 2.8.8",
              "type": "version"
            }
          ]
        },
        "similarity": 369.05108917346104
      },
      {
        "metadata": {
          "doc_id": "201",
          "name": "Insertion of Sensitive Information Into Sent Data",
          "source": "sparse",
          "original_content": "The code transmits data to another actor, but a portion of the data includes sensitive information that should not be accessible to that actor.",
          "keyphrase_sources": [
            {
              "id": "weakness:Sensitive Information Exposure",
              "keyphrase": "Sensitive Information Exposure",
              "type": "weakness"
            },
            {
              "id": "weakness:sensitive data disclosure",
              "keyphrase": "sensitive data disclosure",
              "type": "weakness"
            },
            {
              "id": "weakness:information disclosure",
              "keyphrase": "information disclosure",
              "type": "weakness"
            },
            {
              "id": "impact:extract sensitive data",
              "keyphrase": "extract sensitive data",
              "type": "impact"
            },
            {
              "id": "product:JS Help Desk",
              "keyphrase": "JS Help Desk",
              "type": "product"
            },
            {
              "id": "version:all versions up to and including 2.8.8",
              "keyphrase": "all versions up to and including 2.8.8",
              "type": "version"
            }
          ]
        },
        "similarity": 337.9770082294699
      },
      {
        "metadata": {
          "doc_id": "200",
          "name": "Exposure of Sensitive Information to an Unauthorized Actor",
          "source": "sparse",
          "original_content": "The product exposes sensitive information to an actor that is not explicitly authorized to have access to that information.",
          "keyphrase_sources": [
            {
              "id": "weakness:Sensitive Information Exposure",
              "keyphrase": "Sensitive Information Exposure",
              "type": "weakness"
            }
          ]
        },
        "similarity": 334.60609951425613
      },
      {
        "metadata": {
          "doc_id": "434",
          "name": "Unrestricted Upload of File with Dangerous Type",
          "source": "sparse",
          "original_content": "The product allows the upload or transfer of dangerous file types that are automatically processed within its environment.",
          "keyphrase_sources": [
            {
              "id": "vector:unauthenticated access to jssupportticketdata directory",
              "keyphrase": "unauthenticated access to jssupportticketdata directory",
              "type": "vector"
            },
            {
              "id": "attacker:unauthenticated attackers",
              "keyphrase": "unauthenticated attackers",
              "type": "attacker"
            },
            {
              "id": "component:/wp-content/uploads/jssupportticketdata directory",
              "keyphrase": "/wp-content/uploads/jssupportticketdata directory",
              "type": "component"
            }
          ]
        },
        "similarity": 132.4745050748759
      },
      {
        "metadata": {
          "doc_id": "24",
          "name": "Path Traversal: '../filedir'",
          "source": "sparse",
          "original_content": "The product uses external input to construct a pathname that should be within a restricted directory, but it does not properly neutralize \"../\" sequences that can resolve to a location that is outside of that directory.",
          "keyphrase_sources": [
            {
              "id": "vector:unauthenticated access to jssupportticketdata directory",
              "keyphrase": "unauthenticated access to jssupportticketdata directory",
              "type": "vector"
            },
            {
              "id": "attacker:unauthenticated attackers",
              "keyphrase": "unauthenticated attackers",
              "type": "attacker"
            },
            {
              "id": "component:/wp-content/uploads/jssupportticketdata directory",
              "keyphrase": "/wp-content/uploads/jssupportticketdata directory",
              "type": "component"
            }
          ]
        },
        "similarity": 132.04320778806377
      },
      {
        "metadata": {
          "doc_id": "352",
          "name": "Cross-Site Request Forgery (CSRF)",
          "source": "sparse",
          "original_content": "The web application does not, or can not, sufficiently verify whether a well-formed, valid, consistent request was intentionally provided by the user who submitted the request.",
          "keyphrase_sources": [
            {
              "id": "vector:unauthenticated access to jssupportticketdata directory",
              "keyphrase": "unauthenticated access to jssupportticketdata directory",
              "type": "vector"
            },
            {
              "id": "attacker:unauthenticated attackers",
              "keyphrase": "unauthenticated attackers",
              "type": "attacker"
            },
            {
              "id": "product:JS Help Desk",
              "keyphrase": "JS Help Desk",
              "type": "product"
            },
            {
              "id": "version:all versions up to and including 2.8.8",
              "keyphrase": "all versions up to and including 2.8.8",
              "type": "version"
            },
            {
              "id": "component:/wp-content/uploads/jssupportticketdata directory",
              "keyphrase": "/wp-content/uploads/jssupportticketdata directory",
              "type": "component"
            }
          ]
        },
        "similarity": 129.95093956382422
      }
    ],
    "enhanced_query": "# Vulnerability Description\n\n    The JS Help Desk The Ultimate Help Desk & Support Plugin plugin for WordPress is vulnerable to **Sensitive Information Exposure** in all versions up to, and including, 2.8.8 via the jssupportticketdata directory. This makes it possible for unauthenticated attackers to extract sensitive data stored insecurely in the /wp-content/uploads/jssupportticketdata directory which can contain file attachments included in support tickets.\n\n    # Keyphrase-Specific CWE Analysis\n    This vulnerability contains multiple keyphrases that may map to different CWEs. \n    Please analyze each keyphrase separately and determine the most appropriate CWE(s) for each.\n\n    ## ROOTCAUSE: 'insecure file access permissions'\n\nRelevant CWEs for this ROOTCAUSE:\n\n### 1. CWE-639: Authorization Bypass Through User-Controlled Key (Score: 393.07)\n\nThe system's authorization functionality does not prevent one user from gaining access to another user's data or record by modifying the key value identifying the data....\n\n### 2. CWE-425: Direct Request ('Forced Browsing') (Score: 380.63)\n\nThe web application does not adequately enforce appropriate authorization on all restricted URLs, scripts, or files....\n\n### 3. CWE-522: Insufficiently Protected Credentials (Score: 376.65)\n\nThe product transmits or stores authentication credentials, but it uses an insecure method that is susceptible to unauthorized interception and/or retrieval....\n\n### 4. CWE-863: Incorrect Authorization (Score: 371.80)\n\nThe product performs an authorization check when an actor attempts to access a resource or perform an action, but it does not correctly perform the check....\n\n### 5. CWE-862: Missing Authorization (Score: 369.05)\n\nThe product does not perform an authorization check when an actor attempts to access a resource or perform an action....\n\n## WEAKNESS: 'Sensitive Information Exposure'\n\nRelevant CWEs for this WEAKNESS:\n\n### 1. CWE-639: Authorization Bypass Through User-Controlled Key (Score: 393.07)\n\nThe system's authorization functionality does not prevent one user from gaining access to another user's data or record by modifying the key value identifying the data....\n\n### 2. CWE-425: Direct Request ('Forced Browsing') (Score: 380.63)\n\nThe web application does not adequately enforce appropriate authorization on all restricted URLs, scripts, or files....\n\n### 3. CWE-863: Incorrect Authorization (Score: 371.80)\n\nThe product performs an authorization check when an actor attempts to access a resource or perform an action, but it does not correctly perform the check....\n\n### 4. CWE-201: Insertion of Sensitive Information Into Sent Data (Score: 337.98)\n\nThe code transmits data to another actor, but a portion of the data includes sensitive information that should not be accessible to that actor....\n\n### 5. CWE-200: Exposure of Sensitive Information to an Unauthorized Actor (Score: 334.61)\n\nThe product exposes sensitive information to an actor that is not explicitly authorized to have access to that information....\n\n## WEAKNESS: 'sensitive data disclosure'\n\nRelevant CWEs for this WEAKNESS:\n\n### 1. CWE-639: Authorization Bypass Through User-Controlled Key (Score: 393.07)\n\nThe system's authorization functionality does not prevent one user from gaining access to another user's data or record by modifying the key value identifying the data....\n\n### 2. CWE-425: Direct Request ('Forced Browsing') (Score: 380.63)\n\nThe web application does not adequately enforce appropriate authorization on all restricted URLs, scripts, or files....\n\n### 3. CWE-522: Insufficiently Protected Credentials (Score: 376.65)\n\nThe product transmits or stores authentication credentials, but it uses an insecure method that is susceptible to unauthorized interception and/or retrieval....\n\n### 4. CWE-862: Missing Authorization (Score: 369.05)\n\nThe product does not perform an authorization check when an actor attempts to access a resource or perform an action....\n\n### 5. CWE-201: Insertion of Sensitive Information Into Sent Data (Score: 337.98)\n\nThe code transmits data to another actor, but a portion of the data includes sensitive information that should not be accessible to that actor....\n\n## WEAKNESS: 'information disclosure'\n\nRelevant CWEs for this WEAKNESS:\n\n### 1. CWE-639: Authorization Bypass Through User-Controlled Key (Score: 393.07)\n\nThe system's authorization functionality does not prevent one user from gaining access to another user's data or record by modifying the key value identifying the data....\n\n### 2. CWE-522: Insufficiently Protected Credentials (Score: 376.65)\n\nThe product transmits or stores authentication credentials, but it uses an insecure method that is susceptible to unauthorized interception and/or retrieval....\n\n### 3. CWE-863: Incorrect Authorization (Score: 371.80)\n\nThe product performs an authorization check when an actor attempts to access a resource or perform an action, but it does not correctly perform the check....\n\n### 4. CWE-862: Missing Authorization (Score: 369.05)\n\nThe product does not perform an authorization check when an actor attempts to access a resource or perform an action....\n\n### 5. CWE-201: Insertion of Sensitive Information Into Sent Data (Score: 337.98)\n\nThe code transmits data to another actor, but a portion of the data includes sensitive information that should not be accessible to that actor....\n\n## IMPACT: 'extract sensitive data'\n\nRelevant CWEs for this IMPACT:\n\n### 1. CWE-639: Authorization Bypass Through User-Controlled Key (Score: 393.07)\n\nThe system's authorization functionality does not prevent one user from gaining access to another user's data or record by modifying the key value identifying the data....\n\n### 2. CWE-522: Insufficiently Protected Credentials (Score: 376.65)\n\nThe product transmits or stores authentication credentials, but it uses an insecure method that is susceptible to unauthorized interception and/or retrieval....\n\n### 3. CWE-863: Incorrect Authorization (Score: 371.80)\n\nThe product performs an authorization check when an actor attempts to access a resource or perform an action, but it does not correctly perform the check....\n\n### 4. CWE-862: Missing Authorization (Score: 369.05)\n\nThe product does not perform an authorization check when an actor attempts to access a resource or perform an action....\n\n### 5. CWE-201: Insertion of Sensitive Information Into Sent Data (Score: 337.98)\n\nThe code transmits data to another actor, but a portion of the data includes sensitive information that should not be accessible to that actor....\n\n## ATTACKER: 'unauthenticated attackers'\n\nRelevant CWEs for this ATTACKER:\n\n### 1. CWE-639: Authorization Bypass Through User-Controlled Key (Score: 393.07)\n\nThe system's authorization functionality does not prevent one user from gaining access to another user's data or record by modifying the key value identifying the data....\n\n### 2. CWE-862: Missing Authorization (Score: 369.05)\n\nThe product does not perform an authorization check when an actor attempts to access a resource or perform an action....\n\n### 3. CWE-434: Unrestricted Upload of File with Dangerous Type (Score: 132.47)\n\nThe product allows the upload or transfer of dangerous file types that are automatically processed within its environment....\n\n### 4. CWE-24: Path Traversal: '../filedir' (Score: 132.04)\n\nThe product uses external input to construct a pathname that should be within a restricted directory, but it does not properly neutralize \"../\" sequences that can resolve to a location that is outside of that directory....\n\n### 5. CWE-352: Cross-Site Request Forgery (CSRF) (Score: 129.95)\n\nThe web application does not, or can not, sufficiently verify whether a well-formed, valid, consistent request was intentionally provided by the user who submitted the request....\n\n## PRODUCT: 'JS Help Desk'\n\nRelevant CWEs for this PRODUCT:\n\n### 1. CWE-639: Authorization Bypass Through User-Controlled Key (Score: 393.07)\n\nThe system's authorization functionality does not prevent one user from gaining access to another user's data or record by modifying the key value identifying the data....\n\n### 2. CWE-522: Insufficiently Protected Credentials (Score: 376.65)\n\nThe product transmits or stores authentication credentials, but it uses an insecure method that is susceptible to unauthorized interception and/or retrieval....\n\n### 3. CWE-863: Incorrect Authorization (Score: 371.80)\n\nThe product performs an authorization check when an actor attempts to access a resource or perform an action, but it does not correctly perform the check....\n\n### 4. CWE-201: Insertion of Sensitive Information Into Sent Data (Score: 337.98)\n\nThe code transmits data to another actor, but a portion of the data includes sensitive information that should not be accessible to that actor....\n\n### 5. CWE-352: Cross-Site Request Forgery (CSRF) (Score: 129.95)\n\nThe web application does not, or can not, sufficiently verify whether a well-formed, valid, consistent request was intentionally provided by the user who submitted the request....\n\n## VECTOR: 'unauthenticated access to jssupportticketdata directory'\n\nRelevant CWEs for this VECTOR:\n\n### 1. CWE-425: Direct Request ('Forced Browsing') (Score: 380.63)\n\nThe web application does not adequately enforce appropriate authorization on all restricted URLs, scripts, or files....\n\n### 2. CWE-863: Incorrect Authorization (Score: 371.80)\n\nThe product performs an authorization check when an actor attempts to access a resource or perform an action, but it does not correctly perform the check....\n\n### 3. CWE-434: Unrestricted Upload of File with Dangerous Type (Score: 132.47)\n\nThe product allows the upload or transfer of dangerous file types that are automatically processed within its environment....\n\n### 4. CWE-24: Path Traversal: '../filedir' (Score: 132.04)\n\nThe product uses external input to construct a pathname that should be within a restricted directory, but it does not properly neutralize \"../\" sequences that can resolve to a location that is outside of that directory....\n\n### 5. CWE-352: Cross-Site Request Forgery (CSRF) (Score: 129.95)\n\nThe web application does not, or can not, sufficiently verify whether a well-formed, valid, consistent request was intentionally provided by the user who submitted the request....\n\n## COMPONENT: '/wp-content/uploads/jssupportticketdata directory'\n\nRelevant CWEs for this COMPONENT:\n\n### 1. CWE-425: Direct Request ('Forced Browsing') (Score: 380.63)\n\nThe web application does not adequately enforce appropriate authorization on all restricted URLs, scripts, or files....\n\n### 2. CWE-863: Incorrect Authorization (Score: 371.80)\n\nThe product performs an authorization check when an actor attempts to access a resource or perform an action, but it does not correctly perform the check....\n\n### 3. CWE-434: Unrestricted Upload of File with Dangerous Type (Score: 132.47)\n\nThe product allows the upload or transfer of dangerous file types that are automatically processed within its environment....\n\n### 4. CWE-24: Path Traversal: '../filedir' (Score: 132.04)\n\nThe product uses external input to construct a pathname that should be within a restricted directory, but it does not properly neutralize \"../\" sequences that can resolve to a location that is outside of that directory....\n\n### 5. CWE-352: Cross-Site Request Forgery (CSRF) (Score: 129.95)\n\nThe web application does not, or can not, sufficiently verify whether a well-formed, valid, consistent request was intentionally provided by the user who submitted the request....\n\n## VERSION: 'all versions up to and including 2.8.8'\n\nRelevant CWEs for this VERSION:\n\n### 1. CWE-522: Insufficiently Protected Credentials (Score: 376.65)\n\nThe product transmits or stores authentication credentials, but it uses an insecure method that is susceptible to unauthorized interception and/or retrieval....\n\n### 2. CWE-863: Incorrect Authorization (Score: 371.80)\n\nThe product performs an authorization check when an actor attempts to access a resource or perform an action, but it does not correctly perform the check....\n\n### 3. CWE-862: Missing Authorization (Score: 369.05)\n\nThe product does not perform an authorization check when an actor attempts to access a resource or perform an action....\n\n### 4. CWE-201: Insertion of Sensitive Information Into Sent Data (Score: 337.98)\n\nThe code transmits data to another actor, but a portion of the data includes sensitive information that should not be accessible to that actor....\n\n### 5. CWE-352: Cross-Site Request Forgery (CSRF) (Score: 129.95)\n\nThe web application does not, or can not, sufficiently verify whether a well-formed, valid, consistent request was intentionally provided by the user who submitted the request....\n\n\n    # Analysis Instructions\n    1. For each keyphrase, identify the most appropriate CWE(s) that represent the weakness.\n    2. Consider how the different keyphrases might relate to each other in the vulnerability chain.\n    3. Provide a final determination of primary CWE(s) and any secondary CWEs.\n    4. Format your response using the standard analysis template.\n\n    Please analyze how these different weaknesses interact and provide a comprehensive CWE classification.\n    "
  },
  "retrieval_time": 2.957958221435547
}