{
  "vulnerability_info": "VulnerabilityInfo(cve_id='CVE-2024-45781', description='A flaw was found in grub2. When reading a symbolic links name from a UFS filesystem, grub2 **fails to validate the string length taken as an input**. The **lack of validation** may lead to a **heap out-of-bounds write**, causing data integrity issues and eventually allowing an attacker to circumvent secure boot protections.', key_phrases={'rootcause': ['fails to validate the string length taken as an input', 'lack of validation'], 'weakness': 'heap out-of-bounds write', 'impact': ['circumvent secure boot protections', 'data integrity issues'], 'vector': 'reading symbolic links name from UFS filesystem', 'attacker': 'attacker', 'product': 'grub2', 'version': '', 'component': ''}, reference_content=\"**1. Content from access.redhat.com_c74bc20c_20250624_195620.html (stripped)**\\n\\n*   **Relevant**\\n    *   **Root cause of vulnerability:** The grub2 packages provide version 2 of the Grand Unified Boot Loader (GRUB), a highly configurable and customizable boot loader with modular architecture. The packages support a variety of kernel formats, file systems, computer architectures, and hardware devices.\\n    *   **Weaknesses/vulnerabilities present:**\\n        *   CVE-2024-45781 grub2: fs/ufs: OOB write in the heap\\n        *   CVE-2024-45774 grub2: reader/jpeg: Heap OOB Write during JPEG parsing\\n        *   CVE-2024-45775 grub2: commands/extcmd: Missing check for failed allocation\\n        *   CVE-2024-45776 grub2: grub-core/gettext: Integer overflow leads to Heap OOB Write and Read.\\n        *   CVE-2024-45783 grub2: fs/hfs+: refcount can be decremented twice\\n        *   CVE-2025-0622 grub2: command/gpg: Use-after-free due to hooks not being removed on module unload\\n        *   CVE-2025-0677 grub2: UFS: Integer overflow may lead to heap based out-of-bounds write when handling symlinks\\n        *   CVE-2025-0690 grub2: read: Integer overflow may lead to out-of-bounds write\\n    *   **Impact of exploitation:** The security impact is rated as Moderate.\\n    *   **Mitigation or fix:** An update for grub2 is now available for Red Hat Enterprise Linux 9.\\n\\n**2. Content from bugzilla.redhat.com\\\\_5b935c35\\\\_20250624\\\\_211154.html (text)**\\n\\n*   **Relevant**\\n    *   **Weaknesses/vulnerabilities present:** CVE-2024-45781 grub2: fs/ufs: OOB write in the heap\\n    *   **Impact of exploitation:** When reading a symbolic link's name from a UFS filesystem, grub2 fails to validate the string length taken as an input. The lack of validation may lead to a heap Out-of-bounds write, causing data integrity issues and eventually allowing an attacker to circumvent secure boot protections.\\n    *   **Mitigation or fix:** This issue has been addressed in the following products: Red Hat Enterprise Linux 9 Via RHSA-2025:6990.\\n\\n**3. Content from bugzilla.redhat.com\\\\_d3bf86c9\\\\_20250624\\\\_211152.html (text)**\\n\\n*   **Relevant**\\n    *   **Weaknesses/vulnerabilities present:** CVE-2024-45783 grub2: fs/hfs+: refcount can be decremented twice\\n    *   **Impact of exploitation:** When failing to mount a HFS+ grub hfsplus filesystem driver doesn't properly set a ERRNO value. This may lead to a NULL pointer access.\\n    *   **Mitigation or fix:** This issue has been addressed in the following products: Red Hat Enterprise Linux 9 Via RHSA-2025:6990\", similar_info={'cwe_distribution': {}, 'cwe_consensus': '', 'similarity_stats': {'thresholds': [], 'total_samples_by_threshold': {}, 'top_cwes_by_threshold': {}}}, similarity_summary=SimilarityInsight(consensus_cwe='', top_cwes=[], confidence_levels={}, total_samples=0), analysis='', analysis_with_relationships='', criticism='', resolution='', relevant_cwes=[{'metadata': {'doc_id': '1284', 'name': 'Improper Validation of Specified Quantity in Input', 'source': 'sparse', 'original_content': 'The product receives input that is expected to specify a quantity (such as size or length), but it does not validate or incorrectly validates that the quantity has the required properties.', 'keyphrase_sources': [{'id': 'rootcause:fails to validate the string length taken as an input', 'keyphrase': 'fails to validate the string length taken as an input', 'type': 'rootcause'}, {'id': 'rootcause:lack of validation', 'keyphrase': 'lack of validation', 'type': 'rootcause'}, {'id': 'weakness:heap out-of-bounds write', 'keyphrase': 'heap out-of-bounds write', 'type': 'weakness'}, {'id': 'impact:circumvent secure boot protections', 'keyphrase': 'circumvent secure boot protections', 'type': 'impact'}, {'id': 'impact:data integrity issues', 'keyphrase': 'data integrity issues', 'type': 'impact'}, {'id': 'attacker:attacker', 'keyphrase': 'attacker', 'type': 'attacker'}, {'id': 'product:grub2', 'keyphrase': 'grub2', 'type': 'product'}]}, 'similarity': np.float64(483.1539735343653)}, {'metadata': {'doc_id': '125', 'name': 'Out-of-bounds Read', 'source': 'sparse', 'original_content': 'The product reads data past the end, or before the beginning, of the intended buffer.', 'keyphrase_sources': [{'id': 'rootcause:fails to validate the string length taken as an input', 'keyphrase': 'fails to validate the string length taken as an input', 'type': 'rootcause'}, {'id': 'rootcause:lack of validation', 'keyphrase': 'lack of validation', 'type': 'rootcause'}, {'id': 'weakness:heap out-of-bounds write', 'keyphrase': 'heap out-of-bounds write', 'type': 'weakness'}, {'id': 'impact:circumvent secure boot protections', 'keyphrase': 'circumvent secure boot protections', 'type': 'impact'}, {'id': 'impact:data integrity issues', 'keyphrase': 'data integrity issues', 'type': 'impact'}, {'id': 'vector:reading symbolic links name from UFS filesystem', 'keyphrase': 'reading symbolic links name from UFS filesystem', 'type': 'vector'}, {'id': 'attacker:attacker', 'keyphrase': 'attacker', 'type': 'attacker'}, {'id': 'product:grub2', 'keyphrase': 'grub2', 'type': 'product'}]}, 'similarity': np.float64(481.85351497393697)}, {'metadata': {'doc_id': '789', 'name': 'Memory Allocation with Excessive Size Value', 'source': 'sparse', 'original_content': 'The product allocates memory based on an untrusted, large size value, but it does not ensure that the size is within expected limits, allowing arbitrary amounts of memory to be allocated.', 'keyphrase_sources': [{'id': 'rootcause:fails to validate the string length taken as an input', 'keyphrase': 'fails to validate the string length taken as an input', 'type': 'rootcause'}]}, 'similarity': np.float64(450.0220203779836)}, {'metadata': {'doc_id': '190', 'name': 'Integer Overflow or Wraparound', 'source': 'sparse', 'original_content': 'The product performs a calculation that can\\n         produce an integer overflow or wraparound when the logic\\n         assumes that the resulting value will always be larger than\\n         the original value. This occurs when an integer value is\\n         incremented to a value that is too large to store in the\\n         associated representation. When this occurs, the value may\\n         become a very small or negative number.', 'keyphrase_sources': [{'id': 'rootcause:fails to validate the string length taken as an input', 'keyphrase': 'fails to validate the string length taken as an input', 'type': 'rootcause'}, {'id': 'weakness:heap out-of-bounds write', 'keyphrase': 'heap out-of-bounds write', 'type': 'weakness'}, {'id': 'impact:circumvent secure boot protections', 'keyphrase': 'circumvent secure boot protections', 'type': 'impact'}, {'id': 'impact:data integrity issues', 'keyphrase': 'data integrity issues', 'type': 'impact'}, {'id': 'attacker:attacker', 'keyphrase': 'attacker', 'type': 'attacker'}, {'id': 'product:grub2', 'keyphrase': 'grub2', 'type': 'product'}]}, 'similarity': np.float64(436.0014924343243)}, {'metadata': {'doc_id': '20', 'name': 'Improper Input Validation', 'source': 'sparse', 'original_content': 'The product receives input or data, but it does\\n        not validate or incorrectly validates that the input has the\\n        properties that are required to process the data safely and\\n        correctly.', 'keyphrase_sources': [{'id': 'rootcause:fails to validate the string length taken as an input', 'keyphrase': 'fails to validate the string length taken as an input', 'type': 'rootcause'}, {'id': 'rootcause:lack of validation', 'keyphrase': 'lack of validation', 'type': 'rootcause'}]}, 'similarity': np.float64(428.8750279164677)}, {'metadata': {'doc_id': '122', 'name': 'Heap-based Buffer Overflow', 'source': 'sparse', 'original_content': 'A heap overflow condition is a buffer overflow, where the buffer that can be overwritten is allocated in the heap portion of memory, generally meaning that the buffer was allocated using a routine such as malloc().', 'keyphrase_sources': [{'id': 'weakness:heap out-of-bounds write', 'keyphrase': 'heap out-of-bounds write', 'type': 'weakness'}, {'id': 'attacker:attacker', 'keyphrase': 'attacker', 'type': 'attacker'}]}, 'similarity': np.float64(396.3535483067532)}, {'metadata': {'doc_id': '191', 'name': 'Integer Underflow (Wrap or Wraparound)', 'source': 'sparse', 'original_content': 'The product subtracts one value from another, such that the result is less than the minimum allowable integer value, which produces a value that is not equal to the correct result.', 'keyphrase_sources': [{'id': 'weakness:heap out-of-bounds write', 'keyphrase': 'heap out-of-bounds write', 'type': 'weakness'}]}, 'similarity': np.float64(385.0116086058019)}, {'metadata': {'doc_id': '787', 'name': 'Out-of-bounds Write', 'source': 'sparse', 'original_content': 'The product writes data past the end, or before the beginning, of the intended buffer.', 'keyphrase_sources': [{'id': 'rootcause:lack of validation', 'keyphrase': 'lack of validation', 'type': 'rootcause'}, {'id': 'impact:data integrity issues', 'keyphrase': 'data integrity issues', 'type': 'impact'}, {'id': 'attacker:attacker', 'keyphrase': 'attacker', 'type': 'attacker'}, {'id': 'product:grub2', 'keyphrase': 'grub2', 'type': 'product'}]}, 'similarity': np.float64(345.97417212348716)}, {'metadata': {'doc_id': '119', 'name': 'Improper Restriction of Operations within the Bounds of a Memory Buffer', 'source': 'sparse', 'original_content': \"The product performs operations on a memory buffer, but it reads from or writes to a memory location outside the buffer's intended boundary. This may result in read or write operations on unexpected memory locations that could be linked to other variables, data structures, or internal program data.\", 'keyphrase_sources': [{'id': 'rootcause:lack of validation', 'keyphrase': 'lack of validation', 'type': 'rootcause'}]}, 'similarity': np.float64(342.7561105016059)}, {'metadata': {'doc_id': '61', 'name': 'UNIX Symbolic Link (Symlink) Following', 'source': 'sparse', 'original_content': 'The product, when opening a file or directory, does not sufficiently account for when the file is a symbolic link that resolves to a target outside of the intended control sphere. This could allow an attacker to cause the product to operate on unauthorized files.', 'keyphrase_sources': [{'id': 'vector:reading symbolic links name from UFS filesystem', 'keyphrase': 'reading symbolic links name from UFS filesystem', 'type': 'vector'}]}, 'similarity': np.float64(143.4003800186367)}, {'metadata': {'doc_id': '59', 'name': \"Improper Link Resolution Before File Access ('Link Following')\", 'source': 'sparse', 'original_content': 'The product attempts to access a file based on the filename, but it does not properly prevent that filename from identifying a link or shortcut that resolves to an unintended resource.', 'keyphrase_sources': [{'id': 'vector:reading symbolic links name from UFS filesystem', 'keyphrase': 'reading symbolic links name from UFS filesystem', 'type': 'vector'}]}, 'similarity': np.float64(141.7088316529249)}, {'metadata': {'doc_id': '22', 'name': \"Improper Limitation of a Pathname to a Restricted Directory ('Path Traversal')\", 'source': 'sparse', 'original_content': 'The product uses external input to construct a pathname that is intended to identify a file or directory that is located underneath a restricted parent directory, but the product does not properly neutralize special elements within the pathname that can cause the pathname to resolve to a location that is outside of the restricted directory.', 'keyphrase_sources': [{'id': 'vector:reading symbolic links name from UFS filesystem', 'keyphrase': 'reading symbolic links name from UFS filesystem', 'type': 'vector'}]}, 'similarity': np.float64(119.15232297127596)}, {'metadata': {'doc_id': '1289', 'name': 'Improper Validation of Unsafe Equivalence in Input', 'source': 'sparse', 'original_content': 'The product receives an input value that is used as a resource identifier or other type of reference, but it does not validate or incorrectly validates that the input is equivalent to a potentially-unsafe value.', 'keyphrase_sources': [{'id': 'vector:reading symbolic links name from UFS filesystem', 'keyphrase': 'reading symbolic links name from UFS filesystem', 'type': 'vector'}]}, 'similarity': np.float64(116.58695973183305)}, {'metadata': {'doc_id': '1247', 'name': 'Improper Protection Against Voltage and Clock Glitches', 'source': 'sparse', 'original_content': 'The device does not contain or contains incorrectly implemented circuitry or sensors to detect and mitigate voltage and clock glitches and protect sensitive information or software contained on the device.', 'keyphrase_sources': [{'id': 'impact:circumvent secure boot protections', 'keyphrase': 'circumvent secure boot protections', 'type': 'impact'}]}, 'similarity': np.float64(109.18223464396279)}, {'metadata': {'doc_id': '1274', 'name': 'Improper Access Control for Volatile Memory Containing Boot Code', 'source': 'sparse', 'original_content': 'The product conducts a secure-boot process that transfers bootloader code from Non-Volatile Memory (NVM) into Volatile Memory (VM), but it does not have sufficient access control or other protections for the Volatile Memory.', 'keyphrase_sources': [{'id': 'impact:circumvent secure boot protections', 'keyphrase': 'circumvent secure boot protections', 'type': 'impact'}]}, 'similarity': np.float64(107.84795018624206)}, {'metadata': {'doc_id': '276', 'name': 'Incorrect Default Permissions', 'source': 'sparse', 'original_content': 'During installation, installed file permissions are set to allow anyone to modify those files.', 'keyphrase_sources': [{'id': 'impact:data integrity issues', 'keyphrase': 'data integrity issues', 'type': 'impact'}, {'id': 'product:grub2', 'keyphrase': 'grub2', 'type': 'product'}]}, 'similarity': np.float64(106.17919184842388)}], identified_cwes={'analyzer': [], 'critic_additional': []})",
  "retrieval_results": {
    "has_multiple_keyphrases": true,
    "keyphrase_cwe_sets": {
      "rootcause:fails to validate the string length taken as an input": {
        "keyphrase": "fails to validate the string length taken as an input",
        "type": "rootcause",
        "cwes": [
          {
            "metadata": {
              "doc_id": "1284",
              "name": "Improper Validation of Specified Quantity in Input",
              "source": "sparse",
              "original_content": "The product receives input that is expected to specify a quantity (such as size or length), but it does not validate or incorrectly validates that the quantity has the required properties.",
              "keyphrase_sources": [
                {
                  "id": "rootcause:fails to validate the string length taken as an input",
                  "keyphrase": "fails to validate the string length taken as an input",
                  "type": "rootcause"
                },
                {
                  "id": "rootcause:lack of validation",
                  "keyphrase": "lack of validation",
                  "type": "rootcause"
                },
                {
                  "id": "weakness:heap out-of-bounds write",
                  "keyphrase": "heap out-of-bounds write",
                  "type": "weakness"
                },
                {
                  "id": "impact:circumvent secure boot protections",
                  "keyphrase": "circumvent secure boot protections",
                  "type": "impact"
                },
                {
                  "id": "impact:data integrity issues",
                  "keyphrase": "data integrity issues",
                  "type": "impact"
                },
                {
                  "id": "attacker:attacker",
                  "keyphrase": "attacker",
                  "type": "attacker"
                },
                {
                  "id": "product:grub2",
                  "keyphrase": "grub2",
                  "type": "product"
                }
              ]
            },
            "similarity": 483.1539735343653
          },
          {
            "metadata": {
              "doc_id": "125",
              "name": "Out-of-bounds Read",
              "source": "sparse",
              "original_content": "The product reads data past the end, or before the beginning, of the intended buffer.",
              "keyphrase_sources": [
                {
                  "id": "rootcause:fails to validate the string length taken as an input",
                  "keyphrase": "fails to validate the string length taken as an input",
                  "type": "rootcause"
                },
                {
                  "id": "rootcause:lack of validation",
                  "keyphrase": "lack of validation",
                  "type": "rootcause"
                },
                {
                  "id": "weakness:heap out-of-bounds write",
                  "keyphrase": "heap out-of-bounds write",
                  "type": "weakness"
                },
                {
                  "id": "impact:circumvent secure boot protections",
                  "keyphrase": "circumvent secure boot protections",
                  "type": "impact"
                },
                {
                  "id": "impact:data integrity issues",
                  "keyphrase": "data integrity issues",
                  "type": "impact"
                },
                {
                  "id": "vector:reading symbolic links name from UFS filesystem",
                  "keyphrase": "reading symbolic links name from UFS filesystem",
                  "type": "vector"
                },
                {
                  "id": "attacker:attacker",
                  "keyphrase": "attacker",
                  "type": "attacker"
                },
                {
                  "id": "product:grub2",
                  "keyphrase": "grub2",
                  "type": "product"
                }
              ]
            },
            "similarity": 481.85351497393697
          },
          {
            "metadata": {
              "doc_id": "789",
              "name": "Memory Allocation with Excessive Size Value",
              "source": "sparse",
              "original_content": "The product allocates memory based on an untrusted, large size value, but it does not ensure that the size is within expected limits, allowing arbitrary amounts of memory to be allocated.",
              "keyphrase_sources": [
                {
                  "id": "rootcause:fails to validate the string length taken as an input",
                  "keyphrase": "fails to validate the string length taken as an input",
                  "type": "rootcause"
                }
              ]
            },
            "similarity": 450.0220203779836
          },
          {
            "metadata": {
              "doc_id": "190",
              "name": "Integer Overflow or Wraparound",
              "source": "sparse",
              "original_content": "The product performs a calculation that can\n         produce an integer overflow or wraparound when the logic\n         assumes that the resulting value will always be larger than\n         the original value. This occurs when an integer value is\n         incremented to a value that is too large to store in the\n         associated representation. When this occurs, the value may\n         become a very small or negative number.",
              "keyphrase_sources": [
                {
                  "id": "rootcause:fails to validate the string length taken as an input",
                  "keyphrase": "fails to validate the string length taken as an input",
                  "type": "rootcause"
                },
                {
                  "id": "weakness:heap out-of-bounds write",
                  "keyphrase": "heap out-of-bounds write",
                  "type": "weakness"
                },
                {
                  "id": "impact:circumvent secure boot protections",
                  "keyphrase": "circumvent secure boot protections",
                  "type": "impact"
                },
                {
                  "id": "impact:data integrity issues",
                  "keyphrase": "data integrity issues",
                  "type": "impact"
                },
                {
                  "id": "attacker:attacker",
                  "keyphrase": "attacker",
                  "type": "attacker"
                },
                {
                  "id": "product:grub2",
                  "keyphrase": "grub2",
                  "type": "product"
                }
              ]
            },
            "similarity": 436.0014924343243
          },
          {
            "metadata": {
              "doc_id": "20",
              "name": "Improper Input Validation",
              "source": "sparse",
              "original_content": "The product receives input or data, but it does\n        not validate or incorrectly validates that the input has the\n        properties that are required to process the data safely and\n        correctly.",
              "keyphrase_sources": [
                {
                  "id": "rootcause:fails to validate the string length taken as an input",
                  "keyphrase": "fails to validate the string length taken as an input",
                  "type": "rootcause"
                },
                {
                  "id": "rootcause:lack of validation",
                  "keyphrase": "lack of validation",
                  "type": "rootcause"
                }
              ]
            },
            "similarity": 428.8750279164677
          }
        ]
      },
      "rootcause:lack of validation": {
        "keyphrase": "lack of validation",
        "type": "rootcause",
        "cwes": [
          {
            "metadata": {
              "doc_id": "1284",
              "name": "Improper Validation of Specified Quantity in Input",
              "source": "sparse",
              "original_content": "The product receives input that is expected to specify a quantity (such as size or length), but it does not validate or incorrectly validates that the quantity has the required properties."
            },
            "similarity": 382.0178430129332
          },
          {
            "metadata": {
              "doc_id": "125",
              "name": "Out-of-bounds Read",
              "source": "sparse",
              "original_content": "The product reads data past the end, or before the beginning, of the intended buffer."
            },
            "similarity": 378.5408909249336
          },
          {
            "metadata": {
              "doc_id": "20",
              "name": "Improper Input Validation",
              "source": "sparse",
              "original_content": "The product receives input or data, but it does\n        not validate or incorrectly validates that the input has the\n        properties that are required to process the data safely and\n        correctly."
            },
            "similarity": 358.34173654668894
          },
          {
            "metadata": {
              "doc_id": "787",
              "name": "Out-of-bounds Write",
              "source": "sparse",
              "original_content": "The product writes data past the end, or before the beginning, of the intended buffer.",
              "keyphrase_sources": [
                {
                  "id": "rootcause:lack of validation",
                  "keyphrase": "lack of validation",
                  "type": "rootcause"
                },
                {
                  "id": "impact:data integrity issues",
                  "keyphrase": "data integrity issues",
                  "type": "impact"
                },
                {
                  "id": "attacker:attacker",
                  "keyphrase": "attacker",
                  "type": "attacker"
                },
                {
                  "id": "product:grub2",
                  "keyphrase": "grub2",
                  "type": "product"
                }
              ]
            },
            "similarity": 345.97417212348716
          },
          {
            "metadata": {
              "doc_id": "119",
              "name": "Improper Restriction of Operations within the Bounds of a Memory Buffer",
              "source": "sparse",
              "original_content": "The product performs operations on a memory buffer, but it reads from or writes to a memory location outside the buffer's intended boundary. This may result in read or write operations on unexpected memory locations that could be linked to other variables, data structures, or internal program data.",
              "keyphrase_sources": [
                {
                  "id": "rootcause:lack of validation",
                  "keyphrase": "lack of validation",
                  "type": "rootcause"
                }
              ]
            },
            "similarity": 342.7561105016059
          }
        ]
      },
      "weakness:heap out-of-bounds write": {
        "keyphrase": "heap out-of-bounds write",
        "type": "weakness",
        "cwes": [
          {
            "metadata": {
              "doc_id": "125",
              "name": "Out-of-bounds Read",
              "source": "sparse",
              "original_content": "The product reads data past the end, or before the beginning, of the intended buffer."
            },
            "similarity": 428.0513616749351
          },
          {
            "metadata": {
              "doc_id": "190",
              "name": "Integer Overflow or Wraparound",
              "source": "sparse",
              "original_content": "The product performs a calculation that can\n         produce an integer overflow or wraparound when the logic\n         assumes that the resulting value will always be larger than\n         the original value. This occurs when an integer value is\n         incremented to a value that is too large to store in the\n         associated representation. When this occurs, the value may\n         become a very small or negative number."
            },
            "similarity": 401.3814966415024
          },
          {
            "metadata": {
              "doc_id": "122",
              "name": "Heap-based Buffer Overflow",
              "source": "sparse",
              "original_content": "A heap overflow condition is a buffer overflow, where the buffer that can be overwritten is allocated in the heap portion of memory, generally meaning that the buffer was allocated using a routine such as malloc().",
              "keyphrase_sources": [
                {
                  "id": "weakness:heap out-of-bounds write",
                  "keyphrase": "heap out-of-bounds write",
                  "type": "weakness"
                },
                {
                  "id": "attacker:attacker",
                  "keyphrase": "attacker",
                  "type": "attacker"
                }
              ]
            },
            "similarity": 396.3535483067532
          },
          {
            "metadata": {
              "doc_id": "1284",
              "name": "Improper Validation of Specified Quantity in Input",
              "source": "sparse",
              "original_content": "The product receives input that is expected to specify a quantity (such as size or length), but it does not validate or incorrectly validates that the quantity has the required properties."
            },
            "similarity": 393.327037159109
          },
          {
            "metadata": {
              "doc_id": "191",
              "name": "Integer Underflow (Wrap or Wraparound)",
              "source": "sparse",
              "original_content": "The product subtracts one value from another, such that the result is less than the minimum allowable integer value, which produces a value that is not equal to the correct result.",
              "keyphrase_sources": [
                {
                  "id": "weakness:heap out-of-bounds write",
                  "keyphrase": "heap out-of-bounds write",
                  "type": "weakness"
                }
              ]
            },
            "similarity": 385.0116086058019
          }
        ]
      },
      "impact:circumvent secure boot protections": {
        "keyphrase": "circumvent secure boot protections",
        "type": "impact",
        "cwes": [
          {
            "metadata": {
              "doc_id": "125",
              "name": "Out-of-bounds Read",
              "source": "sparse",
              "original_content": "The product reads data past the end, or before the beginning, of the intended buffer."
            },
            "similarity": 115.07788793187532
          },
          {
            "metadata": {
              "doc_id": "1284",
              "name": "Improper Validation of Specified Quantity in Input",
              "source": "sparse",
              "original_content": "The product receives input that is expected to specify a quantity (such as size or length), but it does not validate or incorrectly validates that the quantity has the required properties."
            },
            "similarity": 112.72771350816373
          },
          {
            "metadata": {
              "doc_id": "1247",
              "name": "Improper Protection Against Voltage and Clock Glitches",
              "source": "sparse",
              "original_content": "The device does not contain or contains incorrectly implemented circuitry or sensors to detect and mitigate voltage and clock glitches and protect sensitive information or software contained on the device.",
              "keyphrase_sources": [
                {
                  "id": "impact:circumvent secure boot protections",
                  "keyphrase": "circumvent secure boot protections",
                  "type": "impact"
                }
              ]
            },
            "similarity": 109.18223464396279
          },
          {
            "metadata": {
              "doc_id": "1274",
              "name": "Improper Access Control for Volatile Memory Containing Boot Code",
              "source": "sparse",
              "original_content": "The product conducts a secure-boot process that transfers bootloader code from Non-Volatile Memory (NVM) into Volatile Memory (VM), but it does not have sufficient access control or other protections for the Volatile Memory.",
              "keyphrase_sources": [
                {
                  "id": "impact:circumvent secure boot protections",
                  "keyphrase": "circumvent secure boot protections",
                  "type": "impact"
                }
              ]
            },
            "similarity": 107.84795018624206
          },
          {
            "metadata": {
              "doc_id": "190",
              "name": "Integer Overflow or Wraparound",
              "source": "sparse",
              "original_content": "The product performs a calculation that can\n         produce an integer overflow or wraparound when the logic\n         assumes that the resulting value will always be larger than\n         the original value. This occurs when an integer value is\n         incremented to a value that is too large to store in the\n         associated representation. When this occurs, the value may\n         become a very small or negative number."
            },
            "similarity": 105.95117037416144
          }
        ]
      },
      "impact:data integrity issues": {
        "keyphrase": "data integrity issues",
        "type": "impact",
        "cwes": [
          {
            "metadata": {
              "doc_id": "125",
              "name": "Out-of-bounds Read",
              "source": "sparse",
              "original_content": "The product reads data past the end, or before the beginning, of the intended buffer."
            },
            "similarity": 121.0085896056506
          },
          {
            "metadata": {
              "doc_id": "1284",
              "name": "Improper Validation of Specified Quantity in Input",
              "source": "sparse",
              "original_content": "The product receives input that is expected to specify a quantity (such as size or length), but it does not validate or incorrectly validates that the quantity has the required properties."
            },
            "similarity": 113.0956752855767
          },
          {
            "metadata": {
              "doc_id": "190",
              "name": "Integer Overflow or Wraparound",
              "source": "sparse",
              "original_content": "The product performs a calculation that can\n         produce an integer overflow or wraparound when the logic\n         assumes that the resulting value will always be larger than\n         the original value. This occurs when an integer value is\n         incremented to a value that is too large to store in the\n         associated representation. When this occurs, the value may\n         become a very small or negative number."
            },
            "similarity": 108.49753877469338
          },
          {
            "metadata": {
              "doc_id": "787",
              "name": "Out-of-bounds Write",
              "source": "sparse",
              "original_content": "The product writes data past the end, or before the beginning, of the intended buffer."
            },
            "similarity": 107.28015737277934
          },
          {
            "metadata": {
              "doc_id": "276",
              "name": "Incorrect Default Permissions",
              "source": "sparse",
              "original_content": "During installation, installed file permissions are set to allow anyone to modify those files.",
              "keyphrase_sources": [
                {
                  "id": "impact:data integrity issues",
                  "keyphrase": "data integrity issues",
                  "type": "impact"
                },
                {
                  "id": "product:grub2",
                  "keyphrase": "grub2",
                  "type": "product"
                }
              ]
            },
            "similarity": 106.17919184842388
          }
        ]
      },
      "vector:reading symbolic links name from UFS filesystem": {
        "keyphrase": "reading symbolic links name from UFS filesystem",
        "type": "vector",
        "cwes": [
          {
            "metadata": {
              "doc_id": "61",
              "name": "UNIX Symbolic Link (Symlink) Following",
              "source": "sparse",
              "original_content": "The product, when opening a file or directory, does not sufficiently account for when the file is a symbolic link that resolves to a target outside of the intended control sphere. This could allow an attacker to cause the product to operate on unauthorized files.",
              "keyphrase_sources": [
                {
                  "id": "vector:reading symbolic links name from UFS filesystem",
                  "keyphrase": "reading symbolic links name from UFS filesystem",
                  "type": "vector"
                }
              ]
            },
            "similarity": 143.4003800186367
          },
          {
            "metadata": {
              "doc_id": "59",
              "name": "Improper Link Resolution Before File Access ('Link Following')",
              "source": "sparse",
              "original_content": "The product attempts to access a file based on the filename, but it does not properly prevent that filename from identifying a link or shortcut that resolves to an unintended resource.",
              "keyphrase_sources": [
                {
                  "id": "vector:reading symbolic links name from UFS filesystem",
                  "keyphrase": "reading symbolic links name from UFS filesystem",
                  "type": "vector"
                }
              ]
            },
            "similarity": 141.7088316529249
          },
          {
            "metadata": {
              "doc_id": "125",
              "name": "Out-of-bounds Read",
              "source": "sparse",
              "original_content": "The product reads data past the end, or before the beginning, of the intended buffer."
            },
            "similarity": 125.06705874110179
          },
          {
            "metadata": {
              "doc_id": "22",
              "name": "Improper Limitation of a Pathname to a Restricted Directory ('Path Traversal')",
              "source": "sparse",
              "original_content": "The product uses external input to construct a pathname that is intended to identify a file or directory that is located underneath a restricted parent directory, but the product does not properly neutralize special elements within the pathname that can cause the pathname to resolve to a location that is outside of the restricted directory.",
              "keyphrase_sources": [
                {
                  "id": "vector:reading symbolic links name from UFS filesystem",
                  "keyphrase": "reading symbolic links name from UFS filesystem",
                  "type": "vector"
                }
              ]
            },
            "similarity": 119.15232297127596
          },
          {
            "metadata": {
              "doc_id": "1289",
              "name": "Improper Validation of Unsafe Equivalence in Input",
              "source": "sparse",
              "original_content": "The product receives an input value that is used as a resource identifier or other type of reference, but it does not validate or incorrectly validates that the input is equivalent to a potentially-unsafe value.",
              "keyphrase_sources": [
                {
                  "id": "vector:reading symbolic links name from UFS filesystem",
                  "keyphrase": "reading symbolic links name from UFS filesystem",
                  "type": "vector"
                }
              ]
            },
            "similarity": 116.58695973183305
          }
        ]
      },
      "attacker:attacker": {
        "keyphrase": "attacker",
        "type": "attacker",
        "cwes": [
          {
            "metadata": {
              "doc_id": "125",
              "name": "Out-of-bounds Read",
              "source": "sparse",
              "original_content": "The product reads data past the end, or before the beginning, of the intended buffer."
            },
            "similarity": 119.08608243545228
          },
          {
            "metadata": {
              "doc_id": "1284",
              "name": "Improper Validation of Specified Quantity in Input",
              "source": "sparse",
              "original_content": "The product receives input that is expected to specify a quantity (such as size or length), but it does not validate or incorrectly validates that the quantity has the required properties."
            },
            "similarity": 115.61894853340308
          },
          {
            "metadata": {
              "doc_id": "190",
              "name": "Integer Overflow or Wraparound",
              "source": "sparse",
              "original_content": "The product performs a calculation that can\n         produce an integer overflow or wraparound when the logic\n         assumes that the resulting value will always be larger than\n         the original value. This occurs when an integer value is\n         incremented to a value that is too large to store in the\n         associated representation. When this occurs, the value may\n         become a very small or negative number."
            },
            "similarity": 110.65700118204016
          },
          {
            "metadata": {
              "doc_id": "787",
              "name": "Out-of-bounds Write",
              "source": "sparse",
              "original_content": "The product writes data past the end, or before the beginning, of the intended buffer."
            },
            "similarity": 109.08363955280004
          },
          {
            "metadata": {
              "doc_id": "122",
              "name": "Heap-based Buffer Overflow",
              "source": "sparse",
              "original_content": "A heap overflow condition is a buffer overflow, where the buffer that can be overwritten is allocated in the heap portion of memory, generally meaning that the buffer was allocated using a routine such as malloc()."
            },
            "similarity": 108.87785534169024
          }
        ]
      },
      "product:grub2": {
        "keyphrase": "grub2",
        "type": "product",
        "cwes": [
          {
            "metadata": {
              "doc_id": "276",
              "name": "Incorrect Default Permissions",
              "source": "sparse",
              "original_content": "During installation, installed file permissions are set to allow anyone to modify those files."
            },
            "similarity": 117.37446128346333
          },
          {
            "metadata": {
              "doc_id": "125",
              "name": "Out-of-bounds Read",
              "source": "sparse",
              "original_content": "The product reads data past the end, or before the beginning, of the intended buffer."
            },
            "similarity": 113.56798203313465
          },
          {
            "metadata": {
              "doc_id": "1284",
              "name": "Improper Validation of Specified Quantity in Input",
              "source": "sparse",
              "original_content": "The product receives input that is expected to specify a quantity (such as size or length), but it does not validate or incorrectly validates that the quantity has the required properties."
            },
            "similarity": 109.33706189300815
          },
          {
            "metadata": {
              "doc_id": "190",
              "name": "Integer Overflow or Wraparound",
              "source": "sparse",
              "original_content": "The product performs a calculation that can\n         produce an integer overflow or wraparound when the logic\n         assumes that the resulting value will always be larger than\n         the original value. This occurs when an integer value is\n         incremented to a value that is too large to store in the\n         associated representation. When this occurs, the value may\n         become a very small or negative number."
            },
            "similarity": 104.52463551414563
          },
          {
            "metadata": {
              "doc_id": "787",
              "name": "Out-of-bounds Write",
              "source": "sparse",
              "original_content": "The product writes data past the end, or before the beginning, of the intended buffer."
            },
            "similarity": 102.55747267096083
          }
        ]
      }
    },
    "keyphrase_mapping": {
      "1284": [
        {
          "id": "rootcause:fails to validate the string length taken as an input",
          "keyphrase": "fails to validate the string length taken as an input",
          "type": "rootcause"
        },
        {
          "id": "rootcause:lack of validation",
          "keyphrase": "lack of validation",
          "type": "rootcause"
        },
        {
          "id": "weakness:heap out-of-bounds write",
          "keyphrase": "heap out-of-bounds write",
          "type": "weakness"
        },
        {
          "id": "impact:circumvent secure boot protections",
          "keyphrase": "circumvent secure boot protections",
          "type": "impact"
        },
        {
          "id": "impact:data integrity issues",
          "keyphrase": "data integrity issues",
          "type": "impact"
        },
        {
          "id": "attacker:attacker",
          "keyphrase": "attacker",
          "type": "attacker"
        },
        {
          "id": "product:grub2",
          "keyphrase": "grub2",
          "type": "product"
        }
      ],
      "125": [
        {
          "id": "rootcause:fails to validate the string length taken as an input",
          "keyphrase": "fails to validate the string length taken as an input",
          "type": "rootcause"
        },
        {
          "id": "rootcause:lack of validation",
          "keyphrase": "lack of validation",
          "type": "rootcause"
        },
        {
          "id": "weakness:heap out-of-bounds write",
          "keyphrase": "heap out-of-bounds write",
          "type": "weakness"
        },
        {
          "id": "impact:circumvent secure boot protections",
          "keyphrase": "circumvent secure boot protections",
          "type": "impact"
        },
        {
          "id": "impact:data integrity issues",
          "keyphrase": "data integrity issues",
          "type": "impact"
        },
        {
          "id": "vector:reading symbolic links name from UFS filesystem",
          "keyphrase": "reading symbolic links name from UFS filesystem",
          "type": "vector"
        },
        {
          "id": "attacker:attacker",
          "keyphrase": "attacker",
          "type": "attacker"
        },
        {
          "id": "product:grub2",
          "keyphrase": "grub2",
          "type": "product"
        }
      ],
      "789": [
        {
          "id": "rootcause:fails to validate the string length taken as an input",
          "keyphrase": "fails to validate the string length taken as an input",
          "type": "rootcause"
        }
      ],
      "190": [
        {
          "id": "rootcause:fails to validate the string length taken as an input",
          "keyphrase": "fails to validate the string length taken as an input",
          "type": "rootcause"
        },
        {
          "id": "weakness:heap out-of-bounds write",
          "keyphrase": "heap out-of-bounds write",
          "type": "weakness"
        },
        {
          "id": "impact:circumvent secure boot protections",
          "keyphrase": "circumvent secure boot protections",
          "type": "impact"
        },
        {
          "id": "impact:data integrity issues",
          "keyphrase": "data integrity issues",
          "type": "impact"
        },
        {
          "id": "attacker:attacker",
          "keyphrase": "attacker",
          "type": "attacker"
        },
        {
          "id": "product:grub2",
          "keyphrase": "grub2",
          "type": "product"
        }
      ],
      "20": [
        {
          "id": "rootcause:fails to validate the string length taken as an input",
          "keyphrase": "fails to validate the string length taken as an input",
          "type": "rootcause"
        },
        {
          "id": "rootcause:lack of validation",
          "keyphrase": "lack of validation",
          "type": "rootcause"
        }
      ],
      "787": [
        {
          "id": "rootcause:lack of validation",
          "keyphrase": "lack of validation",
          "type": "rootcause"
        },
        {
          "id": "impact:data integrity issues",
          "keyphrase": "data integrity issues",
          "type": "impact"
        },
        {
          "id": "attacker:attacker",
          "keyphrase": "attacker",
          "type": "attacker"
        },
        {
          "id": "product:grub2",
          "keyphrase": "grub2",
          "type": "product"
        }
      ],
      "119": [
        {
          "id": "rootcause:lack of validation",
          "keyphrase": "lack of validation",
          "type": "rootcause"
        }
      ],
      "122": [
        {
          "id": "weakness:heap out-of-bounds write",
          "keyphrase": "heap out-of-bounds write",
          "type": "weakness"
        },
        {
          "id": "attacker:attacker",
          "keyphrase": "attacker",
          "type": "attacker"
        }
      ],
      "191": [
        {
          "id": "weakness:heap out-of-bounds write",
          "keyphrase": "heap out-of-bounds write",
          "type": "weakness"
        }
      ],
      "1247": [
        {
          "id": "impact:circumvent secure boot protections",
          "keyphrase": "circumvent secure boot protections",
          "type": "impact"
        }
      ],
      "1274": [
        {
          "id": "impact:circumvent secure boot protections",
          "keyphrase": "circumvent secure boot protections",
          "type": "impact"
        }
      ],
      "276": [
        {
          "id": "impact:data integrity issues",
          "keyphrase": "data integrity issues",
          "type": "impact"
        },
        {
          "id": "product:grub2",
          "keyphrase": "grub2",
          "type": "product"
        }
      ],
      "61": [
        {
          "id": "vector:reading symbolic links name from UFS filesystem",
          "keyphrase": "reading symbolic links name from UFS filesystem",
          "type": "vector"
        }
      ],
      "59": [
        {
          "id": "vector:reading symbolic links name from UFS filesystem",
          "keyphrase": "reading symbolic links name from UFS filesystem",
          "type": "vector"
        }
      ],
      "22": [
        {
          "id": "vector:reading symbolic links name from UFS filesystem",
          "keyphrase": "reading symbolic links name from UFS filesystem",
          "type": "vector"
        }
      ],
      "1289": [
        {
          "id": "vector:reading symbolic links name from UFS filesystem",
          "keyphrase": "reading symbolic links name from UFS filesystem",
          "type": "vector"
        }
      ]
    },
    "relevant_cwes": [
      {
        "metadata": {
          "doc_id": "1284",
          "name": "Improper Validation of Specified Quantity in Input",
          "source": "sparse",
          "original_content": "The product receives input that is expected to specify a quantity (such as size or length), but it does not validate or incorrectly validates that the quantity has the required properties.",
          "keyphrase_sources": [
            {
              "id": "rootcause:fails to validate the string length taken as an input",
              "keyphrase": "fails to validate the string length taken as an input",
              "type": "rootcause"
            },
            {
              "id": "rootcause:lack of validation",
              "keyphrase": "lack of validation",
              "type": "rootcause"
            },
            {
              "id": "weakness:heap out-of-bounds write",
              "keyphrase": "heap out-of-bounds write",
              "type": "weakness"
            },
            {
              "id": "impact:circumvent secure boot protections",
              "keyphrase": "circumvent secure boot protections",
              "type": "impact"
            },
            {
              "id": "impact:data integrity issues",
              "keyphrase": "data integrity issues",
              "type": "impact"
            },
            {
              "id": "attacker:attacker",
              "keyphrase": "attacker",
              "type": "attacker"
            },
            {
              "id": "product:grub2",
              "keyphrase": "grub2",
              "type": "product"
            }
          ]
        },
        "similarity": 483.1539735343653
      },
      {
        "metadata": {
          "doc_id": "125",
          "name": "Out-of-bounds Read",
          "source": "sparse",
          "original_content": "The product reads data past the end, or before the beginning, of the intended buffer.",
          "keyphrase_sources": [
            {
              "id": "rootcause:fails to validate the string length taken as an input",
              "keyphrase": "fails to validate the string length taken as an input",
              "type": "rootcause"
            },
            {
              "id": "rootcause:lack of validation",
              "keyphrase": "lack of validation",
              "type": "rootcause"
            },
            {
              "id": "weakness:heap out-of-bounds write",
              "keyphrase": "heap out-of-bounds write",
              "type": "weakness"
            },
            {
              "id": "impact:circumvent secure boot protections",
              "keyphrase": "circumvent secure boot protections",
              "type": "impact"
            },
            {
              "id": "impact:data integrity issues",
              "keyphrase": "data integrity issues",
              "type": "impact"
            },
            {
              "id": "vector:reading symbolic links name from UFS filesystem",
              "keyphrase": "reading symbolic links name from UFS filesystem",
              "type": "vector"
            },
            {
              "id": "attacker:attacker",
              "keyphrase": "attacker",
              "type": "attacker"
            },
            {
              "id": "product:grub2",
              "keyphrase": "grub2",
              "type": "product"
            }
          ]
        },
        "similarity": 481.85351497393697
      },
      {
        "metadata": {
          "doc_id": "789",
          "name": "Memory Allocation with Excessive Size Value",
          "source": "sparse",
          "original_content": "The product allocates memory based on an untrusted, large size value, but it does not ensure that the size is within expected limits, allowing arbitrary amounts of memory to be allocated.",
          "keyphrase_sources": [
            {
              "id": "rootcause:fails to validate the string length taken as an input",
              "keyphrase": "fails to validate the string length taken as an input",
              "type": "rootcause"
            }
          ]
        },
        "similarity": 450.0220203779836
      },
      {
        "metadata": {
          "doc_id": "190",
          "name": "Integer Overflow or Wraparound",
          "source": "sparse",
          "original_content": "The product performs a calculation that can\n         produce an integer overflow or wraparound when the logic\n         assumes that the resulting value will always be larger than\n         the original value. This occurs when an integer value is\n         incremented to a value that is too large to store in the\n         associated representation. When this occurs, the value may\n         become a very small or negative number.",
          "keyphrase_sources": [
            {
              "id": "rootcause:fails to validate the string length taken as an input",
              "keyphrase": "fails to validate the string length taken as an input",
              "type": "rootcause"
            },
            {
              "id": "weakness:heap out-of-bounds write",
              "keyphrase": "heap out-of-bounds write",
              "type": "weakness"
            },
            {
              "id": "impact:circumvent secure boot protections",
              "keyphrase": "circumvent secure boot protections",
              "type": "impact"
            },
            {
              "id": "impact:data integrity issues",
              "keyphrase": "data integrity issues",
              "type": "impact"
            },
            {
              "id": "attacker:attacker",
              "keyphrase": "attacker",
              "type": "attacker"
            },
            {
              "id": "product:grub2",
              "keyphrase": "grub2",
              "type": "product"
            }
          ]
        },
        "similarity": 436.0014924343243
      },
      {
        "metadata": {
          "doc_id": "20",
          "name": "Improper Input Validation",
          "source": "sparse",
          "original_content": "The product receives input or data, but it does\n        not validate or incorrectly validates that the input has the\n        properties that are required to process the data safely and\n        correctly.",
          "keyphrase_sources": [
            {
              "id": "rootcause:fails to validate the string length taken as an input",
              "keyphrase": "fails to validate the string length taken as an input",
              "type": "rootcause"
            },
            {
              "id": "rootcause:lack of validation",
              "keyphrase": "lack of validation",
              "type": "rootcause"
            }
          ]
        },
        "similarity": 428.8750279164677
      },
      {
        "metadata": {
          "doc_id": "122",
          "name": "Heap-based Buffer Overflow",
          "source": "sparse",
          "original_content": "A heap overflow condition is a buffer overflow, where the buffer that can be overwritten is allocated in the heap portion of memory, generally meaning that the buffer was allocated using a routine such as malloc().",
          "keyphrase_sources": [
            {
              "id": "weakness:heap out-of-bounds write",
              "keyphrase": "heap out-of-bounds write",
              "type": "weakness"
            },
            {
              "id": "attacker:attacker",
              "keyphrase": "attacker",
              "type": "attacker"
            }
          ]
        },
        "similarity": 396.3535483067532
      },
      {
        "metadata": {
          "doc_id": "191",
          "name": "Integer Underflow (Wrap or Wraparound)",
          "source": "sparse",
          "original_content": "The product subtracts one value from another, such that the result is less than the minimum allowable integer value, which produces a value that is not equal to the correct result.",
          "keyphrase_sources": [
            {
              "id": "weakness:heap out-of-bounds write",
              "keyphrase": "heap out-of-bounds write",
              "type": "weakness"
            }
          ]
        },
        "similarity": 385.0116086058019
      },
      {
        "metadata": {
          "doc_id": "787",
          "name": "Out-of-bounds Write",
          "source": "sparse",
          "original_content": "The product writes data past the end, or before the beginning, of the intended buffer.",
          "keyphrase_sources": [
            {
              "id": "rootcause:lack of validation",
              "keyphrase": "lack of validation",
              "type": "rootcause"
            },
            {
              "id": "impact:data integrity issues",
              "keyphrase": "data integrity issues",
              "type": "impact"
            },
            {
              "id": "attacker:attacker",
              "keyphrase": "attacker",
              "type": "attacker"
            },
            {
              "id": "product:grub2",
              "keyphrase": "grub2",
              "type": "product"
            }
          ]
        },
        "similarity": 345.97417212348716
      },
      {
        "metadata": {
          "doc_id": "119",
          "name": "Improper Restriction of Operations within the Bounds of a Memory Buffer",
          "source": "sparse",
          "original_content": "The product performs operations on a memory buffer, but it reads from or writes to a memory location outside the buffer's intended boundary. This may result in read or write operations on unexpected memory locations that could be linked to other variables, data structures, or internal program data.",
          "keyphrase_sources": [
            {
              "id": "rootcause:lack of validation",
              "keyphrase": "lack of validation",
              "type": "rootcause"
            }
          ]
        },
        "similarity": 342.7561105016059
      },
      {
        "metadata": {
          "doc_id": "61",
          "name": "UNIX Symbolic Link (Symlink) Following",
          "source": "sparse",
          "original_content": "The product, when opening a file or directory, does not sufficiently account for when the file is a symbolic link that resolves to a target outside of the intended control sphere. This could allow an attacker to cause the product to operate on unauthorized files.",
          "keyphrase_sources": [
            {
              "id": "vector:reading symbolic links name from UFS filesystem",
              "keyphrase": "reading symbolic links name from UFS filesystem",
              "type": "vector"
            }
          ]
        },
        "similarity": 143.4003800186367
      },
      {
        "metadata": {
          "doc_id": "59",
          "name": "Improper Link Resolution Before File Access ('Link Following')",
          "source": "sparse",
          "original_content": "The product attempts to access a file based on the filename, but it does not properly prevent that filename from identifying a link or shortcut that resolves to an unintended resource.",
          "keyphrase_sources": [
            {
              "id": "vector:reading symbolic links name from UFS filesystem",
              "keyphrase": "reading symbolic links name from UFS filesystem",
              "type": "vector"
            }
          ]
        },
        "similarity": 141.7088316529249
      },
      {
        "metadata": {
          "doc_id": "22",
          "name": "Improper Limitation of a Pathname to a Restricted Directory ('Path Traversal')",
          "source": "sparse",
          "original_content": "The product uses external input to construct a pathname that is intended to identify a file or directory that is located underneath a restricted parent directory, but the product does not properly neutralize special elements within the pathname that can cause the pathname to resolve to a location that is outside of the restricted directory.",
          "keyphrase_sources": [
            {
              "id": "vector:reading symbolic links name from UFS filesystem",
              "keyphrase": "reading symbolic links name from UFS filesystem",
              "type": "vector"
            }
          ]
        },
        "similarity": 119.15232297127596
      },
      {
        "metadata": {
          "doc_id": "1289",
          "name": "Improper Validation of Unsafe Equivalence in Input",
          "source": "sparse",
          "original_content": "The product receives an input value that is used as a resource identifier or other type of reference, but it does not validate or incorrectly validates that the input is equivalent to a potentially-unsafe value.",
          "keyphrase_sources": [
            {
              "id": "vector:reading symbolic links name from UFS filesystem",
              "keyphrase": "reading symbolic links name from UFS filesystem",
              "type": "vector"
            }
          ]
        },
        "similarity": 116.58695973183305
      },
      {
        "metadata": {
          "doc_id": "1247",
          "name": "Improper Protection Against Voltage and Clock Glitches",
          "source": "sparse",
          "original_content": "The device does not contain or contains incorrectly implemented circuitry or sensors to detect and mitigate voltage and clock glitches and protect sensitive information or software contained on the device.",
          "keyphrase_sources": [
            {
              "id": "impact:circumvent secure boot protections",
              "keyphrase": "circumvent secure boot protections",
              "type": "impact"
            }
          ]
        },
        "similarity": 109.18223464396279
      },
      {
        "metadata": {
          "doc_id": "1274",
          "name": "Improper Access Control for Volatile Memory Containing Boot Code",
          "source": "sparse",
          "original_content": "The product conducts a secure-boot process that transfers bootloader code from Non-Volatile Memory (NVM) into Volatile Memory (VM), but it does not have sufficient access control or other protections for the Volatile Memory.",
          "keyphrase_sources": [
            {
              "id": "impact:circumvent secure boot protections",
              "keyphrase": "circumvent secure boot protections",
              "type": "impact"
            }
          ]
        },
        "similarity": 107.84795018624206
      },
      {
        "metadata": {
          "doc_id": "276",
          "name": "Incorrect Default Permissions",
          "source": "sparse",
          "original_content": "During installation, installed file permissions are set to allow anyone to modify those files.",
          "keyphrase_sources": [
            {
              "id": "impact:data integrity issues",
              "keyphrase": "data integrity issues",
              "type": "impact"
            },
            {
              "id": "product:grub2",
              "keyphrase": "grub2",
              "type": "product"
            }
          ]
        },
        "similarity": 106.17919184842388
      }
    ],
    "enhanced_query": "# Vulnerability Description\n\n    A flaw was found in grub2. When reading a symbolic links name from a UFS filesystem, grub2 **fails to validate the string length taken as an input**. The **lack of validation** may lead to a **heap out-of-bounds write**, causing data integrity issues and eventually allowing an attacker to circumvent secure boot protections.\n\n    # Keyphrase-Specific CWE Analysis\n    This vulnerability contains multiple keyphrases that may map to different CWEs. \n    Please analyze each keyphrase separately and determine the most appropriate CWE(s) for each.\n\n    ## ROOTCAUSE: 'fails to validate the string length taken as an input'\n\nRelevant CWEs for this ROOTCAUSE:\n\n### 1. CWE-1284: Improper Validation of Specified Quantity in Input (Score: 483.15)\n\nThe product receives input that is expected to specify a quantity (such as size or length), but it does not validate or incorrectly validates that the quantity has the required properties....\n\n### 2. CWE-125: Out-of-bounds Read (Score: 481.85)\n\nThe product reads data past the end, or before the beginning, of the intended buffer....\n\n### 3. CWE-789: Memory Allocation with Excessive Size Value (Score: 450.02)\n\nThe product allocates memory based on an untrusted, large size value, but it does not ensure that the size is within expected limits, allowing arbitrary amounts of memory to be allocated....\n\n### 4. CWE-190: Integer Overflow or Wraparound (Score: 436.00)\n\nThe product performs a calculation that can\n         produce an integer overflow or wraparound when the logic\n         assumes that the resulting value will always be larger than\n         the original value. This occurs when an integer value is\n         incremented to a value that is too large to st...\n\n### 5. CWE-20: Improper Input Validation (Score: 428.88)\n\nThe product receives input or data, but it does\n        not validate or incorrectly validates that the input has the\n        properties that are required to process the data safely and\n        correctly....\n\n## ROOTCAUSE: 'lack of validation'\n\nRelevant CWEs for this ROOTCAUSE:\n\n### 1. CWE-1284: Improper Validation of Specified Quantity in Input (Score: 483.15)\n\nThe product receives input that is expected to specify a quantity (such as size or length), but it does not validate or incorrectly validates that the quantity has the required properties....\n\n### 2. CWE-125: Out-of-bounds Read (Score: 481.85)\n\nThe product reads data past the end, or before the beginning, of the intended buffer....\n\n### 3. CWE-20: Improper Input Validation (Score: 428.88)\n\nThe product receives input or data, but it does\n        not validate or incorrectly validates that the input has the\n        properties that are required to process the data safely and\n        correctly....\n\n### 4. CWE-787: Out-of-bounds Write (Score: 345.97)\n\nThe product writes data past the end, or before the beginning, of the intended buffer....\n\n### 5. CWE-119: Improper Restriction of Operations within the Bounds of a Memory Buffer (Score: 342.76)\n\nThe product performs operations on a memory buffer, but it reads from or writes to a memory location outside the buffer's intended boundary. This may result in read or write operations on unexpected memory locations that could be linked to other variables, data structures, or internal program data....\n\n## WEAKNESS: 'heap out-of-bounds write'\n\nRelevant CWEs for this WEAKNESS:\n\n### 1. CWE-1284: Improper Validation of Specified Quantity in Input (Score: 483.15)\n\nThe product receives input that is expected to specify a quantity (such as size or length), but it does not validate or incorrectly validates that the quantity has the required properties....\n\n### 2. CWE-125: Out-of-bounds Read (Score: 481.85)\n\nThe product reads data past the end, or before the beginning, of the intended buffer....\n\n### 3. CWE-190: Integer Overflow or Wraparound (Score: 436.00)\n\nThe product performs a calculation that can\n         produce an integer overflow or wraparound when the logic\n         assumes that the resulting value will always be larger than\n         the original value. This occurs when an integer value is\n         incremented to a value that is too large to st...\n\n### 4. CWE-122: Heap-based Buffer Overflow (Score: 396.35)\n\nA heap overflow condition is a buffer overflow, where the buffer that can be overwritten is allocated in the heap portion of memory, generally meaning that the buffer was allocated using a routine such as malloc()....\n\n### 5. CWE-191: Integer Underflow (Wrap or Wraparound) (Score: 385.01)\n\nThe product subtracts one value from another, such that the result is less than the minimum allowable integer value, which produces a value that is not equal to the correct result....\n\n## IMPACT: 'circumvent secure boot protections'\n\nRelevant CWEs for this IMPACT:\n\n### 1. CWE-1284: Improper Validation of Specified Quantity in Input (Score: 483.15)\n\nThe product receives input that is expected to specify a quantity (such as size or length), but it does not validate or incorrectly validates that the quantity has the required properties....\n\n### 2. CWE-125: Out-of-bounds Read (Score: 481.85)\n\nThe product reads data past the end, or before the beginning, of the intended buffer....\n\n### 3. CWE-190: Integer Overflow or Wraparound (Score: 436.00)\n\nThe product performs a calculation that can\n         produce an integer overflow or wraparound when the logic\n         assumes that the resulting value will always be larger than\n         the original value. This occurs when an integer value is\n         incremented to a value that is too large to st...\n\n### 4. CWE-1247: Improper Protection Against Voltage and Clock Glitches (Score: 109.18)\n\nThe device does not contain or contains incorrectly implemented circuitry or sensors to detect and mitigate voltage and clock glitches and protect sensitive information or software contained on the device....\n\n### 5. CWE-1274: Improper Access Control for Volatile Memory Containing Boot Code (Score: 107.85)\n\nThe product conducts a secure-boot process that transfers bootloader code from Non-Volatile Memory (NVM) into Volatile Memory (VM), but it does not have sufficient access control or other protections for the Volatile Memory....\n\n## IMPACT: 'data integrity issues'\n\nRelevant CWEs for this IMPACT:\n\n### 1. CWE-1284: Improper Validation of Specified Quantity in Input (Score: 483.15)\n\nThe product receives input that is expected to specify a quantity (such as size or length), but it does not validate or incorrectly validates that the quantity has the required properties....\n\n### 2. CWE-125: Out-of-bounds Read (Score: 481.85)\n\nThe product reads data past the end, or before the beginning, of the intended buffer....\n\n### 3. CWE-190: Integer Overflow or Wraparound (Score: 436.00)\n\nThe product performs a calculation that can\n         produce an integer overflow or wraparound when the logic\n         assumes that the resulting value will always be larger than\n         the original value. This occurs when an integer value is\n         incremented to a value that is too large to st...\n\n### 4. CWE-787: Out-of-bounds Write (Score: 345.97)\n\nThe product writes data past the end, or before the beginning, of the intended buffer....\n\n### 5. CWE-276: Incorrect Default Permissions (Score: 106.18)\n\nDuring installation, installed file permissions are set to allow anyone to modify those files....\n\n## ATTACKER: 'attacker'\n\nRelevant CWEs for this ATTACKER:\n\n### 1. CWE-1284: Improper Validation of Specified Quantity in Input (Score: 483.15)\n\nThe product receives input that is expected to specify a quantity (such as size or length), but it does not validate or incorrectly validates that the quantity has the required properties....\n\n### 2. CWE-125: Out-of-bounds Read (Score: 481.85)\n\nThe product reads data past the end, or before the beginning, of the intended buffer....\n\n### 3. CWE-190: Integer Overflow or Wraparound (Score: 436.00)\n\nThe product performs a calculation that can\n         produce an integer overflow or wraparound when the logic\n         assumes that the resulting value will always be larger than\n         the original value. This occurs when an integer value is\n         incremented to a value that is too large to st...\n\n### 4. CWE-122: Heap-based Buffer Overflow (Score: 396.35)\n\nA heap overflow condition is a buffer overflow, where the buffer that can be overwritten is allocated in the heap portion of memory, generally meaning that the buffer was allocated using a routine such as malloc()....\n\n### 5. CWE-787: Out-of-bounds Write (Score: 345.97)\n\nThe product writes data past the end, or before the beginning, of the intended buffer....\n\n## PRODUCT: 'grub2'\n\nRelevant CWEs for this PRODUCT:\n\n### 1. CWE-1284: Improper Validation of Specified Quantity in Input (Score: 483.15)\n\nThe product receives input that is expected to specify a quantity (such as size or length), but it does not validate or incorrectly validates that the quantity has the required properties....\n\n### 2. CWE-125: Out-of-bounds Read (Score: 481.85)\n\nThe product reads data past the end, or before the beginning, of the intended buffer....\n\n### 3. CWE-190: Integer Overflow or Wraparound (Score: 436.00)\n\nThe product performs a calculation that can\n         produce an integer overflow or wraparound when the logic\n         assumes that the resulting value will always be larger than\n         the original value. This occurs when an integer value is\n         incremented to a value that is too large to st...\n\n### 4. CWE-787: Out-of-bounds Write (Score: 345.97)\n\nThe product writes data past the end, or before the beginning, of the intended buffer....\n\n### 5. CWE-276: Incorrect Default Permissions (Score: 106.18)\n\nDuring installation, installed file permissions are set to allow anyone to modify those files....\n\n## VECTOR: 'reading symbolic links name from UFS filesystem'\n\nRelevant CWEs for this VECTOR:\n\n### 1. CWE-125: Out-of-bounds Read (Score: 481.85)\n\nThe product reads data past the end, or before the beginning, of the intended buffer....\n\n### 2. CWE-61: UNIX Symbolic Link (Symlink) Following (Score: 143.40)\n\nThe product, when opening a file or directory, does not sufficiently account for when the file is a symbolic link that resolves to a target outside of the intended control sphere. This could allow an attacker to cause the product to operate on unauthorized files....\n\n### 3. CWE-59: Improper Link Resolution Before File Access ('Link Following') (Score: 141.71)\n\nThe product attempts to access a file based on the filename, but it does not properly prevent that filename from identifying a link or shortcut that resolves to an unintended resource....\n\n### 4. CWE-22: Improper Limitation of a Pathname to a Restricted Directory ('Path Traversal') (Score: 119.15)\n\nThe product uses external input to construct a pathname that is intended to identify a file or directory that is located underneath a restricted parent directory, but the product does not properly neutralize special elements within the pathname that can cause the pathname to resolve to a location th...\n\n### 5. CWE-1289: Improper Validation of Unsafe Equivalence in Input (Score: 116.59)\n\nThe product receives an input value that is used as a resource identifier or other type of reference, but it does not validate or incorrectly validates that the input is equivalent to a potentially-unsafe value....\n\n\n    # Analysis Instructions\n    1. For each keyphrase, identify the most appropriate CWE(s) that represent the weakness.\n    2. Consider how the different keyphrases might relate to each other in the vulnerability chain.\n    3. Provide a final determination of primary CWE(s) and any secondary CWEs.\n    4. Format your response using the standard analysis template.\n\n    Please analyze how these different weaknesses interact and provide a comprehensive CWE classification.\n    "
  },
  "retrieval_time": 1.288327932357788
}