{
  "vulnerability_info": "VulnerabilityInfo(cve_id='CVE-2025-0815', description='CWE-20 Improper **Input Validation vulnerability** exists that could cause Denial-of-Service of the product when malicious ICMPV6 packets are sent to the device.', key_phrases={'rootcause': ['Input Validation vulnerability', 'Improper Input Validation'], 'weakness': '', 'impact': 'Denial-of-Service', 'vector': 'malicious ICMPV6 packets', 'attacker': '', 'product': '', 'version': '', 'component': ''}, reference_content='```\\nVulnerability Details\\n\\nCVE ID: CVE-2025-0815\\n\\nCVSS v3.1 Base Score 6.5 | Medium | CVSS:3.1/AV:A/AC:L/PR:N/UI:N/S:U/C:N/I:N/A:H\\n\\nCVSS v4.0 Base Score 7.1 | High |  CVSS:4.0/AV:A/AC:L/AT:N/PR:N/UI:N/VC:N/VI:N/VA:H/SC:N/SI:N/SA:N\\n\\nCWE-20: Improper Input Validation vulnerability exists that could cause Denial-of-Service of the\\nproduct when malicious ICMPV6 packets are sent to the device.\\n\\nImpact of exploitation: Denial-of-Service of the product\\n\\nAttack vector: Malicious ICMPv6 packets sent to the device\\n\\nAffected products: Enerlin\u2019X IFE interface (LV434001), Enerlin\u2019X eIFE (LV851001)\\n\\nRequired attacker capabilities/position: The attacker must be on the local network (AV:A)\\n\\nMitigations:\\n\\n*   Use devices only in a protected environment to minimize network exposure and ensure that they are not accessible from public internet or untrusted networks.\\n*   Setup network segmentation and implement a firewall to block all unauthorized access to ports supported by the product and listed in the user guide:  https://www.se.com/ww/en/download/document/DOCA0084EN/\\n*   Configure the Access Control List following the recommendations of the Cybersecurity Guide:  https://www.se.com/ww/en/download/document/DOCA0122EN/ and the user guide: https://www.se.com/ww/en/download/document/DOCA0084EN/\\n```', similar_info={'cwe_distribution': {}, 'cwe_consensus': '', 'similarity_stats': {'thresholds': [], 'total_samples_by_threshold': {}, 'top_cwes_by_threshold': {}}}, similarity_summary=SimilarityInsight(consensus_cwe='', top_cwes=[], confidence_levels={}, total_samples=0), analysis='', analysis_with_relationships='', criticism='', resolution='', relevant_cwes=[{'metadata': {'doc_id': '20', 'name': 'Improper Input Validation', 'source': 'sparse', 'original_content': 'The product receives input or data, but it does\\n        not validate or incorrectly validates that the input has the\\n        properties that are required to process the data safely and\\n        correctly.', 'keyphrase_sources': [{'id': 'rootcause:Input Validation vulnerability', 'keyphrase': 'Input Validation vulnerability', 'type': 'rootcause'}, {'id': 'rootcause:Improper Input Validation', 'keyphrase': 'Improper Input Validation', 'type': 'rootcause'}, {'id': 'impact:Denial-of-Service', 'keyphrase': 'Denial-of-Service', 'type': 'impact'}, {'id': 'vector:malicious ICMPV6 packets', 'keyphrase': 'malicious ICMPV6 packets', 'type': 'vector'}]}, 'similarity': np.float64(193.79687048574306)}, {'metadata': {'doc_id': '1285', 'name': 'Improper Validation of Specified Index, Position, or Offset in Input', 'source': 'sparse', 'original_content': 'The product receives input that is expected to specify an index, position, or offset into an indexable resource such as a buffer or file, but it does not validate or incorrectly validates that the specified index/position/offset has the required properties.', 'keyphrase_sources': [{'id': 'rootcause:Input Validation vulnerability', 'keyphrase': 'Input Validation vulnerability', 'type': 'rootcause'}, {'id': 'rootcause:Improper Input Validation', 'keyphrase': 'Improper Input Validation', 'type': 'rootcause'}, {'id': 'impact:Denial-of-Service', 'keyphrase': 'Denial-of-Service', 'type': 'impact'}, {'id': 'vector:malicious ICMPV6 packets', 'keyphrase': 'malicious ICMPV6 packets', 'type': 'vector'}]}, 'similarity': np.float64(188.8876780739572)}, {'metadata': {'doc_id': '1284', 'name': 'Improper Validation of Specified Quantity in Input', 'source': 'sparse', 'original_content': 'The product receives input that is expected to specify a quantity (such as size or length), but it does not validate or incorrectly validates that the quantity has the required properties.', 'keyphrase_sources': [{'id': 'rootcause:Input Validation vulnerability', 'keyphrase': 'Input Validation vulnerability', 'type': 'rootcause'}, {'id': 'rootcause:Improper Input Validation', 'keyphrase': 'Improper Input Validation', 'type': 'rootcause'}, {'id': 'impact:Denial-of-Service', 'keyphrase': 'Denial-of-Service', 'type': 'impact'}]}, 'similarity': np.float64(186.81335712219456)}, {'metadata': {'doc_id': '1286', 'name': 'Improper Validation of Syntactic Correctness of Input', 'source': 'sparse', 'original_content': 'The product receives input that is expected to be well-formed - i.e., to comply with a certain syntax - but it does not validate or incorrectly validates that the input complies with the syntax.', 'keyphrase_sources': [{'id': 'rootcause:Input Validation vulnerability', 'keyphrase': 'Input Validation vulnerability', 'type': 'rootcause'}, {'id': 'rootcause:Improper Input Validation', 'keyphrase': 'Improper Input Validation', 'type': 'rootcause'}]}, 'similarity': np.float64(182.94682019206329)}, {'metadata': {'doc_id': '789', 'name': 'Memory Allocation with Excessive Size Value', 'source': 'sparse', 'original_content': 'The product allocates memory based on an untrusted, large size value, but it does not ensure that the size is within expected limits, allowing arbitrary amounts of memory to be allocated.', 'keyphrase_sources': [{'id': 'rootcause:Input Validation vulnerability', 'keyphrase': 'Input Validation vulnerability', 'type': 'rootcause'}, {'id': 'rootcause:Improper Input Validation', 'keyphrase': 'Improper Input Validation', 'type': 'rootcause'}, {'id': 'impact:Denial-of-Service', 'keyphrase': 'Denial-of-Service', 'type': 'impact'}, {'id': 'vector:malicious ICMPV6 packets', 'keyphrase': 'malicious ICMPV6 packets', 'type': 'vector'}]}, 'similarity': np.float64(173.9059180570099)}, {'metadata': {'doc_id': '617', 'name': 'Reachable Assertion', 'source': 'sparse', 'original_content': 'The product contains an assert() or similar statement that can be triggered by an attacker, which leads to an application exit or other behavior that is more severe than necessary.', 'keyphrase_sources': [{'id': 'impact:Denial-of-Service', 'keyphrase': 'Denial-of-Service', 'type': 'impact'}, {'id': 'vector:malicious ICMPV6 packets', 'keyphrase': 'malicious ICMPV6 packets', 'type': 'vector'}]}, 'similarity': np.float64(66.42227536888396)}, {'metadata': {'doc_id': '119', 'name': 'Improper Restriction of Operations within the Bounds of a Memory Buffer', 'source': 'sparse', 'original_content': \"The product performs operations on a memory buffer, but it reads from or writes to a memory location outside the buffer's intended boundary. This may result in read or write operations on unexpected memory locations that could be linked to other variables, data structures, or internal program data.\", 'keyphrase_sources': [{'id': 'vector:malicious ICMPV6 packets', 'keyphrase': 'malicious ICMPV6 packets', 'type': 'vector'}]}, 'similarity': np.float64(58.668669488435384)}], identified_cwes={'analyzer': [], 'critic_additional': []})",
  "retrieval_results": {
    "has_multiple_keyphrases": true,
    "keyphrase_cwe_sets": {
      "rootcause:Input Validation vulnerability": {
        "keyphrase": "Input Validation vulnerability",
        "type": "rootcause",
        "cwes": [
          {
            "metadata": {
              "doc_id": "20",
              "name": "Improper Input Validation",
              "source": "sparse",
              "original_content": "The product receives input or data, but it does\n        not validate or incorrectly validates that the input has the\n        properties that are required to process the data safely and\n        correctly.",
              "keyphrase_sources": [
                {
                  "id": "rootcause:Input Validation vulnerability",
                  "keyphrase": "Input Validation vulnerability",
                  "type": "rootcause"
                },
                {
                  "id": "rootcause:Improper Input Validation",
                  "keyphrase": "Improper Input Validation",
                  "type": "rootcause"
                },
                {
                  "id": "impact:Denial-of-Service",
                  "keyphrase": "Denial-of-Service",
                  "type": "impact"
                },
                {
                  "id": "vector:malicious ICMPV6 packets",
                  "keyphrase": "malicious ICMPV6 packets",
                  "type": "vector"
                }
              ]
            },
            "similarity": 193.79687048574306
          },
          {
            "metadata": {
              "doc_id": "1285",
              "name": "Improper Validation of Specified Index, Position, or Offset in Input",
              "source": "sparse",
              "original_content": "The product receives input that is expected to specify an index, position, or offset into an indexable resource such as a buffer or file, but it does not validate or incorrectly validates that the specified index/position/offset has the required properties.",
              "keyphrase_sources": [
                {
                  "id": "rootcause:Input Validation vulnerability",
                  "keyphrase": "Input Validation vulnerability",
                  "type": "rootcause"
                },
                {
                  "id": "rootcause:Improper Input Validation",
                  "keyphrase": "Improper Input Validation",
                  "type": "rootcause"
                },
                {
                  "id": "impact:Denial-of-Service",
                  "keyphrase": "Denial-of-Service",
                  "type": "impact"
                },
                {
                  "id": "vector:malicious ICMPV6 packets",
                  "keyphrase": "malicious ICMPV6 packets",
                  "type": "vector"
                }
              ]
            },
            "similarity": 188.8876780739572
          },
          {
            "metadata": {
              "doc_id": "1284",
              "name": "Improper Validation of Specified Quantity in Input",
              "source": "sparse",
              "original_content": "The product receives input that is expected to specify a quantity (such as size or length), but it does not validate or incorrectly validates that the quantity has the required properties.",
              "keyphrase_sources": [
                {
                  "id": "rootcause:Input Validation vulnerability",
                  "keyphrase": "Input Validation vulnerability",
                  "type": "rootcause"
                },
                {
                  "id": "rootcause:Improper Input Validation",
                  "keyphrase": "Improper Input Validation",
                  "type": "rootcause"
                },
                {
                  "id": "impact:Denial-of-Service",
                  "keyphrase": "Denial-of-Service",
                  "type": "impact"
                }
              ]
            },
            "similarity": 186.81335712219456
          },
          {
            "metadata": {
              "doc_id": "1286",
              "name": "Improper Validation of Syntactic Correctness of Input",
              "source": "sparse",
              "original_content": "The product receives input that is expected to be well-formed - i.e., to comply with a certain syntax - but it does not validate or incorrectly validates that the input complies with the syntax.",
              "keyphrase_sources": [
                {
                  "id": "rootcause:Input Validation vulnerability",
                  "keyphrase": "Input Validation vulnerability",
                  "type": "rootcause"
                },
                {
                  "id": "rootcause:Improper Input Validation",
                  "keyphrase": "Improper Input Validation",
                  "type": "rootcause"
                }
              ]
            },
            "similarity": 182.94682019206329
          },
          {
            "metadata": {
              "doc_id": "789",
              "name": "Memory Allocation with Excessive Size Value",
              "source": "sparse",
              "original_content": "The product allocates memory based on an untrusted, large size value, but it does not ensure that the size is within expected limits, allowing arbitrary amounts of memory to be allocated.",
              "keyphrase_sources": [
                {
                  "id": "rootcause:Input Validation vulnerability",
                  "keyphrase": "Input Validation vulnerability",
                  "type": "rootcause"
                },
                {
                  "id": "rootcause:Improper Input Validation",
                  "keyphrase": "Improper Input Validation",
                  "type": "rootcause"
                },
                {
                  "id": "impact:Denial-of-Service",
                  "keyphrase": "Denial-of-Service",
                  "type": "impact"
                },
                {
                  "id": "vector:malicious ICMPV6 packets",
                  "keyphrase": "malicious ICMPV6 packets",
                  "type": "vector"
                }
              ]
            },
            "similarity": 173.9059180570099
          }
        ]
      },
      "rootcause:Improper Input Validation": {
        "keyphrase": "Improper Input Validation",
        "type": "rootcause",
        "cwes": [
          {
            "metadata": {
              "doc_id": "20",
              "name": "Improper Input Validation",
              "source": "sparse",
              "original_content": "The product receives input or data, but it does\n        not validate or incorrectly validates that the input has the\n        properties that are required to process the data safely and\n        correctly."
            },
            "similarity": 198.54984900317748
          },
          {
            "metadata": {
              "doc_id": "1285",
              "name": "Improper Validation of Specified Index, Position, or Offset in Input",
              "source": "sparse",
              "original_content": "The product receives input that is expected to specify an index, position, or offset into an indexable resource such as a buffer or file, but it does not validate or incorrectly validates that the specified index/position/offset has the required properties."
            },
            "similarity": 193.1968078333615
          },
          {
            "metadata": {
              "doc_id": "1284",
              "name": "Improper Validation of Specified Quantity in Input",
              "source": "sparse",
              "original_content": "The product receives input that is expected to specify a quantity (such as size or length), but it does not validate or incorrectly validates that the quantity has the required properties."
            },
            "similarity": 189.86826698646433
          },
          {
            "metadata": {
              "doc_id": "1286",
              "name": "Improper Validation of Syntactic Correctness of Input",
              "source": "sparse",
              "original_content": "The product receives input that is expected to be well-formed - i.e., to comply with a certain syntax - but it does not validate or incorrectly validates that the input complies with the syntax."
            },
            "similarity": 187.05362986044065
          },
          {
            "metadata": {
              "doc_id": "789",
              "name": "Memory Allocation with Excessive Size Value",
              "source": "sparse",
              "original_content": "The product allocates memory based on an untrusted, large size value, but it does not ensure that the size is within expected limits, allowing arbitrary amounts of memory to be allocated."
            },
            "similarity": 173.76998734210093
          }
        ]
      },
      "impact:Denial-of-Service": {
        "keyphrase": "Denial-of-Service",
        "type": "impact",
        "cwes": [
          {
            "metadata": {
              "doc_id": "1285",
              "name": "Improper Validation of Specified Index, Position, or Offset in Input",
              "source": "sparse",
              "original_content": "The product receives input that is expected to specify an index, position, or offset into an indexable resource such as a buffer or file, but it does not validate or incorrectly validates that the specified index/position/offset has the required properties."
            },
            "similarity": 67.85091064350974
          },
          {
            "metadata": {
              "doc_id": "20",
              "name": "Improper Input Validation",
              "source": "sparse",
              "original_content": "The product receives input or data, but it does\n        not validate or incorrectly validates that the input has the\n        properties that are required to process the data safely and\n        correctly."
            },
            "similarity": 67.74407949147579
          },
          {
            "metadata": {
              "doc_id": "789",
              "name": "Memory Allocation with Excessive Size Value",
              "source": "sparse",
              "original_content": "The product allocates memory based on an untrusted, large size value, but it does not ensure that the size is within expected limits, allowing arbitrary amounts of memory to be allocated."
            },
            "similarity": 67.36454666574488
          },
          {
            "metadata": {
              "doc_id": "1284",
              "name": "Improper Validation of Specified Quantity in Input",
              "source": "sparse",
              "original_content": "The product receives input that is expected to specify a quantity (such as size or length), but it does not validate or incorrectly validates that the quantity has the required properties."
            },
            "similarity": 67.30648655251962
          },
          {
            "metadata": {
              "doc_id": "617",
              "name": "Reachable Assertion",
              "source": "sparse",
              "original_content": "The product contains an assert() or similar statement that can be triggered by an attacker, which leads to an application exit or other behavior that is more severe than necessary.",
              "keyphrase_sources": [
                {
                  "id": "impact:Denial-of-Service",
                  "keyphrase": "Denial-of-Service",
                  "type": "impact"
                },
                {
                  "id": "vector:malicious ICMPV6 packets",
                  "keyphrase": "malicious ICMPV6 packets",
                  "type": "vector"
                }
              ]
            },
            "similarity": 66.42227536888396
          }
        ]
      },
      "vector:malicious ICMPV6 packets": {
        "keyphrase": "malicious ICMPV6 packets",
        "type": "vector",
        "cwes": [
          {
            "metadata": {
              "doc_id": "1285",
              "name": "Improper Validation of Specified Index, Position, or Offset in Input",
              "source": "sparse",
              "original_content": "The product receives input that is expected to specify an index, position, or offset into an indexable resource such as a buffer or file, but it does not validate or incorrectly validates that the specified index/position/offset has the required properties."
            },
            "similarity": 63.66581434908787
          },
          {
            "metadata": {
              "doc_id": "789",
              "name": "Memory Allocation with Excessive Size Value",
              "source": "sparse",
              "original_content": "The product allocates memory based on an untrusted, large size value, but it does not ensure that the size is within expected limits, allowing arbitrary amounts of memory to be allocated."
            },
            "similarity": 63.00265917678391
          },
          {
            "metadata": {
              "doc_id": "20",
              "name": "Improper Input Validation",
              "source": "sparse",
              "original_content": "The product receives input or data, but it does\n        not validate or incorrectly validates that the input has the\n        properties that are required to process the data safely and\n        correctly."
            },
            "similarity": 59.63144080352492
          },
          {
            "metadata": {
              "doc_id": "617",
              "name": "Reachable Assertion",
              "source": "sparse",
              "original_content": "The product contains an assert() or similar statement that can be triggered by an attacker, which leads to an application exit or other behavior that is more severe than necessary."
            },
            "similarity": 58.692154707129895
          },
          {
            "metadata": {
              "doc_id": "119",
              "name": "Improper Restriction of Operations within the Bounds of a Memory Buffer",
              "source": "sparse",
              "original_content": "The product performs operations on a memory buffer, but it reads from or writes to a memory location outside the buffer's intended boundary. This may result in read or write operations on unexpected memory locations that could be linked to other variables, data structures, or internal program data.",
              "keyphrase_sources": [
                {
                  "id": "vector:malicious ICMPV6 packets",
                  "keyphrase": "malicious ICMPV6 packets",
                  "type": "vector"
                }
              ]
            },
            "similarity": 58.668669488435384
          }
        ]
      }
    },
    "keyphrase_mapping": {
      "20": [
        {
          "id": "rootcause:Input Validation vulnerability",
          "keyphrase": "Input Validation vulnerability",
          "type": "rootcause"
        },
        {
          "id": "rootcause:Improper Input Validation",
          "keyphrase": "Improper Input Validation",
          "type": "rootcause"
        },
        {
          "id": "impact:Denial-of-Service",
          "keyphrase": "Denial-of-Service",
          "type": "impact"
        },
        {
          "id": "vector:malicious ICMPV6 packets",
          "keyphrase": "malicious ICMPV6 packets",
          "type": "vector"
        }
      ],
      "1285": [
        {
          "id": "rootcause:Input Validation vulnerability",
          "keyphrase": "Input Validation vulnerability",
          "type": "rootcause"
        },
        {
          "id": "rootcause:Improper Input Validation",
          "keyphrase": "Improper Input Validation",
          "type": "rootcause"
        },
        {
          "id": "impact:Denial-of-Service",
          "keyphrase": "Denial-of-Service",
          "type": "impact"
        },
        {
          "id": "vector:malicious ICMPV6 packets",
          "keyphrase": "malicious ICMPV6 packets",
          "type": "vector"
        }
      ],
      "1284": [
        {
          "id": "rootcause:Input Validation vulnerability",
          "keyphrase": "Input Validation vulnerability",
          "type": "rootcause"
        },
        {
          "id": "rootcause:Improper Input Validation",
          "keyphrase": "Improper Input Validation",
          "type": "rootcause"
        },
        {
          "id": "impact:Denial-of-Service",
          "keyphrase": "Denial-of-Service",
          "type": "impact"
        }
      ],
      "1286": [
        {
          "id": "rootcause:Input Validation vulnerability",
          "keyphrase": "Input Validation vulnerability",
          "type": "rootcause"
        },
        {
          "id": "rootcause:Improper Input Validation",
          "keyphrase": "Improper Input Validation",
          "type": "rootcause"
        }
      ],
      "789": [
        {
          "id": "rootcause:Input Validation vulnerability",
          "keyphrase": "Input Validation vulnerability",
          "type": "rootcause"
        },
        {
          "id": "rootcause:Improper Input Validation",
          "keyphrase": "Improper Input Validation",
          "type": "rootcause"
        },
        {
          "id": "impact:Denial-of-Service",
          "keyphrase": "Denial-of-Service",
          "type": "impact"
        },
        {
          "id": "vector:malicious ICMPV6 packets",
          "keyphrase": "malicious ICMPV6 packets",
          "type": "vector"
        }
      ],
      "617": [
        {
          "id": "impact:Denial-of-Service",
          "keyphrase": "Denial-of-Service",
          "type": "impact"
        },
        {
          "id": "vector:malicious ICMPV6 packets",
          "keyphrase": "malicious ICMPV6 packets",
          "type": "vector"
        }
      ],
      "119": [
        {
          "id": "vector:malicious ICMPV6 packets",
          "keyphrase": "malicious ICMPV6 packets",
          "type": "vector"
        }
      ]
    },
    "relevant_cwes": [
      {
        "metadata": {
          "doc_id": "20",
          "name": "Improper Input Validation",
          "source": "sparse",
          "original_content": "The product receives input or data, but it does\n        not validate or incorrectly validates that the input has the\n        properties that are required to process the data safely and\n        correctly.",
          "keyphrase_sources": [
            {
              "id": "rootcause:Input Validation vulnerability",
              "keyphrase": "Input Validation vulnerability",
              "type": "rootcause"
            },
            {
              "id": "rootcause:Improper Input Validation",
              "keyphrase": "Improper Input Validation",
              "type": "rootcause"
            },
            {
              "id": "impact:Denial-of-Service",
              "keyphrase": "Denial-of-Service",
              "type": "impact"
            },
            {
              "id": "vector:malicious ICMPV6 packets",
              "keyphrase": "malicious ICMPV6 packets",
              "type": "vector"
            }
          ]
        },
        "similarity": 193.79687048574306
      },
      {
        "metadata": {
          "doc_id": "1285",
          "name": "Improper Validation of Specified Index, Position, or Offset in Input",
          "source": "sparse",
          "original_content": "The product receives input that is expected to specify an index, position, or offset into an indexable resource such as a buffer or file, but it does not validate or incorrectly validates that the specified index/position/offset has the required properties.",
          "keyphrase_sources": [
            {
              "id": "rootcause:Input Validation vulnerability",
              "keyphrase": "Input Validation vulnerability",
              "type": "rootcause"
            },
            {
              "id": "rootcause:Improper Input Validation",
              "keyphrase": "Improper Input Validation",
              "type": "rootcause"
            },
            {
              "id": "impact:Denial-of-Service",
              "keyphrase": "Denial-of-Service",
              "type": "impact"
            },
            {
              "id": "vector:malicious ICMPV6 packets",
              "keyphrase": "malicious ICMPV6 packets",
              "type": "vector"
            }
          ]
        },
        "similarity": 188.8876780739572
      },
      {
        "metadata": {
          "doc_id": "1284",
          "name": "Improper Validation of Specified Quantity in Input",
          "source": "sparse",
          "original_content": "The product receives input that is expected to specify a quantity (such as size or length), but it does not validate or incorrectly validates that the quantity has the required properties.",
          "keyphrase_sources": [
            {
              "id": "rootcause:Input Validation vulnerability",
              "keyphrase": "Input Validation vulnerability",
              "type": "rootcause"
            },
            {
              "id": "rootcause:Improper Input Validation",
              "keyphrase": "Improper Input Validation",
              "type": "rootcause"
            },
            {
              "id": "impact:Denial-of-Service",
              "keyphrase": "Denial-of-Service",
              "type": "impact"
            }
          ]
        },
        "similarity": 186.81335712219456
      },
      {
        "metadata": {
          "doc_id": "1286",
          "name": "Improper Validation of Syntactic Correctness of Input",
          "source": "sparse",
          "original_content": "The product receives input that is expected to be well-formed - i.e., to comply with a certain syntax - but it does not validate or incorrectly validates that the input complies with the syntax.",
          "keyphrase_sources": [
            {
              "id": "rootcause:Input Validation vulnerability",
              "keyphrase": "Input Validation vulnerability",
              "type": "rootcause"
            },
            {
              "id": "rootcause:Improper Input Validation",
              "keyphrase": "Improper Input Validation",
              "type": "rootcause"
            }
          ]
        },
        "similarity": 182.94682019206329
      },
      {
        "metadata": {
          "doc_id": "789",
          "name": "Memory Allocation with Excessive Size Value",
          "source": "sparse",
          "original_content": "The product allocates memory based on an untrusted, large size value, but it does not ensure that the size is within expected limits, allowing arbitrary amounts of memory to be allocated.",
          "keyphrase_sources": [
            {
              "id": "rootcause:Input Validation vulnerability",
              "keyphrase": "Input Validation vulnerability",
              "type": "rootcause"
            },
            {
              "id": "rootcause:Improper Input Validation",
              "keyphrase": "Improper Input Validation",
              "type": "rootcause"
            },
            {
              "id": "impact:Denial-of-Service",
              "keyphrase": "Denial-of-Service",
              "type": "impact"
            },
            {
              "id": "vector:malicious ICMPV6 packets",
              "keyphrase": "malicious ICMPV6 packets",
              "type": "vector"
            }
          ]
        },
        "similarity": 173.9059180570099
      },
      {
        "metadata": {
          "doc_id": "617",
          "name": "Reachable Assertion",
          "source": "sparse",
          "original_content": "The product contains an assert() or similar statement that can be triggered by an attacker, which leads to an application exit or other behavior that is more severe than necessary.",
          "keyphrase_sources": [
            {
              "id": "impact:Denial-of-Service",
              "keyphrase": "Denial-of-Service",
              "type": "impact"
            },
            {
              "id": "vector:malicious ICMPV6 packets",
              "keyphrase": "malicious ICMPV6 packets",
              "type": "vector"
            }
          ]
        },
        "similarity": 66.42227536888396
      },
      {
        "metadata": {
          "doc_id": "119",
          "name": "Improper Restriction of Operations within the Bounds of a Memory Buffer",
          "source": "sparse",
          "original_content": "The product performs operations on a memory buffer, but it reads from or writes to a memory location outside the buffer's intended boundary. This may result in read or write operations on unexpected memory locations that could be linked to other variables, data structures, or internal program data.",
          "keyphrase_sources": [
            {
              "id": "vector:malicious ICMPV6 packets",
              "keyphrase": "malicious ICMPV6 packets",
              "type": "vector"
            }
          ]
        },
        "similarity": 58.668669488435384
      }
    ],
    "enhanced_query": "# Vulnerability Description\n\n    CWE-20 Improper **Input Validation vulnerability** exists that could cause Denial-of-Service of the product when malicious ICMPV6 packets are sent to the device.\n\n    # Keyphrase-Specific CWE Analysis\n    This vulnerability contains multiple keyphrases that may map to different CWEs. \n    Please analyze each keyphrase separately and determine the most appropriate CWE(s) for each.\n\n    ## ROOTCAUSE: 'Input Validation vulnerability'\n\nRelevant CWEs for this ROOTCAUSE:\n\n### 1. CWE-20: Improper Input Validation (Score: 193.80)\n\nThe product receives input or data, but it does\n        not validate or incorrectly validates that the input has the\n        properties that are required to process the data safely and\n        correctly....\n\n### 2. CWE-1285: Improper Validation of Specified Index, Position, or Offset in Input (Score: 188.89)\n\nThe product receives input that is expected to specify an index, position, or offset into an indexable resource such as a buffer or file, but it does not validate or incorrectly validates that the specified index/position/offset has the required properties....\n\n### 3. CWE-1284: Improper Validation of Specified Quantity in Input (Score: 186.81)\n\nThe product receives input that is expected to specify a quantity (such as size or length), but it does not validate or incorrectly validates that the quantity has the required properties....\n\n### 4. CWE-1286: Improper Validation of Syntactic Correctness of Input (Score: 182.95)\n\nThe product receives input that is expected to be well-formed - i.e., to comply with a certain syntax - but it does not validate or incorrectly validates that the input complies with the syntax....\n\n### 5. CWE-789: Memory Allocation with Excessive Size Value (Score: 173.91)\n\nThe product allocates memory based on an untrusted, large size value, but it does not ensure that the size is within expected limits, allowing arbitrary amounts of memory to be allocated....\n\n## ROOTCAUSE: 'Improper Input Validation'\n\nRelevant CWEs for this ROOTCAUSE:\n\n### 1. CWE-20: Improper Input Validation (Score: 193.80)\n\nThe product receives input or data, but it does\n        not validate or incorrectly validates that the input has the\n        properties that are required to process the data safely and\n        correctly....\n\n### 2. CWE-1285: Improper Validation of Specified Index, Position, or Offset in Input (Score: 188.89)\n\nThe product receives input that is expected to specify an index, position, or offset into an indexable resource such as a buffer or file, but it does not validate or incorrectly validates that the specified index/position/offset has the required properties....\n\n### 3. CWE-1284: Improper Validation of Specified Quantity in Input (Score: 186.81)\n\nThe product receives input that is expected to specify a quantity (such as size or length), but it does not validate or incorrectly validates that the quantity has the required properties....\n\n### 4. CWE-1286: Improper Validation of Syntactic Correctness of Input (Score: 182.95)\n\nThe product receives input that is expected to be well-formed - i.e., to comply with a certain syntax - but it does not validate or incorrectly validates that the input complies with the syntax....\n\n### 5. CWE-789: Memory Allocation with Excessive Size Value (Score: 173.91)\n\nThe product allocates memory based on an untrusted, large size value, but it does not ensure that the size is within expected limits, allowing arbitrary amounts of memory to be allocated....\n\n## IMPACT: 'Denial-of-Service'\n\nRelevant CWEs for this IMPACT:\n\n### 1. CWE-20: Improper Input Validation (Score: 193.80)\n\nThe product receives input or data, but it does\n        not validate or incorrectly validates that the input has the\n        properties that are required to process the data safely and\n        correctly....\n\n### 2. CWE-1285: Improper Validation of Specified Index, Position, or Offset in Input (Score: 188.89)\n\nThe product receives input that is expected to specify an index, position, or offset into an indexable resource such as a buffer or file, but it does not validate or incorrectly validates that the specified index/position/offset has the required properties....\n\n### 3. CWE-1284: Improper Validation of Specified Quantity in Input (Score: 186.81)\n\nThe product receives input that is expected to specify a quantity (such as size or length), but it does not validate or incorrectly validates that the quantity has the required properties....\n\n### 4. CWE-789: Memory Allocation with Excessive Size Value (Score: 173.91)\n\nThe product allocates memory based on an untrusted, large size value, but it does not ensure that the size is within expected limits, allowing arbitrary amounts of memory to be allocated....\n\n### 5. CWE-617: Reachable Assertion (Score: 66.42)\n\nThe product contains an assert() or similar statement that can be triggered by an attacker, which leads to an application exit or other behavior that is more severe than necessary....\n\n## VECTOR: 'malicious ICMPV6 packets'\n\nRelevant CWEs for this VECTOR:\n\n### 1. CWE-20: Improper Input Validation (Score: 193.80)\n\nThe product receives input or data, but it does\n        not validate or incorrectly validates that the input has the\n        properties that are required to process the data safely and\n        correctly....\n\n### 2. CWE-1285: Improper Validation of Specified Index, Position, or Offset in Input (Score: 188.89)\n\nThe product receives input that is expected to specify an index, position, or offset into an indexable resource such as a buffer or file, but it does not validate or incorrectly validates that the specified index/position/offset has the required properties....\n\n### 3. CWE-789: Memory Allocation with Excessive Size Value (Score: 173.91)\n\nThe product allocates memory based on an untrusted, large size value, but it does not ensure that the size is within expected limits, allowing arbitrary amounts of memory to be allocated....\n\n### 4. CWE-617: Reachable Assertion (Score: 66.42)\n\nThe product contains an assert() or similar statement that can be triggered by an attacker, which leads to an application exit or other behavior that is more severe than necessary....\n\n### 5. CWE-119: Improper Restriction of Operations within the Bounds of a Memory Buffer (Score: 58.67)\n\nThe product performs operations on a memory buffer, but it reads from or writes to a memory location outside the buffer's intended boundary. This may result in read or write operations on unexpected memory locations that could be linked to other variables, data structures, or internal program data....\n\n\n    # Analysis Instructions\n    1. For each keyphrase, identify the most appropriate CWE(s) that represent the weakness.\n    2. Consider how the different keyphrases might relate to each other in the vulnerability chain.\n    3. Provide a final determination of primary CWE(s) and any secondary CWEs.\n    4. Format your response using the standard analysis template.\n\n    Please analyze how these different weaknesses interact and provide a comprehensive CWE classification.\n    "
  },
  "retrieval_time": 1.0231993198394775
}