{
  "vulnerability_info": "VulnerabilityInfo(cve_id='CVE-2025-31382', description='Cross-Site Request Forgery (CSRF) vulnerability in theode Language Field allows Stored **XSS**. This issue affects Language Field from n/a through 0.9.', key_phrases={'rootcause': '', 'weakness': ['cross-site request forgery', 'XSS'], 'impact': 'cross-site scripting', 'vector': '', 'attacker': '', 'product': 'theode Language Field', 'version': 'n/a through 0.9', 'component': ''}, reference_content=\"Here's an analysis of the provided content:\\n\\n**1. Verification:**\\n\\nThe content explicitly mentions the CVE ID CVE-2025-31382.\\n\\n**2. Relevant Content Extraction:**\\n\\n*   **Weaknesses/vulnerabilities present:** Cross-Site Request Forgery (CSRF).\\n*   **Impact of exploitation:** Could allow a malicious actor to force higher privileged users to execute unwanted actions under their current authentication.\\n*   **Attack vectors:** Not explicitly mentioned, but CSRF generally involves tricking a user into submitting a request to a vulnerable site.\\n*   **Required attacker capabilities/position:** Unauthenticated.\\n*   **Mitigation or fix:** No official fix available.\\n*   **Vulnerable software:** WordPress Language Field plugin.\\n*   **Vulnerable versions:** <= 0.9\\n*   **Severity:** Low (CVSS 7.1)\\n*   **Classification:** Cross Site Request Forgery (CSRF)\\n\\n**3. Additional Detail:**\\n\\nThis content provides details beyond a standard CVE description, including the specific plugin, affected versions, and impact details.\", similar_info={'cwe_distribution': {}, 'cwe_consensus': '', 'similarity_stats': {'thresholds': [], 'total_samples_by_threshold': {}, 'top_cwes_by_threshold': {}}}, similarity_summary=SimilarityInsight(consensus_cwe='', top_cwes=[], confidence_levels={}, total_samples=0), analysis='', analysis_with_relationships='', criticism='', resolution='', relevant_cwes=[{'metadata': {'doc_id': '352', 'name': 'Cross-Site Request Forgery (CSRF)', 'source': 'sparse', 'original_content': 'The web application does not, or can not, sufficiently verify whether a well-formed, valid, consistent request was intentionally provided by the user who submitted the request.', 'keyphrase_sources': [{'id': 'weakness:cross-site request forgery', 'keyphrase': 'cross-site request forgery', 'type': 'weakness'}, {'id': 'weakness:XSS', 'keyphrase': 'XSS', 'type': 'weakness'}, {'id': 'impact:cross-site scripting', 'keyphrase': 'cross-site scripting', 'type': 'impact'}, {'id': 'product:theode Language Field', 'keyphrase': 'theode Language Field', 'type': 'product'}, {'id': 'version:n/a through 0.9', 'keyphrase': 'n/a through 0.9', 'type': 'version'}]}, 'similarity': np.float64(278.9516191485266)}, {'metadata': {'doc_id': '89', 'name': \"Improper Neutralization of Special Elements used in an SQL Command ('SQL Injection')\", 'source': 'sparse', 'original_content': 'The product constructs all or part of an SQL command using externally-influenced input from an upstream component, but it does not neutralize or incorrectly neutralizes special elements that could modify the intended SQL command when it is sent to a downstream component. Without sufficient removal or quoting of SQL syntax in user-controllable inputs, the generated SQL query can cause those inputs to be interpreted as SQL instead of ordinary user data.', 'keyphrase_sources': [{'id': 'weakness:cross-site request forgery', 'keyphrase': 'cross-site request forgery', 'type': 'weakness'}, {'id': 'impact:cross-site scripting', 'keyphrase': 'cross-site scripting', 'type': 'impact'}, {'id': 'product:theode Language Field', 'keyphrase': 'theode Language Field', 'type': 'product'}, {'id': 'version:n/a through 0.9', 'keyphrase': 'n/a through 0.9', 'type': 'version'}]}, 'similarity': np.float64(235.96962424738894)}, {'metadata': {'doc_id': '918', 'name': 'Server-Side Request Forgery (SSRF)', 'source': 'sparse', 'original_content': 'The web server receives a URL or similar request from an upstream component and retrieves the contents of this URL, but it does not sufficiently ensure that the request is being sent to the expected destination.', 'keyphrase_sources': [{'id': 'weakness:cross-site request forgery', 'keyphrase': 'cross-site request forgery', 'type': 'weakness'}]}, 'similarity': np.float64(220.14583486766384)}, {'metadata': {'doc_id': '79', 'name': \"Improper Neutralization of Input During Web Page Generation ('Cross-site Scripting')\", 'source': 'sparse', 'original_content': 'The product does not neutralize or incorrectly neutralizes user-controllable input before it is placed in output that is used as a web page that is served to other users.', 'keyphrase_sources': [{'id': 'weakness:cross-site request forgery', 'keyphrase': 'cross-site request forgery', 'type': 'weakness'}, {'id': 'weakness:XSS', 'keyphrase': 'XSS', 'type': 'weakness'}, {'id': 'impact:cross-site scripting', 'keyphrase': 'cross-site scripting', 'type': 'impact'}, {'id': 'product:theode Language Field', 'keyphrase': 'theode Language Field', 'type': 'product'}, {'id': 'version:n/a through 0.9', 'keyphrase': 'n/a through 0.9', 'type': 'version'}]}, 'similarity': np.float64(213.9330402049695)}, {'metadata': {'doc_id': '601', 'name': \"URL Redirection to Untrusted Site ('Open Redirect')\", 'source': 'sparse', 'original_content': 'The web application accepts a user-controlled input that specifies a link to an external site, and uses that link in a redirect.', 'keyphrase_sources': [{'id': 'weakness:cross-site request forgery', 'keyphrase': 'cross-site request forgery', 'type': 'weakness'}]}, 'similarity': np.float64(210.63975416408996)}, {'metadata': {'doc_id': '434', 'name': 'Unrestricted Upload of File with Dangerous Type', 'source': 'sparse', 'original_content': 'The product allows the upload or transfer of dangerous file types that are automatically processed within its environment.', 'keyphrase_sources': [{'id': 'weakness:XSS', 'keyphrase': 'XSS', 'type': 'weakness'}, {'id': 'product:theode Language Field', 'keyphrase': 'theode Language Field', 'type': 'product'}, {'id': 'version:n/a through 0.9', 'keyphrase': 'n/a through 0.9', 'type': 'version'}]}, 'similarity': np.float64(146.94583866330666)}, {'metadata': {'doc_id': '1004', 'name': \"Sensitive Cookie Without 'HttpOnly' Flag\", 'source': 'sparse', 'original_content': 'The product uses a cookie to store sensitive information, but the cookie is not marked with the HttpOnly flag.', 'keyphrase_sources': [{'id': 'weakness:XSS', 'keyphrase': 'XSS', 'type': 'weakness'}, {'id': 'impact:cross-site scripting', 'keyphrase': 'cross-site scripting', 'type': 'impact'}]}, 'similarity': np.float64(143.30311754698513)}, {'metadata': {'doc_id': '116', 'name': 'Improper Encoding or Escaping of Output', 'source': 'sparse', 'original_content': 'The product prepares a structured message for communication with another component, but encoding or escaping of the data is either missing or done incorrectly. As a result, the intended structure of the message is not preserved.', 'keyphrase_sources': [{'id': 'weakness:XSS', 'keyphrase': 'XSS', 'type': 'weakness'}]}, 'similarity': np.float64(138.85504175336052)}, {'metadata': {'doc_id': '80', 'name': 'Improper Neutralization of Script-Related HTML Tags in a Web Page (Basic XSS)', 'source': 'sparse', 'original_content': 'The product receives input from an upstream component, but it does not neutralize or incorrectly neutralizes special characters such as \"<\", \">\", and \"&\" that could be interpreted as web-scripting elements when they are sent to a downstream component that processes web pages.', 'keyphrase_sources': [{'id': 'impact:cross-site scripting', 'keyphrase': 'cross-site scripting', 'type': 'impact'}]}, 'similarity': np.float64(69.67371394499169)}, {'metadata': {'doc_id': '22', 'name': \"Improper Limitation of a Pathname to a Restricted Directory ('Path Traversal')\", 'source': 'sparse', 'original_content': 'The product uses external input to construct a pathname that is intended to identify a file or directory that is located underneath a restricted parent directory, but the product does not properly neutralize special elements within the pathname that can cause the pathname to resolve to a location that is outside of the restricted directory.', 'keyphrase_sources': [{'id': 'version:n/a through 0.9', 'keyphrase': 'n/a through 0.9', 'type': 'version'}]}, 'similarity': np.float64(62.419783506422384)}, {'metadata': {'doc_id': '642', 'name': 'External Control of Critical State Data', 'source': 'sparse', 'original_content': 'The product stores security-critical state information about its users, or the product itself, in a location that is accessible to unauthorized actors.', 'keyphrase_sources': [{'id': 'product:theode Language Field', 'keyphrase': 'theode Language Field', 'type': 'product'}]}, 'similarity': np.float64(46.823446939710685)}], identified_cwes={'analyzer': [], 'critic_additional': []})",
  "retrieval_results": {
    "has_multiple_keyphrases": true,
    "keyphrase_cwe_sets": {
      "weakness:cross-site request forgery": {
        "keyphrase": "cross-site request forgery",
        "type": "weakness",
        "cwes": [
          {
            "metadata": {
              "doc_id": "352",
              "name": "Cross-Site Request Forgery (CSRF)",
              "source": "sparse",
              "original_content": "The web application does not, or can not, sufficiently verify whether a well-formed, valid, consistent request was intentionally provided by the user who submitted the request.",
              "keyphrase_sources": [
                {
                  "id": "weakness:cross-site request forgery",
                  "keyphrase": "cross-site request forgery",
                  "type": "weakness"
                },
                {
                  "id": "weakness:XSS",
                  "keyphrase": "XSS",
                  "type": "weakness"
                },
                {
                  "id": "impact:cross-site scripting",
                  "keyphrase": "cross-site scripting",
                  "type": "impact"
                },
                {
                  "id": "product:theode Language Field",
                  "keyphrase": "theode Language Field",
                  "type": "product"
                },
                {
                  "id": "version:n/a through 0.9",
                  "keyphrase": "n/a through 0.9",
                  "type": "version"
                }
              ]
            },
            "similarity": 278.9516191485266
          },
          {
            "metadata": {
              "doc_id": "89",
              "name": "Improper Neutralization of Special Elements used in an SQL Command ('SQL Injection')",
              "source": "sparse",
              "original_content": "The product constructs all or part of an SQL command using externally-influenced input from an upstream component, but it does not neutralize or incorrectly neutralizes special elements that could modify the intended SQL command when it is sent to a downstream component. Without sufficient removal or quoting of SQL syntax in user-controllable inputs, the generated SQL query can cause those inputs to be interpreted as SQL instead of ordinary user data.",
              "keyphrase_sources": [
                {
                  "id": "weakness:cross-site request forgery",
                  "keyphrase": "cross-site request forgery",
                  "type": "weakness"
                },
                {
                  "id": "impact:cross-site scripting",
                  "keyphrase": "cross-site scripting",
                  "type": "impact"
                },
                {
                  "id": "product:theode Language Field",
                  "keyphrase": "theode Language Field",
                  "type": "product"
                },
                {
                  "id": "version:n/a through 0.9",
                  "keyphrase": "n/a through 0.9",
                  "type": "version"
                }
              ]
            },
            "similarity": 235.96962424738894
          },
          {
            "metadata": {
              "doc_id": "918",
              "name": "Server-Side Request Forgery (SSRF)",
              "source": "sparse",
              "original_content": "The web server receives a URL or similar request from an upstream component and retrieves the contents of this URL, but it does not sufficiently ensure that the request is being sent to the expected destination.",
              "keyphrase_sources": [
                {
                  "id": "weakness:cross-site request forgery",
                  "keyphrase": "cross-site request forgery",
                  "type": "weakness"
                }
              ]
            },
            "similarity": 220.14583486766384
          },
          {
            "metadata": {
              "doc_id": "79",
              "name": "Improper Neutralization of Input During Web Page Generation ('Cross-site Scripting')",
              "source": "sparse",
              "original_content": "The product does not neutralize or incorrectly neutralizes user-controllable input before it is placed in output that is used as a web page that is served to other users.",
              "keyphrase_sources": [
                {
                  "id": "weakness:cross-site request forgery",
                  "keyphrase": "cross-site request forgery",
                  "type": "weakness"
                },
                {
                  "id": "weakness:XSS",
                  "keyphrase": "XSS",
                  "type": "weakness"
                },
                {
                  "id": "impact:cross-site scripting",
                  "keyphrase": "cross-site scripting",
                  "type": "impact"
                },
                {
                  "id": "product:theode Language Field",
                  "keyphrase": "theode Language Field",
                  "type": "product"
                },
                {
                  "id": "version:n/a through 0.9",
                  "keyphrase": "n/a through 0.9",
                  "type": "version"
                }
              ]
            },
            "similarity": 213.9330402049695
          },
          {
            "metadata": {
              "doc_id": "601",
              "name": "URL Redirection to Untrusted Site ('Open Redirect')",
              "source": "sparse",
              "original_content": "The web application accepts a user-controlled input that specifies a link to an external site, and uses that link in a redirect.",
              "keyphrase_sources": [
                {
                  "id": "weakness:cross-site request forgery",
                  "keyphrase": "cross-site request forgery",
                  "type": "weakness"
                }
              ]
            },
            "similarity": 210.63975416408996
          }
        ]
      },
      "weakness:XSS": {
        "keyphrase": "XSS",
        "type": "weakness",
        "cwes": [
          {
            "metadata": {
              "doc_id": "352",
              "name": "Cross-Site Request Forgery (CSRF)",
              "source": "sparse",
              "original_content": "The web application does not, or can not, sufficiently verify whether a well-formed, valid, consistent request was intentionally provided by the user who submitted the request."
            },
            "similarity": 192.77186953520877
          },
          {
            "metadata": {
              "doc_id": "79",
              "name": "Improper Neutralization of Input During Web Page Generation ('Cross-site Scripting')",
              "source": "sparse",
              "original_content": "The product does not neutralize or incorrectly neutralizes user-controllable input before it is placed in output that is used as a web page that is served to other users."
            },
            "similarity": 171.13265822496183
          },
          {
            "metadata": {
              "doc_id": "434",
              "name": "Unrestricted Upload of File with Dangerous Type",
              "source": "sparse",
              "original_content": "The product allows the upload or transfer of dangerous file types that are automatically processed within its environment.",
              "keyphrase_sources": [
                {
                  "id": "weakness:XSS",
                  "keyphrase": "XSS",
                  "type": "weakness"
                },
                {
                  "id": "product:theode Language Field",
                  "keyphrase": "theode Language Field",
                  "type": "product"
                },
                {
                  "id": "version:n/a through 0.9",
                  "keyphrase": "n/a through 0.9",
                  "type": "version"
                }
              ]
            },
            "similarity": 146.94583866330666
          },
          {
            "metadata": {
              "doc_id": "1004",
              "name": "Sensitive Cookie Without 'HttpOnly' Flag",
              "source": "sparse",
              "original_content": "The product uses a cookie to store sensitive information, but the cookie is not marked with the HttpOnly flag.",
              "keyphrase_sources": [
                {
                  "id": "weakness:XSS",
                  "keyphrase": "XSS",
                  "type": "weakness"
                },
                {
                  "id": "impact:cross-site scripting",
                  "keyphrase": "cross-site scripting",
                  "type": "impact"
                }
              ]
            },
            "similarity": 143.30311754698513
          },
          {
            "metadata": {
              "doc_id": "116",
              "name": "Improper Encoding or Escaping of Output",
              "source": "sparse",
              "original_content": "The product prepares a structured message for communication with another component, but encoding or escaping of the data is either missing or done incorrectly. As a result, the intended structure of the message is not preserved.",
              "keyphrase_sources": [
                {
                  "id": "weakness:XSS",
                  "keyphrase": "XSS",
                  "type": "weakness"
                }
              ]
            },
            "similarity": 138.85504175336052
          }
        ]
      },
      "impact:cross-site scripting": {
        "keyphrase": "cross-site scripting",
        "type": "impact",
        "cwes": [
          {
            "metadata": {
              "doc_id": "352",
              "name": "Cross-Site Request Forgery (CSRF)",
              "source": "sparse",
              "original_content": "The web application does not, or can not, sufficiently verify whether a well-formed, valid, consistent request was intentionally provided by the user who submitted the request."
            },
            "similarity": 93.1410767183374
          },
          {
            "metadata": {
              "doc_id": "79",
              "name": "Improper Neutralization of Input During Web Page Generation ('Cross-site Scripting')",
              "source": "sparse",
              "original_content": "The product does not neutralize or incorrectly neutralizes user-controllable input before it is placed in output that is used as a web page that is served to other users."
            },
            "similarity": 83.24908913637428
          },
          {
            "metadata": {
              "doc_id": "80",
              "name": "Improper Neutralization of Script-Related HTML Tags in a Web Page (Basic XSS)",
              "source": "sparse",
              "original_content": "The product receives input from an upstream component, but it does not neutralize or incorrectly neutralizes special characters such as \"<\", \">\", and \"&\" that could be interpreted as web-scripting elements when they are sent to a downstream component that processes web pages.",
              "keyphrase_sources": [
                {
                  "id": "impact:cross-site scripting",
                  "keyphrase": "cross-site scripting",
                  "type": "impact"
                }
              ]
            },
            "similarity": 69.67371394499169
          },
          {
            "metadata": {
              "doc_id": "89",
              "name": "Improper Neutralization of Special Elements used in an SQL Command ('SQL Injection')",
              "source": "sparse",
              "original_content": "The product constructs all or part of an SQL command using externally-influenced input from an upstream component, but it does not neutralize or incorrectly neutralizes special elements that could modify the intended SQL command when it is sent to a downstream component. Without sufficient removal or quoting of SQL syntax in user-controllable inputs, the generated SQL query can cause those inputs to be interpreted as SQL instead of ordinary user data."
            },
            "similarity": 68.21491252184991
          },
          {
            "metadata": {
              "doc_id": "1004",
              "name": "Sensitive Cookie Without 'HttpOnly' Flag",
              "source": "sparse",
              "original_content": "The product uses a cookie to store sensitive information, but the cookie is not marked with the HttpOnly flag."
            },
            "similarity": 67.09103367611785
          }
        ]
      },
      "product:theode Language Field": {
        "keyphrase": "theode Language Field",
        "type": "product",
        "cwes": [
          {
            "metadata": {
              "doc_id": "352",
              "name": "Cross-Site Request Forgery (CSRF)",
              "source": "sparse",
              "original_content": "The web application does not, or can not, sufficiently verify whether a well-formed, valid, consistent request was intentionally provided by the user who submitted the request."
            },
            "similarity": 64.10171174908324
          },
          {
            "metadata": {
              "doc_id": "79",
              "name": "Improper Neutralization of Input During Web Page Generation ('Cross-site Scripting')",
              "source": "sparse",
              "original_content": "The product does not neutralize or incorrectly neutralizes user-controllable input before it is placed in output that is used as a web page that is served to other users."
            },
            "similarity": 55.77363284397329
          },
          {
            "metadata": {
              "doc_id": "89",
              "name": "Improper Neutralization of Special Elements used in an SQL Command ('SQL Injection')",
              "source": "sparse",
              "original_content": "The product constructs all or part of an SQL command using externally-influenced input from an upstream component, but it does not neutralize or incorrectly neutralizes special elements that could modify the intended SQL command when it is sent to a downstream component. Without sufficient removal or quoting of SQL syntax in user-controllable inputs, the generated SQL query can cause those inputs to be interpreted as SQL instead of ordinary user data."
            },
            "similarity": 48.6328106844667
          },
          {
            "metadata": {
              "doc_id": "434",
              "name": "Unrestricted Upload of File with Dangerous Type",
              "source": "sparse",
              "original_content": "The product allows the upload or transfer of dangerous file types that are automatically processed within its environment."
            },
            "similarity": 48.01552317515659
          },
          {
            "metadata": {
              "doc_id": "642",
              "name": "External Control of Critical State Data",
              "source": "sparse",
              "original_content": "The product stores security-critical state information about its users, or the product itself, in a location that is accessible to unauthorized actors.",
              "keyphrase_sources": [
                {
                  "id": "product:theode Language Field",
                  "keyphrase": "theode Language Field",
                  "type": "product"
                }
              ]
            },
            "similarity": 46.823446939710685
          }
        ]
      },
      "version:n/a through 0.9": {
        "keyphrase": "n/a through 0.9",
        "type": "version",
        "cwes": [
          {
            "metadata": {
              "doc_id": "352",
              "name": "Cross-Site Request Forgery (CSRF)",
              "source": "sparse",
              "original_content": "The web application does not, or can not, sufficiently verify whether a well-formed, valid, consistent request was intentionally provided by the user who submitted the request."
            },
            "similarity": 74.49110721894708
          },
          {
            "metadata": {
              "doc_id": "434",
              "name": "Unrestricted Upload of File with Dangerous Type",
              "source": "sparse",
              "original_content": "The product allows the upload or transfer of dangerous file types that are automatically processed within its environment."
            },
            "similarity": 66.56708993957089
          },
          {
            "metadata": {
              "doc_id": "79",
              "name": "Improper Neutralization of Input During Web Page Generation ('Cross-site Scripting')",
              "source": "sparse",
              "original_content": "The product does not neutralize or incorrectly neutralizes user-controllable input before it is placed in output that is used as a web page that is served to other users."
            },
            "similarity": 64.39622359192207
          },
          {
            "metadata": {
              "doc_id": "22",
              "name": "Improper Limitation of a Pathname to a Restricted Directory ('Path Traversal')",
              "source": "sparse",
              "original_content": "The product uses external input to construct a pathname that is intended to identify a file or directory that is located underneath a restricted parent directory, but the product does not properly neutralize special elements within the pathname that can cause the pathname to resolve to a location that is outside of the restricted directory.",
              "keyphrase_sources": [
                {
                  "id": "version:n/a through 0.9",
                  "keyphrase": "n/a through 0.9",
                  "type": "version"
                }
              ]
            },
            "similarity": 62.419783506422384
          },
          {
            "metadata": {
              "doc_id": "89",
              "name": "Improper Neutralization of Special Elements used in an SQL Command ('SQL Injection')",
              "source": "sparse",
              "original_content": "The product constructs all or part of an SQL command using externally-influenced input from an upstream component, but it does not neutralize or incorrectly neutralizes special elements that could modify the intended SQL command when it is sent to a downstream component. Without sufficient removal or quoting of SQL syntax in user-controllable inputs, the generated SQL query can cause those inputs to be interpreted as SQL instead of ordinary user data."
            },
            "similarity": 59.99996314805923
          }
        ]
      }
    },
    "keyphrase_mapping": {
      "352": [
        {
          "id": "weakness:cross-site request forgery",
          "keyphrase": "cross-site request forgery",
          "type": "weakness"
        },
        {
          "id": "weakness:XSS",
          "keyphrase": "XSS",
          "type": "weakness"
        },
        {
          "id": "impact:cross-site scripting",
          "keyphrase": "cross-site scripting",
          "type": "impact"
        },
        {
          "id": "product:theode Language Field",
          "keyphrase": "theode Language Field",
          "type": "product"
        },
        {
          "id": "version:n/a through 0.9",
          "keyphrase": "n/a through 0.9",
          "type": "version"
        }
      ],
      "89": [
        {
          "id": "weakness:cross-site request forgery",
          "keyphrase": "cross-site request forgery",
          "type": "weakness"
        },
        {
          "id": "impact:cross-site scripting",
          "keyphrase": "cross-site scripting",
          "type": "impact"
        },
        {
          "id": "product:theode Language Field",
          "keyphrase": "theode Language Field",
          "type": "product"
        },
        {
          "id": "version:n/a through 0.9",
          "keyphrase": "n/a through 0.9",
          "type": "version"
        }
      ],
      "918": [
        {
          "id": "weakness:cross-site request forgery",
          "keyphrase": "cross-site request forgery",
          "type": "weakness"
        }
      ],
      "79": [
        {
          "id": "weakness:cross-site request forgery",
          "keyphrase": "cross-site request forgery",
          "type": "weakness"
        },
        {
          "id": "weakness:XSS",
          "keyphrase": "XSS",
          "type": "weakness"
        },
        {
          "id": "impact:cross-site scripting",
          "keyphrase": "cross-site scripting",
          "type": "impact"
        },
        {
          "id": "product:theode Language Field",
          "keyphrase": "theode Language Field",
          "type": "product"
        },
        {
          "id": "version:n/a through 0.9",
          "keyphrase": "n/a through 0.9",
          "type": "version"
        }
      ],
      "601": [
        {
          "id": "weakness:cross-site request forgery",
          "keyphrase": "cross-site request forgery",
          "type": "weakness"
        }
      ],
      "434": [
        {
          "id": "weakness:XSS",
          "keyphrase": "XSS",
          "type": "weakness"
        },
        {
          "id": "product:theode Language Field",
          "keyphrase": "theode Language Field",
          "type": "product"
        },
        {
          "id": "version:n/a through 0.9",
          "keyphrase": "n/a through 0.9",
          "type": "version"
        }
      ],
      "1004": [
        {
          "id": "weakness:XSS",
          "keyphrase": "XSS",
          "type": "weakness"
        },
        {
          "id": "impact:cross-site scripting",
          "keyphrase": "cross-site scripting",
          "type": "impact"
        }
      ],
      "116": [
        {
          "id": "weakness:XSS",
          "keyphrase": "XSS",
          "type": "weakness"
        }
      ],
      "80": [
        {
          "id": "impact:cross-site scripting",
          "keyphrase": "cross-site scripting",
          "type": "impact"
        }
      ],
      "642": [
        {
          "id": "product:theode Language Field",
          "keyphrase": "theode Language Field",
          "type": "product"
        }
      ],
      "22": [
        {
          "id": "version:n/a through 0.9",
          "keyphrase": "n/a through 0.9",
          "type": "version"
        }
      ]
    },
    "relevant_cwes": [
      {
        "metadata": {
          "doc_id": "352",
          "name": "Cross-Site Request Forgery (CSRF)",
          "source": "sparse",
          "original_content": "The web application does not, or can not, sufficiently verify whether a well-formed, valid, consistent request was intentionally provided by the user who submitted the request.",
          "keyphrase_sources": [
            {
              "id": "weakness:cross-site request forgery",
              "keyphrase": "cross-site request forgery",
              "type": "weakness"
            },
            {
              "id": "weakness:XSS",
              "keyphrase": "XSS",
              "type": "weakness"
            },
            {
              "id": "impact:cross-site scripting",
              "keyphrase": "cross-site scripting",
              "type": "impact"
            },
            {
              "id": "product:theode Language Field",
              "keyphrase": "theode Language Field",
              "type": "product"
            },
            {
              "id": "version:n/a through 0.9",
              "keyphrase": "n/a through 0.9",
              "type": "version"
            }
          ]
        },
        "similarity": 278.9516191485266
      },
      {
        "metadata": {
          "doc_id": "89",
          "name": "Improper Neutralization of Special Elements used in an SQL Command ('SQL Injection')",
          "source": "sparse",
          "original_content": "The product constructs all or part of an SQL command using externally-influenced input from an upstream component, but it does not neutralize or incorrectly neutralizes special elements that could modify the intended SQL command when it is sent to a downstream component. Without sufficient removal or quoting of SQL syntax in user-controllable inputs, the generated SQL query can cause those inputs to be interpreted as SQL instead of ordinary user data.",
          "keyphrase_sources": [
            {
              "id": "weakness:cross-site request forgery",
              "keyphrase": "cross-site request forgery",
              "type": "weakness"
            },
            {
              "id": "impact:cross-site scripting",
              "keyphrase": "cross-site scripting",
              "type": "impact"
            },
            {
              "id": "product:theode Language Field",
              "keyphrase": "theode Language Field",
              "type": "product"
            },
            {
              "id": "version:n/a through 0.9",
              "keyphrase": "n/a through 0.9",
              "type": "version"
            }
          ]
        },
        "similarity": 235.96962424738894
      },
      {
        "metadata": {
          "doc_id": "918",
          "name": "Server-Side Request Forgery (SSRF)",
          "source": "sparse",
          "original_content": "The web server receives a URL or similar request from an upstream component and retrieves the contents of this URL, but it does not sufficiently ensure that the request is being sent to the expected destination.",
          "keyphrase_sources": [
            {
              "id": "weakness:cross-site request forgery",
              "keyphrase": "cross-site request forgery",
              "type": "weakness"
            }
          ]
        },
        "similarity": 220.14583486766384
      },
      {
        "metadata": {
          "doc_id": "79",
          "name": "Improper Neutralization of Input During Web Page Generation ('Cross-site Scripting')",
          "source": "sparse",
          "original_content": "The product does not neutralize or incorrectly neutralizes user-controllable input before it is placed in output that is used as a web page that is served to other users.",
          "keyphrase_sources": [
            {
              "id": "weakness:cross-site request forgery",
              "keyphrase": "cross-site request forgery",
              "type": "weakness"
            },
            {
              "id": "weakness:XSS",
              "keyphrase": "XSS",
              "type": "weakness"
            },
            {
              "id": "impact:cross-site scripting",
              "keyphrase": "cross-site scripting",
              "type": "impact"
            },
            {
              "id": "product:theode Language Field",
              "keyphrase": "theode Language Field",
              "type": "product"
            },
            {
              "id": "version:n/a through 0.9",
              "keyphrase": "n/a through 0.9",
              "type": "version"
            }
          ]
        },
        "similarity": 213.9330402049695
      },
      {
        "metadata": {
          "doc_id": "601",
          "name": "URL Redirection to Untrusted Site ('Open Redirect')",
          "source": "sparse",
          "original_content": "The web application accepts a user-controlled input that specifies a link to an external site, and uses that link in a redirect.",
          "keyphrase_sources": [
            {
              "id": "weakness:cross-site request forgery",
              "keyphrase": "cross-site request forgery",
              "type": "weakness"
            }
          ]
        },
        "similarity": 210.63975416408996
      },
      {
        "metadata": {
          "doc_id": "434",
          "name": "Unrestricted Upload of File with Dangerous Type",
          "source": "sparse",
          "original_content": "The product allows the upload or transfer of dangerous file types that are automatically processed within its environment.",
          "keyphrase_sources": [
            {
              "id": "weakness:XSS",
              "keyphrase": "XSS",
              "type": "weakness"
            },
            {
              "id": "product:theode Language Field",
              "keyphrase": "theode Language Field",
              "type": "product"
            },
            {
              "id": "version:n/a through 0.9",
              "keyphrase": "n/a through 0.9",
              "type": "version"
            }
          ]
        },
        "similarity": 146.94583866330666
      },
      {
        "metadata": {
          "doc_id": "1004",
          "name": "Sensitive Cookie Without 'HttpOnly' Flag",
          "source": "sparse",
          "original_content": "The product uses a cookie to store sensitive information, but the cookie is not marked with the HttpOnly flag.",
          "keyphrase_sources": [
            {
              "id": "weakness:XSS",
              "keyphrase": "XSS",
              "type": "weakness"
            },
            {
              "id": "impact:cross-site scripting",
              "keyphrase": "cross-site scripting",
              "type": "impact"
            }
          ]
        },
        "similarity": 143.30311754698513
      },
      {
        "metadata": {
          "doc_id": "116",
          "name": "Improper Encoding or Escaping of Output",
          "source": "sparse",
          "original_content": "The product prepares a structured message for communication with another component, but encoding or escaping of the data is either missing or done incorrectly. As a result, the intended structure of the message is not preserved.",
          "keyphrase_sources": [
            {
              "id": "weakness:XSS",
              "keyphrase": "XSS",
              "type": "weakness"
            }
          ]
        },
        "similarity": 138.85504175336052
      },
      {
        "metadata": {
          "doc_id": "80",
          "name": "Improper Neutralization of Script-Related HTML Tags in a Web Page (Basic XSS)",
          "source": "sparse",
          "original_content": "The product receives input from an upstream component, but it does not neutralize or incorrectly neutralizes special characters such as \"<\", \">\", and \"&\" that could be interpreted as web-scripting elements when they are sent to a downstream component that processes web pages.",
          "keyphrase_sources": [
            {
              "id": "impact:cross-site scripting",
              "keyphrase": "cross-site scripting",
              "type": "impact"
            }
          ]
        },
        "similarity": 69.67371394499169
      },
      {
        "metadata": {
          "doc_id": "22",
          "name": "Improper Limitation of a Pathname to a Restricted Directory ('Path Traversal')",
          "source": "sparse",
          "original_content": "The product uses external input to construct a pathname that is intended to identify a file or directory that is located underneath a restricted parent directory, but the product does not properly neutralize special elements within the pathname that can cause the pathname to resolve to a location that is outside of the restricted directory.",
          "keyphrase_sources": [
            {
              "id": "version:n/a through 0.9",
              "keyphrase": "n/a through 0.9",
              "type": "version"
            }
          ]
        },
        "similarity": 62.419783506422384
      },
      {
        "metadata": {
          "doc_id": "642",
          "name": "External Control of Critical State Data",
          "source": "sparse",
          "original_content": "The product stores security-critical state information about its users, or the product itself, in a location that is accessible to unauthorized actors.",
          "keyphrase_sources": [
            {
              "id": "product:theode Language Field",
              "keyphrase": "theode Language Field",
              "type": "product"
            }
          ]
        },
        "similarity": 46.823446939710685
      }
    ],
    "enhanced_query": "# Vulnerability Description\n\n    Cross-Site Request Forgery (CSRF) vulnerability in theode Language Field allows Stored **XSS**. This issue affects Language Field from n/a through 0.9.\n\n    # Keyphrase-Specific CWE Analysis\n    This vulnerability contains multiple keyphrases that may map to different CWEs. \n    Please analyze each keyphrase separately and determine the most appropriate CWE(s) for each.\n\n    ## WEAKNESS: 'cross-site request forgery'\n\nRelevant CWEs for this WEAKNESS:\n\n### 1. CWE-352: Cross-Site Request Forgery (CSRF) (Score: 278.95)\n\nThe web application does not, or can not, sufficiently verify whether a well-formed, valid, consistent request was intentionally provided by the user who submitted the request....\n\n### 2. CWE-89: Improper Neutralization of Special Elements used in an SQL Command ('SQL Injection') (Score: 235.97)\n\nThe product constructs all or part of an SQL command using externally-influenced input from an upstream component, but it does not neutralize or incorrectly neutralizes special elements that could modify the intended SQL command when it is sent to a downstream component. Without sufficient removal o...\n\n### 3. CWE-918: Server-Side Request Forgery (SSRF) (Score: 220.15)\n\nThe web server receives a URL or similar request from an upstream component and retrieves the contents of this URL, but it does not sufficiently ensure that the request is being sent to the expected destination....\n\n### 4. CWE-79: Improper Neutralization of Input During Web Page Generation ('Cross-site Scripting') (Score: 213.93)\n\nThe product does not neutralize or incorrectly neutralizes user-controllable input before it is placed in output that is used as a web page that is served to other users....\n\n### 5. CWE-601: URL Redirection to Untrusted Site ('Open Redirect') (Score: 210.64)\n\nThe web application accepts a user-controlled input that specifies a link to an external site, and uses that link in a redirect....\n\n## WEAKNESS: 'XSS'\n\nRelevant CWEs for this WEAKNESS:\n\n### 1. CWE-352: Cross-Site Request Forgery (CSRF) (Score: 278.95)\n\nThe web application does not, or can not, sufficiently verify whether a well-formed, valid, consistent request was intentionally provided by the user who submitted the request....\n\n### 2. CWE-79: Improper Neutralization of Input During Web Page Generation ('Cross-site Scripting') (Score: 213.93)\n\nThe product does not neutralize or incorrectly neutralizes user-controllable input before it is placed in output that is used as a web page that is served to other users....\n\n### 3. CWE-434: Unrestricted Upload of File with Dangerous Type (Score: 146.95)\n\nThe product allows the upload or transfer of dangerous file types that are automatically processed within its environment....\n\n### 4. CWE-1004: Sensitive Cookie Without 'HttpOnly' Flag (Score: 143.30)\n\nThe product uses a cookie to store sensitive information, but the cookie is not marked with the HttpOnly flag....\n\n### 5. CWE-116: Improper Encoding or Escaping of Output (Score: 138.86)\n\nThe product prepares a structured message for communication with another component, but encoding or escaping of the data is either missing or done incorrectly. As a result, the intended structure of the message is not preserved....\n\n## IMPACT: 'cross-site scripting'\n\nRelevant CWEs for this IMPACT:\n\n### 1. CWE-352: Cross-Site Request Forgery (CSRF) (Score: 278.95)\n\nThe web application does not, or can not, sufficiently verify whether a well-formed, valid, consistent request was intentionally provided by the user who submitted the request....\n\n### 2. CWE-89: Improper Neutralization of Special Elements used in an SQL Command ('SQL Injection') (Score: 235.97)\n\nThe product constructs all or part of an SQL command using externally-influenced input from an upstream component, but it does not neutralize or incorrectly neutralizes special elements that could modify the intended SQL command when it is sent to a downstream component. Without sufficient removal o...\n\n### 3. CWE-79: Improper Neutralization of Input During Web Page Generation ('Cross-site Scripting') (Score: 213.93)\n\nThe product does not neutralize or incorrectly neutralizes user-controllable input before it is placed in output that is used as a web page that is served to other users....\n\n### 4. CWE-1004: Sensitive Cookie Without 'HttpOnly' Flag (Score: 143.30)\n\nThe product uses a cookie to store sensitive information, but the cookie is not marked with the HttpOnly flag....\n\n### 5. CWE-80: Improper Neutralization of Script-Related HTML Tags in a Web Page (Basic XSS) (Score: 69.67)\n\nThe product receives input from an upstream component, but it does not neutralize or incorrectly neutralizes special characters such as \"<\", \">\", and \"&\" that could be interpreted as web-scripting elements when they are sent to a downstream component that processes web pages....\n\n## PRODUCT: 'theode Language Field'\n\nRelevant CWEs for this PRODUCT:\n\n### 1. CWE-352: Cross-Site Request Forgery (CSRF) (Score: 278.95)\n\nThe web application does not, or can not, sufficiently verify whether a well-formed, valid, consistent request was intentionally provided by the user who submitted the request....\n\n### 2. CWE-89: Improper Neutralization of Special Elements used in an SQL Command ('SQL Injection') (Score: 235.97)\n\nThe product constructs all or part of an SQL command using externally-influenced input from an upstream component, but it does not neutralize or incorrectly neutralizes special elements that could modify the intended SQL command when it is sent to a downstream component. Without sufficient removal o...\n\n### 3. CWE-79: Improper Neutralization of Input During Web Page Generation ('Cross-site Scripting') (Score: 213.93)\n\nThe product does not neutralize or incorrectly neutralizes user-controllable input before it is placed in output that is used as a web page that is served to other users....\n\n### 4. CWE-434: Unrestricted Upload of File with Dangerous Type (Score: 146.95)\n\nThe product allows the upload or transfer of dangerous file types that are automatically processed within its environment....\n\n### 5. CWE-642: External Control of Critical State Data (Score: 46.82)\n\nThe product stores security-critical state information about its users, or the product itself, in a location that is accessible to unauthorized actors....\n\n## VERSION: 'n/a through 0.9'\n\nRelevant CWEs for this VERSION:\n\n### 1. CWE-352: Cross-Site Request Forgery (CSRF) (Score: 278.95)\n\nThe web application does not, or can not, sufficiently verify whether a well-formed, valid, consistent request was intentionally provided by the user who submitted the request....\n\n### 2. CWE-89: Improper Neutralization of Special Elements used in an SQL Command ('SQL Injection') (Score: 235.97)\n\nThe product constructs all or part of an SQL command using externally-influenced input from an upstream component, but it does not neutralize or incorrectly neutralizes special elements that could modify the intended SQL command when it is sent to a downstream component. Without sufficient removal o...\n\n### 3. CWE-79: Improper Neutralization of Input During Web Page Generation ('Cross-site Scripting') (Score: 213.93)\n\nThe product does not neutralize or incorrectly neutralizes user-controllable input before it is placed in output that is used as a web page that is served to other users....\n\n### 4. CWE-434: Unrestricted Upload of File with Dangerous Type (Score: 146.95)\n\nThe product allows the upload or transfer of dangerous file types that are automatically processed within its environment....\n\n### 5. CWE-22: Improper Limitation of a Pathname to a Restricted Directory ('Path Traversal') (Score: 62.42)\n\nThe product uses external input to construct a pathname that is intended to identify a file or directory that is located underneath a restricted parent directory, but the product does not properly neutralize special elements within the pathname that can cause the pathname to resolve to a location th...\n\n\n    # Analysis Instructions\n    1. For each keyphrase, identify the most appropriate CWE(s) that represent the weakness.\n    2. Consider how the different keyphrases might relate to each other in the vulnerability chain.\n    3. Provide a final determination of primary CWE(s) and any secondary CWEs.\n    4. Format your response using the standard analysis template.\n\n    Please analyze how these different weaknesses interact and provide a comprehensive CWE classification.\n    "
  },
  "retrieval_time": 1.0105140209197998
}